{
    "original": "LARSON BYGGARE AB, ÅKE\n\nPnr 11183\n\nStockholm 1, Box 1337. Kungsg 28.\nTel 08-23 44 05. Bankgiro\n196-1747. Postgiro 703730-2\nVerksamhet: Byggnadsprojektering,\nbyggnadsproduktion\nÅrsomsättning: 30 000 000\nAktiekapital: 130 000\nVerkst dir: Ake Larson\nEtableringsår: 1963.\n\nTRIVSEL-BELYSNING AB\n\nPnr 523 00\n\nUlricehamn. Källg 9. Tel\n0321-11847. Bankgiro 671-4604.\nPost-giro 582370-3\n\nVerksamhet: Säljer\nbelysningsarmatur för hemmiljö\nVerkst din Olof Olofsson.\n\nTROEDS INDUSTRIER, AB\nHUGO\n\nPnr 280 20\n\nBjärnum. Tel 0451-209 00. Bank-\n\ngiro 265-3509. Postgiro 87408-3.\nTga Troeds\n\nVerksamhet: Möbler för hem o\noffentlig miljö\nAntal anställda: 140\nAktiekapital: 500 000\nVerkst dir. Hugo Troedsson\nEtableringsån 1933.\n\nGEITSYKONFEKTION, AB\n\nPnr 360 40\n\nRottne, G ullebov 5. Tel\n0470-91283. Bankgiro 357-1940.\nPostgiro 518282-9\n\nVerksamhet: Lönsömnad av\nklänningar\n\nFilial: Laholm, Tegelbruksv 45.\nTel 0430-106 46\nAntal anställda: 50\nÅrsomsättning: 1200 000\nAktiekapital: 20 000\nVerkst dir: Stig Aronsson\nDisp: Daisy Aronsson\nEtableringsår: 1958\nOmbildat till aktiebolag 1963.\n\nGEJDE, AB\n\nPnr 234 00\n\nLomma, Karstorpsv 16. Tel\n040-463100\n\nVerksamhet: Tillverkar\nindustridetaljer av plast\nAktiekapital: 10 000\nVerkst dir: Gustav Johansson\nEtableringsår: 1947.\n\nINDUSTRIPUTS, AB\n\nPnr 813 00\n\nHofors, Blockv 33. Tel 0290-221 33.\nBankgiro 63-3508. Postgiro 117140\nVerksamhet: Kontinuerliga\nrengöringar av traverser,\ngångbanor,fläktar, glas o verk för industrier\nFilial: Domnarvet, Sågargränd 10A.\nTel 0243-150 03\nAntal anställda: 20\nAktiekapital: 5 000\nVerkst din Roland Nilsson\nEtableringsår: 1958.\n\nTORELL AB, J W\n\nPnr 580 03\n\nLinköping 3, Barhällsg 10. Box\n3105. Tel 013-12 99 35. Bankgiro\n\n346-9525. Postgiro 84022-3. Tga\nTorellkyl\n\nVerksamhet: Tillverkar motorkyla.\nre o värmeväxlare\nAntal anställda: 60\nÅrsomsättning: 7 000 000\nAktiekapital: 200 000\nStyrelse: Dir H-E Löfkvist (ordf),\ndir E Larsson, ing N W Torell\nVerkst din Edvin Larsson\nEtableringsår 1894\nOmbildat till aktiebolag 1945.\n\nTORÉMA, AB\n\nPnr 11523\n\nStockholm, Narvav 30. Tel\n08-63 01 25. Bankgiro 605-0306,\nPostgiro 501230-7. Tga Toremabol\nVerksamhet: Tillverkar o säljer\nme tall tv ättmaskiner\nAntal anställda: 4\nAktiekapital: 10 000\nVerkst dir: Töre Fridholm\nEtableringsår: 1952.\n\nSWEBELTRA, AB\n\nPnr 126 53\n\nHägersten, Jakobsdalsv 20. Tel\n08-744 03 80. Postgiro 151560.\nTga Swebeltra\n\nVerksamhet: Agentur för kem\nfärgpigment, anilinfärgämnen,\nlivsmedelsfärger, tryckfärger samt\nexperimentlådor\n\nAktiekapital: 5 000\nVerkst dir: Gunnar Held\nEtableringsår: 1948.\n\nARA GÄVLE AB\n\nPnr 80102\n\nGävle 1, Centralplan 5. Box 96.\nTel 026-129160. Postgiro 32206-5.\nTga Arabolaget. Telex 81046\nVerksamhet: Säljer stenkol, koks o\neldningsoljor\nAntal anställda: 30\nÅrsomsättning: 10 000 000\nAktiekapital: 100 000\nVerkst dir: Nils Hasselgren\nEtableringsår: 1923.\n\nSTENHOLMSVERKEN AB\n\nPnr 292 00\n\nKarlshamn, Fack. Tel 0454-172 80,\n172 81. Bankgiro 603-3898.\nPostgiro 546057-1\n\nVerksamhet: Tillverkar bildetaljer\nsåsom karosseridetaljer o\navgassystem\n\nVarunamn: PSV\nAntal anställda: 40\nÅrsomsättning: 5 000000\nAktiekapital: 50 000\nVerkst dir: Tom Stenholm\nEtableringsår: 1969.\n\nhagell ab\n\nPnr 5 90 96\n\nDvenm, Vallong 11. Tel\n0493-305 48. Bankgiro 66-7129.\nPostgiro 125242\n\nVerksamhet: Tillverkar o säljer\ndamblusar\nAntal anställda: 35\nÅrsomsättning: 2 000000\nAktiekapital: 9 000\nEtableringsår: 1948.\n\nhåkanssons industrier,\nab\n\nPnr 662 00\n\nAmål, V Bang 4. Box 126. Tel\n0532-121 05. Bankgiro 369-0161.\n\nPostgiro 9001-9. Tga Hawkind.\nTelex 5344 HINDUS S\n\nBHINDUS\n\nVerksamhet: Tillverkar o\nsäljer’elspisar, kylskåp, elklosetter o\nmetallbandsågblad\nAvdelningskontor: 430 70\nSäve-dalen 1, Box 12. Tel 031-26 2050\n653 40 Karlstad, Våxnäsg 1. Tel\n054-115180\n\n21145 Malmö, Davidshallstorg 10.\nTel 040-305 33, 322 35\n17149 Solna, S Långg 31. Tel\n08-8244 20, 82 75 30, 82 76 40\nSundsvall, Tullg 4. Tel 060-1175 25\nVarunamn: Hindus, Ecett, Silco,\nCitus, High Speed\nAntal anställda: 490\nÅrsomsättning: 46 000 000\nAktiekapital: 550 000\nStyrelse: Kamrer Stig Håkansson\n(ordf), fru Britta Berg, dir Bengt\nHåkansson, ekonomidir Curt\nAxelson, intendent Karl Håkanson, fru\nKarin Mathisen\nVerkst dir: Bengt Håkansson\nEkonomidir: Curt Axelson\nFörsäljn-chef: Bengt Olof\nÅkerberg\n\nInköpschef: Fredrik Persson\nEtableringsår: 1944.\n\nhåkansson &amp; lindström\nab, byggnadsfirman\n\nPnr 83100\n\nÖstersund, Gröng 31. Tel\n063-205 00, 205 02. Bankgiro 25-0017.\nPostgiro 207133\n\nVerksamhet: Uppför bostads-,\nindustri-, skol- o sjukhusbyggnader\nAntal anställda: 200\nÅrsomsättning: 15 000 000\nAktiekapital: 150 000\nVerkst dir.r: Byggmästare John\nHåkansson, byggmästare Erik\nLindström\nEtableringsår. 1949\nOmbildat tiU aktiebolag 1962.\n\nhåkanssons\nmanufaktur ab\n\nPnr 662 00\n\nAmål, V Bang 4. Box 126. Tel\n0532-121 05. Bankgiro 369-0724.\nPostgiro 9035-7. Tga Hawkind.\nTelex 5344 HINDUS S\nVerksamhet: Tillverkar o säljer\nmetallbandsågblad, skärverktyg o\nme-tallbandsågar\n\nVarunamn: citus, Silco, High Speed\nAntal anställda: 25\nÅrsomsättning: 4 500 000\nAktiekapital: 50 000\nStyrelse: Kamrer Stig Håkansson\n(ordf), ekonomidir Curt Axelson, fru\nBritta Berg, dir Bengt Håkansson,\nfru Karin Mathisen\nVerkst dir: Bengt Håkansson\nVerkstadschef: Ing Lennart Ek\nEtableringsår: 1959.\n\nhåkanssons maskinaffär\nab, g\n\nPnr 35103\n\nVäxjö 1, Sandgärdsg 33. Box 29.\nTel 0470-144 80. Bankgiro\n357-0751. Postgiro 463674-2\n\nVerksamhet: Säljer traktorer o\n\nlantbruksmaskiner\n\nAntal anställda: 20\n\nÅrsomsättning: 5 200 000\nVerkst dir: Erik Nilsson\nEtableringsår: 1952.\n\nLAXÅ BRUKS AB\n\nPnr 695 00\n\nLaxå. Tel 0584-10880. Postgiro\n671643 Skövde. Tga Laxåbolaget\nVerksamhet: Tillverkar o säljer\nmineralull o stålsand\nFörsäljningskontor: Solna 1. Laxå\nBruks Försäljningskontor i\nStockholm, Magasinsv 5. Tel 08-83 35 35\nVarunamn: Laxå, Laxå-plattan\nAntal anställda: 160\nÅrsomsättning: 11000 000\nAktiekapital: 2 500 000\nVerkst dir: Bo I Anderberg\nPlatschef: Holger Gustavsson\nEtableringsår: 1917.",
    "structured": {
        "1": {
            "company_name": "LARSON BYGGARE AB",
            "pnr": "11183",
            "address": "Stockholm 1, Box 1337. Kungsg 28.",
            "phone_number": "08-23 44 05",
            "bank_details": {
                "bankgiro": "196-1747",
                "postgiro": "703730-2"
            },
            "activity": "Byggnadsprojektering, byggnadsproduktion",
            "annual_turnover": 30000000,
            "capital": 130000,
            "key_personnel": [
                {
                    "name": "ÅKE",
                    "position": "Verkst dir"
                }
            ],
            "establishment_year": 1963
        },
        "2": {
            "company_name": "TRIVSEL-BELYSNING AB",
            "pnr": "523 00",
            "address": "Ulricehamn. Källg 9.",
            "phone_number": "0321-11847",
            "bank_details": {
                "bankgiro": "671-4604",
                "postgiro": "582370-3"
            },
            "activity": "Säljer belysningsarmatur för hemmiljö",
            "key_personnel": [
                {
                    "name": "Olof Olofsson",
                    "position": "Verkst din"
                }
            ],
            "establishment_year": 1933
        },
        "3": {
            "company_name": "TROEDS INDUSTRIER, AB",
            "pnr": "280 20",
            "address": "Bjärnum.",
            "phone_number": "0451-209 00",
            "bank_details": {
                "bankgiro": "265-3509",
                "postgiro": "87408-3"
            },
            "activity": "Möbler för hem o offentlig miljö",
            "employees": 140,
            "capital": 500000,
            "key_personnel": [
                {
                    "name": "Hugo Troedsson",
                    "position": "Verkst dir"
                }
            ],
            "establishment_year": 1933
        },
        "4": {
            "company_name": "GEITSYKONFEKTION, AB",
            "pnr": "360 40",
            "address": "Rottne, G ullebov 5.",
            "phone_number": "0470-91283",
            "bank_details": {
                "bankgiro": "357-1940",
                "postgiro": "518282-9"
            },
            "activity": "Lönsömnad av klänningar",
            "branch_office": {
                "location": "Laholm",
                "phone_number": "0430-106 46"
            },
            "employees": 50,
            "annual_turnover": 1200000,
            "capital": 20000,
            "key_personnel": [
                {
                    "name": "Stig Aronsson",
                    "position": "Verkst dir"
                },
                {
                    "name": "Daisy Aronsson",
                    "position": "Disp"
                }
            ],
            "establishment_year": 1958
        },
        "5": {
            "company_name": "GEJDE, AB",
            "pnr": "234 00",
            "address": "Lomma, Karstorpsv 16.",
            "phone_number": "040-463100",
            "activity": "Tillverkar industridetaljer av plast",
            "capital": 10000,
            "key_personnel": [
                {
                    "name": "Gustav Johansson",
                    "position": "Verkst dir"
                }
            ],
            "establishment_year": 1947
        },
        "6": {
            "company_name": "INDUSTRIPUTS, AB",
            "pnr": "813 00",
            "address": "Hofors, Blockv 33.",
            "phone_number": "0290-221 33",
            "bank_details": {
                "bankgiro": "63-3508",
                "postgiro": "117140"
            },
            "activity": "Kontinuerliga rengöringar av traverser, gångbanor, fläktar, glas o verk för industrier",
            "branch_office": {
                "location": "Domnarvet",
                "phone_number": "0243-150 03"
            },
            "employees": 20,
            "capital": 5000,
            "key_personnel": [
                {
                    "name": "Roland Nilsson",
                    "position": "Verkst din"
                }
            ],
            "establishment_year": 1958
        },
        "7": {
            "company_name": "TORELL AB",
            "pnr": "580 03",
            "address": "Linköping 3, Barhällsg 10. Box 3105.",
            "phone_number": "013-12 99 35",
            "bank_details": {
                "bankgiro": "346-9525",
                "postgiro": "84022-3"
            },
            "activity": "Tillverkar motorkyla, re o värmeväxlare",
            "employees": 60,
            "annual_turnover": 7000000,
            "capital": 200000,
            "key_personnel": [
                {
                    "name": "H-E Löfkvist",
                    "position": "Styrelse"
                },
                {
                    "name": "E Larsson",
                    "position": "Styrelse"
                },
                {
                    "name": "N W Torell",
                    "position": "Styrelse"
                },
                {
                    "name": "Edvin Larsson",
                    "position": "Verkst din"
                }
            ],
            "establishment_year": 1945
        },
        "8": {
            "company_name": "TORÉMA, AB",
            "pnr": "11523",
            "address": "Stockholm, Narvav 30.",
            "phone_number": "08-63 01 25",
            "bank_details": {
                "bankgiro": "605-0306",
                "postgiro": "501230-7"
            },
            "activity": "Tillverkar o säljer metalltvättmaskiner",
            "employees": 4,
            "capital": 10000,
            "key_personnel": [
                {
                    "name": "Töre Fridholm",
                    "position": "Verkst dir"
                }
            ],
            "establishment_year": 1952
        },
        "9": {
            "company_name": "SWEBELTRA, AB",
            "pnr": "126 53",
            "address": "Hägersten, Jakobsdalsv 20.",
            "phone_number": "08-744 03 80",
            "postgiro": "151560",
            "activity": "Agentur för kem färgpigment, anilinfärgämnen, livsmedelsfärger, tryckfärger samt experimentlådor",
            "capital": 5000,
            "key_personnel": [
                {
                    "name": "Gunnar Held",
                    "position": "Verkst dir"
                }
            ],
            "establishment_year": 1948
        },
        "10": {
            "company_name": "ARA GÄVLE AB",
            "pnr": "80102",
            "address": "Gävle 1, Centralplan 5. Box 96.",
            "phone_number": "026-129160",
            "postgiro": "32206-5",
            "activity": "Säljer stenkol, koks o eldningsoljor",
            "employees": 30,
            "annual_turnover": 10000000,
            "capital": 100000,
            "key_personnel": [
                {
                    "name": "Nils Hasselgren",
                    "position": "Verkst dir"
                }
            ],
            "establishment_year": 1923
        },
        "11": {
            "company_name": "STENHOLMSVERKEN AB",
            "pnr": "292 00",
            "address": "Karlshamn, Fack.",
            "phone_number": "0454-172 80, 172 81",
            "bank_details": {
                "bankgiro": "603-3898",
                "postgiro": "546057-1"
            },
            "activity": "Tillverkar bildetaljer såsom karosseridetaljer o avgassystem",
            "branch_name": "PSV",
            "employees": 40,
            "annual_turnover": 5000000,
            "capital": 50000,
            "key_personnel": [
                {
                    "name": "Tom Stenholm",
                    "position": "Verkst dir"
                }
            ],
            "establishment_year": 1969
        },
        "12": {
            "company_name": "hagell ab",
            "pnr": "5 90 96",
            "address": "Dvenm, Vallong 11.",
            "phone_number": "0493-305 48",
            "bank_details": {
                "bankgiro": "66-7129",
                "postgiro": "125242"
            },
            "activity": "Tillverkar o säljer damblusar",
            "employees": 35,
            "annual_turnover": 2000000,
            "capital": 9000,
            "establishment_year": 1948
        },
        "13": {
            "company_name": "håkanssons industrier, AB",
            "pnr": "662 00",
            "address": "Amål, V Bang 4. Box 126.",
            "phone_number": "0532-121 05",
            "bank_details": {
                "bankgiro": "369-0161",
                "postgiro": "9001-9"
            },
            "activity": "Tillverkar o säljer elsipar, kylskåp, elklosetter o metallbandsågblad",
            "branch_offices": [
                "430 70 Säve-dalen 1, 031-26 2050",
                "653 40 Karlstad, Våxnäsg 1, 054-115180",
                "21145 Malmö, Davidshallstorg 10, 040-305 33, 322 35",
                "17149 Solna, S Långg 31, 08-8244 20, 82 75 30, 82 76 40",
                "Sundsvall, Tullg 4, 060-1175 25"
            ],
            "varunamn": [
                "Hindus",
                "Ecett",
                "Silco",
                "Citus",
                "High Speed"
            ],
            "employees": 490,
            "annual_turnover": 46000000,
            "capital": 550000,
            "key_personnel": [
                {
                    "name": "Stig Håkansson",
                    "position": "Styrelse"
                },
                {
                    "name": "Britta Berg",
                    "position": "Styrelse"
                },
                {
                    "name": "Bengt Håkansson",
                    "position": "Styrelse"
                },
                {
                    "name": "Curt Axelson",
                    "position": "Ekonomidir"
                },
                {
                    "name": "Karl Håkanson",
                    "position": "Intendent"
                },
                {
                    "name": "Karin Mathisen",
                    "position": "Styrelse"
                },
                {
                    "name": "Bengt Olof Åkerberg",
                    "position": "Försäljn-chef"
                },
                {
                    "name": "Fredrik Persson",
                    "position": "Inköpschef"
                }
            ],
            "establishment_year": 1944
        },
        "14": {
            "company_name": "håkansson & lindström ab, byggnadsfirman",
            "pnr": "83100",
            "address": "Östersund, Gröng 31.",
            "phone_number": "063-205 00, 205 02",
            "bank_details": {
                "bankgiro": "25-0017",
                "postgiro": "207133"
            },
            "activity": "Uppför bostads-, industri-, skol- o sjukhusbyggnader",
            "employees": 200,
            "annual_turnover": 15000000,
            "capital": 150000,
            "key_personnel": [
                {
                    "name": "Byggmästare John Håkansson",
                    "position": "Verkst dir.r"
                },
                {
                    "name": "Byggmästare Erik Lindström",
                    "position": "Verkst dir.r"
                }
            ],
            "establishment_year": 1949
        },
        "15": {
            "company_name": "håkanssons manufaktur ab",
            "pnr": "662 00",
            "address": "Amål, V Bang 4. Box 126.",
            "phone_number": "0532-121 05",
            "bank_details": {
                "bankgiro": "369-0724",
                "postgiro": "9035-7"
            },
            "activity": "Tillverkar o säljer metallbandsågblad, skärverktyg o metallbandsågar",
            "varunamn": [
                "citus",
                "Silco",
                "High Speed"
            ],
            "employees": 25,
            "annual_turnover": 4500000,
            "capital": 50000,
            "key_personnel": [
                {
                    "name": "Stig Håkansson",
                    "position": "Styrelse"
                },
                {
                    "name": "Bengt Håkansson",
                    "position": "Styrelse"
                },
                {
                    "name": "Curt Axelson",
                    "position": "Ekonomidir"
                },
                {
                    "name": "Britta Berg",
                    "position": "Styrelse"
                },
                {
                    "name": "Karin Mathisen",
                    "position": "Styrelse"
                },
                {
                    "name": "Bengt Håkansson",
                    "position": "Verkst dir"
                },
                {
                    "name": "Ing Lennart Ek",
                    "position": "Verkstadschef"
                }
            ],
            "establishment_year": 1959
        },
        "16": {
            "company_name": "håkanssons maskinaffär ab, g",
            "pnr": "35103",
            "address": "Växjö 1, Sandgärdsg 33. Box 29.",
            "phone_number": "0470-144 80",
            "bank_details": {
                "bankgiro": "357-0751",
                "postgiro": "463674-2"
            },
            "activity": "Säljer traktorer o lantbruksmaskiner",
            "employees": 20,
            "annual_turnover": 5200000,
            "key_personnel": [
                {
                    "name": "Erik Nilsson",
                    "position": "Verkst dir"
                }
            ],
            "establishment_year": 1952
        },
        "17": {
            "company_name": "LAXÅ BRUKS AB",
            "pnr": "695 00",
            "address": "Laxå.",
            "phone_number": "0584-10880",
            "postgiro": "671643 Skövde",
            "activity": "Tillverkar o säljer mineralull o stålsand",
            "branch_office": {
                "location": "Solna 1. Laxå Bruks Försäljningskontor i Stockholm, Magasinsv 5.",
                "phone_number": "08-83 35 35"
            },
            "varunamn": [
                "Laxå",
                "Laxå-plattan"
            ],
            "employees": 160,
            "annual_turnover": 11000000,
            "capital": 2500000,
            "key_personnel": [
                {
                    "name": "Bo I Anderberg",
                    "position": "Verkst dir"
                },
                {
                    "name": "Holger Gustavsson",
                    "position": "Platschef"
                }
            ],
            "establishment_year": 1917
        }
    }
}