{
    "original": "KRONOMETER, AB\n\nPnr 14105\n\nHuddinge 5, Box 5057.\nJakobs-lundsv 25. Tel 08-97 0260.\nBankgiro 572-263. Postgiro 58593-5.\nTelex 10858\n\nVerksamhet: Kronometrar,\narbets-studie- o. stoppur, industriur\nAktiekapital: 10 000\nDir: Albert Maier\nEtableringsår: 1930.\n\nELMO, AB\n\nPnr 64200\n\nFlen, Box 41. Industriv 7. Tel\n0157-123 15. Bankgiro 363-9655.\nPostgiro 7156-3. Tga Elmo. Telex\n64101\n\nVerksamhet: Tillverkar o säljer\nkortslutna elektr motorer upp till\n25 hk, såväl normmotorer enligt\ninternationell standard som\nspecialmotorer. Generalagentur för\nElek-tra.Tailfingen, Tyskland, gällande\nderas tillverkningsprogram på elektr\nmanöverapparater\nVarunamn: Elmo\nAntal anställda: 210\nÅrsomsättning: 18 000 000\nAktiekapital: 400000\nStyrelse: Adv Herman Heilborn\n(ordf), herr Gösta Björk, dir Ernst\nClaeson, bankdir Curt Ericson,\ndisp Göte Johansson\nVerkst dir: Ernst Claeson\nFörsäljn-chef: Erling Sörensen\nVerkstadschef: Töre Reutermo\nEtableringsår: 1948.\n\nELMO-CALF, AB\nCHROM-LADERFABRIKEN\n\nPnr 51201\n\nSvenljunga 1, Box 133. Tel\n0325-100 50. Bankgiro 23-6301.\nPostgiro 338644. Tga Elmocalf. Telex\n36039\n\nVerksamhet: Tillverkar\nskoovanläder\n\nAntal anställda: 160\nÅrsomsättning: 30 000 000\nAktiekapital: 150 000\nVerkst dir: Nils G J Johansson\nEtableringsår: 1931.\n\nEL-MOTRONIC AB\n\nPit 18103\n\nLidingö 3. V Allén 12. Fack. Tel\n08-766 02 65. Bankgiro 65-3765.\nPostgiro 441170. Tga Elmotronic.\nTelex 10054\n\nVerksamhet: Importerar elektriska\nmotorer, kugg- o snäckväxelmotorer\nsamt st art apparater o\nelektronikutrustningar\n\nVarunamn: Starkström, Brook,\nGefeg, Heidolph, Ziehl-Abegg,\nStatronic\n\nAntal anställda: 7\nÅrsomsättning: 4 000 000\nAktiekapital: 25 000\nStyrelse: Dir Bengt Lindberg\n(ordf), Mats Hellstadius, Per E\nEkström\n\nVerkst dir: Ing P E Ekström\nEtableringsår: 1958.\n\nARBETET\n\nPnr 20121\n\nMalmö 1, Box 125. Bergsg 20. Tel\n040-2 0 5 0 00. Bankgiro 644-0374.\nPostgiro 14065-7.\nTelex 3182 ARB S\nVerksamhet: Tidningstryckeri\nAntal anställda: 609\nÅrsomsättning: 55 000 000\nAktiekapital: 4 837 000\nVerkst dir: Chefred Frans Nilsson\nAnnonsdir: H Holmström\nDir. L Ewers\n\nDistributionsdir: N Olausson\nEkonomidir: F Anderberg\nRedaktionschef: H Ekblom\nTeknisk dir: P J Erixson\nEtableringsår: 1887\nÄgare: Tryckeri AB Framtiden,\nMalmö.\n\nARBETSGIVARNES\nÖMSESIDIGA ANSVARS.\nFÖRSÄKRINGSBOLAG\n\nPnr 104 40\n\nStockholm 14, Grevg 34. Fack.\nTel 08-67 00 75. Bankgiro 73-2031.\nPostgiro 50767. Tga Trauma\n\nVerksamhet: Bolaget meddelar\nansvarighetsförsäkring inom\nföreträdesvis företagssektorn samt\nmeddelar i anslutning härtill även i\nmindre omfattning trafik- o annan\nmotorfordonsförsäkring till företag\nAntal anställda: 10\nÅrsomsättning: 6 100000\nStyrelse: Dir Gösta Frisell (ordf),\ndir L G Albåge, dir Olof Asplund,\ndir Bengt Olof Berggren, dir J\nHaegerstrand, dir P E Paulson, dir\nOlof Risholm, dir Bertil Schéle,\ngruvdir Boris Serning, dir Gunnar\nWerner\n\nVerkst dir: Bertil Björkman\nEtableringsår: 1926.\n\nARBETSGIVARNES\nÖMSESIDIGA\nOLYCKSFALLS-FÖRSÄKRINGSBOLAG\n\nPnr 104 40\n\nStockholm 14, Grevg 34. Fack.\nTel 08-67 00 75. Bankgiro 73-2030.\nPostgiro 466. Tga Trauma\nVerksamhet: Bolaget har meddelat\nförsäkring enl lagen om\nyrkesskadeförsäkring. Bolaget äger enligt\nriksdagsbeslut icke rätt meddela\nyrkesskadeförsäkring efter 1968\nårs utgång. Bolaget har därefter\nförvaltnings- o avvecklingsuppgifter\nför sitt försäkringsbestånd mm\nAntal anställda: 45\nÅrsomsättning: 25 000 000 (1968)\nStyrelse: Dir Gösta Frisell (ordf),\ndir Gunnar L Arvidsson, dir Olof\nAsplund, dlr Bengt Olof Berggren,\ndisp Nils Elfström, dir Sven\nFri-berger, dir Sven Hydén, disp Sture\nNilsson, dir Olof Risholm, dir\nBertil Schéle, gruvdir Boris Serning,\ndir Gunnar Werner\nVerkst dir: Gunnar Werner\nBitr dir:r: Ivar Dahlin, Per\nGår-ding\n\nEtableringsår: 1887.\n\nARBETS-RATIONALISERING\nAB ARAB\n\nPnr 41118\n\nGöteborg C, Kaserntorget 7. Tel\n031-10 50 72\n\nVerksamhet: Utför rationalisering\ninom industri o handel\nAktiekapital: 5 000\nVerkst dir: Ing Anders\nAbrahamsson\n\nEtableringsår: 1954.\n\nBLOMÉ &amp; CO MASKIN AB\n\nPnr 701 06\n\nÖrebro 1, Sörbyallén 13. Box 453.\nTel 019-12 22 28, 1275 73.\nBankgiro 61-4332. Postgiro 272003\nVerksamhet: Tillverkar o säljer\ndegkavlingsmaskiner\nVarunamn: Roulette\nAktiekapital: 10 000\nVerkst dir: Olof Blomé\nKamrer: Olof Lindgren\nEtableringsår: 1955.\n\nBLOMGREN &amp; CO\nINGENIORSFIRMA AB\n\nPnr 11221\n\nStockholm, Hantverkarg 11. Tel\n08-24 55 20. Bankgiro 332-1445.\nPostgiro 3993-3. Tga Bloco\nVerksamhet: Konsulter inom\nbyggnadsfacket\nAntal anställda: 80\nÅrsomsättning: 6 000 000\nAktiekapital: 100 000\nÄgare o chefer: Civiling Viktor\nSvensson, civiling Gustav\nHenrics-son\n\nEtableringsår: 1924.\n\nmalå snickeri ab\n\nPnr 930 70\n\nMalå, Storg. Tel 0953-107 40.\nBankgiro 766-2265. Postgiro 68225-2\nVerksamhet: Tillverkar\nspecialdörrar, ljud- o brandsäkra\nFörsäljningskontor: 931 00\nSkellefteå. Skellefteå Snickeri central.\nTel 0910-142 90\nVarunamn; Malådörren\nAntal anställda: 25\nÅrsomsättning: 2 000 000\nAktiekapital: 100000\nVerkst dir: Sven-Arne Nilsson\nEtableringsår: 1938.\n\nVEDEVE, AB\n\nPnr 402 32\n\nGöteborg 7, Första Långg 21. Box\n7127. Tel 031-24 39 42, 24 39 43.\nTelex 2241\n\nVerksamhet: Import o export av\nstål- o metallrör\nAntal anställda: 4\nÅrsomsättning: 10 000 000\nAktiekapital: 100 000\nVerkst din Charles van der Vliet\nEtableringsår: 1953.\n\nKINDE &amp; CO, AB\n\nPnr 411 16\n\nGöteborg, Vallg 17. Tel\n031-17 43 80. Bankgiro 50-0774.\nPostgiro 40615. Tga Vaxduk\nVerksamhet: Heminredningar i\ndetalj o parti\n\nÅrsomsättning: 2 000 000\nAktiekapital: 75 000\nVerkst dir: Yngve Kinde\nEtableringsår: 1914.\n\nITT KOMPONENT\n\nPnr 17120\n\nSolna 1, Nybodag 2. Fack. Tel\n08-83 00 20. Bankgiro 55-1160.\nPostgiro 127725. Telex 10516 ITTMK S.\nTga Stancomp, Stockholm\nVerksamhet: Säljer komponenter o\nannan materiel för\nelektronikindustrin o elektrotekniska industrin\nsåsom: halvledare, filmkretsar,\nelektronrör, kondensatorer,\ntermi-storer, styrkristaller, kristallfilter,\nreläer, omkopplare, småmotorer,\nfläktar, magnetiskt materiel,\nappa-ratbyggnadsmateriei, bildrör färg o\nsvartvitt samt komponenter för\nTV-industrin\n\nChef: Ing Bo Isakson.\nITT Komponent är en avdelning av\nStandard Radio &amp; Telefon AB.\nIngår i International Telephone &amp;\nTelegraph Corporation, New York\n\n(nr).\n\nITV TELEVISION SYSTEM AB\n\nPnr 17121\n\nSolna 1, Pyramidv 7. Box 1037.\nTel 08-83 44 40, 82 04 70. Bankgiro\n40-0470. Postgiro 261999.\nTelex 10512 PHOTOAX S\nVerksamhet: Säljer intern\ntelevisionsutrustning bl a Ampex\nvideobandspelare\nAntal anställda: 10\nÅrsomsättning: 4 000 000\nAktiekapital: 300000\nVerkst dir: Axel Bergström\nEtableringsår: 1969.\n\nSVE\n\nSVENSK EXPORTUT.\nSTÄLLNING AB\n\nPnr 41251\n\nGöteborg, Skåneg 26. Tel\n031-20 24 44. Bankgiro 15-0605.\nPostgiro 243828-1. Tga Maessan.\nTelex 20600\n\nVerksamhet: Permanent\nexportutställning\n\nAktiekapital: 90 000\nVerkst dir: Erie Ehrengren\nUtställningschef: Christer\nHill-Lindquist\n\nEtableringsår: 1968.\n\nSVENSK FASTIGHETSFDR.\nMEDLING AB\n\nPnr 58102\n\nLinköping 1, Box 143. Repslagarg\n33. Tel 013-11 17 20. Bankgiro\n27-6592. Postgiro 138639\nVerksamhet: Fastighetsmäklare\nÅrsomsättning: 300 000 000\nVeikst dir: Sven Wass\nEtableringsår: 1937\nOmbildat till aktiebolag 1966.\nAntal förmedlingskontor i hela\nlandet: 90.\n\nSVENSK FASTIGHETSKREDIT\nAB\n\nPnr 103 81\n\nStockholm 7, Kungsg 8. Box 7005.\nTel 08-24 5150. Bankgiro 991-0993.\nPostgiro 655200-4\nAntal anställda: 20\nÅrsomsättning: 5 554 238 000\nAktiekapital: 60 000 000\nVerkst dir: Arne Janson\nEtableringsår: 1961.\n\neklora, ab\n\nPnr 114 35\n\nStockholm, Stureg 6. Tel\n08-113216, 1132 00. Tga Ekloraur\nVerksamhet: Säljer ur av alla slag\nAntal anställda: 11\nÅrsomsättning: 3 000 000\nAktiekapital: 10 000\nVerkst din Horst W Bramsen\nEtableringsår: 1951.",
    "structured": {
        "1": {
            "company_name": "KRONOMETER, AB",
            "pnr": "14105",
            "address": "Huddinge 5, Box 5057. Jakobs-lundsv 25",
            "phone_number": "08-97 0260",
            "bank_details": {
                "bankgiro": "572-263",
                "postgiro": "58593-5"
            },
            "activity": "Kronometrar, arbets-studie- o. stoppur, industriur",
            "capital": 10000,
            "key_personnel": [
                {
                    "name": "Albert Maier"
                }
            ],
            "establishment_year": 1930
        },
        "2": {
            "company_name": "ELMO, AB",
            "pnr": "64200",
            "address": "Flen, Box 41. Industriv 7",
            "phone_number": "0157-123 15",
            "bank_details": {
                "bankgiro": "363-9655",
                "postgiro": "7156-3"
            },
            "activity": "Tillverkar o säljer kortslutna elektr motorer",
            "employees": 210,
            "annual_turnover": 18000000,
            "capital": 400000,
            "key_personnel": [
                {
                    "name": "Adv Herman Heilborn",
                    "position": "ordf"
                },
                {
                    "name": "herr Gösta Björk"
                },
                {
                    "name": "dir Ernst Claeson"
                },
                {
                    "name": "bankdir Curt Ericson"
                },
                {
                    "name": "disp Göte Johansson"
                }
            ],
            "establishment_year": 1948
        },
        "3": {
            "company_name": "ELMO-CALF, AB",
            "pnr": "51201",
            "address": "Svenljunga 1, Box 133",
            "phone_number": "0325-100 50",
            "bank_details": {
                "bankgiro": "23-6301",
                "postgiro": "338644"
            },
            "activity": "Tillverkar skoovanläder",
            "employees": 160,
            "annual_turnover": 30000000,
            "capital": 150000,
            "key_personnel": [
                {
                    "name": "Nils G J Johansson"
                }
            ],
            "establishment_year": 1931
        },
        "4": {
            "company_name": "EL-MOTRONIC AB",
            "pnr": "18103",
            "address": "Lidingö 3. V Allén 12",
            "phone_number": "08-766 02 65",
            "bank_details": {
                "bankgiro": "65-3765",
                "postgiro": "441170"
            },
            "activity": "Importerar elektriska motorer, kugg- o snäckväxelmotorer samt st art apparater o elektronikutrustningar",
            "employees": 7,
            "annual_turnover": 4000000,
            "capital": 25000,
            "key_personnel": [
                {
                    "name": "Dir Bengt Lindberg",
                    "position": "ordf"
                },
                {
                    "name": "Mats Hellstadius"
                },
                {
                    "name": "Per E Ekström"
                }
            ],
            "establishment_year": 1958
        },
        "5": {
            "company_name": "ARBETET",
            "pnr": "20121",
            "address": "Malmö 1, Box 125. Bergsg 20",
            "phone_number": "040-2 0 5 0 00",
            "bank_details": {
                "bankgiro": "644-0374",
                "postgiro": "14065-7"
            },
            "activity": "Tidningstryckeri",
            "employees": 609,
            "annual_turnover": 55000000,
            "capital": 4837000,
            "key_personnel": [
                {
                    "name": "Chefred Frans Nilsson"
                },
                {
                    "name": "H Holmström"
                },
                {
                    "name": "L Ewers"
                },
                {
                    "name": "N Olausson"
                },
                {
                    "name": "F Anderberg"
                },
                {
                    "name": "H Ekblom"
                },
                {
                    "name": "P J Erixson"
                }
            ],
            "establishment_year": 1887,
            "owner": "Tryckeri AB Framtiden, Malmö"
        },
        "6": {
            "company_name": "ARBETSGIVARNES ÖMSESIDIGA ANSVARS. FÖRSÄKRINGSBOLAG",
            "pnr": "104 40",
            "address": "Stockholm 14, Grevg 34",
            "phone_number": "08-67 00 75",
            "bank_details": {
                "bankgiro": "73-2031",
                "postgiro": "50767"
            },
            "activity": "Bolaget meddelar ansvarighetsförsäkring inom företrädesvis företagssektorn samt meddelar i anslutning härtill även i mindre omfattning trafik- o annan motorfordonsförsäkring till företag",
            "employees": 10,
            "annual_turnover": 6100000,
            "key_personnel": [
                {
                    "name": "Dir Gösta Frisell",
                    "position": "ordf"
                },
                {
                    "name": "dir L G Albåge"
                },
                {
                    "name": "dir Olof Asplund"
                },
                {
                    "name": "dir Bengt Olof Berggren"
                },
                {
                    "name": "dir J Haegerstrand"
                },
                {
                    "name": "dir P E Paulson"
                },
                {
                    "name": "dir Olof Risholm"
                },
                {
                    "name": "dir Bertil Schéle"
                },
                {
                    "name": "gruvdir Boris Serning"
                },
                {
                    "name": "dir Gunnar Werner"
                }
            ],
            "establishment_year": 1926
        },
        "7": {
            "company_name": "ARBETSGIVARNES ÖMSESIDIGA OLYCKSFALLS-FÖRSÄKRINGSBOLAG",
            "pnr": "104 40",
            "address": "Stockholm 14, Grevg 34",
            "phone_number": "08-67 00 75",
            "bank_details": {
                "bankgiro": "73-2030",
                "postgiro": "466"
            },
            "activity": "Bolaget har meddelat försäkring enl lagen om yrkesskadeförsäkring. Bolaget äger enligt riksda...",
            "employees": 45,
            "annual_turnover": 25000000,
            "key_personnel": [
                {
                    "name": "Dir Gösta Frisell",
                    "position": "ordf"
                },
                {
                    "name": "dir Gunnar L Arvidsson"
                },
                {
                    "name": "dir Olof Asplund"
                },
                {
                    "name": "dlr Bengt Olof Berggren"
                },
                {
                    "name": "disp Nils Elfström"
                },
                {
                    "name": "dir Sven Fri-berger"
                },
                {
                    "name": "dir Sven Hydén"
                },
                {
                    "name": "disp Sture Nilsson"
                },
                {
                    "name": "dir Olof Risholm"
                },
                {
                    "name": "dir Bertil Schéle"
                },
                {
                    "name": "gruvdir Boris Serning"
                },
                {
                    "name": "dir Gunnar Werner"
                },
                {
                    "name": "Ivar Dahlin"
                },
                {
                    "name": "Per Går-ding"
                }
            ],
            "establishment_year": 1887
        },
        "8": {
            "company_name": "ARBETS-RATIONALISERING AB ARAB",
            "pnr": "41118",
            "address": "Göteborg C, Kaserntorget 7",
            "phone_number": "031-10 50 72",
            "activity": "Utför rationalisering inom industri o handel",
            "capital": 5000,
            "key_personnel": [
                {
                    "name": "Ing Anders Abrahamsson"
                }
            ],
            "establishment_year": 1954
        },
        "9": {
            "company_name": "BLOMÉ & CO MASKIN AB",
            "pnr": "701 06",
            "address": "Örebro 1, Sörbyallén 13. Box 453",
            "phone_number": "019-12 22 28, 1275 73",
            "bank_details": {
                "bankgiro": "61-4332",
                "postgiro": "272003"
            },
            "activity": "Tillverkar o säljer degkavlingsmaskiner",
            "varunamn": "Roulette",
            "capital": 10000,
            "key_personnel": [
                {
                    "name": "Olof Blomé",
                    "position": "Verkst dir"
                },
                {
                    "name": "Olof Lindgren",
                    "position": "Kamrer"
                }
            ],
            "establishment_year": 1955
        },
        "10": {
            "company_name": "BLOMGREN & CO INGENIORSFIRMA AB",
            "pnr": "11221",
            "address": "Stockholm, Hantverkarg 11",
            "phone_number": "08-24 55 20",
            "bank_details": {
                "bankgiro": "332-1445",
                "postgiro": "3993-3"
            },
            "activity": "Konsulter inom byggnadsfacket",
            "employees": 80,
            "annual_turnover": 6000000,
            "capital": 100000,
            "key_personnel": [
                {
                    "name": "Civiling Viktor Svensson"
                },
                {
                    "name": "civiling Gustav Henrics-son"
                }
            ],
            "establishment_year": 1924
        },
        "11": {
            "company_name": "malå snickeri ab",
            "pnr": "930 70",
            "address": "Malå, Storg",
            "phone_number": "0953-107 40",
            "bank_details": {
                "bankgiro": "766-2265",
                "postgiro": "68225-2"
            },
            "activity": "Tillverkar specialdörrar, ljud- o brandsäkra",
            "försäljningskontor": "931 00 Skellefteå",
            "varunamn": "Malådörren",
            "employees": 25,
            "annual_turnover": 2000000,
            "capital": 100000,
            "key_personnel": [
                {
                    "name": "Sven-Arne Nilsson",
                    "position": "Verkst dir"
                }
            ],
            "establishment_year": 1938
        },
        "12": {
            "company_name": "VEDEVE, AB",
            "pnr": "402 32",
            "address": "Göteborg 7, Första Långg 21. Box 7127",
            "phone_number": "031-24 39 42, 24 39 43",
            "telex": "2241",
            "activity": "Import o export av stål- o metallrör",
            "employees": 4,
            "annual_turnover": 10000000,
            "capital": 100000,
            "key_personnel": [
                {
                    "name": "Charles van der Vliet",
                    "position": "Verkst din"
                }
            ],
            "establishment_year": 1953
        },
        "13": {
            "company_name": "KINDE & CO, AB",
            "pnr": "411 16",
            "address": "Göteborg, Vallg 17",
            "phone_number": "031-17 43 80",
            "bank_details": {
                "bankgiro": "50-0774",
                "postgiro": "40615"
            },
            "activity": "Heminredningar i detalj o parti",
            "annual_turnover": 2000000,
            "capital": 75000,
            "key_personnel": [
                {
                    "name": "Yngve Kinde",
                    "position": "Verkst dir"
                }
            ],
            "establishment_year": 1914
        },
        "14": {
            "company_name": "ITT KOMPONENT",
            "pnr": "17120",
            "address": "Solna 1, Nybodag 2",
            "phone_number": "08-83 00 20",
            "bank_details": {
                "bankgiro": "55-1160",
                "postgiro": "127725"
            },
            "telex": "10516 ITTMK S",
            "activity": "Säljer komponenter o annan materiel för elektronikindustrin o elektrotekniska industrin",
            "chief": "Ing Bo Isakson",
            "parent_company": "Standard Radio & Telefon AB, Ingår i International Telephone & Telegraph Corporation, New York (nr)"
        },
        "15": {
            "company_name": "ITV TELEVISION SYSTEM AB",
            "pnr": "17121",
            "address": "Solna 1, Pyramidv 7. Box 1037",
            "phone_number": "08-83 44 40, 82 04 70",
            "bank_details": {
                "bankgiro": "40-0470",
                "postgiro": "261999"
            },
            "telex": "10512 PHOTOAX S",
            "activity": "Säljer intern televisionsutrustning bl a Ampex videobandspelare",
            "employees": 10,
            "annual_turnover": 4000000,
            "capital": 300000,
            "key_personnel": [
                {
                    "name": "Axel Bergström",
                    "position": "Verkst dir"
                }
            ],
            "establishment_year": 1969
        },
        "16": {
            "company_name": "SVENSK EXPORTUT. STÄLLNING AB",
            "pnr": "41251",
            "address": "Göteborg, Skåneg 26",
            "phone_number": "031-20 24 44",
            "bank_details": {
                "bankgiro": "15-0605"
            },
            "telex": "20600",
            "activity": "Permanent exportutställning",
            "capital": 90000,
            "key_personnel": [
                {
                    "name": "Erie Ehrengren",
                    "position": "Verkst dir"
                },
                {
                    "name": "Christer Hill-Lindquist",
                    "position": "Utställningschef"
                }
            ],
            "establishment_year": 1968
        },
        "17": {
            "company_name": "SVENSK FASTIGHETSFDR. MEDLING AB",
            "pnr": "58102",
            "address": "Linköping 1, Box 143. Repslagarg 33",
            "phone_number": "013-11 17 20",
            "bank_details": {
                "bankgiro": "27-6592",
                "postgiro": "138639"
            },
            "activity": "Fastighetsmäklare",
            "annual_turnover": 300000000,
            "key_personnel": [
                {
                    "name": "Sven Wass",
                    "position": "Verkst dir"
                }
            ],
            "establishment_year": 1937,
            "restructured_year": 1966,
            "number_of_brokerage_offices": 90
        },
        "18": {
            "company_name": "SVENSK FASTIGHETSKREDIT AB",
            "pnr": "103 81",
            "address": "Stockholm 7, Kungsg 8. Box 7005",
            "phone_number": "08-24 5150",
            "bank_details": {
                "bankgiro": "991-0993",
                "postgiro": "655200-4"
            },
            "employees": 20,
            "annual_turnover": 5554238000,
            "capital": 60000000,
            "key_personnel": [
                {
                    "name": "Arne Janson",
                    "position": "Verkst dir"
                }
            ],
            "establishment_year": 1961
        },
        "19": {
            "company_name": "eklora, ab",
            "pnr": "114 35",
            "address": "Stockholm, Stureg 6",
            "phone_number": "08-113216, 1132 00",
            "activity": "Säljer ur av alla slag",
            "employees": 11,
            "annual_turnover": 3000000,
            "capital": 10000,
            "key_personnel": [
                {
                    "name": "Horst W Bramsen",
                    "position": "Verkst din"
                }
            ],
            "establishment_year": 1951
        }
    }
}