{
    "original": "UREBRO ELKONSULT AB\n\nPnr 70105\n\nÖrebro 1. Trädgårdsg 15. Box 354.\nTel 019-1247 80. Bankgiro\n463-1230. Postgiro 518267-0\nVerksamhet: Konsult för\nelanläggningar inom industri, bostäder,\nbutiker, förvaltningsbyggnader,\nkontor, skolor, vårdanstalter etc.\nKontroll o besiktningar\nAntal anstäUda: 15\nÅrsomsättning: 800 000\nAktiekapital: 10 000\nVeikst dir: Ing Ingemar Langeroth\nEtableringsår: 1960\nOmbildat till aktiebolag 1963.\n\nOREBRO EXPORTAFFÄR AB\n\nPnr 703 63\n\nÖrebro, Virkesv. Tel 019-1115 28,\n1128 33. Bankgiro 495-5233.\nPostgiro 92250-0\n\nVerksamhet: Handel med järn- o\nmetallskrot\nAntal anstäUda: 16\nÅrsomsättning: 2 000 000\nAktiekapital: 100 000\nVerkst dir: Disp Karl Glänt\nEtableringsår 1912.\n\nWEBRA INDUSTRI, AB\n\nPnr 126 48\n\nHägersten, Främlingsv 31. Tel\n08-18 71 25. Bankgiro 57-7956.\nPostgiro 658530\n\nVerksamhet: Utför mekanisk\nbearbetning\n\nAntal anställda: 18\nÅrsomsättning: 1200 000\nAktiekapital: 10 000\nVerkst dir. Erling Buråker\nEtableringsår: 1962.\n\nIVARS ARMATUR AB\n\nPnr 33010\n\nBredaryd. Tel 0370-831 75.\nBankgiro 542-4320. Postgiro 283080-0\nVerksamhet: Tillverkar elektrisk\nbelysningsarmatur\nAntal anställda: 25\nÅrsomsättning: 4 000 000\nAktiekapital: 90 000\nStvrelse: Fabr Ivar Johansson (ordf),\nkont Ove Ivarsson, lagerchef Rune\nIvarsson\n\nVerkst dir: Fabr Ivar Johansson\nEtableringsår 1945.\n\nEKEDALS GRÄVMASKINER AB\n\nPnr 64100\n\nKatrineholm, Stensättersg 33 A.\nTel 0150-100 01. Postgiro 295944\nVerksamhet: Utför schaktnings- o\nplaneringsarbeten samt lastningar\nAktiekapital: 25 000\nVerkst dir: Hugo Ekman\nEtableringsår: 1952.\n\nEKEDORFF\nARKITEKT-KONTOR AB\n\nPnr 400 30\n\nGöteborg 11, Box 11041. Jungmansg\n41. Tel 031-4204 25. Postgiro\n426139\n\nVerksamhet: Byggnadsprojektering,\nkontroll, besiktningar,\nbyggnadsledning\n\nAntal anställda: 15\nÅrsomsättning: 1 500 000\nAktiekapital: 50 000\n\nEKELUND, AB JOHN O\n\nPnr 41104\n\nGöteborg, Kruthusg. Gullbergsvass.\nTel 031-196341. 1963 61.\nBankgiro 510-5515. Postgiro 521766-6\nVerksamhet; Säljer\nbyggnadsmaterial en gros\nAntal anställda: 5\nÅrsomsättning: 2 500 000\nAktiekapital: 50 000\nVerkst dir. John Ove Ekelund\nEtableringsår 1958.\n\neklund, ab edgar r\n\nPnr 21146\n\nMalmö, Rådmansg 8. Tel\n040-1148 74. Bankgiro 64-1374.\nPostgiro 39929. Tga Eleklund\nVerksamhet: Säljer elmaterial i\nparti, glödlampor o lysrör\nAktiekapital: 25 000\nVerkst dir: Edgar R Eklund\nEtableringsår: 1932.\n\neklunds\nbakelitindustri, g l\n\nPnr 332 00\n\nGislaved, Box 8. Tel 0371-107 36.\nBankgiro 42-6716. Postgiro 295179\nVerksamhet: Handtagskulor,\nlönpressning i alla förekommande\nhärdplastmaterial\nÄgare o chef: G L Eklund\nEtableringsår: 1949.\n\nSVENSKA ESSO AB\n\nPnr 102 40\n\nStockholm 5, Fack. Nybrog 55. Tel\n08-67 97 40, 67 98 40. Bankgiro\n700-5101. Postgiro 891-2. Tga\nEsso, Essoswed. Telex 19135\nVerksamhet: Försäljning av alla\nslags petroleumprodukter samt\nbiltillbehör o fritidsartiklar.\nSmörjoljetillverkning. Biluthyrning\nAvdelningskontor Göteborg S,\nSödra v 12. Tel 031-20 07 00\nMalmö C, Studentg 5. Tel\n040-706 60\n\nSkärholmen 1, Storsätragränd 4.\nTel 08-88 00 20\nSundsvall, Storg 22. Tel\n060-15 43 00\n\nAntal anställda: 1750\nÅrsomsättning: 1 060 000 000\nAktiekapital: 145 000 000\nStyrelse: Tekn dr Töre Browaldh\n(ordf), dir Torsten Andersson,\ndir Bengt I:son Sjögren\nVerkst dir: Bengt I:son Sjögren\nAdm-dir: Torsten Andersson\nEtableringsår: 1896.\n\nSVENSKA EXTRAKTIONS.\nFURENINGEN EK FUR\n\nPnr 104 25\n\nStockholm 30, Box 30025.\nStrand-bergsg 20. Tel 08-514110.\nBankgiro 656-6327. Postgiro 297570-4.\nTga Svenex, Karlshamn\nVerksamhet: Bearbetar\nvegetabiliska fröer. Pressar o extraherar\noljeväxtfrö, huvudsakligen raps o\nsenap, varur utvinnes rå\nvegetabilisk olja, fodermjöl samt lecitin\nFabrik: 292 00 Karlshamn,\nEspinge-hamnsv 3 A. Tel 0454-150 50\nAntal anställda: 37\nÅrsomsättning: 125 000 000\nStyrelse: Dir Lars Olof Bergman\n(ordf), dir Reidar Due, dir Gordon\nNävert, dir Gert Mankert\nVerkst dir: Willard Tingnell\nPlatschef: Tekn lic Josef Dahlén\nFabrikschef: Ing Assar Goude\nEkonomichef: Bo Gimle\nEtableringsår: 1957\nFöreningen ägs av landets\nsamt-liga margarinfabriker.\n\nSVENSKA AB FIAT\n\nPnr 172 20 Sundbyberg 1\nBromma, Karlsbodav 17-19. Fack,\n\nSundbyberg 1. Tel 08-28 29 60.\nBankgiro 102-8703. Postgiro\n53010-5. Tga Svenskfiat.\nTelex 1465\n\nVerksamhet: Import av Fiat-bilar o\nreservdelar\nAntal anställda: 160\nÅrsomsättning: 66100 000\nAktiekapital: 10 000 000\nStyrelse: Adv NO Lilliehöök (ordf),\ndr G Calvi, dir Svante Möller\nVerkst dir: Riccardo Santarelli\nEtableringsår 1931.\n\nTRUCK &amp; KRANTJÄNST, AB\n\nPnr 54100\n\nSkövde, Mariestadsv 87. Tel\n0500-180 25. Bankgiro 210-1772.\nPostgiro 279260-4\n\nVerksamhet: Uthyr mobilkranar,\ntruckar o trailers\nAntal anställda: 24\nÅrsomsättning: 2 000 000\nAktiekapital: 60 000\nVerkst dir Henry Johansson\nEtableringsår. 1960.\n\nTRUCK-BOLAGET\nV STENBORG AB\n\nPnr 114 59\n\nStockholm, Karlav 72. Tel\n08-67 42 38. Postgiro 191166. Tga\nTruckbolaget\n\nVerksamhet: Säljer Heden-trucken,\nHarefield gummiportar samt Abeko\ngaffelstaplare\nVarunamn: Harefield\nChef: Victor Stenborg\nEtableringsår: 1952.\n\nTRUCKBOLAGET I OREBRO\nAB\n\nPnr 703 58\n\nÖrebro, Industrig 10. Tel\n019-18 54 3 7, 18 7 6 84. Bankgiro\n143-1642. Postgiro 446809-6\nVerksamhet: Uthyr truckar från\n1-10 ton med eller utan förare\nAntal anställda: 3\nÅrsomsättning: 300 000\nAktiekapital: 20 000\nVerkst dir: H Bäckström\nEtableringsår: 1966.\n\nEL-MATERIEL AB\n\nPnr 211 29\n\nMalmö, S Promenaden 7 B. Tel\n040-717 60. Bankgiro 264-7113. Postgiro\n39725-7. Tga Elmateriel\nVerksamhet: Säljer elektr\ninstallationsmateriel, securusapparater,\nmotorer, pumpar o transformatorer\nAktiekapital: 150 000\nVerkst dir: Sven Lindström\nEtableringsår: 1937.\n\nKROON, AB CH\n\nPnr 780 50\n\nVansbro, Box 4. Tel 0281-110 40.\nBankgiro 798-9031. Postgiro\n7676-0. Tga Kroon\nVerksamhet: Tillverkar o säljer\ncyklar, mopeder o tillbehör\nAntal anställda: 26\nÅrsomsättning: 2 800 000\nAktiekapital: 100000\nVerkst dir: Civiling Einar\nBåtels-son\n\nEtableringsår: 1910.\n\nBANKERYDS MASKIN AB\n\nPnr 560 23\n\nBanketyd. Tel 036-77160.\nBankgiro 836-9241. Postgiro 144984-2.\nTga Bankerydmaskin\nVerksamhet: Köttbandsågar,\nköttkvarnar, el-grillar, huggblock mm\nAntal anstäUda: 35\nÅrsomsättning: 3 000 000\nAktiekapital: 90 000\n\nVerkst dir: Fabr Torsten\nMartinsson\n\nEtableringsår: 1941.",
    "structured": {
        "1": {
            "company_name": "UREBRO ELKONSULT AB",
            "pnr": "70105",
            "address": "Örebro 1. Trädgårdsg 15. Box 354",
            "phone_number": "019-1247 80",
            "bank_details": {
                "bankgiro": "463-1230",
                "postgiro": "518267-0"
            },
            "activity": "Konsult för elanläggningar inom industri, bostäder, butiker, förvaltningsbyggnader, kontor, skolor, vårdanstalter etc. Kontroll o besiktningar",
            "employees": 15,
            "annual_turnover": 800000,
            "capital": 10000,
            "key_personnel": [
                {
                    "name": "Ing Ingemar Langeroth",
                    "position": "Veikst dir"
                }
            ],
            "establishment_year": 1960
        },
        "2": {
            "company_name": "OREBRO EXPORTAFFÄR AB",
            "pnr": "703 63",
            "address": "Örebro, Virkesv",
            "phone_number": "019-1115 28, 1128 33",
            "bank_details": {
                "bankgiro": "495-5233",
                "postgiro": "92250-0"
            },
            "activity": "Handel med järn- o metallskrot",
            "employees": 16,
            "annual_turnover": 2000000,
            "capital": 100000,
            "key_personnel": [
                {
                    "name": "Disp Karl Glänt",
                    "position": "Verkst dir"
                }
            ],
            "establishment_year": 1912
        },
        "3": {
            "company_name": "WEBRA INDUSTRI, AB",
            "pnr": "126 48",
            "address": "Hägersten, Främlingsv 31",
            "phone_number": "08-18 71 25",
            "bank_details": {
                "bankgiro": "57-7956",
                "postgiro": "658530"
            },
            "activity": "Utför mekanisk bearbetning",
            "employees": 18,
            "annual_turnover": 1200000,
            "capital": 10000,
            "key_personnel": [
                {
                    "name": "Erling Buråker",
                    "position": "Verkst dir"
                }
            ],
            "establishment_year": 1962
        },
        "4": {
            "company_name": "IVARS ARMATUR AB",
            "pnr": "33010",
            "address": "Bredaryd",
            "phone_number": "0370-831 75",
            "bank_details": {
                "bankgiro": "542-4320",
                "postgiro": "283080-0"
            },
            "activity": "Tillverkar elektrisk belysningsarmatur",
            "employees": 25,
            "annual_turnover": 4000000,
            "capital": 90000,
            "key_personnel": [
                {
                    "name": "Fabr Ivar Johansson",
                    "position": "Stvrelse"
                },
                {
                    "name": "Ove Ivarsson",
                    "position": "kont"
                },
                {
                    "name": "Rune Ivarsson",
                    "position": "lagerchef"
                }
            ],
            "establishment_year": 1945
        },
        "5": {
            "company_name": "EKEDALS GRÄVMASKINER AB",
            "pnr": "64100",
            "address": "Katrineholm, Stensättersg 33 A",
            "phone_number": "0150-100 01",
            "postgiro": "295944",
            "activity": "Utför schaktnings- o planeringsarbeten samt lastningar",
            "capital": 25000,
            "key_personnel": [
                {
                    "name": "Hugo Ekman",
                    "position": "Verkst dir"
                }
            ],
            "establishment_year": 1952
        },
        "6": {
            "company_name": "EKEDORFF ARKITEKT-KONTOR AB",
            "pnr": "400 30",
            "address": "Göteborg 11, Box 11041. Jungmansg 41",
            "phone_number": "031-4204 25",
            "postgiro": "426139",
            "activity": "Byggnadsprojektering, kontroll, besiktningar, byggnadsledning",
            "employees": 15,
            "annual_turnover": 1500000,
            "capital": 50000,
            "establishment_year": 1958
        },
        "7": {
            "company_name": "EKELUND, AB JOHN O",
            "pnr": "41104",
            "address": "Göteborg, Kruthusg. Gullbergsvass",
            "phone_number": "031-196341. 1963 61",
            "bank_details": {
                "bankgiro": "510-5515",
                "postgiro": "521766-6"
            },
            "activity": "Säljer byggnadsmaterial en gros",
            "employees": 5,
            "annual_turnover": 2500000,
            "capital": 50000,
            "key_personnel": [
                {
                    "name": "John Ove Ekelund",
                    "position": "Verkst dir"
                }
            ],
            "establishment_year": 1958
        },
        "8": {
            "company_name": "eklund, ab edgar r",
            "pnr": "21146",
            "address": "Malmö, Rådmansg 8",
            "phone_number": "040-1148 74",
            "bank_details": {
                "bankgiro": "64-1374",
                "postgiro": "39929"
            },
            "activity": "Säljer elmaterial i parti, glödlampor o lysrör",
            "capital": 25000,
            "key_personnel": [
                {
                    "name": "Edgar R Eklund",
                    "position": "Verkst dir"
                }
            ],
            "establishment_year": 1932
        },
        "9": {
            "company_name": "eklunds bakelitindustri, g l",
            "pnr": "332 00",
            "address": "Gislaved, Box 8",
            "phone_number": "0371-107 36",
            "bank_details": {
                "bankgiro": "42-6716",
                "postgiro": "295179"
            },
            "activity": "Handtagskulor, lönpressning i alla förekommande härdplastmaterial",
            "key_personnel": [
                {
                    "name": "G L Eklund",
                    "position": "Ägare o chef"
                },
                {
                    "name": "G L Eklund",
                    "position": "Etableringsår"
                }
            ],
            "establishment_year": 1949
        },
        "10": {
            "company_name": "SVENSKA ESSO AB",
            "pnr": "102 40",
            "address": "Stockholm 5, Fack. Nybrog 55",
            "phone_number": "08-67 97 40, 67 98 40",
            "bank_details": {
                "bankgiro": "700-5101",
                "postgiro": "891-2"
            },
            "activity": "Försäljning av alla slags petroleumprodukter samt biltillbehör o fritidsartiklar. Smörjoljetillverkning. Biluthyrning",
            "employees": 1750,
            "annual_turnover": 1060000000,
            "capital": 145000000,
            "key_personnel": [
                {
                    "name": "Tekn dr Töre Browaldh",
                    "position": "Styrelse ordförande"
                },
                {
                    "name": "Torsten Andersson",
                    "position": "Verkst dir"
                },
                {
                    "name": "Torsten Andersson",
                    "position": "Adm-dir"
                }
            ],
            "establishment_year": 1896
        },
        "11": {
            "company_name": "SVENSKA EXTRAKTIONS. FURENINGEN EK FUR",
            "pnr": "104 25",
            "address": "Stockholm 30, Box 30025. Strand-bergsg 20",
            "phone_number": "08-514110",
            "bank_details": {
                "bankgiro": "656-6327",
                "postgiro": "297570-4"
            },
            "activity": "Bearbetar vegetabiliska fröer. Pressar o extraherar oljeväxtfrö, huvudsakligen raps o senap, varur utvinnes rå vegetabilisk olja, fodermjöl samt lecitin",
            "employees": 37,
            "annual_turnover": 125000000,
            "key_personnel": [
                {
                    "name": "Dir Lars Olof Bergman",
                    "position": "Styrelse ordförande"
                }
            ],
            "establishment_year": 1957
        },
        "12": {
            "company_name": "SVENSKA AB FIAT",
            "pnr": "172 20",
            "address": "Sundbyberg 1 Bromma, Karlsbodav 17-19. Fack Sundbyberg 1",
            "phone_number": "08-28 29 60",
            "bank_details": {
                "bankgiro": "102-8703",
                "postgiro": "53010-5"
            },
            "activity": "Import av Fiat-bilar o reservdelar",
            "employees": 160,
            "annual_turnover": 66100000,
            "capital": 10000000,
            "key_personnel": [
                {
                    "name": "Adv NO Lilliehöök",
                    "position": "Styrelse ordförande"
                },
                {
                    "name": "Riccardo Santarelli",
                    "position": "Verkst dir"
                }
            ],
            "establishment_year": 1931
        },
        "13": {
            "company_name": "TRUCK & KRANTJÄNST, AB",
            "pnr": "54100",
            "address": "Skövde, Mariestadsv 87",
            "phone_number": "0500-180 25",
            "bank_details": {
                "bankgiro": "210-1772",
                "postgiro": "279260-4"
            },
            "activity": "Uthyr mobilkranar, truckar o trailers",
            "employees": 24,
            "annual_turnover": 2000000,
            "capital": 60000,
            "key_personnel": [
                {
                    "name": "Henry Johansson",
                    "position": "Verkst dir"
                }
            ],
            "establishment_year": 1960
        },
        "14": {
            "company_name": "TRUCK-BOLAGET V STENBORG AB",
            "pnr": "114 59",
            "address": "Stockholm, Karlav 72",
            "phone_number": "08-67 42 38",
            "postgiro": "191166",
            "activity": "Säljer Heden-trucken, Harefield gummiportar samt Abeko gaffelstaplare",
            "key_personnel": [
                {
                    "name": "Victor Stenborg",
                    "position": "Chef"
                }
            ],
            "establishment_year": 1952
        },
        "15": {
            "company_name": "TRUCKBOLAGET I OREBRO AB",
            "pnr": "703 58",
            "address": "Örebro, Industrig 10",
            "phone_number": "019-18 54 3 7, 18 7 6 84",
            "bank_details": {
                "bankgiro": "143-1642",
                "postgiro": "446809-6"
            },
            "activity": "Uthyr truckar från 1-10 ton med eller utan förare",
            "employees": 3,
            "annual_turnover": 300000,
            "capital": 20000,
            "key_personnel": [
                {
                    "name": "H Bäckström",
                    "position": "Verkst dir"
                }
            ],
            "establishment_year": 1966
        },
        "16": {
            "company_name": "EL-MATERIEL AB",
            "pnr": "211 29",
            "address": "Malmö, S Promenaden 7 B",
            "phone_number": "040-717 60",
            "bank_details": {
                "bankgiro": "264-7113",
                "postgiro": "39725-7"
            },
            "activity": "Säljer elektr installationsmateriel, securusapparater, motorer, pumpar o transformatorer",
            "capital": 150000,
            "key_personnel": [
                {
                    "name": "Sven Lindström",
                    "position": "Verkst dir"
                }
            ],
            "establishment_year": 1937
        },
        "17": {
            "company_name": "KROON, AB CH",
            "pnr": "780 50",
            "address": "Vansbro, Box 4",
            "phone_number": "0281-110 40",
            "bank_details": {
                "bankgiro": "798-9031",
                "postgiro": "7676-0"
            },
            "activity": "Tillverkar o säljer cyklar, mopeder o tillbehör",
            "employees": 26,
            "annual_turnover": 2800000,
            "capital": 100000,
            "key_personnel": [
                {
                    "name": "Civiling Einar Båtels-son",
                    "position": "Verkst dir"
                }
            ],
            "establishment_year": 1910
        },
        "18": {
            "company_name": "BANKERYDS MASKIN AB",
            "pnr": "560 23",
            "address": "Banketyd",
            "phone_number": "036-77160",
            "bank_details": {
                "bankgiro": "836-9241",
                "postgiro": "144984-2"
            },
            "activity": "Köttbandsågar, köttkvarnar, el-grillar, huggblock mm",
            "employees": 35,
            "annual_turnover": 3000000,
            "capital": 90000,
            "key_personnel": [
                {
                    "name": "Fabr Torsten Martinsson",
                    "position": "Verkst dir"
                }
            ],
            "establishment_year": 1941
        }
    }
}