{
    "original": "GRAF, AB ALEXANDER\n\nPnr 302 39\n\nHalmstad, Schélev. Tel\n035-110107. Bankgiro 42-3525.\nPostgiro 157325-2. Tga Agenta\n\nVerksamhet: Nordiska\ngeneralagenturer av kortvaror\nAntal anställda: 5\nÅrsomsättning: 2 500 000\nAktiekapital: 75 000\nVerkst dir: Fredrik Graf\nEtableringsår 1939.\n\nGRAFIA I GOTEBORG AB,\nKLICHEANSTALTEN\n\nPnr 412 63\n\nGöteborg S, Almedalsv 1. Tel\n031-40 8141, 40 8142. Postgiro 44917\nVerksamhet: Klichétillverkning\nAntal anställda: 12\nÄgare: Stig Brattkvist\nEtableringsår: 1922\nOmbildat till aktiebolag 1961.\n\nGRAFIA REKLAM/\nTRYCKERI AB GRAFIA\n\nPnr 57100\n\nNässjö, Tryckerig 7. Box 73. Tel\n0380-18170. Bankgiro 83-7853.\nPostgiro 378963\n\nVerksamhet: Specialitet:\nreklam-trycksaker i 4-färgsutförande,\nbåde offset o boktryck, annonser,\nförpackningar, firmalogo,\nblanketter. Egen ateljé o reproavdelning\nAntal anställda: 20\nÅrsomsättning: 2 000 000\nAktiekapital: 70 000\nVerkst din John Theleskog\nEtableringsår: 1965.\n\nHÄSTENS SÄNGKLÄDER KB\n\nPnr 73101\n\nKöping 1, Nya Hamnv. Box 130.\nTel 0221-135 70. Bankgiro\n811-3101. Postgiro 11122-9. Tga\nNy-tagel\n\nVerksamhet: Sängklädersfabrik,\ntagelspinneri o fjäderrenseri.\nTillverkar bäddar , kuddar, täcken,\ntagel- o polyetermadrasser, plymåer\nVarunamn: Etalon\nAntal anställda: 60\nÅrsomsättning: 5 000 000\nChef: Jack Ryde\nEtableringsår: 1917.\n\nFRA\n\nÖvriga kontor: 402 31 Göteborg 7,\nBox 7048. Första Långg 21. Tel\n031-17 68 00. Telex 2343 fossalp.\nTga Fosselius\n\n25005 Hälsingborg, Box 5064.\nKielerg 44. Tel 042-614 50\n652 26 Karlstad, Orrholmsg. Tel\n054-15 0210. Telex 66083\n211 24 Malmö, Styrsö g 4. Tel\n040-93 58 00\n\n600 06 Norrköping 6, Box 6009.\nImportg 11. Tel 011-10 63 20\n\n931 031 Skellefteå 3, Box 656.\n\nDegerbyn. Tel 0910-17210\n\n851 05 Sundsvall 1, Box 288. Thuleg\n\n10. Tel 060-115170\n\n352 47 Växjö, Hj Petris väg 25.\n\nTel 0470-225 20\n\n702 27 Örebro. Radiatorv 17. Tel\n019-13 6120\nAntal anställda: 600\nAktiekapital: 15 000 000\nStyrelse: Dir Bengt Lyberg, fru\nDora Dahl, dir Karl Robert Ameln,\ndir L E Fosselius\nVerkst dir: L E Fosselius\nV verkst dir:r: Erik Lagerström\nStockholm, Jakob Fischer Göteborg\nEkonomidir: Lennart Almqvist,\nStockholm\n\nFörsäljn-chefer: lvo Spaak\nStockholm, Gunnar Fridström Göteborg\nEtableringsår: 1916.\n\nBIL &amp; BUSS I LUDVIKA AB\n\nPnr 77100\n\nLudvika, Grängesbergs v. Tel\n0240-139 30\n\nVerksamhet: Bilar, reservdelar,\nbilverkstad, lackeringsverkstad\nAntal anställda: 54\nÅrsomsättning: 10 781000\nAktiekapital: 400 000\nVerkst dir: Gösta Lindqvist\nEtableringsår: 1952.\n\nMARKARYDS EMBALLAGE AB\n\nPnr 285 00\"\n\nMarkaryd. Tel 0433-122 68, 11713.\nBankgiro 279-7462. Postgiro\n679300-4\n\nVerksamhet: Tillverkar\npappers-hylsor o runt emballage\nAntal anställda: 15\nAktiekapital: 100 000\nVeikst dir: Ake Erichs (Malmö)\nEtableringsår 1965.\n\nMARKARYDS METALL.\nARMATUR, AB\n\nPnr 285 00\n\nMarkaryd, Järnvägsg 19. Tel\n0433-11260. Bankgiro 27-9647.Postgiro\n395601\n\nVerksamhet: Tillverkar oljearmatur,\n\ntermostat- o shuntventiler\n\nVarunamn: Stato\n\nAntal anställda: 75\n\nÅrsomsättning: 11500 000\n\nAktiekapital: 200 000\n\nStyrelse: Dir Sven Nilsson, dir\n\nOlof Neljesjö, fru Wivan Nilsson,\n\nfru Olly Neljesjö\n\nVerkst dir:r Sven Nilsson, Olof\n\nNeljesjö\n\nEtableringsår: 1950.\n\nMARKARYDS SNICKERI.\nFABRIK, AB\n\nPnr 285 01\n\nMarkaryd 1, Box 23. Tel\n0433-103 01,103 05. Bankgiro 279-5912.\nPostgiro 341219-4\nVeiksamhet: Tillverkar ytterdörrar\no partier i teak, även enl ritning\nAntal anställda: 15\nÅrsomsättning: 1 000 000\nAktiekapital: 25 000\nVerkst dir: Bertil Melin\nEtableringsår: 1949.\n\nAH LM &amp; CO KNAPPTJÄNST AB\n\nPnr 10031\n\nStockholm 21, Box 21046.\nRör-strandsg 40. Tel 08-3133 30.\nBankgiro 726-1555. Postgiro\n409493-4\n\nVerksamhet: Grossist i knappar\nAntal anställda: 3\nÅrsomsättning: 250 000\nAktiekapital: 15 000\nVerkst dir: Sten Ahlm\nEtableringsår: 1946\nOmbildat till aktiebolag 1949.\n\nALM AB, BYGGNADS.\nFIRMAN E A\n\nPnr 763 01\n\nHallstavik 1, Box 48. Uppsalav 1 C.\nTel 0175-201 97, 205 48. Bankgiro\n804-8423. Postgiro 411452-6\nVerksamhet: Utför\nbyggnadsentreprenader o tillverkar färdig betong\nAntal anställda: 27\nÅrsomsättning: 1 400 000\n.Aktiekapital: 50 000\nVerkst din Ingenjör Lars Alm\nEtableringsår: 1957.\n\nALECTOR-KONSULT AB\n\nPnr 113 45\n\nStockholm, Idung 10. Tel\n08-330306. Bankgiro 370-1257.\nPostgiro 457099-0\n\nVerksamhet: Husrivningar,\nplaneringar, schaktningar\nAntal anställda: 23\nÅrsomsättning: 1700 000\nAktiekapital: 10 000\nVerkst dir: Bruno Lindström\nEtableringsår: 1968.\n\nBERGMAN AB, BERNHARD M\n\nPnr 112 24\n\nStockholm, Kungsholms\nKyrko-plan 6. Tel 08-52 09 60. Postgiro\n157922. Tga Bernberg.\nTelex 17943 BERNPAC S\nVerksamhet: Specialitet\nmaskinpackningar, isoleringsdetaljer för\nflyg- o raketindustrin\nAktiekapital: 50 000\nVerkst dir: Bernhard Bergman\nV verkst dir: Lennart Carlson\nProk: E Bergman\nEtableringsår: 1940.\n\nCEDERSKOG, AB OLOF\n\nPnr 302 34\n\nHalmstad, Hvitfeldtsg 12. Tel\n035-1174 00. Bankgiro 530-0058.\nPostgiro 178787-8. Tga Olofskog\nVerksamhet: Agentur- o\nengros-firma för handskar o vantar\nAktiekapital: 20 000\nVerkst dir: Olof Cederskog\nEtableringsår: 1953.\n\nCEDERVALL&amp; SÖNER,\nAB F R\n\nPnr 411 01\n\nGöteborg, Stampg 24. Tel\n031-15 27 95. Bankgiro 50-7942.\nPostgiro 40095. Tga Ceder\nVerksamhet: Mek verkstad o\nmetall gjuteri\nAntal anstäUda: 24\nÅrsomsättning: 1300 000\nAktiekapital: 150 000\nVerkst dir: C E Cedervall\nEtableringsår: 1899.\n\nELVÄRME\n\nPnr 602 21\n\nNorrköping, Bredg 11. Tel\n011-12 74 40. Bankgiro 60-9917.\nPostgiro 94440. Tga Elvärme\nVerksamhet: Tillverkar\nelvärmeplattor för snickeriindustrin\nChef: Bo Vesterlund\nEtableringsår: 1935.",
    "structured": {
        "1": {
            "company_name": "GRAF, AB ALEXANDER",
            "pnr": "302 39",
            "address": "Halmstad, Schélev",
            "phone_number": "035-110107",
            "bank_details": {
                "bankgiro": "42-3525",
                "postgiro": "157325-2"
            },
            "activity": "Nordiska generalagenturer av kortvaror",
            "employees": 5,
            "annual_turnover": 2500000,
            "capital": 75000,
            "key_personnel": [
                {
                    "name": "Fredrik Graf",
                    "position": "Verkst dir"
                }
            ],
            "establishment_year": 1939
        },
        "2": {
            "company_name": "GRAFIA I GOTEBORG AB, KLICHEANSTALTEN",
            "pnr": "412 63",
            "address": "Göteborg S, Almedalsv 1",
            "phone_number": "031-40 8141, 40 8142",
            "postgiro": "44917",
            "activity": "Klichétillverkning",
            "employees": 12,
            "establishment_year": 1922
        },
        "3": {
            "company_name": "GRAFIA REKLAM/TRYCKERI AB GRAFIA",
            "pnr": "57100",
            "address": "Nässjö, Tryckerig 7, Box 73",
            "phone_number": "0380-18170",
            "bank_details": {
                "bankgiro": "83-7853",
                "postgiro": "378963"
            },
            "activity": "Specialitet: reklam-trycksaker i 4-färgsutförande, både offset o boktryck, annonser, förpackningar, firmalogo, blanketter. Egen ateljé o reproavdelning",
            "employees": 20,
            "annual_turnover": 2000000,
            "capital": 70000,
            "key_personnel": [
                {
                    "name": "John Theleskog",
                    "position": "Verkst din"
                }
            ],
            "establishment_year": 1965
        },
        "4": {
            "company_name": "HÄSTENS SÄNGKLÄDER KB",
            "pnr": "73101",
            "address": "Köping 1, Nya Hamnv. Box 130",
            "phone_number": "0221-135 70",
            "bank_details": {
                "bankgiro": "811-3101",
                "postgiro": "11122-9"
            },
            "activity": "Sängklädersfabrik, tagelspinneri o fjäderrenseri. Tillverkar bäddar, kuddar, täcken, tagel- o polyetermadrasser, plymåer",
            "employees": 60,
            "annual_turnover": 5000000,
            "key_personnel": [
                {
                    "name": "Jack Ryde",
                    "position": "Chef"
                }
            ],
            "establishment_year": 1917
        },
        "5": {
            "company_name": "FRA",
            "address": "Övriga kontor: 402 31 Göteborg 7, Box 7048",
            "phone_number": "031-17 68 00",
            "employees": 600,
            "capital": 15000000,
            "key_personnel": [
                {
                    "name": "Dir Bengt Lyberg",
                    "position": "Styrelse"
                },
                {
                    "name": "fru Dora Dahl",
                    "position": "Styrelse"
                },
                {
                    "name": "dir Karl Robert Ameln",
                    "position": "Styrelse"
                },
                {
                    "name": "dir L E Fosselius",
                    "position": "Styrelse"
                },
                {
                    "name": "L E Fosselius",
                    "position": "Verkst dir"
                },
                {
                    "name": "Erik Lagerström",
                    "position": "V verkst dir"
                },
                {
                    "name": "Jakob Fischer Göteborg",
                    "position": "V verkst dir"
                },
                {
                    "name": "Lennart Almqvist",
                    "position": "Ekonomidir"
                },
                {
                    "name": "lvo Spaak Stockholm",
                    "position": "Försäljn-chef"
                },
                {
                    "name": "Gunnar Fridström Göteborg",
                    "position": "Försäljn-chef"
                }
            ],
            "establishment_year": 1916
        },
        "6": {
            "company_name": "BIL & BUSS I LUDVIKA AB",
            "pnr": "77100",
            "address": "Ludvika, Grängesbergs v",
            "phone_number": "0240-139 30",
            "activity": "Bilar, reservdelar, bilverkstad, lackeringsverkstad",
            "employees": 54,
            "annual_turnover": 10781000,
            "capital": 400000,
            "key_personnel": [
                {
                    "name": "Gösta Lindqvist",
                    "position": "Verkst dir"
                }
            ],
            "establishment_year": 1952
        },
        "7": {
            "company_name": "MARKARYDS EMBALLAGE AB",
            "pnr": "285 00",
            "address": "Markaryd",
            "phone_number": "0433-122 68, 11713",
            "bank_details": {
                "bankgiro": "279-7462",
                "postgiro": "679300-4"
            },
            "activity": "Tillverkar pappers-hylsor o runt emballage",
            "employees": 15,
            "capital": 100000,
            "key_personnel": [
                {
                    "name": "Ake Erichs",
                    "position": "Veikst dir"
                }
            ],
            "establishment_year": 1965
        },
        "8": {
            "company_name": "MARKARYDS METALL. ARMATUR, AB",
            "pnr": "285 00",
            "address": "Markaryd, Järnvägsg 19",
            "phone_number": "0433-11260",
            "bank_details": {
                "bankgiro": "27-9647",
                "postgiro": "395601"
            },
            "activity": "Tillverkar oljearmatur, termostat- o shuntventiler",
            "employees": 75,
            "annual_turnover": 11500000,
            "capital": 200000,
            "key_personnel": [
                {
                    "name": "Dir Sven Nilsson",
                    "position": "Styrelse"
                },
                {
                    "name": "dir Olof Neljesjö",
                    "position": "Styrelse"
                },
                {
                    "name": "fru Wivan Nilsson",
                    "position": "Styrelse"
                },
                {
                    "name": "fru Olly Neljesjö",
                    "position": "Styrelse"
                },
                {
                    "name": "Sven Nilsson",
                    "position": "Verkst dir:r"
                },
                {
                    "name": "Olof Neljesjö",
                    "position": "Verkst dir:r"
                }
            ],
            "establishment_year": 1950
        },
        "9": {
            "company_name": "MARKARYDS SNICKERI. FABRIK, AB",
            "pnr": "285 01",
            "address": "Markaryd 1, Box 23",
            "phone_number": "0433-103 01,103 05",
            "bank_details": {
                "bankgiro": "279-5912",
                "postgiro": "341219-4"
            },
            "activity": "Tillverkar ytterdörrar o partier i teak, även enl ritning",
            "employees": 15,
            "annual_turnover": 1000000,
            "capital": 25000,
            "key_personnel": [
                {
                    "name": "Bertil Melin",
                    "position": "Verkst dir"
                }
            ],
            "establishment_year": 1949
        },
        "10": {
            "company_name": "AH LM & CO KNAPPTJÄNST AB",
            "pnr": "10031",
            "address": "Stockholm 21, Box 21046",
            "phone_number": "08-3133 30",
            "bank_details": {
                "bankgiro": "726-1555",
                "postgiro": "409493-4"
            },
            "activity": "Grossist i knappar",
            "employees": 3,
            "annual_turnover": 250000,
            "capital": 15000,
            "key_personnel": [
                {
                    "name": "Sten Ahlm",
                    "position": "Verkst dir"
                }
            ],
            "establishment_year": 1946
        },
        "11": {
            "company_name": "ALM AB, BYGGNADS. FIRMAN E A",
            "pnr": "763 01",
            "address": "Hallstavik 1, Box 48, Uppsalav 1 C",
            "phone_number": "0175-201 97, 205 48",
            "bank_details": {
                "bankgiro": "804-8423",
                "postgiro": "411452-6"
            },
            "activity": "Utför byggnadsentreprenader o tillverkar färdig betong",
            "employees": 27,
            "annual_turnover": 1400000,
            "capital": 50000,
            "key_personnel": [
                {
                    "name": "Ingenjör Lars Alm",
                    "position": "Verkst din"
                }
            ],
            "establishment_year": 1957
        },
        "12": {
            "company_name": "ALECTOR-KONSULT AB",
            "pnr": "113 45",
            "address": "Stockholm, Idung 10",
            "phone_number": "08-330306",
            "bank_details": {
                "bankgiro": "370-1257",
                "postgiro": "457099-0"
            },
            "activity": "Husrivningar, planeringar, schaktningar",
            "employees": 23,
            "annual_turnover": 1700000,
            "capital": 10000,
            "key_personnel": [
                {
                    "name": "Bruno Lindström",
                    "position": "Verkst dir"
                }
            ],
            "establishment_year": 1968
        },
        "13": {
            "company_name": "BERGMAN AB, BERNHARD M",
            "pnr": "112 24",
            "address": "Stockholm, Kungsholms Kyrko-plan 6",
            "phone_number": "08-52 09 60",
            "postgiro": "157922",
            "activity": "Specialitet maskinpackningar, isoleringsdetaljer för flyg- o raketindustrin",
            "capital": 50000,
            "key_personnel": [
                {
                    "name": "Bernhard Bergman",
                    "position": "Verkst dir"
                },
                {
                    "name": "Lennart Carlson",
                    "position": "V verkst dir"
                },
                {
                    "name": "E Bergman",
                    "position": "Prok"
                }
            ],
            "establishment_year": 1940
        },
        "14": {
            "company_name": "CEDERSKOG, AB OLOF",
            "pnr": "302 34",
            "address": "Halmstad, Hvitfeldtsg 12",
            "phone_number": "035-1174 00",
            "bank_details": {
                "bankgiro": "530-0058",
                "postgiro": "178787-8"
            },
            "activity": "Agentur- o engros-firma för handskar o vantar",
            "capital": 20000,
            "key_personnel": [
                {
                    "name": "Olof Cederskog",
                    "position": "Verkst dir"
                }
            ],
            "establishment_year": 1953
        },
        "15": {
            "company_name": "CEDERVALL& SÖNER, AB F R",
            "pnr": "411 01",
            "address": "Göteborg, Stampg 24",
            "phone_number": "031-15 27 95",
            "bank_details": {
                "bankgiro": "50-7942",
                "postgiro": "40095"
            },
            "activity": "Mek verkstad o metall gjuteri",
            "employees": 24,
            "annual_turnover": 1300000,
            "capital": 150000,
            "key_personnel": [
                {
                    "name": "C E Cedervall",
                    "position": "Verkst dir"
                }
            ],
            "establishment_year": 1899
        },
        "16": {
            "company_name": "ELVÄRME",
            "pnr": "602 21",
            "address": "Norrköping, Bredg 11",
            "phone_number": "011-12 74 40",
            "bank_details": {
                "bankgiro": "60-9917",
                "postgiro": "94440"
            },
            "activity": "Tillverkar elvärmeplattor för snickeriindustrin",
            "key_personnel": [
                {
                    "name": "Bo Vesterlund",
                    "position": "Chef"
                }
            ],
            "establishment_year": 1935
        }
    }
}