{
    "original": "ÄNG\n\nBankgiro 37-3007. Postgiro\n480960-4\n\nVerksamhet: Byggnadssnickerier,\ninredningar, trappor mm\nÄgare o chefer: Allan Stenberg,\nOlov Risberg.\n\nÄNGELHOLMS PLÅT,AB\n\nPnr 262 01\n\nÄngelholm 1. Box 34. Tel 0431-\n\n105 36. Bankgiro 403-1266.\nPostgiro 231292-4\n\nVerksamhet: Tillverkar krok, ränner\nm m för plåtslageribranschen\nAktiekapital: 10 000\nVerkst dir: Tcrsten Ydström\nEtableringsår 1970.\n\nÄNGELHOLMS SPANNMÅL &amp;\nTRÅ AB\n\nPnr 262 01\n\nÄngelholm 1, Nybrov 5. Box 95.\nTel 0431-135 70. Bankgiro 672-2276.\nPostgiro 84201-3\n\nVerksamhet: Säljer byggvaror,\nträvaror, golvbeläggningsmaterial o\nbränsle. Utför golvläggning med\nalla förekommande material\nAntal anställda: 57\nÅrsomsättning: 19 000 000\nAktiekapital: 200 000\nVerkst dir: Lars Jönerup\nEtableringsår: 1925.\n\nESS KÅ METALLINDUSTRI AB\n\nPnr 31081\n\nLångaryd. Tel 0371-46170.\nBankgiro 434-4503. Postgiro 411845-1\nVerksamhet: Tillverkar rostfria\nkabelklammer, jordkabelklammer,\nkabelrännor o stolptak. Utför\nlegoarbeten i rostfritt o annat material.\nEgen verktygsavdelning,\nkonsulterande verksamhet\nAntal anställda: 20\nÅrsomsättning: 1400 000\nAktiekapital: 50 000\nVerkst dir: Stig Karlsson\nEtableringsår: 1958\nOmbildat till aktiebolag 1963.\n\nESSANO AB\n\nPnr 21228\n\nMalmö, Singelg 7. Tel 040-93 60 60\nVerksamhet: Tillverkar kontors- o\nkatalogpärmar, svetsade\nplastartiklar\n\nAktiekapital: 30 000\nVerkst dir: Sune Andersson\nEtableringsår: 1949\nOmbildat till aktiebolag 1961.\n\nESSBJURN AB, BYGGNADS.\nVAROR SVEN\n\nPnr 300 03\n\nHalmstad 3, Box 3085. Brog 33.\nTel 035-11 90 90. Bankgiro 85-9509.\nPostgiro 370974\n\nVerksamhet: Säljer o distribuerar\nbygg nadsmaterial\nAntal anställda: 17\nÅrsomsättning: 7 100 000\nAktiekapital: 50 000\nVerkst dir: Sven Essbjörn\nEtableringsår: 1954.\n\nBENGTSSON &amp; GEDELIUS, AB\n\nPnr 461 00\n\nTrollhättan, Tingvallav 12. Tel\n0520-180 80. Bankgiro 551-9046.\nPostgiro 133863-1. Tga Begius\nVerksamhet: Engrosförsäljning av\nbyggnadsmaterial\n\nAvdelningskontor: 652 21 Karlstad,\nGjuterig 3. Tel 054-15 68 10\nAktiekapital: 600 000\nVerkst dir: A Gedelius\nEtableringsår: 1908.\n\nBMC SWEDEN AB\n\nPnr 402 70\n\nGöteborg 8, Gamla Tuvev 15 B.\nPack. Tel 031-5138 00. Bankgiro\n170-6407. Postgiro 575330-6. Tga\nLeyscan. Telex 20941\nVerksamhet: Generalagent i Sverige\nför British Leylandbilar\nAntal anställda: 174\nÅrsomsättning: 82 000 000\nAktiekapital: 1500 000\nEtableringsår: 1960.\n\nBM-FI NÄNS AB\n\nPnr 400 71\n\nGöteborg 21, Kyrkbytorget. Box\n21044. Tel 031-5133 70\nAktiekapital: 5 000\nVerkst dir: Claes-Ake Nygren\nEtableringsår: 1965.\n\nBMJ\nSILKSCREEN-SPECIALISTEN, AB\n\nPnr 172 31\n\nSundbyberg, Esplanaden 10. Tel 08-\n\n28 1 4 6 3-66. Bankgiro 331-7195.\n\nPostgiro 351238-1\n\nVerksamhet: Screen-tryck på alla\n\nplana material\n\nVarunamn: BMJ\n\nAktiekapital: 30 000\n\nVerkst dir: Olle Blyberg\n\nEtableringsår: 1947.\n\nSONERUDS MASKIN AB\n\nPnr 824 01\n\nHudiksvall 1,Magasinsg9. Box 415.\nTel 0650-153 40, 126 40. Bankgiro\n19-1074. Postgiro 464006\nVerksamhet: Säljer traktorer (BMC)\nsamt HYMAS traktorgrävmaskiner\nAntal anställda: 10\nÅrsomsättning: 2000 000\nAktiekapital: 10 000\nVerkst dir: John Teodor Sonerud\nEtableringsår: 1958.\n\nESK\n\nVerksamhet: Industri- o\nmaskinförnödenheter\nÅrsomsättning: 1 600 000\nAntal anställda: 7\nAktiekapital: 50 000\nVerkst dir: Disp Roland Ekström\nEtableringsår: 1951.\n\nESKILSTUNA\nJERN-MANUFAKTUR AB\n\nPnr 63105\n\nEskilstuna 1, Gillbergav 4. Box\n373. Tel 016-13 94 18. Bankgiro\n601-3304. Postgiro 10716-9. Tga\nJernbo laget\n\nVerksamhet: Fastighetsförvaltning\nAntal anställda: 4\nAktiekapital: 400 000\nVerkst dir: Gunnar Wickman\nEtableringsår: 1868.\n\nERIKSON &amp; CO. AB W\n\nPnr 283 00\n\nOsby. Tel 0479-118 20. Bankgiro\n281-6197. Postgiro 10820-9\nVerksamhet: Bokbinderi,\nboktryckeri, kuvert- o pappersvarufabrik.\nTillverkar album, skrivunderlägg,\npärmar o alla slags block\nAntal anställda: 125\nÅrsomsättning: 12000 000\nAktiekapital: 500 000\nVerkst dir: Sten Erikson\nEtableringsår: 1922.\n\nSTRÖMS IMPORT AB\n\nPnr 403 17\n\nGöteborg 2, V Hamng 12. Box 2504.\nTel 031-177100. Postgiro 241115.\nTga Strömsimport\nVerksamhet: Import av textilvaror\nAktiekapital: 10 000\nVerkst dir: Alvar Ström\nEtableringsår: 1945.\n\nSTRÖM &amp; SVENSSONS\nSNICKERIFABRIK AB\n\nPnr 113 34\n\nStockholm, Gästrikeg 13. Tel\n08-30 27 96,3177 91. Bankgiro\n72-6134. Postgiro 52340\nVerksamhet: Inrednings- o\nbyggnadssnickeriarbeten\nAntal anställda: 6\nÅrsomsättning: 406 000\nAktiekapital: 20 000\nVerkst din Sven Svensson\nEtableringsår: 1929.\n\nALS\n\nALSTERFORS GLASBRUK AB\n\nPnr 360 75\n\nAlstermo. Tel 0481-614 50.\nPostgiro 413732. Tga Alsterforsglas\nVerksamhet: Tillverkar hushålls-,\nprydnads- o konstglas i sodaglas,\nhalv- o helkristall,\nbelysningsarmatur samt färgat o ofärgat\nbyggnadsglas\n\nAntal anställda: 130\nAktiekapital: 500 000\nVerkst dir: Civiling Tom Jeppson\nEtableringsår: 1886.\n\nWRETMAN AB, TYCHO\n\nPnr 11629\n\nStockholm, Bcrgmästarg 12.\nTel 08-24 59 30. Bankgiro 16-7012.\nPostgiro 50305-2\n\nVerksamhet: Boktryckeri,\nkontors-varufabrik, partihandel med\npapper o kontorsvaror\nAntal anställda: 30\nÅrsomsättning: 3 000 000\nAktiekapital: 150 000\nVerkst dir: Anders Wretman\nEtableringsår: 1928.\n\nVRETSTORPS MEK\nVERKSTAD\n\nPnr 690 51\n\nOstansjö, Box 614. Tel 0582-\n\n522 67, 522 63. Bankgiro 81-9365.\nPostgiro 395521\n\nVerksamhet: Tillverkar\nbandtransportörer, elevatorer, rullar, rullställ\nAntal anställda: 10\nÄgare o chet Pabr John Eriksson\nEtableringsår. 1950.",
    "structured": {
        "1": {
            "company_name": "ÄNGELHOLMS PLÅT,AB",
            "pnr": "262 01",
            "address": "Ängelholm 1, Box 34",
            "phone_number": "0431-105 36",
            "bank_details": {
                "bankgiro": "403-1266",
                "postgiro": "231292-4"
            },
            "activity": "Tillverkar krok, ränner m m för plåtslageribranschen",
            "capital": 10000,
            "key_personnel": [
                {
                    "name": "Torsten Ydström",
                    "position": "Verkst dir"
                }
            ],
            "establishment_year": 1970
        },
        "2": {
            "company_name": "ÄNGELHOLMS SPANNMÅL & TRÅ AB",
            "pnr": "262 01",
            "address": "Ängelholm 1, Nybrov 5, Box 95",
            "phone_number": "0431-135 70",
            "bank_details": {
                "bankgiro": "672-2276",
                "postgiro": "84201-3"
            },
            "activity": "Säljer byggvaror, trävaror, golvbeläggningsmaterial o bränsle. Utför golvläggning med alla förekommande material",
            "employees": 57,
            "annual_turnover": 19000000,
            "capital": 200000,
            "key_personnel": [
                {
                    "name": "Lars Jönerup",
                    "position": "Verkst dir"
                }
            ],
            "establishment_year": 1925
        },
        "3": {
            "company_name": "ESS KÅ METALLINDUSTRI AB",
            "pnr": "31081",
            "address": "Långaryd",
            "phone_number": "0371-46170",
            "bank_details": {
                "bankgiro": "434-4503",
                "postgiro": "411845-1"
            },
            "activity": "Tillverkar rostfria kabelklammer, jordkabelklammer, kabelrännor o stolptak. Utför legoarbeten i rostfritt o annat material. Egen verktygsavdelning, konsulterande verksamhet",
            "employees": 20,
            "annual_turnover": 1400000,
            "capital": 50000,
            "key_personnel": [
                {
                    "name": "Stig Karlsson",
                    "position": "Verkst dir"
                }
            ],
            "establishment_year": 1958
        },
        "4": {
            "company_name": "ESSANO AB",
            "pnr": "21228",
            "address": "Malmö, Singelg 7",
            "phone_number": "040-93 60 60",
            "activity": "Tillverkar kontors- o katalogpärmar, svetsade plastartiklar",
            "capital": 30000,
            "key_personnel": [
                {
                    "name": "Sune Andersson",
                    "position": "Verkst dir"
                }
            ],
            "establishment_year": 1949
        },
        "5": {
            "company_name": "ESSBJURN AB, BYGGNADSVAROR SVEN",
            "pnr": "300 03",
            "address": "Halmstad 3, Box 3085, Brog 33",
            "phone_number": "035-11 90 90",
            "bank_details": {
                "bankgiro": "85-9509",
                "postgiro": "370974"
            },
            "activity": "Säljer o distribuerar byggnadsmaterial",
            "employees": 17,
            "annual_turnover": 7100000,
            "capital": 50000,
            "key_personnel": [
                {
                    "name": "Sven Essbjörn",
                    "position": "Verkst dir"
                }
            ],
            "establishment_year": 1954
        },
        "6": {
            "company_name": "BENGTSSON & GEDELIUS, AB",
            "pnr": "461 00",
            "address": "Trollhättan, Tingvallav 12",
            "phone_number": "0520-180 80",
            "bank_details": {
                "bankgiro": "551-9046",
                "postgiro": "133863-1"
            },
            "activity": "Engrosförsäljning av byggnadsmaterial",
            "employees": 0,
            "annual_turnover": 0,
            "capital": 600000,
            "key_personnel": [
                {
                    "name": "A Gedelius",
                    "position": "Verkst dir"
                }
            ],
            "establishment_year": 1908
        },
        "7": {
            "company_name": "BMC SWEDEN AB",
            "pnr": "402 70",
            "address": "Göteborg 8, Gamla Tuvev 15 B, Pack",
            "phone_number": "031-5138 00",
            "bank_details": {
                "bankgiro": "170-6407",
                "postgiro": "575330-6"
            },
            "activity": "Generalagent i Sverige för British Leylandbilar",
            "employees": 174,
            "annual_turnover": 82000000,
            "capital": 1500000,
            "establishment_year": 1960
        },
        "8": {
            "company_name": "BM-FI NÄNS AB",
            "pnr": "400 71",
            "address": "Göteborg 21, Kyrkbytorget, Box 21044",
            "phone_number": "031-5133 70",
            "capital": 5000,
            "key_personnel": [
                {
                    "name": "Claes-Ake Nygren",
                    "position": "Verkst dir"
                }
            ],
            "establishment_year": 1965
        },
        "9": {
            "company_name": "BMJ SILKSCREEN-SPECIALISTEN, AB",
            "pnr": "172 31",
            "address": "Sundbyberg, Esplanaden 10",
            "phone_number": "08-28 1 4 6 3-66",
            "bank_details": {
                "bankgiro": "331-7195",
                "postgiro": "351238-1"
            },
            "activity": "Screen-tryck på alla plana material",
            "capital": 30000,
            "key_personnel": [
                {
                    "name": "Olle Blyberg",
                    "position": "Verkst dir"
                }
            ],
            "establishment_year": 1947
        },
        "10": {
            "company_name": "SONERUDS MASKIN AB",
            "pnr": "824 01",
            "address": "Hudiksvall 1, Magasinsg9, Box 415",
            "phone_number": "0650-153 40, 126 40",
            "bank_details": {
                "bankgiro": "19-1074",
                "postgiro": "464006"
            },
            "activity": "Säljer traktorer (BMC) samt HYMAS traktorgrävmaskiner",
            "employees": 10,
            "annual_turnover": 2000000,
            "capital": 10000,
            "key_personnel": [
                {
                    "name": "John Teodor Sonerud",
                    "position": "Verkst dir"
                }
            ],
            "establishment_year": 1958
        },
        "11": {
            "company_name": "ESK",
            "activity": "Industri- o maskinförnödenheter",
            "employees": 7,
            "annual_turnover": 1600000,
            "capital": 50000,
            "key_personnel": [
                {
                    "name": "Disp Roland Ekström",
                    "position": "Verkst dir"
                }
            ],
            "establishment_year": 1951
        },
        "12": {
            "company_name": "ESKILSTUNA JERN-MANUFAKTUR AB",
            "pnr": "63105",
            "address": "Eskilstuna 1, Gillbergav 4, Box 373",
            "phone_number": "016-13 94 18",
            "bank_details": {
                "bankgiro": "601-3304",
                "postgiro": "10716-9"
            },
            "activity": "Fastighetsförvaltning",
            "employees": 4,
            "capital": 400000,
            "key_personnel": [
                {
                    "name": "Gunnar Wickman",
                    "position": "Verkst dir"
                }
            ],
            "establishment_year": 1868
        },
        "13": {
            "company_name": "ERIKSON & CO. AB W",
            "pnr": "283 00",
            "address": "Osby",
            "phone_number": "0479-118 20",
            "bank_details": {
                "bankgiro": "281-6197",
                "postgiro": "10820-9"
            },
            "activity": "Bokbinderi, boktryckeri, kuvert- o pappersvarufabrik. Tillverkar album, skrivunderlägg, pärmar o alla slags block",
            "employees": 125,
            "annual_turnover": 12000000,
            "capital": 500000,
            "key_personnel": [
                {
                    "name": "Sten Erikson",
                    "position": "Verkst dir"
                }
            ],
            "establishment_year": 1922
        },
        "14": {
            "company_name": "STRÖMS IMPORT AB",
            "pnr": "403 17",
            "address": "Göteborg 2, V Hamng 12, Box 2504",
            "phone_number": "031-177100",
            "postgiro": "241115",
            "activity": "Import av textilvaror",
            "capital": 10000,
            "key_personnel": [
                {
                    "name": "Alvar Ström",
                    "position": "Verkst dir"
                }
            ],
            "establishment_year": 1945
        },
        "15": {
            "company_name": "STRÖM & SVENSSONS SNICKERIFABRIK AB",
            "pnr": "113 34",
            "address": "Stockholm, Gästrikeg 13",
            "phone_number": "08-30 27 96,3177 91",
            "bank_details": {
                "bankgiro": "72-6134",
                "postgiro": "52340"
            },
            "activity": "Inrednings- o byggnadssnickeriarbeten",
            "employees": 6,
            "annual_turnover": 406000,
            "capital": 20000,
            "key_personnel": [
                {
                    "name": "Sven Svensson",
                    "position": "Verkst dir"
                }
            ],
            "establishment_year": 1929
        },
        "16": {
            "company_name": "ALSTERFORS GLASBRUK AB",
            "pnr": "360 75",
            "address": "Alstermo",
            "phone_number": "0481-614 50",
            "postgiro": "413732",
            "activity": "Tillverkar hushålls-, prydnads- o konstglas i sodaglas, halv- o helkristall, belysningsarmatur samt färgat o ofärgat byggnadsglas",
            "employees": 130,
            "capital": 500000,
            "key_personnel": [
                {
                    "name": "Civiling Tom Jeppson",
                    "position": "Verkst dir"
                }
            ],
            "establishment_year": 1886
        },
        "17": {
            "company_name": "WRETMAN AB, TYCHO",
            "pnr": "11629",
            "address": "Stockholm, Bcrgmästarg 12",
            "phone_number": "08-24 59 30",
            "bank_details": {
                "bankgiro": "16-7012",
                "postgiro": "50305-2"
            },
            "activity": "Boktryckeri, kontors-varufabrik, partihandel med papper o kontorsvaror",
            "employees": 30,
            "annual_turnover": 3000000,
            "capital": 150000,
            "key_personnel": [
                {
                    "name": "Anders Wretman",
                    "position": "Verkst dir"
                }
            ],
            "establishment_year": 1928
        },
        "18": {
            "company_name": "VRETSTORPS MEK VERKSTAD",
            "pnr": "690 51",
            "address": "Ostansjö, Box 614",
            "phone_number": "0582-522 67, 522 63",
            "bank_details": {
                "bankgiro": "81-9365",
                "postgiro": "395521"
            },
            "activity": "Tillverkar bandtransportörer, elevatorer, rullar, rullställ",
            "employees": 10,
            "capital": 0,
            "key_personnel": [
                {
                    "name": "Pabr John Eriksson",
                    "position": "Ägare o chet"
                }
            ],
            "establishment_year": 1950
        }
    }
}