{
    "original": "WITTBOLDT AB. M L\n\nPnr 402 73\n\nGöteborg 8. Box 8903. Importg\n19-21. Tel 031-5200 80. Tga\nWitt-boldt. Telex 20792\nVerksamhet: Säljer trävaror o\nbyggnadsmaterial\nAntal anställda: 40\nÅrsomsättning: 14 000 000\nAktiekapital: 600 000\nVerkst dir: Sten Sjöstedt\nEtableringsår: 1912\nDotterbolag till Dickson &amp; Sjöstedt\nKB, Göteborg.\n\nWITTE &amp; SJÖHOLM AB\n\nPnr 417 07\n\nGöteborg, Tackjärnsg 3. Tel\n031-23 64 44, 23 64 45. Bankgiro 84-7792.\nPostgiro 44280. Tga Sotco\nVeiksamhet: Utför\nIngjutningsde-taljer för betongindustrin,\nautomat-svarvning mm\nVarunamn: Vemo\nAktiekapital: 80 000\nVerkst dir: Paul Witte\nEtableringsår: 1923.\n\nRISTO INGENJÖRSFIRMA AB\n\nPnr 72132\n\nVästerås 3, Box 942. Godsadress:\nSeglarg 6. Tel 021-1200 15.\nBankgiro 808-7801. Postgiro 397606-5\nVerksamhet: Värmebehandling i\nskyddsgas såsom hårdlödning,\nblankhärdning, blankglödgning,\nsätthärdning, carbonitrering\nAntal anställda: 21\nÅrsomsättning: 2500 000\nFirmatecknare: Ing Erie Lundbladh,\ning Sven Sjöblom\nEtableringsår: 1957.\n\nWING-PLAST AB\n\nPnr 330 23\n\nSmålandsstenar, Box 42. Tel 0371\n309 00. Bankgiro 142-7897.\nPost-giro 663 888-6\n\nVerksamhet: Pormsprutgods.\nIndustri- o hushållsmaskiner\nAntal anställda: 3\nÅrsomsättning: 500 000\nAktiekapital: 50 000\nChef: Kamrer Roland Wilhelmsson\nEtableringsår: 1965.\n\nPLAST- &amp; METALLTRYCK AB\n\nPnr 172 36\n\nSundbyberg, Hamng 33. Tel\n08-29 1 8 35. Bankgiro 118-5990.\nPostgiro 507494-3\n\nVerksamhet: Screentryckeri\nAktiekapital: 10 000\nVerkst dir Ake Österberg\nEtableringsår: 1954.\n\nPLAST &amp; TRÄ AB\n\nPnr 25011\n\nHelsingborg 11, Box 11053. Söderg\n137. Tel 042-124842, 13 3101.\nBankgiro 863-8181. Postgiro\n492155-7\n\nVerksamhet: Tillverkar allt i\nskumplast\nAntal anställda: 10\nAktiekapital: 25 000\nVerkst dir: Sture Dahl\nEtableringsår: 1956.\n\nRANIMETALL AB\n\nPnr 505 90\n\nBorås, Myrekulla. Tel 033-450 11,\n45111. Bankgiro 531-3382.\nPostgiro 475972-6\n\nVerksamhet: Gjutning i alla slags\nmetaller. Specialitet: komplicerat\nkärngods i alum, trycktätt gods i\nsilumin, kokillgjutning,\npressgjut-ning o maskinformning. Verktyg o\nmodeller ordnas på beställning\nAntal anställda: 30\nÅrsomsättning: 3 000 000\nAktiekapital: 100 000\nÄgare o chefer: Sten Jernkrok,\nGösta Persson\nEtableringsår: 1954\nOmbildat till aktiebolag 1963.\n\nRANK XEROX AB\n\nPnr 172 20\n\nSundbyberg 1, Pack. Bällstav 6-8.\nTel 08-98 07 00. Tga Rankxerox.\nTelex 1686 RAXE S\nVerksamhet: Uthyrning av\nkopierings- o dupliceringsmaskiner.\nService över hela landet\nFilialer: Stockholm, Enighetsv 1.\nTel 08-981120. Utställning:\nSveav 20. Tel 08-23 67 90\nGöteborg, Södra v 3-5. Tel\n031-176150\n\nMalmö, Barkg 11. Tel 040-753 60\nUmeå, Storg 36. Tel 090-11 85 90\nVarunamn: Rank Xerox\nAktiekapital: 1000 000\nVerkst dir: Carl G Vernersson\nEtableringsår 1961.\n\nÅSIVERKEN, AB\n\nPnr 662 00\n\nÅmål, Gamla Ornäsg 13. Box 51.\nTel 0532-120 00. Bankgiro 53-4649.\nPostgiro 280344. Tga Asiverken\nVerksamhet: Tillverkar stålfartyg\nupp till 1000 dw, bogserbåtar,\nfärjor o stålpråmar. Reparerar fartyg\nupp till 300 brt. Tillverkar\nresväskor, shopping väskor, bags,\nbilgarderober, flygväskor mfl artiklar\n\nSkeppsvarv: Amål, Gamla Ornäsg\n13. Tel 0532-120 00\nRes effektfabrik: Amål, Drottning\nKristinas v 4. Tel 0532-120 00\nAntal anställda: 150\nÅrsomsättning: 12 000 000\nAktiekapital: 200 000\nStyrelse: Disp Ivar Nordström\n(ordf), ing Erik Nordström, dir\nHans Nordström\nVerkst dir: Hans Nordström\nEtableringsår: 1944.\n\nSCHRÖDER AB, HANS\n\nPnr 18121\n\nLidingö 1, Box 70. Lejonv 14. Tel\n08-765 25 65. Bankgiro 627-4039.\nPostgiro 355877-2. Tga\nHaschroe-der. Telex 10468 HANSEAT S\nVerksamhet: Försäljning av\nluftkonditioneringsanläggningar, buss-värmare, pumpar, byggbara broar,\nsnöfordon o trädgårdsmaskiner\nAktiekapital: 600 000\nEtableringsån 1936.\n\nGLIMNE ANNONSBYRÅ AB\n\nPnr 30103\n\nHalmstad 1, Karl XI v 33. Box 118.\nTel 035-11 84 60. Bankgiro\n420-0008. Postgiro 399080. Tga Glimne\nVerksamhet: Auktoriserad\nannonsbyrå\n\nAktiekapital: 200 000\nVerkst dir: Ejde Glimne\nEtableringsår: 1953.\n\nGLIMÅKRA ARMATUR AB\n\nPnr 280 64\n\nGlimåkra. Box 16. Tel 044-423 00,\n426 70. Bankgiro 26-7435. Postgiro\n462713\n\nVerksamhet: Tillverkar armatur för\nvarv-, oljeindustrin\nAntal anställda: 45\nÅrsomsättning: 3 000 000\nAktiekapital: 48 000\nVerkst dir: Nils Malmsten\nEtableringsår: 1950.\n\nGLIMÅKRA MEK VERKSTAD\nAB\n\nPnr 280 64\n\nGUmåkra, Box 124. Tel 044-424 50.\nBankgiro 267-5601. Postgiro\n369300-9\n\nVerksamhet: Tillverkar\nbagerimaskiner o transportanläggningar\nVerkst dir: Fabr Erling Erlandsson\nEtableringsår: 1948.\n\nMATT-TEXTIL, AB\n\nPnr 11143\n\nStockholm, Norrlandsg 25. Tel\n08-2316 85. Bankgiro 170-1630.\nPostgiro 199629-7. Tga Mattextil\nVerksamhet: Säljer mattor en gros\nAntal anställda: 4\nAktiekapital: 50000\nChef: Dir Ove Fahlander\nKamrer: Matts-Olof Friberg\nEtableringsår: 1944\nDotterbolag: AB Sven Myrstedt,\nMyrstedts Matthörna i Västerås AB,\nAB Västerås Mattlager.\n\nmavello ab\n\nPnr 10271\n\nStockholm 9, Box 9052.\nSjöviksbacken 19. Tel 08-19 00 40.\nTelex 1655\n\nVerksamhet: Agentur o\nförsäljningsverksamhet inom\nförpackningsområdet\nAntal anställda: 5\nÅrsomsättning: 5 000 000\nVerkst dir: Civilekonom Owe\nSandegren\n\nDotterbolag till Consiva AB.\nIngår i Fortiagruppen.\n\nmaxbo, ab\n\nPnr 600 06\n\nNorrköping 6, Stohagsg 6 A. Box\n6059. Tel 011-1610 20. Postgiro\n141071\n\nVerksamhet: Konstruktionskontor\nför förpacknings- o textilmaskiner\nAntal anställda: 10\nAktiekapital: 600 000\nVerkst dir: John Gillberg\nEtableringsår: 1951.\n\nINDUSTRIUTENSILIER\n\nPnr 18131\n\nLidingö, Bergsv 27. Tel\n08-7673812, 7673820. Bankgiro 57-\n\n6475. Postgiro 159777.\nTgaRocarub-ber\n\nVerksamhet: Förkläden,\nskyddskläder m m för industrin\nChef: Roland Carnefeldt\nEtableringsår: 1941.\n\nINDUSTRIVARDERINGAR,\nINGENJÖRSFIRMAN AB\n\nPnr 651 09\n\nKarlstad 1, Herrgårdsg 6. Box 551.\nTel 054-1156 15. Bankgiro\n881-4410. Postgiro 611932-5\nVerksamhet: Försäkrings värderingar\no ekonomiska utredningar\nAntal anställda: 14\nÅrsomsättning: 316000\nChef: Dir A E Bylock\nEtableringsån 1951.",
    "structured": {
        "1": {
            "company_name": "WITTBOLDT AB",
            "activity": "Säljer trävaror och byggnadsmaterial",
            "establishment_year": 1912,
            "employees": 40,
            "annual_turnover": 14000000,
            "capital": 600000,
            "key_personnel": [
                {
                    "name": "Sten Sjöstedt",
                    "position": "Verkställande direktör"
                }
            ]
        },
        "2": {
            "company_name": "WITTE &amp; SJÖHOLM AB",
            "activity": "Utför ingjutningsdetaljer för betongindustrin, automatsvarvning mm",
            "establishment_year": 1923,
            "bank_details": {
                "bankgiro": "84-7792",
                "postgiro": "44280"
            },
            "capital": 80000,
            "key_personnel": [
                {
                    "name": "Paul Witte",
                    "position": "Verkställande direktör"
                }
            ]
        },
        "3": {
            "company_name": "RISTO INGENJÖRSFIRMA AB",
            "activity": "Värmebehandling i skyddsgas såsom hårdlödning, blankhärdning, blankglödgning, sätthärdning, carbonitrering",
            "establishment_year": 1957,
            "employees": 21,
            "annual_turnover": 2500000,
            "key_personnel": [
                {
                    "name": "Ing Erie Lundbladh",
                    "position": "Firmatecknare"
                },
                {
                    "name": "Ing Sven Sjöblom",
                    "position": "Firmatecknare"
                }
            ]
        },
        "4": {
            "company_name": "WING-PLAST AB",
            "activity": "Pormsprutgods, industri- och hushållsmaskiner",
            "establishment_year": 1965,
            "employees": 3,
            "annual_turnover": 500000,
            "capital": 50000,
            "key_personnel": [
                {
                    "name": "Kamrer Roland Wilhelmsson",
                    "position": "Chef"
                }
            ]
        },
        "5": {
            "company_name": "PLAST- &amp; METALLTRYCK AB",
            "activity": "Screentryckeri",
            "establishment_year": 1954,
            "capital": 10000,
            "key_personnel": [
                {
                    "name": "Ake Österberg",
                    "position": "Verkställande direktör"
                }
            ]
        },
        "6": {
            "company_name": "PLAST &amp; TRÄ AB",
            "activity": "Tillverkar allt i skumplast",
            "establishment_year": 1956,
            "employees": 10,
            "capital": 25000,
            "key_personnel": [
                {
                    "name": "Sture Dahl",
                    "position": "Verkställande direktör"
                }
            ]
        },
        "7": {
            "company_name": "RANIMETALL AB",
            "activity": "Gjutning i alla slags metaller, specialitet: komplicerat kärngods i alum, trycktätt gods i silumin, kokillgjutning, pressgjutning o maskinformning",
            "establishment_year": 1954,
            "employees": 30,
            "annual_turnover": 3000000,
            "capital": 100000,
            "key_personnel": [
                {
                    "name": "Sten Jernkrok",
                    "position": "Ägare och chef"
                },
                {
                    "name": "Gösta Persson",
                    "position": "Ägare och chef"
                }
            ]
        },
        "8": {
            "company_name": "RANK XEROX AB",
            "activity": "Uthyrning av kopierings- och dupliceringsmaskiner, service över hela landet",
            "establishment_year": 1961,
            "capital": 1000000,
            "key_personnel": [
                {
                    "name": "Carl G Vernersson",
                    "position": "Verkställande direktör"
                }
            ]
        },
        "9": {
            "company_name": "ÅSIVERKEN AB",
            "activity": "Tillverkar stålfartyg upp till 1000 dw, bogserbåtar, färjor och stålpråmar, repararer fartyg upp till 300 brt, tillverkar resväskor, shopping väskor, bags, bilgarderober, flygväskor mfl artiklar",
            "establishment_year": 1944,
            "employees": 150,
            "annual_turnover": 12000000,
            "capital": 200000,
            "key_personnel": [
                {
                    "name": "Disp Ivar Nordström",
                    "position": "Styrelseordförande"
                },
                {
                    "name": "Ing Erik Nordström",
                    "position": "Styrelseledamot"
                },
                {
                    "name": "Dir Hans Nordström",
                    "position": "Verkställande direktör"
                }
            ]
        },
        "10": {
            "company_name": "SCHRÖDER AB, HANS",
            "activity": "Försäljning av luftkonditioneringsanläggningar, bussvärmare, pumpar, byggbara broar, snöfordon och trädgårdsmaskiner",
            "establishment_year": 1936,
            "capital": 600000
        },
        "11": {
            "company_name": "GLIMNE ANNONSBYRÅ AB",
            "activity": "Auktoriserad annonsbyrå",
            "establishment_year": 1953,
            "capital": 200000,
            "key_personnel": [
                {
                    "name": "Ejde Glimne",
                    "position": "Verkställande direktör"
                }
            ]
        },
        "12": {
            "company_name": "GLIMÅKRA ARMATUR AB",
            "activity": "Tillverkar armatur för varv- och oljeindustrin",
            "establishment_year": 1950,
            "employees": 45,
            "annual_turnover": 3000000,
            "capital": 48000,
            "key_personnel": [
                {
                    "name": "Nils Malmsten",
                    "position": "Verkställande direktör"
                }
            ]
        },
        "13": {
            "company_name": "GLIMÅKRA MEK VERKSTAD AB",
            "activity": "Tillverkar bagerimaskiner och transportanläggningar",
            "establishment_year": 1948,
            "key_personnel": [
                {
                    "name": "Fabr Erling Erlandsson",
                    "position": "Verkställande direktör"
                }
            ]
        },
        "14": {
            "company_name": "MATT-TEXTIL AB",
            "activity": "Säljer mattor en gros",
            "establishment_year": 1944,
            "employees": 4,
            "capital": 50000,
            "key_personnel": [
                {
                    "name": "Dir Ove Fahlander",
                    "position": "Chef"
                },
                {
                    "name": "Matts-Olof Friberg",
                    "position": "Kamrer"
                }
            ]
        },
        "15": {
            "company_name": "MAVELLO AB",
            "activity": "Agentur och försäljningsverksamhet inom förpackningsområdet",
            "establishment_year": null,
            "employees": 5,
            "annual_turnover": 5000000,
            "key_personnel": [
                {
                    "name": "Civilekonom Owe Sandegren",
                    "position": "Verkställande direktör"
                }
            ],
            "parent_company": "Consiva AB, ingår i Fortiagruppen"
        },
        "16": {
            "company_name": "MAXBO AB",
            "activity": "Konstruktionskontor för förpacknings- och textilmaskiner",
            "establishment_year": 1951,
            "employees": 10,
            "capital": 600000,
            "key_personnel": [
                {
                    "name": "John Gillberg",
                    "position": "Verkställande direktör"
                }
            ]
        },
        "17": {
            "company_name": "INDUSTRIUTENSILIER",
            "activity": "Förkläden, skyddskläder m.m. för industrin",
            "establishment_year": 1941,
            "employees": 14,
            "annual_turnover": 316000,
            "key_personnel": [
                {
                    "name": "Dir A E Bylock",
                    "position": "Chef"
                }
            ]
        },
        "18": {
            "company_name": "INDUSTRIVARDERINGAR, INGENJÖRSFIRMAN AB",
            "activity": "Försäkringsvärderingar och ekonomiska utredningar",
            "establishment_year": 1951,
            "employees": 14,
            "annual_turnover": 316000,
            "key_personnel": [
                {
                    "name": "Dir A E Bylock",
                    "position": "Chef"
                }
            ]
        }
    }
}