{
    "original": "BÄCKSTRUM, AB GÖSTA\n\nPnr 102 23\n\nStockholm 12, Box 12089.\nSysslo-mansg 16. Tel 08-54 03 90.\nBankgiro 296-1043. Postgiro 50457-1.\nTga Radioback. Telex 10135\nVerksamhet: Agentur för\nelektronik, komponenter\nAntal anställda: 37\nÅrsomsättning: 20 000000\nAktiekapital: 110 000\nStyrelseordf: Gösta Bäckström\nVerkst dir: Folke Mannerstedt\nEtableringsår: 1948.\n\nBÄCKSTRÖM\nRATIONALISERINGSBYRÅ AB, GÖSTA\n\nPnr 43142\n\nMölndal, Häradsg 15. Tel\n031-27 65 30, 27 65 31. Bankgiro\n36-4761. Postgiro 428803\nVerksamhet: Konsulterande i\nekonomi, organisation,\nkvalitetskontroll o arbetsstudier\nAntal anställda: 15\nAktiekapital: 10 000\nVerkst dir: Civiling Gösta\nBäckström\n\nEtableringsår: 1954\nOmbildat till aktiebolag 1962.\n\nBÄCKSTRÖMS ÅKERI AB,\nHADAR\n\nPnr 703 58\n\nÖrebro, Industrig 10. Tel\n019-13 45 28, 13 53 40. Bankgiro\n217-6592. Postgiro 370518-3\nVerksamhet: Akerirörelse\nAntal anställda: 12\nÅrsomsättning: 1 500 000\nAktiekapital: 20 000\nVerkst dir: H Bäckström\nEtableringsår: 1949.\n\nALTO, AB\n\nPnr 660 90\n\nFotshaga, Box 14. Klarafors. Tel\n054-71940, 71941. Bankgiro\n530-9695. Postgiro 111999-9\nVerksamhet: Tillverkar\nautomat-svarvade detaljer upp till 42 mm\nO för bl a bil-, el- o\ninstrumentin-dustrin samt standardskruv,\nmuttrar o brickor\nAntal anställda: 20\nÅrsomsättning: 135 0 000\nAktiekapital: 25 000\nVerkst dir: Gunnar Bergqvist\nEtableringsår: 1968.\n\nALTON\nGULDVARU-AKTIEBOLAG\n\nPnr 52101\n\nFalköping 1, Box 42. Odeng-Aslev.\nTel 0515-130 60\n\nVerksamhet: Tillverkar silver- o\nguldsmycken\nAntal anställda: 100\nÅrsomsättning: 7 000 000\nAktiekapital: 500 000\nVerkst dir: Uno Sandell\nEtableringsår: 1945.\n\nTAIBA, AB\n\nPnr 89100\n\nÖrnsköldsvik. Tel 0660-10675.\nBankgiro 768-7411. Postgiro\n333124-6\n\nVerksamhet: Tillverkar o säljer\nlysrörsarmatur\n\nAntal anställda: 120\nÅrsomsättning: 15 000 000\nAktiekapital: 250 000\nStyrelse: Tandläk Knut Tjernström\n(ordf), dir B Vågberg\nVerkst dir: B Vågberg\nEtableringsår: 1947.\n\nTAKNER &amp; ROOS,\nBYGGNADS AB\n\nPnr 68100\n\nKristinehamn, Andra Industrig 8.\nTel 0550-130 60. Bankgiro\n110-0759. Postgiro 347411-1\nVerksamhet: Byggnadsrörelse\nAntal anställda: 40\nÅrsomsättning: 2 500 000\nAktiekapital: 30 000\nVerkst dir: Arne Roos\nEtableringsår: 1950.\n\nTALAB\n\nse Teleplan, AB\n\nTALLING, EVERT\n\nPnr 11630\n\nStockholm, Folkungag 103. Tel\n08-43 80 90,43 87 54. Bankgiro\n16-9768. Postgiro 158631. Tga\nTallingen\n\nVerksamhet: Agentur o lager för\nblixtlås, sytråd, nitar mm\nÅrsomsättning: 1000 000\nÄgare o chef: Evert Talling\nEtableringsår: 1939.\n\nTALLASENS\nMÖBEL-INDUSTRIER AB\n\nPnr 820 44\n\nTallåsen. Tel 0651-333 00.\nBankgiro 788-0222. Postgiro 33121-5\nVerksamhet: Tillverkar köks- o\nmatrumsbord\nAntal anställda: 90\nÅrsomsättning: 4 200 000\nAktiekapital: 200 000\nVeikst dir. Bengt Persson\nKamrer: Lars A Kaneskog\nFörsäljn-chef: Stig Hedlund\nEtableringsår: 1959.\n\nTAMM LABORATORIER AB,\nP-H\n\nPnr 752 36\n\nUppsala, Lilljeborgsv 12. Tel\n018-10 20 70. Bankgiro 810-7146.\nPostgiro 251637-5. TgaChemtam\nVerksamhet: Tillverkar kemiska\nlaboratoriepreparat samt utrustningar\nför kemiska analyser\nFabrik: 190 72 Altuna. Tel\n0171-960 60, 960 61\nVarunamn: Chemtam\nAntal anställda: 15\nVerkst dir: P-H S Tamm\nEtableringsår: 1946.\n\nB AGG ER AB, W\n\nPnr 26131\n\nLandskrona, Kungsg 6. Tel\n0418-100 06\n\nVerksamhet: Säljer planglas\nen gros\n\nAktiekapital: 50 000\nDisp: Gust Olsson\nEtableringsår: 1878.\n\nBAGGERMANS\nENTREPRENAD AB\n\nPnr 444 00\n\nStenungsund, Box 2. Tel\n0303-709 92, 71100. Postgiro 378403-0.\nTga Baggermans\n\nVerksamhet: Säljer makadam alla\nstorlekar, grus o sand\nFilial: Wallhamn. Tel 0304-604 26\nAntal anställda: 30\nAktiekapital: 130 000\nVerkst dir: Polke Simrén\nEtableringsår: 1956.\n\nSTORHUSQVARN, AB\n\nPnr 61101\n\nNyköping 1, V Kvarng 26. Box 98.\nTel 0155-10161. Bankgiro 82-7240.\nPostgiro 10287. Tga Storhusqvarn\nVerksamhet: Kvarnrörelse med\nspannmål, mjöl o fodervaror\nAntal anställda: 24\nÅrsomsättning: 6 100 000\nAktiekapital: 1200 000\nVerkst dir: Stig Carlborn\n(Stockholm)\n\nEtableringsår: 1888.\n\nBERGMARK &amp; CO AB, AXEL\n\nPnr 41109\n\nGöteborg, O Hamng 14. Tel 031-\n\n13 15 40, 13 3198. Bankgiro 506-\n\n5677. Postgiro 12321-6.\n\nTga Axbergmark\n\nVerksamhet: Grosshandel inom\n\nmejerihanteringen\n\nAntal anställda: 10\n\nAktiekapital: 180 600\n\nStyrelse: Generalkonsul Jes Schytt\n\n(ordf), dir Per Daun, Henning Bern-\n\nhoft\n\nVerkst dir: Per Daun\nEtableringsår: 1879\nOmbildat till aktiebolag 1938.\n\nBERGSHOLMENS\nINDUSTRIMEKANISKA\n\nPnr 93100\n\nSkellefteå, Bergsholmen. Tel\n0910-524 83. Bankgiro 98-4942. Postgiro\n487287\n\nVerksamhet: Utför\nlegotillverkning, mekaniska arbeten,\nreparationer, konstruktions- o\nmontagearbeten\n\nÄgare o chefer: A Johansson,\nJ Marklund.\n\nBERGSLAGENS BIL I\nHÄLLEFORS AB\n\nPnr 712 00\n\nHällefors, Köpmannav. Tel\n0591-11650. Bankgiro 462-2122.\nPostgiro 584260-4\n\nVerksamhet: Säljer o reparerar\nbilar. Reservdelar\nAntal anställda: 23\nÅrsomsättning: 3 000 000\n.Aktiekapital: 300 000\nVerkst dir: Nils Svensson\nEtableringsår: 1953.\n\nBERGSLAGENS BIL I\nLINDESBERG AB\n\nPnr 711 00\n\nLindesberg, Kristinav 48. Tel\n0581-124 20. Bankgiro 462-0134.\nPostgiro 29920-6\nVerksamhet: Säljer o reparerar\nbilar. Reservdelar\nAntal anställda: 55\nÅrsomsättning: 16 000 000\nAktiekapital: 90 000\nVerkst dir: Nils Svensson\nEtableringsår: 1953.\n\nBERGSLAGENS\nBYGGNADS-VAROR AB\n\nPnr 72350\n\nVästerås, Fältmätarg 12. Tel\n021-11 0 2 20. Bankgiro 808-7280.\nPostgiro 327114-5\n\nVerksamhet Golventreprenader över\nhela landet. Golvmarknad i\nVästerås med detaljförsäljning\nFilial: Gävle, S Skepparg 6 B. Tel\n026-119343\nAntal anställda: 80\nÅrsomsättning: 10 000 000\nAktiekapital: 75 000\nStyrelse: Adv Bertil Alderin (ordf),\ndir Göran Alderin, pol stud\nClaes-Göran Alderin, ekonomichef Lennart\nAxelson, försäljn-chef Per Holst,\narbetschef Kjell Björk, fru Kerstin\nAlderin (suppl)\nVerkst dir: Göran Alderin\nFörsäljn-chef: Per Holst\nArbetschef: Kjell Björk\nEtableringsår: 1946.\n\nBERGSLAGENS INDUSTRI AB\nBIAB\n\nPnr 771 00\n\nLudvika, Ostansbo. Tel\n0240-138 45. Bankgiro 467-5179.\nPostgiro 371370-8\n\nVerksamhet: Tillverkar\nluftkompressorer jämte tillbehör såsom\nfärgpistoler, luftrenare,\ntryckluft-apparater o tryckluftarmatur\nVarunamn: Biab\n\nVerksamhet: Engrosförsäljning av\nplanglas för byggnadsindustrin,\nbilrutor samt planplast o\nbyggnadsplast\n\nAvdelningskontor: Johanneshov,\nBildhuggare v 35. Tel 08-48 40 40,\n4 8 4 0 30. Chef: T Fredriksson\nVarunamn: Duoterm,\nEster-Bono-well, Perspex, Plexiglas, Rymway,\nWestcoast\nAntal anställda: 45\nÅrsomsättning: 19 000 000\nAktiekapital: 200 000\nVerkst dir: Gunnar Jarland\nEtableringsår: 1916.\n\nCEDE-VERKEN, AB\n\nPnr 280 20\n\nBjärnum, Box 122. Tel 0451-209 20.\n\nBankgiro 265-3822. Postgiro\n75380-6\n\nVerksamhet: Tillverkar\nköksinredningar, garderober o linneskåp\nAntal anställda: 25\nÅrsomsättning: 2 000 000\nAktiekapital: 100000\nVerkst dir: Pabr L Dahl\nFabrikschef: Ing N-A Svensson\nEtableringsår: 1957.\n\nCEDHAGENS MEKANISKA\nVERKSTAD AB\n\nPnr 440 03\n\nFloda. Tel 0302-303 36. Bankgiro\n547-6619. Postgiro 429818-8\nVerksamhet: Tillverkar bult o\nmutter av stål, plana mutterbrickor\nsamt metallgängad skruv\nAntal anställda: 7\nÅrsomsättning: 500 000\nAktiekapital: 15 000\nVerkst dir: Ing Lennart Cedhagen\nEtableringsår: 1954.\n\nMOTORREIMERS, AB\n\nPnr 115 33\n\nStockholm, Hedins g 11. Tel\n08-624916. Bankgiro 73-0711.\nPostgiro 258047- 0. Tga Motorreimers\nVerksamhet: Generalagenter i\nSverige för The British Seagull Co, Ltd\nÅrsomsättning: 400 000\nAktiekapital: 30 000\nVerkst dir: Knud H Reimers\nEtableringsår: 1947.\n\nmalmö byggplast ab\n\nPnr 211 57\n\nMalmö, Disponentg 10. Tel\n040-713 70. Bankgiro 876-7022.\nPostgiro 248472-3\n\nVerksamhet: Säljer plastartiklar\no -material för byggbranschen\nAntal anställda: 3\nÅrsomsättning: 400 000\nAktiekapital: 5 000\nVerkst dir: N J Ericsson\nEtableringsår: 1963.\n\nmalmö central.\ntryckeri, ab\n\nPnr 21124\n\nMalmö, Lodg 1. Tel 040-93 49 40.\nBankgiro 263-4426. Postgiro\n14193-7\n\nVerksamhet: Bok-, reklam-, o\nblankettryck\n\nAktiekapital: 50 000\nVerkst dir: Ingrid Planck\nEtableringsår: 1905.\n\nARÉN AB, B\n\nPnr 400 10\n\nGöteborg 3, Box 3043. Vasag 4.\nTel 031-17 5165. Bankgiro\n268-1369. Postgiro 425628-5\nVerksamhet: Säljer\nkontorsmaskiner, kontorssystem, luftbefuktare o\n-avfuktare, luftrenare\nAntal anställda: 7\nAktiekapital: 5 000\nVeikst din Civilekonom Bertil Arën\nEtableringsår: 1952.\n\nAHRËNS ARKITEKTKONTOR\nAB, BERTIL\n\nPnr 701 04\n\nÖrebro 1, Olaig 38. Box 290. Tel\n019-130260. Bankgiro 614-3275.\nPostgiro 543800-7\nVerksamhet Konsultverksamhet\nsamt försäljning av\nbutiksinredningar\n\nAntal anställda: 25\nÅrsomsättning: 9 000 000\nAktiekapital: 50 000\nStyrelse: Dir Helmer Reveman\n(ordf), dir Klaes Waller, dir Bertil\nÅhrén\n\nVerkst dir: Bertil Åhrén\nDisp: Olle Fröberg\nEtableringsår: 1959.",
    "structured": {
        "1": {
            "company_name": "BÄCKSTRUM, AB GÖSTA",
            "pnr": "102 23",
            "address": "Stockholm 12, Box 12089. Sysslo-mansg 16",
            "phone_number": "08-54 03 90",
            "bank_details": {
                "bankgiro": "296-1043",
                "postgiro": "50457-1"
            },
            "activity": "Agentur för elektronik, komponenter",
            "employees": 37,
            "annual_turnover": 20000000,
            "capital": 110000,
            "key_personnel": [
                {
                    "name": "Gösta Bäckström",
                    "position": "Styrelseordf"
                },
                {
                    "name": "Folke Mannerstedt",
                    "position": "Verkst dir"
                }
            ],
            "establishment_year": 1948
        },
        "2": {
            "company_name": "BÄCKSTRÖM RATIONALISERINGSBYRÅ AB, GÖSTA",
            "pnr": "43142",
            "address": "Mölndal, Häradsg 15",
            "phone_number": "031-27 65 30, 27 65 31",
            "bank_details": {
                "bankgiro": "36-4761",
                "postgiro": 428803
            },
            "activity": "Konsulterande i ekonomi, organisation, kvalitetskontroll o arbetsstudier",
            "employees": 15,
            "capital": 10000,
            "establishment_year": 1954
        },
        "3": {
            "company_name": "BÄCKSTRÖMS ÅKERI AB, HADAR",
            "pnr": "703 58",
            "address": "Örebro, Industrig 10",
            "phone_number": "019-13 45 28, 13 53 40",
            "bank_details": {
                "bankgiro": "217-6592",
                "postgiro": "370518-3"
            },
            "activity": "Akerirörelse",
            "employees": 12,
            "annual_turnover": 1500000,
            "capital": 20000,
            "key_personnel": [
                {
                    "name": "H Bäckström",
                    "position": "Verkst dir"
                }
            ],
            "establishment_year": 1949
        },
        "4": {
            "company_name": "ALTO, AB",
            "pnr": "660 90",
            "address": "Fotshaga, Box 14. Klarafors",
            "phone_number": "054-71940, 71941",
            "bank_details": {
                "bankgiro": "530-9695",
                "postgiro": "111999-9"
            },
            "activity": "Tillverkar automat-svarvade detaljer upp till 42 mm för bl a bil-, el- o instrumentin-dustrin samt standardskruv, muttrar o brickor",
            "employees": 20,
            "annual_turnover": 1350000,
            "capital": 25000,
            "key_personnel": [
                {
                    "name": "Gunnar Bergqvist",
                    "position": "Verkst dir"
                }
            ],
            "establishment_year": 1968
        },
        "5": {
            "company_name": "ALTON GULDVARU-AKTIEBOLAG",
            "pnr": "52101",
            "address": "Falköping 1, Box 42. Odeng-Aslev",
            "phone_number": "0515-130 60",
            "activity": "Tillverkar silver- o guldsmycken",
            "employees": 100,
            "annual_turnover": 7000000,
            "capital": 500000,
            "key_personnel": [
                {
                    "name": "Uno Sandell",
                    "position": "Verkst dir"
                }
            ],
            "establishment_year": 1945
        },
        "6": {
            "company_name": "TAIBA, AB",
            "pnr": "89100",
            "address": "Örnsköldsvik",
            "phone_number": "0660-10675",
            "bank_details": {
                "bankgiro": "768-7411",
                "postgiro": "333124-6"
            },
            "activity": "Tillverkar o säljer lysrörsarmatur",
            "employees": 120,
            "annual_turnover": 15000000,
            "capital": 250000,
            "key_personnel": [
                {
                    "name": "Tandläk Knut Tjernström",
                    "position": "Styrelse (ordf)"
                },
                {
                    "name": "B Vågberg",
                    "position": "Verkst dir"
                }
            ],
            "establishment_year": 1947
        },
        "7": {
            "company_name": "TAKNER & ROOS, BYGGNADS AB",
            "pnr": "68100",
            "address": "Kristinehamn, Andra Industrig 8",
            "phone_number": "0550-130 60",
            "bank_details": {
                "bankgiro": "110-0759",
                "postgiro": "347411-1"
            },
            "activity": "Byggnadsrörelse",
            "employees": 40,
            "annual_turnover": 2500000,
            "capital": 30000,
            "key_personnel": [
                {
                    "name": "Arne Roos",
                    "position": "Verkst dir"
                }
            ],
            "establishment_year": 1950
        }
    }
}