{
    "original": "WIDEBERGS ELEKTRISKA AB\n\nPnr 182 61\n\nDjursholm, Stockholmsv 107. Tel\n08-755 28 80. Bankgiro 33-5308.\nPostgiro 24627\n\nVerksamhet: Elektr\nentreprenadföretag\n\nFilial: 180 10 Täby, Täbyv 73.\nTel 08-7681930\nAntal anställda: 50\nÅrsomsättning: 4 000 000\nAktiekapital: 50 000\nVerkst dir: Per Jacobsen\nEtableringsår: 1907.\n\nTOMTENS KALKBRUKS AB\n\nPnr 520 52\n\nTorbjömtorp. Tel 0515-310 30,\n\n310 32. Bankgiro 54-1610. Postgiro\n26826\n\nVerksamhet: Tillverkar bindemedel\no puts för byggnadsindustrin,\njordbrukskalk\n\nVarunamn: Tomurex\nAntal anstäUda: 15\nAktiekapital: 195 000\nVerkst dir: Bengt Torstensson\nEtableringsår: 1913.\n\nAGRAFO AB\n\nPnr 162 11\n\nVällingby 1, Box 15. Grimstag 25.\nTel 08-37 26 90. Bankgiro 57-7404.\nPostgiro 505465\n\nVerksamhet: Arkivfilmning på70 mm\nfilm.\nMikrofilmsystem-Filmhålkort-Bildkort med fullständig kontroll\nenl US Milnorm 9868. Statistisk\nkontroll utföres av Statens\nProvningsanstalt. Framställning av\nnegativ för tryckta kretsar.\nFotografiska negativ till byggnadsnämnder.\nFotografiska kopior av typ\nCrona-flex. Sammanställningskartor i\nönskade skalor, lämpliga för\ninventerings-, planerings- o projekterings-\n\nändamål. Fullständig rektifiering\npå måttsäkert material. Specialitet:\nlednings kartverk\n\nDotterbolag: Agrafo i Skövde AB.\n54101 Skövde 1, Box 170.\nBarrstigen 2. Tel 0500-149 20. Platschef:\nBerndt Jivesten\nAntal anställda: 25\nÅrsomsättning: 1500 000\nAktiekapital: 112 500\nVerkst dir: Sture Ålander\nEtableringsår: 1954.\n\nDAHLMANS, MANUFAKTUR AB\n\nPnr 83101\n\nÖstersund 1, Storg 21. Box 562. Tel\n063-143 96. Bankgiro 777-8376.\nPostgiro 84939-8. Tga Dahlmans\nVerksamhet: Textilgrossist\nAktiekapital: 100 000\nVerkst dir: Nils Herlitz\nEtableringsår: 1933.\n\nDAHLMANS FILIALS EFTR,\nA G, ERLAND HERLITZ AB\n\nPnr 83101\n\nÖstersund 1, Storg 21. Box 562.\n\nTel 063-143 96. Tga Herlitz\nVerksamhet: Säljer garn,\nmanufaktur o gardiner\nAktiekapital: 186 250\nVerkst dir: Nils Herlitz\nEtableringsår: 1921.\n\nHÄGGH, AB GÖSTA\n\nPnr 577 00\n\nHultsfred, Box 139. Skolg 1. Tel\n0495-11120, 11121. Bankgiro\n268-5337. Postgiro 167346-6\nVerksamhet: Säljer bilreservdelar\no -tillbehör engros\nAntal anställda: 10\nÅrsomsättning: 2 000 000\nAktiekapital: 15 000\nStyrelse: Dir Gösta Häggh, fru\nKarin Häggh\nVerkst dir: Gösta Häggh\nLagerchef: Sven-Olof Moberg\nEtableringsår. 1949\nOmbildat till aktiebolag 1960.\n\nHÄGGKVIST, BRÖDERNA\n\nPnr 870 50\n\nBoUstabruk, Box 39. Tel\n0612-205 20. Bankgiro 187-4023.\nPostgiro 274063-7\n\nVerksamhet: Återförsäljare för\nSaab-bilar samt bilverkstadsrörelse\nAntal anställda: 14\nÅrsomsättning: 1505 000\nChef: Sven Häggkvist\nEtableringsår: 1943.\n\nSüD\n\nEtableringsàr: 1905\nTillhör Varnäsföretagen AB,\nKolbäck.\n\nSDDERBERGS FÖRSÄLJNINGS\nAB\n\nPnr 111 60\n\nStockholm, Välling 12. Tel\n08-2332 55. Bankgiro 482-4280.\nPostgiro 155115-9. Tga Usatrade.\nTelex 1587\n\nVerksamhet: Säljer\nentreprenadmaskiner\n\nAktiekapital: 100 000\nEtableringsàr: 1945.\n\nSÖDERBERG &amp; GRUBBENSAB\n\nPnr 124 21\n\nBandhagen 1, Stallarholmsv 40.\nBox 30. Tel 08-47 28 60. Bankgiro\n560-4871. Postgiro 51193-1.\nTelex 17928 SGSTHLM S\nVerksamhet: Grossiströrelse med\npapper\n\nAktiekapital: 2 000 000\nVerkst dir: Birger Lydén.\n\nSÖDERBERG &amp; GRUBBENS\nI NORRKÖPING AB\n\nPnr 601 03\n\nNorrköping 1, Box 89. Exportg 28.\nTel 011-13 43 80. Bankgiro\n824-2414. Postgiro 94080-9. Tga\nGrub-bens. Telex 64173\nVerksamhet: Grosshandel med\nfinpapper, omslagspapper samt\nemballageartiklar\nAntal anställda: 26\nÅrsomsättning: 15 000 000\nAktiekapital: 100 000\nVerkst dir: Allan Wijkander\nEtableringsàr: 1935\nÄger även Landbergs Papper AB.\n\nSÖDERBERG &amp; HAAK AB\n\nPnr 103 10\n\nStockholm 2, Pack. Drottningg 2.\nTel 08-24 20 00. Tga Söderberghaak.\nTelex 19355\n\nVerksamhet: Grossist i stål,\nmetaller, rör, värme, sanitet, glas,\nentreprenad- o lantbruksmaskiner\nRegionkontor: Stockholm, Göteborg,\nMalmö, Sundsvall o Köping\nLantbruksmaskiner: Staffanstorp\nAntal anställda: 950\nÅrsomsättning: 990000 000\nAktiekapital: 50 000 000\nVerkst dir: Sven Söderberg\nEtableringsàr. 1866.\n\nSÖDERBERG AB, E G\n\nPnr 11135\n\nStockholm, Kungsg 48. Tel\n08-2301 65. Bankgiro 700-0706.\nPostgiro 155360-1. Tga Egesberg\nVerksamhet: Styckning o försäljning\nav tomter för fritidsbebyggelse\nAntal anställda: 7\nAktiekapital: 1000 000\nVerkst dir: Björn Wärn\nEtableringsàr: 1941.\n\nSÖDERBERG,\nINGENJÖRSFIRMAN FOLKE\n\nPnr 430 50\n\nKållered, Box 102. Tel 031-75 12 30.\nBankgiro 410-0889. Postgiro\n243309-2. Tga Sodervent, Göteborg\n\nVerksamhet: Tillverkar fläktar för\ngruv- o tunnel ventilation\nAntal anställda: 20\nÅrsomsättning: 3 000 000\nChef: Ing Folke Söderberg\nEtableringsàr: 1948.\n\nSÖDERBERGS MASKINAFFÄR,\nAB H\n\nPnr 11640\n\nStockholm, Nytorget 4. Tel\n08-2374 70. Tga Soedermaskin.\nTelex 19009\n\nVerksamhet: Verktyg o maskiner\nAktiekapital: 150 000\nVerkst dir: H Söderberg\nEtableringsàr: 1938\nOmbildat till aktiebolag 1944.\n\nSODERBERGH\nASSURANS-FIRMA, JOHN\n\nPnr 11145\n\nStockholm, Birger Jarlsg 33. Tel\n08-1145 76, 1155 47. Bankgiro\n727-1802. Postgiro 50500-8. Tga\nRut-nega\n\nÄgare o chef: Carl-Oscar Howing\nEtableringsàr 1921.\n\nBRO\n\nTel 0590-125 50. Bankgiro 18-9424.\nPostgiro 684237\n\nVerksamhet: Civiltryckeri samt\nförlagsverksamhet. Tillverkar\ntrycksaker i boktryck o offset av alla\nkategorier. Specialitet: tidskrifter\no bokarbeten samt färgtryck\nAntal anställda: 20\nÅrsomsättning: 1000 000\nAktiekapital: 25 000\nStyrelse: Generaldir Gunnar Svärd\n(ordf), dir Einar Lidberg, dir Ulf\nLundström, disp Per Wenander,\növerstelöjtnant Agne Wärnsund\nVerkst dir: Einar W Lidberg\nTryckeriföreståndare: Fritz\nLindberg\n\nKamrer: Kerstin Olofson\nEtableringsår: 1837.\n\nNÄSLUNDS SNICKERIFABRIK\n\nPnr 87100\n\nHärnösand, Säbråv 37. Tel\n0611-128 63. Bankgiro 604-8482.\nPostgiro 73388-1\n\nVerksamhet: Tillverkar o säljer\nbyggnadssnickerier o fönster\nAntal anställda: 8\nÅrsomsättning: 800 000\nChef: Fabr Sven Erik Näslund\nEtableringsår 1925.\n\nCAPLANCO, KONFEKTIONSAB\n\nPnr 40020\n\nGöteborg 14, Box 14038. Agatan 34,\nMölndal. Tel 031-27 17 01.\nBankgiro 848-6375. Postgiro 422154-5\nVerksamhet: Säljer\npersonalkonfektion\n\nÅrsomsättning: 400 000\nAktiekapital: 5 000\nVerkst dir: Gunnar Kaplan\nEtableringsår: 1950.\n\nCITYKOPIA, AB\n\nPnr 114 26\n\nStockholm, Danderydsg 7. Tel 08-\n\n2188 15,11 2677. Bankgiro 72-8439.\nPostgiro 553926\n\nVerksamhet: Ljuskopieringsanstalt\nAktiekapital: 15 000\nVerkst dir: Fru Maja Bergström\nEtableringsår: 1957.",
    "structured": {
        "1": {
            "company_name": "WIDEBERGS ELEKTRISKA AB",
            "pnr": "182 61",
            "address": "Djursholm, Stockholmsv 107.",
            "phone_number": "08-755 28 80",
            "bank_details": {
                "bankgiro": "33-5308",
                "postgiro": "24627"
            },
            "activity": "Elektr entreprenadföretag",
            "employees": 50,
            "annual_turnover": 4000000,
            "capital": 50000,
            "key_personnel": [
                {
                    "name": "Per Jacobsen",
                    "position": "Verkst dir"
                }
            ],
            "establishment_year": 1907
        },
        "2": {
            "company_name": "TOMTENS KALKBRUKS AB",
            "pnr": "520 52",
            "address": "Torbjömtorp",
            "phone_number": "0515-310 30",
            "bank_details": {
                "bankgiro": "54-1610",
                "postgiro": "26826"
            },
            "activity": "Tillverkar bindemedel o puts för byggnadsindustrin, jordbrukskalk",
            "employees": 15,
            "capital": 195000,
            "key_personnel": [
                {
                    "name": "Bengt Torstensson",
                    "position": "Verkst dir"
                }
            ],
            "establishment_year": 1913
        },
        "3": {
            "company_name": "AGRAFO AB",
            "pnr": "162 11",
            "address": "Vällingby 1, Box 15. Grimstag 25.",
            "phone_number": "08-37 26 90",
            "bank_details": {
                "bankgiro": "57-7404",
                "postgiro": "505465"
            },
            "activity": "Arkivfilmning på 70 mm film.",
            "employees": 25,
            "annual_turnover": 1500000,
            "capital": 112500,
            "key_personnel": [
                {
                    "name": "Sture Ålander",
                    "position": "Verkst dir"
                }
            ],
            "establishment_year": 1954
        },
        "4": {
            "company_name": "DAHLMANS, MANUFAKTUR AB",
            "pnr": "83101",
            "address": "Östersund 1, Storg 21. Box 562.",
            "phone_number": "063-143 96",
            "bank_details": {
                "bankgiro": "777-8376",
                "postgiro": "84939-8"
            },
            "activity": "Textilgrossist",
            "capital": 100000,
            "key_personnel": [
                {
                    "name": "Nils Herlitz",
                    "position": "Verkst dir"
                }
            ],
            "establishment_year": 1933
        },
        "5": {
            "company_name": "DAHLMANS FILIALS EFTR, A G, ERLAND HERLITZ AB",
            "pnr": "83101",
            "address": "Östersund 1, Storg 21. Box 562.",
            "phone_number": "063-143 96",
            "activity": "Säljer garn, manufaktur o gardiner",
            "capital": 186250,
            "key_personnel": [
                {
                    "name": "Nils Herlitz",
                    "position": "Verkst dir"
                }
            ],
            "establishment_year": 1921
        },
        "6": {
            "company_name": "HÄGGH, AB GÖSTA",
            "pnr": "577 00",
            "address": "Hultsfred, Box 139. Skolg 1.",
            "phone_number": "0495-11120, 11121",
            "bank_details": {
                "bankgiro": "268-5337",
                "postgiro": "167346-6"
            },
            "activity": "Säljer bilreservdelar o -tillbehör engros",
            "employees": 10,
            "annual_turnover": 2000000,
            "capital": 15000,
            "key_personnel": [
                {
                    "name": "Gösta Häggh",
                    "position": "Verkst dir"
                }
            ],
            "establishment_year": 1949
        },
        "7": {
            "company_name": "HÄGGKVIST, BRÖDERNA",
            "pnr": "870 50",
            "address": "BoUstabruk, Box 39.",
            "phone_number": "0612-205 20",
            "bank_details": {
                "bankgiro": "187-4023",
                "postgiro": "274063-7"
            },
            "activity": "Återförsäljare för Saab-bilar samt bilverkstadsrörelse",
            "employees": 14,
            "annual_turnover": 1505000,
            "key_personnel": [
                {
                    "name": "Sven Häggkvist",
                    "position": "Chef"
                }
            ],
            "establishment_year": 1943
        },
        "8": {
            "company_name": "SDDERBERGS FÖRSÄLJNINGS AB",
            "pnr": "111 60",
            "address": "Stockholm, Välling 12.",
            "phone_number": "08-2332 55",
            "bank_details": {
                "bankgiro": "482-4280",
                "postgiro": "155115-9"
            },
            "activity": "Säljer entreprenadmaskiner",
            "capital": 100000,
            "establishment_year": 1945
        },
        "9": {
            "company_name": "SÖDERBERG & GRUBBENS AB",
            "pnr": "124 21",
            "address": "Bandhagen 1, Stallarholmsv 40. Box 30.",
            "phone_number": "08-47 28 60",
            "bank_details": {
                "bankgiro": "560-4871",
                "postgiro": "51193-1"
            },
            "activity": "Grossiströrelse med papper",
            "capital": 2000000,
            "key_personnel": [
                {
                    "name": "Birger Lydén",
                    "position": "Verkst dir"
                }
            ],
            "establishment_year": 1935
        },
        "10": {
            "company_name": "SÖDERBERG & GRUBBENS I NORRKÖPING AB",
            "pnr": "601 03",
            "address": "Norrköping 1, Box 89. Exportg 28.",
            "phone_number": "011-13 43 80",
            "bank_details": {
                "bankgiro": "824-2414",
                "postgiro": "94080-9"
            },
            "activity": "Grosshandel med finpapper, omslagspapper samt emballageartiklar",
            "employees": 26,
            "annual_turnover": 15000000,
            "capital": 100000,
            "key_personnel": [
                {
                    "name": "Allan Wijkander",
                    "position": "Verkst dir"
                }
            ],
            "establishment_year": 1935
        },
        "11": {
            "company_name": "SÖDERBERG & HAAK AB",
            "pnr": "103 10",
            "address": "Stockholm 2, Pack. Drottningg 2.",
            "phone_number": "08-24 20 00",
            "bank_details": {
                "bankgiro": "Not Available",
                "postgiro": "Not Available"
            },
            "activity": "Grossist i stål, metaller, rör, värme, sanitet, glas, entreprenad- o lantbruksmaskiner",
            "employees": 950,
            "annual_turnover": 990000000,
            "capital": 50000000,
            "key_personnel": [
                {
                    "name": "Sven Söderberg",
                    "position": "Verkst dir"
                }
            ],
            "establishment_year": 1866
        },
        "12": {
            "company_name": "SÖDERBERG AB, E G",
            "pnr": "11135",
            "address": "Stockholm, Kungsg 48.",
            "phone_number": "08-2301 65",
            "bank_details": {
                "bankgiro": "700-0706",
                "postgiro": "155360-1"
            },
            "activity": "Styckning o försäljning av tomter för fritidsbebyggelse",
            "employees": 7,
            "capital": 1000000,
            "key_personnel": [
                {
                    "name": "Björn Wärn",
                    "position": "Verkst dir"
                }
            ],
            "establishment_year": 1941
        },
        "13": {
            "company_name": "SÖDERBERG, INGENJÖRSFIRMAN FOLKE",
            "pnr": "430 50",
            "address": "Kållered, Box 102.",
            "phone_number": "031-75 12 30",
            "bank_details": {
                "bankgiro": "410-0889",
                "postgiro": "243309-2"
            },
            "activity": "Tillverkar fläktar för gruv- o tunnel ventilation",
            "employees": 20,
            "annual_turnover": 3000000,
            "key_personnel": [
                {
                    "name": "Ing Folke Söderberg",
                    "position": "Chef"
                }
            ],
            "establishment_year": 1948
        },
        "14": {
            "company_name": "SÖDERBERGS MASKINAFFÄR, AB H",
            "pnr": "11640",
            "address": "Stockholm, Nytorget 4.",
            "phone_number": "08-2374 70",
            "bank_details": {
                "bankgiro": "Not Available",
                "postgiro": "Not Available"
            },
            "activity": "Verktyg o maskiner",
            "capital": 150000,
            "key_personnel": [
                {
                    "name": "H Söderberg",
                    "position": "Verkst dir"
                }
            ],
            "establishment_year": 1938
        },
        "15": {
            "company_name": "SODERBERGH ASSURANS-FIRMA, JOHN",
            "pnr": "11145",
            "address": "Stockholm, Birger Jarlsg 33.",
            "phone_number": "08-1145 76, 1155 47",
            "bank_details": {
                "bankgiro": "727-1802",
                "postgiro": "50500-8"
            },
            "activity": "Not Available",
            "key_personnel": [
                {
                    "name": "Carl-Oscar Howing",
                    "position": "Ägare o chef"
                }
            ],
            "establishment_year": 1921
        },
        "16": {
            "company_name": "BRO",
            "phone_number": "0590-125 50",
            "bank_details": {
                "bankgiro": "18-9424",
                "postgiro": "684237"
            },
            "activity": "Civiltryckeri samt förlagsverksamhet. Tillverkar trycksaker i boktryck o offset av alla kategorier. Specialitet: tidskrifter o bokarbeten samt färgtryck",
            "employees": 20,
            "annual_turnover": 1000000,
            "capital": 25000,
            "key_personnel": [
                {
                    "name": "Einar W Lidberg",
                    "position": "Verkst dir"
                },
                {
                    "name": "Fritz Lindberg",
                    "position": "Tryckeriföreståndare"
                }
            ],
            "establishment_year": 1837
        },
        "17": {
            "company_name": "NÄSLUNDS SNICKERIFABRIK",
            "pnr": "87100",
            "address": "Härnösand, Säbråv 37.",
            "phone_number": "0611-128 63",
            "bank_details": {
                "bankgiro": "604-8482",
                "postgiro": "73388-1"
            },
            "activity": "Tillverkar o säljer byggnadssnickerier o fönster",
            "employees": 8,
            "annual_turnover": 800000,
            "key_personnel": [
                {
                    "name": "Fabr Sven Erik Näslund",
                    "position": "Chef"
                }
            ],
            "establishment_year": 1925
        },
        "18": {
            "company_name": "CAPLANCO, KONFEKTIONSAB",
            "pnr": "40020",
            "address": "Göteborg 14, Box 14038. Agatan 34, Mölndal.",
            "phone_number": "031-27 17 01",
            "bank_details": {
                "bankgiro": "848-6375",
                "postgiro": "422154-5"
            },
            "activity": "Säljer personalkonfektion",
            "annual_turnover": 400000,
            "capital": 5000,
            "key_personnel": [
                {
                    "name": "Gunnar Kaplan",
                    "position": "Verkst dir"
                }
            ],
            "establishment_year": 1950
        },
        "19": {
            "company_name": "CITYKOPIA, AB",
            "pnr": "114 26",
            "address": "Stockholm, Danderydsg 7.",
            "phone_number": "08-2188 15,11 2677",
            "bank_details": {
                "bankgiro": "72-8439",
                "postgiro": "553926"
            },
            "activity": "Ljuskopieringsanstalt",
            "capital": 15000,
            "key_personnel": [
                {
                    "name": "Fru Maja Bergström",
                    "position": "Verkst dir"
                }
            ],
            "establishment_year": 1957
        }
    }
}