{
    "original": "EKDAHLS PLÅTINDUSTRI AB\n\nPnr 260 24\n\nRöstånga. Tel 0435-913 00.\nBankgiro 282-5107. Postgiro 535516-9.\nVerksamhet Tillverkar\noljecisterner o kupade cisterngavlar\nAntal anställda: 22\nAktiekapital: 45 000\nVerkst dir: John Ekdahl\nEtableringsår: 1920.\n\nLUNNBERGS BIL AB, HANS\n\nPnr 58104\n\nLinköping 1, Box 428. Kungsg 16.\nTel 013-13 8418\n\nVerksamhet: Försäljning av\nbegagnade bilar\nAktiekapital: 70 000\nVerkst dir: Hans Lönnberg\nEtableringsår: 1939.\n\nTHEODOR|O|S &amp; CO AB\n\nPnr 11221\n\nStockholm. Hantverkarg 34. Tel\n\n08-54 1180. Bankgiro 560-5225.\nPostgiro 2671-6. Tga Theodoriab.\nTelex 10141\n\nVerksamhet: Exporterar trävaror,\nboard, papper, cellulosa. Importerar\ntobaksvaror, pipor, tändare,\nkonserver, öl. Säljer engros tvättsvamp,\nsämskskinn o övriga bilvårdsmedel\nVarunamn: Kent. Newport, Willemll,\nRowenta, Lucas, Three Diamonds,\nPilsner-Urquell, Theo\nAntal anställda: 26\nAktiekapital: 400 000\nStyrelse: Dir D J Theodoridis\n(ordf), disp Anton Theodoridis\nEtableringsår: 1883\nOmbildat till aktiebolag 1941.\n\nTHEORELLS INGENIORSBYRÅ\nAB, HUGO\n\nPnr 102 21\n\nStockholm 12, Lindhagensg 80. Box\n\n120 28. Tel 08-24 50 20. Postgiro\n55883\n\nVerksamhet: Konsulterande in-\n\ngeniörsbyrå för ång-, värme-,\nventilations-, sanitets- o kyltekniska\nanläggningar samt\nregléranlägg-ningar\n\nFilialkontor. 41136 Göteborg,\nKungsportsavenyen 33. Tel\n031-810120\n\n582 30 Linköping, Smedstadsv 9.\nTel 013-12 33 11, 12 33 49\n21148 Malmö, Erik Dahlbergsg 30D.\nTel 040-76 2 80\n\n90245 Umeå, Kungsg 66. Tel\n090-111772, 112772\n\n752 35 Uppsala, Sankt Johannesg 8.\nTel 018-127200, 1272 01\nAntal anställda: 275\nÅrsomsättning: 18000 000\nAktiekapital: 300 000\nVerkst dir: Civiling Stig Göthlin\nEtableringsår: 1889\nOmbildat till aktiebolag 1932.\n\nTERBA AB\n\nPnr 10125\n\nStockholm 1, Klara Norra Kyrkog\n31. Box 412. Tel 08-24 27 50.\nBankgiro 48-3406. Postgiro 192050.\nTelex 10553. Tga Terba\nVerksamhet: Bromsband o\nkopplingar\n\nAktiekapital: 225 000\nDir: H Wikman\nEtableringsår: 1942.\n\nDOCKSTA TRÄINDUSTRI, AB\n\nPnr 870 33\n\nDocks ta. Tel 0613-400 18.\nPostgiro 633 70\n\nVerksamhet: Tillverkar sågade o\nhyvlade trävaror\nAntal anställda: 25\nÅrsomsättning: 1000 000\nAktiekapital: 100 000\nVerkst dir: Karl-Einar Wedin\nEtableringsår 1926.\n\nTRYBOM AB, STEFAN\n\nPnr 80104\n\nGävle 1, Box 286. Nyg 20. Tel\n026-18 8 1 80. Bankgiro 60-3672.\nPostgiro 215422. Tga Nordship.\nTelex 81108\n\nVerksamhet: Skeppsmäkleri,\nbefraktning, spedition, linjeagentur\no försäkringsagentur\nAntal anställda: 8\nÅrsomsättning: 300 000\nAktiekapital: 60 000\nStyrelse: Skeppsmäkl Stefan\nTry-bom (ordf), fru Birgit Trybom, dir\nErnst Blauert\nVerkst dir: Stefan Trybom\nSpeditionsavd: Kamrer Bo Olsson\nBefraktning: Björn Bergman\nEtableringsår: 1961.\n\nTRYCK- &amp; KARTONG AB\nMÄLARDALEN\n\nPnr 150 32\n\nStallarholmen. Tel 0152-400 19.\nBankgiro 831-5574. Postgiro\n375970-1\n\nVerksamhet: Tillverkar kartonger,\nkapslar samt skol- o\nkontorsmate-riel m m\n\nFabrik: Strängnäs. Tel 0152-801 11\nAntal anställda: 50\nÅrsomsättning: 2 500 000\nAktiekapital: 110 000\nStyrelse: Dir Einar Danielsson\n(ordf), disp Oscar Hultquist, fru\nDaisy Danielsson\nVerkst dir: Einar Danielsson\nEtableringsår: 1935.\n\nAKB MILJUBYRÅN AB\n\nPnr 112 64\n\nStockholm, Eknäsv 10. Tel 08-\n\n1312 20\n\nVerksamhet: Verkar inom områdena\nmiljöteknisk forskning\nAktiekapital: 5 000\nVerkst dir: Fil mag K Spång\nEtableringsår: 1968.\n\nSTO\n\nVerksamhet: Specialitet:\nparalell-skruvstycken\n\nÄgare o chefer: Bertil Svensson,\nErik Andersson\nEtableringsår: 1938.\n\nSTORA ÅKERIET I\nGÖTE-BORG AB\n\nPnr 417 07\n\nGöteborg, Kalkbruksg 3-5. Tel\n031-51 33 20. Bankgiro 506-8291.\nPostgiro 627160-5\n\nVerksamhet: Lastbilsåkeri o\nentreprenadrörelse\n.’intal anställda: 150\nÅrsomsättning: 9000 000\nAktiekapital: 300 000\nVerkst dir: CarlrOtto Cronander\nEtableringsår: 1965.\n\nKILHAGEN &amp; CO AB\n\nPnr 41131\n\nGöteborg, Erik Dahlbergsg 46.\nTel 031-2039 11, 16 86 40.\nBankgiro 420-3568. Postgiro 44623-7.\nTga Cases\n\nVerksamhet: Export av trävaror o\nträalster\n\nAktiekapital: 20 000\nVerkst dir: Kapten Arthur\nKilhagen\n\nEtableringsår: 1937.\n\nALSTERMO BRUKS AB\n\nPnr 360 75\n\nAlstermo. Tel 0481-614 40.\nBankgiro 853-6047. Postgiro 37212-8.\nTga Amobruk, Kalmar. Telex 43008\nVerksamhet: Tillverkar reseffekter,\nspecialväskor, förvaringsboxar m m\nFörsäljningskontor: 111 35\nStockholm, Kungsg 38. Tel 08-2051 82,\n201615\n\n21120 Malmö, Nordenskiöldsg 17.\nTel 040-97 12 80\nAntal anställda: 100\nÅrsomsättning: 6 000 000\nAktiekapital: 437 500\nStyrelse: Adv Sture Hovden (ordf),\ndir Göran Langenskiöld, bankdir\nHarald Magnusson, Gösta Lönn\nVerkst dir: Gösta Lönn\nEtableringsår: 1865\nOmbildat till aktiebolag 1893.\n\nÅHLSTRÖMS\nGENERAL-AGENTUR AB\n\nPnr 122 07\n\nEnskede 7, Fack. Muskög 8. Tel\n08-59 65 70, 59 65 75. Bankgiro\n08-59 65 70, 59 65 75. Bankgiro\n731-0022. Postgiro 57621-5. Tga\nAll-tools, Stockholm\n\nVerksamhet: Fabriksrepresentant\nför utländska verktygsfabriker\nAntal anställda: 6\nÅrsomsättning: 2 000 000\nAktiekapital: 100 000\nVerkst dir: Sten Ahlström\nEtableringsår: 1935.\n\nÅHLSTRÖMS\nREVISIONS-BYRÅ AB\n\nPnr 411 37\n\nGöteborg, Kristinelundsg 5. Tel\n031-20 18 20. 20 19 20. Bankgiro\n669-4350. Postgiro 426928-8\nVerksamhet: Bokföring, revision,\nskatte- o aktiebolagsärenden\nFilial: Öckerö. Tel 031-78 20 85\nAntal anställda: 6\nÅrsomsättning: 300 000\nAktiekapital: 5 000\nChef: Revisor Bertil Ahlström\nEtableringsår 1929.\n\nÅHLSTRÖMS\nSKRUVHAKS-FABRIK &amp; CO, AB A\n\nPnr 73040\n\nKolbäck, Strömsholm. Tel\n0220-430 72. Bankgiro 810-9415.\nPostgiro 6519-3\n\nVerksamhet: Tillverkar broddar till\nhästskor, barkningsmaskiner\nAntal anställda: 4\nÅrsomsättning: 350 000\nAktiekapital: 5 000\nVerkst dir: Erik Ahlström\nEtableringsår: 1970.\n\nBAR\n\nÅrsomsättning: 5 500 000\nAktiekapital: 240 000\nEtableringsår: 1963.\n\nBALTIC,\nTRÄVARU-AKTIEBOLAGET\n\nPnr 126 62\n\nHägersten, Bandyv 47. Tel\n08-885790, 885795. Postgiro 157091.\nTga Balticwood, Stockholm\nVerksamhet: Sågade trävaror\nexport o engros\nÅrsomsättning: 2 500 000\nAktiekapital: 50 000\nVerkst dir: Anders Steinholtz\nFtableringsår: 1939.\n\nBALTIC WOODPRODUCTS AB\n\nPnr 11152\n\nStockholm, Jakobs Torg 3. Tel\n08-1189 82, 218183. Tga Balprod.\nTelex 19397 BALPROD S\nVerksamhet: Agentur för trävaror,\nrundvirke o papper\nAntal anställda: 4\nÅrsomsättning: 15000 000\nAktiekapital: 50 000\nVerkst dir: Bertil Sandström\nEtableringsår: 1950.\n\nBALTISKA\nSKINNKOMPANIET, AB\n\nPnr 103 82\n\nStockholm 7, Birger Jarlsg 6 B.\nBox 7063. Tel 08-22 68 00. Telex\n1590. Tga Baltskin\nVerksamhet: Import o export av\nhudar o skinn\nAktiekapital: 1000 000\nVerkst dir: Fritz Hollander\nEtableringsår: 1920.",
    "structured": {
        "1": {
            "company_name": "EKDAHLS PLÅTINDUSTRI AB",
            "pnr": "260 24",
            "address": "Röstånga",
            "phone_number": "0435-913 00",
            "bank_details": {
                "bankgiro": "282-5107",
                "postgiro": "535516-9"
            },
            "activity": "Tillverkar oljecisterner o kupade cisterngavlar",
            "employees": 22,
            "capital": 45000,
            "key_personnel": [
                {
                    "name": "John Ekdahl",
                    "position": "Verkst dir"
                }
            ],
            "establishment_year": 1920
        },
        "2": {
            "company_name": "LUNNBERGS BIL AB, HANS",
            "pnr": "58104",
            "address": "Linköping 1, Box 428, Kungsg 16",
            "phone_number": "013-13 8418",
            "activity": "Försäljning av begagnade bilar",
            "capital": 70000,
            "key_personnel": [
                {
                    "name": "Hans Lönnberg",
                    "position": "Verkst dir"
                }
            ],
            "establishment_year": 1939
        },
        "3": {
            "company_name": "THEODOR|O|S & CO AB",
            "pnr": "11221",
            "address": "Stockholm, Hantverkarg 34",
            "phone_number": "08-54 1180",
            "bank_details": {
                "bankgiro": "560-5225",
                "postgiro": "2671-6"
            },
            "activity": "Exporterar trävaror, board, papper, cellulosa. Importerar tobaksvaror, pipor, tändare, konserver, öl. Säljer engros tvättsvamp, sämskskinn o övriga bilvårdsmedel",
            "employees": 26,
            "capital": 400000,
            "key_personnel": [
                {
                    "name": "Dir D J Theodoridis",
                    "position": "Styrelse"
                },
                {
                    "name": "Anton Theodoridis",
                    "position": "Disp"
                }
            ],
            "establishment_year": 1883
        },
        "4": {
            "company_name": "THEORELLS INGENIORSBYRÅ AB, HUGO",
            "pnr": "102 21",
            "address": "Stockholm 12, Lindhagensg 80, Box 120 28",
            "phone_number": "08-24 50 20",
            "bank_details": {
                "postgiro": "55883"
            },
            "activity": "Konsulterande ingenjörsbyrå för ång-, värme-, ventilations-, sanitets- o kyltekniska anläggningar samt régleranläggningar",
            "employees": 275,
            "capital": 300000,
            "key_personnel": [
                {
                    "name": "Civiling Stig Göthlin",
                    "position": "Verkst dir"
                }
            ],
            "establishment_year": 1889
        },
        "5": {
            "company_name": "TERBA AB",
            "pnr": "10125",
            "address": "Stockholm 1, Klara Norra Kyrkog 31, Box 412",
            "phone_number": "08-24 27 50",
            "bank_details": {
                "bankgiro": "48-3406",
                "postgiro": "192050"
            },
            "activity": "Bromsband o kopplingar",
            "capital": 225000,
            "key_personnel": [
                {
                    "name": "H Wikman",
                    "position": "Dir"
                }
            ],
            "establishment_year": 1942
        },
        "6": {
            "company_name": "DOCKSTA TRÄINDUSTRI, AB",
            "pnr": "870 33",
            "address": "Docksta",
            "phone_number": "0613-400 18",
            "postgiro": "633 70",
            "activity": "Tillverkar sågade o hyvlade trävaror",
            "employees": 25,
            "annual_turnover": "1000 000",
            "capital": 100000,
            "key_personnel": [
                {
                    "name": "Karl-Einar Wedin",
                    "position": "Verkst dir"
                }
            ],
            "establishment_year": 1926
        },
        "7": {
            "company_name": "TRYBOM AB, STEFAN",
            "pnr": "80104",
            "address": "Gävle 1, Box 286, Nyg 20",
            "phone_number": "026-18 8 1 80",
            "bank_details": {
                "bankgiro": "60-3672",
                "postgiro": "215422"
            },
            "activity": "Skeppsmäkleri, befraktning, spedition, linjeagentur o försäkringsagentur",
            "employees": 8,
            "annual_turnover": "300 000",
            "capital": 60000,
            "key_personnel": [
                {
                    "name": "Skeppsmäkl Stefan Try-bom",
                    "position": "Styrelse (ordf)"
                },
                {
                    "name": "Birgit Trybom",
                    "position": "Styrelse"
                }
            ],
            "establishment_year": 1961
        },
        "8": {
            "company_name": "TRYCK- & KARTONG AB MÄLARDALEN",
            "pnr": "150 32",
            "address": "Stallarholmen",
            "phone_number": "0152-400 19",
            "bank_details": {
                "bankgiro": "831-5574"
            },
            "activity": "Tillverkar kartonger, kapslar samt skol- o kontorsmate-riel m m",
            "employees": 50,
            "annual_turnover": "2 500 000",
            "capital": 110000,
            "key_personnel": [
                {
                    "name": "Dir Einar Danielsson",
                    "position": "Styrelse (ordf)"
                },
                {
                    "name": "Oscar Hultquist",
                    "position": "Disp"
                }
            ],
            "establishment_year": 1935
        },
        "9": {
            "company_name": "AKB MILJUBYRÅN AB",
            "pnr": "112 64",
            "address": "Stockholm, Eknäsv 10",
            "phone_number": "08-1312 20",
            "activity": "Verkar inom områdena miljöteknisk forskning",
            "capital": 5000,
            "key_personnel": [
                {
                    "name": "Fil mag K Spång",
                    "position": "Verkst dir"
                }
            ],
            "establishment_year": 1968
        },
        "10": {
            "company_name": "STO",
            "activity": "Specialitet: paralell-skruvstycken",
            "key_personnel": [
                {
                    "name": "Bertil Svensson",
                    "position": "Ägare o chefer"
                },
                {
                    "name": "Erik Andersson",
                    "position": "Ägare o chefer"
                }
            ],
            "establishment_year": 1938
        },
        "11": {
            "company_name": "STORA ÅKERIET I GÖTE-BORG AB",
            "pnr": "417 07",
            "address": "Göteborg, Kalkbruksg 3-5",
            "phone_number": "031-51 33 20",
            "bank_details": {
                "bankgiro": "506-8291",
                "postgiro": "627160-5"
            },
            "activity": "Lastbilsåkeri o entreprenadrörelse",
            "employees": 150,
            "annual_turnover": "9000 000",
            "capital": 300000,
            "key_personnel": [
                {
                    "name": "CarlrOtto Cronander",
                    "position": "Verkst dir"
                }
            ],
            "establishment_year": 1965
        },
        "12": {
            "company_name": "KILHAGEN & CO AB",
            "pnr": "41131",
            "address": "Göteborg, Erik Dahlbergsg 46",
            "phone_number": "031-2039 11, 16 86 40",
            "bank_details": {
                "bankgiro": "420-3568",
                "postgiro": "44623-7"
            },
            "activity": "Export av trävaror o träalster",
            "capital": 20000,
            "key_personnel": [
                {
                    "name": "Kapten Arthur Kilhagen",
                    "position": "Verkst dir"
                }
            ],
            "establishment_year": 1937
        },
        "13": {
            "company_name": "ALSTERMO BRUKS AB",
            "pnr": "360 75",
            "address": "Alstermo",
            "phone_number": "0481-614 40",
            "bank_details": {
                "bankgiro": "853-6047",
                "postgiro": "37212-8"
            },
            "activity": "Tillverkar reseffekter, specialväskor, förvaringsboxar m m",
            "employees": 100,
            "annual_turnover": "6 000 000",
            "capital": 437500,
            "key_personnel": [
                {
                    "name": "Adv Sture Hovden",
                    "position": "Styrelse (ordf)"
                },
                {
                    "name": "Göran Langenskiöld",
                    "position": "Styrelse"
                }
            ],
            "establishment_year": 1865
        },
        "14": {
            "company_name": "ÅHLSTRÖMS GENERAL-AGENTUR AB",
            "pnr": "122 07",
            "address": "Enskede 7, Fack. Muskög 8",
            "phone_number": "08-59 65 70, 59 65 75",
            "bank_details": {
                "bankgiro": "731-0022",
                "postgiro": "57621-5"
            },
            "activity": "Fabriksrepresentant för utländska verktygsfabriker",
            "employees": 6,
            "annual_turnover": "2 000 000",
            "capital": 100000,
            "key_personnel": [
                {
                    "name": "Sten Ahlström",
                    "position": "Verkst dir"
                }
            ],
            "establishment_year": 1935
        },
        "15": {
            "company_name": "ÅHLSTRÖMS REVISIONS-BYRÅ AB",
            "pnr": "411 37",
            "address": "Göteborg, Kristinelundsg 5",
            "phone_number": "031-20 18 20, 20 19 20",
            "bank_details": {
                "bankgiro": "669-4350",
                "postgiro": "426928-8"
            },
            "activity": "Bokföring, revision, skatte- o aktiebolagsärenden",
            "filial": "Öckerö",
            "filial_phone_number": "031-78 20 85",
            "employees": 6,
            "annual_turnover": "300 000",
            "capital": 5000,
            "key_personnel": [
                {
                    "name": "Revisor Bertil Ahlström",
                    "position": "Chef"
                }
            ],
            "establishment_year": 1929
        },
        "16": {
            "company_name": "ÅHLSTRÖMS SKRUVHAKS-FABRIK & CO, AB A",
            "pnr": "73040",
            "address": "Kolbäck, Strömsholm",
            "phone_number": "0220-430 72",
            "bank_details": {
                "bankgiro": "810-9415",
                "postgiro": "6519-3"
            },
            "activity": "Tillverkar broddar till hästskor, barkningsmaskiner",
            "employees": 4,
            "annual_turnover": "350 000",
            "capital": 5000,
            "key_personnel": [
                {
                    "name": "Erik Ahlström",
                    "position": "Verkst dir"
                }
            ],
            "establishment_year": 1970
        },
        "17": {
            "company_name": "BAR",
            "annual_turnover": "5 500 000",
            "capital": 240000,
            "establishment_year": 1963
        },
        "18": {
            "company_name": "BALTIC, TRÄVARU-AKTIEBOLAGET",
            "pnr": "126 62",
            "address": "Hägersten, Bandyv 47",
            "phone_number": "08-885790, 885795",
            "bank_details": {
                "postgiro": "157091"
            },
            "activity": "Sågade trävaror export o engros",
            "annual_turnover": "2 500 000",
            "capital": 50000,
            "key_personnel": [
                {
                    "name": "Anders Steinholtz",
                    "position": "Verkst dir"
                }
            ],
            "establishment_year": 1939
        },
        "19": {
            "company_name": "BALTIC WOODPRODUCTS AB",
            "pnr": "11152",
            "address": "Stockholm, Jakobs Torg 3",
            "phone_number": "08-1189 82, 218183",
            "activity": "Agentur för trävaror, rundvirke o papper",
            "employees": 4,
            "annual_turnover": "15000 000",
            "capital": 50000,
            "key_personnel": [
                {
                    "name": "Bertil Sandström",
                    "position": "Verkst dir"
                }
            ],
            "establishment_year": 1950
        },
        "20": {
            "company_name": "BALTISKA SKINNKOMPANIET, AB",
            "pnr": "103 82",
            "address": "Stockholm 7, Birger Jarlsg 6 B, Box 7063",
            "phone_number": "08-22 68 00",
            "activity": "Import o export av hudar o skinn",
            "capital": 1000000,
            "key_personnel": [
                {
                    "name": "Fritz Hollander",
                    "position": "Verkst dir"
                }
            ],
            "establishment_year": 1920
        }
    }
}