{
    "original": "ALBA MASKIN CO, AB\n\nPnr 660 51\n\nNorsbron. Tel 054-41075. Bankgiro\n88-1528. Postgiro 472120. Tga\nAlbama\n\nVerksamhet: Spel o vinschar\nAktiekapital: 15 000\nVerkst dir: Per Hanmarberg\nEtableringsår: 1959.\n\nSKOGSLUNDS\nMETALL-GJUT ER I, AB\n\nPnr 330 20\n\nAnderstorp, Götg 5. Box 70. Tel\n0371-161 20. Bankgiro 488-0571.\nPostgiro 138613-5\n\nVerksamhet: Metallgjuteri\nAntal anställda: 30\nAktiekapital: 60 000\nVerkst dir: Walter Bolin\nEtableringsån 1937.\n\nBUTIKSETABLERING, AB\n\nPnr 11139\n\nStockholm, Regeringsg 109. Tel\n08-14 29 70. Bankgiro 446-8807.\nPostgiro 601633-1\n\nVerksamhet: Planering, utrustning\netc för enskild detaljhandel\nAntal anställda: 12\nÅrsomsättning: 7 000 000\nAktiekapital: 300 000\nVerkst dir: Törd Brotaeus\nEtableringsår: 1959.\n\nBUTIKSSERVICE\nSNICKERIFABRIK AB\n\nPnr 124 46\n\nBandhagen, Götlundag 3. Tel\n08-860145. Bankgiro 150-6807.\nPostgiro 508758-0\n\nVerksamhet: Tillverkar o monterar\nalla slag av specialsnickerier\nAntal anställda: 15\nÅrsomsättning: 1300 000\nAktiekapital: 50 000\nVerkst dir: Roland Runfast\nEtableringsår: 1955.\n\nCHAMPION RADIO, AB\n\nPnr 20010\n\nMalmö 17, Regementsg 10. Box\n17048. Tel 040-729 75. Bankgiro\n28-3857. Postgiro 150 684. Tga\nChampionradio\n\nVerksamhet: Radio- o\ntelevisions-materiel i parti\nAntal anställda: 15\nÅrsomsättning: 4 000 000\nAktiekapital: 100 000\nVerkst din Folke Hedlund\nEtableringsår: 1937.\n\nSCHNEIDLER AB, EDVARD\n\nPnr 10366\n\nStockholm 3, Box 3312.\nMalmskillnadsg 54. Tel 08-23 24 20, 23 47 25.\nBankgiro 446-9623. Postgiro 474-7.\nTga Schneidlers. Telex 17434\nVerksamhet: Material o\nutrustningar för grafisk o elektronisk\nindustri\n\nAktiekapital: 630 000\nVerkst dir: Jan Skantze\nEtableringsån 1850.\n\nSCHNELLPATENTBYRÅ,\nCARL T\n\nPnr 59103\n\nMotala 3, Box 331.Herrgårdsg 65 A.\nTel 0141-128 89. Bankgiro822-0337.\nPostgiro 395083-9. Tga\nSchnell-patent\n\nVerksamhet: Patentbyrå\nChef: Carl T Schnell\nEtableringsår: 1967.\n\nFURHOFFS ROSTFRIA, AB\n\nPnr 541 01\n\nSkövde 1, Box 230. Haganders v 2.\nTel 0500-108 20. Bankgiro\n210-2036. Postgiro 141385-5\nVerksamhet: Tillverkar o säljer\nrostfria storköksinredningar\nAntal anställda: 54\nÅrsomsättning: 4 000 000\nAktiekapital: 50 000\nVerkst dir: Olof Furhoff\nEtableringsår: 1899.\n\nANDERSSON AB, ROBERT\n\nPnr 331 00\n\nVärnamo, Malmstens g 13. Tel\n0370-10109\n\nVerksamhet: Tillverkar i parti alla\nslags svarveriartiklar o\nslöjdalster såsom träljusstakar,\nsällskapsspel, husgerådsartiklar\nAntal anställda: 25\nÅrsomsättning: 1000 000\nAktiekapital: 60 000\nStyrelse: Pabr Hans Aspler, fabr\nKarl-Erik Aspler\nVerkst dir: Karl-Erik Aspler\nEtableringsår: 1907.\n\nANDERSSON &amp; CO\nVERKTYGS AB, S\n\nPnr 63344\n\nEskilstuna, Vikingag 29. Tel\n016-1418 93. Bankgiro 618-2620.\nPostgiro 710470-6\n\nVerksamhet: Tillverkning av\nvattenpass o hyvlar\nAktiekapital: 5000\nVerkst dir: Sven Andersson\nEtableringsår: 1967.\n\nBOH\n\nBOHUS VARV\nKNUT TIDERMAN AB\n\nPnr 445 00\n\nBohus. Tel 031-98 00 03, 98 03 80.\nBankgiro 848-0154. Postgiro\n145621-9\n\nVerksamhet: Reparation av fartyg,\ntorrsättning upp till 800 ton.\nStål-pråmar, sopcontainers\nAntal anställda: 40\nÅrsomsättning: 2 000 000\nAktiekapital: 100 000\nVerkst dir: S A Tiderman\nEtableringsår: 1907.\n\nAktiekapital: 450 000\nVerkst dir: Manne Haby\nEtableringsår: 1955.\n\nBOHUS-TRYCK\nBRÖDERNA KARLSSON AB\n\nPnr 45100\n\nUddevalla, Brattg 8. Tel\n0522-107 78, 108 02. Bankgiro 893-8599.\nPostgiro 34566-0\nVerksamhet: Bok- o offsettryck\nAntal anställda: 11\nAktiekapital: 30000\nEtableringsår: 1919.\n\nBT-METODER, AB\n\nPnr 112 25\n\nStockholm, Kungsklippan 7. Tel\n08-50 40 22,52 24 04. Postgiro\n194214. Tga Betemetoder\nVerksamhet: Säljer apparatur för\nbehandling av avfallslutar samt\napparatur för luktbekämpning vid\nsulfatcellulosatillverkning\nÅrsomsättning: 750 000\nAktiekapital: 50 000\nVerkst dir: Ake Furrer\nEtableringsår: 1943.\n\nPSYKOTEKNISKA INSTITUTET\nI GÖTEBORG AB\n\nPnr 402 31\n\nGöteborg 7, Box 7022. Första\nLångg 30. Tel 031-12 43 10.\nBankgiro 852-6998. Postgiro 620685-8\nVerksamhet: Personalurval,\nrekryteringsfrågor, marknadspsykologi, psykologisk yrkesrådgivning\nAntal anställda: 105\nÅrsomsättning: 6 000 000\nAktiekapital: 200 000\nVerkst dir: Bo Lindkvist\nKamrer: Andrås Klss\nInformationschef: Nils Fostvedt\nChef för anlagsundersökningar:\nLars-Erik Liljequist\nEtableringsår: 1962.",
    "structured": {
        "1": {
            "company_name": "ALBA MASKIN CO, AB",
            "pnr": "660 51",
            "address": "Norsbron",
            "phone_number": "054-41075",
            "bank_details": {
                "bankgiro": "88-1528",
                "postgiro": "472120"
            },
            "activity": "Spel o vinschar",
            "capital": 15000,
            "key_personnel": [
                {
                    "name": "Per Hanmarberg",
                    "position": "Verkst dir"
                }
            ],
            "establishment_year": 1959
        },
        "2": {
            "company_name": "SKOGSLUNDS METALL-GJUTERI, AB",
            "pnr": "330 20",
            "address": "Anderstorp, Götg 5. Box 70",
            "phone_number": "0371-161 20",
            "bank_details": {
                "bankgiro": "488-0571",
                "postgiro": "138613-5"
            },
            "activity": "Metallgjuteri",
            "employees": 30,
            "capital": 60000,
            "key_personnel": [
                {
                    "name": "Walter Bolin",
                    "position": "Verkst dir"
                }
            ],
            "establishment_year": 1937
        },
        "3": {
            "company_name": "BUTIKSETABLERING, AB",
            "pnr": "11139",
            "address": "Stockholm, Regeringsg 109",
            "phone_number": "08-14 29 70",
            "bank_details": {
                "bankgiro": "446-8807",
                "postgiro": "601633-1"
            },
            "activity": "Planering, utrustning etc för enskild detaljhandel",
            "employees": 12,
            "annual_turnover": 7000000,
            "capital": 300000,
            "key_personnel": [
                {
                    "name": "Törd Brotaeus",
                    "position": "Verkst dir"
                }
            ],
            "establishment_year": 1959
        },
        "4": {
            "company_name": "BUTIKSSERVICE SNICKERIFABRIK AB",
            "pnr": "124 46",
            "address": "Bandhagen, Götlundag 3",
            "phone_number": "08-860145",
            "bank_details": {
                "bankgiro": "150-6807",
                "postgiro": "508758-0"
            },
            "activity": "Tillverkar o monterar alla slag av specialsnickerier",
            "employees": 15,
            "annual_turnover": "1300000",
            "capital": 50000,
            "key_personnel": [
                {
                    "name": "Roland Runfast",
                    "position": "Verkst dir"
                }
            ],
            "establishment_year": 1955
        },
        "5": {
            "company_name": "CHAMPION RADIO, AB",
            "pnr": "20010",
            "address": "Malmö 17, Regementsg 10. Box 17048",
            "phone_number": "040-729 75",
            "bank_details": {
                "bankgiro": "28-3857",
                "postgiro": "150 684"
            },
            "activity": "Radio- o televisi...o materiel i parti",
            "employees": 15,
            "annual_turnover": 4000000,
            "capital": 100000,
            "key_personnel": [
                {
                    "name": "Folke Hedlund",
                    "position": "Verkst dir"
                }
            ],
            "establishment_year": 1937
        },
        "6": {
            "company_name": "SCHNEIDLER AB, EDVARD",
            "pnr": "10366",
            "address": "Stockholm 3, Box 3312. Malmskillnadsg 54",
            "phone_number": "08-23 24 20, 23 47 25",
            "bank_details": {
                "bankgiro": "446-9623",
                "postgiro": "474-7"
            },
            "activity": "Material o utrustningar för grafisk o elektronisk industri",
            "capital": 630000,
            "key_personnel": [
                {
                    "name": "Jan Skantze",
                    "position": "Verkst dir"
                }
            ],
            "establishment_year": 1850
        },
        "7": {
            "company_name": "SCHNELLPATENTBYRÅ, CARL T",
            "pnr": "59103",
            "address": "Motala 3, Box 331. Herrgårdsg 65 A",
            "phone_number": "0141-128 89",
            "bank_details": {
                "bankgiro": "822-0337",
                "postgiro": "395083-9"
            },
            "activity": "Patentbyrå",
            "key_personnel": [
                {
                    "name": "Carl T Schnell",
                    "position": "Chef"
                }
            ],
            "establishment_year": 1967
        },
        "8": {
            "company_name": "FURHOFFS ROSTFRIA, AB",
            "pnr": "541 01",
            "address": "Skövde 1, Box 230. Haganders v 2",
            "phone_number": "0500-108 20",
            "bank_details": {
                "bankgiro": "210-2036",
                "postgiro": "141385-5"
            },
            "activity": "Tillverkar o säljer rostfria storköksinredningar",
            "employees": 54,
            "annual_turnover": 4000000,
            "capital": 50000,
            "key_personnel": [
                {
                    "name": "Olof Furhoff",
                    "position": "Verkst dir"
                }
            ],
            "establishment_year": 1899
        },
        "9": {
            "company_name": "ANDERSSON AB, ROBERT",
            "pnr": "331 00",
            "address": "Värnamo, Malmstens g 13",
            "phone_number": "0370-10109",
            "activity": "Tillverkar i parti alla slags svarveriartiklar o slöjdalster såsom träljusstakar, sällskapsspel, husgerådsartiklar",
            "employees": 25,
            "annual_turnover": 1000000,
            "capital": 60000,
            "key_personnel": [
                {
                    "name": "Karl-Erik Aspler",
                    "position": "Verkst dir"
                }
            ],
            "establishment_year": 1907
        },
        "10": {
            "company_name": "ANDERSSON & CO VERKTYGS AB, S",
            "pnr": "63344",
            "address": "Eskilstuna, Vikingag 29",
            "phone_number": "016-1418 93",
            "bank_details": {
                "bankgiro": "618-2620",
                "postgiro": "710470-6"
            },
            "activity": "Tillverkning av vattenpass o hyvlar",
            "capital": 5000,
            "key_personnel": [
                {
                    "name": "Sven Andersson",
                    "position": "Verkst dir"
                }
            ],
            "establishment_year": 1967
        },
        "11": {
            "company_name": "BOHUS VARV KNUT TIDERMAN AB",
            "pnr": "445 00",
            "address": "Bohus",
            "phone_number": "031-98 00 03, 98 03 80",
            "bank_details": {
                "bankgiro": "848-0154",
                "postgiro": "145621-9"
            },
            "activity": "Reparation av fartyg, torrsättning upp till 800 ton. Stål-pråmar, sopcontainers",
            "employees": 40,
            "annual_turnover": 2000000,
            "capital": 100000,
            "key_personnel": [
                {
                    "name": "S A Tiderman",
                    "position": "Verkst dir"
                }
            ],
            "establishment_year": 1907
        },
        "12": {
            "company_name": "BOHUS-TRYCK BRÖDERNA KARLSSON AB",
            "pnr": "45100",
            "address": "Uddevalla, Brattg 8",
            "phone_number": "0522-107 78, 108 02",
            "bank_details": {
                "bankgiro": "893-8599",
                "postgiro": "34566-0"
            },
            "activity": "Bok- o offsettryck",
            "employees": 11,
            "capital": 30000,
            "establishment_year": 1919
        },
        "13": {
            "company_name": "BT-METODER, AB",
            "pnr": "112 25",
            "address": "Stockholm, Kungsklippan 7",
            "phone_number": "08-50 40 22,52 24 04",
            "postgiro": "194214",
            "activity": "Säljer apparatur för behandling av avfallslutar samt apparatur för luktbekämpning vid sulfatcellulosatillverkning",
            "annual_turnover": 750000,
            "capital": 50000,
            "key_personnel": [
                {
                    "name": "Ake Furrer",
                    "position": "Verkst dir"
                }
            ],
            "establishment_year": 1943
        },
        "14": {
            "company_name": "PSYKOTEKNISKA INSTITUTET I GÖTEBORG AB",
            "pnr": "402 31",
            "address": "Göteborg 7, Box 7022. Första Långg 30",
            "phone_number": "031-12 43 10",
            "bank_details": {
                "bankgiro": "852-6998",
                "postgiro": "620685-8"
            },
            "activity": "Personalurval, rekryteringsfrågor, marknadspsykologi, psykologisk yrkesrådgivning",
            "employees": 105,
            "annual_turnover": 6000000,
            "capital": 200000,
            "key_personnel": [
                {
                    "name": "Bo Lindkvist",
                    "position": "Verkst dir"
                },
                {
                    "name": "Andrås Klss",
                    "position": "Kamrer"
                },
                {
                    "name": "Nils Fostvedt",
                    "position": "Informationschef"
                },
                {
                    "name": "Lars-Erik Liljequist",
                    "position": "Chef för anlagsundersökningar"
                }
            ],
            "establishment_year": 1962
        }
    }
}