{
    "original": "FIRESTONE - VISKAFORS AB\n\nPnr 501 04\n\nBorås 1, österlångg 40. Box 167.\nTel 033-12 70 80. Bankgiro 43-4861.\nPostgiro 30862. Tga Firestone,\nViskaforsgummi.\nTelex 36116 FIRESTB S\nVerksamhet: Tillverkar i samarbete\nmed Firestone Tire &amp; Rubber Co,\nUSA, bil-, traktor- o\nvägmaskins-däck, tekn gummivaror såsom\nslangar, gummibeläggningar,\ngummimattor, gummiduk, formgjorda o\nspritsade artiklar etc\nAvdelningskontor: Göteborg 8,\nTors-landav. Box 8893. Tel 031-53 04 55,\n54 18 13, 54 2157\n\nMalmö, Borrg 36. Tel 040-93 61 20\nSundbyberg, Ekensbergsv 128. Tel\n08-83 50 30\n\nSundsvall, Gäxdsv 1. Tel\n060-668 70\n\nÖrebro, Kyrkog 11. Tel\n019-117692\n\nAntal anställda: 1300\nAktiekapital: 19 600 000\nStyrelse: Dir Gösta Österman (ordf),\nadv Sten Lindskog, bankdir Töre\nBjörkman, civiling Harry\nBryniels-son, mr J Lombardo.mr J M Harvey,\nadv Wilhelm Pehrsson\nVerkst dir: John M Harvey\nV verkst dir: Rune Hörnfeldt\nInköpschef: Disp Björn Sällström\nFabrikschef: Tekn dir Arne\nJakobsson\n\nEtableringsår: 1890\n\nDotterbolag till The Firestone Tire\n&amp; Rubber Co, Akron, Ohio, USA.\n\nFISCHER &amp; PORTER AB\n\nPnr 127 04\n\nSkärholmen 4, Box 4026.\nStorholms-backarna 78. Tel 08-710 00 95.\nBankgiro 857-6118. Postgiro\n408470-3. Telex 10276\nVerksamhet: Säljer automatiska\ninstrument för kontroll av\nindustriella o andra processer. Utför\nplanering, utveckling, installering o\n\nunderhåll av ovannämnda\ninstrument\n\nFilial: 85249 Sundsvall, Mästerg4.\nTel 060-1100 94\nVarunamn: Fischer &amp; Porter\nAntal anställda: 12\nÅrsomsättning: 5 000000\nAktiekapital: 60 000\nVerkst dir: Sven Olof Löf\nEtableringsår: 1968.\n\nFISKARHEDENS SNICKERI.\nFABRIK, AB\n\nPnr 780 68\n\nTranstrand, Fiskarheden. Tel\n0280-222 00. Bankgiro 471-6023.\nPostgiro 71469-1\nAntal anställda: 26\nÅrsomsättning: 1600 000\nVerksamhet: Tillverkar fönster,\ndörrpartier o sportstugemöbler.\nSäljer byggnadsmaterial från lager\nAntal anställda: 30\nÅrsomsättning: 1400 000\nAktiekapital: 54000\nVerkst dir: Alf Johansson\nEtableringsår: 1920\nOmbildat till aktiebolag 1945.\n\nFISKEBRODERNA AB\n\nPnr 450 40\n\nKungshamn. Box 90. Hamng 2.\nTel 0523-300 87, 300 10. Bankgiro\n543-4188. Postgiro 26739-3. Tga\nFiskebröderna\n\nVerksamhet: Fiskkonservfabrik\nAntal anställda: 125\nÅrsomsättning: 10 000 000\nAktiekapital: 500 000\nVerkst dir: Knut Sjöman\nEtableringsår: 1920.\n\nGUL\n\nGULDSTRAND AB, CARL\n\nPnr 113 57\n\nStockholm, Kungstensg 12. Tel\n08-1505 05. Bankgiro 211-1383.\nPostgiro 450500-4. Tga Carlguld.\nTelex 10317\n\nVerksamhet: Import av herr- o\ndamstrumpor samt herr- o damstickat\nAktiekapital: 30 000\nVerkst dir: Leo Goldensohn\nEtableringsår: 1906.\n\nWONS AB, MASKINFIRMAN\n\nPnr 85241\n\nSundsvall, Solg 5. Tel 060-11 77 70.\nBankgiro 180-4129. Postgiro\n100842-4\n\nVerksamhet: Tillverkar patenterade\nprovtrycknings- o\nprovtätningsut-rustningar för alla slags rör. Säljer\nmaskiner o redskap för\nanläggningsbranschen\nAntal anställda: 5\nÅrsomsättning: 500 000\nAktiekapital: 8 000\nVerkst dir: Erie Henry Norman\nEtableringsår: 1955.\n\nELEKTRO-METALL AB\n\nPnr 232 00\n\nArlöv, Box 92. Smedjev 2. Tel\n040-43 15 15. Bankgiro 874-3254.\nPostgiro 38504-7\n\nVerksamhet: Utför drag- o\nexcenter-pressning samt metalltryckning\nAntal anstäUda: 17\nAktiekapital: 105 000\nVerkst dir: Klas Johansson\nEtableringsår: 1921.\n\nELEKTROMIKANIT I LAXÅ AB\n\nPnr 69501\n\nLaxå, Box 43. Tel 0584-108 60.\nBankgiro 461-6025. Postgiro\n80687-7. Tga Elektromikanit.\nTelex 73380 EMIL S\nVerksamhet: Säljer dynamotråd o\nelektr isolationsmaterial\nFörsäljningskontor: 113 29\nStockholm. Agenturfirman Isoma, Vegag 1.\nTel 08-30 6010\n\n25232 Helsingborg, Elektrog. Tel\n042-18 18 5 6\nAntal anställda: 10\nÅrsomsättning: 9000 000\nAktiekapital: 40 400\nVerkst dir: Ake Olson\nEtableringsår: 1945.\n\nTHORNWALLS FABRIKS AB\n\nPnr 570 76\n\nRuda, Box 53. Tel 0491-22082,\n222 82. Bankgiro 859-0119.\nPostgiro 108409-4\n\nVerksamhet: Tillverkar möbler\nAntal anställda: 21\nÅrsomsättning: 2 500 000\nAktiekapital: 120 000\nVerkst dir. Ing Boo Thörnwall\nEtableringsår: 1948.\n\nTIN\n\nVerksamhet: Tillverkar\nmineralvatten, läskedrycker, juicer o öl\nGeneralagent för Bass, England,\nCeres, Danmark o Löwenbräu,\nTyskland\n\nAntal anställda: 251\nÅrsomsättning: 68 000 000\nAktiekapital: 210 000\nVerkst din Henry Larsson\nEtableringsår: 1931.\n\nMEMO-TOOL, AB\n\nPnr 631 03\n\nEskilstuna 1, Box 197. Eriksdals g\n18. Tel 016-13 55 93. Bankgiro\n58-2337. Postgiro 137663-1. Tga\nMemo\n\nVerksamhet: Tillverkar\nprecisionsvattenpass, vattenpass o mätverktyg\nVarunamn: Memo, Memo-Tool\nAktiekapital: 60 000\nVerkst dir: Börje Broberg\nEtableringsår: 1941.\n\nARENCO AB\n\nPnr 16210\n\nVällingby 1, Fack. Siktg 11. Tel\n08-89 00 60. Bankgiro 57-7513.\nPostgiro 1647. Tga Arenco.\nTelex 10264\n\nVerksamhet: Tillverkar\ntändsticks-maskiner, maskiner för\ntobaksindustrin, packningsmaskiner o\nfisk-rensningsmaskiner\nAntal anställda: 850\nÅrsomsättning: 60 000000\nAktiekapital: 6 000 000\nVerkst dir: K E Sahlberg\nEtableringsår: 1885.\n\nARENTORPS\nCEMENT-VARUFABRIK, AB\n\nPnr 534 00\n\nVara, Arentorp. Tel 0512-13170.\nBankgiro 215-5539. Postgiro\n385612-7\n\nVerksamhet: Tillverkar o säljer\nbetongrör, betongelement\nAntal anställda: 30\nÅrsomsättning: 2 700 000\nAktiekapital: 60 000\nVerkst dir: Sven Ehn\nEtableringsår: 1922.\n\nWIBECO, AB\n\nPnr 413 04\n\nGöteborg, Risåsg 23. Tel\n031-1062 34, 110188. Bankgiro\n500-2704. Postgiro 421984-6. Tga\nWi-beco\n\nVerksamhet: Tillverkar o säljer\nvägmärken o trafikanordningar.\nExporterar present- o träartiklar\nArsomsättning: 350 000\nAktiekapital: 31000\nVerkst dir: Ing Hjälte Wiberg\nEtableringsår: 1928.\n\nWIBERGS KONTORS.\nORGANISATION\n\nPnr 417 40\n\nGöteborg, Rimfrostg 27. Tel\n031-54 33 59. Bankgiro 107-6504.\nPostgiro 426015-4\n\nVerksamhet: Utför förslag o lämnar\noffert samt utför leveranser å\ninredningar till kontor,\npastorsexpeditioner, bibliotek mm\nÄgare o chef: Arkitekt Erie Wiberg\nEtableringsår: 1952.\n\nWIBERGS VAGN. &amp; RED.\nSKAPSFABRIK, AB C M\n\nPnr 730 73\n\nRansta, Box 19. Tel 0224-20 2 20.\nBankgiro 811-8499. Postgiro\n83900-1. Tga Wibergs\nVerksamhet: Tillverkar\nlantbruksredskap o belysningsstolpar\nAntal anstäUda: 28\nÅrsomsättning: 2500 000\nAktiekapital: 468 600\nVerkst dir: Jan Wiberg\nEtableringsår: 1898.\n\nWIBERGS INDUSTRIER,\nAB E A\n\nPnr 300 07\n\nHalmstad 7, Olovsdalsv. Box 7015.\nTel 035-1190 50. Bankgiro\n153-4247. Postgiro 28782-1\nVerksamhet: Tillverkar stålmöbler\no hydrauliska frisörstolar\nAntal anstäUda: 30\nÅrsomsättning: 1 200 000\nAktiekapital: 125 000\nVerkst dir: Ing B Wiberg\nEtableringsår: 1915.\n\nmalmsten &amp; bergvall ab\n\nPnr 401 20\n\nGöteborg 1, Box 48. Packhusg 2-3.\nTel 031-17 5080. Bankgiro\n500-0815. Postgiro 41600-8. Tga\nEm-bechem. Telex 2205 EMBE S\nVeiksamhet: Försäljning av\nindustrikemikalier, plastråvaror m m\nAvdelningskontor: 102 73 Stockholm\n9, Sjöviksbacken 21. Box 9195. Tel\n08-18 02 20. Telex 1865 EMBE S\n203 11 Malmö 4, Torgg 4. Box 4004.\nTel 040-770 50. Telex 32645 EMBE S\n601 02 Norrköping 1, Box 21.\nTrädgårdsg 38. Tel 011-13 58 25\n381 01 Kalmar 1, Box 53.\nSkeppsbron 5. Tel 0480-101 77\nAntal anställda: 86\nÅrsomsättning: 73 000 000\nAktiekapital: 3 000000\nVerkst dir: Anders Ghristensson\nEtableringsår: 1877.",
    "structured": {
        "1": {
            "company_name": "FIRESTONE - VISKAFORS AB",
            "pnr": "501 04",
            "address": "Borås 1, österlångg 40. Box 167.",
            "phone_number": "033-12 70 80",
            "bank_details": {
                "bankgiro": "43-4861",
                "postgiro": "30862"
            },
            "activity": "Tillverkar i samarbete med Firestone Tire & Rubber Co, USA, bil-, traktor- o vägmaskins-däck, tekn gummivaror såsom slangar, gummibeläggningar, gummimattor, gummiduk, formgjorda o spritsade artiklar etc",
            "employees": 1300,
            "capital": 19600000,
            "key_personnel": [
                {
                    "name": "Dir Gösta Österman",
                    "position": "ordf"
                },
                {
                    "name": "adv Sten Lindskog",
                    "position": null
                },
                {
                    "name": "bankdir Töre Björkman",
                    "position": null
                },
                {
                    "name": "civiling Harry Bryniels-son",
                    "position": null
                },
                {
                    "name": "mr J Lombardo",
                    "position": null
                },
                {
                    "name": "mr J M Harvey",
                    "position": null
                },
                {
                    "name": "adv Wilhelm Pehrsson",
                    "position": null
                },
                {
                    "name": "John M Harvey",
                    "position": "Verkst dir"
                },
                {
                    "name": "Rune Hörnfeldt",
                    "position": "V verkst dir"
                },
                {
                    "name": "Disp Björn Sällström",
                    "position": "Inköpschef"
                },
                {
                    "name": "Tekn dir Arne Jakobsson",
                    "position": "Fabrikschef"
                }
            ],
            "establishment_year": 1890
        },
        "2": {
            "company_name": "FISCHER & PORTER AB",
            "pnr": "127 04",
            "address": "Skärholmen 4, Box 4026. Storholms-backarna 78.",
            "phone_number": "08-710 00 95",
            "bank_details": {
                "bankgiro": "857-6118",
                "postgiro": "408470-3"
            },
            "activity": "Säljer automatiska instrument för kontroll av industriella o andra processer. Utför planering, utveckling, installering o underhåll av ovannämnda instrument",
            "employees": 12,
            "annual_turnover": 5000000,
            "capital": 60000,
            "key_personnel": [
                {
                    "name": "Sven Olof Löf",
                    "position": "Verkst dir"
                }
            ],
            "establishment_year": 1968
        },
        "3": {
            "company_name": "FISKARHEDENS SNICKERI. FABRIK, AB",
            "pnr": "780 68",
            "address": "Transtrand, Fiskarheden",
            "phone_number": "0280-222 00",
            "bank_details": {
                "bankgiro": "471-6023",
                "postgiro": "71469-1"
            },
            "activity": "Tillverkar fönster, dörrpartier o sportstugemöbler. Säljer byggnadsmaterial från lager",
            "employees": 26,
            "annual_turnover": 1600000,
            "capital": 54000,
            "key_personnel": [
                {
                    "name": "Alf Johansson",
                    "position": "Verkst dir"
                }
            ],
            "establishment_year": 1920
        },
        "4": {
            "company_name": "FISKEBRODERNA AB",
            "pnr": "450 40",
            "address": "Kungshamn. Box 90. Hamng 2.",
            "phone_number": "0523-300 87, 300 10",
            "bank_details": {
                "bankgiro": "543-4188",
                "postgiro": "26739-3"
            },
            "activity": "Fiskkonservfabrik",
            "employees": 125,
            "annual_turnover": 10000000,
            "capital": 500000,
            "key_personnel": [
                {
                    "name": "Knut Sjöman",
                    "position": "Verkst dir"
                }
            ],
            "establishment_year": 1920
        },
        "5": {
            "company_name": "GULDSTRAND AB, CARL",
            "pnr": "113 57",
            "address": "Stockholm, Kungstensg 12",
            "phone_number": "08-1505 05",
            "bank_details": {
                "bankgiro": "211-1383",
                "postgiro": "450500-4"
            },
            "activity": "Import av herr- o damstrumpor samt herr- o damstickat",
            "capital": 30000,
            "key_personnel": [
                {
                    "name": "Leo Goldensohn",
                    "position": "Verkst dir"
                }
            ],
            "establishment_year": 1906
        },
        "6": {
            "company_name": "WONS AB, MASKINFIRMAN",
            "pnr": "85241",
            "address": "Sundsvall, Solg 5",
            "phone_number": "060-11 77 70",
            "bank_details": {
                "bankgiro": "180-4129",
                "postgiro": "100842-4"
            },
            "activity": "Tillverkar patenterade provtrycknings- o provtätningsutrustningar för alla slags rör. Säljer maskiner o redskap för anläggningsbranschen",
            "employees": 5,
            "annual_turnover": 500000,
            "capital": 8000,
            "key_personnel": [
                {
                    "name": "Erie Henry Norman",
                    "position": "Verkst dir"
                }
            ],
            "establishment_year": 1955
        },
        "7": {
            "company_name": "ELEKTRO-METALL AB",
            "pnr": "232 00",
            "address": "Arlöv, Box 92. Smedjev 2",
            "phone_number": "040-43 15 15",
            "bank_details": {
                "bankgiro": "874-3254",
                "postgiro": "38504-7"
            },
            "activity": "Utför drag- o excenter-pressning samt metalltryckning",
            "employees": 17,
            "capital": 105000,
            "key_personnel": [
                {
                    "name": "Klas Johansson",
                    "position": "Verkst dir"
                }
            ],
            "establishment_year": 1921
        },
        "8": {
            "company_name": "ELEKTROMIKANIT I LAXÅ AB",
            "pnr": "69501",
            "address": "Laxå, Box 43",
            "phone_number": "0584-108 60",
            "bank_details": {
                "bankgiro": "461-6025",
                "postgiro": "80687-7"
            },
            "activity": "Säljer dynamotråd o elektr isolationsmaterial",
            "employees": 10,
            "annual_turnover": 9000000,
            "capital": 40400,
            "key_personnel": [
                {
                    "name": "Ake Olson",
                    "position": "Verkst dir"
                }
            ],
            "establishment_year": 1945
        },
        "9": {
            "company_name": "THORNWALLS FABRIKS AB",
            "pnr": "570 76",
            "address": "Ruda, Box 53",
            "phone_number": "0491-22082, 222 82",
            "bank_details": {
                "bankgiro": "859-0119",
                "postgiro": "108409-4"
            },
            "activity": "Tillverkar möbler",
            "employees": 21,
            "annual_turnover": 2500000,
            "capital": 120000,
            "key_personnel": [
                {
                    "name": "Ing Boo Thörnwall",
                    "position": "Verkst dir"
                }
            ],
            "establishment_year": 1948
        },
        "10": {
            "company_name": "TIN",
            "activity": "Tillverkar mineralvatten, läskedrycker, juicer o öl. Generalagent för Bass, England, Ceres, Danmark o Löwenbräu, Tyskland",
            "employees": 251,
            "annual_turnover": 68000000,
            "capital": 210000,
            "key_personnel": [
                {
                    "name": "Henry Larsson",
                    "position": "Verkst din"
                }
            ],
            "establishment_year": 1931
        },
        "11": {
            "company_name": "MEMO-TOOL, AB",
            "pnr": "631 03",
            "address": "Eskilstuna 1, Box 197. Eriksdals g 18",
            "phone_number": "016-13 55 93",
            "bank_details": {
                "bankgiro": "58-2337",
                "postgiro": "137663-1"
            },
            "activity": "Tillverkar precisionsvattenpass, vattenpass o mätverktyg",
            "employees": null,
            "annual_turnover": null,
            "capital": 60000,
            "key_personnel": [
                {
                    "name": "Börje Broberg",
                    "position": "Verkst dir"
                }
            ],
            "establishment_year": 1941
        },
        "12": {
            "company_name": "ARENCO AB",
            "pnr": "16210",
            "address": "Vällingby 1, Fack. Siktg 11",
            "phone_number": "08-89 00 60",
            "bank_details": {
                "bankgiro": "57-7513",
                "postgiro": "1647"
            },
            "activity": "Tillverkar tändsticks-maskiner, maskiner för tobaksindustrin, packningsmaskiner o fisk-rensningsmaskiner",
            "employees": 850,
            "annual_turnover": 60000000,
            "capital": 6000000,
            "key_personnel": [
                {
                    "name": "K E Sahlberg",
                    "position": "Verkst dir"
                }
            ],
            "establishment_year": 1885
        },
        "13": {
            "company_name": "ARENTORPS CEMENT-VARUFABRIK, AB",
            "pnr": "534 00",
            "address": "Vara, Arentorp",
            "phone_number": "0512-13170",
            "bank_details": {
                "bankgiro": "215-5539",
                "postgiro": "385612-7"
            },
            "activity": "Tillverkar o säljer betongrör, betongelement",
            "employees": 30,
            "annual_turnover": 2700000,
            "capital": 60000,
            "key_personnel": [
                {
                    "name": "Sven Ehn",
                    "position": "Verkst dir"
                }
            ],
            "establishment_year": 1922
        },
        "14": {
            "company_name": "WIBECO, AB",
            "pnr": "413 04",
            "address": "Göteborg, Risåsg 23",
            "phone_number": "031-1062 34, 110188",
            "bank_details": {
                "bankgiro": "500-2704",
                "postgiro": "421984-6"
            },
            "activity": "Tillverkar o säljer vägmärken o trafikanordningar. Exporterar present- o träartiklar",
            "employees": null,
            "annual_turnover": 350000,
            "capital": 31000,
            "key_personnel": [
                {
                    "name": "Ing Hjälte Wiberg",
                    "position": "Verkst dir"
                }
            ],
            "establishment_year": 1928
        },
        "15": {
            "company_name": "WIBERGS KONTORS. ORGANISATION",
            "pnr": "417 40",
            "address": "Göteborg, Rimfrostg 27",
            "phone_number": "031-54 33 59",
            "bank_details": {
                "bankgiro": "107-6504",
                "postgiro": "426015-4"
            },
            "activity": "Utför förslag o lämnar offert samt utför leveranser å inredningar till kontor, pastorsexpeditioner, bibliotek mm",
            "key_personnel": [
                {
                    "name": "Arkitekt Erie Wiberg",
                    "position": "Ägare o chef"
                }
            ],
            "establishment_year": 1952
        },
        "16": {
            "company_name": "WIBERGS VAGN. & RED. SKAPSFABRIK, AB C M",
            "pnr": "730 73",
            "address": "Ransta, Box 19",
            "phone_number": "0224-20 2 20",
            "bank_details": {
                "bankgiro": "811-8499",
                "postgiro": "83900-1"
            },
            "activity": "Tillverkar lantbruksredskap o belysningsstolpar",
            "employees": 28,
            "annual_turnover": 2500000,
            "capital": 468600,
            "key_personnel": [
                {
                    "name": "Jan Wiberg",
                    "position": "Verkst dir"
                }
            ],
            "establishment_year": 1898
        },
        "17": {
            "company_name": "WIBERGS INDUSTRIER, AB E A",
            "pnr": "300 07",
            "address": "Halmstad 7, Olovsdalsv. Box 7015",
            "phone_number": "035-1190 50",
            "bank_details": {
                "bankgiro": "153-4247",
                "postgiro": "28782-1"
            },
            "activity": "Tillverkar stålmöbler o hydrauliska frisörstolar",
            "employees": 30,
            "annual_turnover": 1200000,
            "capital": 125000,
            "key_personnel": [
                {
                    "name": "Ing B Wiberg",
                    "position": "Verkst dir"
                }
            ],
            "establishment_year": 1915
        },
        "18": {
            "company_name": "malmsten & bergvall ab",
            "pnr": "401 20",
            "address": "Göteborg 1, Box 48. Packhusg 2-3",
            "phone_number": "031-17 5080",
            "bank_details": {
                "bankgiro": "500-0815",
                "postgiro": "41600-8"
            },
            "activity": "Försäljning av industri kemikalier, plastråvaror m m",
            "employees": 86,
            "annual_turnover": 73000000,
            "capital": 3000000,
            "key_personnel": [
                {
                    "name": "Anders Ghristensson",
                    "position": "Verkst dir"
                }
            ],
            "establishment_year": 1877
        }
    }
}