{
    "original": "ERIKSON &amp; CO AB, JEAN O\n\nPnr 402 72\n\nGöteborg 8, Karlavagnsg 5-7. Box\n8854. Tel 031-5105 01. Tga Jean\nVerksamhet: Agenturer kemikalier,\ngrosshandel med textil- o jutevaror,\nimport o expert\nVerkst dir: Nils Gröndahl\nEtableringsår: 1866.\n\ntexla industri ab\n\nPnr 433 00\n\nPartilie, Gamla Kronv 28-32. Box\n59. Tel 031-44 30 84, 444084.\nBankgiro 852-2419\\ Postgiro\n45699-6\n\nVerksamhet: Utför laminering på\nvävnader av olika slag\nAntal anställda: 15\nÅrsomsättning: 2000 000\nAktiekapital: 60 000\nStyrelse: Dir Harry Svenningson\n(ordf), fabrikschef Nils Bengtsson\nVeikst dir: Harry Svenningson\nEtableringsàr: 1962.\n\ntexlin, ab\n\nPnr 51104\n\nKinna 4. Box 4030. Tel\n0320-106 60. Bankgiro 54-6188.\nPostgiro 660736. Tga Texlin\nVerksamhet: Tillverkar textil\nväggbeklädnad\n\nVarunamn: Taplin, Texlin\nAktiekapital: 10 000\n\nStyrelse: Dir Mats Fransson, dir\nBill Fransson\nVerkst dir. Bill Fransson\nEtableringsàr: 1964.\n\ntexotan, ab\n\nPnr 400 20\n\nGöteborg 14, Box 14034.\nTalje-gàrdsg 4. Mölndal. Tel 031-87 00 20.\nBankgiro 33-7510. Postgiro 163021.\nTga Texotan. Telex 20724\nVerksamhet: Tillverkar o säljer\nspecialprodukter, råvaror,\nförnödenheter o maskiner för läder-,\ntex-til-, pappers-, plast-, färg- o kem\ntekn industrier\n\nVarunamn: Plexidur, Plexiglas,\nPlexigum, Plextol, Rohagit, Oropon\nAktiekapital: 700 000\nVerkst dir: Robert Ebel\nEtableringsàr: 1934\nDotterbolag till Uniplex G.m.b.H.\nBasel.\n\ntexrep, ab\n\nPnr 510 60\n\nOverlida. Box 79. Tel 0325-322 20.\nBankgiro 553-0084. Postgiro\n133977-9\n\nVerksamhet: Tillverkar\nsnedskurna, längdskurna o vävda band\nAntal anställda: 30\nÅrsomsättning: 5000 000\nAktiekapital: 300 000\nVeikst dir Sten Isacson\nEtableringsàr: 1951.\n\ntextil. &amp; stoppmobel.\nindustrin, ab\n\nPnr 560 10\n\nSkillingaryd, Smedjeg 12. Box 86.\nTel 0370-700 30. Bankgiro 14-1389.\nPostgiro 5385\n\nVerksamhet: Tillverkar stilgrupper\no bäddsoffor\nAntal anställda: 12\nÅrsomsättning: 800000\nAktiekapital: 75 000\nVerkst dlr Holger Eriksson\nEtableringsàr: 1945.\n\ntextil-ab\n\nse resp namn.\n\ntextile processing ab\n\nPnr 501 03\n\nBorås 1, Box 101. Brämhultsv 4.\nTel 033-10 2120. Bankgiro\n234-647 6. Postgiro 695051-3. Tga\nProcessing.\n\nTelex 36104 TEXPRO S\nVerksamhet: Utvecklar, tillverkar\no säljer programstyrd utrustning\nför textila färgeri- o\nberedningsindustrin\n\nAntal anställda: 8\nÅrsomsättning: 18 000 000\nAktiekapital: 60 0 000\nVerkst dir. Ing Staffan Gran\nEtableringsàr: 1966.\n\ntextilkompaniet. ab\n\nPnr 510 80\n\nTranemo. Tel 0325-70140.\nBankgiro 531-1733. Postgiro 14947-6\nVerksamhet: Täcken, kuddar,\nsovsäckar. sovsäckstäcken o\ncampingmadrasser\nVarunamn: TK\n\nAktiekapital: 500 000\nVerkst dir: Knut Palmquist\nEtableringsàr: 1919.\n\ntextilkonst. ab\n\nPnr 201 20\n\nMalmö 1, Norbergsg 7. Box 4. Tel\n040-803 10. Bankgiro 87-0167.\nPost-giro 39273. Telex 3324. Tga\nTextilkonst\n\nVerksamhet: Tillverkar\nsnörmake-rier o band för bl a möbler,\ngardiner o annan heminredning, tekniska\nband, stegband o cord för persienner\nsamt band för bilsäkerhetsbälten\nAntal anställda: 120\nAktiekapital: 250 000\nV verkst dir: Henry Norrman\nEtableringsàr: 1932.\n\ntextilkredit, ab\n\nPnr 103 82\n\nStockholm 7, Box 7081. Birger\nJarlsg 33. Tel 08-23 68 80.\nBankgiro 161-1706. Postgiro 554930-8\nVerksamhet: Kreditinstitut\nAktiekapital: 240 000\nStyrelse: Dir Nils Allan Svensson\n(ordf), ekonomidir Töre Croona,\ndisp Töre Dahlström, adv Erik\nGrenfors, dir Gottfrid Olsson, dir\nCarl Wilhelm Petri, dir Ulf\nSynner-stad, dir Sten Theorin, dir Erie\nTornvall. dir Gunnar Wadstein,\ndir Törd Westlund\nVerkst dir: Törd Westlund\nEtableringsàr: 1957.\n\ntextilmaterial\n\nPnr 530 20\n\nKvänum. Tel 0512-923 42, 925 42.\nBankgiro 84-2102. Postgiro 394453\nVerksamhet: Löntvinning.\nMattväven\n\nAntal anställda: 28\nÅrsomsättning: 800 000\nChef: Ing Carl-Gustaf Eiserman\nEtableringsàr 1955.\n\nWALMARS KONFEKTION, AB\n\nPnr 502 44\n\nBorås, Neumansg 46. Tel\n033-1196 46, 13 47 88. Bankgiro 53-1233.\nPostgiro 328737\n\nVerksamhet: Tillverkar\ndamklänningar, kjolar m m\nAntal anställda: 18\nÅrsomsättning: 800 000\nAktiekapital: 50000\nVerkst dir: Knut Högberg\nEtableringsår: 1940.\n\nWAHLSTEDT AB, BYGGNADS.\nFIRMAN\n\nPnr 550 03\n\nJönköping 3, Fridhemsg 5. Box 609.\nTel 036-1192 65. Bankgiro 54-5373.\nPostgiro 105282\n\nVerksamhet: Byggnadsentreprenör\nAntal anställda: 300\nÅrsomsättning: 27 000 000\nAktiekapital: 160 000\nVerkst dir: Carl-Ake Wahlstedt\nEtableringsår: 1952.\n\nWAHLSTRÖM &amp; CO,\nVERKSTADS AB\n\nPnr 33100\n\nVärnamo, Gröna g 12. Tel\n0370-116 35\n\nVerksamhet: Tillverkar bandsågar\nför trä o metall, kontur- o\ncirkel-sågar, rikthyvlar,\nbandslipmaski-ner, kombinerade snickerimaskiner,\nträsvarvar m m\nAntal anställda: 40\nÅrsomsättning: 3 000 000\nAktiekapital: 100 000\nVerkst dir: Erie Johansson\nDisp: H Z Karlsson\nEtableringsår: 1942.\n\nWAHLSTRÖM &amp; WIDSTRAND,\nAB\n\nPnr 11522\n\nStockholm, Banérg 37. Tel\n08-67 9815. Bankgiro 700-2132.\nPostgiro 3622-8. Tga Wahlwid\nVerksamhet: Utger skönlitteratur,\nfackböcker o pocketböcker\nAntal anställda: 18\nÅrsomsättning: 6 800 000\nAktiekapital: 225 000\nVerkst dir. Fil lic Per Israel Gedin\nEtableringsår: 1884.\n\nBESTON, KONFEKTIONS AB\n\nPnr 57071\n\nBerga, S Storg 46. Tel 0491-50109,\n50209. Bankgiro 85-5344. Postgiro\n328192\n\nVerksamhet: Tillverkar kostymer,\nblazers, byxor o överplagg\nAntal anställda: 50\nÅrsomsättning: 1800 000\nAktiekapital: 90 000\nVerkst dir: Walter Svensson\nDisp: Birger Svensson\nEtableringsår: 1946.\n\nBORÅS KONFEKTIONS AB\n\nPnr 50109\n\nBorås 1, Box 606. Ulricehamnsv 36.\nTel 033-13 70 60. Bankgiro 83-9137.\nPostgiro 385848\n\nVerksamhet: Tillverkar damkläder\nVerkst dir: Civiling Bengt\nWenner-lund\n\nEtableringsår: 1947.\n\nBORÅS\nKONSTHARTSPRODUKTER, AB\n\nPnr 50102\n\nBorås 1, Almenäsv. Box 48. Tel\n033-136110. Bankgiro 53-1166.\nPostgiro 331663. Tga Abokon\nVerksamhet: Formsprutning av\ntermoplastartiklar speciellt för\nindustrins behov. Formtillverkning\nAntal anställda: 55\nÅrsomsättning: 5 000 000\nAktiekapital: 100000\nVerkst dir: Arne Sparf\nEtableringsår: 1947.\n\nBORÅS KRAVATTFABRIK, AB\n\nPnr 50107\n\nBorås 1, Vennerbergsplatsen l.Box\n424. Tel 033-113687. Bankgiro\n83-9299. Postgiro 85940\nVerksamhet: Tillverkar vagnpåsar,\nvagndynor o babypåsar\nAntal anställda: 15\nÅrsomsättning: 800 000\nAktiekapital: 30000\nVerkst dir: Ester Sandberg\nEtableringsår: 1931.\n\nBORÅS MEKANISKA\nVERKSTADS AB\n\nPnr 502 65\n\nBorås, Magasinsg 12. Tel\n033-1102 16, 1100 16. Bankgiro\n839-3142. Postgiro 76800-2.\nTga Verkstaden\nVerksamhet: Spec: hydrauliska\npressar, kugghjulsfräsmaskiner,\nreningsanläggningar för\navloppsvat-ten, ångpannor, järnkonstruktioner.\nTextilfärgerianläggningar\nAntal anställda: 70\nÅrsomsättning: 2 000 000\nAktiekapital: 300 000\nVerkst dir: Axel-Uno Nylander\nEtableringsår: 1888.\n\nBORÅS\nROR-INSTALLATIONER, AB\n\nPnr 502 34\n\nBorås, Skaraborgsv 21. Tel\n033-114161, 115161. Bankgiro\n53-1181. Postgiro 170462\nVerksamhet:\nRörledningsentreprenör\n\nAntal anställda: 20\nÅrsomsättning: 1200 000\nAktiekapital: 30 000\nStyrelse: Ing Birger Svensson\n(ordf), verkm Arvid Adolfsson,\nverkstadsäg Axel Bergström\nVerkst dir: Ing Birger Svensson\nEtableringsår: 1933.\n\nSESCO, INGENIORSFIRMA\n\nPnr 115 27\n\nStockholm, Wittstocksg 21. Tel\n08-615161. 6103 65. Bankgiro\n565-4082. Postgiro 154848-6\nVetksamhet: Tillverkar o säljer\nmörkrumsridåer etc\nAntal anställda: 20\nÅrsomsättning: 1500 000\nChef: Ing Sture Sjöblom\nEtableringsàr: 1938.\n\nSETTERWALL &amp; CO AB, CARL\n\nPnr 103 83\n\nStockholm 7, Norrmalms torg 12.\nBox 7140. Tel 08-23 25 65.\nBankgiro 57-6915. Postgiro 155062.\nTga Setterwalls.\nTelex 19998 SETTER S\nVerksamhet: Import o export av\njärn o stål\n\nVerkst dir: Torsten Ando\nEtableringsån 1869.\n\nBERCK AB, VIGGO\n\nPnr 11137\n\nStockholm, Tunnelg 12. Tel\n08-1019 50, 1194 50. Bankgiro\n447-0803. Tga Push. Telex 1815\nVerksamhet: Exportörer i trävaror,\nwallboard o papper\nAktiekapital: 200 000\nVerkst dir: Folke Svedstrand\nEtableringsår: 1938\nOmbildat till aktiebolag 1940.\n\nBERDI:N &amp; CO AB\n\nPnr 21214\n\nMalmö, Industrig 14-18. Tel\n040-93 49 90. Bankgiro 26-3412.Postgiro\n247140. Tga Nordper. Telex 32725\nVerksamhet: Tillverkar persienner,\nsolskärmar, markiser, rullgardiner,\nmörkrumsridåer, scenridåer,\nprojektionsdukar. Specialitet:\nutomhus-monterade solavskärmningar o\nhöggradig mörkläggning. Säljer till\nåterförsäljare o byggnadsindustrin\nVarunamn: Solovent, Solomatic,\nSoloscreen, Metalunic, Sundrape\nAktiekapital: 100000\nÄgare o chef: Hans Berdén\nEtableringsår: 1948.\n\nMAL\n\nmala\ntryckimpreg-nering ab\n\nPnr 280 20\n\nBjärnum. Tel 0451-171 46\nVerksamhet: Tryckimpregnering.\nKabelskydd\n\nFirmatecknare: Ebba Stenmo.\n\nmalaga, ab\n\nPnr 440 60\n\nSkärhamn, Box 39. Tel\n0304-704 60. Bankgiro 535-4402. Tga\nMalaga. Telex 2428 OTERED S\nVerksamhet: Agenturer,\nbefraktning, rederier, oljeterminal\nAntal anställda: 40\nAktiekapital: 50000\nStyrelse: Skeppsredare Lars\nJohansson, dir Vilgot Johansson\nEtableringsår: 1962.\n\nTRÄSTANDARD AB\n\nPnr 112 38\n\nStockholm. Hantverkarg 85. Tel\n08-24 93 00. Bankgiro 575-2258.\nPostgiro 557088-2\nVerksamhet: Tillverkar inredningar\ntör handel o industriföretag m m\nAntal anställda: 10\nÅrsomsättning: 3 500 000\nAktiekapital: 100000\nVerkst dir. Rune V Liljemark\nEtableringsår 1957.\n\nCIWAB HYDRAULIK AB\n\nPnr 44200\n\nKungälv, västra g 63. Tel\n0303-139 05. Tga Ciwab\nVerksamhet: Konstruerar o säljer\nhydrauliska motorer o anläggningar\nAktiekapital: 30 000\nVerkst dir: Hans Ake Reis\nEtableringsår: 1962.\n\nCIVILTRYCKERIET\nHALMSTAD, AB\n\nPnr 300 03\n\nHalmstad 3, Bohusg 1. Box 3009.\nTel 035-1190 30\n\nVerksamhet: Boktryck, fullständig\nreproduktionsavdelning, offset,\nefterarbete o distribution\nAntal anställda: 39\nÅrsomsättning: 3 300 000\nAktiekapital: 90 000\nÄgare o chefer: Knut Persson, Stig\nBrandt, Bertil Nielsen, Viggo\nOlsson\n\nEtableringsår: 1947.\n\nCIVILTRYCKERIET I\nKRISTIANSTAD AB\n\nPnr 29101\n\nKristianstad 1, V Boulevarden 19.\nBox 134. Tel 044-11 09 54, 12 06 57.\nBankgiro 345-25 70. Postgiro\n411335-3\n\nVerksamhet: Trycker tidskrifter,\nbroschyrer, reklam, blanketter mm\nAntal anställda: 13\nÅrsomsättning: 900 000\nAktiekapital: 5 000\nVerkst dir: Roland Johansson\nEtableringsår: 1958.\n\nCLAÉSONS BYGGNADS AB,\nNILS\n\nPnr 43122\n\nMölndal 1, Box 143. Agatan 26 B.\nTel-031-27 1114, 27 18 02.\nBankgiro 439-8327. Postgiro 49953-3\nVerksamhet: Utför byggnads- o\nverkstadsarbeten av alla slag\nAntal anställda: 40\nAktiekapital: 150 000\nVerkst dir: Arne Claéson\nEtableringsår: 1956.",
    "structured": {
        "1": {
            "company_name": "ERIKSON & CO AB",
            "activity": "Agenturer kemikalier, grosshandel med textil- o jutevaror, import o export",
            "establishment_year": 1866
        },
        "2": {
            "company_name": "texla industri ab",
            "address": "Gamla Kronv 28-32, Partilie",
            "phone_number": "031-44 30 84, 444084",
            "bank_details": {
                "bankgiro": "852-2419",
                "postgiro": "45699-6"
            },
            "activity": "Utför laminering på vävnader av olika slag",
            "employees": 15,
            "annual_turnover": 2000000,
            "capital": 60000,
            "key_personnel": [
                {
                    "name": "Harry Svenningson",
                    "position": "Dir (ordf)"
                },
                {
                    "name": "Nils Bengtsson",
                    "position": "Fabrikschef"
                }
            ],
            "establishment_year": 1962
        },
        "3": {
            "company_name": "texlin, ab",
            "address": "Kinna 4",
            "phone_number": "0320-106 60",
            "bank_details": {
                "bankgiro": "54-6188",
                "postgiro": "660736"
            },
            "activity": "Tillverkar textil väggbeklädnad",
            "capital": 10000,
            "key_personnel": [
                {
                    "name": "Mats Fransson",
                    "position": "Dir"
                },
                {
                    "name": "Bill Fransson",
                    "position": "Dir"
                }
            ],
            "establishment_year": 1964
        },
        "4": {
            "company_name": "texotan, ab",
            "address": "Box 14034, Göteborg 14, Mölndal",
            "phone_number": "031-87 00 20",
            "bank_details": {
                "bankgiro": "33-7510",
                "postgiro": "163021"
            },
            "activity": "Tillverkar o säljer specialprodukter, råvaror, förnödenheter o maskiner för läder-, textil-, pappers-, plast-, färg- o kem tekn industrier",
            "varunamn": "Plexidur, Plexiglas, Plexigum, Plextol, Rohagit, Oropon",
            "capital": 700000,
            "key_personnel": [
                {
                    "name": "Robert Ebel",
                    "position": "Verkst dir"
                }
            ],
            "establishment_year": 1934,
            "parent_company": "Uniplex G.m.b.H. Basel"
        },
        "5": {
            "company_name": "texrep, ab",
            "address": "Overlida",
            "phone_number": "0325-322 20",
            "bank_details": {
                "bankgiro": "553-0084",
                "postgiro": "133977-9"
            },
            "activity": "Tillverkar snedskurna, längdskurna o vävda band",
            "employees": 30,
            "annual_turnover": 5000000,
            "capital": 300000,
            "key_personnel": [
                {
                    "name": "Sten Isacson",
                    "position": "Veikst dir"
                }
            ],
            "establishment_year": 1951
        },
        "6": {
            "company_name": "textil. & stoppmobel. industrin, ab",
            "address": "Smedjeg 12, Skillingaryd",
            "phone_number": "0370-700 30",
            "bank_details": {
                "bankgiro": "14-1389",
                "postgiro": "5385"
            },
            "activity": "Tillverkar stilgrupper o bäddsoffor",
            "employees": 12,
            "annual_turnover": 800000,
            "capital": 75000,
            "key_personnel": [
                {
                    "name": "Holger Eriksson",
                    "position": "Verkst dlr"
                }
            ],
            "establishment_year": 1945
        }
    }
}