{
    "original": "GEMLA FABRIKERS AB\n\nPnr 340 21\n\nDiö. Tel 0476-214 00. Bankgiro\n87-3811. Postgiro 8400. Tga\nGemlabo-laget\n\nVerksamhet: Tillverkar\nhemmöbler, sjukhus- o restaurantmöbler.\nSpecialitet: bord o helböjda stolar\nFörsäljningskontor o permanent\nutställning: 115 34 Stockholm, Svensk\nMöbelcenter Furniture Mart AB,\nS:t Eriksmässan, Storängsbotten.\nTel 08-62 67 22\nFilialfabrik: Tbllarp\nAntal anställda: 140\nÅrsomsättning: 9 000000\nAktiekapital: 528 000\nStyrelse: Adv Einar Berggren(ordf),\ndir Olle Bjärmark, dir Alistair\nBroms, disp Margit Holden, fru\nUlla Holden, inredningsark Sven\nStaaf\n\nVerkst dir: Fru Margit Holden\nV verkst dir: Bengt Lindblom\nEtableringsår: 1861.\n\nBOXHOLMS AB\n\nPnr 590 10\n\nBoxholm. Tel 0142-510 00.\nBankgiro 131-8039. Postgiro 29774-7.\nTga Boxholmsbolaget.\nTelex 5577 o 5554 BOXHOLM S\nVerksamhet: Stål- o träindustri,\nskogsbruk. Tillverkar varmvalsat\no kalldraget stål, komprimerade\naxlar, kallformade profiler. Sågade\no hyvlade trävaror (sågat/hyvlat,\nlängdpaketerat trä), massiva dörrar\n(för sjukhus, skolor, kontor etc),\nträtuber o träkar, massaved,\nplywood- o fanértimmer.\nDelikatessost\nAntal anställda: 1 200\nÅrsomsättning: 135 000 000\nAktiekapital: 14 400 000\nVerkst dir: Disp Stig Tillmar\nEtableringsår: 1754\nOmbildat till aktiebolag 1872.\nBolaget ägs av AB Iggesunds Bruk.\n\nBOYD AB, JOHN J\n\nPnr 417 05\n\nGöteborg, Pärgfabriksg 5. Tel\n031-22 29 20. 2215 11. Bankgiro\n513-6239. Postgiro 41338-5. Tga Ibex\nVerksamhet: Säljer korgmaterial\nsåsom rotting, korgpil, sjögräs,\nplastmaterial till korgar o d.\nBambu\n\nAntal anställda: 3\nÅrsomsättning: 450 000\nAktiekapital: 10 000\nVerkst dir: Greta Lindbom\nEtableringsår: 1888\nOmbildat till aktiebolag 1929.\n\nBP RAFFINADERI\n(GOTEBORG) AB\n\nPnr 40121\n\nGöteborg 1, Torslandav. Box 117.\nTel 031-53 02 80. Bankgiro\n420-7411. Postgiro 625745-5. Tga\nBee-peeraff. Telex 20754 BPRAFF S\nVerksamhet: Raffinering av olja\nAntal anställda: 168\nÅrsomsättning: 63 500 000\nAktiekapital: 35 000 000\nVerkst dir: Mr G P Panckridge\nEtableringsår: 1963.\n\nBPA BYGGPRODUKTION\nAB\n\nPnr 104 30\n\nStockholm 45, Huvudkontor,\nTegnér-g 23. Box 45126. Tel 08-24 97 60.\nPostgiro 700240\n\nVerksamhet: Hus- o\nmarkprojektering, markarbeten, byggnads- o\nanläggningsarbeten, vvs-, måleri-, el-,\nglas-, plåt- o mek verkstadsarbeten,\nbetong- o snickerifabriker\nProduktionskontor:\n500 05 Borås 5, Sparreg 10. Box\n55045. Tel 033-12 79 40\n63106 Eskilstuna 1, Hejarg 22. Box\n520. Tel 016-110300\n402 30 Göteborg 7,\nMasthuggsterrassen 1. Fack. Tel 031-42 04 00\n\nHelsingborg. Vedbyv 21, pa 264 00\n\nKlippan. Tel 0435-120 90\n\n38101 Kalmar 1, Scheeleg8. Box\n\n78. Tel 0480-28 0 80\n\n58103 Linköping, Kungsg 41 A.\n\nBox 327. Tel 013-13 03 30\n\n200 32 Malmö 18, Volframg 3. Box\n\n18029. Tel 040-94 5100\n\n601 01 Norrköping 1, Olai Kyrkog 11.\n\nFack. Tel 011-13 95 40\n\n93100 Skellefteå, Asg 22 B. Tel\n\n0910-142 40\n\nStockholm, Skytteholmsv 2. Fack,\npa 171 20 Solna. Tel 08-83 40 60\n85101 Sundsvall 1, Storg 58. Fack.\nTel 060-12 56 00\n\n75105 Uppsala 1, Sankt Persg 16.\nBox 296. Tel 018-10 04 00\n62100 Visby, Stenkumlav 7. Tel\n0498-173 70\n\n721 36 Västerås, Betongg 1. Box\n\n969. Tel 021-13 75 60\n\n701 33 Örebro 1, Osmundg 10. Box\n\n981. Tel 019-130600\n\nBPA Färgmaterial. 753 27 Uppsala,\n\nRoslagsg 2. Box 30 64. Tel 018-\n\n14 90 75\n\nBPA, Värmbolindustrierna. 64100\nKatrineholm. Tel 0150-13180\nElementfabriker:\n\nBPA, Elementfabriken i Västerås.\n723 46 Västerås, Tallmätarg 2. Tel\n021-18 54 00\n\nBPA, Elementfabriken i Bollebygd.\n510 35 Bollebygd, Råssa. Box 34.\nTel 033-852 35\n\nBetongkonstruktioner i Amål AB.\n662 00 Amål, Box 78. Tel\n0532-122 90\n\nMalmö Betongkonstruktioner AB.\n245 00 Staffanstorp, Box 34. Tel\n046-15 62 80\nAntal anställda: 19 000\nÅrsomsättning: 1970 000 000\nAktiekapital: 30 000 000\nVerkst dir: Carl Olof Ek.\n\nBPA BYGGPRODUKTION AB\nVÄRMBOLSINDUSTRIERNA\n\nPnr 64100\n\nKatrineholm, Värmbols Bruk. Tel\n0150-131 80. Bankgiro 36-3959.\nPostgiro 491175\nVerksamhet: Tillverkar köks- o\ngarderobsskåp samt fönster till\nbostäder\n\nAntal anställda: 190\nÅrsomsättning: 25 000 000\nChef: Disp P R Wickman\nEtableringsår. 1954\n\nÄges av BPA Byggproduktion AB.\n\nBRA BOHAG AB\n\nPnr 20110\n\nMalmö 1, Fack. Trelleborgsv 13.\nTel 040-92 23 00\n\nVerksamhet: Moderbolag för Dux\nMöbel AB med fabriker i Trelleborg\no Bodators samt för Dux Sängar AB,\nSösdala\n\nAntal anställda: 7\nAktiekapital: 10 856 600\nStyrelse: Prof Ulf af Trolle (ordf),\ndisp Erie Ljung, disp Erie\nTingström, disp Eskil Hjällsten, dir\nGunnar Ericsson\nVerkst dir: Disp Erie Ljung.\n\nBRAND- &amp;\nSÄKERHETSTJÄNST, AB\n\nPnr 111 35\n\nStockholm, Kungsg 30. Tel\n08-24 9 9 30. Bankgiro 729-3350. Post-\n\ngiro 197016-9. Tga Brandservice.\nTelex 17810\n\nVerksamhet: Brandredskap,\nrädd-ningsmateriel, skumsläckningsut-rustning, hand brands läckare\nFilialer: 414 72 Göteborg,\nMaj-stångsg 20. Tel 031-24 35 64\n555 90 Jönköping, Tredje Radhusv\n5. Tel 036-18 41 31\n724 69 Västerås, Råbykorset 4.\nTel 021-35 89 15\nAntal anställda: 15\nAktiekapital: 90 000\nVerkst dir: Roland Kontin\nEtableringsår: 1964.\n\nKNÄREDS WERKSTADS AB\n\nPnr 310 20\n\nKnäred. Tel 0430-500 00\nVerksamhet: Säljer allt i stålmöbler\nÅrsomsättning: 3 500 000\nAktiekapital: 25000\nVerkst dir: Nils Gustafsson\nEtableringsår: 1960.\n\nNORRTELJE GJUTERI AB\n\nPnr 76100\n\nNorrtälje, G juteriv 1. Tel\n0176-126 20. Bankgiro 231-8095.\nPost-giro 88873-5\n\nVerksamhet: Tillverkar\njärngjut-gods enl SIS 0125, 0130, 0135,\nsegjärn, höglegerat eldhärdigt gjutgods,\n\"Ni-Resist\" korrosionsbeständigt\ngods o slitgods \"Ni-Hard\".\nMa-skinbearbetning, värmebehandling\no målning av gjutgods\nAntal anställda: 80\nÅrsomsättning: 6 000 000\nAktiekapital: 50100.\n\nNORRTÄLJE SKEPPS.\nMÄKLERI AB\n\nPnr 76100\n\nNorrtälje, Box 122. Hamnv. Tel\n0176-155 25. Bankgiro 80-5247.\nPostgiro 693480-6. Tga Norrship.\nTelex 1252\n\nVerksamhet: Skeppsmäkleri,\nklare-ring o spedition\nAktiekapital: 5 000\nVerkst dir: Gunnar Bodén\nEtableringsår. 1967.\n\nNORRTELJE TIDNINGS\nBOKTRYCKERI AB\n\nPnr 761 00\n\nNorrtälje, Hantverkareg 11-13. Box\n64. Tel 0176-125 00. Bankgiro\n231-8103. Postgiro 31814-7, 671814-2\nVerksamhet: Tidnings- o\nboktryckeri\n\nAntal anställda: 70\nÅrsomsättning: 4 500 000\nAktiekapital: 55 000\nVerkst dir: Armas Mörby\nEtableringsår: 1880.\n\nZEILON-MASKINER AB\n\nPnr 112 27\n\nStockholm, Kungsholmsg 8. Tel\n08-54 07 30. Bankgiro 57-4807.\nPostgiro 258860. Tga\nZeilon-maskiner\n\nVerksamhet: Säljer transport- o\nlagerutrustningar\nAntal anstäUda: 14\nÅrsomsättning: 3 700 000\n.Aktiekapital: 5 000\nVerkst dir: Civiüng Rolf Zeilon\nEtableringsår: 1963.\n\nGEVEKO BYGGNADS AB\n\nPnr 403 13\n\nGöteborg 2, Magasinsg 3. Box\n2137. Tel 031-17 29 55. Bankgiro\n238-3024. Postgiro 420460-8\nVerksamhet: Reparationer,\nändringar o nybyggnader\nAntal anställda: 50\nÅrsomsättning: 6 000 000\nAktiekapital: 50 000\nVerkst dir: Jarl Ergel\nEtableringsår. 1967.\n\nASK\n\nA S K-BOLAGENS EKONO.\nMISKA FÖRENING U P A\n\nPnr 104 01\n\nStockholm 60, Pack. Industriv 14,\nSolna. Tel 08-27 29 80. Bankgiro\n56-6009. Postgiro 153909. Tga\nAskol. Telex 17410\nVerksamhet: Inköps- o\ncentralorganisation för anslutna\nkolonialvaru-grossister\n\nStyrelseordf: Dir Hans Möller\nVerkst dir: Carl Erik Hedlund\nEtableringsår: 1937.\n\nASKERSUNDS NYA\nSTADSHOTELL AB\n\nPnr 696 00\n\nAskersund, Libergsg 12. Tel\n0583-10010\n\nVerksamhet: Hotell o restaurant\nAntal anställda: 10\nÅrsomsättning: 700 000\nAktiekapital: 30 000\nVerkst dir: Ola Olsson\nEtableringsår: 1970.\n\nÅKERMANMASKINER, AB\n\nPnr 161 26\n\nBromma 1, Box 76. Kvarnbacksv\n135. Tel 08-26 2640. Bankgiro\n560-5779. Postgiro 252060-9. Tga\n\nAkermachine\n\nVerksamhet: Försäljning o service\nav grävmaskiner o pålmaskiner\nAntal anställda: 50\nÅrsomsättning: 20 000000\nAktiekapital: 50 000\nChef: Ing Curt Lennart Blomstrand\nEtableringsår: 1955.\n\nÅKERMANMASKINER I\nGÖTEBORG AB\n\nPnr 43121\n\nMölndal 1, Kråketorpsg 14. Box 23.\nTel 031-87 03 00. Postgiro 622000\nVerksamhet: Säljer Åkerman\ngrävmaskiner\n\nAntal anställda: 30\nÅrsomsättning: 10000 000\nAktiekapital: 20 000\nStyrelse: Civiling Bengt Ydmark,\ndisp Göran Larsson, ing Nils\nLinander (suppl), disp Lars Ake\nNyström (suppl)\nChef: Disp G Larsson\nEtableringsån 1955.\n\nHOECHST-PERSTORP AB\n\nPnr 402 20\n\nGöteborg 5, Fack. Göteborgsv\n91 B, Mölndal. Tel 031-27 50 75.\nBankgiro 573-1088. Postgiro\n723486-7. Telex 2275 HOEGBG S\nVerksamhet: Tillverkning o\nförsäljning av plastdispersioner\nAntal anstäUda: 40\nAktiekapital: 7 000 000\nVerkst dir Ing Töre Östergren\nEtableringsår. 1970\nDotterbolag till Svenska Hoechst\nAB o Perstorp AB.\n\nHOFFMAN &amp; CO AB\n\nPnr 17148\n\nSolna, Fabriks v 1. Tel 08-27 27 50.\nBankgiro566-0378. Postgiro 2366-3.\nTga Tryckfärg\n\nVerksamhet: Tryckfärgsfabrik\nAntal anstäUda: 20\nÅrsomsättning: 1000 000\nAktiekapital: 152700\nVerkst dir: Bo Hoffman\nEtableringsår: 1913.\n\nELEKTRO JOHNSSON, AB\n\nPnr 201 23\n\nMalmö 1, Lodg 3. Box 377. Tel\n040-18 08 40. Bankgiro 870-1179.\nPostgiro 38755-5. Tga Eljonson\nVerksamhet: Säljer elektr\ninstallationsmaterial i parti\nAntal anställda: 20\nAktiekapital: 500 000\nVetkst dir: Lars-Erik Eklöf\nEtableringsår: 1947.\nDotterbolag till Svenska Elgrossist\nAB SELGA.\n\nELEKTRO MIBO AB\n\nPnr 54201\n\nMariestad 1. Box 125. Tel\n0501-136 20. Telex 5939 MIBOMST S\nVerksamhet: Tillverkar o säljer\nbelysningsarmaturer,\nköksventila-torer o skyltar\n\nVarunamn: Imvac, Interma, Mibo,\nSun-Lux\n\nAntal anställda: 90\nÅrsomsättning: 10000 000\nPlatschef: Disp I Hermansson\nEtableringsår 1959.",
    "structured": {
        "1": {
            "company_name": "GEMLA FABRIKERS AB",
            "pnr": "340 21",
            "phone_number": "0476-214 00",
            "bank_details": {
                "bankgiro": "87-3811",
                "postgiro": "8400"
            },
            "activity": "Tillverkar hemmöbler, sjukhus- o restaurantmöbler. Specialitet: bord o helböjda stolar",
            "employees": 140,
            "annual_turnover": 9000000,
            "capital": 528000,
            "key_personnel": [
                {
                    "name": "Fru Margit Holden",
                    "position": "Verkst dir"
                },
                {
                    "name": "Bengt Lindblom",
                    "position": "V verkst dir"
                }
            ],
            "establishment_year": 1861
        },
        "2": {
            "company_name": "BOXHOLMS AB",
            "pnr": "590 10",
            "phone_number": "0142-510 00",
            "bank_details": {
                "bankgiro": "131-8039",
                "postgiro": "29774-7"
            },
            "activity": "Stål- o träindustri, skogsbruk. Tillverkar varmvalsat o kalldraget stål, komprimerade axlar, kallformade profiler.",
            "employees": 1200,
            "annual_turnover": 135000000,
            "capital": 14400000,
            "key_personnel": [
                {
                    "name": "Disp Stig Tillmar",
                    "position": "Verkst dir"
                }
            ],
            "establishment_year": 1754
        },
        "3": {
            "company_name": "BOYD AB, JOHN J",
            "pnr": "417 05",
            "phone_number": "031-22 29 20",
            "bank_details": {
                "bankgiro": "513-6239",
                "postgiro": "41338-5"
            },
            "activity": "Säljer korgmaterial såsom rotting, korgpil, sjögräs, plastmaterial till korgar o d.",
            "employees": 3,
            "annual_turnover": 450000,
            "capital": 10000,
            "key_personnel": [
                {
                    "name": "Greta Lindbom",
                    "position": "Verkst dir"
                }
            ],
            "establishment_year": 1888
        },
        "4": {
            "company_name": "BP RAFFINADERI (GOTEBORG) AB",
            "pnr": "40121",
            "phone_number": "031-53 02 80",
            "bank_details": {
                "bankgiro": "420-7411",
                "postgiro": "625745-5"
            },
            "activity": "Raffinering av olja",
            "employees": 168,
            "annual_turnover": 63500000,
            "capital": 35000000,
            "key_personnel": [
                {
                    "name": "Mr G P Panckridge",
                    "position": "Verkst dir"
                }
            ],
            "establishment_year": 1963
        },
        "5": {
            "company_name": "BPA BYGGPRODUKTION AB",
            "pnr": "104 30",
            "phone_number": "08-24 97 60",
            "postgiro": "700240",
            "activity": "Hus- o markprojektering, markarbeten, byggnads- o anläggningsarbeten, vvs-, måleri-, el-, glas-, plåt- o mek verkstadsarbeten, betong- o snickerifabriker",
            "employees": 19000,
            "annual_turnover": 1970000000,
            "capital": 30000000,
            "key_personnel": [
                {
                    "name": "Carl Olof Ek",
                    "position": "Verkst dir"
                }
            ]
        },
        "6": {
            "company_name": "BPA BYGGPRODUKTION AB VÄRMBOLSINDUSTRIERNA",
            "pnr": "64100",
            "phone_number": "0150-131 80",
            "bank_details": {
                "bankgiro": "36-3959",
                "postgiro": "491175"
            },
            "activity": "Tillverkar köks- o garderobsskåp samt fönster till bostäder",
            "employees": 190,
            "annual_turnover": 25000000,
            "chief": "Disp P R Wickman",
            "establishment_year": 1954
        },
        "7": {
            "company_name": "BRA BOHAG AB",
            "pnr": "20110",
            "phone_number": "040-92 23 00",
            "activity": "Moderbolag för Dux Möbel AB med fabriker i Trelleborg o Bodatorp samt för Dux Sängar AB, Sösdala",
            "employees": 7,
            "capital": 10856600,
            "key_personnel": [
                {
                    "name": "Disp Erie Ljung",
                    "position": "Verkst dir"
                }
            ]
        },
        "8": {
            "company_name": "BRAND- & SÄKERHETSTJÄNST, AB",
            "pnr": "111 35",
            "phone_number": "08-24 9 9 30",
            "bank_details": {
                "bankgiro": "729-3350",
                "postgiro": "197016-9"
            },
            "activity": "Brandredskap, räddningsmateriel, skumsläckningsutrustning, handbrandsläckare",
            "employees": 15,
            "capital": 90000,
            "key_personnel": {
                "name": "Roland Kontin",
                "position": "Verkst dir"
            },
            "establishment_year": 1964
        },
        "9": {
            "company_name": "KNÄREDS WERKSTADS AB",
            "pnr": "310 20",
            "phone_number": "0430-500 00",
            "activity": "Säljer allt i stålmöbler",
            "annual_turnover": 3500000,
            "capital": 25000,
            "key_personnel": [
                {
                    "name": "Nils Gustafsson",
                    "position": "Verkst dir"
                }
            ],
            "establishment_year": 1960
        },
        "10": {
            "company_name": "NORRTELJE GJUTERI AB",
            "pnr": "76100",
            "phone_number": "0176-126 20",
            "bank_details": {
                "bankgiro": "231-8095",
                "postgiro": "88873-5"
            },
            "activity": "Tillverkar järngjutgods enl SIS 0125, 0130, 0135, segjärn, höglegerat eldhärdigt gjutgods, 'Ni-Resist' korrosionsbeständigt gods o slitgods 'Ni-Hard'.",
            "employees": 80,
            "annual_turnover": 6000000,
            "capital": 50100,
            "establishment_year": 1967
        },
        "11": {
            "company_name": "NORRTELJE SKEPPSMÄKLERI AB",
            "pnr": "76100",
            "phone_number": "0176-155 25",
            "bank_details": {
                "bankgiro": "80-5247",
                "postgiro": "693480-6"
            },
            "activity": "Skeppsmäkleri, klaring o spedition",
            "capital": 5000,
            "key_personnel": {
                "name": "Gunnar Bodén",
                "position": "Verkst dir"
            },
            "establishment_year": 1967
        },
        "12": {
            "company_name": "NORRTELJE TIDNINGSBOKTRYCKERI AB",
            "pnr": "761 00",
            "phone_number": "0176-125 00",
            "bank_details": {
                "bankgiro": "231-8103",
                "postgiro": "31814-7, 671814-2"
            },
            "activity": "Tidnings- o boktryckeri",
            "employees": 70,
            "annual_turnover": 4500000,
            "capital": 55000,
            "key_personnel": {
                "name": "Armas Mörby",
                "position": "Verkst dir"
            },
            "establishment_year": 1880
        },
        "13": {
            "company_name": "ZEILON-MASKINER AB",
            "pnr": "112 27",
            "phone_number": "08-54 07 30",
            "bank_details": {
                "bankgiro": "57-4807",
                "postgiro": "258860"
            },
            "activity": "Säljer transport- o lagerutrustningar",
            "employees": 14,
            "annual_turnover": 3700000,
            "capital": 5000,
            "key_personnel": {
                "name": "Civiüng Rolf Zeilon",
                "position": "Verkst dir"
            },
            "establishment_year": 1963
        },
        "14": {
            "company_name": "GEVEKO BYGGNADS AB",
            "pnr": "403 13",
            "phone_number": "031-17 29 55",
            "bank_details": {
                "bankgiro": "238-3024",
                "postgiro": "420460-8"
            },
            "activity": "Reparationer, ändringar o nybyggnader",
            "employees": 50,
            "annual_turnover": 6000000,
            "capital": 50000,
            "key_personnel": {
                "name": "Jarl Ergel",
                "position": "Verkst dir"
            },
            "establishment_year": 1967
        },
        "15": {
            "company_name": "ASK",
            "pnr": "104 01",
            "phone_number": "08-27 29 80",
            "bank_details": {
                "bankgiro": "56-6009",
                "postgiro": "153909"
            },
            "activity": "Inköps- o centralorganisation för anslutna kolonialvarugrossister",
            "establishment_year": 1937
        },
        "16": {
            "company_name": "ASKERSUNDS NYA STADSHOTELL AB",
            "pnr": "696 00",
            "phone_number": "0583-10010",
            "activity": "Hotell o restaurant",
            "employees": 10,
            "annual_turnover": 700000,
            "capital": 30000,
            "key_personnel": {
                "name": "Ola Olsson",
                "position": "Verkst dir"
            },
            "establishment_year": 1970
        },
        "17": {
            "company_name": "ÅKERMANMASKINER, AB",
            "pnr": "161 26",
            "phone_number": "08-26 2640",
            "bank_details": {
                "bankgiro": "560-5779",
                "postgiro": "252060-9"
            },
            "activity": "Försäljning o service av grävmaskiner o pålmaskiner",
            "employees": 50,
            "annual_turnover": 20000000,
            "capital": 50000,
            "key_personnel": {
                "name": "Ing Curt Lennart Blomstrand",
                "position": "Chef"
            },
            "establishment_year": 1955
        },
        "18": {
            "company_name": "ÅKERMANMASKINER I GÖTEBORG AB",
            "pnr": "43121",
            "phone_number": "031-87 03 00",
            "postgiro": "622000",
            "activity": "Säljer Åkerman grävmaskiner",
            "employees": 30,
            "annual_turnover": 10000000,
            "capital": 20000,
            "key_personnel": {
                "name": "Disp G Larsson",
                "position": "Chef"
            },
            "establishment_year": 1955
        },
        "19": {
            "company_name": "HOECHST-PERSTORP AB",
            "pnr": "402 20",
            "phone_number": "031-27 50 75",
            "bank_details": {
                "bankgiro": "573-1088",
                "postgiro": "723486-7"
            },
            "activity": "Tillverkning o försäljning av plastdispersioner",
            "employees": 40,
            "capital": 7000000,
            "key_personnel": {
                "name": "Ing Töre Östergren",
                "position": "Verkst dir"
            },
            "establishment_year": 1970
        },
        "20": {
            "company_name": "HOFFMAN & CO AB",
            "pnr": "17148",
            "phone_number": "08-27 27 50",
            "bank_details": {
                "bankgiro": "566-0378",
                "postgiro": "2366-3"
            },
            "activity": "Tryckfärgsfabrik",
            "employees": 20,
            "annual_turnover": 1000000,
            "capital": 152700,
            "key_personnel": {
                "name": "Bo Hoffman",
                "position": "Verkst dir"
            },
            "establishment_year": 1913
        },
        "21": {
            "company_name": "ELEKTRO JOHNSSON, AB",
            "pnr": "201 23",
            "phone_number": "040-18 08 40",
            "bank_details": {
                "bankgiro": "870-1179",
                "postgiro": "38755-5"
            },
            "activity": "Säljer elektr installationsmaterial i parti",
            "employees": 20,
            "capital": 500000,
            "key_personnel": {
                "name": "Lars-Erik Eklöf",
                "position": "Verkst dir"
            },
            "establishment_year": 1947
        },
        "22": {
            "company_name": "ELEKTRO MIBO AB",
            "pnr": "54201",
            "phone_number": "0501-136 20",
            "telex": "5939 MIBOMST S",
            "activity": "Tillverkar o säljer belysningsarmaturer, köksventilatorer o skyltar",
            "employees": 90,
            "annual_turnover": 10000000,
            "chief": "Disp I Hermansson",
            "establishment_year": 1959
        }
    }
}