{
    "original": "TEKNO.MONTAN, AB\n\nPnr 171 22\n\nSolna 1, Pyramidv 7. Box 1116. Tel\n08-27 27 25. Bankgiro 16-0177.\nPost-giro 320489. Telex 1527. Tga\nTek no montan\n\nPUMPAR\nALLA SLAG\n\nFilial: Hälsingborg, Hamntorget 5.\nTel 04 2-1130 13\n\nVarunamn: Golfetto, HoechsUUhde,\nRheinhtitte. Weise &amp; Monski, Lewa\nAntal anställda: 22\nÅrsomsättning: 1700 000\nAktiekapital: 60 000\nVerkst dir: L Hennig\nEtableringsår 1944.\n\nTEKNO-PRODUKTER,\nINGENIORSFIRMA\n\nPnr 104 65\n\nStockholm 15, Box 15021.\nStadsgården 24. Tel 08-23 19 70.\nBankgiro 720-1726. Postgiro 511105-9\nVerksamhet Säljer aggregat för\nluktborttagning med aktivt kol mm\nAntal anställda: 6\nÅrsomsättning: 500000\nChef: Ing Thorsten Möller\nEtableringsår: 1962.\n\nSVEA AB, ANNONSBYRÄN\n\nPnr 103 10\n\nStockholm 2, Stora Nyg 27. Fack.\nTel 08-44 92 80. Bankgiro 721-7177.\nPostgiro 55195-2\n\nVerksamhet: Auktoriserad\nannonsbyrå med fullständig reklamservice\nAntal anställda: 230\nÅrsomsättning: 90 000 000\nAktiekapital: 180 000\nVerkst dir: Lars Berg\nEtableringsår: 1897.\n\nATTEVIKS B IL-AB\n\nPnr 550 02\n\nJönköping 2, Box 2122. John\nBauersg 1. Tel 036-1188 30\nVerksamhet: Säljer Scania-Vabis,\nVolkswagen o Porsche\nAktiebolag: 300000\nVerkst dir: Per-Ake Löf\nEtableringsår: 1951.\n\nSWERCO.MASKINER\n\nPnr 820 40\n\nJärvsö. Tel 0651-404 76, 404 90\nVerksamhet: Tillverkar kilrems- o\nplanskivor i lättmetall o gjutjärn,\ntransportörer, transportrullar o\nskidliftar. Gjuteri för aluminium,\nlättmetall o järn\nChef: Arvid Persson.\n\nSVERËMO AB, INGENJÖRS.\nFIRMA\n\nPnr 211 21\n\nMalmö, Gråbrödersg 2. Tel\n040-10 0160. Telex 32461. Tga Sveremo\nVeiksamhet: Elektromagnetiska\nvibratorer, maskinmontage\nAntal anställda: 60\nÅrsomsättning: 3 500 000\nAktiekapital: 30 000\nVeikst dir: Georg Lindström\nEtableringsår 1953.\n\nHOFWERBERG&amp; ANDERSON\n\nPnr 42105\n\nVästra Frölunda 5, Box 5022. Tel\n031-29 3100, 290200. Bankgiro\n50-0636. Postgiro 12255-6. Tga\nBergand\n\nVerksamhet: Agentur o\nhandelsrörelse med maskinförnödenheter\nÄgare: Lars Nordwall\nEtableringsår 1916.\n\nKAISER, HANS\n\nPnr 11140\n\nStockholm C, Tegnérg 11. Tel\n08-103656. Bankgiro 728-7048.\nPostgiro 555659-2. Tga Hakaiser.\nTelex 10337\n\nVerksamhet: Handelsagenturer för\n\nheminredningsartiklar\n\nÄgare o chef: Disp Hans Kaiser\n\nEtableringsår: 1913.\n\nNYMOLLA AB\n\nPnr 290 42\n\nNymö Ila. Tel 044-54200. Bankgiro\n16-0586. Postgiro 575550. Telex\n4420 nymolla ksd. Tga Nymöllapulp\nVerksamhet: Tillverkar blekt\nmag-nefitcellulosa av barrved o löwed\nAntal anställda: 265\nÅrsomsättning: 75 000 000\nAktiekapital: 25 000 000\nEtableringsår: 1960.\n\nBS-MASKINER AB\n\nPnr 594 00\n\nGamleby, Box 571. Västerviksvl3.\nTel 0493-115 10. Bankgiro\n985-3987. Postgiro 567540-0\nVerksamhet: Aukt återförsäljare\nför AB Bolinder-Munktell\njordbruks-o entreprenadmaskiner\nFilialer: Kisa, Kalmerv 14. Tel\n0494-112 78\n\nVimmerby, Västerviksv. Tel 04\n92-116 61\n\nAntal anställda: 50\nÅrsomsättning: 15 000 000\nAktiekapital: 100 000\nStyrelseordf: Dir Bo Svensson\nVerkst dir: Bo Svensson\nEtableringsår: 1965.\n\nPRYDNOBOLAGET\n\nPnr 113 53\n\nStockholm, Tuleg 35. Tel\n08-318216, 318242. Bankgiro\n57-6194. Postgiro 57629. Tga Prydno\nVerksamhet: Butiksinredningar\nAntal anställda: 12\nÅrsomsättning: 600 000\nChef: Fabr Hjalmar Holmquist\nEtableringsår: 1928.\n\nCHARKOFABRIKEN, AB\n\nPnr 93101\n\nSkellefteå 1, Box 203. Tel\n0910-173 60. Bankgiro 20-3993.\nPostgiro 66932-5\n\nVerksamhet: Tillverkar\ncharkute-varor\n\nCHE-BE IMPORT AB\n\nPnr15123\n\nSödertälje 1, Box 247. Järnag 6 A.\nTel 0755-10309, 126 20. Bankgiro\n622-6641. Postgiro 443467-6. Tga\nChebe\n\nVerksamhet: Import av livsmedel\nAktiekapital: 50 000\nStyrelse: Dir Johnny K S Cheng\n(ordf), fru Hanna Cheng\nVerkst dir. Johnny K S Cheng\nEtableringsår: 1953\nOmbildat till aktiebolag 1967.\n\nCHEMACRYL AB\n\nPnr 16103\n\nBromma 3, Holbergsg 95. Box 3041.\nTel 08-37 28 90. Bankgiro\n161-2142. Tga Chemacrylab.\nTelex 10735 CHEMAB S\nVerksamhet: Säljer kemiska råvaror\nför industrin\nAntal anställda: 18\nAktiekapital: 75000\nVerkst dir: Dr George P Herz\nEtableringsår: 1964.",
    "structured": {
        "1": {
            "company_name": "TEKNO.MONTAN, AB",
            "pnr": "171 22",
            "address": "Solna 1, Pyramidv 7. Box 1116",
            "phone_number": "08-27 27 25",
            "bank_details": {
                "bankgiro": "16-0177",
                "postgiro": "320489"
            },
            "activity": "PUMPAR ALLA SLAG",
            "employees": 22,
            "annual_turnover": 1700000,
            "capital": 60000,
            "key_personnel": [
                {
                    "name": "L Hennig",
                    "position": "Verkst dir"
                }
            ],
            "establishment_year": 1944
        },
        "2": {
            "company_name": "TEKNO-PRODUKTER, INGENIORSFIRMA",
            "pnr": "104 65",
            "address": "Stockholm 15, Box 15021. Stadsgården 24",
            "phone_number": "08-23 19 70",
            "bank_details": {
                "bankgiro": "720-1726",
                "postgiro": "511105-9"
            },
            "activity": "Säljer aggregat för luktborttagning med aktivt kol mm",
            "employees": 6,
            "annual_turnover": 500000,
            "key_personnel": [
                {
                    "name": "Ing Thorsten Möller",
                    "position": "Chef"
                }
            ],
            "establishment_year": 1962
        },
        "3": {
            "company_name": "SVEA AB, ANNONSBYRÄN",
            "pnr": "103 10",
            "address": "Stockholm 2, Stora Nyg 27. Fack",
            "phone_number": "08-44 92 80",
            "bank_details": {
                "bankgiro": "721-7177",
                "postgiro": "55195-2"
            },
            "activity": "Auktoriserad annonsbyrå med fullständig reklamservice",
            "employees": 230,
            "annual_turnover": 90000000,
            "capital": 180000,
            "key_personnel": [
                {
                    "name": "Lars Berg",
                    "position": "Verkst dir"
                }
            ],
            "establishment_year": 1897
        },
        "4": {
            "company_name": "ATTEVIKS B IL-AB",
            "pnr": "550 02",
            "address": "Jönköping 2, Box 2122. John Bauersg 1",
            "phone_number": "036-1188 30",
            "activity": "Säljer Scania-Vabis, Volkswagen o Porsche",
            "capital": 300000,
            "key_personnel": [
                {
                    "name": "Per-Ake Löf",
                    "position": "Verkst dir"
                }
            ],
            "establishment_year": 1951
        },
        "5": {
            "company_name": "SWERCO.MASKINER",
            "pnr": "820 40",
            "address": "Järvsö",
            "phone_number": "0651-404 76, 404 90",
            "activity": "Tillverkar kilrems- o planskivor i lättmetall o gjutjärn, transportörer, transportrullar o skidliftar. Gjuteri för aluminium, lättmetall o järn",
            "key_personnel": [
                {
                    "name": "Arvid Persson",
                    "position": "Chef"
                }
            ]
        },
        "6": {
            "company_name": "SVERËMO AB, INGENJÖRS. FIRMA",
            "pnr": "211 21",
            "address": "Malmö, Gråbrödersg 2",
            "phone_number": "040-10 0160",
            "bank_details": {
                "telex": "32461",
                "tga": "Sveremo"
            },
            "activity": "Elektromagnetiska vibratorer, maskinmontage",
            "employees": 60,
            "annual_turnover": 3500000,
            "capital": 30000,
            "key_personnel": [
                {
                    "name": "Georg Lindström",
                    "position": "Veikst dir"
                }
            ],
            "establishment_year": 1953
        },
        "7": {
            "company_name": "HOFWERBERG&amp; ANDERSON",
            "pnr": "42105",
            "address": "Västra Frölunda 5, Box 5022",
            "phone_number": "031-29 3100, 290200",
            "bank_details": {
                "bankgiro": "50-0636",
                "postgiro": "12255-6",
                "tga": "Bergand"
            },
            "activity": "Agentur o handelsrörelse med maskinförnödenheter",
            "owner": "Lars Nordwall",
            "establishment_year": 1916
        },
        "8": {
            "company_name": "KAISER, HANS",
            "pnr": "11140",
            "address": "Stockholm C, Tegnérg 11",
            "phone_number": "08-103656",
            "bank_details": {
                "bankgiro": "728-7048",
                "postgiro": "555659-2",
                "telex": "10337",
                "tga": "Hakaiser"
            },
            "activity": "Handelsagenturer för heminredningsartiklar",
            "owner": "Disp Hans Kaiser",
            "establishment_year": 1913
        },
        "9": {
            "company_name": "NYMOLLA AB",
            "pnr": "290 42",
            "address": "Nymö Ila",
            "phone_number": "044-54200",
            "bank_details": {
                "bankgiro": "16-0586",
                "postgiro": "575550",
                "telex": "4420 nymolla ksd",
                "tga": "Nymöllapulp"
            },
            "activity": "Tillverkar blekt mag-nefitcellulosa av barrved o löwed",
            "employees": 265,
            "annual_turnover": 75000000,
            "capital": 25000000,
            "establishment_year": 1960
        },
        "10": {
            "company_name": "BS-MASKINER AB",
            "pnr": "594 00",
            "address": "Gamleby, Box 571. Västerviksvl3",
            "phone_number": "0493-115 10",
            "bank_details": {
                "bankgiro": "985-3987",
                "postgiro": "567540-0"
            },
            "activity": "Aukt återförsäljare för AB Bolinder-Munktell jordbruks-o entreprenadmaskiner",
            "branch_offices": [
                "Kisa, Kalmerv 14",
                "Vimmerby, Västerviksv"
            ]
        },
        "11": {
            "company_name": "PRYDNOBOLAGET",
            "pnr": "113 53",
            "address": "Stockholm, Tuleg 35",
            "phone_number": "08-318216, 318242",
            "bank_details": {
                "bankgiro": "57-6194",
                "postgiro": "57629",
                "tga": "Prydno"
            },
            "activity": "Butiksinredningar",
            "employees": 12,
            "annual_turnover": 600000,
            "owner": "Fabr Hjalmar Holmquist",
            "establishment_year": 1928
        },
        "12": {
            "company_name": "CHARKOFABRIKEN, AB",
            "pnr": "93101",
            "address": "Skellefteå 1, Box 203",
            "phone_number": "0910-173 60",
            "bank_details": {
                "bankgiro": "20-3993",
                "postgiro": "66932-5"
            },
            "activity": "Tillverkar charkute-varor"
        },
        "13": {
            "company_name": "CHE-BE IMPORT AB",
            "pnr": "15123",
            "address": "Södertälje 1, Box 247. Järnag 6 A",
            "phone_number": "0755-10309, 126 20",
            "bank_details": {
                "bankgiro": "622-6641",
                "postgiro": "443467-6",
                "tga": "Chebe"
            },
            "activity": "Import av livsmedel",
            "capital": 50000,
            "board_of_directors": [
                "Dir Johnny K S Cheng (ordf)",
                "fru Hanna Cheng",
                "Johnny K S Cheng (Verkst dir)"
            ],
            "establishment_year": 1953,
            "restructured_year": 1967
        },
        "14": {
            "company_name": "CHEMACRYL AB",
            "pnr": "16103",
            "address": "Bromma 3, Holbergsg 95. Box 3041",
            "phone_number": "08-37 28 90",
            "bank_details": {
                "bankgiro": "161-2142",
                "telex": "10735 CHEMAB S",
                "tga": "Chemacrylab"
            },
            "activity": "Säljer kemiska råvaror för industrin",
            "employees": 18,
            "capital": 75000,
            "key_personnel": [
                {
                    "name": "Dr George P Herz",
                    "position": "Verkst dir"
                }
            ],
            "establishment_year": 1964
        }
    }
}