{
    "original": "VIDE-LEN AB\n\nPnr 14102\n\nHuddinge 2, Lönnv 42-44. Fack.\nTel 08-757 28 90. Bankgiro 19-5605.\nPostgiro 497260\n\nVerksamhet Tillverkar\nsmåbarnskläder upp till 5 år i trikå o tyg\nVarunamn: Vide-len\nAktiekapital: 150 000\nVerkst dir: Fru Vera Wallén\nEtableringsår: 1955.\n\nTHULINS BOKTRYCKERI AB\n\nPnr 500 02\n\nÆorås 2, Norrby Långg 18. Box\n22079. Tel 033-111195. Bankgiro\n839-2102. Postgiro 377526-9\nVerksamhet: Specialité:\nfyrfärgs-tryck\n\nAktiekapital: 20 000\nChefer: Gunnar Thulin, Valter\nThulin\n\nEtableringsår: 1916.\n\nBEN\n\nSALA\n\nTAPPVÄXLAR\n\nmedför lägre kostnader\ngenom färre typer och\nenklare konstruktion.\nTillverkas i 10 storlekar\ni såväl 1, 2 plan som 3\nplansväxlar.\n\nBENZLER åt CO\n\nSTOCKHOLM - Box 1067\n171 22 SOLNA Telefon växel 83 44 00\n\nRep. för Norrland: AB ÅKESSON &amp; BLOMQUIST\n\nlätt att installera\ninga fundament\ninga kopplingar\ninga spännlinjaler\nkompakt och\nutrymmesbesparande.\n\nAKTIEBOLAG\n\n211 35 MALMÖ - Djäknegatan 4, Tel. 702 75\n416 72 GÖTEBORG - Lilla Munkebäcksgatan 6,\nTel. 25 00 80\n\nSUNDSVALL, Tel. 060/15 40 20\n\nBENGTSSON AB,\nRORLED-NINGSFIRMAN CYRUS\n\nPnr 732 00\n\nArboga, Box 94. Strängen 5. Tel\n0589-138 35. Bankgiro 80-9844.\nPostgiro 142705\"\nVerksamhet:\nRörledningsinstallationer, oljeeldnings- o\nventilationsanläggningar, VVS-material\nAntal anställda: 38\nÅrsomsättning: 4 000 000\nAktiekapital: 60 000\nVerkst dir: N E Johansson\nEtableringsår: 1921.\n\nALG\n\nALEXANDERSON &amp; CO AB, S\n\nPnr 151 23\n\nSödertälje 1, V Kanalg 9. Box 272.\nTel 0755-399 90. Bankgiro\n160-1905. Postgiro 257363-2. Tga\nStenaco. Telex 17872\nVerksamhet: Konstruktion o\nförsäljning av gjuteri o\nsmältutrust-ningar samt allmänna\ntransportanordningar, specialitet:\ntryckluft-transportörer\nAntal anställda: 5\nAktiekapital 50 000\nStyrelse: Disp C-V Wahlgren, ing\nK G Fuhrman\nEtableringsår: 1946.\n\nHÖGBERG &amp; HULTNER AB\n\nPnr 595 00\n\nMjölby, Smàlandsv. Tel\n0142-13150. Postgiro 11686. Tga Hultner\nVerksamhet: Tillverkar radio- o\nTV-möbler, kontorsmöbler\nAktiekapital: 100000\nVerkst dir: Gösta Hultner\nEtableringsår: 1901\nOmbildat till aktiebolag 1932.\n\nHÖGBERGS ROR AB\n\nPnr 502 63\n\nBorås, Stuartsg 4. Tel 033-13 70 25.\nBankgiro 843-4458. Postgiro\n23149-8\n\nVerksamhet: Rörlednings- o\nel-entreprenör\nAntal anställda: 35\nÅrsomsättning: 3750 000\nAktiekapital: 50 000\nVerkst dir: Erik Högberg\nEtableringsår: 1922\nOmbildat till aktiebolag 1954.\n\nHÖGBERG &amp; SCHONOW AB\n\nPnr 114 20\n\nStockholm, Birger Jarlsg 108. Tel\n08-234410. Bankgiro 57-2345.\nPostgiro 3206. Tga Glashögberg\nVeiksamhet: Planglas en gros.\nGlasmästeri o spegelfabrik.\nTillverkar speglar samt utför\ninsättning av glas. Glasslipning o\netsning\n\nAntal anställda: 40\nÅrsomsättning: 7 000 000\nAktiekapital: 150000\nVerkst dir: Arne Högberg\nEtableringsår 1903\nOmbildat till aktiebolag 1932.\n\nHÖGBERG, AB BROR\n\nPnr 41108\n\nGöteborg, Stora Nyg 1. Tel\n031-11 23 60. 11 25 32. Tga Furbror\nVerksamhet: Importagenturer i\ntextilbranschen\nÅrsomsättning: 10 000 000\nAktiekapital: 75 000\nVerkst dir: Kapten Bror Högberg\nEtableringsår 1931.\n\nSVENSK NEONINDUSTRI\n\nPnr 416 56\n\nGöteborg, Stenströmsg 14. Tel\n031-21 24 20, 21 17 60. Bankgiro\n444-2687. Postgiro 521356-6\nVerksamhet: Tillverkar o säljer\nneonanläggningar o plastskyltar\nChef: Arne Neptun\nEtableringsår: 1956.\n\nÅREVALL AB\n\nPnr 33100\n\nVärnamo, Malmöv. Tel 0370-141 00,\n142 00. Bankgiro 14-3033.\nPostgiro 367293\n\nVerksamhet: Industri o\nmassartiklar i termoplast\nAntal anställda: 32\nÅrsomsättning: 2 500 000\nAktiekapital: 40 000\nVerkst din Bertil Arevall\nEtableringsån 1948.\n\nGRÄSTORPS TRÄVARUAFFÄR\n\nPnr 460 50\n\nGrästorp. Tel 0514-10107, 109 33.\nBankgiro 218-8522. Postgiro\n175614-7\n\nVerksamhet: Säljer trävaror o\nbyggmaterial\nAntal anställda: 3\nÅrsomsättning: 1000000\nChef: Disp Bertil Ideberg\nEtableringsår: 1926.\n\nGRÄVMASKINS AB BIRGER\nANDERSSON &amp; CO\n\nPnr 602 24\n\nNorrköping, Plemingg 1. Tel\nOHIO 60 20. Bankgiro 349-1446.\nPostgiro 177593-1\n\nVerksamhet: Maskingrävning o\nentreprenadrörelse\nAntal anställda: 4\nÅrsomsättning: 247 700\nAktiekapital: 20 000\nVerkst dir: Byggnadsing Birger\nAndersson\n\nGRÄVMASKINS. &amp; TRAKTOR.\nSERVICE\n\nPnr 421 31\n\nVästra Frölunda, Fröhandelsg. Tel\n031-45 25 46, 45 85 46. Bankgiro\n51-5831. Postgiro 524660\nVerksamhet: Reparation av\nentreprenadmaskiner\nAntal anställda: 15\nÅrsomsättning: 1 200 000\nChefer: Pabr Einar Olsson, fabr\nBengt Andréasson\nEtableringsår: 1958.\n\nTDR\n\nTYSKLIND, AB BRÖDERNA\n\nPnr 790 30\n\nInsjön, Box 8. Tel 0247-40145,\n406 00. Bankgiro 795-9489.\nPostgiro 77328-3. Tga Betesport\nVerksamhet: Tillverkar fiskdrag o\ngarnfiskredskap. Säljer all slags\nfiskredskap samt campingartiklar o\nsportartiklar för vinter- o\nsommarsport\n\nVarunamn: Bete, Bingo, Blue Star\n\nAntal anställda: 25\n\nÅrsomsättning: 3 850 000\n\nAktiekapital: 80 000\n\nStyrelse: Dir Bengt Tysklind (ordf),\n\nkontorist Sören Tysklind, fabr Ake\n\nTysklind\n\nVerkst din Bengt Tysklind\nEtableringsår: 1917\nOmbildat till aktiebolag 1937.\n\nTYSTBERGA\nSNICKERIFABRIK\n\nPnr 610 60\n\nTystberga. Tel 0155-60019, 600 29\nVerksamhet: Tillverkar\ninrednings-snickerier av alla slag\nÄgare o chef: Gustaf Larsson.\n\nTÅGAR PS CEMENTGJUTERI,\nAB\n\nPnr 260 22\n\nTågan». Tel 0418-502 50. Bankgiro\n868-5935. Postgiro 137390-1\nVerksamhet:\nBetongvarutillverkning samt entreprenadverksamhet\nAntal anställda: 100\nÅrsomsättning: 8 000000\nAktiekapital: 100 000\nVerkst din Ing Ingemar Johansson\nEtableringsår: 1920.\n\nNILSSON &amp; CO AB, J E\n\nPnr 414 51\n\nGöteborg, Banehagsg 1. Tel\n031-149873, 149874. Bankgiro 33-7716.\nPostgiro 46079\n\nVerksamhet: Specialverkstad för\nrostfritt samt byggnadsplåt\nAntal anställda: 14\nÅrsomsättning: 1200 000\nAktiekapital: 30 000\nVerkst dir: Sven A Jakobson\nEtableringsår: 1917.\n\nNILSSON, BYGGNADSFIRMA\nJOHANNES\n\nPnr 45100\n\nUddevalla, Kungsg 13. Tel\n0522-147 80. Bankgiro 618-5268.\nPostgiro 448676-7\n\nVerksamhet:\nReparationsverksamhet, markförvärv o\nfastighetsförvaltning, egen-regi-byggande,\nkonsult- o kontrollantverksamhet\nAntal anställda: 20\nÅrsomsättning: 5 000 000\n\nChef: Byggmäst Johannes Nilsson\nEtableringsår: 1953\nDotterbolag: AB Johannes &amp; Son\nKB, Uddevalla. Hotell\nStenungs-baden AB, Stenungsund. Kv Börsen\nAB &amp; Co KB. Uddevalla. AB\nRöd-jan, Uddevalla. AB Sex Broar,\nUddevalla.\n\nNILSSON, KARL\n\nPnr 570 91\n\nKristdala. Tel 0491-70130, 704 44.\nBankgiro 451-2299. Postgiro\n377039-3\n\nVerksamhet: Sågar o hyvlar\nbarr-trä, tryckimpregnering av furuvirke\nAntal anställda: 35\nÅrsomsättning: 5 500 000\nFörvaltare: Henrik Hägerdal\nEtableringsår: 1936.",
    "structured": {
        "1": {
            "company_name": "VIDE-LEN AB",
            "pnr": "14102",
            "address": "Huddinge 2, Lönnv 42-44. Fack.",
            "phone_number": "08-757 28 90",
            "bank_details": {
                "bankgiro": "19-5605",
                "postgiro": "497260"
            },
            "activity": "Tillverkar småbarnskläder upp till 5 år i trikå o tyg",
            "capital": 150000,
            "key_personnel": [
                {
                    "name": "Fru Vera Wallén",
                    "position": "Verkst dir"
                }
            ],
            "establishment_year": 1955
        },
        "2": {
            "company_name": "THULINS BOKTRYCKERI AB",
            "pnr": "500 02",
            "address": "Æorås 2, Norrby Långg 18. Box 22079",
            "phone_number": "033-111195",
            "bank_details": {
                "bankgiro": "839-2102",
                "postgiro": "377526-9"
            },
            "activity": "Specialité: fyrfärgs-tryck",
            "capital": 20000,
            "key_personnel": [
                {
                    "name": "Gunnar Thulin",
                    "position": "Chefer"
                },
                {
                    "name": "Valter Thulin",
                    "position": "Chefer"
                }
            ],
            "establishment_year": 1916
        },
        "3": {
            "company_name": "BENZLER",
            "activity": "medför lägre kostnader genom färre typer och enklare konstruktion. Tillverkas i 10 storlekar i såväl 1, 2 plan som 3 plansväxlar."
        },
        "4": {
            "company_name": "BENZLER åt CO",
            "address": "STOCKHOLM - Box 1067 171 22 SOLNA",
            "phone_number": "Telefon växel 83 44 00",
            "key_personnel": [
                {
                    "name": "AB ÅKESSON & BLOMQUIST",
                    "position": "Rep. för Norrland"
                }
            ]
        },
        "5": {
            "company_name": "BENGTSSON AB, RÖRLEDNINGSFIRMAN CYRUS",
            "pnr": "732 00",
            "address": "Arboga, Box 94. Strängen 5",
            "phone_number": "0589-138 35",
            "bank_details": {
                "bankgiro": "80-9844",
                "postgiro": "142705"
            },
            "activity": "Rörledningsinstallationer, oljeeldnings- o ventilationsanläggningar, VVS-material",
            "employees": 38,
            "annual_turnover": 4000000,
            "capital": 60000,
            "key_personnel": [
                {
                    "name": "N E Johansson",
                    "position": "Verkst dir"
                }
            ],
            "establishment_year": 1921
        },
        "6": {
            "company_name": "ALEXANDERSON & CO AB, S",
            "pnr": "151 23",
            "address": "Södertälje 1, V Kanalg 9. Box 272",
            "phone_number": "0755-399 90",
            "bank_details": {
                "bankgiro": "160-1905",
                "postgiro": "257363-2"
            },
            "activity": "Konstruktion o försäljning av gjuteri o smältutrust-ningar samt allmänna transportanordningar, specialitet: tryckluft-transportörer",
            "employees": 5,
            "capital": 50000,
            "key_personnel": [
                {
                    "name": "Disp C-V Wahlgren",
                    "position": "Styrelse"
                },
                {
                    "name": "ing K G Fuhrman",
                    "position": "Styrelse"
                }
            ],
            "establishment_year": 1946
        },
        "7": {
            "company_name": "HÖGBERG & HULTNER AB",
            "pnr": "595 00",
            "address": "Mjölby, Smàlandsv",
            "phone_number": "0142-13150",
            "postgiro": "11686",
            "activity": "Tillverkar radio- o TV-möbler, kontorsmöbler",
            "capital": 100000,
            "key_personnel": [
                {
                    "name": "Gösta Hultner",
                    "position": "Verkst dir"
                }
            ],
            "establishment_year": 1901
        },
        "8": {
            "company_name": "HÖGBERGS RÖR AB",
            "pnr": "502 63",
            "address": "Borås, Stuartsg 4",
            "phone_number": "033-13 70 25",
            "bank_details": {
                "bankgiro": "843-4458",
                "postgiro": "23149-8"
            },
            "activity": "Rörlednings- o el-entreprenör",
            "employees": 35,
            "annual_turnover": 3750000,
            "capital": 50000,
            "key_personnel": [
                {
                    "name": "Erik Högberg",
                    "position": "Verkst dir"
                }
            ],
            "establishment_year": 1922
        },
        "9": {
            "company_name": "HÖGBERG & SCHONOW AB",
            "pnr": "114 20",
            "address": "Stockholm, Birger Jarlsg 108",
            "phone_number": "08-234410",
            "bank_details": {
                "bankgiro": "57-2345",
                "postgiro": "3206"
            },
            "activity": "Planglas en gros. Glasmästeri o spegelfabrik. Tillverkar speglar samt utför insättning av glas. Glasslipning o etsning",
            "employees": 40,
            "annual_turnover": 7000000,
            "capital": 150000,
            "key_personnel": [
                {
                    "name": "Arne Högberg",
                    "position": "Verkst dir"
                }
            ],
            "establishment_year": 1903
        },
        "10": {
            "company_name": "HÖGBERG, AB BROR",
            "pnr": "41108",
            "address": "Göteborg, Stora Nyg 1",
            "phone_number": "031-11 23 60",
            "activity": "Importagenturer i textilbranschen",
            "annual_turnover": 10000000,
            "capital": 75000,
            "key_personnel": [
                {
                    "name": "Kapten Bror Högberg",
                    "position": "Verkst dir"
                }
            ],
            "establishment_year": 1931
        },
        "11": {
            "company_name": "SVENSK NEONINDUSTRI",
            "pnr": "416 56",
            "address": "Göteborg, Stenströmsg 14",
            "phone_number": "031-21 24 20",
            "bank_details": {
                "bankgiro": "444-2687",
                "postgiro": "521356-6"
            },
            "activity": "Tillverkar o säljer neonanläggningar o plastskyltar",
            "chief": "Arne Neptun",
            "establishment_year": 1956
        },
        "12": {
            "company_name": "ÅREVALL AB",
            "pnr": "33100",
            "address": "Värnamo, Malmöv",
            "phone_number": "0370-141 00",
            "bank_details": {
                "bankgiro": "14-3033",
                "postgiro": "367293"
            },
            "activity": "Industri o massartiklar i termoplast",
            "employees": 32,
            "annual_turnover": 2500000,
            "capital": 40000,
            "key_personnel": [
                {
                    "name": "Bertil Arevall",
                    "position": "Verkst din"
                }
            ],
            "establishment_year": 1948
        },
        "13": {
            "company_name": "GRÄSTORPS TRÄVARUAFFÄR",
            "pnr": "460 50",
            "address": "Grästorp",
            "phone_number": "0514-10107",
            "activity": "Säljer trävaror o byggmaterial",
            "employees": 3,
            "annual_turnover": 1000000,
            "chief": "Disp Bertil Ideberg",
            "establishment_year": 1926
        },
        "14": {
            "company_name": "GRÄVMASKINS AB BIRGER ANDERSSON & CO",
            "pnr": "602 24",
            "address": "Norrköping, Plemingg 1",
            "phone_number": "OHIO 60 20",
            "bank_details": {
                "bankgiro": "349-1446",
                "postgiro": "177593-1"
            },
            "activity": "Maskingrävning o entreprenadrörelse",
            "employees": 4,
            "annual_turnover": 247700,
            "capital": 20000,
            "key_personnel": [
                {
                    "name": "Byggnadsing Birger Andersson",
                    "position": "Verkst dir"
                }
            ]
        },
        "15": {
            "company_name": "GRÄVMASKINS. & TRAKTOR. SERVICE",
            "pnr": "421 31",
            "address": "Västra Frölunda, Fröhandelsg",
            "phone_number": "031-45 25 46",
            "activity": "Reparation av entreprenadmaskiner",
            "employees": 15,
            "annual_turnover": 1200000,
            "key_personnel": [
                {
                    "name": "Pabr Einar Olsson",
                    "position": "Chefer"
                },
                {
                    "name": "fabr Bengt Andréasson",
                    "position": "Chefer"
                }
            ],
            "establishment_year": 1958
        },
        "16": {
            "company_name": "TYSKLIND, AB BRÖDERNA",
            "pnr": "790 30",
            "address": "Insjön, Box 8",
            "phone_number": "0247-40145",
            "activity": "Tillverkar fiskdrag o garnfiskredskap. Säljer all slags fiskredskap samt campingartiklar o sportartiklar för vinter- o sommarsport",
            "varunamn": "Bete, Bingo, Blue Star",
            "employees": 25,
            "annual_turnover": 3850000,
            "capital": 80000,
            "key_personnel": [
                {
                    "name": "Dir Bengt Tysklind (ordf)",
                    "position": "Styrelse"
                },
                {
                    "name": "kontorist Sören Tysklind",
                    "position": "Styrelse"
                },
                {
                    "name": "fabr Ake Tysklind",
                    "position": "Styrelse"
                }
            ],
            "establishment_year": 1917
        },
        "17": {
            "company_name": "TYSTBERGA SNICKERIFABRIK",
            "pnr": "610 60",
            "address": "Tystberga",
            "phone_number": "0155-60019",
            "activity": "Tillverkar inrednings-snickerier av alla slag",
            "chief": "Gustaf Larsson"
        },
        "18": {
            "company_name": "TÅGAR PS CEMENTGJUTERI, AB",
            "pnr": "260 22",
            "address": "Tågan»",
            "phone_number": "0418-502 50",
            "bank_details": {
                "bankgiro": "868-5935",
                "postgiro": "137390-1"
            },
            "activity": "Betongvarutillverkning samt entreprenadverksamhet",
            "employees": 100,
            "annual_turnover": 8000000,
            "capital": 100000,
            "key_personnel": [
                {
                    "name": "Ing Ingemar Johansson",
                    "position": "Verkst din"
                }
            ],
            "establishment_year": 1920
        },
        "19": {
            "company_name": "NILSSON & CO AB, J E",
            "pnr": "414 51",
            "address": "Göteborg, Banehagsg 1",
            "phone_number": "031-149873",
            "bank_details": {
                "bankgiro": "33-7716",
                "postgiro": "46079"
            },
            "activity": "Specialverkstad för rostfritt samt byggnadsplåt",
            "employees": 14,
            "annual_turnover": 1200000,
            "capital": 30000,
            "key_personnel": [
                {
                    "name": "Sven A Jakobson",
                    "position": "Verkst dir"
                }
            ],
            "establishment_year": 1917
        },
        "20": {
            "company_name": "NILSSON, BYGGNADSFIRMA JOHANNES",
            "pnr": "45100",
            "address": "Uddevalla, Kungsg 13",
            "phone_number": "0522-147 80",
            "bank_details": {
                "bankgiro": "618-5268",
                "postgiro": "448676-7"
            },
            "activity": "Reparationsverksamhet, markförvärv o fastighetsförvaltning, egen-regi-byggande, konsult- o kontrollantverksamhet",
            "employees": 20,
            "annual_turnover": 5000000,
            "chief": "Byggmäst Johannes Nilsson",
            "establishment_year": 1953,
            "dotterbolag": {
                "AB Johannes & Son KB, Uddevalla": "Hotell Stenungs-baden AB, Stenungsund. Kv Börsen AB & Co KB. Uddevalla. AB Röd-jan, Uddevalla. AB Sex Broar, Uddevalla"
            }
        },
        "21": {
            "company_name": "NILSSON, KARL",
            "pnr": "570 91",
            "address": "Kristdala",
            "phone_number": "0491-70130",
            "activity": "Sågar o hyvlar barr-trä, tryckimpregnering av furuvirke",
            "employees": 35,
            "annual_turnover": 5500000,
            "förvaltare": "Henrik Hägerdal",
            "establishment_year": 1936
        }
    }
}