{
    "original": "SOEMTRONIC, AB\n\nPnr 112 34\n\nStockholm, Sankt Eriksg 60 B. Tel\n08-52 0715. Bankgiro 561-1769.\n\nPostgiro 704700-4. Tga Soemtronic.\nTelex 10082\n\nVerksamhet: Generalagent för\nSoemtron elektroniska\nfaktureringsmaskiner o Ascota\nbokföringsmaskiner. Serviceverkstad för dessa\nmaskiner\n\nVerkst dir: Olle Lundgren\nEtableringsår: 1964.\n\nFINLANDSTRAFIKEN AB\n\nPnr 103 14\n\nStockholm 2, Box 2144. S\nBenicke-brinken 4. Tel 08-24 86 10.\nPostgiro 451071-5. Tga Finntraffic.\nTelex 10791\n\nVerksamhet: Handhar Silja Lines\nmarknadsföring o hökning\nAntal anstäUda: 16\nAktiekapital: 75 000\nVerkst dir. Gösta Ryning\nEtableringsår. 1966.\n\nKARLSSON KB, ALB\n\nPnr 63102\n\nEskilstuna 1, Eskilsg 20. Box 71.\nTel 016-14 7130. Bankgiro\n601-4781. Postgiro 32878-1. Tga Alb eka\nVerksamhet: Tillverkar bildetaljer,\nhögtalare m m. Utför förnickling,\nförkromning, förzinkning,\npressnings- o svetsningsarbeten\nVarunamn: Ticka, Voxtone\nAntal anställda: 270\nVerkst dir: C G Nilsson\nEtableringsår: 1889.\n\nCARLSSONS JÄRNHANDEL,\nAB ALBIN\n\nPnr 598 00\n\nVimmerby, Box 20. Storg 42. Tel\n0492-121 05. Bankgiro 85-7512.\nPostgiro 33513-3\n\nVerksamhet: Säljer järn o metaller,\nverktyg o redskap, spcrtartiklar,\nhushållsartiklar, hushållsmaskiner,\nmotorsågar samt byggnadsmaterial.\nUthyr presenningar. Gas\n\nAntal anställda: 22\nÅrsomsättning: 4 500 000\nAktiekapital: 150 000\nVerkst dir: Stig Brogren\nEtableringsår: 1945.\n\nKARLSSON, BYGGNADS AB\nALFRED\n\nPnr 502 43\n\nBorås, Brämhultsv 4. Tel\n033-136325\n\nVerksamhet: Byggnadsfirma för\nbostads-, affärs- o\nindustribyggnader\n\nChef: Byggmäst Alfred Karlsson\nEtableringsår: 1941.\n\nBORÅS ELP RO DUKTER, AB\n\nPnr 501 02\n\nBorås 1, Almenäsv. Box 48. Tel\n033-13 6110. Bankgiro 53-1666.\nPostgiro 123229\n\nVerksamhet: Plastartiklar för\nel-installation\n\nFörsäljningskontor: 113 51\nStockholm. AB Karl W Olsson, Odeng 45.\nTel 08-34 92 40\nVarunamn: BELP\nVerkst dir: S Stenlund\nEtableringsår: 1957.\n\nGÄVLE PATENTBYRÅ AB\n\nPnr 801 04\n\nGävle 1. Kyrkog 24 B. Box 304. Tel\n026-1123 14. Bankgiro 603-5125.\nPostgiro 467463-6. Tga\nGävlepatent\n\nVerksamhet: Patentombud\nAntal anställda: 6\nAktiekapital: 5 000\nVerkst dir: Diploming T Bjerkén\nEtableringsår: 1961.\n\nDUX,AB\n\nPnr 18121\n\nLidingö 1, Box 118. Vasav 76. Tel\n08-767 0380. Bankgiro 72-9204.\nPostgiro 913. Tga Feeder.\nTelex 10807 GALCO S\nVerksamhet: Tillverkar o säljer\nmaskiner för grafiska industrin\nÅrsomsättning: 1700 000\nAktiekapital: 200 000\nVerkst dir: Sven Winqvist\nEtableringsår: 1900.\n\nREG\n\nVarunamn: Fiender,Tandler, Cavex,\nZapex\n\nAktiekapital: 50 000\nVerkst dir: Hans Gerbaulet\nEtableringsår: 1943.\n\nREGULA AB, INGENJURS.\nFIRMAN\n\nPnr 121 21\n\nJohanneshov 1, Box 13. Gullmarsv\n51. Tel 08-81 02 20. Tga Ingregula,\nStockholm. Telex 17183 REGULA S\nVerksamhet: Import av armatur,\ninstrument o regulatorer\nAntal anställda: 6\nÅrsomsättning: 2000 000\nAktiekapital: 100 000\nVerkst dlr. Civiling Artur Monsén\nEtableringsår: 1947.\n\ndanalys ab\n\nPnr 212 15\n\nMalmö, Nobelv 129 B. Tel 040-\n\n755 55\n\nVerksamhet: Kemisk tekniska\nartiklar en gros\nAktiekapital: 125 000\nVerkst dir: Stig Holmström\nEtableringsår: 1918.\n\nSDD\n\nSÖDERTÄLJE BYGGNADS.\nVAROR AB\n\nPnr 151 24\n\nSödertälje 1, Box 367. Morabergsv\n13. Tel 0755-39610. Bankgiro\n622-5254. Postgiro 92869-7\nVerksamhet: Säljer\nbyggnadsmaterial, trävaror o golvprodukter samt\nutför golvbeläggningar.\nSmåhusavdelning\n\nAntal anställda: 60\nÅrsomsättning: 17 000 000\nAktiekapital: 300 000\nStyrelse: Dir Sven Dingertz, dir\nBörje Olsson, dir Göte Gustafsson\nVerkst dir: Göte Gustafsson\nEtableringsår: 1929\nOmbildat till aktiebolag 1935.\n\nSÖDERTÄLJE ISOLERINGS AB\n\nPnr 151 21\n\nSödertälje 1, Box 20. V Kanalg 23.\nTel 0755-13182, 33244. Bankgiro\n622-6765. Postgiro 998 94-8\nVerksamhet: Utför VVS-isolering,\nrör- o cisternisolering,\nventilations-Isolering, taktäckningar samt kyl- o\nfrysrumsisoleringar. Säljer all\nteknisk Isolering\n\nFilial: 126 40 Hägersten, Sulv 65.\nTel 08-19 08 10\n\n753 23 Uppsala, Mjölnarg 6. Tel\n018-10 5510\nAntal anställda: 35\nÅrsomsättning: 3 000 000\nAktiekapital: 30 000\nStyrelse: Dir Tage Waldekrantz\n(ordf), fru Lillemor Waldekrantz\nVerkst dir: Tage Waldekrantz\nArbetschef: Hans Vestin\nKalkylchef: Rolf Lindholm\nEtableringsår: 1962.\n\nLOF.EDA VERKEN, AB\n\nPnr 651 06\n\nKarlstad 1, Box 368. Sjömansg 1.\nTel 054-15 00 80. Postgiro 97631-6.\nTga Abai. Telex 66035\nVerksamhet: Tillverkar\nkaffemaskiner\n\nAntal anställda: 20\nÅrsomsättning: 1500 000\nAktiekapital: 100 000\nVerkst dir: Ake Löfberg\nEtableringsår: 1955.",
    "structured": {
        "1": {
            "company_name": "SOEMTRONIC, AB",
            "pnr": "112 34",
            "address": "Stockholm, Sankt Eriksg 60 B",
            "phone_number": "08-52 0715",
            "bank_details": {
                "bankgiro": "561-1769",
                "postgiro": "704700-4"
            },
            "activity": "Generalagent för Soemtron elektroniska faktureringsmaskiner o Ascota bokföringsmaskiner. Serviceverkstad för dessa maskiner",
            "establishment_year": 1964
        },
        "2": {
            "company_name": "FINLANDSTRAFIKEN AB",
            "pnr": "103 14",
            "address": "Stockholm 2, Box 2144, Benicke-brinken 4",
            "phone_number": "08-24 86 10",
            "postgiro": "451071-5",
            "activity": "Handhar Silja Lines marknadsföring o hökning",
            "employees": 16,
            "capital": 75000,
            "establishment_year": 1966
        },
        "3": {
            "company_name": "KARLSSON KB, ALB",
            "pnr": "63102",
            "address": "Eskilstuna 1, Eskilsg 20, Box 71",
            "phone_number": "016-14 7130",
            "bank_details": {
                "bankgiro": "601-4781",
                "postgiro": "32878-1"
            },
            "activity": "Tillverkar bildetaljer, högtalare m m. Utför förnickling, förkromning, förzinkning, pressnings- o svetsningsarbeten",
            "employees": 270,
            "key_personnel": [
                {
                    "name": "C G Nilsson",
                    "position": "Verkst dir"
                }
            ],
            "establishment_year": 1889
        },
        "4": {
            "company_name": "CARLSSONS JÄRNHANDEL, AB ALBIN",
            "pnr": "598 00",
            "address": "Vimmerby, Box 20, Storg 42",
            "phone_number": "0492-121 05",
            "bank_details": {
                "bankgiro": "85-7512",
                "postgiro": "33513-3"
            },
            "activity": "Säljer järn o metaller, verktyg o redskap, spcrtartiklar, hushållsartiklar, hushållsmaskiner, motorsågar samt byggnadsmaterial. Uthyr presenningar. Gas",
            "employees": 22,
            "annual_turnover": 4500000,
            "capital": 150000,
            "key_personnel": [
                {
                    "name": "Stig Brogren",
                    "position": "Verkst dir"
                }
            ],
            "establishment_year": 1945
        },
        "5": {
            "company_name": "KARLSSON, BYGGNADS AB ALFRED",
            "pnr": "502 43",
            "address": "Borås, Brämhultsv 4",
            "phone_number": "033-136325",
            "activity": "Byggnadsfirma för bostads-, affärs- o industribyggnader",
            "key_personnel": [
                {
                    "name": "Byggmäst Alfred Karlsson",
                    "position": "Chef"
                }
            ],
            "establishment_year": 1941
        },
        "6": {
            "company_name": "BORÅS ELP RO DUKTER, AB",
            "pnr": "501 02",
            "address": "Borås 1, Almenäsv. Box 48",
            "phone_number": "033-13 6110",
            "bank_details": {
                "bankgiro": "53-1666",
                "postgiro": "123229"
            },
            "activity": "Plastartiklar för el-installation",
            "sales_office": {
                "location": "Stockholm",
                "company_name": "AB Karl W Olsson",
                "address": "Odeng 45",
                "phone_number": "08-34 92 40"
            },
            "product_name": "BELP",
            "key_personnel": [
                {
                    "name": "S Stenlund",
                    "position": "Verkst dir"
                }
            ],
            "establishment_year": 1957
        },
        "7": {
            "company_name": "GÄVLE PATENTBYRÅ AB",
            "pnr": "801 04",
            "address": "Gävle 1, Kyrkog 24 B, Box 304",
            "phone_number": "026-1123 14",
            "bank_details": {
                "bankgiro": "603-5125",
                "postgiro": "467463-6"
            },
            "activity": "Patentombud",
            "employees": 6,
            "capital": 5000,
            "key_personnel": [
                {
                    "name": "Diploming T Bjerkén",
                    "position": "Verkst dir"
                }
            ],
            "establishment_year": 1961
        },
        "8": {
            "company_name": "DUX, AB",
            "pnr": "18121",
            "address": "Lidingö 1, Box 118, Vasav 76",
            "phone_number": "08-767 0380",
            "bank_details": {
                "bankgiro": "72-9204",
                "postgiro": "913"
            },
            "activity": "Tillverkar o säljer maskiner för grafiska industrin",
            "annual_turnover": 1700000,
            "capital": 200000,
            "key_personnel": [
                {
                    "name": "Sven Winqvist",
                    "position": "Verkst dir"
                }
            ],
            "establishment_year": 1900
        },
        "9": {
            "company_name": "REGULA AB, INGENJURS. FIRMAN",
            "pnr": "121 21",
            "address": "Johanneshov 1, Box 13, Gullmarsv 51",
            "phone_number": "08-81 02 20",
            "activity": "Import av armatur, instrument o regulatorer",
            "employees": 6,
            "annual_turnover": 2000000,
            "capital": 100000,
            "key_personnel": [
                {
                    "name": "Civiling Artur Monsén",
                    "position": "Verkst dir"
                }
            ],
            "establishment_year": 1947
        },
        "10": {
            "company_name": "danalys ab",
            "pnr": "212 15",
            "address": "Malmö, Nobelv 129 B",
            "phone_number": "040-755 55",
            "activity": "Kemisk tekniska artiklar en gros",
            "capital": 125000,
            "key_personnel": [
                {
                    "name": "Stig Holmström",
                    "position": "Verkst dir"
                }
            ],
            "establishment_year": 1918
        },
        "11": {
            "company_name": "SÖDERTÄLJE BYGGNADS. VAROR AB",
            "pnr": "151 24",
            "address": "Södertälje 1, Box 367, Morabergsv 13",
            "phone_number": "0755-39610",
            "bank_details": {
                "bankgiro": "622-5254",
                "postgiro": "92869-7"
            },
            "activity": "Säljer byggnadsmaterial, trävaror o golvprodukter samt utför golvbeläggningar. Småhusavdelning",
            "employees": 60,
            "annual_turnover": 17000000,
            "capital": 300000,
            "key_personnel": [
                {
                    "name": "Göte Gustafsson",
                    "position": "Verkst dir"
                }
            ],
            "establishment_year": 1929
        },
        "12": {
            "company_name": "SÖDERTÄLJE ISOLERINGS AB",
            "pnr": "151 21",
            "address": "Södertälje 1, Box 20, V Kanalg 23",
            "phone_numbers": [
                "0755-13182",
                "33244"
            ],
            "bank_details": {
                "bankgiro": "622-6765",
                "postgiro": "998 94-8"
            },
            "activity": "Utför VVS-isolering, rör- o cisternisolering, ventilation-Isolering, taktäckningar samt kyl- o frysrumsisoleringar. Säljer all teknisk Isolering",
            "branch_offices": {
                "Hägersten": {
                    "location": "126 40 Hägersten, Sulv 65",
                    "phone_number": "08-19 08 10"
                },
                "Uppsala": {
                    "location": "753 23 Uppsala, Mjölnarg 6",
                    "phone_number": "018-10 5510"
                }
            },
            "employees": 35,
            "annual_turnover": 3000000,
            "capital": 30000,
            "key_personnel": [
                {
                    "name": "Tage Waldekrantz",
                    "position": "Verkst dir"
                },
                {
                    "name": "Hans Vestin",
                    "position": "Arbetschef"
                },
                {
                    "name": "Rolf Lindholm",
                    "position": "Kalkylchef"
                }
            ],
            "establishment_year": 1962
        },
        "13": {
            "company_name": "LOF.EDA VERKEN, AB",
            "pnr": "651 06",
            "address": "Karlstad 1, Box 368, Sjömansg 1",
            "phone_number": "054-15 00 80",
            "postgiro": "97631-6",
            "activity": "Tillverkar kaffemaskiner",
            "employees": 20,
            "annual_turnover": 1500000,
            "capital": 100000,
            "key_personnel": [
                {
                    "name": "Ake Löfberg",
                    "position": "Verkst dir"
                }
            ],
            "establishment_year": 1955
        }
    }
}