{
    "original": "BYGGMEKANISERING, AB\n\nPnr 21133\n\nMalmö, Grynbodg 3. Tel 040-757 40.\nBankgiro 64-0401. Postgiro 431907.\nTga Byggmekanik.\nTelex 32374 SERVIO S\nVerksamhet: Tillverkar formlås,\nformstag, byggstämp, rörställningar,\npelarband, golvläggningsmaskiner\no mellanväggar. Strålningsskydd\nmot t ex röntgenstrålning m m\nVarunamn: Antitron, E G\nAntal anställda: 8\nÅrsomsättning: 4 500 000\nAktiekapital: 100 000\nStyrelse: Dir Bo Ekelund (ordf),\ndir Sven Askling, dir Erie\nGustafsson\n\nVerkst dir: Erie Gustafsson\nEtableringsår: 1952.\n\nULTRAMARE AB\n\nPnr 113 22\n\nStockholm, Odeng 106. Tel\n08-2417 55, 3019 31. Bankgiro\n726-1571. Postgiro 503144-8. Tga\nPythagoras. Telex 19063 ULMA S\nVerksamhet:\n\nLuftfilteravdelning: Tillverkare av\nluftfilter, importör av\nluftfilterme-dia, luftreningsanläggningar,\nren-lighetsteknisk utrustning\nTeknisk avdelning: Import av jute\no plastsäckar, papperssäckar\nAktiekapital: 50 000\nVerkst dir: E Matthias\nDisp: B Lundquist\nEtableringsår: 1953.\n\nLUNDBERG &amp;ALLERT AB\n\nPnr 401 27\n\nGöteborg 1, Tackjärnsg 1. Box\n495. Tel 031-22 2270. Bankgiro\n500-4551. Postgiro 12244-0.\nTga Lundallert\n\n\n\nVerksamhet: Partiförsäljning av\nverktyg, husgeråd, fritidsartiklar\nm m\n\nVarunamn: Laga, Master,\nQuick-Wedge, Tola\nÅrsomsättning: 8 000 000\nAktiekapital: 531500\nVerkst dir: Sten Allert\nEtableringsår: 1905.\n\nHAN\n\nStyrelse: Dir Gösta Hannell (ordf),\ndir Rolf Hannell, fru Ann-Charlotte\nMillez\n\nVerkst dir: Rolf Hannell.\n\nHANNILS MÖBELFABRIK, AB\n\nPnr 570 21\n\nMalmbäck, Pabriksg 20. Tel\n0380-600 90. Bankgiro 145-7514.\nPost-giro 175893-7\n\nVerksamhet: Tillverkar bokhyllor,\nsideboard, skåp, bord, byråer m m\nAntal anställda: 29\nÅrsomsättning: 2 250 000\nAktiekapital: 130 000\nVerkst dir: Göte Lundberg\nEtableringsår: 1947.\n\nSTÅLBERGS BIL AB\n\nPnr 93100\n\nSkellefteå, S Järnvägsg 30-32. Tel\n0910-770 20, 171 90. Bankgiro\n764-0360. Postgiro 386136-6\nVerksamhet: Bilförsäljning o\nrepareparationer. Peugeot\nAntal anställda: 22\nÅrsomsättning: 10 000 000\nAktiekapital: 50 000\nVerkst dir: Rune Stålberg\nEtableringsår: 1946.\n\nHONEYWELL BULL AB\n\nPnr 104 35\n\nStockholm, Sveav 163. Tel\n08-24 6 6 20. Postgiro 603730.\nTelex 10355 HWBULL S\nVerksamhet: Honeywell Bull\ndatamaskiner o hålkortsmaskiner.\nFörsäljningsbolag för Compagnie\nHoneywell Bull. Servicearbeten\ninom databehandling. Time Sharing\nService\n\nFUialer: Göteborg SV, Andra Långg\n44. Tel 031-124235\nMalmö C, Jörgen Ankersg 12. Tel\n040-736 25\n\nAktiekapital: 12 000 000\nVerkst dir: Léon Philips\nEtableringsår: 1950\nOmbildat till aktiebolag 1960.\n\nHOOKS MEKANISKA AB\n\nPnr 56013\n\nHok, Box 17. Tel 0393-211 34,\n21180. Bankgiro 714-2961. Postgiro\n264450-8\n\nVerksamhet: Tillverkar\nljusrörsar-maturer, bokhyllebelysning,\ndetaljer för utomhusbelysning, elektr\nljusstakar, julgransbelysningar\nsamt diverse beslag för.\nmöbelindustrin\n\nVarunamn: HM\nAntal anstäUda: 30\nÅrsomsättning: 2 500 000\nAktiekapital: 50000\nVerkst dir: Hans Larsson.\n\nHOPKINSON &amp; CARLSTEDT\nLTD, AB\n\nPnr 12656\n\nHägersten, Brådstupsv 11. Tel\n08-8812 90, 881291. Bankgiro\n196-0756. Postgiro 256612-3. Tga\nHopcarl\n\nVerksamhet: Elektr mätinstrument\n\no komponenter\n\nÅrsomsättning: 2 000 000\n\nAktiekapital: 5 000\n\nVerkst dir: Ing Torsten Järnmark\n\nEtableringsår: 1946.\n\nCERBO AB\n\nPnr 46104\n\nTrollhättan 4, Box 4007. Tel\n0520-183 00. Tga Cerbo\nVerksamhet: Plastindustri.\nTillverkar formsprutade\nförpackningsar-tiklar såsom askar, burkar,\nkapslar, lock etc samt engångsartiklar\nför sjukvård\nVarunamn: Cerbo\nAntal anställda: 160\nÅrsomsättning: 11000000\nAktiekapital: 400 000\nVerkst dir: Ing Evald Lind\nV verkst dir: Civilekonom Rune\nJohnson\n\nFabrikschef: Ing Lars Holmén\nMarknadschef: Jan Lidbeck\nEtableringsår: 1948.\n\nGARDIN AB\n\nPnr 101 31\n\nStockholm 1, Gamla Brog 29. Box\n763. Tel 08-23 52 50. Postgiro\n2087. Tga Curtain\nVerksamhet: Grossisthandel med\ngardiner o draperier\nAktiekapital: 270 000\nVerkst din K Sandberg\nEtableringsår: 1904.\n\nGRA\n\nInnovation!\n\nEn \"servicemaskin\" specialiserad på att lösa\njust Era reklam/tryck-problem!\n\nEtt team av artfolk, reprotekniker\noch tryckare - tillsammans ca 25 personer - med\ntoppmodern utrustning för boktryck och offset, under ett tak.\nDet är Grafia!\n\n\"Servicemaskinen\" och dess sifferbeteckningar förklarar\nvi så gärna för Er. Med ett personligt besök eller\ngenom att sända vår \"Servicehandbok\".\n\ng grafia\n\nTryckerigatan7/Box73/57100Nässjö/Telefon 0380-18170\n\nVerksamhet: Företaget är\nförsäljningskontor för snickerifabriker\nAntal anställda: 8\nÅrsomsättning: 4 000 000\nAktiekapital: 400000\nVerkst din John E Bolling\nEtableringsår: 1969.\n\nGOTLÄNDSKA\nLÅNT-MÄNNENS CENTRAL.\nFÖRENING\n\nPnr 62101\n\nVisby 1, Söderv 8-10. Fack. Tel\n0498-154 50. Postgiro 189094\nVerksamhet: Spannmål, foder- o\ngödselmedel, fröer o utsäden,\nmaskiner, byggnadsvaror, drivmedel,\nkemikalier mm\nAntal anställda: 212\nÅrsomsättning: 88 500 000\nVerkst dir: Arne Rabne\nEtableringsår: 1906.\n\nGOTTHARD\n\nAB HERMAN GOTTHARDT\n\nPnr 20040\n\nMalmö 8, Trelleborgsv 12-14. Fack.\nTel 040-800 80. Tga Gotthardt.\nTelex 32250 GOTHARD S\nVerksamhet: Tillverkare o grossist.\nBåtartiklar, stållinor med tillbehör,\nmattor, flaggor, flätade produkter,\ntågvirke, plasthallar o\nmotions-re dskap\n\nOrdermottagning, lager o\nproduktion: 232 00 Arlöv, Lommav. Box 45.\nTel 040-43 05 20\n\nAvdelningskontor: 411 08 Göteborg,\nStora Nyg 13. Tel 031-17 39 80\n11130 Stockholm, Packhusgränd 6.\nTel 08-14 02 55\n\nAktiekapital: 1500 000\nStyrelse: Adv Sten Lindskog (ordf),\ndir Karl Almström, adv Sven Munck\nav Rosenschöld, dir N R Wikander\nVerkst dir: Karl Almström\nEtableringsår: 1905.\n\nGOTTLOW KNAPPFABRIK,\nAB OSCAR\n\nPnr 24100\n\nEslöv, Sjöhusv 16. Box 91. Tel\n0413-105 94, 118 95. Bankgiro\n334-9537. Postgiro 6177-0. Tga Gottlow\nVerksamhet: Tillverkar\ndammode-knappar o spännen\nAntal anställda: 24\nÅrsomsättning: 900 000\nAktiekapital: 75 000\nVerkst dir: Kurt Gottlow\nEtableringsår: 1923\nOmbildat till aktiebolag 1939.\n\nGOTHUS ANNONSBYRÅ, AB\n\nPnr 413 01\n\nGöteborg, N Allég 5. Tel\n031-17 48 30. Bankgiro 10-7612.\nPostgiro 528505. Tga Gothus\nVerksamhet: Annonsbyrå\nAntal anställda: 29\nÅrsomsättning: 8 000 000\nAktiekapital: 300 000\nVerkst dir: Arnold Bergqvist\nEtableringsår: 1960.\n\nASSAB MEDICIN AB\n\nPnr 171 41\n\nSolna, Svets arv 20. Tel 08-29 02 45.\nPostgiro 526066-6\nVerksamhet: Tillverkar o säljer\nlaboratorieinredningar samt\ntermosta-terade utrustningar för\nbakteriologiska laboratorier\nAntal anställda: 11\nÅrsomsättning: 2 000 000\nAktiekapital: 495000\nVeikst dir: Erik Albertsson\nEtableringsår: 1959.",
    "structured": {
        "1": {
            "company_name": "BYGGMEKANISERING, AB",
            "pnr": "21133",
            "address": "Malmö, Grynbodg 3",
            "phone_number": "040-757 40",
            "bank_details": {
                "bankgiro": "64-0401",
                "postgiro": "431907"
            },
            "activity": "Tillverkar formlås, formstag, byggstämp, rörställningar, pelarband, golvläggningsmaskiner o mellanväggar. Strålningsskydd mot t ex röntgenstrålning m m",
            "employees": 8,
            "annual_turnover": 4500000,
            "capital": 100000,
            "key_personnel": [
                {
                    "name": "Bo Ekelund",
                    "position": "ordf"
                },
                {
                    "name": "Sven Askling",
                    "position": "dir"
                },
                {
                    "name": "Erie Gustafsson",
                    "position": "dir"
                }
            ],
            "establishment_year": 1952
        },
        "2": {
            "company_name": "ULTRAMARE AB",
            "pnr": "113 22",
            "address": "Stockholm, Odeng 106",
            "phone_number": "08-2417 55, 3019 31",
            "bank_details": {
                "bankgiro": "726-1571",
                "postgiro": "503144-8"
            },
            "activity": "Luftfilteravdelning: Tillverkare av luftfilter, importör av luftfiltermedia, luftreningsanläggningar, renlighetsteknisk utrustning. Teknisk avdelning: Import av jute o plastsäckar, papperssäckar",
            "capital": 50000,
            "key_personnel": [
                {
                    "name": "E Matthias",
                    "position": "Verkst dir"
                },
                {
                    "name": "B Lundquist",
                    "position": "Disp"
                }
            ],
            "establishment_year": 1953
        },
        "3": {
            "company_name": "LUNDBERG &ALLERT AB",
            "pnr": "401 27",
            "address": "Göteborg 1, Tackjärnsg 1, Box 495",
            "phone_number": "031-22 2270",
            "bank_details": {
                "bankgiro": "500-4551",
                "postgiro": "12244-0"
            },
            "activity": "Partiförsäljning av verktyg, husgeråd, fritidsartiklar m m",
            "annual_turnover": 8000000,
            "capital": 531500,
            "key_personnel": [
                {
                    "name": "Sten Allert",
                    "position": "Verkst dir"
                }
            ],
            "establishment_year": 1905
        },
        "4": {
            "company_name": "HANNILS MÖBELFABRIK, AB",
            "pnr": "570 21",
            "address": "Malmbäck, Pabriksg 20",
            "phone_number": "0380-600 90",
            "bank_details": {
                "bankgiro": "145-7514",
                "postgiro": "175893-7"
            },
            "activity": "Tillverkar bokhyllor, sideboard, skåp, bord, byråer m m",
            "employees": 29,
            "annual_turnover": 2250000,
            "capital": 130000,
            "key_personnel": [
                {
                    "name": "Göte Lundberg",
                    "position": "Verkst dir"
                }
            ],
            "establishment_year": 1947
        },
        "5": {
            "company_name": "STÅLBERGS BIL AB",
            "pnr": "93100",
            "address": "Skellefteå, S Järnvägsg 30-32",
            "phone_number": "0910-770 20, 171 90",
            "bank_details": {
                "bankgiro": "764-0360",
                "postgiro": "386136-6"
            },
            "activity": "Bilförsäljning o reparparationer. Peugeot",
            "employees": 22,
            "annual_turnover": 10000000,
            "capital": 50000,
            "key_personnel": [
                {
                    "name": "Rune Stålberg",
                    "position": "Verkst dir"
                }
            ],
            "establishment_year": 1946
        },
        "6": {
            "company_name": "HONEYWELL BULL AB",
            "pnr": "104 35",
            "address": "Stockholm, Sveav 163",
            "phone_number": "08-24 6 6 20",
            "postgiro": "603730",
            "activity": "Honeywell Bull datamaskiner o hålkortsmaskiner. Försäljningsbolag för Compagnie Honeywell Bull. Servicearbeten inom databehandling. Time Sharing Service",
            "capital": 12000000,
            "key_personnel": [
                {
                    "name": "Léon Philips",
                    "position": "Verkst dir"
                }
            ],
            "establishment_year": 1950
        },
        "7": {
            "company_name": "HOOKS MEKANISKA AB",
            "pnr": "56013",
            "address": "Hok, Box 17",
            "phone_number": "0393-211 34, 21180",
            "bank_details": {
                "bankgiro": "714-2961",
                "postgiro": "264450-8"
            },
            "activity": "Tillverkar ljusrörsmaturer, bokhyllebelysning, detaljer för utomhusbelysning, elektr ljusstakar, julgransbelysningar samt diverse beslag för möbelindustrin",
            "employees": 30,
            "annual_turnover": 2500000,
            "capital": 50000,
            "key_personnel": [
                {
                    "name": "Hans Larsson",
                    "position": "Verkst dir"
                }
            ]
        },
        "8": {
            "company_name": "HOPKINSON &CARLSTEDT LTD, AB",
            "pnr": "12656",
            "address": "Hägersten, Brådstupsv 11",
            "phone_number": "08-8812 90, 881291",
            "bank_details": {
                "bankgiro": "196-0756",
                "postgiro": "256612-3"
            },
            "activity": "Elektr mätinstrument o komponenter",
            "annual_turnover": 2000000,
            "capital": 5000,
            "key_personnel": [
                {
                    "name": "Ing Torsten Järnmark",
                    "position": "Verkst dir"
                }
            ],
            "establishment_year": 1946
        },
        "9": {
            "company_name": "CERBO AB",
            "pnr": "46104",
            "address": "Trollhättan 4, Box 4007",
            "phone_number": "0520-183 00",
            "activity": "Plastindustri. Tillverkar formsprutade förpackningsartiklar såsom askar, burkar, kapslar, lock etc samt engångsartiklar för sjukvård",
            "employees": 160,
            "annual_turnover": 11000000,
            "capital": 400000,
            "key_personnel": [
                {
                    "name": "Ing Evald Lind",
                    "position": "Verkst dir"
                },
                {
                    "name": "Rune Johnson",
                    "position": "V verkst dir"
                },
                {
                    "name": "Lars Holmén",
                    "position": "Fabrikschef"
                },
                {
                    "name": "Jan Lidbeck",
                    "position": "Marknadschef"
                }
            ],
            "establishment_year": 1948
        },
        "10": {
            "company_name": "GARDIN AB",
            "pnr": "101 31",
            "address": "Stockholm 1, Gamla Brog 29, Box 763",
            "phone_number": "08-23 52 50",
            "postgiro": "2087",
            "activity": "Grossisthandel med gardiner o draperier",
            "capital": 270000,
            "key_personnel": [
                {
                    "name": "K Sandberg",
                    "position": "Verkst dir"
                }
            ],
            "establishment_year": 1904
        },
        "11": {
            "company_name": "GRAFIA",
            "activity": "Företaget är försäljningskontor för snickerifabriker",
            "employees": 8,
            "annual_turnover": 4000000,
            "capital": 400000,
            "key_personnel": [
                {
                    "name": "John E Bolling",
                    "position": "Verkst dir"
                }
            ],
            "establishment_year": 1969
        },
        "12": {
            "company_name": "GOTLÄNDSKA LÅNT-MÄNNENS CENTRAL. FÖRENING",
            "pnr": "62101",
            "address": "Visby 1, Söderv 8-10",
            "phone_number": "0498-154 50",
            "postgiro": "189094",
            "activity": "Spannmål, foder- o gödselmedel, fröer o utsäden, maskiner, byggnadsvaror, drivmedel, kemikalier mm",
            "employees": 212,
            "annual_turnover": 88500000,
            "key_personnel": [
                {
                    "name": "Arne Rabne",
                    "position": "Verkst dir"
                }
            ],
            "establishment_year": 1906
        },
        "13": {
            "company_name": "GOTTHARD AB HERMAN GOTTHARDT",
            "pnr": "20040",
            "address": "Malmö 8, Trelleborgsv 12-14",
            "phone_number": "040-800 80",
            "telex": "32250 GOTHARD S",
            "activity": "Tillverkare o grossist. Båtartiklar, stållinor med tillbehör, mattor, flaggor, flätade produkter, tågvirke, plasthallar o motionsredskap",
            "employees": "Ordermottagning, lager o produktion: 232 00 Arlöv, Lommav. Box 45. Tel 040-43 05 20, Avdelningskontor: 411 08 Göteborg, Stora Nyg 13. Tel 031-17 39 80, 11130 Stockholm, Packhusgränd 6. Tel 08-14 02 55",
            "capital": 1500000,
            "key_personnel": [
                {
                    "name": "Karl Almström",
                    "position": "Verkst dir"
                }
            ],
            "establishment_year": 1905
        },
        "14": {
            "company_name": "GOTTLOW KNAPPFABRIK, AB OSCAR",
            "pnr": "24100",
            "address": "Eslöv, Sjöhusv 16, Box 91",
            "phone_number": "0413-105 94, 118 95",
            "bank_details": {
                "bankgiro": "334-9537",
                "postgiro": "6177-0"
            },
            "activity": "Tillverkar dammodeknappar o spännen",
            "employees": 24,
            "annual_turnover": 900000,
            "capital": 75000,
            "key_personnel": [
                {
                    "name": "Kurt Gottlow",
                    "position": "Verkst dir"
                }
            ],
            "establishment_year": 1923
        },
        "15": {
            "company_name": "GOTHUS ANNONSBYRÅ, AB",
            "pnr": "413 01",
            "address": "Göteborg, N Allég 5",
            "phone_number": "031-17 48 30",
            "bank_details": {
                "bankgiro": "10-7612",
                "postgiro": "528505"
            },
            "activity": "Annonsbyrå",
            "employees": 29,
            "annual_turnover": 8000000,
            "capital": 300000,
            "key_personnel": [
                {
                    "name": "Arnold Bergqvist",
                    "position": "Verkst dir"
                }
            ],
            "establishment_year": 1960
        },
        "16": {
            "company_name": "ASSAB MEDICIN AB",
            "pnr": "171 41",
            "address": "Solna, Svets arv 20",
            "phone_number": "08-29 02 45",
            "postgiro": "526066-6",
            "activity": "Tillverkar o säljer laboratorieinredningar samt termostaterade utrustningar för bakteriologiska laboratorier",
            "employees": 11,
            "annual_turnover": 2000000,
            "capital": 495000,
            "key_personnel": [
                {
                    "name": "Erik Albertsson",
                    "position": "Verkst dir"
                }
            ],
            "establishment_year": 1959
        }
    }
}