{
    "original": "FAXES FABRIKS AB\n\nPnr 330 26\n\nSmålands Burseryd. Tel 0371-\n\n500 08. Tga Faxes\nVerksamhet: Tillverkar\nkultivato-rer, allt i byggnadssmide även\ngalvat\n\nAktiekapital: 70 000\nVerkst dir: Lars Davidsson\nEtableringsår: 1949.\n\nSYLWANDER AB,GEORG\n\nPnr 115 37\n\nStockholm, Lidingö v 75. Tel\n08-67 07 00. Tga Sylwex\nVerksamhet: Säljer\nelektronikprodukter\n\nAntal anställda: 20\nAktiekapital: 100 000\nVerkst dir: Civiling Stig Jakobson\nEtableringsår: 1947.\n\nSEV\n\nSEVERINS KONTORS.\nPRODUKTER AB\n\nPnr 126 02\n\nHägersten 2, Box 234. Hägerstens v\n269. Tel 08-46 22 30, 46 22 32\nVerksamhet: Kontorsartiklar o\ntrycksaker, kontorsplast, papper o\ntrycksaker\nAktiekapital: 5 000\nVerkst dir. Gösta Wigerman\nEtableringsår 1920.\n\nSPÅ\n\nBox 46. Tel 08-47 25 40. Bankgiro\n642-2034. Postgiro 55930-2. Telex\n17599\n\nVerksamhet: Tillverkar skruv- o\nkuggväxlar\nAktiekapital: 200 000\nVerkst dir: I Ramnhagen\nEtableringsår: 1948.\n\nFROMELLS VERKSTÄDER, AB\n\nPnr 852 47\n\nSundsvall, Montörv. Tel\n060-15 03 20. Bankgiro 180-1125.\nPostgiro 271752-8\n\nVerksamhet: Beställningsarbeten.\nTillverkar plåtfack, pulpeter,\nur-vattnare, cisterner av stål o\nsyrafast material, järnkonstruktioner,\nstödben för trailers, sopcontainers\n4-30 kbm mm\nAntal anställda: 43\nÅrsomsättning: 3 000 000\nAktiekapital: 100 000\nVerkst dir: Ivar Fromell\nV verkst dir: Ing Kurt Fromell\nVerkstadschef: Ing Ingemar Sjöbom\nEtableringsår: 1900.\n\nSUNDSVALLS TIDNINGS AB\n\nPnr 85106\n\nSundsvall 1, Trädgårdsg 27-29.\nBox 467. Tel 060-12 33 00.\nBankgiro 774-4501. Postgiro 72480-7,\n807900-6. Tga Tidningen.\nTelex 71055, 71056\nVerksamhet: Tidningsutgivning\nAntal anställda: 171\nÅrsomsättning: 11400 000\nAktiekapital: 360 000\nStyrelse: Chefred Yngvar Alström\n(ordf), dir Bror E Berg,boktr Nils\nWide\n\nVerkst dir: Bror E Berg\nEtableringsår: 1841.\n\nSUNDSVALLS VERK.\nSTÄDER, AB\n\nPnr 85101\n\nSundsvall 1, Fack. Fabriksg. Tel\n060-1557 40. Bankgiro 774-4881.\nPostgiro 24174-5.\nTga Verkstäderna.\nTelex 71260 EMHART S\nVerksamhet: Automatmaskiner för\nglasemballagetill verkning\nFilial: Örebro 3,Fack 3040. Tel\n019-13 05 20. Chef: Övering Gustav\nÅström\n\nFörsäljningskontor:\n\nEmhart Sweden AB. Fack, 85101\nSundsvall 1. Tel 060-15 57 40\nVarunamn: Emhart\nAntal anställda: 850\nÅrsomsättning: 124 000 000\nAktiekapital: 12 000 000\n\nStyrelse: Dir Arvid Hammarskiöld\n(ordf), dir Gottlieb Steiner, adv\nMagnus Lindahl, dir Folke\nLundquist, dir Stig Lundquist, dir David\nMuirhead\n\nVerkst dir: Stig Lundquist\nEkonomidir: Sture Evertsson\nProd-dir: Töre Gran\nKontrollchef: Ole Höe\nInköpschef: Gösta Nygren\nEtableringsår: 1756\nDotterbolag till Emhart\nCorporation, Hartford, Connecticut, USA.\n\nSUNDSVALLS VÄRME &amp;\nSANITET AB\n\nPnr 851 84\n\nSundsvall, Bergsg 24. Tel\n060-15 58 00. Bankgiro 180-2503.\nPostgiro 389069-6\n\nVerksamhet: Entreprenadrörelse\ninom VVS\n\nAvdelningskontor: 113 22 Stockholm\nSigtunag 6. Tel 08-34 95 40\nAntal anstäUda: 80\nÅrsomsättning: 11000 000\nAktiekapital: 15 000\nVerkst dir: Göran Källqvist\nDisp: Bengt Fahlström\nEtableringsår: 1948\nKoncernföretag till Byggnads AB\nHallström &amp; Nisses, Sundsvall.\n\nSUNDSVALLSBANKEN\n\nPnr 851 01\n\nSundsvall 1, Kyrkog 15. Fack. Tel\n060-12 34 00. Telex 71047 SUB S.\nTga Sundsvallbanken\nAntal anstäUda: 426\nAktiekapital: 35 525 000\nVerkst dir; Bankdir Harald\nWestling\n\nEtableringsår: 1864.\n\nORE LAND, AB\n\nPnr 26120\n\nLandskrona 1, Fack. Tel\n0418-150 00, 150 55. Bankgiro 660-2965.\nPostgiro 575490-8.\nTelex 72209 BROKER S\nVerksamhet: Skärande verktyg från\nledande utländska verk\nAktiekapital: 100 000\nVerkst dir: Håkan Zätterström\nEtableringsår: 1966.\n\nEKBERG, TEXTIL AB M&amp;S\n\nPnr 28101\n\nHässleholm 1, Vattug 18. Box 176.\nTel 0451-118 28, 109 28. Bankgiro\n270-1399. Postgiro 93266-5\nVerksamhet: Tillverkar klänningar,\nrockklänningar, förkläden, dam- o\nflickpyjamas, nattlinnen o\nsovroc-kar i bomull\nAntal anställda: 28\nÅrsomsättning: 1500 000\nAktiekapital: 30 000\nVerkst dir: Sture Ekberg\nLagerchef: Thorsten Nilsson\nEtableringsår: 1948.\n\nAHLGREN AB, NILS\n\nPnr 11130\n\nStockholm, Skeppsbron 32. Tel\n08-23 16 75. Bankgiro 28-3805.\nPostgiro 57030. Tga Ahlgrenjern.\nTelex 10367\n\nVerksamhet: Grossist- o\nagentur-rörelse med järn, stål, plåt samt\njärnmanufaktur för\nbyggnadsindustrin såsom spik, nät, kätting o\njärntråd\n\nAntal anställda: 18\nAktiekapital: 200 000\nStyrelse: Överste C Alsterlund\n(ordf), dir H Nicklasson, disp P\nSamuelsson, fru B Nicklasson\nVerkst dir: Harry Nicklasson\nEtableringsår: 1934.\n\nAHLGREN MEK VERKSTAD\nAB, P\n\nPnr 11638\n\nStockholm, Malmgårds v 24. Tel\n08-42 48 78. Postgiro 355105\nVerksamhet: Tillverkar geoteknisk\nutrustning. Utför legoarbeten\nAktiekapital: 20 000\nVerkst dir: P Ahlgren\nEtableringsår: 1949.\n\nAHLGRENS MEK VERKSTAD\nAB, THOR\n\nPnr 560 10\n\nSkillingaryd, Fåglabäcksv. Box 10.\nTel 0370-70075. 709 75. Bankgiro\n14-1360. Postgiro 29238\nVerksamhet: Tillverkar dragna,\nbockade o stansade massartiklar.\nSpecialitet: underläggsbrickor,\nmutter- o nitbrickor, tryckerimärlor\no kartongklammer\nAntal anställda: 28\nAktiekapital: 160 000\nVerkst dir: Werner Ahlgren\nEtableringsår: 1918.\n\nHAL\n\nHALLBERGS BOKHANDEL AB\n\nPnr 80102\n\nGävle 1, N Slottsg 6. Box 76. Tel\n026-1241 21, 124221. Bankgiro\n603-5372. Postgiro 22349-5\nVerksamhet: Bok- o pappershandel\nAktiekapital: 10 000\nVerkst dir: Björn G Hallberg\nEtableringsår: 1926.",
    "structured": {
        "firms": [
            {
                "company_name": "FAXES FABRIKS AB",
                "pnr": "330 26",
                "address": "Smålands Burseryd",
                "phone_number": "0371-500 08",
                "activity": "Tillverkar kultivatorer, allt i byggnadssmide även galvat",
                "capital": 70000,
                "key_personnel": [
                    {
                        "name": "Lars Davidsson",
                        "position": "Verkst dir"
                    }
                ],
                "establishment_year": 1949
            },
            {
                "company_name": "SYLWANDER AB,GEORG",
                "pnr": "115 37",
                "address": "Stockholm, Lidingö v 75",
                "phone_number": "08-67 07 00",
                "activity": "Säljer elektronikprodukter",
                "employees": 20,
                "capital": 100000,
                "key_personnel": [
                    {
                        "name": "Civiling Stig Jakobson",
                        "position": "Verkst dir"
                    }
                ],
                "establishment_year": 1947
            },
            {
                "company_name": "SEVERINS KONTORS. PRODUKTER AB",
                "pnr": "126 02",
                "address": "Hägersten 2, Box 234, Hägerstens v 269",
                "phone_number": "08-46 22 30, 46 22 32",
                "activity": "Kontorsartiklar o trycksaker, kontorsplast, papper o trycksaker",
                "capital": 5000,
                "key_personnel": [
                    {
                        "name": "Gösta Wigerman",
                        "position": "Verkst dir"
                    }
                ],
                "establishment_year": 1920
            },
            {
                "company_name": "SPÅ",
                "address": "Box 46",
                "phone_number": "08-47 25 40",
                "bank_details": {
                    "bankgiro": "642-2034",
                    "postgiro": "55930-2"
                },
                "activity": "Tillverkar skruv- o kuggväxlar",
                "capital": 200000,
                "key_personnel": [
                    {
                        "name": "I Ramnhagen",
                        "position": "Verkst dir"
                    }
                ],
                "establishment_year": 1948
            },
            {
                "company_name": "FROMELLS VERKSTÄDER, AB",
                "pnr": "852 47",
                "address": "Sundsvall, Montörv",
                "phone_number": "060-15 03 20",
                "bank_details": {
                    "bankgiro": "180-1125",
                    "postgiro": "271752-8"
                },
                "activity": "Beställningsarbeten. Tillverkar plåtfack, pulpeter, ur-vattnare, cisterner av stål o syrafast material, järnkonstruktioner, stödben för trailers, sopcontainers 4-30 kbm mm",
                "employees": 43,
                "annual_turnover": 3000000,
                "capital": 100000,
                "key_personnel": [
                    {
                        "name": "Ivar Fromell",
                        "position": "V verkst dir"
                    },
                    {
                        "name": "Ing Kurt Fromell",
                        "position": "Verkstadschef"
                    }
                ],
                "establishment_year": 1900
            },
            {
                "company_name": "SUNDSVALLS TIDNINGS AB",
                "pnr": "85106",
                "address": "Sundsvall 1, Trädgårdsg 27-29, Box 467",
                "phone_number": "060-12 33 00",
                "bank_details": {
                    "bankgiro": "774-4501",
                    "postgiro": "72480-7, 807900-6"
                },
                "activity": "Tidningsutgivning",
                "employees": 171,
                "annual_turnover": 11400000,
                "capital": 360000,
                "key_personnel": [
                    {
                        "name": "Chefred Yngvar Alström",
                        "position": "Styrelse ordf"
                    },
                    {
                        "name": "Bror E Berg",
                        "position": "Verkst dir"
                    }
                ],
                "establishment_year": 1841
            },
            {
                "company_name": "SUNDSVALLS VERK. STÄDER, AB",
                "pnr": "85101",
                "address": "Sundsvall 1, Fack. Fabriksg",
                "phone_number": "060-1557 40",
                "bank_details": {
                    "bankgiro": "774-4881",
                    "postgiro": "24174-5"
                },
                "activity": "Automatmaskiner för glasemballagetill verkning",
                "employees": 850,
                "annual_turnover": 124000000,
                "capital": 12000000,
                "key_personnel": [
                    {
                        "name": "Dir Arvid Hammarskiöld",
                        "position": "Styrelse ordf"
                    },
                    {
                        "name": "Gottlieb Steiner",
                        "position": "Styrelse dir"
                    },
                    {
                        "name": "adv Magnus Lindahl",
                        "position": "Styrelse dir"
                    },
                    {
                        "name": "Folke Lundquist",
                        "position": "Styrelse dir"
                    },
                    {
                        "name": "Stig Lundquist",
                        "position": "Styrelse dir"
                    },
                    {
                        "name": "David Muirhead",
                        "position": "Styrelse dir"
                    }
                ],
                "establishment_year": 1756
            },
            {
                "company_name": "SUNDSVALLS VÄRME & SANITET AB",
                "pnr": "85184",
                "address": "Sundsvall, Bergsg 24",
                "phone_number": "060-1558 00",
                "bank_details": {
                    "bankgiro": "180-2503",
                    "postgiro": "389069-6"
                },
                "activity": "Entreprenadrörelse inom VVS",
                "employees": 80,
                "annual_turnover": 11000000,
                "capital": 15000,
                "key_personnel": [
                    {
                        "name": "Göran Källqvist",
                        "position": "Verkst dir"
                    },
                    {
                        "name": "Bengt Fahlström",
                        "position": "Disp"
                    }
                ],
                "establishment_year": 1948
            },
            {
                "company_name": "SUNDSVALLSBANKEN",
                "pnr": "85101",
                "address": "Sundsvall 1, Kyrkog 15. Fack",
                "phone_number": "060-123400",
                "activity": "Bank",
                "employees": 426,
                "capital": 35525000,
                "key_personnel": [
                    {
                        "name": "Bankdir Harald Westling",
                        "position": "Verkst dir"
                    }
                ],
                "establishment_year": 1864
            },
            {
                "company_name": "ORE LAND, AB",
                "pnr": "26120",
                "address": "Landskrona 1, Fack",
                "phone_number": "0418-150 00, 150 55",
                "bank_details": {
                    "bankgiro": "660-2965",
                    "postgiro": "575490-8"
                },
                "activity": "Skärande verktyg från ledande utländska verk",
                "capital": 100000,
                "key_personnel": [
                    {
                        "name": "Håkan Zätterström",
                        "position": "Verkst dir"
                    }
                ],
                "establishment_year": 1966
            },
            {
                "company_name": "EKBERG, TEXTIL AB M&S",
                "pnr": "28101",
                "address": "Hässleholm 1, Vattug 18. Box 176",
                "phone_number": "0451-118 28, 109 28",
                "bank_details": {
                    "bankgiro": "270-1399",
                    "postgiro": "93266-5"
                },
                "activity": "Tillverkar klänningar, rockklänningar, förkläden, dam- o flickpyjamas, nattlinnen o sovrockar i bomull",
                "employees": 28,
                "annual_turnover": 1500000,
                "capital": 30000,
                "key_personnel": [
                    {
                        "name": "Sture Ekberg",
                        "position": "Verkst dir"
                    },
                    {
                        "name": "Thorsten Nilsson",
                        "position": "Lagerchef"
                    }
                ],
                "establishment_year": 1948
            },
            {
                "company_name": "AHLGREN AB, NILS",
                "pnr": "11130",
                "address": "Stockholm, Skeppsbron 32",
                "phone_number": "08-23 16 75",
                "bank_details": {
                    "bankgiro": "28-3805",
                    "postgiro": "57030"
                },
                "activity": "Grossist- o agenturrörelse med järn, stål, plåt samt järnmanufaktur för byggnadsindustrin såsom spik, nät, kätting o järntråd",
                "employees": 18,
                "capital": 200000,
                "key_personnel": [
                    {
                        "name": "Överste C Alsterlund",
                        "position": "Styrelse ordf"
                    },
                    {
                        "name": "dir H Nicklasson",
                        "position": "Styrelse dir"
                    },
                    {
                        "name": "P Samuelsson",
                        "position": "disp"
                    }
                ],
                "establishment_year": 1934
            },
            {
                "company_name": "AHLGREN MEK VERKSTAD AB, P",
                "pnr": "11638",
                "address": "Stockholm, Malmgårds v 24",
                "phone_number": "08-42 48 78",
                "bank_details": {
                    "postgiro": "355105"
                },
                "activity": "Tillverkar geoteknisk utrustning. Utför legoarbeten",
                "capital": 20000,
                "key_personnel": [
                    {
                        "name": "P Ahlgren",
                        "position": "Verkst dir"
                    }
                ],
                "establishment_year": 1949
            },
            {
                "company_name": "AHLGRENS MEK VERKSTAD AB, THOR",
                "pnr": "560 10",
                "address": "Skillingaryd, Fåglabäcksv. Box 10",
                "phone_number": "0370-70075, 709 75",
                "bank_details": {
                    "bankgiro": "14-1360",
                    "postgiro": "29238"
                },
                "activity": "Tillverkar dragna, bockade o stansade massartiklar. Specialitet: underläggsbrickor, mutter- o nitbrickor, tryckerimärlor o kartongklammer",
                "employees": 28,
                "capital": 160000,
                "key_personnel": [
                    {
                        "name": "Werner Ahlgren",
                        "position": "Verkst dir"
                    }
                ],
                "establishment_year": 1918
            },
            {
                "company_name": "HALLBERGS BOKHANDEL AB",
                "pnr": "80102",
                "address": "Gävle 1, N Slottsg 6. Box 76",
                "phone_number": "026-1241 21, 124221",
                "bank_details": {
                    "bankgiro": "603-5372",
                    "postgiro": "22349-5"
                },
                "activity": "Bok- o pappershandel",
                "capital": 10000,
                "key_personnel": [
                    {
                        "name": "Björn G Hallberg",
                        "position": "Verkst dir"
                    }
                ],
                "establishment_year": 1926
            }
        ]
    }
}