{
    "original": "ANDERSSON &amp; LUNDQVIST AB\n\nPnr 80107\n\nGävle 1, Box 556. Drottningg. 48.\nTel 026-18 03 00. Bankgiro\n783-8402. Postgiro 27095-9. Tga\nLund-qvists. Telex 81039, 81049\nVerksamhet: Auktoriserad\nskeppsklarerare, spedition,\nmagasineringar, sjöförsäkringar, linje- o\ntrampbefraktning samt resebyrån\nverksamhet\n\nDotterbolag: 801 07 Gävle 1. A &amp; L\nResebyrå AB, Nyg 25. Box 556.\nTel 026-18 03 00\n\n81100 Sandviken. A &amp; L Resebyrå\nAB. Hyttg 16. Tel 026-25 5050\nAntal anställda: 53\nAktiekapital: 600 000\nStyrelse: Skeppsredare Emanuel\nHögberg (ordf), konsul Karl-Erik\nHögberg, dir Curt Högberg, dir\nFolke Lindahl, dir Herbert\nGabrielson, disp Ake Bengtzon, ing Stig\nGabrielson\n\nVerkst dir: Konsul Karl-Erik\n\nHögberg\n\nSpeditionsavdelning: Dir Kjell\n\nStenberg\n\nBefraktningsavdelning: Befraktare\nKurt Edwall\n\nResebyråerna: Resebyråchef\nCarl-Eric Sälgö\nEtableringsår: 1887.\n\nANDERSSONS MARK &amp;\nTRÄD-GÄRDSPLANERING AB,\nBRÖDERNA\n\nPnr 17135\n\nSolna. Backv 4. Tel 08-82 29 21.\nBankgiro 23-9305. Postgiro 582034\nVerksamhet: Mark- o\nträdgårdsplanering\n\nAntal anställda: 25\nÅrsomsättning: 1000 000\nAktiekapital: 35 000\nVerkst dir: B Arne Andersson\nEtableringsår: 1956.\n\nSVE\n\nFörsäljningskontor: Västra\nFrölunda, Galeasg 37. Tel 031-29 6605\nÅrsomsättning: 2 000 000\nAktiekapital: 45 000\nVerkst dir: Lars Erie Häggström\nEtableringsår: 1964.\n\nSVENSKA TURIST.\nFÖRENINGEN\n\nPnr 103 80\n\nStockholm 7, Stureplan 2. Fack.\nTel 08-22 7200. Tga\nTuristförening. Telex 17760 STF S\nVerksamhet; Resebyrå.\nFjällanläggningar. Vandrarhem\nGeneralsekr: Halvar Sehlin\nDir: Finn Allertz\nEtableringsår 1885.\n\nWÄRNLING, MASKINFIRMA A\n\nPnr 101 33\n\nStockholm 1, Box 911. Upplandsg\n14. Tel 08-110911, 11 0929\nVerksamhet: Agenturfirma för\nverktygsmaskiner. Säljer svarvar,\nfräsmaskiner, arborrverk o borrmaskiner\nÅrsomsättning: 3 000 000\nChef: g A Wärnling\nEtableringsår: 1965.\n\nFERM &amp; PERSSON AB\n\nPnr 421 02\n\nVästra Frölunda 2. Fröfästeg 12.\nFack. Tel 031-450100.\nBankgiro 42-0054. Postgiro 12231. Tga\nFermpersson\n\nVerksamhet: Säljer planglas en\ngros. Glasmästeri. Tillverkar\ndörrar, fönsterpartier av metaller\nAntal anställda: 140\nÅrsomsättning: 11500 000\nAktiekapital: 696 000\nVerkst dir: Bertil Persson\nEtableringsår: 1894\nOmbildat till aktiebolag 1897.\n\nFERNGRENS\nVERKTYGSFABRIK AB, K A\n\nPnr 76100\n\nNorrtälje, Vegag3. Tel 0176-103 90.\nBankgiro 23-1817. Postgiro\n29235-9. Tga Ferngrens\nVerksamhet: Tillverkar brotschar,\nfräsar o gängverktyg\nAntal anställda: 25\nAktiekapital: 100 000\nVerkst dir: K A Ferngren\nEtableringsår: 1917.\n\nWENNERBERG, HARALD\n\nPnr 411 17\n\nGöteborg C, V Hamng 5. Tel\n031-13 2017, 13 28 91. Bankgiro\n50-0582. Postgiro 41548. Telex 2306.\nTga Haraldus\n\nVerksamhet: Säljer som grossist\nträfiberplattor, plywood,\nspånski-vor, plastlaminat, ädelträpaneler,\nträvikdörrar, plastfolie, takmaterial\nAntal anställda: 6\nChef: Harald Wennerberg\nKontorschef: Nils Stenborg\nKamrer: Stig Andersson\nEtableringsår: 1913-\n\nSÖDERTÄLJE SKROT AB\n\nPnr 15103\n\nSödertälje 3, Oxelgrensv 25. Box\n3005. Tel 0755-32144. Postgiro\n279537\n\nVerksamhet: Köper o säljer\njärn-o metallskrot\nAntal anställda: 5\nÅrsomsättning: 1000 000\nAktiekapital: 15 000\n\nStyrelse: Disp Fritz Andersson\n(ordf), kamrer Rig Hertzman\nVerkst dir: Disp Fritz Andersson\nFöreståndare: Sven Dackevall\nEtableringsår: 1961.\n\nLÄTTBETONG, AB\n\nPnr 100 54\n\nStockholm 39, Midskogs gränd 13.\nBox 39039. Tel 08-63 10 80. Telex\n10371. Tga Laettbetong\nVerksamhet: Försäljningsbolag\nför Siporex o Ytong\nAvdelningskontor: Stockholm,\nMid-skogsgränd 13. Box 39039, 100 54\nSthlm 39. Tel 08-63 10 80. Telex\n10371\n\nGöteborg.Mölndalsv 25.Box 14022.\n400 20 Göteborg 14. Tel\n031-8105 00. Telex 2556\nMalmö, Regementsg 50. Fack 5021,\n200 71 Malmö 5. Tel 040-714 80.\nTelex 3322\n\n70212 Örebro, Oskarsparken 1.\nTel 019-13 04 70. Telex 73236\nSundsvall. Storg 10. Box 349,\n85105 Sundsvall 1. Tel\n060-15 78 50. Telex 71057\n932 00 Skelleftehamn, N Hamng 51.\nTel 0910-331 10. Telex 6837\nVarunamn: Siporex, Ytong\nAntal anställda: 325\nÅrsomsättning: 199 500 000\nVerkst dir: E Gustafsson\nEtableringsår: 1958.\n\nSPANSET AB\n\nPnr 20120\n\nMalmö 1, Norbergsg 22. Box 4. Tel\n040-928801, 803 10. Bankgiro\n130-1456. Postgiro 634343-8. Tga\nSpan-set. Telex 32324\nVerksamhet: Tillverkning av\nlyft-sling, stroppar o surrningar av\nsyntetfibermaterial för industri o\nsjöfart\n\nVarunamn: Sp an Set\nAntal anställda: 20\nÅrsomsättning: 3 000 000\n.Aktiekapital: 100 000\nVerkst dir: Ake Röing\nEtableringsàr: 1967.\n\nSPARBANKERNAS BANK AB\n\nPnr 102 61\n\nStockholm 4, Peter Myndes backe\n12-14. Box 4049. Tel 08-229160.\nBankgiro 980-0012. Postgiro\n39050-0\n\nVerksamhet: Bankrörelse\nAntal anställda: 276\nAktiekapital: 45 000 000\nVerkst dir: S Lindblad\nEtableringsån 1942.\n\nSPARBANKERNASINTECK.\nNINGSAKTIEBOLAG\n\nPnr 116 46\n\nStockholm, Peter Myndes backe 12.\nTel 08-229160. Bankgiro 980-0103.\nPostgiro 149800-5\nVerksamhet: Lämnar o förmedlar lån\nmot inteckning i fast egendom eller\ntomträtt samt lämnar\nbyggnadskre-ditiv. Upplånar för verksamheten\nerforderliga medel genom utgivande\nav obligationer eller andra\nförskrivningar\n\nAntal anställda: 80\nAktiekapital: 25 000 000\nStyrelse: H Allard (ordf), P J\nLindgren, S Lindblad, R Ivestedt, G\nOj de, K Tham, K Haeffner-P\nlodman, S Ek, R Duvebäck\nVerkst dir: R Ivestedt\nEtableringsàr: 1885.\n\nSPARFRÄMJANDET\nFOR-LAGSAKTIEBOLAGET\n\nPnr 103 20\n\nStockholm 16, Drottningg 29. Pack.\nTel 08-14 1020. Bankgiro 980-0137.\nPostgiro 30400-6\n\nVerksamhet: Serviceorgan för\nsparbankerna. Bedriver förlags- o\nreklamverksamhet\nAntal anställda: 45\nÅrsomsättning: 12 000 000\nAktiekapital: 200 000\nVeikst dir: Torbjörn Hessling\nEtableringsàr: 1942.\n\nSPARMAN-FABRIKEN AB\n\nPnr 590 50\n\nVikingstad. Box 9. Tel 013-80275.\nBankgiro 276-5535. Postgiro\n269693-8\n\nVerksamhet: Tillverkar\ntransportörer för industrin, varuhantering o\nlantbruk. Halmskärare för lantbruk\nVarunamn: Sparman\nAntal anställda: 40\nÅrsomsättning: 3000 000\nAktiekapital: 50 000\nDisp: Arne Anstérus\nEtableringsån 1942.\n\nSPARRING HYLLINRED.\nNINGAR AB\n\nPnr 114 23\n\nStockholm, Körsbärsv 7. Tel\n08-1503 25. Bankgiro 160-7548.\nPostgiro 51077-6. Tga Sparrkonsol\nVerksamhet: Tillverkar\nsparrkon-soler, väggskenor mm för hy\n11-inredningar till bibliotek, hem,\nkontor, butiker etc\nAktiekapital: 900000\nVerkst dir: Pru Ulla Spaning\nEtableringsàr: 1929.\n\nSPAR.TRIKÄ AB\n\nPnr 500 04\n\nBorås 4, N Sjöbog 56. Box 44082.\nTel 033-13 61 90. Bankgiro\n531-2020. Postgiro 360837-9\nVerksamhet: Tillverkar\njerseyvävnader i metervara för\nkonfektionsindustrin\n\nAntal anställda: 50\nÅrsomsättning: 13 000 000\nAktiekapital: 750 000\nVerkst dir. Hans Orreving\nEtableringsàr: 1947.\n\nSPECERISTERNAS\nVARU-INKUP, AB\n\nPnr 12109\n\nJohanneshov 9, Partihandlarv 47.\nBox 9020. Tel 08-8100 00. Tga\nTga Esve-bolaget.\nTelex 1435 ICA S\nVerksamhet: Livsmedel, textil o\njärnvaror i parti\nDistributionscentraler\nStockholm:\n\nKolonialvaror, bröd, frukt o\ngrönsaker:\n\n12109 Johanneshov 9,\nPartihandlarv 47. Box 9020. Arstaområdet.\nTel 08-8100 00\n\nKött- o charkvaror, djupfrysta varor:\n12121 Johanneshov 1, Hall v 35-37.\nBox 28. Tel 08-8100 00\nChef: Disp Lennart Samuelsson\nÖstergötland:\n\nKolonialvaror, textil- o järnvaror:\n600 08 Norrköping 8, Pinspångsv\n63. Box 8006. Tel 011-134270\nFärskvaror:\n\n58103 Linköping 1, Industrig 15.\nBox 335. Tel 013-12 9190\nChef: Disp Osten Stymne\nGotland: 62101 Visby 1, Donnersg\n2. Box 111. Tel 0498-152 70\nChef: Disp Lars Lundh\nAntal anställda: 402\nÅrsomsättning: 327 500 000\nAktiekapital: 5 600 000\nVerkst dir: Lars Elford\nEtableringsàr: 1922\nAnslutet till ICA.\n\nSPECIALKAROSSER AB\n\nPnr 310 61\n\nÄtran. Tel 0346-602 60\nVerksamhet: Tillverkar karosser i\nplast o aluminium\nAntal anställda: 25\nÅrsomsättning: 2 000 000\nAktiekapital: 20 000\nVerkst dir: Kent Andersson\nEtableringsàr: 1967.\n\nSPECIALMASKINER I\nGOTEBORG AB\n\nPnr 40125\n\nGöteborg 1, Fröodlareg 7. Box 336.\nTel 031-45 0 3 60. Bankgiro 51-1568.\nPostgiro 12082. Tga Specma.\nTelex 20748\n\nVerksamhet: Maskinpackningar,\ngummislangar. Elverktyg,\ntryck-luftverktyg. Maskiner o utrustning\nför fartygsbygge o fartygsdrift.\nSpånavskiljande verktygsmaskiner,\nrörbockningsmasklner,\nplåtbearbet-ràngsmaskiner. Stålgjutgods o\nsmiden, rör o rörmanufaktur.\nElektr-mo-torer, generatorer, transformatorer,\nlikriktare o brytare, elektronik\nFilialkontor: 104 62 Stockholm 17,\nRosenlundsg 17. Box 17001. Tel\n08-24 68 50. Tga Specma. Dir: J\nLindmark\n\nAktiekapital: 300 000\nVerkst dir: Mats Lindmark\nEtableringsàr: 1919.\n\nSPECIAL.METALL och\nAPPARATER AB\n\nPnr 117 21\n\nStockholm, Hornsg 72. Tel\n08-69 85 50. Bankgiro 482-0478.\nPost-giro 155970-7. Tga Specialmetall\nVerksamhet: Testutrustningar,\nklimatskåp, laboratorieapparater\nAktiekapital: 10 000\nVerkst dir: ing Gunnar Samuelsson\nEtableringsàr: 1939.\n\nSPECIALPAPPER, AB\n\nPnr 125 02\n\nÄlvsjö 2, Turingev 59. Box 2015.\nTel 08-47 24 75, 47 34 75. Bankgiro\n744-3765. Postgiro 276640-0.\nTga Specialpapper\nVerksamhet: Tillverkning o\nförsäljning av papper för registrerande\ninstrument i rullar o blad.\nSpecialitet: färdskrivarediagram, vaxade\no strömförande registreringspapper,\nsilikonpapper\nAntal anställda: 25\nÅrsomsättning: 2 500000\nAktiekapital: 100 000\nVerkst dir: Dr Adolf E Wirma\nEtableringsån 1944.\n\nparfum lombard ab\n\nPnr 200 31\n\nMalmö 15, Box 15016.\nBotilden-borgsv 21. Tel 040-94 20 40.\nBankgiro 641-3587. Postgiro 39188-8\nVerksamhet: Tillverkar kem tekn\nartiklar. Grosshandel. Lönfyllning\nav aerosoler\nVarunamn: Chrie\nAntal anställda: 20\nÅrsomsättning: 2000 000\nAktiekapital: 35 000\nVerkst dir: Gustav Mårtensson\nEtableringsår: 1936.\n\nHCJ BILUTHYRNING AB\n\nPnr 430 30\n\nFrillesås, Box 106. Tel\n0340-504 50. Bankgiro 505-7245.\nPostgiro 47380-1\n\nVerksamhet: Tillverkar bilklädslar,\nfårskinnssitsar, bilplädar,\nbilkuddar, värmesitsar, elektr\nsitsar, nackstöd, bilmattor,\ninnertak, sitsskydd, skärmskydd,\ntoppkapell, formsydda garage\nAffär o kontor: 417 05 Götebcrg,\nGustaf Dalénsg 8. Tel 031-23 55 86,\n23 55 87, 23 55 88\nAntal anställda: 25\nÅrsomsättning: 3 000 000\nVerkst dir: Hilding Johansson\nEtableringsår: 1945.",
    "structured": {
        "1": {
            "company_name": "ANDERSSON & LUNDQVIST AB",
            "address": "Gävle 1, Box 556. Drottningg. 48.",
            "phone_number": "026-18 03 00",
            "bank_details": {
                "bankgiro": "783-8402",
                "postgiro": "27095-9"
            },
            "activity": "Auktoriserad skeppsklarerare, spedition, magasineringar, sjöförsäkringar, linje- o trampbefraktning samt resebyrån verksamhet",
            "employees": 53,
            "capital": 600000,
            "key_personnel": [
                {
                    "name": "Skeppsredare Emanuel Högberg",
                    "position": "ordf"
                },
                {
                    "name": "konsul Karl-Erik Högberg",
                    "position": ""
                },
                {
                    "name": "dir Curt Högberg",
                    "position": ""
                },
                {
                    "name": "dir Folke Lindahl",
                    "position": ""
                },
                {
                    "name": "dir Herbert Gabrielson",
                    "position": ""
                },
                {
                    "name": "disp Ake Bengtzon",
                    "position": ""
                },
                {
                    "name": "ing Stig Gabrielson",
                    "position": ""
                },
                {
                    "name": "Konsul Karl-Erik Högberg",
                    "position": "Verkst dir"
                },
                {
                    "name": "Dir Kjell Stenberg",
                    "position": "Speditionsavdelning"
                },
                {
                    "name": "Befraktare Kurt Edwall",
                    "position": "Befraktningsavdelning"
                },
                {
                    "name": "Resebyråchef Carl-Eric Sälgö",
                    "position": "Resebyråerna"
                }
            ],
            "establishment_year": 1887
        },
        "2": {
            "company_name": "ANDERSSONS MARK & TRÄD-GÄRDSPLANERING AB, BRÖDERNA",
            "address": "Solna. Backv 4.",
            "phone_number": "08-82 29 21",
            "bank_details": {
                "bankgiro": "23-9305",
                "postgiro": "582034"
            },
            "activity": "Mark- o trädgårdsplanering",
            "employees": 25,
            "capital": 35000,
            "key_personnel": [
                {
                    "name": "B Arne Andersson",
                    "position": "Verkst dir"
                }
            ],
            "establishment_year": 1956
        },
        "3": {
            "company_name": "SVE",
            "address": "Västra Frölunda, Galeasg 37.",
            "phone_number": "031-29 6605",
            "employees": null,
            "capital": 45000,
            "key_personnel": [
                {
                    "name": "Lars Erie Häggström",
                    "position": "Verkst dir"
                }
            ],
            "establishment_year": 1964
        },
        "4": {
            "company_name": "SVENSKA TURIST. FÖRENINGEN",
            "address": "Stockholm 7, Stureplan 2. Fack.",
            "phone_number": "08-22 7200",
            "activity": "Resebyrå. Fjällanläggningar. Vandrarhem",
            "employees": null,
            "capital": null,
            "key_personnel": [
                {
                    "name": "Halvar Sehlin",
                    "position": "Generalsekr"
                },
                {
                    "name": "Finn Allertz",
                    "position": "Dir"
                }
            ],
            "establishment_year": 1885
        },
        "5": {
            "company_name": "WÄRNLING, MASKINFIRMA A",
            "address": "Stockholm 1, Box 911. Upplandsg 14.",
            "phone_number": "08-110911, 11 0929",
            "activity": "Agenturfirma för verktygsmaskiner. Säljer svarvar, fräsmaskiner, arborrverk o borrmaskiner",
            "employees": null,
            "capital": null,
            "key_personnel": [
                {
                    "name": "g A Wärnling",
                    "position": "Chef"
                }
            ],
            "establishment_year": 1965
        },
        "6": {
            "company_name": "FERM & PERSSON AB",
            "address": "Västra Frölunda 2. Fröfästeg 12. Fack.",
            "phone_number": "031-450100",
            "bank_details": {
                "bankgiro": "42-0054",
                "postgiro": "12231"
            },
            "activity": "Säljer planglas en gros. Glasmästeri. Tillverkar dörrar, fönsterpartier av metaller",
            "employees": 140,
            "capital": 696000,
            "key_personnel": [
                {
                    "name": "Bertil Persson",
                    "position": "Verkst dir"
                }
            ],
            "establishment_year": 1894
        }
    }
}