{
    "original": "SVETSTEKNIK, AB\n\nPnr 421 31\n\nVästra Frölunda, Frörensareg 4.\nTel 031-45 01 15. Bankgiro\n420-1810. Postgiro 241308-6. Tga\n\nSvetstek\n\nVerksamhet: Säljer svetsomformare,\nsvetslikriktare,\nsvetstransformato-rer, halvautomater,\npunktsvetsma-skiner, gassvetsutrustningar,\nelektroder, hårdlod, silverlod samt\ntillbehör för svetsning. Uthyrningar o\nreparationer\nAntal anställda: 12\nAktiekapital: 20 000\nVerkst din Ing Enar Axelsson\nEtableringsår 1946.\n\nSWIAB SVENSSON &amp; WOLD\nINDUSTRI AB\n\nPnr 417 03\n\nGöteborg, Vindragareg 14. Tel\n031-2211 15, 23 9135. Bankgiro 40-1650.\nPostgiro 528277\nVerksamhet: Mekanisk service,\nvarv o industri montage\nÅrsomsättning: 3 000 000\nAktiekapital: 5 000\nEtableringsår: 1959.\n\nSWING LTD AB\n\nPnr 81101\n\nSandviken 1, Köpmang 23. Box 9.\nTel 026-25 2470. Bankgiro 78-8754.\nPostgiro 9450. Tga Razor\nVerksamhet: Försäljningsbolag för\nrakblad o rakhyvlar\nÅrsomsättning: 1500 000\nAktiekapital: 50 000\nVerkst dir: Georg Zeidlitz\nEtableringsår: 1926.\n\nmaterialrontgen, ab\n\nPnr 417 07\n\nGöteborg, Stålverksg 4. Tel\n031-2354 45. Bankgiro 420-3816.\nPostgiro 426430-5\n\nVerksamhet: Oförstörande provning\nav svetsade konstruktioner,\nsvetsarekontroll, besiktningar,\nritningsgranskning, tillverkningskontroll.\nSvetsteknisk rådgivning\nFUialer: Stockholm. Tel 08-38 39 39\nMalmö. Tel 040-11 27 97\nGävle. Tel 026-18 55 23\nUddevalla. Tel 0522-187 87\nKarlstad. Tel 054-11 23 80\nOskarshamn. Tel 0491-341 13\nSundsvall. Tel 060-12 69 40\nAntal anstäUda: 60\nVerkst dir: Dlr E Axelsson\nEtableringsår: 1953.\n\nHALLA TEXTIL AB\n\nPnr 510 60\n\nOverlida. Box 25. Tel 0325-320 18.\nBankgiro 55-3004. Postgiro 13737\nVerksamhet: Tillverkar gardiner o\nsängöverkasttyger av bomull\nAntal anställda: 30\nÅrsomsättning: 1000000\nAktiekapital: 130 000\nVerkst dir: Alf Sterner\nEtableringsår: 1910.\n\nHALLABO METALL.\nGJUTERI AB\n\nPnr 330 30\n\nGnosjö. Tel 0370-910 19. Postgiro\n6538\n\nVerksamhet: Tillverkar båtbeslag\no smiden, skeppsklockor mm. Vi\nutställer på Swed-Expo i Värnamo\nAntal anställda: 9\nÅrsomsättning: 600 000\nAktiekapital: 50 000\nVerkst dir: Alf Halidén\nEtableringsår: 1907.\n\nSKO\n\n76512 85. Postgiro 77241-8\nVerksamhet: Skogsvärdering,\nareal-o förrådsinventering, skadereglering\nför kraftledningar o\ndämningsföre-tag. Ägoutbyte o skogliga\nutredningar\n\nEtableringsàr: 1956.\n\nSKOGSÄGARNAS CELLULOSA\nAB\n\nPnr 383 00\n\nMönsterås. Tel 0499-11100.\nBankgiro 85-5618. Postgiro 4529. Telex\n4986 keypulp mss. Tga Keypulp\nVerksamhet: Tillverkar oblekt o\nhalvblekt sulfatmassa\nFörsäljning: Skogsägarnas Industri\nAB, Cellulosaförsäljningen. Pack,\n35101 Växjö 1. Tel 0470-890 00.\nTga Skogcell, Växjö.\nTelex 52031 SKOGCELL S\nAntal anställda: 465\nÅrstillverkning: 185 000 ton\nÅrsomsättning: 150 000 000\nAktiekapital: 50400 000\nVerkst dir: Vakant\nPlatschef: Dir K-P Gustafsson\nTekn chef: Övering Evert Carlhamn\nEtableringsàr: 1952.\n\nSKOGSÄGARNAS INDUSTRI AB\n\nPnr 35101\n\nVäxjö 1. Pack. Tel 0470-890 00.\nBankgiro 66-8258. Postgiro 271675.\nTga Skogcell, SIAB.\nTelex 52031 SKOGCELL S,\n52046 SIAB S\n\nTrämekanisk förvaltning: Tillverkar\nmonteringsfärdiga bostadshus,\npensionärshem, snickerier i Hultsfred;\nspånskivor i Aryd o Laholm. Chef:\nDir Olle Linnell (Växjö)\nSågverksförvaltningen: Tillverkar\nsågat o hyvlat virke, impregnerade\nstolpar o sliprar m m vid ett flertal\nsågverk o impregneringsverk i\nsödra Sverige. Chef: Dir Olle Linnell\n(Växjö)\n\nEmballage gruppen: Tillverkar\nkraftpapper, säckpapper,\npapperssäckar, smörpapper, papper för\nytteremballage i Strömsnäsbruk o\nsulfatmassa i Delary; mekanisk\nmassa, papp, kartong i Fridafors;\nkartonnage i Fridafors; kartonnage,\nbärkassar, påsar, tryckt emballage\ni Kvidinge. Chef: Dir Bengt\nSund-feldt (Strömsnäsbruk)\nCellulosaförvaltning, Mörrums Bruk:\nTillverkar blekt sulfatmassa i\nMörrum. Chef: Dir Karl-Fredrik\nGustafsson (Mönsterås).\nVerksamheten vid Skogsägarnas Cellulosa\nAB, Mönsterås, är samordnad med\nSIAB:s cellulosaförvaltning\nAntal anställda: 4 500\nAktiekapital: 100000 000\nÅrstillverkning: Sägade trävaror\n335 000 ro5. Impregnerat virke\n6 000 m3. Monteringsfärdiga trähus\n3 200 st. Spånskivor 67 000 ton.\nPappersmassa 500 000 ton. Papper\no papp 90 000 ton. Kartonnage o\ntryckt emballagepapper,\nförsäljningsvärde 67 000000\nÅrsomsättning: 697 000 000\nStyrelse: Dir Gösta Edström (ordf),\ngodsägare S G F\nAdlersüema-Adel-sköld, agronom Kjell Bachman,\nriksdagsman Anders Dahlgren, lantbr\nNils Engquist, fil dr Sven\nFagerberg, lantmäst Nils-Gustav\nIder-mark, kommunalråd Helmer Karls-\n\nson, lantbr Sune Svantesson, lantbr\nGustaf Widebrandt\nVerkst dir: Vakant\nEtableringsàr: 1943\nSkogsägarnas Industri AB (SIAB)\nägs av Södra Sveriges Skogsägares\nförbund (SSSF), Växjö.\n\nSKOINDUSTRINS MASKIN AB\n\nPnr 183 03\n\nTäby 3, Maskinv 1. Box 3033. Tel\n08-758 01 00. Bankgiro 62-5669.\nPostgiro 447720. Tga Shoemex\nVerksamhet: Maskiner o tillbehör\nför stansknivstillverkning\nAntal anställda: 40\nÅrsomsättning: 6 000 000\nAktiekapital: 300 000\nVerkst dir: Karl-Erik Danielsson\nEtableringsàr: 1954.\n\nSKOLAST (JÄRRESTAD) AB\n\nPnr 272 00\n\nSimrishamn. Tel 0414-21210.\nBankgiro 373-4670. Tga Skolast.\nTelex 32340 SKOLAST S\nVerksamhet: Tillverkar\nindustriutrustning för gummi- o plastindustrin\nAntal anställda: 50\nÅrsomsättning: 4 000 000\nAktiekapital: 250000\nVerkst dir: Carl A Davidson\nEtableringsàr: 1896.\n\nSKOL-SUNDSTROM AB\n\nPnr 283 00\n\nOsby, Box 82. Modellg 9-11. Tel\n0479-119 60. Bankgiro 281-7096.\nPostgiro 277410-7\nVerksamhet: Säljer inredningar till\nskolor o offentlig miljö\n.Antal anställda: 55\nÅrsomsättning: 14000000\nAktiekapital: 50 000\nVerkst dir: K Georg Sundström\nEtableringsàr: 1957.\n\nSKOLTJÄNST I SÄVSJO AB\n\nPnr 600 06\n\nNorrköping 6, Grundverksg. Box\n6010. Tel 011-10 60 90. Bankgiro\n83-6597. Postgiro 372726-0\nVerksamhet:\nSkolmaterielförsälj-ning\n\nAntal anställda: 17\nAktiekapital: 75 000\nVerkst dir: Bengt Lundbäck\nEtableringsàr: 1955.\n\nSKRIV - ARTIST -\nRIT-MATERIEL AB\n\nPnr 431 35\n\nMölndal, Lyckholmsv 7. Tel\n031-17 06 50, 87 3248. Bankgiro\n420-5589. Postgiro 243155-9\nVerksamhet: säljer finpapper,\nAV-maskiner. ritmaskiner\nAntal anställda: 6\nÅrsomsättning: 1 300 000\nAktiekapital: 15 000\nVerkst dir: Disp Liss Olof Larson\nEtableringsàr: 1910.\n\nSKRIVRIT, AB\n\nPnr 19188\n\nSollentuna 1, Bäckv 18. Fack. Tel\n08-35 27 00. Bankgiro 73-1259.\nPostgiro 2858. Telex 10254 SKRIVRI S\nVerksamhet: Utrustning o inredning\n\ninom utbildningssektorn\n(förbrukningsmateriel, förlagsartiklar,\ninredningar, förskolemateriel samt\naudivisuella hjälpmedel)\nAntal anställda: 440\nÅrsomsättning: 75 000 000\nAktiekapital: 10 000\nVerkst dir: Göran Digmar\nEtableringsàr: 1898.\n\nSKROT- &amp; AVFALLS.\nPRODUKTER\n\nPnr 402 72\n\nGöteborg 8, Tingstad. Box 8880.\nTel 031-22 54 49,23 65 38. Bankgiro\n851-7450. Postgiro 48332-1.\nTga Scrapmetal.\nTelex 2551 IRONMET S\nVerksamhet: Nedskrotning av\nfartyg, köp o försäljning av järn o\nmetaller\n\nÄgare o chef: T Johannisson\nEtableringsàr: 1943.\n\nSKROTKONSULT, AB\n\nPnr 27100\n\nYstad, Stortorget 6. Box 17. Tel\n0411-136 60. Bankgiro 873-1945.\nPostgiro 593461-7. Tga Allanbolag.\nTelex 32299\n\nVerksamhet: Konsulterande\nverksamhet i skrotfrågor\nAktiekapital: 5 000\nVerkst din Allan Nilsson\nEtableringsån 1963.\n\nKOS AB, JOH CD\n\nPnr 420 14\n\nSäve. Box 101. Gullringev. Tel\n031-96 05 20. Bankgiro 852-2682.\nPostgiro 422843-3.\nTelex 20670 KOSAB S\nVerksamhet: Agentur i mattor\nAntal anställda: 30\nÅrsomsättning: 25 000 000\nAktiekapital: 60 000\nVerkst dir. Joh C D Kos\nEtableringsår: 1951.\n\nKOSTA GLASBRUK, AB\n\nPnr 360 52\n\nKosta. Tel 0478-503 00. Bankgiro\n615-7200. Postgiro 7775-0. Tga\nKostabolaget, Växjö\nVerksamhet: Tillverkar\nkristallglas, glas-, metall- o plastarmaturer\nVerkst dir: Erik Rosén\nEtableringsår: 1742.\n\nWENAHUS, AB\n\nPnr 570 82\n\nMålilla 1, Box 68. Tel 0495-208 10.\nBankgiro 268-5717. Postgiro\n330311-2. Tga Wenahus\nVerksamhet: Tillverkar\nmonteringsfärdiga trähus o sågade\nträvaror\n\nAntal anställda: 40\nÅrsomsättning: 3 000 000\nAktiekapital: 42000\nVerkst dir: Arne Casselberg\nEtableringsår: 1946.\n\nLING METALLGJUTERI AB\n\nPnr 330 33\n\nHillers torp. Tel 0370-930 20.\nPostgiro 166890-4\n\nVerksamhet: Tillverkar biltillbehör\nsåsom jordledningar, startkablar mm\nAntal anställda: 5\nÅrsomsättning: 1000 000\nAktiekapital: 15 000\nVeikst dir: Henning Ling\nEtableringsår: 1937.\n\nMÄLARDALENS STÄD AB\n\nPnr 724 60\n\nVästerås, Hammarbyg 5 B. Tel\n021-116139. Bankgiro 279-4196.\nPostgiro 451142-4\n\nVerksamhet: Städentreprenör. Utför\nkontors-, varuhus-, industri-,\nsjukhus- o skolstädningar i Västerås,\nÖrebro, Köping, Arboga, Sala,\nEnköping o Virsbo\nAntal anstäUda: 175\nÅrsomsättning: 1 300 000\nAktiekapital: 15 000\nVerkst dir. Carl-Arvid Högqvist\nEtableringsår 1966.\n\nMÄLARDALENS TEGEL.\nBRUK, AB\n\nPnr 100 41\n\nStockholm 26, Fack. Eriksbergsg\n27. Tel 08-23 33 65. Postgiro\n3581-6. Tga Tegelbolaget\nTegelbruk: Uppsala. Bergsbrunna\nTegelbruk. Tel 018-32 59 16\nFärentuna. Ilända Tegelbruk. Tel\n0756-420 17\n\nStallarholmen. Husby Tegelbruk.\nTel 0152-40061\nAntal anstäUda: 143\nÅrsomsättning: 35 000 000\nAktiekapital: 2 665 500\nStyrelse: Samma som Kooperativa\nFörbundet, se dessa\nVerkst dir. Ing Hans G Enhus\nEtableringsår: 1914.\n\nHÄS\n\nVeikst dlr: Edvard Hässler\nEtableringsår: 1902\nDotterbolag: AB Librex.\n\nHÄSTEN SKOFABRIK AB\n\nPnr 900 05\n\nUmeå 5, Box 5006. Tel 090-11 23 95.\nBankgiro 80-2660. Postgiro 36606-2.\nTga Hästen\n\nVerksamhet: Tillverkar herr-,\ndam-o barnskor\nVarunamn: Hästens\nChefer: Helge Nilsson, Claes\nNilsson\n\nEtableringsår: 1935.\n\nSKYLLBERGS BRUKS AB\n\nPnr 690 45\n\nÅsbro. Tel 0583-403 00. Bankgiro\n819-3641. Postgiro 25870-7\n\nVerksamhet: Tillverkar trådspik,\nriktad tråd, formstag\nAntal anställda: 100\nÅrsomsättning: 12000 000\nAktiekapital: 500 000\nStyrelse: Ståthållare Sixten\nWohl-fahrt (ordf), dir S Gamfeldt, bankdir\nLars Nyrén, bruksdisp Ivan\nSvensson. dlr Gösta Rehnquist\nVerkst dir: Bruksdisp Ivan\nSvensson\n\nFabrikschef: Ing Herbert Schelin\nKontorschef: Företagsekonom\nBirger Wirsén\nEtableringsår: 1876.\n\nSKYLLBÄCK BYGGNADS AB,\nR\n\nPnr 61100\n\nNyköping, V Storg 15. Tel 0155-\n\n12160, 814 40. Bankgiro 619-0912.\n\nPostgiro 379437-7\n\nVerksamhet: Utför reparations- o\n\nbyggnadsarbeten\n\nAntal anställda: 25\n\nÅrsomsättning: 1600 000\n\nAktiekapital: 25000\n\nVerkst dir: Richard Skyllbäck\n\nEtableringsår: 1965.\n\nSKYLTAR &amp; MÄRKEN AB\n\nPnr 14122\n\nHuddinge 1, Förrådsv 4. Box 1069.\nTel 08-711 25 75. Bankgiro\n745-5522. Postgiro 352420-4\nVerksamhet: Tillverkar vägmärken\no reklamskyltar, speciellt med\nreflexverkan. Utför silkscreen. Säljer\navstängningsmateriel för gator o\nvägar, stolpar m m\nAntal anställda: 50\nÅrsomsättning: 6 000 000\nAktiekapital: 100000\nStyrelse: Adv Håkan Utterström\n(ordf), dir Jan Kjerrman, dir\nGunnar Ringdahl\n\nVerkst dir: Gunnar Ringdahl\nEtableringsår: 1953.\n\nSKYLTTJÄNST REKLAM AB\nLILJA &amp; ECKERUD\n\nPnr 582 63\n\nLinköping, Söderleden 22-24. Tel\n013-1042 40, 14 54 95. Bankgiro\n120-3488\n\nVerksamhet: Utför\nutställningsreklam, skyltar, silkscreentryck,\nblickfång o fönsterskyltningar\nAktiekapital: 5 000\nChefer: Hans Lilja, Ove Eckerud\nEtableringsår: 1956\nOmbildat till aktiebolag 1964.\n\nSKYTTORPS SÅG &amp; SNICKERI.\nFABRIK AB\n\nPnr 740 34\n\nSkyttorp. Tel 018-35 22 35. Bankgiro\n802-5066. Postgiro 166420-0\nVerksamhet: Säljer sågade o\nhyvlade trävaror, byggnadssnickerier\nAntal anställda: 80\nÅrsomsättning: 6 000 000\nAktiekapital: 102 000\nStyrelse: Ing Erik Lindgren (ordf),\ndisp Sven Jansson, ing Gunnar\nLindgren, kamrer Göran Lindgren,\nfru Grete Ring\n\nVerkst dir: Ing Erik Lindgren\nEtableringsår: 1941\nOmbildat till aktiebolag 1956.\n\nSKÅNE, AB TEKNISKA\nFABRIKEN\n\nPnr 233 00\n\nSvedala. Tel 040-48 31 39.\nBankgiro 284-9693. Podtgiro 147707-4\nVerksamhet: Tillverkar kem tekn\nartiklar för skoindustri, gummikitt\nVarunamn: Rubber-Seal\nAktiekapital: 40 000\nVerkst dir: Elvir Lilja\nEtableringsår: 1936.\n\nSKÅNES ALLMÄNNA\nRESTAURANG AB SKAR\n\nPnr 203 10\n\nMalmö 4, Baltzarsg 21. Fack. Tel\n040-714 65. Bankgiro 348-2890.\nPostgiro 39451-0\n\nVerksamhet: Hotell- o\nrestaurangrörelser i Skåne o Blekinge\nAntal anställda: 841\nÅrsomsättning: 36644 000\nAktiekapital: 1100 000\nVerkst dir: Walter Johansson\nEtableringsår: 1922.\n\nSKÅNES\nSTADSHYPOTEKS-FÖRENING\n\nPnr 201 20\n\nMalmö 1, Västerg 38. Box 77. Tel\n040-12 4 0 68. Bankgiro 640-2192.\nPostgiro 38960-1\nVerksamhet: Fastighetsbelåning\nAntal anstäUda: 9\nVerkst dir: Jur kand Gunnar\nThuren\n\nEtableringsår: 1909.",
    "structured": {
        "1": {
            "company_name": "SVETSTEKNIK, AB",
            "pnr": "421 31",
            "address": "Västra Frölunda, Frörensareg 4.",
            "phone_number": "031-45 01 15",
            "bank_details": {
                "bankgiro": "420-1810",
                "postgiro": "241308-6"
            },
            "activity": "Säljer svetsomformare, svetslikriktare, svetstransformatörer, halvautomater, punktsvetsmaskiner, gassvetsutrustningar, elektroder, hårdlod, silverlod samt tillbehör för svetsning. Uthyrningar o reparationer",
            "employees": 12,
            "capital": 20000,
            "key_personnel": [
                {
                    "name": "Ing Enar Axelsson"
                }
            ],
            "establishment_year": 1946
        },
        "2": {
            "company_name": "SWIAB SVENSSON & WOLD INDUSTRI AB",
            "pnr": "417 03",
            "address": "Göteborg, Vindragareg 14.",
            "phone_number": "031-2211 15, 23 9135",
            "bank_details": {
                "bankgiro": "40-1650",
                "postgiro": "528277"
            },
            "activity": "Mekanisk service, varv o industri montage",
            "annual_turnover": 3000000,
            "capital": 5000,
            "establishment_year": 1959
        },
        "3": {
            "company_name": "SWING LTD AB",
            "pnr": "81101",
            "address": "Sandviken 1, Köpmang 23. Box 9.",
            "phone_number": "026-25 2470",
            "bank_details": {
                "bankgiro": "78-8754",
                "postgiro": "9450"
            },
            "activity": "Försäljningsbolag för rakblad o rakhyvlar",
            "annual_turnover": 1500000,
            "capital": 50000,
            "key_personnel": [
                {
                    "name": "Georg Zeidlitz"
                }
            ],
            "establishment_year": 1926
        },
        "4": {
            "company_name": "materialrontgen, ab",
            "pnr": "417 07",
            "address": "Göteborg, Stålverksg 4.",
            "phone_number": "031-2354 45",
            "bank_details": {
                "bankgiro": "420-3816",
                "postgiro": "426430-5"
            },
            "activity": "Oförstörande provning av svetsade konstruktioner, svetsarekontroll, besiktningar, ritningsgranskning, tillverkningskontroll. Svetsteknisk rådgivning",
            "employees": 60,
            "key_personnel": [
                {
                    "name": "Dlr E Axelsson"
                }
            ],
            "establishment_year": 1953
        },
        "5": {
            "company_name": "HALLA TEXTIL AB",
            "pnr": "510 60",
            "address": "Overlida. Box 25.",
            "phone_number": "0325-320 18",
            "bank_details": {
                "bankgiro": "55-3004",
                "postgiro": "13737"
            },
            "activity": "Tillverkar gardiner o sängöverkasttyger av bomull",
            "employees": 30,
            "annual_turnover": 1000000,
            "capital": 130000,
            "key_personnel": [
                {
                    "name": "Alf Sterner"
                }
            ],
            "establishment_year": 1910
        }
    }
}