{
    "original": "SÖDERBERG &amp; CO AB, R\n\nPnr 403 14\n\nGöteborg2, Drottningg 13. Box 2213.\nTel 031-17 07 40. Bankgiro\n500-5624. Postgiro 12026-1. Tga\nEres-co. Telex 21083 SEVATO S\nVerksamhet: Kirurgiska\ninstrument o sjukvårdsartiklar samt\nvacuuro-extractorer\nAntal anställda: 30\nAktiekapital: 200 000\nVerkst dir: Göran Uddenberg\nDisp: Arne Clarholm\nEtableringsàr: 1919.\n\nSÖDERHAMNS ELEKTRISKA\nBYRÅ, AB\n\nPnr 826 00\n\nSödertiamn, Kungsg 8. Tel\n0270-11950. Bankgiro 612-6833.\nPostgiro 22904-7\n\nVerksamhet: Elektr artiklar,\nel-installationer\nAntal anställda: 9\nÅrsomsättning: 1 000 000\nAktiekapital: 65 000\nVerkst dir: Göran Lindén\nEtableringsàr: 1899.\n\nSÖDERHAMNS STUVERI AB\n\nPnr 820 32\n\nStugsund, Box 9. Strandg 4. Tel\n0270-544 26. Bankgiro 789-5352.\nPostgiro 416436-4\nVerksamhet: Stuveriverksamhet i\nSöderhamns skeppningsdistrikt\nAntal anställda: 90\nÅrsomsättning: 4 000 000\nAktiekapital: 110 000\nVerkst dir: Sjökapten Bodo Renz\nEtableringsàr: 1927.\n\nSÖDERHAMNS TRÄVARU AB\n\nPnr 826 02\n\nSöderhamn 2, Box 1001. Kungsg 61.\nTel 0270-129 83, 131 33. Bankgiro\n789-5741. Postgiro 333468-7\nVerksamhet: Säljer trävaror o\nbyggnadsmaterial\n\nAktiekapital: 10 000\nVerkst dir: Disp Per Svedlund\nEtableringsàr: 1947.\n\nSODERHAMNS-KURIRENS\nTRYCKERI, AB\n\nPnr 826 01\n\nSöderhamn 1, Oxtorgsg 14. Box 60.\nTel 0270-114 15. Bankgiro 78-9573.\nPostgiro 75401\n\nVerksamhet: Tidnings- o\nciviltryckeri\n\nHälsinge-Kuriren: Hudiksvall. Tel\n0650-122 31\n\nBollnäs. Tel 0278-102 28\nIggesund. Tel 0650-201 56\nLjusdal. Tel 0651-112 92\nAntal anställda: 84\nÅrsomsättning: 6 000 000\nAktiekapital: 500 000\nVerkst dir: Ekonomichef Harald\nOlsson\n\nChefred: Einar Stråhle\nEtableringsàr 1895.\n\nCAP\n\nBankgiro 61-5873. Postgiro\n129739-9\n\nVerksamhet: Tillverkar o säljer\nhusgeråd-, present- o\nrestaurangartiklar\n\nVarunamn: Cany\nAntal anställda: 10\nÅrsomsättning: 1200 000\nVerkst dir: Carin Nygren\nEtableringsår: 1957.\n\nCITY HOTEL\n\nPnr 551 02\n\nJönköping 1, V Storg 23-25. Box\n118. Tel 036-119280. Bankgiro\n83-5766. Postgiro 121653. Tga\nSavoycity\n\nVerksamhet: Hotellet är beläget\n200 m från Centralstation. 80 rum\nÄgare o chef: Sture Gunnarsson\nEtableringsår: 1963.\n\nWIDTSKOFLE, AB\n\nPnr 290 15\n\nVittskövle. Tel 0450-530 28,\n53188. Bankgiro 657-7068. Postr\ngiro 74596-8\n\nVerksamhet: Sågverk, eldistribution,\njordbruk, skog\nAntal anställda: 100\nÅrsomsättning: 8 100 000\nAktiekapital: 700 000\nVerkst dir: Rolf H Stjernswärd\nEtableringsår: 1916.\n\nÅSCO METALL AB\n\nPnr 560 10\n\nSkillingaryd. Tel 0370-702 81.\nBankgiro 14-1380. Postgiro\n361343-7.\n\nVerksamhet: Tillverkar rörnitar\nChef: Ake Svensson\nEtableringsår: 1945.\n\nRATIO, AB\n\nPnr 41103\n\nGöteborg, Nils Ericsonsg 5. Tel\n031-1132 98. Bankgiro 337-3461.\nPostgiro 427800-8\nVerksamhet: Mek verkstad o\nkonsulterande verksamhet\nAntal anställda: 10\nÅrsomsättning: 600 000\nAktiekapital: 30000\nStyrelse: Ing Gunnar Lundgren\n(ordf), ing Arne Lundgren\nEtableringsår: 1954.\n\nLINDELL ANNONSBYRÅ AB\n\nPnr 21129\n\nMalmö, Gasverksg 9. Tel\n040-39910. Bankgiro 260-6 218. Postgiro\n531112-1\n\nVerksamhet: Fullservicebyrå inom\nreklam o marknadsföring\nAntal anställda: 30\nÅrsomsättning: 6500 000\nAktiekapital: 150 000\nStyrelse: Prof Curt Kihlstedt\n(ordf), adv Kurt Hjertberg, dir\nArne Lindell, dir Curt Lindell\nVerkst dir: Curt Lindell\nEtableringsår: 1953.\n\nLINDELLS I BILLESHOLM\nMASKIN AB\n\nPnr 260 50\n\nBillesholm, Box 48. Tel\n042-724 20. Bankgiro 671-6 1 20. Postgiro\n387380-9. Telex 72346\nVerksamhet: Försäljning o service\nav palltruckar, staplare, truckar o\nentreprenadmaskiner.\nBensinförsäljning\n\nAntal anställda: 45\nÅrsomsättning: 5 500 000\nAktiekapital: 100 000\nVerkst dir: stig Lindell\nFörsäljn-chef: Thore Lindell\nReservdelschef: Gunnar Hansson\nEtableringsår: 1947\nDotterbolag: Lindells Motor i\nHälsingborg AB.\n\nLINDELL, AB GEORG W\n\nPnr 37100\n\nKarlskrona, Gullbernav. Tel\n0455-230 20. Bankgiro 343-9650. Postgiro\n264704-8. Tga Lindellträ. Telex\n4859\n\nVerksamhet: Export av sågade\nträvaror\n\nAntal anställda: 30\nÅrsomsättning: 8 000 000\nAktiekapital: 180 000\nVerkst dir: Ivar Ericson\nEtableringsår: 1935.\n\nLINDELL RÖRLEDNINGS AB,\nSVEN\n\nPnr 702 25\n\nÖrebro, Boskärsg 23. Tel\n019-13 07 45. Bankgiro 822-7118.\nPostgiro 367104-7\n\nVerksamhet: Utför\nVVS-installa-tioner o reparationer\nAntal anställda: 20\nÅrsomsättning: 2 500 000\nAktiekapital: 50 000\nVerkst dir: Sven Lindell\nEtableringsår: 1948.\n\nBETTNA SÄG,AB\n\nPnr 640 33\n\nBettna. Tel 0155-921 13.\nBankgiro 83-0080. Postgiro 577207\nVerksamhet: Sågverksrörelse o\nhyvleri\n\nAntal anställda: 7\nÅrsomsättning: 650 000\nChefer: Rune Andersson, Arne\nAndersson\nEtableringsår: 1954.\n\nKÄGE-VERKEN, AB\n\nPnr 341 00\n\nLjungby, Hamneda. Box 21. Tel\n0372-50160\n\nVerksamhet: Mek verkstad.\nTillverkar cisterner för lagring av\nbensin o oljor upp till 2 000 kbm,\ntryckkärl, flishuggmaskiner o\nflis-såll\n\nAktiekapital: 130 000\nVerkst dir: Rune Karlsson\nEtableringsår: 1956.\n\nACETAT OCH VISCOS\n\nPnr 11266\n\nStockholm, Essingestråket 37.\nTel 08-56 44 54, 56 44 55. Bankgiro\n730-2367. Postgiro 255087-9\nVerksamhet: Säljer förpackningar\nav acetat, cellofan o polyeten\nChef: Disp Erie S Ekman\nEtableringsår: 1958.",
    "structured": {
        "1": {
            "company_name": "SÖDERBERG & CO AB",
            "pnr": "403 14",
            "address": "Drottningg 13. Box 2213, Göteborg",
            "phone_number": "031-17 07 40",
            "bank_details": {
                "bankgiro": "500-5624",
                "postgiro": "12026-1"
            },
            "activity": "Kirurgiska instrument o sjukvårdsartiklar samt vacuuro-extractorer",
            "employees": 30,
            "capital": 200000,
            "key_personnel": [
                {
                    "name": "Göran Uddenberg",
                    "position": "Verkst dir"
                },
                {
                    "name": "Arne Clarholm",
                    "position": "Disp"
                }
            ],
            "establishment_year": 1919
        },
        "2": {
            "company_name": "SÖDERHAMNS ELEKTRISKA BYRÅ, AB",
            "pnr": "826 00",
            "address": "Kungsg 8, Södertiamn",
            "phone_number": "0270-11950",
            "bank_details": {
                "bankgiro": "612-6833",
                "postgiro": "22904-7"
            },
            "activity": "Elektr artiklar, el-installationer",
            "employees": 9,
            "annual_turnover": 1000000,
            "capital": 65000,
            "key_personnel": {
                "name": "Göran Lindén",
                "position": "Verkst dir"
            },
            "establishment_year": 1899
        },
        "3": {
            "company_name": "SÖDERHAMNS STUVERI AB",
            "pnr": "820 32",
            "address": "Strandg 4, Stugsund, Box 9",
            "phone_number": "0270-544 26",
            "bank_details": {
                "bankgiro": "789-5352",
                "postgiro": "416436-4"
            },
            "activity": "Stuveriverksamhet i Söderhamns skeppningsdistrikt",
            "employees": 90,
            "annual_turnover": 4000000,
            "capital": 110000,
            "key_personnel": {
                "name": "Sjökapten Bodo Renz",
                "position": "Verkst dir"
            },
            "establishment_year": 1927
        },
        "4": {
            "company_name": "SÖDERHAMNS TRÄVARU AB",
            "pnr": "826 02",
            "address": "Box 1001, Kungsg 61, Söderhamn 2",
            "phone_number": "0270-129 83, 131 33",
            "bank_details": {
                "bankgiro": "789-5741",
                "postgiro": "333468-7"
            },
            "activity": "Säljer trävaror o byggnadsmaterial",
            "capital": 10000,
            "key_personnel": {
                "name": "Disp Per Svedlund",
                "position": "Verkst dir"
            },
            "establishment_year": 1947
        },
        "5": {
            "company_name": "SODERHAMNS-KURIRENS TRYCKERI, AB",
            "pnr": "826 01",
            "address": "Oxtorgsg 14, Söderhamn 1, Box 60",
            "phone_number": "0270-114 15",
            "bank_details": {
                "bankgiro": "78-9573",
                "postgiro": "75401"
            },
            "activity": "Tidnings- o civiltryckeri",
            "employees": 84,
            "annual_turnover": 6000000,
            "capital": 500000,
            "key_personnel": [
                {
                    "name": "Ekonomichef Harald Olsson",
                    "position": "Verkst dir"
                },
                {
                    "name": "Einar Stråhle",
                    "position": "Chefred"
                }
            ],
            "establishment_year": 1895
        },
        "6": {
            "company_name": "CAP",
            "bank_details": {
                "bankgiro": "61-5873",
                "postgiro": "129739-9"
            },
            "activity": "Tillverkar o säljer husgeråd-, present- o restaurangartiklar",
            "employees": 10,
            "annual_turnover": 1200000,
            "key_personnel": {
                "name": "Carin Nygren",
                "position": "Verkst dir"
            },
            "establishment_year": 1957
        },
        "7": {
            "company_name": "CITY HOTEL",
            "pnr": "551 02",
            "address": "V Storg 23-25, Jönköping 1, Box 118",
            "phone_number": "036-119280",
            "bank_details": {
                "bankgiro": "83-5766",
                "postgiro": "121653"
            },
            "activity": "Hotellet är beläget 200 m från Centralstation. 80 rum",
            "owner_chef": "Sture Gunnarsson",
            "establishment_year": 1963
        },
        "8": {
            "company_name": "WIDTSKOFLE, AB",
            "pnr": "290 15",
            "address": "Vittskövle",
            "phone_number": "0450-530 28, 53188",
            "bank_details": {
                "bankgiro": "657-7068",
                "postgiro": "74596-8"
            },
            "activity": "Sågverk, eldistribution, jordbruk, skog",
            "employees": 100,
            "annual_turnover": 8100000,
            "capital": 700000,
            "key_personnel": {
                "name": "Rolf H Stjernswärd",
                "position": "Verkst dir"
            },
            "establishment_year": 1916
        },
        "9": {
            "company_name": "ÅSCO METALL AB",
            "pnr": "560 10",
            "address": "Skillingaryd",
            "phone_number": "0370-702 81",
            "bank_details": {
                "bankgiro": "14-1380",
                "postgiro": "361343-7"
            },
            "activity": "Tillverkar rörnitar",
            "owner_chef": "Ake Svensson",
            "establishment_year": 1945
        },
        "10": {
            "company_name": "RATIO, AB",
            "pnr": "41103",
            "address": "Nils Ericsonsg 5, Göteborg",
            "phone_number": "031-1132 98",
            "bank_details": {
                "bankgiro": "337-3461",
                "postgiro": "427800-8"
            },
            "activity": "Mek verkstad o konsulterande verksamhet",
            "employees": 10,
            "annual_turnover": 600000,
            "capital": 30000,
            "board_members": [
                "Ing Gunnar Lundgren (ordf)",
                "Ing Arne Lundgren"
            ],
            "establishment_year": 1954
        },
        "11": {
            "company_name": "LINDELL ANNONSBYRÅ AB",
            "pnr": "21129",
            "address": "Gasverksg 9, Malmö",
            "phone_number": "040-39910",
            "bank_details": {
                "bankgiro": "260-6 218",
                "postgiro": "531112-1"
            },
            "activity": "Fullservicebyrå inom reklam o marknadsföring",
            "employees": 30,
            "annual_turnover": 6500000,
            "capital": 150000,
            "board_members": [
                "Prof Curt Kihlstedt (ordf)",
                "Adv Kurt Hjertberg",
                "Dir Arne Lindell",
                "Dir Curt Lindell"
            ],
            "owner_chef": "Curt Lindell",
            "establishment_year": 1953
        },
        "12": {
            "company_name": "LINDELLS I BILLESHOLM MASKIN AB",
            "pnr": "260 50",
            "address": "Box 48, Billesholm",
            "phone_number": "042-724 20",
            "bank_details": {
                "bankgiro": "671-6 1 20",
                "postgiro": "387380-9"
            },
            "activity": "Försäljning o service av palltruckar, staplare, truckar o entreprenadmaskiner. Bensinförsäljning",
            "employees": 45,
            "annual_turnover": 5500000,
            "capital": 100000,
            "key_personnel": [
                {
                    "name": "Stig Lindell",
                    "position": "Verkst dir"
                },
                {
                    "name": "Thore Lindell",
                    "position": "Försäljn-chef"
                },
                {
                    "name": "Gunnar Hansson",
                    "position": "Reservdelschef"
                }
            ],
            "subsidiary": "Lindells Motor i Hälsingborg AB",
            "establishment_year": 1947
        },
        "13": {
            "company_name": "LINDELL, AB GEORG W",
            "pnr": "37100",
            "address": "Gullbernav, Karlskrona",
            "phone_number": "0455-230 20",
            "bank_details": {
                "bankgiro": "343-9650",
                "postgiro": "264704-8"
            },
            "activity": "Export av sågade trävaror",
            "employees": 30,
            "annual_turnover": 8000000,
            "capital": 180000,
            "key_personnel": {
                "name": "Ivar Ericson",
                "position": "Verkst dir"
            },
            "establishment_year": 1935
        },
        "14": {
            "company_name": "LINDELL RÖRLEDNINGS AB",
            "pnr": "702 25",
            "address": "Boskärsg 23, Örebro",
            "phone_number": "019-13 07 45",
            "bank_details": {
                "bankgiro": "822-7118",
                "postgiro": "367104-7"
            },
            "activity": "Utför VVS-installa-tioner o reparationer",
            "employees": 20,
            "annual_turnover": 2500000,
            "capital": 50000,
            "key_personnel": {
                "name": "Sven Lindell",
                "position": "Verkst dir"
            },
            "establishment_year": 1948
        },
        "15": {
            "company_name": "BETTNA SÄG,AB",
            "pnr": "640 33",
            "address": "Bettna",
            "phone_number": "0155-921 13",
            "bank_details": {
                "bankgiro": "83-0080",
                "postgiro": "577207"
            },
            "activity": "Sågverksrörelse o hyvleri",
            "employees": 7,
            "annual_turnover": 650000,
            "key_personnel": [
                "Rune Andersson",
                "Arne Andersson"
            ],
            "establishment_year": 1954
        },
        "16": {
            "company_name": "KÄGE-VERKEN, AB",
            "pnr": "341 00",
            "address": "Hamneda, Ljungby, Box 21",
            "phone_number": "0372-50160",
            "activity": "Mek verkstad. Tillverkar cisterner för lagring av bensin o oljor upp till 2 000 kbm, tryckkärl, flishuggmaskiner o flis-såll",
            "capital": 130000,
            "key_personnel": {
                "name": "Rune Karlsson",
                "position": "Verkst dir"
            },
            "establishment_year": 1956
        },
        "17": {
            "company_name": "ACETAT OCH VISCOS",
            "pnr": "11266",
            "address": "Essingestråket 37, Stockholm",
            "phone_number": "08-56 44 54, 56 44 55",
            "bank_details": {
                "bankgiro": "730-2367",
                "postgiro": "255087-9"
            },
            "activity": "Säljer förpackningar av acetat, cellofan o polyeten",
            "owner_chef": "Disp Erie S Ekman",
            "establishment_year": 1958
        }
    }
}