{
    "original": "maskinverktyg\n\nPnr 33100\n\nVärnamo, Svenskbygget Växjöv.\nTel 0370-111 91. Bankgiro\n554-4077. Postgiro 571468-8\nVeiksamhet: Säljer hand- o\nmaskinverktyg, spännelement samt mindre\nmaskiner\n\nÄgare o chef: Fabr Enar Fransson\nEtableringsår 1946.\n\nSAN\n\nÅrsomsättning: 3 500000\nChef: Ingvar Sanderson\nEtableringsår: 1892.\n\nLAGERSTRÖMS FABRIKS AB\n\nPnr 595 00\n\nMjölby, Kyrkog 23. Box 36. Tel\n0142-13135. Bankgiro 128-2896.\nPostgiro 156191-9\nVerksamhet: Tillverkar\nfirmaemblem, reklammärken,\nföreningsmärken, medaljer o plaketter\nFörsäljningskontor: 112 60\nStockholm, Fyrverkarbacken 28. Tel\n08-50 38 10\n\nAntal anställda: 50\n.Aktiekapital: 100 000\nDisp: Bertil Berg\nEtableringsår: 1939.\n\nLINDACO AB\n\nPnr 113 44\n\nStockholm, Upplandsg 81. Tel\n08-23 24 25. Bankgiro 70-0113. Post-\n\ngiro 52619. Tga Lindacotel\nVerksamhet: Kontorsmaskiner,\ngrafiska maskiner o lim\n.Aktiekapital: 500000\nVerkst dir: Sture H Lindfeldt\nFörsäljn-dir: Fredrik Jensen\nEtableringsår: 1952.\n\nLINDAHL &amp; CO,\nAUTOMOBIL AB\n\nPnr 401 21\n\nGöteborg 1, O Hamng 19. Box 101.\nTel 031-17 05 35. Tga Autolindahl\nVerksamhet: Bilar, bilreservdelar\nAktiekapital: 500 000\nVerkst dir: Ing Nils Lindahl\nKamrer: Bengt Henriksson\nEtableringsår: 1931.\n\nLINDAHL &amp; JOHANSSONS\nMEK VERKSTAD\n\nPnr 56012\n\nVaggeryd, Karlav 21. Tel\n0393-104 63. Bankgiro 982-458. Postgiro\n332468-8\n\nVerksamhet: Tillverkar\nspecialmaskiner o verktyg, hydraulik\nAntal anställda: 15\nÅrsomsättning: 1700 000\nChef: Bertil Johansson\nEtableringsår: 1945.\n\nHOL\n\nHOLMGRENS PASFABRIK AB\n\nPnr 104 22\n\nStockholm 22, Pack 22014. Tel\n08-52 00 25. Bankgiro 57-4727.\nPostgiro 2624\n\nVerksamhet: Tillverkar påsar\nAktiekapital: 150000\nVerkst dir: Sven-Gunnar Mörck\nEtableringsår: 1926.\n\nHOLMGRENS\nSMIDESVERK-STAD\n\nPnr 773 01\n\nFagersta 1, Avestbo. Box 6294. Tel\n0223-530 62. Postgiro 576981\nVerksamhet: Tillverkar\nbyggnads-smide, järnkonstruktioner o\ncisterner. Utför el- o gassvetsning\nÄgare o chef: Erik Holmgren\nEtableringsår: 1950.\n\nMO och DOMS JO AB\n\nPnr 89101\n\nÖrnsköldsvik 1, Fack. Tel\n0660-105 00. Bankgiro 700-1217.\nPostgiro 62730-7. Tga Modomsjö.\nTelex 6054\n\nVerksamhet: Blekt sulfit- o\nsulfatmassa, slipmassa,\nmjukpappers-produkter, kemiska produkter,\nträvaror, trähus o verkstadsprodukter\nAntal anställda: 8 000\nÅrsomsättning: 1 000 000 000\nAktiekapital: 200 000000\nVerkst dir: Bengt Lyberg\nEtableringsår: 1873.\n\nMJÖLBY MOBELSNICKERI ER\nAB\n\nPnr 595 00\n\nMjölby, Strand v 32. Tel\n0142-115 66. Postgiro 572240-0\nVerksamhet: Tillverkar trähöljen\ntill radio o el industrin såsom i\nhuvudsak: högtalarelådor,\nförstärkarelådor, ljudpelarelådor,\ngrammofon o bandspelarlådor, radio- o\nTV-lådor mm\n\nAntal anställda: 12\nÅrsomsättning: 800 000\nAktiekapital: 30 000\nVerkst dir: Lennart Johansson\nEtableringsår: 1968.\n\nMJOLKCENTRALEN,\nLÅNT-MANNENS MJOLKFORSALJ.\nNINGSFORENING UPA (MC)\n\nPnr 10110\n\nStockholm 1, Dalag 3. Fack. Tel\n08-22 60 60. Bankgiro 72-8717.\nPostgiro 661. Tga Mjölkcentralen\nAvdelningskontor: 63107\nEskilstuna, Ruddammsg 2. Tel 016-13 76 50\n552 57 Jönköping, Myntg 5. Tel\n036-118070\n\n531 00 Lidköping, Nya stadens torg\n8. Tel 0510-27180\n602 13 Norrköping, Fridhemsv 3.\nTel 011-129205\n\n101 10 Stockholm, Dalag 7. Tel\n08-22 60 60\n\n753 31 Uppsala, Vaksalag 22. Tel\n018-13 9120\n\n62100 Visby, Järnvägsg. Tel\n0498-153 50\n\n.Antal anställda: 2 583\nÅrsomsättning: 950 000 000\nVerkst dir: Jan-Robert Eklind\nEtableringsån 1915.\n\nDAHL, AB K G\n\nPnr 113 23\n\nStockholm, Vanadisv 27. Tel\n08-33 31 95. 33 35 00. Bankgiro\n746-8226. Postgiro 652088-6\nVerksamhet: Tillverkar\ninrednings-o byggnadssnickerier\nAntal anställda: 8\nÅrsomsättning: 800 000\nDriftchef: Kenneth Bonaparte\nEtableringsår: 1961.\n\nDAHL AB, BORSTBINDERU\nFIRMAN OTTO\n\nPnr 602 24\n\nNorrköping, Gamla Rådstugug 24.\nTel 011-12 03 27. Bankgiro\n34-9199. Postgiro 27290\nVerksamhet: Tillverkar alla slags\nborstar till industrin\nAktiekapital: 5 000\nChef: Borstbindaremäst Sven Dahl\nEtableringsår: 1876.\n\nKULLENS GJUTERI, AB\n\nPnr 384 00\n\nBlomstermåla, Storg 90. Tel\n0499-20132. Bankgiro 29-3838. Postgiro\n330399\n\nVerksamhet: Tillverkar\ntackjärns-gjutgods\n\nAntal anställda: 30\nÅrsomsättning: 1 500 000\nAktiekapital: 80 000\nVerkst dir: Fabr Yngve Lööw\nEtableringsår: 1946.\n\nBERGKVIST AB, AXEL\n\nPnr 790 30\n\nInsjön, Box 52. Tel 0247-400 83,\n408 30. Bankgiro 795-5906.\nPostgiro 29493-4. Tga Abi.\nTelex 7631 ABI S\n\nVerksamhet: Tillverkar o säljer\nsågade o hyvlade trävaror, fönster o\ndörrar\n\nAntal anställda: 145\nÅrsomsättning: 13 000 000\nAktiekapital: 500 000\n\nStyrelse: Faktor Björn Bergkvist\n(ordf), förvaltare Ragnar Bergkvist,\ning Bengt Bergkvist\nVerkst dir: Förvaltare Ragnar\nBergkvist\n\nEtableringsår: 1935\nDotterbolag: Norsbro Sågverk AB,\nLeksand.\n\nBERGQVISTS PLÅTSLAGERI,\nAB AXEL\n\nPnr 641 00\n\nKatrineholm, Kungsg 17. Tel\n0150-104 12. Bankgiro 36-3905. Postgiro\n163423\n\nVerksamhet: Byggnadsplåtslageri\no ventilationsarbeten\nAntal anställda: 14\nÅrsomsättning: 650 000\nAktiekapital: 15 000\nStyrelseordförande: Dir Sven Erie\nJohansson\n\nVerkst dir: Sven Erie Johansson\nEtableringsår: 1891\nOmbildat till aktiebolag 1963.\n\nBERGQVIST FABRIKS AB, C R\n\nPnr 512 03\n\nSvenljunga 3, Box 3035. Hillared.\nTel 033-821 70. Bankgiro\n531-2210. Postgiro 135878-7\nVerksamhet: Tillverkar o säljer\narbetskläder av blåtyg eller\nliknande, fritidsbyxor o vita\nskyddsrockar av bomullstyg samt polyester/\nbomull\n\nFilialfabrik: Ljungsarp. Tel\n0321-63017\n\nTrollhättan. Tel 0520-14151\n\nVarunamn: Bergis\n\nAntal anställda: 120\n\nÅrsomsättning: 8 000 000\n\nAktiekapital: 85 000\n\nStyrelse: Disp Bernt Bergqvist\n\n(ordf), disp Torsten Bergqvist\n\nChef för tillverkning o försäljning:\n\nDisp Torsten Bergqvist\n\nChef för kamerala avd: Disp Bernt\n\nBergqvist\n\nEtableringsår: 1915\nOmbildat till aktiebolag 1946.\n\nBERGQVIST,\nINGENIÖRSFIRMAN OLA\n\nPnr 42102\n\nVästra Frölunda 2, Box 2011.\nFrö-tallsg 17. Tel 031-4 9 04 3 0,\n42 2962. Bankgiro 35-0626.\nPostgiro 524301. Tga Ingola\nVerksamhet: Säljer hydrauliska\ngrävmaskiner, stållinor etc\nAntal anställda: 10\nÅrsomsättning: 4 000 000\nChef: Ing Ola Bergqvist\nEtableringsår: 1962.\n\nPRESSURKLIPP, AB\n\nPnr 102 20\n\nStockholm 12, Fack. Sankt Göransg\n84. Tel 08-53 88 50, 53 88 85.\nBankgiro 991-1322. Postgiro 3248-2.\nTga Pressklipp\n\nVerksamhet: Klippservice, svenska\no utländska tidningar o tidskrifter.\nRadio- o TV-bevakning\nAktiekapital: 25 000\nVerkst dir: R Berggren\nEtableringsår: 1943.",
    "structured": {
        "firms": [
            {
                "company_name": "SAN",
                "activity": "Säljer hand- o maskinverktyg, spännelement samt mindre maskiner",
                "establishment_year": 1892
            },
            {
                "company_name": "LAGERSTRÖMS FABRIKS AB",
                "activity": "Tillverkar firmaemblem, reklammärken, föreningsmärken, medaljer o plaketter",
                "address": "Mjölby, Kyrkog 23, Box 36",
                "phone_number": "0142-13135",
                "bank_details": {
                    "bankgiro": "128-2896",
                    "postgiro": "156191-9"
                },
                "employees": 50,
                "capital": 100000,
                "key_personnel": [
                    {
                        "name": "Bertil Berg",
                        "position": "Disp"
                    }
                ],
                "establishment_year": 1939
            },
            {
                "company_name": "LINDACO AB",
                "activity": "Kontorsmaskiner, grafiska maskiner o lim",
                "address": "Stockholm, Upplandsg 81",
                "phone_number": "08-23 24 25",
                "bank_details": {
                    "bankgiro": "70-0113",
                    "postgiro": "52619"
                },
                "capital": 500000,
                "key_personnel": [
                    {
                        "name": "Sture H Lindfeldt",
                        "position": "Verkst dir"
                    },
                    {
                        "name": "Fredrik Jensen",
                        "position": "Försäljn-dir"
                    }
                ],
                "establishment_year": 1952
            },
            {
                "company_name": "LINDAHL & CO, AUTOMOBIL AB",
                "activity": "Bilar, bilreservdelar",
                "address": "Göteborg 1, O Hamng 19, Box 101",
                "phone_number": "031-17 05 35",
                "key_personnel": [
                    {
                        "name": "Ing Nils Lindahl",
                        "position": "Verkst dir"
                    },
                    {
                        "name": "Bengt Henriksson",
                        "position": "Kamrer"
                    }
                ],
                "establishment_year": 1931
            },
            {
                "company_name": "LINDAHL & JOHANSSONS MEK VERKSTAD",
                "activity": "Tillverkar specialmaskiner o verktyg, hydraulik",
                "address": "Vaggeryd, Karlav 21",
                "phone_number": "0393-104 63",
                "bank_details": {
                    "bankgiro": "982-458",
                    "postgiro": "332468-8"
                },
                "employees": 15,
                "annual_turnover": 1700000,
                "key_personnel": [
                    {
                        "name": "Bertil Johansson",
                        "position": "Chef"
                    }
                ],
                "establishment_year": 1945
            },
            {
                "company_name": "HOLMGRENS PASFABRIK AB",
                "activity": "Tillverkar påsar",
                "address": "Stockholm 22, Pack 22014",
                "phone_number": "08-52 00 25",
                "bank_details": {
                    "bankgiro": "57-4727",
                    "postgiro": "2624"
                },
                "capital": 150000,
                "key_personnel": [
                    {
                        "name": "Sven-Gunnar Mörck",
                        "position": "Verkst dir"
                    }
                ],
                "establishment_year": 1926
            },
            {
                "company_name": "HOLMGRENS SMIDESVERK-STAD",
                "activity": "Tillverkar byggnads-smide, järnkonstruktioner o cisterner. Utför el- o gassvetsning",
                "address": "Fagersta 1, Avestbo, Box 6294",
                "phone_number": "0223-530 62",
                "postgiro": "576981",
                "key_personnel": [
                    {
                        "name": "Erik Holmgren",
                        "position": "Ägare o chef"
                    }
                ],
                "establishment_year": 1950
            },
            {
                "company_name": "MO och DOMS JO AB",
                "activity": "Blekt sulfit- o sulfatmassa, slipmassa, mjukpappers-produkter, kemiska produkter, trävaror, trähus o verkstadsprodukter",
                "address": "Örnsköldsvik 1, Fack",
                "phone_number": "0660-105 00",
                "bank_details": {
                    "bankgiro": "700-1217",
                    "postgiro": "62730-7"
                },
                "employees": 8000,
                "annual_turnover": 1000000000,
                "capital": 200000000,
                "key_personnel": [
                    {
                        "name": "Bengt Lyberg",
                        "position": "Verkst dir"
                    }
                ],
                "establishment_year": 1873
            },
            {
                "company_name": "MJÖLBY MOBELSNICKERI ER AB",
                "activity": "Tillverkar trähöljen till radio o el industrin såsom i huvudsak: högtalarelådor, förstärkarelådor, ljudpelarelådor, grammofon o bandspelarlådor, radio- o TV-lådor mm",
                "address": "Mjölby, Strand v 32",
                "phone_number": "0142-115 66",
                "postgiro": "572240-0",
                "employees": 12,
                "annual_turnover": 800000,
                "capital": 30000,
                "key_personnel": [
                    {
                        "name": "Lennart Johansson",
                        "position": "Verkst dir"
                    }
                ],
                "establishment_year": 1968
            },
            {
                "company_name": "MJOLKCENTRALEN, LÅNT-MANNENS MJOLKFORSALJNINGSFORENING UPA (MC)",
                "activity": "Mjölkförsäljning",
                "address": "Stockholm 1, Dalag 3, Fack",
                "phone_number": "08-22 60 60",
                "bank_details": {
                    "bankgiro": "72-8717",
                    "postgiro": "661"
                },
                "employees": 2583,
                "annual_turnover": 950000000,
                "key_personnel": [
                    {
                        "name": "Jan-Robert Eklind",
                        "position": "Verkst dir"
                    }
                ],
                "establishment_year": 1915
            },
            {
                "company_name": "DAHL, AB K G",
                "activity": "Tillverkar inrednings-o byggnadssnickerier",
                "address": "Stockholm, Vanadisv 27",
                "phone_number": "08-33 31 95, 33 35 00",
                "bank_details": {
                    "bankgiro": "746-8226",
                    "postgiro": "652088-6"
                },
                "employees": 8,
                "annual_turnover": 800000,
                "key_personnel": [
                    {
                        "name": "Kenneth Bonaparte",
                        "position": "Driftchef"
                    }
                ],
                "establishment_year": 1961
            },
            {
                "company_name": "DAHL AB, BORSTBINDERU FIRMAN OTTO",
                "activity": "Tillverkar alla slags borstar till industrin",
                "address": "Norrköping, Gamla Rådstugug 24",
                "phone_number": "011-12 03 27",
                "bank_details": {
                    "bankgiro": "34-9199",
                    "postgiro": "27290"
                },
                "capital": 5000,
                "key_personnel": [
                    {
                        "name": "Sven Dahl",
                        "position": "Chef"
                    }
                ],
                "establishment_year": 1876
            },
            {
                "company_name": "KULLENS GJUTERI, AB",
                "activity": "Tillverkar tackjärns-gjutgods",
                "address": "Blomstermåla, Storg 90",
                "phone_number": "0499-20132",
                "bank_details": {
                    "bankgiro": "29-3838",
                    "postgiro": "330399"
                },
                "employees": 30,
                "annual_turnover": 1500000,
                "capital": 80000,
                "key_personnel": [
                    {
                        "name": "Fabr Yngve Lööw",
                        "position": "Verkst dir"
                    }
                ],
                "establishment_year": 1946
            },
            {
                "company_name": "BERGKVIST AB, AXEL",
                "activity": "Tillverkar o säljer sågade o hyvlade trävaror, fönster o dörrar",
                "address": "Insjön, Box 52",
                "phone_number": "0247-400 83, 408 30",
                "bank_details": {
                    "bankgiro": "795-5906",
                    "postgiro": "29493-4"
                },
                "employees": 145,
                "annual_turnover": 13000000,
                "capital": 500000,
                "key_personnel": [
                    {
                        "name": "Faktor Björn Bergkvist",
                        "position": "Styrelse ordf"
                    }
                ],
                "establishment_year": 1935
            },
            {
                "company_name": "BERGQVISTS PLÅTSLAGERI, AB AXEL",
                "activity": "Byggnadsplåtslageri o ventilationsarbeten",
                "address": "Katrineholm, Kungsg 17",
                "phone_number": "0150-104 12",
                "bank_details": {
                    "bankgiro": "36-3905",
                    "postgiro": "163423"
                },
                "employees": 14,
                "annual_turnover": 650000,
                "capital": 15000,
                "key_personnel": [
                    {
                        "name": "Dir Sven Erie Johansson",
                        "position": "Styrelseordförande"
                    },
                    {
                        "name": "Sven Erie Johansson",
                        "position": "Verkst dir"
                    }
                ],
                "establishment_year": 1891
            },
            {
                "company_name": "BERGQVIST FABRIKS AB, C R",
                "activity": "Tillverkar o säljer arbetskläder av blåtyg eller liknande, fritidsbyxor o vita skyddsrockar av bomullstyg samt polyester/bomull",
                "address": "Svenljunga 3, Box 3035, Hillared",
                "phone_number": "033-821 70",
                "bank_details": {
                    "bankgiro": "531-2210",
                    "postgiro": "135878-7"
                },
                "employees": 120,
                "annual_turnover": 8000000,
                "capital": 85000,
                "key_personnel": [
                    {
                        "name": "Disp Bernt Bergqvist",
                        "position": "Styrelse"
                    },
                    {
                        "name": "Disp Torsten Bergqvist",
                        "position": "Chef för tillverkning o försäljning"
                    },
                    {
                        "name": "Disp Bernt Bergqvist",
                        "position": "Chef för kamerala avdelningen"
                    }
                ],
                "establishment_year": 1915
            },
            {
                "company_name": "BERGQVIST, INGENIÖRSFIRMAN OLA",
                "activity": "Säljer hydrauliska grävmaskiner, stållinor etc",
                "address": "Västra Frölunda 2, Box 2011, Frö-tallsg 17",
                "phone_number": "031-4 9 04 3 0, 42 2962",
                "bank_details": {
                    "bankgiro": "35-0626",
                    "postgiro": "524301"
                },
                "employees": 10,
                "annual_turnover": 4000000,
                "key_personnel": [
                    {
                        "name": "Ing Ola Bergqvist",
                        "position": "Chef"
                    }
                ],
                "establishment_year": 1962
            },
            {
                "company_name": "PRESSURKLIPP, AB",
                "activity": "Klippservice, svenska o utländska tidningar o tidskrifter, Radio- o TV-bevakning",
                "address": "Stockholm 12, Fack, Sankt Göransg 84",
                "phone_number": "08-53 88 50, 53 88 85",
                "bank_details": {
                    "bankgiro": "991-1322",
                    "postgiro": "3248-2"
                },
                "capital": 25000,
                "key_personnel": [
                    {
                        "name": "R Berggren",
                        "position": "Verkst dir"
                    }
                ],
                "establishment_year": 1943
            }
        ]
    }
}