{
    "original": "TORNER &amp; CO KB, CARL\n\nPnr 421 52\n\nVästra Frölunda, Klangfärgsg 11.\nTel 031-29 00 75, 29 00 82.\nBankgiro 33-7516. Postgiro 41005\nVerksamhet: Säljer\nbyggnadsmaterial, utför nybyggnader o\nreparationer av skorstenar o rökkanaler,\ntaktäckningar o väggbeklädnader\nFirmatecknare: Nils Witehall\nEtableringsår: 1920.\n\nLÅS-&amp; METALLFABRIKEN,\nAB\n\nPnr 360 51\n\nHovmantorp. Tel 0478-400 31,\n40161. Bankgiro 293-3174.\nPostgiro 284837-2\n\nVerksamhet: Tillverkar lås o\nmetallbeslag för\njärnvägspersonvagnar, bussar o båtar, delar till\nbåtmotorer, sanitetsgods m m samt\nmetallgjutgods av brons, lödmetall,\nmässing, zink o lättmetallegeringar.\nUtför förnickling, förkromning o\nförkoppring\nAntal anställda: 45\nÅrsomsättning: 2 700000\nAktiekapital: 150000\nStyrelse: Disp Georg Mattsson\n(ordf), fabr Albin Håkansson,\nfabr Elis Mattsson\nVerkst dir: Georg Mattsson\nEtableringsår: 1943.\n\nSTEIN AB, WILLIAM\n\nPnr 18107\n\nLidingö 7, Bodalsv 47. Box 705.\nTel 08-765 28 20. Bankgiro\n165-2494. Postgiro 609882-6.\nTga Willstein, Stockholm.\nTelex 19065\n\nVerksamhet: Säljer maskiner o\nplastråvaror för plastindustrin samt\nverkstadsindustrin\nAntal anställda: 12\nÅrsomsättning: 17 500 000\nAktiekapital: 100 000\nVerkst dir: Stein Ahlqvist\nEtableringsår: 1960.\n\nLENNSTRÖM, ELEKTRISKA AB\n\nPnr 11128\n\nStockholm, Munkbron 5-7. Tel\n08-23 06 10. Bankgiro 568-9294.\nPostgiro 3895-0\n\nVerksamhet: Utför elektriska\ninstallationer, takvärme- o\nTV-an-tennanläggningar. Säljer elartiklar\n(ej armatur, radio o TV)\nAntal anställda: 50\nÅrsomsättning: 4 000 000\nAktiekapital: 200 000\nEtableringsår: 1919\nOmbildat till aktiebolag 1938.\n\nLENNSTRÖM, ERNST\n\nPnr 402 51\n\nGöteborg 13, Waterloog 12. Box\n13047. Tel 031-19 66 07, 19 66 08.\n\nBankgiro 506-6832. Postgiro\n40408-7. Tga Lennström\nVerksamhet: Tillverkar\nbyggnadspapp o impregnerat omslagspapper.\nSäljer grovpapper, alla slag\nVarunamn: Ornol, örnpapp\nVerkst dir: Nils-Eric Lennström\nEtableringsår: 1909.\n\nLENSINGS REVISIONSBYRÅ\nAB, KNUT\n\nPnr 632 21\n\nEskilstuna, Kungsg 5. Tel\n016-13 7170. Postgiro 168630\nVerksamhet: Revisionsverksamhet,\nskattekonsultationer, ekonomiska\nutredningar\nAntal anställda: 4\nÅrsomsättning: 200 000\nAktiekapital: 15 000\nStyrelse: Aukt revisor Einar Eklund\n(ordf), revisor Holger Lust (suppl)\nEtableringsår: 1949.\n\nLENTIX WOOD INDUSTRIES\nAB\n\nPnr 38101\n\nKalmar 1. Lagmansg 4. Box 206.\nTel 0480-121 02, 18 2 02. Bankgiro\n655-7912. Postgiro 378595-3. Tga\n\nLentixwood\n\nVerksamhet: Export av förädlade\nträvaror\n\nÅrsomsättning: 2 000000\nAktiekapital: 25 000\nVerkst dir: Lennart A-E Åhlander\nEtableringsår: 1952.\n\nMERKANTIL-TRYCKERIET AB\n\nPnr 75103\n\nUppsala 1, Dragarbrunnsg 65 D. Box\n95. Tel 018-13 2043, 115120.\nBankgiro 80-2129. Postgiro 164780\nAntal anstäUda: 10\nÅrsomsättning: 775 000\nChef: Boktr Birger Söderholm\nEtableringsår: 1925.\n\ngenevads vägmärken ab\n\nPnr 312 02\n\nLaholm 2, Box 34. Tel 0430-702 70.\nBankgiro 296-5432. Postgiro\n72067-2\n\nVerksamhet: Tillverkar väg- o\ntrafikskyltar ,\navstängningsanordning-ar, stolprör, fundament, flaggspel,\nstativ, spett, bockar samt säljer\nblinkfyrar o skyltar för vatten o\navlopp\n\nAntal anställda: 80\nÅrsomsättning: 8 000 000\nAktiekapital: 100 000\nStyrelse: Dir Stig Holmkvist (ordf),\nfru Ing-Margret Holmkvist\nVerkst dir: Stig Holmkvist\nEtableringsår: 1928\nOmbildat till aktiebolag 1962.\n\ngense, ab\n\nPnr 631 04\n\nEskilstuna 1, Box 308. Vilsta. Tel\n016-13 70 80. Bankgiro 60-1342.\nPostgiro 10703. Tga Gense\nVerksamhet: Tillverkar rostfria o\nförsilvrade bordsbestick o\nservisartiklar\n\nAntal anställda: 375\nÅrsomsättning: 20 000 000\nAktiekapital: 1000 000\nStyrelse: Bankdir Axel Roos (ordf),\ndir Carl-S Roos, dir Per\nKullengren, dir Harry Sjöholm\nVerkst dir: Carl-S Roos\nEtableringsår: 1856\nAktiebolag 1898 med ändring 1946.\nModerbolag till AB A Th Broms,\nEskilstuna o Gense Import Ltd\nNorth-vale, N J, USA.\nDotterbolag till Guldsmeds AB\nG A B, Malmö.\n\ngepe ab, händels- &amp;\nINGENIÖRSFIRMAN\n\nPnr 41105\n\nGöteborg. Kronhusg 16. Tel\n031-17 50 35. Bankgiro 420-5415.\nPjost-giro 243560-0. TgaGepeimpex\nVerksamhet: Import agent urer. El-,\n\njärn-, hushålls- o sportartiklar\nAntal anställda: 15\nÅrsomsättning: 11000 000\nChef: Göthe R Peterson\nEtableringsår: 1947.\n\nmalmqvists mek verkstad\n\nPnr 78101\n\nBorlänge l.Box 5. Tel 0243-168 80,\n196 80. Bankgiro 79-1540. Postgiro\n364356\n\nVerksamhet: Tillverkar\nbyggnadskranar o hissar\nAntal anställda: 40\nÅrsomsättning: 2 800 000\nChef: Folke Valdemar Malmqvist\nEtableringsår: 1945.\n\nCONSEIL AB\n\nPnr 182 31\n\nDanderyd, Kevinge strand 7 B. Tel\n08-755 68 98. Postgiro 579174. Tga\n\nConceilab\n\nVerksamhet: Konsulter inom teknik\no ekonomi\nAktiekapital: 5 000\nStyrelseordf: Dir Harry Schein\nVerkst dir: Harry Schein\nEtableringsår: 1961.\n\nRIFA, AB\n\nPnr 16111\n\nBromma 11, Norrbyv 30. Fack. Tel\n08-2626 00. Bankgiro 743-5100.\nPostgiro 193111-2. Tga Elrifa.\nTelex 10308 ELRIFA S\nVeiksamhet: Tillverkar\nkondensatorer, elektronrör, halvledare,\ntungelement samt integrerade kretsar\nAntal anstäUda: 1 600\nÅrsomsättning: 90 000 000\nAktiekapital: 8 000 000\nVerkst din Civiling Torsten Skytt\nEtableringsår: 1942.\n\nGOTENE TRYCKERI AB\n\nPnr 533 00\n\nGötene, Box 104. Tel 0511-516 50.\nBankgiro 219-8562. Postgiro\n292175-7\n\nVerksamhet: Tillverkar\ndatablanketter o stamsatser\nAntal anställda: 60\nÅrsomsättning: 5 000 000\nAktiekapital: 100 000\nVerkst dir: Ole Henriksson\nEtableringsår: 1945.",
    "structured": {
        "1": {
            "company_name": "TORNER & CO KB",
            "address": "Klangfärgsg 11, 421 52 Västra Frölunda",
            "phone_number": "031-29 00 75, 031-29 00 82",
            "bank_details": {
                "bankgiro": "33-7516",
                "postgiro": "41005"
            },
            "activity": "Säljer byggnadsmaterial, utför nybyggnader o reparationer av skorstenar o rökkanaler, taktäckningar o väggbeklädnader",
            "key_personnel": [
                {
                    "name": "Nils Witehall",
                    "position": "Firmatecknare"
                }
            ],
            "establishment_year": 1920
        },
        "2": {
            "company_name": "LÅS-& METALLFABRIKEN, AB",
            "address": "Hovmantorp",
            "phone_number": "0478-400 31, 0478-401 61",
            "bank_details": {
                "bankgiro": "293-3174",
                "postgiro": "284837-2"
            },
            "activity": "Tillverkar lås o metallbeslag för järnvägspersonvagnar, bussar o båtar, delar till båtmotorer, sanitetsgods m m samt metallgjutgods av brons, lödmetall, mässing, zink o lättmetallegeringar. Utför förnickling, förkromning o förkoppring",
            "employees": 45,
            "annual_turnover": 2700000,
            "capital": 150000,
            "key_personnel": [
                {
                    "name": "Disp Georg Mattsson",
                    "position": "Styrelseordförande"
                },
                {
                    "name": "fabr Albin Håkansson",
                    "position": "Styrelseledamot"
                },
                {
                    "name": "fabr Elis Mattsson",
                    "position": "Styrelseledamot"
                },
                {
                    "name": "Georg Mattsson",
                    "position": "Verkställande direktör"
                }
            ],
            "establishment_year": 1943
        },
        "3": {
            "company_name": "STEIN AB, WILLIAM",
            "address": "Bodalsv 47, 18107 Lidingö",
            "phone_number": "08-765 28 20",
            "bank_details": {
                "bankgiro": "165-2494",
                "postgiro": "609882-6"
            },
            "activity": "Säljer maskiner o plastråvaror för plastindustrin samt verkstadsindustrin",
            "employees": 12,
            "annual_turnover": 17500000,
            "capital": 100000,
            "key_personnel": [
                {
                    "name": "Stein Ahlqvist",
                    "position": "Verkställande direktör"
                }
            ],
            "establishment_year": 1960
        },
        "4": {
            "company_name": "LENNSTRÖM, ELEKTRISKA AB",
            "address": "Munkbron 5-7, 11128 Stockholm",
            "phone_number": "08-23 06 10",
            "bank_details": {
                "bankgiro": "568-9294",
                "postgiro": "3895-0"
            },
            "activity": "Utför elektriska installationer, takvärme- o TV-antenanläggningar. Säljer elartiklar (ej armatur, radio o TV)",
            "employees": 50,
            "annual_turnover": 4000000,
            "capital": 200000,
            "establishment_year": 1919
        },
        "5": {
            "company_name": "LENNSTRÖM, ERNST",
            "address": "Waterloog 12, 402 51 Göteborg",
            "phone_number": "031-19 66 07, 031-19 66 08",
            "bank_details": {
                "bankgiro": "506-6832",
                "postgiro": "40408-7"
            },
            "activity": "Tillverkar byggnadspapp o impregnerat omslagspapper. Säljer grovpapper, alla slag",
            "employees": null,
            "annual_turnover": null,
            "capital": null,
            "key_personnel": [
                {
                    "name": "Nils-Eric Lennström",
                    "position": "Verkställande direktör"
                }
            ],
            "establishment_year": 1909
        },
        "6": {
            "company_name": "LENSINGS REVISIONSBYRÅ AB, KNUT",
            "address": "Kungsg 5, 632 21 Eskilstuna",
            "phone_number": "016-13 7170",
            "bank_details": {
                "postgiro": "168630"
            },
            "activity": "Revisionsverksamhet, skattekonsultationer, ekonomiska utredningar",
            "employees": 4,
            "annual_turnover": 200000,
            "capital": 15000,
            "key_personnel": [
                {
                    "name": "Aukt revisor Einar Eklund",
                    "position": "Styrelseordförande"
                },
                {
                    "name": "revisor Holger Lust",
                    "position": "Suppleant"
                }
            ],
            "establishment_year": 1949
        },
        "7": {
            "company_name": "LENTIX WOOD INDUSTRIES AB",
            "address": "Lagmansg 4, 38101 Kalmar",
            "phone_number": "0480-121 02, 0480-18 2 02",
            "bank_details": {
                "bankgiro": "655-7912",
                "postgiro": "378595-3"
            },
            "activity": "Export av förädlade trävaror",
            "annual_turnover": 2000000,
            "capital": 25000,
            "key_personnel": [
                {
                    "name": "Lennart A-E Åhlander",
                    "position": "Verkställande direktör"
                }
            ],
            "establishment_year": 1952
        },
        "8": {
            "company_name": "MERKANTIL-TRYCKERIET AB",
            "address": "Dragarbrunnsg 65 D, 75103 Uppsala",
            "phone_number": "018-13 2043, 018-115120",
            "bank_details": {
                "bankgiro": "80-2129",
                "postgiro": "164780"
            },
            "employees": 10,
            "annual_turnover": 775000,
            "key_personnel": [
                {
                    "name": "Boktr Birger Söderholm",
                    "position": "Chief"
                }
            ],
            "establishment_year": 1925
        },
        "9": {
            "company_name": "genevads vägmärken ab",
            "address": "Box 34, 312 02 Laholm",
            "phone_number": "0430-702 70",
            "bank_details": {
                "bankgiro": "296-5432",
                "postgiro": "72067-2"
            },
            "activity": "Tillverkar väg- o trafikskyltar, avstängningsanordningar, stolprör, fundament, flaggspel, stativ, spett, bockar samt säljer blinkfyrar o skyltar för vatten o avlopp",
            "employees": 80,
            "annual_turnover": 8000000,
            "capital": 100000,
            "key_personnel": [
                {
                    "name": "Dir Stig Holmkvist",
                    "position": "Styrelseordförande"
                },
                {
                    "name": "fru Ing-Margret Holmkvist",
                    "position": null
                },
                {
                    "name": "Stig Holmkvist",
                    "position": "Verkställande direktör"
                }
            ],
            "establishment_year": 1928
        },
        "10": {
            "company_name": "gense, ab",
            "address": "Box 308, Vilsta, 631 04 Eskilstuna",
            "phone_number": "016-13 70 80",
            "bank_details": {
                "bankgiro": "60-1342",
                "postgiro": "10703"
            },
            "activity": "Tillverkar rostfria o försilvrade bordsbestick o servisartiklar",
            "employees": 375,
            "annual_turnover": 20000000,
            "capital": 1000000,
            "key_personnel": [
                {
                    "name": "Bankdir Axel Roos",
                    "position": "Styrelseordförande"
                },
                {
                    "name": "dir Carl-S Roos",
                    "position": "Styrelseledamot"
                },
                {
                    "name": "dir Per Kullengren",
                    "position": "Styrelseledamot"
                },
                {
                    "name": "dir Harry Sjöholm",
                    "position": "Styrelseledamot"
                },
                {
                    "name": "Carl-S Roos",
                    "position": "Verkställande direktör"
                }
            ],
            "establishment_year": 1856
        },
        "11": {
            "company_name": "gepe ab, händels- & INGENIÖRSFIRMAN",
            "address": "Kronhusg 16, 41105 Göteborg",
            "phone_number": "031-17 50 35",
            "bank_details": {
                "bankgiro": "420-5415",
                "postgiro": "243560-0"
            },
            "activity": "Import agenturer. El-, järn-, hushålls- o sportartiklar",
            "employees": 15,
            "annual_turnover": 11000000,
            "key_personnel": [
                {
                    "name": "Göthe R Peterson",
                    "position": "Chef"
                }
            ],
            "establishment_year": 1947
        },
        "12": {
            "company_name": "malmqvists mek verkstad",
            "address": "Box 5, 78101 Borlänge",
            "phone_number": "0243-168 80, 0243-196 80",
            "bank_details": {
                "bankgiro": "79-1540",
                "postgiro": "364356"
            },
            "activity": "Tillverkar byggnadskranar o hissar",
            "employees": 40,
            "annual_turnover": 2800000,
            "key_personnel": [
                {
                    "name": "Folke Valdemar Malmqvist",
                    "position": "Chef"
                }
            ],
            "establishment_year": 1945
        },
        "13": {
            "company_name": "CONSEIL AB",
            "address": "Kevinge strand 7 B, 182 31 Danderyd",
            "phone_number": "08-755 68 98",
            "bank_details": {
                "postgiro": "579174"
            },
            "activity": "Konsulter inom teknik o ekonomi",
            "capital": 5000,
            "key_personnel": [
                {
                    "name": "Dir Harry Schein",
                    "position": "Styrelseordförande"
                },
                {
                    "name": "Harry Schein",
                    "position": "Verkställande direktör"
                }
            ],
            "establishment_year": 1961
        },
        "14": {
            "company_name": "RIFA, AB",
            "address": "Norrbyv 30, 16111 Bromma",
            "phone_number": "08-2626 00",
            "bank_details": {
                "bankgiro": "743-5100",
                "postgiro": "193111-2"
            },
            "activity": "Tillverkar kondensatorer, elektronrör, halvledare, tungelement samt integrerade kretsar",
            "employees": 1600,
            "annual_turnover": 90000000,
            "capital": 8000000,
            "key_personnel": [
                {
                    "name": "Civiling Torsten Skytt",
                    "position": "Verkställande direktör"
                }
            ],
            "establishment_year": 1942
        },
        "15": {
            "company_name": "GOTENE TRYCKERI AB",
            "address": "Box 104, 533 00 Götene",
            "phone_number": "0511-516 50",
            "bank_details": {
                "bankgiro": "219-8562",
                "postgiro": "292175-7"
            },
            "activity": "Tillverkar datablanketter o stamsatser",
            "employees": 60,
            "annual_turnover": 5000000,
            "capital": 100000,
            "key_personnel": [
                {
                    "name": "Ole Henriksson",
                    "position": "Verkställande direktör"
                }
            ],
            "establishment_year": 1945
        }
    }
}