{
    "original": "GASOLTEKNIK AB\n\nPnr 701 03\n\nÖrebro 1, Gryt, Gällersta. Box 142.\nTel 019-23 92 60, 23 92 61.\nBankgiro 815-9097. Postgiro 15433-6\nVerksamhet: Specialutrustning för\ngasolbranschen, montage, service\no tillverkning\nAntal anstäUda: 20\nÅrsomsättning: 1 300 000\nAktiekapital: 5000\nVerkst dir: Ing Olof Lindell\nEtableringsår: 1963.\n\nfalk-läder ab\n\nPnr 31100\n\nFalkenberg. Tel 0346-142 80.\nBankgiro 425-7457. Postgiro 25879-8.\nTga Läder. Telex 38083\nVerksamhet: Skoovanläder,\ntoffel-läder o skoförnödenheter\nAntal anstäUda: 100\nÅrsomsättning: 12 000 000\nAktiekapital: 700 000\nVerkst dir: Bengt Nordström\nEtableringsår: 1835.\n\nINTERMERCUR KB\n\nPnr 142 00\n\nTrångsund, Tornslingan 45. Tel\n08-77144 55. Bankgiro 748-9131.\nPostgiro 82839-2. Tga Interstock\nVerksamhet: Organisation,\nmarketing, exportkonsultation,\nexposervice. Observatörer o kunder i 9\nländer. Bland kunder Ford Motor Co\nAntal anstäUda: 49\nKapital: 35 000\n\nStyrelse: Dipl-phil B Gawrilo\nwitsch-Marinkowitsch (ordf),\ncivilekonom R Nilsson, dr S B Ericsson,\ncivüing A Palmér,\ndiplomjurist-diplomekonom D Marinkowitsch, ark\nJ Köhler\n\nChef: Dipl-phil Bisa\nGawrilowitsch-Marinkowitsch\nEtableringsår: 1964\nKommanditbolagl967. Svenskt bolag.\nDotterbolag: AB\nServicebyrå-Revision &amp; Jurudik.\n\nINTERMITENT AB\n\nPnr 44080\n\nEUös. Tel 0304-503 88, 504 71\nVerksamhet: Tillverkar o säljer\nmanskaps- o kontorsvagnar samt\nskåpbyggnationer på lastbilar i\nglasfiberarmerad plast\nAntal anstäUda: 35\nÅrsomsättning: 2 800 000\nAktiekapital: 50 000\nVerkst dir: Ing Hugo Samuelsson\nEtableringsår: 1964.\n\nINTERNATIONAL CANDY\nIMPORT AB\n\nPnr 400 80\n\nGöteborgs Frihamn, Fack. Tel\n031-23 86 06,23 86 07. Postgiro425200.\nTga Candyport\n\nVerksamhet: Importerar choklad o\nkonfektyrer i fast räkning för\nförsäljning till grossister över hela\nlandet\n\nAntal anstäUda: 4\nÅrsomsättning: 5 000 000\nAktiekapital: 50000\nStyrelse: Adv Kjell Holmqvist\n(ordf), dir Tage Derning\nVerkst dir: Tage Derning\nKamrer: Örjan Bäckström\nEtableringsår: 1950.\n\nINTERNATIONAL CONSUMER\nSERVICES AB\n\nPnr 141 22\n\nHuddinge 1, Sjödalstorget 1. Box\n1060. Tel 08-757 15 50 , 757 60 11.\nBankgiro 62-6112. Postgiro 545150.\nTelex 1274 IMSERV S.\nTga Swimserv, Stockholm\nVerksamhet: Skoreparationer,\nnyckeltillverkning m m\nAntal anstäUda: 95\nÅrsomsättning: 5 700 000\nAktiekapital: 250 000\nVerkst dir: Stig Henningsson\nEtableringsår: 1960.\n\nTEDAB, AB\n\nPnr 414 63\n\nGöteborg, Bang 16. Tel\n031-24 49 55, 1406 22. Bankgiro\n51-2715. Tga Dahlship\nVerksamhet: Tillverkar verktyg,\nprototyper, kugghjul\nAntal anställda: 20\nÅrsomsättning: 1400 000\nAktiekapital: 40 000\nVerkst dir: E Dahl\nEtableringsår: 1957.\n\nTYRINGE.VERKEN\n\nPnr 282 00\n\nTyringe, Box 171. Tel 0451-514 50.\nBankgiro 288-9608. Postgiro\n29 3532-8\n\nVerksamhet: Tillverkar\nventilationstillbehör, pallställningar.\nLegotillverkning. Utför o\nprojekterar ventilationsanläggningar\nAvdelningskontor 20123 Malmö 1,\nBox 367. Skeppsbron 5. Tel\n040-727 10. Chef: Disp Bertil\nWUeg-gertz\n\nFilial: 29103 Kristianstad 3,\nBox 3056. Tel 044-119173\nAntal anställda: 150\nÅrsomsättning: 9000 000\nChef: Fabrikör Claes Eliasson\nProduktions- o inköpschef: Bertil\nVüeggertz\nEtableringsår: 1949.\n\nAFFÄRSREKLAM\n\nPnr 803 57\n\nGävle, Norrtullsg 18. Tel\n026-1124 00. Postgiro 471547-0\nVerksamhet: Säljer skyltar av alla\nslag\n\nChef: G Ahlqvist.\n\nAFFÄRSSYSTEM, AB\n\nPnr 212 28\n\nMalmö, Scheeleg 7. Tel\n040-93 5070. Bankgiro 870-2409.\nPostgiro 148621-6. Tga Affärssystem.\nTelex 32681 ABA S\nVerksamhet: Säljer system,\nkontorsmöbler, kontorsvaror,\nritut-rustning, skolmaterial\nFörsäljning o utställning: 111 60\nStockholm, Drott ni ngg 81. Tel\n08-2304 30\n\n412 53 Göteborg, Hedåsg 5. Tel\n\n031-207125\n\nAntal anställda: 80\n\nAktiekapital: 55 000\n\nVerkst dir: Erie Roskvist\n\nEtableringsår: 1942.\n\nBERG OCH NYCANDER AB\n\nPnr 11123\n\nStockholm, Barnhusg 3. Tel\n08-10 75 65, 23 2500. Bankgiro\n721-7573. Postgiro 3902-4. Tga\nBergs-jern\n\nVerksamhet: Agentur o partiaffär i\njärnmanufaktur. Suffolk, Atco,\nQualcast gräsklippningsmaskiner.\nFresco vridmaskiner\nVarunamn: Atco, Fresco, Qualcast,\nSuffolk\n\nAktiekapital: 50 000\nEtableringsår: 1928.\n\nBERG &amp; STARCK,\nINGENJÖRSFIRMAN\n\nPnr 761 00\n\nNorrtälje, Hantverkareg 21. Box\n40. Tel 0176-10220, 120 22\nVerksamhet: Konstruktion,\nprojektering o tillverkning\nAntal anställda: 16\nÅrsomsättning: 2 250 000\nÄgare o chefer: Ing Folke Berg,\ning Gösta Starck\nEtableringsår: 1958.\n\nkirurgiska instrument o apparater\n\nFilial: 170 20 Kallhäll, Lädersätt-\n\nrav 21. Tel 0758-39604\n\n902 35 Umeå, Rågången 10 A. Tel\n\n090-12 26 43\n\nAktiekapital: 75 000\n\nVerkst dir: I Harlid\n\nEtableringsår: 1958.\n\nHARLITZ &amp; CO AB,\nINGENIÖRSFIRMAN ALVAR\n\nPnr 462 00\n\nVänersborg, Regementsg. Tel\n0521-11032. Bankgiro 88-8791.\nPostgiro 94328. Tga Kroma\nVerksamhet: Metallgjutgods i\nkoppar o kopparlegeringar.\nStyckevikt upp till 1 000 kg. Fluss- o\nreningsmedel för metall\nVarunamn: Kroma, Tempyrex\nAktiekapital: 40 000\nVerkst dir: Alvar Harlitz\nEtableringsår: 1933.\n\nHARRION AKTIEBOLAG\nHARRY GRANDIN\n\nPnr 251 03\n\nHelsingborg 1, Box 130.\nHöga-stensg 2. Tel 042-614 30. Bankgiro\n863-4081. Postgiro 265200-6. Tga\nHarrion. Telex 72244\nVerksamhet: Säljer ärmlappar,\nsorgband o sorgknappar. Konstläder,\nplastväv o måttband från Stamm AG\nEglisau, Schweiz, sy- o stoppnålar\nfrån Milward, jumperstickor\nStud-ley, England, Schmetz\nsymaskinsnålar. Verktyg för sko- o\ntapetserar industrin\nAktiekapital: 60 000\nVerkst dir: Harry Grandin.\n\nHARTFELDT SCREEN\nPRINTING MACHINES AB\n\nPnr 250 05\n\nHelsingborg 5, Box 5063.\nHöga-stensg 16. Tel 042-614 20.\nBankgiro 653-0158. Postgiro 97020. Tga\nHartfeldt\n\nVerksamhet: Tillverkar\nscreentryck-maskiner\n\nAntal anställda: 8\nÅrsomsättning: 1500 000\nAktiekapital: 30 000\nVerkst dir: Erie Hartfeldt-Johansson\nEtableringsår: 1963.\n\nHARTFELDT SERIGRAFISKA\nTRYCKERI AB\n\nPnr 250 05\n\nHelsingborg 5, Box 5063.\nHöga-stensg 16. Tel 042-614 20.\nBankgiro 67-6418. Postgiro 446432. Tga\nHartfeldt\n\nVerksamhet: Screentryckeri.\nAffischer, skyltar, dekaler etc\nAntal anstäUda: 10\nÅrsomsättning: 1500 000\nAktiekapital: 20 000\nVerkst dir: EHc Hartfeldt-Johansson\nEtableringsår: 1963.\n\nHARTIG FLIESBERG\nFORETAGEN AB\n\nse AB Hugo Hartig respektive\nIngenjörsfirman Fliesberg AB.\n\nHAS\n\nHARTIG, AKTIEBOLAGET\nHUGO\n\n(Ingår i Hartig Fliesberg\nFöretagen AB)\nPnr 103 81\n\nStockholm 7, Box 7044. Nybrog 3.\nTel 08-234120. Bankgiro 160-5377.\nPostgiro 2674-0. Tga Hartigus.\nTelex 19102, 21120 HARTIG S\nVerksamhet: Tillverkar o säljer\nElgotenpåsar, -folier o -slang\n(po-lyten), Elgofan PT, Elgofilm MSAT\nmed o utan tryck, Elgoceta (acetat),\nElgopropen (polypropylen),\nlaminerade folier. Export av cellulosa,\npapper, kemiska produkter. Import\nav specialcellulosa, -papper,\nstärkelse, vax, hot melt\nFabrik o avdelningskontor:\n402 74 Göteborg 8, Box 8965.\nKvil-leg 26. Tel 031-51 35 40. Tga\nHartigus. Telex 21120 HARTIG S\nAntal anstäUda: 52\nAktiekapital: 1000 000\nVerkst dir: Stig H Arvidson\nEtableringsår: 1907.\n\nSVENSKA RAYON AB\n\nPnr 660 50\n\nVålberg, Älvenäs. Tel 054-421 00.\nBankgiro34-4447. Postgiro 192409.\nTga Rayon, Karlstad.\nTelex 66086 RAYON S\nVerksamhet: Tillverkar rayonull,\nrayoncordprodukter o nylongarn\nVarunamn: Artilana, Elaston,\nSwelan, Älvenäs Nylon\nAntal anställda: 1200\n\nÅrsomsättning: 110 000 000\nAktiekapital: 12 000 000\nVerkst din Civiling Olle Johansson\nEtableringsår: 1941.\n\nNORDICOLD AB\n\nPnr 43080\n\nHovås, Vassgången 2. Tel\n031-28 54 66, 28 54 77. Bankgiro\n226-1915. Postgiro 230645-4. Tga\nNor-dicold\n\nVerksamhet: Säljer detaljer för kyl-,\nvärme- o elindustri samt\nhögtrycks-tvättaggregat för bilservice m m\nVarunamn: Elco, Jupiter\nChef: Tage Jannemark\nEtableringsår: 1968.",
    "structured": {
        "1": {
            "company_name": "GASOLTEKNIK AB",
            "address": "Örebro 1, Gryt, Gällersta. Box 142.",
            "phone_number": "019-23 92 60, 23 92 61",
            "bank_details": {
                "bankgiro": "815-9097",
                "postgiro": "15433-6"
            },
            "activity": "Specialutrustning för gasolbranschen, montage, service o tillverkning",
            "employees": 20,
            "annual_turnover": 1300000,
            "capital": 5000,
            "key_personnel": [
                {
                    "name": "Ing Olof Lindell",
                    "position": "Verkst dir"
                }
            ],
            "establishment_year": 1963
        },
        "2": {
            "company_name": "falk-läder ab",
            "address": "Falkenberg",
            "phone_number": "0346-142 80",
            "bank_details": {
                "bankgiro": "425-7457",
                "postgiro": "25879-8"
            },
            "activity": "Skoovanläder, toffel-läder o skoförnödenheter",
            "employees": 100,
            "annual_turnover": 12000000,
            "capital": 700000,
            "key_personnel": [
                {
                    "name": "Bengt Nordström",
                    "position": "Verkst dir"
                }
            ],
            "establishment_year": 1835
        },
        "3": {
            "company_name": "INTERMERCUR KB",
            "address": "Trångsund, Tornslingan 45",
            "phone_number": "08-77144 55",
            "bank_details": {
                "bankgiro": "748-9131",
                "postgiro": "82839-2"
            },
            "activity": "Organisation, marketing, exportkonsultation, exposervice. Observatörer o kunder i 9 länder. Bland kunder Ford Motor Co",
            "employees": 49,
            "capital": 35000,
            "key_personnel": [
                {
                    "name": "Dipl-phil B Gawrilowitsch-Marinkowitsch",
                    "position": "Styrelseordförande"
                },
                {
                    "name": "Dia S B Ericsson",
                    "position": "Styrelsemedlem"
                }
            ],
            "establishment_year": 1964
        },
        "4": {
            "company_name": "INTERMITENT AB",
            "address": "EUös",
            "phone_number": "0304-503 88, 504 71",
            "activity": "Tillverkar o säljer manskaps- o kontorsvagnar samt skåpbyggnationer på lastbilar i glasfiberarmerad plast",
            "employees": 35,
            "annual_turnover": 2800000,
            "capital": 50000,
            "key_personnel": [
                {
                    "name": "Ing Hugo Samuelsson",
                    "position": "Verkst dir"
                }
            ],
            "establishment_year": 1964
        },
        "5": {
            "company_name": "INTERNATIONAL CANDY IMPORT AB",
            "address": "Göteborgs Frihamn, Fack",
            "phone_number": "031-23 86 06,23 86 07",
            "bank_details": {
                "postgiro": "425200"
            },
            "activity": "Importerar choklad o konfektyrer i fast räkning för försäljning till grossister över hela landet",
            "employees": 4,
            "annual_turnover": 5000000,
            "capital": 50000,
            "key_personnel": [
                {
                    "name": "Adv Kjell Holmqvist",
                    "position": "Styrelseordförande"
                },
                {
                    "name": "Tage Derning",
                    "position": "Verkst dir"
                }
            ],
            "establishment_year": 1950
        },
        "6": {
            "company_name": "INTERNATIONAL CONSUMER SERVICES AB",
            "address": "Huddinge 1, Sjödalstorget 1. Box 1060",
            "phone_number": "08-757 15 50 , 757 60 11",
            "bank_details": {
                "bankgiro": "62-6112",
                "postgiro": "545150"
            },
            "activity": "Skoreparationer, nyckeltillverkning m m",
            "employees": 95,
            "annual_turnover": 5700000,
            "capital": 250000,
            "key_personnel": [
                {
                    "name": "Stig Henningsson",
                    "position": "Verkst dir"
                }
            ],
            "establishment_year": 1960
        },
        "7": {
            "company_name": "TEDAB, AB",
            "address": "Göteborg, Bang 16",
            "phone_number": "031-24 49 55, 1406 22",
            "bank_details": {
                "bankgiro": "51-2715"
            },
            "activity": "Tillverkar verktyg, prototyper, kugghjul",
            "employees": 20,
            "annual_turnover": 1400000,
            "capital": 40000,
            "key_personnel": [
                {
                    "name": "E Dahl",
                    "position": "Verkst dir"
                }
            ],
            "establishment_year": 1957
        },
        "8": {
            "company_name": "TYRINGE.VERKEN",
            "address": "Tyringe, Box 171",
            "phone_number": "0451-514 50",
            "bank_details": {
                "bankgiro": "288-9608",
                "postgiro": "293532-8"
            },
            "activity": "Tillverkar ventilationstillbehör, pallställningar. Legotillverkning. Utför o projekterar ventilationsanläggningar",
            "employees": 150,
            "annual_turnover": 9000000,
            "key_personnel": [
                {
                    "name": "Bertil WUeg-gertz",
                    "position": "Avdelningskontorschef, Tyringe"
                },
                {
                    "name": "Claes Eliasson",
                    "position": "Fabrikschef"
                }
            ],
            "establishment_year": 1949
        },
        "9": {
            "company_name": "AFFÄRSREKLAM",
            "address": "Gävle, Norrtullsg 18",
            "phone_number": "026-1124 00",
            "bank_details": {
                "postgiro": "471547-0"
            },
            "activity": "Säljer skyltar av alla slag",
            "key_personnel": [
                {
                    "name": "G Ahlqvist",
                    "position": "Chef"
                }
            ]
        },
        "10": {
            "company_name": "AFFÄRSSYSTEM, AB",
            "address": "Malmö, Scheeleg 7",
            "phone_number": "040-93 5070",
            "bank_details": {
                "bankgiro": "870-2409",
                "postgiro": "148621-6"
            },
            "activity": "Säljer system, kontorsmöbler, kontorsvaror, ritutrustning, skolmaterial",
            "employees": 80,
            "capital": 55000,
            "key_personnel": [
                {
                    "name": "Erie Roskvist",
                    "position": "Verkst dir"
                }
            ],
            "establishment_year": 1942
        },
        "11": {
            "company_name": "BERG OCH NYCANDER AB",
            "address": "Stockholm, Barnhusg 3",
            "phone_number": "08-10 75 65, 23 2500",
            "bank_details": {
                "bankgiro": "721-7573",
                "postgiro": "3902-4"
            },
            "activity": "Agentur o partiaffär i järnmanufaktur",
            "capital": 50000,
            "establishment_year": 1928
        },
        "12": {
            "company_name": "BERG & STARCK, INGENJÖRSFIRMAN",
            "address": "Norrtälje, Hantverkareg 21. Box 40",
            "phone_number": "0176-10220, 120 22",
            "activity": "Konstruktion, projektering o tillverkning",
            "employees": 16,
            "annual_turnover": 2250000,
            "key_personnel": [
                {
                    "name": "Ing Folke Berg",
                    "position": "Ägare"
                },
                {
                    "name": "Ing Gösta Starck",
                    "position": "Ägare"
                }
            ],
            "establishment_year": 1958
        },
        "13": {
            "company_name": "HARLITZ & CO AB, INGENIÖRSFIRMAN ALVAR",
            "address": "Vänersborg, Regementsg",
            "phone_number": "0521-11032",
            "bank_details": {
                "bankgiro": "88-8791",
                "postgiro": "94328"
            },
            "activity": "Metallgjutgods i koppar o kopparlegeringar. Fluss- o reningsmedel för metall",
            "varunamn": "Kroma, Tempyrex",
            "capital": 40000,
            "key_personnel": [
                {
                    "name": "Alvar Harlitz",
                    "position": "Verkst dir"
                }
            ],
            "establishment_year": 1933
        },
        "14": {
            "company_name": "HARRION AKTIEBOLAG HARRY GRANDIN",
            "address": "Helsingborg 1, Box 130",
            "phone_number": "042-614 30",
            "bank_details": {
                "bankgiro": "863-4081",
                "postgiro": "265200-6"
            },
            "activity": "Säljer ärmlappar, sorgband o sorgknappar. Konstläder, plastväv o måttband från Stamm AG Eglisau, Schweiz, sy- o stoppnålar från Milward, jumperstickor Stud-ley, England, Schmetz symaskinsnålar. Verktyg för sko- o tapetserar industrin",
            "varunamn": "Harrion",
            "capital": 60000,
            "key_personnel": [
                {
                    "name": "Harry Grandin",
                    "position": "Verkst dir"
                }
            ]
        },
        "15": {
            "company_name": "HARTFELDT SCREEN PRINTING MACHINES AB",
            "address": "Helsingborg 5, Box 5063",
            "phone_number": "042-614 20",
            "bank_details": {
                "bankgiro": "653-0158",
                "postgiro": "97020"
            },
            "activity": "Tillverkar screentryck-maskiner",
            "employees": 8,
            "annual_turnover": 1500000,
            "capital": 30000,
            "key_personnel": [
                {
                    "name": "Erie Hartfeldt-Johansson",
                    "position": "Verkst dir"
                }
            ],
            "establishment_year": 1963
        },
        "16": {
            "company_name": "HARTFELDT SERIGRAFISKA TRYCKERI AB",
            "address": "Helsingborg 5, Box 5063",
            "phone_number": "042-614 20",
            "bank_details": {
                "bankgiro": "67-6418",
                "postgiro": "446432"
            },
            "activity": "Screentryckeri. Affischer, skyltar, dekaler etc",
            "employees": 10,
            "annual_turnover": 1500000,
            "capital": 20000,
            "key_personnel": [
                {
                    "name": "EHc Hartfeldt-Johansson",
                    "position": "Verkst dir"
                }
            ],
            "establishment_year": 1963
        },
        "17": {
            "company_name": "HARTIG FLIESBERG FORETAGEN AB",
            "activity": "Ingen information"
        },
        "18": {
            "company_name": "HARTIG, AKTIEBOLAGET HUGO",
            "address": "Stockholm 7, Box 7044. Nybrog 3",
            "phone_number": "08-234120",
            "bank_details": {
                "bankgiro": "160-5377",
                "postgiro": "2674-0"
            },
            "activity": "Tillverkar o säljer Elgotenpåsar, -folier o -slang (polyten), Elgofan PT, Elgofilm MSAT med o utan tryck, Elgoceta (acetat), Elgopropen (polypropylen), laminerade folier. Export av cellulosa, papper, kemiska produkter. Import av specialcellulosa, -papper, stärkelse, vax, hot melt",
            "fabrik_avdelnar": "402 74 Göteborg 8, Box 8965. Kvill-leg 26",
            "phone_fabrik_av": "031-51 35 40",
            "employees": 52,
            "capital": 1000000,
            "key_personnel": [
                {
                    "name": "Stig H Arvidson",
                    "position": "Verkst dir"
                }
            ],
            "establishment_year": 1907
        },
        "19": {
            "company_name": "SVENSKA RAYON AB",
            "address": "Vålberg, Älvenäs",
            "phone_number": "054-421 00",
            "bank_details": {
                "bankgiro": "34-4447",
                "postgiro": "192409"
            },
            "activity": "Tillverkar rayonull, rayoncordprodukter o nylongarn",
            "varunamn": "Artilana, Elaston, Swelan, Älvenäs Nylon",
            "employees": 1200,
            "annual_turnover": 110000000,
            "capital": 12000000,
            "key_personnel": [
                {
                    "name": "Civiling Olle Johansson",
                    "position": "Verkst dir"
                }
            ],
            "establishment_year": 1941
        },
        "20": {
            "company_name": "NORDICOLD AB",
            "address": "Hovås, Vassgången 2",
            "phone_number": "031-28 54 66, 28 54 77",
            "bank_details": {
                "bankgiro": "226-1915",
                "postgiro": "230645-4"
            },
            "activity": "Säljer detaljer för kyl-, värme- o elindustri samt högtryckstvättaggregat för bilservice m m",
            "varunamn": "Elco, Jupiter",
            "key_personnel": [
                {
                    "name": "Tage Jannemark",
                    "position": "Chef"
                }
            ],
            "establishment_year": 1968
        }
    }
}