{
    "original": "VÄSTAN TRYCKERI AB\n\nPnr 402 32\n\nGöteborg 7, Andra Långg 20. Box\n7124. Tel 031-12 98 48. Bankgiro\n33-7532. Postgiro 242914\nVerksamhet: Framställer\ntrycksaker, tidskrifter o böcker\nAktiekapital: 175 000\nVerkst dir: Nils Kullgren\nEtableringsår: 1948.\n\nVÄSTANFORS INDUSTRIER.\nAB\n\nPnr 773 00\n\nFagersta. S Linian. Tel\n0223-129 25. Bankgiro 81-2422. Postgiro\n268288\n\nVerksamhet: Tillverkning av\nmonteringsfärdiga stålbyggnader\nAntal anställda: 120\nÅrsomsättning: 14 500 000\nAktiekapital: 1250 000\nVerkst dir: Olof Stråth\nEtableringsår: 1952.\n\nHULTÉN AB, A\n\nPnr 21444\n\nMalmö, N Grängesbergsg 10. Tel\n040-804 40. Bankgiro 644-0093.\nPostgiro 38117-8\n\nVerksamhet: Tillverkar inredningar\nför banker, butiker, varuhus,\nskolor, sjukhus, kontor, hotell o\nrestauranger m fi\nAntal anställda: 45\nAktiekapital: 80 000\nStyrelse: Adv Erik Grenfors (ordf),\nfabr Sture Hultén, fabrikschef\nAnders Hultén, ark Lars Hultén\nVeikst din Ark Lars Hultén\nFabrikschef: Anders Hultén\nEtableringsår 1893\nOmbildat till aktiebolag 1947.\n\nHULTÉN AB, ASSAR\n\nPnr 400 72\n\nGöteborg 22, Gustaf Dalénsg 13.\nBox 22031. Tel 031-23 7318,\n23 73 1 9. Bankgiro 513-1065.\nPostgiro 429491-4. TgaHultenia. Telex\n20920\n\nVerksamhet: Säljer järnvaror en\ngros, speciellt alla slag av skruv\no mutter\n\nAktiekapital: 100000\nVerkst dir: Assar Hultén\nEtableringsår: 1955\nOmbildat till aktiebolag 1961.\n\nHULTHËNS INGENJORSBYRÄ\nAB, HARALD\n\nPnr 65109\n\nKarlstad 1, Drottningg 18. Box 584.\nTel 054-1151 35. Bankgiro\n344-5624. Postgiro 79409-9\nVerksamhet: Rådgivande\nverksamhet för väg-, bro- o husbyggnad\nAntal anställda: 40\nÅrsomsättning: 2 000 000\nAktiekapital: 100000\nVeikst dir: Lennart Carlsson\nEtableringsår 1930\nOmbildat till aktiebolag 1963.\n\nHULTHÉN, AB HENRY\n\nPnr 25102\n\nHelsingborg 1, Box 94.\nDrottningg 31. Tel 042-13 94 75.\nBankgiro 438-0549. Postgiro 449331-8.\nTga Kitchenhenry\nVerksamhet: Tillverkar o säljer\nköksredskap i metall samt\nutegril-lar o campingrökar\nVarunamn: Henry’s\nAktiekapital: 10 000\nStyrelse: Fru Maj-Britt Hulthén\n(ordf), dir Henry Hulthén, fabr\nOskar Pauls son\nVerkst dir: Henry Hulthén\nEtableringsår: 1954\nOmbildat till aktiebolag 1962.\n\nHULTÉN AB, MALTE\n\nPnr 214 44\n\nMalmö, N Grängesbergsg 8. Tel\n040-837 00 , 837 01. Bankgiro\n644-0101. Postgiro 37508-9. Tga\nSkinnkonfektion\n\nVeiksamhet: Tillverkar\nskinnkläder, alla slags modeller i dam,\nherr, flick o goss\nAntal anställda: 100\nÅrsomsättning: 4 500 000\nAktiekapital: 100 000\nStyrelse: Fabr Malte Hultén (ordf),\ndir Ola Hultén, prof Bo Lennart\nAdamson\n\nVerkst dir: Ola Hultén\nEtableringsår 1927.\n\nSVENSKA von ROLL AB\n\nPnr 102 32\n\nStockholm 6, Box 6112. Västman-\n\nnag 41. Tel 08-34 03 55. Bankgiro\n296-7552\n\nVerksamhet: Säljer o projekterar\nsopförbränningsanläggningar av\nsystem Von Roll till industrier,\nstäder o kommuner i Sverige\nVarunamn: Svenska Von Roll\nAktiekapital: 100000\nStyrelse: Dir Ragnar ödman (ordf),\nbankdir Karl Einar Rasmusson,\ndir René Starke\nVerkst dir. Hans Ström\nEtableringsår: 1966.\n\nUNIFOS KEMI AB\n\nPnr 444 00\n\nStenungsund, Box 44. Tel\n0303-715 20. Bankgiro 16-0622. Postgiro\n651170. Telex 2402. Tga Unifos\nVerksamhet: Tillverkar polyeten,\nbasråvara för plastindustrin\nAntal anställda: 280\nÅrsomsättning: 126 000 000\nAktikapital: 48 000 000\nVeikst dir: Bengt Lidén\nFörsäljn-dir: Ulf Jacobson\nTekn-dir: R Schwarz\nEkonomidir: L Crafoord\nEtableringsår: 1961\nDotterbolag: Unifos Kemi A/S,\nKöpenhamn, Unifos Kjemi Norsk A/S,\nOslo.\n\nUNION CARBIDE NORDEN AB\n\nPnr 46101\n\nTrollhättan 1. Huvudkontor Box 79.\nTel 0520-128 15. Bankgiro\n892-5570. Postgiro 34661-9. Tga\nUni-carbide. Telex 42045\nVerksamhet: Tillverkar o säljer\ngrafitelektroder, grafitanoder,\ngrafitdetaljer o grafitpulver. Säljer\ndessutom bl a kolelektroder o\nka-todblock samt apparatur av\nKAR-BATE, impregnerad grafit\nAvdelningskontor: 11121 Stockholm,\nDrottning g 49. Tel 08-232710.\nTelex 10039. Tga Unicarbide. Säljer\nkemikalier, plaster, silikoner o\nkonsumentartiklar. Chef: Gunnar Björck\nAntal anställda: 125\nÅrsomsättning: 43 000 000\nAktiekapital: 1560 000\nStyrelse: Adv Bengt Westerling\n(ordf), dir Leif Karlsen, dir Sven\nTrued, J R Paus\nVerkst dir: Leif Karlsen\nFabrikschef: Allan Lundh\nEkonomichef: Ture Eriksson\nFörsäljn-chef kol- o\ngrafitproduk-ter: Ingvar Johansson\nEtableringsår: 1917\nÄges av Union Carbide\nCorporation, USA.\n\nUNION AB, METALL.\nFABRIKEN\n\nPnr 330 20\n\nAnderstorp, Industrig 18. Box 14.\nTel 0371-150 94. Bankgiro\n488-1264. Postgiro 97576-3\nVerksamhet: Tillverkar klippta,\npressade o dragna massartiklar i\njärn o metall till bl a bakelit- o\nradioindustrin, svenskremspännen\nAntal anställda: 13\nÅrsomsättning: 1800 000\nAktiekapital: 60 000\nVerkst dir: Stig Sjögren\nEtableringsår: 1935\nOmbildat till aktiebolag 1954.\n\nUNION AB, PACKNINGS.\nFABRIKEN\n\nPnr 104 65\n\nStockholm 15, Homsg 24. Box\n15035. Tel 08-44 68 68, 44 78 58.\nBankgiro 569-8618. Postgiro\n\n357525-5. Tga Unionpackning.\nTelex 1839\n\nVerksamhet: Tillverkar alla slags\nmanschetter o packningar mm\nAntal anställda: 25\nÅrsomsättning: 2 000 000\nAktiekapital: 50 000\nVerkst dir. Disp H U Butschkan\nEtableringsår: 1899.\n\nRENOLD SVENSKA AB\n\nPnr 104 30\n\nStockholm 45, Drottningg 99. Box\n45093. Tel 08-34 92 20. Bankgiro\n632-0493. Postgiro 351820-6.\nTga Rensven. Telex 17515\nVerksamhet: Marknadsför kedjor,\nväxlar, variatorer, kopplingar o\nandra produkter för kraftöverföring\no mekanisk hantering från\nRenold-gruppen\n\nUtställning/Kundmottagning:\n\nStockholm, Kungstensg 36\nFilial: 21148 Malmö, Erik\nDahl-bergsg 18. Tel 040-97 1 0 2 0\nAktiekapital: 600 000\nVerkst dir: J P Tylecote\nEtableringsår: 1922\nNuvarande namn 1969.\n\nRENSTIG AB, ÅKE\n\nPnr 252 20\n\nHelsingborg, Stortorget 13. Tel\n042-1804 90. Bankgiro 863-9858.\nPostgiro 291085-9. Tga Reda\nVerksamhet: Tillverkar o säljer alls\nslag av listverk i furu o lövträ\nAntal anstäUda: 30\nÅrsomsättning: 5 000 000\nChef: Dir Ake Renstig\nEtableringsår: 1953.\n\nTOR\n\nÅrsomsättning: 12 000 000\nAktiekapital: 500 000\nVerkst dir: Civiling Sverker Wåhlin\nEtableringsår: 1898\nDotterbolag: AB Kiruna Bryggeri.\n\nTOPECO, FABRIKS AB\n\nPnr 523 00\n\nUlricehamn, Storg 69. Pack. Tel\n0321-123 20. Bankgiro 532-8505.\nPostgiro 338770-1\nVerksamhet: Tillverkar o säljer\nstrumpor\n\nFörsäljningskontor för\nStockholmsdistriktet: 111 83 Stockholm.\nApel-bergsg 58. Tel 08-11 67 75.\nPlatschef: köpman Alf Werdin\nVarunamn: Topeco\nAntal anställda: 70\nÅrsomsättning: 5 000 000\nAktiekapital: 200 000\nStyrelse: Adv Arne Gullack (ordf),\ndir Nils Hiolén, fru Hedda Tholén,\nförsäljn-chef Sten Ljungdahl,\nkamrer Ove Blomqvist\nVerkst dir: Nils Tholén\nEtableringsår: 1948.\n\nFROSTENSON AB, F TH\n\nPnr 21120\n\nMalmö, Navigationsg 3. Tel\n040-11 56 67. Postgiro 37678. Tga\nFrostensonbolag\n\nFRUKTNORLIN AB\n\nPnr 12109\n\nJohanneshov 9, Box 9010.\nBrunn-byv 15. Tel 08-9100 80. Bankgiro\n560-3535. Postgiro 353001-1. Tga\nFruktnorlin. Telex 1528, 17709\nVerksamhet: Importerar färsk frukt\no grönsaker\n.Antal anställda: 10\nÅrsomsättning: 12 000 000\nAktiekapital: 100 000\nVerkst dir: Hans Norlin\nEtableringsår: 1961.\n\nFRUNCK JÄRNAFFÄR AB,\nRAGNAR\n\nPnr 113 84\n\nStockholm 6, Sankt Eriksg 86. Box\n6601. Tel 08-34 02 20. Bankgiro\n566-0303. Postgiro 4949-4. Tga\nJernfrunck\n\nVerksamhet: Järnaffär\nAntal anstäUda: 55\nÅrsomsättning: 16000 000\nAktiekapital: 510 000\nVerkst dir: Gabriel Sandskog\nEtableringsår: 1928\nOmbildat till aktiebolag 1939.\n\nFRYKENS TRÄINDUSTRI AB\n\nPnr 46400\n\nMellerud, Odeng. Tel 0530-113 63.\nBankgiro 533-8108. Postgiro\n173357-5\n\nVerksamhet: Export av téemballage\ntill Indonesien, Afrika\nÅrsomsättning: 600 000\nAktiekapital: 15 000\nVerkst dir: Karl-Axel Bengtsson\nEtableringsår: 1949.\n\nLKL INGENJURSBYRÅ\nLITZBERG, KÄLLQVIST &amp;\nLIND AB\n\nPnr 123 21\n\nFarsta 1, Ostmarksg 27. Box 45.\nTel 08-94 0190. Bankgiro 74-5766.\nPostgiro 65999-5\n\nVerksamhet: Konsulterande\ningenjörsbyrå\n\nFilialer: 123 55 Farsta, Bagarfruv\n52. Tel 08-93 55 03, 93 55 06\n95100 Luleå, Skeppsbrog 48. Tel\n0920-204 00\n\n222 21 Lund, Sankt Petri kyrkog\n11. Tel 046-126060, 126061,\n12 60 64\n\nAktiekapital: 30 000\nVerkst dir: Civiling Fred Lind\nEtableringsår: 1943.\n\nENG\n\nAktiekapital: 20000\nVeikst dir: Jan Åkerberg\nEtableringsår: 1929.\n\nNOR\n\nVerksamhet: Utför ytbehandling i\nlasttankarna på kemikalietankers\nAntal anställda: 5\nVerkst dir: Karlolof Lindquist\nEtableringsår: 1970.\n\nNORD, NORDH\n\nNORDS VERKSTADS AB\n\nPnr 660 60\n\nMolkom, Box 85. Tel 0553-105 25.\nBankgiro 881-4196. Postgiro\n30183-8\n\nVerksamhet: Tillverkar\nSMJ-flän-sar o skurna ämnen\nAntal anställda: 150\nÅrsomsättning: 8 500 000\nAktiekapital: 300 000\nVerkst dir: Fabr Erik Nord\nEtableringsår: 1904.\n\nNORD AB, BYGGNADSFIRMA\nOSCAR H\n\nPnr 703 56\n\ntfrebro, Norrg 15. Tel 019-13 0170.\nBankgiro 815-6309. Postgiro\n206781-7\n\nVerksamhet: Uppför byggnader\nAntal anställda: 100\nÅrsomsättning: 10 000 000\nAktiekapital: 75 000\nVerkst dir: Lennart Jansson\nEtableringsår: 1948.",
    "structured": {
        "1": {
            "company_name": "VÄSTAN TRYCKERI AB",
            "pnr": "402 32",
            "address": "Göteborg 7, Andra Långg 20. Box 7124",
            "phone_number": "031-12 98 48",
            "bank_details": {
                "bankgiro": "33-7532",
                "postgiro": "242914"
            },
            "activity": "Framställer trycksaker, tidskrifter o böcker",
            "capital": 175000,
            "key_personnel": [
                {
                    "name": "Nils Kullgren",
                    "position": "Verkst dir"
                }
            ],
            "establishment_year": 1948
        },
        "2": {
            "company_name": "VÄSTANFORS INDUSTRIER. AB",
            "pnr": "773 00",
            "address": "Fagersta. S Linian",
            "phone_number": "0223-129 25",
            "bank_details": {
                "bankgiro": "81-2422",
                "postgiro": "268288"
            },
            "activity": "Tillverkning av monteringsfärdiga stålbyggnader",
            "employees": 120,
            "annual_turnover": 14500000,
            "capital": 1250000,
            "key_personnel": [
                {
                    "name": "Olof Stråth",
                    "position": "Verkst dir"
                }
            ],
            "establishment_year": 1952
        },
        "3": {
            "company_name": "HULTÉN AB, A",
            "pnr": "21444",
            "address": "Malmö, N Grängesbergsg 10",
            "phone_number": "040-804 40",
            "bank_details": {
                "bankgiro": "644-0093",
                "postgiro": "38117-8"
            },
            "activity": "Tillverkar inredningar för banker, butiker, varuhus, skolor, sjukhus, kontor, hotell o restauranger m fi",
            "employees": 45,
            "capital": 80000,
            "key_personnel": [
                {
                    "name": "Adv Erik Grenfors",
                    "position": "Styrelse"
                },
                {
                    "name": "Sture Hultén",
                    "position": "fabr"
                },
                {
                    "name": "Anders Hultén",
                    "position": "fabrikschef"
                },
                {
                    "name": "Lars Hultén",
                    "position": "ark"
                },
                {
                    "name": "Lars Hultén",
                    "position": "Veikst din Ark"
                },
                {
                    "name": "Anders Hultén",
                    "position": "Fabrikschef"
                }
            ],
            "establishment_year": 1893
        },
        "4": {
            "company_name": "HULTÉN AB, ASSAR",
            "pnr": "400 72",
            "address": "Göteborg 22, Gustaf Dalénsg 13. Box 22031",
            "phone_number": "031-23 7318, 23 73 1 9",
            "bank_details": {
                "bankgiro": "513-1065",
                "postgiro": "429491-4"
            },
            "activity": "Säljer järnvaror en gros, speciellt alla slag av skruv o mutter",
            "capital": 100000,
            "key_personnel": [
                {
                    "name": "Assar Hultén",
                    "position": "Verkst dir"
                }
            ],
            "establishment_year": 1955
        },
        "5": {
            "company_name": "HULTHËNS INGENJORSBYRÄ AB, HARALD",
            "pnr": "65109",
            "address": "Karlstad 1, Drottningg 18. Box 584",
            "phone_number": "054-1151 35",
            "bank_details": {
                "bankgiro": "344-5624",
                "postgiro": "79409-9"
            },
            "activity": "Rådgivande verksamhet för väg-, bro- o husbyggnad",
            "employees": 40,
            "annual_turnover": 2000000,
            "capital": 100000,
            "key_personnel": [
                {
                    "name": "Lennart Carlsson",
                    "position": "Veikst dir"
                }
            ],
            "establishment_year": 1930
        },
        "6": {
            "company_name": "HULTHÉN, AB HENRY",
            "pnr": "25102",
            "address": "Helsingborg 1, Box 94. Drottningg 31",
            "phone_number": "042-13 94 75",
            "bank_details": {
                "bankgiro": "438-0549",
                "postgiro": "449331-8"
            },
            "activity": "Tillverkar o säljer köksredskap i metall samt utegrillar o campingrökar",
            "employees": 0,
            "annual_turnover": 0,
            "capital": 10000,
            "key_personnel": [
                {
                    "name": "Fru Maj-Britt Hulthén",
                    "position": "Styrelse"
                },
                {
                    "name": "Henry Hulthén",
                    "position": "dir"
                },
                {
                    "name": "Oskar Pauls son",
                    "position": "fabr"
                },
                {
                    "name": "Henry Hulthén",
                    "position": "Verkst dir"
                }
            ],
            "establishment_year": 1954
        },
        "7": {
            "company_name": "HULTÉN AB, MALTE",
            "pnr": "214 44",
            "address": "Malmö, N Grängesbergsg 8",
            "phone_number": "040-837 00 , 837 01",
            "bank_details": {
                "bankgiro": "644-0101",
                "postgiro": "37508-9"
            },
            "activity": "Tillverkar skinnkläder, alla slags modeller i dam, herr, flick o goss",
            "employees": 100,
            "annual_turnover": 4500000,
            "capital": 100000,
            "key_personnel": [
                {
                    "name": "Fabr Malte Hultén",
                    "position": "Styrelse"
                },
                {
                    "name": "Ola Hultén",
                    "position": "dir"
                },
                {
                    "name": "Bo Lennart Adamson",
                    "position": "prof"
                },
                {
                    "name": "Ola Hultén",
                    "position": "Verkst dir"
                }
            ],
            "establishment_year": 1927
        },
        "8": {
            "company_name": "SVENSKA von ROLL AB",
            "pnr": "102 32",
            "address": "Stockholm 6, Box 6112. Västman-nag 41",
            "phone_number": "08-34 03 55",
            "bank_details": {
                "bankgiro": "296-7552"
            },
            "activity": "Säljer o projekterar sopförbränningsanläggningar av system Von Roll till industrier, städer o kommuner i Sverige",
            "capital": 100000,
            "key_personnel": [
                {
                    "name": "Ragnar ödman",
                    "position": "Styrelse"
                },
                {
                    "name": "Karl Einar Rasmusson",
                    "position": "bankdir"
                },
                {
                    "name": "René Starke",
                    "position": "dir"
                },
                {
                    "name": "Hans Ström",
                    "position": "Verkst dir"
                }
            ],
            "establishment_year": 1966
        },
        "9": {
            "company_name": "UNIFOS KEMI AB",
            "pnr": "444 00",
            "address": "Stenungsund, Box 44",
            "phone_number": "0303-715 20",
            "bank_details": {
                "bankgiro": "16-0622",
                "postgiro": "651170"
            },
            "activity": "Tillverkar polyeten, basråvara för plastindustrin",
            "employees": 280,
            "annual_turnover": 126000000,
            "capital": 48000000,
            "key_personnel": [
                {
                    "name": "Bengt Lidén",
                    "position": "Veikst dir"
                },
                {
                    "name": "Ulf Jacobson",
                    "position": "Försäljn-dir"
                },
                {
                    "name": "R Schwarz",
                    "position": "Tekn-dir"
                },
                {
                    "name": "L Crafoord",
                    "position": "Ekonomidir"
                }
            ],
            "establishment_year": 1961
        },
        "10": {
            "company_name": "UNION CARBIDE NORDEN AB",
            "pnr": "46101",
            "address": "Trollhättan 1. Huvudkontor Box 79",
            "phone_number": "0520-128 15",
            "bank_details": {
                "bankgiro": "892-5570",
                "postgiro": "34661-9"
            },
            "activity": "Tillverkar o säljer grafitelektroder, grafitanoder, grafitdetaljer o grafitpulver. Säljer dessutom bl a kolelektroder o katodblock samt apparatur av KAR-BATE, impregnerad grafit",
            "employees": 125,
            "annual_turnover": 43000000,
            "capital": 1560000,
            "key_personnel": [
                {
                    "name": "Bengt Westerling",
                    "position": "Styrelse"
                },
                {
                    "name": "Leif Karlsen",
                    "position": "Verkst dir"
                },
                {
                    "name": "Allan Lundh",
                    "position": "Fabrikschef"
                },
                {
                    "name": "Ture Eriksson",
                    "position": "Ekonomichef"
                },
                {
                    "name": "Ingvar Johansson",
                    "position": "Försäljn-chef kol- o grafitproduk-ter"
                }
            ],
            "establishment_year": 1917
        }
    }
}