{
    "original": "OPTO INGENIORSFIRMA AB\n\nPnr 64031\n\nMellösa. Tel 0157-603 40.\nBankgiro 569-5614. Tga Optokem, Flen\nVerksamhet: Tillverkning av\ndamm-sugarfilter o skafferifilter i plast.\nTrevinge rörkopplingssystem för\nlagerinredningar,\nproduktionshjälpmedel, butiksinredningar m m.\nMasso-systemet för upphängning på\nperforerade träfiberskivor\nVarunamn: Masso-systemet,\nTrevinge\n\nVerkst dir: Torsten Brimberg\nDriftechef: Ing Olof Anell\nVerkstadsing: Ing Bengt Magnér\nEtableringsår: 1960.\n\nVIGGO AB\n\nPnr 252 27\n\nHelsingborg, Gåsebäcksv 36. Tel\n042-12 77 50. Bankgiro 864-0138.\nPostgiro 29595-6. Tga Viggo\nVerksamhet: Medicinsk\nengångs-materiel, operationsmöbler o\nsjukvårdsartiklar\nAntal anställda: 100\nAktiekapital: 75 000\nStyrelse: Carl Ravén (ordf),\nCarl-Bertil Ravén\n\nVerkst din Carl-Bertil Ravén\nEtableringsår: 1921\nOmbildat till aktiebolag 1940.\n\nVIGOR VERKTYGS AB\n\nPnr 632 29\n\nEskilstuna, Hejarg 8. Tel\n016-13 35 97. Bankgiro 604-4085.\nPostgiro 291102-2. Tga Vigortools\nVerksamhet: Specialfabrik i tänger\nVarunamn: Vigor\nAktiekapital: 90 000\nVerkst din Fabr Carl Bengt\nAndersson\nEtableringsår: 1934\nOmbildat till aktiebolag 1947.\n\nVIGÄR, AB\n\nPnr 252 27\n\nHelsingborg, Carl Krooksg 65. Tel\n042-1147 01, 922 85. Postgiro\n92088-4. Tga Vigär\nVerksamhet: Förpackningsindustri\nför vitaminmedicinaljästtabletter\nAktiekapital: 58 125\nVerkst din Fabr Hans Henric\nMalte Ramel\n\nEtableringsår: 1937.\n\nERI\n\nVerksamhet: Verktygsmaskiner\nAntal anställda: 12\nÅrsomsättning: 10 000 000\nAktiekapital: 50 000\nVerkst dir: Ing Sigurd Erixon\nEtableringsår: 1951.\n\nSÖDERTÄLJE KOLIMPORT AB\n\nPnr 151 02\n\nSödertälje 2, Box 2042. Solviksv\n50. Tel 0755-341 10. Bankgiro\n622-5296. Postgiro 834400-4. Tga\nTeljekol\n\nVerksamhet: Säljer eldningsoljor,\nkoks o stenkol, briketter\nAntal anställda: 25\nÅrsomsättning: 12 000 000\nAktiekapital: 250 000\nVerkst dir: C E Hammarlund\nEtableringsår. 1935.\n\nLÖFGREN, AB BRÖDERNA\n\nPnr 801 03\n\nGävle 1, Centralplan 3. Box 136.\nTel 026-12 6410, 1214 10.\nBankgiro 336-7380. Postgiro 28285-5.\nTga Baltic. Telex 81047\nVerksamhet: Skeppsmäkleri,\nspedition, trävaruagentur\nAktiekapital: 150 000\nStyrelse: Herr Mats Haag (ordf),\nskeppsmäkl Joel Haag, skeppsmäkl\nGöran Englund\nVeikst dir: Joel Haag\nEtableringsår: 1907\nOmbildat till aktiebolag 1915.\n\nLÖFGREN AB, BO\n\nPnr 11145\n\nStockholm C, Birger Jarlsg 27. Tel\n08-10 21 84. Bankgiro 56-4580.\nPostgiro 351055. Telex 10527.\nTga Bolofmachines\nVerksamhet: Tillverkar o säljer\nmetallsprutor o\nsandblästringsagg-regat av egna konstruktioner,\nsäljer dammfria sandblästerapparater\no glaskulor\n\nVarunamn: EM, Microbeads,\nVacu-Blast\n\nAntal anställda: 3\nÅrsomsättning: 1000 000\nAktiekapital: 5 000\nVerkst dir: Bo Löfgren\nEtableringsår: 1955.\n\nWENNBERG AB, JACOB\n\nPnr 80108\n\nGävle 1, Nyg 11. Box 583. Tel\n026-12 94 60. Bankgiro 603-5927.\nPostgiro 10349-9. Tga Jaco\nVerksamhet: Järn- o\nbyggnadsmaterial, engros o detalj\nAntal anställda: 73\nÅrsomsättning: 16773 000\nAktiekapital: 300 000\nStyrelse: Disp Gösta Westlund\n(ordf), fru Margareta\nHöjer-Bolin-der, adv Gösta Malmsten, herr\nLorentz Höjer\n\nVerkst dir: Fru Margareta\nHöjer-Bolinder\n\nDisp: Gösta Westlund\nEtableringsår: 1911\nOmbildat till aktiebolag 1942.\n\nWENNBERG,\nKONSULTE-RANDE 1NGENIORSBYRAN\nLARS\n\nPnr 65107\n\nKarlstad 1, V Torgg 11. Box 463.\nTel 054-15 03 30. Bankgiro 88-1495.\nPostgiro 264421\n\nVerksamhet: Konstruktionsbyrå för\nWS-anläggningar. Utför kontroll\no besiktningar\n\nAvdelningskontor: Arvika, Skövde\nAntal anställda: 11\nÅrsomsättning: 500 000\nChef: Ing Lars Wennberg\nEtableringsår: 1943.\n\nWENNBERG AB,\nINGENJÖRSFIRMAN ÅKE\n\nPnr 65102\n\nKarlstad 1, Drottningg 9. Box 34.\nTel 054-1194 60, 11 9461.\nBankgiro 100-0769. Postgiro 394718-1.\nTga Wengo\n\nVerksamhet: Maskiner, verktyg o\nslipmaterial\n\nVarunamn: Deprag, Feldmühle,\nFlex\n\nAktiekapital: 300000\n\nÄgare o chef: Gunnar Wennberg\n\nEtableringsår: 1949.\n\nDINSDALE &amp; CO LTD, AB H\n\nPnr 41121\n\nGöteborg, Skeppsbron 5-6. Tel\n031-11 3282. Bankgiro 511-4434.\nPostgiro 47421-3. Tga Dinsdaleco.\nTelex 2264\n\nVerksamhet: Export av\nträmanufaktur, hushållsartiklar m m\nAktiekapital: 100 000\nVerkst dir: Hans Drews\nEtableringsår: 1938.\n\nSQUIBB AB\n\nPnr 18109\n\nLidingö 9, Box 925. Vesslev 2. Tel\n08-767 02 00. Bankgiro 164-6777.\nPostgiro 641480-9. Tga Ersquibb\nVerksamhet: Läkemedel i parti\nAntal anstäUda: 22\nAktiekapital: 1000 000\nVerkst dir: Sven L Holmberg\nEtableringsår: 1963.\n\nBYGGELIT AB\n\nPnr 830 30\n\nLit. Tel 0642-103 20. Bankgiro\n250-2656. Postgiro 674630-9.\nTelex 6505 ELIT S\nVerksamhet: Tillverkar spånskivor\nAntal anställda: 50\nÅrsomsättning: 10000 000\nVerkst dir: Sven O Persson\nDisp: Steinar Haukebö\nFörsäljn-chef: Bengt Johansson\nEtableringsår 1965.\n\nRINGSTRÖM AB, N P\n\nPnr 116 25\n\nStockholm, Ostgötag 9. Tel\n08-4147 09, 43 3173. Bankgiro 72-0027\nPostgiro 728-6. Tga Ringström\nVerksamhet: Glasmästeri o\nglassli-peri. Säljer spegel-, fönster-, rå-,\nantik- o arkitekturglas. Utför\nblyin-fattade fönster o glasmålningar\nsamt limning av glas\nAntal anställda: 9\nÅrsomsättning: 700 000\nAktiekapital: 90000\nVerkst dir: Göran Ringström\nEtableringsår: 1886\nOmbildat till aktiebolag 1929.\n\nRINGONS DIESEL, AB\n\nPnr 417 07\n\nGöteborg, Ringög. Tel 031-51 24 52.\nBankgiro 33-7315. Tga Ringödiesel\nVerksamhet: Reparerar\nfartygsmaskinerier samt tillverkar\nvärmeväxlare o evaporatorer\nAntal anstäUda: 15\nÅrsomsättning: 2 000 000\nAktiekapital: 15 000\nVeikst dir: Karl-Gustav Lemming\nEtableringsår: 1959.",
    "structured": {
        "1": {
            "company_name": "OPTO INGENIORSFIRMA AB",
            "activity": "Tillverkning av damm-sugarfilter o skafferifilter i plast. Trevinge rörkopplingssystem för lagerinredningar, produktionshjälpmedel, butiksinredningar m m. Masso-systemet för upphängning på perforerade träfiberskivor",
            "establishment_year": 1960
        },
        "2": {
            "company_name": "VIGGO AB",
            "activity": "Medicinsk engångs-materiel, operationsmöbler o sjukvårdsartiklar",
            "employees": 100,
            "capital": 75000,
            "key_personnel": [
                {
                    "name": "Carl Ravén",
                    "position": "ordf"
                },
                {
                    "name": "Carl-Bertil Ravén"
                }
            ],
            "establishment_year": 1921
        },
        "3": {
            "company_name": "VIGOR VERKTYGS AB",
            "activity": "Specialfabrik i tänger",
            "capital": 90000,
            "key_personnel": [
                {
                    "name": "Fabr Carl Bengt Andersson"
                }
            ],
            "establishment_year": 1934
        },
        "4": {
            "company_name": "VIGÄR, AB",
            "activity": "Förpackningsindustri för vitaminmedicinaljästtabletter",
            "capital": 58125,
            "key_personnel": [
                {
                    "name": "Fabr Hans Henric Malte Ramel"
                }
            ],
            "establishment_year": 1937
        },
        "5": {
            "activity": "Verktygsmaskiner",
            "employees": 12,
            "annual_turnover": 10000000,
            "capital": 50000,
            "key_personnel": [
                {
                    "name": "Ing Sigurd Erixon"
                }
            ],
            "establishment_year": 1951
        },
        "6": {
            "company_name": "SÖDERTÄLJE KOLIMPORT AB",
            "activity": "Säljer eldningsoljor, koks o stenkol, briketter",
            "employees": 25,
            "annual_turnover": 12000000,
            "capital": 250000,
            "key_personnel": [
                {
                    "name": "C E Hammarlund"
                }
            ],
            "establishment_year": 1935
        },
        "7": {
            "company_name": "LÖFGREN, AB BRÖDERNA",
            "activity": "Skeppsmäkleri, spedition, trävaruagentur",
            "capital": 150000,
            "key_personnel": [
                {
                    "name": "Herr Mats Haag",
                    "position": "ordf"
                },
                {
                    "name": "skeppsmäkl Joel Haag"
                },
                {
                    "name": "skeppsmäkl Göran Englund"
                }
            ],
            "establishment_year": 1907
        },
        "8": {
            "company_name": "LÖFGREN AB, BO",
            "activity": "Tillverkar o säljer metallsprutor o sandblästringsagg-regat av egna konstruktioner, säljer dammfria sandblästerapparater o glaskulor",
            "employees": 3,
            "annual_turnover": 1000000,
            "capital": 5000,
            "key_personnel": [
                {
                    "name": "Bo Löfgren"
                }
            ],
            "establishment_year": 1955
        },
        "9": {
            "company_name": "WENNBERG AB, JACOB",
            "activity": "Järn- o byggnadsmaterial, engros o detalj",
            "employees": 73,
            "annual_turnover": 16773000,
            "capital": 300000,
            "key_personnel": [
                {
                    "name": "Disp Gösta Westlund",
                    "position": "ordf"
                },
                {
                    "name": "fru Margareta Höjer-Bolinder"
                },
                {
                    "name": "adv Gösta Malmsten"
                },
                {
                    "name": "herr Lorentz Höjer"
                }
            ],
            "establishment_year": 1911
        },
        "10": {
            "company_name": "WENNBERG, KONSULTERANDE 1NGENIORSBYRAN LARS",
            "activity": "Konstruktionsbyrå för WS-anläggningar. Utför kontroll o besiktningar",
            "employees": 11,
            "annual_turnover": 500000,
            "key_personnel": [
                {
                    "name": "Ing Lars Wennberg"
                }
            ],
            "establishment_year": 1943
        },
        "11": {
            "company_name": "WENNBERG AB, INGENJÖRSFIRMAN ÅKE",
            "activity": "Maskiner, verktyg o slipmaterial",
            "capital": 300000,
            "key_personnel": [
                {
                    "name": "Gunnar Wennberg"
                }
            ],
            "establishment_year": 1949
        },
        "12": {
            "company_name": "DINSDALE & CO LTD, AB H",
            "activity": "Export av trämanufaktur, hushållsartiklar m m",
            "capital": 100000,
            "key_personnel": [
                {
                    "name": "Hans Drews"
                }
            ],
            "establishment_year": 1938
        },
        "13": {
            "company_name": "SQUIBB AB",
            "activity": "Läkemedel i parti",
            "employees": 22,
            "capital": 1000000,
            "key_personnel": [
                {
                    "name": "Sven L Holmberg"
                }
            ],
            "establishment_year": 1963
        },
        "14": {
            "company_name": "BYGGELIT AB",
            "activity": "Tillverkar spånskivor",
            "employees": 50,
            "annual_turnover": 10000000,
            "key_personnel": [
                {
                    "name": "Sven O Persson",
                    "position": "Verkst dir"
                },
                {
                    "name": "Steinar Haukebö",
                    "position": "Disp"
                },
                {
                    "name": "Bengt Johansson",
                    "position": "Försäljn-chef"
                }
            ],
            "establishment_year": 1965
        },
        "15": {
            "company_name": "RINGSTRÖM AB, N P",
            "activity": "Glasmästeri o glassliberi. Säljer spegel-, fönster-, rå-, antik- o arkitekturglas. Utför blyinfattade fönster o glasmålningar samt limning av glas",
            "employees": 9,
            "annual_turnover": 700000,
            "capital": 90000,
            "key_personnel": [
                {
                    "name": "Göran Ringström"
                }
            ],
            "establishment_year": 1886
        },
        "16": {
            "company_name": "RINGÖNS DIESEL, AB",
            "activity": "Reparerar fartygsmaskinerier samt tillverkar värmeväxlare o evaporatorer",
            "employees": 15,
            "annual_turnover": 2000000,
            "capital": 15000,
            "key_personnel": [
                {
                    "name": "Karl-Gustav Lemming"
                }
            ],
            "establishment_year": 1959
        }
    }
}