{
    "original": "C DM, AB\n\nPnr 403 12\n\nGöteborg 2, Box 2082. O Hamng 5.\nTel 031-17 83 20. Bankgiro\n42-0697. Postgiro 625830. Tga\nCedem-bol. Telex 20777\nVerksamhet: Importerar\nicke-me-talliska mineral, kemikalier o\nblandningsmaskiner\nAntal anställda: 15\nAktiekapital: 100 000\nVerkst dir: P O Goliath\nEtableringsår: 1964.\n\nMET\n\nÅrsomsättning: 1500 000\nAktiekapital: 25 000\nVerkst dir: Tage Herneland\nEtableringsàr: 1946\nOmbildat till aktiebolag med\nnuvarande namn 1962.\n\nMETALLKONTOR AB\n\nPnr 111 20\n\nStockholm, Vasag 15-17. Tel 08-\n\n2318 30. Bankgiro 16^1576. Postgiro\n159787-1\n\nVerksamhet: Importerar stålrör.\nSpecialitet: hydraulrör\nAntal anställda: 6\nÅrsomsättning: 12 000 000\nAktiekapital: 30 000\nVerkst dir: Priedhelm Schlabach\nEtableringsàr 1938.\n\nGRANHOLM AB, HJALMAR\n\nPnr 421 77\n\nVästra Frölunda, Palmgrensg 120.\nTel 031-2920 75. Bankgiro\n420-6736. Postgiro 53859-5\n161 37 Bromma, Mårdv 39. Tel\n08-26 29 90\n\nVerksamhet: Byggnadsteknik o\nkonsultation\nAntal anstäUda: 40\nÅrsomsättning: 3 000 000\nAktiekapital: 50 000\nVerkst dir: Hans Berglund\nEtableringsår: 1934.\n\nGRANINGEVERKENS AB\n\nPnr 870 50\n\nBollstabruk. Tel 0612-205 00.\n\nBankgiro 187-4080. Postgiro\n6428-7. Tga Graningeverken.\nTelex 71242\n\nVerksamhet: Sågverk, hyvleri o\nimpregnering av trävaror\nFörsäljningskontor: 114 35\nStockholm, Stureplan 2. Tel 08-114679.\nTelex 17196\nAktiekapital: 42 1 20 000\nVerkst din A M Versteegh\nEtableringsår: 1873.\n\nBRIO BARNVAGNAR AB\n\nPnr 283 00\n\nOsby, V Järnvgsg. Tel 0479-119 00.\nBankgiro 28-1636. Postgiro 6075\nVerksamhet: Tillverkar barnvagnar\no -möbler\n\nVerkst dir: Lars Hall.\n\nBRIO METALLFABRIK &amp;\nHANDELSFIRMA\nKNUT MELANDER &amp; CO\n\nPnr 411 27\n\nGöteborg, Engelbrektsg 5. Tel\n031-1124 90\n\nBRITANNIAFABRIKS AB\n\nPnr 440 01\n\nStenkullen. Tel 0302-22075, 22150.\nBankgiro 54-7660. Postgiro 285891\nVerksamhet: Specialitet:\nkokillgjut-ning\n\nAntal anställda: 25\nÅrsomsättning: 1 500 000\nAktiekapital: 90 000\nStyrelse: Dir H D Colsman (ordf),\nfru Gerda Colsman, hr Björn Stahre\nVerkst dir: H D Colsman\nEtableringsår: 1892.\n\nDAP\n\nÅrsomsättning: 4 400 000\nAktiekapital: 50000\nVerkst dir: Bengt Dalström\nEtableringsår: 1954.\n\ndalsy konfektions.\naktiebolag\n\nPnr 510 95\n\nDalstorp. Tel 0321-60100.\nBankgiro 532-7150. Postgiro 83536-3\nVerksamhet: Tillverkar o säljer\narbetskläder, skyddskläder o\nfritidsbyxor i bomull (jeans)\nVarunamn: Dalsy\nAntal anställda: 100\nÅrsomsättning: 7 000 000\nAktiekapital: 100 000\nVerkst dir: Ing Anders Sigurdson\nEtableringsår: 1931.\n\nCARLS, AB SVEN\n\nPnr 172 34\n\nSundbyberg, Fredsg 10. Tel\n08-28 45 58, 29 17 78. Bankgiro\n17-0940. Postgiro 158522\nVerksamhet: Finmekanisk verkstad\nAntal anställda: 14\nÅrsomsättning: 1000 000\nAktiekapital: 5 000\nVerkst dir: Ing Sven Carls\nEtableringsår: 1944.\n\nCARLS-BERGH BIOKEMISK o\nFARMACEUTISK FABRIK, AB\n\nPnr 400 51\n\nGöteborg 47, Dagjämningsg 24-26.\nBox 47025. Tel 031-46 49 10.\nBankgiro 85-2250. Postgiro 425500. Tga\nCarlsberghbol\n\nVerksamhet: Tillverkar vitamin- o\nbiokemiska preparat\nAktiekapital: 55 000\nVerkst dir. Erie Bergh\nEtableringsår: 1952.\n\nCARLSÉNS\nOMNIBUS-TRAFIK AB\n\nPnr 575 00\n\nEksjö, Stora Torget 3. Tel\n0381-13180. Bankgiro 144-5121.\nPostgiro 96746-3\n\nVerksamhet: Linje- o stadstrafik.\nBussuthyrning. Resebyrå\nAntal anställda: 30\nÅrsomsättning: 6 000 000\nAktiekapital: 150 000\nVerkst dir: Lennarth Lingmerth\nEtableringsår: 1950.\n\nCARLSÉNS SÖNER\nSTOL-FABRIK, AB P H\n\nPnr 570 14\n\nNye. Tel 0383-420 36. Bankgiro\n144-9107. Postgiro 285189-7\nVerksamhet: Tillverkar stolar,\nkarmstolar samt bord. Specialitë:\nStilstolar\n\nAntal anställda: 14\nAktiekapital: 50 000\nVerkst din Olof Carlsen\nEtableringsår: 1903\nOmbildat till aktiebolag 1953.\n\nCARLSFORS LÅD- &amp;\nSNICKERIFABRIK, AB\n\nPnr 710 12\n\nMullhyttemo. Tel 0585-400 06.\nBankgiro 81-9116. Postgiro\n92755-8\n\nVerksamhet: Tillverkar skåp för\nritningar, ritbord o ritskivor\n\nAntal anställda: 7\nÅrsomsättning: 450 000\nAktiekapital: 50 000\nVerkst dir: Håkan Olsson\nEtableringsår: 1916\nOmbildat till aktiebolag 1935.\n\nCARLSSON se KARLSSON\n\nCARLSTEDT AB,\nINGENIÖRSFIRMAN RAGNAR\n\nPnr 116 26\n\nStockholm, Bangårdsg 12. Tel\n08-40 5459. Bankgiro 731-0147.\nPostgiro 5 00041-9\nVerksamhet: Mek verkstad\nAktiekapital: 10000\nStyrelse: Ing Björn Lundström (ordf),\nfru Astrid Lundström\nVerkst dir: Björn Lundström\nEtableringsår: 1929.\n\nEKSTRÖM &amp; BLOHM AB\n\nPnr 52101\n\nFalköping 1, Dotorps 55. Box 65.\nTel 0515-12045, 12046. Bankgiro\n541-5757. Postgiro 36386-1\nVerksamhet: Grossist i guldvaror\nAntal anställda: 12\nÅrsomsättning: 2 000 000\nAktiekapital: 210 000\nVerkst dir: Nils Blohm\nEtableringsår: 1928.\n\nPRENCKER, AB SVEN\n\nPnr 703 54\n\nÖrebro, Vasastrand 3. Tel\n019-11 1155. Bankgiro 815-9006.\nPostgiro 611772-5\n\nVeiksamhet: Säljer\nkarosseridetal-jer för bilindustrin\nAktiekapital: 5 000\nVeikst din Sven Prencker\nEtableringsår: 1963.\n\nPRENELLS\nKONSTRUKTIONS-BYRÅ AB\n\nPnr 123 21\n\nFarsta 1, Nordmarksv 25-27. Box\n107. Tel 08-94 0130. Postgiro\n250605-3\n\nVerksamhet: Rådgivande o\nkonsulterande ingenjörsverksamhet inom\nvärme-, ventilations- o\nsanitetsteknik. Specialitet:\nplaströrskon-struktioner för industri o\nbostadshus\n\nVerkst dir. Ing P A Prenell\nEtableringsår: 1944.\n\nPRENNFORS MEKANISKA\nVERKSTAD, AB\n\nPnr 630 02\n\nEskilstuna 2, Nyforsg 46. Box\n2029. Tel 016-136659, 13 66 63.\nBankgiro 601-3791. Postgiro\n348441-7\n\nVerksamhet: Tillverkar verktyg,\n\nkokiller, fixturer samt slitsmått\n\nAntal anställda: 17\n\nÅrsomsättning: 700000\n\nAktiekapital: 50 000\n\nÄgare o chef: Fabr Ingemar Prenn-\n\nfors\n\nEtableringsår: 1951.\n\nBEY\n\nSmålands g 10. Tel 08-1100 27\nAntal anställda: 240\nÅrsomsättning: 12 000 000\nAktiekapital: 600 000\nStyrelse: Adv Sten G Carlston\n(ordf), dir Hagbarth Schött jr, dir\nFolke Kjellnäs\nVerkst dir: Folke Kjellnäs\nEkonomichef: C A Andersson\nProd-chef: Göte Johansson\nEtableringsår: 1949.\n\nSUKAB, AB\n\nPnr 103 82\n\nStockholm 7, Birger Jarlsg 2. Box\n7060. Tel 08-23 47 95. Bankgiro\n700-1993, 560-4558, 160-1640.\nPostgiro 158980-3. Tga Sukab.\nTelex 19146\n\nVerksamhet: Kompensationsaffärer,\n\ndeblockeringar\n\nAntal anstäUda: 14\n\nÅrsomsättning: 538000 000\n\nAktiekapital: 30 000\n\nVerkst dir: Tom Ph Bojsen\n\nEtableringsår: 1940.",
    "structured": {
        "1": {
            "company_name": "C DM, AB",
            "pnr": "403 12",
            "address": "Göteborg 2, Box 2082. O Hamng 5.",
            "phone_number": "031-17 83 20",
            "bank_details": {
                "bankgiro": "42-0697",
                "postgiro": "625830"
            },
            "activity": "Importerar icke-metalliska mineral, kemikalier och blandningsmaskiner",
            "employees": 15,
            "capital": 100000,
            "key_personnel": [
                {
                    "name": "P O Goliath",
                    "position": "Verkst dir"
                }
            ],
            "establishment_year": 1964,
            "annual_turnover": 1500000
        },
        "2": {
            "company_name": "MET",
            "establishment_year": 1946,
            "annual_turnover": 1500000,
            "capital": 25000,
            "key_personnel": [
                {
                    "name": "Tage Herneland",
                    "position": "Verkst dir"
                }
            ]
        },
        "3": {
            "company_name": "METALLKONTOR AB",
            "pnr": "111 20",
            "address": "Stockholm, Vasag 15-17.",
            "phone_number": "08-2318 30",
            "bank_details": {
                "bankgiro": "16^1576",
                "postgiro": "159787-1"
            },
            "activity": "Importerar stålrör. Specialitet: hydraulrör",
            "employees": 6,
            "annual_turnover": 12000000,
            "capital": 30000,
            "key_personnel": [
                {
                    "name": "Priedhelm Schlabach",
                    "position": "Verkst dir"
                }
            ],
            "establishment_year": 1938
        },
        "4": {
            "company_name": "GRANHOLM AB, HJALMAR",
            "pnr": "421 77",
            "address": "Västra Frölunda, Palmgrensg 120. Tel 031-2920 75.",
            "bank_details": {
                "bankgiro": "420-6736",
                "postgiro": "53859-5"
            },
            "activity": "Byggnadsteknik och konsultation",
            "employees": 40,
            "annual_turnover": 3000000,
            "capital": 50000,
            "key_personnel": [
                {
                    "name": "Hans Berglund",
                    "position": "Verkst dir"
                }
            ],
            "establishment_year": 1934
        },
        "5": {
            "company_name": "GRANINGEVERKENS AB",
            "pnr": "870 50",
            "address": "Bollstabruk. Tel 0612-205 00.",
            "bank_details": {
                "bankgiro": "187-4080",
                "postgiro": "6428-7"
            },
            "activity": "Sågverk, hyvleri och impregnering av trävaror",
            "employees": null,
            "annual_turnover": null,
            "capital": 42120000,
            "key_personnel": [
                {
                    "name": "A M Versteegh",
                    "position": "Verkst dir"
                }
            ],
            "establishment_year": 1873
        },
        "6": {
            "company_name": "BRIO BARNVAGNAR AB",
            "pnr": "283 00",
            "address": "Osby, V Järnvgsg. Tel 0479-119 00.",
            "bank_details": {
                "bankgiro": "28-1636",
                "postgiro": "6075"
            },
            "activity": "Tillverkar barnvagnar och möbler",
            "key_personnel": [
                {
                    "name": "Lars Hall",
                    "position": "Verkst dir"
                }
            ]
        },
        "7": {
            "company_name": "BRIO METALLFABRIK & HANDLERSFIRMA",
            "address": "Göteborg, Engelbrektsg 5. Tel 031-1124 90"
        },
        "8": {
            "company_name": "BRITANNIAFABRIKS AB",
            "pnr": "440 01",
            "address": "Stenkullen. Tel 0302-22075, 22150.",
            "bank_details": {
                "bankgiro": "54-7660",
                "postgiro": "285891"
            },
            "activity": "Specialitet: kokillgjutning",
            "employees": 25,
            "annual_turnover": 1500000,
            "capital": 90000,
            "key_personnel": [
                {
                    "name": "H D Colsman",
                    "position": "Styrelse: Dir (ordf)"
                },
                {
                    "name": "fru Gerda Colsman",
                    "position": "Styrelse"
                },
                {
                    "name": "hr Björn Stahre",
                    "position": "Styrelse"
                },
                {
                    "name": "H D Colsman",
                    "position": "Verkst dir"
                }
            ],
            "establishment_year": 1892
        },
        "9": {
            "company_name": "DAP",
            "annual_turnover": 4400000,
            "capital": 50000,
            "key_personnel": [
                {
                    "name": "Bengt Dalström",
                    "position": "Verkst dir"
                }
            ],
            "establishment_year": 1954
        },
        "10": {
            "company_name": "DALSY KONFEKTIONS. AKTIEBOLAG",
            "pnr": "510 95",
            "address": "Dalstorp. Tel 0321-60100.",
            "bank_details": {
                "bankgiro": "532-7150",
                "postgiro": "83536-3"
            },
            "activity": "Tillverkar och säljer arbetskläder, skyddskläder och fritidsbyxor i bomull (jeans). Varunamn: Dalsy",
            "employees": 100,
            "annual_turnover": 7000000,
            "capital": 100000,
            "key_personnel": [
                {
                    "name": "Ing Anders Sigurdson",
                    "position": "Verkst dir"
                }
            ],
            "establishment_year": 1931
        },
        "11": {
            "company_name": "CARLS, AB SVEN",
            "pnr": "172 34",
            "address": "Sundbyberg, Fredsg 10. Tel 08-28 45 58, 29 17 78.",
            "bank_details": {
                "bankgiro": "17-0940",
                "postgiro": "158522"
            },
            "activity": "Finmekanisk verkstad",
            "employees": 14,
            "annual_turnover": 1000000,
            "capital": 5000,
            "key_personnel": [
                {
                    "name": "Ing Sven Carls",
                    "position": "Verkst dir"
                }
            ],
            "establishment_year": 1944
        },
        "12": {
            "company_name": "CARLS-BERGH BIOKEMISK o FARMACEUTISK FABRIK, AB",
            "pnr": "400 51",
            "address": "Göteborg 47, Dagjämningsg 24-26. Box 47025. Tel 031-46 49 10.",
            "bank_details": {
                "bankgiro": "85-2250",
                "postgiro": "425500"
            },
            "activity": "Tillverkar vitamin- och biokemiska preparat",
            "capital": 55000,
            "key_personnel": [
                {
                    "name": "Erie Bergh",
                    "position": "Verkst dir"
                }
            ],
            "establishment_year": 1952
        },
        "13": {
            "company_name": "CARLSÉNS OMNIBUS-TRAFIK AB",
            "pnr": "575 00",
            "address": "Eksjö, Stora Torget 3. Tel 0381-13180.",
            "bank_details": {
                "bankgiro": "144-5121",
                "postgiro": "96746-3"
            },
            "activity": "Linje- och stadstrafik. Bussuthyrning. Resebyrå",
            "employees": 30,
            "annual_turnover": 6000000,
            "capital": 150000,
            "key_personnel": [
                {
                    "name": "Lennarth Lingmerth",
                    "position": "Verkst dir"
                }
            ],
            "establishment_year": 1950
        },
        "14": {
            "company_name": "CARLSÉNS SÖNER STOL-FABRIK, AB P H",
            "pnr": "570 14",
            "address": "Nye. Tel 0383-420 36.",
            "bank_details": {
                "bankgiro": "144-9107",
                "postgiro": "285189-7"
            },
            "activity": "Tillverkar stolar, karmstolar samt bord. Specialitet: Stilstolar",
            "employees": 14,
            "capital": 50000,
            "key_personnel": [
                {
                    "name": "Olof Carlsen",
                    "position": "Verkst din"
                }
            ],
            "establishment_year": 1903
        },
        "15": {
            "company_name": "CARLSFORS LÅD- & SNICKERIFABRIK, AB",
            "pnr": "710 12",
            "address": "Mullhyttemo. Tel 0585-400 06.",
            "bank_details": {
                "bankgiro": "81-9116",
                "postgiro": "92755-8"
            },
            "activity": "Tillverkar skåp för ritningar, ritbord och ritskivor",
            "employees": 7,
            "annual_turnover": 450000,
            "capital": 50000,
            "key_personnel": [
                {
                    "name": "Håkan Olsson",
                    "position": "Verkst dir"
                }
            ],
            "establishment_year": 1916
        },
        "16": {
            "company_name": "CARLSSON se KARLSSON"
        },
        "17": {
            "company_name": "CARLSTEDT AB, INGENIÖRSFIRMAN RAGNAR",
            "pnr": "116 26",
            "address": "Stockholm, Bangårdsg 12. Tel 08-40 5459.",
            "bank_details": {
                "bankgiro": "731-0147",
                "postgiro": "500041-9"
            },
            "activity": "Mek verkstad",
            "capital": 10000,
            "key_personnel": [
                {
                    "name": "Björn Lundström",
                    "position": "Styrelse: Ing (ordf)"
                },
                {
                    "name": "fru Astrid Lundström",
                    "position": "Styrelse"
                },
                {
                    "name": "Björn Lundström",
                    "position": "Verkst dir"
                }
            ],
            "establishment_year": 1929
        },
        "18": {
            "company_name": "EKSTRÖM & BLOHM AB",
            "pnr": "52101",
            "address": "Falköping 1, Dotorps 55. Box 65. Tel 0515-12045, 12046.",
            "bank_details": {
                "bankgiro": "541-5757",
                "postgiro": "36386-1"
            },
            "activity": "Grossist i guldvaror",
            "employees": 12,
            "annual_turnover": 2000000,
            "capital": 210000,
            "key_personnel": [
                {
                    "name": "Nils Blohm",
                    "position": "Verkst dir"
                }
            ],
            "establishment_year": 1928
        },
        "19": {
            "company_name": "PRENCKER, AB SVEN",
            "pnr": "703 54",
            "address": "Örebro, Vasastrand 3. Tel 019-11 1155.",
            "bank_details": {
                "bankgiro": "815-9006",
                "postgiro": "611772-5"
            },
            "activity": "Säljer karosseridetaljer för bilindustrin",
            "capital": 5000,
            "key_personnel": [
                {
                    "name": "Sven Prencker",
                    "position": "Verkst dir"
                }
            ],
            "establishment_year": 1963
        },
        "20": {
            "company_name": "PRENELLS KONSTRUKTIONS-BYRÅ AB",
            "pnr": "123 21",
            "address": "Farsta 1, Nordmarksv 25-27. Box 107. Tel 08-94 0130.",
            "postgiro": "250605-3",
            "activity": "Rådgivande och konsulterande ingenjörsverksamhet inom värme-, ventilations- och sanitetsteknik. Specialitet: plaströrskonstruktioner för industri och bostadshus",
            "key_personnel": [
                {
                    "name": "P A Prenell",
                    "position": "Verkst dir"
                }
            ],
            "establishment_year": 1944
        },
        "21": {
            "company_name": "PRENNFORS MEKANISKA VERKSTAD, AB",
            "pnr": "630 02",
            "address": "Eskilstuna 2, Nyforsg 46. Box 2029. Tel 016-136659, 13 66 63.",
            "bank_details": {
                "bankgiro": "601-3791",
                "postgiro": "348441-7"
            },
            "activity": "Tillverkar verktyg, kokiller, fixturer samt slitsmått",
            "employees": 17,
            "annual_turnover": 700000,
            "capital": 50000,
            "key_personnel": [
                {
                    "name": "Fabr Ingemar Prennfors",
                    "position": "Ägare och chef"
                }
            ],
            "establishment_year": 1951
        },
        "22": {
            "company_name": "BEY",
            "address": "Smålands g 10. Tel 08-1100 27",
            "employees": 240,
            "annual_turnover": 12000000,
            "capital": 600000,
            "key_personnel": [
                {
                    "name": "Folke Kjellnäs",
                    "position": "Verkst dir"
                },
                {
                    "name": "C A Andersson",
                    "position": "Ekonomichef"
                },
                {
                    "name": "Göte Johansson",
                    "position": "Prod-chef"
                }
            ],
            "establishment_year": 1949
        },
        "23": {
            "company_name": "SUKAB, AB",
            "pnr": "103 82",
            "address": "Stockholm 7, Birger Jarlsg 2. Box 7060. Tel 08-23 47 95.",
            "bank_details": {
                "bankgiro": "700-1993, 560-4558, 160-1640",
                "postgiro": "158980-3"
            },
            "activity": "Kompensationsaffärer, deblockeringar",
            "employees": 14,
            "annual_turnover": 538000000,
            "capital": 30000,
            "key_personnel": [
                {
                    "name": "Tom Ph Bojsen",
                    "position": "Verkst dir"
                }
            ],
            "establishment_year": 1940
        }
    }
}