{
    "original": "FÄRGMATERIAL\n\nPnr 75003\n\nUppsala 3, Box 3064. Roslagsg 2.\nTel 018-14 90 75. Bankgiro 353-3932.\nPostgiro 452172-0\nVerksamhet: Grossist- o\ndetaljhandelsförsäljning av färger, tapeter,\ngolvmaterial, verktyg samt\narbetskläder\n\nChef: Dir Torsten Palm\nEtableringsår: 1950.\n\nTVI\n\n1857. Postgiro 521061-2. Tga\nTu-verttrade\n\nVerksamhet: Konsulterande\narkitekter\n\nAntal anställda: 50\n\nÅrsomsättning: 2 500 000\n\nAktiekapital: 10 000\n\nVerkst din Ark SAR Johan E Tu-\n\nvert\n\nEtableringsån 1956.\n\nGASOLBOLAGET AGA-BP\n\nPnr 16120\n\nBromma 20, Box 8. Karlsbodav 14.\nTel 08-28 25 55. Bankgiro\n492-7356. Postgiro 136660-8\nVerksamhet: Säljer gasol o\n-utrustning till industri, hushåll etc\nAntal anstäUda: 18\nChef: Dir Hugo Bruce\nEtableringsår: 1967.\n\nOSTRUP-JEPPESEN AB\n\nPnr 21142\n\nMalmö, Verkstadsg 3. Tel\n040-97 89 80, 37680. Postgiro 38859-5.\nTga Dragé\n\nVerksamhet: Agenturaffär o\nengros-försäljning av choklad, dragéer m m\nAktiekapital: 5 000\nVerkst dir: H Ostrup-Jeppesen\nEtableringsån 1933.\n\nMOSJONS SÅGVERKS AB\n\nPnr 782 00\n\nMalung, Box 1433. Tel 0280-10511.\nBankgiro 46-8438. Postgiro 37163.\nTga Mosågen\n\nVerksamhet: Tillverkar sågade o\nhyvlade trävaror\nAntal anställda: 25\nÅrsomsättning: 1500 000\nAktiekapital: 187 500\nVerkst dir: Erie Bengtsson\nEtableringsår: 1917.\n\nMOTALA BIL &amp; ROSTFRIA\nPLÅTSLAGERI\n\nPnr 591 00\n\nMotala, Vinterg 8. Tel 0141-135 33.\nBankgiro 134-4480. Postgiro\n399099-1\n\nVerksamhet:\nVentilationsanläggningar, bilplåtslageri samt\nmonteringsarbeten för\nindustrianläggningar. Beställningsarbeten i\ntunnplåtsarbeten\nAntal anställda: 10\nChef: A Muhr\nVerkmäst: L Muhr\nEtableringsår: 1950.\n\nSCA\n\nStyrelse: Adv Kjell Brorsson (ordf),\nfru Karin Heinonen, fabr Mauno\nKurppa\n\nVerkst dir: Elis Heinonen\nEtableringsår: 1965.\n\nCITRUSFRUKTER, AB\n\nPnr 252 25\n\nHelsingborg, Speditörsg 2. Tel\n042-1205 40. Bankgiro 863-7258.\nPostgiro 481340-8\n\nVerksamhet: Import av frukt o\ngrönsaker, försäljning i parti\nAntal anställda: 17\nÅrsomsättning: 14 000 000\nAktiekapital: 74 000\nVerkst dir: Kjell Jönsson\nEtableringsår: 1953.\n\nNORSJO ALMEKO AB\n\nPnr 93104\n\nSkellefteå 4, Box 416. Tel\n0918-10610. Bankgiro 25-1073. Postgiro\n488710-5\n\nVerksamhet: Mek verkstad för\ntillverkning av hydrauliska billyftare\nVarunamn: Almeko\nAntal anställda: 15\nÅrsomsättning: 1500 000\nVerkst dir: Torsten Gustafsson\nEtableringsår: 1958.\n\nCEWILKO AB\n\nPnr 21214\n\nMalmö, Celsiusg 31. Tel\n040-18 63 60. Bankgiro 605-6212\nVerksamhet: Tillverkar kappor o\ndräkter för dam o tonår\nFabriker: Malmö. Tel 040-1863 60\nEslöv. Tel 0413-126 10\nHörby. Tel 0415-106 94\nAntal anställda: 450\nÅrsomsättning: 25 000 000\nAktiekapital: 200 000\nVerkst dir: Sven-Erik Olsson\nV verkst dir: Arne Skoglund\nEkonomidir: Börje Malmgren\nEtablerings&amp;r: 1963\n\nDotterbolag: AB Cewo-Kappor,\n\nTebewe-Modeller AB, Sahlins\nKonfektions AB.\n\nCEWO-KAPPOR, AB\n\nPnr 21214\n\nMalmö. Celsiusg 31. Tel\n040-93 6770. Bankgiro 870-1138.\nPostgiro 147431-1. Tga Cewo\nVerksamhet: Försäljer kappor o\ndräkter för dam o tonår\nAntal anställda: 8\nÅrsomsättning: 10 000 000\nAktiekapital: 350 000\nVerkst dir: Arne Skoglund\nEkonomidir: Börje Malmgren\nEtableringsår: 1936\nDotterbolag till Cewilko AB.\n\nAntal anställda: 120\nÅrsomsättning: 26 000 000\nAktiekapital: 100 000\nVerkst dir: Pontus Sundman\nEtableringsår: 1951.\n\nCHASSI E &amp; KAROSS I\nRONNEBY AB\n\nPnr 372 00\n\nRonneby, Karlshamnsv. Tel\n0457-11180. Postgiro 665050-1\nVerksamhet: Bilkarosser, tippar o\nkranar. Lastanordningar\nAntal anställda: 30\nÅrsomsättning: 1500 000\nAktiekapital: 100 000\nVerkst dir: Sven Jepson\nEtableringsår: 1937.\n\nFUTURA MÖBLER AB\n\nPnr 543 01\n\nTibro, Skövdev. Box 66. Tel\n0504-123 85. Bankgiro 22-1383. Postgiro\n9736. Tga Futura\nVerksamhet: Tillverkar stoppade\nmöbler, blombord o armatur\nAntal anställda: 80\nÅrsomsättning: 7 000 000\nVerkst dir: Eine Ward.\n\nFUTURUMVERKEN AB\n\nPnr 930 47\n\nByske. Tel 0912-105 10. Bankgiro\n764-4053. Postgiro 480042-1. Tga\nFuturumv erken.\nTelex 6838 FUTURUM S\nVerksamhet: Tillverkar Futurum\nköksventilator, torkskåp,\nimpulsdusch, spiskåpa, lavoar\nFörsäljning: 111 56 Stockholm,\nKungsg 35. Tel 08-24 36 20. Telex\n1816 FUTURM S. Försäljn-dir:\nUlf Sandberg\nVarunamn: Futurum\nAntal anställda: 175\nÅrsomsättning: 25 000 000\nAktiekapital: 150000\nDirektion: Nils Bergmark, Lennart\nBergmark\n\nVerkst dir: Nils Bergmark\nProd-chef: Hans-Olov Karlsson\nInköpschef: Nils Nordholm\nEkonomichef: Georg Westermaik\nKamrer: Per-Erik Marklund\nEtableringsår: 1952\nOmbildat till aktiebolag 1962.\n\nFYLEDALENSTEGEL.\nBRUKS AB\n\nPnr 273 00\n\nTomelilla. Tel0417-117 17, 11718.\nBankgiro 287-0160. Postgiro\n168936-3\n\nVerksamhet: Tillverkar röd borstad\n\nhålkälsfasad\n\n.Antal anställda: 20\n\nAktiekapital: 60000\n\nVerkst dir: Greta Fyledal-Adamson\n\nEtableringsår: 1859.",
    "structured": {
        "1": {
            "company_name": "FÄRGMATERIAL",
            "pnr": "75003",
            "address": "Uppsala 3, Box 3064. Roslagsg 2.",
            "phone_number": "018-14 90 75",
            "bank_details": {
                "bankgiro": "353-3932",
                "postgiro": "452172-0"
            },
            "activity": "Grossist- o detaljhandelsförsäljning av färger, tapeter, golvmaterial, verktyg samt arbetskläder",
            "key_personnel": [
                {
                    "name": "Dir Torsten Palm",
                    "position": "Chef"
                }
            ],
            "establishment_year": 1950
        },
        "2": {
            "company_name": "TVI",
            "pnr": "1857",
            "address": "",
            "phone_number": "",
            "bank_details": {
                "postgiro": "521061-2"
            },
            "activity": "Konsulterande arkitekter",
            "employees": 50,
            "annual_turnover": 2500000,
            "capital": 10000,
            "key_personnel": [
                {
                    "name": "Johan E Tu-vert",
                    "position": "Verkst din Ark SAR"
                }
            ],
            "establishment_year": 1956
        },
        "3": {
            "company_name": "GASOLBOLAGET AGA-BP",
            "pnr": "16120",
            "address": "Bromma 20, Box 8. Karlsbodav 14.",
            "phone_number": "08-28 25 55",
            "bank_details": {
                "bankgiro": "492-7356",
                "postgiro": "136660-8"
            },
            "activity": "Säljer gasol o -utrustning till industri, hushåll etc",
            "employees": 18,
            "key_personnel": [
                {
                    "name": "Hugo Bruce",
                    "position": "Chef"
                }
            ],
            "establishment_year": 1967
        },
        "4": {
            "company_name": "OSTRUP-JEPPESEN AB",
            "pnr": "21142",
            "address": "Malmö, Verkstadsg 3.",
            "phone_number": "040-97 89 80, 37680",
            "bank_details": {
                "postgiro": "38859-5"
            },
            "activity": "Agenturaffär o engros-försäljning av choklad, dragéer m m",
            "capital": 5000,
            "key_personnel": [
                {
                    "name": "H Ostrup-Jeppesen",
                    "position": "Verkst dir"
                }
            ],
            "establishment_year": 1933
        },
        "5": {
            "company_name": "MOSJONS SÅGVERKS AB",
            "pnr": "78200",
            "address": "Malung, Box 1433.",
            "phone_number": "0280-10511",
            "bank_details": {
                "bankgiro": "46-8438",
                "postgiro": "37163"
            },
            "activity": "Tillverkar sågade o hyvlade trävaror",
            "employees": 25,
            "annual_turnover": 1500000,
            "capital": 187500,
            "key_personnel": [
                {
                    "name": "Erie Bengtsson",
                    "position": "Verkst dir"
                }
            ],
            "establishment_year": 1917
        },
        "6": {
            "company_name": "MOTALA BIL & ROSTFRIA PLÅTSLAGERI",
            "pnr": "59100",
            "address": "Motala, Vinterg 8.",
            "phone_number": "0141-135 33",
            "bank_details": {
                "bankgiro": "134-4480",
                "postgiro": "399099-1"
            },
            "activity": "Ventilationsanläggningar, bilplåtslageri samt monteringsarbeten för industr...rinläggningar. Beställningsarbeten i tunnplåtsarbeten",
            "employees": 10,
            "key_personnel": [
                {
                    "name": "A Muhr",
                    "position": "Chef"
                },
                {
                    "name": "L Muhr",
                    "position": "Verkmäst"
                }
            ],
            "establishment_year": 1950
        },
        "7": {
            "company_name": "SCA",
            "key_personnel": [
                {
                    "name": "Elis Heinonen",
                    "position": "Verkst dir"
                }
            ],
            "establishment_year": 1965
        },
        "8": {
            "company_name": "CITRUSFRUKTER, AB",
            "pnr": "25225",
            "address": "Helsingborg, Speditörsg 2.",
            "phone_number": "042-1205 40",
            "bank_details": {
                "bankgiro": "863-7258",
                "postgiro": "481340-8"
            },
            "activity": "Import av frukt o grönsaker, försäljning i parti",
            "employees": 17,
            "annual_turnover": 14000000,
            "capital": 74000,
            "key_personnel": [
                {
                    "name": "Kjell Jönsson",
                    "position": "Verkst dir"
                }
            ],
            "establishment_year": 1953
        },
        "9": {
            "company_name": "NORSJO ALMEKO AB",
            "pnr": "93104",
            "address": "Skellefteå 4, Box 416.",
            "phone_number": "0918-10610",
            "bank_details": {
                "bankgiro": "25-1073",
                "postgiro": "488710-5"
            },
            "activity": "Mek verkstad för tillverkning av hydrauliska billyftare",
            "employees": 15,
            "annual_turnover": 1500000,
            "key_personnel": [
                {
                    "name": "Torsten Gustafsson",
                    "position": "Verkst dir"
                }
            ],
            "establishment_year": 1958
        },
        "10": {
            "company_name": "CEWILKO AB",
            "pnr": "21214",
            "address": "Malmö, Celsiusg 31.",
            "phone_number": "040-18 63 60",
            "bank_details": {
                "bankgiro": "605-6212"
            },
            "activity": "Tillverkar kappor o dräkter för dam o tonår",
            "employees": 450,
            "annual_turnover": 25000000,
            "capital": 200000,
            "key_personnel": [
                {
                    "name": "Sven-Erik Olsson",
                    "position": "Verkst dir"
                },
                {
                    "name": "Arne Skoglund",
                    "position": "V verkst dir"
                },
                {
                    "name": "Börje Malmgren",
                    "position": "Ekonomidir"
                }
            ],
            "establishment_year": 1963
        },
        "11": {
            "company_name": "CEWO-KAPPOR, AB",
            "pnr": "21214",
            "address": "Malmö, Celsiusg 31.",
            "phone_number": "040-93 6770",
            "bank_details": {
                "bankgiro": "870-1138",
                "postgiro": "147431-1"
            },
            "activity": "Försäljer kappor o dräkter för dam o tonår",
            "employees": 8,
            "annual_turnover": 10000000,
            "capital": 350000,
            "key_personnel": [
                {
                    "name": "Arne Skoglund",
                    "position": "Verkst dir"
                },
                {
                    "name": "Börje Malmgren",
                    "position": "Ekonomidir"
                }
            ],
            "establishment_year": 1936
        },
        "12": {
            "company_name": "CHASSI E & KAROSSI RONNEBY AB",
            "pnr": "37200",
            "address": "Ronneby, Karlshamnsv.",
            "phone_number": "0457-11180",
            "bank_details": {
                "postgiro": "665050-1"
            },
            "activity": "Bilkarosser, tippar o kranar. Lastanordningar",
            "employees": 30,
            "annual_turnover": 1500000,
            "capital": 100000,
            "key_personnel": [
                {
                    "name": "Sven Jepson",
                    "position": "Verkst dir"
                }
            ],
            "establishment_year": 1937
        },
        "13": {
            "company_name": "FUTURA MÖBLER AB",
            "pnr": "54301",
            "address": "Tibro, Skövdev. Box 66.",
            "phone_number": "0504-123 85",
            "bank_details": {
                "bankgiro": "22-1383"
            },
            "activity": "Tillverkar stoppade möbler, blombord o armatur",
            "employees": 80,
            "annual_turnover": 7000000,
            "key_personnel": [
                {
                    "name": "Eine Ward",
                    "position": "Verkst dir"
                }
            ]
        },
        "14": {
            "company_name": "FUTURUMVERKEN AB",
            "pnr": "93047",
            "address": "Byske.",
            "phone_number": "0912-105 10",
            "bank_details": {
                "bankgiro": "764-4053",
                "postgiro": "480042-1"
            },
            "activity": "Tillverkar Futurum köksventilator, torkskåp, impulsdusch, spiskåpa, lavoar",
            "address_sales": "111 56 Stockholm, Kungsg 35.",
            "phone_number_sales": "08-24 36 20",
            "varunamn": "Futurum",
            "employees": 175,
            "annual_turnover": 25000000,
            "capital": 150000,
            "key_personnel": [
                {
                    "name": "Nils Bergmark",
                    "position": "Verkst dir"
                }
            ],
            "establishment_year": 1952
        },
        "15": {
            "company_name": "FYLEDALENSTEGEL BRUKS AB",
            "pnr": "27300",
            "address": "Tomelilla.",
            "phone_number": "0417-117 17, 11718",
            "bank_details": {
                "bankgiro": "287-0160",
                "postgiro": "168936-3"
            },
            "activity": "Tillverkar röd borstad hålkälsfasad",
            "employees": 20,
            "capital": 60000,
            "key_personnel": [
                {
                    "name": "Greta Fyledal-Adamson",
                    "position": "Verkst dir"
                }
            ],
            "establishment_year": 1859
        }
    }
}