{
    "original": "MARINARMATUR, AB\n\nPnr 41707\n\nGöteborg, Bessemerg 1. Tel\n031-2210 50, 22 1059. Tga Marinarmatur\nVerksamhet: Elektr material för\nfartyg\n\nAktiekapital: 50 000\nVerkst dir: Arthur H Andersson\nEtableringsår 1930\nOmbildat till aktiebolag 1946.\n\nMARINDIESEL, AB\n\nPnr 112 33\n\nStockholm, Kronobergsg 21. Tel\n08-54 07 25. Bankgiro 16-8152.\nPostgiro 555402. Tga Marindiesel.\nTelex 17305 NORDCO S\nVerksamhet: Säljer Maybach\nMercedes-Benz dieselmotorer o\ngeneratoraggregat\nAntal anställda: 10\nÅrsomsättning: 5 500 000\nAktiekapital: 150 000\nStyrelse: Dir Björn Scherrer,\nombudsman Bo Ståhle, adv Wilhelm\nMoberg\n\nVerkst dir: Björn Scherrer\nKontorschef: Torbjörn Steiner\nEtableringsår: 1957.\n\nAHLMARK &amp; CO EFTR AB,OF\n\nPnr 65105\n\nKarlstad 1, S Kyrkog 6. Box 306.\nTel 054-115200. Bankgiro\n100-1429. Postgiro 21485-8.\nTga Ahlmarco.\nTelex 66081 AHLMARK S\nVerksamhet: Rederi, befraktning,\nskeppsmäkleri o spedition\nAntal anställda: 182\nÅrsomsättning: 79539 000\nAktiekapital: 2700000\nVerkst dir: Bengt Rejmer\nEtableringsår: 1847.\n\nALCOMETALLER, AB\n\nPnr 700 11\n\nÖrebro 11, Box 11076. Tel\n019-22 5155. Bankgiro 614-5551.\nPostgiro 36277-2\n\nVerksamhet: Tillverkar gjutgods,\näven maskinarbetat i\naluminium-brons o lättmetaller, speciellt\nfartygs- o båtpropellrar samt beslag\nVarunamn: Alcobrons, Ampco,\nNovoston, Silveral, Superston\nAntal anställda: 70\nÅrsomsättning: 6000 000\nAktiekapital: 400 000\nStyrelse: DirHaraldBernström(ordf),\ndir Erland Johnson, dlr J M\nLang-ham\n\nVerkst dir: Erland Johnson\nEtableringsår: 1921.\n\nSVE\n\nDirektion: Tel 22 92 20, riks\n08-22 92 80\n\nAntal anställda: 5 500\nAktiekapital: 501 656 000\nBalansomslutning: 17 741000 000\nVerkst dir: Dr Jan Wallander\nEtableringsår: 1871\n522 kontor över hela landet.\n\nSVENSKA HERBERTS\nAGENTUREN AB\n\nPnr 41120\n\nGöteborg, Hvitfeldtsg 14. Tel\n031-17 75 75. Bankgiro 337-4600.\nPostgiro 44352-3. Tga Herbertlack.\nTelex 21107 STIGEN S\nVerksamhet: Säljer bil- o\nindustri-läcker, grundmaterial o slipmaterial\nVerkst din Folke Stigen\nEtableringsår. 1958.\n\nGRA\n\nAntal anställda: 110\nÅrsomsättning: 20 000 000\nAktiekapital: 200000\nVerkst dir: Curt Grauers\nEtableringsår: 1957.\n\nSVENSKA MOTORBORR AB\n\nPnr 17102\n\nSoln*2, Box 237. Erik Sandbergs\ng 19. Tel 08-82 47 80. Bankgiro\n764-2278. Postgiro 251263-0. Tga\nMotorborr ab\n\nVerksamhet: Säljer transportband.\nMüller vibrationsplattor- o vältar\nAntal anställda: 4\nÅrsomsättning: 500 000\nAktiekapital: 75 000\nVerkst dir: Ing Magnus Nyström\nEtableringsår: 1945.\n\nWERNER &amp; PFLEIDERER AB\n\nPnr 112 27\n\nStockholm, Kungsholmsg 21. Tel\n08-24 42 90. Bankgiro 73-1293.\nPostgiro 359409. Telex 19946. Tga\nWepebolaget\n\nVerksamhet: Bageriutrustningar,\napparater o maskiner för den kem\nindustrin o anläggningar för\nytbehandling\n\nAntal anställda: 12\nÅrsomsättning: 5 000 000\nAktiekapital: 100000\nStyrelse: Adv Sture Hovden (ordf),\ndr C Meyer-Schulthess, bankdir\nH Magnusson\nVerkst dir: P Asmussen\nEtableringsår: 1949\nDotterbolag till Werner &amp;\nPfleiderer, Stuttgart- Feuerbach.\n\nWERNER &amp; CO AB, AUG\n\nPnr 401 25\n\nGöteborg 1, Avägen 6. Box 335.\nTel 031-19 70 30. Bankgiro 42-0471.\nPostgiro 12076. Tga Werners\nVerksamhet: Garn o vävnader i\nparti\n\nFabriker Lindome. Tel 031-76 10 00.\nFärgeri o beredningsverk,\nbomullsgarnsförsäljning\nAntal anställda: 275\nÅrsomsättning: 25 000 000\nAktiekapital: 1500 000\nStyrelse: Generalmajor C H\nNordenskiöld (ordf), bankdir Sven Raab\n(v ordf), dir Ake Werner, dir\nCarl-Eric Odelberg, dir Ingvar Grotte,\nadv Gösta Sjögren, dir Birger No-\n\nrinder, bankdir Bert Lindström\n(suppl), dir John C Werner (suppl)\nVerkst dir: Birger Norinder\nEtableringsår: 1894.\n\nDotterbolag till Gustaf Werner AB.\n\nWERNER AB, GUSTAF\n\nPnr 40121\n\nGöteborg 1, Avägen 6. Box 114.\nTel 031-19 25 60\n\nVerksamhet: Textil produktion o\ndistribution bedrives av\nnedanstående dotterbolag\n\nAntal anställda: 750 (koncernen)\nÅrsomsättning: 80 000 000\n(koncernen)\n\nAktiekapital: 4 800 000\nStyrelse: Generalmajor C H\nNordenskiöld (ordf), bankdir Sven Raab\n(v ordf), dir Ake Werner, dir\nCarl-Eric Odelberg, dir Ingvar Grotte,\nadv Gösta Sjögren, dir Birger\nNorinder, bankdir Bert Lindström\n(suppl), dir John C Werner (suppl)\nVeikst dir: Birger Norinder\nEtableringsår: 1885\nDotterbolag: Göteborgs\nKamgarns-spinneri AB, AB Hermann Kürzel,\nAug J:son Mark &amp; Co AB, AB\nWerner &amp; Carlström, Aug Werner &amp;\nCo AB samtliga i Göteborg. AB\nKamgarn, Borås (se respektive\nbolag). Marks Garner AS,\nKöpenhamn.\n\nWERNGRENSBROD AB\n\nPnr 653 41\n\nKarlstad, Blockg 8. Tel\n054-115650. Bankgiro 438-8872.\nPostgiro 494365-0\n\nVerksamhet: Tillverkar\nbageriprodukter\n\nAntal anställda: 25\nÅrsomsättning: 3 000 000\nAktiekapital: 180000\nVerkst dir. Ingmar Werngren\nEtableringsår: 1868.\n\nWHERNMAN AB KONSULTE.\nRANDE INGEN JÖR SBYRÄ,\nFRANZ\n\nPra 40010\n\nGöteborg 3, Vasag 21. Fack. Tel\n031-11 87 00. Bankgiro 223-9689.\nPostgiro 240276-6\nVerksamhet: Industriell\norganisation o maskinkonstruktioner\nAktiekapital: 5 000\nVerkst dir: Overing Hugo Andersson\nEtableringsår: 1952.\n\nLANNA TRÄ &amp; METALL AB\n\nPnr 33010\n\nBredaryd. Tel 0370-830 79\nVerksamhet: Tillverkar rör o\ntrådartiklar i metall\nAktiekapital: 5 000\nVerkst dir: Evert Johansson.\n\nLANTBRUKARNAS\nEKONOMI-AB\n\nPnr 105 33\n\nStockholm, Klara O Kyrkog 12.\nTel 08-14 16 00\n\nVerksamhet: Konsultation i\nekonomiska o tekniska ärenden,\nfinansrörelse, förlags- o\naffärsverksamhet\n\nAktiekapital: 10 000 000\nVerkst dir: H Håkansson\nEtableringsår: 1934\n\nNamnändring 1970.\n\nLANTBRUKARNAS MJULK.\nCENTRAL FÖRENING U P A\n\nPnr 402 20\n\nGöteborg 5, Mejerig 3. Fack. Tel\n\n031-40 02 40\n\nMejerier:\n\nAlingsås. Tel 0322-142 80\nBorås. Tel 033-1174 80\nDingle. Tel 0524-403 95\nFalkenberg. Tel 0346-141 70\nGällstad. Tel 0321-700 10\nHalmstad. Tel 035-11 87 80\nKvibille. Tel 035-560 01\nNossebro. Tel 0512-506 20\nOrust. Tel 0304-470 30\nSkee. Tel 0526-210 20\nTrollhättan. Tel 0520-10101\nVallberga. Tel 0430-23 2 80\nVallbro. Tel 0325-500 14\nVarberg. Tel 03 40-165 1 5\nVänersborg. Tel 0521-190 10\nAntal anställda: 1200\nÅrsomsättning: 420 000 000\nStyrelseordf: Folke Samuelson\nVerkst dir: Pär Arne Darj\nEtableringsår: 1935.\n\nLANTBRUKS. &amp; INDUSTRI.\nMASKINER, AB\n\nPnr 220 14\n\nLund 14, Box 14041. Rossings v.\nTel 046-483 00. Bankgiro 640-0246,\nPostgiro 435895-8\nVerksamhet: Tillverkar\nlantbruks-o skogssprutor, pumpar o\ntankvagnar samt tankar av\nglasfiberarme-rad plast\n\nVarunamn: Lindus\nÅrsomsättning: 700 000\nAktiekapital: 10 000\nVerkst dir: Per Jakobsson\nEtableringsår: 1954.\n\nLANTBRUKSFURBUNDETS\nREVISIONSBYRÅ AB\n\nPnr 105 33\n\nStockholm, Drottningg 56. Tel\n08-14 16 00. Bankgiro 655-1865.\nPostgiro 256999-4\n\nVerksamhet: Revisions- o liknande\nkonsulterande verksamhet\nAntal anstäUda: 96\nÅrsomsättning: 5 200 000\nAktiekapital: 100 000\n\nVerkst dir. Aukt revisor Ivar\nClaesson\n\nEtableringsår: 1947.\n\nULRICEHAMNS STOLFABRIK\n\nPnr 523 00\n\nUlricehamn, Jägareg 54. Tel\n0321-10345. Bankgiro 84-4230. Postgiro\n375594\n\nVerksamhet: Tillverkar trävita\nstolar o fåtölj stommar\nAntal anställda: 5\nÅrsomsättning: 200 000\nÄgare o chef: Holger Lindberg\nEtableringsår: 1949.\n\nULRICEHAMNS YLLE.\nFABRIK, AB\n\nPnr 523 00\n\nUlricehamn, Höjdg 3, Box 111. Tel\n0321-123 00. Bankgiro 53-2853.\nPostgiro 32671. Tga Yllefabriken\nVerksamhet: Trikåtillverkning för\nbarn, dam o herr\nAntal anställda: 140\nÅrsomsättning: 7 000 000\nAktiekapital: 303 000\nVerkst dir: Folke Hultgren\nEtableringsår: 1916.\n\nSMIDE &amp; SVETSNING\n\nPnr 681 00\n\nKristinehamn, Andra Industrig 5.\nTel 0550-124 18, 130 16. Bankgiro\n82-0007. Postgiro 336588\nVerksamhet: Tillverkar\nbyggnads-smiden, plåt- o stålkonstruktioner\nAntal anställda: 11\nChef: Bertil Johansson\nEtableringsår: 1948.\n\nSMIDES- &amp;\nJÄRNSÄNGSFABRIKS AB\n\nPnr 740 60\n\nörbyhus. Tel 0295-106 10\nVerksamhet: Tillverkar järn- o\nträsängar, bårar, rullande material.\nSpecialitet: sjukhusutrustning\nKontor: Stockholm C, Norrlandsg\n16. Tel 08-23 17 95\nAntal anstäUda: 132\nÅrsomsättning: 6 600 000\nAktiekapital: 625 000\nStyrelse: Adv Clas Ostberg (ordf),\nherr Lars Ericsson, dir Töre\nEricsson\n\nVerkst dir: Töre Ericsson\nEtableringsår: 1911.",
    "structured": {
        "1": {
            "company_name": "MARINARMATUR, AB",
            "pnr": "41707",
            "address": "Göteborg, Bessemerg 1",
            "phone_number": "031-2210 50, 22 1059",
            "activity": "Elektr material för fartyg",
            "employees": null,
            "annual_turnover": null,
            "capital": 50000,
            "key_personnel": [
                {
                    "name": "Arthur H Andersson",
                    "position": "Verkst dir"
                }
            ],
            "establishment_year": 1930
        },
        "2": {
            "company_name": "MARINDIESEL, AB",
            "pnr": "112 33",
            "address": "Stockholm, Kronobergsg 21",
            "phone_number": "08-54 07 25",
            "bank_details": {
                "bankgiro": "16-8152",
                "postgiro": "555402"
            },
            "activity": "Säljer Maybach Mercedes-Benz dieselmotorer o generatoraggregat",
            "employees": 10,
            "annual_turnover": 5500000,
            "capital": 150000,
            "key_personnel": [
                {
                    "name": "Björn Scherrer",
                    "position": "Verkst dir"
                },
                {
                    "name": "Torbjörn Steiner",
                    "position": "Kontorschef"
                }
            ],
            "establishment_year": 1957
        },
        "3": {
            "company_name": "AHLMARK & CO EFTR AB,OF",
            "pnr": "65105",
            "address": "Karlstad 1, S Kyrkog 6, Box 306",
            "phone_number": "054-115200",
            "bank_details": {
                "bankgiro": "100-1429",
                "postgiro": "21485-8"
            },
            "activity": "Rederi, befraktning, skeppsmäkleri o spedition",
            "employees": 182,
            "annual_turnover": 79539000,
            "capital": 2700000,
            "key_personnel": [
                {
                    "name": "Bengt Rejmer",
                    "position": "Verkst dir"
                }
            ],
            "establishment_year": 1847
        },
        "4": {
            "company_name": "ALCOMETALLER, AB",
            "pnr": "700 11",
            "address": "Örebro 11, Box 11076",
            "phone_number": "019-22 5155",
            "bank_details": {
                "bankgiro": "614-5551",
                "postgiro": "36277-2"
            },
            "activity": "Tillverkar gjutgods, även maskinarbetat i aluminium-brons o lättmetaller, speciellt fartygs- o båtpropellrar samt beslag",
            "employees": 70,
            "annual_turnover": 6000000,
            "capital": 400000,
            "key_personnel": [
                {
                    "name": "Erland Johnson",
                    "position": "Verkst dir"
                }
            ],
            "establishment_year": 1921
        },
        "5": {
            "company_name": "SVE",
            "employees": 5500,
            "capital": 501656000,
            "establishment_year": 1871
        },
        "6": {
            "company_name": "SVENSKA HERBERTS",
            "pnr": "41120",
            "address": "Göteborg, Hvitfeldtsg 14",
            "phone_number": "031-17 75 75",
            "bank_details": {
                "bankgiro": "337-4600",
                "postgiro": "44352-3"
            },
            "activity": "Säljer bil- o industri-läcker, grundmaterial o slipmaterial",
            "employees": null,
            "annual_turnover": 20000000,
            "capital": 200000,
            "key_personnel": [
                {
                    "name": "Folke Stigen",
                    "position": "Verkst dir"
                }
            ],
            "establishment_year": 1958
        },
        "7": {
            "company_name": "GRA",
            "employees": 110,
            "annual_turnover": 20000000,
            "capital": 200000,
            "key_personnel": [
                {
                    "name": "Curt Grauers",
                    "position": "Verkst dir"
                }
            ],
            "establishment_year": 1957
        },
        "8": {
            "company_name": "SVENSKA MOTORBORR AB",
            "pnr": "17102",
            "address": "Soln*2, Box 237, Erik Sandbergs g 19",
            "phone_number": "08-82 47 80",
            "bank_details": {
                "bankgiro": "764-2278",
                "postgiro": "251263-0"
            },
            "activity": "Säljer transportband, Müller vibrationsplattor- o vältar",
            "employees": 4,
            "annual_turnover": 500000,
            "capital": 75000,
            "key_personnel": [
                {
                    "name": "Ing Magnus Nyström",
                    "position": "Verkst dir"
                }
            ],
            "establishment_year": 1945
        },
        "9": {
            "company_name": "WERNER & PFLEIDERER AB",
            "pnr": "112 27",
            "address": "Stockholm, Kungsholmsg 21",
            "phone_number": "08-24 42 90",
            "bank_details": {
                "bankgiro": "73-1293",
                "postgiro": "359409"
            },
            "activity": "Bageriutrustningar, apparater o maskiner för den kem industrin o anläggningar för ytbehandling",
            "employees": 12,
            "annual_turnover": 5000000,
            "capital": 100000,
            "key_personnel": [
                {
                    "name": "P Asmussen",
                    "position": "Verkst dir"
                }
            ],
            "establishment_year": 1949
        },
        "10": {
            "company_name": "WERNER & CO AB, AUG",
            "pnr": "401 25",
            "address": "Göteborg 1, Avägen 6, Box 335",
            "phone_number": "031-19 70 30",
            "bank_details": {
                "bankgiro": "42-0471",
                "postgiro": "12076"
            },
            "activity": "Garn o vävnader i parti",
            "employees": 275,
            "annual_turnover": 25000000,
            "capital": 1500000,
            "key_personnel": [
                {
                    "name": "Birger Norinder",
                    "position": "Verkst dir"
                }
            ],
            "establishment_year": 1894
        },
        "11": {
            "company_name": "WERNER AB, GUSTAF",
            "pnr": "40121",
            "address": "Göteborg 1, Avägen 6, Box 114",
            "phone_number": "031-19 25 60",
            "activity": "Textil produktion o distribution bedrives av nedanstående dotterbolag",
            "employees": 750,
            "annual_turnover": 80000000,
            "capital": 4800000,
            "key_personnel": [
                {
                    "name": "Birger Norinder",
                    "position": "Verkst dir"
                }
            ],
            "establishment_year": 1885
        },
        "12": {
            "company_name": "WERNGRENSBROD AB",
            "pnr": "653 41",
            "address": "Karlstad, Blockg 8",
            "phone_number": "054-115650",
            "bank_details": {
                "bankgiro": "438-8872",
                "postgiro": "494365-0"
            },
            "activity": "Tillverkar bageriprodukter",
            "employees": 25,
            "annual_turnover": 3000000,
            "capital": 180000,
            "key_personnel": [
                {
                    "name": "Ingmar Werngren",
                    "position": "Verkst dir"
                }
            ],
            "establishment_year": 1868
        },
        "13": {
            "company_name": "WHERNMAN AB KONSULTE.",
            "pnr": "40010",
            "address": "Göteborg 3, Vasag 21",
            "phone_number": "031-11 87 00",
            "bank_details": {
                "bankgiro": "223-9689",
                "postgiro": "240276-6"
            },
            "activity": "Industriell organisation o maskinkonstruktioner",
            "capital": 5000,
            "key_personnel": [
                {
                    "name": "Overing Hugo Andersson",
                    "position": "Verkst dir"
                }
            ],
            "establishment_year": 1952
        },
        "14": {
            "company_name": "LANNA TRÄ & METALL AB",
            "pnr": "33010",
            "address": "Bredaryd",
            "phone_number": "0370-830 79",
            "activity": "Tillverkar rör o trådartiklar i metall",
            "capital": 5000,
            "key_personnel": [
                {
                    "name": "Evert Johansson",
                    "position": "Verkst dir"
                }
            ]
        },
        "15": {
            "company_name": "LANTBRUKARNAS",
            "pnr": "105 33",
            "address": "Stockholm, Klara O Kyrkog 12",
            "phone_number": "08-14 16 00",
            "activity": "Konsultation i ekonomiska o tekniska ärenden, finansrörelse, förlags- o affärsverksamhet",
            "capital": 10000000,
            "key_personnel": [
                {
                    "name": "H Håkansson",
                    "position": "Verkst dir"
                }
            ],
            "establishment_year": 1934
        },
        "16": {
            "company_name": "LANTBRUKARNAS MJULK. CENTRAL FÖRENING U P A",
            "pnr": "402 20",
            "address": "Göteborg 5, Mejerig 3",
            "phone_number": "031-40 02 40",
            "activity": "Mejerier",
            "employees": 1200,
            "annual_turnover": 420000000,
            "key_personnel": [
                {
                    "name": "Pär Arne Darj",
                    "position": "Verkst dir"
                }
            ],
            "establishment_year": 1935
        },
        "17": {
            "company_name": "LANTBRUKS. & INDUSTRI. MASKINER, AB",
            "pnr": "220 14",
            "address": "Lund 14, Box 14041, Rossings v",
            "phone_number": "046-483 00",
            "bank_details": {
                "bankgiro": "640-0246",
                "postgiro": "435895-8"
            },
            "activity": "Tillverkar lantbruks-o skogssprutor, pumpar o tankvagnar samt tankar av glasfiberarmelad plast",
            "employees": null,
            "annual_turnover": 700000,
            "capital": 10000,
            "key_personnel": [
                {
                    "name": "Per Jakobsson",
                    "position": "Verkst dir"
                }
            ],
            "establishment_year": 1954
        },
        "18": {
            "company_name": "LANTBRUKSFURBUNDETS REVISIONSBYRÅ AB",
            "pnr": "105 33",
            "address": "Stockholm, Drottningg 56",
            "phone_number": "08-14 16 00",
            "bank_details": {
                "bankgiro": "655-1865",
                "postgiro": "256999-4"
            },
            "activity": "Revisions- o liknande konsulterande verksamhet",
            "employees": 96,
            "annual_turnover": 5200000,
            "capital": 100000,
            "key_personnel": [
                {
                    "name": "Aukt revisor Ivar Claesson",
                    "position": "Verkst dir"
                }
            ],
            "establishment_year": 1947
        },
        "19": {
            "company_name": "ULRICEHAMNS STOLFABRIK",
            "pnr": "523 00",
            "address": "Ulricehamn, Jägareg 54",
            "phone_number": "0321-10345",
            "bank_details": {
                "bankgiro": "84-4230",
                "postgiro": "375594"
            },
            "activity": "Tillverkar trävita stolar o fåtölj stommar",
            "employees": 5,
            "annual_turnover": 200000,
            "key_personnel": [
                {
                    "name": "Holger Lindberg",
                    "position": "Ägare o chef"
                }
            ],
            "establishment_year": 1949
        },
        "20": {
            "company_name": "ULRICEHAMNS YLLE. FABRIK, AB",
            "pnr": "523 00",
            "address": "Ulricehamn, Höjdg 3, Box 111",
            "phone_number": "0321-123 00",
            "bank_details": {
                "bankgiro": "53-2853",
                "postgiro": "32671"
            },
            "activity": "Trikåtillverkning för barn, dam o herr",
            "employees": 140,
            "annual_turnover": 7000000,
            "capital": 303000,
            "key_personnel": [
                {
                    "name": "Folke Hultgren",
                    "position": "Verkst dir"
                }
            ],
            "establishment_year": 1916
        },
        "21": {
            "company_name": "SMIDE & SVETSNING",
            "pnr": "681 00",
            "address": "Kristinehamn, Andra Industrig 5",
            "phone_number": "0550-124 18, 130 16",
            "bank_details": {
                "bankgiro": "82-0007",
                "postgiro": "336588"
            },
            "activity": "Tillverkar byggnadssmiden, plåt- o stålkonstruktioner",
            "employees": 11,
            "key_personnel": [
                {
                    "name": "Bertil Johansson",
                    "position": "Chef"
                }
            ],
            "establishment_year": 1948
        },
        "22": {
            "company_name": "SMIDES- &  JÄRNSÄNGSFABRIKS AB",
            "pnr": "740 60",
            "address": "örbyhus",
            "phone_number": "0295-106 10",
            "activity": "Tillverkar järn- o träsängar, bårar, rullande material. Specialitet: sjukhusutrustning",
            "employees": 132,
            "annual_turnover": 6600000,
            "capital": 625000,
            "key_personnel": [
                {
                    "name": "Töre Ericsson",
                    "position": "Verkst dir"
                }
            ],
            "establishment_year": 1911
        }
    }
}