{
    "original": "ZANDER &amp; INGESTROM, AB\n\nPnr 102 23\n\nStockholm 12, Fyrverkarbacken 34.\nBox 12088. Tel 08-2241 00.\nBankgiro 19-6058. Postgiro 3699. Telex\n10074. Tga Maskinzeta\nVerksamhet: Säljer pumpar,\nhydrauliska utrustningar,\npumpan-läggningar o maskinell utrustning\nför vatten- o avloppsverk,\nvattenreningsutrustningar, industrisepar\nratorer, värmeväxlare, elektr\nångpannor, mät- o\nregleringsinstrument, högfrekvensapparater mm\nAvdelningskontor: 402 41 Göteborg\n12. Fiskhamnsg 4. Box 12051. Tel\n031-42 0140\n\n65105 Karlstad 1. Brog 1. Box\n325. Tel 054-15 0145\n21140 Malmö. S Tullg 3. Tel\n040-757 60\n\nz\n\n852 35 Sundsvall, Nybrog 17. Tel\n060-12 3260\nAntal anställda: 290\nÅrsomsättning: 100000 000\nAktiekapital: 10 000 000\nStyrelse: Dir Carl Fr Jacobsson\n(crdf), dir Hans Ståhle, dir Peder\nBonde, dir Karl Nilsson, dir Sten\nSöderström\n\nVerkst dir: Sten Söderström\nV verkst dir o ekonomidir: Svante\nThunander\n\nFörsäljn-dir: Ernst Hildebeck\nEtableringsår 1898\nDotterbolag till Alfa-Laval AB.\n\nZANTONSRORMONTAGE AB\n\nPnr 593 01\n\nVästervik 1, Box 50. Rådhusg 36.\nTel 0490-102 06, 109 86. Bankgiro\n821-1914. Postgiro 56850-6\nVerksamhet: Installationer av\nvärme- o sanitära anläggningar\nAntal anställda: 17\nÅrsomsättning: 1000 000\nAktiekapital: 5 000\nVerkst dir: Stig Zanton\nEtableringsår: 1912.\n\nGEVEKO, AB\n\nPnr 403 13\n\nGöteborg 2, Magasinsg 3. Box\n2137. Tel 031-17 29 45. Bankgiro\n847-7375. Postgiro 40163-8.\nTga Geveko\n\nVerksamhet: Koncernbolag för\nGatu o Väg AB, Underås AB, AB\nDiabas, Geveko Industri AB o\nGeveko Byggnads AB\nAktiekapital: 6000 000\nStyrelse: Dir Harald Magnusson\n(ordf), dir Nils Berggren, civiling\nJarl Ergel, dir Folke Pehrsson, dir\nGunnar Mattsson\nVerkst dir: Civiling Jarl Ergel\nEtableringsår: 1926.\n\nASKERSUNDS STÄNGSEL AB\n\nPnr 696 00\n\nAskersund, Torebergsv 13. Tel\n0583-116 00. Bankgiro 581-0593.\nPostgiro 234030-5\nVerksamhet: Leverans o\nuppsättning av stängselnät\nAntal anställda: 12\nÅrsomsättning: 800 000\nAktiekapital: 30 000\nVerkst dir: Benny Rosenblom\nEtableringsår: 1968.\n\nASKERSUNDS TRIKÅ.\nFABRIK, AB\n\nPnr 696 00\n\nAskersund, Box 29. Tel\n0583-10069, 10169. Postgiro 10004-0.\nTga Trikåfabriken\nVerksamhet: Tillverkar tränings- o\ngymnastikdräkter, modeplagg\nAntal anställda: 70\nAktiekapital: 300 000\nVerkst dir: Pru Lisa Pors\nEtableringsår. 1909.\n\nÅKERS STYCKEBRUK, AB\n\nPnr 150 31\n\nÅkers Styckebruk. Tel 0159-302 60.\nBankgiro 330-1215. Postgiro\n12795-1. Tga Akersroll, Stockholm.\nTelex 10257 ÅKERS S\n\nVerksamhet: Gjuteri o mekanisk\nverkstad\n\nAntal anställda: 500\nÅrsomsättning: 50000 000\nAktiekapital: 6 300 000\nVerkst dir. Torsten Collën\nEtableringsån Omkring 1580.\n\nHOAB, HOLGER af BURÉN AB\n\nPnr 415 02\n\nGöteborg, von Holtensg 12. Tel\n031-15 20 33, 15 2133. Telex 20095.\nTga Hoabmachine\nVerksamhet: säljer STG\ndukfilter-anläggningar för ren luft\nÄgare o chef: Holger af Burén\nEtableringsår: 1962.\n\nHOCO, ELEKTRISKA AB\nHOLM &amp; CO\n\nPnr 104 40\n\nStockholm 14, Riddarg 17. Box\n14037. Tel 08-223120. Bankgiro\n235-2243. Postgiro 1749-1. Tga\n\nHo co\n\nVerksamhet: Elektr\ninstallationsmateriel engros\nAntal anstäUda: 86\nÅrsomsättning: 28 500 000\nAktiekapital: 5 225 000\nVerkst dir: Hans J Bergschöld\nEtableringsår: 1928.\n\nELEKTRO STANDARD AB\n\nPnr 64100\n\nKatrineholm, Västgötag 18. Tel\n0150-13170. Tga Elstandard\nVerksamhet: Tillverkar el\nvärme-o hushållsapparater\nAntal anställda: 100\nÅrsomsättning: 10000000\nAktiekapital: 100 000\nVerkst dir: Sten Nilson\nEtableringsår: 1938.\n\nBK\n\nBJDRKSUNDSFODER, AB\n\nPnr 610 60\n\nTystberga. Tel 0155-64011, 64014.\nBankgiro 61-9173. Postgiro 570825\nVerksamhet: Jord- o skogsbruk.\nFodertillverkning\nAntal anställda: 18\nÅrsomsättning: 2 000 000\nAktiekapital: 100000\nVerkst dir: Greve Nils Mörner\nEtableringsår: 1960.\n\nWI RO. AB\n\nPnr 104 35\n\nStockholm 23, Box 23100.\nYng-lingag 17. Tel 08-23 32 00.\nBankgiro 724-5301. Postgiro 57171-1.\nTga Wirotrade. Telex 1403 WIRO S\nVerksamhet: Försäljning o\ntillverkning av industrispecialiteter inom\nde hydrauliska, pneumatiska,\nvärmetekniska o logistiska områdena\nDistribunal o fabrik: 591 01 Motala 1,\nBox 97. Drakv 5. Tel 0141-520 20\nVarunamn: Aeroquip, ASB, Bettis,\nBoa. EMB. Macwhyte. Numatics,\nWi ro\n\nAntal anstäUda: 75\nAktiekapital: 500 000\n\nDirektion: Rune G Berggren, Sten\nBerggren\n\nEtableringsår: 1923.\n\nESTRELLA, AB\n\nPnr 400 51\n\nGöteborg 47, Dagjämningsg 4,\nKortedala. Fack. Tel 031-46 00 80.\nBankgiro 43-6608. Postgiro 429486.\nTga Estrella\n\nVerksamhet: Tillverkar o säljer\npotatischips samt olika\nsnacksprodukter som Popcorn, Ostbågar,\nBacon Crisp, Dip Mix m m\nAntal anställda: 120\nÅrsomsättning: 25 000 000\nVerkst dir: Leif Throne-Holst\nEtableringsår 1946.\n\nANDELL &amp; ANDERSON AB\n\nPnr 400 10\n\nGöteborg 3, Viktoriag 16. Box\n3001. Tel 031-1705 90. Bankgiro\n42-0005. Postgiro 240826. Tga\nAndeländer\n\nVerksamhet: Textilvaror, sybehör\nengros\n\nAktiekapital: 500 000\nVerkst dir: Lennart Bülow\nEtableringsår: 1946.",
    "structured": {
        "1": {
            "company_name": "ZANDER & INGESTROM, AB",
            "address": "Stockholm 12, Fyrverkarbacken 34. Box 12088",
            "phone_number": "08-2241 00",
            "bank_details": {
                "bankgiro": "19-6058",
                "postgiro": "3699"
            },
            "activity": "Säljer pumpar, hydrauliska utrustningar, pumpanläggningar o maskinell utrustning för vatten- o avloppsverk, vattenreningsutrustningar, industriseparatorer, värmeväxlare, elektrångpannor, mät- o regleringsinstrument, högfrekvensapparater mm",
            "employees": 290,
            "annual_turnover": 100000000,
            "capital": 10000000,
            "key_personnel": [
                {
                    "name": "Carl Fr Jacobsson",
                    "position": "Director"
                },
                {
                    "name": "Hans Ståhle",
                    "position": "Director"
                },
                {
                    "name": "Peder Bonde",
                    "position": "Director"
                },
                {
                    "name": "Karl Nilsson",
                    "position": "Director"
                },
                {
                    "name": "Sten Söderström",
                    "position": "Director"
                }
            ],
            "establishment_year": 1898
        },
        "2": {
            "company_name": "ZANTONSRORMONTAGE AB",
            "address": "Västervik 1, Box 50. Rådhusg 36",
            "phone_number": "0490-102 06, 109 86",
            "bank_details": {
                "bankgiro": "821-1914",
                "postgiro": "56850-6"
            },
            "activity": "Installationer av värme- o sanitära anläggningar",
            "employees": 17,
            "annual_turnover": 1000000,
            "capital": 5000,
            "key_personnel": [
                {
                    "name": "Stig Zanton",
                    "position": "Director"
                }
            ],
            "establishment_year": 1912
        },
        "3": {
            "company_name": "GEVEKO, AB",
            "address": "Göteborg 2, Magasinsg 3. Box 2137",
            "phone_number": "031-17 29 45",
            "bank_details": {
                "bankgiro": "847-7375",
                "postgiro": "40163-8"
            },
            "activity": "Koncernbolag för Gatu o Väg AB, Underås AB, AB Diabas, Geveko Industri AB o Geveko Byggnads AB",
            "capital": 6000000,
            "key_personnel": [
                {
                    "name": "Harald Magnusson",
                    "position": "Chairman"
                },
                {
                    "name": "Nils Berggren",
                    "position": "Director"
                },
                {
                    "name": "Jarl Ergel",
                    "position": "Civil Engineer"
                },
                {
                    "name": "Folke Pehrsson",
                    "position": "Director"
                },
                {
                    "name": "Gunnar Mattsson",
                    "position": "Director"
                }
            ],
            "establishment_year": 1926
        },
        "4": {
            "company_name": "ASKERSUNDS STÄNGSEL AB",
            "address": "Askersund, Torebergsv 13",
            "phone_number": "0583-116 00",
            "bank_details": {
                "bankgiro": "581-0593",
                "postgiro": "234030-5"
            },
            "activity": "Leverans o uppsättning av stängselnät",
            "employees": 12,
            "annual_turnover": 800000,
            "capital": 30000,
            "key_personnel": [
                {
                    "name": "Benny Rosenblom",
                    "position": "Director"
                }
            ],
            "establishment_year": 1968
        },
        "5": {
            "company_name": "ASKERSUNDS TRIKÅ. FABRIK, AB",
            "address": "Askersund, Box 29",
            "phone_number": "0583-10069, 10169",
            "bank_details": {
                "postgiro": "10004-0"
            },
            "activity": "Tillverkar tränings- o gymnastikdräkter, modeplagg",
            "employees": 70,
            "capital": 300000,
            "key_personnel": [
                {
                    "name": "Pru Lisa Pors",
                    "position": "Director"
                }
            ],
            "establishment_year": 1909
        },
        "6": {
            "company_name": "ÅKERS STYCKEBRUK, AB",
            "address": "Åkers Styckebruk",
            "phone_number": "0159-302 60",
            "bank_details": {
                "bankgiro": "330-1215",
                "postgiro": "12795-1"
            },
            "activity": "Gjuteri o mekanisk verkstad",
            "employees": 500,
            "annual_turnover": 50000000,
            "capital": 6300000,
            "key_personnel": [
                {
                    "name": "Torsten Collën",
                    "position": "Director"
                }
            ],
            "establishment_year": "Omkring 1580"
        },
        "7": {
            "company_name": "HOAB, HOLGER af BURÉN AB",
            "address": "Göteborg, von Holtensg 12",
            "phone_number": "031-15 20 33, 15 2133",
            "bank_details": {
                "telex": "20095"
            },
            "activity": "Säljer STG dukfilter-anläggningar för ren luft",
            "capital": null,
            "key_personnel": null,
            "establishment_year": 1962
        },
        "8": {
            "company_name": "HOCO, ELEKTRISKA AB HOLM & CO",
            "address": "Stockholm 14, Riddarg 17. Box 14037",
            "phone_number": "08-223120",
            "bank_details": {
                "bankgiro": "235-2243",
                "postgiro": "1749-1"
            },
            "activity": "Elektr installationsmateriel engros",
            "employees": 86,
            "annual_turnover": 28500000,
            "capital": 5225000,
            "key_personnel": [
                {
                    "name": "Hans J Bergschöld",
                    "position": "Director"
                }
            ],
            "establishment_year": 1928
        },
        "9": {
            "company_name": "ELEKTRO STANDARD AB",
            "address": "Katrineholm, Västgötag 18",
            "phone_number": "0150-13170",
            "bank_details": {
                "telex": "Elstandard"
            },
            "activity": "Tillverkar el värme-o hushållsapparater",
            "employees": 100,
            "annual_turnover": 10000000,
            "capital": 100000,
            "key_personnel": [
                {
                    "name": "Sten Nilson",
                    "position": "Director"
                }
            ],
            "establishment_year": 1938
        },
        "10": {
            "company_name": "BJDRKSUNDSFODER, AB",
            "address": "Tystberga",
            "phone_number": "0155-64011, 64014",
            "bank_details": {
                "bankgiro": "61-9173",
                "postgiro": "570825"
            },
            "activity": "Jord- o skogsbruk. Fodertillverkning",
            "employees": 18,
            "annual_turnover": 2000000,
            "capital": 100000,
            "key_personnel": [
                {
                    "name": "Greve Nils Mörner",
                    "position": "Director"
                }
            ],
            "establishment_year": 1960
        },
        "11": {
            "company_name": "WI RO. AB",
            "address": "Stockholm 23, Box 23100. Yng-lingag 17",
            "phone_number": "08-23 32 00",
            "bank_details": {
                "bankgiro": "724-5301",
                "postgiro": "57171-1",
                "telex": "1403 WIRO S"
            },
            "activity": "Försäljning o tillverkning av industrispecialiteter inom de hydrauliska, pneumatiska, värmetekniska o logistiska områdena",
            "distribunal_fabrik": "591 01 Motala 1, Box 97. Drakv 5. Tel 0141-520 20",
            "varunamn": "Aeroquip, ASB, Bettis, Boa. EMB. Macwhyte. Numatics, Wi ro",
            "employees": 75,
            "capital": 500000,
            "key_personnel": [
                {
                    "name": "Rune G Berggren",
                    "position": "Director"
                },
                {
                    "name": "Sten Berggren",
                    "position": "Director"
                }
            ],
            "establishment_year": 1923
        },
        "12": {
            "company_name": "ESTRELLA, AB",
            "address": "Göteborg 47, Dagjämningsg 4, Kortedala",
            "phone_number": "031-46 00 80",
            "bank_details": {
                "bankgiro": "43-6608",
                "postgiro": "429486"
            },
            "activity": "Tillverkar o säljer potatischips samt olika snacksprodukter som Popcorn, Ostbågar, Bacon Crisp, Dip Mix m m",
            "employees": 120,
            "annual_turnover": 25000000,
            "key_personnel": [
                {
                    "name": "Leif Throne-Holst",
                    "position": "Director"
                }
            ],
            "establishment_year": 1946
        },
        "13": {
            "company_name": "ANDELL & ANDERSON AB",
            "address": "Göteborg 3, Viktoriag 16. Box 3001",
            "phone_number": "031-1705 90",
            "bank_details": {
                "bankgiro": "42-0005",
                "postgiro": "240826"
            },
            "activity": "Textilvaror, sybehör engros",
            "capital": 500000,
            "key_personnel": [
                {
                    "name": "Lennart Bülow",
                    "position": "Director"
                }
            ],
            "establishment_year": "1946.."
        }
    }
}