{
    "original": "BIL &amp; BUSS I FALUN AB\n\nPnr 79100\n\nFalun, Timmerv 14. Tel 023-188 50\nVerksamhet: Bilar, reservdelar o\nbilverkstäder\nAntal anställda: 118\nÅrsomsättning: 24 902 000\nAktiekapital: 200 000\nVerkst dir: Gösta Lindqvist\nEtableringsår: 1958.\n\nESSE BYGGNADSMATERIAL\n\nPnr 770 20\n\nSöderbärke. Tel 0240-503 71, 510 92.\nBankgiro 47-1405. Postgiro\n467388-5\n\nVerksamhet: Tillverkar o säljer\nmurartrallar, betongformar etc\nAntal anställda: 30\nÅrsomsättning: 3 000 000\nChef: Fabrikör Rune Eriksson\nEtableringsår: 1950.\n\nFAM\n\nFALKÖPINGS BILCITY AB\n\nPnr 52101\n\nFalköping 1, Box 95. Allebergsv 10.\nTel 0515-132 50. Postgiro 348240-3\nVerksamhet: Försäljning o\nreparation av personbilar\nAntal anställda: 20\nÅrsomsättning: 4 400 000\nAktiekapital: 150000\nVerkst din O Rehnquist\nEtableringsår: 1967.\n\nFALKÖPINGS LIKKIST.\nFABRIK, AB\n\nPnr 52100\n\nFalköping, Bang 18. Tel\n0515-10170, 147 70. Bankgiro 541-5799.\nPostgiro 73611-6.\nVerksamhet: Tillverkar o säljer\nlikkista1 o sarkofager i fur o ek\nAntal anställda: 26\nAktiekapital: 50 000\nVerkst din Olle Grahn\nEtableringsår: 1927\nOmbildat till aktiebolag 1953.\n\nFALKÖPINGS TIDNING, AB\n\nPnr 52101\n\nFalköping 1, Box 47. Landbog 4.\nTel 0515-134 50. Bankgiro\n213-8493. Postgiro 12873-6\nVerksamhet: Tidningsutgivning\nAntal anställda: 43\nÅrsomsättning: 3 000000\nAktiekapital: 320000\nVerkst din Bengt Karmert\nEtableringsår: 1857.\n\nBENGTERS RORAKTIEBOLAG\n\nPnr 82400\n\nHudiksvall, Nyg 7. Tel 0650-150 35,\n134 31. Bankgiro 191-0280.\nPostgiro 29888-5\n\nVerksamhet: VVS-installationer o\nkonstruktioner\nAntal anställda: 30\nAktiekapital: 43 500\nVerkst dir: Ewert Bengter\nEtableringsår: 1919.\n\nBLUHME AB, YNGVE\n\nPnr 400 14\n\nGöteborg 53, Box 53022. Vasag 42.\nTel 031-1144 60, 1144 21. Bankgiro\n363-4128. Postgiro 48144-0. Tga\nOrtonit\n\nVerksamhet: Säljer kirurgiska\ninstrument, laboratorieartiklar,\nsjukvårdsartiklar, tillverkar\nortopediska artiklar\nVerkst dir: Yngve Bluhme\nEtableringsår: 1938.\n\nBLYBERGS\nSNICKERIFABRIK AB\n\nPnr 790 80\n\nÄlvdalen, Blyberg. Tel 0251-520 34,\n520 65. Bankgiro 47-2007. Postgiro\n124274\n\nVerksamhet: Tillverkar\ninredningar. Specialitet: skolinredningar\nAktiekapital: 41 500\nVerkst dir: Oscar Wallin\nDisp: O Wallin\nEtableringsår: 1951.\n\nBLÅ BAND PRODUKTER AB\n\nse Novia Livsmedelsindustrier AB.\n\nBLÅ PILEN AB\n\nPnr 790 30\n\nInsjön, Box 61. Tel 0247-402 30,\n402 31. Bankgiro 795-9083.\nPostgiro 96595-4. Tga Blå Pilen\nVerksamhet: Tillverkar slipsar,\nvävda o stickade scarves samt\nstickade mössor\nVarunamn: Blå Pilen\nAntal anställda: 18\nÅrsomsättning: 1100 000\n\nAktiekapital: 100 000\nVerkst dir: Ing A Martin Bortås\nEtableringsår: 1936.\n\nBLÅSJOS\nMETALL-TRYCKERI, GUSTAF\n\nPnr 104 60\n\nStockholm 20, Hammarby Fabriksv\n43 B. Tel 08-4343 63. Bankgiro\n744-7378. Postgiro 156051-5\nVerksamhet: Utför metalltryckning\no pressningsarbeten\nEtableringsår: 1921.\n\nSONDELLS FABRIKS AB\n\nPnr 890 51\n\nLångviksmon. Tel 0662-300 04.\nBankgiro 77-1209. Postgiro 64333\nVerksamhet: Tillverkar oljetankar,\nexpansionskärl o värmepannor\nVerkst dir: Erie Sondell\nEtableringsår: 1923.\n\nERIKSSON &amp; CO, VERNER\n\nPnr 330 31\n\nKulltorp. Tel 0370-820 46\nVerksamhet: Tillverkar\nhushållsartiklar m m. Specialitet: vispar o\nborstar\n\nChef: Fabr Verner Eriksson.\n\nERICSSONS EFTR, WERNER\n\nPnr 602 24\n\nNorrköping, Drottningg 36. Tel\n011-1237 25, 124474. Bankgiro\n12-5254. Postgiro 27895\nVerksamhet: Säljer omslagspapper,\npapperspåsar o kartonger\nAntal anställda: 3\nÅrsomsättning: 600 000\nÄgare o chef: Gunnar Ahlström\nEtableringsår: 1900.\n\nERICSON BYGGNADS AB,\nAKE E\n\nPnr 11121\n\nStockholm, Bryggarg 12 A. Tel\n08-1183 70, 1183 80. Bankgiro\n16-4637. Postgiro 454562\nVerksamhet: Hus o\nindustribyggnader\n\nAktiekapital: 50000\n\nÄgare o chef: Dir Ake E Ericson\n\nArbetschef: Byggnadsing Bengt\n\nBernhardsson\n\nEtableringsår: 1957.\n\nFIX KONFEKTION, AB\n\nPnr 50005\n\nBorås 5, Kellgrensg 26. Box 1531.\nTel 033-1149 47. Bankgiro 53-1112.\nPostgiro 272930\n\nVerksamhet: Tillverkar\nsportkonfektion o regnkläder\nAktiekapital: 50 000\nVerkst dir: Kurt Johansson\nEtableringsår: 1951.\n\npatent.information ab\n\nPnr 103 84\n\nStockholm 7, Norrlandsg 16. Box\n7186. Tel 08-6160 30. Bankgiro\n481-7391. Postgiro 253211-7. Tga\nPatinform\n\nVerksamhet: Patentbevakningar o°\nefterforskningar i in- o utlandet\nAntal anställda: 5\nAktiekapital: 5 000\nVerkst dir: Gösta Sundbergh\nEtableringsår: 1953.\n\nBERG AB, VICTOR\n\nPnr 103 81\n\nStockholm 7, Kungsg 4 B. Box\n7025. Tel 08-23 2195. Bankgiro\n160-5526. Postgiro 51969-4. Tga\nVictorberg. Telex 19325\nVerksamhet: Maskinagenturer för\njärnverk o mekaniska industrin\nVarunamn: Bowex, Dieffenbacher,\nHeilbronn, Heine, Julius.\nKrupp-HEB, Schäfer, Täcke, Wieger\nAntal anställda: 16\nÅrsomsättning: 4 000 000\nAktiekapital: 50 000\nVerkst dir: Lars Berg\nEtableringsår: 1873.\n\nBERGA MEKANISKA\nVERKSTADS AB\n\nPnr 252 55\n\nHelsingborg, Rundgången 12. Tel\n042-1167 43. Bankgiro 269-1335.\nPostgiro 138822-2\nVerksamhet: Tillverkar plast-,\npress- o stansverktyg. Specialitet:\nstörre plastverktyg. Utför\nmekaniska arbeten samt legoarbeten\nAktiekapital: 25 000\nEtableringsår: 1962.",
    "structured": {
        "1": {
            "company_name": "BIL & BUSS I FALUN AB",
            "pnr": "79100",
            "address": "Falun, Timmerv 14",
            "phone_number": "023-188 50",
            "activity": "Bilar, reservdelar o bilverkstäder",
            "employees": 118,
            "annual_turnover": 24902000,
            "capital": 200000,
            "key_personnel": [
                {
                    "name": "Gösta Lindqvist",
                    "position": "Verkst dir"
                }
            ],
            "establishment_year": 1958
        },
        "2": {
            "company_name": "ESSE BYGGNADSMATERIAL",
            "pnr": "770 20",
            "address": "Söderbärke",
            "phone_number": "0240-503 71, 510 92",
            "bank_details": {
                "bankgiro": "47-1405",
                "postgiro": "467388-5"
            },
            "activity": "Tillverkar o säljer murartrallar, betongformar etc",
            "employees": 30,
            "annual_turnover": 3000000,
            "key_personnel": [
                {
                    "name": "Rune Eriksson",
                    "position": "Chef"
                }
            ],
            "establishment_year": 1950
        },
        "3": {
            "company_name": "FAM FALKÖPINGS BILCITY AB",
            "pnr": "52101",
            "address": "Falköping 1, Box 95, Allebergsv 10",
            "phone_number": "0515-132 50",
            "postgiro": "348240-3",
            "activity": "Försäljning o reparation av personbilar",
            "employees": 20,
            "annual_turnover": 4400000,
            "capital": 150000,
            "key_personnel": [
                {
                    "name": "O Rehnquist",
                    "position": "Verkst din"
                }
            ],
            "establishment_year": 1967
        },
        "4": {
            "company_name": "FALKÖPINGS LIKKIST. FABRIK, AB",
            "pnr": "52100",
            "address": "Falköping, Bang 18",
            "phone_number": "0515-10170, 147 70",
            "bank_details": {
                "bankgiro": "541-5799",
                "postgiro": "73611-6"
            },
            "activity": "Tillverkar o säljer likkista1 o sarkofager i fur o ek",
            "employees": 26,
            "capital": 50000,
            "key_personnel": [
                {
                    "name": "Olle Grahn",
                    "position": "Verkst din"
                }
            ],
            "establishment_year": 1927
        },
        "5": {
            "company_name": "FALKÖPINGS TIDNING, AB",
            "pnr": "52101",
            "address": "Falköping 1, Box 47, Landbog 4",
            "phone_number": "0515-134 50",
            "bank_details": {
                "bankgiro": "213-8493",
                "postgiro": "12873-6"
            },
            "activity": "Tidningsutgivning",
            "employees": 43,
            "annual_turnover": 3000000,
            "capital": 320000,
            "key_personnel": [
                {
                    "name": "Bengt Karmert",
                    "position": "Verkst din"
                }
            ],
            "establishment_year": 1857
        },
        "6": {
            "company_name": "BENGTERS RORAKTIEBOLAG",
            "pnr": "82400",
            "address": "Hudiksvall, Nyg 7",
            "phone_number": "0650-150 35, 134 31",
            "bank_details": {
                "bankgiro": "191-0280",
                "postgiro": "29888-5"
            },
            "activity": "VVS-installationer o konstruktioner",
            "employees": 30,
            "capital": 43500,
            "key_personnel": [
                {
                    "name": "Ewert Bengter",
                    "position": "Verkst dir"
                }
            ],
            "establishment_year": 1919
        },
        "7": {
            "company_name": "BLUHME AB, YNGVE",
            "pnr": "400 14",
            "address": "Göteborg 53, Box 53022, Vasag 42",
            "phone_number": "031-1144 60, 1144 21",
            "bank_details": {
                "bankgiro": "363-4128",
                "postgiro": "48144-0"
            },
            "activity": "Säljer kirurgiska instrument, laboratorieartiklar, sjukvårdsartiklar, tillverkar ortopediska artiklar",
            "key_personnel": [
                {
                    "name": "Yngve Bluhme",
                    "position": "Verkst dir"
                }
            ],
            "establishment_year": 1938
        },
        "8": {
            "company_name": "BLYBERGS SNICKERIFABRIK AB",
            "pnr": "790 80",
            "address": "Älvdalen, Blyberg",
            "phone_number": "0251-520 34, 520 65",
            "bank_details": {
                "bankgiro": "47-2007",
                "postgiro": "124274"
            },
            "activity": "Tillverkar inredningar. Specialitet: skolinredningar",
            "capital": 41500,
            "key_personnel": [
                {
                    "name": "Oscar Wallin",
                    "position": "Verkst dir"
                },
                {
                    "name": "O Wallin",
                    "position": "Disp"
                }
            ],
            "establishment_year": 1951
        },
        "9": {
            "company_name": "BLÅ PILEN AB",
            "pnr": "790 30",
            "address": "Insjön, Box 61",
            "phone_number": "0247-402 30, 402 31",
            "bank_details": {
                "bankgiro": "795-9083",
                "postgiro": "96595-4"
            },
            "activity": "Tillverkar slipsar, vävda o stickade scarves samt stickade mössor",
            "employees": 18,
            "annual_turnover": 1100000,
            "capital": 100000,
            "key_personnel": [
                {
                    "name": "Ing A Martin Bortås",
                    "position": "Verkst dir"
                }
            ],
            "establishment_year": 1936
        },
        "10": {
            "company_name": "BLÅSJOS METALL-TRYCKERI, GUSTAF",
            "pnr": "104 60",
            "address": "Stockholm 20, Hammarby Fabriksv 43 B",
            "phone_number": "08-4343 63",
            "bank_details": {
                "bankgiro": "744-7378",
                "postgiro": "156051-5"
            },
            "activity": "Utför metalltryckning o pressningsarbeten",
            "establishment_year": 1921
        },
        "11": {
            "company_name": "SONDELLS FABRIKS AB",
            "pnr": "890 51",
            "address": "Långviksmon",
            "phone_number": "0662-300 04",
            "bank_details": {
                "bankgiro": "77-1209",
                "postgiro": "64333"
            },
            "activity": "Tillverkar oljetankar, expansionskärl o värmepannor",
            "key_personnel": [
                {
                    "name": "Erie Sondell",
                    "position": "Verkst dir"
                }
            ],
            "establishment_year": 1923
        },
        "12": {
            "company_name": "ERIKSSON & CO, VERNER",
            "pnr": "330 31",
            "address": "Kulltorp",
            "phone_number": "0370-820 46",
            "activity": "Tillverkar hushållsartiklar m m. Specialitet: vispar o borstar",
            "key_personnel": [
                {
                    "name": "Verner Eriksson",
                    "position": "Chef"
                }
            ]
        },
        "13": {
            "company_name": "ERICSSONS EFTR, WERNER",
            "pnr": "602 24",
            "address": "Norrköping, Drottningg 36",
            "phone_number": "011-1237 25, 124474",
            "bank_details": {
                "bankgiro": "12-5254",
                "postgiro": "27895"
            },
            "activity": "Säljer omslagspapper, papperspåsar o kartonger",
            "employees": 3,
            "annual_turnover": 600000,
            "key_personnel": [
                {
                    "name": "Gunnar Ahlström",
                    "position": "Ägare o chef"
                }
            ],
            "establishment_year": 1900
        },
        "14": {
            "company_name": "ERICSON BYGGNADS AB, AKE E",
            "pnr": "11121",
            "address": "Stockholm, Bryggarg 12 A",
            "phone_number": "08-1183 70, 1183 80",
            "bank_details": {
                "bankgiro": "16-4637",
                "postgiro": "454562"
            },
            "activity": "Hus o industribyggnader",
            "capital": 50000,
            "key_personnel": [
                {
                    "name": "Dir Ake E Ericson",
                    "position": "Ägare o chef"
                },
                {
                    "name": "Byggnadsing Bengt Bernhardsson",
                    "position": "Arbetschef"
                }
            ],
            "establishment_year": 1957
        },
        "15": {
            "company_name": "FIX KONFEKTION, AB",
            "pnr": "50005",
            "address": "Borås 5, Kellgrensg 26, Box 1531",
            "phone_number": "033-1149 47",
            "bank_details": {
                "bankgiro": "53-1112",
                "postgiro": "272930"
            },
            "activity": "Tillverkar sportkonfektion o regnkläder",
            "capital": 50000,
            "key_personnel": [
                {
                    "name": "Kurt Johansson",
                    "position": "Verkst dir"
                }
            ],
            "establishment_year": 1951
        },
        "16": {
            "company_name": "patent.information ab",
            "pnr": "103 84",
            "address": "Stockholm 7, Norrlandsg 16, Box 7186",
            "phone_number": "08-6160 30",
            "bank_details": {
                "bankgiro": "481-7391",
                "postgiro": "253211-7"
            },
            "activity": "Patentbevakningar o° efterforskningar i in- o utlandet",
            "employees": 5,
            "capital": 5000,
            "key_personnel": [
                {
                    "name": "Gösta Sundbergh",
                    "position": "Verkst dir"
                }
            ],
            "establishment_year": 1953
        },
        "17": {
            "company_name": "BERG AB, VICTOR",
            "pnr": "103 81",
            "address": "Stockholm 7, Kungsg 4 B, Box 7025",
            "phone_number": "08-23 2195",
            "bank_details": {
                "bankgiro": "160-5526",
                "postgiro": "51969-4"
            },
            "activity": "Maskinagenturer för järnverk o mekaniska industrin",
            "employees": 16,
            "annual_turnover": 4000000,
            "capital": 50000,
            "key_personnel": [
                {
                    "name": "Lars Berg",
                    "position": "Verkst dir"
                }
            ],
            "establishment_year": 1873
        },
        "18": {
            "company_name": "BERGA MEKANISKA VERKSTADS AB",
            "pnr": "252 55",
            "address": "Helsingborg, Rundgången 12",
            "phone_number": "042-1167 43",
            "bank_details": {
                "bankgiro": "269-1335",
                "postgiro": "138822-2"
            },
            "activity": "Tillverkar plast-, press- o stansverktyg. Specialitet: större plastverktyg. Utför mekaniska arbeten samt legoarbeten",
            "capital": 25000,
            "establishment_year": 1962
        }
    }
}