{
    "original": "MOT\n\nChefred: Erik Friberg\nAnnonsdir: P O Sundelin\nEtableringsår: 1943.\n\nPFIZER AB\n\nPnr 183 03\n\nTäby 3, Nytorpsv 2. Fack. Tel\n08-758 0130. Bankgiro 626-4139. Tga\nPfizersub. Telex 1254\nVerksamhet: Säljer farmaceutiska\nspecialiteter, fodertillsatsmedel o\nkemikalier\nAntal anställda: 56\nÅrsomsättning: 35 000 000\nAktiekapital: 4 000 000\nStyrelse: Styrbjörn Gärde (ordf),\nHolger Ahlsvik, Bryan Carmichael,\nGustav Magnusson, Göran\nSöderqvist, Anders Saxon\nVerkst dir: Holger Ahlsvik\nEtableringsån 1954.\n\nPGM AB, KONSULTERANDE\nINGENJÖRSFIRMAN\n\nPnr 41120\n\nGöteborg C, Rosenlundsg 6-8. Tel\n031-17 73 50\n\nVerksamhet: Konsulterande\nverksamhet i rationalisering\n.Antal anställda: 20\nÅrsomsättning: 1000 000\nAktiekapital: 50 000\nVerkst dir: Övering Frans\nHellström\n\nEtableringsår: 1962.\n\nARONSSONS AB, ARVID\n\nPnr 522 00\n\nTidaholm, Box 53. Kullö. Tel\n0502-100 09, 106 09. Bankgiro 218-2137.\nPostgiro 288 297-5. Tga Aronssons\nVerksamhet: Trävaror o wallboard\nengross. Exporterar massaved\nAntal anställda: 11\nÅrsomsättning: 5 000 000\nAktiekapital: 75 000\nVerkst dir: Disp Rune Aronsson\nEtableringsår: 1937.\n\nAROS RORCENTRAL, AB\n\nPnr 723 35\n\nVästerås, Stjernhöksg 11. Tel\n021-13 3184, 13 33 69. Bankgiro\n808-6076. Postgiro 161493-2\nVerksamhet:\nRörlednings-entreprenör\nAntal anställda: 30\nÅrsomsättning: 3 000 000\nAktiekapital: 25 400\nStyrelseordf: Dir Ulf Pettersson\nVerkst dir: Ulf Pettersson\nPlatschef: Nils Frantzén\nEtableringsår: 1932.\n\n[-AROSBYGDENSLANTMANNA-FÖRBUND-]\n\n{+AROSBYGDENSLANTMANNA-\nFÖRBUND+} FÖRENING U P A\n\nPnr 72103\n\nVästerås 1, Box 17. Björnöv 2. Tel\n021-13 71 80. Bankgiro 356-6122.\nPostgiro 98988-9\n\nVerksamhet: Idkar handel med\nväxtodlingsprodukter från lantbruket\nAntal anställda: 275\nÅrsomsättning: 179 000 000\nVerkst dir: Lennart Larsson\nEtableringsår: 1936.\n\nJÄR\n\ndr Hjalmar Olson, bruksdisp Hans\nRudberg\n\nVerkst dir: Bruksdisp Hans\nRudberg\n\nEkonomidir: Nils Östling\nTekn dir: Curt Holtström\nEtableringsår: 1906.\n\nJÄRNFÖRÄDLINGS\nESKILSTUNAFABRIK AB\n\nPnr 63105\n\nEskilstuna 1, Kungsg 67. Box 337.\nTel 016-13 78 40. Bankgiro 60-1490.\nPostgiro 107 07. Tga Aducerverk\nVerksamhet: Beställningsgjuteri\nför obearbetat o bearbetat aducera\ngods. Tillverkar Ewarts- o\nstål-bultad kätting samt Magnikätting.\nTYyckluftkopplingar,\nbågfilsställ-ningar, skruvtvingar, limtvingar,\nlimknektar, limklämmor, grindlås\nAntal anställda: 160\nAktiekapital: 232 000\nVerkst dir: Hans Rudberg\nEtableringsår: 1889\nDotterbolag till AB Järnförädling,\nHälleforsnäs.\n\nFörsäljning sker från moderbolaget.\n\nJARNFURÄDLINGS VÄSTER.\nVIKSFABRIK AB\n\nPnr 593 01\n\nVästervik 1, Stationsg 6. Box 5.\nTel 04 90-133 40. Telex 3919\nVarunamn: JP, Navilight, Strong\nGrip\n\nAntal anställda: 120\nAktiekapital: 1000000\nVerkst din Bruksdisp Hans\nRudberg (Hälleforsnäs)\nDotterbolag till AB Järnförädling,\nHälleforsnäs.\n\nJÄRNHANDLARE\n\nse resp namn.\n\nJÄRN|A SVENSKA AB\n\nPnr 631 05\n\nEskilstuna 1, Brunskogsg 5. Box\n342. Tel 016-13 78 50. Bankgiro\n57-9755. Postgiro 54798. Telex\n40977. Tga Ironlink\nVerksamhet: Samarbetsföretag för\ninköp, planläggning av sortiment\nsamt planering av försäljningen\nför 125 svenska järnhandlare\nAntal anställda: 50\nÅrsomsättning: 77 800000\nAktiekapital: 800 000\nStyrelse: Dir Rune Sjöberg (ordf),\ndir Per-Gunnar Carlson, dir Bertil\nWollter, disp Bertil Ohlsson, dir\nHolger Sjögren, dir Axel Sundström,\ndir Bertil Wedlund\nVerkst dir: Karl-Erik Olson\nDisp: Erik Zetterberg\nInköpschef: Berndt Blom\nKamrer: Ingvar Larsson\nLagerchef: Gunnar Karlsson\nEtableringsår: 1963.\n\nBREVENS BRUK AB\n\nPnr 690 74\n\nKilsmo. Tel 019-540 70. Bankgiro\n815-4205. Postgiro 23363-5\nVerksamhet: Sågverk,\nskogsförvaltning, lantbruk samt gjuteri\nAntal anställda: 200\nÅrsomsättning: 10 000 000\nVerkst dir: Jägmäst Johan\nGripenstedt.\n\nBRICKEGÄRDENS\nINDUSTRI AB\n\nPnr 691 00\n\nKarlskoga, Källmossv 13. Tel\n0586-28 2 86. Bankgiro 371-1397\nVerksamhet: Tillverkar hjul för\nbeläggning av massivt gummi\nAntal anställda: 5\nAktiekapital: 36 000\nVerkst dir: A Persson\nEtableringsår: 1947.\n\nBRINGHOLTZ MÖBELFABRIK,\nAB BRDDERNA\n\nPnr 570 76\n\nRuda, Box 50. Industrig 1. Tel\n0491-220 21, 220 22. Bankgiro\n859-0036. Postgiro 449686-5\nVerksamhet: Tillverkar stolar o\nkarmstolar för kontor- o offentlig\nmiljö. Endast legotillverkning\nAntal anställda: 23\nÅrsomsättning: 1800 000\nAktiekapital: 200000\nVerkst dir. Linder Bringholtz\nDriftschef: Evert Bringholtz\nKamrer: Sven Olof Kullberg\nEtableringsår: 1926.\n\nVerksamhet: Skyltar,\nskyltbokstä-ver, magnettavlor etc\nÄgare o chef: Knut Melander\nEtableringsår: 1937.\n\nBI GM AN AB\n\nPnr 103 63\n\nStockholm 3, Box 3176. Sveav 21.\nTel 08-23 43 00. Bankgiro 405-9812.\nPostgiro 352172-1.\nTelex 1428 BIGMAN S\nVerksamhet: Agenturer med\nkemikalier, metallpulver, elektrokorund etc\nVerkst dir: K Bigg Hoffman\nEtableringsår: 1971.\n\nUMEÅ BILKOMPANI, AB\n\nPnr 901 04\n\nUmeå 1. Verk stad sg 9-11. Box 260.\nTel 090-13 22 00. Bankgiro\n759-8832. Postgiro 62420-5\nVerksamhet: Bilverkstad. Bilar o\nbiltillbehör. Auktoriserad\nåterförsäljare för AB Volvo\nAntal anställda: 130\nÅrsomsättning: 35 000 000\nAktiekapital: 150 000\nVerkst dir: E Rune Gabrielsson\nEtableringsår: 1928.\n\nLUNDBERG AB, K E\n\nPnr 16103\n\nBromma 3, Björnsonsg 299. Fack.\nTel 08-87 5050. Telex 17785\nVeiksamhet: Textilagenturer,\nsytråd märke DMC Hästen, kortvaror\nmärke Prym\n\nVeikst dir: J O Lundberg\nEtableringsår: 1945.\n\nHESTRA INDUSTRI AB\n\nPnr 330 27\n\nHestra. Tel 0370-352 50. Bankgiro\n54-24 24. Postgiro 22768. Tga Heab\nVerksamhet: Tillverkar herr- o\ngosskjortor. Herr o gosspyjamas\nVarunamn: Heab\nAntal anställda: 80\nÅrsomsättning: 3 500 000\nAktiekapital: 270 000\nVerkst dir: Malte Eberstål\nEtableringsår: 1919\nOmbildat till aktiebolag 1925.\n\nHESTRA REKLAM AB\n\nPnr 330 27\n\nHestra. Tel 0370-35041, 35051\nVerksamhet: syfabrik o\nscreen-tryckeri. Tillverkar reklam artiklar,\nreklambags, reklammärken,\nreklamtändstickor. Specialitet:\nreklammössor o hattar\nAntal anställda: 45\nÅrsomsättning: 2700 000\nAktiekapital: 45 000\nÄgare o chefer: Fabr Arne\nWestlund, fabr Franz Liebscher\nEtableringsår: 1951.",
    "structured": {
        "1": {
            "company_name": "PFIZER AB",
            "pnr": "183 03",
            "address": "Täby 3, Nytorpsv 2",
            "phone_number": "08-758 0130",
            "bank_details": {
                "bankgiro": "626-4139"
            },
            "activity": "Säljer farmaceutiska specialiteter, fodertillsatsmedel o kemikalier",
            "employees": 56,
            "annual_turnover": 35000000,
            "capital": 4000000,
            "key_personnel": [
                {
                    "name": "Styrbjörn Gärde",
                    "position": "ordf"
                },
                {
                    "name": "Holger Ahlsvik",
                    "position": ""
                },
                {
                    "name": "Bryan Carmichael",
                    "position": ""
                },
                {
                    "name": "Gustav Magnusson",
                    "position": ""
                },
                {
                    "name": "Göran Söderqvist",
                    "position": ""
                },
                {
                    "name": "Anders Saxon",
                    "position": ""
                }
            ],
            "establishment_year": 1954
        },
        "2": {
            "company_name": "PGM AB, KONSULTERANDE INGENJÖRSFIRMAN",
            "pnr": "41120",
            "address": "Göteborg C, Rosenlundsg 6-8",
            "phone_number": "031-17 73 50",
            "activity": "Konsulterande verksamhet i rationalisering",
            "employees": 20,
            "annual_turnover": 1000000,
            "capital": 50000,
            "key_personnel": [
                {
                    "name": "Övering Frans Hellström",
                    "position": ""
                }
            ],
            "establishment_year": 1962
        },
        "3": {
            "company_name": "ARONSSONS AB, ARVID",
            "pnr": "522 00",
            "address": "Tidaholm, Box 53, Kullö",
            "phone_number": "0502-100 09, 106 09",
            "bank_details": {
                "bankgiro": "218-2137",
                "postgiro": "288 297-5"
            },
            "activity": "Trävaror o wallboard engross. Exporterar massaved",
            "employees": 11,
            "annual_turnover": 5000000,
            "capital": 75000,
            "key_personnel": [
                {
                    "name": "Disp Rune Aronsson",
                    "position": ""
                }
            ],
            "establishment_year": 1937
        },
        "4": {
            "company_name": "AROS RORCENTRAL, AB",
            "pnr": "723 35",
            "address": "Västerås, Stjernhöksg 11",
            "phone_number": "021-13 3184, 13 33 69",
            "bank_details": {
                "bankgiro": "808-6076",
                "postgiro": "161493-2"
            },
            "activity": "Rörlednings-entreprenör",
            "employees": 30,
            "annual_turnover": 3000000,
            "capital": 25400,
            "key_personnel": [
                {
                    "name": "Dir Ulf Pettersson",
                    "position": "Styrelseordf"
                },
                {
                    "name": "Ulf Pettersson",
                    "position": "Verkst dir, Platschef"
                },
                {
                    "name": "Nils Frantzén",
                    "position": "Platschef"
                }
            ],
            "establishment_year": 1932
        },
        "5": {
            "company_name": "AROSBYGDENSLANTMANNA-FÖRBUND-",
            "pnr": "72103",
            "address": "Västerås 1, Box 17, Björnöv 2",
            "phone_number": "021-13 71 80",
            "bank_details": {
                "bankgiro": "356-6122",
                "postgiro": "98988-9"
            },
            "activity": "Idkar handel med växtodlingsprodukter från lantbruket",
            "employees": 275,
            "annual_turnover": 179000000,
            "key_personnel": [
                {
                    "name": "Lennart Larsson",
                    "position": "Verkst dir"
                }
            ],
            "establishment_year": 1936
        },
        "6": {
            "company_name": "JÄRNFÖRÄDLINGS ESKILSTUNAFABRIK AB",
            "pnr": "63105",
            "address": "Eskilstuna 1, Kungsg 67, Box 337",
            "phone_number": "016-13 78 40",
            "bank_details": {
                "bankgiro": "60-1490",
                "postgiro": "107 07"
            },
            "activity": "Beställningsgjuteri för obearbetat o bearbetat aducera gods. Tillverkar Ewarts- o stål-bultad kätting samt Magnikätting. TYyckluftkopplingar, bågfilsställningar, skruvtvingar, limtvingar, limknektar, limklämmor, grindlås",
            "employees": 160,
            "capital": 232000,
            "key_personnel": [
                {
                    "name": "Hans Rudberg",
                    "position": "Verkst dir"
                }
            ],
            "establishment_year": 1889
        },
        "7": {
            "company_name": "JARNFURÄDLINGS VÄSTER. VIKSFABRIK AB",
            "pnr": "593 01",
            "address": "Västervik 1, Stationsg 6, Box 5",
            "phone_number": "04 90-133 40",
            "activity": "Tillverkar herr- o gosskjortor. Herr o gosspyjamas",
            "employees": 120,
            "capital": 1000000,
            "key_personnel": [
                {
                    "name": "Bruksdisp Hans Rudberg (Hälleforsnäs)",
                    "position": "Verkst dir"
                }
            ]
        },
        "8": {
            "company_name": "JÄRN|A SVENSKA AB",
            "pnr": "631 05",
            "address": "Eskilstuna 1, Brunskogsg 5, Box 342",
            "phone_number": "016-13 78 50",
            "bank_details": {
                "bankgiro": "57-9755",
                "postgiro": "54798"
            },
            "activity": "Samarbetsföretag för inköp, planläggning av sortiment samt planering av försäljningen för 125 svenska järnhandlare",
            "employees": 50,
            "annual_turnover": 77800000,
            "capital": 800000,
            "key_personnel": [
                {
                    "name": "Dir Rune Sjöberg",
                    "position": "Styrelseordf"
                },
                {
                    "name": "dir Per-Gunnar Carlson",
                    "position": ""
                },
                {
                    "name": "dir Bertil Wollter",
                    "position": ""
                },
                {
                    "name": "disp Bertil Ohlsson",
                    "position": ""
                },
                {
                    "name": "dir Holger Sjögren",
                    "position": ""
                },
                {
                    "name": "dir Axel Sundström",
                    "position": ""
                },
                {
                    "name": "dir Bertil Wedlund",
                    "position": ""
                },
                {
                    "name": "Karl-Erik Olson",
                    "position": "Verkst dir"
                },
                {
                    "name": "Erik Zetterberg",
                    "position": "Disp"
                },
                {
                    "name": "Berndt Blom",
                    "position": "Inköpschef"
                },
                {
                    "name": "Ingvar Larsson",
                    "position": "Kamrer"
                },
                {
                    "name": "Gunnar Karlsson",
                    "position": "Lagerchef"
                }
            ],
            "establishment_year": 1963
        },
        "9": {
            "company_name": "BREVENS BRUK AB",
            "pnr": "690 74",
            "address": "Kilsmo",
            "phone_number": "019-540 70",
            "bank_details": {
                "bankgiro": "815-4205",
                "postgiro": "23363-5"
            },
            "activity": "Sågverk, skogsförvaltning, lantbruk samt gjuteri",
            "employees": 200,
            "annual_turnover": 10000000,
            "key_personnel": [
                {
                    "name": "Jägmäst Johan Gripenstedt",
                    "position": "Verkst dir"
                }
            ]
        },
        "10": {
            "company_name": "BRICKEGÄRDENS INDUSTRI AB",
            "pnr": "691 00",
            "address": "Karlskoga, Källmossv 13",
            "phone_number": "0586-28 2 86",
            "bank_details": {
                "bankgiro": "371-1397"
            },
            "activity": "Tillverkar hjul för beläggning av massivt gummi",
            "employees": 5,
            "capital": 36000,
            "key_personnel": [
                {
                    "name": "A Persson",
                    "position": "Verkst dir"
                }
            ],
            "establishment_year": 1947
        },
        "11": {
            "company_name": "BRINGHOLTZ MÖBELFABRIK, AB BRDDERNA",
            "pnr": "570 76",
            "address": "Ruda, Box 50, Industrig 1",
            "phone_number": "0491-220 21, 220 22",
            "bank_details": {
                "bankgiro": "859-0036",
                "postgiro": "449686-5"
            },
            "activity": "Tillverkar stolar o karmstolar för kontor- o offentlig miljö. Endast legotillverkning",
            "employees": 23,
            "annual_turnover": 1800000,
            "capital": 200000,
            "key_personnel": [
                {
                    "name": "Linder Bringholtz",
                    "position": "Verkst dir"
                },
                {
                    "name": "Evert Bringholtz",
                    "position": "Driftschef"
                },
                {
                    "name": "Sven Olof Kullberg",
                    "position": "Kamrer"
                }
            ],
            "establishment_year": 1926
        },
        "12": {
            "company_name": "BI GM AN AB",
            "pnr": "103 63",
            "address": "Stockholm 3, Box 3176, Sveav 21",
            "phone_number": "08-23 43 00",
            "bank_details": {
                "bankgiro": "405-9812",
                "postgiro": "352172-1"
            },
            "activity": "Agenturer med kemikalier, metallpulver, elektrokorund etc",
            "key_personnel": [
                {
                    "name": "K Bigg Hoffman",
                    "position": "Verkst dir"
                }
            ],
            "establishment_year": 1971
        },
        "13": {
            "company_name": "UMEÅ BILKOMPANI, AB",
            "pnr": "901 04",
            "address": "Umeå 1, Verkstadsg 9-11, Box 260",
            "phone_number": "090-13 22 00",
            "bank_details": {
                "bankgiro": "759-8832",
                "postgiro": "62420-5"
            },
            "activity": "Bilverkstad. Bilar o biltillbehör. Auktoriserad återförsäljare för AB Volvo",
            "employees": 130,
            "annual_turnover": 35000000,
            "capital": 150000,
            "key_personnel": [
                {
                    "name": "E Rune Gabrielsson",
                    "position": "Verkst dir"
                }
            ],
            "establishment_year": 1928
        },
        "14": {
            "company_name": "LUNDBERG AB, K E",
            "pnr": "16103",
            "address": "Bromma 3, Björnsonsg 299",
            "phone_number": "08-87 5050",
            "bank_details": {
                "bankgiro": "na"
            },
            "activity": "Textilagenturer, sytråd märke DMC Hästen, kortvaror märke Prym",
            "key_personnel": [
                {
                    "name": "J O Lundberg",
                    "position": "Veikst dir"
                }
            ],
            "establishment_year": 1945
        },
        "15": {
            "company_name": "HESTRA INDUSTRI AB",
            "pnr": "330 27",
            "address": "Hestra",
            "phone_number": "0370-352 50",
            "bank_details": {
                "bankgiro": "54-24 24",
                "postgiro": "22768"
            },
            "activity": "Tillverkar herr- o gosskjortor. Herr o gosspyjamas",
            "employees": 80,
            "annual_turnover": 3500000,
            "capital": 270000,
            "key_personnel": [
                {
                    "name": "Malte Eberstål",
                    "position": "Verkst dir"
                }
            ],
            "establishment_year": 1919
        },
        "16": {
            "company_name": "HESTRA REKLAM AB",
            "pnr": "330 27",
            "address": "Hestra",
            "phone_number": "0370-35041, 35051",
            "activity": "Syfabrik o screen-tryckeri. Tillverkar reklam artiklar, reklambags, reklammärken, reklamtändstickor. Specialitet: reklammössor o hattar",
            "employees": 45,
            "annual_turnover": 2700000,
            "capital": 45000,
            "key_personnel": [
                {
                    "name": "Fabr Arne Westlund",
                    "position": "Ägare o chefer"
                },
                {
                    "name": "fabr Franz Liebscher",
                    "position": "Ägare o chefer"
                }
            ],
            "establishment_year": 1951
        }
    }
}