{
    "original": "ELCATOR, SVENSKA AB\n\nPnr 11426\n\nStockholm, Danderydsg 32. Tel\n08-112612, teltid 14-17 08-71519 56.\nBankgiro 700-2850. Postgiro\n194425-5. Tga Elcatorab\nVerksamhet: Representant för Sté\nQuartz &amp; Silice, Paris. Säljer\nprodukter av ren, smält kvarts\nAktiekapital: 45 000\nVerkst din Greger Borgman\nEtableringsår 1930.\n\nBERICO, AB\n\nPnr 212 28\n\nMalmö, Scheeleg 13. Tel\n040-93 63 70. Bankgiro 874-8006.\nPostgiro 435141-7\n\nVerksamhet: Leksaker o\nhobbyartiklar engros\nAntal anställda: 20\nÅrsomsättning: 3 500 000\nAktiekapital: 30 000\nVerkst dir: Ivan Andersson\nEtableringsår: 1953.\n\nHISSELEKTRA I MALMÖ AB\n\nPnr 211 25\n\nMalmö, Bagersg 2. Tel 040-768 30.\nBankgiro 26-4285. Postgiro 147658\nVerksamhet: Försäljning,\nmontering, reparation o service av\nhissar, traverser, telfrar o\nelinstalla-tioner\n\nAntal anställda: 20\nÅrsomsättning: 1500000\nAktiekapital: 30 000\nStyrelse: Fabr Walter Ericsson\n(ordf), kamrer Kaj Mårtensson, herr\nGöran Ericsson\n\nVerkst dir: Fabr Walter Ericsson\nEtableringsår: 1949\nOmbildat till aktiebolag 1960.\n\nHJELM IMPORT &amp; EXPORT\nAB, HOLGER\n\nPnr 102 42\n\nStockholm 5, Sibylleg 39. Box 5081.\nTel 08-67 99 45. Bankgiro 23-6731.\nTelex 10843. Tga Mipasto\nVerksamhet: Importerar o säljer\nbyggmateriel\nAntal anställda: 20\nÅrsomsättning: 8 000 000\nAktiekapital: 250000\nVerkst dir: Holger Hjelm\nEtableringsår: 1966.\n\nSMÄLANDSHYTTAN, AB\n\nPnr 360 64\n\nBroakulla. Tel 0471-40114. Tga\nSmålandshyttan\n\nVerksamhet: Tillverkar servis- o\nprydnadsglas\nAktiekapital: 196 000\nFirmatecknare: Arne Ernlothsson\nEtableringsår: 1947.\n\nSMÅLANDSPOSTENS BOK.\nTRYCKERI AB\n\nPnr 35103\n\nVäxjö 1, Storg 1. Box 57. Tel\n0470-260 00. Bankgiro 668-1258.\nPostgiro 20856-1. Tga Smålandsposten.\nTelex 4641\n\nVerksamhet: Tidnings- o\nboktryckeri. Utger Smålandsposten\nAntal anstäUda: 148\nÅrsomsättning: 8 230 000\nAktiekapital: 232 000\nVerkst dir: Torvald Göthe\nEtableringsår: 1866.\n\nHOLMBERG, AB PONTUS\n\nPnr 63102\n\nEskilstuna 1, Rademacherg 34.\nBox 3. Tel 016-13 89 92, 13 00 92.\nBankgiro 828-0372. Postgiro\n10786-2. Tga Holmbergs\nVerksamhet: Tillverkar knivar för\njakt, sport o fiske, hushåll m m\nEtableringsår: 1876\nDotterbolag tül AB C V\nHelje-strand, Eskilstuna.\n\nHOLMBOM &amp; HEDLUND, AB\n\nPnr 93100\n\nSkellefteå, Mullbergsv 13. Tel\n0910-107 76. Bankgiro 764-0931.\nPostgiro 349385-5\nVerksamhet: Tillverkning av hytter\no arbetsredskap för last- o\nschaktmaskiner\n\nAntal anställda: 40\nÅrsomsättning: 3 000 000\nAktiekapital: 100 000\nÄgare o chefer: H Holmbom,\nGunnar Hedlund\nEtableringsår: 1958.\n\nJUNGHEINRICH SVENSKA AB\n\nPnr 19147\n\nSollentuna, Industriv 6. Tel\n08-96 01 90. Bankgiro 23-5267.\nPostgiro 1105. Telex 10220 AMEISE S\nVerksamhet: Lyftvagnar, truckar,\npallhyllor, industrisopmaskiner,\nsmådelslådor o boxar\nVarunamn: Ameise, Hubertus,\nPropermat\nAntal anställda: 40\nÅrsomsättning: 10 000 000\nAktiekapital: 300 000\nDirektion: W Handel, E Protzmann\nEtableringsår: 1958.\n\nALBINO\n\nPnr 370 34\n\nHolmsjö, Nävragöl. Tel\n0455-92100. Bankgiro 861-4091.\nPostgiro 161879-2\n\nVerksamhet: Tillverkar o säljer\nvägredskap o swimmingpooler\nAntal anställda: 10\nÅrsomsättning: 1000 000\nChef: Gunnar Albinson\nEtableringsår: 1951.\n\nALBINSSONS MEK VERKSTADS\nAB, BRÖDERNA\n\nPnr 731 01\n\nKöping 1, Fabriksg. Box 9. Tel\n0221-139 75. Bankgiro 811-2617.\nPostgiro 418715-9\nVerksamhet: Mek verkstadsindustri.\nLegotillverkningar av alla slag\nAntal anställda: 75\nÅrsomsättning: 7 000 000\nAktiekapital: 20 000\nVerkst dir: Erik Albinsson\nV verkst dir: Ruben Albinsson\nEtableringsår: 1944.\nHelägt dotterföretag till\nSandvikens Jernverks AB, Sandviken.\n\n[-ALBREKTSONSPRESENNINGSFABRIKER-]\n\n{+ALBREKTSONSPRESEN-\nNINGSFABRIKER+} &amp; CO KB\n\nPnr 402 71\n\nGöteborg 8, Box 8848. Manufakturg\n17. Tel 031-23 28 87. Bankgiro\n847-9149. Postgiro 241474-6\nVerksamhet: Tillverkar\npresenningar\n\nVerkst dir: Lennart Albrektson\nEtableringsår: 1946.\n\nALBREKTSON, AB\nTHORSTEN F\n\nPnr 402 71\n\nGöteborg 8, Box 8848. Manufakturg\n17. Tel 031-23 5050. Bankgiro\n848-1038. Postgiro 41141-3. Tga Thefa\nVerksamhet: Uthyr presenningar\nVerkst dir: Lennart Albrektson.\n\nALBRECHTSON-HASSE AB\n\nPnr 400 40-\n\nGoteborg 4, Lotsg 8-12. Box 4016.\nTel 031-1242 20. Bankgiro\n512-8558. Postgiro 12037-8.\nTga Sailpartner.\nTelex 2425 JONSRED S\nVerksamhet: Fartygsutrustningar i\nparti o detalj med verkstäder för\nsömnad o riggningar,\nsegelsömme-rier, verkstäder för smiden o block;\nlager av vävnader, stållinor,\ntågvirke m m för sjöfarten o industrin;\nyachtavdelningar\n\nAvdelningskontor: 11131 Stockholm,\nOsterlångg 19. Tel 08-2143 00\n21124 Malmö, Blidög 28. Tel\n040-93 4 3 60\n\nAntal anställda: 180\nAktiekapital: 400 000\nVerkst dir: Ake Jehrn\nEtableringsår: 1849\nTillhör Jonseredskoncernen.\n\nALBY CISTERNSVETS, AB\n\nPnr 840 22\n\nAlby, Box 54. Tel 0690-40179,\n\n402 79. Bankgiro 77-6376.\nPostgiro 574313-3\n\nVerksamhet: Tillverkar olje- o\n\ntransportabla cisterner,\nfarmaggregat, bergflag o mindre\nskidliftar\n\nAntal anställda: 18\nÅrsomsättning: 1500000\nAktiekapital: 10 000\nVerkst dir: Sven Bertil Decker\nVerkmäst: Karl Erik Decker\nEtableringsår: 1955.\n\nFRANCATOR, AB\n\nPnr 11352\n\nStockholm, Döbelnsg 39. Tel\n08-3256 66. Bankgiro 29-5851. Postgiro\n54869\n\nVerksamhet: Konstruerar o\ntillverkar förpackningsmaskiner\nAktiekapital: 435 000\nÄgare o chef: Ing Hadar Öberg\nEtableringsår: 1930.\n\nBLEKINGE SPINNERI AB\n\nPnr 290 70\n\nSvängsta, Box 20. Tel 0454-225 60.\nBankgiro 86-2241. Postgiro 383444.\nTga Blekingegarn\n\nVerksamhet: Spinneri av ull- o\nhårgarn\n\nAntal anställda: 15\nÅrsomsättning: 3 000 000\nAktiekapital: 25 000\nVerkst dir: Lars-Ake Norlander\nEtableringsår: 1965.\n\nVIDAL &amp; CO AB, OTTO\n\nPnr 41118\n\nGöteborg, Skeppsbroplatsen 1. Tel\n031-13 14 32, 13 17 82. Bankgiro\n420-4764. Postgiro 40415-2. Tga\nVidal\n\nVerksamhet: Agentur inom\nlivsmedel\n\nAntal anställda: 10\nÅrsomsättning: 5 000 000\nAktiekapital: 50 000\nVerkst dir Torsten Vidal\nEtableringsår: 1897.",
    "structured": {
        "1": {
            "company_name": "ELCATOR, SVENSKA AB",
            "pnr": "11426",
            "address": "Stockholm, Danderydsg 32",
            "phone_number": "08-112612, teltid 14-17 08-71519 56",
            "bank_details": {
                "bankgiro": "700-2850",
                "postgiro": "194425-5"
            },
            "activity": "Representant för Sté Quartz & Silice, Paris. Säljer produkter av ren, smält kvarts",
            "capital": 45000,
            "key_personnel": [
                {
                    "name": "Greger Borgman",
                    "position": "Verkst din"
                }
            ],
            "establishment_year": 1930
        },
        "2": {
            "company_name": "BERICO, AB",
            "pnr": "212 28",
            "address": "Malmö, Scheeleg 13",
            "phone_number": "040-93 63 70",
            "bank_details": {
                "bankgiro": "874-8006",
                "postgiro": "435141-7"
            },
            "activity": "Leksaker o hobbyartiklar engros",
            "employees": 20,
            "annual_turnover": 3500000,
            "capital": 30000,
            "key_personnel": [
                {
                    "name": "Ivan Andersson",
                    "position": "Verkst dir"
                }
            ],
            "establishment_year": 1953
        },
        "3": {
            "company_name": "HISSELEKTRA I MALMÖ AB",
            "pnr": "211 25",
            "address": "Malmö, Bagersg 2",
            "phone_number": "040-768 30",
            "bank_details": {
                "bankgiro": "26-4285",
                "postgiro": "147658"
            },
            "activity": "Försäljning, montering, reparation o service av hissar, traverser, telfrar o elinstallationer",
            "employees": 20,
            "annual_turnover": 1500000,
            "capital": 30000,
            "key_personnel": [
                {
                    "name": "Fabr Walter Ericsson",
                    "position": "Styrelse: Ordf"
                },
                {
                    "name": "Kaj Mårtensson",
                    "position": "Styrelse: Kamrer"
                },
                {
                    "name": "Göran Ericsson",
                    "position": "Styrelse: Herr"
                },
                {
                    "name": "Fabr Walter Ericsson",
                    "position": "Verkst dir"
                }
            ],
            "establishment_year": 1949
        },
        "4": {
            "company_name": "HJELM IMPORT & EXPORT AB, HOLGER",
            "pnr": "102 42",
            "address": "Stockholm 5, Sibylleg 39, Box 5081",
            "phone_number": "08-67 99 45",
            "bank_details": {
                "bankgiro": "23-6731"
            },
            "activity": "Importerar o säljer byggmateriel",
            "employees": 20,
            "annual_turnover": 8000000,
            "capital": 250000,
            "key_personnel": [
                {
                    "name": "Holger Hjelm",
                    "position": "Verkst dir"
                }
            ],
            "establishment_year": 1966
        },
        "5": {
            "company_name": "SMÄLANDSHYTTAN, AB",
            "pnr": "360 64",
            "address": "Broakulla",
            "phone_number": "0471-40114",
            "activity": "Tillverkar servis- o prydnadsglas",
            "capital": 196000,
            "key_personnel": [
                {
                    "name": "Arne Ernlothsson",
                    "position": "Firmatecknare"
                }
            ],
            "establishment_year": 1947
        }
    }
}