{
    "original": "JUHLINS AB, OTTO\n\nPnr 111 29\n\nStockholm, Järntorgsg 6. Tel\n08-10 15 42, 1044 35. Bankgiro\n721-7425. Postgiro 352544-1. Tga\nHudjuhlin\n\nVerksamhet: Handel med hudar o\nskinn, pälsvaror o pappersavfall\nAntal anställda: 3\nAktiekapital: 283 000\nVerkst dir: Jur kand Carl Emil\nElsell\n\nEtableringsår: 1890.\n\nALVENIUS BILAKTIEBOLAG\n\nPnr 632 21\n\nEskilstuna, Kungsg 42. Tel\n016-110160. Postgiro 91114. Tga\nAlvenius\n\nVerksamhet: Säljer bilar,\nreservdelar o biltillbehör\nAktiekapital: 2000000\nVerkst dir: Erik Alvenius\nEtableringsår: 1954\n\nJANSSONS GLASMÄSTERI AB\n\nPnr 41123\n\nGöteborg. Sprängkullsg 19 B. Tel\n031-13 2066. Bankgiro 10-7705.\nPostgiro 420934\n\nVerksamhet: Glasmästeri,\nglassli-peri. Utför sandblästring\nAntal anställda: 20\nÅrsomsättning: 1500000\nAktiekapital: 10000\nVerkst dir: Leif Ryd\nEtableringsår: 1894.\n\nEKOPLAST EMBALLAGE AB\n\nPnr 43015\n\nGrimeton. Tel 0340-742 30, 742 20.\nBankgiro 35-5000. Postgiro 10902\nVerksamhet: Förpackningsfilm.\nSpecialitet: krympfilm\nAntal anställda: 7\nAktiekapital: 100 000\nVerkst din Krister Lundgren\nEtableringsår: 1965.\n\nBOSTROM, AB HARRY N\n\nPnr 78100\n\nBorlänge, Byggmästarg. Tel\n0243-178 60. Telex 7607. Tga Boström\nVerksamhet: Tillverkar\npresentartiklar o bohag i trä o metall\nVarunamn: Bo/ström\nAntal anställda: 55 (+ hemarbetare)\nÅrsomsättning: 6 000 000\nÄgare o chef: Fabr Harry Boström\nEtableringsår: 1950.\n\nBOSTROM,\nINDUSTRI-AKTIEBOLAGET Å\n\nPnr 45101\n\nUddevalla 1, Box 222. Tel\n0522-601 20, 60185. Bankgiro 42-8008.\nPostgiro 115865\n\nVerksamhet:\nEl-apparatutrustningar för industri o fartyg.\nSvetstill-behör\n\nAntal anställda: 17\nÅrsomsättning: 1 000 000\nAktiekapital: 10 000\nÄgare o chef: Ing A Boström\nEtableringsår: 1952.\n\nBARLEX, AB\n\nPnr 41108\n\nGöteborg, Kungsg 62. Tel\n031-17 55 55. Bankgiro 51-0672. Postgiro\n40340. Tga Barlex\nVerksamhet: Säljer glasögon,\n-bågar, barometrar, kikare etc\nAntal anställda: 8\nAktiekapital: 50 000\nVerkst dir: Konsul Allan Hüttner\nEtableringsår: 1945.\n\nekman, a h\n\nPnr 580 02\n\nLinköping 2, Box 2041. Ostgötag\n22. Tel 013-126668, 1307 32.\nPostgiro 475103-8\n\nVerksamhet: Säljer\nsågverksmaskiner, gaffeltruckar, huggmaskiner,\nbarkningsmaskiner, timmer- o\nklyvbandsågar, barkningskryssare,\nel- o dieselmotorer samt olika\nslag av maskiner m m\nChef: Harry Ekman\nEtableringsår: 1954.\n\nekman plåtslageri ab,\nelon\n\nPnr 434 00\n\nKungsbacka, S Torgg 18. Tel\n0300-101 50. Bankgiro 659-5979.\nPostgiro 15257-9\n\nVerksamhet: Byggnadsplåtslageri\nAntal anställda: 8\nÅrsomsättning: 700 000\nAktiekapital: 12 000\nVerkst dir: Nils-Olof Ekman\nEtableringsår: 1886.\n\nTERVENTO AB\n\nPnr 931 00\n\nSkellefteå, Kanalg 51. Tel\n0910-17180. Tga Tervento\nVerksamhet: Tillverkar\nvarmlufts-pannor-apparater, torkugnar,\nbygg-torkar, fläktar\nVarunamn: Terventor\nAntal anställda: 30\nÅrsomsättning: 2 500000\nVerkst dir: Ernst Johansson\nEtableringsår: 1952.\n\nBROBY MODELLSNICKERI AB\n\nPnr 280 60\n\nBroby, Box 79. Verkstadsg 3. Tel\n044-40466. Bankgiro 982-0523\nVerksamhet: Tillverkar\ngjutmodel-ler i trä, plast o frigolit\n.Antal anställda: 13\nÅrsomsättning: 400 000\nAktiekapital: 7 000\nVerkst dir: Harry Mars\nEtableringsår: 1957.\n\nBYGGPRIMER AB\n\nPnr 430 60\n\nLandvetter, Box 57. Tel\n031-7111 80, 711027. Bankgiro\n37-2412. Postgiro 479880\nVerksamhet: Tillverkar o säljer\nasfaltprodukter, träskyddsmedel o\nkem byggnadsprodukter\n\nAntal anställda: 10\nÅrsomsättning: 800 000\nAktiekapital: 5 000\nChef: Fabr Erie Pettersson\nEtableringsår 1966.\n\nBYGGPRODUKTER STIG JO.\nHANSSON &amp; CO AB\n\nPnr 213 62\n\nMalmö. Jägersrov 80. Tel\n040-94 54 20. Bankgiro 64-1603.\nPostgiro 245177\n\nVerksamhet: Tillverkning o\nförsäljning av monteringsfärdiga villor,\nskolpaviljonger, barndaghem,\nbutiker od\n\nVarunamn: Byggbovillan\nAntal anställda: 20\nÅrsomsättning: 3 500 000\nAktiekapital: 100 000\nVerkst dir: Rolf Johansson\nFörsäljn-chef: Hans Johansson\nEtableringsår: 1965.",
    "structured": {
        "1": {
            "company_name": "JUHLINS AB",
            "pnr": "111 29",
            "address": "Stockholm, Järntorgsg 6",
            "phone_number": "08-10 15 42",
            "bank_details": {
                "bankgiro": "721-7425",
                "postgiro": "352544-1"
            },
            "activity": "Handel med hudar o skinn, pälsvaror o pappersavfall",
            "employees": 3,
            "capital": 283000,
            "key_personnel": [
                {
                    "name": "Jur kand Carl Emil Elsell",
                    "position": "Verkst dir"
                }
            ],
            "establishment_year": 1890
        },
        "2": {
            "company_name": "ALVENIUS BILAKTIEBOLAG",
            "pnr": "632 21",
            "address": "Eskilstuna, Kungsg 42",
            "phone_number": "016-110160",
            "postgiro": "91114",
            "activity": "Säljer bilar, reservdelar o biltillbehör",
            "capital": 2000000,
            "key_personnel": {
                "name": "Erik Alvenius",
                "position": "Verkst dir"
            },
            "establishment_year": 1954
        },
        "3": {
            "company_name": "JANSSONS GLASMÄSTERI AB",
            "pnr": "41123",
            "address": "Göteborg, Sprängkullsg 19 B",
            "phone_number": "031-13 2066",
            "bank_details": {
                "bankgiro": "10-7705",
                "postgiro": "420934"
            },
            "activity": "Glasmästeri, glassli-peri. Utför sandblästring",
            "employees": 20,
            "annual_turnover": 1500000,
            "capital": 10000,
            "key_personnel": {
                "name": "Leif Ryd",
                "position": "Verkst dir"
            },
            "establishment_year": 1894
        },
        "4": {
            "company_name": "EKOPLAST EMBALLAGE AB",
            "pnr": "43015",
            "address": "Grimeton",
            "phone_number": "0340-742 30",
            "bank_details": {
                "bankgiro": "35-5000",
                "postgiro": "10902"
            },
            "activity": "Förpackningsfilm. Specialitet: krympfilm",
            "employees": 7,
            "capital": 100000,
            "key_personnel": {
                "name": "Krister Lundgren",
                "position": "Verkst dir"
            },
            "establishment_year": 1965
        },
        "5": {
            "company_name": "BOSTROM, AB HARRY N",
            "pnr": "78100",
            "address": "Borlänge, Byggmästarg",
            "phone_number": "0243-178 60",
            "activity": "Tillverkar presentartiklar o bohag i trä o metall",
            "employees": 55,
            "annual_turnover": 6000000,
            "key_personnel": {
                "name": "Fabr Harry Boström",
                "position": "Ägare o chef"
            },
            "establishment_year": 1950
        },
        "6": {
            "company_name": "BOSTROM, INDUSTRI-AKTIEBOLAGET Å",
            "pnr": "45101",
            "address": "Uddevalla 1, Box 222",
            "phone_number": "0522-601 20",
            "bank_details": {
                "bankgiro": "42-8008",
                "postgiro": "115865"
            },
            "activity": "El-apparatutrustningar för industri o fartyg. Svetstill-behör",
            "employees": 17,
            "annual_turnover": 1000000,
            "capital": 10000,
            "key_personnel": {
                "name": "Ing A Boström",
                "position": "Ägare o chef"
            },
            "establishment_year": 1952
        },
        "7": {
            "company_name": "BARLEX, AB",
            "pnr": "41108",
            "address": "Göteborg, Kungsg 62",
            "phone_number": "031-17 55 55",
            "bank_details": {
                "bankgiro": "51-0672",
                "postgiro": "40340"
            },
            "activity": "Säljer glasögon, -bågar, barometrar, kikare etc",
            "employees": 8,
            "capital": 50000,
            "key_personnel": {
                "name": "Konsul Allan Hüttner",
                "position": "Verkst dir"
            },
            "establishment_year": 1945
        },
        "8": {
            "company_name": "ekman, a h",
            "pnr": "580 02",
            "address": "Linköping 2, Box 2041. Ostgötag 22",
            "phone_number": "013-126668",
            "activity": "Säljer sågverksmaskiner, gaffeltruckar, huggmaskiner, barkningsmaskiner, timmer- o klyvbandsågar, barkningskryssare, el- o dieselmotorer samt olika slag av maskiner m m",
            "key_personnel": {
                "name": "Harry Ekman",
                "position": "Chef"
            },
            "establishment_year": 1954
        },
        "9": {
            "company_name": "ekman plåtslageri ab, elon",
            "pnr": "434 00",
            "address": "Kungsbacka, S Torgg 18",
            "phone_number": "0300-101 50",
            "bank_details": {
                "bankgiro": "659-5979",
                "postgiro": "15257-9"
            },
            "activity": "Byggnadsplåtslageri",
            "employees": 8,
            "annual_turnover": 700000,
            "capital": 12000,
            "key_personnel": {
                "name": "Nils-Olof Ekman",
                "position": "Verkst dir"
            },
            "establishment_year": 1886
        },
        "10": {
            "company_name": "TERVENTO AB",
            "pnr": "931 00",
            "address": "Skellefteå, Kanalg 51",
            "phone_number": "0910-17180",
            "activity": "Tillverkar varmlufts-pannor-apparater, torkugnar, bygg-torkar, fläktar",
            "employees": 30,
            "capital": 2500000,
            "key_personnel": {
                "name": "Ernst Johansson",
                "position": "Verkst dir"
            },
            "establishment_year": 1952
        },
        "11": {
            "company_name": "BROBY MODELLSNICKERI AB",
            "pnr": "280 60",
            "address": "Broby, Box 79. Verkstadsg 3",
            "phone_number": "044-40466",
            "bank_details": {
                "bankgiro": "982-0523"
            },
            "activity": "Tillverkar gjutmodel-ler i trä, plast o frigolit",
            "employees": 13,
            "annual_turnover": 400000,
            "capital": 7000,
            "key_personnel": {
                "name": "Harry Mars",
                "position": "Verkst dir"
            },
            "establishment_year": 1957
        },
        "12": {
            "company_name": "BYGGPRIMER AB",
            "pnr": "430 60",
            "address": "Landvetter, Box 57",
            "phone_number": "031-7111 80",
            "bank_details": {
                "bankgiro": "37-2412",
                "postgiro": "479880"
            },
            "activity": "Tillverkar o säljer asfaltprodukter, träskyddsmedel o kem byggnadsprodukter",
            "employees": 10,
            "annual_turnover": 800000,
            "capital": 5000,
            "key_personnel": {
                "name": "Fabr Erie Pettersson",
                "position": "Chef"
            },
            "establishment_year": 1966
        },
        "13": {
            "company_name": "BYGGPRODUKTER STIG JO. HANSSON & CO AB",
            "pnr": "213 62",
            "address": "Malmö, Jägersrov 80",
            "phone_number": "040-94 54 20",
            "bank_details": {
                "bankgiro": "64-1603",
                "postgiro": "245177"
            },
            "activity": "Tillverkning o försäljning av monteringsfärdiga villor, skolpaviljonger, barndaghem, butiker od",
            "employees": 20,
            "annual_turnover": 3500000,
            "capital": 100000,
            "key_personnel": {
                "name": "Rolf Johansson",
                "position": "Verkst dir"
            },
            "establishment_year": 1965
        }
    }
}