{
    "original": "VIK\n\nAntal anställda: 15\nÅrsomsättning: 500 000\nÄgare o chef: Viking Hansson\nEtableringsår: 1949.\n\nVIKINGSTAD MÖBEL- &amp;\nSNICKERIFABRIK, AB\n\nPnr 590 50\n\nVikingstad. Box 106. Industrig 6.\nTel 013-800 12, 800 08. Bankgiro\n607-9859. Postgiro 295281-0\nVerksamhet: Tillverkar o säljer\nspecialinredningar för apotek,\nbanker o annan offentlig miljö\nAntal anställda: 16\nÅrsomsättning: 1200 000\nAktiekapital: 68 000\nVerkst dir: Gunnar Petersson\nEtableringsår: 1945.\n\nWIKLUNDS VERKSTÄDER AB,\nBRUDERNA\n\nPnr 890 28\n\nGullänget, Grevlingsv 5. Tel\n0660-427 00. Bankgiro 161-5319.\nPostgiro 460290-0\n\nVerksamhet: Tillverkar travers- o\ntruckhytter, containers, cisterner\nsamt rostfria konstruktioner\nAntal anställda: 30\nÅrsomsättning: 1500 000\nVerkst dir: Lennart Wiklund\nFabrikör: Roland Wiklund\nKamrer: Sten Peterson\nVerkmästare: Lennart Andersson\nEtableringsår: 1963.\n\nBJORSELL, AB J F\n\nPnr 50102\n\nBorås 1, Stora Torget. Box 14.\nTel 033-1178 40. Bankgiro\n839-1302. Postgiro 8652-0. Tga\nBjörsells\n\nVerksamhet: Boktryckeri,\nbokbinderi o pappershandel. Säljer\nkon-torsmateriel, kontorsmaskiner o\nkontorsmöbler\n\nAvdelningskontor: Alingsås,\nKungsg 34. Tel 0322-164 00\nMariestad, Västerlångg 9. Tel\n0501-14350\nAktiekapital: 89 900\nVerkst dir: Ake Björsell\nEtableringsår: 1888.\n\nWI LEN AB. ERIC\n\nPnr 411 14\n\nGöteborg, N Hamng 6. Tel\n031-119111. 119141. Bankgiro\n500-7067. Postgiro 47727-3. Tga\nEr-wiab. Telex 20623\nVerksamhet: Säljer rulltrappor,\npersontransportörer, lyftkranar\nAntal anställda: 7\nAktiekapital: 5 000\nVeikst dir: Erie Wilén\nEtableringsår: 1942.\n\nELEKTRO-EMFA AB\n\nPnr 260 35\n\nödåkra. Tel 042-943 59 , 943 79\nVerksamhet: Tillverkar elektr\nmotorer\n\nAntal anställda: 40\nEtableringsår: 1947.\n\nELEKTROENGROS, AB\n\nPnr 25102\n\nHelsingborg 1, Box 85. Garnisonsg\n6. Tel 042-1204 60\nVerksamhet: Elektr material i parti\nVerkst dir: Hans Hallberg\nEtableringsår: 1923.\n\nELEKTROFLÄKT\nFABRIKS AB\n\nPnr 150 22\n\nNykvam, Trädgårdsg. Box 42. Tel\n0755-400 64 , 400 65. Bankgiro\n83-0447. Postgiro 197320\nVerksamhet: Tillverkar fläktar o\nventilatorer\nAntal anställda: 15\nÅrsomsättning: 1000 000\nAktiekapital: 75 000\nVerkst dir: Ing Hugo Palmquist\nEtableringsår: 1944.\n\nECKERSTRÖM AB, KURT\n\nPnr 40124\n\nGöteborg 1, Box 304. Avägen 17.\nTel 031-8107 55. Bankgiro\n500-0484. Postgiro 41946-5. Tga Ecker\nVerksamhet: Handels- o\nagentur-firma i kortvaror\nAntal anställda: 25\nÅrsomsättning: 6 000 000\nAktiekapital: 250 000\nÄgare o chefer: Kurt Eckerström,\nAke Staafgård\nEtableringsår: 1938.\n\nFRANSSON AB, ROLF\n\nPnr 551 02\n\nJönköping 1, V Storg 7. Box 148.\nTel 036-16 35 11. Bankgiro\n144-5725. Postgiro 77319-2. Tga\nRolfab. Telex 70158\nVerksamhet: Export av sågade o\nhyvlade trävaror\nAntal anställda: 7\nÅrsomsättning: 22 000 000\nAktiekapital: 50 000\nVerkst dir: Rolf Fransson\nEtableringsår: 1958.\n\nKÄGSTROM &amp; CO, AB E\n\nPnr 93101\n\nSkellefteå 1, Magasinsgränd 3. Box\n86. Tel 0910-174 60. Bankgiro\n203-9105. Postgiro 10509-8\nVerksamhet: Säljer skor, pjäxor,\nträskor o gummiskor i parti o minut\nAntal anställda: 5\nÅrsomsättning: 2 800 000\nAktiekapital: 110 000\nStyrelse: Nils Kågström, Hans\nKågström\n\nEtableringsår: 1881.\n\nBETTNA INREDNINGAR AB\n\nPnr 640 33\n\nBettna. Tel 0155-920 50. Bankgiro\n370-4541. Postgiro 690470-0\nVerksamhet: Tillverkning av\ninredningar i trä o stål\nAntal anställda: 7\nÅrsomsättning: 500 000\nVerkst dir: Ove Malm\nEtableringsår: 1939.\n\nLINDELÖF &amp; CO AB, E\n\nPnr 400 20\n\nGöteborg 14, Mölndalsv 38. Box\n14029. Tel 031-20 03 60. Bankgiro\n501-0418. Postgiro 420885-6. Tga\nLindelöfcomp. Telex 2338\nVerksamhet: Textilfibrer, garner,\nråväv o textilkemikalier\nAntal anställda: 12\nÅrsomsättning: 30 000 000\nAktiekapital: 5 000\nVerkst dir: Winfried Mann\nEtableringsår: 1894.\n\nLINDENS\n\nFritz Nilssons Eftr AB\n\nPnr 290 20\n\nÅhus, Hamnen. Box 33. Tel\n044-24 00 02, 2403 47. Bankgiro\n873-6522. Postgiro 7563-0. Tga Linden.\nTelex 4477\n\nVerksamhet: Skeppsmäkleri,\nspedition, lagerhållning.\nFörsäkrings-o haveriagentur. Ombud för\nAlbrekt-sons presenningsuthyrning\nÅrsomsättning: 3000 000\nAktiekapital: 40 000\nVerkst dir: Skeppsmäkl Gösta\nLindén\n\nEtableringsår: 1888.\n\nLINDÉNS\nMETALLVARUFABRIK AB\n\nPnr 33031\n\nKulltorp. Tel 0370-82070\nVerksamhet: Utför pressningar i\nplåt o tråd\nAktiekapital: 5 000\nFirmatecknare: Thure Lindén\nEtableringsår: 1957.\n\nACIEREX AB\n\nPnr 102 44\n\nStockholm 5, Stureg 16. Box 5156.\nTel 08-63 5100. Bankgiro 56-0002.\nPostgiro 199052. Tga Acierex.\nTelex 1618\n\nVerksamhet: Försäljning för\nsvenska bruk samt import o export av\nstål o industriutrustning\nStålförsäljning o lager: Stockholm\nVA, Björnnäsv 10, Albano\nAntal anställda: 35\nAktiekapital: 500 000\nVerkst dir: M Månsson\nEtableringsår: 1944.\n\nACKURAT, AB\nBAKELIT-FABRIKEN\n\nPnr 360 30\n\nLammhult. Tel 0472-602 44.\nBankgiro 275-5478. Postgiro 381511-5\nVerksamhet: Tillverkar ett\n1000-tal olika standard plastdetaljer\nfor industrin såsom de flesta slag\nav plastfötter, glidknappar även\nställbara, lagerbussningar av\nnylon, genomföringsbussningar,\nmaskeringsringar, distansklossar,\nstapelskydd, skyddspluggar,\nplastbrickor, möbelrullar, rattar,\nhandtagsknoppar, handtagskulor,\nhushållsartiklar, uppläggningsfat för\nbutiker m m från automatisk\nmasstillverkning. Egen verktygs\ntillverkning\n\nAntal anställda: 16\nÅrsomsättning: 800 000\nAktiekapital: 50 000\nVerkst dir: I Svensson\nEtableringsår: 1947.",
    "structured": {
        "1": {
            "company_name": "VIKINGSTAD MÖBEL- & SNICKERIFABRIK, AB",
            "address": "Vikingstad. Box 106. Industrig 6.",
            "phone_number": "013-800 12, 800 08",
            "bank_details": {
                "bankgiro": "607-9859",
                "postgiro": "295281-0"
            },
            "activity": "Tillverkar o säljer specialinredningar för apotek, banker o annan offentlig miljö",
            "employees": 16,
            "annual_turnover": 1200000,
            "capital": 68000,
            "key_personnel": [
                {
                    "name": "Gunnar Petersson",
                    "position": "Verkst dir"
                }
            ],
            "establishment_year": 1945
        },
        "2": {
            "company_name": "WIKLUNDS VERKSTÄDER AB, BRUDERNA",
            "address": "Gullänget, Grevlingsv 5",
            "phone_number": "0660-427 00",
            "bank_details": {
                "bankgiro": "161-5319",
                "postgiro": "460290-0"
            },
            "activity": "Tillverkar travers- o truckhytter, containers, cisterner samt rostfria konstruktioner",
            "employees": 30,
            "annual_turnover": 1500000,
            "key_personnel": [
                {
                    "name": "Lennart Wiklund",
                    "position": "Verkst dir"
                },
                {
                    "name": "Roland Wiklund",
                    "position": "Fabrikör"
                },
                {
                    "name": "Sten Peterson",
                    "position": "Kamrer"
                },
                {
                    "name": "Lennart Andersson",
                    "position": "Verkmästare"
                }
            ],
            "establishment_year": 1963
        },
        "3": {
            "company_name": "BJORSELL, AB J F",
            "address": "Borås 1, Stora Torget. Box 14",
            "phone_number": "033-1178 40",
            "bank_details": {
                "bankgiro": "839-1302",
                "postgiro": "8652-0"
            },
            "activity": "Boktryckeri, bokbinderi o pappershandel. Säljer kontorsmateriel, kontorsmaskiner o kontorsmöbler",
            "locations": [
                {
                    "city": "Alingsås",
                    "phone_number": "0322-164 00"
                },
                {
                    "city": "Mariestad",
                    "phone_number": "0501-14350"
                }
            ],
            "capital": 89900,
            "key_personnel": [
                {
                    "name": "Ake Björsell",
                    "position": "Verkst dir"
                }
            ],
            "establishment_year": 1888
        },
        "4": {
            "company_name": "WI LEN AB. ERIC",
            "address": "Göteborg, N Hamng 6",
            "phone_number": "031-119111, 119141",
            "bank_details": {
                "bankgiro": "500-7067",
                "postgiro": "47727-3"
            },
            "activity": "Säljer rulltrappor, persontransportörer, lyftkranar",
            "employees": 7,
            "capital": 5000,
            "key_personnel": [
                {
                    "name": "Erie Wilén",
                    "position": "Veikst dir"
                }
            ],
            "establishment_year": 1942
        },
        "5": {
            "company_name": "ELEKTRO-EMFA AB",
            "address": "ödåkra",
            "phone_number": "042-943 59 , 943 79",
            "activity": "Tillverkar elektr motorer",
            "employees": 40,
            "establishment_year": 1947
        },
        "6": {
            "company_name": "ELEKTROENGROS, AB",
            "address": "Helsingborg 1, Box 85. Garnisonsg 6",
            "phone_number": "042-1204 60",
            "activity": "Elektr material i parti",
            "key_personnel": [
                {
                    "name": "Hans Hallberg",
                    "position": "Verkst dir"
                }
            ],
            "establishment_year": 1923
        },
        "7": {
            "company_name": "ELEKTROFLÄKT FABRIKS AB",
            "address": "Nykvam, Trädgårdsg. Box 42",
            "phone_number": "0755-400 64 , 400 65",
            "bank_details": {
                "bankgiro": "83-0447",
                "postgiro": "197320"
            },
            "activity": "Tillverkar fläktar o ventilatorer",
            "employees": 15,
            "annual_turnover": 1000000,
            "capital": 75000,
            "key_personnel": [
                {
                    "name": "Ing Hugo Palmquist",
                    "position": "Verkst dir"
                }
            ],
            "establishment_year": 1944
        },
        "8": {
            "company_name": "ECKERSTRÖM AB, KURT",
            "address": "Göteborg 1, Box 304. Avägen 17",
            "phone_number": "031-8107 55",
            "bank_details": {
                "bankgiro": "500-0484",
                "postgiro": "41946-5"
            },
            "activity": "Handels- o agentur-firma i kortvaror",
            "employees": 25,
            "annual_turnover": 6000000,
            "capital": 250000,
            "key_personnel": [
                {
                    "name": "Kurt Eckerström",
                    "position": "Ägare o chefer"
                },
                {
                    "name": "Ake Staafgård",
                    "position": "Ägare o chefer"
                }
            ],
            "establishment_year": 1938
        },
        "9": {
            "company_name": "FRANSSON AB, ROLF",
            "address": "Jönköping 1, V Storg 7. Box 148",
            "phone_number": "036-16 35 11",
            "bank_details": {
                "bankgiro": "144-5725",
                "postgiro": "77319-2"
            },
            "activity": "Export av sågade o hyvlade trävaror",
            "employees": 7,
            "annual_turnover": 22000000,
            "capital": 50000,
            "key_personnel": [
                {
                    "name": "Rolf Fransson",
                    "position": "Verkst dir"
                }
            ],
            "establishment_year": 1958
        },
        "10": {
            "company_name": "KÄGSTROM & CO, AB E",
            "address": "Skellefteå 1, Magasinsgränd 3. Box 86",
            "phone_number": "0910-174 60",
            "bank_details": {
                "bankgiro": "203-9105",
                "postgiro": "10509-8"
            },
            "activity": "Säljer skor, pjäxor, träskor o gummiskor i parti o minut",
            "employees": 5,
            "annual_turnover": 2800000,
            "capital": 110000,
            "key_personnel": [
                {
                    "name": "Nils Kågström",
                    "position": "Styrelse"
                },
                {
                    "name": "Hans Kågström",
                    "position": "Styrelse"
                }
            ],
            "establishment_year": 1881
        },
        "11": {
            "company_name": "BETTNA INREDNINGAR AB",
            "address": "Bettna",
            "phone_number": "0155-920 50",
            "bank_details": {
                "bankgiro": "370-4541",
                "postgiro": "690470-0"
            },
            "activity": "Tillverkning av inredningar i trä o stål",
            "employees": 7,
            "annual_turnover": 500000,
            "key_personnel": [
                {
                    "name": "Ove Malm",
                    "position": "Verkst dir"
                }
            ],
            "establishment_year": 1939
        },
        "12": {
            "company_name": "LINDELÖF & CO AB, E",
            "address": "Göteborg 14, Mölndalsv 38. Box 14029",
            "phone_number": "031-20 03 60",
            "bank_details": {
                "bankgiro": "501-0418",
                "postgiro": "420885-6"
            },
            "activity": "Textilfibrer, garner, råväv o textilkemikalier",
            "employees": 12,
            "annual_turnover": 30000000,
            "capital": 5000,
            "key_personnel": [
                {
                    "name": "Winfried Mann",
                    "position": "Verkst dir"
                }
            ],
            "establishment_year": 1894
        },
        "13": {
            "company_name": "LINDENS",
            "address": "Åhus, Hamnen. Box 33",
            "phone_number": "044-24 00 02, 2403 47",
            "bank_details": {
                "bankgiro": "873-6522",
                "postgiro": "7563-0"
            },
            "activity": "Skeppsmäkleri, spedition, lagerhållning. Försäkrings-o haveriagentur. Ombud för Albrekt-sons presenningsuthyrning",
            "annual_turnover": 3000000,
            "capital": 40000,
            "key_personnel": [
                {
                    "name": "Skeppsmäkl Gösta Lindén",
                    "position": "Verkst dir"
                }
            ],
            "establishment_year": 1888
        },
        "14": {
            "company_name": "LINDÉNS METALLVARUFABRIK AB",
            "address": "Kulltorp",
            "phone_number": "0370-82070",
            "activity": "Utför pressningar i plåt o tråd",
            "capital": 5000,
            "key_personnel": [
                {
                    "name": "Thure Lindén",
                    "position": "Firmatecknare"
                }
            ],
            "establishment_year": 1957
        },
        "15": {
            "company_name": "ACIEREX AB",
            "address": "Stockholm 5, Stureg 16. Box 5156",
            "phone_number": "08-63 5100",
            "bank_details": {
                "bankgiro": "56-0002",
                "postgiro": "199052"
            },
            "activity": "Försäljning för svenska bruk samt import o export av stål o industriutrustning",
            "locations": [
                {
                    "city": "Stockholm VA",
                    "address": "Björnnäsv 10, Albano"
                }
            ],
            "employees": 35,
            "capital": 500000,
            "key_personnel": [
                {
                    "name": "M Månsson",
                    "position": "Verkst dir"
                }
            ],
            "establishment_year": 1944
        },
        "16": {
            "company_name": "ACKURAT, AB BAKELIT-FABRIKEN",
            "address": "Lammhult",
            "phone_number": "0472-602 44",
            "bank_details": {
                "bankgiro": "275-5478",
                "postgiro": "381511-5"
            },
            "activity": "Tillverkar ett 1000-tal olika standard plastdetaljer for industrin såsom de flesta slag av plastfötter, glidknappar även ställbara, lagerbussningar av nylon, genomföringsbussningar, maskeringsringar, distansklossar, stapelskydd, skyddspluggar, plastbrickor, möbelrullar, rattar, handtagsknoppar, handtagskulor, hushållsartiklar, uppläggningsfat för butiker m m från automatisk masstillverkning. Egen verktygs tillverkning",
            "employees": 16,
            "annual_turnover": 800000,
            "capital": 50000,
            "key_personnel": [
                {
                    "name": "I Svensson",
                    "position": "Verkst dir"
                }
            ],
            "establishment_year": 1947
        }
    }
}