{
    "original": "PET\n\nsoffor o fåtöljer till detaljhandeln\nAntal anställda: 70\nÅrsomsättning: 10 000 000\nAktiekapital: 200 000\nVerkst dir: Olof Person\nEtableringsår: 1940.\n\nHELANDER &amp; CO, C V\n\nPnr 41101\n\nGöteborg, Stampg 52. Tel\n031-198463, 1984 74. Bankgiro\n508-0502. Postgiro40294-1. TgaCevehå\nVeiksamhet: Konserver o\ndelikatesser i parti\n\nÄgare o chefer: Berndt Larsson,\nGunnar Svenning\nEtableringsår: 1835.\n\nVAL\n\nWALINGSVETS, AB\n\nPnr 113 53\n\nStockholm, Tuleg 39. Tel 08-\n\n31 85 12. Bankgiro 724-5897.\nPostgiro 197868-3\n\nVerksamhet: Svetsmaterial för\nel-o gassvets\nAktiekapital: 30 000\nVerkst dir: Alexis Blomqvist\nEtableringsår: 1944.\n\nCLIVUS, AB\n\nPnr 135 00\n\nTyresö, Tonstigen 6. Tel\n08-770 04 33, 2128 46. Bankgiro\n74-9148. Postgiro 664848\nVerksamhet: Konstruerar o säljer\nanläggningar för biologisk\nnedbrytning av organiskt avfall\nVarunamn: Clivus\nVerkst dir: Rikard Lindström\nEtableringsår: 1964.\n\nMEKANO.PLAST, AB\n\nPnr 79101\n\nFalun 1, Vallav 16. Box 91. Tel\n023-106 61, 10634. Bankgiro 46-4351.\nPostgiro 469000\n\nVerksamhet: Tillverkar\nplastmattor o plastrullgardiner\nAntal anställda: 18\nAktiekapital: 25 000\nVerkst dir: Lars Ericson\nEtableringsår: 1951.\n\nMIKKOS SÄG &amp; HYVLERI\n\nPnr 970 40\n\nPajala, Box 56. Tel 0978-102 34.\nBankförbindelse: Pajala\nJordbrukskassa. Postgiro 349199\nVerksamhet: Säljer sågade o\nhyvlade trävaror\nAntal anställda: 5\nChef: Thure J Mikko\nEtableringsår: 1950.\n\nSPORDA VADD, AB\n\nPnr 33010\n\nBredaryd, Sporda. Tel 0371-711 19,\n\n71036\n\nVerksamhet: Tillverkar vadd för\nmöbeltillverkning, sängkläder m m.\nPolyestervadd, acrylvadd, elaston-\n\nvadd\n\nAntal anställda: 10\nÅrsomsättning: 2 000 000\nAktiekapital: 40 000\nChef: Våge Claeson\nEtableringsår: 1939.\n\nFASTIGHETSKONTROLL, AB\n\nPnr 11145\n\nStockholm, Birger Jarlsg 13. Tel\n08-1014 44. Postgiro 58442\nVerksamhet: Bekämpning av\nskadeinsekter o råttor\nAktiekapital: 30 000\nEtableringsår: 1935.\n\nKRI\n\nFilialer: 281 00 Hässleholm,\nHäl-singborgsv 10. Tel 0451-14215.\nPlatschef: Jan Westerberg\n283 00 Osby, Nya industriområdet.\nTel 0479-113 10\n\n24300 Höör, Ringsjöv 4. Tel\n0413-20945\n\n295 00 Bromölla, Tians v 2. Tel\n0456-277 50\nAntal anställda: 200\nÅrsomsättning: 35 000 000\nAktiekapital: 1 500 000\nStyrelse: Dir Erik Nilsson (ordf),\ndir Bertil Magnusson, dir Ulf\nNorell, dir Lennart Wiberg\nVeikst dir: Ulf A Norell\nEkonomichef: Sven Giljam\nFörs älj nin gsch ef en\nPersonbilar: Dick Karlsson\nLastbilar: Carl Gustaf Folkeson\nServicechef: Harry Falk\nEtableringsår: 1961\nDotterbolag till AB Scania-Vabis,\nSödertälje.\n\nKRISTIANSTADS BOK.\nTRYCKERI AB\n\nPnr 29101\n\nKristianstad 1, Lastageplatsen 5.\nBox 101. Tel 044-1155 70.\nBankgiro 34-5258- Postgiro 20943\nVerksamhet: Färgtryck,\nreklamtryck, kataloger, offsettryck\nAntal anställda: 110\nÅrsomsättning: 7 000 000\nAktiekapital: 360 000\nVeikst dir: Sture Svensson.\n\nKRISTIANSTADS\nLÄNS-TRYCKERI AB\n\nPnr 29102\n\nKristianstad 2, Industrig 58. Box\n2065. Tel 044-1110 14, 11 01 19.\nBankgiro 859-9052. Postgiro\n122238-9\n\nVerksamhet: Tillverkar kataloger,\ntidskrifter, böcker, reklamtryck,\nsnabbset o bokbinderiarbeten.\nBok-o offsettryck\nÅrsomsättning: 1 300 000\nVerkst dir: Boktr Martin Appelkvist\nV verkst dir: Boktr Lars Porsman.\n\nKRISTIANSTADS OLJE.\nIMPORT AB\n\nPnr 201 23\n\nMalmö 1, Box 325. Tel 040-735 60.\nBankgiro 182-7153. Postgiro\n633940-2\n\nVerksamhet: Säljer eldningsoljor\nFörsäljningskontor: 290 20 Åhus,\nSt ef fan Sohstg. Tel 044-24 00 07\nÅrsomsättning: 7 000 000\nAktiekapital: 160 000\nVerkst dir: John Hain\nEtableringsår: 1915\nDotterbolag till G &amp; L Beijer AB,\nMalmö.\n\nKRISTIANSTADS TRÄ. o\nBYGGNADSVAROR, AB\n\nPnr 29100\n\nKristianstad, Björkhemsv 12. Tel\n044-1155 20. Bankgiro 867-3741.\nPostgiro 263727-0\nVerksamhet: Säljer trä- o\nbyggvaror\n\nAktiekapital: 400 000\nVerkst dir: Bror Killgren\nEtableringsår: 1943.\n\nKRISTIANSTAD YLLEFABRIK\nAB\n\nPnr 29101\n\nKristianstad 1, Väverig 2. Box 913.\nTel 044-1152 50. Bankgiro 15-1010.\nPostgiro 15003. Tga Kristianstad\nYlle\n\nVeiksamhet: Tillverkar herr- o\ndamtyger samt möbeltyger\nAntal anställda: 170\nÅrsomsättning: 12 000 000\nAktiekapital: 2 500 000\nVerkst dir: Göran Wirenstam\nEtableringsår: 1898.\n\nKRISTINEDALS FÄRG. och\nUNDERHÄLLS AB\n\nPnr 451 00\n\nUddevalla, S Drottningg 25. Tel\n0522-11214, 159 92. Bankgiro\n89-3890. Postgiro 395347\nVerksamhet: Tillverkar\nspecialolje-lack. Utför rostskyddsbehandling\nVarunamn: Holst-Teak-Fasad\nAktiekapital: 5 000\nVerkst dir: Bertil\nHolst-Hermans-son\n\nEtableringsår: 1959\nDotterbolag till Måleri AB\nBröderna Magnusson, Uddevalla.\n\nKRISTINEHAMNS CEMENT.\nGJUTERI, AB\n\nPnr 681 01\n\nKristinehamn 1, Box 43.\nVäster-långg 10. Tel 0550-15415.\nBankgiro 819-9408. Postgiro 27999-2\nVerksamhet: Säljer betongvaror,\nsåsom rör, block, plattor samt\nbyggnadsmaterial, snickerier, trappor,\nköksinredningar mm\nAntal anställda: 15\n.Aktiekapital: 300 000\nVerkst dir: Karl Axel Sohlberg\nEtableringsår: 1905.\n\nKRISTINEHAMNS GRÄV.\nMASKINS AB\n\nPnr 68101\n\nKristinehamn 1, Första Industrig 1.\nBox 33. Tel 0550-155 60. 167 43.\nBankgiro 81-9965. Postgiro 463050\nVerksamhet: Utfor vägbyggnads-,\nvatten- o avloppsarbeten\n.Antal anställda: 33\nÅrsomsättning: 2 500 000\n.Aktiekapital: 30 000\nVerkst dir: Ing A E Hesselius\nEtableringsår: 1950.\n\nKRISTINEHAMNS TRÄFOR.\nADLINGSFABRIK\nGÖSTA OLSSON KB\n\nPnr 68100\n\nKristinehamn, Nyhamnsv 5. Tel\n0550-154 40. Bankgiro 110-0965.\nPostgiro 28616-1\n\nVerksamhet: Tillverkar\ndörrsnickerier i alla träslag o utföranden\nVarunamn: Solido-dörren\nVerkst dir: Ing Ulf Kulling\nEtableringsår: 1895.\n\nINDUSTRIMASKINER IMA, AB\n\nPnr 11452\n\nStockholm. Skepparg 22. Tel\n08-63 16 20. Bankgiro 29-5067.\nPostgiro 406574-4. Tga Industrimaskin\nVerksamhet: Köper o säljer nya o\nbegagnade verktygsmaskiner såsom\nsvarvar, borrmaskiner etc\nVarunamn: Oilo-Master\nAntal anställda: 9\nÅrsomsättning: 2500 000\nAktiekapital: 30000\nVeikst dir Hans Rune Aggenberg\nEtableringsår 1936.",
    "structured": {
        "1": {
            "company_name": "PET soffor o fåtöljer till detaljhandeln",
            "activity": "soffor o fåtöljer till detaljhandeln",
            "establishment_year": 1940,
            "employees": 70,
            "annual_turnover": 10000000,
            "capital": 200000,
            "key_personnel": [
                {
                    "name": "Olof Person",
                    "position": "Verkst dir"
                }
            ]
        },
        "2": {
            "company_name": "HELANDER & CO, C V",
            "pnr": "41101",
            "address": "Göteborg, Stampg 52",
            "phone_number": "031-198463, 1984 74",
            "bank_details": {
                "bankgiro": "508-0502",
                "postgiro": "40294-1"
            },
            "activity": "Konserver o delikatesser i parti",
            "key_personnel": [
                {
                    "name": "Berndt Larsson",
                    "position": "Ägare o chefer"
                },
                {
                    "name": "Gunnar Svenning",
                    "position": "Ägare o chefer"
                }
            ],
            "establishment_year": 1835
        },
        "3": {
            "company_name": "VAL WALINGSVETS, AB",
            "pnr": "113 53",
            "address": "Stockholm, Tuleg 39",
            "phone_number": "08-31 85 12",
            "bank_details": {
                "bankgiro": "724-5897",
                "postgiro": "197868-3"
            },
            "activity": "Svetsmaterial för el-o gassvets",
            "capital": 30000,
            "key_personnel": [
                {
                    "name": "Alexis Blomqvist",
                    "position": "Verkst dir"
                }
            ],
            "establishment_year": 1944
        },
        "4": {
            "company_name": "CLIVUS, AB",
            "pnr": "135 00",
            "address": "Tyresö, Tonstigen 6",
            "phone_number": "08-770 04 33, 2128 46",
            "bank_details": {
                "bankgiro": "74-9148",
                "postgiro": "664848"
            },
            "activity": "Konstruerar o säljer anläggningar för biologisk nedbrytning av organiskt avfall",
            "annual_production_value": "Clivus",
            "key_personnel": [
                {
                    "name": "Rikard Lindström",
                    "position": "Verkst dir"
                }
            ],
            "establishment_year": 1964
        },
        "5": {
            "company_name": "MEKANO.PLAST, AB",
            "pnr": "79101",
            "address": "Falun 1, Vallav 16, Box 91",
            "phone_number": "023-106 61, 10634",
            "bank_details": {
                "bankgiro": "46-4351",
                "postgiro": "469000"
            },
            "activity": "Tillverkar plastmattor o plastrullgardiner",
            "employees": 18,
            "capital": 25000,
            "key_personnel": [
                {
                    "name": "Lars Ericson",
                    "position": "Verkst dir"
                }
            ],
            "establishment_year": 1951
        },
        "6": {
            "company_name": "MIKKOS SÄG & HYVLERI",
            "pnr": "970 40",
            "address": "Pajala, Box 56",
            "phone_number": "0978-102 34",
            "activity": "Säljer sågade o hyvlade trävaror",
            "employees": 5,
            "key_personnel": [
                {
                    "name": "Thure J Mikko",
                    "position": "Chef"
                }
            ],
            "establishment_year": 1950
        },
        "7": {
            "company_name": "SPORDA VADD, AB",
            "pnr": "33010",
            "address": "Bredaryd, Sporda",
            "phone_number": "0371-711 19, 71036",
            "activity": "Tillverkar vadd för möbeltillverkning, sängkläder m m. Polyestervadd, acrylvadd, elaston-vadd",
            "employees": 10,
            "annual_turnover": 2000000,
            "capital": 40000,
            "key_personnel": [
                {
                    "name": "Våge Claeson",
                    "position": "Chef"
                }
            ],
            "establishment_year": 1939
        },
        "8": {
            "company_name": "FASTIGHETSKONTROLL, AB",
            "pnr": "11145",
            "address": "Stockholm, Birger Jarlsg 13",
            "phone_number": "08-1014 44",
            "activity": "Bekämpning av skadeinsekter o råttor",
            "capital": 30000,
            "establishment_year": 1935
        },
        "9": {
            "company_name": "KRI",
            "activity": "Personbilar: Dick Karlsson Lastbilar: Carl Gustaf Folkeson Servicechef: Harry Falk",
            "establishment_year": 1961
        },
        "10": {
            "company_name": "KRISTIANSTADS BOK. TRYCKERI AB",
            "pnr": "29101",
            "address": "Kristianstad 1, Lastageplatsen 5, Box 101",
            "phone_number": "044-1155 70",
            "bank_details": {
                "bankgiro": "34-5258",
                "postgiro": "20943"
            },
            "activity": "Färgtryck, reklamtryck, kataloger, offsettryck",
            "employees": 110,
            "annual_turnover": 7000000,
            "capital": 360000,
            "key_personnel": [
                {
                    "name": "Sture Svensson",
                    "position": "Verkst dir"
                }
            ]
        },
        "11": {
            "company_name": "KRISTIANSTADS LÄNS-TRYCKERI AB",
            "pnr": "29102",
            "address": "Kristianstad 2, Industrig 58, Box 2065",
            "phone_number": "044-1110 14, 11 01 19",
            "bank_details": {
                "bankgiro": "859-9052",
                "postgiro": "122238-9"
            },
            "activity": "Tillverkar kataloger, tidskrifter, böcker, reklamtryck, snabbset o bokbinderiarbeten. Bok-o offsettryck",
            "annual_turnover": 1300000,
            "key_personnel": [
                {
                    "name": "Boktr Martin Appelkvist",
                    "position": "Verkst dir"
                },
                {
                    "name": "Boktr Lars Porsman",
                    "position": "Verkst dir"
                }
            ]
        },
        "12": {
            "company_name": "KRISTIANSTADS OLJE. IMPORT AB",
            "pnr": "201 23",
            "address": "Malmö 1, Box 325",
            "phone_number": "040-735 60",
            "bank_details": {
                "bankgiro": "182-7153",
                "postgiro": "633940-2"
            },
            "activity": "Säljer eldningsoljor",
            "annual_turnover": 7000000,
            "capital": 160000,
            "key_personnel": [
                {
                    "name": "John Hain",
                    "position": "Verkst dir"
                }
            ],
            "establishment_year": 1915
        },
        "13": {
            "company_name": "KRISTIANSTADS TRÄ. o BYGGNADSVAROR, AB",
            "pnr": "29100",
            "address": "Kristianstad, Björkhemsv 12",
            "phone_number": "044-1155 20",
            "bank_details": {
                "bankgiro": "867-3741",
                "postgiro": "263727-0"
            },
            "activity": "Säljer trä- o byggvaror",
            "capital": 400000,
            "key_personnel": [
                {
                    "name": "Bror Killgren",
                    "position": "Verkst dir"
                }
            ],
            "establishment_year": 1943
        },
        "14": {
            "company_name": "KRISTIANSTADS YLLEFABRIK AB",
            "pnr": "29101",
            "address": "Kristianstad 1, Väverig 2, Box 913",
            "phone_number": "044-1152 50",
            "bank_details": {
                "bankgiro": "15-1010",
                "postgiro": "15003"
            },
            "activity": "Tillverkar herr- o damtyger samt möbeltyger",
            "employees": 170,
            "annual_turnover": 12000000,
            "capital": 2500000,
            "key_personnel": [
                {
                    "name": "Göran Wirenstam",
                    "position": "Verkst dir"
                }
            ],
            "establishment_year": 1898
        },
        "15": {
            "company_name": "KRISTINEDALS FÄRG. och UNDERHÄLLS AB",
            "pnr": "451 00",
            "address": "Uddevalla, S Drottningg 25",
            "phone_number": "0522-11214, 159 92",
            "bank_details": {
                "bankgiro": "89-3890",
                "postgiro": "395347"
            },
            "activity": "Tillverkar specialolje-lack. Utför rostskyddsbehandling",
            "annual_turnover": 5000,
            "key_personnel": [
                {
                    "name": "Bertil Holst-Hermansson",
                    "position": "Verkst dir"
                }
            ],
            "establishment_year": 1959
        },
        "16": {
            "company_name": "KRISTINEHAMNS CEMENT. GJUTERI, AB",
            "pnr": "681 01",
            "address": "Kristinehamn 1, Box 43, Väster-långg 10",
            "phone_number": "0550-15415",
            "bank_details": {
                "bankgiro": "819-9408",
                "postgiro": "27999-2"
            },
            "activity": "Säljer betongvaror, såsom rör, block, plattor samt byggnadsmaterial, snickerier, trappor, köksinredningar mm",
            "employees": 15,
            "capital": 300000,
            "key_personnel": [
                {
                    "name": "Karl Axel Sohlberg",
                    "position": "Verkst dir"
                }
            ],
            "establishment_year": 1905
        },
        "17": {
            "company_name": "KRISTINEHAMNS GRÄV. MASKINS AB",
            "pnr": "68101",
            "address": "Kristinehamn 1, Första Industrig 1, Box 33",
            "phone_number": "0550-155 60, 167 43",
            "bank_details": {
                "bankgiro": "81-9965",
                "postgiro": "463050"
            },
            "activity": "Utfor vägbyggnads-, vatten- o avloppsarbeten",
            "employees": 33,
            "annual_turnover": 2500000,
            "capital": 30000,
            "key_personnel": [
                {
                    "name": "Ing A E Hesselius",
                    "position": "Verkst dir"
                }
            ],
            "establishment_year": 1950
        },
        "18": {
            "company_name": "KRISTINEHAMNS TRÄFOR. ADLINGSFABRIK GÖSTA OLSSON KB",
            "pnr": "68100",
            "address": "Kristinehamn, Nyhamnsv 5",
            "phone_number": "0550-154 40",
            "bank_details": {
                "bankgiro": "110-0965",
                "postgiro": "28616-1"
            },
            "activity": "Tillverkar dörrsnickerier i alla träslag o utföranden",
            "capital": 300000,
            "key_personnel": [
                {
                    "name": "Ing Ulf Kulling",
                    "position": "Verkst dir"
                }
            ],
            "establishment_year": 1895
        },
        "19": {
            "company_name": "INDUSTRIMASKINER IMA, AB",
            "pnr": "11452",
            "address": "Stockholm, Skepparg 22",
            "phone_number": "08-63 16 20",
            "bank_details": {
                "bankgiro": "29-5067",
                "postgiro": "406574-4"
            },
            "activity": "Köper o säljer nya o begagnade verktygsmaskiner såsom svarvar, borrmaskiner etc",
            "annual_turnover": 2500000,
            "capital": 30000,
            "key_personnel": [
                {
                    "name": "Hans Rune Aggenberg",
                    "position": "Veikst dir"
                }
            ],
            "establishment_year": 1936
        }
    }
}