{
    "original": "SCAN-TECHNIC AB\n\nPnr 20313\n\nMalmö 4, S Tullg 4 A. Box 4179.\nTel 040-12 6873. Bankgiro\n894-9992. Postgiro 636003-6.\nTelex 32374 SERVIO S\nVerksamhet: Säljer produkter inom\nmaskin-, värme-, vatten- o\nsani-tetsbranschen\nÅrsomsättning: 300 000\nAktiekapital: 25 000\nVerkst dir: Karl-Gustav Rexing\nEtableringsår: 1967.\n\nRYONBOLAGET AB\n\nPnr 824 01\n\nHudiksvall 1, Hamng 19. Box 445.\nTel 0650-154 20. Bankgiro\n787-0157. Postgiro 140729-5. Tga Ryon\nVerksamhet: Sport- o\nförbandsartiklar samt text- o mäxkpennor\nAntal anställda: 30\nÅrsomsättning: 11000 000\nAktiekapital: 50 000\nChefer Emil Olsson, Werner Olsson\nEtableringsår 1940.\n\nNIHLÉN &amp; CO AB, A\n\nPnr 252 27\n\nHelsingborg, Rågångsg 4. Tel\n042-18 00 90. Bankgiro 445-4708.\nPostgiro 264642-0\n\nVerksamhet: Järnkonstruktioner o\nbyggnadssmide. Industriservice\nAntal anställda: 60\nÅrsomsättning: 3 500 000\nAktiekapital: 100 000\nVeikst dir. Gunnar Linde\nEtableringsår: 1944.\n\nBODINS MEKANISKA AB\n\nPnr 693 02\n\nDegerfors 2, Box 2017. Lokstallsg.\nTel 0586-42180. Bankgiro\n605-3631. Postgiro 292881-0\nVerksamhet: Tillverkar verktyg,\nfixturer o jiggar\nAntal anställda: 22\nÅrsomsättning: 1500 000\nAktiekapital: 10 000\nVerkst dir: Ing E G Bodin\nEtableringsår: 1945\nOmbildat till aktiebolag 1959.\n\nBOETHIUS AB, HUGO\n\nPnr 101 33\n\nStockholm 1, Box 911. Tel\n08-110911, 21 1409.Bankgiro 33-0109.\nPostgiro 51438\n\nVerksamhet: Tillverkar o säljer\nindustri o laboratoriestolar\nUtställning: Sthlm C, Upplandsg 14\nAktiekapital: 15 000\nVerkst dir: A Wärnling\nEtableringsår: 1927\nOmbildat till aktiebolag 1954.\n\nBOFORS, AB\n\nPnr 690 20\n\nBofors. Tel 0586-360 00. Tga\nBoforsco, (för de kem\nanläggningarna) Nobelkrut. Telex 73210\nFörsäljningskontor: 11120\nStockholm, V as ag 12. Tel 08-234480.\nTelex 1311\n\n415 05 Göteborg, Korpralsg 3. Tel\n031-840200. Telex 2265\n211 24 Malmö, Hanög 5. Tel\n040-93 5210. Telex 3165\n702 17 Örebro, Tingslagsg 4. Tel\n019-124125. Telex 73429\n633 46 Eskilstuna, Kardang 5. Tel\n016-1377 40. Telex 40946\n851 03 Sundsvall, Storg 26. Tel\n060-15 0 6 00. Telex 71205\nMetallurgiska anläggningar:\nTillverkar stålgöt, stålgjutgods,\nkonstruktionsstål, verktygsstål,\ni form av stång o tråd, press-,\nhammar- o sänksmide, för bl a\nbil- o motorindustrin\nMekaniska verkstäder:\nVerktyg, maskindelar o maskiner,\nanläggningsmaskiner o\ntransport-utrustningar, såsom grensletruckar\no portalkranar, slitgods för band-\n\ntraktorer o grävmaskiner, förkrossar\no kvarnar, elektronikprodukter,\nsåsom mätgivare för kraft, tryck,\nrörelse, bärfrekvenssystem,\nvärme-bildskameror\n\nFörsvarsmateriel: Armé-, marin- o\nLv-pjäser, antiubåtsvapen,\ntråd-styrda missiler,\nartilleriammunition, bomber, raketer\nKemiska fabriker:\nTillverkar krut för handvapen,\nartilleri, raketer o robotar;\ntändmedel, pyrotekn o sprängämnen för\nammunition; nitrocellulosa för\ndynamit-, färg- o lackindustrin;\nacetylsalisylsyra, bensokain,\nisoniazid, niacinamid, prokain m m\nför läkemedelsindustrin; nitro-,\ndinitro-, klornitro-, amino- o\ndia-minobensoesyror, nitrobensoylklo-rider, nitro- o dinitrotoluener m fi\nmellanprodukter för färgämnes- o\nläkemedelsindustrierna;\nakryl-plaster för polish, läcker, färger o\ntätningsmedel; sackarin o\nkonserveringsmedel för\nlivsmedelsindustrin; kloramin för desinfektion,\nuretanskumplastråvaror för mjuka,\nhalvstyva o styva skum för\nframställning av stötskydd,\nisoleringsmaterial, byggnadselement m m;\nläkemedelsspecialiteter\nAktiekapital: 132 000 000\nAntal anställda: 9 000\nTillverkningsvärde: 734 000 000\nStyrelse: Bruksdisp Sverre R:son\nSohlman (ordf), hovrättsrådet Sven\nHammarskiöld (v ordf), dir Erland\nWaldenström, agronom Stig Janson,\nbankdir L E Thunholm, dir Tryggve\nHolm, bruksdisp Gunnar Hindemark,\nbruksdisp Per Odelberg\nVerkst dir: Per Odelberg\nV verkst dir: Bert Henning\nEkonomichef: Dir Bert Henning\nInköpschef: Dir Erling Spiik\nUtvecklingschef: Dir Sven Gerdin\nInformationschef: Overing Nils\nWahlberg\n\nFörsvarsmateriel: Artilleridir\nLennart Pålsson\n\nFörsäljning: Dir Karl-Edvin Plyhr\nKonstruktion: Dir Nils-Erik Kliller\nStål: Dir Stig Caspersson\nFörsäljning: Dir Gustaf Tamm\nProduktion: Overing Törd Krey\nAnläggningsmaskiner o\ntransport-utrustningar: Overing Stig Olsson\nFörsäljning\n\nAnläggningsmaskiner: Herr Stig\nUtterström\n\nTransport utrustning ar: Ing Per-Erik\nBlix\n\nElektronik: Dir Nils-Erik KUller\n\nFörsäljning: Civiling Svein Kalgraff\n\nVerkstäder: Overing Stig Olsson\n\nKEMISKA PRODUKTER:\n\nDir Allan Dahlén\n\nNobelkrut: Dir Nils Carbonnier\n\nFörsäljning\n\nKrut o sprängämnen: Herr P G\nWarming\n\nKemiska produkter: Civiling Gunnar\nRenius\n\nProduktion: Overing Rolf Berntson\nForskning: Tekn dr Erik Bengtsson\nNobel-Pharma: Dir Allan Dahlén\nPlatschef Mölndal: Dr Bo af\nEkenstam\n\nFörsäljning: Civilekonom Bengt O\nBengtsson\n\nForskning: Dr Fritz Henn\nKem tekn avd: Ing Nils-Olov\nMagnusson\n\nFabriksprojekt: Overing Torvald\nNorell\n\nJärnverket anlades i mitten av\n1600-talet. Övertogs 1873 av AB\nBofors-Gullspång.\nNuvarande namn o bolagsordning\n1919. Bolaget har år 1935 i sig\nupptagit f d AB Bofors Nobelkrut,\ngrundat 1898.\n\nTill bolaget är följande\nindustriföretag anslutna: Larsbo Kalk AB,\nStorå, AB NOHAB, Trollhättan,\nBofors-Tidaholmsverken AB,\nTidaholm o Ulvsunda Verkstäder\nAB, Bromma, Metior AB, Malmö.\nSe annons på bakre pärmens insida.\n\n[-BOFORS-TIDAHOLMS-VERKEN-]\n\n{+BOFORS-TIDAHOLMS-\nVERKEN+} AB\n\nPnr 522 00\n\nTidaholm. Tel 0502-113 20. Tga\nBeteve. Telex 5066 BETEVE S\nVerksamhet: Tillverkar halvtunga\nprecisionsbetonade maskiner\n(delvis för AB Bofori), akrylplast,\narmerad esterplast, styv\nuretanskum-plast, diverse manufaktur av\ntermoplaster (hel- o halvfabrikat)\nVarunamn: Bonocar, Bonocell,\nBonomar, Bonoplex, Bonopol,\nEster-Bo nowell\nAktiekapital: 5 000 000\nStyrelse: Bruksdisp Per Odelberg\n(ordf), dir Bert Henning, dir Ludvig\nSterky\n\nVerkst din Ludvig Sterky\nLaboratoriechef: Ing Harry Mattsson\nMek verkstadschef: Ing Lars Falk\nInköpschef: Kurt Ekdahl\nFörsäljn-avd: Bygg- o\nstandard-prod: Ing David Bickel\nIndustri-o exportprod: Erik Åsberg\nKamrer: Lennart Warnstam\nEtableringsår: 1935\nHelägt dotterbolag till AB Bofors.\n\nBOGERYDS MÖBLER AB\n\nPnr 543 01\n\n0504-116 80. Bankgiro 221-3155.\nPostgiro 174874-8\nVerksamhet: Möbeltillverkning.\nSpecialitet: byggbara bokhyllor\nVerkst dir: Uno Bogeryd.\n\nBOGESUNDS VÄVERI AB\n\nPnr 52300\n\nUlricehamn, Strandg 42. Tel\n0321-122 90. Bankgiro 532-7895.\nPostgiro 91455-6. Tga Bogesunds väveri.\nTelex 36047\n\nVerksamhet: Tillverkar möbeltyger\nAntal anställda: 160\nÅrsomsättning: 18 000000\nAktiekapital: 500 000\nStyrelse: Gunnar Cardell, Stig\nCardell, Roald Philipp\nVeikst dir. Stig Cardell\nEtableringsår: 1934.\n\nTEDECO, AB\n\nPnr 102 52\n\nStockholm 27, Storängsv 23. Box\n27127. Tel 08-233485, 67 27 27.\nBankgiro 160-4339. Postgiro\n50471-2. Tga Tedecompany\nVerksamhet: Säljer maskiner o\nförnödenheter för grafiska industrin\nAntal anställda: 22’\nÅrsomsättning: 5000 000\nAktiekapital: 250 000\nStyrelse: Adv Peter Wadsted (ordf),\ndisp Carsten Bratt, dir Knut Arthur\nThiel, civiling Sten Thiel\nVerkst dir: Knut Arthur Thiel\nEtableringsår: 1954.\n\nWANCO AB\n\nPnr 117 37\n\nStockholm, Bergsundsg 25. Tel\n08-68 10 60. Bankgiro 730-2185.\nPostgiro 255106-7. Tgalngwanco\nVerksamhet: Ingenjörsfirma o\nmaskinaffär\nAktiekapital: 21600\nVerkst dir: Sture Berg\nEtableringsår: 1946.\n\nSKEPPSELEKTRO\n\nPnr 20045\n\nMalmö 23, Rödkullastigen 5 A. Box\n23009. Tel 040-96 74 46. Bankgiro\n603-3765. Postgiro 202881-9\nVerksamhet: Konsulterande\ningenjörsbyrå\n\nVerkst dir: Lars Hed\nEtableringsår: 1964.\n\nPRIMUS-SIEVERT AB\n\nPnr 172 21\n\nSundbyberg 1, Box 6. Vretenv 4,\nSolna. Tel 08-2825 30. Bankgiro\n743-6140. Postgiro 510420-3.\nTga Primswe, Stockholm.\n\nTelex 1853 PRIMSWE S\nVerksamhet: Tillverkar camping-,\nhobby- o hushållsapparater samt\nirxiustriverktyg för gasol (propån,\nbutan), gasolflaskor, motorvärmare\no hus vagns varmare för gasol,\nslipskiveavrivare\n\nFörsäljning i Sverige genom Primus\nSvenska Försäljnings AB\nFabriker: Flen. Tel 0157-133 50\nHagfors. Tel 0563-110 70\nVarunamn: Primus, Sievert\nAntal anstäUda: 400\nÅrsomsättning: 35 000 000\nAktiekapital: 1500 000\nStyrelse: Dir Bengt I:sson Sjögren,\ndir Karl Nyqvist, dir Gösta Källén\nVerkst dir: Gösta Källén\nMarknadschef: Bertil Säw\nEtableringsår: 1882\nOmbildat till aktiebolag 1906.\n\nPRINCEPS LAGERMAN\nPRESS AB\n\nPnr 411 40\n\nGöteborg, Fabriksg 22. Tel\n031-15 19 35. Postgiro 40479\nVerksamhet: Arborrning,\nplanhyv-ling o kuggfräsning\nAntal anställda: 8\nAktiekapital: 86000\nVerkst dir: R Carlman\nEtableringsår: 1916.\n\nSVENSKA PÅLFABRIKEN, AB\n\nPnr 411 24\n\nGöteborg C, Vasag 5 A. Tel\n031-17 81 20. Bankgiro 420-5787.\nPostgiro 525520\n\nVerksamhet: Tillverkar o säljer\nbetongpålar. Utför pålningsarbeten\nAntal anställda: 80\nÅrsomsättning: 12 000 000\nAktiekapital: 30 000\nVerkst dir: Sture Johansson\nEtableringsår: 1957.\n\nNORA TÄNDRORSFABRIK, AB\n\nPnr 713 00\n\nNora stad. Tel 0587-114 50.\nPostgiro 71374\n\nVerksamhet: Tillverkar stubintråd\no elektr tändare samt utför\nformsprutning, formblåsning o\nsträngsprutning av plast\nAktiekapital: 900000\nStyrelse: Dlr Ulf Langefors (ordf),\ndir Allan Wetterholm, kamrer Rune\nBjörklund, Jörgen M Blegvad\nVerkst dir: Allan Wetterholm\nFabrikschef: Civiling Nils H\nCarlborg\n\nEtableringsår: 1871\nOmbildat till aktiebolag 1899.\n\nNORA-GOMEX, AB\n\nPnr 71300\n\nNora stad, Box 40. Kvarnv. Tel\n0587-11400. Bankgiro 609-4213.\nPostgiro 339788-2. Tga Gomexn.\nTelex 73376\n\nVerksamhet: Tillverkar\nhårdmetall-belagda verktyg etc\nAktiekapital: 1000 000\nVerkst dir: Jan Danielsen\nEtableringsår: 1898.",
    "structured": {
        "1": {
            "company_name": "SCAN-TECHNIC AB",
            "address": "Malmö 4, S Tullg 4 A. Box 4179",
            "phone_number": "040-12 6873",
            "bank_details": {
                "bankgiro": "894-9992",
                "postgiro": "636003-6"
            },
            "activity": "Säljer produkter inom maskin-, värme-, vatten- o sani-tetsbranschen",
            "annual_turnover": 300000,
            "capital": 25000,
            "key_personnel": [
                {
                    "name": "Karl-Gustav Rexing",
                    "position": "Verkst dir"
                }
            ],
            "establishment_year": 1967
        },
        "2": {
            "company_name": "RYONBOLAGET AB",
            "address": "Hudiksvall 1, Hamng 19. Box 445",
            "phone_number": "0650-154 20",
            "bank_details": {
                "bankgiro": "787-0157",
                "postgiro": "140729-5"
            },
            "activity": "Sport- o förbandsartiklar samt text- o mäxkpennor",
            "employees": 30,
            "annual_turnover": 11000000,
            "capital": 50000,
            "key_personnel": [
                {
                    "name": "Emil Olsson",
                    "position": "Chefer"
                },
                {
                    "name": "Werner Olsson",
                    "position": "Chefer"
                }
            ],
            "establishment_year": 1940
        },
        "3": {
            "company_name": "NIHLÉN & CO AB, A",
            "address": "Helsingborg, Rågångsg 4",
            "phone_number": "042-18 00 90",
            "bank_details": {
                "bankgiro": "445-4708",
                "postgiro": "264642-0"
            },
            "activity": "Järnkonstruktioner o byggnadssmide. Industriservice",
            "employees": 60,
            "annual_turnover": 3500000,
            "capital": 100000,
            "key_personnel": [
                {
                    "name": "Gunnar Linde",
                    "position": "Veikst dir"
                }
            ],
            "establishment_year": 1944
        },
        "4": {
            "company_name": "BODINS MEKANISKA AB",
            "address": "Degerfors 2, Box 2017. Lokstallsg",
            "phone_number": "0586-42180",
            "bank_details": {
                "bankgiro": "605-3631",
                "postgiro": "292881-0"
            },
            "activity": "Tillverkar verktyg, fixturer o jiggar",
            "employees": 22,
            "annual_turnover": 1500000,
            "capital": 10000,
            "key_personnel": [
                {
                    "name": "Ing E G Bodin",
                    "position": "Verkst dir"
                }
            ],
            "establishment_year": 1945
        },
        "5": {
            "company_name": "BOETHIUS AB, HUGO",
            "address": "Stockholm 1, Box 911",
            "phone_number": "08-110911, 21 1409",
            "bank_details": {
                "bankgiro": "33-0109",
                "postgiro": "51438"
            },
            "activity": "Tillverkar o säljer industri o laboratoriestolar",
            "capital": 15000,
            "key_personnel": [
                {
                    "name": "A Wärnling",
                    "position": "Verkst dir"
                }
            ],
            "establishment_year": 1927
        },
        "6": {
            "company_name": "BOFORS, AB",
            "address": "Bofors",
            "phone_number": "0586-360 00",
            "activity": "Tillverkar stålgöt, stålgjutgods, konstruktionsstål",
            "employees": 9000,
            "annual_turnover": 734000000,
            "capital": 132000000,
            "key_personnel": [
                {
                    "name": "Per Odelberg",
                    "position": "Verkst dir"
                },
                {
                    "name": "Bert Henning",
                    "position": "V verkst dir"
                }
            ],
            "establishment_year": 1873
        },
        "7": {
            "company_name": "BOFORS-TIDAHOLMS-VERKEN AB",
            "address": "Tidaholm",
            "phone_number": "0502-113 20",
            "bank_details": {
                "bankgiro": "Tga Beteve",
                "postgiro": "5066 BETEVE S"
            },
            "activity": "Tillverkar halvtunga precisionsbetonade maskiner",
            "capital": 5000000,
            "key_personnel": [
                {
                    "name": "Ludvig Sterky",
                    "position": "Verkst din"
                }
            ],
            "establishment_year": 1935
        }
    }
}