{
    "original": "PANI PRODUKTER\n\nPnr 44200\n\nKtmgälv. Tel 0303-120 88.\nBankgiro 430-9654. Postgiro 529088-7\nVerksamhet: Tillverkar vikdörren\nPani i både vävplast o trä\nÄgare o chef: Paul Nilsson\nEtableringsår: 1960.\n\nBOHMAN AB, ROLF\n\nPnr 94101\n\nPiteå 1, Box 24. Hamng 55. Tel\n0911-16000. Bankgiro 98-6334.\nPostgiro 487411. Telex 80438\nVeiksamhet: Biluthyrning.\nTrafikskola. Filialer i Sundsvall,\nÖrnsköldsvik, Umeå, Skellefteå, Piteå,\nLuleå o Kiruna. Representant för\nHertz Rent a Car, New York\nAntal anställda: 13\nÅrsomsättning: 1 300 000\nAktiekapital: 5 000\nVerkst dir: Rolf Bohman\nEtableringsår: 1967.\n\nBOMAN PATENTBYRÅ, AB\nWALDEMAR\n\nPnr 114 27\n\nStockholm, Sköldungag 9. Tel\n08-23 00 65. Bankgiro 72-8483.\nPost-giro 57884. Tga Waldemar\nVerksamhet; Patentbyrå o ärenden\nför registrering av varumärken\no mönster\nAntal anställda: 17\nÅrsomsättning: 1 000 000\nAktiekapital: 40400\nVerkst dir: Civiling Sigvard Boman\nEtableringsår: 1890.\n\nAVANT I MASKINER, AB\n\nPnr 195 00\n\nMärsta, Charlottenbergs gård. Tel\n0760-490 90. Bankgiro 572-3408.\nPostgiro 553488-8. Tga Avantima\nVerksamhet: Säljer o uthyr\nbrunnsborrningsmaskiner. Säljer Telma\nelektrodynamiska bromsar o Honda\nprodukter\n\nÅrsomsättning: 3 000 000\nAktiekapital: 100 000\nVerkst dir: Ing Sten Engwall\nEtableringsår: 1956.\n\nUVE\n\nUPPÄKRA MEK VERKSTAD AB\n\nPnr 560 10\n\nSkillingaryd, Smålandsg 20. Tel\n0370-70625\n\nVerksamhet: Tillverkar\noljebrännare, låsmuttrar i olika utförande, re.\nvolver- o supportsvarvning utföres\nefter ritning, automatsvarvning\nsamt fräsning, pressning o\nverktygstillverkning\nAktiekapital: 30 000\nVerkst dir: Birger Ekström\nEtableringsår: 1948.\n\nGRAFISKA BILDER AB\n\nPnr 112 27\n\nStockholm, Kungsholmsg 19. Tel\n\nGRAFISKA I VÄRNAMO AB\n\nPnr 33101\n\nVärnamo 1. Expov. Box 77. Tel\n0370-117 05. Bankgiro 29-1521.\nPostgiro 473543-7\nVerksamhet: Tillverkar klichéer,\nmatriser, termosetter, plastklichéer,\nskurna o vulkade gummistämplar,\noffsetplåtar o offsetfilm\nAvdelningskontor: Stockholm,\nGrafiska AB, Drottningholmsv 31-33.\nTel 08-54 29 30\nAntal anställda: 60\nAktiekapital: 570 000\nStyrelse: Dir Gunnar Fälth (ordf),\ndir Bertil Estberg, dir Gunnar\nOlsson\n\nVerkst dir: Bertil Estberg\nEtableringsår: 1954\nNamnändring 1967.\n\nGRAFLUND, BYGGNADS.\nFIRMA GUNNAR\n\nPnr 632 20\n\nEskilstuna, Teaterg 1. Tel\n016-13 7730. Bankgiro 828-0323.\nPostgiro 290401-9\n\nVerksamhet: Uppför bostadshus o\nindustribyggnader\nAntal anstäUda: 150\nÅrsomsättning: 15 000 000\nChef: Ing Gunnar Graflund\nEtableringsår: 1948.\n\nROBELA AB\n\nPnr 41122\n\nGöteborg, Skanstorget 18. Tel\n031-11 1092, 13 09 53. Bankgiro\n506-1726. Postgiro 425855-4. Tga\nScandilinerob\n\nVerksamhet: Arbetshandskar,\narbetskläder, stövlar,\ngummiarbets-kängor, skyddsglasögon,\nsvetsglas-ögon, respiratorer, hörselskydd.\nGeneralagent för Britton\nInternational Pius 50 skyddsskor o\nUniversal PU 88 med extra lätt\nsula\n\nVarunamn: Pius 50\nAntal anställda: 6\nAktiekapital: 20 000\nVerkst dir: Rolf Bertil Larsson\nEtableringsår: 1959.\n\nBORE-VERKEN AB\n\nPnr 590 30\n\nBorensberg. Tel 0141-400 73.\nBankgiro 13-4307. Postgiro 14895\nVerksamhet: Tillverkar säckkärror\nAntal anställda: 4\nÅrsomsättning: 300 000\nAktiekapital: 44 200\nVerkst dir: H Fackler\nEtableringsår: 1925.\n\nOPE.TRYCK, AB\n\nPnr 83100\n\nÖstersund, Kyrkg 52. Tel 063-\n\n248 60\n\nVerksamhet: Bok- o\naccidens-tryckeri\n\nAktiekapital: 50000\n\nStyrelse: Bengt Magnusson, Sven\nWallin\n\nVerkst dir: Sven Wallin\nEtableringsår 1964.\n\nBOR\n\nBORGEN, AB TRIKÄFABRIKEN\n\nPnr 612 00\n\nFinspång, Ekbacksv 3. Tel\n0122-128 30. Bankgiro 13-2715.Postgiro\n380894. Tga Borgen\nVerksamhet: Tillverkar\nsjukvårdsartiklar i kamelull\nAntal anställda: 15\nÅrsomsättning: 1000000\nAktiekapital: 25 000\nVerkst dir: Stig Hildemar\nEtableringsår: 1948.\n\nBORGENSTIERNA &amp; CO AB,\nBERTIL\n\nPnr 115 27\n\nStockholm, Wittstocksg 13 B. Tel\n08-63 93 90. Bankgiro 563-0041.\nPostgiro 864-9. Tga Borgis\nVerksamhet: Säljerverktyg,\nmomentnycklar, domkrafter, pressade\ngavlar, tumstockar, skruvmejslar\nAntal anställda: 3\nAktiekapital: 10 000\nVerkst dir: Ing E Frestadius\nEtableringsår: 1909.\n\nGRUNDBERG &amp; CO, AB CARL\n\nPnr 41475\n\nGöteborg, Oxhagsg 34. Tel\n031-14 42 23. Bankgiro 15-1462.\nPostgiro 42280. Tga Grundbergco\nVerksamhet: Maskiner för\npappersbruk o cellulosafabriker, begagnade\nmaskiner\n\nAktiekapital: 15 000\nEtableringsår: 1917.",
    "structured": {
        "1": {
            "company_name": "PANI PRODUKTER",
            "pnr": "44200",
            "address": "Ktmgälv",
            "phone_number": "0303-120 88",
            "bank_details": {
                "bankgiro": "430-9654",
                "postgiro": "529088-7"
            },
            "activity": "Tillverkar vikdörren Pani i både vävplast o trä",
            "key_personnel": [
                {
                    "name": "Paul Nilsson",
                    "position": "Ägare o chef"
                }
            ],
            "establishment_year": 1960
        },
        "2": {
            "company_name": "BOHMAN AB, ROLF",
            "pnr": "94101",
            "address": "Piteå 1, Box 24. Hamng 55",
            "phone_number": "0911-16000",
            "bank_details": {
                "bankgiro": "98-6334",
                "postgiro": "487411"
            },
            "activity": "Biluthyrning Trafikskola. Filialer i Sundsvall, Örnsköldsvik, Umeå, Skellefteå, Piteå, Luleå o Kiruna. Representant för Hertz Rent a Car, New York",
            "employees": 13,
            "annual_turnover": 1300000,
            "capital": 5000,
            "key_personnel": [
                {
                    "name": "Rolf Bohman",
                    "position": "Verkst dir"
                }
            ],
            "establishment_year": 1967
        },
        "3": {
            "company_name": "BOMAN PATENTBYRÅ, AB WALDEMAR",
            "pnr": "114 27",
            "address": "Stockholm, Sköldungag 9",
            "phone_number": "08-23 00 65",
            "bank_details": {
                "bankgiro": "72-8483",
                "postgiro": "57884"
            },
            "activity": "Patentbyrå o ärenden för registrering av varumärken o mönster",
            "employees": 17,
            "annual_turnover": 1000000,
            "capital": 40400,
            "key_personnel": [
                {
                    "name": "Civiling Sigvard Boman",
                    "position": "Verkst dir"
                }
            ],
            "establishment_year": 1890
        },
        "4": {
            "company_name": "AVANT I MASKINER, AB",
            "pnr": "195 00",
            "address": "Märsta, Charlottenbergs gård",
            "phone_number": "0760-490 90",
            "bank_details": {
                "bankgiro": "572-3408",
                "postgiro": "553488-8"
            },
            "activity": "Säljer o uthyr brunnsborrningsmaskiner. Säljer Telma elektrodynamiska bromsar o Honda produkter",
            "annual_turnover": 3000000,
            "capital": 100000,
            "key_personnel": [
                {
                    "name": "Ing Sten Engwall",
                    "position": "Verkst dir"
                }
            ],
            "establishment_year": 1956
        },
        "5": {
            "company_name": "UVE UPPÄKRA MEK VERKSTAD AB",
            "pnr": "560 10",
            "address": "Skillingaryd, Smålandsg 20",
            "phone_number": "0370-70625",
            "activity": "Tillverkar oljebrännare, låsmuttrar i olika utförande, revolver- o supportsvarvning utföres efter ritning, automatsvarvning samt fräsning, pressning o verktygstillverkning",
            "capital": 30000,
            "key_personnel": [
                {
                    "name": "Birger Ekström",
                    "position": "Verkst dir"
                }
            ],
            "establishment_year": 1948
        },
        "6": {
            "company_name": "GRAFISKA BILDER AB",
            "pnr": "112 27",
            "address": "Stockholm, Kungsholmsg 19",
            "phone_number": "N/A",
            "activity": "N/A",
            "establishment_year": "N/A"
        },
        "7": {
            "company_name": "GRAFISKA I VÄRNAMO AB",
            "pnr": "33101",
            "address": "Värnamo 1. Expov. Box 77",
            "phone_number": "0370-117 05",
            "bank_details": {
                "bankgiro": "29-1521",
                "postgiro": "473543-7"
            },
            "activity": "Tillverkar klichéer, matriser, termosetter, plastklichéer, skurna o vulkade gummistämplar, offsetplåtar o offsetfilm",
            "employees": 60,
            "capital": 570000,
            "key_personnel": [
                {
                    "name": "Bertil Estberg",
                    "position": "Verkst dir"
                }
            ],
            "establishment_year": 1954
        },
        "8": {
            "company_name": "GRAFLUND, BYGGNADS. FIRMA GUNNAR",
            "pnr": "632 20",
            "address": "Eskilstuna, Teaterg 1",
            "phone_number": "016-13 7730",
            "bank_details": {
                "bankgiro": "828-0323",
                "postgiro": "290401-9"
            },
            "activity": "Uppför bostadshus o industribyggnader",
            "employees": 150,
            "annual_turnover": 15000000,
            "key_personnel": [
                {
                    "name": "Ing Gunnar Graflund",
                    "position": "Chef"
                }
            ],
            "establishment_year": 1948
        },
        "9": {
            "company_name": "ROBELA AB",
            "pnr": "41122",
            "address": "Göteborg, Skanstorget 18",
            "phone_number": "031-11 1092, 13 09 53",
            "bank_details": {
                "bankgiro": "506-1726",
                "postgiro": "425855-4"
            },
            "activity": "Arbetshandskar, arbetskläder, stövlar, gummiarbets-kängor, skyddsglasögon, svetsglas-ögon, respiratorer, hörselskydd. Generalagent för Britton International Pius 50 skyddsskor o Universal PU 88 med extra lätt sula",
            "employees": 6,
            "capital": 20000,
            "key_personnel": [
                {
                    "name": "Rolf Bertil Larsson",
                    "position": "Verkst dir"
                }
            ],
            "establishment_year": 1959
        },
        "10": {
            "company_name": "BORE-VERKEN AB",
            "pnr": "590 30",
            "address": "Borensberg",
            "phone_number": "0141-400 73",
            "bank_details": {
                "bankgiro": "13-4307",
                "postgiro": "14895"
            },
            "activity": "Tillverkar säckkärror",
            "employees": 4,
            "annual_turnover": 300000,
            "capital": 44200,
            "key_personnel": [
                {
                    "name": "H Fackler",
                    "position": "Verkst dir"
                }
            ],
            "establishment_year": 1925
        },
        "11": {
            "company_name": "OPE.TRYCK, AB",
            "pnr": "83100",
            "address": "Östersund, Kyrkg 52",
            "phone_number": "N/A",
            "activity": "Bok- o accidens-tryckeri",
            "capital": 50000,
            "key_personnel": [
                {
                    "name": "Sven Wallin",
                    "position": "Verkst dir"
                }
            ],
            "establishment_year": 1964
        },
        "12": {
            "company_name": "BOR BORGEN, AB TRIKÄFABRIKEN",
            "pnr": "612 00",
            "address": "Finspång, Ekbacksv 3",
            "phone_number": "0122-128 30",
            "bank_details": {
                "bankgiro": "13-2715",
                "postgiro": "380894"
            },
            "activity": "Tillverkar sjukvårdsartiklar i kamelull",
            "employees": 15,
            "annual_turnover": 1000000,
            "capital": 25000,
            "key_personnel": [
                {
                    "name": "Stig Hildemar",
                    "position": "Verkst dir"
                }
            ],
            "establishment_year": 1948
        },
        "13": {
            "company_name": "BORGENSTIERNA & CO AB, BERTIL",
            "pnr": "115 27",
            "address": "Stockholm, Wittstocksg 13 B",
            "phone_number": "08-63 93 90",
            "bank_details": {
                "bankgiro": "563-0041",
                "postgiro": "864-9"
            },
            "activity": "Säljerverktyg, momentnycklar, domkrafter, pressade gavlar, tumstockar, skruvmejslar",
            "employees": 3,
            "capital": 10000,
            "key_personnel": [
                {
                    "name": "Ing E Frestadius",
                    "position": "Verkst dir"
                }
            ],
            "establishment_year": 1909
        },
        "14": {
            "company_name": "GRUNDBERG & CO, AB CARL",
            "pnr": "41475",
            "address": "Göteborg, Oxhagsg 34",
            "phone_number": "031-14 42 23",
            "bank_details": {
                "bankgiro": "15-1462",
                "postgiro": "42280"
            },
            "activity": "Maskiner för pappersbruk o cellulosafabriker, begagnade maskiner",
            "capital": 15000,
            "establishment_year": 1917
        }
    }
}