{
    "original": "HAN\n\nChefer: Anders Hansson, Axel\nHööglund\n\nEtableringsår: 1952.\n\nHANSSONS I GOTEBORG\nEXPORT AB, B RUDE RNA\n\nPnr 414 58\n\nGöteborg, Fiskhamnen, Hall F.\nTel 031-24 7131, 24 7132.\nBankgiro 51-1627. Postgiro 41336. Tga\nPisk\n\nVerksamhet: Säljer färsk fisk o\nsalt sill i parti. Specialitet: filéer\nAntal anställda: 6\nÅrsomsättning: 886 700\nAktiekapital: 30 000\nFirmatecknare: Bertil Florén, Arne\nMeurling\n\nEtableringsår: 1888.\n\nHANSSON &amp; LUNDBOM\nMOTOR AB/SVETSMEKANO\nMARIN AB\n\nPnr 402 73\n\nGöteborg 8, Manufakturg 7 A,\nRingön. Box 8904. Tel\n031-513390. Bankgiro 659-9765.\nPostgiro 429114. Tga Harrfol\nVerksamhet: Båtar o motorer\nAktiekapital: 50 000\nVerkst dir: Stig Holmberg.\n\nAktiekapital: 30 000\nVerkst dir: Hans Hansson\nEtableringsår: 1960.\n\nHANSSONS SKOFABRIK,\nAB ALFR\n\nPnr 790 21\n\nBjursås. Tel 023-50500. Bankgiro\n799-5079. Postgiro 24801-3\nVerksamhet: Tillverkar damskor,\ndamstövlar o stövletter samt\nslippers\n\nAntal anställda: 140\nÅrsomsättning: 6 000 000\nAktiekapital: 100 000\nStyrelse: Kamrer Ernst Hansson\n(ordf), dir Bengt Hansson, Anna\nHansson\n\nVerkst dir: Bengt Hansson\nEtableringsår: 1913.\n\nHANSSON ELEKTRO-MEK\nVERKSTAD, AB C G\n\nPnr 79101\n\nFalun 1, Trotzg 79-81. Box 90. Tel\n023-112 93, 136 93. Bankgiro\n464-1601. Postgiro 90236-1\nVerksamhet: Tillverkar o\nreparerar elektr motorer\nVerkst dir: B Erik Hansson\nEtableringsår: 1917.\n\nRADONA IRRADIATIONS AB\n\nPnr 440 60\n\nSkärhamn. Tel 0304-704 65.\nBankgiro 33-687 4. Tga Radona\nVerksamhet: Sterilisation genom\ngammabestrålning.\nForskningslaboratorium - mikrobiologi o kemi.\nUtvecklingsprojekt, plast.\nKonsulterande verksamhet för industrihygien\nAntal anstäUda: 20\nAktiekapital: 1500 000\nVerkst dir: Civiling Per Engström.\n\nRAGNE, REDERI AB\n\nPnr 593 01\n\nVästervik 1, Box 31. Tel\n0490-130 30. Bankgiro 36-8253. Postgiro\n91198-2. Tga Ragne. Telex 3926\nVerksamhet: Linjetrafik o tankfart\nAntal anställda: 100\nÅrsomsättning: 20 000 000\nAktiekapital: 2 000 000\nVerkst dir: F Lennart Nilsson\nEtableringsår: 1924.\n\nERIKSON &amp; CO, AB JOHN\n\nPnr 543 01\n\nTibro 1, Pack 20. Tel 0504-116 15.\nBankgiro 221-3098. Postgiro\n99799-7. Tga Jerco\nVerksamhet: Tillverkar\nherrskjortor m m\n\nAntal anställda: 98\nÅrsomsättning: 3 500 000\nAktiekapital: 300 000\nVerkst dir: Acsis Lennaärd\nEtableringsår: 1936.\n\nERICSSONS PLATTSÄTT.\nNING AB, JOHN\n\nPnr 112 35\n\nStockholm, Norr Mälarstrand 74.\nTel 08-5202 20. Bankgiro73-3476.\nPostgiro 58973. Tga Jepplatt\nVerksamhet: Utför isolerings- o\nplattsättningsarbeten\nAntal anställda: 105\nÅrsomsättning: 7000 000\nAktiekapital: 330 000\nVerkst dir: Bertil Svahn\nEtableringsår: 1933.\n\nEL-TABRO AB\n\nPnr 67101\n\nArvika 1, Box 54. Kyrkog 36. Tel\n0570-13245. Bankgiro 102-9743.\nPostgiro 14361-0\n\nVerksamhet: Armaturer o\ninstallationer av svag- o starkström\nAntal anställda: 29\nÅrsomsättning: 2000 000\nInnehavare: Stig Taserud, ing Sture\nBrolund\n\nEtableringsår: 1926.\n\nELTEKNISK INDUSTRIKON.\nSULT WIKLUND &amp; CO AB\n\nPnr 126 32\n\nHägersten, Svandammsv 4. Tel\n08-18 03 20. Bankgiro 27-83Z9.\nPostgiro 679734-4\n\nVerksamhet: Konsulterande inom\neltekniska facket. Projektering av\nbland annat industrianläggningar\nAktiekapital: 30 000\nStyrelse: Jur kand Sven Langenius\n(ordf), ing Gösta Karlberg, ing\nMarvin Kristiansen, ing Vilho\nWiklund\n\nVerkst dir: Ing Vilho Wiklund\nEtableringsår: 1966\nOmbildat till aktiebolag 1967.\n\nEL.TEKNISKA KONSULT.\nBYRÅN\n\nPnr 603 53\n\nNorrköping, Gamla Ovägen 5. Tel\n011-18 51 61. Bankgiro 825-8253.\nPostgiro 693655-3\nVerksamhet: Konsulterande\nverksamhet inom elektroteknik\nAntal anställda: 4\nChef: Ing Lennart Claesson\nEtableringsår: 1963.\n\nELTEKNISKA\nPLANERINGS-BYRÅN, S BACKEFELDT AB\n\nPnr 41128\n\nGöteborg, üvre Fogelbergsg 3. Tel\n031-17 72 20. Bankgiro 85-2402.\nPostgiro 527360-2\nVerksamhet: Konsulterande el\ningenjörsbyrå\n\nÄgare o chef: S Backefeldt.\n\nELTEX, AB\n\nPnr 343 00\n\nÄlmhult, Box 147. Tel 0476-124 80.\nBankgiro 873-9492.\nTelex 4616 ELTEX S\nVerksamhet: Tillverkar elektr\nkontrollanordningar f ör värme m m\nAntal anställda: 30\nÅrsomsättning: 2 500 000\nAktiekapital: 50 000\nVerkst dir: Ake Rydborn\nEtableringsår: 1964.\n\nHOLUVERKEN AB\n\nPnr 112 24\n\nStockholm. Bolindersplan 2. Tel\n08-54 47 28, 54 47 29. Tga\nMann-green\n\nVerksamhet: Tillverkar\nstålinredningar\n\nPlåtpressningsfabrik: Hölö. Tel\n0755-571 15. 57135\nAntal anställda: 49\nÅrsomsättning: 3 000 000\nAktiekapital: 250 000\nVerkst dir Curt Mannbrink\nEtableringsår: 1951.\n\nARBOGA MASKINER, AB\n\nPnr 732 00\n\nArboga, Box 73. N Agatan. Tel\n0589-128 20. Bankgiro 600-0103.\nPostgiro 77023-0. Tga\nArboga-maskin. Telex 73200\nVerksamhet: Tillverkning av bänk-,\npelar-, radial- o flerspindliga\nborrmaskiner i standard o\nspecialutförande i kapacitetsområden från\n10-60 mm\n\nAntal anställda: 230\nÅrsomsättning: 18 000 000\nAktiekapital: 4 800 000\nVerkst dir: Hroar de la Cour\n\nDisp: T Brüde\nMarknadsdir: T Eklund\nExportchef: S Liljhagen\nFörsäljn-chef: S Wessgren\nInköpschef: R Brüde\nEtableringsår: 1932\nDotterbolag: AB Hvilans Mek\nVerkstad, Kristianstad. AB\nScania-Verktyg, Helsingborg,\nVerktygsfabriken Ring &amp; Co AB. Arboga.\nARBOGA Maschinenbau GmbH.\nMünchen.\n\nARE\n\nARBOGA MEK VERKSTAD, AB\n\nPnr 732 00\n\nArboga, Jädersv. Tel 0589-127 20.\nTelex 73318. Tga Verkstaden\nVerksamhet: Specialitet: stång-,\nrör- o tråddragningsmaskiner,\nplåt-bearbetningsmaskiner, spånkrossar\nAntal anställda: 200\nAktiekapital: 712 500\nVerkst dir: Hans Warrol\n(Morgårdshammar)\n\nAdm-platschef: övering V Ryner\nEtableringsår: 1856\nMaskinförsäljningen handhas av\nmoderbolaget Morgårdshammar AB.\n\nARBRÅ VERKSTADS AB\n\nse Svedala- Arbrå.\n\nARCOS MEK INDUSTRI AB\n\nPnr 781 00\n\nBorlänge, Herrgårdsg 14. Tel\n0243-183 90. Bankgiro 79-4516. Postgiro\n162946\n\nVerksamhet: Tillverkar kugg- o\nkedjehjul, luft- o hydraulcylindrar\n0150-500 mm samt rör för luft o\nhydraulik\n\nAntal anställda: 15\n\nÅrsomsättning: 1000 000\nAktiekapital: 150 000\nVerkst dir: Arthur Carlsson\nEtableringsår: 1948\nOmbildat till aktiebolag 1961.\n\nARCO.METALL, AB\n\nPnr 163 21\n\nSpånga 1, Kälvestav 110. Box 4.\nTel 08-36 44 55, 36 44 56.\nBankgiro 33-3099. Postgiro 92164\nVerksamhet: Utför\ntunnplåtsarbeten, smidesarbeten, metallarbeten,\nmek tillverkningar o\nserietillverkningar\nAntal anställda: 35\nÅrsomsättning: 2 000 000\nAktiekapital: 200 000\nVerkst dir: Ing Töre Eriksson\nVerkmäst: Sten Lidman\nKamrer: Einar Olsson\nEtableringsår: 1936.\n\nNÄSSJÖ BRYGGERI AB\n\nPnr 57100\n\nNässjö, Köpmansg 20. Tel\n0380-13140. Postgiro 131199-2\nVerksamhet: Tillverkar malt samt\nmalt- o läskedrycker\nAntal anställda: 70\nAktiekapital: 481600\nVerkst dir: Civilekonom N Gäre\nEtableringsår: 1873.\n\nFIXTRA AB\n\nPnr 100 28\n\nStockholm 49, Kungsholms Strand\n169. Box 49021. Tel 08-54 81 07,\n54 82 07. Bankgiro 567-1722.\nPostgiro 559857-8\n\nVerksamhet; Säljer, importerar o\nexporterar elektr artiklar:\nArmaturer, lampor, lysrör, strålkastare,\nväglyktor, väg- o skyltbelysningar\n12, 24. 220 V. Väg- o\ntrafiktillbehör: Trafikskyltar,\navstängnings-material. Grammofoner: Mono, stereo\no högtalare. Fick- o handlampor\nsamt batterier\nVarunamn: Toga\nAktiekapital: 5 000\nVerkst dir: Leonard Persson\nEtableringsår: 1964.\n\nFJUGESTA MÖBELINDUSTRI,\nAB\n\nPnr 71010\n\nFjugesta, Box 5. Bang 14. Tel\n0585-10048. Postgiro 266681-6\nVerksamhet: Tillverkar skåp,\nbyråar, bord o bokhyllor\nAntal anställda: 13\nAktiekapital: 35 000\nVerkst dir: Kurt Berg\nEtableringsår: 1923.\n\nFJUGESTA\nRULLGARDINFABRIK, AB\n\nPnr 71010\n\nFjugesta. Tel 0585-100 08,103 88.\nTga Blindroller\n\nVerksamhet: Tillverkar\nrullgardiner o rullgardinskäppar\nAktiekapital: 150 000\nVerkst dir: Stig Wirén\nEtableringsår: 1908\nOmbildat till aktiebolag 1918.\n\nFJÄLLBONÄSSÅGFORENING,\nEK FOR\n\nPnr 930 80\n\nArvidsjaur, Fjällbonäs. Fack 212.\nTel 0960-140 10.140 24. Bankgiro\n753-1049. Postgiro 61696-1\nVerksamhet: Sågverk o hyvleri.\nTillverkar timrade stugor\nAntal anställda: 10\nÅrsomsättning: 600 000\n\nAndelskapital: 12 000\nChef: Gust Grahn\nEtableringsår: 1937.\n\nISAKSSON &amp; CO, AB C G\n\nPnr 560 40\n\nHabo, Jönköpingsv 28. Box203. Tel\n036-404 00. Bankgiro 980-0376.\nPostgiro 29037-9\n\nVerksamhet: Tillverkar\nbyggnadsbeslag, såsom dörr- o\nfönsterbeslag, handtag, reglar,\nventilationsmaterial, tamburhyllor m m\nVarunamn: Habo\nAntal anställda: 200\nÅrsomsättning: 23000 000\nAktiekapital: 800 000\nVerkst dir: Ake Isaksson\nEtableringsår: 1921\nOmbildat till aktiebolag 1944.\n\nISACSONS ANNONSBYRÅ, AB\nOLOF\n\nPnr 41137\n\nGöteborg, Vasag 40. Tel\n031-1733 70. Tga Adman\nVerksamhet: Aukt annonsbyrå.\nFullservicebyrå. Trycksaker,\nreklamfilmer o\nmarknadsundersökningar\n\nAktiekapital: 150 000\nVeikst dir: Olof Isacson\nEtableringsår: 1945.\n\nISACSONS TRYCKERI AB,\nOSCAR\n\nPnr 41113\n\nGöteborg, Postg 3 B. Tel\n031-17 60 80. Bankgiro 50-0987.\nPostgiro 12106. Tga Printing\nVerksamhet: Boktryck, offset,\nbokbinderi o reklamavdelning\nAntal anställda: 60\nAktiekapital: 200 000\nVerkst dir: Claes Göran Isacson\n\nEtableringsår 1903\nOmbildat till aktiebolag 1929.\n\nDotterföretag: Isacsons PR-byrå AB.\n\nISBERG &amp; SON KB, AB A\n\nPnr 60105\n\nNorrköping 1, Fabriksg 8. Box 409.\nTel 011-12 90 90. Bankgiro 82-6017.\nPostgiro 22288. Tga Isbergetson\nVerksamhet: Bokbinderi o\npärmfabrik. Tillverkar kontorsböcker,\nplastartiklar, kortsystem,\nringböcker, hängmappar o emballage\nVarunamn: AIS\nVerkst dir: Holger Rappestad\nEtableringsår: 1892.\n\nISCO INTERCOMMERCE\nSALES CORPORATION\n\nPnr 122 05\n\nEnskede 5, Billerudsv 6. Fack.\nTel 08-8120 81. Postgiro 353045.\nTga Iscorp\n\nVerksamhet: Export-import,\nhandels- o industrivaror, patent\nÄgare o chef: E Thoors\nEtableringsår: 1948.\n\nVERDEXA, AB\n\nPnr 200 21\n\nMalmö 21, Box 21016. Murmansg\n124. Tel 040-93 56 20. Bankgiro\n640-1913. Postgiro 246888-2. Tga\nVerdexa\n\nVerksamhet Säljer nya o\nbegagnade person- o lastbilar, reservdelar\no tillbehör. Reparationer\nAntal anställda: 600\nÅrsomsättning: 125 000 000\nAktiekapital: 4 500 000\nVerkst dir. Erie Johanson\nFörsäljn-chef PV: Dir Bertil\nAnderson\n\nFörsäljn-chef LV: Disp Bertil\nPersson\n\nServicechef: Disp Kjell Thelin\nReservdelschef: Disp K E Dorthé.\n\nWERI-PRODUKTER AB\n\nPnr 103 27\n\nStockholm 16, Regeringsg 9. Box\n16366. Tel 08-11 51 23, 40 56 55.\nBankgiro 731-6490. Postgiro\n57380-8\n\nVerksamhet: Tillverkar o säljer\n\"Torkalätt\" torkhängare av plast\n\nVarunamn: Torkalätt\nÅrsomsättning: 100 000\nAktiekapital: 10 000\nVerkst dir: Wilhelm Ericson\nEtableringsår: 1957.",
    "structured": {
        "1": {
            "company_name": "HANSSONS I GOTEBORG EXPORT AB",
            "activity": "Säljer färsk fisk o salt sill i parti. Specialitet: filéer",
            "establishment_year": 1952,
            "employees": 6,
            "annual_turnover": 886700,
            "capital": 30000,
            "key_personnel": [
                {
                    "name": "Bertil Florén",
                    "position": "Firmatecknare"
                },
                {
                    "name": "Arne Meurling",
                    "position": "Firmatecknare"
                }
            ]
        },
        "2": {
            "company_name": "HANSSON & LUNDBOM MOTOR AB/SVETSMEKANO MARIN AB",
            "establishment_year": 1960,
            "capital": 30000,
            "key_personnel": [
                {
                    "name": "Hans Hansson",
                    "position": "Verkst dir"
                },
                {
                    "name": "Stig Holmberg",
                    "position": "Verkst dir"
                }
            ]
        },
        "3": {
            "company_name": "HANSSONS SKOFABRIK, AB ALFR",
            "activity": "Tillverkar damskor, damstövlar o stövletter samt slippers",
            "establishment_year": 1913,
            "employees": 140,
            "annual_turnover": 6000000,
            "capital": 100000,
            "key_personnel": [
                {
                    "name": "Kamrer Ernst Hansson",
                    "position": "Styrelseordförande"
                },
                {
                    "name": "Bengt Hansson",
                    "position": "Styrelseledamot"
                },
                {
                    "name": "Anna Hansson",
                    "position": "Styrelseledamot"
                },
                {
                    "name": "Bengt Hansson",
                    "position": "Verkställande direktör"
                }
            ]
        },
        "4": {
            "company_name": "HANSSON ELEKTRO-MEKVERKSTAD, AB C G",
            "activity": "Tillverkar o reparerar elektr motorer",
            "establishment_year": 1917,
            "key_personnel": [
                {
                    "name": "B Erik Hansson",
                    "position": "Verkst dir"
                }
            ]
        },
        "5": {
            "company_name": "RADONA IRRADIATIONS AB",
            "activity": "Sterilisation genom gammabestrålning. Forskningslaboratorium - mikrobiologi o kemi. Utvecklingsprojekt, plast. Konsulterande verksamhet för industrihygien",
            "employees": 20,
            "annual_turnover": 1500000,
            "capital": 1500000,
            "key_personnel": [
                {
                    "name": "Civiling Per Engström",
                    "position": "Verkst dir"
                }
            ]
        },
        "6": {
            "company_name": "RAGNE, REDERI AB",
            "activity": "Linjetrafik o tankfart",
            "establishment_year": 1924,
            "employees": 100,
            "annual_turnover": 20000000,
            "capital": 2000000,
            "key_personnel": [
                {
                    "name": "F Lennart Nilsson",
                    "position": "Verkst dir"
                }
            ]
        },
        "7": {
            "company_name": "ERIKSON & CO, AB JOHN",
            "activity": "Tillverkar herrskjortor m m",
            "establishment_year": 1936,
            "employees": 98,
            "annual_turnover": 3500000,
            "capital": 300000,
            "key_personnel": [
                {
                    "name": "Acsis Lennaärd",
                    "position": "Verkst dir"
                }
            ]
        },
        "8": {
            "company_name": "ERICSSONS PLATTSÄTTNING AB, JOHN",
            "activity": "Utför isolerings- o plattsättningsarbeten",
            "establishment_year": 1933,
            "employees": 105,
            "annual_turnover": 7000000,
            "capital": 330000,
            "key_personnel": [
                {
                    "name": "Bertil Svahn",
                    "position": "Verkst dir"
                }
            ]
        },
        "9": {
            "company_name": "EL-TABRO AB",
            "activity": "Armaturer o installationer av svag- o starkström",
            "employees": 29,
            "annual_turnover": 2000000
        },
        "10": {
            "company_name": "ELTEKNISK INDUSTRIKONSULT WIKLUND & CO AB",
            "activity": "Konsulterande inom eltekniska facket. Projektering av bland annat industrianläggningar",
            "capital": 30000,
            "key_personnel": [
                {
                    "name": "Jur kand Sven Langenius",
                    "position": "Styrelseordförande"
                },
                {
                    "name": "Ing Vilho Wiklund",
                    "position": "Verkst dir"
                }
            ]
        },
        "11": {
            "company_name": "EL.TEKNISKA KONSULT.BYRÅN",
            "activity": "Konsulterande verksamhet inom elektroteknik",
            "employees": 4,
            "key_personnel": [
                {
                    "name": "Ing Lennart Claesson",
                    "position": "Chef"
                }
            ]
        },
        "12": {
            "company_name": "ELTEKNISKA PLANERINGS-BYRÅN, S BACKEFELDT AB",
            "activity": "Konsulterande el ingenjörsbyrå",
            "key_personnel": [
                {
                    "name": "S Backefeldt",
                    "position": "Ägare o chef"
                }
            ]
        },
        "13": {
            "company_name": "ELTEX, AB",
            "activity": "Tillverkar elektr kontrollanordningar f ör värme m m",
            "employees": 30,
            "annual_turnover": 2500000,
            "capital": 50000,
            "key_personnel": [
                {
                    "name": "Ake Rydborn",
                    "position": "Verkst dir"
                }
            ],
            "establishment_year": 1964
        },
        "14": {
            "company_name": "HOLUVERKEN AB",
            "activity": "Tillverkar stålinredningar",
            "employees": 49,
            "annual_turnover": 3000000,
            "capital": 250000,
            "key_personnel": [
                {
                    "name": "Curt Mannbrink",
                    "position": "Verkst dir"
                }
            ]
        },
        "15": {
            "company_name": "ARBOGA MASKINER, AB",
            "activity": "Tillverkning av bänk-, pelar-, radial- o flerspindliga borrmaskiner i standard o specialutförande i kapacitetsområden från 10-60 mm",
            "employees": 230,
            "annual_turnover": 18000000,
            "capital": 4800000,
            "key_personnel": [
                {
                    "name": "Hroar de la Cour",
                    "position": "Verkst dir"
                },
                {
                    "name": "T Brüde",
                    "position": "Disp"
                },
                {
                    "name": "T Eklund",
                    "position": "Marknadsdir"
                },
                {
                    "name": "S Liljhagen",
                    "position": "Exportchef"
                },
                {
                    "name": "S Wessgren",
                    "position": "Försäljn-chef"
                },
                {
                    "name": "R Brüde",
                    "position": "Inköpschef"
                }
            ],
            "establishment_year": 1932
        },
        "16": {
            "company_name": "ARBOGA MEK VERKSTAD, AB",
            "activity": "Specialitet: stång-, rör- o tråddragningsmaskiner, plåt-bearbetningsmaskiner, spånkrossar",
            "employees": 200,
            "capital": 712500,
            "key_personnel": [
                {
                    "name": "Hans Warrol",
                    "position": "Verkst dir"
                },
                {
                    "name": "övering V Ryner",
                    "position": "Adm-platschef"
                }
            ],
            "establishment_year": 1856
        },
        "17": {
            "company_name": "ARBRÅ VERKSTADS AB",
            "activity": "see Svedala-Arbrå"
        },
        "18": {
            "company_name": "ARCOS MEK INDUSTRI AB",
            "activity": "Tillverkar kugg- o kedjehjul, luft- o hydraulcylindrar 0150-500 mm samt rör för luft o hydraulik",
            "employees": 15,
            "annual_turnover": 1000000,
            "capital": 150000,
            "key_personnel": [
                {
                    "name": "Arthur Carlsson",
                    "position": "Verkst dir"
                }
            ],
            "establishment_year": 1948
        },
        "19": {
            "company_name": "ARCO.METALL, AB",
            "activity": "Utför tunnplåtsarbeten, smidesarbeten, metallarbeten, mek tillverkningar o serietillverkningar",
            "employees": 35,
            "annual_turnover": 2000000,
            "capital": 200000,
            "key_personnel": [
                {
                    "name": "Ing Töre Eriksson",
                    "position": "Verkst dir"
                },
                {
                    "name": "Sten Lidman",
                    "position": "Verkmäst"
                },
                {
                    "name": "Einar Olsson",
                    "position": "Kamrer"
                }
            ],
            "establishment_year": 1936
        },
        "20": {
            "company_name": "NÄSSJÖ BRYGGERI AB",
            "activity": "Tillverkar malt samt malt- o läskedrycker",
            "employees": 70,
            "capital": 481600,
            "key_personnel": [
                {
                    "name": "Civilekonom N Gäre",
                    "position": "Verkst dir"
                }
            ],
            "establishment_year": 1873
        },
        "21": {
            "company_name": "FIXTRA AB",
            "activity": "Säljer, importerar o exporterar elektr artiklar: Armaturer, lampor, lysrör, strålkastare, väglyktor, väg- o skyltbelysningar 12, 24. 220 V. Väg- o trafiktillbehör: Trafikskyltar, avstängnings-material. Grammofoner: Mono, stereo o högtalare. Fick- o handlampor samt batterier",
            "capital": 5000,
            "key_personnel": [
                {
                    "name": "Leonard Persson",
                    "position": "Verkst dir"
                }
            ],
            "establishment_year": 1964
        },
        "22": {
            "company_name": "FJUGESTA MÖBELINDUSTRI, AB",
            "activity": "Tillverkar skåp, byråar, bord o bokhyllor",
            "employees": 13,
            "capital": 35000,
            "key_personnel": [
                {
                    "name": "Kurt Berg",
                    "position": "Verkst dir"
                }
            ],
            "establishment_year": 1923
        },
        "23": {
            "company_name": "FJUGESTA RULLGARDINFABRIK, AB",
            "activity": "Tillverkar rullgardiner o rullgardinskäppar",
            "capital": 150000,
            "key_personnel": [
                {
                    "name": "Stig Wirén",
                    "position": "Verkst dir"
                }
            ],
            "establishment_year": 1908
        },
        "24": {
            "company_name": "FJÄLLBONÄSSÅGFORENING, EK FOR",
            "activity": "Sågverk o hyvleri. Tillverkar timrade stugor",
            "employees": 10,
            "annual_turnover": 600000,
            "capital": 12000,
            "key_personnel": [
                {
                    "name": "Gust Grahn",
                    "position": "Chef"
                }
            ],
            "establishment_year": 1937
        },
        "25": {
            "company_name": "ISAKSSON & CO, AB C G",
            "activity": "Tillverkar byggnadsbeslag, såsom dörr- o fönsterbeslag, handtag, reglar, ventilationsmaterial, tamburhyllor m m",
            "employees": 200,
            "annual_turnover": 23000000,
            "capital": 800000,
            "key_personnel": [
                {
                    "name": "Ake Isaksson",
                    "position": "Verkst dir"
                }
            ],
            "establishment_year": 1921
        },
        "26": {
            "company_name": "ISACSONS ANNONSBYRÅ, AB OLOF",
            "activity": "Aukt annonsbyrå. Fullservicebyrå. Trycksaker, reklamfilmer o marknadsundersökningar",
            "capital": 150000,
            "key_personnel": [
                {
                    "name": "Olof Isacson",
                    "position": "Verkst dir"
                }
            ],
            "establishment_year": 1945
        },
        "27": {
            "company_name": "ISACSONS TRYCKERI AB, OSCAR",
            "activity": "Boktryck, offset, bokbinderi o reklamavdelning",
            "employees": 60,
            "capital": 200000,
            "key_personnel": [
                {
                    "name": "Claes Göran Isacson",
                    "position": "Verkst dir"
                }
            ],
            "establishment_year": 1903
        },
        "28": {
            "company_name": "ISCO INTERCOMMERCE SALES CORPORATION",
            "activity": "Export-import, handels- o industrivaror, patent",
            "key_personnel": [
                {
                    "name": "E Thoors",
                    "position": "Ägare o chef"
                }
            ],
            "establishment_year": 1948
        },
        "29": {
            "company_name": "VERDEXA, AB",
            "activity": "Säljer nya o begagnade person- o lastbilar, reservdelar o tillbehör. Reparationer",
            "employees": 600,
            "annual_turnover": 125000000,
            "capital": 4500000,
            "key_personnel": [
                {
                    "name": "Erie Johanson",
                    "position": "Verkst dir"
                },
                {
                    "name": "Bertil Anderson",
                    "position": "Försäljn-chef PV"
                },
                {
                    "name": "Bertil Persson",
                    "position": "Disp LV"
                },
                {
                    "name": "Kjell Thelin",
                    "position": "Servicechef"
                },
                {
                    "name": "K E Dorthé",
                    "position": "Reservdelschef"
                }
            ]
        },
        "30": {
            "company_name": "WERI-PRODUKTER AB",
            "activity": "Tillverkar o säljer 'Torkalätt' torkhängare av plast",
            "annual_turnover": 100000,
            "capital": 10000,
            "key_personnel": [
                {
                    "name": "Wilhelm Ericson",
                    "position": "Verkst dir"
                }
            ],
            "establishment_year": 1957
        }
    }
}