{
    "original": "OPTI-NORD AB\n\nPnr 280 61\n\nKnislinge. Box 81. Tel 044-604 30.\nTelex 4436 OPTINOR S. Tga\nOptinord\n\nVerksamhet: Tillverkar o säljer\nblixtlås\n\nAntal anställda: 105\nAktiekapital: 1000 000\nVerkst dir: Sven Enocson\nEtableringsår: 1946.\n\nGULLERS AB, STUDIO\n\nPnr 11135\n\nStockholm, Kungsg 30. Tel\n08-23 05 85. Bankgiro 57-6879.\nPostgiro 52077. Tga Gullersphoto\nVerksamhet: Industri- o\nreklamfoto i färg o svart vitt\nAktiekapital: 5 000\nVerkst dir: K W Gull ers\nEtableringsår: 1957.\n\nKLEVESTAD AB OKAB, OLOF\n\nPnr 126 06\n\nHägersten, Box 601.\nFruängs-gången 2-4. Tel 08-88 0135.\nBankgiro 486-5044. Postgiro 556710-2.\nTga Okab. Telex 17122 OKAB S\nVerksamhet: Import, agentur- o\nengrosförsäljning av teletekniska\nkomponenter för industriell o\nmilitär elektronik, såsom\nkondensatorer, motstånd, halvledare,\nintegrerade kretsar, potentiometrar,\nomkopplare, panelinstrument, av\nlödningsverktyg, komponentformnings-aggregat, sifferindikatorer,\nsub-miniatyrlampor, Reed-Reläer etc\nVarunamn: OKAB T-2, OKAB T-3\nAntal anställda: 10\nÅrsomsättning: 4 300 000\n■Aktiekapital: 100 000\nStyrelse: Handelsagent Olof\nKlevestav (ordf), fru Maud Klevestav\nVerkst dir: Olof Klevestav\nFörsäljn-chef: Stig Ödlund\nEtableringsår: 1965.\n\nWINBERG KINO AB\n\nPnr 852 36\n\nSundsvall, Bergsg 40. Tel\n060-690 00, 15 15 00. bankgiro\n201-9263. Postgiro 235100-5. Tga\nKino-winberg. Telex 71207\nVerksamhet: Säljer\nljudfilmsprojek-torer o tillbehör\nVarunamn: Bauer. Klangfilm\nVerkst dir: Bengt Erik Winberg\nEtableringsàr: 1968.\n\nWINBERGS VERKSTADER AB\n\nPnr 850 13\n\nSundsvall 13. Box 13035. Tel\n060-697 80. Bankgiro 774-4584.\nPostgiro 165037-3\n\nVerksamhet: Tillverkar maskiner\no tillbehör för cellulosaindustrin\nAntal anställda: 35\nÅrsomsättning: 2 500 000\nAktiekapital: 100 000\nStyrelseordf: Dir Bengt-Erik\nWinberg\n\nVerkst dir: Bengt-Erik Winberg\nEtableringsån 1946.\n\nSEDELL REKLAM AB\n\nPnr 70133\n\nÖrebro 1, Järnvägsg 13. Box 980.\nTel 019-124040. Bankgiro\n817-4815. Postgiro 122836-0\nVerksamhet: Auktoriserad\nreklamkonsult\n\nAvdelningskontor: 104 22 Stockholm\n22, Box 22114. Tel 08-52 07 20\nAntal anställda: 12\nÅrsomsättning: 2 700 000\nAktiekapital: 100 000\nVerkst dir: Rolf Sedell\nEtableringsår: 1950.\n\nCARLSSON, AB J O\n\nPnr 574 01\n\nVetlanda 1, Järnvägsg. Box 69.Tel\n0383-12040. Tga Jocmoebler\nVerksamhet: Tillverkar möbler\nAntal anställda: 76\nAktiekapital: 300 000\nVerkst dir: Ark Karl Erik Ekselius\nEtableringsår: 1930.\n\nCARLSON AB, TRÄ.\nVARUFIRMAN JOSEF\n\nPnr 733 00\n\nSala, Telehuset. Box 38. Tel\n0224-102 40. Tga Timber\nVerksamhet: Sågrörelse. Export av\nträvaror, telegrafstolpar o rundvirke\nAntal anställda: 18\nÅrsomsättning: 4 00 0 000\nAktiekapital: 150000\nVerkst dir: Josef Carlson\nEtableringsår: 1953.\n\nYG DATA AB\n\nPnr 54101\n\nSkövde 1, Box 33. Tel 0500-106 20.\nBankgiro 84-5402. Postgiro 26865.\nTga Gullhögen. Telex 5060\nVerksamhet: Systemarbete,\nprogrammering, databehandling\nAntal anställda: 12\nÅrsomsättning: 1800 000\nAktiekapital: 20 000\nStyrelse: Dir Willy Malmros (ordf),\ndir Göran Carlén, dir Gösta\nSellgren\n\nVerkst dir: Gösta Sellgren\nEtableringsår: 1968.\n\nSTADSBYGGNADSBYRÅN AB\n\nPnr 115 22\n\nStockholm, Banérg 13. Tel\n08-22 40 60. Postgiro 452177-9\nVerksamhet: Rådgivningsbyrå\nAntal anställda: 5\nÅrsomsättning: 350000\nAktiekapital: 50 000\nVerkst dir: Carl-Olof Abelson\nEtableringsår 1959.\n\nDISTRA, AB\n\nPnr 15185\n\nSödertälje 1, Fack. Tel 0755-329 80.\nBankgiro 170-6274. Postgiro\n8324-6. Tga Distra.\nTelex 1237 ASTRA S\nVerksamhet: Grosshandelsrörelse\nmed främst farmacevtiska\nspecialiteter\n\nAktiekapital: 5 000 000\nStyrelse: Dir Karl Arne Wegerfelt\n(ordf), dir Stig Jakobsson, dir\nBengt Ekholm\nVerkst dir: Bengt Ekholm\nEtableringsår: 1943\nDotterbolag till AB Astra,\nSödertälje.\n\nDIO SLÖJD &amp; MÖBLER, AB\n\nPnr 340 21\n\nDiö. Tel 0476-210 56, 210 06.\nBankgiro 276-1112. Postgiro 34377-2.\nTga Diöslöjd\n\nVerksamhet: Tillverkning av\nstoppade sittmöbler, furumöbler,\ntevagnar, TV-bänkar, fåtöljer o soffor\nför vårdhem, bänk- o\nrestaurangsoffor\n\nVarunamn: DS Möbler\nAntal anställda: 45\nÅrsomsättning: 2 600000\n.Aktiekapital: 120 000\nVerkst dir G Nilsson\nDisp: Stig Neil gård\nEtableringsår: 1939.\n\nDIOS AB, BYGGNADSFIRMAN\nANDERS\n\nPnr 75104\n\nUppsala 1, Stora Torget 3.Box 116.\nTel 018-13 93 40. Bankgiro 99-0109.\nPostgiro 5131\n\nVerksamhet: Byggnadsrörelse o\nf astighetsförvaltning\nAntal anställda: 4 100\nÅrsomsättning: 507 000 000\nAktiekapital: 10 000 000\nStyrelse: Fil hedersdr A Diös (ordf),\nadv K Winberg (v ordf), fru Lisa\nDiös, dir H Stjernberg, dir D\nEriksson, dir E Jacobsson, dir L\nDal-häll, dir E Osthol, dir B Rjelmér\nVerkst dir Erik Osthol\nV verkst dir: Bertil Hjelmér\nEtableringsår 1921\nOmbildat till aktiebolag 1952.\n\nDIVERCO AB\n\nPnr 252 34\n\nHelsingborg, Kung Kristoffersg 25.\nTel 042-111640. Tga Diverco\nVerksamhet: Rengörings- o\ndesinfektionsmedel, doseringsautomatik\nEtableringsår: 1967.\n\nWÄSTANSJO INDUSTRI AB\n\nPnr 16140\n\nBromma, orev 13. Tel 08-26 66 62\nVerksamhet: Försäljning av\njular-tlklar o påskartiklar samt\ndekorationsband\n\nAktiekapital: 15 000\nVerkst din John Wahlund\nEtableringsår: 1948.\n\nWÄSTBERG. AB BRÖDERNA\n\nPnr 824 01\n\nHudiksvall 1, Hamng 43. Box 161.\nTel 0650-153 60. Postgiro\n71290-1. Tga Abewe\nVeiksamhet: Trä- o byggvaruaffär.\nMek verkstad för yttertrappor\nAntal anställda: 15\nÅrsomsättning: 7 000 000\nAktiekapital: 100 000\nVerkst dir: Nils Wästberg\nEtableringsår: 1925\nOmbildat till aktiebolag 1950.\n\nVÄSTBERGA MEKANISKA\nVERKSTAD AB\n\nPnr 126 30\n\nHägersten, Elektravägen 64. Tel\n08-45 28 55. Bankgiro 447-1272.\nPostgiro 4782-9. Tga Westmekan\nVerksamhet: Tillverkar fönster för\nfordon, karosseribeslag samt\nautomatiska skjutdörrar\nAntal anställda: 40\nÅrsomsättning: 3 000 000\nAktiekapital: 10000\nChef: Disp J-H Köhler\nEtableringsår. 1954.\n\nVÄST BO MEKANISKA\nVERKSTAD AB\n\nPnr 310 80\n\nHyltebruk. Tel 0345-10260, 11160.\nBankgiro 43-4426. Postgiro 299817\nVerksamhet: Tillverkar barncyklar\nmärke \"Rustibus\", vattenspridare,\nslangkärror, kabelskor, press- o\nstansverktyg. Utför alla slags\nstansade massartiklar i pressar\nfrån 8-100 ton. El-, gas- o\npunkt-svetsning\n\nAntal anställda: 45\nÅrsomsättning: 3 200 000\nAktiekapital: 84 000\nVerkst din Carl Thiger\nEtableringsår: 1946\nOmbildat till aktiebolag 1954.\n\nVÄ ST BO TEKNISKA BYRÅ AB\n\nPnr 330 20\n\nAnderstorp, Box 5. Dalg 10. Tel\n0371-155 78. Bankgiro 986-0669.\nPostgiro 15175-3\nVerksamhet: Byggnads- o\nanläggningsprojektering. Säljer Fribohus\nÅrsomsättning: 1000 000\nAktiekapital: 10 000\nVerkst dir: Ing Roland Svensson\nEtableringsår: 1964.",
    "structured": {
        "firms": {
            "0": {
                "company_name": "OPTI-NORD AB",
                "activity": "Tillverkar o säljer blixtlås",
                "employees": 105,
                "capital": 1000000,
                "key_personnel": [
                    {
                        "name": "Sven Enocson",
                        "position": "Verkst dir"
                    }
                ],
                "establishment_year": 1946
            },
            "1": {
                "company_name": "GULLERS AB, STUDIO",
                "activity": "Industri- o reklamfoto i färg o svartvitt",
                "employees": null,
                "capital": 5000,
                "key_personnel": [
                    {
                        "name": "K W Gullers",
                        "position": "Verkst dir"
                    }
                ],
                "establishment_year": 1957
            },
            "2": {
                "company_name": "KLEVESTAD AB OKAB, OLOF",
                "activity": "Import, agentur- o engrosförsäljning av teletekniska komponenter för industriell o militär elektronik",
                "employees": 10,
                "annual_turnover": 4300000,
                "capital": 100000,
                "key_personnel": [
                    {
                        "name": "Olof Klevestav",
                        "position": "Handelsagent"
                    },
                    {
                        "name": "Maud Klevestav",
                        "position": "fru"
                    },
                    {
                        "name": "Olof Klevestav",
                        "position": "Verkst dir"
                    },
                    {
                        "name": "Stig Ödlund",
                        "position": "Försäljn-chef"
                    }
                ],
                "establishment_year": 1965
            },
            "3": {
                "company_name": "WINBERG KINO AB",
                "activity": "Säljer ljudfilmsprojek-torer o tillbehör",
                "employees": null,
                "capital": null,
                "key_personnel": [
                    {
                        "name": "Bengt Erik Winberg",
                        "position": "Verkst dir"
                    }
                ],
                "establishment_year": 1968
            },
            "4": {
                "company_name": "WINBERGS VERKSTADER AB",
                "activity": "Tillverkar maskiner o tillbehör för cellulosaindustrin",
                "employees": 35,
                "annual_turnover": 2500000,
                "capital": 100000,
                "key_personnel": [
                    {
                        "name": "Bengt-Erik Winberg",
                        "position": "Styrelseordf"
                    },
                    {
                        "name": "Bengt-Erik Winberg",
                        "position": "Verkst dir"
                    }
                ],
                "establishment_year": 1946
            },
            "5": {
                "company_name": "SEDELL REKLAM AB",
                "activity": "Auktoriserad reklamkonsult",
                "employees": 12,
                "annual_turnover": 2700000,
                "capital": 100000,
                "key_personnel": [
                    {
                        "name": "Rolf Sedell",
                        "position": "Verkst dir"
                    }
                ],
                "establishment_year": 1950
            },
            "6": {
                "company_name": "CARLSSON, AB J O",
                "activity": "Tillverkar möbler",
                "employees": 76,
                "capital": 300000,
                "key_personnel": [
                    {
                        "name": "Karl Erik Ekselius",
                        "position": "Verkst dir"
                    }
                ],
                "establishment_year": 1930
            },
            "7": {
                "company_name": "CARLSON AB, TRÄ. VARUFIRMAN JOSEF",
                "activity": "Sågrörelse. Export av trävaror, telegrafstolpar o rundvirke",
                "employees": 18,
                "annual_turnover": 4000000,
                "capital": 150000,
                "key_personnel": [
                    {
                        "name": "Josef Carlson",
                        "position": "Verkst dir"
                    }
                ],
                "establishment_year": 1953
            },
            "8": {
                "company_name": "YG DATA AB",
                "activity": "Systemarbete, programmering, databehandling",
                "employees": 12,
                "annual_turnover": 1800000,
                "capital": 20000,
                "key_personnel": [
                    {
                        "name": "Willy Malmros",
                        "position": "Styrelse"
                    },
                    {
                        "name": "Göran Carlén",
                        "position": "Styrelse"
                    },
                    {
                        "name": "Gösta Sellgren",
                        "position": "Styrelse"
                    }
                ],
                "establishment_year": 1968
            },
            "9": {
                "company_name": "STADSBYGGNADSBYRÅN AB",
                "activity": "Rådgivningsbyrå",
                "employees": 5,
                "annual_turnover": 350000,
                "capital": 50000,
                "key_personnel": [
                    {
                        "name": "Carl-Olof Abelson",
                        "position": "Verkst dir"
                    }
                ],
                "establishment_year": 1959
            },
            "10": {
                "company_name": "DISTRA, AB",
                "activity": "Grosshandelsrörelse med främst farmacevtiska specialiteter",
                "annual_turnover": null,
                "capital": 5000000,
                "key_personnel": [
                    {
                        "name": "Karl Arne Wegerfelt",
                        "position": "Styrelse"
                    },
                    {
                        "name": "Stig Jakobsson",
                        "position": "Styrelse"
                    },
                    {
                        "name": "Bengt Ekholm",
                        "position": "Verkst dir"
                    }
                ],
                "establishment_year": 1943
            },
            "11": {
                "company_name": "DIO SLÖJD & MÖBLER, AB",
                "activity": "Tillverkning av stoppade sittmöbler, furumöbler, tevagnar, TV-bänkar, fåtöljer o soffor för vårdhem, bänk- o restaurangsoffor",
                "employees": 45,
                "annual_turnover": 2600000,
                "capital": 120000,
                "key_personnel": [
                    {
                        "name": "G Nilsson",
                        "position": "Verkst dir"
                    },
                    {
                        "name": "Stig Neilgård",
                        "position": "Disp"
                    }
                ],
                "establishment_year": 1939
            },
            "12": {
                "company_name": "DIOS AB, BYGGNADSFIRMAN ANDERS",
                "activity": "Byggnadsrörelse o fastighetsförvaltning",
                "employees": 4100,
                "annual_turnover": 507000000,
                "capital": 10000000,
                "key_personnel": [
                    {
                        "name": "Fil hedersdr A Diös",
                        "position": "Styrelse"
                    },
                    {
                        "name": "K Winberg",
                        "position": "Styrelse"
                    },
                    {
                        "name": "Lisa Diös",
                        "position": "Styrelse"
                    },
                    {
                        "name": "H Stjernberg",
                        "position": "Styrelse"
                    },
                    {
                        "name": "D Eriksson",
                        "position": "Styrelse"
                    },
                    {
                        "name": "E Jacobsson",
                        "position": "Styrelse"
                    },
                    {
                        "name": "L Dal-häll",
                        "position": "Styrelse"
                    },
                    {
                        "name": "E Osthol",
                        "position": "Styrelse"
                    },
                    {
                        "name": "B Rjelmér",
                        "position": "Styrelse"
                    },
                    {
                        "name": "Erik Osthol",
                        "position": "Verkst dir"
                    },
                    {
                        "name": "Bertil Hjelmér",
                        "position": "V verkst dir"
                    }
                ],
                "establishment_year": 1921
            },
            "13": {
                "company_name": "DIVERCO AB",
                "activity": "Rengörings- o desinfektionsmedel, doseringsautomatik",
                "establishment_year": 1967
            },
            "14": {
                "company_name": "WÄSTANSJO INDUSTRI AB",
                "activity": "Försäljning av jular-tlklar o påskartiklar samt dekorationsband",
                "capital": 15000,
                "key_personnel": [
                    {
                        "name": "John Wahlund",
                        "position": "Verkst dir"
                    }
                ],
                "establishment_year": 1948
            },
            "15": {
                "company_name": "WÄSTBERG. AB BRÖDERNA",
                "activity": "Trä- o byggvaruaffär. Mek verkstad för yttertrappor",
                "employees": 15,
                "annual_turnover": 7000000,
                "capital": 100000,
                "key_personnel": [
                    {
                        "name": "Nils Wästberg",
                        "position": "Verkst dir"
                    }
                ],
                "establishment_year": 1925
            },
            "16": {
                "company_name": "VÄSTBERGA MEKANISKA VERKSTAD AB",
                "activity": "Tillverkar fönster för fordon, karosseribeslag samt automatiska skjutdörrar",
                "employees": 40,
                "annual_turnover": 3000000,
                "capital": 10000,
                "key_personnel": [
                    {
                        "name": "J-H Köhler",
                        "position": "Disp"
                    }
                ],
                "establishment_year": 1954
            },
            "17": {
                "company_name": "VÄST BO MEKANISKA VERKSTAD AB",
                "activity": "Tillverkar barncyklar märke ",
                "employees": 45,
                "annual_turnover": 3200000,
                "capital": 84000,
                "key_personnel": [
                    {
                        "name": "Carl Thiger",
                        "position": "Verkst din"
                    }
                ],
                "establishment_year": 1946
            },
            "18": {
                "company_name": "VÄ ST BO TEKNISKA BYRÅ AB",
                "activity": "Byggnads- o anläggningsprojektering. Säljer Fribohus",
                "employees": null,
                "annual_turnover": 1000000,
                "capital": 10000,
                "key_personnel": [
                    {
                        "name": "Ing Roland Svensson",
                        "position": "Verkst dir"
                    }
                ],
                "establishment_year": 1964
            }
        }
    }
}