{
    "original": "TINTO AB\n\nPnr 55006\n\nJönköping 6,Osterängsv 16. Box\n6040. Tel 036-11 91 25. Bankgiro\n835-6495. Postgiro 81251-1. Tga\nTinto\n\nVerksamhet: Säljer rit- o\nskrivmateriel en gros, generalagent\nför SchwarvBleistift-Fabrik\nChef: Dir Sven Ahlström.\n\nTIRFING, ÄNGFARTYGS AB\n\nPnr 40317\n\nGöteborg 2, Broströmia. Box 2521.\nTel 17 20 20, riks 031-17 5100.\nBankgiro 50-0567. Postgiro 240815.\nTelex 2244. Tga Broström\nVerksamhet: Rederirörelse\nAktiekapital: 144 000 000\nVerkst din Kristian von Sydow\nEtableringsår: 1890.\n\nTITAN, AB INGENIORS.\nFIRMAN\n\nPnr 102 43\n\nStockholm 5, Sibylleg 79. Box\n5106. Tel 08-63 52 60. Bankgiro\n70-0084. Postgiro 51209-5. Tga\nTitan. Telex 1472\n\nVerksamhet: Import-Agentur i\nmetaller, järn, cement, maskiner, el-\n\nmaterial\n\nAntal anställda: 11\nÅrsomsättning: 34 200 000\nAktiekapital: 500000\nVerkst dir: Torsten Jöhncke\nEtableringsår: 1911.\n\nCLI\n\nCLINTON TRADING\nCOMPANY AB\n\nPnr 114 56\n\nStockholm 14. Torstenssonsg 3.\nTel 08-67 5050. Bankgiro\n572-9728. Postgiro 32945-8\nVerksamhet: Köp o försäljning av\naktier o värdehandlingar\nAntal anställda: 5\nÅrsomsättning: 5 000000\nAktiekapital: 1000 000\nVeikst dir: Carl-Willy Sjöholm\nEtableringsår: 1934.\n\nMICRO BILDELAR AB\n\nPnr 330 20\n\nAnderstorp, Box 34. Tel\n0371-160 75. Bankgiro 17-1007. Postgiro\n413018\n\nVerksamhet: Import o försäljning\nav biltillbehör o reservdelar\nAntal anställda: 10\nÅrsomsättning: 4 000 000\nAktiekapital: 10 000\nVerkst dir: Kenneth Kroon\nEtableringsår: 1958.\n\nMICROMATIC INTERNATIONAL\nAB\n\nPnr 113 53\n\nStockholm. Tuleg 17. Tel\n08-24 12 50. Bankgiro 13-6180. Postr\ngiro 190757. Tga Micromatic.\nTelex 17439\n\nVerksamhet Tillverkar o säljer\nproduktionsverktyg, jiggar, fixturer\nsamt pumpar\nVarunamn: Micromatic\nAntal anställda: 80\nÅrsomsättning: 8 000 000\nAktiekapital: 400000\nStyrelse: Dir Sven Blomberg (ordf),\ndir Tage Strömberg, dir Sture\nSundström\n\nVerkst dir: Tage Strömberg\nEtableringsår: 1941.\n\nHEINTZ BIL AB, GUNNAR\n\nPnr 66100\n\nSäffle, Karl stads v 24. Box 34. Tel\n0533-124 20. Bankgiro 114-9848.\nPostgiro 281114-9\nVerksamhet: Säljer Opel\npersonbilar o lastbilar\nAntal anstäUda: 22\nÅrsomsättning: 6 500 000\nAktiekapital: 100 000\nVerkst dir: Gunnar Heintz\nEtableringsår: 1944.\n\nWALL, AB JOHN\n\nPnr 103 43\n\nStockholm 40, Drottningg 68. Box\n40140. Tel 08-22 4 0 4 0. Bankgiro\n168-7656. Postgiro 1191-6. Tga\nJernwall\n\nVeiksamhet: Järn- o maskinaffär.\nFörsäljning i parti o minut\nAktiekapital: 400 000\nVerkst dir: Rolf Gjers\nEtableringsår: 1865.\n\nSAVOY, HOTEL\n\nPnr 551 02\n\nJönköping 2,Brunnsg 15. Box 1078.\nTel 036-1194 80. Bankgiro\n83-5766. Postgiro 121653. Tga\nSavoy-city\n\nVeiksamhet: Hotellet är beläget\n400 m från Centralstationen\nChef: Dina Gunnarsson\nEtableringsår: 1957.\n\nSAXLUND &amp; CO AB,\nINGENIÖRSFIRMAN\n\nPnr 137 01\n\nVästerhaninge 1, Box 79. Tel\n0750-21115. Bankgiro 626-1309.\nPostgiro 570600-7. Tga Ingsaxo.\nTelex 10991\n\nVeiksamhet: Tillverkar o säljer\ndoseringssilor för träindustrin.\nTräbränsleanläggningar o\ntransportanordningar. Ensamförsäljare för\nABO-luckan, samtliga typer för\nsågverksindustrin i Sverige,\nFinland, Danmark o Västtyskland\nTillverkar ABO-luckan vid:\nA Boström Sågverksbyrå, 360 31\nHelgevärma. Tel 0470-602 45\nAntal anställda: 9\nÅrsomsättning: 3 500 000\nAktiekapital: 25 000\nVeikst dir: Ing R Spjuth\nEtableringsår: 1960.\n\nBRE\n\nBRANN PATENTBYRÅ AB,\nDR LUDWIG\n\nPnr 103 84\n\nStockholm 7, Kungsg 3. Box 7231.\nTel 08-23 7270. Bankgiro 56-2911.\nPostgiro 358254. Tga Brannpatent\nVerksamhet: Patentombud\nFilial: Uppsala, Skolg 55 A. Tel\n018-13 96 35. Chef: Dr W Heinemann\nAntal anställda: 62\nÅrsomsättning: 6 500 000\nAktiekapital: 200 000\nStyrelse: Dr Ludwig Brann (ordf),\ndr Irene Brann-Nilsson, civiling\nRune Söderström\nVerkst dir: Dr Ludwig Brann\nEtableringsår: 1950\nOmbildat till aktiebolag 1961.\n\nBRANZELL AB, G\n\nPnr 65108\n\nKarlstad 1, Box 468. N Strandg 7.\nTel 054-11 57 60. Bankgiro 10-0074.\nPostgiro 27644. Tga Branzells\nVerksamhet: Grossistförsäljning.\nBoschprodukter. Bilelektri.sk- o\ndieselservice\nAktiekapital: 100 000\nVerkst dir: G Branzell.\n\nBRANÄS MOTOR AB\n\nPnr 700 03\n\nÖrebro 3, Triangelg 8-10. Box 3058.\nTel 019-13 50 20. Bankgiro 61-4701.\nPostgiro 610156-2. Tga Bramotor\nVerksamhet Import o försäljning av\nentreprenadmaskiner\nAntal anställda: 5\nÅrsomsättning: 1500 000\nAktiekapital: 50 000\nVerkst dir: Olof Branäs\nEtableringsår: 1963.\n\nAMF (SKANDINAVISKA) AB\n\nPnr 560 30\n\nGränna. Tel 0390-108 10. Postgiro\n605184\n\nVerksamhet: Tillverkar o säljer\nallt för bowling o biljard\n.Antal anställda: 50\n.Aktiekapital: 2000 000\nVerkst dir: Erik Ericsson\nEtableringsår: 1959.\n\nSKÅNEOFFSET AB\n\nPnr 200 44\n\nMalmö 13, N Grängesbergsg 19. Box\n13044. Tel 040-868 40. Bankgiro\n264-3252. Postgiro 38540-1\nVerksamhet: Tillverkar trycksaker\ni offsettryck\nAntal anställda: 22\nÅrsomsättning: 4 500 000\nAktiekapital: 5 000\nVerkst dir: Boktr Gösta Landby\nEtableringsår: 1965.\n\nSOLCO, MASKIN AB\n\nPnr 601 04\n\nNorrköping 1, Västgöteg 13. Box\n205. Tel 011-18 0165. Bankgiro\n349-2584. Postgiro 560302-2.\nTelex 64321\n\nVerksamhet: Tillverkar o\nkonstruerar förpackningsmaskiner samt\nmaskiner för livsmedels-, plast- o\ngummiindustrin\nAntal anstäUda: 20\nÅrsomsättning: 3 000 000\nAktiekapital: 50 000\nVerkst dir: Göran Eriksson\nKonstr-chef: Ing Sören Sollerud\nEtableringsår: 1964.",
    "structured": {
        "1": {
            "company_name": "TINTO AB",
            "pnr": "55006",
            "address": "Jönköping 6, Osterängsv 16, Box 6040",
            "phone_number": "036-11 91 25",
            "bank_details": {
                "bankgiro": "835-6495",
                "postgiro": "81251-1"
            },
            "activity": "Säljer rit- o skrivmateriel en gros, generalagent för SchwarvBleistift-Fabrik",
            "capital": null,
            "key_personnel": [
                {
                    "name": "Sven Ahlström",
                    "position": "Dir"
                }
            ],
            "establishment_year": 1957
        },
        "2": {
            "company_name": "TIRFING, ÄNGFARTYGS AB",
            "pnr": "40317",
            "address": "Göteborg 2, Broströmia, Box 2521",
            "phone_number": "17 20 20, riks 031-17 5100",
            "bank_details": {
                "bankgiro": "50-0567",
                "postgiro": "240815"
            },
            "activity": "Rederirörelse",
            "capital": 144000000,
            "key_personnel": [
                {
                    "name": "Kristian von Sydow",
                    "position": "Verkst din"
                }
            ],
            "establishment_year": 1890
        },
        "3": {
            "company_name": "TITAN, AB INGENIORS. FIRMAN",
            "pnr": "102 43",
            "address": "Stockholm 5, Sibylleg 79, Box 5106",
            "phone_number": "08-63 52 60",
            "bank_details": {
                "bankgiro": "70-0084",
                "postgiro": "51209-5"
            },
            "activity": "Import-Agentur i metaller, järn, cement, maskiner, el-material",
            "employees": 11,
            "annual_turnover": 34200000,
            "capital": 500000,
            "key_personnel": [
                {
                    "name": "Torsten Jöhncke",
                    "position": "Verkst dir"
                }
            ],
            "establishment_year": 1911
        },
        "4": {
            "company_name": "CLI CLINTON TRADING COMPANY AB",
            "pnr": "114 56",
            "address": "Stockholm 14, Torstenssonsg 3",
            "phone_number": "08-67 5050",
            "bank_details": {
                "bankgiro": "572-9728",
                "postgiro": "32945-8"
            },
            "activity": "Köp o försäljning av aktier o värdehandlingar",
            "employees": 5,
            "annual_turnover": 5000000,
            "capital": 1000000,
            "key_personnel": [
                {
                    "name": "Carl-Willy Sjöholm",
                    "position": "Veikst dir"
                }
            ],
            "establishment_year": 1934
        },
        "5": {
            "company_name": "MICRO BILDELAR AB",
            "pnr": "330 20",
            "address": "Anderstorp, Box 34",
            "phone_number": "0371-160 75",
            "bank_details": {
                "bankgiro": "17-1007",
                "postgiro": "413018"
            },
            "activity": "Import o försäljning av biltillbehör o reservdelar",
            "employees": 10,
            "annual_turnover": 4000000,
            "capital": 10000,
            "key_personnel": [
                {
                    "name": "Kenneth Kroon",
                    "position": "Verkst dir"
                }
            ],
            "establishment_year": 1958
        },
        "6": {
            "company_name": "MICROMATIC INTERNATIONAL AB",
            "pnr": "113 53",
            "address": "Stockholm, Tuleg 17",
            "phone_number": "08-24 12 50",
            "bank_details": {
                "bankgiro": "13-6180",
                "postgiro": "190757"
            },
            "activity": "Tillverkar o säljer produktionsverktyg, jiggar, fixturer samt pumpar",
            "employees": 80,
            "annual_turnover": 8000000,
            "capital": 400000,
            "key_personnel": [
                {
                    "name": "Sven Blomberg",
                    "position": "ordf"
                },
                {
                    "name": "Tage Strömberg",
                    "position": "dir"
                },
                {
                    "name": "Sture Sundström",
                    "position": "dir"
                }
            ],
            "establishment_year": 1941
        },
        "7": {
            "company_name": "HEINTZ BIL AB, GUNNAR",
            "pnr": "66100",
            "address": "Säffle, Karl stads v 24, Box 34",
            "phone_number": "0533-124 20",
            "bank_details": {
                "bankgiro": "114-9848",
                "postgiro": "281114-9"
            },
            "activity": "Säljer Opel personbilar o lastbilar",
            "employees": 22,
            "annual_turnover": 6500000,
            "capital": 100000,
            "key_personnel": [
                {
                    "name": "Gunnar Heintz",
                    "position": "Verkst dir"
                }
            ],
            "establishment_year": 1944
        },
        "8": {
            "company_name": "WALL, AB JOHN",
            "pnr": "103 43",
            "address": "Stockholm 40, Drottningg 68, Box 40140",
            "phone_number": "08-22 4 0 4 0",
            "bank_details": {
                "bankgiro": "168-7656",
                "postgiro": "1191-6"
            },
            "activity": "Järn- o maskinaffär. Försäljning i parti o minut",
            "capital": 400000,
            "key_personnel": [
                {
                    "name": "Rolf Gjers",
                    "position": "Verkst dir"
                }
            ],
            "establishment_year": 1865
        },
        "9": {
            "company_name": "SAVOY, HOTEL",
            "pnr": "551 02",
            "address": "Jönköping 2, Brunnsg 15, Box 1078",
            "phone_number": "036-1194 80",
            "bank_details": {
                "bankgiro": "83-5766",
                "postgiro": "121653"
            },
            "activity": "Hotellet är beläget 400 m från Centralstationen",
            "key_personnel": [
                {
                    "name": "Dina Gunnarsson",
                    "position": "Chef"
                }
            ],
            "establishment_year": 1957
        },
        "10": {
            "company_name": "SAXLUND & CO AB, INGENIÖRSFIRMAN",
            "pnr": "137 01",
            "address": "Västerhaninge 1, Box 79",
            "phone_number": "0750-21115",
            "bank_details": {
                "bankgiro": "626-1309",
                "postgiro": "570600-7"
            },
            "activity": "Tillverkar o säljer doseringssilor för träindustrin. Träbränsleanläggningar o transportanordningar. Ensamförsäljare för ABO-luckan, samtliga typer för sågverksindustrin i Sverige, Finland, Danmark o Västtyskland. Tillverkar ABO-luckan vid: A Boström Sågverksbyrå, 360 31 Helgevärma, Tel 0470-602 45",
            "employees": 9,
            "annual_turnover": 3500000,
            "capital": 25000,
            "key_personnel": [
                {
                    "name": "Ing R Spjuth",
                    "position": "Veikst dir"
                }
            ],
            "establishment_year": 1960
        },
        "11": {
            "company_name": "BRE BRANN PATENTBYRÅ AB, DR LUDWIG",
            "pnr": "103 84",
            "address": "Stockholm 7, Kungsg 3, Box 7231",
            "phone_number": "08-23 7270",
            "bank_details": {
                "bankgiro": "56-2911",
                "postgiro": "358254"
            },
            "activity": "Patentombud",
            "employees": 62,
            "annual_turnover": 6500000,
            "capital": 200000,
            "key_personnel": [
                {
                    "name": "Dr Ludwig Brann",
                    "position": "ordf"
                },
                {
                    "name": "dr Irene Brann-Nilsson",
                    "position": "dr"
                },
                {
                    "name": "civiling Rune Söderström",
                    "position": null
                }
            ],
            "establishment_year": 1950
        },
        "12": {
            "company_name": "BRANZELL AB, G",
            "pnr": "65108",
            "address": "Karlstad 1, Box 468, N Strandg 7",
            "phone_number": "054-11 57 60",
            "bank_details": {
                "bankgiro": "10-0074",
                "postgiro": "27644"
            },
            "activity": "Grossistförsäljning. Boschprodukter. Bilelektri.sk- o dieselservice",
            "capital": 100000,
            "key_personnel": [
                {
                    "name": "G Branzell",
                    "position": "Verkst dir"
                }
            ]
        },
        "13": {
            "company_name": "BRANÄS MOTOR AB",
            "pnr": "700 03",
            "address": "Örebro 3, Triangelg 8-10, Box 3058",
            "phone_number": "019-13 50 20",
            "bank_details": {
                "bankgiro": "61-4701",
                "postgiro": "610156-2"
            },
            "activity": "Import o försäljning av entreprenadmaskiner",
            "employees": 5,
            "annual_turnover": 1500000,
            "capital": 50000,
            "key_personnel": [
                {
                    "name": "Olof Branäs",
                    "position": "Verkst dir"
                }
            ],
            "establishment_year": 1963
        },
        "14": {
            "company_name": "AMF (SKANDINAVISKA) AB",
            "pnr": "560 30",
            "address": "Gränna",
            "phone_number": "0390-108 10",
            "postgiro": "605184",
            "activity": "Tillverkar o säljer allt för bowling o biljard",
            "employees": 50,
            "capital": 2000000,
            "key_personnel": [
                {
                    "name": "Erik Ericsson",
                    "position": "Verkst dir"
                }
            ],
            "establishment_year": 1959
        },
        "15": {
            "company_name": "SKÅNEOFFSET AB",
            "pnr": "200 44",
            "address": "Malmö 13, N Grängesbergsg 19, Box 13044",
            "phone_number": "040-868 40",
            "bank_details": {
                "bankgiro": "264-3252",
                "postgiro": "38540-1"
            },
            "activity": "Tillverkar trycksaker i offsettryck",
            "employees": 22,
            "annual_turnover": 4500000,
            "capital": 5000,
            "key_personnel": [
                {
                    "name": "Boktr Gösta Landby",
                    "position": "Verkst dir"
                }
            ],
            "establishment_year": 1965
        },
        "16": {
            "company_name": "SOLCO, MASKIN AB",
            "pnr": "601 04",
            "address": "Norrköping 1, Västgöteg 13, Box 205",
            "phone_number": "011-18 0165",
            "bank_details": {
                "bankgiro": "349-2584",
                "postgiro": "560302-2"
            },
            "activity": "Tillverkar o konstruerar förpackningsmaskiner samt maskiner för livsmedels-, plast- o gummiindustrin",
            "employees": 20,
            "annual_turnover": 3000000,
            "capital": 50000,
            "key_personnel": [
                {
                    "name": "Göran Eriksson",
                    "position": "Verkst dir"
                },
                {
                    "name": "Ing Sören Sollerud",
                    "position": "Konstr-chef"
                }
            ],
            "establishment_year": 1964
        }
    }
}