{
    "original": "HIAB-FOCO AKTIEBOLAG\n\nPnr 824 01\n\nHudiksvall 1, Fack. Tel\n0650-15100. Bankgiro 78-7022. Postgiro\n277680. Tga Hiabfoco. Telex 8224\nVerksamhet: Tillverkar hydrauliska\nlastapparater, tippar, liftdumpers\nm m\n\nVarunamn: Hl AB, FOCO, Hiab-Foco\nAntal anställda: 1500\nAktiekapital: 12 000 000\nTillverkningsvärde: 151000 000\nStyrelse: Dir Nils Edholm (ordf),\nprof Stig Strömholm (v ordf),\ndir Jan-Eric Bladh, dir John\nEngellau, dir Lennart Forslund,\n{rof Bengt Jakobsson, konsul\nErie Sundin\n\nVerkst dir: Bengt Hökby\nV verkst dir: K-F Km Karlsson\nEkonomidir: Yngve Burnelius\nMarknadsdir: Bertil Bredinger\nTeknisk dir: Hans G Bäckman\nInformation: Dir Lennart Wassner\nDessutom dotterbolag i Danmark,\n\nFrankrike, Holland, Spanien, USA\no Västtyskland. Generalagenter i\nett 30-tal länder.\n\nHIAB-FOCO SERVICE AB\n\nse HIAB-FOCO AKTIEBOLAG.\n\nHIFAB AB\n\nPnr 10341\n\nStockholm40, Sergelg 1. Box40005.\nTel 08-2247 20. Bankgiro 19-5931.\nPostgiro 251311\n\nVerksamhet: Byggherreombud,\nbygg-projektering o kontroll\nAktiekapital: 5 000\nVerkst dir: Rolf Landstedt\nEtableringsår: 1948.\nModerbolag: Bror Kullström AB.\n\nHILLERSTORPS MEK\nVERKSTAD, AB\n\nPnr 330 33\n\nHillers torp, Brog 19. Box 155. Tel\n0370-220 45. Bankgiro 54-3237.\nPostgiro 274481-1\nVerksamhet: Tillverkar länkrullar,\nhjul. Pressningsarbeten\nAntal anställda: 8\nAktiekapital: 30 000\nVerkst dir: Elof Johansson\nEtableringsår: 1953.\n\nHILLERSTORPS METALL.\nVERK, AB\n\nPnr 330 33\n\nHillers torp. Tel 0370-222 00.\nBankgiro 291-5429. Postgiro 8487-1. Tga\nMetallverket\n\nVerksamhet: Tillverkar\nbyggnadsbeslag, fönsterlås, fönstervred,\nkoppelhakar, kantreglar, gångjärn,\nhandtag, skåpreglar, stormhaspar,\nskruvöglor, träskruv, koppelskruv\nm m\n\nVarunamn: Stil, Stilo\nAntal anställda: 100\nÅrsomsättning: 10000000\nAktiekapital: 1000000\nVerkst dir: Fabr Carl Törefors\nKamrer o försäljn-chef: Erie\nMyr-s£n\n\nEtableringsår: 1942.\n\nHILLERSTORPS TRÄ.\nINDUSTRI\n\nPnr 330 33\n\nHillerstorp. Tel 0370-220 73, 224 73\nVerksamhet: Tillverkar\nträdgårdsmöbler i trä o stålrör samt vilstolar\no tvättbräden\n\nChef: Fabr Sven Andersson.\n\nHILLERSTRÖM &amp; CO, AB\n\nPnr 20123\n\nMalmö 1, Jörgen Kocksg 4. Box\n346. Tel 040-726 00. Bankgiro\n870-1278. Postgiro 37708-5.\nTga Hillerström. Telex 3100, 32307\nVerksamhet: Spedition,\nskeppsmäk-leri, befraktning, rederi,\nlinjeagentur o lagerhus\n\nAvdelningskontor: Trelleborg,\nKon-tinentg 2 Tel 0410-137 15,137 35\nLimhamn, Box 1008. Tel\n040-1515 60\n\nAntal anställda: 65\nÅrsomsättning: 46000 000\nAktiekapital: 150 000\nStyrelse: Adv Stig Boström (ordf),\n\ndir Sven Qik Byhr, befraktare\nGösta Hedström, skeppsklarerare\nErik Håkansson, sped-chef B\nTegnér\n\nVerkst dir: Knut Ryberg\nV verkst dir: Sven-Erik Byhr\nSped-chefer: Bertil Tegnér, Stig\nGerle\n\nEtableringsår: 1913\nOmbildat till aktiebolag 1917.\nDotterbolag: Fastighets AB Utgrunden,\nSvenska Hamburglinjen AB,\nStrandhems Bilverkstad AB.\n\nHILLERSTRÖM, AB OTTO\n\nPnr 25102\n\nHelsingborg 1, Box 41. Kungsg 2.\nTel 042-12 09 20. Bankgiro\n863-9379. Postgiro 14201-8 Tga\nHillerstrombol. Telex 72290, 72291\nVerksamhet: Befraktning, spedition,\nklarering, affärsflyg: Lloyd’s Agents\nAktiekapital: 275 000\nVerkst dir: Konsul Folke Hillerström\nEtableringsår: 1921.\n\nFRÖSÖ HANDTRYCK AB\n\nPnr 83201\n\nFrösön 1, Box 19. Lövstav. Tel\n063-153 04, 153 56. Bankgiro\n199-1082. Postgiro 297536-5\nVerksamhet: Tillverkar o säljer\nborddukar, linnetabletter, löpare,\nfestremsor, servetter, bonader,\nve-por, förkläden, vimplar,\nbordsflaggor o reklamartiklar. Säljer\nbroderade o vävda märken m fi\nsouvenirer\n\nAntal anställda: 25\nAktiekapital: 87 000\nVerkst dir: Lars Evert Lindahl\nEtableringsår: 1958.\n\nGEFA AB\n\nPnr 510 80\n\nTranemo. Tel 0325-701 60.\nBankgiro 55-3108. Postgiro 134638.\nTelex 36059 GEFA S\nVerksamhet: Tillverkar arbets- o\nfritidskläder samt sjukhusartiklar\nAntal anställda: 600\nÅrsomsättning: 37 000 000\nAktiekapital: 2 7 30 000\nVerkst dir: Lennart Gustavson\nEtableringsår: 1937.\n\nTOR LINE AB\n\nPnr 402 73\n\nGöteborg 8, Box 8895.\nSkandiaham-nen. Tel 031-54 03 00. Bankgiro\n820-0925. Postgiro 628710-6. Tga\nTorline. Telex 20800 TORGOT S,\n20688 TORGOT S\nVerksamhet: Bedriver\npassagerar-o lasttrafik\nAntal anställda: 300\nÅrsomsättning: 100 000 000\nAktiekapital: 300 000\nVerkst dir: Hans Laurin\nV verkst dir o passagerarchef:\nMagnus Bergelin\nFraktchef: Leif Lidholm\nEtableringsår: 1965.\n\nmeag, ab\n\nPnr 73101\n\nKöping 1, Box 196. Tel 0221-139 30.\nBankgiro 811-2435. Postgiro\n163812-1\n\nVerksamhet: Tillverkar o säljer\nbetongvaror o trafikmateriel m m\nAntal anställda: 45\nÅrsomsättning: 8 000 000\nAktiekapital: 55 000\nVerkst dir: Mats Andersson\nEtableringsår: 1937.\n\nAPPELGREN&amp; OBERG AB\n\nPnr 582 23\n\nLinköping, Stora Torget 10. Tel\n013-12 73 00, 13 60 30. Bankgiro\n12-0498. Postgiro 128106\nVerksamhet: Byggnadsrörelse\nAntal anställda: 20\nÅrsomsättning: 1800 000\nAktiekapital: 30 000\nChefer: Byggmäst H Oberg,\nbygg-mäst A Appelgren\nEtableringsår: 1959.\n\nSUNDIN BILAR AB\n\nPnr 462 01\n\nVänersborg 1, Fack. Tel\n0521-121 80. Bankgiro 888-7226.\nPost-giro 87385-1\n\nVerksamhet: Auktoriserad\nåterförsäljare för Scania Vabis\nAntal anställda: 90\nÅrsomsättning: 14 000 000\nAktiekapital: 300 000\nVerkst dir: Sten Sundin\nEtableringsår: 1907.\n\nSAILE AB, INGENIÖRSFIRMAN\n\nPnr 421 21\n\nVästra Frölunda 1, Fröodläreg 5.\nBox 22. Tel 031-45 0125. Bankgiro\n549-9629. Postgiro 528116-7\n\nKonstruktion, formgivning,\npatent, planering,\nprojektering och tillverkning\n\nAntal anställda: 50\n\nAktiekapital: 20 000\n\nÄgare o chefen Ing S Eliasson,\n\ning B Nord\n\nEtableringsàr: 1958.\n\nSAKOM TRYCK AB\n\nPnr 11124\n\nStockholm, Walling 15. Tel\n08-24 72 90. Bankgiro 402-4359.\nPostgiro 704150-2\n\nVerksamhet: Skrivbyrå o tryckeri\nAntal anställda: 5\nÅrsomsättning: 500 000\nAktiekapital: 50 000\nStyrelse: John-Olof Persson (ordf),\nRoland Bjurberg, Gunnar Halidén\nVerkst dir: Gunnar Halidén\nTryckeriförest: Roland Bjurberg\nEtableringsàr: 1963.\n\nSALA BYGGNADSSMIDE, AB\n\nPnr 733 00\n\nSala, Hyttv 15. Tel 0224-13075\nVerksamhet: Tillverkar plåt- o\nrörkonstruktioner, skylt- o\nbelysningsstolpar samt flaggstänger i rör\nAktiekapital: 250 000\nVerkst dir: Olof Sköllermark\nEtableringsàr: 1946\nOmbildat till aktiebolag 1956.\n\nSALA GALVAN-FABRIKS AB\n\nPnr 733 00\n\nSala. Tel 0224-15025. Postgiro\n294760-4\n\nVetksamhet: Utför varmförzinkning\no sprutförzinkning, elförzinkning\nmed kromatering, förnickling o\nför-kromning\n\nAntal anställda: 40\nÅrsomsättning: 3 000 000\nAktiekapital: 500 000\nVerkst dir: Georg Johanson\nEtableringsàr 1945.\n\nEBRO-SLIPMATERIAL AB\n\nPnr 652 23\n\nKarlstad, Herrhagsg 5. Tel\n054-18 20 40, 15 90 40. Bankgiro\n881-6753. Postgiro 666262-1\nVerksamhet: Generalagent för Foss\nSlipeskivefabrik A/S, Norge\nAntal anställda: 7\nÅrsomsättning: 1000 000\nAktiekapital: 5000\nVerkst dir: Erie Brolin\nEtableringsår: 1964.\n\nISOTRONIC AB\n\nPnr 183 03\n\nTäby 3, Eskaderv 44. Box 3056.\nTel 08-7560155. Bankgiro 62-6439.\nPostgiro 606536. Tga Isotronic\nVerksamhet: Import o export av\nmedicinska, vetenskapäga o\nindustriella mätinstrument\nAntal anställda: 10\nÅrsomsättning: 3 500 000\nAktiekapital: 100 000\nVerkst dir: Eugen von Sabsay\nEtableringsår: 1964.",
    "structured": {
        "1": {
            "company_name": "HIAB-FOCO AKTIEBOLAG",
            "pnr": "824 01",
            "address": "Hudiksvall 1, Fack",
            "phone_number": "0650-15100",
            "bank_details": {
                "bankgiro": "78-7022",
                "postgiro": "277680"
            },
            "activity": "Tillverkar hydrauliska lastapparater, tippar, liftdumpers m m",
            "employees": 1500,
            "capital": 12000000,
            "annual_production_value": "151000 000",
            "key_personnel": [
                {
                    "name": "Dir Nils Edholm",
                    "position": "ordf"
                },
                {
                    "name": "prof Stig Strömholm",
                    "position": "v ordf"
                },
                {
                    "name": "dir Jan-Eric Bladh",
                    "position": null
                },
                {
                    "name": "dir John Engellau",
                    "position": null
                },
                {
                    "name": "dir Lennart Forslund",
                    "position": null
                },
                {
                    "name": null,
                    "position": "rof Bengt Jakobsson"
                },
                {
                    "name": "konsul Erie Sundin",
                    "position": null
                }
            ],
            "establishment_year": 0
        },
        "2": {
            "company_name": "HILLERSTORPS MEK VERKSTAD, AB",
            "pnr": "330 33",
            "address": "Hillers torp, Brog 19, Box 155",
            "phone_number": "0370-220 45",
            "bank_details": {
                "bankgiro": "54-3237",
                "postgiro": "274481-1"
            },
            "activity": "Tillverkar länkrullar, hjul. Pressningsarbeten",
            "employees": 8,
            "capital": 30000,
            "key_personnel": [
                {
                    "name": "Elof Johansson",
                    "position": "Verkst dir"
                }
            ],
            "establishment_year": 1953
        },
        "3": {
            "company_name": "HILLERSTORPS METALL. VERK, AB",
            "pnr": "330 33",
            "address": "Hillers torp",
            "phone_number": "0370-222 00",
            "bank_details": {
                "bankgiro": "291-5429",
                "postgiro": "8487-1"
            },
            "activity": "Tillverkar byggnadsbeslag, fönsterlås, fönstervred, koppelhakar, kantreglar, gångjärn, handtag, skåpreglar, stormhaspar, skruvöglor, träskruv, koppelskruv m m",
            "employees": 100,
            "annual_turnover": 10000000,
            "capital": 1000000,
            "key_personnel": [
                {
                    "name": "Fabr Carl Törefors",
                    "position": "Verkst dir"
                },
                {
                    "name": "Erie Myr-s£n",
                    "position": "Kamrer o försäljn-chef"
                }
            ],
            "establishment_year": 1942
        },
        "4": {
            "company_name": "HILLERSTORPS TRÄ. INDUSTRI",
            "pnr": "330 33",
            "address": "Hillerstorp",
            "phone_number": "0370-220 73, 224 73",
            "activity": "Tillverkar trädgårdsmöbler i trä o stålrör samt vilstolar o tvättbräden",
            "key_personnel": [
                {
                    "name": "Fabr Sven Andersson",
                    "position": "Chef"
                }
            ]
        },
        "5": {
            "company_name": "HILLERSTRÖM, AB OTTO",
            "pnr": "25102",
            "address": "Helsingborg 1, Box 41, Kungsg 2",
            "phone_number": "042-12 09 20",
            "bank_details": {
                "bankgiro": "863-9379",
                "postgiro": "14201-8"
            },
            "activity": "Befraktning, spedition, klarering, affärsflyg: Lloyd’s Agents",
            "establishment_year": 1921
        }
    }
}