{
    "original": "JOHNCKES I ÅTVIDABERG AB\n\nPnr 597 00\n\nÅtvidaberg, Prästängsv 1. Tel\n0120-120 00. Bankgiro 120-6895.\nPostgiro 445769-3\nVeiksamhet: Lejdverkstad med\nreservdels lager för Volvo\nAntal anställda: 21\nÅrsomsättning: 1400 000\nAktiekapital: 70 000\nVeikst dir: Lennart Jöhncke\nEtableringsår: 1953.\n\nKIRUNA BYGGNADSSMIDE AB\n\nPnr 981 00\n\nKiruna, Lastv 14. Tel 0980-187 10.\nBankgiro 37-0202. Postgiro 67786-4\nVeiksamhet: Tillverkar\nbredfläns-balkar o utför grovplåtslageri,\nsmi-desarbeten samt licenssvetsning\nAntal anställda: 70\nÅrsomsättning: 4 500 000\nAktiekapital: 50 000\nVerkst dir: Töre Högberg\nInköpschef: Rune Pettersson\n\nVerkstadschef: Torulf Högberg\nEtableringsår: 1956\nOmbildat till aktiebolag 1970.\n\nKISA SMIDE &amp; SVETS, AB\n\nPnr 590 40\n\nKisa, Kölefors. Tel 0494-100 96.\nBankgiro 550-9435. Postgiro\n125280-8\n\nVerksamhet: Byggnads- o\nlantbruks-smide. Värme o sanitet\nAntal anställda: 17\nÅrsomsättning: 500 000\nAktiekapital: 20 000\nStyrelse: Verkmäst Birger Larsson\n(ordf), ing Gunnar Melander\nVerkst dir: Ing G Melander\nVeikmäst: Birger Larsson\nEtableringsår: 1967.\n\nJOH\n\nJOHANSON INGENJURSBYRÅ\nAB, FOLKE\n\nPnr 103 13\n\nStockholm 2, Box 2107. Tyska\nBrinken 28. Tel 08-14 23 60.\nBankgiro 74-7060. Postgiro 653884\nVerksamhet: Konsulterande inom\nkraft, belysning, teleteknik,\nhögspänning, hissar o\ntransportanläggningar\n\nAntal anställda: 80\nÅrsomsättning: 5 500 000\nAktiekapital: 50 000\nVerkst dir: Folke Johanson\nEtableringsår: 1961.\n\nJOHANSON INGENJURSBYRÅ\nI UMEÅ AB, FOLKE\n\nPnr 902 44\n\nUmeå, Storg 20 A. Tel 090-13 2140.\nBankgiro 747-1345. Postgiro\n157173-6\n\nVerksamhet: Elkonsulter. Utför\nelektr konstruktioner\nAntal anställda: 12\nVerkst din Ing Bernth Hellman\nEtableringsår: 1963.\n\nJOHANSSON FISKEXPORT,\nAB FREDR\n\nPnr 414 58\n\nGöteborg, Fiskhamnen. Tel\n031-14 90 00. Bankgiro 512-7360.\nPostgiro 42690-8. Tga Fred\nVerksamhet: Grosshandel i färsk\nfisk o sill\nAntal anställda: 4\nÅrsomsättning: 500 000\nAktiekapital: 30 000\nChef: Erik Jarlevik\nEtableringsår: 1875.\n\nCEDERBERG &amp; CO, GÖSTA\n\nPnr 59101\n\nMotala 1, Box 27. Tel 0141-702 20,\n70221. Bankgiro 821-9651.\nPostgiro 272217-1\n\nVerksamhet: Tillverkar\nthermo-plastartiklar. Specialitet: kammar\no blomkrukor. Legoarbeten för\nindustrin upp till 500 gram\nVarunamn: Gececo\nEtableringsår: 1950.\n\nNÄSSILS LJUSSKYLTAR AB\n\nPnr 172 34\n\nSundbyberg, Vegag 7. Tel\n08-28 26 90. Bankgiro 568-1200.\nPostgiro 254455-9. Tga Nassilco\nVerksamhet: Tillverkar plast- o\nneonskyltar\nAntal anställda: 32\nÅrsomsättning: 3 500 000\nAktiekapital: 250 000\nVerkst dir: Bertil Nässil.\n\nNÄSSJÖ BILHALL, AB\n\nPnr 571 00\n\nNässjö, Storg 1. Tel 0380-13040\nVerksamhet: Säljer o reparerar\nVolvo personbilar o lastbilar\nAntal anställda: 97\nÅrsomsättning: 22 000 000\nAktiekapital: 100500\nVerkst dir: Gunnar Lind\nEtableringsår: 1936.\n\nARBOGA BRYGGERI AB\n\nPnr 732 00\n\nArboga, Box 73. Tel 0589-138 60.\nBankgiro 809-8063. Postgiro 636-0\nVerksamhet: Tillverkar o säljer\nmalfc- o läskedrycker\nAntal anställda: 110\nAktiekapital: 800 000\nVerkst dir: Lars Anderson\nEtableringsår: 1899.\n\nHAL\n\n110 60. Bankgiro 477-3123.\nPostgiro 56407-0\n\nVerksamhet: Rostfria plåtarbeten,\nsamt vagnar av skilda slag\nAntal anställda: 65\nÅrsomsättning: 5 000 000\nAktiekapital: 225 000\nVerkst dir: Pabr Ola Hallin\nEtableringsår: 1922.\n\nFJÄRÄSGNEJS, AB\n\nPnr 41303\n\nGöteborg, Första Långg 13 B. Tel\n031-14 64 23. Bankgiro 51-2774.\nPostgiro 41632\n\nVerksamhet: Säljer byggnadssten\nAntal anstäUda: 10\nÅrsomsättning: 1000 000\nAktiekapital: 15 000\nVerkst dir: Leif Andersson\nEtableringsår: 1929.\n\nGYLLANDER &amp; CREUTZ AB\n\nPnr 24100\n\nEslöv, Per Håkanssons v 20. Tel\n0413-160 35. Bankgiro 651-5357.\nPostgiro 535839-5\nVerksamhet: Mek verkstad\nAntal anställda: 50\nAktiekapital: 80 000\nVerkst dir: Fabr Gösta Gyllander\nEtableringsår: 1958.\n\nGYLLENBERG&amp; ROSEN.\nGREN, AB\n\nPnr 104 30\n\nStockholm 45, Rådmansg 56. Box\n45156. Tel 08-30 60 22, 30 05 22.\nBankgiro 446-9409. Postgiro\n3457-9. Tga Gyrosuret\nVerksamhet: Armbandsur,\nväckar-ur o köksur\nAntal anställda: 13\nÅrsomsättning: 1200 000\nAktiekapital: 100 000\nVerkst dir: Ake Rosengren\nEtableringsår: 1858.\n\nGYLLENHAMMAR &amp; CO AB,\nEINAR\n\nPnr 113 59\n\nStockholm, Tegnérlunden 14. Tel\n08-23 5140. Bankgiro 167-0561.\nPostgiro 50095-9. Tga Egyl\nVerksamhet: Engrosförsäljmng av\njärnmanufaktur, verktyg. Sport- o\nträdgårdsartiklar\nAntal anstäUda: 20\nAktiekapital: 100 000\nVerkst dir: H Erik Jurëhn\nEtableringsår: 1926.\n\nRAGNA AB\n\nPnr 183 02\n\nTäby 2, Box 2066, Raka v 6. Tel\n08-758 73 40. Postgiro 151518-8.\nTga Ratrade, Stockholm\nVerksamhet: Textil i parti\nAktiekapital: 5 000\nVerkst dir: E Ragnar Ågren\nEtableringsår: 1936.",
    "structured": {
        "1": {
            "company_name": "JOHNCKES I ÅTVIDABERG AB",
            "address": "Åtvidaberg, Prästängsv 1",
            "phone_number": "0120-120 00",
            "bank_details": {
                "bankgiro": "120-6895",
                "postgiro": "445769-3"
            },
            "activity": "Lejdverkstad med reservdels lager för Volvo",
            "employees": 21,
            "annual_turnover": 1400000,
            "capital": 70000,
            "key_personnel": [
                {
                    "name": "Lennart Jöhncke",
                    "position": "Veikst dir"
                }
            ],
            "establishment_year": 1953
        },
        "2": {
            "company_name": "KIRUNA BYGGNADSSMIDE AB",
            "address": "Kiruna, Lastv 14",
            "phone_number": "0980-187 10",
            "bank_details": {
                "bankgiro": "37-0202",
                "postgiro": "67786-4"
            },
            "activity": "Tillverkar bredfläns-balkar o utför grovplåtslageri, smi-desarbeten samt licenssvetsning",
            "employees": 70,
            "annual_turnover": 4500000,
            "capital": 50000,
            "key_personnel": [
                {
                    "name": "Töre Högberg",
                    "position": "Verkst dir"
                },
                {
                    "name": "Rune Pettersson",
                    "position": "Inköpschef"
                },
                {
                    "name": "Torulf Högberg",
                    "position": "Verkstadschef"
                }
            ],
            "establishment_year": 1956
        },
        "3": {
            "company_name": "KISA SMIDE & SVETS, AB",
            "address": "Kisa, Kölefors",
            "phone_number": "0494-100 96",
            "bank_details": {
                "bankgiro": "550-9435",
                "postgiro": "125280-8"
            },
            "activity": "Byggnads- o lantbruks-smide. Värme o sanitet",
            "employees": 17,
            "annual_turnover": 500000,
            "capital": 20000,
            "key_personnel": [
                {
                    "name": "Verkmäst Birger Larsson",
                    "position": "Styrelse: Verkmäst"
                },
                {
                    "name": "ing Gunnar Melander",
                    "position": "Styrelse: ing"
                },
                {
                    "name": "Ing G Melander",
                    "position": "Verkst dir"
                },
                {
                    "name": "Birger Larsson",
                    "position": "Veikmäst"
                }
            ],
            "establishment_year": 1967
        },
        "4": {
            "company_name": "JOHANSON INGENJURSBYRÅ AB, FOLKE",
            "address": "Stockholm 2, Box 2107, Tyska Brinken 28",
            "phone_number": "08-14 23 60",
            "bank_details": {
                "bankgiro": "74-7060",
                "postgiro": "653884"
            },
            "activity": "Konsulterande inom kraft, belysning, teleteknik, högspänning, hissar o transportanläggningar",
            "employees": 80,
            "annual_turnover": 5500000,
            "capital": 50000,
            "key_personnel": [
                {
                    "name": "Folke Johanson",
                    "position": "Verkst dir"
                }
            ],
            "establishment_year": 1961
        },
        "5": {
            "company_name": "JOHANSSON INGENJURSBYRÅ I UMEÅ AB, FOLKE",
            "address": "Umeå, Storg 20 A",
            "phone_number": "090-13 2140",
            "bank_details": {
                "bankgiro": "747-1345",
                "postgiro": "157173-6"
            },
            "activity": "Elkonsulter. Utför elektr konstruktioner",
            "employees": 12,
            "key_personnel": [
                {
                    "name": "Ing Bernth Hellman",
                    "position": "Verkst dir"
                }
            ],
            "establishment_year": 1963
        },
        "6": {
            "company_name": "JOHANSSON FISKEXPORT, AB FREDR",
            "address": "Göteborg, Fiskhamnen",
            "phone_number": "031-14 90 00",
            "bank_details": {
                "bankgiro": "512-7360",
                "postgiro": "42690-8"
            },
            "activity": "Grosshandel i färsk fisk o sill",
            "employees": 4,
            "annual_turnover": 500000,
            "capital": 30000,
            "key_personnel": [
                {
                    "name": "Erik Jarlevik",
                    "position": "Chef"
                }
            ],
            "establishment_year": 1875
        },
        "7": {
            "company_name": "CEDERBERG & CO, GÖSTA",
            "address": "Motala 1, Box 27",
            "phone_number": "0141-702 20, 70221",
            "bank_details": {
                "bankgiro": "821-9651",
                "postgiro": "272217-1"
            },
            "activity": "Tillverkar thermo-plastartiklar. Specialitet: kammar o blomkrukor. Legoarbeten för industrin upp till 500 gram",
            "establishment_year": 1950
        },
        "8": {
            "company_name": "NÄSSILS LJUSSKYLTAR AB",
            "address": "Sundbyberg, Vegag 7",
            "phone_number": "08-28 26 90",
            "bank_details": {
                "bankgiro": "568-1200",
                "postgiro": "254455-9"
            },
            "activity": "Tillverkar plast- o neonskyltar",
            "employees": 32,
            "annual_turnover": 3500000,
            "capital": 250000,
            "key_personnel": [
                {
                    "name": "Bertil Nässil",
                    "position": "Verkst dir"
                }
            ],
            "establishment_year": null
        },
        "9": {
            "company_name": "NÄSSJÖ BILHALL, AB",
            "address": "Nässjö, Storg 1",
            "phone_number": "0380-13040",
            "activity": "Säljer o reparerar Volvo personbilar o lastbilar",
            "employees": 97,
            "annual_turnover": 22000000,
            "capital": 100500,
            "key_personnel": [
                {
                    "name": "Gunnar Lind",
                    "position": "Verkst dir"
                }
            ],
            "establishment_year": 1936
        },
        "10": {
            "company_name": "ARBOGA BRYGGERI AB",
            "address": "Arboga, Box 73",
            "phone_number": "0589-138 60",
            "bank_details": {
                "bankgiro": "809-8063",
                "postgiro": "636-0"
            },
            "activity": "Tillverkar o säljer malfc- o läskedrycker",
            "employees": 110,
            "capital": 800000,
            "key_personnel": [
                {
                    "name": "Lars Anderson",
                    "position": "Verkst dir"
                }
            ],
            "establishment_year": 1899
        },
        "11": {
            "company_name": "HAL",
            "address": null,
            "phone_number": "0140-110 60",
            "bank_details": {
                "bankgiro": "477-3123",
                "postgiro": "56407-0"
            },
            "activity": "Rostfria plåtarbeten, samt vagnar av skilda slag",
            "employees": 65,
            "annual_turnover": 5000000,
            "capital": 225000,
            "key_personnel": [
                {
                    "name": "Pabr Ola Hallin",
                    "position": "Verkst dir"
                }
            ],
            "establishment_year": 1922
        },
        "12": {
            "company_name": "FJÄRÄSGNEJS, AB",
            "address": "Göteborg, Första Långg 13 B",
            "phone_number": "031-14 64 23",
            "bank_details": {
                "bankgiro": "51-2774",
                "postgiro": "41632"
            },
            "activity": "Säljer byggnadssten",
            "employees": 10,
            "annual_turnover": 1000000,
            "capital": 15000,
            "key_personnel": [
                {
                    "name": "Leif Andersson",
                    "position": "Verkst dir"
                }
            ],
            "establishment_year": 1929
        },
        "13": {
            "company_name": "GYLLANDER & CREUTZ AB",
            "address": "Eslöv, Per Håkanssons v 20",
            "phone_number": "0413-160 35",
            "bank_details": {
                "bankgiro": "651-5357",
                "postgiro": "535839-5"
            },
            "activity": "Mek verkstad",
            "employees": 50,
            "capital": 80000,
            "key_personnel": [
                {
                    "name": "Fabr Gösta Gyllander",
                    "position": "Verkst dir"
                }
            ],
            "establishment_year": 1958
        },
        "14": {
            "company_name": "GYLLENBERG & ROSEN. GREN, AB",
            "address": "Stockholm 45, Rådmansg 56, Box 45156",
            "phone_number": "08-30 60 22, 30 05 22",
            "bank_details": {
                "bankgiro": "446-9409",
                "postgiro": "3457-9"
            },
            "activity": "Armbandsur, väckar-ur o köksur",
            "employees": 13,
            "annual_turnover": 1200000,
            "capital": 100000,
            "key_personnel": [
                {
                    "name": "Ake Rosengren",
                    "position": "Verkst dir"
                }
            ],
            "establishment_year": 1858
        },
        "15": {
            "company_name": "GYLLENHAMMAR & CO AB, EINAR",
            "address": "Stockholm, Tegnérlunden 14",
            "phone_number": "08-23 5140",
            "bank_details": {
                "bankgiro": "167-0561",
                "postgiro": "50095-9"
            },
            "activity": "Engrosförsäljmng av järnmanufaktur, verktyg. Sport- o trädgårdsartiklar",
            "employees": 20,
            "capital": 100000,
            "key_personnel": [
                {
                    "name": "H Erik Jurëhn",
                    "position": "Verkst dir"
                }
            ],
            "establishment_year": 1926
        },
        "16": {
            "company_name": "RAGNA AB",
            "address": "Täby 2, Box 2066, Raka v 6",
            "phone_number": "08-758 73 40",
            "postgiro": "151518-8",
            "activity": "Textil i parti",
            "capital": 5000,
            "key_personnel": [
                {
                    "name": "E Ragnar Ågren",
                    "position": "Verkst dir"
                }
            ],
            "establishment_year": 1936
        }
    }
}