{
    "original": "ERICSON, AB IVAR\n\nPnr 550 07\n\nJönköping 7, Box 7008. Gräshagsg\n13. Tel 036-1187 55. Bankgiro 83-\n\n5694. Postgiro 9843. Tga\nIvarericson. Telex 70170\nVerksamhet: Grosshandel, import\no export av artiklar för trä- o\nmöbelindustrin samt artiklar för\nstoppmöbelindustrin\nAktiekapital: 200 000\nVerkst dir: Ake Ericson\nFörsäljn-chef: Egil Berggren\nEtableringsår: 1917.\n\nLID\n\nAvdelningskontor: 112 24 Stockholm,\nParmmätarg 5. Tel 08-54 34 35,\n53 88 38\n\nAntal anställda: 20\nÅrsomsättning: 4 000 000\nAktiekapital: 120 000\nVerkst dir: K A Levin\nEtableringsår: 1953.\n\nFEDERATIV, TRYCKERI AB\n\nPnr 113 50\n\nStockholm, Sveav 98. Tel\n08-34 35 14, 34 35 16. Bankgiro\n730-4413. Postgiro 1485-2\nVerksamhet: Civil- o\ntidningstryckeri. Utger tidningen Arbetaren\nAntal anställda: 55\nÅrsomsättning: 3 000 000\nAktiekapital: 300 000\nVerkst din Yngve Carlsson\nEtableringsår: 1921.\n\nFÄRDIGHUS, AB\n\nPnr 114 24\n\nStockholm, Odeng 15. Tel 08-\n\n24 73 55\n\nVerksamhet: Tillverkar\nmonteringsfärdiga byggnader\nAntal anställda: 5\nÅrsomsättning: 6 000 000\nAktiekapital: 400 000\nVërkst dir: Sven Thorin\nEtableringsår: 1967.\n\nHAM\n\nAktiekapital: 200 000\nVerkst dir: Lars Hammar\nEtableringsår: 1916\nOmbildat till aktiebolag 1960.\n\nHAMMAR &amp; CO, AB AN T\n\nPnr 820 76\n\nJättendal. Tel 0652-160 15, 160 25.\nBankgiro 78-7020. Postgiro 31375.\nTga Hammarbolag\nVerksamhet: Säljer saltströmming,\no fiskredskap i parti\nAntal anställda: 8\nAktiekapital: 60 000\nVerkst dir; Gunnar Högdahl\nEtableringsår: 1900\nOmbildat till aktiebolag 1946.\n\nHAMMAR, AB C M\n\nPnr 40311\n\nGöteborg 2, Box 2025. Bryggareg 3.\nTel 031-17 1150. Bankgiro\n511-4756. Postgiro 45907-3.\nTelex 20948\n\nVeiksamhet: Plåtslageri,\nmetallvarufabrik. Kompasser, lanternor,\ngyrokompasser, loggar, kronometrar,\norderhögtalare,\nunderhållningsanläggningar o centralantenner för\nfartyg, uppblåsbara livbåtar,\nlivvästar o oljeläns or,\nräddningssäckar\n\nVarunamn: Amplidan, Brown, Golay,\nRFD-GQ\n\nAktiekapital: 60 000\nVerkst dir: Torild Hammar\nEtableringsår: 1856\nOmbildat till aktiebolag 1960.\n\nHAMMAR &amp; CO, TRANSPORT\nAB F\n\nPnr 301 04\n\nHalmstad 1, Kaptensg 5. Box 213.\nTel 035-11 8710. Bankgiro 15-3363.\nPostgiro 14837. Tga Carlhammar\nVerksamhet: Spedition, transporter\no omlastningar\nAktiekapital: 10 000\nStyrelseordf: Dir Gösta Samuelsson\nChef: Disp Walter Karlsson\nEtableringsår: 1864.\n\nBJÖRKLUND &amp; VEDIN, AB\n\nPnr 104 32\n\nStockholm 19, Rehnsg 18. Box\n19054. Tel 08-24 02 10. Bankgiro\n48-2073. Postgiro 151034-6\nVerksamhet: Rörentreprenader\nAntal anställda: 600\nÅrsomsättning: 70 000 000\n\nAktiekapital: 600000\nVerkst dir: Torsten Björklund\nEtableringsår: 1936.\n\nBJÖRKLUND &amp;\nWINGQVIST AB\n\nPnr 104 22\n\nStockholm 22, Box 22075. Tel\n08-52 07 00. Bankgiro 734-0854.\nPostgiro 3055-1. Tga Wingtapet\nVerksamhet: Säljer tapeter i parti\no detalj\n\nButik: Stockholm,\nKungsholms-torg 10\n\nAntal anställda: 35\nAktiekapital: 161200\nVerkst dir: Sten Dahlner.\n\nBJÖRKLUNDS BYGGNADS AB,\nERIK\n\nPnr 652 21\n\nKarlstad, Orkang 2. Tel\n054-18 70 70. Bankgiro 691-9724.\nPostgiro 643270-2\n\nVerksamhet: Uppför byggnader.\nSpecialitet: serviceanläggningar\nför bilvård\nAntal anställda: 45\nÅrsomsättning: 4 000 000\nAktiekapital: 50 000\nStyrelse: Byggmäst Erik\nBjörklund, fru Gunborg Björklund,\nrevisor Bertil Oom\nInköp: Ing Rolf Lindström\nKalkyler: Ing Leif Andersson\nKamrer: Fru Valborg Niklasson\nEtableringsår: 1964.\n\nBJÖRKLUND I\nGÖTEBORG AB, G\n\nPnr 411 25\n\nGoteborg, Viktoriag 16. Tel\n031-17 77 20. Bankgiro 652-3609.\nPostgiro 527310-7\n\nVerksamhet: Redovisningsbyrå\n\nAntal anställda: 18\n\nÄgare o chef: Revisor SRS Jan\n\nJonason\n\nEtableringsår: 1953.\n\nCAPRI, AGENTURFIRMAN\n\nPnr 212 14\n\nMalmö, Industrig 14-18. Tel\n040-18 04 3 0. Bankgiro 643-0086.\nPostgiro 245621-8. Tga Capri.\nTelex 32378 CAPRI S\nVerksamhet: Säljer plastfolier o\nvävplast, plastprofiler o skumplast,\nPVC-filt-matta, nålfiltmatta\nVarunamn: Acella, Benelit, Bocato,\nRoy Air\n\nAntal anställda: 12\nÅrsomsättning: 5 000 000\nÄgare o chef: Ing Gunnar\nMårtenson\n\nEtableringsår: 1946.\n\nRAG\n\nR\n\nR och T:s SPORTTRIKÄ\n\nPnr 520 10\n\nGällstad, Ängabo. Tel 0321-220 1 5.\nBankgiro 84-0605. Postgiro 546018\nVerksamhet: Specialitet:\nishockeydamasker o tröjor,\nfotbollsstrumpor, tennissockor, herrstrumpor\nAntal anställda: 15\nÄgare: Töre Berglund\nEtableringsår: 1961.\n\nSJÖGREN, AB IVAR\n\nPnr 10251\n\nStockholm 27, Box 27056. Kontor:\nKarlav 84. Lager o verkstad:\nVär-tav 4. Tel 08-605178, 605389.\nPostgiro 57999-5\n\nVerksamhet: Säljer oljeaggregat o\ntillbehör. Installationer o service\nAntal anställda: 9\nÅrsomsättning: 1500 000\nAktiekapital: 5 000\nEtableringsår: 1965.\n\nSWÄRDHS VVS-BYRÅ AB\n\nPnr 30238\n\nHalmstad, Fiskareg 10. Tel\n035-1002 70. Bankgiro 147-0781.\nPostgiro 324663-4\n\nVerksamhet: Konsulterande\ningenjörsbyrå\n\nAntal anställda: 8\nÅrsomsättning: 175 000\nAktiekapital: 5 000\nVerkst dir: Ing Kjell Swärdh\nEtableringsår 1960.",
    "structured": {
        "1": {
            "company_name": "ERICSON, AB IVAR",
            "pnr": "550 07",
            "address": "Jönköping 7, Box 7008. Gräshagsg 13",
            "phone_number": "036-1187 55",
            "bank_details": {
                "bankgiro": "83-5694",
                "postgiro": "9843"
            },
            "activity": "Grosshandel, import o export av artiklar för trä- o möbelindustrin samt artiklar för stoppmöbelindustrin",
            "capital": 200000,
            "key_personnel": [
                {
                    "name": "Ake Ericson",
                    "position": "Verkst dir"
                },
                {
                    "name": "Egil Berggren",
                    "position": "Försäljn-chef"
                }
            ],
            "establishment_year": 1917
        },
        "2": {
            "company_name": "LID",
            "address": "Avdelningskontor: 112 24 Stockholm, Parmmätarg 5",
            "phone_number": "08-54 34 35, 53 88 38",
            "employees": 20,
            "annual_turnover": 4000000,
            "capital": 120000,
            "key_personnel": [
                {
                    "name": "K A Levin",
                    "position": "Verkst dir"
                }
            ],
            "establishment_year": 1953
        },
        "3": {
            "company_name": "FEDERATIV, TRYCKERI AB",
            "pnr": "113 50",
            "address": "Stockholm, Sveav 98",
            "phone_number": "08-34 35 14, 34 35 16",
            "bank_details": {
                "bankgiro": "730-4413",
                "postgiro": "1485-2"
            },
            "activity": "Civil- o tidningstryckeri. Utger tidningen Arbetaren",
            "employees": 55,
            "annual_turnover": 3000000,
            "capital": 300000,
            "key_personnel": [
                {
                    "name": "Yngve Carlsson",
                    "position": "Verkst dir"
                }
            ],
            "establishment_year": 1921
        },
        "4": {
            "company_name": "FÄRDIGHUS, AB",
            "pnr": "114 24",
            "address": "Stockholm, Odeng 15",
            "phone_number": "08-24 73 55",
            "activity": "Tillverkar monteringsfärdiga byggnader",
            "employees": 5,
            "annual_turnover": 6000000,
            "capital": 400000,
            "key_personnel": [
                {
                    "name": "Sven Thorin",
                    "position": "Verkst dir"
                }
            ],
            "establishment_year": 1967
        },
        "5": {
            "company_name": "HAM",
            "capital": 200000,
            "key_personnel": [
                {
                    "name": "Lars Hammar",
                    "position": "Verkst dir"
                }
            ],
            "establishment_year": 1916
        },
        "6": {
            "company_name": "HAMMAR & CO, AB AN T",
            "pnr": "820 76",
            "address": "Jättendal",
            "phone_number": "0652-160 15, 160 25",
            "bank_details": {
                "bankgiro": "78-7020",
                "postgiro": "31375"
            },
            "activity": "Säljer saltströmming, o fiskredskap i parti",
            "employees": 8,
            "capital": 60000,
            "key_personnel": [
                {
                    "name": "Gunnar Högdahl",
                    "position": "Verkst dir"
                }
            ],
            "establishment_year": 1900
        },
        "7": {
            "company_name": "HAMMAR, AB C M",
            "pnr": "40311",
            "address": "Göteborg 2, Box 2025. Bryggareg 3",
            "phone_number": "031-17 1150",
            "bank_details": {
                "bankgiro": "511-4756",
                "postgiro": "45907-3"
            },
            "activity": "Plåtslageri, metallvarufabrik. Kompasser, lanternor, gyrokompasser, loggar, kronometrar, orderhögtalare, underhållningsanläggningar o centralantenner för fartyg, uppblåsbara livbåtar, livvästar o oljeläns or, räddningssäckar",
            "employees": 0,
            "capital": 60000,
            "key_personnel": [
                {
                    "name": "Torild Hammar",
                    "position": "Verkst dir"
                }
            ],
            "establishment_year": 1856
        },
        "8": {
            "company_name": "HAMMAR & CO, TRANSPORT AB F",
            "pnr": "301 04",
            "address": "Halmstad 1, Kaptensg 5. Box 213",
            "phone_number": "035-11 8710",
            "bank_details": {
                "bankgiro": "15-3363",
                "postgiro": "14837"
            },
            "activity": "Spedition, transporter o omlastningar",
            "capital": 10000,
            "key_personnel": [
                {
                    "name": "Dir Gösta Samuelsson",
                    "position": "Styrelseordf"
                },
                {
                    "name": "Walter Karlsson",
                    "position": "Chef: Disp"
                }
            ],
            "establishment_year": 1864
        },
        "9": {
            "company_name": "BJÖRKLUND & VEDIN, AB",
            "pnr": "104 32",
            "address": "Stockholm 19, Rehnsg 18. Box 19054",
            "phone_number": "08-24 02 10",
            "bank_details": {
                "bankgiro": "48-2073",
                "postgiro": "151034-6"
            },
            "activity": "Rörentreprenader",
            "employees": 600,
            "annual_turnover": 70000000,
            "capital": 600000,
            "key_personnel": [
                {
                    "name": "Torsten Björklund",
                    "position": "Verkst dir"
                }
            ],
            "establishment_year": 1936
        },
        "10": {
            "company_name": "BJÖRKLUND & WINGQVIST AB",
            "pnr": "104 22",
            "address": "Stockholm 22, Box 22075",
            "phone_number": "08-52 07 00",
            "bank_details": {
                "bankgiro": "734-0854",
                "postgiro": "3055-1"
            },
            "activity": "Säljer tapeter i parti o detalj",
            "employees": 35,
            "capital": 161200,
            "key_personnel": [
                {
                    "name": "Sten Dahlner",
                    "position": "Verkst dir"
                }
            ],
            "establishment_year": 0
        },
        "11": {
            "company_name": "BJÖRKLUNDS BYGGNADS AB, ERIK",
            "pnr": "652 21",
            "address": "Karlstad, Orkang 2",
            "phone_number": "054-18 70 70",
            "bank_details": {
                "bankgiro": "691-9724",
                "postgiro": "643270-2"
            },
            "activity": "Uppför byggnader. Specialitet: serviceanläggningar för bilvård",
            "employees": 45,
            "annual_turnover": 4000000,
            "capital": 50000,
            "key_personnel": [
                {
                    "name": "Byggmäst Erik Björklund",
                    "position": "Styrelse"
                },
                {
                    "name": "fru Gunborg Björklund",
                    "position": "Styrelse"
                },
                {
                    "name": "Bertil Oom",
                    "position": "Revisor"
                },
                {
                    "name": "Rolf Lindström",
                    "position": "Inköp"
                },
                {
                    "name": "Leif Andersson",
                    "position": "Kalkyler"
                },
                {
                    "name": "Valborg Niklasson",
                    "position": "Kamrer"
                }
            ],
            "establishment_year": 1964
        },
        "12": {
            "company_name": "BJÖRKLUND I GÖTEBORG AB, G",
            "pnr": "411 25",
            "address": "Goteborg, Viktoriag 16",
            "phone_number": "031-17 77 20",
            "bank_details": {
                "bankgiro": "652-3609",
                "postgiro": "527310-7"
            },
            "activity": "Redovisningsbyrå",
            "employees": 18,
            "key_personnel": [
                {
                    "name": "Jan Jonason",
                    "position": "Ägare o chef: Revisor SRS"
                }
            ],
            "establishment_year": 1953
        },
        "13": {
            "company_name": "CAPRI, AGENTURFIRMAN",
            "pnr": "212 14",
            "address": "Malmö, Industrig 14-18",
            "phone_number": "040-18 04 3 0",
            "bank_details": {
                "bankgiro": "643-0086",
                "postgiro": "245621-8"
            },
            "activity": "Säljer plastfolier o vävplast, plastprofiler o skumplast, PVC-filt-matta, nålfiltmatta",
            "employees": 12,
            "annual_turnover": 5000000,
            "key_personnel": [
                {
                    "name": "Gunnar Mårtenson",
                    "position": "Ägare o chef"
                }
            ],
            "establishment_year": 1946
        },
        "14": {
            "company_name": "RAG R R och T:s SPORTTRIKÄ",
            "pnr": "520 10",
            "address": "Gällstad, Ängabo",
            "phone_number": "0321-220 1 5",
            "bank_details": {
                "bankgiro": "84-0605",
                "postgiro": "546018"
            },
            "activity": "Specialitet: ishockeydamasker o tröjor, fotbollsstrumpor, tennissockor, herrstrumpor",
            "employees": 15,
            "key_personnel": [
                {
                    "name": "Töre Berglund",
                    "position": "Ägare"
                }
            ],
            "establishment_year": 1961
        },
        "15": {
            "company_name": "SJÖGREN, AB IVAR",
            "pnr": "10251",
            "address": "Stockholm 27, Box 27056. Kontor: Karlav 84. Lager o verkstad: Värtav 4",
            "phone_number": "08-605178, 605389",
            "postgiro": "57999-5",
            "activity": "Säljer oljeaggregat o tillbehör. Installationer o service",
            "employees": 9,
            "annual_turnover": 1500000,
            "capital": 5000,
            "establishment_year": 1965
        },
        "16": {
            "company_name": "SWÄRDHS VVS-BYRÅ AB",
            "pnr": "30238",
            "address": "Halmstad, Fiskareg 10",
            "phone_number": "035-1002 70",
            "bank_details": {
                "bankgiro": "147-0781",
                "postgiro": "324663-4"
            },
            "activity": "Konsulterande ingenjörsbyrå",
            "employees": 8,
            "annual_turnover": 175000,
            "capital": 5000,
            "key_personnel": [
                {
                    "name": "Kjell Swärdh",
                    "position": "Verkst dir"
                }
            ],
            "establishment_year": 1960
        }
    }
}