{
    "original": "BERJOBOLAGET\n\nPnr 500 07\n\nBorås 7, Getängsv 28. Box 1713.\nTel 033-13 00 20, 13 81 40. Bankgiro\n84-3666. Postgiro 291274\nVerksamhet: Tillverkar solur,\nvindflöjlar o inredningsartiklar,\nindustri- o byggmaterial engros\nChef: Bertil Jogner\nEtableringsår: 1946.\n\nJUNGERS VERKSTADS AB\n\nPnr 414 74\n\nGöteborg, Fotög 2-4. Tel\n031-1247 50. Telex 20979. Tga Juvab\nVerksamhet: Tillverkar\nautomatmaskiner för glasbruk o\nglasslipe-rier samt anläggningar för\nmineralullstillverkning, specialmaskiner, maskinrenoveringar\nAntal anställda: 125\nAktiekapital: 250 000\nStyrelse: Dir Torsten Lilja (ordf),\ndir Arne Hedelius, dir Ake Mark,\nbankdir Bengt Widén, dir Magnus\nLagercrantz, dir Eivind Eidering\nVerkst dir: Arne Hedelius\nEtableringsår: 1947.\n\nBÄCKMAN, AB BRÖDERNA\n\nPnr 430 50\n\nKållered. Tel 031-75 0495.\nBankgiro 441-1153. Postgiro 424760-7\nVerksamhet: Tillverkar o säljer\nångpannor, hetvattenpannor,\nhetvattencentraler, portabla\nVarunamn: Bassöe\nÅrsomsättning: 7 000 000\nAktiekapital: 60 000\nVerkst dir. Ingemar Bäckman\nEtableringsår: 1947\nOmbildat till aktiebolag 1961.\n\nBÄCKMANS VERKSTÄDER, AB\n\nPnr 602 28\n\nNorrköping, Exportg 12. Tel\n011-12 1126, 12 5126. Bankgiro\n125-0380. Postgiro 76044-7\nVerksamhet: Järn- o\nstålkonstruktioner, maskiner o verktyg\nAntal anställda: 20\nAktiekapital: 60000\nVerkst dir: Gust Bäckman\nEtableringsår: 1903\nOmbildat till aktiebolag 1940.\n\nBÄCKMAN, AB ARNE\n\nPnr 682 00\n\nFilipstad, Industrig. Tel\n0590-125 45. Bankgiro 81-8705.\nPostgiro 163088\n\nVerksamhet: Plåtslageri o mek\nverkstad. Tillverkar ytrensmaskiner\nsåsom slungrensmaskiner,\nblästerapparater o - anläggningar.\nPlåt- o stålkonstruktioner. Utför\nmontage- o reparationsarbeten.\nLicenssvetsning. Legoarbeten\n.Antal anställda: 110\nÅrsomsättning: 10 000 000\nAktiekapital: 210 000\nVerkst dir: Arne Bäckman\nEtableringsår 1939.\n\nLAK\n\nPostgiro 153771. Telex 10363. Tga\nLagcrantz\n\nVerksamhet: Säljer elektrotekniska\nlaboratorieinstrument,\nradiokommunikationsanläggningar, elektroniska\nkomponenter\n\nVarunamn: Amphenol, Analogie,\nBell &amp; Howell, Borg-Warner,\nCho-merics, Collins, Du Mont, Esterline\nAngus, Peedback Ltd, Flight\nRe-fuelling, Frederick Electronies Co,\nGeneral Radio, Indiana General,\nKnott Elektronik, National, OAK\nElectro-Netics, Pye\nTelecommuni-cations, Texscan Corporation,\nUnion Carbide-Kemet\nAntal anställda: 30\nFirmatecknare: Ing Ulf Clementz\nEtableringsår: 1938.\n\nBLEKINGE ÅNGBÅTS AB\n\nPnr 292 00\n\nKarlshamn, Box 81. Drottningg 40.\nTel 0454-100 34, 102 75. Bankgiro\n86-2157. Postgiro 71350. Telex\n4562\n\nVerksamhet: Rederirörelse\nAktiekapital: 390 000\nVerkst dir: Fru Ellen Lundström\nEtableringsår: 1878.\n\nBLIDSBERGS MEKANISKA\nVERKSTAD, AB\n\nPnr 520 24\n\nBlidsberg. Tel 0321-311 11.\nBankgiro 84-3327. Postgiro 85027\nVerksamhet: Tillverkar\nförrådsbodar, lagerbyggnader o garage\nAntal anställda: 20\nAktiekapital: 50 000\nVerkst dir: G W Törnqvist\nEtableringsår: 1946.\n\nSVENSSON AB, BOKFORINGS.\n&amp; REVISIONSBYRÅN H\n\nPnr 691 00\n\nKarlskoga, Centralplan 3. Tel\n0586-325 20. Bankgiro 823-3157.\nPostgiro 110559-2\n\nVerksamhet: Bokförings- o\nrevisionsbyrå\n\nÅrsomsättning: 275 000\nAktiekapital: 5 000\nVerkst dir: Henry Svensson\nEtableringsår: 1961.\n\nJOH\n\nJOHANSSON BYGG AB, J A\n\nPnr 93100\n\nSkellefteå, Varvs g 4. Tel\n0910-105 60, 11060. Bankgiro 611-6735.\nPostgiro 66764-2\n\nVerksamhet: Bostads-, affärs-,\nindustri- o förvaltningsbyggnader\nAntal anställda: 100\nÅrsomsättning: 5 000 000\nAktiekapital: 80 000\nVerkst dir: Byggm K Ingvar A\nJohansson\nEtableringsår: 1946.\n\nWICO TEXTIL AB\n\nPnr 100 72\n\nStockholm 43, Liljeholmsv 8. Box\n43019. Tel 08-45 35 05, 45 95 05. Tga\nWicotextil. Telex 17765 WICO S\n\nVerksamhet: Grossister i\ndamytter-trikå.\n\nVICTORIA. FABRIKS AB\n\nPnr 250 11\n\nHelsingborg 11, Box 11043.\nVicto-riag 6. Tel 042-1202 20. Bankgiro\n65-3004. Postgiro 5052. Tga\nVictoria\n\nVerksamhet: Tillverkar o säljer\nhushålls- o bagerimargarin,\nmarzi-pan o tvål\n\nAntal anställda: 105\nAktiekapital: 1500 000\nVerkst dir: Gert Mankert\nEtableringsår: 1920.\n\nHAN ST ROM AB, SVEN\n\nPnr 58102\n\nLinköping 1, Box 39. Djurgårdsg 4.\nTel 013-1292 35. Postgiro\n278604-4\n\nVerksamhet: inköp o försäljning av\nmassaved (Export)\nAntal anställda: 20\nÅrsomsättning: 7 000 000\nAktiekapital: 400 000\nVerkst dir: Sven Hanström\nEtableringsår: 1922.\n\nINDUSTRI HYGIEN\n\nPnr 46100\n\nTrollhättan, N Björke. Tel 0520-\n\n23166, 23002. Bankgiro 892-3559.\n\nPostgiro 273806-0\n\nVeiksamhet: Tillverkar babyblöjor\n\no sanitetsbindor\n\nVarunamn: Väni\n\nAntal anställda: 5\n\nChef: NUs Welén.\n\nINDUSTRI &amp; KRAFT.\nBYGGNADS AB\n\nPnr 72216\n\nVästerås, Engelbrektsg 9. Tel\n021-1103 60. Bankgiro 35-6645.\nPostgiro 492207\n\nVerksamhet:\nByggnadsentreprenörer\n\nFüial: 57700 Hultsfred, Oskarsg\n28. Tel 0495-121 40. Chef: Disp\nGustaf Rollborn\nAntal anstäUda: 160\nÅrsomsättning: 12000000\nAktiekapital: 150000\nVerkst dir: Gustav Ahlqvist\nEtableringsår: 1945.\n\nINDUSTRI TEKNISKA\nKONSTRUKTIONER, AB\n\nPnr 123 21\n\nFarsta 1, Box 46. Lysviksg 10.\nTel 08-94 03 1 0. Bankgiro 578-2040.\nPostgiro 551650-5. Tga\nIndust-construct\n\nVerksamhet: Konsulterar o säljer\nprodukter för miljövårdande\nanläggningar inom industriella\nsektorn\n\nAktiekapital: 80 000\nVerkst dir Kjell-Erik Själin\nEtableringsår 1955.\n\nINDUSTRI UNION EUROPA.\nPRODUKTER AB\n\nPnr 412 54\n\nGöteborg, Södra v 91. Tel\n031-20 66 77. Bankgiro 36-2616.\nPostgiro 44310. Tga Euprod\nVerksamhet: Tillverkar hembastun\nSisu. Importerar textilier,\npresent-artiklar, ädla stenar o collier mm,\nspeciellt från Indien\nÅrsomsättning: 200 000\nAktiekapital: 6 000\nVerkst dir: Aldor Emanuelson\nEtableringsår 1952.\n\nINDUSTRI &amp;\nVARVS-MASKINER, AB\n\nPnr 400 10\n\nGöteborg 3, Bellmansg 11. Box\n3042. Tel 031-1148 76, 11 1276.\nBankgiro 630-4455. Postgiro\n243260-7. Tga Shipmachines.\nTelex 21053\n\nVerksamhet: Säljer gjutgods av alla\nslag, perforerad plåt, pressade\nplåtdetaljer, allt i smide, svetsade\nmaskinkonstruktioner, oljefilter,\nventilationshuvar, maskiner etc\nVarunamn: Auto-Klean\nAktiekapital: 5 000\nVerkst dir: Ing Kurt Morén\nEtableringsår: 1948.",
    "structured": {
        "1": {
            "company_name": "BERJOBOLAGET",
            "activity": "Tillverkar solur, vindflöjlar o inredningsartiklar, industri- o byggmaterial engros",
            "establishment_year": 1946
        },
        "2": {
            "company_name": "JUNGERS VERKSTADS AB",
            "pnr": "414 74",
            "address": "Göteborg, Fotög 2-4",
            "phone_number": "031-1247 50",
            "activity": "Tillverkar automatmaskiner för glasbruk o glasslipe-rier samt anläggningar för mineralullstillverkning, specialmaskiner, maskinrenoveringar",
            "employees": 125,
            "capital": 250000,
            "key_personnel": [
                {
                    "name": "Torsten Lilja",
                    "position": "ordf"
                },
                {
                    "name": "Arne Hedelius",
                    "position": "dir"
                },
                {
                    "name": "Ake Mark",
                    "position": "dir"
                },
                {
                    "name": "Bengt Widén",
                    "position": "bankdir"
                },
                {
                    "name": "Magnus Lagercrantz",
                    "position": "dir"
                },
                {
                    "name": "Eivind Eidering",
                    "position": "dir"
                }
            ],
            "establishment_year": 1947
        },
        "3": {
            "company_name": "BÄCKMAN, AB BRÖDERNA",
            "pnr": "430 50",
            "address": "Kållered",
            "phone_number": "031-75 0495",
            "activity": "Tillverkar o säljer ångpannor, hetvattenpannor, hetvattencentraler, portabla",
            "annual_turnover": 7000000,
            "capital": 60000,
            "key_personnel": [
                {
                    "name": "Ingemar Bäckman",
                    "position": "Verkst dir"
                }
            ],
            "establishment_year": 1947
        },
        "4": {
            "company_name": "BÄCKMANS VERKSTÄDER, AB",
            "pnr": "602 28",
            "address": "Norrköping, Exportg 12",
            "phone_number": "011-12 1126, 12 5126",
            "activity": "Järn- o stålkonstruktioner, maskiner o verktyg",
            "employees": 20,
            "capital": 60000,
            "key_personnel": [
                {
                    "name": "Gust Bäckman",
                    "position": "Verkst dir"
                }
            ],
            "establishment_year": 1903
        },
        "5": {
            "company_name": "BÄCKMAN, AB ARNE",
            "pnr": "682 00",
            "address": "Filipstad, Industrig",
            "phone_number": "0590-125 45",
            "bank_details": {
                "bankgiro": "81-8705",
                "postgiro": "163088"
            },
            "activity": "Plåtslageri o mek verkstad. Tillverkar ytrensmaskiner såsom slungrensmaskiner, blästerapparater o - anläggningar. Plåt- o stålkonstruktioner. Utför montage- o reparationsarbeten. Licenssvetsning. Legoarbeten",
            "employees": 110,
            "annual_turnover": 10000000,
            "capital": 210000,
            "key_personnel": [
                {
                    "name": "Arne Bäckman",
                    "position": "Verkst dir"
                }
            ],
            "establishment_year": 1939
        },
        "6": {
            "company_name": "LAK",
            "postgiro": "153771",
            "activity": "Säljer elektrotekniska laboratorieinstrument, radiokommunikationsanläggningar, elektroniska komponenter",
            "key_personnel": {
                "name": "Ing Ulf Clementz",
                "position": "Firmatecknare"
            },
            "establishment_year": 1938
        },
        "7": {
            "company_name": "BLEKINGE ÅNGBÅTS AB",
            "pnr": "292 00",
            "address": "Karlshamn, Box 81. Drottningg 40",
            "phone_number": "0454-100 34, 102 75",
            "bank_details": {
                "bankgiro": "86-2157",
                "postgiro": "71350"
            },
            "activity": "Rederirörelse",
            "capital": 390000,
            "key_personnel": {
                "name": "Fru Ellen Lundström",
                "position": "Verkst dir"
            },
            "establishment_year": 1878
        },
        "8": {
            "company_name": "BLIDSBERGS MEKANISKA VERKSTAD, AB",
            "pnr": "520 24",
            "address": "Blidsberg",
            "phone_number": "0321-311 11",
            "bank_details": {
                "bankgiro": "84-3327",
                "postgiro": "85027"
            },
            "activity": "Tillverkar förrådsbodar, lagerbyggnader o garage",
            "employees": 20,
            "capital": 50000,
            "key_personnel": [
                {
                    "name": "G W Törnqvist",
                    "position": "Verkst dir"
                }
            ],
            "establishment_year": 1946
        },
        "9": {
            "company_name": "SVENSSON AB, BOKFORINGS. & REVISIONSBYRÅN H",
            "pnr": "691 00",
            "address": "Karlskoga, Centralplan 3",
            "phone_number": "0586-325 20",
            "bank_details": {
                "bankgiro": "823-3157",
                "postgiro": "110559-2"
            },
            "activity": "Bokförings- o revisionsbyrå",
            "annual_turnover": 275000,
            "capital": 5000,
            "key_personnel": {
                "name": "Henry Svensson",
                "position": "Verkst dir"
            },
            "establishment_year": 1961
        },
        "10": {
            "company_name": "JOHANSSON BYGG AB, J A",
            "pnr": "93100",
            "address": "Skellefteå, Varvs g 4",
            "phone_number": "0910-105 60, 11060",
            "bank_details": {
                "bankgiro": "611-6735",
                "postgiro": "66764-2"
            },
            "activity": "Bostads-, affärs-, industri- o förvaltningsbyggnader",
            "employees": 100,
            "annual_turnover": 5000000,
            "capital": 80000,
            "key_personnel": {
                "name": "Byggm K Ingvar A Johansson",
                "position": "Verkst dir"
            },
            "establishment_year": 1946
        },
        "11": {
            "company_name": "WICO TEXTIL AB",
            "pnr": "100 72",
            "address": "Stockholm 43, Liljeholmsv 8. Box 43019",
            "phone_number": "08-45 35 05, 45 95 05",
            "activity": "Grossister i damytter-trikå."
        },
        "12": {
            "company_name": "VICTORIA. FABRIKS AB",
            "pnr": "250 11",
            "address": "Helsingborg 11, Box 11043. Victo-riag 6",
            "phone_number": "042-1202 20",
            "bank_details": {
                "bankgiro": "65-3004",
                "postgiro": "5052"
            },
            "activity": "Tillverkar o säljer hushålls- o bagerimargarin, marzi-pan o tvål",
            "employees": 105,
            "capital": 1500000,
            "key_personnel": {
                "name": "Gert Mankert",
                "position": "Verkst dir"
            },
            "establishment_year": 1920
        },
        "13": {
            "company_name": "HAN ST ROM AB, SVEN",
            "pnr": "58102",
            "address": "Linköping 1, Box 39. Djurgårdsg 4",
            "phone_number": "013-1292 35",
            "bank_details": {
                "postgiro": "278604-4"
            },
            "activity": "inköp o försäljning av massaved (Export)",
            "employees": 20,
            "annual_turnover": 7000000,
            "capital": 400000,
            "key_personnel": {
                "name": "Sven Hanström",
                "position": "Verkst dir"
            },
            "establishment_year": 1922
        },
        "14": {
            "company_name": "INDUSTRI HYGIEN",
            "pnr": "46100",
            "address": "Trollhättan, N Björke",
            "phone_number": "0520-23166, 23002",
            "bank_details": {
                "bankgiro": "892-3559",
                "postgiro": "273806-0"
            },
            "activity": "Tillverkar babyblöjor o sanitetsbindor",
            "varunamn": "Väni",
            "employees": 5,
            "key_personnel": {
                "name": "NUs Welén",
                "position": "Chef"
            }
        },
        "15": {
            "company_name": "INDUSTRI & KRAFT. BYGGNADS AB",
            "pnr": "72216",
            "address": "Västerås, Engelbrektsg 9",
            "phone_number": "021-1103 60",
            "bank_details": {
                "bankgiro": "35-6645",
                "postgiro": "492207"
            },
            "activity": "Byggnadsentreprenörer",
            "fïial": "57700 Hultsfred, Oskarsg 28. Tel 0495-121 40",
            "employees": 160,
            "annual_turnover": 12000000,
            "capital": 150000,
            "key_personnel": {
                "name": "Gustav Ahlqvist",
                "position": "Verkst dir"
            },
            "establishment_year": 1945
        },
        "16": {
            "company_name": "INDUSTRI TEKNISKA KONSTRUKTIONER, AB",
            "pnr": "123 21",
            "address": "Farsta 1, Box 46. Lysviksg 10",
            "phone_number": "08-94 03 1 0",
            "bank_details": {
                "bankgiro": "578-2040",
                "postgiro": "551650-5"
            },
            "activity": "Konsulterar o säljer produkter för miljövårdande anläggningar inom industriella sektorn",
            "capital": 80000,
            "key_personnel": {
                "name": "Kjell-Erik Själin",
                "position": "Verkst dir"
            },
            "establishment_year": 1955
        },
        "17": {
            "company_name": "INDUSTRI UNION EUROPA. PRODUKTER AB",
            "pnr": "412 54",
            "address": "Göteborg, Södra v 91",
            "phone_number": "031-20 66 77",
            "bank_details": {
                "bankgiro": "36-2616",
                "postgiro": "44310"
            },
            "activity": "Tillverkar hembastun Sisu. Importerar textilier, present-artiklar, ädla stenar o collier mm, speciellt från Indien",
            "annual_turnover": 200000,
            "capital": 6000,
            "key_personnel": {
                "name": "Aldor Emanuelson",
                "position": "Verkst dir"
            },
            "establishment_year": 1952
        },
        "18": {
            "company_name": "INDUSTRI & VARVS-MASKINER, AB",
            "pnr": "400 10",
            "address": "Göteborg 3, Bellmansg 11. Box 3042",
            "phone_number": "031-1148 76, 11 1276",
            "bank_details": {
                "bankgiro": "630-4455",
                "postgiro": "243260-7"
            },
            "activity": "Säljer gjutgods av alla slag, perforerad plåt, pressade plåtdetaljer, allt i smide, svetsade maskinkonstruktioner, oljefilter, ventilationshuvar, maskiner etc",
            "varunamn": "Auto-Klean",
            "capital": 5000,
            "key_personnel": {
                "name": "Ing Kurt Morén",
                "position": "Verkst dir"
            },
            "establishment_year": 1948
        }
    }
}