{
    "original": "SÄTERS ÄNGSÄGS AB\n\nPnr 783 00\n\nSäter, Box 66. Tel 0225-500 82,\n502 82. Bankgiro 798-7092.\nPostgiro 130522-6\n\nVerksamhet: Tillverkar sågade o\nhyvlade trävaror\nAntal anställda: 30\nÅrsomsättning: 3 500 000\nAktiekapital: 200 000\nStyrelse: Dir Jan Berggren (ordf),\ning Lars Hedin, ing Erie Krafft\nVerkst dir: Ing Lars Hedin\nFörvaltare: Per Dahl\nEtableringsår: 1935.\n\nGUWA AB\n\nPnr 703 65\n\nÖrebro, Rynningeg 20. Tel\n019-13 60 80. Bankgiro 614-6229.\nPostgiro 230210-7. Tga Guwa.\nTelex 73399\n\nVerksamhet: Agent för livsmedel o\nkonsumtionsartiklar\nAktiekapital: 5 000\nVerkst dir: Ingvar Wallstedt\nEtableringsår: 1962.\n\nJUNOPRODUKTER AB\n\nPnr 100 21\n\nStockholm 18, Fack. Tel\n08-54 05 40. Tga Håessbe\nVerksamhet: Fönster,\nAlliansfönster\n\nAntal anställda: 325\n\nJÄM\n\nÅrsomsättning: 26 100 000\nAktiekapital: 225 000\nVerkst dir: Sven Kypengren\nEtableringsår: 1957.\n\nHALLMAN &amp; KARLSSON, AB\n\nPnr 125 30\n\nÄlvsjö, Långsjöv 32. Tel\n08-47 25 70. Bankgiro 58-1522.\nPostgiro 555517. Tga Hallcon\nVerksamhet: Pappersindustri.\nTillverkar konfektionskartonger\nAntal anställda: 20\nAktiekapital: 90 000\nVerkst dir: Wllli Falck\nEtableringsår: 1921.\n\nNÄS\n\nNÄSLUNDS JERNHANDEL,\nAB J\n\nPnr 89101\n\nÖrnsköldsvik 1, Storg 20. Box 40.\nTel0660-10130. Bankgiro 771-6392.\nPostgiro 28912-4. Tga\nNäslunds-jern. Telex 6043\nNäslundsjern\n\nVerksamhet: Säljer järnvaror o\nmaskiner\n\nAntal anställda: 38\nÅrsomsättning: 8 000 000\nAktiekapital: 180 000\nStyrelse: Dir Olle Näslund (ordf),\ndisp Gösta Jönsson, fru Göta\nNäslund\n\nVerkst dir: Olle Näslund\nEtableringsån 1913.\n\nWENDESBOLAGET AB\n\nPnr 11121\n\nStockholm, Drottningg 55. Tel\n08-10 39 02, 11 13 65. Bankgiro\n722-2532. Postgiro 2385-3. Tga\nWen-desneon\n\nVerksamhet: Neon- o plastskyltar\nAntal anställda: 15\nAktiekapital: 25 000\nVerkstdir: Wilhelm Wendes\nEtableringsår: 1926.\n\nLINJEBUSS, AB\n\nPnr 103 61\n\nStockholm 3, Sveav 52. Box 3094.\nTel 08-22 34 60. Bankgiro 136-2490.\nPostgiro 191750-9\nVeiksamhet: Buss- o lastbilstrafik,\nkiosk- o resebyrårörelse\nAktiekapital: 1200 000\nVerkst dir: Carl-Axel Seth\nEtableringsår: 1940.\n\nLINJEBUSS INTERNATIONAL\nAB\n\nPnr 25102\n\nHelsingborg 1, Box 16. Järnvägsg\n9. Tel 042-12 0180. Bankgiro\n864-0773. Postgiro 478979-8. Tga\nLinjebuss. Telex 72220 LBBOKN S\nVerksamhet Holdingcompany för\nScandinavian-Ferry-Lines. Rederi\no färjetrafik för passagerare o\nbilar mellan Sverige o Danmark samt\nSverige o Tyskland. LB-färjorna\nHelsingborg-Helsingör, Trave-Line\nHelsingborg-Köpenhamn-Trav em\nlindé, SL-färjorna\nLandskrona^Köpen-hamn\n\nAktiekapital: 1000 000\nVerkst din Carl Hall\nEkonomidirektör: Knut Näckmark\nRederiinspektön K-O Påhlsson\növerfartsledare: Sven Backe\nEtableringsår: 1954.\n\nÅNGSÅGEN I VISLANDA AB\n\nPnr 340 30\n\nVislanda, Box 102. Tel 0472-306 40.\nTelex 4681\n\nVerksamhet: Tillverkar sågade o\nhyvlade trävaror\nAntal anställda: 80\nÅrsomsättning: 15 000 000\nAktiekapital: 600 000\nVerkst din Disp Göte Johansson\nEtableringsår: 1940.\n\nSCHERLAG &amp; CO AB\n\nPnr 11458\n\nStockholm, Linné g 51-53. Tel\n08-610128. Bankgiro 155-5812.\nPostgiro 600711-6. Tga Scherlag\nVerksamhet: Fruktimport samt\nannan import o export\nVerkst dir: Civilekonom Stefan\nScherlag.\n\nSCHJLDS SÅGBLADSFABRIK,\nAB K A\n\nPnr 199 01\n\nEnköping 1, Munksundet. Box 14.\nTel 0171-33085. Bankgiro\n804-2475. Postgiro 30388-3. Tga Schild\nVerksamhet: Tillverkar skärande\nverktyg\n\nVarunamn: SDS\nAktiekapital: 350 000\nVerkst dir: Töre Schild\nEtableringsàr: 1909\nOmbildat tül aktiebolag 1922.\n\nSCHILDTS ROR AB\n\nPnr 265 00\n\nÅstorp, Fabriksg 30. Tel\n042-590 90. Bankgiro 67-1329. Postgiro\n321584\n\nVerksamhet: VVS-installationer.\nSäljer VVS-material o\nbadrumsartiklar\n\nAntal anstäUda: 30\nÅrsomsättning: 3 000 000\nAktiekapital: 50 000\nVerkst dir: Fabr Henry Schildt\nEtableringsàr: 1944.\n\nSCHLASBERGS\nFÖRSÄLJNINGS AB\n\nPnr 11146\n\nStockholm C, Norrmalmstorg 1. Tel\n08-10 30 66, 20 04 02\nVerksamhet: Säljer herr- o\ndamkon-konfektion\n\nDotterbolag till Schlasbergs\nKonfektionsfabrik AB, Landskrona.\n\nSCHLASBERGS\nKONFEKTIONSFABRIK AB\n\nPnr 26141\n\nLandskrona, Pilåkersg 32. Tel\n0418-161 00. Telex 4363\nVerksamhet: Tillverkar herr- o\ndamkonfektion\n\nAvdelningskontor Göteborg C, O\nHarang 19. Tel 031-1170 95\nStockholm C, Norrmalmstorg 1.\nTel 08-10 30 66, 2004 02\nAntal anstäUda: 378\nÅrsomsättning: 2 1 060 000\nAktiekapital: 2 000 000\nStyrelse: Dir Erie Wennerholm\n(ordf), adv Torsten Lundius\n(v ordf), bankdir Karl Cederquist,\nekonomidir Kjell Holmgren, dir\nHans Persson, textiling Henrik\nSchlasberg, dir Harald\nSchlas-berg (verkst dir)\nVerkst din Harald Schlasberg\nEtableringsàr 1896\nOmbildat till aktiebolag 1936.\n\nSCHLIEREN AB\n\nPnr 126 12 Sthlm 42\nHägersten, Elektrav 10. Box42064,\nSthlm 42. Tel 08-19 03 70. Bankgiro\n62-0807. Postgiro 553147. Telex\n17107. Tga Schliesto\nVerksamhet: Tillverkar, säljer o\nmonterar alla slags hissar o\nliknande konstruktioner, däri\ninräknat rullande trappa-. Utför alla\nslags underhållsarbeten o ger\nservice i anslutning till denna\nverksamhet\n\nAntal anstäUda: 59\nÅrsomsättning: 9 000 000\nAktiekapital: 1 100 000\nStyrelse: Dir Carl Axel Åmark\n(ordf), adv Hans Ihre, dir\nHeinrich Steiger\n\nVerkst dir Civiling Folke Nilsson\nEtableringsån 1955\nDotterbolag till Schweizerische\nWagons- und Aufzügefabrik A G,\nSchlieren-Zurich, Schweiz.\n\nSCHLUMBERGER AB\n\nPnr 18109\n\nLidingö 9, Vesslev 2-4. Box 944.\nTel 08-765 28 55. Bankgiro\n160-3828. Postgiro 600920-3.\nTga Schlumberger, Stockholm.\n\nTelex 10672 SCHLUMA S\nVerksamhet: Elektronik\nAntal anstäUda: 34\nÅrsomsättning: 9500 000\nAktiekapital: 1300 000\nVerkst dir: Hans Timan\nEtableringsàr 1957.\n\nVAGMAT ERI EL AB\n\nPnr 112 20\n\nStockholm, Jakob Westinsg 3. Tel\n08-52 0910. Bankgiro 574-7746.\nPostgiro 2315-0\n\nVerksamhet: Vägmärken,\nparkeringsanläggningar. trafikspeglar\nAntal anställda: 7\nAktiekapital: 120 000\nVerkst dir: Anders Brodin\nEtableringsår 1956.\n\nVÄNERINDUSTRIER AB,\nSKOGSÄGARNAS\n\nPnr 651 09\n\nKarlstad 1, Box 558. S Kyrkog 6.\nTel 054-18 53 40. Bankgiro\n642-3677. Postgiro 97250-5. Tga\nVäner-wood, Karlstad.\nTelex 66068 VWOOD S\nStyrelseordf: Carl Lindén\nVerkst dir: Bernt Frisk\nTekn dir: Bertil Sandberg\nFörsäljn-ledn: Marknadsdir Per\nAke Westin\n\nSulfatfabrik o pappersbruk:\n\nBäckhammars Bruk\n680 70 Bäckhammar, Tel\n0550-290 00. Bankgiro 500-0526.\nPostgiro 91169-3. Tga Vänerkraft,\nKristinehamn\nTelex 66031 VKRAFT S\nTillverkar MG kraftpapper,\nbitumen-råpapper, gummeringsråpapper,\nomslagspapper, påspapper,\nkasche-ringspapper, smärgelråpapper,\nspinnpapper, säckpapper,\nlämine-ringspapper samt våtstarkt papper\nPlatschef: övering Ulf Sandberg\nEtableringsår: 1871\nSågverk: 13 st\n\nFörsäljn-ledn: Marknadsdir Per Ake\nWestin\n\nPlywoodfabrik: 540 74 Otterbäcken,\nFack 101. Tel 0551-222 60\nTel Karlstad 054-18 53 40. Tga\nVänerwood, Karlstad.\nTelex 66068 VWOOD S\nFörsäljn-ledn: Marknadsdir Per Ake\nWestin.\n\nVÄNERSBORGS\nBOK-TRYCKERI AB\n\nPnr 462 01\n\nVänersborg 1, Sundsg 14. Box 97.\nTel 0521-100 02. 133 02. Bankgiro\n888-7663. Postgiro 36030-5\nVerksamhet: Bok-, affärs-,\nreklam-o accidenstryck\nAntal anställda: 24\nÅrsomsättning: 1 800 000\nAktiekapital: 100 000\nVeikst dir: Gunnar Berg\nEtableringsår: 1911.\n\nVÄNERSBORG GLASMÄSTERI\nHELLMAN &amp; CO\n\nPnr 462 00\n\nVänersborg, Edsg 10. Tel\n0521-101 28. Bankgiro 888-7671.\nPostgiro 15461-7\n\nVerksamhet: Lager o försäljning\nav byggnadsglas o bilglas.\nGlas-mästeri, glassliperi o inramningar.\nSäljer fotoramar, tavlor, konst o\npresentartiklar\n\nVerkstad: Vänersborg, L\nVassbotten\n\nAntal anställda: 5\nEtableringsår: 1920.",
    "structured": {
        "0": {
            "company_name": "SÄTERS ÄNGSÄGS AB",
            "pnr": "783 00",
            "address": "Säter, Box 66, 502 82",
            "phone_number": "0225-500 82",
            "bank_details": {
                "bankgiro": "798-7092",
                "postgiro": "130522-6"
            },
            "activity": "Tillverkar sågade o hyvlade trävaror",
            "employees": 30,
            "annual_turnover": 3500000,
            "capital": 200000,
            "key_personnel": [
                {
                    "name": "Jan Berggren",
                    "position": "ordf"
                },
                {
                    "name": "Lars Hedin",
                    "position": "ing"
                },
                {
                    "name": "Erie Krafft",
                    "position": "ing"
                }
            ],
            "establishment_year": 1935
        },
        "1": {
            "company_name": "GUWA AB",
            "pnr": "703 65",
            "address": "Örebro, Rynningeg 20",
            "phone_number": "019-13 60 80",
            "bank_details": {
                "bankgiro": "614-6229",
                "postgiro": "230210-7"
            },
            "activity": "Agent för livsmedel o konsumtionsartiklar",
            "capital": 5000,
            "key_personnel": [
                {
                    "name": "Ingvar Wallstedt",
                    "position": "Verkst dir"
                }
            ],
            "establishment_year": 1962
        },
        "2": {
            "company_name": "JUNOPRODUKTER AB",
            "pnr": "100 21",
            "address": "Stockholm 18, Fack",
            "phone_number": "08-54 05 40",
            "activity": "Fönster, Alliansfönster",
            "employees": 325,
            "annual_turnover": 26100000,
            "capital": 225000,
            "key_personnel": [
                {
                    "name": "Sven Kypengren",
                    "position": "Verkst dir"
                }
            ],
            "establishment_year": 1957
        },
        "3": {
            "company_name": "HALLMAN & KARLSSON, AB",
            "pnr": "125 30",
            "address": "Älvsjö, Långsjöv 32",
            "phone_number": "08-47 25 70",
            "bank_details": {
                "bankgiro": "58-1522",
                "postgiro": "555517"
            },
            "activity": "Pappersindustri. Tillverkar konfektionskartonger",
            "employees": 20,
            "capital": 90000,
            "key_personnel": [
                {
                    "name": "Wllli Falck",
                    "position": "Verkst dir"
                }
            ],
            "establishment_year": 1921
        },
        "4": {
            "company_name": "NÄSLUNDS JERNHANDEL, AB J",
            "pnr": "89101",
            "address": "Örnsköldsvik 1, Storg 20, Box 40",
            "phone_number": "0660-10130",
            "bank_details": {
                "bankgiro": "771-6392",
                "postgiro": "28912-4"
            },
            "activity": "Säljer järnvaror o maskiner",
            "employees": 38,
            "annual_turnover": 8000000,
            "capital": 180000,
            "key_personnel": [
                {
                    "name": "Olle Näslund",
                    "position": "ordf"
                },
                {
                    "name": "Gösta Jönsson",
                    "position": "disp"
                },
                {
                    "name": "Göta Näslund",
                    "position": "fru"
                },
                {
                    "name": "Olle Näslund",
                    "position": "Verkst dir"
                }
            ],
            "establishment_year": 1913
        },
        "5": {
            "company_name": "WENDESBOLAGET AB",
            "pnr": "11121",
            "address": "Stockholm, Drottningg 55",
            "phone_number": "08-10 39 02, 11 13 65",
            "bank_details": {
                "bankgiro": "722-2532",
                "postgiro": "2385-3"
            },
            "activity": "Neon- o plastskyltar",
            "employees": 15,
            "capital": 25000,
            "key_personnel": [
                {
                    "name": "Wilhelm Wendes",
                    "position": "Verkstdir"
                }
            ],
            "establishment_year": 1926
        },
        "6": {
            "company_name": "LINJEBUSS, AB",
            "pnr": "103 61",
            "address": "Stockholm 3, Sveav 52, Box 3094",
            "phone_number": "08-22 34 60",
            "bank_details": {
                "bankgiro": "136-2490",
                "postgiro": "191750-9"
            },
            "activity": "Buss- o lastbilstrafik, kiosk- o resebyrårörelse",
            "capital": 1200000,
            "key_personnel": [
                {
                    "name": "Carl-Axel Seth",
                    "position": "Verkst dir"
                }
            ],
            "establishment_year": 1940
        },
        "7": {
            "company_name": "LINJEBUSS INTERNATIONAL AB",
            "pnr": "25102",
            "address": "Helsingborg 1, Box 16, Järnvägsg 9",
            "phone_number": "042-12 0180",
            "bank_details": {
                "bankgiro": "864-0773",
                "postgiro": "478979-8"
            },
            "activity": "Holdingcompany för Scandinavian-Ferry-Lines. Rederi o färjetrafik för passagerare o bilar mellan Sverige o Danmark samt Sverige o Tyskland",
            "capital": 1000000,
            "key_personnel": [
                {
                    "name": "Carl Hall",
                    "position": "Verkst din"
                },
                {
                    "name": "Knut Näckmark",
                    "position": "Ekonomidirektör"
                },
                {
                    "name": "K-O Påhlsson",
                    "position": "Rederiinspektön"
                },
                {
                    "name": "Sven Backe",
                    "position": "överfartsledare"
                }
            ],
            "establishment_year": 1954
        },
        "8": {
            "company_name": "ÅNGSÅGEN I VISLANDA AB",
            "pnr": "340 30",
            "address": "Vislanda, Box 102",
            "phone_number": "0472-306 40",
            "activity": "Tillverkar sågade o hyvlade trävaror",
            "employees": 80,
            "annual_turnover": 15000000,
            "capital": 600000,
            "key_personnel": [
                {
                    "name": "Göte Johansson",
                    "position": "Verkst din"
                }
            ],
            "establishment_year": 1940
        },
        "9": {
            "company_name": "SCHERLAG & CO AB",
            "pnr": "11458",
            "address": "Stockholm, Linné g 51-53",
            "phone_number": "08-610128",
            "bank_details": {
                "bankgiro": "155-5812",
                "postgiro": "600711-6"
            },
            "activity": "Fruktimport samt annan import o export",
            "key_personnel": [
                {
                    "name": "Stefan Scherlag",
                    "position": "Verkst dir"
                }
            ]
        },
        "10": {
            "company_name": "SCHJLDS SÅGBLADSFABRIK, AB K A",
            "pnr": "199 01",
            "address": "Enköping 1, Munksundet, Box 14",
            "phone_number": "0171-33085",
            "bank_details": {
                "bankgiro": "804-2475",
                "postgiro": "30388-3"
            },
            "activity": "Tillverkar skärande verktyg",
            "employees": 350,
            "capital": 350000,
            "key_personnel": [
                {
                    "name": "Töre Schild",
                    "position": "Verkst dir"
                }
            ],
            "establishment_year": 1909
        },
        "11": {
            "company_name": "SCHILDTS ROR AB",
            "pnr": "265 00",
            "address": "Åstorp, Fabriksg 30",
            "phone_number": "042-590 90",
            "bank_details": {
                "bankgiro": "67-1329",
                "postgiro": "321584"
            },
            "activity": "VVS-installationer. Säljer VVS-material o badrumsartiklar",
            "employees": 30,
            "annual_turnover": 3000000,
            "capital": 50000,
            "key_personnel": [
                {
                    "name": "Henry Schildt",
                    "position": "Verkst dir"
                }
            ],
            "establishment_year": 1944
        },
        "12": {
            "company_name": "SCHLASBERGS FÖRSÄLJNINGS AB",
            "pnr": "11146",
            "address": "Stockholm C, Norrmalmstorg 1",
            "phone_number": "08-10 30 66, 20 04 02",
            "activity": "Säljer herr- o damkon-konfektion"
        },
        "13": {
            "company_name": "SCHLASBERGS KONFEKTIONSFABRIK AB",
            "pnr": "26141",
            "address": "Landskrona, Pilåkersg 32",
            "phone_number": "0418-161 00",
            "activity": "Tillverkar herr- o damkonfektion",
            "employees": 378,
            "annual_turnover": 21060000,
            "capital": 2000000,
            "key_personnel": [
                {
                    "name": "Erie Wennerholm",
                    "position": "ordf"
                },
                {
                    "name": "Torsten Lundius",
                    "position": "v ordf"
                },
                {
                    "name": "Karl Cederquist",
                    "position": "bankdir"
                },
                {
                    "name": "Kjell Holmgren",
                    "position": "ekonomidir"
                },
                {
                    "name": "Hans Persson",
                    "position": "dir"
                },
                {
                    "name": "Henrik Schlasberg",
                    "position": "textiling"
                },
                {
                    "name": "Harald Schlasberg",
                    "position": "verkst dir"
                }
            ],
            "establishment_year": 1896
        },
        "14": {
            "company_name": "SCHLIEREN AB",
            "pnr": "126 12 Sthlm 42",
            "address": "Hägersten, Elektrav 10, Box42064, Sthlm 42",
            "phone_number": "08-19 03 70",
            "bank_details": {
                "bankgiro": "62-0807",
                "postgiro": "553147"
            },
            "activity": "Tillverkar, säljer o monterar alla slags hissar o liknande konstruktioner, däri inräknat rullande trappa-. Utför alla slags underhållsarbeten o ger service i anslutning till denna verksamhet",
            "employees": 59,
            "annual_turnover": 9000000,
            "capital": 1100000,
            "key_personnel": [
                {
                    "name": "Carl Axel Åmark",
                    "position": "ordf"
                },
                {
                    "name": "Hans Ihre",
                    "position": "adv"
                },
                {
                    "name": "Heinrich Steiger",
                    "position": "dir"
                }
            ],
            "establishment_year": 1955
        },
        "15": {
            "company_name": "SCHLUMBERGER AB",
            "pnr": "18109",
            "address": "Lidingö 9, Vesslev 2-4, Box 944",
            "phone_number": "08-765 28 55",
            "bank_details": {
                "bankgiro": "160-3828",
                "postgiro": "600920-3"
            },
            "activity": "Elektronik",
            "employees": 34,
            "annual_turnover": 9500000,
            "capital": 1300000,
            "key_personnel": [
                {
                    "name": "Hans Timan",
                    "position": "Verkst dir"
                }
            ],
            "establishment_year": 1957
        },
        "16": {
            "company_name": "VÄGMAT ERI EL AB",
            "pnr": "112 20",
            "address": "Stockholm, Jakob Westinsg 3",
            "phone_number": "08-52 0910",
            "bank_details": {
                "bankgiro": "574-7746",
                "postgiro": "2315-0"
            },
            "activity": "Vägmärken, parkeringsanläggningar. trafikspeglar",
            "employees": 7,
            "capital": 120000,
            "key_personnel": [
                {
                    "name": "Anders Brodin",
                    "position": "Verkst dir"
                }
            ],
            "establishment_year": 1956
        },
        "17": {
            "company_name": "VÄNERINDUSTRIER AB, SKOGSÄGARNAS",
            "pnr": "651 09",
            "address": "Karlstad 1, Box 558, S Kyrkog 6",
            "phone_number": "054-18 53 40",
            "bank_details": {
                "bankgiro": "642-3677",
                "postgiro": "97250-5"
            },
            "activity": "Sulfatfabrik o pappersbruk",
            "establishment_year": 1871
        },
        "18": {
            "company_name": "VÄNERSBORGS BOK-TRYCKERI AB",
            "pnr": "462 01",
            "address": "Vänersborg 1, Sundsg 14, Box 97",
            "phone_number": "0521-100 02. 133 02",
            "bank_details": {
                "bankgiro": "888-7663",
                "postgiro": "36030-5"
            },
            "activity": "Bok-, affärs-, reklam-o accidenstryck",
            "employees": 24,
            "annual_turnover": 1800000,
            "capital": 100000,
            "key_personnel": [
                {
                    "name": "Gunnar Berg",
                    "position": "Veikst dir"
                }
            ],
            "establishment_year": 1911
        },
        "19": {
            "company_name": "VÄNERBORGS GLASMÄSTERI HELLMAN & CO",
            "pnr": "462 00",
            "address": "Vänersborg, Edsg 10",
            "phone_number": "0521-101 28",
            "bank_details": {
                "bankgiro": "888-7671",
                "postgiro": "15461-7"
            },
            "activity": "Lager o försäljning av byggnadsglas o bilglas. Glas-mästeri, glassliperi o inramningar. Säljer fotoramar, tavlor, konst o presentartiklar'",
            "employees": 5,
            "establishment_year": 1920
        }
    }
}