{
    "original": "RUNES MEK VERKSTAD\n\nPnr 590 21\n\nVäderstad. Tel 0142-703 10, 700 04.\nPostgiro 688022\n\nVerksamhet: Tillverkar\nlantbruksredskap\n\nAntal anställda: 10\nÅrsomsättning: 1000 000\nChef: Rune Stark\nEtableringsår: 1962.\n\nRUNEBORGS METALLFABRIK,\nAB BRUDERNA\n\nPnr 11123\n\nStockholm, Upp lands g 1. Tel\n08-1109 71,1107 35. Postgiro 53711\nVerksamhet: Tillverkar\nbutiksinredningar av metall\nAktiekapital: 15 500\nVerkst din Gunnar Runeborg\nEtableringsår: 1946.\n\nRUNEFELT INGENIORSBYRÅ\nAB, ELIS\n\nPnr 113 43\n\nStockholm, Dalag 61. Tel\n08-2413 65. Bankgiro 72-8478.\nPostgiro 156492\n\nVerksamhet: Konsulterande byrå\nför VVS\n\nAntal anställda: 32\nÅrsomsättning: 2 000 000\nAktiekapital: 15 000\nVerkst dir: Gösta Wennberg\nEtableringsår: 1937.\n\nNORDSTROM &amp; THULIN AB\n\nPnr 11182\n\nStockholm 1, Box 1215. Skeppsbron\n34-36. Tel 08-23 17 40. Bankgiro\n165-2692. Postgiro 4500-5. Tga\nNordstroms. Telex 19352\nVerksamhet: Redare,\nskeppsmäklare, auktoriserade speditörer o\nklarerare, fartygsförsäljare\nAvdelningskontor: Arlanda,\nGöteborg, Hälsingborg, Malmö,\nNorrköping o Trelleborg\nAntal anställda: 90\nAktiekapital: 1600 000\nVerkst dir: Torbjörn Oström\nEtableringsår: 1850.\n\nNORDSTROM VERKTYGS.\nMASKINER AB, JOHAN\n\nPnr 11157\n\nStockholm, Sveav 13-15. Tel\n08-237900. Bankgiro 44-6813.\nPostgiro 550650. Telex 1854. Tga\nJono-werk\n\nVerksamhet: Säljer\nverktygsmaskiner\n\nÄgare o chef: Johan Nordström\nEtableringsår: 1955.\n\nNORDSTROMS SÄG &amp;\nHYVLERI, AB T\n\nPnr 910 01\n\nNordmaling. Tel 0930-410 41, 41042,\n41043, 41046. Bankgiro 76-3293.\nPostgiro 366091. Tga T N M Wood.\nTelex 54065\n\nVerksamhet: Sågade o hyvlade\nträvaror\n\nAntal anstäUda: 135\nÅrsomsättning: 15 000 000\nAktiekapital: 250 000\n\nVerkst dir: Torsten Nordström\nEtableringsår: 1945\nOmbildat till aktiebolag 1965.\n\nNORDVALL &amp; CO AB, A R\n\nPnr 103 44\n\nStockholm 40, Sveav 9-11. Box\n40195. Tel 08-10 1652, 2016 56.\nPostgiro 194763. Telex 1537. Tga\nArnordvall\n\nVerksamhet: Agenturer i\nforder-medel o spannmål\nAntal anstäUda: 4\nAktiekapital: 25 000\nVerkst dir: Allan Karnéus\nEtableringsår: 1927.\n\nNORD WALL AGENTURFIRMA,\nBIRGER\n\nPnr 501 07\n\nBorås 1, Alströmerg 18. Box 399.\nTel 033-1318 31, 13 38 31. Bankgiro\n53-1385. Postgiro 570314. Telex\n36019 BIRNO S. Tga Birno\nVerksamhet: Importagentur, olika\nslag av fibrer, garner o vävnader\nVerkst dir: Civiling Birger\nNord-wall\n\nEtableringsår: 1959.\n\nALMKVIST &amp; CO, AB R\n\nPnr 633 46\n\nEskilstuna, Gustavsv 9 B. Tel\n016-13 5108. Tga Tunatool\nVerksamhet: Tillverkar\nmätinstrument, djupmått, skjutmått,\nstålskalor, jiggar, fixturer o modeller\nVarunamn: Tuna\nPlatschef: Ing Stig Lindberg\nEtableringsår: 1942.\n\nINDALSHUS AB\n\nPnr 831 01\n\nÖstersund l.Box 440. Storg 19. Tel\n063-247 15. Bankgiro 774-5987.\nPostgiro 164467-3\nVeiksamhet: Tillverkar o säljer\nmonteringsfärdiga trähus såväl\nhyreshus som fritidshus\nFabrik: 833 00 Strömsund, Näs\nviken. Tel 0670-114 20\n\nAntal anställda: 45\n\nÅrsomsättning: 6000 000\nAktiekapital: 319000\nVeikst dir Lennart Hägglund\nFörsäljning: Göran Sundegård,\nKlas Lif\n\nEtableringsår. 1964.\n\nINDEL, INDUSTRIELL\nELEK-TRONIK AB\n\nPnr 440 53\n\nOdsmål, Odsmål industriområde.\nBox 30. Tel 0303-736 00\nVeiksamhet: Elektroniska\nstyrsystem för maskiner\nAntal anställda: 10\nAktiekapital: 15 000\nVeikst dir S Gawell\nEtableringsår: 1965.\n\nJAKOBSSONS FABRIKS AB, C\n\nPnr 690 75\n\nOdensbacken, Box 40. Tel 019-\n\n502 60. Bankgiro 82-2405.\nPostgiro 24888\n\nVeiksamhet: Tillverkar plåt- o\nplastförpackningar för färg- o kem\nindustrin samt livsmedelsindustrin\nFörsäljningskontor: Stockholm,\nFregatt v 68. Tel 08-84 00 40\nAntal anställda: 125\nÅrsomsättning: 15000 000\nAktiekapital: 165 000\nStyrelse: Försäljn-chef Ake\nJakobsson (ordf), dir Gösta\nJakobsson, ing Lennart Jakobsson, fru\nBritta Jakobsson\nVeikst dir: Gösta Jakobsson\nEtableringsår: 1895\nOmbildat till aktiebolag 1926.\n\nJACOBSSON &amp; CO, GÖSTA\n\nPnr 40125\n\nGöteborg 1, Kristinelundsg 5. Box\n309. Tel 031-18 49 25, 18 49 04.\nPostgiro 48492. Telex 2514. Tga\nJasonco\n\nVerksamhet: Exporterar sågade o\nhyvlade trävaror samt wallboard\nÄgare o chef: Gösta Jacobsson\nEtableringsår: 1927.\n\nBJURENWALLS I KOLBÄCK\n\nPnr 730 40\n\nKolbäck, Box 55. Tel 0220-404 90.\nBankgiro 81-0916. Postgiro 224909\nVerksamhet: Harvar\n(stelpinne-harvar, hjulharvar), varmluftstorkar\nAntal anställda: 60\nÅrsomsättning: 8 000 000\nChef: Fabr Alf Bjurenwall\nEtableringsår: 1959.\n\nGRAVELEIJ, AB SVEN\n\nPnr 600 02\n\nNorrköping 2, von Leeseng 3. Box\n2104. Tel 011-12 65 88, 13 64 88.\nBankgiro 609-8222. Postgiro\n26691-6. Tga Graveleijs\nVerksamhet: Engrosförsäljning av\nbilelektriska artiklar\nVarunamn: Dowal, Heid, Schier,\nWego\n\nAntal anställda: 6\nAktiekapital: 50 100\nVerkst dir: Ing Sven Graveleij\nEtableringsår: 1923.\n\nHESTRA-INREDNINGAR AB\n\nPnr 330 27\n\nHestra, Box 112. Tel 0370-352 80.\nBankgiro 14-3328. Postgiro 168849\nVerksamhet: Tillverkar butiks-,\nhotell- o lagerinredningar\nAntal anställda: 23\nÅrsomsättning: 1800 000\nAktiekapital: 180 000\nVerkst dir. Fabr Tage Petersson\nEtableringsår: 1900.\n\nHETTEMARKS\nKONFEKTIONS AB\n\nPnr 199 01\n\nEnköping 1, Box 64. Tel\n0171-33270. Tga Hettemarks.\nTelex 40646 HETMARK S\nVerksamhet: Tillverkar\ndamkonfektion\n\nEtableringsår: 1944.\n\nROCKWOOL AB\n\nPnr 54101\n\nSkövde 1, Fack. Huvudkontor. Tel\n0500-10 6 50. Postgiro 134062-9.\nTga Rockwool. Telex 67021\nVerksamhet: Tillverkar o säljer\nmineralull o isolervaror för\nisolering mot värme, brand, kyla o ljud\nFörsäljningskonton\nGöteborg. Tel 031-20 08 00\nMalmö. Tel 040-759 65\nStockholm. Tel 08-15 09 80\nSundsvall. Tel 060-15 0 6 50\nÖrebro. Tel 019-13 02 70\nVarunamn: Rockwool\nAntal anställda: 1100\nAktiekapital: 12000 000\nVerkst dir: Bo Anderberg\nEtableringsår: 1937.\n\nVERMIT-PRODUKTER AB\n\nPnr 724 10\n\nVästerås. Skepparg 6. Tel\n021-110255. Bankgiro 641-7554.\nPostgiro 710390-2\n\nVerksamhet: Tillverkar\nbrandisolering sprodukter, fasad-, akustik- o\ndekorputs\nVarunamn: Vermit.\n\nWERNE, INGENIORS.\nFIRMAN STIG\n\nPnr 41121\n\nGöteborg C, Stora Badhusg 20. Tel\n031-11 11 55, 111122. Bankgiro\n51-1605. Postgiro 47381. Tga Stigwe\nVerksamhet: Sjukhusutrustningar,\ntruckar, vacuumapparater,\nindustrirationalisering, konsult\nÄgare o chef: Stig Werne\nEtableringsår: 1942.",
    "structured": {
        "firms": [
            {
                "company_name": "RUNES MEK VERKSTAD",
                "pnr": "590 21",
                "address": "Väderstad",
                "phone_number": "0142-703 10, 700 04",
                "postgiro": "688022",
                "activity": "Tillverkar lantbruksredskap",
                "employees": 10,
                "annual_turnover": 1000000,
                "key_personnel": [
                    {
                        "name": "Rune Stark",
                        "position": "Chef"
                    }
                ],
                "establishment_year": 1962
            },
            {
                "company_name": "RUNEBORGS METALLFABRIK, AB BRUDERNA",
                "pnr": "11123",
                "address": "Stockholm, Upp lands g 1",
                "phone_number": "08-1109 71,1107 35",
                "postgiro": "53711",
                "activity": "Tillverkar butiksinredningar av metall",
                "capital": 15500,
                "key_personnel": [
                    {
                        "name": "Gunnar Runeborg",
                        "position": "Verkst din"
                    }
                ],
                "establishment_year": 1946
            },
            {
                "company_name": "RUNEFELT INGENIORSBYRÅ AB, ELIS",
                "pnr": "113 43",
                "address": "Stockholm, Dalag 61",
                "phone_number": "08-2413 65",
                "bank_details": {
                    "bankgiro": "72-8478",
                    "postgiro": "156492"
                },
                "activity": "Konsulterande byrå för VVS",
                "employees": 32,
                "annual_turnover": 2000000,
                "capital": 15000,
                "key_personnel": [
                    {
                        "name": "Gösta Wennberg",
                        "position": "Verkst dir"
                    }
                ],
                "establishment_year": 1937
            },
            {
                "company_name": "NORDSTROM & THULIN AB",
                "pnr": "11182",
                "address": "Stockholm 1, Box 1215, Skeppsbron 34-36",
                "phone_number": "08-23 17 40",
                "bank_details": {
                    "bankgiro": "165-2692",
                    "postgiro": "4500-5"
                },
                "activity": "Redare, skeppsmäklare, auktoriserade speditörer o klarerare, fartygsförsäljare",
                "employees": 90,
                "capital": 1600000,
                "key_personnel": [
                    {
                        "name": "Torbjörn Oström",
                        "position": "Verkst dir"
                    }
                ],
                "establishment_year": 1850
            },
            {
                "company_name": "NORDSTROM VERKTYGS. MASKINER AB, JOHAN",
                "pnr": "11157",
                "address": "Stockholm, Sveav 13-15",
                "phone_number": "08-237900",
                "bank_details": {
                    "bankgiro": "44-6813",
                    "postgiro": "550650"
                },
                "activity": "Säljer verktygsmaskiner",
                "key_personnel": [
                    {
                        "name": "Johan Nordström",
                        "position": "Ägare o chef"
                    }
                ],
                "establishment_year": 1955
            },
            {
                "company_name": "NORDSTROMS SÄG & HYVLERI, AB T",
                "pnr": "910 01",
                "address": "Nordmaling",
                "phone_number": "0930-410 41, 41042, 41043, 41046",
                "bank_details": {
                    "bankgiro": "76-3293",
                    "postgiro": "366091"
                },
                "activity": "Sågade o hyvlade trävaror",
                "employees": 135,
                "annual_turnover": 15000000,
                "capital": 250000,
                "key_personnel": [
                    {
                        "name": "Torsten Nordström",
                        "position": "Verkst dir"
                    }
                ],
                "establishment_year": 1945
            },
            {
                "company_name": "NORDVALL & CO AB, A R",
                "pnr": "103 44",
                "address": "Stockholm 40, Sveav 9-11, Box 40195",
                "phone_number": "08-10 1652, 2016 56",
                "postgiro": "194763",
                "activity": "Agenturer i forder-medel o spannmål",
                "employees": 4,
                "capital": 25000,
                "key_personnel": [
                    {
                        "name": "Allan Karnéus",
                        "position": "Verkst dir"
                    }
                ],
                "establishment_year": 1927
            },
            {
                "company_name": "NORD WALL AGENTURFIRMA, BIRGER",
                "pnr": "501 07",
                "address": "Borås 1, Alströmerg 18, Box 399",
                "phone_number": "033-1318 31, 13 38 31",
                "bank_details": {
                    "bankgiro": "53-1385",
                    "postgiro": "570314"
                },
                "activity": "Importagentur, olika slag av fibrer, garner o vävnader",
                "key_personnel": [
                    {
                        "name": "Civiling Birger Nord-wall",
                        "position": "Verkst dir"
                    }
                ],
                "establishment_year": 1959
            },
            {
                "company_name": "ALMKVIST & CO, AB R",
                "pnr": "633 46",
                "address": "Eskilstuna, Gustavsv 9 B",
                "phone_number": "016-13 5108",
                "activity": "Tillverkar mätinstrument, djupmått, skjutmått, stålskalor, jiggar, fixturer o modeller",
                "varunamn": "Tuna",
                "key_personnel": [
                    {
                        "name": "Ing Stig Lindberg",
                        "position": "Platschef"
                    }
                ],
                "establishment_year": 1942
            },
            {
                "company_name": "INDALSHUS AB",
                "pnr": "831 01",
                "address": "Östersund l.Box 440, Storg 19",
                "phone_number": "063-247 15",
                "bank_details": {
                    "bankgiro": "774-5987",
                    "postgiro": "164467-3"
                },
                "activity": "Tillverkar o säljer monteringsfärdiga trähus såväl hyreshus som fritidshus",
                "employees": 45,
                "annual_turnover": 6000000,
                "capital": 319000,
                "key_personnel": [
                    {
                        "name": "Lennart Hägglund",
                        "position": "Veikst dir"
                    },
                    {
                        "name": "Göran Sundegård",
                        "position": "Försäljning"
                    },
                    {
                        "name": "Klas Lif",
                        "position": "Försäljning"
                    }
                ],
                "establishment_year": 1964
            },
            {
                "company_name": "INDEL, INDUSTRIELL ELEK-TRONIK AB",
                "pnr": "440 53",
                "address": "Odsmål, Odsmål industriområde, Box 30",
                "phone_number": "0303-736 00",
                "activity": "Elektroniska styrsystem för maskiner",
                "employees": 10,
                "capital": 15000,
                "key_personnel": [
                    {
                        "name": "S Gawell",
                        "position": "Veikst dir"
                    }
                ],
                "establishment_year": 1965
            },
            {
                "company_name": "JAKOBSSONS FABRIKS AB, C",
                "pnr": "690 75",
                "address": "Odensbacken, Box 40",
                "phone_number": "019-502 60",
                "bankgiro": "82-2405",
                "postgiro": "24888",
                "activity": "Tillverkar plåt- o plastförpackningar för färg- o kem industrin samt livsmedelsindustrin",
                "employees": 125,
                "annual_turnover": 15000000,
                "capital": 165000,
                "key_personnel": [
                    {
                        "name": "Ake Jakobsson",
                        "position": "Försäljn-chef (ordf)"
                    },
                    {
                        "name": "Gösta Jakobsson",
                        "position": "dir"
                    },
                    {
                        "name": "Lennart Jakobsson",
                        "position": "ing"
                    },
                    {
                        "name": "Britta Jakobsson",
                        "position": "fru"
                    }
                ],
                "establishment_year": 1895
            },
            {
                "company_name": "JACOBSSON & CO, GÖSTA",
                "pnr": "40125",
                "address": "Göteborg 1, Kristinelundsg 5, Box 309",
                "phone_number": "031-18 49 25, 18 49 04",
                "postgiro": "48492",
                "activity": "Exporterar sågade o hyvlade trävaror samt wallboard",
                "key_personnel": [
                    {
                        "name": "Gösta Jacobsson",
                        "position": "Ägare o chef"
                    }
                ],
                "establishment_year": 1927
            },
            {
                "company_name": "BJURENWALLS I KOLBÄCK",
                "pnr": "730 40",
                "address": "Kolbäck, Box 55",
                "phone_number": "0220-404 90",
                "bankgiro": "81-0916",
                "postgiro": "224909",
                "activity": "Harvar (stelpinne-harvar, hjulharvar), varmluftstorkar",
                "employees": 60,
                "annual_turnover": 8000000,
                "key_personnel": [
                    {
                        "name": "Fabr Alf Bjurenwall",
                        "position": "Chef"
                    }
                ],
                "establishment_year": 1959
            },
            {
                "company_name": "GRAVELEIJ, AB SVEN",
                "pnr": "600 02",
                "address": "Norrköping 2, von Leeseng 3, Box 2104",
                "phone_number": "011-12 65 88, 13 64 88",
                "bankgiro": "609-8222",
                "postgiro": "26691-6",
                "activity": "Engrosförsäljning av bilelektriska artiklar",
                "employees": 6,
                "capital": 50100,
                "key_personnel": [
                    {
                        "name": "Ing Sven Graveleij",
                        "position": "Verkst dir"
                    }
                ],
                "establishment_year": 1923
            },
            {
                "company_name": "HESTRA-INREDNINGAR AB",
                "pnr": "330 27",
                "address": "Hestra, Box 112",
                "phone_number": "0370-352 80",
                "bankgiro": "14-3328",
                "postgiro": "168849",
                "activity": "Tillverkar butiks-, hotell- o lagerinredningar",
                "employees": 23,
                "annual_turnover": 1800000,
                "capital": 180000,
                "key_personnel": [
                    {
                        "name": "Fabr Tage Petersson",
                        "position": "Verkst dir"
                    }
                ],
                "establishment_year": 1900
            },
            {
                "company_name": "HETTEMARKS KONFEKTIONS AB",
                "pnr": "199 01",
                "address": "Enköping 1, Box 64",
                "phone_number": "0171-33270",
                "activity": "Tillverkar damkonfektion",
                "establishment_year": 1944
            },
            {
                "company_name": "ROCKWOOL AB",
                "pnr": "54101",
                "address": "Skövde 1, Fack. Huvudkontor",
                "phone_number": "0500-10 6 50",
                "postgiro": "134062-9",
                "activity": "Tillverkar o säljer mineralull o isolervaror för isolering mot värme, brand, kyla o ljud",
                "varunamn": "Rockwool",
                "employees": 1100,
                "capital": 12000000,
                "key_personnel": [
                    {
                        "name": "Bo Anderberg",
                        "position": "Verkst dir"
                    }
                ],
                "establishment_year": 1937
            },
            {
                "company_name": "VERMIT-PRODUKTER AB",
                "pnr": "724 10",
                "address": "Västerås, Skepparg 6",
                "phone_number": "021-110255",
                "bankgiro": "641-7554",
                "postgiro": "710390-2",
                "activity": "Tillverkar brandisolering sprodukter, fasad-, akustik- o dekorputs",
                "varunamn": "Vermit",
                "establishment_year": 1923
            },
            {
                "company_name": "WERNE, INGENIORS. FIRMAN STIG",
                "pnr": "41121",
                "address": "Göteborg C, Stora Badhusg 20",
                "phone_number": "031-11 11 55, 111122",
                "bankgiro": "51-1605",
                "postgiro": "47381",
                "activity": "Sjukhusutrustningar, truckar, vacuumapparater, industrirationalisering, konsult",
                "key_personnel": [
                    {
                        "name": "Stig Werne",
                        "position": "Ägare o chef"
                    }
                ],
                "establishment_year": 1942
            }
        ]
    }
}