{
    "original": "SOS\n\nSOLVESBORGS\nGRÄV-MASKINER AB\n\nPnr 294 00\n\nSölvesborg, Verkstadsg 2. Tel\n0456-125 55. Bankgiro 664-0692.\nPostgiro 373383-9\nVerksamhet: Tillverkar\nbetongpålar. Grävmaskinsentreprenör\nAntal anställda: 30\nÅrsomsättning: 4 000 000\nAktiekapital: 50 000\nVerkst dir: Harald Persson\nEtableringsår: 1953.\n\nSOLVESBORGS\nSKEPPSMÄK-LERI. &amp; SPEDITIONSKON.\nTOR, AB\n\nPnr 294 00\n\nSölvesborg, Järnvägsstation. Box 29\nTel 0456-100 38, 101 15. Bankgiro\n66-3958. Postgiro 322748. Tga\nSpedition. Telex 4474\nVerksamhet: Skeppsmäkleri o\nspedition\n\nAktiekapital: 30 000\nVerkst din Konsul Bertil Ståhl\nEtableringsår: 1906.\n\nSOLVESBORGS SKOFABRIK,\nAB\n\nPnr 294 00\n\nSölvesborg, Dr Sternsg 11. Tel\n0456-10163. Postgiro 12959\nVerksamhet: Tillverkar\nkonståknings-, ishockey- o skrinnarrör,\norienterings- o bowlingsskor,\nträtofflor\n\nAntal anställda: 30\nÅrsomsättning: 2 400 000\nAktiekapital: 16 000\nVerkst dir: L Malmberg (Gävle)\nEtableringsår: 1923.\n\nSOLVESBORGS VARV AB\n\nSe AB Göta verken.\n\nSONNERGRENS VERK.\nSTÄDER, AB\n\nPnr 41140\n\nGöteborg, Avägen 17. Tel\n031-2040 34. Bankgiro 171-4500.\nPost-giro 41484-7\n\nVerksamhet: Pressningsarbete o\nstansverktyg\nAntal anställda: 20\nÅrsomsättning: 1000 000\nAktiekapital: 26 000\nVerkst dir: Ture Sönnergren\nEtableringsår: 1895.\n\nEPECO AB\n\nPnr 104 62\n\nStockholm 17, Krukmakarg 3. Box\n17056. Tel 08-6901 15. Bankgiro\n44-6 953. Postgiro 3708. Tga A gency\nDirektion: Tideliusg 42\nVerksamhet: Agent, importör o\ndistributör för märkesvaror inom livs-\n\nmedels-, kem tekn- o\nparfymeribranscherna\nAntal anställda: 35\nÅrsomsättning: 7 000000\nAktiekapital: 1 000000\nStyrelse: Ambassadör Gösta\nEngzell (ordf), kommerserådet Holger\nBergenheim, adv Sven Janzon, dir\nLennart Söderström\nVerkst dir: Holger Bergenheim\nEtableringsår: 1930.\n\nPEMAC INDUSTRI AB\n\nPnr 310 60\n\nUllared. Tel 0346-302 20. Bankgiro\n425-9800. Postgiro 669300-6\nVerksamhet: Specialitet: bockade\no svetsade trådartiklar\nAntal anställda: 35\nVerkst dir: Per Göranson\nPlatschef: Disp Sture Svensson\nEtableringsår: 1964.\n\nFREDRIKSSON &amp; CO AB\n\nPnr 103 84\n\nStockholm 7, Birger Jarlsg 31. Box\n7215. Tel 08-231445. Bankgiro\n72-7063. Postgiro 59560. Telex 1536.\nTga Timberfred\n\nVerksamhet:\nSkogsindustriprodukter engros\nAntal anställda: 35\nÅrsomsättning: 62 360 300\nAktiekapital: 1000 000\nVerkst dir: Tage Nyström.\n\nFREDRIKSSON &amp; DAHL.\nSTRAND, AB-FREDAHL-\n\nPnr 520 43\n\nAsarp, Box 34. Tel 0515-50375.\nBankgiro 552-7056. Postgiro\n73893-0\n\nVerksamhet: Tillverkar likkistor\nVarunamn: Fredahl\nAntal anställda: 60\nÅrsomsättning: 5 500 000\nAktiekapital: 204 000\nStyrelse: Karl-Erie Dahlstrand\n(ordf), Stina Fredriksson, Märta\nDahlstrand\n\nVerkst dir: Lars Fredriksson\nEtableringsår: 1925.\n\nFORDONSMATERIEL AB\n\nPnr 17142\n\nSolna, Nybodag 7. Tel 08-83 43 40.\nTga Fordonsmat, Stockholm. Telex\n10649\n\nFO\n\n\n\nVerksamhet: BPW-fordonsaxlar o\nboggier, Jost-kopplingar o stödben,\nGrau-tryckluftbromsar,\nAusti-stänk-skärmar, Suer-fordons- o\nkarosseri-tillbehör, Hunger-hydrauliska\nstödben, hjul o fälgar,\nGriimer-påskjuts-bromsar, Clark-lättmetall-karosse-rier\n\nVarunamn: BPW, Grau, Jost\nAntal anställda: 15\nÅrsomsättning: 12 000 000\nAktiekapital: 200 000\nVerkst dir: Walter Palm\nEtableringsår: 1964.\n\nFÖRESTÅ, HOTEL &amp;\nRESTAURANT AB\n\nPnr 18105\n\nLidingö 5, Fack. Herserudsv 22.\nTel 08-765 27 00. Bankgiro\n743-1646. Postgiro 6514-4. Tga\nForesthotel. Telex 19104\nVerksamhet: Hotell- o\nrestaurangrörelse\n\nAntal anställda: 150\nÅrsomsättning: 12 000000\nVerkst dir. Rolf Sundström.\n\nFORMEL. PRODUKTER\n\nPnr 951 01\n\nLuleå 1, Fack. Storg 13. Tel\n0920-28110. Bankgiro 75-2445.\nPostgiro 126900\nVerksamhet:\nEGNA PRODUKTER:\nTräavdelningen: PERGO\ngardin-upphängningssystem. Skidstavar,\nsnöskor, bandyklubbor,\nishockeyklubbor, klädhängare, köksinred-\n\nningar o timrade fritidshus\n(Gällivare-stugan), bänkskivor för\nbadrum, villastaket, trädgårdsskärmar,\nemballagelådor, sjöfartsmärken,\ntrappledstänger, borstträn, Rational\npärmhyllor, rundstav. laddkäppar,\nsviktplankor, livräddningsatrapper,\nribbstolar. gymnastikredskap,\nhyllor, lådor, NOLA lekredskap,\nspe-specialtillverkning av\ntryckimpreg-nerat virke\n\nMek avdelningen:\nBåttrailer/släpvagn (Combi-TS), Y-bommen, Bovli\nkägelställ, båtshakar, motordrivna\nissågar, broar till villor,\ntrappstegar, plattformar för\nbyggnadsarbeten, Entrémattor (Garantimattan),\narbetstrallar (för ståarbetsplatser),\ngolvsilar, skrapgaller o\ningjutnings-ramar.\n\nPlastavdelningen: (cellplast):\nFlyt-block o bojar. Formsprutade\nplastdetaljer såsom skidstavsdetaljer,\nprovbägare till sjukhus, byxhängare\n\nBok- o pappersavdelningen:\nmappar, tidskriftssamlare,\nbigningsar-beten etc\n\nLEGO:\n\nTräavdelningen: Konventionell\nmaskinbearbetning o ytbehandling.\nKapacitet: 275 000 maskintimmar/år\n\nMek avdelningen: Svarvning,\nfräsning. excenterpressning, bockning,\nsvetsning, ytbehandling, service av\nvatten- o parkeringsmätare mm.\nKapacitet: 175 000 maskintimmar/år\n\nPlastavdelningen: Formsprutad\nplast ill maskiner med gramvikter\nmellan 15-350 gram.\nKapacitet: 17 500 maskintimmar/år\nPlastavdelningen: Glasfiberarmerad\nplast samt expanderad plast inom\nen avdelning\nAntal anställda: 250\nChef: Bengt Svanberg.\n\nFORMEX AB, INGENJÖRS.\nFIRMAN\n\nPnr 162 04\n\nVällingby 4, Maltesholmsv 182.\nBox 447. Tel 08-3840 01. Postgiro\n112267-0\n\nVerksamhet: Tillverkar elektr\nartiklar\n\nAntal anställda: 25\nÅrsomsättning: 2 000 000\nAktiekapital: 25 000\nVerkst dir: Ing Ove Liljenberg\nEtableringsår: 1960\n\nSCAN - INJECT AB\n\nPnr 141 02\n\nHuddinge 2, Vikingav 11. Box 2093.\nTel 08-757 58 70. Bankgiro\n626-1226. Postgiro 54134-2\nVerksamhet: Säljer\ntrycklufts-drivna dammsugare för\nservicestationer o verkstäder\nVarunamn: Scan-Inject\nAntal anstäUda: 3\nÅrsomsättning: 250 000\nAktiekapital: 5 000\nVerkst dir: John A Malmström\nExportchef: Lars Isaksson\nEtableringsår: 1962.\n\nMOT IN &amp; CO AB\n\nPnr 302 43\n\nHalmstad, Brog 2. Tel 035-12 04 58,\n11 18 90. Bankgiro 33-8910.\nPostgiro 162076. Tga Motin\nVerksamhet: Säljer reglerinstrument\nsamt förpackningsmaskiner\nÄgare och chef: Karl-Olov Motin\nEtableringsår: 1948.\n\nARLÖVS EXPLOATERINGS AB\n\nPnr 232 00\n\nArlöv, Länsmansg 5-Stortorget 1.\nTel 040-43 05 40. Postgiro 537916-9\nVerksamhet:\nExploateringsverksamhet samt uthyrning av\nindustribyggnader\n\nTeknisk avdelning: Svenska\nIndustribyggen AB. 201 24 Malmö 1,\nBox 445. Tel 040-740 40\nAktiekapital: 40 000\nStyrelse: Personalkons E\nAndersson (ordf), herr J Hallsten,\nkomu-naldir A Sjödin, civiling B\nSvensson, dir H Birke, dir F Sundberg,\ndir A Grenner\n\nVerkst dir: Kommunaldir Axel\nSjödin\n\nEtableringsår: 1961.\n\nTJEDERS INDUSTRI AB\n\nPnr 640 32\n\nMalmköping, Kungsg 9. Box 25.\nTel 0157-208 00. Bankgiro\n61-8315. Postgiro 413108-2. Tga\nTele-tjeder\n\nVerksamhet: Tillverkar\nsignalanläggningar för sjukhus o kontor,\nsökartelefoner, resultat- o\nkötablå-er, biljettautomater\nAvdelningskontor 21155 Malmö,\nAmiralsg 14. Tel 040-365 06\n113 20 Stockholm, Sankt Eriksg 66.\nTel 08-32 79 75\nVarunamn: System Tjeder\nAntal anställda: 70\nÅrsomsättning: 4 000 000\nAktiekapital: 150 000\nVeikst dir. Lars Axel Tjeder\nEtableringsån 1958.\n\nTJUSTS MEKANISKA\nverkstads ab\n\nPnr 593 00\n\nVästervik, Allén 78. Tel\n0490-165 30\n\nVetksamhet: Tillverkar\npressverktyg, fixturer, klipp o stansverktyg\nsamt specialmaskiner\nAntal anställda: 40\nÅrsomsättning: 2 000 000\nAktiekapital: 50000\nVerkst dir: Pabr Evert Ericson\nEtableringsån 1954.\n\nNÄSSJÖ STÅL AB\n\nPnr 57100\n\nNässjö, Industrig 30. Tel\n0380-12358, 123 85. Bankgiro 452-7685.\nPostgiro 368559-1\nVerksamhet: Säljer nya o\nbegagnade verkstadsmaskiner\nAntal anställda: 5\nÅrsomsättning: 300 000\nAktiekapital: 42000\nÄgare o chefer: Gösta Spjuth, Ake\nBlomquist\n\nEtableringsår: 1948.",
    "structured": {
        "1": {
            "company_name": "SOLVESBORGS GRÄV-MASKINER AB",
            "activity": "Tillverkar betongpålar. Grävmaskinsentreprenör",
            "establishment_year": 1953,
            "employees": 30,
            "annual_turnover": 4000000,
            "capital": 50000,
            "key_personnel": [
                {
                    "name": "Harald Persson",
                    "position": "Verkst dir"
                }
            ]
        },
        "2": {
            "company_name": "SOLVESBORGS SKEPPSMÄK-LERI. & SPEDITIONSKON. TOR, AB",
            "activity": "Skeppsmäkleri o spedition",
            "establishment_year": 1906,
            "capital": 30000,
            "key_personnel": [
                {
                    "name": "Konsul Bertil Ståhl",
                    "position": "Verkst din"
                }
            ]
        },
        "3": {
            "company_name": "SOLVESBORGS SKOFABRIK, AB",
            "activity": "Tillverkar konståknings-, ishockey- o skrinnarrör, orienterings- o bowlingsskor, trätofflor",
            "establishment_year": 1923,
            "employees": 30,
            "annual_turnover": 2400000,
            "capital": 16000,
            "key_personnel": [
                {
                    "name": "L Malmberg (Gävle)",
                    "position": "Verkst dir"
                }
            ]
        },
        "4": {
            "company_name": "SONNERGRENS VERK. STÄDER, AB",
            "activity": "Pressningsarbete o stansverktyg",
            "establishment_year": 1895,
            "employees": 20,
            "annual_turnover": 1000000,
            "capital": 26000,
            "key_personnel": [
                {
                    "name": "Ture Sönnergren",
                    "position": "Verkst dir"
                }
            ]
        },
        "5": {
            "company_name": "EPECO AB",
            "activity": "Agent, importör o distributör för märkesvaror inom livsmedels-, kemteknik- o parfymeribranscherna",
            "establishment_year": 1930,
            "employees": 35,
            "annual_turnover": 7000000,
            "capital": 1000000,
            "key_personnel": [
                {
                    "name": "Holger Bergenheim",
                    "position": "Verkst dir"
                }
            ]
        },
        "6": {
            "company_name": "PEMAC INDUSTRI AB",
            "activity": "Specialitet: bockade o svetsade trådartiklar",
            "establishment_year": 1964,
            "employees": 35,
            "key_personnel": [
                {
                    "name": "Per Göranson",
                    "position": "Verkst dir"
                },
                {
                    "name": "Disp Sture Svensson",
                    "position": "Platschef"
                }
            ]
        },
        "7": {
            "company_name": "FREDRIKSSON & CO AB",
            "activity": "Skogsindustriprodukter engros",
            "employees": 35,
            "annual_turnover": 62360300,
            "capital": 1000000,
            "key_personnel": [
                {
                    "name": "Tage Nyström",
                    "position": "Verkst dir"
                }
            ]
        },
        "8": {
            "company_name": "FREDRIKSSON & DAHL. STRAND, AB-FREDAHL-",
            "activity": "Tillverkar likkistor",
            "establishment_year": 1925,
            "employees": 60,
            "annual_turnover": 5500000,
            "capital": 204000,
            "key_personnel": [
                {
                    "name": "Lars Fredriksson",
                    "position": "Verkst dir"
                }
            ]
        },
        "9": {
            "company_name": "FORDONSMATERIEL AB",
            "activity": "BPW-fordonsaxlar o boggier, Jost-kopplingar o stödben, Grau-tryckluftbromsar, Austi-stänk-skärmar, Suer-fordons- o karosseritillbehör, Hunger-hydrauliska stödben, hjul o fälgar, Griimer-påskjuts-bromsar, Clark-lättmetall-karosserier",
            "employees": 15,
            "annual_turnover": 12000000,
            "capital": 200000,
            "key_personnel": [
                {
                    "name": "Walter Palm",
                    "position": "Verkst dir"
                }
            ]
        },
        "10": {
            "company_name": "FÖRESTÅ, HOTEL & RESTAURANT AB",
            "activity": "Hotell- o restaurangrörelse",
            "employees": 150,
            "annual_turnover": 12000000,
            "key_personnel": [
                {
                    "name": "Rolf Sundström",
                    "position": "Verkst dir"
                }
            ]
        },
        "11": {
            "company_name": "FORMEX AB, INGENJÖRS. FIRMAN",
            "activity": "Tillverkar elektr artiklar",
            "employees": 25,
            "annual_turnover": 2000000,
            "capital": 25000,
            "key_personnel": [
                {
                    "name": "Ing Ove Liljenberg",
                    "position": "Verkst dir"
                }
            ]
        },
        "12": {
            "company_name": "SCAN - INJECT AB",
            "activity": "Säljer tryckluftsdrivna dammsugare för servicestationer o verkstäder",
            "employees": 3,
            "annual_turnover": 250000,
            "capital": 5000,
            "key_personnel": [
                {
                    "name": "John A Malmström",
                    "position": "Verkst dir"
                },
                {
                    "name": "Lars Isaksson",
                    "position": "Exportchef"
                }
            ]
        },
        "13": {
            "company_name": "MOT IN & CO AB",
            "activity": "Säljer reglerinstrument samt förpackningsmaskiner",
            "establishment_year": 1948,
            "key_personnel": [
                {
                    "name": "Karl-Olov Motin",
                    "position": "Ägare och chef"
                }
            ]
        },
        "14": {
            "company_name": "ARLÖVS EXPLOATERINGS AB",
            "activity": "Exploateringsverksamhet samt uthyrning av industribyggnader",
            "establishment_year": 1961,
            "capital": 40000,
            "key_personnel": [
                {
                    "name": "Kommunaldir Axel Sjödin",
                    "position": "Verkst dir"
                }
            ]
        },
        "15": {
            "company_name": "TJEDERS INDUSTRI AB",
            "activity": "Tillverkar signalanläggningar för sjukhus o kontor, sökartelefoner, resultat- o kötablå-er, biljettautomater",
            "establishment_year": 1958,
            "employees": 70,
            "annual_turnover": 4000000,
            "capital": 150000,
            "key_personnel": [
                {
                    "name": "Lars Axel Tjeder",
                    "position": "Veikst dir"
                }
            ]
        },
        "16": {
            "company_name": "TJUSTS MEKANISKA verkstads ab",
            "activity": "Tillverkar pressverktyg, fixturer, klipp o stansverktyg samt specialmaskiner",
            "establishment_year": 1954,
            "employees": 40,
            "annual_turnover": 2000000,
            "capital": 50000,
            "key_personnel": [
                {
                    "name": "Pabr Evert Ericson",
                    "position": "Verkst dir"
                }
            ]
        },
        "17": {
            "company_name": "NÄSSJÖ STÅL AB",
            "activity": "Säljer nya o begagnade verkstadsmaskiner",
            "establishment_year": 1948,
            "employees": 5,
            "annual_turnover": 300000,
            "capital": 42000,
            "key_personnel": [
                {
                    "name": "Gösta Spjuth",
                    "position": "Ägare"
                },
                {
                    "name": "Ake Blomquist",
                    "position": "Chefer"
                }
            ]
        }
    }
}