{
    "original": "BYGGNADSKOMPANIET\n\nPnr 88101\n\nSollefteå 1, Storg 24. Box 57. Tel\n0620-107 29. Postgiro 292929\nVerksamhet: Sten- o\nträhusförsäljning, ritningar o byggnadsservice\nÄgare o chef: J Sjölander\nEtableringsår: 1938.\n\nBYGGNADSPLÅT I\nJUN KÖPING AB\n\nPnr 552 67\n\nJönköping, Fridhemsv 29. Tel\n036-1158 80. Bankgiro 341-9686.\nPostgiro 329177-0\n\nVerksamhet: Utför\nbyggnadsplåt-slageriarbeten samt reparationer\nAntal anställda: 11\nÅrsomsättning: 700 000\nAktiekapital: 12 000\nChefer: Karl-Runo Magnusson,\nEgon Rydell\nEtableringsår: 1962.\n\nGRANZOW AB\n\nPnr 571 00\n\nNässjö, Box 116. Tryckerig 10.\nTel 0380-12060, 120 61. Bankgiro\n153-5913. Postgiro 636125-7\nVerksamhet: Styr- o reglerteknik.\nImporterar tryckluftutrustningar,\nventiler, cylindrar, kopplingar o\nrör, luftserviceutrustningar, filter o\nluftsmörjare, magnetventiler för\nluft, hydraulik o aggressiva media,\nplast- o vacuumslang,\nkompressorer samt universalcylindrar\nVarunamn: Enots, Skinner, Watts,\nGriflex, Stenhøj, Endex\nAntal anstäUda: 3\nÅrsomsättning: 1 000 000\nAktiekapital: 10 000\nVerkst dir: Peter Granzow\nPlatschef: Berndt Svensson\nEtableringsår: 1968\nDotterbolag till Granzow AS,\nDanmark.\n\nGARPENDAL\nINGENJORS-BYRA AB\n\nPnr 127 43\n\nSkärholmen, Storholmsbackarna 90.\nTel 08-7102432, 7102433.\nBankgiro 626-4766. Postgiro 609020-3.\nTga Graping\n\nVerksamhet; Marknadsför utrusta\nningar för processkontroll\nAntal anstäUda: 5\nÅrsomsättning: 2 000 000\nAktiekapital; 10 000\nChef: Dir B Grapendal\nEtableringsår 1967.\n\nFUNDAHN &amp; CO FÄRGFABRIK\n\nPnr 27100\n\nYstad, Besökaregränd 2. Tel\n0411-13670.Bankgiro 87-3200.Postgiro\n30974\n\nVerksamhet: Tillverkar o säljer\nolje-, lack-, plast- o maskinfärger\nAntal anställda: 4\nÄgare o chef: Ake Lindhoff\nEtableringsår: 1921.\n\nBERGGREN &amp; SON AB, AUG\n\nPnr 11351\n\nStockholm, Luntmakarg 86-88. Tel\n08-3144 03, 314404. Bankgiro\n167-0322. Postgiro 3091-6. Tga\nPainters\n\nVerksamhet: Målerirörelse i\nkommission\n\nAktiekapital: 10 000\nVerkst dir: Ivan Gustavsson\nEtableringsår: 1946.\n\nBERGGRENS MEK VERKSTAD,\nAB AXEL\n\nPnr 431 35\n\nMölndal, Agatan. Tel 031-27 2741,\n27 27 4 2. Bankgiro 505-7567.\nPostgiro 48650-6\n\nVerksamhet: Specialfirma för\ntillverkning av kugghjul, kuggstänger\no snäckväxlar\nAntal anställda: 20\nVerkst dir: Fabr Axel Berggren\nEtableringsår: 1923.\n\nJENSSEN &amp; CO AB, G M\n\nPnr 41110\n\nGöteborg. O Hamng 19. Tel\n031-13 88 12, 13 88 14. Tga Gerard.\nTelex 20850\n\nVerksamhet: Säljer\nasbestcement-rör m m\n\nVarunamn: Itälit\nVerkst dir: Knut Jénssen\nEtableringsår: 1931.\n\nLANGE AB, H &amp; S\n\nPnr 80105\n\nGävle 1, Màsbergsv 9. Box 384.\n\nTel 026-12 29 19. Bankgiro 60-3550.\n\nPostgiro 341492-7\n\nVerksamhet: Generalagent för UTP\n\nsvetsmaterial\n\nChef: Dir H Lange.\n\nLANGE AB, L J\n\nPnr 40231\n\nGöteborg 7, Värmlandsg 16. Box\n7015. Tel 031-12 44 05. Bankgiro\n84-5902. Postgiro 12040. Telex\n20659. Tga Glasögonlange\nVerksamhet: Grossist i optik\nAktiekapital: 300 000\nVerkst dir: Gunnar Schramm\nEtableringsår: 1881.\n\nLANGERS KLICHÉANSTALT\nAB\n\nPnr 601 05\n\nNorrköping 1, Torsgränd 15. Box\n404. Tel 011-12 10 50, 13 78 30.\nBankgiro 550-6522. Postgiro\n33836-8\n\nVerksamhet: Klichéer, teckningar,\nretuscher, matriser, plastklichéer\no offsetplåtar\n\nFilial: 58102 Linköping 1, Roxeng\n\n4. Box 216. Tel 013-13 6185\n\nAntal anställda: 30\n\nAktiekapital: 50 000\n\nÄgare o chefer: Sven Andersson,\n\nRune Svensson\n\nEtableringsår: 1914.\n\nHANSEN AB, G A\n\nPnr 217 51\n\nMalmö V, Regementsg 102. Tel\n040-707 30. Bankgiro 87-0317.\nPostgiro 430439. Tga Gapo\nVerksamhet: Agenturfirma, import\no export med tekniskt gummi,\nma-skinfömödenheter o sportartiklar\nVarunamn: Gapo, Fenter\nAntal anställda: 8\nAktiekapital: 30 000\nVerkst dir: Leif Dahlqvist\nEtableringsår: 1945.\n\nHANSER, LARSSON &amp;\nRUSTLUND AB\n\nPnr 102 44\n\nStockholm 5, Box 5166. Karlav 67.\nTel 08-63 13 15. Bankgiro\n670-4514. Postgiro 507790-4\nVerksamhet: Auktoriserad\nreklamkonsult\n\nAntal anställda: 12\nÅrsomsättning: 2 500 000\nAktiekapital: 60 000\nVerkst dir: Bengt Hanser\nEtableringsår: 1968.\n\nMITEX GLASFIBER AB\n\nPnr 250 07\n\nHelsingborg 7, Box 7017.\nRundgången 24. Tel 042-12 06 45.\nBankgiro 652-9630. Postgiro 135780-5.\nTga Svesiko. Telex 72357\nVerksamhet: Tillverkar\nglasfiber-väv\n\nVarunamn: Textoglass, Mika\nAntal anställda: 100\nÅrsomsättning: 12 000000\nAktiekapital: 500000\nStyrelse: Adv Bengt Linders (ordf),\ndir Bjarne Colbjörnsen, dir Ove\nMichaelsen\n\nVerkst din Ella Michaelsen\nEtableringsån 1937.\n\nSVENSKA NO-HA AB\n\nPnr 100 73\n\nStockholm 44, Box 44042. Tel\n08-97 40 00. Bankgiro 375-3068.\nPostgiro 2520-5. Tga Nohabolagen\nVerksamhet: Försäljning av Norsk\nHammerverk AS tillverkade produkter\nÅrsomsättning: 600 000\nAktiekapital: 10 000\nVerkst dir: Alf Hjalmarsson\nEtableringsår: 1967.\n\nSVENSKA OLJESLAGERI AB\n\nse MoDoKemi AB.\n\nSVENSKA OLYMPIA\nKONTORSMASKINER AB\n\nPnr 11634\n\nStockholm, Duvnäsg 14. Tel\n08-44 09 50. Bankgiro 731-6607.\nPostgiro 507485-1. Tga Olympiatyp\nVerksamhet: Säljer skriv-,\nadditions-, kalkylerings-,\ndikterings-o kopieringsmaskiner\nAktiekapital: 1500000\nVeikst dir: H van der Veide\nEtableringsår: 1950.\n\nDALA KEMISKA FABRIK AB\n\nPnr 710 23\n\nGlanshammar. Tel 019-653 22,\n65320.Bankgiro 796-7078.Postgiro\n287473-3\n\nVerksamhet: Tillverkar\nindustritvättmedel o sandspackel\nAktiekapital: 60 000\nVerkst dir: Nils Ch Eriksson\nEtableringsår: 1939.\n\nDALA\nSKINN-KONFEKTION, AB\n\nPnr 783 00\n\nSäter, Järnvägs g 16. Box 76. Tel\n0225-510 60. Bankgiro 238-1325.\nPostgiro 337027-7\nVerksamhet: Tillverkar o säljer\nskinnkläder\nAntal anställda: 45\nÅrsomsättning: 3 500 000\nAktiekapital: 50000\nStyrelse: Disp Arthur E Ericson,\ndir Anders Ohlsson\nVerkst dir: Anders Ohlsson\nEtableringsår: 1967.",
    "structured": {
        "1": {
            "company_name": "BYGGNADSKOMPANIET",
            "pnr": "88101",
            "address": "Sollefteå 1, Storg 24. Box 57.",
            "phone_number": "0620-107 29",
            "bank_details": {
                "postgiro": "292929"
            },
            "activity": "Sten- o trähusförsäljning, ritningar o byggnadsservice",
            "key_personnel": [
                {
                    "name": "J Sjölander",
                    "position": "Ägare o chef"
                }
            ],
            "establishment_year": 1938
        },
        "2": {
            "company_name": "BYGGNADSPLÅT I JUN KÖPING AB",
            "pnr": "552 67",
            "address": "Jönköping, Fridhemsv 29",
            "phone_number": "036-1158 80",
            "bank_details": {
                "bankgiro": "341-9686",
                "postgiro": "329177-0"
            },
            "activity": "Utför byggnadsplåt-slageriarbeten samt reparationer",
            "employees": 11,
            "annual_turnover": 700000,
            "capital": 12000,
            "key_personnel": [
                {
                    "name": "Karl-Runo Magnusson",
                    "position": "Chef"
                },
                {
                    "name": "Egon Rydell",
                    "position": "Chef"
                }
            ],
            "establishment_year": 1962
        },
        "3": {
            "company_name": "GRANZOW AB",
            "pnr": "571 00",
            "address": "Nässjö, Box 116. Tryckerig 10",
            "phone_number": "0380-12060, 120 61",
            "bank_details": {
                "bankgiro": "153-5913",
                "postgiro": "636125-7"
            },
            "activity": "Styr- o reglerteknik. Importerar tryckluftutrustningar, ventiler, cylindrar, kopplingar o rör, luftserviceutrustningar, filter o luftsmörjare, magnetventiler för luft, hydraulik o aggressiva media, plast- o vacuumslang, kompressorer samt universalcylindrar",
            "employees": 3,
            "annual_turnover": 1000000,
            "capital": 10000,
            "key_personnel": [
                {
                    "name": "Peter Granzow",
                    "position": "Verkst dir"
                },
                {
                    "name": "Berndt Svensson",
                    "position": "Platschef"
                }
            ],
            "establishment_year": 1968
        },
        "4": {
            "company_name": "GARPENDAL INGENJORS-BYRA AB",
            "pnr": "127 43",
            "address": "Skärholmen, Storholmsbackarna 90",
            "phone_number": "08-7102432, 7102433",
            "bank_details": {
                "bankgiro": "626-4766",
                "postgiro": "609020-3"
            },
            "activity": "Marknadsför utrustaningar för processkontroll",
            "employees": 5,
            "annual_turnover": 2000000,
            "capital": 10000,
            "key_personnel": [
                {
                    "name": "Dir B Grapendal",
                    "position": "Chef"
                }
            ],
            "establishment_year": 1967
        },
        "5": {
            "company_name": "FUNDAHN & CO FÄRGFABRIK",
            "pnr": "27100",
            "address": "Ystad, Besökaregränd 2",
            "phone_number": "0411-13670",
            "bank_details": {
                "bankgiro": "87-3200",
                "postgiro": "30974"
            },
            "activity": "Tillverkar o säljer olje-, lack-, plast- o maskinfärger",
            "employees": 4,
            "key_personnel": [
                {
                    "name": "Ake Lindhoff",
                    "position": "Ägare o chef"
                }
            ],
            "establishment_year": 1921
        },
        "6": {
            "company_name": "BERGGREN & SON AB, AUG",
            "pnr": "11351",
            "address": "Stockholm, Luntmakarg 86-88",
            "phone_number": "08-3144 03, 314404",
            "bank_details": {
                "bankgiro": "167-0322",
                "postgiro": "3091-6"
            },
            "activity": "Målerirörelse i kommission",
            "capital": 10000,
            "key_personnel": [
                {
                    "name": "Ivan Gustavsson",
                    "position": "Verkst dir"
                }
            ],
            "establishment_year": 1946
        },
        "7": {
            "company_name": "BERGGRENS MEK VERKSTAD, AB AXEL",
            "pnr": "431 35",
            "address": "Mölndal, Agatan",
            "phone_number": "031-27 2741, 27 27 4 2",
            "bank_details": {
                "bankgiro": "505-7567",
                "postgiro": "48650-6"
            },
            "activity": "Specialfirma för tillverkning av kugghjul, kuggstänger o snäckväxlar",
            "employees": 20,
            "key_personnel": [
                {
                    "name": "Fabr Axel Berggren",
                    "position": "Verkst dir"
                }
            ],
            "establishment_year": 1923
        },
        "8": {
            "company_name": "JENSSEN & CO AB, G M",
            "pnr": "41110",
            "address": "Göteborg, O Hamng 19",
            "phone_number": "031-13 88 12, 13 88 14",
            "activity": "Säljer asbestcement-rör m m",
            "varunamn": "Itälit",
            "key_personnel": [
                {
                    "name": "Knut Jénssen",
                    "position": "Verkst dir"
                }
            ],
            "establishment_year": 1931
        },
        "9": {
            "company_name": "LANGE AB, H & S",
            "pnr": "80105",
            "address": "Gävle 1, Màsbergsv 9. Box 384.",
            "phone_number": "026-12 29 19",
            "bank_details": {
                "bankgiro": "60-3550",
                "postgiro": "341492-7"
            },
            "activity": "Generalagent för UTP svetsmaterial",
            "key_personnel": [
                {
                    "name": "Dir H Lange",
                    "position": "Chef"
                }
            ],
            "establishment_year": 1968
        },
        "10": {
            "company_name": "LANGE AB, L J",
            "pnr": "40231",
            "address": "Göteborg 7, Värmlandsg 16. Box 7015",
            "phone_number": "031-12 44 05",
            "bank_details": {
                "bankgiro": "84-5902",
                "postgiro": "12040"
            },
            "activity": "Grossist i optik",
            "employees": 30,
            "capital": 300000,
            "key_personnel": [
                {
                    "name": "Gunnar Schramm",
                    "position": "Verkst dir"
                }
            ],
            "establishment_year": 1881
        },
        "11": {
            "company_name": "LANGERS KLICHÉANSTALT AB",
            "pnr": "601 05",
            "address": "Norrköping 1, Torsgränd 15. Box 404",
            "phone_number": "011-12 10 50, 13 78 30",
            "bank_details": {
                "bankgiro": "550-6522",
                "postgiro": "33836-8"
            },
            "activity": "Klichéer, teckningar, retuscher, matriser, plastklichéer o offsetplåtar",
            "filial": "58102 Linköping 1, Roxeng 4. Box 216. Tel 013-13 6185",
            "employees": 30,
            "capital": 50000,
            "key_personnel": [
                {
                    "name": "Sven Andersson",
                    "position": "Ägare o chefer"
                },
                {
                    "name": "Rune Svensson",
                    "position": "Ägare o chefer"
                }
            ],
            "establishment_year": 1914
        },
        "12": {
            "company_name": "HANSEN AB, G A",
            "pnr": "217 51",
            "address": "Malmö V, Regementsg 102",
            "phone_number": "040-707 30",
            "bank_details": {
                "bankgiro": "87-0317",
                "postgiro": "430439"
            },
            "activity": "Agenturfirma, import o export med tekniskt gummi, ma-skinfömödenheter o sportartiklar",
            "varunamn": "Gapo, Fenter",
            "employees": 8,
            "capital": 30000,
            "key_personnel": [
                {
                    "name": "Leif Dahlqvist",
                    "position": "Verkst dir"
                }
            ],
            "establishment_year": 1945
        },
        "13": {
            "company_name": "HANSER, LARSSON & RUSTLUND AB",
            "pnr": "102 44",
            "address": "Stockholm 5, Box 5166. Karlav 67",
            "phone_number": "08-63 13 15",
            "bank_details": {
                "bankgiro": "670-4514",
                "postgiro": "507790-4"
            },
            "activity": "Auktoriserad reklamkonsult",
            "employees": 12,
            "annual_turnover": 2500000,
            "capital": 60000,
            "key_personnel": [
                {
                    "name": "Bengt Hanser",
                    "position": "Verkst dir"
                }
            ],
            "establishment_year": 1968
        },
        "14": {
            "company_name": "MITEX GLASFIBER AB",
            "pnr": "250 07",
            "address": "Helsingborg 7, Box 7017. Rundgången 24",
            "phone_number": "042-12 06 45",
            "bank_details": {
                "bankgiro": "652-9630",
                "postgiro": "135780-5"
            },
            "activity": "Tillverkar glasfiber-väv",
            "varunamn": "Textoglass, Mika",
            "employees": 100,
            "annual_turnover": 12000000,
            "capital": 500000,
            "key_personnel": [
                {
                    "name": "EllA Michaelsen",
                    "position": "Verkst din"
                }
            ],
            "establishment_year": 1937
        },
        "15": {
            "company_name": "SVENSKA NO-HA AB",
            "pnr": "100 73",
            "address": "Stockholm 44, Box 44042",
            "phone_number": "08-97 40 00",
            "bank_details": {
                "bankgiro": "375-3068",
                "postgiro": "2520-5"
            },
            "activity": "Försäljning av Norsk Hammerverk AS tillverkade produkter",
            "annual_turnover": 600000,
            "capital": 10000,
            "key_personnel": [
                {
                    "name": "Alf Hjalmarsson",
                    "position": "Verkst dir"
                }
            ],
            "establishment_year": 1967
        },
        "16": {
            "company_name": "SVENSKA OLYMPIA KONTORSMASKINER AB",
            "pnr": "11634",
            "address": "Stockholm, Duvnäsg 14",
            "phone_number": "08-44 09 50",
            "bank_details": {
                "bankgiro": "731-6607",
                "postgiro": "507485-1"
            },
            "activity": "Säljer skriv-, additions-, kalkylerings-, dikterings-o kopieringsmaskiner",
            "capital": 1500000,
            "key_personnel": [
                {
                    "name": "H van der Veide",
                    "position": "Verkst dir"
                }
            ],
            "establishment_year": 1950
        },
        "17": {
            "company_name": "DALA KEMISKA FABRIK AB",
            "pnr": "710 23",
            "address": "Glanshammar",
            "phone_number": "019-653 22, 65320",
            "bank_details": {
                "bankgiro": "796-7078",
                "postgiro": "287473-3"
            },
            "activity": "Tillverkar industritvättmedel o sandspackel",
            "capital": 60000,
            "key_personnel": [
                {
                    "name": "Nils Ch Eriksson",
                    "position": "Verkst dir"
                }
            ],
            "establishment_year": 1939
        },
        "18": {
            "company_name": "DALA SKINN-KONFEKTION, AB",
            "pnr": "783 00",
            "address": "Säter, Järnvägs g 16. Box 76",
            "phone_number": "0225-510 60",
            "bank_details": {
                "bankgiro": "238-1325",
                "postgiro": "337027-7"
            },
            "activity": "Tillverkar o säljer skinnkläder",
            "employees": 45,
            "annual_turnover": 3500000,
            "capital": 50000,
            "key_personnel": [
                {
                    "name": "Disp Arthur E Ericson",
                    "position": "Styrelse"
                },
                {
                    "name": "Anders Ohlsson",
                    "position": "Styrelse"
                },
                {
                    "name": "Anders Ohlsson",
                    "position": "Verkst dir"
                }
            ],
            "establishment_year": 1967
        }
    }
}