{
    "original": "SVENSKA PANG AB\n\nPnr 17104\n\nSolna 4, Framnäsbacken 14. Box\n430. Tel 08-83 03 80. Bankgiro\n58-1219. Postgiro 648064. Tga Svepang\nVerksamhet Försäljning av\nkemiskt vulkaniserande\nreparationsmaterial, domkrafter,\nmonteringsmaskiner, balansering smaskiner,\nbalansvikter, ventiler m m\nAntal anställda: 8\nAktiekapital: 200 000\nVerkst din Hans-Ola Claeson\nEtableringsår: 1964.\n\nSVENSKA PAPPERSBRUKENS\nHANDELS AB\n\nPnr 114 32\n\nStockholm, Villag 1. Tel\n08-22 1700. Bankgiro 560-4764.\nPostgiro 153015-3. Tga Swapco.\nTelex 1519\n\nVerksamhet: Import av råvaror för\npappers- o cellulosaindustrierna\nAktiekapital: 1500 000\nVerkst dir P-G Albrechtsson\nEtableringsår: 1917.\n\nSVENSKA PERSONAL.\nPENSIONSKASSAN (SPP)\n\nPnr 103 82\n\nStockholm 7, Nybrog 11. Box 7052.\n\nTel 08-2238 00. Tga Pension\nVerksamhet:\nTjänstepensionsförsäkring o därtill knuten\ngrupplivförsäkring\n\nAntal anställda: 350\nStyrelse: Justitierådet G Lind\n(ordf), dir S Hammarskiöld, dir G\nJohansson, dir E Bendz,\nförbunds-ordf S Eriksson, disp L Gabrielson,\ndir C-S Giesecke, förbundsordf R\nLindforss, dir G Nilsson,\nförbunds-dir A Nilstein, övering R Thorburn,\nbankdir M Wallenberg, dir G Winberg\nVerkst dir Erik Bendz\nV verkst dir:r N-A Frisk, G Larsson\nChefaktuarie: G Larsson\nEtableringsår 1917.\n\nSEGEBADEN.BERG AB\n\nPnr 783 00\n\nSäter, Fack 65. Tel 0225-50015.\nBankgiro 798-7076. Postgiro\n27755-8\n\nVerksamhet: Tillverkar pulkor o\ntillbehör\n\nAntal anställda: 8\nÅrsomsättning: 1000 000.\n\nSEGEMANS\nSKINNVARU-FABRIK AB\n\nPnr 570 31\n\nIngatorp, Kyrkog 9. Tel 0381-212 00.\nBankgiro 468-4973. Postgiro\n115483-0\n\nVeiksamhet: Modeinriktad\ntillverkning av skinnkläder\nAntal anställda: 15\nAktiekapital: 50 000\nVeikst dir: Fabr Olof Segeman\nEtableringsår: 1956-\n\nDJUPAFORS FABRIKS AB\n\nPnr 373 00\n\nKallinge. Tel 0457-129 00.\nTga Indju, Ronneby.\nTelex 4514 IDMILLS S\nVerksamhet: Kartongfabrik o\nträsliperi. Tillverkar papp o kartong\nAntal anställda: 230\nAktiekapital: 4000 000\nStyrelse: Adv Sture Hovden (ordf),\ndir Göran Langenskiöld, dir Gösta\nLönn, bankdir Harald Magnusson\nVerkst dir: Gösta Lönn\nDriftsing: Stig Lindén\nInköp: Olle Danielsson\nEkonomiavd: Karl-Erik Warner\nFörsäljningsavd: Inland-Djupafors\nExport: Gunnar Sjöberger.Leif Dahl\nFörsäljningsavd: Sverige, Danmark:\nGösta Elifors\nEtableringsår: 1868.\n\nRIN\n\n6116. Postgiro 58035. Tga Rindab\nVeiksamhet: Försäljning genom\nmoderbolaget Rima AB\nAktiekapital: 30 000\nVerkst dir: Ake Dunér\nEtableringsår: 1930\nDotterbolag till Rima AB.\n\nRINDEBORG AB, BRÖDERNA\n\nPnr 42131\n\nVästra Frölunda, Frökontrollg 6.\nTel 031-4 5 77 70, 45 77 71.\nBankgiro 36-4836. Postgiro 241329\nVerksamhet: Plast o metallindustri\nAntal anställda: 20\nÅrsomsättning: 150 0 000\nAktiekapital: 60 000\nChefer: Gösta Rindeborg, Tor\nRindeborg, Ake Rindeborg\nEtableringsår: 1946.\n\nRINGBERG &amp; GUSTAFSSON,\nAB\n\nPnr 360 52\n\nKosta. Tel 0478-500 61, 503 72.\nBankgiro 29-2660. Postgiro 130193\nVeiksamhet: Elektrisk\nbelysningsarmatur\n\nAntal anställda: 16\nÅrsomsättning: 2 000 000\nAktiekapital: 120 000\nChef: Disp Isidor Ringberg\nEtableringsår: 1934\nOmbildat till aktiebolag 1960.\n\nRINGBLOM AB, CARL GUST\n\nPnr 871 01\n\nHärnösand 1, Skeppsbron 21. Box 11.\nTel 0611-124 90. Tga Ringblom.\nTelex 71039\n\nVerksamhet: Skeppsklarerare\nVerkst din C A Ringblom\nEtableringsår: 1842.\n\nBYG\n\nBYGG &amp; GOLVTJÄNST\nI GÄVLE AB\n\nPnr 80104\n\nGävle 1, Box 233. S Fiskarg 3. Tel\n026-110638, 1132 50, 11 29 09.\nPostgiro 367044-5\nVerksamhet: Säljer\nheltäckningsmattor, plastmattor, plastfiltmattor,\nväggmattor o tapeter. Utför\ngolventreprenader\nAntal anställda: 15\nÅrsomsättning: 1500 000\nAktiekapital: 15 000\nStyrelse: Dir Sven Olof Jansson\n(ordf), dir David N Jansson\nVerkst dir: Sven Olof Jansson,\nD N Jansson\nEtableringsår: 1954\nDotterbolag: Gävleborgs\nGolvmarknad.\n\nBYGG- o\nINREDNINGS-ARTIKLAR, AB\n\nPnr 42131\n\nVästra Frölunda, Frörensareg 6.\nTel 031-45 07 75. Bankgiro\n853-0180. Postgiro 521426-7\nVerksamhet: Specialfirma för\nträlister o paneler i in- o utländska\nträslag, även färdigmålade\nAntal anställda: 7\nÅrsomsättning: 1500 000\nAktiekapital: 50 000\nÄgare o chefer. Bertil Melander,\nRyno Andréasson\nEtableringsår 1960.\n\nBYGG- och TRANSPORT.\nEKONOMI (BT), AB\n\nPnr 16111\n\nBromma 11, Fack. Masungsv 28.\nTel 08-9814 00. Tga Byggekonomi.\nTelex 19052 BETE S\nVerksamhet: Gaffeltruckar,\ngrän-sletruckar, sopmaskiner,\nlastmaskiner, hydraulgrävare, skogstraktorer,\nmobilkranar, staplare o lyftvagnar\nFabrik: Mjölby, Svarvarg 8. Tel\n0142-132 00. Telex 5579 bete\nmjoelby. Tga Byggekonomi.\nTillverkar o säljer gaffelstaplare,\nlyftvagnar, hydrauliska\nverkstadslyft-bord, telfergafflar o lyftdon. Dir\nKarl-Eric Andersson\nVarunamn: BT, Clark, Clark-Hoss,\nDustbane, Fiat, Grove, Liebherr,\nSkytrak, Tennant, Timberjack, Yale\nAntal anställda: 1100\nÅrsomsättning: 149 000 000\nAktiekapital: 1500 000\nStyrelse: Dir Kurt Lindfors, dir\nF Gunnar Ekman, dir Karl-Axel\nLinderoth, dir H Harry Hjalmarson,\ndir John Sallborg, dir Bertil Tronët,\ndir Nils Thedin\nVerkst dir: Ivan F Lundquist\nEtableringsår: 1946.\n\nNILSSON &amp; SUNER AB, E\n\nPnr 75104\n\nUppsala 1, Dragarbrunnsg 50. Box\n132. Tel 018-13 95 50. Bankgiro\n23-0018. Postgiro 72225\nVerksamhet: Auktoriserad\nrörled-ningsentreprenör\nAktiekapital: 50 000\nVerkst dir: Harry Ellemo\nEtableringsår: 1938.\n\nHUD\n\ninstallationsmaterial, svets- o\nskäraggregat samt utrustningar för\ndessa. Utför sanitära installationer,\nrörledningsentreprenader m m\nVerkst dir: E Berglund\nEtableringsår: 1931.\n\nHUDSON ST RUMP.\nFABRIKER AB\n\nPnr 60101\n\nNorrköping j, Hagag 6. Fack. Tel\n011-12 93 85. Bankgiro 63-1303.\nPostgiro 10084. Telex 64196. Tga\nHudsonstocking\n\nVerksamhet: Tillverkar o säljer\ndamstrumpor\nAntal anställda: 170\nAktiekapital: 400 000\nVerkst dir: Jan-Olof Berglund\nEtableringsår: 1964.\n\nSYNTES, AB\n\nPnr 440 41\n\nNol. Tel 0303-404 40. Telex 2438.\nTga Syntes\n\nVerksamhet: Tillverkar eter,\nftal-syraanhydrid, ftalsyraestrar,\npoly-esterharts mm\nAktiekapital: 500000\nStyrelse: Generalkonsul Nils\nSterner (ordf), dir Ake Roos, dir W\nSöderman, bankdir Sten Wetter, tekn\ndr Ragnar Winbladh\nVerkst dir: Erik Hammerlund\n(Uppsala)\n\nFabrikschef: Dir S Nilsson\nEtableringsår: 1913\nDotterbolag till Upsala-Ekeby AB,\nUppsala.\n\nSYRABRUK, AB\n\nPnr 17124\n\nSolna 1, Box 1250. V Vägen 11 A.\nTel 08-730 03 40. Bankgiro\n722-3514. Postgiro 15054-7. Tga\nSyrabrak, Stockholm.\nTelex 10306 RAMIT S\nVerksamhet: Tillverkar o säljer\nsyrafasta murmassor o syrafasta\nmurningar o gummibeklädnader.\nSäljer korrosions- o\nvärmebeständiga legeringar o metaller\nVarunamn: Hastelloy\nAktiekapital: 50 000\nStyrelseordf: Dir Fritz Ramström\nVeikst din Civiling Hans V\nFriberg\n\nEtableringsår: 1939.\n\nSUNDSVALLS RUR AB\n\nPnr 851 03\n\nSundsvall 1, S Järnvägsg 11. Box\n134. Tel 060-15 78 65\nVerksamhet: Entreprenör för\nvärme, vatten o sanitet\nAktiekapital: 100000\nVerkst dir: K H Eriksson\nEtableringsår: 1944.\n\nFRITZNER &amp; CO AB\n\nPnr 11157\n\nStockholm, Sveav 17. Tel\n08-116922, 116923. Bankgiro\n16-0628. Postgiro 554615. Telex 1689\nFERRO S. Tga Anfri\nVerksamhet: Agenturverksamhet i\njärnmalm samt järn o stål\nAktiekapital: 100 000\nVerkst dir: Jan Fritzner\nEtableringsår: 1948.\n\nFRITZSON &amp; CARLSSON\nSTOLFABRIK\n\nPnr 523 00\n\nUlricehamn, Jönköpingsv 57. Box\n130.Tel0321-105 50, 105 54.\nBankgiro 532-8018. Postgiro 142017-3\nVeiksamhet: Tillverkning av\nstolar o karmstolar\nAntal anställda: 14\nÅrsomsättning: 1000 000\nChef: Fabr Olof Fritzson\nEtableringsår: 1936.",
    "structured": {
        "1": {
            "company_name": "SVENSKA PANG AB",
            "pnr": "17104",
            "address": "Solna 4, Framnäsbacken 14. Box 430",
            "phone_number": "08-83 03 80",
            "bank_details": {
                "bankgiro": "58-1219",
                "postgiro": "648064"
            },
            "activity": "Försäljning av kemiskt vulkaniserande reparationsmaterial, domkrafter, monteringsmaskiner, balansering smaskiner, balansvikter, ventiler m m",
            "employees": 8,
            "capital": 200000,
            "key_personnel": [
                {
                    "name": "Hans-Ola Claeson",
                    "position": "Verkst din"
                }
            ],
            "establishment_year": 1964
        },
        "2": {
            "company_name": "SVENSKA PAPPERSBRUKENS HANDELS AB",
            "pnr": "114 32",
            "address": "Stockholm, Villag 1",
            "phone_number": "08-22 1700",
            "bank_details": {
                "bankgiro": "560-4764",
                "postgiro": "153015-3"
            },
            "activity": "Import av råvaror för pappers- o cellulosaindustrierna",
            "capital": 1500000,
            "key_personnel": [
                {
                    "name": "P-G Albrechtsson",
                    "position": "Verkst dir"
                }
            ],
            "establishment_year": 1917
        },
        "3": {
            "company_name": "SVENSKA PERSONAL. PENSIONSKASSAN (SPP)",
            "pnr": "103 82",
            "address": "Stockholm 7, Nybrog 11. Box 7052",
            "phone_number": "08-2238 00",
            "activity": "Tjänstepensionsförsäkring o därtill knuten grupplivförsäkring",
            "employees": 350,
            "key_personnel": [
                {
                    "name": "Erik Bendz",
                    "position": "Verkst dir"
                },
                {
                    "name": "N-A Frisk",
                    "position": "V verkst dir:r"
                },
                {
                    "name": "G Larsson",
                    "position": "V verkst dir:r"
                }
            ],
            "establishment_year": 1917
        },
        "4": {
            "company_name": "SEGEBADEN.BERG AB",
            "pnr": "783 00",
            "address": "Säter, Fack 65",
            "phone_number": "0225-50015",
            "bank_details": {
                "bankgiro": "798-7076",
                "postgiro": "27755-8"
            },
            "activity": "Tillverkar pulkor o tillbehör",
            "employees": 8,
            "annual_turnover": 1000000
        },
        "5": {
            "company_name": "SEGEMANS SKINNVARU-FABRIK AB",
            "pnr": "570 31",
            "address": "Ingatorp, Kyrkog 9",
            "phone_number": "0381-212 00",
            "bank_details": {
                "bankgiro": "468-4973",
                "postgiro": "115483-0"
            },
            "activity": "Modeinriktad tillverkning av skinnkläder",
            "employees": 15,
            "capital": 50000,
            "key_personnel": [
                {
                    "name": "Fabr Olof Segeman",
                    "position": "Veikst dir"
                }
            ],
            "establishment_year": "1956-"
        },
        "6": {
            "company_name": "DJUPAFORS FABRIKS AB",
            "pnr": "373 00",
            "address": "Kallinge",
            "phone_number": "0457-129 00",
            "activity": "Kartongfabrik o träsliperi. Tillverkar papp o kartong",
            "employees": 230,
            "capital": 4000000,
            "key_personnel": [
                {
                    "name": "Gösta Lönn",
                    "position": "Verkst dir"
                },
                {
                    "name": "Stig Lindén",
                    "position": "Driftsing"
                },
                {
                    "name": "Olle Danielsson",
                    "position": "Inköp"
                }
            ],
            "establishment_year": 1868
        },
        "7": {
            "company_name": "RIN",
            "pnr": "6116",
            "activity": "Försäljning genom moderbolaget Rima AB",
            "capital": 30000,
            "key_personnel": [
                {
                    "name": "Ake Dunér",
                    "position": "Verkst dir"
                }
            ],
            "establishment_year": 1930,
            "remarks": "Dotterbolag till Rima AB."
        },
        "8": {
            "company_name": "RINDEBORG AB, BRÖDERNA",
            "pnr": "42131",
            "address": "Västra Frölunda, Frökontrollg 6",
            "phone_number": "031-4 5 77 70, 45 77 71",
            "bank_details": {
                "bankgiro": "36-4836",
                "postgiro": "241329"
            },
            "activity": "Plast o metallindustri",
            "employees": 20,
            "annual_turnover": 150000,
            "capital": 60000,
            "key_personnel": [
                {
                    "name": "Gösta Rindeborg",
                    "position": "Chefer"
                },
                {
                    "name": "Tor Rindeborg",
                    "position": "Chefer"
                },
                {
                    "name": "Ake Rindeborg",
                    "position": "Chefer"
                }
            ],
            "establishment_year": 1946
        }
    }
}