{
    "original": "BARKLUND &amp; CO AB, A\n\nPnr 124 42\n\nBandhagen, Bjursätrag 62. Tel\n08-86 0 2 30. Bankgiro 72-2113. Postgiro\n150488. Tga Abacomp\nVerksamhet: Säljer kontors- o\nrit-material. Importörer o agenter i\nritpapper o specialartiklar\nAntal anställda: 12\nAktiekapital: 60 000\nStyrelse: Dir Bertil Wirström (ordf),\nfru Karin Wirström, disp Tage\nWirström\n\nVerkst dir: Bertil Wirström\nEtableringsår: 1936.\n\nBOSTIK AB\n\nPnr 25101\n\nHelsingborg 1, Fack. Strandbadsv.\nTel 042-14 40 00. Bankgiro\n445-4658. Postgiro 5566-5. Tga Bostik.\nTelex 72263\n\nVerksamhet: Lim o fogmassor för\nhantverk o industri. Kemiska\nbygg-produkter. Skovårdsmedel o\nhushållsprodukter\n\nFörsäljningskontor: 100 63\nStockholm 35, Fack. Finnbodav 2. Tel\n08-44 03 30\n\nVarunamn: Bostik, Boston, Cemen-\n\ntex, Viking\n\nAntal anställda: 240\n\nÅrsomsättning: 41 000 000 (inkl\n\ndotterbolag)\n\nAktiekapital: 3 500 000\n\nVerkst dir: G Nilsson\n\nEtableringsår: 1911.\n\nBOSTROM &amp; BOSTROM,\nVERKSTADS AB\n\nPnr 612 00\n\nFinspång. Tel 0122-104 51,10651\n\nBO-BO\n\nBOSTRÖM « BOSTRÖM.\n\nVerksamhet: Tillverkar förarhytter\ntill truckar o lastmaskiner\nAntal anställda: 25\nÅrsomsättning: 2 000 000\nAktiekapital: 50 000\nÄgare o chefer: Erik Boström,\nRune Boström\nEtableringsår: 1947\nOmbildat till aktiebolag 1963.\n\nBOSTROM &amp; CO MOTOR AB\n\nPnr 95100\n\nLuleå, Algatan 14. Tel\n0920-10180. Bankgiro 752-5363.\nPostgiro 480506-5\n\nVerksamhet: Auktoriserad\nåterförsäljare av Ford\nAntal anställda: 38\nÅrsomsättning: 9 500 000\nAktiekapital: 50 000\nVerkst dir. Felix Boström\nEtableringsår: 1964.\n\nB OST ROMS INREDNINGS O\nKYL AB\n\nPnr 343 00\n\nÄlmhult, Box 6. Bäckg. Tel\n0476-117 65, 117 66. Bankgiro 873-9443.\nPostgiro 125747-6\nVerksamhet: Tillverkar\nbarinredningar, storköks- o\nbageriinred-ningar\n\nAntal anställda: 45\nÅrsomsättning: 5 500 000\nAktiekapital: 150 000\nFörsäljn-dir: Ing Sven Johansson\nEkonomichef: Ake Palmgren\nEtableringsår: 1960.\n\nBIL &amp; BUSS I BOLLNÄS AB\n\nPnr 82100\n\nBollnäs, Framnäsv 3. Tel 0278-\n\n132 30\n\nVerksamhet: Bilar, reservdelar,\nbilverkstad o lackeringsverkstad\nAntal anställda: 83\nÅrsomsättning: 15 049 000\nAktiekapital: 1 000 000\nVerkst dir: Gösta Lindqvist\nEtableringsår: 1953.\n\nBRO\n\nBROBERG, AB HELGE\n\nPnr 931 01\n\nSkellefteå 1, Stämningsgården. Box\n122. Tel 0910-111 28. Bankgiro\n61-1720. Postgiro 485880\nVerksamhet: Tillverkar Polygon-,\nlantmäteri- o detaljmätband\nVerkst dir: Einar Ohrlund\nEtableringsår: 1923\nOmbildat till aktiebolag 1962.\n\nBROBY ARMATURFABRIK, AB\n\nPnr 280 60\n\nBroby, Box 22. Tel 044-407 40.\nBankgiro 867-3899. Postgiro\n293119-4. Tga Brobyarmatur.\nTelex 4439 BAVÄLVE S\nVerksamhet: Tillverkar rörlednings-,\nindustri- o varvsarmatur av mässing,\nrödmetall, brons, gjutjärn o\nelektro-stålgjutgods för vatten, gas, ånga,\nolja o lösningar. Specialitet:\nkompletta ventilutrustningar för\nolje-lagringsanläggningar\nAntal anställda: 85\nÅrsomsättning: 6 800000\nAktiekapital: 360 000\nStyrelse: Disp W Haajanen (ordf),\nbankkamrer Gösta Nilsson, dir\nEdvin Persson, lantbr Louis\nAndersson, lantbr Erik Bengtsson,\nlantbr Gert Svenle, lantbr Matts\nJohnsson\n\nVerkst dir: L Haajanen\nEtableringsår: 1945.\n\nHUBERTSAB,E\n\nPnr 70106\n\nÖrebro 1, Storg 21. Box 416. Tel\n019-12 02 41, 12 02 42. Bankgiro\n75-9010. Postgiro 345200\nVerksamhet: Säljer\nhushållsmaskiner\n\nAntal anställda: 14\nAktiekapital: 5 000\nVerkst dir Hubert Andersson\nEtableringsår: 1967.\n\nHUDDINGE BETONG- &amp;\nMURBRUKSFABRIK, AB\n\nPnr 14149\n\nHuddinge, Glömstav 31. Tel\n08-75740 43, 757 57 14. Bankgiro\n626-0368. Postgiro 396969-8\nVerksamhet: Tillverkar o säljer\nfa-brikstillverkad betong o murbruk\nsamt övriga kalkbrukssortiment\nAntal anställda: 13\nÅrsomsättning: 4 000 000\nAktiekapital: 50 000\nStyrelse: Mätare Rune Krantz\n(ordf), dir Sven Linder, kamrer\nKjell Pettersson, ing Valdemar\nSo-lin, lantmäst Ake Wirtén\nVerkst dir: Dir Sven Linder\nEtableringsår 1951.\n\nJÄRN-LINDGREN, AB\n\nPnr 972 00\n\nGällivare, Industrig 2. Tel\n0970-120 45. Bankgiro 754-1212.\nPostgiro 68095-9\n\nVerksamhet: Järnhandel med\nbyggnadsvaruförsäljning\nAntal anställda: 25\nÅrsomsättning: 5 000 000\nAktiekapital: 120 000\nVerkst dir. Gunnar Lindgren\nEtableringsår: 1909.\n\nTERRY-TEXTIL, AB\n\nPnr 114 51\n\nStockholm, Strandv 5 B. Tel\n08-639105. Bankgiro 72-8500.\nPostgiro 656421\n\nVerksamhet: Tillverkar o säljer\nplastbelagd frotté o artiklar därav\nAktiekapital: 10 000\nVerkst dir Fru Harriet Horwitz\nEtableringsår: 1961.\n\nekman, haglund ab\n\nPnr 692 00\n\nKumla. Box 16. Sveav 6. Tel\n019-792 30. Bankgiro 60-6017. Postgiro\n8217. Tga Haglundssko\nVerksamhet: Säljer skor i parti\nfrån svenska o utländska fabriker\nAntal anställda: 14\nAktiekapital: 150000\nVerkst dir: Finn Haglund\nEtableringsår: 1914\nOmbildat till aktiebolag 1942.\n\nekmans kartong ab\n\nPnr 552 67\n\nJönköping, Kämpev 32. Tel 036-\n\n1194 70. Bankgiro 342-0536.\nPostgiro 36878-7\n\nVerksamhet: Kartong- o påsfabrik.\nFlexo-, bok- o offsettryckeri\nAntal anställda: 40\nÅrsomsättning: 5 000 000\nAktiekapital: 10 000\nFirmatecknare: A Billing, L Billing\nEtableringsår: 1927.\n\nBYGGSTÅL AB\n\nPnr 652 21\n\nKarlstad, Sågverksg 45. Tel\n054-15 55 45, 15 55 50. Bankgiro\n881-5632. Postgiro 581872-9\n\nBYGG STÅL\n\nVerksamhet: Stålkonstruktioner.\nIndustriportar o -fönster.\nMellanväggar av stål. Byggnadssmide o\ngrovplåtsarbeten\nVerkst dir: Harry Södergren\nEtableringsår: 1961.\n\nBYGGTJÄNST I\nJÖNKÖPING AB\n\nPnr 550 03\n\nJönköping 3, Materialv 4. Box\n3143. Tel 036-11 93 95. Bankgiro\n544-9145. Postgiro 84930-7. Tga\nByggtjänst\n\nVerksamhet: Säljer maskiner för\nbyggnadsindustrin, fönster-,\ndörr-o inredningssnickerier,\nbranddörrar o skyddsrumsmaterial\nEtableringsår: 1945.\n\nHAGRA AB\n\nPnr 50108\n\nBorås 1, Björkhyddan 2,\nFunning-en. Box 491. Tel 033-52110,\n52120. Bankgiro 839-3308.\nPostgiro 367915-6\n\nVerksamhet: Tillverkar\nstrumpbyxor, barn- o dam\nAntal anställda: 13\n\nÅrsomsättning: 900 000\nVerkst dir: Stefan Josef Gradder\nEtableringsår: 1954.\n\n[-HAGSONSDAMKONFEK-TION,-]\n\n{+HAGSONSDAMKONFEK-\nTION,+} AB\n\nPnr 502 44\n\nBorås, Neumansg 46. Tel\n033-1275 35\n\nVerksamhet: Tillverkar kappor o\ndräkter\n\nAntal anställda: 125\nÅrsomsättning: 10 000 000\nAktiekapital: 100 000\nVerkst din Tage Gunnarsson\nEtableringsår. 1946.\n\nHAGSTRÖM &amp; KLINGA\nINGENJORSBYRÄ\n\nPnr 11122\n\nStockholm. Tunnelg 25. Tel\n08-21 1707, 20 33 37. Postgiro 455003\nVerksamhet: Konsulterande\nverksamhet VVS\n\nChef: Ing Sven A Klinga\nEtableringsår. 1937.",
    "structured": {
        "1": {
            "company_name": "BARKLUND & CO AB",
            "address": "Bjursätrag 62, Bandhagen",
            "phone_number": "08-86 0 2 30",
            "bank_details": {
                "bankgiro": "72-2113",
                "postgiro": "150488"
            },
            "activity": "Säljer kontors- o rit-material. Importörer o agenter i ritpapper o specialartiklar",
            "employees": 12,
            "capital": 60000,
            "key_personnel": [
                {
                    "name": "Dir Bertil Wirström",
                    "position": "ordf"
                },
                {
                    "name": "fru Karin Wirström"
                },
                {
                    "name": "disp Tage Wirström"
                },
                {
                    "name": "Bertil Wirström",
                    "position": "Verkst dir"
                }
            ],
            "establishment_year": 1936
        },
        "2": {
            "company_name": "BOSTIK AB",
            "address": "Helsingborg 1, Fack. Strandbadsv.",
            "phone_number": "042-14 40 00",
            "bank_details": {
                "bankgiro": "445-4658",
                "postgiro": "5566-5"
            },
            "activity": "Lim o fogmassor för hantverk o industri. Kemiska bygg-produkter. Skovårdsmedel o hushållsprodukter",
            "employees": 240,
            "annual_turnover": 41000000,
            "capital": 350000,
            "key_personnel": [
                {
                    "name": "G Nilsson",
                    "position": "Verkst dir"
                }
            ],
            "establishment_year": 1911
        },
        "3": {
            "company_name": "BOSTROM & BOSTROM, VERKSTADS AB",
            "address": "Finspång",
            "phone_number": "0122-104 51,10651",
            "activity": "Tillverkar förarhytter till truckar o lastmaskiner",
            "employees": 25,
            "annual_turnover": 2000000,
            "capital": 50000,
            "key_personnel": [
                {
                    "name": "Erik Boström",
                    "position": "Ägare o chefer"
                },
                {
                    "name": "Rune Boström",
                    "position": "Ägare o chefer"
                }
            ],
            "establishment_year": 1947
        },
        "4": {
            "company_name": "BOSTROM & CO MOTOR AB",
            "address": "Luleå, Algatan 14",
            "phone_number": "0920-10180",
            "bank_details": {
                "bankgiro": "752-5363",
                "postgiro": "480506-5"
            },
            "activity": "Auktoriserad återförsäljare av Ford",
            "employees": 38,
            "annual_turnover": 9500000,
            "capital": 50000,
            "key_personnel": [
                {
                    "name": "Felix Boström",
                    "position": "Verkst dir"
                }
            ],
            "establishment_year": 1964
        },
        "5": {
            "company_name": "BOSTROMS INREDNINGS O KYL AB",
            "address": "Älmhult, Box 6. Bäckg.",
            "phone_number": "0476-117 65, 117 66",
            "bank_details": {
                "bankgiro": "873-9443",
                "postgiro": "125747-6"
            },
            "activity": "Tillverkar barinredningar, storköks- o bageriinred-ningar",
            "employees": 45,
            "annual_turnover": 5500000,
            "capital": 150000,
            "key_personnel": [
                {
                    "name": "Ing Sven Johansson",
                    "position": "Försäljn-dir"
                },
                {
                    "name": "Ake Palmgren",
                    "position": "Ekonomichef"
                }
            ],
            "establishment_year": 1960
        },
        "6": {
            "company_name": "BIL & BUSS I BOLLNÄS AB",
            "address": "Bollnäs, Framnäsv 3",
            "phone_number": "0278-132 30",
            "activity": "Bilar, reservdelar, bilverkstad o lackeringsverkstad",
            "employees": 83,
            "annual_turnover": 15049000,
            "capital": 1000000,
            "key_personnel": [
                {
                    "name": "Gösta Lindqvist",
                    "position": "Verkst dir"
                }
            ],
            "establishment_year": 1953
        },
        "7": {
            "company_name": "BROBERG, AB HELGE",
            "address": "Skellefteå 1, Stämningsgården. Box 122",
            "phone_number": "0910-111 28",
            "bank_details": {
                "bankgiro": "61-1720",
                "postgiro": "485880"
            },
            "activity": "Tillverkar Polygon-, lantmäteri- o detaljmätband",
            "employees": 0,
            "capital": 0,
            "key_personnel": [
                {
                    "name": "Einar Ohrlund",
                    "position": "Verkst dir"
                }
            ],
            "establishment_year": 1923
        },
        "8": {
            "company_name": "BROBY ARMATURFABRIK, AB",
            "address": "Broby, Box 22",
            "phone_number": "044-407 40",
            "bank_details": {
                "bankgiro": "867-3899",
                "postgiro": "293119-4"
            },
            "activity": "Tillverkar rörlednings-, industri- o varvsarmatur av mässing, rödmetall, brons, gjutjärn o elektro-stålgjutgods för vatten, gas, ånga, olja o lösningar",
            "employees": 85,
            "annual_turnover": 6800000,
            "capital": 360000,
            "key_personnel": [
                {
                    "name": "Disp W Haajanen",
                    "position": "Styrelse"
                },
                {
                    "name": "bankkamrer Gösta Nilsson",
                    "position": "Styrelse"
                },
                {
                    "name": "dir Edvin Persson",
                    "position": "Styrelse"
                },
                {
                    "name": "lantbr Louis Andersson",
                    "position": "Styrelse"
                },
                {
                    "name": "lantbr Erik Bengtsson",
                    "position": "Styrelse"
                },
                {
                    "name": "lantbr Gert Svenle",
                    "position": "Styrelse"
                },
                {
                    "name": "lantbr Matts Johnsson",
                    "position": "Styrelse"
                },
                {
                    "name": "L Haajanen",
                    "position": "Verkst dir"
                }
            ],
            "establishment_year": 1945
        },
        "9": {
            "company_name": "TERRY-TEXTIL, AB",
            "address": "Stockholm, Strandv 5 B",
            "phone_number": "08-639105",
            "bank_details": {
                "bankgiro": "72-8500",
                "postgiro": "656421"
            },
            "activity": "Tillverkar o säljer plastbelagd frotté o artiklar därav",
            "capital": 10000,
            "key_personnel": [
                {
                    "name": "Fru Harriet Horwitz",
                    "position": "Verkst dir"
                }
            ],
            "establishment_year": 1961
        },
        "10": {
            "company_name": "ekman, haglund ab",
            "address": "Kumla, Box 16. Sveav 6",
            "phone_number": "019-792 30",
            "bank_details": {
                "bankgiro": "60-6017",
                "postgiro": "8217"
            },
            "activity": "Säljer skor i parti från svenska o utländska fabriker",
            "employees": 14,
            "capital": 150000,
            "key_personnel": [
                {
                    "name": "Finn Haglund",
                    "position": "Verkst dir"
                }
            ],
            "establishment_year": 1914
        },
        "11": {
            "company_name": "ekmans kartong ab",
            "address": "Jönköping, Kämpev 32",
            "phone_number": "036-1194 70",
            "bank_details": {
                "bankgiro": "342-0536",
                "postgiro": "36878-7"
            },
            "activity": "Kartong- o påsfabrik. Flexo-, bok- o offsettryckeri",
            "employees": 40,
            "annual_turnover": 5000000,
            "capital": 10000,
            "key_personnel": [
                {
                    "name": "A Billing",
                    "position": "Firmatecknare"
                },
                {
                    "name": "L Billing",
                    "position": "Firmatecknare"
                }
            ],
            "establishment_year": 1927
        },
        "12": {
            "company_name": "BYGGSTÅL AB",
            "address": "Karlstad, Sågverksg 45",
            "phone_number": "054-15 55 45, 15 55 50",
            "bank_details": {
                "bankgiro": "881-5632",
                "postgiro": "581872-9"
            },
            "activity": "Stålkonstruktioner. Industriportar o -fönster. Mellanväggar av stål. Byggnadssmide o grovplåtsarbeten",
            "employees": 0,
            "capital": 0,
            "key_personnel": [
                {
                    "name": "Harry Södergren",
                    "position": "Verkst dir"
                }
            ],
            "establishment_year": 1961
        },
        "13": {
            "company_name": "BYGGTJÄNST I JÖNKÖPING AB",
            "address": "Jönköping 3, Materialv 4. Box 3143",
            "phone_number": "036-11 93 95",
            "bank_details": {
                "bankgiro": "544-9145",
                "postgiro": "84930-7"
            },
            "activity": "Säljer maskiner för byggnadsindustrin, fönster-, dörr-o inredningssnickerier, branddörrar o skyddsrumsmaterial",
            "establishment_year": 1945
        },
        "14": {
            "company_name": "HAGRA AB",
            "address": "Borås 1, Björkhyddan 2, Funing-en. Box 491",
            "phone_number": "033-52110, 52120",
            "bank_details": {
                "bankgiro": "839-3308",
                "postgiro": "367915-6"
            },
            "activity": "Tillverkar strumpbyxor, barn- o dam",
            "employees": 13,
            "annual_turnover": 900000,
            "key_personnel": [
                {
                    "name": "Stefan Josef Gradder",
                    "position": "Verkst dir"
                }
            ],
            "establishment_year": 1954
        },
        "15": {
            "company_name": "HAGSONSDAMKONFEKTION, AB",
            "address": "Borås, Neumansg 46",
            "phone_number": "033-1275 35",
            "activity": "Tillverkar kappor o dräkter",
            "employees": 125,
            "annual_turnover": 10000000,
            "capital": 100000,
            "key_personnel": [
                {
                    "name": "Tage Gunnarsson",
                    "position": "Verkst dir"
                }
            ],
            "establishment_year": 1946
        },
        "16": {
            "company_name": "HAGSTRÖM & KLINGA INGENJORSBYRÄ",
            "address": "Stockholm, Tunnelg 25",
            "phone_number": "08-21 1707, 20 33 37",
            "bank_details": {
                "postgiro": "455003"
            },
            "activity": "Konsulterande verksamhet VVS",
            "key_personnel": [
                {
                    "name": "Ing Sven A Klinga",
                    "position": "Chef"
                }
            ],
            "establishment_year": 1937
        },
        "17": {
            "company_name": "HUBERTSAB,E",
            "address": "Örebro 1, Storg 21, Box 416",
            "phone_number": "019-12 02 41, 12 02 42",
            "bank_details": {
                "bankgiro": "75-9010",
                "postgiro": "345200"
            },
            "activity": "Säljer hushållsmaskiner",
            "employees": 14,
            "capital": 5000,
            "key_personnel": [
                {
                    "name": "Hubert Andersson",
                    "position": "Verkst dir"
                }
            ],
            "establishment_year": 1967
        },
        "18": {
            "company_name": "HUDDINGE BETONG- & MURBRUKSFABRIK, AB",
            "address": "Huddinge, Glömstav 31",
            "phone_number": "08-75740 43, 757 57 14",
            "bank_details": {
                "bankgiro": "626-0368",
                "postgiro": "396969-8"
            },
            "activity": "Tillverkar o säljer fabrikstillverkad betong o murbruk samt övriga kalkbrukssortiment",
            "employees": 13,
            "annual_turnover": 4000000,
            "capital": 50000,
            "key_personnel": [
                {
                    "name": "Mätare Rune Krantz",
                    "position": "Styrelse"
                },
                {
                    "name": "dir Sven Linder",
                    "position": "Verkst dir"
                }
            ],
            "establishment_year": 1951
        },
        "19": {
            "company_name": "JÄRN-LINDGREN, AB",
            "address": "Gällivare, Industrig 2",
            "phone_number": "0970-120 45",
            "bank_details": {
                "bankgiro": "754-1212",
                "postgiro": "68095-9"
            },
            "activity": "Järnhandel med byggnadsvaruförsäljning",
            "employees": 25,
            "annual_turnover": 5000000,
            "capital": 120000,
            "key_personnel": [
                {
                    "name": "Gunnar Lindgren",
                    "position": "Verkst dir"
                }
            ],
            "establishment_year": 1909
        }
    }
}