{
    "original": "SVENSSON &amp; SÖNER, AB CARL\n\nPnr 350 03\n\nVäxjö, Box 30 63. Ljungdalsg 10.\nTel 0470-199 00. Bankgiro\n667-9211. Postgiro 271272-7\nVerksamhet: Säljer sågade o\nhyvlade trävaror\nAntal anställda: 15\nÅrsomsättning: 1500 000\nAktiekapital: 15 500\nVerkst dir: Weilandt Svensson\nInköpschef: Lasalle Svensson\nEtableringsår 1946.\n\nSVENSSONS BYGGNADS.\nVAROR, AB E\n\nPnr 560 27\n\nTenhult. Tel 036-916 20\nVerksamhet: Specialitet:\nbyggnadsbeslag, byggmaterial\nAktiekapital: 100 000\nVerkst dir: Lars H Svensson\nEtableringsår 1934.\n\nPALMA BYGGVAROR, AB\n\nPnr 852 39\n\nSundsvall, Trädgårdsg 15 A. Tel\n060-1-258 70. Bankgiro 646-0299.\nPostgiro 613600-6\nVeiksamhet: Tillverkar o säljer\nPiano takelement för yttertak\nsamt formluckor. Säljer\nbyggnadsmaterial, Ryab spånplattor,\nsnickerier o paneler samt Tors viks\nfcrmplywood\nAntal anställda: 3\nÅrsomsättning: 3 000 000\nAktiekapital: 20 000\nChefer: Erland Adervall, Ingemar\nPalm\n\nEtableringsår: 1967.\n\nBORÉNS FABRIKS AB, P\n\nPnr 434 00\n\nKungsbacka. Tel 0300-145 00.\nBankgiro 54-6515. Postgiro 424315\nTga Bofacable\nVerksamhet: Elektrisk kabel\nAktiekapital: 2 000 000\nVerkst dir: Magnus Berg\nEtableringsår: 1951.\n\nKARLSTADS-TIDNINGENS AB\n\nPnr 65103\n\nKarlstad 1, Box 70. S Kyrkog 9.\nTel 054-1156 00. Bankgiro\n100-3623. Postgiro 36760-7\nVerksamhet: utger\nKarlstads-Tidningen, som utkommer lördagar o\nden 15 i varje månad. Bok- o\naccidens tryckeri\nAntal anställda: 20\nÅrsomsättning: 900 000\nAktiekapital: 96 100\nVerkst dir: Göran B J Salomonsson\nEtableringsår: 1879.\n\nÖSTERMANSAERO AB\n\nPnr 16110\n\nBromma 10, Ulvsundav 191. Fack.\nTel 08-28 28 40. Bankgiro 16-0548.\nPostgiro 195199. Tga Ostermanair.\nTelex 1898\n\nVerksamhet; Yrkesmässig\npassagerar- o godsbefordran med\nhelikoptrar o flygplan såsom taxi-,\nambulans- o postflygningar. Säljër\nhelikoptrar, flygplan o flygmotorer samt\nutrustningar o reservdelar till\ndessa. Bedriver en omfattande\nverkstadsrörelse för underhåll av\nluftfartyg inklusive översynsverkstad\nför flygmotorer o apparater,\nplåtslageri mm\nAntal anstäUda: 160\nÅrsomsättning: 21300 000\nAktiekapital: 700 000\nStyrelse: General Axel Ljungdahl\n(ordf), adv Hans Berggren, dir\nThorvald Hedin, dir Bengt Myrén,\ning Lennart Österman, fru Loo\nÖsterman\n\nVeikst dir: Ing Göran Wallert\nV verkst dir, försäljnings- o\nekonomichef: Rolf Claesson\nFlygchef: Nils-Gunnar Grimskog\nKontrollchef: Thorvald Lundholm\nVerkstaäschef: Arne Mattsson\nReservdelschef: Ragnar Frimodig\nEtableringsår: 1943.\n\nÖSTERMAN, AB HANS\n\nPnr 103 80\n\nStockholm 7, Birger Jarlsg 18. Fack.\nTel 08-22 09 00. Bankgiro 16-0383.\nPostgiro 767. Tga Bilosterman\nVerksamhet: Pörvaltningsbolag\nAktiekapital: 2500000\nVerkst dir: Bengt Myrén\nEtableringsår: 1908.\n\nUNS VERKSTADS AB\n\nPnr 200 61\n\nMalmö 30, Box 30100. Tel\n040-15 02 64. Bankgiro 370-2495.\nPostgiro 634223-2\n\nVerksamhet: Tillverkar\nkompressorer, hydrauliska materialfickor o\nbyggnadskranar\nVarunamn: öVAB\nAktiekapital: 125 000\nVerkst dir: Erie Eninge\nEtableringsår: 1966.\n\nOHNESKOG KONSULTERANDE\nINGENJüRSBYRÄ AB, THURE\n\nPnr 125 40\n\nÄlvsjö, Vansöv 21. Tel 08-8603 90\nVerksamhet: Konsulterande inom\nbyggnadsteknik\nEtableringsår 1957.\n\nBOMAN EFTR, E\n\nPnr 11429\n\nStockholm, Birger Jarlsg 34. Tel\n08-1132 84, 1196 32. Bankgiro\n734-1605. Postgiro 51424-0. Tga\nBomanband\n\nVerksamhet: Engrosfirma i\nurarm-band\n\nVerkst dir: Anders Schock\nEtableringsår: 1926.\n\nPANTEKTOR AB\n\nPnr 200 60\n\nMalmö 30, Strandg 80 A. Fack. Tel\n040-15 9040. Bankgiro 641-1854.\nPostgiro 430300-4\n\nVerksamhet: Konsulterande\ningenjörer. Generalplanering,\nprojektering av industribyggnader, broar o\nbyggnadskonstruktioner\nChefer: ing Nils Tegmar, civiling\nKaj Evers, ing T G Nydrén.\n\nPANTZAR AB, E\n\nPnr 11421\n\nStockholm, Surbrunnsg 5. Tel\n08-3102 08. Postgiro 352633-2\nVeiksamhet: Agenturiörelse.\nDamkonfektion en gros\nAktiekapital: 5 000\nVerkst dir: E Pantzar\nEtableringsår: 1936.\n\nLYKTAN AB, ATELJÉ\n\nPnr 290 20\n\nÅhus, Rönnowsg. Box 30. Tel\n044-24 10 30. Bankgiro 873-6266.\nPostgiro 95371-1. Tga Lyktan\nVerksamhet: Tillverkar o säljer\nglödljusarmaturer för hem o\noffentliga lokaler\nAntal anställda: 50\nAktiekapital: 110 000\nVerkst dir: Anders Pehrson\nEtableringsår: 1934.\n\nLYTH, INSTRUMENT.\nFABRIKS AB\n\nPnr 104 32\n\nStockholm 19, Döbelnsg 36 A. Box\n19037. Tel 08-23 43 60. Postgiro\n55854. Tga Lythkompass\nVerksamhet: Tillverkar nautiska,\ngeodetiska, elektroniska instrument\nAktiekapital: 60 000\nVerkst dir: Ing O Bulow\nEtableringsår: 1861.\n\nRIVELLA AB\n\nPnr 18121\n\nLidingö 1, Hagstigen 14. Box 63.\nTel 08-775 07 36. Bankgiro 44-7484.\nPostgiro 679890. Tga Rivint,\nStockholm\n\nVerksamhet: Tillverkar o säljer\ndrycken Rivella\nAktiekapital: 30000\nVeikst dir: Magnus Myhrman\nEtableringsår: 1964.",
    "structured": {
        "1": {
            "company_name": "SVENSSON & SÖNER, AB CARL",
            "pnr": "350 03",
            "address": "Växjö, Box 30 63. Ljungdalsg 10.",
            "phone_number": "0470-199 00",
            "bank_details": {
                "bankgiro": "667-9211",
                "postgiro": "271272-7"
            },
            "activity": "Säljer sågade o hyvlade trävaror",
            "employees": 15,
            "annual_turnover": 1500000,
            "capital": 15500,
            "key_personnel": [
                {
                    "name": "Weilandt Svensson",
                    "position": "Verkst dir"
                },
                {
                    "name": "Lasalle Svensson",
                    "position": "Inköpschef"
                }
            ],
            "establishment_year": 1946
        },
        "2": {
            "company_name": "SVENSSONS BYGGNADS. VAROR, AB E",
            "pnr": "560 27",
            "address": "Tenhult",
            "phone_number": "036-916 20",
            "activity": "Specialitet: byggnadsbeslag, byggmaterial",
            "capital": 100000,
            "key_personnel": [
                {
                    "name": "Lars H Svensson",
                    "position": "Verkst dir"
                }
            ],
            "establishment_year": 1934
        },
        "3": {
            "company_name": "PALMA BYGGVAROR, AB",
            "pnr": "852 39",
            "address": "Sundsvall, Trädgårdsg 15 A",
            "phone_number": "060-1-258 70",
            "bank_details": {
                "bankgiro": "646-0299",
                "postgiro": "613600-6"
            },
            "activity": "Tillverkar o säljer Piano takelement för yttertak samt formluckor.",
            "employees": 3,
            "annual_turnover": 3000000,
            "capital": 20000,
            "key_personnel": [
                {
                    "name": "Erland Adervall",
                    "position": "Chefer"
                },
                {
                    "name": "Ingemar Palm",
                    "position": "Chefer"
                }
            ],
            "establishment_year": 1967
        },
        "4": {
            "company_name": "BORÉNS FABRIKS AB, P",
            "pnr": "434 00",
            "address": "Kungsbacka",
            "phone_number": "0300-145 00",
            "bank_details": {
                "bankgiro": "54-6515",
                "postgiro": "424315 Tga Bofacable"
            },
            "activity": "Elektrisk kabel",
            "capital": 2000000,
            "key_personnel": [
                {
                    "name": "Magnus Berg",
                    "position": "Verkst dir"
                }
            ],
            "establishment_year": 1951
        },
        "5": {
            "company_name": "KARLSTADS-TIDNINGENS AB",
            "pnr": "65103",
            "address": "Karlstad 1, Box 70. S Kyrkog 9",
            "phone_number": "054-1156 00",
            "bank_details": {
                "bankgiro": "100-3623",
                "postgiro": "36760-7"
            },
            "activity": "utger Karlstads-Tidningen, som utkommer lördagar o den 15 i varje månad. Bok- o accidens tryckeri",
            "employees": 20,
            "annual_turnover": 900000,
            "capital": 96100,
            "key_personnel": [
                {
                    "name": "Göran B J Salomonsson",
                    "position": "Verkst dir"
                }
            ],
            "establishment_year": 1879
        },
        "6": {
            "company_name": "ÖSTERMANSAERO AB",
            "pnr": "16110",
            "address": "Bromma 10, Ulvsundav 191. Fack",
            "phone_number": "08-28 28 40",
            "bank_details": {
                "bankgiro": "16-0548",
                "postgiro": "195199. Tga Ostermanair. Telex 1898"
            },
            "activity": "Yrkesmässig passagerar- o godsbefordran med helikoptrar o flygplan såsom taxi-, ambulans- o postflygningar.",
            "employees": 160,
            "annual_turnover": 21300000,
            "capital": 700000,
            "key_personnel": [
                {
                    "name": "General Axel Ljungdahl",
                    "position": "Styrelse (ordf.)"
                },
                {
                    "name": "adv Hans Berggren",
                    "position": "Styrelse"
                },
                {
                    "name": "dir Thorvald Hedin",
                    "position": "Styrelse"
                },
                {
                    "name": "dir Bengt Myrén",
                    "position": "Styrelse"
                },
                {
                    "name": "ing Lennart Österman",
                    "position": "Styrelse"
                },
                {
                    "name": "fru Loo Österman",
                    "position": "Styrelse"
                },
                {
                    "name": "Ing Göran Wallert",
                    "position": "V verkst dir, försäljnings- o ekonomichef"
                },
                {
                    "name": "Rolf Claesson",
                    "position": "Flygchef"
                },
                {
                    "name": "Nils-Gunnar Grimskog",
                    "position": "Kontrollchef"
                },
                {
                    "name": "Arne Mattsson",
                    "position": "Verkstaäschef"
                },
                {
                    "name": "Ragnar Frimodig",
                    "position": "Reservdelschef"
                }
            ],
            "establishment_year": 1943
        },
        "7": {
            "company_name": "ÖSTERMAN, AB HANS",
            "pnr": "103 80",
            "address": "Stockholm 7, Birger Jarlsg 18. Fack",
            "phone_number": "08-22 09 00",
            "bank_details": {
                "bankgiro": "16-0383",
                "postgiro": "767. Tga Bilosterman"
            },
            "activity": "Pörvaltningsbolag",
            "capital": 2500000,
            "key_personnel": [
                {
                    "name": "Bengt Myrén",
                    "position": "Verkst dir"
                }
            ],
            "establishment_year": 1908
        },
        "8": {
            "company_name": "UNS VERKSTADS AB",
            "pnr": "200 61",
            "address": "Malmö 30, Box 30100",
            "phone_number": "040-15 02 64",
            "bank_details": {
                "bankgiro": "370-2495",
                "postgiro": "634223-2"
            },
            "activity": "Tillverkar kompressorer, hydrauliska materialfickor o byggnadskranar",
            "capital": 125000,
            "key_personnel": [
                {
                    "name": "Erie Eninge",
                    "position": "Verkst dir"
                }
            ],
            "establishment_year": 1966
        },
        "9": {
            "company_name": "OHNESKOG KONSULTERANDE INGENJÜRSBYRÄ AB, THURE",
            "pnr": "125 40",
            "address": "Älvsjö, Vansöv 21",
            "phone_number": "08-8603 90",
            "activity": "Konsulterande inom byggnadsteknik",
            "establishment_year": 1957
        },
        "10": {
            "company_name": "BOMAN EFTR, E",
            "pnr": "11429",
            "address": "Stockholm, Birger Jarlsg 34",
            "phone_number": "08-1132 84, 1196 32",
            "bank_details": {
                "bankgiro": "734-1605",
                "postgiro": "51424-0. Tga Bomanband"
            },
            "activity": "Engrosfirma i urarm-band",
            "key_personnel": [
                {
                    "name": "Anders Schock",
                    "position": "Verkst dir"
                }
            ],
            "establishment_year": 1926
        },
        "11": {
            "company_name": "PANTEKTOR AB",
            "pnr": "200 60",
            "address": "Malmö 30, Strandg 80 A. Fack",
            "phone_number": "040-15 9040",
            "bank_details": {
                "bankgiro": "641-1854",
                "postgiro": "430300-4"
            },
            "activity": "Konsulterande ingenjörer. Generalplanering, projektering av industribyggnader, broar o byggnadskonstruktioner",
            "key_personnel": [
                {
                    "name": "ing Nils Tegmar",
                    "position": "Chefer"
                },
                {
                    "name": "civiling Kaj Evers",
                    "position": "Chefer"
                },
                {
                    "name": "ing T G Nydrén",
                    "position": "Chefer"
                }
            ]
        },
        "12": {
            "company_name": "PANTZAR AB, E",
            "pnr": "11421",
            "address": "Stockholm, Surbrunnsg 5",
            "phone_number": "08-3102 08",
            "postgiro": "352633-2",
            "activity": "Agenturiörelse. Damkonfektion en gros",
            "capital": 5000,
            "key_personnel": [
                {
                    "name": "E Pantzar",
                    "position": "Verkst dir"
                }
            ],
            "establishment_year": 1936
        },
        "13": {
            "company_name": "LYKTAN AB, ATELJÉ",
            "pnr": "290 20",
            "address": "Åhus, Rönnowsg. Box 30",
            "phone_number": "044-24 10 30",
            "bank_details": {
                "bankgiro": "873-6266",
                "postgiro": "95371-1. Tga Lyktan"
            },
            "activity": "Tillverkar o säljer glödljusarmaturer för hem o offentliga lokaler",
            "employees": 50,
            "capital": 110000,
            "key_personnel": [
                {
                    "name": "Anders Pehrson",
                    "position": "Verkst dir"
                }
            ],
            "establishment_year": 1934
        },
        "14": {
            "company_name": "LYTH, INSTRUMENT. FABRIKS AB",
            "pnr": "104 32",
            "address": "Stockholm 19, Döbelnsg 36 A. Box 19037",
            "phone_number": "08-23 43 60",
            "postgiro": "55854. Tga Lythkompass",
            "activity": "Tillverkar nautiska, geodetiska, elektroniska instrument",
            "capital": 60000,
            "key_personnel": [
                {
                    "name": "Ing O Bulow",
                    "position": "Verkst dir"
                }
            ],
            "establishment_year": 1861
        },
        "15": {
            "company_name": "RIVELLA AB",
            "pnr": "18121",
            "address": "Lidingö 1, Hagstigen 14. Box 63",
            "phone_number": "08-775 07 36",
            "bank_details": {
                "bankgiro": "44-7484",
                "postgiro": "679890. Tga Rivint, Stockholm"
            },
            "activity": "Tillverkar o säljer drycken Rivella",
            "capital": 30000,
            "key_personnel": [
                {
                    "name": "Magnus Myhrman",
                    "position": "Veikst dir"
                }
            ],
            "establishment_year": 1964
        }
    }
}