{
    "original": "CARLSON PLÅTSLAGERI\nAB, NILS G\n\nPnr 417 34\n\nGöteborg, Ovädersg 3 A. Tel\n031-54 20 01-04. Bankgiro 513-6536.\nPostgiro 240362-2\nVerksamhet: Rostfria arbeten\nAntal anställda: 55\nAktiekapital: 150 000\nÅrsomsättning: 5 000 000\nVerkst dir: Bert Carlson\nEtableringsår: 1945.\n\nKARLSSON FISKEXPORT AB,\nRUDOLF\n\nPnr 450 43\n\nSmögen, Box 6. Tel 0523-309 25,\n305 26. Bankgiro 551-0243.\nPostgiro 37180-7\n\nVerksamhet: Partihandel med fisk\n\no skaldjur\n\nAntal anställda: 7\n\nÅrsomsättning: 1300 000\nAktiekapital: 100 000\nVeikst dir: Eskil Karlsson\nEtableringsår: 1943.\n\nRONNHEDH, AB P G\n\nPnr 50109\n\nBorås 1, Viskastrandsg 3-5. Box\n579. Tel 033-10 03 50. Bankgiro\n667-9161. Postgiro 338382-5\nVerksamhet: Tillverkar\nhushållsartiklar o blomkrukor av plast\nAntal anställda: 30\nÅrsomsättning: 1 500 000\nAktiekapital: 40 000\nVerkst dir Per Göran Rönnhedh\nEtableringsår 1947.\n\nTRÄTÄLJA, AB\n\nPnr 41117\n\nGöteborg, V Hamng 5. Tel\n031-13 2177, 13 59 00. Bankgiro\n501-0871. Postgiro 47153-2. Tga\nForest. Telex 2257\nVerksamhet: Trävaruagentur med\nexport av trävaror, papper o\nwallboard. Lagerförande grossister i\nbyggnadsmaterial\nAntal anställda: 12\nÅrsomsättning: 9 000 000\nAktiekapital: 290 000\nVerkst dir: Ulf Enström\nTrävaror Rune Jendeby\nPapper: Gunnar Nilsson\nByggnadsmaterial: Björn Gillstedt\nEtableringsår: 1906.\n\nCLAESSON AB, ERNST 0\n\nPnr 100 31\n\nStockholm 21, Box 21031. Tel\n08-34 94 20. Bankgiro 566-0469.\nPostgiro 694-0. Tga Eoclas\nVerksamhet: Färg- o\nlacktillverkning\n\nFabrik: 16170 Mariehäll,\nAdolfs-bergsv 33-35. Tel 08-28 58 58\nAktiekapital: 100 000\nVerkst dir: Bertil Claesson\nEtableringsår: 1915.\n\nde CLAIRE\nDAMKONFEKTION AB\n\nPnr 51050\n\nDalsjöfors. Tel 033-702 94, 702 95.\nBankgiro 53-2109. Postgiro 279777.\nVerksamhet: Tillverkar o säljer\nkappor o dräkter\nAntal anställda: 40\nAktiekapital: 40 000\nVerkst dir: Arne Hedin\nEtableringsår: 1954.\n\nFIGURA AB\n\nPnr 127 33\n\nSkärholmen, Lilla Sällskapets v 76.\nTel 08-88 9120. Bankgiro 569-9087.\nPostgiro 707866-0. Telex 10537\nVerksamhet: Säljer behå- o\nkorsettartiklar\n\nÅrsomsättning: 3 000 000\nAktiekapital: 25000\nVerkst dir: Carl-Magnus Hoffrén\nEtableringsår: 1965.\n\nWINTHER. AB ERIK\n\nPnr 50103\n\nBorås 1, Göteborgsv 8. Box 105.\nTel 033-112341, 112361.\nBankgiro 83-9379. Postgiro 86108\nVerksamhet: Damkonfektion,\nklänningar, rockar\nAktiekapital: 90 000\nVerkst dir: Fru Karin Winther\nDisp: Lars Winther\nEtableringsår: 1933.\nOmbildat till aktiebolag 1939.\n\nWINTER AB, F\n\nPnr 703 61\n\nÖrebro, Klosterg 18. Tel\n019-18 7618. 118181. Bankgiro\n358-8910. Postgiro 477292-7\nVerksamhet: Konsulterande inom\nbyggnadsbranschen\nAntal anställda: 8\nÅrsomsättning: 480 000\nAktiekapital: 15 000\nVerkst dir. Civiling F Winter\nEtableringsån 1955.\n\nPONTÅN AB, CAJ\n\nPnr 17140\n\nSolna, Vårv 3. Tel 08-83 13 74,\n83 13 75. Bankgiro 566-1848.\nPostgiro 402471-7. Tga Pontanus\nVerksamhet: Tillverkar o\nmarknadsför Caj P’s torra o flytande\nkrydd-produkter i konsument- o\nindustriförpackningar\nVarunamn: Caj P’s\nAntal anställda: 3\nÅrsomsättning: 920 000\nAktiekapital: 15 000\nVerkst dir: Caj Pontån\nEtableringsår: 1960.\n\nPERCO\n\nPnr 213 63\n\nMalmö, Pinjeg 6. Tel 040-94 64 20.\nBankgiro 87-4388. Postgiro 437014.\nTga Percoma\n\nVerksamhet: Tillverkar o säljer\nmanuella o eldrivna markistyper\nAntal anställda: 15\nChef: Dir Börje Pernert\nEtableringsår: 1956.\n\nPERFECT AB, PENSEL.\nFABRIKEN\n\nPnr 560 23\n\nBankeryd. Tel 036-720 37, 720 67.\nBankgiro 836-9324. Postgiro\n31477-3. Tga Perfectverken\nVerksamhet: Tillverkar\nmålarpenslar, målarrullar, målarverktyg,\nspe-cialborstar o kammar\nAntal anställda: 150\nÅrsomsättning: 7 500 000\nAktiekapital: 800000\nStyrelse: Thomas Isaksson (ordf),\nfabr Harry Isaksson, disp Björn\nLeifland\n\nVerkst dir: Fabr Harry Isaksson\nEtableringsår: 1920.\n\nBETONG AB HANS HADENIUS\n\nPnr 582 23\n\nLinköping, Klosterg 66. Tel\n013-130350. Bankgiro 134-2831.\nPostgiro 689170-9\n\nVerksamhet: Betong- o torrbruks-\n\ntillverkning\n\nAntal anställda: 50\n\nÅrsomsättning: 15 000 000\n\nAktiekapital: 25 000\n\nVerkst dir: Hans Hadenius\n\nEtableringsår: 1966.\n\nBORÅS SVETS &amp; MONTERING\n\nPnr 500 09\n\nBorås 9, Box 19056. Tel\n033-10 10 82. Bankgiro 152-9312\nVerksamhet: Tillverkar balk o\njärnkonstruktioner samt\nsmldes-arbeten\n\nÄgare o chef: Ake Gustafsson\nEtableringsår: 1966.",
    "structured": {
        "0": {
            "company_name": "CARLSON PLÅTSLAGERI AB",
            "address": "Ovädersg 3 A, Göteborg",
            "phone_number": "031-54 20 01-04",
            "bank_details": {
                "bankgiro": "513-6536",
                "postgiro": "240362-2"
            },
            "activity": "Rostfria arbeten",
            "employees": 55,
            "capital": 150000,
            "annual_turnover": 5000000,
            "key_personnel": [
                {
                    "name": "Bert Carlson",
                    "position": "Verkst dir"
                }
            ],
            "establishment_year": 1945
        },
        "1": {
            "company_name": "KARLSSON FISKEXPORT AB",
            "address": "Box 6, Smögen",
            "phone_number": "0523-309 25, 305 26",
            "bank_details": {
                "bankgiro": "551-0243",
                "postgiro": "37180-7"
            },
            "activity": "Partihandel med fisk o skaldjur",
            "employees": 7,
            "capital": 100000,
            "annual_turnover": 1300000,
            "key_personnel": [
                {
                    "name": "Eskil Karlsson",
                    "position": "Veikst dir"
                }
            ],
            "establishment_year": 1943
        },
        "2": {
            "company_name": "RONNHEDH AB P G",
            "address": "Viskastrandsg 3-5, Borås 1",
            "phone_number": "033-10 03 50",
            "bank_details": {
                "bankgiro": "667-9161",
                "postgiro": "338382-5"
            },
            "activity": "Tillverkar hushållsartiklar o blomkrukor av plast",
            "employees": 30,
            "capital": 40000,
            "annual_turnover": 1500000,
            "key_personnel": [
                {
                    "name": "Per Göran Rönnhedh",
                    "position": "Verkst dir"
                }
            ],
            "establishment_year": 1947
        },
        "3": {
            "company_name": "TRÄTÄLJA AB",
            "address": "V Hamng 5, Göteborg",
            "phone_number": "031-13 2177, 13 59 00",
            "bank_details": {
                "bankgiro": "501-0871",
                "postgiro": "47153-2"
            },
            "activity": "Trävaruagentur med export av trävaror, papper o wallboard. Lagerförande grossister i byggnadsmaterial",
            "employees": 12,
            "capital": 290000,
            "annual_turnover": 9000000,
            "key_personnel": [
                {
                    "name": "Ulf Enström",
                    "position": "Verkst dir"
                },
                {
                    "name": "Rune Jendeby",
                    "position": "Trävaror"
                },
                {
                    "name": "Gunnar Nilsson",
                    "position": "Papper"
                },
                {
                    "name": "Björn Gillstedt",
                    "position": "Byggnadsmaterial"
                }
            ],
            "establishment_year": 1906
        },
        "4": {
            "company_name": "CLAESSON AB ERNST 0",
            "address": "Box 21031, Stockholm 21",
            "phone_number": "08-34 94 20",
            "bank_details": {
                "bankgiro": "566-0469",
                "postgiro": "694-0"
            },
            "activity": "Färg- o lacktillverkning",
            "capital": 100000,
            "key_personnel": [
                {
                    "name": "Bertil Claesson",
                    "position": "Verkst dir"
                }
            ],
            "establishment_year": 1915
        },
        "5": {
            "company_name": "de CLAIRE DAMKONFEKTION AB",
            "address": "Dalsjöfors",
            "phone_number": "033-702 94, 702 95",
            "bank_details": {
                "bankgiro": "53-2109",
                "postgiro": "279777"
            },
            "activity": "Tillverkar o säljer kappor o dräkter",
            "employees": 40,
            "capital": 40000,
            "key_personnel": [
                {
                    "name": "Arne Hedin",
                    "position": "Verkst dir"
                }
            ],
            "establishment_year": 1954
        },
        "6": {
            "company_name": "FIGURA AB",
            "address": "Lilla Sällskapets v 76, Skärholmen",
            "phone_number": "08-88 9120",
            "bank_details": {
                "bankgiro": "569-9087",
                "postgiro": "707866-0"
            },
            "activity": "Säljer behå- o korsettartiklar",
            "annual_turnover": 3000000,
            "capital": 25000,
            "key_personnel": [
                {
                    "name": "Carl-Magnus Hoffrén",
                    "position": "Verkst dir"
                }
            ],
            "establishment_year": 1965
        },
        "7": {
            "company_name": "WINTHER AB ERIK",
            "address": "Göteborgsv 8, Borås 1",
            "phone_number": "033-112341, 112361",
            "bank_details": {
                "bankgiro": "83-9379",
                "postgiro": "86108"
            },
            "activity": "Damkonfektion, klänningar, rockar",
            "capital": 90000,
            "key_personnel": [
                {
                    "name": "Fru Karin Winther",
                    "position": "Verkst dir"
                },
                {
                    "name": "Lars Winther",
                    "position": "Disp"
                }
            ],
            "establishment_year": 1933
        },
        "8": {
            "company_name": "WINTER AB F",
            "address": "Klosterg 18, Örebro",
            "phone_number": "019-18 7618, 118181",
            "bank_details": {
                "bankgiro": "358-8910",
                "postgiro": "477292-7"
            },
            "activity": "Konsulterande inom byggnadsbranschen",
            "employees": 8,
            "annual_turnover": 480000,
            "capital": 15000,
            "key_personnel": [
                {
                    "name": "Civiling F Winter",
                    "position": "Verkst dir"
                }
            ],
            "establishment_year": 1955
        },
        "9": {
            "company_name": "PONTÅN AB CAJ",
            "address": "Vårv 3, Solna",
            "phone_number": "08-83 13 74, 83 13 75",
            "bank_details": {
                "bankgiro": "566-1848",
                "postgiro": "402471-7"
            },
            "activity": "Tillverkar o marknadsför Caj P’s torra o flytande krydd-produkter i konsument- o industriförpackningar",
            "employees": 3,
            "annual_turnover": 920000,
            "capital": 15000,
            "key_personnel": [
                {
                    "name": "Caj Pontån",
                    "position": "Verkst dir"
                }
            ],
            "establishment_year": 1960
        },
        "10": {
            "company_name": "PERCO",
            "address": "Pinjeg 6, Malmö",
            "phone_number": "040-94 64 20",
            "bank_details": {
                "bankgiro": "87-4388",
                "postgiro": "437014"
            },
            "activity": "Tillverkar o säljer manuella o eldrivna markistyper",
            "employees": 15,
            "key_personnel": [
                {
                    "name": "Dir Börje Pernert",
                    "position": "Chef"
                }
            ],
            "establishment_year": 1956
        },
        "11": {
            "company_name": "PERFECT AB PENSEL FABRIKEN",
            "address": "Bankeryd",
            "phone_number": "036-720 37, 720 67",
            "bank_details": {
                "bankgiro": "836-9324",
                "postgiro": "31477-3"
            },
            "activity": "Tillverkar målarpenslar, målarrullar, målarverktyg, specialborstar o kammar",
            "employees": 150,
            "annual_turnover": 7500000,
            "capital": 800000,
            "key_personnel": [
                {
                    "name": "Thomas Isaksson",
                    "position": "Styrelse (ordf)"
                },
                {
                    "name": "Harry Isaksson",
                    "position": "Fabr"
                },
                {
                    "name": "Björn Leifland",
                    "position": "Disp"
                }
            ],
            "establishment_year": 1920
        },
        "12": {
            "company_name": "BETONG AB HANS HADENIUS",
            "address": "Klosterg 66, Linköping",
            "phone_number": "013-130350",
            "bank_details": {
                "bankgiro": "134-2831",
                "postgiro": "689170-9"
            },
            "activity": "Betong- o torrbrukstillverkning",
            "employees": 50,
            "annual_turnover": 15000000,
            "capital": 25000,
            "key_personnel": [
                {
                    "name": "Hans Hadenius",
                    "position": "Verkst dir"
                }
            ],
            "establishment_year": 1966
        },
        "13": {
            "company_name": "BORÅS SVETS & MONTERING",
            "address": "Box 19056, Borås 9",
            "phone_number": "033-10 10 82",
            "bank_details": {
                "bankgiro": "152-9312"
            },
            "activity": "Tillverkar balk o järnkonstruktioner samt smidesarbeten",
            "key_personnel": [
                {
                    "name": "Ake Gustafsson",
                    "position": "Ägare o chef"
                }
            ],
            "establishment_year": 1966
        }
    }
}