{
    "original": "MÅNSSONS VERKSTÄDER, AB\n\nPnr 190 60\n\nBälsta, Bälsunda. Tel 0171-63080.\nPostgiro 494273\n\nVerksamhet: Tillverkar järn- o\nstålkonstruktioner. Utför plåtarbeten\nAktiekapital: 30 000\nVerkst dir: Gösta Månsson\nEtableringsår: 1955.\n\nAL-FORPACKNING, AB\n\nPnr 402 51\n\nGöteborg 13, Box 13045. Tel\n031-15 60 51. Bankgiro 514-3086.\nPostgiro 118279-9\n\nVerksamhet: Aluminiumformar med\nlock, aluminiumfolie. Manuella o\nautomatiska lockpåläggare o\nförslutnings maskiner\nFabrik: Vänersborg, Skytteg 8. Tel\n0521-160 05\nAntal anstäUda: 25\nÅrsomsättning: 5 000 000\nAktiekapital: 60 000\nStyrelse: Björn Lundgren, C Krister\nLundgren, E Söderros\nVerkst dir: Björn Lundgren\nEtableringsår: 1956.\n\nWITTE AB. C.O\n\nPnr 41101\n\nGöteborg. Stampg 28. Tel\n031-15 35 26, 15 41 26. Bankgiro\n822-2192. Postgiro 529301-4. Tga\nTur-bestos. Telex 20726\nVerksamhet: Representant för\nutländska tillverkare av asbestvaror,\npolyestrar (omättade), trassel o\nsjälvhäftande material\nVerkst dir: Ing C-O Witte\nEtableringsår: 1958.\n\nWITTE &amp; CO, EXPORT AB\nFRANZ\n\nPnr 401 22\n\nGöteborg 1. Box 137. Manufakturg\n2. Tel 031-51 32 50. Bankgiro\n420-2024. Postgiro 12146-7. Tga Witte\nVerksamhet: Säljer salt sill,\nkryddsill, salt fisk, lutfisk mm en gros.\nBåtsman hundfisk\nAntal anställda: 44\nÅrsomsättning: 14 500 000\nAktiekapital: 140 000\nStyrelse: Dir Hans E Ahlstedt (ordf),\nfru Solveig Witte-Ahlstedt, dir\nHenning Nilsson\nVerkst dir: Henning Nilsson\nEtableringsår: 1886.\n\nTEGLUND MARKETING AB\n\nPnr 220 09\n\nLund 9, Sunnanv 14 H. Fack. Tel\n046-1177 30. Bankgiro 775-9676.\nPostgiro 696420-9. Telex 32270\nVerksamhet: Alla slags\nmarknadsundersökningar. Konsultationer i\nmarknadsfrågor\nAntal anställda: 45\n\nVerkst dir: Civilekonom Jan\nTeglund\n\nEtableringsår: 1967.\n\nPLANTEX, AB\n\nPnr 15120\n\nSödertälje 1, Svalängsv 1. Fack.\nTel 0755-340 80. Tga Ewos.\nTelex 10222 EWEX S\nVerksamhet: Marknadsföring av\ninsekts- o växt skydds preparat för\nlantbruk, skog o hemträdgård samt\nimpregneringsmedel för\ncellulosaindustrin\n\nLokalkontor o lager: Malmö. Tel\n040-93 55 60\nVerkst dir Sven Strand\nEtableringsår: 1966\nDotterbolag till AstrarEwos AB.\nSe vidare Astra-Ewos AB.\n\nPLANTIN &amp; CO, AB W\n\nPnr 23030\n\nOxie, Box 36. Tel 040^14 94 5 0.\nBankgiro 260-1375. Postgiro\n435457-7\n\nVerksamhet: Tillverkar o säljer\nEnhets jord till handelsträdgårdar,\nförsöksstationer (statliga o\nenskilda), botaniska trädgårdar,\nstadsträdgårdar, hobbyodlare\nVarunamn: Enhetsjord\nAntal anställda: 22\nÅrsomsättning: 3 500 000\nAktiekapital: 25 000\nStyrelse: Dir Wilgot Plantin (ordf),\nförsäljn-chef Allan Grönvall\nVerkst dir: Wilgot Plantin\nFörsäljn-chef: Allan Grönvall\nTrädgårdsmästare: Einar Andersson\nEtableringsår: 1954.\n\nPLAST-\n\nse i övrigt resp namn.\n\nPLAST LEM ECO AB\n\nPnr 740 60\n\nOrbiyhus. Tel 0295-110 00. Tga\nLemeco. Telex 81007\nVerksamhet: Plasttillverkning i\nmoderna maskiner\nAntal anställda: 11\nAktiekapital: 5 000\nEtableringsår. 1968.\n\nRAT\n\nRANG, KONFEKTIONS AB\n\nPnr 571 00\n\nNässjö, Teleg 3. Box 193. Tel\n0380-130 00. Bankgiro 835-7782.\nPostgiro 85777-1. Tga Rangbolaget\nVerksamhet: Tillverkar o säljer\nherrkonfektion\nAntal anställda: 260\nÅrsomsättning: 12 000 000\nAktiekapital: 450 000\nVerkst dir: Jonas Ljungqvist\nEtableringsår. 1909.\n\nNYQVIST AB, BERNT\n\nPnr 20124\n\nMalmö 1, Adelg 2. Box 414. Tel\n040-726 10. Bankgiro 87-0231.\nPostgiro 436275. Tga Betex\nVerksamhet: Säljer maskiner o\ntillbehör för textilindustrin\nAktiekapital: 50000\nVeikst dir: Bernt Nyqvist\nEtableringsår: 1955.\n\nFORSMAN ARMERAD PLAST\nAB, S\n\nPnr 152 00\n\nSträngnäs, Finnin ge v 75. Tel\n0152-145 70, 145 71. Postgiro 122141\nVerksamhet: Tillverkar detaljer i\nglasfiberarmerad plast\nVerkst dir. Hans Forsman\nEtableringsår: 1959.\n\nFORSNÄS\nBYGGNADS-PLATTOR, AB\n\nPnr 570 60\n\nösterbymo, Box 20. Tel\n0381-60214. Postgiro 71327\nVerksamhet: Tillverkar\nträulls-plattor\n\nAntal anställda: 25\nÅrsomsättning: 5 000 000\nAktiekapital: 50 000\nVerkst dir: Disp Lennart Rääf\nEtableringsår: 1946.\n\nFORSNÄS FANÉRSITSFABRIK,\nHB. BRÖDERNA BERGQUIST\n\nPnr 570 60\n\nÖsterbymo. Tel 0381-550 47\n\n2036. Tel 031-1105 71. Postgiro\n40329. Tga Carlfors\nVerksamhet: Skeppsmäkleri o\nspeditionsfirma\nAktiekapital: 25 000\nVerkst dir: Karl-Olov Olhede\nEtableringsår: 1916.\n\nAGRI CONSULT AB\n\nPnr 200 10\n\nMalmö 17, Box 17019. Jörgen\nAn-kersg 12. Tel 040-762 20. Bankgiro\n876-5117. Postgiro 538576-0.\nTga Agriconsult. Telex 32474\nVerksamhet: Konsulterande\ningen-jörsforetag med speciell inriktning\npå projekt for jordbrukets\nindustrier, t ex siloanläggningar,\nfoderfabriker, frukt- o grönsakslager,\nslakterier, charkuterifabriker,\nmejerier, verkstäder, djurstallar o\nlagerbyggnader för specialiserad\njordbruksproduktion. Företaget har\nspecialister inom flera olika\nområden såsom allmän\njordbruksteknik, byggnadsteknik, byggledning\nsamt byggnads- o\nanläggningskontroll, maskinteknik, elteknik,\nmanöverteknik, VVS-teknik,\nrationalisering, varuhantering, kylteknik\nFilial: Luxembourg, 16 Bvd\nd*Avranches. Tel 479 31\nAntal anställda: 70\nÅrsomsättning: 5 500 000\nAktiekapital: 300 000\nStyrelse: Civiling Yngve Lindberg,\nciviling Göte Mårtensson, civiling\nTöre Olbjer\n\nVerkst dir: Civiling Töre Olbjer\nEtableringsår: 1962.\n\nhuttners ab,b s\n\nPnr 41108\n\nGöteborg, Kungsg 62. Tel\n031-170515. Bankgiro 51-0676.\nPostgiro 12078. Tga Hüttner\nVerksamhet: Ur, tillbehör m m en\ngros\n\nAktiekapital: 450 000\nÄgare o chef: Konsul All an Hüttner\nEtableringsår: 1871.",
    "structured": {
        "1": {
            "company_name": "MÅNSSONS VERKSTÄDER, AB",
            "address": "Bälsta, Bälsunda",
            "phone_number": "0171-63080",
            "bank_details": {
                "postgiro": "494273"
            },
            "activity": "Tillverkar järn- o stålkonstruktioner. Utför plåtarbeten",
            "capital": 30000,
            "key_personnel": [
                {
                    "name": "Gösta Månsson",
                    "position": "Verkst dir"
                }
            ],
            "establishment_year": 1955
        },
        "2": {
            "company_name": "AL-FORPACKNING, AB",
            "address": "Göteborg 13, Box 13045",
            "phone_number": "031-15 60 51",
            "bank_details": {
                "bankgiro": "514-3086",
                "postgiro": "118279-9"
            },
            "activity": "Aluminiumformar med lock, aluminiumfolie. Manuella o automatiska lockpåläggare o förslutnings maskiner",
            "employees": 25,
            "annual_turnover": 5000000,
            "capital": 60000,
            "key_personnel": [
                {
                    "name": "Björn Lundgren",
                    "position": "Styrelse"
                },
                {
                    "name": "C Krister Lundgren",
                    "position": "Styrelse"
                },
                {
                    "name": "E Söderros",
                    "position": "Styrelse"
                },
                {
                    "name": "Björn Lundgren",
                    "position": "Verkst dir"
                }
            ],
            "establishment_year": 1956
        },
        "3": {
            "company_name": "WITTE AB. C.O",
            "address": "Göteborg, Stampg 28",
            "phone_number": "031-15 35 26, 15 41 26",
            "bank_details": {
                "bankgiro": "822-2192",
                "postgiro": "529301-4"
            },
            "activity": "Representant för utländska tillverkare av asbestvaror, polyestrar (omättade), trassel o självhäftande material",
            "key_personnel": [
                {
                    "name": "Ing C-O Witte",
                    "position": "Verkst dir"
                }
            ],
            "establishment_year": 1958
        },
        "4": {
            "company_name": "WITTE & CO, EXPORT AB FRANZ",
            "address": "Göteborg 1, Box 137, Manufakturg 2",
            "phone_number": "031-51 32 50",
            "bank_details": {
                "bankgiro": "420-2024",
                "postgiro": "12146-7"
            },
            "activity": "Säljer salt sill, kryddsill, salt fisk, lutfisk mm en gros. Båtsman hundfisk",
            "employees": 44,
            "annual_turnover": 14500000,
            "capital": 140000,
            "key_personnel": [
                {
                    "name": "Dir Hans E Ahlstedt (ordf)",
                    "position": "Styrelse"
                },
                {
                    "name": "fru Solveig Witte-Ahlstedt",
                    "position": "Styrelse"
                },
                {
                    "name": "dir Henning Nilsson",
                    "position": "Styrelse"
                },
                {
                    "name": "Henning Nilsson",
                    "position": "Verkst dir"
                }
            ],
            "establishment_year": 1886
        },
        "5": {
            "company_name": "TEGLUND MARKETING AB",
            "address": "Lund 9, Sunnanv 14 H",
            "phone_number": "046-1177 30",
            "bank_details": {
                "bankgiro": "775-9676",
                "postgiro": "696420-9"
            },
            "activity": "Alla slags marknadsundersökningar. Konsultationer i marknadsfrågor",
            "employees": 45,
            "key_personnel": [
                {
                    "name": "Civilekonom Jan Teglund",
                    "position": "Verkst dir"
                }
            ],
            "establishment_year": 1967
        },
        "6": {
            "company_name": "PLANTEX, AB",
            "address": "Södertälje 1, Svalängsv 1",
            "phone_number": "0755-340 80",
            "activity": "Marknadsföring av insekts- o växt skydds preparat för lantbruk, skog o hemträdgård samt impregneringsmedel för cellulosaindustrin",
            "key_personnel": [
                {
                    "name": "Sven Strand",
                    "position": "Verkst dir"
                }
            ],
            "establishment_year": 1966
        },
        "7": {
            "company_name": "PLANTIN & CO, AB W",
            "address": "Oxie, Box 36",
            "phone_number": "040^14 94 5 0",
            "bank_details": {
                "bankgiro": "260-1375",
                "postgiro": "435457-7"
            },
            "activity": "Tillverkar o säljer Enhets jord till handelsträdgårdar, försöksstationer (statliga o enskilda), botaniska trädgårdar, stadsträdgårdar, hobbyodlare",
            "employees": 22,
            "annual_turnover": 3500000,
            "capital": 25000,
            "key_personnel": [
                {
                    "name": "Dir Wilgot Plantin (ordf)",
                    "position": "Styrelse"
                },
                {
                    "name": "försäljn-chef Allan Grönvall",
                    "position": "Styrelse"
                },
                {
                    "name": "Wilgot Plantin",
                    "position": "Verkst dir"
                },
                {
                    "name": "Allan Grönvall",
                    "position": "Försäljn-chef"
                },
                {
                    "name": "Einar Andersson",
                    "position": "Trädgårdsmästare"
                }
            ],
            "establishment_year": 1954
        },
        "8": {
            "company_name": "PLAST LEM ECO AB",
            "address": "Orbiyhus",
            "phone_number": "0295-110 00",
            "bank_details": {
                "bankgiro": "N/A",
                "postgiro": "N/A"
            },
            "activity": "Plasttillverkning i moderna maskiner",
            "employees": 11,
            "capital": 5000,
            "establishment_year": 1968
        },
        "9": {
            "company_name": "RANG, KONFEKTIONS AB",
            "address": "Nässjö, Teleg 3, Box 193",
            "phone_number": "0380-130 00",
            "bank_details": {
                "bankgiro": "835-7782",
                "postgiro": "85777-1"
            },
            "activity": "Tillverkar o säljer herrkonfektion",
            "employees": 260,
            "annual_turnover": 12000000,
            "capital": 450000,
            "key_personnel": [
                {
                    "name": "Jonas Ljungqvist",
                    "position": "Verkst dir"
                }
            ],
            "establishment_year": 1909
        },
        "10": {
            "company_name": "NYQVIST AB, BERNT",
            "address": "Malmö 1, Adelg 2, Box 414",
            "phone_number": "040-726 10",
            "bank_details": {
                "bankgiro": "87-0231",
                "postgiro": "436275"
            },
            "activity": "Säljer maskiner o tillbehör för textilindustrin",
            "capital": 50000,
            "key_personnel": [
                {
                    "name": "Bernt Nyqvist",
                    "position": "Veikst dir"
                }
            ],
            "establishment_year": 1955
        },
        "11": {
            "company_name": "FORSMAN ARMERAD PLAST AB, S",
            "address": "Strängnäs, Finnin ge v 75",
            "phone_number": "0152-145 70, 145 71",
            "bank_details": {
                "bankgiro": "N/A",
                "postgiro": "122141"
            },
            "activity": "Tillverkar detaljer i glasfiberarmerad plast",
            "key_personnel": [
                {
                    "name": "Hans Forsman",
                    "position": "Verkst dir"
                }
            ],
            "establishment_year": 1959
        },
        "12": {
            "company_name": "FORSNÄS BYGGNADS-PLATTOR, AB",
            "address": "österbymo, Box 20",
            "phone_number": "0381-60214",
            "bank_details": {
                "bankgiro": "N/A",
                "postgiro": "71327"
            },
            "activity": "Tillverkar träulls-plattor",
            "employees": 25,
            "annual_turnover": 5000000,
            "capital": 50000,
            "key_personnel": [
                {
                    "name": "Disp Lennart Rääf",
                    "position": "Verkst dir"
                }
            ],
            "establishment_year": 1946
        },
        "13": {
            "company_name": "FORSNÄS FANÉRSITSFABRIK, HB. BRÖDERNA BERGQUIST",
            "address": "Österbymo",
            "phone_number": "0381-550 47",
            "bank_details": {
                "bankgiro": "N/A",
                "postgiro": "40329"
            },
            "activity": "Skeppsmäkleri o speditionsfirma",
            "capital": 25000,
            "key_personnel": [
                {
                    "name": "Karl-Olov Olhede",
                    "position": "Verkst dir"
                }
            ],
            "establishment_year": 1916
        },
        "14": {
            "company_name": "AGRI CONSULT AB",
            "address": "Malmö 17, Box 17019, Jörgen An-kersg 12",
            "phone_number": "040-762 20",
            "bank_details": {
                "bankgiro": "876-5117",
                "postgiro": "538576-0"
            },
            "activity": "Konsulterande ingen-jörsforetag med speciell inriktning på projekt for jordbrukets industrier, t ex siloanläggningar, foderfabriker, frukt- o grönsakslager, slakterier, charkuterifabriker, mejerier, verkstäder, djurstallar o lagerbyggnader för specialiserad jordbruksproduktion. Företaget har specialister inom flera olika områden såsom allmän jordbruksteknik, byggnadsteknik, byggledning samt byggnads- o anläggningskontroll, maskinteknik, elteknik, manöverteknik, VVS-teknik, rationalisering, varuhantering, kylteknik",
            "employees": 70,
            "annual_turnover": 5500000,
            "capital": 300000,
            "key_personnel": [
                {
                    "name": "Civiling Yngve Lindberg",
                    "position": "Styrelse"
                },
                {
                    "name": "civiling Göte Mårtensson",
                    "position": "Styrelse"
                },
                {
                    "name": "civiling Töre Olbjer",
                    "position": "Styrelse"
                },
                {
                    "name": "Civiling Töre Olbjer",
                    "position": "Verkst dir"
                }
            ],
            "establishment_year": 1962
        }
    }
}