{
    "original": "ÅFORS, PLASTFABRIKEN\n\nPnr 330 20\n\nAnders torp, Törås. Postl 441. Tel\n0371-162 61. Bankgiro 488-1884.\nPostgiro 95647-4\nVerksamhet: Tillverkar handtag.\nUtför legoarbeten\nÅrsomsättning: 200 000\nChef: Lennart Tibratt\nEtableringsår 1958.\n\nROSTFRIA TAK AB\n\nPnr 773 01\n\nFagersta 1, Fack. Tel 0223-180 00.\nBankgiro 81-0386. Postgiro 590270.\nTelex 7525. Tga Koncern\nVerksamhet: Tillverkar o\nmarknadsför sömsvetsad rostfri plåt för tak,\nfasader, fuktisoleringar o fryshus\nsamt tillhörande detaljer\nFilialer: Stockholm. Fack, pa\n124 04 Bandhagen. Tel 08-47 28 00\n400 60 Göteborg 6, Box 6093. Tel\n031-52 02 1 0\nAntal anställda: 18\nÅrsomsättning: 8000 000\nAktiekapital: 20 000\nStyrelse: Dir Bengt Torssell (ordf),\ning Arne Bergström, dir Sture\nNetterstedt, övering Lars Sjödén\nVerkst dir: Sture Netterstedt\nFörsäljn-chef: Ing Sten Forslund\nTekn chef: Ing Anders Arkestad\nEtableringsår: 1962\nDotterföretag till Fagersta Bruks AB.\n\nROTHAG, AB\n\nPnr 12106\n\nJohanneshov 6, Vikstensv 1. Fack.\nTel 08-49 99 50 , 49 99 90. Bankgiro\n570-3947. Postgiro 553420-1. Tga\nStrict, Stockholm. Telex 10751\nROTHAG S\n\nVerksamhet: Metall o\nädelmetall-halvfabrikat, trådbearbetnings-maskiner, kemikalier, galvanoteknik\n\nAktiekapital: 10000\nVeikst dir: S Rothschild\nEtableringsår: 1956.\n\nHAS\n\nHASSELFORS BRUKS AB\n\nPnr 690 33\n\nHasselfors. Huvudkontor. Tel\n0585-44100. Postgiro 92220-3.\nTga Hasselforsbruk, Örebro.\nTelex 73405\n\nTräindustri: Sågverk, hyvleri,\n\nImpregneringsverk, snickerifabrik\n\no försäljningskontor\n\nSkog o lantbruk: Skogschef Sven E\n\nEkström\n\nTorvindustri: Skyllberg, 690 45\nÅsbro. Tel 0583-403 20. Telex\n73249. Tga Swedpeat, Örebro. Chef:\nÖvering Arne Gunnarson\nBultindustri: 71011 Svartå. Tel\n0585-502 00. Telex 73327. Tga\nSteelbolt, Örebro. Chef: Övering\nNils E Colliander\nVarunamn: Solgöd, Solmull, Solrum,\nSphagnum\n\nAntal anställda: 700\nÅrsomsättning: 48 000 000\nAktiekapital: 3 000 000\nVerkst dir: Disp Bo Risberg\nEkonomichef: Henric Stenby\nEtableringsår: 1646\nOmbildat till aktiebolag 1876.\nModerbolag: Förvaltnings AB\nHasselfors.\n\nHASSELGRENS TRÄVARU\nAB, GUSTAF\n\nPnr 11137\n\nStockholm, Luntmakarg 36. Tel\n08-20 75 28, 11 16 38. Bankgiro\n57-0919. Postgiro 51238\nVerksamhet: Säljer trävaror\nVarunamn: Trävaror\nAntal anstäHda: 5\nÅrsomsättning: 500 000\nAktiekapital: 80 000\nVerkst dir: Gustaf Hasselgren\nEtableringsår 1910.\n\nHASSES BIL I\nKRISTIANSTAD AB\n\nPnr 291 05\n\nKristianstad 5, Box 5102. Nässelv\n4. Tel 044-126050. Bankgiro\n655-1014. Postgiro 696684-0\nVerksamhet: Auktoriserad\nåterförsäljare av SAAB o Chrysler bilar\nsamt service. Biluthyrning\nFilialer: 27 2 00 Simrishamn. Hasses\nBil i Simrishamn AB, Stora Rådhusg\n27. Tel 0414-122 80. Chef: Disp\nJan-Ake Månsson\n270 53 Gärsnäs. Tel 0414-50 3 40\n283 00 Osby. Hasses Bil i Osby AB.\nTel 0479-126 00\nAntal anställda: 85\nÅrsomsättning: 19000 000\nStyrelse: Disp Hans-Bertil Månsson,\ndisp Jan-Ake Månsson\nVerkst dir: Hans-Bertil Månsson\nEtableringsår: 1967.\n\nHASSLAROD\nKISELGUR-FABRIK\n\n.Pnr 283 00\n\nOsby, Box 42. Tel 0479-100 71.\nPostgiro 30801. Tga Kiselgur\nVerksamhet: Tillverkar kiselgur o\nisoleringsmassa\nAntal anstäUda: 10\nÅrsomsättning: 200 000\nÄgare o chef: Ing Axel Hedberg\nDisp: Gillis Nordström\nEtableringsår: 1916.\n\nBNG FABRIKS AB\n\nPnr 417 34\n\nGöteborg, Ovädersg 14. Tel\n031-53 04 65. Bankgiro 687-7690.\nPostgiro 401646-5\n\nVerksamhet: Säljer o uthyr\nbygg-maskiner\n\nAntal anställda: 4\nÅrsomsättning: 300 000\nAktiekapital: 15 000\nVerkst dir: Georg Lindeberg\nEtableringsår: 1965.\n\nBOARD &amp; PLASTIC LTD AB\n\nPnr 22101\n\nLund 1, Fack. Råbyholms Allé 2.\nTel 046-14 0018. Bankgiro\n173-1108. Telex 32203 BOARD S\nVerksamhet: Säljer på agenturbasis\npapper, plast, PE-belagd kartong\no andra material för\nlivsmedelsförpackningar\nAntal anställda: 3\nÅrsomsättning: 10 000 000\nAktiekapital: 5 000\nVerkst dir: Lars Leander\nEtableringsår: 1966.\n\nNORDISKA KARDAN AB\n\nPnr 16111\n\nBromma 11, Ranhammarsv 24. Fack.\nTel 08-26 25 00. Bankgiro 74-3524.\nPostgiro 196. Tga Nordjoints.\nTelex 10502\n\nVerksamhet: Tillverkar\nkardanaxlar, -kopplingar o delar därtill med\ntillhörande reparations- o\nserviceverksamhet\nAntal anställda: 90\nÅrsomsättning: 10 000 000\nAktiekapital: 1000 000\nVerkst dir: Nils Dahlberg\nEtableringsår: 1894\nNuvarande namn 1962.\n\nNORDISKA KOMPANIET, AB\n\nPnr 103 83\n\nStockholm 7, Hamng 18-20. Box\n7159. Tel 23 00 00, riks 08-23 63 00.\nPostgiro 481. Telex 10357. Tga\nKompaniet\n\nVerksamhet: Fullsortimentsvaruhus\ni Stockholm, Malmö o Göteborg\nAntal anställda: 3 500\nÅrsomsättning: Detaljhandel\n359000 000, leveransrörelse\n53 000 000\n\nAktiekapital: 76 500 000\nVerkst din Erik Söderberg\nEtableringsår: 1902.\n\nSONESSON INREDNINGAR AB\n\nPnr 21124\n\nMalmö, Sturkög 9. Tel 040-93 50 00.\nBankgiro 644-0069. Postgiro\n149393-1. Telex 3180 SONESON S\nVerksamhet: Tillverkar o säljer\nolika typer av stålinredningar för\nverkstäder, lager, förråd,\nomklädningsrum o lunchrum. Dessutom\nolika typer av förvaringsskåp för\nskolor, sjukhus o andra offentliga\ninrättningar\n\nFörsäljningskonton Stockholm. Tel\n08-44 96 90\n\nGöteborg. Tel 031-20 02 40\nSundsvall. Tel 060-157565\nVarunamn: Sono\nAntal anställda: 90\nÅrsomsättning: 13 000 000\nAktiekapital: 360 000\nStyrelse: Dir Alf Ltining, dir Hans\nBrand\n\nMarknadschef: L-E Ahlberg\nEtableringsår: 1909.\nNamnändring till Sonesson\nInredningar AB 1968. Ett företag i\nSo-nessonkoncernen.\n\nSONESSON PLAST AB\n\nPnr 21613\n\nMalmö, Limhamnsv 108-110. Tel\n040-15 5 0 20. Bankgiro 870-1781.\nPostgiro 38205-1. Tga Lavella.\nTelex 3180 SONESON S\nVerksamhet: Tillverkar o säljer\nsträngsprutade plastprodukter:\nprofiler, slangar, rör o monofilament\nAvdelningskontor: Mölndal,\nKrok-slätts Parkg. Box 5049, 402 21\nGöteborg 5. Tel 031-20 3440. Telex\n20626 API S\n\n116 21 Stockholm, Tjärhovsg 8. Tel\n08-44 96 90\n\nVarunamn: Lavella, Laveten\nAntal anställda: 225\nÅrsomsättning: 23 000 000\nAktiekapital: 1000 000\nStyrelse: Dir Alf LUning (ordf), dir\nHans Brand, dir Ernst van der Pals\nVerkst dir: Ernst van der Pals\nEtableringsår: 1889\nBolaget omorganiserades 1964.\nSamtidigt ändrades firmanamnet,\nSvenska Bindgamsfabrikens AB till\nSydsvenska Profil AB.\nNamnändring 1968 till Sonesson Plast AB.\nBolaget ingår i Sonessonkoncernen.\n\nSONESSON PUMPINDUSTRI AB\n\nPnr 402 21 Gbg 5\nMölndal, Krokslätts parkg. Box\n5049, Gbg5. Tel 031-20 00 20.\nBankgiro 500-1250. Postgiro 41382-3.\nTga Pumpindustri.\nTelex 20626 API S\nVerksamhet: Tillverkar\ncentrifugalpumpar. Representerar utländska\npumptillverkare\n\nFilialer: Stockholm, Malmö,\nSundsvall\n\nVarunamn: API, EMU, Gothia, SIHI\nAntal anställda: 200\nAktiekapital: 1500 000\nVerkst dir: Sven G Klemming\nEtableringsår: 1918.\n\nYXH\n\nYSTAD PLASTINDUSTRI\n\nPnr 27100\n\nYstad. Disponentg 2. Tel\n0411-15175, 151 76\n\nVerksamhet: Formsprutning.\nSpecialitet: emballage o engångsbestick\nAntal anställda: 25\nÅrsomsättning: 2 400 000\nChef: Fabr Benkt Johansson\nEtableringsår: 1961.\n\nYSTADS STUVERI.\nAKTIEBOLAG\n\nPnr 27100\n\nYstad, Box 47. Hamng 16. Tel\n0411-180 80. Bankgiro 873-1358.\nPostgiro 468900-6\nVerksamhet: Lossning o lastning\nav fartyg. Truckuthyrning. Ombud\nför Jonsereds\nPresenningsuthyrning, Malmö\nAntal anställda: 21\nÅrsomsättning: 750 000\nAktiekapital: 60 000\nStyrelse: Disp Ove Asp (ordf), disp\nMalte Tuvesson, disp Per Ostberg,\ndisp Ove Löf stedt, konsul Ake\nRaihle, dir A Carlekrantz\nVerkst dir: A Carlekrantz\nArbetschef: Sjökapten Allan\nBergquist\n\nEtableringsår: 1908.\n\nYSTA. MASKINER\n\nse Ystads Gjuteri &amp; Mek\nVerkstads AB.\n\nYTONG AB\n\nPnr 52100\n\nFalköping, Sankt Olofsg 4. Tel\n0515-132 80. Postgiro 24242. Telex\n5056. Tga Ytong\n\nVerksamhet: Tillverkar Ytong\n(lättbetong), arbetad o oarbetad\nkalksten, tennismassa, bränd o osläckt\nkalk\n\nFabriker: Ekedalen.\nLawnitfabri-ken. Tel 0502-42130\nFalköping. Kalkhydratfabriken,\nUddagården. Tel 0515-137 07\n\nFalköping. Uddagårdens\nStenhug-geri. Tel 0515-13180\nFalköping. Ytongfabriken\nUddagården. Tel 0515-131 80\nStenstorp. Stenåsens\nKalkstensbrott, Dala. Tel 0500-512 74\nValtorp. Berga Egendom. Tel\n0515-31132\n\nVarunamn: Lawnit, Ytong\nAntal anställda: 547\nÅrsomsättning: 39 000 000\nAktiekapital: 20 000 000\nStyrelse: Dir Bertil Carlén (ordf),\ndisp Erik Carlén, herr Lars\nWir-ström, dlr Karlerik Savén, adv\nLars Sjöborg, dir Sven Öster lind,\njur kan Ulla Hilliard-Hertzman,\ndir Bo Rydin\n\nVeikst din Karlerik Savén\nPlatschef: Disp Bertil Åström\nEtableringsån 1918\nNamnändring 1955 till Ytong AB.\nDotterbolag: Svenska Cellbetong\nAB, Yxhults Stenhuggeri AB, Bo.\nrensbergs Ytong AB, Olands Ytong\nAB, Ytongkontoret AB, AB\nMarmorbrytning, AB Minwool, AB\nYtonghus, Intong AB Ytong AG\n(Tyskland).\n\nYTONGKONTORET AB\n\nPnr 17136\n\nSolna, Pyramidv 4. Tel 08-83 02 90.\nPostgiro 57121. Telex 19975. Tga\nYxhult\n\nVerksamhet: Säljer o distribuerar\nYtong (lättbetong)\nVarunamn: Ytong\nAntal anställda: 14\nÅrsomsättning: 17 800 000\nAktiekapital: 100000\nStyrelse: Dir Bertil Carlén (ordf),\ndir Göran Carlén, dir Karlerik Savén\nVerkst dir: Karlerik Savén\nPlatschef: Stig Bjällsten\nEtableringsån 1942\nNamnändring 1963.\n\nYTTEKNIK, AB\n\nPnr 190 60\n\nBälsta, Håtunav. Tel 0171-540 40.\nBankgiro 720-7780. Postgiro\n\n199373-2. Tga Ytab. Telex 4754\nVerksamhet: Exploaterar metoder\nför fosfaterlng, kromatering o\ntrum-ling samt katodiskt skydd.\nExploaterar metoder samt levererar\nlegeringar för framställning av\nhögvärdigt gjutjärn\n\nVarunamn: Ampak, Bönder, Roto-\n\nFinish, Tenopur\n\nAktiekapital: 600 000\n\nVerkst din Bergsing Sten Porat\n\nEtableringsår: 1932\n\nHelägt dotterbolag till Metallge-\n\nsellschaft AG, Frankfurt/Main.\n\nYvY I MALMÖ AB\n\nPrr 27100\n\nYstad, Box 15. Kopparg 5. Tel\n0411-18045. Bankgiro 874-7594.\nPostgiro 532624-4. Tga YvY\nVerksamhet: Tillverkar o säljer\nkosmetiska preparat, aerosoler o\nkem tekn artiklar\nAntal anställda: 25\nAktiekapital: 100 000\nVerkst dir: Walter Krahlmark\nEtableringsår 1895.\n\nRYB\n\nVerksamhet: Tillverkar\nspecialmaskiner, vapenreparationer\nChef: Dir Claes-H Rundgren\nEtableringsån 1956.\n\nRUNDGRENS VÄVERI,\nAB KARL\n\nPnr 502 35\n\nBorås, Johannelundsg 34. Tel\n033-13 74 40. Tga Curtain. Telex 36122\nVerksamhet: Tillverkar draperi- o\ngardintyger\nAktiekapital: 130 000\nVeikst dir: Karl Rundgren.\n\nRUNDQVIST PLÅT AB\n\nPnr 653 41\n\nKarlstad, Blockg 10. Tel\n054-118191, 1842 00. Bankgiro\n102-4249. Postgiro 395679-4\nVerksamhet: Alla förekommande\narbeten inom byggnadsplåtslageri\nAntal anställda: 26\nÅrsomsättning: 1400 000\nAktiekapital: 25 000\nVerkst dir: Helge Rundqvist\nEtableringsår: 1946.\n\nRUNDLDF AB,\nBYGGNADSFIRMAN EDVIN\n\nPnr 11129\n\nStockholm, Triewaldsgränd 2. Tel\n08-11 68 52, 20 53 65. Bankgiro\n568-9435. Postgiro 57813-8\nVeiksamhet: Bedriver\nbyggnadsrörelse, främst restaurering\nAntal anställda: 30\nAktiekapital: 120 000\nVeikst dir. Byggn-ing Gustaf Ek\nEtableringsår: 1917.\n\nSYDSVENSKA KRAFT AB\n\nPnr 200 70\n\nMalmö 5, Fack. Carl Gustafs v 1.\nTel 040-703 4 0. Bankgiro 991-2320.\nPostgiro 14192-9. Tga Sydkraft\nVerksamhet: Produktion o\ndistribution av elektrisk energi\nAntal anställda: 2 154\nÅrsomsättning: 394 733 000\nAktiekapital: 167 196 000\nStyrelse: Oscar Stenberg (ordf),\nErik Adamsson, Torsten AndrSe,\nGöran Ekberg, Nils Falk, Einar\n\nHenningsson, Harry Hjalmarson,\nSven Johansson, Nils Mårtensson,\nHarald Schoug, Ture Ågren\nVerkst dir: Göran Ekberg\nDirektion: Dir Anders Björgerd, dir\nYngve Larsson, dir Sten-Ake\nCarleheden, övering Arvid Persson\nEtableringsår: 1906\nDotterbolag: AB Atomkraftverk, AB\nBygdeelektrifiering, Dångs AB,\nHjälta AB, Karlshamnsverkets\nKraftgrupp AB, AB Kärnkraftverk,\nMattmars Kraft AB, AB Nordkraft,\nPengfors AB, AB Skanör-Falsterbo\nElverk, Sollefteåforsens AB,\nSva-Löfs Kraft AB, AB Sydenergi, AB\nSydgas, Sydsvens ka Värmekraft AB,\nTeckomatorpsortens Kraft AB,\nTrångfors AB.\n\nSYDSVENSKA MASSAVEDS AB\n\nPnr 30104\n\nHalmstad 1, Karl XI:s väg 19. Box\n197. Tel 035-119130. Bankgiro\n15-3478. Postgiro 124143.\nTga Sydved, Halmstad\nVerksamhet: Förvaltar skogar o\nhandhar virkesköp för AB Papyrus,\nHylte Bruks AB, Ry AB o Nymölla\nAB\n\nAntal anställda: 95\nÅrsomsättning: 62 000 000\nAktiekapital: 500 000\n\nStyrelse: Disp Torkel Högberg\n(ordf), dir Einar Harald, jägmäst\nSven Gilljam\nVerkst dir: Sven Gilljam\növriga chefer: Skogsförvaltare Sven\nEdvardsson, intendent Sten\nPal-gren, kamrer Birger Jansson\nEtableringsår. 1963.\n\nSYDSVENSKA PATENT.\nBYRÅN, T KINBERG\n\nPnr 211 25\n\nMalmö, Drottningtorget 1. Tel\n040-12 71 78, 12 72 22. Bankgiro\n674-8289. Postgiro 147683-7.\nTga Sydpatent.\nTelex 32374 SERVIO S\nVerksamhet: Patentbyrå, inlämning\nav patent, varumärken o mönster,\nundersökningar o utredningar\nAntal anställda: 7\nÅrsomsättning: 600 000\nÄgare o chef: Ing Tage Kinberg\nEtableringsår 1928.\n\nFALLA ÅNGSÅG, AB\n\nPnr 612 00\n\nFinspång. Tel 0122-10178.\nBankgiro 13-2713. Postgiro 11828\nVerksamhet: Sågverk o\nträvaruhandel. Tillverkar o säljer snickerier\nAktiekapital: 75 000\nEtableringsår: 1943.",
    "structured": {
        "1": {
            "company_name": "ÅFORS, PLASTFABRIKEN",
            "address": "Anders torp, Törås, Postl 441",
            "phone_number": "0371-162 61",
            "bank_details": {
                "bankgiro": "488-1884",
                "postgiro": "95647-4"
            },
            "activity": "Tillverkar handtag. Utför legoarbeten",
            "annual_turnover": 200000,
            "key_personnel": [
                {
                    "name": "Lennart Tibratt",
                    "position": "Chef"
                }
            ],
            "establishment_year": 1958
        },
        "2": {
            "company_name": "ROSTFRIA TAK AB",
            "address": "Fagersta 1, Fack",
            "phone_number": "0223-180 00",
            "bank_details": {
                "bankgiro": "81-0386",
                "postgiro": "590270"
            },
            "activity": "Tillverkar o marknadsför sömsvetsad rostfri plåt för tak, fasader, fuktisoleringar o fryshus samt tillhörande detaljer",
            "employees": 18,
            "annual_turnover": 8000000,
            "capital": 20000,
            "key_personnel": [
                {
                    "name": "Dir Bengt Torssell",
                    "position": "Styrelseordförande"
                },
                {
                    "name": "Ing Arne Bergström",
                    "position": "Ing"
                },
                {
                    "name": "Dir Sture Netterstedt",
                    "position": "Dir"
                },
                {
                    "name": "Övering Lars Sjödén",
                    "position": "Övering"
                }
            ],
            "establishment_year": 1962,
            "parent_company": "Fagersta Bruks AB"
        },
        "3": {
            "company_name": "ROTHAG, AB",
            "address": "Johanneshov 6, Vikstensv 1",
            "phone_number": "08-49 99 50 , 49 99 90",
            "bank_details": {
                "bankgiro": "570-3947",
                "postgiro": "553420-1"
            },
            "activity": "Metall o ädelmetall-halvfabrikat, trådbearbetnings-maskiner, kemikalier, galvanoteknik",
            "capital": 10000,
            "key_personnel": [
                {
                    "name": "S Rothschild",
                    "position": "Verkställande direktör"
                }
            ],
            "establishment_year": 1956
        },
        "4": {
            "company_name": "HASSELFORS BRUKS AB",
            "address": "Hasselfors, Huvudkontor",
            "phone_number": "0585-44100",
            "bank_details": {
                "postgiro": "92220-3"
            },
            "activity": "Träindustri: Sågverk, hyvleri, Impregneringsverk, snickerifabrik o försäljningskontor",
            "employees": 700,
            "annual_turnover": 48000000,
            "capital": 3000000,
            "key_personnel": [
                {
                    "name": "Disp Bo Risberg",
                    "position": "Verkställande direktör"
                },
                {
                    "name": "Henric Stenby",
                    "position": "Ekonomidirektör"
                }
            ],
            "establishment_year": 1646,
            "restructuring_year": 1876,
            "parent_company": "Förvaltnings AB Hasselfors"
        },
        "5": {
            "company_name": "HASSELGRENS TRÄVARU AB, GUSTAF",
            "address": "Stockholm, Luntmakarg 36",
            "phone_number": "08-20 75 28, 11 16 38",
            "bank_details": {
                "bankgiro": "57-0919",
                "postgiro": "51238"
            },
            "activity": "Säljer trävaror",
            "employees": 5,
            "annual_turnover": 500000,
            "capital": 80000,
            "key_personnel": [
                {
                    "name": "Gustaf Hasselgren",
                    "position": "Verkställande direktör"
                }
            ],
            "establishment_year": 1910
        },
        "6": {
            "company_name": "HASSES BIL I KRISTIANSTAD AB",
            "address": "Kristianstad 5, Box 5102, Nässelv 4",
            "phone_number": "044-126050",
            "bank_details": {
                "bankgiro": "655-1014",
                "postgiro": "696684-0"
            },
            "activity": "Auktoriserad återförsäljare av SAAB o Chrysler bilar samt service. Biluthyrning",
            "branches": [
                {
                    "location": "Simrishamn",
                    "company_name": "Hasses Bil i Simrishamn AB",
                    "address": "Stora Rådhusg 27",
                    "phone_number": "0414-122 80",
                    "key_personnel": {
                        "name": "Disp Jan-Ake Månsson",
                        "position": "Chef"
                    }
                },
                {
                    "location": "Gärsnäs",
                    "company_name": "Hasses Bil i Gärsnäs AB",
                    "address": "--",
                    "phone_number": "0414-50 3 40",
                    "key_personnel": {
                        "name": "--",
                        "position": "--"
                    }
                },
                {
                    "location": "Osby",
                    "company_name": "Hasses Bil i Osby AB",
                    "address": "--",
                    "phone_number": "0479-126 00",
                    "key_personnel": {
                        "name": "--",
                        "position": "--"
                    }
                }
            ],
            "employees": 85,
            "annual_turnover": 19000000,
            "key_personnel": [
                {
                    "name": "Disp Hans-Bertil Månsson",
                    "position": "Styrelseordförande"
                },
                {
                    "name": "Disp Jan-Ake Månsson",
                    "position": "Verkställande direktör"
                }
            ],
            "establishment_year": 1967
        },
        "7": {
            "company_name": "HASSLAROD KISELGUR-FABRIK",
            "address": "Osby, Box 42",
            "phone_number": "0479-100 71",
            "bank_details": {
                "postgiro": "30801"
            },
            "activity": "Tillverkar kiselgur o isoleringsmassa",
            "employees": 10,
            "annual_turnover": 200000,
            "key_personnel": [
                {
                    "name": "Ing Axel Hedberg",
                    "position": "Ägare o chef"
                },
                {
                    "name": "Gillis Nordström",
                    "position": "Disp"
                }
            ],
            "establishment_year": 1916
        },
        "8": {
            "company_name": "BNG FABRIKS AB",
            "address": "Göteborg, Ovädersg 14",
            "phone_number": "031-53 04 65",
            "bank_details": {
                "bankgiro": "687-7690",
                "postgiro": "401646-5"
            },
            "activity": "Säljer o uthyr bygg-maskiner",
            "employees": 4,
            "annual_turnover": 300000,
            "capital": 15000,
            "key_personnel": [
                {
                    "name": "Georg Lindeberg",
                    "position": "Verkställande direktör"
                }
            ],
            "establishment_year": 1965
        },
        "9": {
            "company_name": "BOARD & PLASTIC LTD AB",
            "address": "Lund 1, Fack, Råbyholms Allé 2",
            "phone_number": "046-14 0018",
            "bank_details": {
                "bankgiro": "173-1108"
            },
            "activity": "Säljer på agenturbasis papper, plast, PE-belagd kartong o andra material för livsmedelsförpackningar",
            "employees": 3,
            "annual_turnover": 10000000,
            "capital": 5000,
            "key_personnel": [
                {
                    "name": "Lars Leander",
                    "position": "Verkställande direktör"
                }
            ],
            "establishment_year": 1966
        }
    }
}