{
    "original": "SPORRONG, AB\n\nPnr 76100\n\nNorrtälje, Pack. Baldersg 25. Tel\n0176-127 20. Bankgiro 41-1405.\nPostgiro 1405. Telex 10258. Tga\nSporrongs\n\nVerksamhet: Tillverkning o\nförsäljning av personal- o yrkesemblem,\nproduktemblem o skyltar,\nuniforms-emblem o knappar, medaljer o\npla-ketter, manschettknappar,\nslips-hållare. rockslagmärken,\nförtjänstmärken, blazermärken o\ndräktmärken, namnplattor o\nnamnkorthålla-re, reklam- o turistmärken,\nnyckel-hållare, ringar o berlocker,\nverk-tygs- o besöksbrickor, polletter\nDistriktskontor: 11143 Stockholm,\nKungsg 17. Tel 08-22 56 60\nAntal anställda: 400\nAktiekapital: 3 780 000\nStyrelse: Dir Göran Tamm (ordf),\ndir Mats Hede, dir Carl Kreuger,\ndir Gunnar Perën, dir Georg\nNyström\n\nVerkst dir: Georg Nyström\nEtableringsår: 1842\nOmbildat till aktiebolag 1891.\n\nSPORRONG MYNTAPPARATER\nAB\n\nPnr 761 00\n\nNorrtälje, Pack. Baldersg 25. Tel\n0176-127 20. Bankgiro 41-1405.\nPostgiro 1405. Telex 10258. Tga\nSporrongs\n\nVerksamhet! Tillverkning o\nförsäljning av Cambist\nmyntväxlings-apparat, P-matic växlingsautomat\nför mynt o polletter,\nväxelåter-givare för snabbkassor, kiosker\netc, kassalådor, myntsorterare,\nmyntbössor mm\nAntal anställda: 15\nProduktionschef: Harald Linnérus\nEtableringsår: 1969.\n\nINDUSTRIMETODER, AB\n\nPnr 102 44\n\nStockholm 5, Nybrog 65-67. Box\n5168. Tel 08-63 06 20. Bankgiro\n160-1186. Postgiro 194972-6. Tga\nIndustrimetoder. Telex 1672\n\nVerksamhet: Händels- o\nagenturfirma, malmer, mineral, kemikalier.\nTillverkar betongkemikalier o\ntät-ni ngslister\n\nVarunamn: Compriband, Darex\nAEA, Ravolen, Dicalite, Flammex\nAntal anställda: 23\nÅrsomsättning: 12 000 000\nAktiekapital: 500 000\nVeikst dir Gunnar Qvenild\nEtableringsår 1922.\n\nFASSON AB\n\nPnr 211 24\n\nMalmö, Kosterög 5. Tel\n040-18 1245. Bankgiro 337-7272.\nPostgiro 624100-4. Tga Fasswed.\nTelex 32599\n\nVerksamhet: Säljer självhäftande\nmaterial. Dubbelhäftande tejp\nVerkst dir: Dick B Bondeson\nEtableringsår: 1962.\n\nVIKONBOLAGET\n\nPnr 411 10\n\nGöteborg, O Hamng 19 B. Tel\n031-10 60 71. Postgiro 243688. Tga\nVikontile\n\nVerksamhet: Säljer väggplattor,\nrostskyddsfärger, motorer o båtar.\n\nWIKSTRAND &amp; BERG WIBE, AB\n\nPnr 792 00\n\nMora, Box 19. Tel 0250-119 00.\nBankgiro 46-9175. Postgiro 77622.\nTelex 7759. Tga Wibe\nVerksamhet: Tillverkar stegar,\nradio- o TV-master m m\nAntal anställda: 300\nÅrsomsättning: 35 000 000\nAktiekapital: 800000\nVerkst dir: Hans O Nilsson\nEtableringsår: 1929.\n\nWIKSTRÖMS\nKARTONG-INDUSTRI AB\n\nPnr 602 29\n\nNorrköping, Stohagsg 4,\nHantverkshuset. Tel 011-124177. Postgiro\n176727.\n\nVerksamhet: Tillverkar förpackning\nmed eller utan tryck för industri o\no handel. Utför alla slags\nstansningsarbeten\n\nÄgare: Bo Wikström, Bengt\nWikström\n\nEtableringsår: 1937.\n\nOREBROLACKERINGAR, AB\n\nPnr 700 06\n\nÖrebro 6, Box 6015. Hammarv 2.\nTel 019-22 5190. Bankgiro\n822-8140. Postgiro 583370-2\nVerksamhet: Utför lackeringar\n.Antal anställda: 6\nÅrsomsättning: 500 000\nAktiekapital: 60 000\nVerkst dir: Raymond Ericson\nEtableringsår: 1950.\n\nÖREBRO-ORTENS MEJERI.\nFÖRENING\n\nPnr 703 67\n\nÖrebro, Längbrog 23-27. Tel\n019-119070. Bankgiro 463-2139.\nPostgiro 12887-6. Tga Mejeriföreningen\nVerksamhet: Mjölk, grädde,\nmjölkpulver, smör, dessertost\nAntal anställda: 197\nÅrsomsättning: 88 000 000\nFirmatecknare: Rolf Ivarsson, Per\nK J Ge is\n\nEtableringsår: 1920.\n\nLIN\n\nAktiekapital: 46 000\nVerkst dir: Torsten Lindstam\nEtableringsàr: 1955.\n\nLINDSTAM AB, T\n\nPnr 124 21\n\nBandhagen 1, Harpsundsv 201. Box\n\n31. Tel 08-47 25 75. Postgiro\n\n704594. Tga Ennelco\n\nVerksamhet: Försäljning av Hatz-\n\ndieselmotorer\n\nVarunamn: Hatz\n\nVerkst dir: Torsten Lindstam\n\nEtableringsàr: 1963.\n\nLINDSTEDT &amp; SONS\nGELBGJUTERI, AB\n\nPnr 38100\n\nKalmar, Fiskareg 22-24. Tel\n0480-100 64. Postgiro 140177-7\nVerksamhet: Metallgjuteri, mek\nverkstad, cykel- o motorverkstad\nChef: Arne Lindstedt.\n\nLINDSTEDTS MEK VERKSTAD,\nC G\n\nPnr 710 27\n\nDyltabruk, Ervalla. Tel019-28 10 45.\nBankgiro 817-4401. Postgiro\n167042-1\n\nVerksamhet: Tillverkar\ntransportvagnar för industrier o lantbruk\nChef: Fabr C G Lindstedt\nEtableringsàr: 1931.\n\nLINDSTEDT &amp; CO, AB H E\n\nPnr 181 46\n\nLidingö, Askrikev 15. Tel\n08-765 42 60, 765 42 61. Bankgiro\n56-0282. Postgiro 255190. Tga\nHel-comp\n\nVerksamhet: Verktygsmaskiner,\ntransportanordningar,\nkuggväxelmotorer, snäckväxlar, kuggväxlar,\nindustrikedjor, telfrar, pumpar,\nvariatorer, växellådor, kopplingar,\nträbearbetningsmaskiner\nUtställning: Stockholm C, Välling\n44. Tel 08-765 4260\nVarunamn: Lindstedts\nAktiekapital: 10 000\nStyrelse: Kamrer Märta Lindstedt\n(ordf), fru Agnes Ohlsson\nVerkst dir: HES Lindstedt\nEtableringsàr: 1946\nOmbildat till aktiebolag 1956.\n\nLINDSTEDT AB, TÖRE\n\nPnr 400 50\n\nGöteborg 20, Månsegårdsg 5. Box\n20027. Tel 031-26 28 92. Bankgiro\n420-0655. Postgiro 526160-5. Tga\nToli\n\nVerksamhet: Säljer råvaror\n(gjut-legeringar av aluminium,\nkemikalier) o färdigfabrikat av elektrografit\nÅrsomsättning: 5 000 000\nAktiekapital: 25 000\nChef: Töre Lindstedt\nEtableringsàr: 1959.\n\nLINDSTEIN, AB BENGT\n\nPnr 630 08\n\nEskilstuna 8, Gustafsv 7. Box\n8036. Tel 016-11 04 75. Bankgiro\n828-1891. Postgiro 499570-0\nVerksamhet: Försäljning, uthyrning\no reparationer av byggmaskiner\nAntal anställda: 10\n\nÅrsomsättning: 3 000 000\nAktiekapital: 30 000\nVerkst dir: Bengt Lindstein\nEtableringsàr 1958.\n\nNORSÄLVENS SÅGVERKS AB\n\nPnr 65103\n\nKarlstad 1, Kungsg 12. Box 108.\nTel 054-11 6256. Tga Norstrae.\nTelex 66064\nVerksamhet: Trävaror\nFilial: Norsbron. Tel 054-450 18,\n450 39. Sågverk o träimpregnering\nAntal anställda: 60\nÅrsomsättning: 10 000000\nAktiekapital: 450 000\nVerkst dir: Sten G Helmer\nDisp: Gösta Sonander\nEtableringsår: 1941.\n\nENGEL-FABRIKERNA AB\n\nPnr 59101\n\nMotala 1, Fack. Tel 0141-16100.\nBankgiro 134-1478. Postgiro 28366-3.\nTga Engel-Fabrikerna\nVerksamhet: Tillverkar möbler o\nheminredningstextilier samt driver\nengrosrörelse i mattor o därmed\nförenlig verksamhet\nVarunamn: Engel\nAntal anställda: 70\nAktiekapital: 600 000\nStyrelse: Jur dr Bertil af Klercker\n(ordf), dir Gösta Engel, adv Erik\nOrrenius\n\nVerkst dir: Gösta Engel\nEtableringsår: 1945.\n\nELECTROSPECIAL AB\n\nPnr 213 63\n\nMalmö, Nya Agnesfri dsv 195. Tel\n040-21 65 00. Bankgiro 87-5202.\nPostgiro 633300\n\nVerksamhet: Tillverkar elektriska\nspecial- o kontrollutrustningar\nAntal anställda: 5\nÅrsomsättning: 750 000\nAktiekapital: 50000\nVerkst dir: Ing E Akerfelt\nEtableringsår: 1964.\n\nELECTROSTAR AB\n\nPnr 701 04\n\nÖrebro 1, Box 228. Fabriksg 12.\nTel 019-13 61 90. Postgiro 2921\nVerksamhet Importerar o säljer\nköksmaskiner, dammsugare,\nkaffeautomater, elvispar, skoputsare,\nråsaftcentrifuger o handtorkare\nVarunamn: Electrostar, Elstar\nAntal anställda: 3\nÅrsomsättning: 400 000\nAktiekapital: 30 000\nStyrelse: Dir Magnus Lundekvam\n(ordf), fru Ruth Lundekvam\nVerkst dir: Magnus Lundekvam\nEtableringsår. 1927.\n\nELECTRONA\nTELEKOMPO-NENT AB\n\nPnr 123 53\n\nFarsta, Sköndalsv 114. Tel\n08-93 08 80. Bankgiro 53-6835. Post-\n\nELEKTRA\n\nRATIONALISERINGS AB\n\nPnr 632 33\n\nEskilstuna. Solingev 1. Tel\n016-209 02. Bankgiro 601-9160.\nPostgiro 644599-3\n\nEskilstuna, Knut Hellbergsg 20.\nTel 016-112173. Bankgiro 60-1916.\nPostgiro 644599\nVerksamhet: Agenturförsäljning\nsamt tillverkning av elektroniska\nutrustningar\nChef: F Sternad\nEtableringsår: 1964.\n\nELEKTRISK\nMASKINSER-VICE, AB\n\nPnr 112 37\n\nStockholm, Pontonjärg 25. Tel\n08-52 48 85. Postgiro 708607\nVerksamhet Utför elektriska\ninstallationer\nÅrsomsättning: 132000\nAktiekapital: 5 000\nVerkst dir o ansvarig installatör:\nJuhani Haapanen\nEtableringsår: 1965.\n\nELEKTRISKA BYRÅN CHR\nBERGH I HALMSTAD AB\n\nPnr 302 42\n\nHalmstad, Köpmansg 5. Tel\n035-110897, 110989. Bankgiro\n42-3787. Postgiro 136395\n\nVerksamhet:\nEl-installationsrörel-se o försäljning av el-artiklar\nAntal anställda: 65\nÅrsomsättning: 3 700 000\nAktiekapital: 100 000\nVerkst din L Gärtner\nV verkst dir: E Glans\nEtableringsår: 1920\nOmbildat till aktiebolag 1961.\n\nELEKTRISKA\nKONSULENT-BYRÅN\n\nPnr 41115\n\nGöteborg, Kyrkog 40. Tel\n031-13 45 96, 13 45 97. Bankgiro\n612-2865. Postgiro 41654-5\nVerksamhet: Konstruktioner för\nelektr anläggningar. Besiktningar\nav elektr anläggningar, hissar o\nlyftinrättningar\nAntal anställda: 6\nÅrsomsättning: 300000\nChef: Ing Knut Flodberg\nEtableringsår. 1908.\n\nELEKTRISKA\nLINDAREVERKSTADEN R OLSSON AB\n\nPnr 681 00\n\nKristinehamn, Hamnbrog 11. Tel\n0550-112 01, 112 44. Bankgiro\n110-1203. Postgiro 395895-6\nVerksamhet: Specialverkstad för\nomlindningar o reparationer av\nelektr motorer o transformatorer.\nTillverkar o säljer elektr\ninbyggnadsmotorer. Uthyr dränkbara\nlänspumpar o svetsverk\nAntal anställda: 24\nÅrsomsättning: 1500000\nAktiekapital: 50 000\nÄgare o chef: Ing Rutger Olsson\nEtableringsår: 1922.\n\nELEKTRISKA MONTERINGS\nAB\n\nPnr 733 00\n\nSala, Box 52. Kålgårdsg 20.Tel\n02 24-133 50. Bankgiro 811-1861.\nPostgiro 27759-0\nVerksamhet: Elektriska\ninstallationer o entreprenader\nAntal anställda: 30\nAktiekapital: 37000\nVerkst dir: Evald Olsson\nEtableringsår: 1917.\n\nELEKTRISKA\nPROVNINGSANSTALTEN AB\n\nPnr 104 22\n\nStockholm 22, Hantverkarg 11 B.\nBox 22065. Tel 08-54 1600.\nBankgiro 44-7093. Postgiro 52933-9.\nTga Elektroprov\n\nVerksamhet: Konsulterande\ningenjörer\n\nAktiekapital: 50 300\nVerkst dir: Civiling H Ostlund\nEtableringsår: 1892.\n\nSUNDSVIKS BRUK AB\n\nPnr 15022\n\nNykvarn. Tel 0755^16060, 46061.\nBankgiro 170-6324. Postgiro\n27 62 52-4\n\nVerksamhet: Tillverkar fasad- o\nmurtegel samt driver skogshantering\nAntal anställda: 40\nÅrsomsättning: 2 500 000\nAktiekapital: 125 000\nVerkst dir: Jägmäst Gunnar Hagelin\nEtableringsår: 1944.",
    "structured": {
        "1": {
            "company_name": "SPORRONG, AB",
            "pnr": "76100",
            "address": "Norrtälje, Pack. Baldersg 25",
            "phone_number": "0176-127 20",
            "bank_details": {
                "bankgiro": "41-1405",
                "postgiro": "1405"
            },
            "activity": "Tillverkning o försäljning av personal- o yrkesemblem, produktemblem o skyltar",
            "employees": 400,
            "capital": 3780000,
            "key_personnel": [
                {
                    "name": "Dir Göran Tamm",
                    "position": "Ordförande"
                },
                {
                    "name": "Dir Mats Hede",
                    "position": null
                },
                {
                    "name": "Dir Carl Kreuger",
                    "position": null
                },
                {
                    "name": "Dir Gunnar Perën",
                    "position": null
                },
                {
                    "name": "Dir Georg Nyström",
                    "position": null
                },
                {
                    "name": "Georg Nyström",
                    "position": "Verkställande direktör"
                }
            ],
            "establishment_year": 1842
        },
        "2": {
            "company_name": "SPORRONG MYNTAPPARATER AB",
            "pnr": "761 00",
            "address": "Norrtälje, Pack. Baldersg 25",
            "phone_number": "0176-127 20",
            "bank_details": {
                "bankgiro": "41-1405",
                "postgiro": "1405"
            },
            "activity": "Tillverkning o försäljning av Cambist myntväxlings-apparat, P-matic växlingsautomat för mynt o polletter",
            "employees": 15,
            "establishment_year": 1969
        },
        "3": {
            "company_name": "INDUSTRIMETODER, AB",
            "pnr": "102 44",
            "address": "Stockholm 5, Nybrog 65-67",
            "phone_number": "08-63 06 20",
            "bank_details": {
                "bankgiro": "160-1186",
                "postgiro": "194972-6"
            },
            "activity": "Händels- o agenturfirma, malmer, mineral, kemikalier. Tillverkar betongkemikalier o tät-ni ngslister",
            "employees": 23,
            "annual_turnover": 12000000,
            "capital": 500000,
            "key_personnel": [
                {
                    "name": "Gunnar Qvenild",
                    "position": "Verkställande direktör"
                }
            ],
            "establishment_year": 1922
        },
        "4": {
            "company_name": "FASSON AB",
            "pnr": "211 24",
            "address": "Malmö, Kosterög 5",
            "phone_number": "040-18 1245",
            "bank_details": {
                "bankgiro": "337-7272",
                "postgiro": "624100-4"
            },
            "activity": "Säljer självhäftande material. Dubbelhäftande tejp",
            "employees": null,
            "capital": null,
            "key_personnel": [
                {
                    "name": "Dick B Bondeson",
                    "position": "Verkställande direktör"
                }
            ],
            "establishment_year": 1962
        },
        "5": {
            "company_name": "VIKONBOLAGET",
            "pnr": "411 10",
            "address": "Göteborg, O Hamng 19 B",
            "phone_number": "031-10 60 71",
            "postgiro": "243688",
            "activity": "Säljer väggplattor, rostskyddsfärger, motorer o båtar",
            "establishment_year": null
        },
        "6": {
            "company_name": "WIKSTRAND & BERG WIBE, AB",
            "pnr": "792 00",
            "address": "Mora, Box 19",
            "phone_number": "0250-119 00",
            "bank_details": {
                "bankgiro": "46-9175",
                "postgiro": "77622"
            },
            "activity": "Tillverkar stegar, radio- o TV-master m m",
            "employees": 300,
            "annual_turnover": 35000000,
            "capital": 800000,
            "key_personnel": [
                {
                    "name": "Hans O Nilsson",
                    "position": "Verkställande direktör"
                }
            ],
            "establishment_year": 1929
        },
        "7": {
            "company_name": "WIKSTRÖMS KARTONG-INDUSTRI AB",
            "pnr": "602 29",
            "address": "Norrköping, Stohagsg 4, Hantverkshuset",
            "phone_number": "011-124177",
            "postgiro": "176727",
            "activity": "Tillverkar förpackning med eller utan tryck för industri o handel. Utför alla slags stansningsarbeten",
            "establishment_year": 1937
        },
        "8": {
            "company_name": "OREBROLACKERINGAR, AB",
            "pnr": "700 06",
            "address": "Örebro 6, Box 6015, Hammarv 2",
            "phone_number": "019-22 5190",
            "bank_details": {
                "bankgiro": "822-8140",
                "postgiro": "583370-2"
            },
            "activity": "Utför lackeringar",
            "employees": 6,
            "annual_turnover": 500000,
            "capital": 60000,
            "key_personnel": [
                {
                    "name": "Raymond Ericson",
                    "position": "Verkställande direktör"
                }
            ],
            "establishment_year": 1950
        },
        "9": {
            "company_name": "ÖREBRO-ORTENS MEJERI. FÖRENING",
            "pnr": "703 67",
            "address": "Örebro, Längbrog 23-27",
            "phone_number": "019-119070",
            "bank_details": {
                "bankgiro": "463-2139",
                "postgiro": "12887-6"
            },
            "activity": "Mjölk, grädde, mjölkpulver, smör, dessertost",
            "employees": 197,
            "annual_turnover": 88000000,
            "key_personnel": [
                {
                    "name": "Rolf Ivarsson",
                    "position": "Firmatecknare"
                },
                {
                    "name": "Per K J Ge is",
                    "position": null
                }
            ],
            "establishment_year": 1920
        },
        "10": {
            "company_name": "LIN",
            "capital": 46000,
            "key_personnel": [
                {
                    "name": "Torsten Lindstam",
                    "position": "Verkställande direktör"
                }
            ],
            "establishment_year": 1955
        }
    }
}