{
    "original": "WENNSTRÖM, ELOF\n\nPnr 702 27\n\nÖrebro, Femkampsg 25. Tel\n019-18 8241. Bankgiro 115-1356.\nPostgiro 419094-8\n\nVerksamhet: Patenter o\nkonstruktioner för licenstillverkning i\nhuvudsak inom byggnadsfacket.\nTillverkar o säljer\nE-W-bjälk-laget\n\nChef: Elof Wennström\nEtableringsår: 1954.\n\nHYLLTEKNIK\n\nPnr 342 00\n\nAlvesta. Box 132. Tel 0472-107 67.\nBankgiro 75-9015. Postgiro 263099\nVerksamhet: Inredningar till lager,\nbutiker, arkiv, lasarett mm\nAntal anställda: 18\nÅrsomsättning: 800 000\nChef: Fabr Harald Hedlund\nEtableringsår: 1958.\n\nSVENSKA P LÄT ROR AB\n\nPnr 58103\n\nLinköping 1, Box 375. Florag 17.\nTel 013-10 2190. Bankgiro\n800-0192. Postgiro 464942-2. Tga\nSwedetubes\n\nVerksamhet: Tillverkar\ntunnväggiga plåtrör, stuprör o hängrännor\nmed alla detaljer, pressade\nrörvinklar för ventilation\nAntal anställda: 185\nÅrsomsättning: 20000000\n.Aktiekapital: 200 000\nVerkst dir: S O Landemark\nEtableringsår 1951.\nDotterbolag: AB Rich Pettersson,\nAneby, Nybrorännor AB, Nybro,\nSkänninge Ventilations AB,\nSkän-ninge.\n\nSVENSKA POLYSTYREN\nFABRIKEN AB\n\nPnr 244 00\n\nKävlinge. Tel 046-313 20.\nBankgiro 274-9745. Postgiro 248480-6.\nTga Styrene.\nTelex 3149 STYRENE S\nVerksamhet: Tillverkar polystyren,\npolystyrenskumplast. skivor o\nfolier av polystyren o polystyrenlim\nFörsäljning Sverige:\nA Johnson &amp; Co HAB. Box 57,\n201 20 Malmö 1. Tel 040-701 00\nVarunamn: Polystron, Polytherm\nAntal anställda: 120\nÅrsomsättning: 27 000 000\nAktiekapital: 4 000 000\nStyrelse: Dir Bengt Nilsson (ordf),\ndr Karl Mönkemeyer, adv Sten\nSandell, konsul Allan Length\nPersson\n\nVerkst dir: Tommy Kjellman\nEtableringsår: 1953.\n\nENGSTRÖM, AB AXEL\n\nPnr 411 38\n\nGöteborg, Nya Allén 5. Tel\n031-177610. Bankgiro 84-7715.\nPostgiro 41425-0\n\nVerksamhet: Byggnadsrörelse\nAntal anställda: 55\nÅrsomsättning: 4 000 000\nAktiekapital: 100 000\nÄgare: Ing Bertil Pettersson,\nciviling Gunnar Forsaeus\nEtableringsån 1903.\n\nGUM AT EX AB\n\nPnr 430 50\n\nKåUered, Box 100. Tel\n031-75 12 20. Bankgiro 420-3030.\nPost-giro 521676-7.\nTelex 2421 MAKADAM S\nVerksamhet: Experterar\nkonverterat papper. Agenturverksamhet\nÅrsomsättning: 4 000 000\nAktiekapital: 10 000\nStyrelse: Dir Sten Assarson (ordf),\njur kand Nils Assarson, dir\nLennart Albihn\nVerkst dir: Lennart Albihn\nExportchef: Lennart Hällegårdh\nEtableringsår: 1956\nModerbolag: Göteborgs Makadam AB.\n\nGDRANSSON,\nINGENJÖRS-FIRMAN BO\n\nPnr 724 10\n\nVästerås, Skeppsg 6. Tel\n021-1102 55. Postgiro 615583-2\nVerksamhet: Utför på entreprenad\nputs av följande typer: Tasad-,\ndekor-, akustik- o\nbrandisolerings-puts samt putsade undertak.\nTeknisk isolering för industrin.\nBrandisolering av stålkonstruktioner med\nskivor o puts\nAntal anställda: 15\nÅrsomsättning: 1100 000\nChef: Byggnadsing Bo Göransson\nEtableringsår: 1963.\n\nROTTNEROS AB\n\nPnr 65101\n\nKarlstad 1, Fack. Tel 054-1802 80.\nBankgiro 113-8734. Postgiro\n593720-6. Tga Rottnerosbruk.\nTelex 66043 RGROUPK S\nVerksamhet: Central\nadministration o försäljning för\nRottneros-concernen\n\nAntal anstäUda: 400\nÅrsomsättning: 14 000 000\nAktiekapital: 5000 000\nStyrelse: Disp P W Möller (ordf),\ntekn dir Sixten Ulfsparre, adv\nGustaf Carlsson, bankdir Olof\nErlandsson, docent Lennart Schotte,\nryttmäst Claes Horn af Åminne\nVerkst dir: C J Wettergren\nDotterbolag: Rottneros Träsliperi\nAB, Göta Cellulosa AB, Amotfors\nPappersbruks AB, AB Rasco.\n\nROTTNEROS TRÄSLIPERI AB\n\nPnr 680 12\n\nRottneros. Tel 0565-602 00\nVerksamhet Tillverkar våt o\nton-mekanisk slipmassa, raffmassa\nFörsäljningskontor: Karlstad 1,\nFack. Tel 054-18 02 80.\nTelex 66043 RGROUPK S\nAntal anstäUda: 200\nÅrsomsättning: 35 000 000\nDriftschef: Ing O S Johansson\nDotterbolag till Rottneros AB.\n\nROX MASKIN AB\n\nPnr 41121\n\nGöteborg, Stora Badhusg 16. Tel\n031-13 75 24, 13 75 45. Tga Duroxab\nVerksamhet: Exportförsäljning av\nmaskiner o utrustningar för betong-,\ngruv- o slakteriindustrierna\nVarunamn: Blu-Rox, Durogun, Tor\nAntal anstäUda: 5\nÅrsomsättning: 2 300 000\nAktiekapital: 50 000\nStyrelse: Dir John Jonasson (ordf),\nark Malte Neuendorf, prof Nils\nObel\n\nVerkst dir: Gunnar N Erikson\nEtableringsår: 1955.\n\nROYAL REFRIGERATION AB\n\nse Plåtindustri AB.\n\nR P RORPRODUKTER AB\n\nVerksamhet: Grossister i VVS-,\nVA-, industri-, el-, byggnads- o\ninredningsbranschen. Tillverkare,\ngrossister o exportörer i\nbrunnsborrningsbranschen\nVarunamn: RP\nAntal anstäUda: 250\nÅrsomsättning: 100 000 000\nAktiekapital: 1 000 000\nÄgare: G Bonevik\nEtableringsår: 1945\n402 52 Göteborg 13, RP-huset, von\nUtfallsg 9. Box 13109. Tel\n031-26 21 20. Telex 20648. Tga Rörprod\n75127 Uppsala 1, Gimog 4. Box 647.\nTel 018-10 03 40. Telex 7425\n93103 Skellefteå 3, Fack 650. Tel\n0910-141 50. Telex 6880\n90110 Umeå 1, Västerslätt. Box\n752. Tel 090-12 24 30. Telex 6762\n252 47 Sundsvall, Bergsg 126. Tel\n060-15 4170. Telex 71046\nFinland:\n\nRörprodukter AB/ Oy\nPutkivalmis-teita:\n\nHelsingfors 55, Notstrandsg 11. Tel\n\n79 06 33, 79 96 00\n\nNorge:\n\nRP Råprodukter A/S:\nStrömmen, Boks 65. TelLillestr^m\n71 50 60.\n\nRTA SVENSKA AB\n\nPnr 58102\n\nLinköping 1. Box 206. Brog 1. Tel\n013-1300 95. Bankgiro 415-3060.\nPostgiro 691820-5. Tga\nTransportdon\n\nVerksamhet: Tillverkar lyftdon\nsåsom Malcusblocket, blockvagnar,\npelarsvängkranar o traverser för\nhand-, el- o luftdrift\nAktiekapital: 400 000\nVerkst dir: Allan Inovius\nEtableringsår: 1967.\n\nÅGREN, ERAGNAR\n\nPnr 183 02\n\nTäby 2, Raka v 6. Box 2066. Tel\n08-758 73 40. Postgiro 151518-8.\nTga Ratrade, Stockholm\nVerksamhet: Import o exportfirma\nVarunamn: Glen Cree\nChef: E Ragnar Ågren\nEtableringsår: 1936.\n\nÅKERBERG &amp; FOGELSTROM\nRÖRLEDNINGS AB\n\nPnr 112 24\n\nStockholm, Plpersg 4. Tel\n08-52 00 90. Bankgiro 731-2382.\nPostgiro 193676-4\n\nVeiksamhet: Rörinstallationer\nAntal anställda: 100\nÅrsomsättning: 10 000000\nAktiekapital: 30 000\nVerkst dir: Nils Johnson\nEtableringsår: 1943.\n\nSVENSKA DAGBLADETS AB\n\nPnr 10517\n\nStockholm, Rålambsv 7-13. Tel\n22 50 00, riks 08-22 50 20. Bankgiro\n560-4657. Postgiro hk 61-2, pren\n823300. Tga Svenskadag.\nTelex 17400 SVED AG S\nVerksamhet: Tryckeri o\nreproavdelning\n\nAntal anställda: 800\nÅrsomsättning: 80 000 000\nAktiekapital: 2 750 000\nVeikst din Sven Gerentz\nEtableringsår 1884.\n\nPERSSON &amp; SON, AB MALTE\n\nPnr 302 44\n\nHalmstad, Furuv 9. Tel\n035-1106 72, 101250. Bankgiro\n85-9508. Postgiro 468260\nVerksamhet: Montering av\nbensin-o oljeanläggningar samt\nförsäljning av allt till samma. Utför\ncisternvård\nAntal anstäUda: 10\nÅrsomsättning: 750 000\nAktiekapital: 5000\nVerkst dir: Malte J V Persson\nVerkmäst: Osborn Valfrid Persson\nEtableringsår: 1921.\n\nPEHRSONS VALSQVARN, AB\nMÄRTEN\n\nPnr 29101\n\nKristianstad 1, Box 113.\nSpann-målsg 1 A. Tel 044-115 1 40.\nBankgiro 867-4186. Postgiro 6827-0.\nTga Mårtenqvarn\nVerksamhet: Kvarnrörelse.\nTillverkar mjöl o fodervaror.\nFörsäljning o expedition genom\nKvarnbolaget Nordmills AB\nAvdelningskontor o kvarn:\nLandskrona. Tel 0418-100 25\n(Varunamn i Kvarnbolaget: Axa,\nKejsarkronan m fi)\nAntal anstäUda: 116\nÅrsomsättning: 70 000 000\nAktiekapital: 9 000 000\nStyrelse: Dir Börje Lindgren (ordf),\nadv Knut Arning, dir Gösta\nCarl-born, dir Stig Carlbarn, dir Bertil\nEwe, dir Malte Ström, adv Wilhelm\nPenser\n\nVerkst dir: Stig Carlborn (Sthlm)\nV verkst dir o platschef: Gösta\nCarlborn\n\nDisp: Magnus Taube\nDriftsing: Bernhard Görman\nEtableringsår: 1888\nOmbildat till aktiebolag 1898.\nDotterbolag: AB Saltsjöqvarn,\nStockholm. AB Storhusqvarn,\nNyköping. Fabriks AB Merkantil,\nKristianstad. Helsingborgs Kvarn\nAB, Helsingborg, till 50 %.\n\nPERSSON AB,\nBYGGNADSFIRMAN NILS\n\nPnr 572 00\n\nOskarshamn, Smedg 21-23. Tel\n0491-105 80, 103 90. Bankgiro\n856-4643. Postgiro 96525-1\nVerksamhet: Husbyggen. Tillverkar\nmurbruk\n\nAntal anstäUda: 53\nÅrsomsättning: 5 291 000\nAktiekapital: 40 000\nStyrelse: Byggn-ing Birger Persson\n(crdf), fru Alva Larsson, herr Ivar\nLarsson, byggn-tekn Nils-Gunnar\nPersson, byggn-tekn Lars-Anders\nPersson\n\nEtableringsår: 1937.\n\nTRIABO INDUSTRI AB\n\nPnr 294 00\n\nSölvesborg, Box 78. Tel\n0456-117 90, 117 91. Bankgiro 663-9801.\nPostgiro 9157-9. Tga Tiab\nVerksamhet: Tillverkar\nbyggnadshjälpmedel såsom valvstämp, form-\n\nbalk, formbord, låsbrickor,\npasser-bryggor, pelarförband, snö- o\nnock-räckskonsoler m m. Utför\nvarmför-zinkning\n\nMek fabrik: Fagerhult. Tel\n0481-71175\n\nVarunamn: Tiab\nAntal anställda: 30\nÅrsomsättning: 2 500 000\nAktiekapital: 135 000\nChefer: Disp Allan Fältström,\ndisp Gunnar Haglind\nEtableringsår: 1955.\n\nTRIANGELN AB,\nKEMISKTEKNISKA FABRIKEN\n\nPnr 21214\n\nMalmö, Industrig 14-18. Tel\n040-180430. Bankgiro 875-3725.\nPostgiro 24513-4. Tga Kemitria\nVerksamhet: Konfektionering av\nplastfolier genom svetsning,\nklistring m m. Tillverkar\nmörkläggningsgardiner, draperier,\npresenningar mm\nAntal anställda: 9\nÅrsomsättning: 350 000\nAktiekapital: 20 000\nVerkst dir: Ing Gunnar Mårtenson\nEtableringsår: 1930.",
    "structured": {
        "1": {
            "company_name": "WENNSTRÖM, ELOF",
            "address": "Femkampsg 25, Örebro",
            "phone_number": "019-18 8241",
            "bank_details": {
                "bankgiro": "115-1356",
                "postgiro": "419094-8"
            },
            "activity": "Patenter o konstruktioner för licenstillverkning i huvudsak inom byggnadsfacket. Tillverkar o säljer E-W-bjälk-laget",
            "key_personnel": [
                {
                    "name": "Elof Wennström",
                    "position": "Chef"
                }
            ],
            "establishment_year": 1954
        },
        "2": {
            "company_name": "HYLLTEKNIK",
            "address": "Box 132, Alvesta",
            "phone_number": "0472-107 67",
            "bank_details": {
                "bankgiro": "75-9015",
                "postgiro": "263099"
            },
            "activity": "Inredningar till lager, butiker, arkiv, lasarett mm",
            "employees": 18,
            "annual_turnover": 800000,
            "key_personnel": [
                {
                    "name": "Fabr Harald Hedlund",
                    "position": "Chef"
                }
            ],
            "establishment_year": 1958
        },
        "3": {
            "company_name": "SVENSKA P LÄT ROR AB",
            "address": "Box 375, Linköping 1, Florag 17",
            "phone_number": "013-10 2190",
            "bank_details": {
                "bankgiro": "800-0192",
                "postgiro": "464942-2"
            },
            "activity": "Tillverkar tunnväggiga plåtrör, stuprör o hängrännor med alla detaljer, pressade rörvinklar för ventilation",
            "employees": 185,
            "annual_turnover": 20000000,
            "capital": 200000,
            "key_personnel": [
                {
                    "name": "S O Landemark",
                    "position": "Verkst dir"
                }
            ],
            "establishment_year": 1951
        },
        "4": {
            "company_name": "SVENSKA POLYSTYREN FABRIKEN AB",
            "address": "Kävlinge",
            "phone_number": "046-313 20",
            "bank_details": {
                "bankgiro": "274-9745",
                "postgiro": "248480-6"
            },
            "activity": "Tillverkar polystyren, polystyrenskumplast. skivor o folier av polystyren o polystyrenlim",
            "annual_turnover": 27000000,
            "capital": 4000000,
            "key_personnel": [
                {
                    "name": "Tommy Kjellman",
                    "position": "Verkst dir"
                }
            ],
            "establishment_year": 1953
        },
        "5": {
            "company_name": "ENGSTRÖM, AB AXEL",
            "address": "Nya Allén 5, Göteborg",
            "phone_number": "031-177610",
            "bank_details": {
                "bankgiro": "84-7715",
                "postgiro": "41425-0"
            },
            "activity": "Byggnadsrörelse",
            "employees": 55,
            "annual_turnover": 4000000,
            "capital": 100000,
            "establishment_year": 1903
        },
        "6": {
            "company_name": "GUM AT EX AB",
            "address": "Box 100, KåUered",
            "phone_number": "031-75 12 20",
            "bank_details": {
                "bankgiro": "420-3030",
                "postgiro": "521676-7"
            },
            "activity": "Experterar konverterat papper. Agenturverksamhet",
            "annual_turnover": 4000000,
            "capital": 10000,
            "key_personnel": [
                {
                    "name": "Lennart Albihn",
                    "position": "Verkst dir"
                },
                {
                    "name": "Lennart Hällegårdh",
                    "position": "Exportchef"
                }
            ],
            "establishment_year": 1956
        },
        "7": {
            "company_name": "GDRANSSON, INGENJÖRS-FIRMAN BO",
            "address": "Skeppsg 6, Västerås",
            "phone_number": "021-1102 55",
            "postgiro": "615583-2",
            "activity": "Utför på entreprenad puts av följande typer: Tasad-, dekor-, akustik- o brandisolerings-puts samt putsade undertak. Teknisk isolering för industrin. Brandisolering av stålkonstruktioner med skivor o puts",
            "employees": 15,
            "annual_turnover": 1100000,
            "key_personnel": [
                {
                    "name": "Bo Göransson",
                    "position": "Chef"
                }
            ],
            "establishment_year": 1963
        },
        "8": {
            "company_name": "ROTTNEROS AB",
            "address": "Fack, Karlstad 1",
            "phone_number": "054-1802 80",
            "bank_details": {
                "bankgiro": "113-8734",
                "postgiro": "593720-6"
            },
            "activity": "Central administration o försäljning för Rottneros-concernen",
            "employees": 400,
            "annual_turnover": 14000000,
            "capital": 5000000,
            "key_personnel": [
                {
                    "name": "P W Möller",
                    "position": "Disp"
                },
                {
                    "name": "Sixten Ulfsparre",
                    "position": "Tekn dir"
                },
                {
                    "name": "Gustaf Carlsson",
                    "position": "Adv"
                },
                {
                    "name": "Olof Erlandsson",
                    "position": "Bankdir"
                },
                {
                    "name": "Lennart Schotte",
                    "position": "Docent"
                },
                {
                    "name": "Claes Horn af Åminne",
                    "position": "Ryttmäst"
                },
                {
                    "name": "C J Wettergren",
                    "position": "Verkst dir"
                }
            ],
            "establishment_year": null
        },
        "9": {
            "company_name": "ROTTNEROS TRÄSLIPERI AB",
            "address": "Rottneros",
            "phone_number": "0565-602 00",
            "activity": "Tillverkar våt o ton-mekanisk slipmassa, raffmassa",
            "employees": 200,
            "annual_turnover": 35000000,
            "key_personnel": [
                {
                    "name": "Ing O S Johansson",
                    "position": "Driftschef"
                }
            ],
            "establishment_year": null
        },
        "10": {
            "company_name": "ROYAL REFRIGERATION AB",
            "address": null,
            "activity": null,
            "annual_turnover": null,
            "establishment_year": null
        },
        "11": {
            "company_name": "R P RORPRODUKTER AB",
            "activity": "Grossister i VVS-, VA-, industri-, el-, byggnads- o inredningsbranschen. Tillverkare, grossister o exportörer i brunnsborrningsbranschen",
            "employees": 250,
            "annual_turnover": 100000000,
            "capital": 1000000,
            "key_personnel": [
                {
                    "name": "G Bonevik",
                    "position": "Ägare"
                }
            ],
            "establishment_year": 1945
        },
        "12": {
            "company_name": "RTA SVENSKA AB",
            "address": "Box 206, Linköping 1, Brog 1",
            "phone_number": "013-1300 95",
            "bank_details": {
                "bankgiro": "415-3060",
                "postgiro": "691820-5"
            },
            "activity": "Tillverkar lyftdon såsom Malcusblocket, blockvagnar, pelarsvängkranar o traverser för hand-, el- o luftdrift",
            "capital": 400000,
            "key_personnel": [
                {
                    "name": "Allan Inovius",
                    "position": "Verkst dir"
                }
            ],
            "establishment_year": 1967
        },
        "13": {
            "company_name": "ÅGREN, ERAGNAR",
            "address": "Raka v 6, Täby 2",
            "phone_number": "08-758 73 40",
            "postgiro": "151518-8",
            "activity": "Import o exportfirma",
            "key_personnel": [
                {
                    "name": "E Ragnar Ågren",
                    "position": "Chef"
                }
            ],
            "establishment_year": 1936
        },
        "14": {
            "company_name": "ÅKERBERG & FOGELSTROM RÖRLEDNINGS AB",
            "address": "Plpersg 4, Stockholm",
            "phone_number": "08-52 00 90",
            "bank_details": {
                "bankgiro": "731-2382",
                "postgiro": "193676-4"
            },
            "activity": "Rörinstallationer",
            "employees": 100,
            "annual_turnover": 10000000,
            "capital": 30000,
            "key_personnel": [
                {
                    "name": "Nils Johnson",
                    "position": "Verkst dir"
                }
            ],
            "establishment_year": 1943
        },
        "15": {
            "company_name": "SVENSKA DAGBLADETS AB",
            "address": "Rålambsv 7-13, Stockholm",
            "phone_number": "22 50 00, riks 08-22 50 20",
            "bank_details": {
                "bankgiro": "560-4657",
                "postgiro": "hk 61-2, pren 823300"
            },
            "activity": "Tryckeri o reproavdelning",
            "employees": 800,
            "annual_turnover": 80000000,
            "capital": 2750000,
            "key_personnel": [
                {
                    "name": "Sven Gerentz",
                    "position": "Veikst din"
                }
            ],
            "establishment_year": 1884
        },
        "16": {
            "company_name": "PERSSON & SON, AB MALTE",
            "address": "Furuv 9, Halmstad",
            "phone_number": "035-1106 72, 101250",
            "bank_details": {
                "bankgiro": "85-9508",
                "postgiro": "468260"
            },
            "activity": "Montering av bensin-o oljeanläggningar samt försäljning av allt till samma. Utför cisternvård",
            "employees": 10,
            "annual_turnover": 750000,
            "capital": 5000,
            "key_personnel": [
                {
                    "name": "Malte J V Persson",
                    "position": "Verkst dir"
                },
                {
                    "name": "Osborn Valfrid Persson",
                    "position": "Verkmäst"
                }
            ],
            "establishment_year": 1921
        },
        "17": {
            "company_name": "PEHRSONS VALSQVARN, AB MÄRTEN",
            "address": "Box 113, Kristianstad 1, Spann-målsg 1 A",
            "phone_number": "044-115 1 40",
            "bank_details": {
                "bankgiro": "867-4186",
                "postgiro": "6827-0"
            },
            "activity": "Kvarnrörelse. Tillverkar mjöl o fodervaror",
            "employees": 116,
            "annual_turnover": 70000000,
            "capital": 9000000,
            "key_personnel": [
                {
                    "name": "Stig Carlborn",
                    "position": "V verkst dir o platschef"
                }
            ],
            "establishment_year": 1888
        },
        "18": {
            "company_name": "PERSSON AB, BYGGNADSFIRMAN NILS",
            "address": "Smedg 21-23, Oskarshamn",
            "phone_number": "0491-105 80, 103 90",
            "bank_details": {
                "bankgiro": "856-4643",
                "postgiro": "96525-1"
            },
            "activity": "Husbyggen. Tillverkar murbruk",
            "employees": 53,
            "annual_turnover": 5291000,
            "capital": 40000,
            "key_personnel": [
                {
                    "name": "Byggn-ing Birger Persson",
                    "position": "Styrelse"
                }
            ],
            "establishment_year": 1937
        },
        "19": {
            "company_name": "TRIABO INDUSTRI AB",
            "address": "Box 78, Sölvesborg",
            "phone_number": "0456-117 90, 117 91",
            "bank_details": {
                "bankgiro": "663-9801",
                "postgiro": "9157-9"
            },
            "activity": "Tillverkar byggnadshjälpmedel såsom valvstämp, form-balk, formbord, låsbrickor, passer-bryggor, pelarförband, snö- o nock-räckskonsoler m m. Utför varmför-zinkning",
            "employees": 30,
            "annual_turnover": 2500000,
            "capital": 135000,
            "key_personnel": [
                {
                    "name": "Allan Fältström",
                    "position": "Disp"
                },
                {
                    "name": "Gunnar Haglind",
                    "position": "Disp"
                }
            ],
            "establishment_year": 1955
        },
        "20": {
            "company_name": "TRIANGELN AB, KEMISKTEKNISKA FABRIKEN",
            "address": "Industrig 14-18, Malmö",
            "phone_number": "040-180430",
            "bank_details": {
                "bankgiro": "875-3725",
                "postgiro": "24513-4"
            },
            "activity": "Konfektionering av plastfolier genom svetsning, klistring m m. Tillverkar mörkläggningsgardiner, draperier, presenningar mm",
            "employees": 9,
            "annual_turnover": 350000,
            "capital": 20000,
            "key_personnel": [
                {
                    "name": "Ing Gunnar Mårtenson",
                    "position": "Verkst dir"
                }
            ],
            "establishment_year": 1930
        }
    }
}