{
    "original": "MJOBÄCKS-HUS AB\n\nPnr 510 60\n\nOverlida, Mjöbäck. Tel 0325-341 50.\nBankgiro 552-8146. Postgiro\n84699-8\n\nVerksamhet: Tillverkar o säljer\nmonteringsfärdigt material till\nfritidshus\n\nVarunamn: Västkust-Stugan\nAntal anställda: 160\nÅrsomsättning: 20000 000\nAktiekapital: 1000 000\nStyrelse: Dir Arthur’ G Nilsson\n(ordf), dir Rolf Nilsson\nVerkst dir: Rolf Nilsson\nEtableringsår: 1932\nOmbildat till aktiebolag 1943.\n\nMJÖLBY BETONGINDUSTRI\nAB\n\nPnr 595 00\n\nMjölby, Box 148. Hulje. Tel\n0142-15015. Bankgiro 280-8616.\nPostgiro 179480-9\n\nVerksamhet: Tillverkar\nfabriksbetong, säljer betongvaror\nAntal anställda: 32\nÅrsomsättning: 4 000000\nAktiekapital: 100 000\nVerkst dir: Harald Aléx\nEtableringsår: 1958.\n\nMJÖLBY INTARSIA,\nFANER AB\n\nPnr 595 00\n\nMjölby, Skänningev 16-18. Box 47.\nTel 0142-130 70. Bankgiro\n12-8213. Postgiro 34122. TgaFanerami\n\nVerksamhet: Import o export,\nen-grosförsäljning av fanér\nAntal anställda: 50\nAktiekapital: 42000\nVerkst dir: Gösta W Dahlström\nEtableringsår: 1909.\n\nMJÖLBY LEDSTÄNGSFABRIK,\nAB\n\nPnr 595 00\n\nMjölby, Kyrkog 28. Box 21. Tel\n0142-101 96. Postgiro 493398-2\nVerksamhet: Tillverkar ledstänger\no överliggare\nAntal anställda: 5\nÅrsomsättning: 254 000\nAktiekapital: 25 000\nVerkst dir: Bertil Svensson\nEtableringsår: 1955.\n\nAktiekapital: 1400 000\nVerkst dir: C A Frick\nEtableringsår: 1892.\n\nDAHL BYGGNADS AB, ERIK L\n\nPnr 52100\n\nFalköping, Trädgårdsg 22. Tel\n0515-105 97, 125 97. Postgiro\n170729-8\n\nVerksamhet: Nybyggnader för\nbostäder, industrier, kontor\nAntal anställda: 140\nVerkst dir: Rolf Andersson\nEtableringsår: 1953.\n\nBERGGREN, HANDELS AB J B\n\nPnr 301 03\n\nHalmstad 1, Svetsareg. Box 136.\nTel 035-1185 00. Bankgiro\n42-3512. Postgiro 5270.\nTga JBBerggren\nVerksamhet:\nKolonialvarugross-handel\n\nAntal anställda: 75\nÅrsomsättning: 70 000 000\nAktiekapital: 1000000\nVerkst dir: Civilekonom Eskil\nWendt\n\nEtableringsår: 1872\nOmbildat till aktiebolag 1900.\n\nBERGHAUS &amp; CO AB, PAUL\n\nPnr 401 10\n\nGöteborg 1, pack. Spannmålsg 8.\nTel 031-13 45 64. Tga Berghaus\nExpeditionskontor: 104 30\nStockholm 45, Box 45057. Rådmansg 57.\nTel 08-23 4210\n\nVerksamhet: Partiaffär,\njärnmanufaktur, vapen, ammunition,\njakt-o sportartiklar, fiskredskap m m\n\nAktiekapital: 100 000\nVerkst dir: B G Sjödahl\nEtableringsår: 1868.\n\nBERGHOLTZ K\nLOCK-GJUTERI AB\n\nPnr 190 30\n\nSigtuna, Box 99. Uppsalav. Tel\n0760-514 45. Bankgiro 23-2241.\nPostgiro 153357\n\nVerksamhet: Kyrkklockor,\nklockspel, klockringningsanläggningar\nAktiekapital: 5 000\nÄgare o chef: Gösta Bergholtz\nEtableringsår: 1853.\n\nBERGKVIST, BERGQVIST\n\nBERGKVIST &amp; CO\n\nPnr 234 00\n\nLomma, Box 6. Tel 040-41 27 20.\nPostgiro 292144\n\nVerksamhet: Tillverkar slip-,\npoler-o glänsskivor, veckade skivor,\nSISAL-skivor, svabbelskivor o\nväxer. Filtskivor, smärgel, lim,\nin-dustriborstar mm. Flanellrondeller\no fårullshättor\n\nChefer: Alf Bergkvist, Börje\nBergkvist\n\nEtableringsår: 1921.\n\nBERGQVIST MEK VERKSTAD\nAB, BRÖDERNA\n\nPnr 56010\n\nSkillingaryd. Tel 0370-703 04.\n\nPostgiro 320943-4\n\nVerksamhet: Hydrauliska\ntippanord-ningar o gaffellyftvagnar\nÄgare o chefer: C G R Bergkvist,\nSAL Bergqvist.\n\nBERGQVIST &amp; SON\n\nPnr 411 21\n\nGöteborg, Stora Badhusg 18. Tel\n031-10 60 97, 13 13 97. Bankgiro\n511-4202. Postgiro 41860-8. Tga\nBergqvistens\n\nVerksamhet: Gjutgods, högeldfast\nkromgjutgods, rostar, stålgjutgods,\nrostfritt o syrafast, slitgods,\noljepumpar, propellrar\nÄgare o chef: Carl G Bergqvist\nEtableringsår: 1869.\n\nBERGQVISTS MEK\nVERKSTAD, A\n\nPnr 930 30\n\nUrs viken, Postl 145. Tel\n0910-304 25. Bankgiro 612-0190.\nPostgiro 349437-4\n\nVerksamhet: Utför konstruktioner,\nsvarvning, fräsning o plåtarbeten\nAntal anställda: 13\nChef: A Bergqvist\nEtableringsår: 1965.\n\nSKÅNE-EMBALLAGE, AB\n\nPnr 245 00\n\nStaffanstorp, Klågerupsv 14. Tel\n046-562 00. Bankgiro 113-2752.\nPostgiro 247070-6. Tga\nSkåneemballage\n\nVerksamhet: Tillverkar\nvakuumlock, kapsyler, askar o alla andra\nslag av förslutningar.\nHelautomatiska lockpåsättningsmaskiner\nAntal anstäUda: 55\nÅrsomsättning: 8 000 000\nAktiekapital: 200 000\nStyrelse: Marindir K A Risberg\n(ordf), disp Bo Risberg, dir Per\nRisberg, marindir K F Risberg\nVerkst dir: Disp Bo Risberg\nChef: Ing Ingvar Åsberg\nEtableringsår 1948.\n\nPRESSVERKTYG, AB\n\nPnr 117 20\n\nStockholm, Maria Trappgränd 5.\nTel 08-40 75 69, 43 27 06. Bankgiro\n211-1532. Postgiro 59088-5\nVerksamhet: Verktyg o pressningar\nAntal anställda: 16\nÅrsomsättning: 2 000 0 00\nAktiekapital: 50 000\nVerkst din Runa Wendler\nEtableringsår: 1929.\n\nDRONNINGBORG SVENSKA AB\n\nPnr 54101\n\nSkövde 1, Box 248. Kaplansg 25.\nTel 0500-820 70. Bankgiro\n224-2253. Postgiro 712611-3\nVerksamhet: En gros- o\ndetalj-försäljning av lantbruksmaskiner\nAntal anställda: 14\nÅrsomsättning: 7 000 000\nAktiekapital: 100 000\nVeikst dir: Göran Lindgren\nEtableringsår: 1968.\n\nCASCO, AB\n\nPnr 100 61\n\nStockholm 11, Sickla. Box 11010.\nTel 08-44 9040. Bankgiro\n160-4198. Postgiro 52544-4. Tga\nCas-cobolag. Telex 10154 CASCO S\nVerksamhet: Tillverkar o säljer\nlim för trä-, byggnads- o\npappersindustri samt hantverk, hartser för\npappers-, plywood-, spånskivor.\nBoard- o mineralullsindustri.\nImpregnerat papper,\nytbehandlingsmedel för parkett, golvpolish,\ninsektsmedel, bekämpningsmedel\nför jordbruket m m\nAntal anstäUda: 600\nÅrsomsättning: 119000 000\nAktiekapital: 16 000 000\nStyrelse: Bankdir Marc Wallenberg\njr (ordf), dir Ulf-Christian Bratt, dir\nIngmar Eidem, dir Lars H\nLandquist\n\nVerkst dir: Lars H Landquist\nEtableringsår: 1928.\n\nGRATONG, AB\n\nPnr 281 01\n\nHässleholm 1, Box 128. Tel\n0451-113 15. Postgiro 265152\nVerksamhet: Gångbaneplattor,\nkörbaneplattor av betong\nAktiekapital: 10 000\nVerkst dir: Håkan Nyman\nEtableringsår: 1953.\n\nKJELLBERG &amp; CO AB\n\nPnr 11151\n\nStockholm, Drottningg 14. Tel\n08-10 05 63\n\nVerksamhet: Förvaltning\nAktiekapital: 2 000 000\nVerkst dir: Karl Rainer\nEtableringsår: 1932.\n\nKJELLBERG FJÄDER.\nFABRIK AB\n\nPnr 183 41\n\nTäby, Grips valls g 26. Tel\n08-785 05 00. Bankgiro 72-9277.\nPostgiro 293294\n\nVeiksamhet: Tillverkar fjädrar\nAntal anställda: 19\nÅrsomsättning: 300 000\nAktiekapital: 10 000\nVerkst dir: Nils Kjellberg\nEtableringsår: 1951.\n\nTER\n\nTHERMOVOLT AB,\nINGENIÖRSFIRMAN\n\nPnr 723 40\n\nVästerås, Lövstag 46. Tel\n021-14 62 80. Bankgiro 356-7179.\nPost-giro 496030-8\n\nVerksamhet: Tillverkar elektr\nshuntar, tidregistreringsapparat\n\"Delay Recorder\", elektr\nyttemperaturgivare för klenrör, justerings\no ersättningsmotstånd för\ntemperaturmätning, mekaniska nivåmätare\nMek Verkstad: 734 00\nHallstahammar, Bryggareg 16. Tel 0220-108 79\nAntal anstäUda: 6\nÅrsomsättning: 650 000\nAktiekapital: 5 000\nStyrelse: Ing Johan Tihani (ordf),\nverkstadschef Istvån Glöckl,\nrevisor Rolf Liljenmalm, kamrer\nHarry Liljenmalm (suppl)\nVerkst dir Ing Johan Tihani\nEtableringsår: 1955\nOmbildat till aktiebolag 1967.\n\nTHERN&amp; CO, TRÄVARU AB G\n\nPnr 217 61\n\nMalmö, ABC-Husen, John\nEricssons v. Tel 040-769 3 0. Bankgiro\n640-6599. Postgiro 632442-0\nTelex 32401. Tga Ternwood\nVerksamhet: Köper o säljer\nträvaror (export- o grossiströrelse)\nAntal anställda: 16\nÅrsomsättning: 40 000 000\nAktiekapital: 200 000\nVerkst dir: Gustaf Thern\nEtableringsår: 1965.",
    "structured": {
        "1": {
            "company_name": "MJOBÄCKS-HUS AB",
            "address": "Overlida, Mjöbäck",
            "phone_number": "0325-341 50",
            "bank_details": {
                "bankgiro": "552-8146",
                "postgiro": "84699-8"
            },
            "activity": "Tillverkar o säljer monteringsfärdigt material till fritidshus",
            "employees": 160,
            "annual_turnover": 20000000,
            "capital": 1000000,
            "key_personnel": [
                {
                    "name": "Dir Arthur’ G Nilsson",
                    "position": "ordf"
                },
                {
                    "name": "dir Rolf Nilsson",
                    "position": ""
                },
                {
                    "name": "Rolf Nilsson",
                    "position": "Verkst dir"
                }
            ],
            "establishment_year": 1932
        },
        "2": {
            "company_name": "MJÖLBY BETONGINDUSTRI AB",
            "address": "Mjölby, Box 148, Hulje",
            "phone_number": "0142-15015",
            "bank_details": {
                "bankgiro": "280-8616",
                "postgiro": "179480-9"
            },
            "activity": "Tillverkar fabriksbetong, säljer betongvaror",
            "employees": 32,
            "annual_turnover": 4000000,
            "capital": 100000,
            "key_personnel": [
                {
                    "name": "Harald Aléx",
                    "position": "Verkst dir"
                }
            ],
            "establishment_year": 1958
        },
        "3": {
            "company_name": "MJÖLBY INTARSIA, FANER AB",
            "address": "Mjölby, Skänningev 16-18, Box 47",
            "phone_number": "0142-130 70",
            "bank_details": {
                "bankgiro": "12-8213",
                "postgiro": "34122"
            },
            "activity": "Import o export, en-grosförsäljning av fanér",
            "employees": 50,
            "capital": 42000,
            "key_personnel": [
                {
                    "name": "Gösta W Dahlström",
                    "position": "Verkst dir"
                }
            ],
            "establishment_year": 1909
        },
        "4": {
            "company_name": "MJÖLBY LEDSTÄNGSFABRIK, AB",
            "address": "Mjölby, Kyrkog 28, Box 21",
            "phone_number": "0142-101 96",
            "postgiro": "493398-2",
            "activity": "Tillverkar ledstänger o överliggare",
            "employees": 5,
            "annual_turnover": 254000,
            "capital": 25000,
            "key_personnel": [
                {
                    "name": "Bertil Svensson",
                    "position": "Verkst dir"
                }
            ],
            "establishment_year": 1955
        },
        "5": {
            "company_name": "DAHL BYGGNADS AB, ERIK L",
            "address": "Falköping, Trädgårdsg 22",
            "phone_number": "0515-105 97, 125 97",
            "postgiro": "170729-8",
            "activity": "Nybyggnader för bostäder, industrier, kontor",
            "employees": 140,
            "key_personnel": [
                {
                    "name": "Rolf Andersson",
                    "position": "Verkst dir"
                }
            ],
            "establishment_year": 1953
        },
        "6": {
            "company_name": "BERGGREN, HANDELS AB J B",
            "address": "Halmstad 1, Svetsareg. Box 136",
            "phone_number": "035-1185 00",
            "bank_details": {
                "bankgiro": "42-3512",
                "postgiro": "5270"
            },
            "activity": "Kolonialvarugross-handel",
            "employees": 75,
            "annual_turnover": 70000000,
            "capital": 1000000,
            "key_personnel": [
                {
                    "name": "Civilekonom Eskil Wendt",
                    "position": "Verkst dir"
                }
            ],
            "establishment_year": 1872
        },
        "7": {
            "company_name": "BERGHAUS & CO AB, PAUL",
            "address": "Göteborg 1, pack. Spannmålsg 8",
            "phone_number": "031-13 45 64",
            "activity": "Partiaffär, järnmanufaktur, vapen, ammunition, jakt-o sportartiklar, fiskredskap m m",
            "capital": 100000,
            "key_personnel": [
                {
                    "name": "B G Sjödahl",
                    "position": "Verkst dir"
                }
            ],
            "establishment_year": 1868
        },
        "8": {
            "company_name": "BERGHOLTZ, BERGQVIST BERGKVIST & CO",
            "address": "Lomma, Box 6",
            "phone_number": "040-41 27 20",
            "postgiro": "292144",
            "activity": "Tillverkar slip-, poler-o glänsskivor, veckade skivor, SISAL-skivor, svabbelskivor o växer. Filtskivor, smärgel, lim, industriborstar mm. Flanellrondeller o fårullshättor",
            "key_personnel": [
                {
                    "name": "Alf Bergkvist",
                    "position": "Chefer"
                },
                {
                    "name": "Börje Bergkvist",
                    "position": ""
                }
            ],
            "establishment_year": 1921
        },
        "9": {
            "company_name": "BERGQVIST MEK VERKSTAD AB, BRÖDERNA",
            "address": "Skillingaryd",
            "phone_number": "0370-703 04",
            "postgiro": "320943-4",
            "activity": "Hydrauliska tippanord-ningar o gaffellyftvagnar",
            "key_personnel": [
                {
                    "name": "C G R Bergkvist",
                    "position": "Ägare o chefer"
                },
                {
                    "name": "SAL Bergqvist",
                    "position": ""
                }
            ]
        },
        "10": {
            "company_name": "BERGQVIST & SON",
            "address": "Göteborg, Stora Badhusg 18",
            "phone_number": "031-10 60 97, 13 13 97",
            "bank_details": {
                "bankgiro": "511-4202",
                "postgiro": "41860-8"
            },
            "activity": "Gjutgods, högeldfast kromgjutgods, rostar, stålgjutgods, rostfritt o syrafast, slitgods, oljepumpar, propellrar",
            "key_personnel": [
                {
                    "name": "Carl G Bergqvist",
                    "position": "Ägare o chef"
                }
            ],
            "establishment_year": 1869
        },
        "11": {
            "company_name": "BERGQVISTS MEK VERKSTAD, A",
            "address": "Urs viken, Postl 145",
            "phone_number": "0910-304 25",
            "bank_details": {
                "bankgiro": "612-0190",
                "postgiro": "349437-4"
            },
            "activity": "Utför konstruktioner, svarvning, fräsning o plåtarbeten",
            "employees": 13,
            "key_personnel": [
                {
                    "name": "A Bergqvist",
                    "position": "Chef"
                }
            ],
            "establishment_year": 1965
        },
        "12": {
            "company_name": "SKÅNE-EMBALLAGE, AB",
            "address": "Staffanstorp, Klågerupsv 14",
            "phone_number": "046-562 00",
            "bank_details": {
                "bankgiro": "113-2752",
                "postgiro": "247070-6"
            },
            "activity": "Tillverkar vakuumlock, kapsyler, askar o alla andra slag av förslutningar. Helautomatiska lockpåsättningsmaskiner",
            "employees": 55,
            "annual_turnover": 8000000,
            "capital": 200000,
            "key_personnel": [
                {
                    "name": "Marindir K A Risberg",
                    "position": "ordf"
                },
                {
                    "name": "Bo Risberg, Per Risberg, K F Risberg",
                    "position": "Styrelse"
                },
                {
                    "name": "Bo Risberg",
                    "position": "Verkst dir"
                },
                {
                    "name": "Ing Ingvar Åsberg",
                    "position": "Chef"
                }
            ],
            "establishment_year": 1948
        },
        "13": {
            "company_name": "PRESSVERKTYG, AB",
            "address": "Stockholm, Maria Trappgränd 5",
            "phone_number": "08-40 75 69, 43 27 06",
            "bank_details": {
                "bankgiro": "211-1532",
                "postgiro": "59088-5"
            },
            "activity": "Verktyg o pressningar",
            "employees": 16,
            "annual_turnover": 2000000,
            "capital": 50000,
            "key_personnel": [
                {
                    "name": "Runa Wendler",
                    "position": "Verkst din"
                }
            ],
            "establishment_year": 1929
        },
        "14": {
            "company_name": "DRONNINGBORG SVENSKA AB",
            "address": "Skövde 1, Box 248, Kaplansg 25",
            "phone_number": "0500-820 70",
            "bank_details": {
                "bankgiro": "224-2253",
                "postgiro": "712611-3"
            },
            "activity": "En gros- o detalj-försäljning av lantbruksmaskiner",
            "employees": 14,
            "annual_turnover": 7000000,
            "capital": 100000,
            "key_personnel": [
                {
                    "name": "Göran Lindgren",
                    "position": "Veikst dir"
                }
            ],
            "establishment_year": 1968
        },
        "15": {
            "company_name": "CASCO, AB",
            "address": "Stockholm 11, Sickla, Box 11010",
            "phone_number": "08-44 9040",
            "bank_details": {
                "bankgiro": "160-4198",
                "postgiro": "52544-4"
            },
            "activity": "Tillverkar o säljer lim för trä-, byggnads- o pappersindustri samt hantverk, hartser för pappers-, plywood-, spånskivor. Board- o mineralullsindustri. Impregnerat papper, ytbehandlingsmedel för parkett, golvpolish, insektsmedel, bekämpningsmedel för jordbruket m m",
            "employees": 600,
            "annual_turnover": 119000000,
            "capital": 16000000,
            "key_personnel": [
                {
                    "name": "Bankdir Marc Wallenberg jr",
                    "position": "ordf"
                },
                {
                    "name": "Ulf-Christian Bratt, Ingmar Eidem, Lars H Landquist",
                    "position": "Styrelse"
                },
                {
                    "name": "Lars H Landquist",
                    "position": "Verkst dir"
                }
            ],
            "establishment_year": 1928
        },
        "16": {
            "company_name": "GRATONG, AB",
            "address": "Hässleholm 1, Box 128",
            "phone_number": "0451-113 15",
            "postgiro": "265152",
            "activity": "Gångbaneplattor, körbaneplattor av betong",
            "capital": 10000,
            "key_personnel": [
                {
                    "name": "Håkan Nyman",
                    "position": "Verkst dir"
                }
            ],
            "establishment_year": 1953
        },
        "17": {
            "company_name": "KJELLBERG & CO AB",
            "address": "Stockholm, Drottningg 14",
            "phone_number": "08-10 05 63",
            "activity": "Förvaltning",
            "capital": 2000000,
            "key_personnel": [
                {
                    "name": "Karl Rainer",
                    "position": "Verkst dir"
                }
            ],
            "establishment_year": 1932
        },
        "18": {
            "company_name": "KJELLBERG FJÄDER. FABRIK AB",
            "address": "Täby, Gripsvallsg 26",
            "phone_number": "08-785 05 00",
            "bank_details": {
                "bankgiro": "72-9277",
                "postgiro": "293294"
            },
            "activity": "Tillverkar fjädrar",
            "employees": 19,
            "annual_turnover": 300000,
            "capital": 10000,
            "key_personnel": [
                {
                    "name": "Nils Kjellberg",
                    "position": "Verkst dir"
                }
            ],
            "establishment_year": 1951
        },
        "19": {
            "company_name": "THERMOVOLT AB, INGENIÖRSFIRMAN",
            "address": "Västerås, Lövstag 46",
            "phone_number": "021-14 62 80",
            "bank_details": {
                "bankgiro": "356-7179",
                "post-giro": "496030-8"
            },
            "activity": "Tillverkar elektr shuntar, tidregistreringsapparat 'Delay Recorder', elektr yttemperaturgivare för klenrör, justerings o ersättningsmotstånd för temperaturmätning, mekaniska nivåmätare",
            "mechanical_workshop": "Hallstahammar, Bryggareg 16",
            "phone_number_for_mechanical_workshop": "0220-108 79",
            "employees": 6,
            "annual_turnover": 650000,
            "capital": 5000,
            "key_personnel": [
                {
                    "name": "Ing Johan Tihani",
                    "position": "ordf"
                },
                {
                    "name": "Istvån Glöckl",
                    "position": "verkstadschef"
                },
                {
                    "name": "Rolf Liljenmalm",
                    "position": "revisor"
                },
                {
                    "name": "Harry Liljenmalm",
                    "position": "kamrer (suppl)"
                }
            ],
            "establishment_year": 1955
        },
        "20": {
            "company_name": "THERN & CO, TRÄVARU AB G",
            "address": "Malmö, ABC-Husen, John Ericssons v",
            "phone_number": "040-769 3 0",
            "bank_details": {
                "bankgiro": "640-6599",
                "postgiro": "632442-0"
            },
            "activity": "Köper o säljer trävaror (export- o grossiströrelse)",
            "employees": 16,
            "annual_turnover": 40000000,
            "capital": 200000,
            "key_personnel": [
                {
                    "name": "Gustaf Thern",
                    "position": "Verkst dir"
                }
            ],
            "establishment_year": 1965
        }
    }
}