{
    "original": "VARATOR-MASKINER, AB\n\nPnr 534 00\n\nVara. Tel 0512-100 03. Tga\nVara-tormaskiner\n\nVerksamhet: Tillverkar\nprecisions-bänkborrmaskiner o verktyg\nAktiekapital: 20 000\nVerkst dir Sture Brocker\nEtableringsår: 1890.\n\nVARBERGS MEKANISKA\nVERKSTAD, AB\n\nPnr 432 00\n\nVarberg, V Vallg 7. Tel 0340-102 69,\n102 70. Bankgiro 35-5046. Postgiro\n674970\n\nVerksamhet: Tillverkar cisterner,\npressade gavlar o\njärnkonstruktioner\n\nAntal anställda: 20\nAktiekapital: 15 000\nVffkst dir: Ing Töre Börjesson\nEtableringsår: 1914.\n\nILSBO INDUSTRIER AB\n\nPnr 820 71\n\nIlsbo. Tel 0650-420 00. Postgiro\n6929-4. Tga Ilsbotippen\nVerksamhet: Släp- o\npåhängsvagnar för tyngre\nlandsvägstransporter, hydrauliska tipputrustningar\nsamt bilpåbyggnader\nAktiekapital: 400 000\nVerkst dir: Stig Frånlund\nEtableringsår: 1919.\n\nILVÉN &amp; KÄLLQVIST,\nBYGGNADS AB\n\nse Platzer Bygg AB.\n\nILO MEKANISKA\n\nPnr 56010\n\nSkUlingaryd, Stureg 40 . Tel\n0370-71050. Bankgiro 14-1410\nVerksamhet: Tillverkning av\ntunnplåtsarbeten, broschyrställ,\nsta-pelboxar (lagerfack). Borstar\nför biltvätt\nAntal anställda: 9\nÅrsomsättning: 1500 000\nChef: Fabr Ingemar Lööf\nEtableringsår: 1959.\n\nL.K. KOKKÄRL\n\nPnr 635 90\n\nEskilstuna, Kjula. Tel 016-913 02.\nBankgiro 601-3197. Postgiro\n331306-1\n\nVerksamhet: Tillverkar kokkärl av\naluminium. Utför metalltryckning\nAntal anställda: 7\nÅrsomsättning: 550 000\nChef: L-E Karlsson\nEtableringsår: 1947.\n\nLKB-BECKMAN\nINSTRUMENTS AB\n\nPnr 162 11\n\nVällingby 1, Box 49. Jämtlandsg\n151 C. Tel 08-37 29 30. Bankgiro\n642-0103. Postgiro 199865-7. Tga\nElkbeckman.\nTelex 17393 LKBECK S\nVerksamhet: Försäljning o service\nav vetenskapliga o medicinska\ninstrument till universitet,\nhögskolor, sjukhus o industri, framförallt\nden farmaceutiska\nAntal anställda: 45\nÅrsomsättning: 12 000 000\nAktiekapital: 1000 000\nVerkst din Bo Lindwall\nEtableringsån 1968.\n\nIFÖ RORKONSULT, AB\n\nPnr 113 23\n\nStockholm, Hälsingeg 19. Tel\n08-3100 66, 32 47 47. Bankgiro\n563-7293. Postgiro 400960-1\nVerksamhet: Konsulter inom\nindustri-, fjärrvärme- o\noljelag-ringsanläggningar\nAktiekapital: 15 000\nVerkst dir: Bo Karlsson\nEtableringsår: 1965.\n\nIFÖ STALPRESSNINGS AB\n\nse Iföverken, AB.\n\nIFÖVERKEN, AB\n\nIngår i Cementakoncemen\n\nPnr 295 00\n\nBromölla. Tel 045 6-280 00. Tga\nIföverken, Sölvesborg.\nTelex 4478 IFOE S\nStyrelse: Se Cementakoncernen\nProduktgruppchef o platschef i\nBromölla: V verkst dir Stig Sunne\nAB Iföverken ingår tillsammans\nmed nedan specificerade företag\nsom en enhet i Cementakoncernen\nunder beteckningen Ifö gruppen\n\nFöretag i Ifögruppen:\nWS-sektor: Dir Olof Nilsson\nSanitetsproduktion, Bromölla\nIfö Stålpressnings AB, Bromölla\nArmaturfabriken Trio AB, Lönsboda\nVärme &amp; Sanitets ABIdo, Stockholm\nProdukter Sanitetsporslin, bad- o\nduschkar, armatur, industrigods o\ndiskbänkar\n\nVarunamn: Carezza, Olofström,\nTrio, Ido\n\nByggmaterialsektor Dir Bernt\nThelander\n\nProdukter: Keramiskt golv-,\nvägg-o fasadmaterial, glasfiberarmerade,\nkorrugerade plastplattor,\nlanterni-ner o fasadmaterial\nVarunamn: Esterlit, Ivex, Ifölit\n\nElmaterielsektor Dir Hans Pappila\nPressgodstillverkning, Bromölla\nAB Installationsmateriel, Vimmerby\nWolfes &amp; Weisse GmbH,\nVästtyskland\n\nProdukter: Isolerande detaljer för\nden elektriska verkstadsindustrin,\nsäkringar, motstånd o\nbelysningsarmatur\n\nSektor för högspänningsisolatorer:\n\nDir Arne Strindemark\nProdukter: Isolatorer för hög- o\nlågspänning\n\nAntal anställda: 1887\nÅrsomsättning: 95 990 209\n\nAktiekapital: 107 250 000\nEtableringsår: 1909\nOmbildat till aktiebolag 1927.\n\nIGA PATENT PRODUKTER AB\n\nPnr 18210\n\nDanderyd 1. Edsviksv 72. Box 25.\nTel 08-755 69 24, 755 69 97.\nBankgiro 56-0203. Postgiro 499599-9.\nTga Igapatenter, Stockholm\nVerksamhet: Konsultativ\ningenjörsfirma, säljer skåpreglar,\nfönster-hållare o byggnadsbeslag\nVarunamn: IGA\nAktiekapital: 15 000\nVerkst dir: Ing G Lewin.\n\nIGE INDUSTRI AB\n\nPnr 430 30\n\nFriUesås, Box 190. Tel 0340-\n\n504 40. Bankgiro 51-3627. Postgiro\n525282\n\nVerksamhet: Tillverkar kem tekn\nartiklar samt infratorkmateriel\nAntal anstäUda: 11\nÄgare o chefer Ing Göthe\nJohanson, Olof Johanson\nEtableringsår 1942.\n\nPRO\n\nVerksamhet: Konsultverksamhet\ninom byggnadsekonomi o därmed\nsammanhängande byggnadsfrågor\nAntal anställda: 8\nÅrsomsättning: 300 000\nAktiekapital: 15 000\nVerkst dir: Ing Göte Bergman\nEtableringsår: 1967.\n\nBERGSTRÖM, AB J E\n\nPnr 710 40\n\nFrövi. Tel 0581-302 27, 306 00.\nBankgiro 822-6201. Postgiro\n289416-0\n\nVerksamhet: Bergström-fästet för\nsvarvar, snäckväxlar. Specialitet:\ngängslipning\nAntal anställda: 24\nÅrsomsättning: 1500 000\nAktiekapital: 116 000\nVerkst dir: Peter Bergström\nEtableringsår: 1944.\n\nBERGSTRÖM BYGGNADS AB,\nKARL\n\nPnr 11157\n\nStockholm, Sergelg 1. Tel\n08-231310. Postgiro 52322\nVerksamhet: Byggnadsrörelse\nAktiekapital: 200 000\nVerkst dir: Byggmäst John\nMattson\n\nEtableringsår: 1944.\n\nBERGSTRÖM REVISIONS.\nBYRÄ AB, R A\n\nPnr 41261\n\nGöteborg, Utlandag 29. Tel\n031-181010, 181616. Bankgiro\n510-2322. Postgiro 49475-7\nVerksamhet: Revisionsbyrå\nAntal anställda: 5\nÅrsomsättning: 200 000\nAktiekapital: 5 000\nÄgare o chef: Revisor SRS R A\nBergström\n\nEtableringsår: 1958.\n\nRONNING &amp; GJERLOFF, AB P\n\nPnr 266 01\n\nRåå 1, Kaptensg 14.\nBox7.Tel042-60957. Bankgiro 445-3221.\nPost-giro 10150-1\n\nVerksamhet: Tillverkar bläck,\nklister, stämpelfärg o dynor, tusch,\nhek-tografartiklar, färg- o märkkritor,\nmärkbläck o pennor, textpennor o\nbläck till dessa\nAntal anställda: 4\nÅrsomsättning: 200 000\nAktiekapital: 44 000\nVerkst dir Egon Strand\nEtableringsår 1911.\n\nELO\n\nELLERSTRDMS BYGGNADS\nAB» OTTO\n\nPnr 212 28\n\nMalmö, Scheeleg 27. Tel\n040-94 22 25. Bankgiro 15-6404.\nPostgiro 247136\n\nVeiksamhet: Industribyggnader,\nångskorstenar, bostads- o affärshus\nAntal anställda: 100\nAktiekapital: 75 000\nEtableringsår: 1923.\n\nPER\n\nTga Pergusting, Stockholm\nVerksamhet TV-kameror (industri o\nstudiobruk), kamerarör, bandspelare\nAntal anställda: 4\nAktiekapital: 150 000\nVerkst dir: Civiling Per Wikström\nEtableringsàr: 1958.\n\nPERKIN-ELMER AB\n\nPnr 421 31\n\nVästra Frölunda, Fröklöversg 7.\nTel 031-45 0160. Bankgiro\n848-3737. Postgiro 4 9046-6. Tga\nPer-kinelmer. Telex 20743\nVerksamhet: Instrument för\nanalytisk kemi\n\nAntal anställda: 30\n\nÅrsomsättning: 10 000 000\nAktiekapital: 15 000\nVerkst dir: Ing Ralf R Jutvik\nEtableringsàr: 1959.\n\nPERLA-KONFEKTION, AB\n\nPnr 52300\n\nUlricehamn, Box 110. Tel 0321-\n\n12710,108 52. Bankgiro 532-8802.\n\nPostgiro 476045. Tga Helltex\n\nVerksamhet: Herr- o gosskläder\n\nVarunamn: Helltex\n\nAntal anställda: 25\n\nÅrsomsättning: 2 000 000\n\nAktiekapital: 100 000\n\nÄgare o chefer: Per Emar, Knut\n\nErlandsson\n\nEtableringsàr: 1959.\n\nPERLMANS FABRIKS AB,\nNILS\n\nPnr 230 23\n\nAnderslöv, Box 102. Tel\n0410-206 37, 203 30. Bankgiro 650-0524.\nPostgiro 249900-2\nVerksamhet: Tillverkar herr- o\npojkbyxor, herr- o pojkmössor\nAntal anstäUda: 34\nAktiekapital: 25 000\nVerkst dir NUs Perlman\nEtableringsàr 1945.\n\nSUNDBERG, AB ERIK\n\nPnr 19120\n\nSollentuna 1, Industriv 12. Fack. Tel\n35 25 15, riks 08-35 16 66. Tga\nSun-trans\n\nVerksamhet: Tillverkar o säljer\ntransformatorer\nAntal anställda: 100\nÅrsomsättning: 8 000 000\n.Aktiekapital: 120 000\nStyrelse: Adv Wilhelm Törsleff\n(ordf), dir Rut-Alice Sundberg, ing\nErik-Alfred Sundberg, ing Olof\nOhgren\n\nVerkst dir: Rut-Alice Sundberg\nV verkst dir; Bernth Lindborg\nTeknisk konsult: Civiling Bo\nThun-vall\n\nEtableringsår: 1921\nOmbildat till aktiebolag 1928.\n\nSUNDBLAD &amp; CARLSSON, AB\n\nPnr 53101\n\nLidköping, Box 460. Skeppareg 1.\nTel 0510-27260. Bankgiro\n841-3957. Postgiro 269273-9\nVerksamhet: Tillverkar modeller av\nträ, järn o metall, även metall- o\nkokillgjuteri o mek verkstad,\nsand-gjutet gods i alla metaller\nAntal anställda: 75\nÅrsomsättning: 4 000 000\nAktiekapital: 100 000\nFirmatecknare: E I Sundblad o\nC E Florberger\nEtableringsår: 1943.",
    "structured": {
        "0": {
            "company_name": "VARATOR-MASKINER, AB",
            "activity": "Tillverkar precisions-bänkborrmaskiner o verktyg",
            "establishment_year": 1890,
            "capital": 20000,
            "key_personnel": [
                {
                    "name": "Sture Brocker",
                    "position": "Verkst dir"
                }
            ]
        },
        "1": {
            "company_name": "VARBERGS MEKANISKA VERKSTAD, AB",
            "activity": "Tillverkar cisterner, pressade gavlar o järnkonstruktioner",
            "employees": 20,
            "establishment_year": 1914,
            "key_personnel": [
                {
                    "name": "Ing Töre Börjesson",
                    "position": "Vffkst dir"
                }
            ]
        },
        "2": {
            "company_name": "ILSBO INDUSTRIER AB",
            "activity": "Släp- o påhängsvagnar för tyngre landsvägstransporter, hydrauliska tipputrustningar samt bilpåbyggnader",
            "capital": 400000,
            "establishment_year": 1919,
            "key_personnel": [
                {
                    "name": "Stig Frånlund",
                    "position": "Verkst dir"
                }
            ]
        },
        "3": {
            "company_name": "ILO MEKANISKA",
            "activity": "Tillverkning av tunnplåtsarbeten, broschyrställ, stapelboxar (lagerfack). Borstar för biltvätt",
            "employees": 9,
            "annual_turnover": 1500000,
            "establishment_year": 1959,
            "key_personnel": [
                {
                    "name": "Fabr Ingemar Lööf",
                    "position": "Chef"
                }
            ]
        },
        "4": {
            "company_name": "L.K. KOKKÄRL",
            "activity": "Tillverkar kokkärl av aluminium. Utför metalltryckning",
            "employees": 7,
            "annual_turnover": 550000,
            "establishment_year": 1947,
            "key_personnel": [
                {
                    "name": "L-E Karlsson",
                    "position": "Chef"
                }
            ]
        },
        "5": {
            "company_name": "LKB-BECKMAN INSTRUMENTS AB"
        },
        "6": {
            "company_name": "IFÖVERKEN, AB",
            "employees": 1887,
            "annual_turnover": 95990209,
            "capital": 107250000,
            "establishment_year": 1909
        },
        "7": {
            "company_name": "IGA PATENT PRODUKTER AB",
            "activity": "Konsultativ ingenjörsfirma, säljer skåpreglar, fönsterhållare o byggnadsbeslag",
            "capital": 15000,
            "key_personnel": [
                {
                    "name": "Ing G Lewin",
                    "position": "Verkst dir"
                }
            ]
        },
        "8": {
            "company_name": "IGE INDUSTRI AB",
            "activity": "Tillverkar kem tekn artiklar samt infrastrukturmaterial",
            "employees": 11,
            "establishment_year": 1942,
            "key_personnel": [
                {
                    "name": "Ing Göthe Johanson",
                    "position": "Ägare"
                },
                {
                    "name": "Olof Johanson",
                    "position": "Ägare"
                }
            ]
        },
        "9": {
            "company_name": "PRO",
            "activity": "Konsultverksamhet inom byggnadsekonomi o därmed sammanhängande byggnadsfrågor",
            "employees": 8,
            "annual_turnover": 300000,
            "capital": 15000,
            "key_personnel": [
                {
                    "name": "Ing Göte Bergman",
                    "position": "Verkst dir"
                }
            ],
            "establishment_year": 1967
        },
        "10": {
            "company_name": "BERGSTRÖM, AB J E",
            "activity": "Bergström-fästet för svarvar, snäckväxlar. Specialitet: gängslipning",
            "employees": 24,
            "annual_turnover": 1500000,
            "capital": 116000,
            "key_personnel": [
                {
                    "name": "Peter Bergström",
                    "position": "Verkst dir"
                }
            ],
            "establishment_year": 1944
        },
        "11": {
            "company_name": "BERGSTRÖM BYGGNADS AB, KARL",
            "activity": "Byggnadsrörelse",
            "capital": 200000,
            "key_personnel": [
                {
                    "name": "Byggmäst John Mattson",
                    "position": "Verkst dir"
                }
            ],
            "establishment_year": 1944
        },
        "12": {
            "company_name": "BERGSTRÖM REVISIONS. BYRÄ AB, R A",
            "activity": "Revisionsbyrå",
            "employees": 5,
            "annual_turnover": 200000,
            "capital": 5000,
            "key_personnel": [
                {
                    "name": "Revisor SRS R A Bergström",
                    "position": "Ägare o chef"
                }
            ],
            "establishment_year": 1958
        },
        "13": {
            "company_name": "RONNING & GJERLOFF, AB P",
            "activity": "Tillverkar bläck, klister, stämpelfärg o dynor, tusch, hektografartiklar, färg- o märkkritor, märkbläck o pennor, textpennor o bläck till dessa",
            "employees": 4,
            "annual_turnover": 200000,
            "capital": 44000,
            "key_personnel": [
                {
                    "name": "Egon Strand",
                    "position": "Verkst dir"
                }
            ],
            "establishment_year": 1911
        },
        "14": {
            "company_name": "ELO ELLERSTRÖMS BYGGNADS AB» OTTO",
            "activity": "Industribyggnader, ångskorstenar, bostads- o affärshus",
            "employees": 100,
            "capital": 75000,
            "establishment_year": 1923
        },
        "15": {
            "company_name": "PER",
            "activity": "TV-kameror (industri o studiobruk), kamerarör, bandspelare",
            "employees": 4,
            "capital": 150000,
            "key_personnel": [
                {
                    "name": "Civiling Per Wikström",
                    "position": "Verkst dir"
                }
            ],
            "establishment_year": 1958
        },
        "16": {
            "company_name": "PERKIN-ELMER AB",
            "activity": "Instrument för analytisk kemi",
            "employees": 30,
            "annual_turnover": 10000000,
            "capital": 15000,
            "key_personnel": [
                {
                    "name": "Ing Ralf R Jutvik",
                    "position": "Verkst dir"
                }
            ],
            "establishment_year": 1959
        },
        "17": {
            "company_name": "PERLA-KONFEKTION, AB",
            "activity": "Herr- o gosskläder",
            "employees": 25,
            "annual_turnover": 2000000,
            "capital": 100000,
            "key_personnel": [
                {
                    "name": "Per Emar",
                    "position": "Ägare o chefer"
                },
                {
                    "name": "Knut Erlandsson",
                    "position": "Ägare o chefer"
                }
            ],
            "establishment_year": 1959
        },
        "18": {
            "company_name": "PERLMANS FABRIKS AB, NILS",
            "activity": "Tillverkar herr- o pojklbyxor, herr- o pojkmössor",
            "employees": 34,
            "capital": 25000,
            "key_personnel": [
                {
                    "name": "Nils Perlman",
                    "position": "Verkst dir"
                }
            ],
            "establishment_year": 1945
        },
        "19": {
            "company_name": "SUNDBERG, AB ERIK",
            "activity": "Tillverkar o säljer transformatorer",
            "employees": 100,
            "annual_turnover": 8000000,
            "capital": 120000,
            "key_personnel": [
                {
                    "name": "Rut-Alice Sundberg",
                    "position": "Verkst dir"
                },
                {
                    "name": "Bernth Lindborg",
                    "position": "V verkst dir"
                },
                {
                    "name": "Civiling Bo Thunvall",
                    "position": "Teknisk konsult"
                }
            ],
            "establishment_year": 1921
        },
        "20": {
            "company_name": "SUNDBLAD & CARLSSON, AB",
            "activity": "Tillverkar modeller av trä, järn o metall, även metall- o kokillgjuteri o mek verkstad, sandgjutet gods i alla metaller",
            "employees": 75,
            "annual_turnover": 4000000,
            "capital": 100000,
            "key_personnel": [
                {
                    "name": "E I Sundblad",
                    "position": "Firmatecknare"
                },
                {
                    "name": "C E Florberger",
                    "position": "Firmatecknare"
                }
            ],
            "establishment_year": 1943
        }
    }
}