{
    "original": "ERDHEIMS MASKINAFFÄR, AB\n\nPnr 184 00\n\nAkersberga, Stenhagsv 30. Tel\n0764-220 30. Bankgiro 626-0699.\nPostgiro 36789-6. Tga\nErdheim-produkt, Stockholm.\nTelex 10206 ERDHEIM S\nVerksamhet: Apparater o\nanläggningar förprocess-, kemisk,\nkemiskteknisk o livsmedelsindustrin m fi.\nRepresentant för Gebr. Herrmann,\nTurbo-Werk Köln, Hans Kotthoff,\nTh Zeise, Meynell Valves Ltd.,\nPann evis &amp; Zn\n\nVarunamn: Gebr Herrmann, Turbo\n\nAntal anställda: 3\n\nÅrsomsättning: 1000 000\n\nAktiekapital: 5 000\n\nVerkst dir: Ing Lennart Erdheim\n\nEtableringsår: 1954\n\nOmbildat till aktiebolag 1960.\n\nERECTOR BYGGNADS AB\n\nPnr 116 36\n\nStockholm, Ers tag 5. Tel\n08-44 94 50. Bankgiro 57-5128.\nPost&gt;-giro 455815\n\nVerksamhet:\nByggnadsentreprenörer\n\nAntal anstäüda: 50\nÅrsomsättning: 7 000 000\nAktiekapital: 25 000\nVerkst dir: Byggn-ing Nils\nVest-lund\n\nEtableringsår: 1951.\n\nDERBY AB, SKJORTFABRIKEN\n\nPnr 510 53\n\nAplared, Box 44. Bcråsv 35. Tel\n033-803 10. Bankgiro 531-5106.\nPostgiro 96078-1\nVerksamhet: Tillverkar o säljer\nskjcrtor\n\nFörsäljningskontor: 113 25\nStockholm, Västmannag 28. Tel\n08-3186 68. Chef: Helge Olsson\nVarunamn: Derby\nAntal anställda: 37\nÅrsomsättning: 2400 000\nAktiekapital: 50 000\nVerkst dir: Carl-Anders Carlquist\nEtableringsår: 1933\nTidigare firmanamn Lysjö\nKonfektions AB. Namnändring 1967\ntill nuvarande firmanamn.\n\nDERMA, AB\n\nPnr 400 22\n\nGöteborg 24, Bergsprängareg 7. Box\n24035. Tel 031-8104 90. Bankgiro\n500-4478. Postgiro 49258-7. Tga\nDermabol. Telex 20774\nVerksamhet: Rostfri väv,\nmetallduk, metalltråd, mikroplåt,\nsträckmetall, drivremmar, brandslang,\ntransportband, teknisk väv,\nfilterduk o förnödenheter för\nscreen-tryck, back o topp splittmaskiner\nför självhäftande materiel\nVarunamn: Monodur, Noridex,\nPolydur\n\nAktiekapital: 150 000\nVerkst dir: Dr H Hauser\nFtableringsår: 1949\nOmbildat till aktiebolag 1956.\n\nDESTACO SVENSKA\nFÖRSÄLJNINGS AB\n\nPnr 11135\n\nStockholm, Kungsg 28. Tel\n08-201314, 20 30 52. Bankgiro\n625-6549. Postgiro 591490-8.\nTga Destacosale\nVerksamhet: Importör av Destaco\nspännverktyg\nVarunamn: Destaco\nAktiekapital: 5 000\nChef: Dir Helle Boberg\nEtableringsår: 1962.\n\nTOM\n\nTelex 17526 TOLUPRO S\nVerksamhet: Maskiner för vatten\no avlopp samt pumpar av skilda\nslag\n\nAntal anställda: 20\nAktiekapital: 150 000\nVerkst dir: B Hellman\nEtableringsår. 1954.\n\nHAGBY BRUK, AB\n\nPnr 713 00\n\nNora stad. Tel 0587-114 60.\nBankgiro 462-7279. Postgiro 575275-3.\nTga Hagbybruk\n\nVerksamhet: Tillverkar o säljer för\nmek industrin: diamantverktyg,\ndiamantslipskivor,\nindustridiamanter o diamantpulver. För\nbergborrning: diamantborrkronor o tillbehör.\nFör stenindustrin: diamantbelagda\nkapklingor o ramsågblad. För\nglas-o keramiska industrin:\ndiamantverktyg, diamantslipskivor o\ndiamantborrkronor. För träindustrin:\nskärpverktyg o diamantslipskivor\nVarunamn: Triefus\nAktiekapital: 200000\nVerkst dir. Ing Sture Håkanson.\n\nHAGCONSULT AB\n\nPnr 115 22\n\nStockholm, Banér g 37. Tel\n08-23 37 50. Bankgiro 196-0822.\nPostgiro 553830-1. Tga Hagconsult\nVerksamhet: Konsulterande\ngeologer o ingenjörer\nVerkst dir: Carl-Olof Morfeldt\nEtableringsår: 1956.\n\nVETLANDA VÄSKFABRIK AB\n\nPnr 574 01\n\nVetlanda 1, Stolmakarg 5. Box 59.\nTel 0383-107 27. Bankgiro\n289-7304. Postgiro 145623-5\nVerksamhet Tillverkar damväskor,\nsmyckeskrin o reklamartiklar\nAntal anställda: 30\nAktiekapital: 40 000\nVerkst dir: Ulf Idoff\nEtableringsår: 1944.\n\nSKE\n\nfinpapper, pappersmanufaktur o\nkopieringsmaskiner etc\nAktiekapital: 25 000\nVerkst dir: Martin Mårtensson\nEtableringsår: 1951.\n\nNORDHAV, AB\n\nPnr 371 00\n\nKarlskrona, Fiskhamnen. Tel\n0455-195 70. Postgiro 362977.\nTga Nordhav.\nTelex 43038 NORDHAV S\nVerksamhet: Fiskförädling o\nförsäljning av färska, frysta o rökta\nfiskprodukter samt skaldjur\nAntal anställda: 180\nÅrsomsättning: 40000 000\nVeikst dir: Gösta F Karlsson.\n\nNORDHOLMS VERKSTÄDER\nAB\n\nPnr 31100\n\nFalkenberg, Kvekatorpsv. Tel\n0346-142 60. Bankgiro 42-5781.\nPostgiro 5568. Tga Nordholmsverken\nVerksamhet Tillverkar\nvarmlufts-pannor, bygg- o sädestorkar,\nventilationsanläggningar, maskin-svetsade rör, fartygscontainers o\nflats\n\nVarunamn: Kompax, Nordholms,\nSwetube, WHG\nAntal anställda: 100\nÅrsomsättning: 12 000 000\nAktiekapital: 350 000\nVerkst dir: Gunnar Ericson\nEtableringsår: 1958.\n\nHÄLSINGBORGS STUVERI AB\n\nPnr 25102\n\nHelsingborg 1, Box 6. Tel\n042-18 04 30. Bankgiro 653-0273.\nPostgiro 410811-4. Tga Stuveribolaget\nVerksamhet: Lossning o lastning\nav fartyg, samt försäljning av\ndiverse stuverimaterial\nAntal anställda: 116\nAktiekapital: 75 000\nStyrelse: Dir Karl Engfors\nVerkst dir: Kapten P G Strömberg\nEtableringsår: 1925.\n\nHÄLSINGBORGS STÄNGSEL.\nNÄT, AB\n\nPnr 252 27\n\nHälsingborg, Söderg 137. Tel\n042-18 0100. Bankgiro 863-1301.\nPostgiro 648770-6\n\nVerksamhet: Tillverkar alla slag\nav stängselnät\nAntal anstäUda: 27\nÅrsomsättning: 2700 000\nAktiekapital: 12 000\nÄgare o chefer: Bertil Gylllng,\nPer Gylllng, Benny Rosenblom\nEtableringsår: 1964.\n\ndata logic ab\n\nPnr 17154\n\nSolna, Vretenv 2. Tel 08-98 12 70.\nBankgiro 481-8258. Postgiro\n5033 90-7 \"\n\nVerksamhet: ADB-konsulter\n(systemmän, programmerare).\nOrganisationskonsulter. Servicebyrå\n(egen-dator)\n\nAvdelningskontor: 632 21\nEskilstuna, Kungsg 10. Tel 016-12 00 30\n211 38 Malmö, Malmborgsg 4. Tel\n040-321 61\n\n42152 Västra Frölunda.\nKlang-färgsg 11. Tel 031-29 29 67\nAntal anställda: 50\nÅrsomsättning: 3 000 000\nAktiekapital: 50 000\n\nVerkst dir: Civilekonom Rolf\nLektell\n\nV verkst dir: Per-Olof Ulmehag\nEtableringsår: 1967\nDotterföretag till Business\nManagement Promotions Ltd, Hereford,\nEngland. Systerföretag i England,\nNorge, Danmark, Schweiz.\n\ndataberäkning, ab\n\nPnr 17133\n\nSolna, Ekensberg sv 95. Tel\n08-83 2010, 83 20 11. Postgiro 56263-7\nVerksamhet: Utvecklar dataprogram\nför VVS-branschen\nÅrsomsättning: 200 000\nAktiekapital: 5 000\nVerkst dir: Ing Thorn Henningsson\nEtableringsår: 1964.\n\ndatabyrån for\ninformationsbehandling, ab\n\nPnr 17147\n\nSolna, Hannebergsg 24. Tel\n08-83 53 80. Bankgiro 16-4688.\nPostgiro 708933\n\nVerksamhet:\nDatakonsultverksamhet innebärande systemarbete o\nprogrammering inom företrädesvis\nden statliga o kommunala sektorn\nAntal anställda: 4\nÅrsomsättning: 400 000\nAktiekapital: 5 000\nVerkst dir: Bertil Cassemar\nEtableringsår: 1965.\n\nSYDSPEDITION, AB\n\nPnr 200 61\n\nMalmö 30, Ovägen, Hamnkontoret.\nBox 30006. Tel 040-16 00 25.\nBankgiro 869-0794. Postgiro 533210-1\nTelex 32531. Tga Sydsped\nVerksamhet: Internationell\nspedition. Transporter, försäkringar,\nförtullningar, stycke- o flyggods\nÅrsomsättning: 12 000 000\nAktiekapital: 150 000\nVerkst dir: Bengt-Göran Olsson\nEtableringsår: 1961\nOmbildat till aktiebolag 1963.\n\nSYDSTEN, AB\n\nPnr 203 11\n\nMalmö 4, S Tullg 3. Box 4072. Tel\n040-73840. Bankgiro 64-0638.\nPostgiro 434830\n\nVerksamhet: Tillverkar o säljer\nmakadam, grus o betong\nFörsäljningskontor: Dalby. Tel\n046-592 50\n\nHardeberga, Södra Sandby. Tel\n046-990 60\n\nForserum. Tel 0380-201 25\nAntal anställda: 250\nÅrsomsättning: 35 000 000\nAktiekapital: 2 250 000\nVerkst dir: Civiling Arne Wehtje\nEkonomiavd: Dir Inge Ellerstrand\nProd-chef: Disp Boje Bojesson\nEtableringsår: 1969.",
    "structured": {
        "1": {
            "company_name": "ERDHEIMS MASKINAFFÄR, AB",
            "pnr": "184 00",
            "address": "Akersberga, Stenhagsv 30",
            "phone_number": "0764-220 30",
            "bank_details": {
                "bankgiro": "626-0699",
                "postgiro": "36789-6"
            },
            "activity": "Apparater o anläggningar för process-, kemisk, kemiskteknisk o livsmedelsindustrin m fi. Representant för Gebr. Herrmann, Turbo-Werk Köln, Hans Kotthoff, Th Zeise, Meynell Valves Ltd., Pann evis & Zn",
            "employees": 3,
            "annual_turnover": 1000000,
            "capital": 5000,
            "key_personnel": [
                {
                    "name": "Ing Lennart Erdheim",
                    "position": "Verkst dir"
                }
            ],
            "establishment_year": 1954
        },
        "2": {
            "company_name": "ERECTOR BYGGNADS AB",
            "pnr": "116 36",
            "address": "Stockholm, Ers tag 5",
            "phone_number": "08-44 94 50",
            "bank_details": {
                "bankgiro": "57-5128",
                "postgiro": "455815"
            },
            "activity": "Byggnadsentreprenörer",
            "employees": 50,
            "annual_turnover": 7000000,
            "capital": 25000,
            "key_personnel": [
                {
                    "name": "Byggn-ing Nils Vest-lund",
                    "position": "Verkst dir"
                }
            ],
            "establishment_year": 1951
        },
        "3": {
            "company_name": "DERBY AB, SKJORTFABRIKEN",
            "pnr": "510 53",
            "address": "Aplared, Box 44, Bcråsv 35",
            "phone_number": "033-803 10",
            "bank_details": {
                "bankgiro": "531-5106",
                "postgiro": "96078-1"
            },
            "activity": "Tillverkar o säljer skjcrtor",
            "sales_office_address": "Stockholm, Västmannag 28",
            "sales_office_phone": "08-3186 68",
            "sales_office_chef": "Helge Olsson",
            "employees": 37,
            "annual_turnover": 2400000,
            "capital": 50000,
            "key_personnel": [
                {
                    "name": "Carl-Anders Carlquist",
                    "position": "Verkst dir"
                }
            ],
            "establishment_year": 1933,
            "former_firm_name": "Lysjö Konfektions AB",
            "name_change_year": 1967
        },
        "4": {
            "company_name": "DERMA, AB",
            "pnr": "400 22",
            "address": "Göteborg 24, Bergsprängareg 7, Box 24035",
            "phone_number": "031-8104 90",
            "bank_details": {
                "bankgiro": "500-4478",
                "postgiro": "49258-7"
            },
            "activity": "Rostfri väv, metallduk, metalltråd, mikroplåt, sträckmetall, drivremmar, brandslang, transportband, teknisk väv, filterduk o förnödenheter för screen-tryck, back o topp splittmaskiner för självhäftande materiel",
            "products": "Monodur, Noridex, Polydur",
            "capital": 150000,
            "key_personnel": [
                {
                    "name": "Dr H Hauser",
                    "position": "Verkst dir"
                }
            ],
            "establishment_year": 1949,
            "company_type_change_year": 1956
        },
        "5": {
            "company_name": "DESTACO SVENSKA FÖRSÄLJNINGS AB",
            "pnr": "11135",
            "address": "Stockholm, Kungsg 28",
            "phone_number": "08-201314, 20 30 52",
            "bank_details": {
                "bankgiro": "625-6549",
                "postgiro": "591490-8"
            },
            "activity": "Importör av Destaco spännverktyg",
            "capital": 5000,
            "key_personnel": [
                {
                    "name": "Dir Helle Boberg",
                    "position": "Chef"
                }
            ],
            "establishment_year": 1962
        },
        "6": {
            "company_name": "TOM",
            "telex": "17526 TOLUPRO S",
            "activity": "Maskiner för vatten o avlopp samt pumpar av skilda slag",
            "employees": 20,
            "capital": 150000,
            "key_personnel": [
                {
                    "name": "B Hellman",
                    "position": "Verkst dir"
                }
            ],
            "establishment_year": 1954
        },
        "7": {
            "company_name": "HAGBY BRUK, AB",
            "pnr": "713 00",
            "address": "Nora stad",
            "phone_number": "0587-114 60",
            "bank_details": {
                "bankgiro": "462-7279",
                "postgiro": "575275-3"
            },
            "activity": "Tillverkar o säljer för mek industrin: diamantverktyg, diamantslipskivor, industridiamanter o diamantpulver. För bergborrning: diamantborrkronor o tillbehör. För stenindustrin: diamantbelagda kapklingor o ramsågblad. För glas-o keramiska industrin: diamantverktyg, diamantslipskivor o diamantborrkronor. För träindustrin: skärpverktyg o diamantslipskivor",
            "products": "Triefus",
            "capital": 200000,
            "key_personnel": [
                {
                    "name": "Ing Sture Håkanson",
                    "position": "Verkst dir"
                }
            ],
            "establishment_year": 1949,
            "company_type_change_year": 1956
        },
        "8": {
            "company_name": "HAGCONSULT AB",
            "pnr": "115 22",
            "address": "Stockholm, Banér g 37",
            "phone_number": "08-23 37 50",
            "bank_details": {
                "bankgiro": "196-0822",
                "postgiro": "553830-1"
            },
            "activity": "Konsulterande geologer o ingenjörer",
            "key_personnel": [
                {
                    "name": "Carl-Olof Morfeldt",
                    "position": "Verkst dir"
                }
            ],
            "establishment_year": 1956
        },
        "9": {
            "company_name": "VETLANDA VÄSKFABRIK AB",
            "pnr": "574 01",
            "address": "Vetlanda 1, Stolmakarg 5, Box 59",
            "phone_number": "0383-107 27",
            "bank_details": {
                "bankgiro": "289-7304",
                "postgiro": "145623-5"
            },
            "activity": "Tillverkar damväskor, smyckeskrin o reklamartiklar",
            "employees": 30,
            "capital": 40000,
            "key_personnel": [
                {
                    "name": "Ulf Idoff",
                    "position": "Verkst dir"
                }
            ],
            "establishment_year": 1944
        },
        "10": {
            "company_name": "SKE",
            "activity": "Finpapper, pappersmanufaktur o kopieringsmaskiner etc",
            "capital": 25000,
            "key_personnel": [
                {
                    "name": "Martin Mårtensson",
                    "position": "Verkst dir"
                }
            ],
            "establishment_year": 1951
        },
        "11": {
            "company_name": "NORDHAV, AB",
            "pnr": "371 00",
            "address": "Karlskrona, Fiskhamnen",
            "phone_number": "0455-195 70",
            "postgiro": "362977",
            "activity": "Fiskförädling o försäljning av färska, frysta o rökta fiskprodukter samt skaldjur",
            "employees": 180,
            "annual_turnover": 40000000,
            "key_personnel": [
                {
                    "name": "Gösta F Karlsson",
                    "position": "Verkst dir"
                }
            ]
        },
        "12": {
            "company_name": "NORDHOLMS VERKSTÄDER AB",
            "pnr": "31100",
            "address": "Falkenberg, Kvekatorpsv",
            "phone_number": "0346-142 60",
            "bank_details": {
                "bankgiro": "42-5781"
            },
            "activity": "Tillverkar varmlufts-pannor, bygg- o sädestorkar, ventilationsanläggningar, maskin-svetsade rör, fartygscontainers o flats",
            "products": "Kompax, Nordholms, Swetube, WHG",
            "employees": 100,
            "annual_turnover": 12000000,
            "capital": 350000,
            "key_personnel": [
                {
                    "name": "Gunnar Ericson",
                    "position": "Verkst dir"
                }
            ],
            "establishment_year": 1958
        },
        "13": {
            "company_name": "HÄLSINGBORGS STUVERI AB",
            "pnr": "25102",
            "address": "Helsingborg 1, Box 6",
            "phone_number": "042-18 04 30",
            "bank_details": {
                "bankgiro": "653-0273",
                "postgiro": "410811-4"
            },
            "activity": "Lossning o lastning av fartyg, samt försäljning av diverse stuverimaterial",
            "employees": 116,
            "capital": 75000,
            "executive_board": "Dir Karl Engfors",
            "key_personnel": [
                {
                    "name": "Kapten P G Strömberg",
                    "position": "Verkst dir"
                }
            ],
            "establishment_year": 1925
        },
        "14": {
            "company_name": "HÄLSINGBORGS STÄNGSEL. NÄT, AB",
            "pnr": "252 27",
            "address": "Hälsingborg, Söderg 137",
            "phone_number": "042-18 0100",
            "bank_details": {
                "bankgiro": "863-1301",
                "postgiro": "648770-6"
            },
            "activity": "Tillverkar alla slag av stängselnät",
            "employees": 27,
            "annual_turnover": 2700000,
            "capital": 12000,
            "executives": [
                "Bertil Gylllng",
                "Per Gylllng",
                "Benny Rosenblom"
            ],
            "establishment_year": 1964
        },
        "15": {
            "company_name": "Data Logic AB",
            "pnr": "17154",
            "address": "Solna, Vretenv 2",
            "phone_number": "08-98 12 70",
            "bank_details": {
                "bankgiro": "481-8258",
                "postgiro": "5033 90-7"
            },
            "activity": "ADB-konsulter (systemmän, programmerare). Organisationskonsulter. Servicebyrå (egen-dator)",
            "sub_offices": [
                "632 21 Eskilstuna, Kungsg 10, Tel 016-12 00 30",
                "211 38 Malmö, Malmborgsg 4, Tel 040-321 61",
                "42152 Västra Frölunda, Klang-färgsg 11, Tel 031-29 29 67"
            ],
            "employees": 50,
            "annual_turnover": 3000000,
            "capital": 50000,
            "key_personnel": [
                {
                    "name": "Civilekonom Rolf Lektell",
                    "position": "Verkst dir"
                },
                {
                    "name": "Per-Olof Ulmehag",
                    "position": "V verkst dir"
                }
            ],
            "establishment_year": 1967,
            "parent_company": "Business Management Promotions Ltd",
            "associated_companies": [
                "England",
                "Norge",
                "Danmark",
                "Schweiz"
            ]
        },
        "16": {
            "company_name": "Databeräkning, AB",
            "pnr": "17133",
            "address": "Solna, Ekensberg sv 95",
            "phone_number": "08-83 2010, 83 20 11",
            "postgiro": "56263-7",
            "activity": "Utvecklar dataprogram för VVS-branschen",
            "annual_turnover": 200000,
            "capital": 5000,
            "key_personnel": [
                {
                    "name": "Ing Thorn Henningsson",
                    "position": "Verkst dir"
                }
            ],
            "establishment_year": 1964
        },
        "17": {
            "company_name": "Databyrån for informationsbehandling, AB",
            "pnr": "17147",
            "address": "Solna, Hannebergsg 24",
            "phone_number": "08-83 53 80",
            "bank_details": {
                "bankgiro": "16-4688",
                "postgiro": "708933"
            },
            "activity": "Datakonsultverksamhet innebärande systemarbete o programmering inom företrädesvis den statliga o kommunala sektorn",
            "employees": 4,
            "annual_turnover": 400000,
            "capital": 5000,
            "key_personnel": [
                {
                    "name": "Bertil Cassemar",
                    "position": "Verkst dir"
                }
            ],
            "establishment_year": 1965
        },
        "18": {
            "company_name": "SYDSPEDITION, AB",
            "pnr": "200 61",
            "address": "Malmö 30, Ovägen, Hamnkontoret, Box 30006",
            "phone_number": "040-16 00 25",
            "bank_details": {
                "bankgiro": "869-0794",
                "postgiro": "533210-1"
            },
            "activity": "Internationell spedition. Transporter, försäkringar, förtullningar, stycke- o flyggods",
            "annual_turnover": 12000000,
            "capital": 150000,
            "key_personnel": [
                {
                    "name": "Bengt-Göran Olsson",
                    "position": "Verkst dir"
                }
            ],
            "establishment_year": 1961,
            "company_type_change_year": 1963
        },
        "19": {
            "company_name": "SYDSTEN, AB",
            "pnr": "203 11",
            "address": "Malmö 4, S Tullg 3, Box 4072",
            "phone_number": "040-73840",
            "bank_details": {
                "bankgiro": "64-0638",
                "postgiro": "434830"
            },
            "activity": "Tillverkar o säljer makadam, grus o betong",
            "sales_office_addresses": [
                "Dalby",
                "Hardeberga, Södra Sandby",
                "Forserum"
            ],
            "employees": 250,
            "annual_turnover": 35000000,
            "capital": 2250000,
            "key_personnel": [
                {
                    "name": "Civiling Arne Wehtje",
                    "position": "Verkst dir"
                },
                {
                    "name": "Dir Inge Ellerstrand",
                    "position": "Ekonomiavd"
                },
                {
                    "name": "Disp Boje Bojesson",
                    "position": "Prod-chef"
                }
            ],
            "establishment_year": 1969
        }
    }
}