{
    "original": "STEENS MEK VERKSTAD\n\nPnr 69100\n\nKarlskoga, Högåsv 45. Tel\n0586-312 37\n\nVerksamhet: Utför legoarbeten samt\nautomat- o revolversvarvning\nÄgare o chefer: Johan Erik Steen,\nA E Steen\n\nEtableringsån 1945.\n\nSTEÉNS TRANSPORT AB,\nHENRY\n\nPnr 703 58\n\nÖrebro, Industrig 10. Tel 019-\n\n12 40 80. Bankgiro 463-2683.\nPostgiro 490781-2\n\nVerksamhet: Utför transporter\nAntal anställda: 50\nÅrsomsättning: 4 000 000\nAktiekapital: 200 000\nVerkst dir: Henry Steén\nEtableringsår: 1959.\n\nKUNGSBACKA BYGGNADS AB\n\nPnr 434 01\n\nKungsbacka 1, Box 21. Storg 33.\nTel 0300-108 01, 108 43. Bankgiro\n54-6557. Postgiro 343948\nVerksamhet: Bygger i egen regi\nsamt fastighetsförvaltning\nAntal anställda: 70\nÅrsomsättning: 11000 000\n.Aktiekapital: 225 000\nVerkst dir: Byggmäst Albert\nCarlsson\n\nEtableringsår: 1941\nOmbildat till aktiebolag 1950.\n\nKUNGSBESLAG AB\n\nPnr 42102\n\nVästra Frölunda 2, Fröhusg 10. Box\n2044. Tel 031-4503 45. Bankgiro\n410-0368. Postgiro 420840-1. Tga\nKungsbeslag\n\nVerksamhet: Försäljning av\nbyggnadsbeslag. Import o export\nVarunamn: Kungs\nAktiekapital: 150 000\nStyrelse: Adv G Lagerlöf, dir Allan\nAndersson\n\nÄgare o chef: Dir Allan Andersson\nEtableringsår: 1949.\n\nNYVALL AB, BERNDT\n\nPnr 68100\n\nKristinehamn, Spelmansg 19. Tel\n0550-11190, 11191. Bankgiro\n110-0270. Postgiro 170077-2. Tga\nBe-vall. Telex 66027\nVerksamhet: Trävaruagentur\nAntal anställda: 4\nAktiekapital: 20 000\nVerkst dir: Berndt Nyvall\nEtableringsår: 1928.\n\nERI\n\nDelsboverkstaden, Stationsg 12.\nTel 0653-105 52\n\nGröndalsverkstaden, Stockholm 44,\nBox 44006. Tel 08-19 01 20\nIngelstafabriken, Norrköping 1,\nBox 166. Tel 011-1803 10\nKabelverket, Älvsjö 1, Fack. Tel\n08-47 25 00\n\nKatrineholmsverkstaden,\nVästgötar 16. Tel 0150-133 20\nKarlskronafabriken, ölandsg 1. Tel\n0455-19190\n\nKristianstadsfabriken, Tegelbruksv\nTellusverkstaden i Norrköping, Box\n3006. Tel 011-18 03 80\n15. Tel 044-12 3180\nOlofströmsverkstaden, Trädgåxdsv\n84. Tel 0454-414 70\nOskarshamnsfabriken, Gyllings v\n9. Tel 0491-160 40\nRonnebyverkstaden, Fridhemsv 15.\nTel 0457-129 10\n\nSöderhamnsfabriken, Tägtg. Tel\n0270-100 40\n\nVisbyverkstaden, N Hanseg 18. Tel\n0498-160 00\n\nOrebrofabriken, Fack. Tel\n019-124260\n\nöstersundsverkstaden, Odenskogsv\n27-29. Tel 063-170 00\nAntal anställda: 27 000 (i Sverige)\n57 000 (Totalt i koncernen)\nÅrsomsättning: 1 250 506000\n(Moderbolaget) 2 906 76 2 000\n(Koncernen) (1969)\n\nAktiekapital: 615 205 000 (1969)\nStyrelse: Tekn dr Marcus\nWallenberg (ordf), talman Erik Boheman,\nbyråchef Lars-Olof Ekeberg, dir\nBjörn Lundvall, dir Wilhelm\nSöderman, bankdir Jan Wallander, prof\nRagnar Woxén, dir Sven Ture Åberg\nVerkst dir: Björn Lundvall\nV verkst dir.r: Christian Jacobaeus,\nArne Mohlin, Arne Stein, Knut\nStyrën, Fred Sundkvist, Gunnar\nSvalling\n\nInköpschef: Bengt Söderberg. Telex\n\n1541 ERICINK S\n\nEtableringsår: 1876\n\nFör ytterligare uppgifter se:\n\nL M Ericsson Telemateriel AB\n\nInstruktionsteknik AB\n\nAB Rifa\n\nSieverts Kabelverk AB\nSvenska Radio AB.\n\nAntal anställda: 1198\nÅrsomsättning: 157 000 000\nAktiekapital: 16 000 000\nVerkst dir. Per-Bertil Janson\nEtableringsår: 1929.\n\nERIKSSON, BYGGNADS AB\nLENNART\n\nPnr 872 01\n\nKramfors 1, Drottningg 12. Box 81.\nTel 0612-11410. Postgiro 410777\nVerksamhet: Ny- o ombyggnader av\nbostäder o industribyggnader\nAntal anställda: 110\nÅrsomsättning: 9 000 000\nAktiekapital: 25 000\nVerkst dir: Byggmäst Lennart\nEriksson\n\nEtableringsår: 1956.\n\nGEFLEBORGS TRYCKERI AB\n\nPnr 800 06\n\nGävle 6, Akarg 67. Box 6043. Tel\n026-12 97 00. Bankgiro 78-3843.\nPostgiro 7696\n\nVerksamhet: Boktryckeri o\nbokbinderi\n\nAntal anställda: 18\nAktiekapital: 165 000\nVerkst dir: Lennart Ekholm\nEtableringsår: 1761.\n\nGÄVLE-DALA LANTMANNA.\nFÖRBUND FÖRENING U P A\n\nPnr 801 07\n\nGävle 1, Drottningg 28. Box 558.\nTel 026-18 03 40. Tga\nLantförbun-det\n\nVerksamhet: Förnödenheter o\nmaskiner till jordbruket\nAntal anstäUda: 316\nÅrsomsättning: 121000 000\nVerkst dir: Edol Eriksson.\n\nGÄVLEFISK EK FOR\n\nPnr 800 04\n\nGävle 4, Box 4045. Båtsmansg 13\nTel 026-1159 20, 12 92 20.\nBankgiro 194-1632. Postgiro 171171-2\nVerksamhet: Kooperativ\nsammanslutning av yrkesfiskare\n\nAntal anstäUda: 63\nÅrsomsättning: 13 000 000\nChef: Dir Vallentin Nordin\nEtableringsår: 1935.\n\nGÄVLE-PERSIENNER\n\nse Ge-Pe Verken.\n\nGÖINGE BIL AB\n\nPnr 28101\n\nHässleholm 1, Box 21.\nKristian-stadsv 2. Tel 0451-142 50.\nBankgiro 270-1175. Postgiro 467900-7\nVerksamhet: Auktoriserad\nVolvoåterförsäljare samt service.\nBillackering. Biluthyrning.\nTurist-busservice\n\nFörsäljningskontor: 28010\nSös-dala. Tel 0451-606 00\nAntal anställda: 90\nÅrsomsättning: 20 000000\nStyrelse: Dir Carl Persson, fru\nEva Persson\nVerkst dir: Carl Persson\nEkonomichef: Wilhelm Mellwing\nEtableringsår: 1952.\n\nEGNA BOSTÄDER, AB\n\nPnr 600 04\n\nNorrköping 4, Slåtterg 15. Box 4039.\nTel 011-1218 64. Postgiro 270497\n\nVerksamhet: Säljer kökssnickerier\n\nspecial\n\nVarunamn: EBO\nAktiekapital: 20 000\n\nChef: Bängt Granberg\nEtableringsår: 1943.\n\nGRUNDIN &amp; CO AB\n\nPnr 172 21\n\nSimdbyberg 1, Box 4. Elieg 14-16.\nTel 08-28 69 28, 28 05 28. Bankgiro\n\n225-0306. Postgiro 336912. Tga\nGrucohab\n\nVerksamhet: Import o\nengrosför-säljning av arbetarskyddsmaterial\nAntal anställda: 6\nÅrsomsättning: 1500 000\nAktiekapital: 100 000\nVerkst dir: Sören Grundin\nEtableringsår: 1949.\n\nPALMER, AB FELIX\n\nPnr 21129\n\nMalmö, Stora Kvarng 36. Tel\n040-33755, 11 64 11. Bankgiro\n156-5027. Postgiro 477036-8. Tga\nPalmérs\n\nVeiksamhet: Säljer VVS-tillbehör,\noljearmatur, packningar, slangar,\ntrassel, sanitetsarmatur\nAntal anstäUda: 5\nAktiekapital: 75 000\nVerkst dir: Felix Palmér\nEtableringsår: 1955.\n\nMORA KNIVFABRIK\n\nPnr 792 00\n\nMora, Box 72. Tel 0250-101 59.\nTga Moraknife\n\nVerksamhet: Tillverkar knivar\nsåsom hushållsknivar, slaktar-,\njakt-o sportknivar, slöjd- o täljknivar\nsamt slidknivar.\n\nMORAINDUSTRI, AB\n\nPnr 792 00\n\nMora, Box 131. Tel 0250-135 30.\nBankgiro 469-1630. Postgiro\n144714-3\n\nVerksamhet: Varmpressning av\nmässing-, koppar- o\nlättmetall-detaljer\n\nAntal anstäUda: 25\nÅrsomsättning: 3 000 000\nAktiekapital: 66000\nVerkst dir Krång Einar Eriksson\nEtableringsår: 1935.\n\nBOO, AB M\n\nPnr 402 22\n\nGöteborg 5, Box 5119. Abäcksg 6,\nMölndal. Tel 031-20 06 25.\nBankgiro 362-601. Postgiro 243945-3\nVerksamhet: Tillverkar\nbilklädslar. Säljer biltextilvaror\nAntal anställda: 20\nÅrsomsättning: 2000 000\nAktiekapital: 30 000\nStyrelse: Dir Nils Gagner,\nverkmäst Yngve Nolhag\nVerkst din Nils Gagner\nVerkmästare: Yngve Nolhag\nEtableringsår: 1947.\n\nBOOSEY&amp; HAWKES\nSVENSKA AB\n\nPnr 402 23\n\nGöteborg 5, S Vägen 64. Box 5147.\nTel 031-165500. Bankgiro\n505-7898. Postgiro 525240-8. Tga\nSwesonorous\n\nVerksamhet: Grossistföretag inom\nmusikinstrumentbranschen\nAntal anställda: 15\nAktiekapital: 90 000\nVerkst dir: Holger Andréasson\nEtableringsår: 1958.",
    "structured": {
        "1": {
            "company_name": "STEENS MEK VERKSTAD",
            "pnr": "69100",
            "address": "Högåsv 45, Karlskoga",
            "phone_number": "0586-312 37",
            "activity": "Utför legoarbeten samt automat- o revolversvarvning",
            "key_personnel": [
                {
                    "name": "Johan Erik Steen",
                    "position": "Ägare"
                },
                {
                    "name": "A E Steen",
                    "position": "Chefer"
                }
            ],
            "establishment_year": 1945
        },
        "2": {
            "company_name": "STEÉNS TRANSPORT AB",
            "pnr": "703 58",
            "address": "Industrig 10, Örebro",
            "phone_number": "019-12 40 80",
            "bank_details": {
                "bankgiro": "463-2683",
                "postgiro": "490781-2"
            },
            "activity": "Utför transporter",
            "employees": 50,
            "annual_turnover": 4000000,
            "capital": 200000,
            "key_personnel": [
                {
                    "name": "Henry Steén",
                    "position": "Verkst dir"
                }
            ],
            "establishment_year": 1959
        },
        "3": {
            "company_name": "KUNGSBACKA BYGGNADS AB",
            "pnr": "434 01",
            "address": "Storg 33, Kungsbacka 1, Box 21",
            "phone_number": "0300-108 01, 108 43",
            "bank_details": {
                "bankgiro": "54-6557",
                "postgiro": "343948"
            },
            "activity": "Bygger i egen regi samt fastighetsförvaltning",
            "employees": 70,
            "annual_turnover": 11000000,
            "capital": 225000,
            "key_personnel": [
                {
                    "name": "Byggmäst Albert Carlsson",
                    "position": "Verkst dir"
                }
            ],
            "establishment_year": 1941
        },
        "4": {
            "company_name": "KUNGSBESLAG AB",
            "pnr": "42102",
            "address": "Västra Frölunda 2, Fröhusg 10, Box 2044",
            "phone_number": "031-4503 45",
            "bank_details": {
                "bankgiro": "410-0368",
                "postgiro": "420840-1"
            },
            "activity": "Försäljning av byggnadsbeslag. Import o export",
            "annual_production_value": "Annual production value.",
            "capital": 150000,
            "key_personnel": [
                {
                    "name": "Dir Allan Andersson",
                    "position": "Ägare o chef"
                }
            ],
            "establishment_year": 1949
        },
        "5": {
            "company_name": "NYVALL AB, BERNDT",
            "pnr": "68100",
            "address": "Spelmansg 19, Kristinehamn",
            "phone_number": "0550-11190, 11191",
            "bank_details": {
                "bankgiro": "110-0270",
                "postgiro": "170077-2"
            },
            "activity": "Trävaruagentur",
            "employees": 4,
            "capital": 20000,
            "key_personnel": [
                {
                    "name": "Berndt Nyvall",
                    "position": "Verkst dir"
                }
            ],
            "establishment_year": 1928
        },
        "6": {
            "company_name": "ERI",
            "address": "Delsboverkstaden, Stationsg 12, Tel 0653-105 52",
            "key_personnel": [],
            "employees": 27000,
            "annual_turnover": 1250506000,
            "capital": 615205000,
            "establishment_year": 1876
        },
        "7": {
            "company_name": "ERIKSSON, BYGGNADS AB LENNART",
            "pnr": "872 01",
            "address": "Drottningg 12, Kramfors 1, Box 81",
            "phone_number": "0612-11410",
            "postgiro": "410777",
            "activity": "Ny- o ombyggnader av bostäder o industribyggnader",
            "employees": 110,
            "annual_turnover": 9000000,
            "capital": 25000,
            "key_personnel": [
                {
                    "name": "Byggmäst Lennart Eriksson",
                    "position": "Verkst dir"
                }
            ],
            "establishment_year": 1956
        },
        "8": {
            "company_name": "GEFLEBORGS TRYCKERI AB",
            "pnr": "800 06",
            "address": "Akarg 67, Gävle 6, Box 6043",
            "phone_number": "026-12 97 00",
            "bankgiro": "78-3843",
            "postgiro": "7696",
            "activity": "Boktryckeri o bokbinderi",
            "employees": 18,
            "capital": 165000,
            "key_personnel": [
                {
                    "name": "Lennart Ekholm",
                    "position": "Verkst dir"
                }
            ],
            "establishment_year": 1761
        },
        "9": {
            "company_name": "GÄVLE-DALA LANTMANNA. FÖRBUND FÖRENING U P A",
            "pnr": "801 07",
            "address": "Drottningg 28, Gävle 1, Box 558",
            "phone_number": "026-18 03 40",
            "activity": "Förnödenheter o maskiner till jordbruket",
            "employees": 316,
            "annual_turnover": 121000000,
            "key_personnel": [
                {
                    "name": "Edol Eriksson",
                    "position": "Verkst dir"
                }
            ]
        },
        "10": {
            "company_name": "GÄVLEFISK EK FOR",
            "pnr": "800 04",
            "address": "Box 4045, Båtsmansg 13, Gävle 4",
            "phone_number": "026-1159 20, 12 92 20",
            "bankgiro": "194-1632",
            "postgiro": "171171-2",
            "activity": "Kooperativ sammanslutning av yrkesfiskare",
            "employees": 63,
            "annual_turnover": 13000000,
            "key_personnel": [
                {
                    "name": "Dir Vallentin Nordin",
                    "position": "Chef"
                }
            ],
            "establishment_year": 1935
        },
        "11": {
            "company_name": "GÖINGE BIL AB",
            "pnr": "28101",
            "address": "Box 21, Kristian-stadsv 2, Hässleholm 1",
            "phone_number": "0451-142 50",
            "bankgiro": "270-1175",
            "postgiro": "467900-7",
            "activity": "Auktoriserad Volvoåterförsäljare samt service. Billackering. Biluthyrning. Turist- busservice",
            "employees": 90,
            "annual_turnover": 20000000,
            "key_personnel": [
                {
                    "name": "Carl Persson",
                    "position": "Verkst dir"
                },
                {
                    "name": "Eva Persson",
                    "position": "Styrelse"
                },
                {
                    "name": "Wilhelm Mellwing",
                    "position": "Ekonomichef"
                }
            ],
            "establishment_year": 1952
        },
        "12": {
            "company_name": "EGNA BOSTÄDER, AB",
            "pnr": "600 04",
            "address": "Slåtterg 15, Norrköping 4, Box 4039",
            "phone_number": "011-1218 64",
            "postgiro": "270497",
            "activity": "Säljer kökssnickerier special",
            "capital": 20000,
            "key_personnel": [
                {
                    "name": "Bängt Granberg",
                    "position": "Chef"
                }
            ],
            "establishment_year": 1943
        },
        "13": {
            "company_name": "GRUNDIN & CO AB",
            "pnr": "172 21",
            "address": "Box 4, Elieg 14-16, Simdbyberg 1",
            "phone_number": "08-28 69 28, 28 05 28",
            "bankgiro": "225-0306",
            "postgiro": "336912",
            "activity": "Import o engrosför-säljning av arbetarskyddsmaterial",
            "employees": 6,
            "annual_turnover": 1500000,
            "capital": 100000,
            "key_personnel": [
                {
                    "name": "Sören Grundin",
                    "position": "Verkst dir"
                }
            ],
            "establishment_year": 1949
        },
        "14": {
            "company_name": "PALMER, AB FELIX",
            "pnr": "21129",
            "address": "Stora Kvarng 36, Malmö",
            "phone_number": "040-33755, 11 64 11",
            "bankgiro": "156-5027",
            "postgiro": "477036-8",
            "activity": "Säljer VVS-tillbehör, oljearmatur, packningar, slangar, trassel, sanitetsarmatur",
            "employees": 5,
            "capital": 75000,
            "key_personnel": [
                {
                    "name": "Felix Palmér",
                    "position": "Verkst dir"
                }
            ],
            "establishment_year": 1955
        },
        "15": {
            "company_name": "MORA KNIVFABRIK",
            "pnr": "792 00",
            "address": "Box 72, Mora",
            "phone_number": "0250-101 59",
            "activity": "Tillverkar knivar såsom hushållsknivar, slaktar-, jakt-o sportknivar, slöjd- o täljknivar samt slidknivar."
        },
        "16": {
            "company_name": "MORAINDUSTRI, AB",
            "pnr": "792 00",
            "address": "Box 131, Mora",
            "phone_number": "0250-135 30",
            "bankgiro": "469-1630",
            "postgiro": "144714-3",
            "activity": "Varmpressning av mässing-, koppar- o lättmetall-detaljer",
            "employees": 25,
            "annual_turnover": 3000000,
            "capital": 66000,
            "key_personnel": [
                {
                    "name": "Krång Einar Eriksson",
                    "position": "Verkst dir"
                }
            ],
            "establishment_year": 1935
        },
        "17": {
            "company_name": "BOO, AB M",
            "pnr": "402 22",
            "address": "Abäcksg 6, Mölndal, Box 5119, Göteborg 5",
            "phone_number": "031-20 06 25",
            "bankgiro": "362-601",
            "postgiro": "243945-3",
            "activity": "Tillverkar bilklädslar. Säljer biltextilvaror",
            "employees": 20,
            "annual_turnover": 2000000,
            "capital": 30000,
            "key_personnel": [
                {
                    "name": "Nils Gagner",
                    "position": "Verkst dir"
                },
                {
                    "name": "Yngve Nolhag",
                    "position": "Verkmästare"
                }
            ],
            "establishment_year": 1947
        },
        "18": {
            "company_name": "BOOSEY&amp; HAWKES SVENSKA AB",
            "pnr": "402 23",
            "address": "S Vägen 64, Box 5147, Göteborg 5",
            "phone_number": "031-165500",
            "bankgiro": "505-7898",
            "postgiro": "525240-8",
            "activity": "Grossistföretag inom musikinstrumentbranschen",
            "employees": 15,
            "capital": 90000,
            "key_personnel": [
                {
                    "name": "Holger Andréasson",
                    "position": "Verkst dir"
                }
            ],
            "establishment_year": 1958
        }
    }
}