{
    "original": "LIMA.VERKEN AB\n\nPnr 200 61\n\nMalmö 30, Box 301 00. Tel\n040-15 3170. Bankgiro 821-5733.\nPostgiro 635813-9\n\nVeiksamhet: Tillverkar\nkompressorer\n\nAktiekapital: 40 000\nVerkst dir: Erie Eninge\nEtableringsår: 1947.\n\nBESLAG &amp; METALL, AB\n\nPnr 57402\n\nVetlanda 2, Fack. Ekenässjön. Tel\n0383-300 3 3. Bankgiro 289-6215.\nPostgiro 146508-7\nVerksamhet: Tillverkar pressade o\ndragna artiklar av plåt,\nbyggnadsbeslag, dörrbeslag, lås o reglar.\nNy patenterad gäddsax\nAntal anställda: 20\nÅrsomsättning: 1500 000\nAktiekapital: 100 000\nVerkst dir: Hugo Carlsson\nEtableringsår: 1938.\n\nVEB\n\ntanklock, arbetslampor,\netiketteringsmaskiner sam\ntrågpackmaski-ner. Utför legotillverkning av\ndiverse finmekaniska produkter\nbaserade på pressgjutning o automats\nsvarvning\n\nVarunamn: Ledu, Waso\nAntal anställda: 210\nÅrsomsättning: 12 000 000\nAktiekapital: 1500 000\nVerkst dir: Roger Wallmark\nFörsäljn-chef: Nils Erie Borg\nProduktionschef: Ivar Ohlsson\nEtableringsår: 1943\nDotterbolag: Deutsche Waso GmbH,\nMedebach, Västtyskland, LEDU\nLamp Corporation, Norwalk, Conn\n06856, USA.\n\nVASSMOLDSA ÅNGSÅG, AB\n\nPnr 380 21\n\nVassmolösa, Box 46. Tel\n0480-32210. Bankgiro 65-5881. Postgiro\n92385. Tga Angsågen\nVerksamhet: Tillverkar sågade o\nhyvlade trävaror\nVarunamn: Vass\nAntal anställda: 40\nÅrsomsättning: 3 500000\nAktiekapital: 130000\nVerkst dir: Tage Petersson\nEtableringsår: 1904.\n\nVÄTÖ PRODUKTER AB\n\nse Novia Livsmedelsindustrier AB.\n\nVATTEN AB,\nVATTENAN-LÄGGNINGSFIRMAN\n\nPnr 116 47\n\nStockholm, Kvarng 3 B. Tel\n08-44 19 10, 44 40 02. Bankgiro\n44-6732. Postgiro 457878\nVerksamhet: Brunnsborrningar.\nPumpanläggningar\nAntal anställda: 14\nÅrsomsättning: 600 000\nAktiekapital: 50 000\nVerkst dir: Lennart Strid\nEtableringsår: 1929.\n\nBORÅS TEXTIL AB\n\nPnr 501 85\n\nBorås, Box 824. Kyrkängsg 6. Tel\n033-12 73 50. Postgiro 117657-7\nVerksamhet: Säljer konfektion,\ntextil o heminredning per\npost-order\n\nAntal anställda: 50\nÅrsomsättning: 23 000 000\nAktiekapital: 25 000\nVerkst dir. Bengt Höglund\nEtableringsår: 1953.\n\nBENTONE-VERKEN, AB\n\nPnr 341 00\n\nLjungby, Märta Ljungbergsv 60.\nBox 136. Tel 0372-125 50.\nBankgiro 672-6996. Postgiro 320010-2.\nTga Bentone. Telex 4659\nVerksamhet: Tillverkar o säljer\noljebrännare\nAntal anställda: 105\nÅrsomsättning: 28 000 000\nAktiekapital: 1500 000\nVerkst dir: Pabr Karl-Erick\nJohansson\nEtableringsår: 1954.\n\nSERVUS, AB\n\nPnr 17123\n\nSolna 1, Box 1197. Industriv 20.\nTel 08-27 27 80. Postgiro 54480-9.\nTelex 19967 SERVUS S. Tga\nServus\n\nVerksamhet: Säljer\nverktygsmaskiner o verktyg\nAktiekapital: 500 000\nVerkst dir: Erik A Eriksson\nEtableringsån 1921.\n\nLAMMHULTSMÖBLER, AB\n\nPnr 360 30\n\nLammhult, Box 13. Tel 0472-\n\n607 30\n\nVerksamhet: Tillverkar möbler\nAntal anställda: 85\nÅrsomsättning: 6 000 000\nAktiekapital: 52 200\nVerkst dir: Nils Erik Johansson\nEtableringsår: 1925.\n\nRYDELL, BYGGNADS AB PER\n\nPnr 114 46\n\nStockholm, Grev Tureg 10. Tel\n08-231145. Bankgiro 572-9496.\nPostgiro 458699-6\n\nVerksamhet: Anläggnings- o\nmudd-ringsarbeten\nAntal anställda: 25\nÅrsomsättning: 2 500 000\nAktiekapital: 180 000\nVerkst dir: Ing Per Rydell\nEtableringsår: 1952.\n\nRYDÉNS METALLINDUSTRI,\nAB\n\nPnr 330 30\n\nGnosjö, Hellmansg 18. Tel\n0370-91081, 91181\n\nVerksamhet: TUlverkar\nhandduks-hängare o skohorn samt utför\nauto-matsvarvning, automatisk\nytbehandling för nickel o krom m m\nAntal anstäUda: 10\nÅrsomsättning: 750 000\nAktiekapital: 50 000\nVerkst dir: Ing Sven Rydén\nEtableringsår 1928.\n\nERENIUS &amp; CO AB\n\nPnr 104 65\n\nStockholm 15, Götg 9. Box 15023.\nTel 08-43 14 43, 43 43 26. Bankgiro\n392-6144. Postgiro 607395. Tga\nEr en co ab\n\nVerksamhet: Import- o\nagenturverksamhet i textilbranschen\nAntal anställda: 4\nÅrsomsättning: 3 000 000\nAktiekapital: 30 000\nVerkst dir: Karl-Erik Berggren\nEtableringsår: 1960.\n\nDENTAL AB\n\nPnr 103 65\n\nStockholm 3, Box 3270. Adolf\nFredriks Kyrkog 9 A. Tel 08-2274 00.\nBankgiro 168-7565. Postgiro\n1644-4. Tga Dental\nVerksamhet: Säljer\ntandläkaruten-silier i parti\nAntal anställda: 162\nÅrsomsättning: 31200 000\nAktiekapital: 1500 000\nEtableringsår: 1903.",
    "structured": {
        "1": {
            "company_name": "LIMA.VERKEN AB",
            "pnr": "200 61",
            "address": "Malmö 30, Box 301 00",
            "phone_number": "040-15 3170",
            "bank_details": {
                "bankgiro": "821-5733",
                "postgiro": "635813-9"
            },
            "activity": "Tillverkar kompressorer",
            "capital": 40000,
            "key_personnel": [
                {
                    "name": "Erie Eninge",
                    "position": "Verkst dir"
                }
            ],
            "establishment_year": 1947
        },
        "2": {
            "company_name": "BESLAG & METALL, AB",
            "pnr": "57402",
            "address": "Vetlanda 2, Fack. Ekenässjön",
            "phone_number": "0383-300 3 3",
            "bank_details": {
                "bankgiro": "289-6215",
                "postgiro": "146508-7"
            },
            "activity": "Tillverkar pressade o dragna artiklar av plåt, byggnadsbeslag, dörrbeslag, lås o reglar",
            "employees": 20,
            "annual_turnover": 1500000,
            "capital": 100000,
            "key_personnel": [
                {
                    "name": "Hugo Carlsson",
                    "position": "Verkst dir"
                }
            ],
            "establishment_year": 1938
        },
        "3": {
            "company_name": "VEB",
            "activity": "Tillverkar tanklock, arbetslampor, etiketteringsmaskiner samt trågpackmaskiner. Utför legotillverkning av diverse finmekaniska produkter baserade på pressgjutning och automatsvarvning",
            "employees": 210,
            "annual_turnover": 12000000,
            "capital": 1500000,
            "key_personnel": [
                {
                    "name": "Roger Wallmark",
                    "position": "Verkst dir"
                },
                {
                    "name": "Nils Erie Borg",
                    "position": "Försäljn-chef"
                },
                {
                    "name": "Ivar Ohlsson",
                    "position": "Produktionschef"
                }
            ],
            "establishment_year": 1943,
            "daughter_company": "Deutsche Waso GmbH, Medebach, Västtyskland, LEDU Lamp Corporation, Norwalk, Conn 06856, USA"
        },
        "4": {
            "company_name": "VASSMOLDSA ÅNGSÅG, AB",
            "pnr": "380 21",
            "address": "Vassmolösa, Box 46",
            "phone_number": "0480-32210",
            "bank_details": {
                "bankgiro": "65-5881",
                "postgiro": "92385"
            },
            "activity": "Tillverkar sågade o hyvlade trävaror",
            "employees": 40,
            "annual_turnover": 3500000,
            "capital": 130000,
            "key_personnel": [
                {
                    "name": "Tage Petersson",
                    "position": "Verkst dir"
                }
            ],
            "establishment_year": 1904
        },
        "5": {
            "company_name": "VÄTÖ PRODUKTER AB",
            "description": "se Novia Livsmedelsindustrier AB."
        },
        "6": {
            "company_name": "VATTEN AB, VATTENAN-LÄGGNINGSFIRMAN",
            "pnr": "116 47",
            "address": "Stockholm, Kvarng 3 B",
            "phone_number": "08-44 19 10, 44 40 02",
            "bank_details": {
                "bankgiro": "44-6732",
                "postgiro": "457878"
            },
            "activity": "Brunnsborrningar. Pumpanläggningar",
            "employees": 14,
            "annual_turnover": 600000,
            "capital": 50000,
            "key_personnel": [
                {
                    "name": "Lennart Strid",
                    "position": "Verkst dir"
                }
            ],
            "establishment_year": 1929
        },
        "7": {
            "company_name": "BORÅS TEXTIL AB",
            "pnr": "501 85",
            "address": "Borås, Box 824, Kyrkängsg 6",
            "phone_number": "033-12 73 50",
            "postgiro": "117657-7",
            "activity": "Säljer konfektion, textil o heminredning per post-order",
            "employees": 50,
            "annual_turnover": 23000000,
            "capital": 25000,
            "key_personnel": [
                {
                    "name": "Bengt Höglund",
                    "position": "Verkst dir"
                }
            ],
            "establishment_year": 1953
        },
        "8": {
            "company_name": "BENTONE-VERKEN, AB",
            "pnr": "341 00",
            "address": "Ljungby, Märta Ljungbergsv 60, Box 136",
            "phone_number": "0372-125 50",
            "bank_details": {
                "bankgiro": "672-6996",
                "postgiro": "320010-2"
            },
            "activity": "Tillverkar o säljer oljebrännare",
            "employees": 105,
            "annual_turnover": 28000000,
            "capital": 1500000,
            "key_personnel": [
                {
                    "name": "Pabr Karl-Erick Johansson",
                    "position": "Verkst dir"
                }
            ],
            "establishment_year": 1954
        },
        "9": {
            "company_name": "SERVUS, AB",
            "pnr": "17123",
            "address": "Solna 1, Box 1197, Industriv 20",
            "phone_number": "08-27 27 80",
            "postgiro": "54480-9",
            "telex": "19967 SERVUS S",
            "activity": "Säljer verktygsmaskiner o verktyg",
            "capital": 500000,
            "key_personnel": [
                {
                    "name": "Erik A Eriksson",
                    "position": "Verkst dir"
                }
            ],
            "establishment_year": 1921
        },
        "10": {
            "company_name": "LAMMHULTSMÖBLER, AB",
            "pnr": "360 30",
            "address": "Lammhult, Box 13",
            "phone_number": "0472-607 30",
            "activity": "Tillverkar möbler",
            "employees": 85,
            "annual_turnover": 6000000,
            "capital": 52200,
            "key_personnel": [
                {
                    "name": "Nils Erik Johansson",
                    "position": "Verkst dir"
                }
            ],
            "establishment_year": 1925
        },
        "11": {
            "company_name": "RYDELL, BYGGNADS AB PER",
            "pnr": "114 46",
            "address": "Stockholm, Grev Tureg 10",
            "phone_number": "08-231145",
            "bankgiro": "572-9496",
            "postgiro": "458699-6",
            "activity": "Anläggnings- o mudd-ringsarbeten",
            "employees": 25,
            "annual_turnover": 2500000,
            "capital": 180000,
            "key_personnel": [
                {
                    "name": "Ing Per Rydell",
                    "position": "Verkst dir"
                }
            ],
            "establishment_year": 1952
        },
        "12": {
            "company_name": "RYDÉNS METALLINDUSTRI, AB",
            "pnr": "330 30",
            "address": "Gnosjö, Hellmansg 18",
            "phone_number": "0370-91081, 91181",
            "activity": "TUlverkar handduks-hängare o skohorn samt utför auto-matsvarvning, automatisk ytbehandling för nickel o krom m m",
            "employees": 10,
            "annual_turnover": 750000,
            "capital": 50000,
            "key_personnel": [
                {
                    "name": "Ing Sven Rydén",
                    "position": "Verkst dir"
                }
            ],
            "establishment_year": 1928
        },
        "13": {
            "company_name": "ERENIUS & CO AB",
            "pnr": "104 65",
            "address": "Stockholm 15, Götg 9, Box 15023",
            "phone_number": "08-43 14 43, 43 43 26",
            "bankgiro": "392-6144",
            "postgiro": "607395",
            "telex": "Er en co ab",
            "activity": "Import- o agenturverksamhet i textilbranschen",
            "employees": 4,
            "annual_turnover": 3000000,
            "capital": 30000,
            "key_personnel": [
                {
                    "name": "Karl-Erik Berggren",
                    "position": "Verkst dir"
                }
            ],
            "establishment_year": 1960
        },
        "14": {
            "company_name": "DENTAL AB",
            "pnr": "103 65",
            "address": "Stockholm 3, Box 3270, Adolf Fredriks Kyrkog 9 A",
            "phone_number": "08-2274 00",
            "bankgiro": "168-7565",
            "postgiro": "1644-4",
            "telex": "Dental",
            "activity": "Säljer tandläkarutensilier i parti",
            "employees": 162,
            "annual_turnover": 31200000,
            "capital": 1500000,
            "establishment_year": 1903
        }
    }
}