{
    "original": "WIBERG AB, TAGE\n\nPnr 401 25\n\nGöteborg 1, N Hamng 18. Box 312.\nTel 031-17 44 60. Bankgiro\n847-8679. Postgiro 40377-4. Tga Wiber.\nTelex 2337\n\nVerksamhet: Importerar stål,\nindustriförnödenheter, fartygsutrustningar m m. Exporterar\nstålmanufaktur\n\nVarunamn: Tawi\nAntal anstäUda: 29\nÅrsomsättning: 50 000 000\nAktiekapital: 400 000\nStyrelse: Adv Ake Eckerstein\n(ordf), dir Erik Dunér, dir Bernt\nEmblad\n\nVerkst dir: Bernt Emblad\nEtableringsår: 1921.\n\nMEPLAKO, AB\n\nPnr 63102\n\nEskilstuna 1, Box 62. Smedjeg 14.\nTel 016-124210. Bankgiro\n403-6810. Postgiro 22234-9\nVeiksamhet: Tillverkar hushålls- o\nindustriartiklar i alla härdplaster\ninkl glasfiberarmerad polyester\nsamt tillverkar kokillgjutgods i\nlättmetall\n\nAvdelningskontor: Eskilstuna,\nFarmv 28. Tel 016-209 70\nAntal anställda: 11\nAktiekapital: 10 000\nVerkst dir: Rolf Larsson\nEtableringsår: 1970.\n\nARESIKS AGENTURER\n\nPnr 114 30\n\nStockholm, Eriksbergsg 14. Tel\n08-118914. Bankgiro 174-0224.\nPostgiro 3146-8\n\nVerksamhet: Säljer Mischke\nkabelöglor o kabelrör\nInnehavare o chef: Fru Märtha\nBroddman-Aresik\nEtableringsår: 1956.\n\nSOBERPLAST, AB\n\nPnr 434 00\n\nKungsbacka, Kungsmässan.\nBorg-mästarg 5. Tel 0300-125 70.\nBankgiro 89-4327\n\nVerksamhet: Agent i akrylplast\nAktiekapital: 10 000\nVerkst dir: O Börjesson\nEtableringsår: 1967.\n\nmalmsjö &amp; co, c l\n\nPnr 411 14\n\nGöteborg, S Hamng 29. Tel\n031-13 36 25, 13 35 27. Bankgiro\n84-7751. Postgiro 41920\nVerksamhet: Säljer o reparerar ur\no nautiska instrument\nAntal anställda: 11\nÅrsomsättning: 1100 000\nChef: Anders Hallgren\nEtableringsår: 1841.\n\nFINESS PAPPERS AB\n\nPnr 171 20\n\nSolna 1, Svetsarv 24. Fack. Tel\n08-98 17 80\n\nVerksamhet: Försäljning av\nmjuk-pappersprodukter för Klippan,\nLångasjönäs, Nyboholm o Munksjö\nVerkst dir: Nils Lundgren.\n\nFINGO, HANDELSFIRMAN\n\nPnr 413 02\n\nGöteborg, Skolg 34. Tel\n031-113215. Postgiro 621959-6\nVerksamhet: Tillverkar väg- o\ntrafikskyltar, avstängningslinor\n(flaggspel), reflexplåtar. Säljer\nblinkfyrar för väg- o gatuarbeten\nAntal anställda: 8\nÄgare o chef: Disp Alv M Söyland\nEtableringsår: 1953.\n\nKARLSON INSTRUMENT AB, A\n\nPnr 104 60\n\nStockholm 20, Fack. Huddingev\n103 B, Johanneshov. Tel\n08-39 0100. Bankgiro 353-4443.\nPostgiro 52820-8. Tga Remind.\nTelex 1562 REMIND S\nVerksamhet: Import o försäljning\nav utrustningar för\nmaterialprovning, processkontroll,\nvätskekroma-tografi, elektroniska, mekaniska o\noptiska komponenter för industri,\nforskning o utbildning, elektroniska\nmätmaskiner,\npositioneringsut-rustningar\nAntal anställda: 9\nAktiekapital: 100 000\nStyrelse: Dr Ivar Friman (ordf),\ndir Olaf Tösen, försäljn-chef Hans\nCarlsson, ing Stig Lundmark\nEtableringsår: 1966.\n\nCARLSSON\nSNICKERIFABRIK AB, A\n\nPnr 46100\n\nTrollhättan, Swedenborgsg 7. Tel\n0520-104 3 6. Bankgiro 892-4847.\nPostgiro 88053-4\n\nVerksamhet: Tillverkar bildetaljer\ni trä, servicesnickerier\nAntal anställda: 8\nÅrsomsättning: 1000 000\nAktiekapital: 15 000\nVerkst din Artur Carlsson\nEtableringsår: 1933.\n\nGEFLE MOTORFABRIK, AB\n\nPnr 801 03 Gävle 1\nSödra Valbo, Sveden. Box 163,\nGävle 1. Tel 026-1314 00.\nBankgiro 237-1227. Postgiro 72842-8\nVerksamhet: Tillverkar alla slags\nbilkarosserier, brandsläckare o\nräddningsbilar. Utför billackeringar\nsamt mek konstruktionsarbeten\nAntal anställda: 100\nÅrsomsättning: 5 000 000\nAktiekapital: 50000\nStyrelse: Disp Einar Karlsson\n(ordf), fabr Ake Carlsson\nVerkst dir: Pabr Ake Carlsson\nEtableringsår: 1908.\n\nBORÅS ETIKETTVÄVERI, AB\n\nPnr 510 47\n\nFristad. Tel 033-605 19\nVerksamhet: Tillverkar vävda\netiketter\n\nAntal anställda: 15\nAktiekapital: 75 000\nVerkst dir: Sten Arvidson\nEtableringsår: 1949.\n\nBORÅS\nHANDVÄVNADS-INDUSTRI, AB\n\nPnr 500 06\n\nBorås 6, Box 66035. Bockasjög 13.\nTel 033-11 3436. Bankgiro\n360-8148. Postgiro 140846-7\nVerksamhet: Tillverkar handvävda\nmöbeltyger\nAntal anställda: 20\nÅrsomsättning: 900 000\nAktiekapital: 25 000\nVerkst dir: Enar Sandblom\nEtableringsår: 1935.\n\nBORÅS\nJACQUARD-VÄFVERI, AB\n\nPnr 501 04\n\nBorås 1, Göteborgsv 19. Box 220.\nTel 033-10 00 90. Bankgiro 84-3426.\nPostgiro 20633-4. Tga Jacquard\nVerksamhet: Tillverkar möbel- o\ndraperityger\nAntal anställda: 50\nÅrsomsättning: 3 500 000\nAktiekapital: 450 000\nStyrelse: Dir Sten Ahlberg, adv Bo\nRedgard, dir B A Wallgren\nVerkst dir: B A Wallgren\nEtableringsår: 1913.\n\ndahm ab, e\n\nPnr 21614\n\nMalmö, Högerudsg 55. Tel\n040-743 88\n\nVerksamhet: Tillverkar tejp o\nfotohörn\n\nAntal anställda: 20\nAktiekapital: 40 000\nVerkst dir: Fru Ingegerd Dahm\nEtableringsår: 1948.\n\ndamita-fabriken,\ngummi ab\n\nPnr 310 36\n\nSennan, Box 95. Tel 035-66140.\nBankgiro 33-9055. Postgiro\n350535. Tga Damita\nVerksamhet: Tillverkar\nstänkskydd samt hjulbeläggningar\nAntal anställda: 11\nÅrsomsättning: 700 000\nAktiekapital: 15 000\nVerkst dir.-Fabr Knut A Sintring\nEtableringsår: 1956.",
    "structured": {
        "1": {
            "company_name": "WIBERG AB",
            "address": "N Hamng 18. Box 312, Göteborg 1",
            "phone_number": "031-17 44 60",
            "bank_details": {
                "bankgiro": "847-8679",
                "postgiro": "40377-4"
            },
            "activity": "Importerar stål, industriförnödenheter, fartygsutrustningar m m. Exporterar stålmanufaktur",
            "employees": 29,
            "annual_turnover": 50000000,
            "capital": 400000,
            "key_personnel": [
                {
                    "name": "Adv Ake Eckerstein",
                    "position": "ordf"
                },
                {
                    "name": "Erik Dunér",
                    "position": "dir"
                },
                {
                    "name": "Bernt Emblad",
                    "position": "dir, Verkst dir"
                }
            ],
            "establishment_year": 1921
        },
        "2": {
            "company_name": "MEPLAKO, AB",
            "address": "Box 62, Eskilstuna 1, Smedjeg 14",
            "phone_number": "016-124210",
            "bank_details": {
                "bankgiro": "403-6810",
                "postgiro": "22234-9"
            },
            "activity": "Tillverkar hushålls- o industriartiklar i härdplaster samt kokillgjutgods i lättmetall",
            "employees": 11,
            "capital": 10000,
            "key_personnel": [
                {
                    "name": "Rolf Larsson",
                    "position": "Verkst dir"
                }
            ],
            "establishment_year": 1970
        },
        "3": {
            "company_name": "ARESIKS AGENTURER",
            "address": "Eriksbergsg 14, Stockholm",
            "phone_number": "08-118914",
            "bank_details": {
                "bankgiro": "174-0224",
                "postgiro": "3146-8"
            },
            "activity": "Säljer Mischke kabelöglor o kabelrör",
            "key_personnel": [
                {
                    "name": "Fru Märtha Broddman-Aresik",
                    "position": "Innehavare o chef"
                }
            ],
            "establishment_year": 1956
        },
        "4": {
            "company_name": "SOBERPLAST, AB",
            "address": "Kungsmässan. Borg-mästarg 5, Kungsbacka",
            "phone_number": "0300-125 70",
            "bank_details": {
                "bankgiro": "89-4327"
            },
            "activity": "Agent i akrylplast",
            "capital": 10000,
            "key_personnel": [
                {
                    "name": "O Börjesson",
                    "position": "Verkst dir"
                }
            ],
            "establishment_year": 1967
        },
        "5": {
            "company_name": "malmsjö & co, c l",
            "address": "S Hamng 29, Göteborg",
            "phone_number": "031-13 36 25, 13 35 27",
            "bank_details": {
                "bankgiro": "84-7751",
                "postgiro": "41920"
            },
            "activity": "Säljer o reparerar ur o nautiska instrument",
            "employees": 11,
            "annual_turnover": 1100000,
            "key_personnel": [
                {
                    "name": "Anders Hallgren",
                    "position": "Chef"
                }
            ],
            "establishment_year": 1841
        },
        "6": {
            "company_name": "FINESS PAPPERS AB",
            "address": "Svetsarv 24, Solna 1",
            "phone_number": "08-98 17 80",
            "activity": "Försäljning av mjuk-pappersprodukter för Klippan, Långasjönäs, Nyboholm o Munksjö",
            "key_personnel": [
                {
                    "name": "Nils Lundgren",
                    "position": "Verkst dir"
                }
            ]
        },
        "7": {
            "company_name": "FINGO, HANDELSFIRMAN",
            "address": "Skolg 34, Göteborg",
            "phone_number": "031-113215",
            "bank_details": {
                "postgiro": "621959-6"
            },
            "activity": "Tillverkar väg- o trafikskyltar, avstängningslinor (flaggspel), reflexplåtar. Säljer blinkfyrar för väg- o gatuarbeten",
            "employees": 8,
            "key_personnel": [
                {
                    "name": "Disp Alv M Söyland",
                    "position": "Ägare o chef"
                }
            ],
            "establishment_year": 1953
        },
        "8": {
            "company_name": "KARLSON INSTRUMENT AB, A",
            "address": "Fack. Huddingev 103 B, Johanneshov, Stockholm 20",
            "phone_number": "08-39 0100",
            "bank_details": {
                "bankgiro": "353-4443",
                "postgiro": "52820-8"
            },
            "activity": "Import o försäljning av utrustningar för materialprovning, processkontroll, vätskekromatografi, elektroniska, mekaniska o optiska komponenter för industri, forskning o utbildning, elektroniska mätmaskiner, positioneringsutrustningar",
            "employees": 9,
            "capital": 100000,
            "key_personnel": [
                {
                    "name": "Dr Ivar Friman",
                    "position": "Styrelse ordförande"
                },
                {
                    "name": "Olaf Tösen",
                    "position": "dir"
                },
                {
                    "name": "Hans Carlsson",
                    "position": "försälj-chef"
                },
                {
                    "name": "Stig Lundmark",
                    "position": "ing"
                }
            ],
            "establishment_year": 1966
        },
        "9": {
            "company_name": "CARLSSON SNICKERIFABRIK AB, A",
            "address": "Swedenborgsg 7, Trollhättan",
            "phone_number": "0520-104 3 6",
            "bank_details": {
                "bankgiro": "892-4847",
                "postgiro": "88053-4"
            },
            "activity": "Tillverkar bildetaljer i trä, servicesnickerier",
            "employees": 8,
            "annual_turnover": 1000000,
            "capital": 15000,
            "key_personnel": [
                {
                    "name": "Artur Carlsson",
                    "position": "Verkst dir"
                }
            ],
            "establishment_year": 1933
        },
        "10": {
            "company_name": "GEFLE MOTORFABRIK, AB",
            "address": "Box 163, Södra Valbo, Sveden, Gävle 1",
            "phone_number": "026-1314 00",
            "bank_details": {
                "bankgiro": "237-1227",
                "postgiro": "72842-8"
            },
            "activity": "Tillverkar alla slags bilkarosserier, brandsläckare o räddningsbilar. Utför billackeringar samt mek konstruktionsarbeten",
            "employees": 100,
            "annual_turnover": 5000000,
            "capital": 50000,
            "key_personnel": [
                {
                    "name": "Einar Karlsson",
                    "position": "Styrelse ordförande"
                },
                {
                    "name": "Ake Carlsson",
                    "position": "fabrikör, Verkst dir"
                }
            ],
            "establishment_year": 1908
        },
        "11": {
            "company_name": "BORÅS ETIKETTVÄVERI, AB",
            "address": "Fristad",
            "phone_number": "033-605 19",
            "activity": "Tillverkar vävda etiketter",
            "employees": 15,
            "capital": 75000,
            "key_personnel": [
                {
                    "name": "Sten Arvidson",
                    "position": "Verkst dir"
                }
            ],
            "establishment_year": 1949
        },
        "12": {
            "company_name": "BORÅS HANDVÄVNADS-INDUSTRI, AB",
            "address": "Box 66035, Bockasjög 13, Borås 6",
            "phone_number": "033-11 3436",
            "bank_details": {
                "bankgiro": "360-8148",
                "postgiro": "140846-7"
            },
            "activity": "Tillverkar handvävda möbeltyger",
            "employees": 20,
            "annual_turnover": 900000,
            "capital": 25000,
            "key_personnel": [
                {
                    "name": "Enar Sandblom",
                    "position": "Verkst dir"
                }
            ],
            "establishment_year": 1935
        },
        "13": {
            "company_name": "BORÅS JACQUARD-VÄFVERI, AB",
            "address": "Göteborgsv 19, Borås 1",
            "phone_number": "033-10 00 90",
            "bank_details": {
                "bankgiro": "84-3426",
                "postgiro": "20633-4"
            },
            "activity": "Tillverkar möbel- o draperityger",
            "employees": 50,
            "annual_turnover": 3500000,
            "capital": 450000,
            "key_personnel": [
                {
                    "name": "Sten Ahlberg",
                    "position": "Styrelse dir"
                },
                {
                    "name": "Bo Redgard",
                    "position": "adv"
                },
                {
                    "name": "B A Wallgren",
                    "position": "Verkst dir"
                }
            ],
            "establishment_year": 1913
        },
        "14": {
            "company_name": "dahm ab, e",
            "address": "Högerudsg 55, Malmö",
            "phone_number": "040-743 88",
            "activity": "Tillverkar tejp o fotohörn",
            "employees": 20,
            "capital": 40000,
            "key_personnel": [
                {
                    "name": "Fru Ingegerd Dahm",
                    "position": "Verkst dir"
                }
            ],
            "establishment_year": 1948
        },
        "15": {
            "company_name": "damita-fabriken, gummi ab",
            "address": "Box 95, Sennan",
            "phone_number": "035-66140",
            "bank_details": {
                "bankgiro": "33-9055",
                "postgiro": "350535"
            },
            "activity": "Tillverkar stänkskydd samt hjulbeläggningar",
            "employees": 11,
            "annual_turnover": 700000,
            "capital": 15000,
            "key_personnel": [
                {
                    "name": "Fabr Knut A Sintring",
                    "position": "Verkst dir"
                }
            ],
            "establishment_year": 1956
        }
    }
}