{
    "original": "TERLING AB, GUSTAF\n\nPnr 411 21\n\nGöteborg, Stora Badhusg 18. Tel\n031-17 04 40. Bankgiro 511-6397.\nPostgiro 12360-4. Tga Terlingab.\nTelex 2513 TERLING S\nVerksamhet: Hydrauliska\nkomponenter, projektering o leverans av\nkompletta anläggningar. Pumpar\nför alla ändamål samt centrifuger\no turbiner för sjöfart o industri.\nElektr apparater o maskiner för\nindustri o sjöfart\n\nAvdelningskontor: 121 21\nJohannes-hov, Skulptörv 30-32. Tel\n08-48 8010, 48 23 00\nVarunamn: AEG-Kanis, Crompton\nParkinson, Galdabini, Hawe,\nLeistritz, Neidig, Sharples,\nTurol-la. Worthington, S.A.I.\nAntal anställda: 35\nÅrsomsättning: 18 000 000\nAktiekapital: 75 000\nVerkst dir. Gustaf Terling\nEtableringsår. 1926\nOmbildat till aktiebolag 1937.\n\nTERMA KONSULTERANDE\nVVS-BYRÄ AB\n\nPnr 421 76\n\nVästra Frölunda, Eckrag 19. Tel\n031-29 47 03, 29 47 06. Bankgiro\n84-8603. Postgiro 524985-9\nVerksamhet: Utför konstruktioner,\nkontroller o besiktningar\nAntal anställda: 7\nÅrsomsättning: 225 000\nAktiekapital: 12 000\nVerkst dir: Lars Lindblom\nEtableringsår: 1965.\n\nGETE MOTORDELAR AB\n\nPnr 102 61\n\nStockholm 4, Högbergs g 30 A. Box\n4029. Tel 08-44 03 90. Bankgiro\n56-9796. Postgiro 509750. Tga\nGetekolv\n\nVerksamhet: Grossist i\nmotorreserv-delar\n\nAntal anställda: 18\nVerkst dir: Holger Wallén\nEtableringsår: 1955.\n\nGETINGE MEKANISKA\nVERKSTADS AB\n\nPnr 31044\n\nGetinge, Box 128. Tel 035-544 20.\nBankgiro 43-1402. Postgiro 22622.\nTga Getinge verken, Halmstad.\nTelex 3537 GTEVERK S\nVerksamhet: Tillverkar o säljer\nsjukhusutrustning: steriliserings-,\ndesinfektions- o\nrengöringsapparater samt badkarslyftar.\nIndustriapparater: konserveringsautoklaver,\nkokare, ångpannor o värmetekniska\napparater. Storköksutrustningar:\nkokapparater för el- o ångdrift,\nstekapparater,\nvarmhållningsappa-rater o potatisskalare\nAntal anställda: 198\nAktiekapital: 60 000\nStyrelse: Dir Hans Werthén, dir\nGösta Bystedt, dir Folke Heibert\nVerkst dir: Folke Heibert\nEtableringsår 1904.\n\nGLISSA, AB\n\nPnr 126 53\n\nHägersten, Instrumentv 21. Tel 08-\n\n19 62 60. Tga Glissa\nVerksamhet: Tillverkar o säljer\nsjälvsmörjande glidlager o\npulver-pressade detaljer\n\nVarunamn: GUssa, Glissec, GUbro\nAntal anstäUda: 40\nÅrsomsättning: 2 700 000\nAktiekapital: 200 000\nStyrelse: Dir Per-Olof Olsson\n(ordf), dir Josef Heuberger, fru\nMarianne Heuberger, civing Gunnar\nKoch\n\nVerkst dir: Fil dr Josef Heuberger\nEtableringsår: 1922\nOmbildat till aktiebolag 1939.\n\nGLYKOCID, AB\n\nPnr 592 00\n\nVadstena. Tel 0143-114 70.\nBankgiro 173-8053. Postgiro 458696-2.\nTga Glykocid\n\nVerksamhet: Tillverkar o säljer\nprodukter för allmän rengöring,\ngolvvård, tvätt, handdiskning,\nmaskin-diskning, handrengöring,\ndesinfektion, luktreglering,\nkalkupplösning, rostupplösning,\nfärgborttag-ning, avfettning, ytbehandlingsbad,\nskärande o borrade arbeten samt\napparaturer för ångavfettning,\nsprutavfettning o\ndoseringsapparaturer för luktreglering,\nhandrengöring, maskindiskning o\nhanddiskning. Specialitet: Miljövård\nVarunamn: Aromistat, Glykocid,\nGlykozo Primower, Renostat,\nSkogs-Dunge, Spraydoff\nAntal anstäUda: 60\nÅrsomsättning: 8 000 000\nAktiekapital: 450000\nVerkst dir: Ing Gunnar Jegrelius\nTekn chef: Ing Bengt Lundberg\nKontorschef: Fru Rut Jegrelius\nEkonomichef: Civilekonom Nils\nLindeblad\nEtableringsår: 1948\nOmbildat till aktiebolag 1953.\n\nGLOSSNER GLAS AB\nKONSTGLASVERKSTÄDERNA\n\nPnr 116 31\n\nStockholm, Renstiernas Gata 12.\nTel 08-44 80 90, 44 89 24. Bankgiro\n73-2351. Postgiro 151508. Tga\nGloessnerdecor\n\nVerksamhet: Motivblästrar dörrglas,\nträ o metall. Böjer i storugn. Blyar\nAktiekapital: 50 000\nVerkst dir: Fra Margit Glössner\nEtableringsår: 1939.\n\nGEMAS DAMKONFEKTION, AB\n\nPnr 502 65\n\nBorås, Magasinsg 16. Tel\n033-1184 96. Bankgiro 843-4 995.\nPostgiro 466425-6\n\nVerksamhet: Tillverkar\ndamklänningar\n\nAntal anställda: 14\nAktiekapital: 23 000\nVerkst dir: Iwan Widahl\nEtableringsår: 1951.\n\nINETRA, IMPORT AB\n\nPnr 11140\n\nStockholm. Tegnérg 29. Tel\n08-23 35 00. Bankgiro 73-0467.\nPostgiro 258068\n\nVerksamhet: Radio- o\nTV-kompo-nenter, antenner, högtalare o d\nen gros\n\nAntal anställda: 6\nÅrsomsättning: 1000 000\nAktiekapital: 10 000\nVerkst dir: Arvid Orrestad\nEtableringsår: 1947\nOmbildat till aktiebolag 1951.\n\nIN FI S INTERNATIONELL\nFARTYG &amp; INDUSTRISERVICE\nAB\n\nPir 423 00\n\nTorslanda, Ostergärde. Tel\n031-231654, 9254 72. Bankgiro\n225-3250. Postgiro 421196-7\nVerksamhet: Installation o\nreparation av fartygsmaskiner.\nSpecialitet: pielstickmaskiner.\nMaskin-o rörinstallationer samt\nreparationer i industrianläggningar.\nVerkstad för tillverkning av mindre rör-,\nplåt- o stålkonstruktioner.\nSpecialverkstad för rekonditionering av\ndieselmotorers\ninsprutningsutrust-ning samt säkerhets- o\navstängningsventiler för industrier\nAntal anställda: 27\nÅrsomsättning: 1 800 000\nAktiekapital: 33 000\nVerkst dir: Sverre Rom Gundersen\nEtableringsår. 1968.\n\nST IN SON AB\n\nPnr 26122\n\nLandskrona, Enock Thulins v. Tel\n0418-163 70. Bankgiro 66-0122.\nPostgiro 324362. Tga Stinson.\nTelex 72438 STINSON S\nVerksamhet: Tillverkar\nfritidskläder o strumpor\nAntal anstäUda: 200\nÅrsomsättning: 12 000 000\nAktiekapital: 100 000\nVerkst dir: Gert Skanert\nEtableringsår: 1946.\n\nCYB\n\nCYBERNETICS\nINTERNATIONAL AB\n\nPnr 182 11\n\nDanderyd 1, Mysingsv 5. Box 48.\nTel 08-753 03 00. Bankgiro 17-1281.\nPostgiro 674 628. Tga Cybernetics,\nStockholm\n\nVerksamhet: System- o\nprogramutveckling\nAntal anställda: 42\nÅrsomsättning: 3 500 000\nAktiekapital: 10 000\nVerkst dir: Lennart Schwieler\nEtableringsår: 1966.\n\nNOP| (SWEDEN) AB\n\nPnr 25012\n\nHelsingborg 12, Muskötg 19. Box\n12060. Tel 042-12 76 25. Bankgiro\n863-7787. Postgiro 393984-0\nVerksamhet: Säljer Nopi tejp,\ntejpmaskiner samt Hafnia plåster\nAktiekapital: 50 000\nVerkst dir: Jan Svedberg\nEtableringsår: 1950.\n\nNOP| ETIKETTER\n\nRagnar Sahlin AB\n\nPnr 25012\n\nHelsingborg 12, Box 12036.\nMuskötg 27, Ind lok A, V Berga. Tel\n042-18 04 80. Bankgiro 863-4925.\nPostgiro 371109-0. Telex 72298\nVerksamhet: Tillverkar\nsjälvhäf-tande etiketter för reklam o\npris-märkningsändamål av pappers-,\nplast-, metallfolie- o\nsidenmaterial. Säljer självhäftande etiketter,\ntilltryckningsmaskiner för etiketter\no etiketteringsanläggningar, hel- o\nhalvautomatiska dispensers för\netiketter\n\nAntal anställda: 60\nAktiekapital: 200 000\nStyrelse: Adv Bengt Holmberg\n(ordf), adv Bengt-Hugo Siwe, H J\nJörgensen\n\nVerkst dir: Erik Brehm Nielsen\nEtableringsår: 1952.\n\nHOLSBY METALLFABRIK, AB\n\nPnr 570 15\n\nHolsbybrunn. Tel 0383-501 85.\nBankgiro 289-7718. Postgiro\n132554-7\n\nVerksamhet: Utför varmpressning\nAntal anställda: 40\nÅrsomsättning: 3 500 000\nAktiekapital: 180 000\nVerkst dir. Curt Arvidsson\nEtableringsår 1937.\n\nWELLTEC AB\n\nPnr 662 00\n\nAmål, Fabriksg 5. Box 130. Tel\n0532-140 20. Bankgiro 345-1770.\n\nPostgiro 22620\n\nVerksamhet: Svetsning o sömnad\nav armerad o oarmerad PVC\nAntal anställda: 7\nÅrsomsättning: 500 000\nAktiekapital: 30000\nVerkstdir: Olov Lindahl\nEtableringsår: 1967.\n\nWEHLOU KONSULTATION AB,\nHERBERT\n\nPnr 211 34\n\nMalmö. Söderg 12. Tel 040-747 50.\nBankgiro 260-7380. Postgiro\n630159-2. Tga Wehlou\nVerksamhet: Konsulter inom\nföretagsledning, marknadsföring,\nsälj-utbildning, redovisning, AR\nAntal anställda: 8\nÅrsomsättning: 600 000\nAktiekapital: 20 000\nVerkst dir: Civilekonom Herbert\nWehlou\n\nEtableringsår: 1963.",
    "structured": {
        "1": {
            "company_name": "TERLING AB",
            "pnr": "411 21",
            "address": "Göteborg, Stora Badhusg 18",
            "phone_number": "031-17 04 40",
            "bank_details": {
                "bankgiro": "511-6397",
                "postgiro": "12360-4"
            },
            "activity": "Hydrauliska komponenter, projektering o leverans av kompletta anläggningar. Pumpar för alla ändamål samt centrifuger o turbiner för sjöfart o industri. Elektr apparater o maskiner för industri o sjöfart",
            "employees": 35,
            "annual_turnover": 18000000,
            "capital": 75000,
            "key_personnel": [
                {
                    "name": "Gustaf Terling",
                    "position": "Verkst dir"
                }
            ],
            "establishment_year": 1926
        },
        "2": {
            "company_name": "TERMA KONSULTERANDE VVS-BYRÄ AB",
            "pnr": "421 76",
            "address": "Västra Frölunda, Eckrag 19",
            "phone_number": "031-29 47 03, 29 47 06",
            "bank_details": {
                "bankgiro": "84-8603",
                "postgiro": "524985-9"
            },
            "activity": "Utför konstruktioner, kontroller o besiktningar",
            "employees": 7,
            "annual_turnover": 225000,
            "capital": 12000,
            "key_personnel": [
                {
                    "name": "Lars Lindblom",
                    "position": "Verkst dir"
                }
            ],
            "establishment_year": 1965
        },
        "3": {
            "company_name": "GETE MOTORDELAR AB",
            "pnr": "102 61",
            "address": "Stockholm 4, Högbergs g 30 A",
            "phone_number": "08-44 03 90",
            "bank_details": {
                "bankgiro": "56-9796",
                "postgiro": "509750"
            },
            "activity": "Grossist i motorreserv-delar",
            "employees": 18,
            "capital": null,
            "key_personnel": [
                {
                    "name": "Holger Wallén",
                    "position": "Verkst dir"
                }
            ],
            "establishment_year": 1955
        },
        "4": {
            "company_name": "GETINGE MEKANISKA VERKSTADS AB",
            "pnr": "31044",
            "address": "Getinge, Box 128",
            "phone_number": "035-544 20",
            "bank_details": {
                "bankgiro": "43-1402",
                "postgiro": "22622"
            },
            "activity": "Tillverkar o säljer sjukhusutrustning: steriliserings-, desinfektions- o rengöringsapparater samt badkarslyftar. Industriapparater: konserveringsautoklaver, kokare, ångpannor o värmetekniska apparater. Storköksutrustningar: kokapparater för el- o ångdrift, stekapparater, varmhållningsappa-rater o potatisskalare",
            "employees": 198,
            "capital": 60000,
            "key_personnel": [
                {
                    "name": "Folke Heibert",
                    "position": "Styrelse"
                }
            ],
            "establishment_year": 1904
        },
        "5": {
            "company_name": "GLISSA, AB",
            "pnr": "126 53",
            "address": "Hägersten, Instrumentv 21",
            "phone_number": "08-19 62 60",
            "activity": "Tillverkar o säljer självsmörjande glidlager o pulver-pressade detaljer",
            "employees": 40,
            "annual_turnover": 2700000,
            "capital": 200000,
            "key_personnel": [
                {
                    "name": "Josef Heuberger",
                    "position": "Verkst dir"
                }
            ],
            "establishment_year": 1922
        },
        "6": {
            "company_name": "GLYKOCID, AB",
            "pnr": "592 00",
            "address": "Vadstena",
            "phone_number": "0143-114 70",
            "bank_details": {
                "bankgiro": "173-8053",
                "postgiro": "458696-2"
            },
            "activity": "Tillverkar o säljer produkter för allmän rengöring, golvvård, tvätt, handdiskning, maskin-diskning, handrengöring, desinfektion, luktreglering, kalkupplösning, rostupplösning, färgborttag-ning, avfettning, ytbehandlingsbad, skärande o borrade arbeten samt apparaturer för ångavfettning, sprutavfettning o doseringsapparaturer för luktreglering, handrengöring, maskindiskning o handdiskning. Specialitet: Miljövård",
            "employees": 60,
            "annual_turnover": 8000000,
            "capital": 450000,
            "key_personnel": [
                {
                    "name": "Ing Gunnar Jegrelius",
                    "position": "Verkst dir"
                },
                {
                    "name": "Ing Bengt Lundberg",
                    "position": "Tekn chef"
                },
                {
                    "name": "Civilekonom Nils Lindeblad",
                    "position": "Ekonomichef"
                }
            ],
            "establishment_year": 1948
        },
        "7": {
            "company_name": "GLOSSNER GLAS AB KONSTGLASVERKSTÄDERNA",
            "pnr": "116 31",
            "address": "Stockholm, Renstiernas Gata 12",
            "phone_number": "08-44 80 90, 44 89 24",
            "bank_details": {
                "bankgiro": "73-2351",
                "postgiro": "151508"
            },
            "activity": "Motivblästrar dörrglas, trä o metall. Böjer i storugn. Blyar",
            "capital": 50000,
            "key_personnel": [
                {
                    "name": "Fra Margit Glössner",
                    "position": "Verkst dir"
                }
            ],
            "establishment_year": 1939
        },
        "8": {
            "company_name": "GEMAS DAMKONFEKTION, AB",
            "pnr": "502 65",
            "address": "Borås, Magasinsg 16",
            "phone_number": "033-1184 96",
            "bank_details": {
                "bankgiro": "843-4 995",
                "postgiro": "466425-6"
            },
            "activity": "Tillverkar damklänningar",
            "employees": 14,
            "capital": 23000,
            "key_personnel": [
                {
                    "name": "Iwan Widahl",
                    "position": "Verkst dir"
                }
            ],
            "establishment_year": 1951
        },
        "9": {
            "company_name": "INETRA, IMPORT AB",
            "pnr": "11140",
            "address": "Stockholm, Tegnérg 29",
            "phone_number": "08-23 35 00",
            "bank_details": {
                "bankgiro": "73-0467",
                "postgiro": "258068"
            },
            "activity": "Radio- o TV-kompo-nenter, antenner, högtalare o d en gros",
            "employees": 6,
            "annual_turnover": 1000000,
            "capital": 10000,
            "key_personnel": [
                {
                    "name": "Arvid Orrestad",
                    "position": "Verkst dir"
                }
            ],
            "establishment_year": 1947
        },
        "10": {
            "company_name": "INFI S INTERNATIONELL FARTYG & INDUSTRISERVICE AB",
            "pnr": "423 00",
            "address": "Torslanda, Ostergärde",
            "phone_number": "031-231654, 9254 72",
            "bank_details": {
                "bankgiro": "225-3250",
                "postgiro": "421196-7"
            },
            "activity": "Installation o reparation av fartygsmaskiner. Specialitet: pielstickmaskiner. Maskin-o rörinstallationer samt reparationer i industrianläggningar. Verkstad för tillverkning av mindre rör-, plåt- o stålkonstruktioner. Specialverkstad för rekonditionering av dieselmotorers insprutningsutrust-ning samt säkerhets- o avstängningsventiler för industrier",
            "employees": 27,
            "annual_turnover": 1800000,
            "capital": 33000,
            "key_personnel": [
                {
                    "name": "Sverre Rom Gundersen",
                    "position": "Verkst dir"
                }
            ],
            "establishment_year": 1968
        },
        "11": {
            "company_name": "ST INSON AB",
            "pnr": "26122",
            "address": "Landskrona, Enock Thulins v",
            "phone_number": "0418-163 70",
            "bank_details": {
                "bankgiro": "66-0122",
                "postgiro": "324362"
            },
            "activity": "Tillverkar fritidskläder o strumpor",
            "employees": 200,
            "annual_turnover": 12000000,
            "capital": 100000,
            "key_personnel": [
                {
                    "name": "Gert Skanert",
                    "position": "Verkst dir"
                }
            ],
            "establishment_year": 1946
        },
        "12": {
            "company_name": "CYBERNETICS INTERNATIONAL AB",
            "pnr": "182 11",
            "address": "Danderyd 1, Mysingsv 5",
            "phone_number": "08-753 03 00",
            "bank_details": {
                "bankgiro": "17-1281",
                "postgiro": "674 628"
            },
            "activity": "System- o programutveckling",
            "employees": 42,
            "annual_turnover": 3500000,
            "capital": 10000,
            "key_personnel": [
                {
                    "name": "Lennart Schwieler",
                    "position": "Verkst dir"
                }
            ],
            "establishment_year": 1966
        },
        "13": {
            "company_name": "NOPI (SWEDEN) AB",
            "pnr": "25012",
            "address": "Helsingborg 12, Muskötg 19",
            "phone_number": "042-12 76 25",
            "bank_details": {
                "bankgiro": "863-7787",
                "postgiro": "393984-0"
            },
            "activity": "Säljer Nopi tejp, tejpmaskiner samt Hafnia plåster",
            "capital": 50000,
            "key_personnel": [
                {
                    "name": "Jan Svedberg",
                    "position": "Verkst dir"
                }
            ],
            "establishment_year": 1950
        },
        "14": {
            "company_name": "NOPI ETIKETTER Ragnar Sahlin AB",
            "pnr": "25012",
            "address": "Helsingborg 12, Box 12036",
            "phone_number": "042-18 04 80",
            "bank_details": {
                "bankgiro": "863-4925",
                "postgiro": "371109-0"
            },
            "activity": "Tillverkar självhäf-tande etiketter för reklam o pris-märkningsändamål av pappers-, plast-, metallfolie- o sidenmaterial. Säljer självhäftande etiketter, tilltryckningsmaskiner för etiketter o etiketteringsanläggningar, hel- o halvautomatiska dispensers för etiketter",
            "employees": 60,
            "capital": 200000,
            "key_personnel": [
                {
                    "name": "Erik Brehm Nielsen",
                    "position": "Verkst dir"
                }
            ],
            "establishment_year": 1952
        },
        "15": {
            "company_name": "HOLSBY METALLFABRIK, AB",
            "pnr": "570 15",
            "address": "Holsbybrunn",
            "phone_number": "0383-501 85",
            "bank_details": {
                "bankgiro": "289-7718",
                "postgiro": "132554-7"
            },
            "activity": "Utför varmpressning",
            "employees": 40,
            "annual_turnover": 3500000,
            "capital": 180000,
            "key_personnel": [
                {
                    "name": "Curt Arvidsson",
                    "position": "Verkst dir"
                }
            ],
            "establishment_year": 1937
        },
        "16": {
            "company_name": "WELLTEC AB",
            "pnr": "662 00",
            "address": "Amål, Fabriksg 5, Box 130",
            "phone_number": "0532-140 20",
            "bank_details": {
                "bankgiro": "345-1770"
            },
            "activity": "Svetsning o sömnad av armerad o oarmerad PVC",
            "employees": 7,
            "annual_turnover": 500000,
            "capital": 30000,
            "key_personnel": [
                {
                    "name": "Olov Lindahl",
                    "position": "Verkstdir"
                }
            ],
            "establishment_year": 1967
        },
        "17": {
            "company_name": "WEHLOU KONSULTATION AB, HERBERT",
            "pnr": "211 34",
            "address": "Malmö, Söderg 12",
            "phone_number": "040-747 50",
            "bank_details": {
                "bankgiro": "260-7380",
                "postgiro": "630159-2"
            },
            "activity": "Konsulter inom företagsledning, marknadsföring, sälj-utbildning, redovisning, AR",
            "employees": 8,
            "annual_turnover": 600000,
            "capital": 20000,
            "key_personnel": [
                {
                    "name": "Herbert Wehlou",
                    "position": "Verkst dir"
                }
            ],
            "establishment_year": 1963
        }
    }
}