{
    "original": "HÄLLARYDSVERKEN, AB\n\nPnr 574 00\n\nVetlanda. Tol 0383-510 47. Telex\n2387. Tga Hallahydro\nVerksamhet: Tillverkar hydrauliska\nutrustningar\nAntal anställda: 50\nÅrsomsättning: 4 900 000\nAktiekapital: 540000\nVerkst dir. Sverker Brunius\nEtableringsår: 1870.\n\nCAN\n\n65102 Karlstad 1, O Klarälvsg 17.\nBox 36. Tel 054-1158 90, 116002\n58104 Linköping 1, Gillbergag 7.\nBox 427. Tel 013-1464 60\n827 00 Ljusdal, Fack. Tel\n0651-133 80\n\n223 55 Lund, Södra v 19. Tel\n046-12 45 70\n\n212 28 Malmö, Scheeleg 3. Tel\n040-93 54 50\n\n59101 Motala 1, Rosendahlsg 8.\nBox 112. Tel 0141-113 91, 115 91\n602 29 Norrköping, Gustaf Adolfsg\n13. Tel 011-18 6140\n.54101 Skövde 1, Haganders väg 9.\nBox 13. Tel 0500-175 20\n17185 Solna, (huvudkontor),\nPyra-midv 2. Tel 08-27 28 00\n17185 Solna, (distriktskontor),\nVretenv 2. Tel 08-27 28 00\n444 00 Stenungsund, Box 69. Tel\n0303-707 90, 712 33\n113 52 Stockholm, Döbelnsg 55.\nTel 08-23 00 80\n\n117 26 Stockholm, Ringv 14. Tel\n08-68 01 10\n\n826 02 Söderhamn 2, Kungsg 34.\nBox 1017. Tel 0270-143 80\n15143 Södertälje, üsterg 6. Tel\n0755-350 48\n\n23100 Trelleborg, Nyg 12. Tel\n\n0410-126 25, 135 01\n\n753 23 Uppsala, Mältarg 19. Tel\n\n018-10\t0130\n\n593 00 Västervik, Kristinebergsg\n18. Tel 0490-173 92, 113 54\n722 14 Västerås, Karlsg 9. Tel\n021-18 03 95\n\n352 46 Växjö, Ljungadalsg 7. Tel\n0470-270 60\n\n702 27 Örebro, Radiatorv 6. Tel\n\n019-136021\n\nVerkst dir: Jan Backmark\nEtableringsår: 1947.\n\nBÄLTARBO TEGELBRUK AB\n\nPnr 776 00\n\nHedemora, Stationsg 6. Tel\n0225-101 58. Bankgiro 67-5358.\nPosfc-giro 71450\n\nVerksamhet: Tillverkar o säljer\nmur- o fasadtegel\nAntal anställda: 14\nÅrsomsättning: 600 000\nAktiekapital: 50 000\nVerkst din Ing Ernst Sundh\nEtableringsår 1958.\n\nBÄRGSLAGSBLADETS\nTRYCKERI AB\n\nPnr 73101\n\nKöping 1, Mellang. Box 116. Tel\n0221-184 00. Bankgiro 606-7102.\nPostgiro 23802-2\nVerksamhet: Utgiver\nBärgslags-bladet o Arboga Tidning 5 ggr i\nveckan\n\nAntal anställda: 70\n\nÅrsomsättning: 3 500 000\nAktiekapital: 50 000\nAnsvarig utgivare: Karl Ostgren\nEtableringsår: 1890.\n\nBOCKERSBODA\nCEMENT-VARUFABRIK AB\n\nPnr 540 65\n\nLyrestad, Box 52. Tel 0501-500 39,\n502 39. Bankgiro 221-0060.\nPostgiro 81551-4\n\nVerksamhet: Tillverkar betongrör,\nbetongtakpannor o lättklinterblock\nAntal anställda: 30\nÅrsomsättning: 2 500000\nAktiekapital: 40 000\nVerkst dir: Carl Johansson\nEtableringsår: 1925.\n\nOvägen, Limhamn, Malmö. Tel\n040-1620 20\n\nCUPRINOL träskyddsprodukter o\nfärger samt övriga\nbyggmaterialprodukter m m, Lodg 12, Malmö.\nTel 040-93 5 1 30\nFabriker: Lodg 12, Malmö. Tel\n040-93 51 30. Tillverkning av\nträskyddsmedel, färger m m.\nTeckomatorp. Tel 04 1 8-606 78. Tillverkning\nav växtskyddsprodukter\nVarunamn: Astral, Bisol, Cuprinol,\nCuprinyl, Herbex\nAntal anställda: 150\nAktiekapital: 1200 000\nVerkst dir: Helge Rickman\nEtableringsår: 1874\nFöretaget ingår i\nHöganäskon-cernen.\n\nBOLEÅ SNICKERIFABRIK AB\n\nPnr 900 05\n\nUmeå 5, Box 5034. Tel 090-1112 61.\nBankgiro766-4071. Postgiro63643-1\nVerksamhet: Tillverkar fönster\nAntal anställda: 18\nÅrsomsättning: 1300 000\nAktiekapital: 100 000\nVeifcst din Gustaf Andersson\nEtableringsår 1946.\n\nSIEVERT, AB MAX\n\nPnr 162 10\n\nVällingby 1, Sorterarg 14. Pack. Tel\n08-89 0 1 00. Bankgiro 743-5209.\nPostgiro 626-2. Tga Sievert,\nStockholm. Telex 10944 SIEVERT S\nVerksamhet: Tillverkar elektroniska\nvågar samt bedriver försäljning av\nmät- o reglerutrustningar för industri\no forskning. Tillverkar även\nelektriska industriugnar för\nvärmebehandling, lågfrekvensugnar för\nmetallsmältning mm,\ndestillationsapparater för industrier, sjukhus o\nlaboratorier samt tvålautomater\nFabrik: Ulvsunda, Ekbacksv 2-4.\nTel 08-25 26 00\n\nFilial: Göteborg O, Nobelg 21.\nTel 031-153111\nSundsvall, Bergsg 58. Tel\n060-12 14 70\n\nAntal anställda: 155\nÅrsomsättning: 20 000 000\nAktiekapital: 1000 000\nStyrelse: Dir Gösta Björck,\növer-ing Torsten Nilsson, adv Töre\nFlodin, dir Nils Gustafson, dir Björn\nSievert\n\nVerkst dir Gösta Björck\nEtableringsår: 1882.\n\nSIFO AB, SVENSKA\nINSTITUTET FOR OPINIONSUNDER.\nSÖKNINGAR\n\nPnr 103 84\n\nStockholm 7, Birger Jarlsg 15. Box\n7207. Tel 08-24 96 95. Bankgiro\n481-3531. Postgiro 507350-7. Tga\nSwedopinion, Swedmarket.\nTelex 17795\n\nVerksamhet: Opinions- o\nmarknadsundersökningar\nAntal anställda: 30\nAktiekapital: 100 000\nVerkst dir: Nils Zetterberg\nEtableringsår 1954.\n\nTURBO ROR AB\n\nPnr 200 71\n\nMalmö 5, Box 5066. Järnyxeg 13.\nTel 040-94 64 45. Bankgiro\n561-8277. Postgiro 637660-2.\nTelex 32446 TURBO S\nVerksamhet: Försäljning av\nPan-Isovit fjärrvärmekulvert samt\nRomag spiralsvetsade stålrör o\nformstycken\n\nFörsälningskontor: Västra Frölunda,\nGaleasg 37. Tel 031-29 66 05\nÅrsomsättning: 4 000 000\nAktiekapital: 60 000\nVerkst dir: Lars Erie Häggström\nEtableringsår: 1968.\n\nEMOND AB, EMIL\n\nPnr 26120\n\nLandskrona 1, Verkstadsg. Fack.\nTel 0418-163 00. Telex 72410. Tga\nEmllemonds\n\nVerksamhet: Tillverkar\nkonstfiber-väv, damunderkläder o klänningar\nAntal anställda: 300\nÅrsomsättning: 20 000 000\nAktiekapital: 900 000\nVerkst dir: Emil Emond\nEtableringsår: 1923.\n\nEMPIRI AB,\nINGENIÖRSFIRMAN\n\nPnr 126 64\n\nHägersten, Ellen Keys g 1. Tel\n08-88 5130. Postgiro 258609\nVerksamhet: Tillverkar o säljer\nreläutrustningar för el-verk,\nvattenverk, avloppsreningsverk,\npanncentraler o d\nAntal anställda: 5\nÅrsomsättning: 500 000\nAktiekapital: 15 000\nVerkst dir: Ing Bertil Bergström\nEtableringsår: 1948\nOmbildat till aktiebolag 1952.\n\nEMRE, HANDELS AB\n\nPnr 250 05\n\nHelsingborg 5, Box 5025. O Sandg\n14. Tel 042-1171 00, 124601.\nBankgiro 652-8442. Postgiro 380664-3.\nTga Wastepaper\n\nVerksamhet: Sortering av\npappersavfall för svenska marknaden o\nexport\n\nVetkst dir: Dalmar Becker\nEtableringsår: 1936.\n\nRONNEBY OLJEIMPORT AB\n\nPnr 201 23\n\nMalmö 1, Box 325. Tel 040-735 60.\nBankgiro 640-5088. Postgiro\n533960-1\n\nVerksamhet: Säljer eldningsoljor\nFörsäljningskontor: 37014\nRonnebyhamn. Tel 0457-701 40\nÅrsomsättning: 5 000 000\nAktiekapital: 100 000\nVerkst dir: John Hain\nEtableringsàr: 1961\nDotterbolag till G &amp; L Beijer AB,\nMalmö.\n\nROOS MASKINAFFÅR AB\n\nPnr 722 11\n\nVästerås, Källg 13. Tel 021-13 67 88.\nBankgiro 63-0068. Postgiro 271820\nVeiksamhet: Säljer\nverktygsmaskiner\n\nAktiekapital: 55 000\nVerkst dir: Töre Roos\nEtableringsàr: 1942.\n\nROOS SKYLTREKLAM, AB\n\nPnr 721 20\n\nVästerås 1, Box 716. Kungsängsg\n10. Tel 021-13 76 40. Bankgiro\n232-5470. Postgiro 26113-1.\nTelex 40656\n\nVeiksamhet: Tillverkar o säljer\nalla slags reklamskyltar\nAntal anställda: 110\n\nÅrsomsättning: 10 000 000\nAktiekapital: 60 000\nVeikst dir Gunnar Roos\nEtableringsàr: 1916.\n\nROOS AB, BYGGNADS.\nFIRMAN DAVID E\n\nPnr 753 33\n\nUppsala, Timmermans g 18. Tel\n018-1114 70\n\nVeiksamhet: Uppför bostads-,\naffärs- o industribyggnader\nAntal anstäUda: 90\nÅrsomsättning: 10000 000\nAktiekapital: 150 000\nVerkst dir: Byggmäst David Roos\nEtableringsàr. 1954.\n\nROSANDER, BYGGNADSFIRMA\nNILS\n\nPnr 75003\n\nUppsala 3, Väderkvarnsg 16. Box\n3032. Tel 018-100040. Bankgiro\n23-0177. Postgiro 176631\nVerksamhet: Husbyggnader\nAntal anstäUda: 100\nÅrsomsättning: 10000 000\nÄgare o chef: Ing Nils Rosander\nEtableringsàr 1936.\n\nDOMSANDS VERKSTADS AB\n\nPnr 560 23\n\nBankeryd, Domsandsv. Tel\n036-721 94. 727 03. Bankgiro 836-9274.\nPostgiro 173799-8\n\nVerksamhet: Tillverkar\npenselringar, skaftringar, pressarbeten,\nspecialmaskiner, pressmatningar,\nriktverk o bagerimaskiner,\nmassartiklar för radio o elarmatur\nVarunamn: DVAB\nAntal anställda: 30\nÅrsomsättning: 1600 000\nAktiekapital: 25 000\nKamrer: B Grennard\nIng: L Grennard\nEtableringsår: 1941.\n\nGOLV-TEKNIK AB\n\nPnr 161 26\n\nBromma 1, Gustavslundsv 167,\nBox 5. Tel 08-26 47 50\nVerksamhet: Säljer golv o\ngolvmaterial\n\nAktiekapital: 50 000\nVerkst dir: S-T Angelin\nEtableringsår: 1953.\n\nJÄRBO SÅGVERKS AB\n\nPnr 810 28\n\nJärbo, Köpmang 27. Box 82. Tel\n0290-706 50. Bankgiro 78-7615.\nPostgiro 363117. Tga Järbosåg\nVerksamhet: Tillverkar hyvlade\nträvaror, monteringsfärdiga trähus\nAntal anställda: 45\nÅrsomsättning: 4 500 000\nAktiekapital: 250 000\nVerkst dir: Sam Bergvall\nEtableringsår: 1947.\n\nJÄRFÄLLA BYGGNADSVAROR,\nAB\n\nPnr 175 00\n\nJakobsberg, Box 51. Lidv 4. Tel\n0758-103 10. Bankgiro 392-3158.\nPostgiro 6350-3\n\nVerksamhet: Säljer trä- o\nbyggnadsmaterial\n\nAntal anställda: 12\nÅrsomsättning: 3 000 000\nAktiekapital: 100 000\nVerkst dir Sven Grönmark\nEtableringsår: 1889.\n\nJÄRLÅSA SÅG och\nTEGELBRUK, AB\n\nPnr 751 28\n\nUppsala 1, Börjeg 67. Box 667. Tel\n018-13 99 35. Bankgiro 23-0136.\nPostgiro 31363. Tga Järlåsavirke\nVerksamhet: Sågverk o hyvleri.\nSäljer trävaror, tegel o\nbyggnadsmateriel\n\nAntal anställda: 65\nÅrsomsättning: 8 000 000\nAktiekapital: 300 000\nStyrelse: Greve Gösta Bonde (ordf),\nnämndeman Lennart Nilsson,\njäg-mäst Sören Walan\nVerkst dir: Sören Walan\nEtableringsår: 1919\nÄges av Uppsala läns\nSkogsägareförening u p a, Uppsala.\n\nJÄRN- och BYGGMATERIAL I\nSUNDSVALL AB\n\nPnr 85101\n\nSundsvall 1, Fack. Esplanaden 24.\nTel 060-1217 40. Bankgiro\n180-6793. Postgiro 498950-5\nVerksamhet: Säljer byggmaterial\nsåsom fasader, dörrar, skåp,\nfönster, väggar o portar\nAntal anställda: 5\nÅrsomsättning: 7 500 000\nAktiekapital: 50 000\nVerkst dir. Sigvard Johansson\nEtableringsår 1945\nDotterbolag: X-Ponent\nStålinredningar AB, Sundsvall.\n\nJÄRN. &amp; BYGGNADS.\nVAROR AB\n\nPnr 67101\n\nArvika 1, Köpmang 11. Box 38. Tel\n0570-13155. Bankgiro 10-2966.\nPostgiro 83210\n\nVerksamhet: Säljer\nbyggnadsmaterial o trävaror\nAktiekapital: 150 000\nVerkst dir: Georg Lindqvist\nEtableringsår 1891\nOmbildat till aktiebolag 1948.\n\nJÄRN. &amp; HUSHÅLLS.\nVAROR AB\n\nPnr 651 06\n\nKarlstad X, N Strandg 15. Box 418.\nTel 054-15 57 00, 15 57 01. Bankgiro\n34-4477. Postgiro 277071\nVerksamhet: Grosshandel med\njärnvaror, hushålls- o sportartiklar\nAntal anställda: 14\nÅrsomsättning: 3 000 000\nAktiekapital: 21000\nStyrelse: Ale Nilsson (ordf), Hans\nIngels, Sven Weidelgren\nVerkst dir: Hans Ingels\nEtableringsår: 1955.",
    "structured": {
        "1": {
            "company_name": "HÄLLARYDSVERKEN, AB",
            "pnr": "574 00",
            "address": "Vetlanda, Tol 0383-510 47",
            "activity": "Tillverkar hydrauliska utrustningar",
            "employees": 50,
            "annual_turnover": 4900000,
            "capital": 540000,
            "key_personnel": [
                {
                    "name": "Sverker Brunius",
                    "position": "Verkst dir"
                }
            ],
            "establishment_year": 1870
        },
        "2": {
            "company_name": "BÄLTARBO TEGELBRUK AB",
            "pnr": "776 00",
            "address": "Hedemora, Stationsg 6",
            "activity": "Tillverkar o säljer mur- o fasadtegel",
            "employees": 14,
            "annual_turnover": 600000,
            "capital": 50000,
            "key_personnel": [
                {
                    "name": "Ing Ernst Sundh",
                    "position": "Verkst dir"
                }
            ],
            "establishment_year": 1958
        },
        "3": {
            "company_name": "BÄRGSLAGSBLADETS TRYCKERI AB",
            "pnr": "73101",
            "address": "Köping 1, Mellang. Box 116",
            "activity": "Utgiver Bärgslags-bladet o Arboga Tidning 5 ggr i veckan",
            "employees": 70,
            "annual_turnover": 3500000,
            "capital": 50000,
            "key_personnel": [
                {
                    "name": "Karl Ostgren",
                    "position": "Ansvarig utgivare"
                }
            ],
            "establishment_year": 1890
        },
        "4": {
            "company_name": "BOCKERSBODA CEMENT-VARUFABRIK AB",
            "pnr": "540 65",
            "address": "Lyrestad, Box 52",
            "activity": "Tillverkar betongrör, betongtakpannor o lättklinterblock",
            "employees": 30,
            "annual_turnover": 2500000,
            "capital": 40000,
            "key_personnel": [
                {
                    "name": "Carl Johansson",
                    "position": "Verkst dir"
                }
            ],
            "establishment_year": 1925
        },
        "5": {
            "company_name": "CUPRINOL träskyddsprodukter o färger samt övriga byggmaterialprodukter",
            "address": "Lodg 12, Malmö",
            "activity": "Tillverkning av träskyddsmedel, färger m m",
            "employees": 150,
            "annual_turnover": null,
            "capital": 1200000,
            "key_personnel": [
                {
                    "name": "Helge Rickman",
                    "position": "Verkst dir"
                }
            ],
            "establishment_year": 1874
        },
        "6": {
            "company_name": "BOLEÅ SNICKERIFABRIK AB",
            "pnr": "900 05",
            "address": "Umeå 5, Box 5034",
            "activity": "Tillverkar fönster",
            "employees": 18,
            "annual_turnover": 1300000,
            "capital": 100000,
            "key_personnel": [
                {
                    "name": "Gustaf Andersson",
                    "position": "Veifcst dir"
                }
            ],
            "establishment_year": 1946
        },
        "7": {
            "company_name": "SIEVERT, AB MAX",
            "pnr": "162 10",
            "address": "Vällingby 1, Sorterarg 14",
            "activity": "Tillverkar elektroniska vågar samt bedriver försäljning av mät- o reglerutrustningar för industri o forskning. Tillverkar även elektriska industriugnar för värmebehandling, lågfrekvensugnar för metallsmältning mm, destillationsapparater för industrier, sjukhus o laboratorier samt tvålautomater",
            "employees": 155,
            "annual_turnover": 20000000,
            "capital": 1000000,
            "key_personnel": [
                {
                    "name": "Gösta Björck",
                    "position": "Styrelse"
                },
                {
                    "name": "Torsten Nilsson",
                    "position": "över-ing"
                },
                {
                    "name": "Töre Flodin",
                    "position": "adv"
                },
                {
                    "name": "Nils Gustafson",
                    "position": "dir"
                },
                {
                    "name": "Björn Sievert",
                    "position": "dir"
                }
            ],
            "establishment_year": 1882
        },
        "8": {
            "company_name": "SIFO AB, SVENSKA INSTITUTET FOR OPINIONSUNDER. SÖKNINGAR",
            "pnr": "103 84",
            "address": "Stockholm 7, Birger Jarlsg 15",
            "activity": "Opinions- o marknadsundersökningar",
            "employees": 30,
            "capital": 100000,
            "key_personnel": [
                {
                    "name": "Nils Zetterberg",
                    "position": "Verkst dir"
                }
            ],
            "establishment_year": 1954
        },
        "9": {
            "company_name": "TURBO ROR AB",
            "pnr": "200 71",
            "address": "Malmö 5, Box 5066, Järnyxeg 13",
            "activity": "Försäljning av Pan-Isovit fjärrvärmekulvert samt Romag spiralsvetsade stålrör o formstycken",
            "employees": null,
            "annual_turnover": 4000000,
            "capital": 60000,
            "key_personnel": [
                {
                    "name": "Lars Erie Häggström",
                    "position": "Verkst dir"
                }
            ],
            "establishment_year": 1968
        },
        "10": {
            "company_name": "EMOND AB, EMIL",
            "pnr": "26120",
            "address": "Landskrona 1, Verkstadsg.",
            "activity": "Tillverkar konstfiber-väv, damunderkläder o klänningar",
            "employees": 300,
            "annual_turnover": 20000000,
            "capital": 900000,
            "key_personnel": [
                {
                    "name": "Emil Emond",
                    "position": "Verkst dir"
                }
            ],
            "establishment_year": 1923
        },
        "11": {
            "company_name": "EMPIRI AB, INGENIÖRSFIRMAN",
            "pnr": "126 64",
            "address": "Hägersten, Ellen Keys g 1",
            "activity": "Tillverkar o säljer reläutrustningar för el-verk, vattenverk, avloppsreningsverk, panncentraler o d",
            "employees": 5,
            "annual_turnover": 500000,
            "capital": 15000,
            "key_personnel": [
                {
                    "name": "Ing Bertil Bergström",
                    "position": "Verkst dir"
                }
            ],
            "establishment_year": 1948
        },
        "12": {
            "company_name": "EMRE, HANDELS AB",
            "pnr": "250 05",
            "address": "Helsingborg 5, Box 5025, O Sandg 14",
            "activity": "Sortering av pappersavfall för svenska marknaden o export",
            "employees": null,
            "annual_turnover": null,
            "capital": null,
            "key_personnel": [
                {
                    "name": "Dalmar Becker",
                    "position": "Verkst dir"
                }
            ],
            "establishment_year": 1936
        },
        "13": {
            "company_name": "RONNEBY OLJEIMPORT AB",
            "pnr": "201 23",
            "address": "Malmö 1, Box 325",
            "activity": "Säljer eldningsoljor",
            "employees": null,
            "annual_turnover": 5000000,
            "capital": 100000,
            "key_personnel": [
                {
                    "name": "John Hain",
                    "position": "Verkst dir"
                }
            ],
            "establishment_year": 1961
        },
        "14": {
            "company_name": "ROOS MASKINAFFÅR AB",
            "pnr": "722 11",
            "address": "Västerås, Källg 13",
            "activity": "Säljer verktygsmaskiner",
            "employees": null,
            "annual_turnover": null,
            "capital": 55000,
            "key_personnel": [
                {
                    "name": "Töre Roos",
                    "position": "Verkst dir"
                }
            ],
            "establishment_year": 1942
        },
        "15": {
            "company_name": "ROOS SKYLTREKLAM, AB",
            "pnr": "721 20",
            "address": "Västerås 1, Box 716, Kungsängsg 10",
            "activity": "Tillverkar o säljer alla slags reklamskyltar",
            "employees": 110,
            "annual_turnover": 10000000,
            "capital": 60000,
            "key_personnel": [
                {
                    "name": "Gunnar Roos",
                    "position": "Verkst dir"
                }
            ],
            "establishment_year": 1916
        },
        "16": {
            "company_name": "ROOS AB, BYGGNADS. FIRMAN DAVID E",
            "pnr": "753 33",
            "address": "Uppsala, Timmermans g 18",
            "activity": "Uppför bostads-, affärs- o industribyggnader",
            "employees": 90,
            "annual_turnover": 10000000,
            "capital": 150000,
            "key_personnel": [
                {
                    "name": "Byggmäst David Roos",
                    "position": "Verkst dir"
                }
            ],
            "establishment_year": 1954
        },
        "17": {
            "company_name": "ROSANDER, BYGGNADSFIRMA NILS",
            "pnr": "75003",
            "address": "Uppsala 3, Väderkvarnsg 16, Box 3032",
            "activity": "Husbyggnader",
            "employees": 100,
            "annual_turnover": 10000000,
            "capital": null,
            "key_personnel": [
                {
                    "name": "Ing Nils Rosander",
                    "position": "Ägare o chef"
                }
            ],
            "establishment_year": 1936
        },
        "18": {
            "company_name": "DOMSANDS VERKSTADS AB",
            "pnr": "560 23",
            "address": "Bankeryd, Domsandsv.",
            "activity": "Tillverkar penselringar, skaftringar, pressarbeten, specialmaskiner, pressmatningar, riktverk o bagerimaskiner, massartiklar för radio o elarmatur",
            "employees": 30,
            "annual_turnover": 1600000,
            "capital": 25000,
            "key_personnel": [
                {
                    "name": "B Grennard",
                    "position": "Kamrer"
                },
                {
                    "name": "L Grennard",
                    "position": "Ing"
                }
            ],
            "establishment_year": 1941
        },
        "19": {
            "company_name": "GOLV-TEKNIK AB",
            "pnr": "161 26",
            "address": "Bromma 1, Gustavslundsv 167, Box 5",
            "activity": "Säljer golv o golvmaterial",
            "employees": null,
            "annual_turnover": null,
            "capital": 50000,
            "key_personnel": [
                {
                    "name": "S-T Angelin",
                    "position": "Verkst dir"
                }
            ],
            "establishment_year": 1953
        },
        "20": {
            "company_name": "JÄRBO SÅGVERKS AB",
            "pnr": "810 28",
            "address": "Järbo, Köpmang 27, Box 82",
            "activity": "Tillverkar hyvlade trävaror, monteringsfärdiga trähus",
            "employees": 45,
            "annual_turnover": 4500000,
            "capital": 250000,
            "key_personnel": [
                {
                    "name": "Sam Bergvall",
                    "position": "Verkst dir"
                }
            ],
            "establishment_year": 1947
        },
        "21": {
            "company_name": "JÄRFÄLLA BYGGNADSVAROR, AB",
            "pnr": "175 00",
            "address": "Jakobsberg, Box 51, Lidv 4",
            "activity": "Säljer trä- o byggnadsmaterial",
            "employees": 12,
            "annual_turnover": 3000000,
            "capital": 100000,
            "key_personnel": [
                {
                    "name": "Sven Grönmark",
                    "position": "Verkst dir"
                }
            ],
            "establishment_year": 1889
        },
        "22": {
            "company_name": "JÄRLÅSA SÅG och TEGELBRUK, AB",
            "pnr": "751 28",
            "address": "Uppsala 1, Börjeg 67, Box 667",
            "activity": "Sågverk o hyvleri. Säljer trävaror, tegel o byggnadsmateriel",
            "employees": 65,
            "annual_turnover": 8000000,
            "capital": 300000,
            "key_personnel": [
                {
                    "name": "Sören Walan",
                    "position": "Verkst dir"
                }
            ],
            "establishment_year": 1919
        },
        "23": {
            "company_name": "JÄRN- och BYGGMATERIAL I SUNDSVALL AB",
            "pnr": "85101",
            "address": "Sundsvall 1, Fack. Esplanaden 24",
            "activity": "Säljer byggmaterial såsom fasader, dörrar, skåp, fönster, väggar o portar",
            "employees": 5,
            "annual_turnover": 7500000,
            "capital": 50000,
            "key_personnel": [
                {
                    "name": "Sigvard Johansson",
                    "position": "Verkst dir"
                }
            ],
            "establishment_year": 1945
        },
        "24": {
            "company_name": "JÄRN. & HUSHÅLLS. VAROR AB",
            "pnr": "651 06",
            "address": "Karlstad X, N Strandg 15",
            "activity": "Grosshandel med järnvaror, hushålls- o sportartiklar",
            "employees": 14,
            "annual_turnover": 3000000,
            "capital": 21000,
            "key_personnel": [
                {
                    "name": "Ale Nilsson",
                    "position": "Styrelse"
                },
                {
                    "name": "Hans Ingels",
                    "position": "Verkst dir"
                }
            ],
            "establishment_year": 1955
        }
    }
}