{
    "original": "SELANDERS ELEKTRISKA AB\n\nPnr 26200\n\nÄngelholm, Nybrov 10. Tel\n0431-17110. Bankgiro 672-2698.\nPostgiro 444758-7\n\nVerksamhet: Utför elektriska\nnyinstallationer\nAntal anställda: 35\nÅrsomsättning: 3 400 000\nAktiekapital: 50 000\nVerkst dir: Göte Selander\nEtableringsår: 1958.\n\nMETIOR AB\n\nPnr 200 25\n\nMalmö 16, Box 16056. Scheeleg 15.\nTel 040-18 0410. Bankgiro\n481-8183. Postgiro 609844-6. Tga\nMeto-mat. Telex 32627\n\nVeiksamhet: Tillverkar\ndatainsara-lande elektroniska utrustningar för:\nsedel- o varuautomater,\nbensinpumpar. Tidregistrering, in- o utr\npasseringskontroll.\nHelautomatiska garageanläggningar\nFörsäljningskontor för\nhelautomatiska garageanläggningar: 18105\nLidingö 5, Albav 7. Fack. Tel\n08-767 0195\n\nVarunamn: Meüor, Bankomat,\nVaru-mat, Tankomat, TDR, PDR\nAntal anställda: 230\nAktiekapital: 1400 000\nVeikst dir: Nils-Eric KUller\nEtableringsår. 1965.\n\nMETRIC, VERKTYGS.\nFABRIKEN\n\nPnr 57100\n\nNässjö, Box 106, Sjögärdsg 23.\nTel 0380-117 43. 109 07. Bankgiro\n452-7529. Postgiro 384096-4\nVerksamhet: Tillverkar o\nexporterar djuptrycksmaskiner för\nmångskiftande ändamål även för\ndjuptryck på hushålls- o toalettpapper\nsamt servetter. Automatiska\nstämpelverk för stämpling av lådor,\nkartonger o etiketter. Kopplingsbar\ntill manöverbord, vågar o\nprogramverk av olika slag\nVarunamn: Metric\nAntal anställda: 8\nÅrsomsättning: 400 000\nChef: Fabr Folke Blomborg\nEtableringsår: 1948.\n\nINGUT AB\n\nPnr 57100\n\nNässjö, Svedjeg 1. Box 69. Tel\n0380-18 1 80. Telex 3721 ingut s.\nTga Ingut\n\nVerksamhet: Maskiner o material\nför re produktions ändamål\nAntal anställda: 240\nÅrsomsättning: 28 000 000\nAktiekapital: 1000 000\nVerkst dir: C Ossian Treutiger\nEtableringsår: 1926.\n\nv SIVERS AB, GUSTAF\n\nPnr 104 25\n\nStockholm 30, Nordenflychtsv 64.\nBox 30039. Tel 08-51 98 01,\n51 21 00. Bankgiro 28-3952.\nPost-giro 50772. Tga Woodvers\nVeiksamhet: Grossist- o\nagenturrörelse med emballage av glas,\naluminium o plast\nVarunamn: Siv\nAntal anstäUda: 12\nÅrsomsättning: 1500 000\nAktiekapital: 40 000\nVerkst dir: Björn von Sivers\nEtableringsàr 1923.\n\nRÅNÄS BRUKS AB\n\nPnr 76200\n\nRimbo. Rånäs. Tel 0175-612 30.\nBankgiro 805-8380. Postgiro\n197172-0. Tga Wallonoxid,\nNorrtälje\n\nVerksamhet: Tillverkar zinkvitt o\nbetongtakpannor\nAntal anställda: 21\nÅrsomsättning: 5 000 000\nAktiekapital: 400000\nVerkst dir: Karl Henrik Andersson\nFörsäljn-chef: Tage Jantze\nEtableringsår 1940.\n\nAGE-METALL AB\n\nPnr 63 0 05\n\nEskilstuna 5, Box 5014. Hejarg 3.\nTel 016-14 84 30. Bankgiro\n604-4143. Postgiro 331441-6\nVerksamhet: Sand- o kokillgjutning\ni SIS-normerade al-legeringar\nAntal anställda: 16\nÅrsomsättning: 1 600 000\nAktiekapital: 15 000\nVerkst dir: Sten Gustavsson\nEtableringsår 1955.\n\nDOWO, AB\n\nPnr 17163\n\nSolna, Lundag 11. Tel 08-83 42 80.\nBankgiro 56-4645. Postgiro 155566.\nTga Dowobolaget\nVerksamhet: Levererar all kemisk,\nmekanisk (automatisk) o elektrisk\nutrustning för galvanoindustrin\nsamt avgiftnlngs- o\nneutralisations-anläggningar, likriktare.\nKonsultation o analysservice\nAvdelningskontor: 114 38 Stockholm,\nGrev Tureg 25. Tel 08-63 2160\nAktiekapital: 50 000\nDir: Karl W Eulau\nEtableringsår: 1938.\n\nABECOJÄRNVARU AB\n\nPnr 25012\n\nHelsingborg 12, Box 12005.\nRundgången 14. Tel 042-12 78 55.\nBankgiro 438-1372. Postgiro 109550-4.\nTga Abeco. Telex 72294\nVerksamhet: Tillverkar\nsträngsprut-gods i PVC för snickeriindustrin\nsamt specialbeslag för\nköksinredningar\n\nVarunamn: Abecol\nAntal anställda: 12\nÅrsomsättning: 4 000 000\nAktiekapital: 100 000\nStyrelse: Byggn-ing Edvin Claes-\n\nson, dir Sven Rehnström\nVerkst din Dir Sven Rehnström\nEtableringsår: 1956\nNamnändring 1963 från AB E\nClaesson &amp; Co till ABECO\nJärnvara AB.\n\nABEKO KONFEKTIONS AB\n\nPnr 672 00\n\nÅrjäng. Tel 0573-108 00. Bankgiro\n11-3431. Postgiro 466367. Tga\nAbeko\n\nVerksamhet: Tillverkar\nregnkläder, arbetskläder o biltillbehör\nFabrik: Årjäng\nVarunamn: Abeko\nAntal anställda: 30\nÅrsomsättning: 1500 000\nAktiekapital: 30 000\nVerkst din Karl Nilson\nEtableringsår: 1951.\n\nekens fabriker, ab\n\nPnr 290 10\n\nTollarp. Tel 0450-105 20.\nBankgiro 665-6029. Postgiro 160003-0\nVerksamhet: Tillverkar\nresårsängar, täcken, kuddar o överkast\nAntal anställda: 130\nÅrsomsättning: 12000 000\nAktiekapital: 451600\nVerkst dir: Bo Sandberg\nEtableringsår: 1938.\n\nWEECO-VERKEN, AB\n\nPnr 80004\n\nGävle 4, Box 4026. Atlasg 8. Tel\n026-180140. Bankgiro 617-7067.\nPostgiro 90773-3\n\nVerksamhet: Konsultuppdrag,\nkonstruktions- o ritningsarbete inom\ncellulosa- o verkstadsindustrin.\nLegoarbeten, maskinbearbetning,\ngrov- o tunnplåtslageri jämte\nsmi-desarbeten\nAntal anställda: 25\nÅrsomsättning: 2 500 000\nAktiekapital: 30 000\nStyrelse: Dir Bertil Engström\n(ordf), dlr Inge Eriksson, civiling\nWilhelm Wexel\nVerkst dir: Bertil Engström\nEtableringsår: 1970.",
    "structured": {
        "1": {
            "company_name": "SELANDERS ELEKTRISKA AB",
            "pnr": "26200",
            "address": "Ängelholm, Nybrov 10",
            "phone_number": "0431-17110",
            "bank_details": {
                "bankgiro": "672-2698",
                "postgiro": "444758-7"
            },
            "activity": "Utför elektriska nyinstallationer",
            "employees": 35,
            "annual_turnover": 3400000,
            "capital": 50000,
            "key_personnel": [
                {
                    "name": "Göte Selander",
                    "position": "Verkst dir"
                }
            ],
            "establishment_year": 1958
        },
        "2": {
            "company_name": "METIOR AB",
            "pnr": "200 25",
            "address": "Malmö 16, Box 16056, Scheeleg 15",
            "phone_number": "040-18 0410",
            "bank_details": {
                "bankgiro": "481-8183",
                "postgiro": "609844-6"
            },
            "activity": "Tillverkar datainsara-lande elektroniska utrustningar",
            "employees": 230,
            "annual_turnover": 1400000,
            "capital": 1400000,
            "key_personnel": [
                {
                    "name": "Nils-Eric KUller",
                    "position": "Veikst dir"
                }
            ],
            "establishment_year": 1965
        },
        "3": {
            "company_name": "METRIC, VERKTYGS. FABRIKEN",
            "pnr": "57100",
            "address": "Nässjö, Box 106, Sjögärdsg 23",
            "phone_number": "0380-117 43, 109 07",
            "bank_details": {
                "bankgiro": "452-7529",
                "postgiro": "384096-4"
            },
            "activity": "Tillverkar o exporterar djuptrycksmaskiner",
            "employees": 8,
            "annual_turnover": 400000,
            "key_personnel": [
                {
                    "name": "Fabr Folke Blomborg",
                    "position": "Chef"
                }
            ],
            "establishment_year": 1948
        },
        "4": {
            "company_name": "INGUT AB",
            "pnr": "57100",
            "address": "Nässjö, Svedjeg 1, Box 69",
            "phone_number": "0380-18 1 80",
            "bank_details": {
                "bankgiro": "",
                "postgiro": ""
            },
            "activity": "Maskiner o material för re produktions ändamål",
            "employees": 240,
            "annual_turnover": 28000000,
            "capital": 1000000,
            "key_personnel": [
                {
                    "name": "C Ossian Treutiger",
                    "position": "Verkst dir"
                }
            ],
            "establishment_year": 1926
        },
        "5": {
            "company_name": "SIVERS AB, GUSTAF",
            "pnr": "104 25",
            "address": "Stockholm 30, Nordenflychtsv 64, Box 30039",
            "phone_number": "08-51 98 01, 51 21 00",
            "bank_details": {
                "bankgiro": "28-3952",
                "postgiro": "50772"
            },
            "activity": "Grossist- o agenturrörelse med emballage av glas, aluminium o plast",
            "employees": 12,
            "annual_turnover": 1500000,
            "capital": 40000,
            "key_personnel": [
                {
                    "name": "Björn von Sivers",
                    "position": "Verkst dir"
                }
            ],
            "establishment_year": 1923
        },
        "6": {
            "company_name": "RÅNÄS BRUKS AB",
            "pnr": "76200",
            "address": "Rimbo, Rånäs",
            "phone_number": "0175-612 30",
            "bank_details": {
                "bankgiro": "805-8380",
                "postgiro": "197172-0"
            },
            "activity": "Tillverkar zinkvitt o betongtakpannor",
            "employees": 21,
            "annual_turnover": 5000000,
            "capital": 400000,
            "key_personnel": [
                {
                    "name": "Karl Henrik Andersson",
                    "position": "Verkst dir"
                },
                {
                    "name": "Tage Jantze",
                    "position": "Försäljn-chef"
                }
            ],
            "establishment_year": 1940
        },
        "7": {
            "company_name": "AGE-METALL AB",
            "pnr": "63 0 05",
            "address": "Eskilstuna 5, Box 5014, Hejarg 3",
            "phone_number": "016-14 84 30",
            "bank_details": {
                "bankgiro": "604-4143",
                "postgiro": "331441-6"
            },
            "activity": "Sand- o kokillgjutning i SIS-normerade al-legeringar",
            "employees": 16,
            "annual_turnover": 1600000,
            "capital": 15000,
            "key_personnel": [
                {
                    "name": "Sten Gustavsson",
                    "position": "Verkst dir"
                }
            ],
            "establishment_year": 1955
        },
        "8": {
            "company_name": "DOWO, AB",
            "pnr": "17163",
            "address": "Solna, Lundag 11",
            "phone_number": "08-83 42 80",
            "bank_details": {
                "bankgiro": "56-4645",
                "postgiro": "155566"
            },
            "activity": "Levererar all kemisk, mekanisk (automatisk) o elektrisk utrustning",
            "employees": null,
            "annual_turnover": null,
            "capital": 50000,
            "key_personnel": [
                {
                    "name": "Karl W Eulau",
                    "position": "Dir"
                }
            ],
            "establishment_year": 1938
        },
        "9": {
            "company_name": "ABECOJÄRNVARU AB",
            "pnr": "25012",
            "address": "Helsingborg 12, Box 12005, Rundgången 14",
            "phone_number": "042-12 78 55",
            "bank_details": {
                "bankgiro": "438-1372",
                "postgiro": "109550-4"
            },
            "activity": "Tillverkar strängsprut-gods i PVC för snickeriindustrin",
            "employees": 12,
            "annual_turnover": 4000000,
            "capital": 100000,
            "key_personnel": [
                {
                    "name": "Byggn-ing Edvin Claes-son",
                    "position": "Styrelse"
                },
                {
                    "name": "Sven Rehnström",
                    "position": "Styrelse"
                },
                {
                    "name": "Sven Rehnström",
                    "position": "Verkst din Dir"
                }
            ],
            "establishment_year": 1956
        },
        "10": {
            "company_name": "ABEKO KONFEKTIONS AB",
            "pnr": "672 00",
            "address": "Årjäng",
            "phone_number": "0573-108 00",
            "bank_details": {
                "bankgiro": "11-3431",
                "postgiro": "466367"
            },
            "activity": "Tillverkar regnkläder, arbetskläder o biltillbehör",
            "employees": 30,
            "annual_turnover": 1500000,
            "capital": 30000,
            "key_personnel": [
                {
                    "name": "Karl Nilson",
                    "position": "Verkst din"
                }
            ],
            "establishment_year": 1951
        },
        "11": {
            "company_name": "EKENS FABRIKER, AB",
            "pnr": "290 10",
            "address": "Tollarp",
            "phone_number": "0450-105 20",
            "bank_details": {
                "bankgiro": "665-6029",
                "postgiro": "160003-0"
            },
            "activity": "Tillverkar resårsängar, täcken, kuddar o överkast",
            "employees": 130,
            "annual_turnover": 12000000,
            "capital": 451600,
            "key_personnel": [
                {
                    "name": "Bo Sandberg",
                    "position": "Verkst dir"
                }
            ],
            "establishment_year": 1938
        },
        "12": {
            "company_name": "WEECO-VERKEN, AB",
            "pnr": "80004",
            "address": "Gävle 4, Box 4026, Atlasg 8",
            "phone_number": "026-180140",
            "bank_details": {
                "bankgiro": "617-7067",
                "postgiro": "90773-3"
            },
            "activity": "Konsultuppdrag, konstruktions- o ritningsarbete inom cellulosa- o verkstadsindustrin",
            "employees": 25,
            "annual_turnover": 2500000,
            "capital": 30000,
            "key_personnel": [
                {
                    "name": "Bertil Engström",
                    "position": "Styrelse"
                },
                {
                    "name": "Inge Eriksson",
                    "position": "Styrelse"
                },
                {
                    "name": "Wilhelm Wexel",
                    "position": "civiling Verkst dir"
                }
            ],
            "establishment_year": 1970
        }
    }
}