{
    "original": "WESTMAN &amp; LUNDMARK, AB\n\nPnr 199 01\n\nEnköping 1, Lilla v 8. Box 53.\nTel 0171-33105. Bankgiro 80-4229.\nPostgiro 145231\n\nW££LU\n\nAB WESTMAN C LUNDMARK\n\nVerksamhet: Betongjärnsaxar,\nhydrauliska saxar för stångmaterial,\nhållare för golvläggning.\nVarmlufts-aggregat, golvplaningsmaskiner,\nbockningsapparater o -maskiner,\nlyftgafflar för tegel o betong m m\nVarunamn: Weelu\nAntal anställda: 60\nÅrsomsättning: 5 000 000\nAktiekapital: 40 000\nVerkst dir. B M Westman\nEtableringsår. 1945.\n\nNORDFORS, DAVID\n\nPnr 702 27\n\nÖrebro, Signalg 10. Tel 019-\n\n11 1222,1261 29. Bankgiro\n61-5426. Postgiro 83620\nVerksamhet: Glasmästeri,\nglas-sliperi o inramningar\nAntal anställda: 8\nÅrsomsättning: 350 000\nChef: Ing David Nordfors\nEtableringsår: 1926.\n\nJAC\n\nJ\n\nJACO FABRIKS AB\n\nPnr740 73\n\nHargshamn. Tel 0173-20100.\nBankgiro 80-6408. Postgiro 279878-3\nVerksamhet: Tillverkar\ntransformatorstationer\nAntal anställda: 40\nÅrsomsättning: 3 000 000\nAktiekapital: 90 000\nVerkst dir: Edvin Johnson\nEtableringsår. 1945.\n\nBEG\n\nBAYER AGRO-KEMI AB\n\nPnr 211 24\n\nMalmö, Bjurög 42. Tel 040-93 69 30.\nBankgiro 875-5136. Postgiro\n431622-4. Tga Agrokemi.\nTelex 32620 BAYAGRO S\nVerksamhet: Importerar o säljer\nväxtskyddsmedel\nAktiekapital: 150 000\nEtableringsår: 1951.\n\nJOHANSSON &amp; CO AB, CARL R\n\nPnr 40127\n\nGöteborg 1, Box 502. Göteborgs\nLagerhus, Heurlins Plats. Tel\n031-17 0150. Bankgiro 506-5099.\nPostgiro 12462-8. Tga Carlerr.\nTelex 2233, 20744\nVerksamhet: Spedition,\nbefrakt-ningar, assuranser, internationella\ntransporter, lagringar,\nskeppsmäklare o rederiagenter\nAvdelningskontor:\nHalmstad, Strandg. Tel 035-118135\nHälsingborg, Kungsg 6. Tel\n042-115601\n\nMalmö C, Jörgen Kocksg 4. Box\n262, Malmö 1. Tel 040-97 64 90\nStockholm C, Bredgränd 2. Tel\n08-2018 02, 20 86 30\n\nTrelleborg, Kontinentg 2. Tel\n0410-137 35\n\nUddevalla, Badökajen. Box 97. Tel\n0522-107 89, 107 49, 106 42. Telex\n5267\n\nAntal anställda: 75\nÅrsomsättning: 65 000 000\nAktiekapital: 300 000\nVerkst dir: Erie Pehrsson\nEtableringsår: 1917.\n\nJOHANSSON, VERKSTADS.\nAKTIEBOLAGET CLAES\n\nPnr 510 95\n\nDalstorp. Box 101. Tel 0321-60165.\nBankgiro 84-0620. Postgiro 31083\nVerksamhet: Tillverkar detaljer till\nbilindustrin, såsom pedaler,\nfönsterhissar m m. Verktygslådor,\nuppsamlingskärl. Legolackering i\ntoppmodern anläggning\nAntal anställda: 55\nAktiekapital: 100 000\nVerkst dir: Gösta Claesson\nEtableringsår: 1895\nOmbildat till aktiebolag 1962.\n\nJOHANSONS\nBYGGNADS-varor, ab d\n\nPnr 573 01\n\nTranås 1, Box 38. Industrig 2. Tel\n\n0140-100 90. Bankgiro 13-0480.\nPostgiro 143606-2\nVerksamhet: Säljer trävaror o\nbyggnadsmaterial. Förädling av trävaror\nAntal anställda: 16\nÅrsomsättning: 5 000 000\nAktiekapital: 404 000\nVerkst dir: Gunnar Ulfsbo\nEtableringsår: 1908.\n\nJOHANSSONS\nSNICKERIFABRIK, E\n\nPnr 270 30\n\nLövestad, Heingetorp 3. Tel\n0417-21126. Bankgiro 87-0025. Postgiro\n172637\n\nVerksamhet: Tillverkar dörrar,\nfönster o köksinredningar\nAntal anställda: 5\nÅrsomsättning: 300 000\nChef: Erik Johansson\nEtableringsår: 1934.\n\nJOHANSSONS METALL.\nGJUTERI, E W\n\nPnr 780 10\n\nGustafs, Bomsarvet. Tel\n0243-400 51. Postgiro 295044\nVerksamhet: Tillverkar\nmetallgjut-gods i förekommande legeringar\nÅrsomsättning: 70 000\nÄgare: Valfrid Johansson.\n\nJOHANSSONS MÖBELFABRIK\nEFTR,AB EDVARD\n\nPnr 33100\n\nVärnamo, Myntg 10. Tel0370-100 71.\nBankgiro 141-7369. Postgiro 5559-0\nVerksamhet: Tillverkar bord,\nhallbyråer o thevagnar\nAktiekapital: 75 000\nVerkst dir: Ulf Ihreborn\nEtableringsår: 1903.\n\nATL\n\n7119910, 7119911. Bankgiro\n744-3450. Postgiro 57903-7\nVerksamhet: Tillverkaf\nplastartiklar o verktyg till sådana\nAktiekapital: 120 000\nÄgare o chef: Aleksander Kull\nEtableringsår: 1950.\n\nATLANTICA,\nFÖRSÄKRINGS AB\n\nPnr 403 14\n\nHuvudkontor: S Hamng 5. Box 2251,\nGöteborg 2. Tel (växel)\n031-17 17 60. Tga Atlantica. Telex 2538\nAvdelningskontor: Kungsg 4 B. Box\n7128, 103 83 Stockholm 7. Tel\n08-1136 34. Tga Sjöatlantica\nVerksamhet: Sjö- o\ntransportförsäkring, montageförsäkring i förening\nmed sjö- o transportförsäkring,\nåterförsäkring i samtliga branscher\nexklusive liv\nAntal anställda: 34\nAktiekapital: 4 000 000\nVerkst dir: Niklas Kihlbom\nDir Nils-Y Danielsson\nExpeditionsavdelning: Per R\nBengtsson\n\nHaveriavdelning: Sture Tingström\nStockholmskontor: Lars-E Liljeborg\nEtableringsår: 1916.\n\nSUN\n\nVerksamhet: Glas för bostäder,\nindustrier, kraftverk samt bilrutor.\nTavelinr amning ar\nÄgare o chef: Erik Ostberg.\n\nSUNDSVALLS MASKIN\nGRAVYR\n\nPnr 852 37\n\nSundsvall, v Långg 71. Tel\n060-15 45 37. Bankgiro 631-6137.\nPostgiro 669839-3\n\nVerksamhet: Tillverkar skyltar i\nallt slags material. Skalor, paneler\nm m\n\nAntal anställda: 5\nChef: Gravör Odd Olaussen\nEtableringsår 1965.\n\nSUNDSVALLS NYA\nKAROSSERI AB\n\nPnr 860 24\n\nAlnö, Pack. Tel 060-85110,\n\n85118. Bankgiro 63-0397.\nPostgiro 293700\n\nVerksamhet: Tillverkar o\nreparerar allt inom karosseribranschen\nAntal anställda: 25\nÅrsomsättning: i 000000\nAktiekapital: 75 000\nVerkst dir: Axel Norell\nEtableringsår: 1955.\n\nFROSTS KNIVFABRIK AB\n\nPnr 792 00\n\nMora, Box 25. Tel 0250-135 80.\nBankgiro 469-1952. Postgiro\n138995-6. Tga Frostknife\nVerksamhet: Tillverkar tälj- o\nslidknivar, jakt- o sportknivar,\nslöjdknivar, hovknivar, läder- o\nlinole-umknivar, slakt- o fiskeriknivar,\nrestaurant- o hushållsknivar samt\nyrkesknivar av alla slag\nVarunamn: Frosts\nAntal anställda: 80\nÅrsomsättning: 5 000 000\nAktiekapital: 105 000\nVerkst dir: Carl-Eric Frost\nEtableringsår: 1891\nOmbildat till aktiebolag 1949.\n\nVerksamhet: Handel, spedition,\nagentur, presenningsuthyrning\nAntal anställda: 5\nAktiekapital: 40 000\nChef: Disp Erik Strandh\nEtableringsår: 1887\nOmbildat till aktiebolag 1920.\n\nFRUCTUS FABRIKER, AB\n\nPnr 161 11\n\nBromma 11, Ulvsundav 108. Box\n11001. Tel 08-25 26 30. Bankgiro\n235-1542. Postgiro 1441-5. Tga\nFructarom. Telex 17662\nVerksamhet: Tillverkar råvaror o\no halvfabrikat för\nläskedrycksindustrin, fruktextrakter,\nsaftkoncen-trater, juicer o jämförbara produkter\nAntal anställda: 80\nAktiekapital: 2 400 000\nVerkst dir: Gunnar Gahn\nEtableringsår: 1919.\n\nVÄXJÖ DATA SYSTEM AB\n\nPnr 350 04\n\nVäxjö 4. Box 4055. Vänortsv 6 D.\nTel 0470-100 70. Bankgiro\n674-4833. Postgiro 71840-3\nVerksamhet: Systemutveckling,\ndatabehandling, programmering,\nAR, tekn konsultverksamhet\nFilial: 33100 Värnamo,\nJönkö-pingsv 11. Tel 0370-158 30\nAntal anställda: 45\nÅrsomsättning: 3 000 000\nAktiekapital: 100 000\nChefer: Företagsekonom Erik\nBendz, ing Gunnar Westinius\nEtableringsår 1967.\n\nWEXIÖ MEKANISKA\nVERKSTAD, AB\n\nPnr 35103\n\nVäxjö 1, Box 53. Tel 0470-200 50.\nTga Verkstaden.\nTelex 4687 MEKANVX S\nVerksamhet: Tillverkar charkuteri-,\nbageri-, köks- o\nrestaurangmaskiner. Rostfria plåtarbeten\nÅterförsäljare: Göteborg. AB\nScha-ub &amp; Co. Tel 031-19 2190\nMalmö. AB Schaub &amp; Co. Tel\n040-93 42 80\n\nStockholm. AB Schaub &amp; Co. Tel\n08-39 00 40\nAntal anställda: 100\nAktiekapital: 400 000\nPlatschef: Bengt Denward\nEtableringsår 1911.\n\nAHLIN &amp; CO KAMFABRIK AB\n\nPnr 56040\n\nHabo, Box 118. Tel 036-402 56.\nBankgiro 553-8020. Postgiro\n343038-6\n\nVerksamhet: Tillverkar kammar i\ncelluloid o metall\nAntal anställda: 49\nÅrsomsättning: 3 000 000\nAktiekapital: 100 000\nChefer: Pabr Allan Isaksson, fabr\nGösta Ekstrand\nEtableringsår: 1948.",
    "structured": {
        "1": {
            "company_name": "WESTMAN & LUNDMARK, AB",
            "pnr": "199 01",
            "address": "Enköping 1, Lilla v 8. Box 53.",
            "phone_number": "0171-33105",
            "bank_details": {
                "bankgiro": "80-4229",
                "postgiro": "145231"
            },
            "activity": "Betongjärnsaxar, hydrauliska saxar för stångmaterial, hållare för golvläggning. Varmlufts-aggregat, golvplaningsmaskiner, bockningsapparater o -maskiner, lyftgafflar för tegel o betong m m",
            "employees": 60,
            "annual_turnover": 5000000,
            "capital": 40000,
            "key_personnel": [
                {
                    "name": "B M Westman",
                    "position": "Verkst dir"
                }
            ],
            "establishment_year": 1945
        },
        "2": {
            "company_name": "NORDFORS, DAVID",
            "pnr": "702 27",
            "address": "Örebro, Signalg 10.",
            "phone_number": "019-11 1222,1261 29",
            "bank_details": {
                "bankgiro": "61-5426",
                "postgiro": "83620"
            },
            "activity": "Glasmästeri, glas-sliperi o inramningar",
            "employees": 8,
            "annual_turnover": 350000,
            "position": "Chef: Ing David Nordfors",
            "establishment_year": 1926
        },
        "3": {
            "company_name": "JACO FABRIKS AB",
            "pnr": "740 73",
            "address": "Hargshamn",
            "phone_number": "0173-20100",
            "bank_details": {
                "bankgiro": "80-6408",
                "postgiro": "279878-3"
            },
            "activity": "Tillverkar transformatorstationer",
            "employees": 40,
            "annual_turnover": 3000000,
            "capital": 90000,
            "key_personnel": [
                {
                    "name": "Edvin Johnson",
                    "position": "Verkst dir"
                }
            ],
            "establishment_year": 1945
        },
        "4": {
            "company_name": "BAYER AGRO-KEMI AB",
            "pnr": "211 24",
            "address": "Malmö, Bjurög 42",
            "phone_number": "040-93 69 30",
            "bank_details": {
                "bankgiro": "875-5136",
                "postgiro": "431622-4"
            },
            "activity": "Importerar o säljer växtskyddsmedel",
            "capital": 150000,
            "establishment_year": 1951
        },
        "5": {
            "company_name": "JOHANSSON & CO AB, CARL R",
            "pnr": "40127",
            "address": "Göteborg 1, Box 502, Göteborgs Lagerhus, Heurlins Plats.",
            "phone_number": "031-17 0150",
            "bank_details": {
                "bankgiro": "506-5099",
                "postgiro": "12462-8"
            },
            "activity": "Spedition, befrakt-ningar, assuranser, internationella transporter, lagringar, skeppsmäklare o rederiagenter",
            "employees": 75,
            "annual_turnover": 65000000,
            "capital": 300000,
            "key_personnel": [
                {
                    "name": "Erie Pehrsson",
                    "position": "Verkst dir"
                }
            ],
            "establishment_year": 1917
        }
    }
}