{
    "original": "BÄCKLUND, AB NJ\n\nPnr 90110\n\nUmeå 10, Timotejv 59. Box 743. Tel\n090-1189 00. Bankgiro 759-9111.\nPostgiro 28972-8. Tga Bäcklunds.\nTelex 54031\n\nVerksamhet: Järnvaror o\nbyggnadsmaterial i parti o minut\nAntal anställda: 175\nÅrsomsättning: 72 000 000\nAktiekapital: 2500 000\nVerkst din Sven Johansson\nEtableringsår: 1861.\n\nBÄCKLUNDS\nMETALLVARUFABRIK, AB V\n\nPnr 931 00\n\nSkellefteå, N Järnvägsg 56. Tel\n0910-11159, 101 59\nVerksamhet: Tillverkar kokkärl av\naluminium o skärmar för\nbelysningsarmatur. Tryckta o pressade\n\ndetaljer, sammansatta genom\nnitning o hård lödning\nVerkst dir: Stig Bäcklund\nEtableringsår: 1860.\n\nLAGERFORS.ALSTERMO AB\n\nPnr 540 51\n\nLagerfors bruk. Tel 0506-540 00.\nBankgiro 365-0496. Postgiro\n77855-5. Tga Lagermo, Töreboda.\nTelex 5930 LAGERMO S\nVerksamhet: Tillverkar konstläder-,\npärm-, sko- o bokbindarpapp mm\nAktiekapital: 200 000\nVerkst dir: E Langenskiöld\nEtableringsår: 1763.\n\nJOHANSSON GUMMI AB, JOHN\n\nPnr 16126\n\nBromma 1, Ulvsundav 71. Box 86.\nTel 08-80 2840. Bankgiro 33-3105.\nPostgiro 2005-7\n\nVerksamhet: Däck för bilar,\ntraktorer, entreprenadmaskiner etc\nFilial: Stockholm, Vanadisv 6.\nTel 08-33 77 20\n\nStockholm, Cederdalsg 7. Tel\n08-3254 92\n\nHägersten, Västbergav 23. Tel\n08-19 19 19\n\nRegummeringsfabrik: Fellingsbro.\nTel 0589-20840\nAntal anställda: 35\nAktiekapital: 80 000\nVerkst dir: Sigge Ahlin\nEtableringsår: 1935.\n\nSVENSSONS ÄKERI AB, IVAN\n\nPnr 661 00\n\nSäffle, Box 44. Sundsg 7. Tel\n0533-105 43, 106 43. Bankgiro\n114-9392. Postgiro 361493-0\nVerksamhet: Utför alla slags\ntransporter samt schakt- o\nplaneringsarbeten\n\nAntal anställda: 26\nÅrsomsättning: 1 500 000\nAktiekapital: 150 000\nStyrelse: Dir Ivan Svensson (ordf),\nförman Wiktor Svensson, fru Jenny\nSvensson\n\nVeikst dir: Ivan S vensson\nEtableringsår: 1934\nOmbildat till aktiebolag 1960.\n\nSVENSSON &amp; BOURGHARDT,\nJ\n\nPnr 402 71\n\nGöteborg 8, Angpanneg. Box 8847.\n\nTel 031-22 80 80. Bankgiro 50-0009.\n\nPostgiro 12396\n\nChef: Disp Ake Bourghardt\n\nSe AB Paradis Sängar o Sängkläder.\n\nSVENSSONS METALLFABRIK\nAB, J A\n\nPnr 550 02\n\nJönköping 2, Box 2078. Gelbgjutarg\n18. Tel 036-11 01 03. 1214 54.\nPostgiro 9355\n\nVeiksamhet: Tillverkar armatur\nfor gas, vatten, ånga o motorer.\nGjutgods av mässing, rödgods,\nbrons o aluminium\nAntal anställda: 20\nÅrsomsättning: 1500 000\nAktiekapital: 150 000\nVerkst din Disp Sven Axelsson\nEtableringsån 1875.\n\nBLIFA, AB\n\nPnr 122 33\n\nEnskede, Sandsborgsv 50. Tel\n08-59 02 80. Bankgiro 569-7222.\nPostgiro 155667-9\n\nVerksamhet: Tillverkar o säljer\nkemtekniska produkter för\nrengöring, golvvård, disk- o\nhandrengöringsmedel samt\ndesinfektionsmedel. Försäljning av\nstäd-maskiner o redskap, borstar,\nskurdukar, moppgarn m m endast till\nstorförbrukare av typ sjukhus,\nskolor, städbolag, kommuner,\nindustrier m m\n\nAvdelningskontor: 417 07 Göteborg,\nStenkolsg 9. Tel 031-5172 23\n21142 Malmö, Regementsg 6. Tel\n040-352 62\nVarunamn: Blifa\nAntal anställda: 92\nÅrsomsättning: 10 000 000\nAktiekapital: 400 000\nStyrelse: Adv Rolf Dillén (ordf),\ndir Charles Hedkvist, dir Gösta\nFalk, red Hans Gedin\nVerkst dir: Sven Thörnstrand\nEtableringsår: 1945\nNamnändring 1971 från De Blindas\nTekniska Fabrik Aktiebolaget\nBlifa till AB Blifa.\n\nBLINKFYRAR, AB\n\nPnr 245 00\n\nStaffanstorp, Industriv 6. Tel\n046-25 6 2 30. Bankgiro 875-9128.\nPostgiro 536925-1\n\nVerksamhet: Säljer vägmärken o\navstängningslampor\nAktiekapital: 200 000\nVerkst dir: Lars Olsson\nEtableringsår: 1960.\n\nWICKSTRUM &amp; SÖNER, AB\n\nPnr 126 48\n\nHägersten, Hägerstensv 123. Tel\n08-45 1801. Bankgiro 413-6362.\nPostgiro 194698-7\nVerksamhet: Tillverkar vävplast\nAktiekapital: 15 000\nVerkst dir. Oscar Wickström\nEtableringsår: 1934.\n\nHANSSON &amp; CO AB, SVEN\n\nPnr 16130\n\nBromma, Ranhammarsv 15. Tel\n08-26 26 30. Bankgiro 743-5076.\nPostgiro 4811-6. Tga Svenco\nVerksamhet: Säckfabrik,\npappersvaror en gros\nVarunamn: Sanigén\nAntal anställda: 30\nAktiekapital: 200 000\nStyrelse: Dir Folke Lindberg (ordf),\ndir Lennart Hansson\nVerkst dir: Lennart Hansson\nEtableringsår: 1921\nOmbildat till aktiebolag 1938.\nDotterbolag: Sanila Produkter AB,\nSödra Valbo.\n\nHANSON AB, BYGGNADS.\nFIRMAN VIKTOR\n\nPnr 113 48\n\nStockholm, Hagag 4. Tel\n08-24 56 60\n\nVerksamhet:\nByggnadsentreprenörer\n\nAktiekapital: 500 000\n\nVerkst dir: Civiling Rune Hanson\n\nEtableringsår: 1914.\n\nMÅNSON AB, MALTE\n\nPnr 585 90\n\nLinköping, Hackeforsv 1. Tel\n013-10 2200. Bankgiro 60-8053.\nPostgiro 23771. Tga Motorverktyg.\nTelex 64949 MMPROD S\nVerksamhet: Specialfirma för\nmo-tcrrenoveringar o -reservdelar.\nTillverkar ventilrenoveringsmaskiner\no -verktyg, poler- o\nvinkelslipma-skiner Elite. Generalrepresentant\nför Perkins o Leyland\ndieselmotorer o Bergin slipmateriel\nVarunamn: Bergin, Elite, Leyland,\nPerkins\n\nAntal anstäUda: 175\nÅrsomsättning: 13 500 000\nAktiekapital: 800 000\n\nStyrelse: Dir M Månson, ing B\nMånson, adv W Brodin, dir L-E Nygren\nVerkst dir: Bert Månson\nEtableringsår 1918\nOmbildat till aktiebolag 1941.\n\nMÅRDÉN.ALDERU AB\n\nPnr 630 04\n\nEskilstuna 4, Vagnmakarev 7. Box\n4066. Tel 016-13 16 55, 13 16 15.\nBankgiro 831-2126. Postgiro\n135993-4\n\nVerksamhet: Tillverkar karosserier,\nförarhytter för traktorer m m\nAktiekapital: 10 000\nVerkst dir: Ing Gunnar Mårdén\nEtableringsår: 1930.\n\nALFTA SKOGSBOLAG AB\n\nPnr 822 00\n\nAlfta, Box 1035. Tel 0271-10163.\nBankgiro 784-7569. Postgiro\n144867-9\n\nVerksamhet: Tillverkar stockpanel,\nfjällpanel, foder, sockel o lister\nAntal anställda: 25\nÅrsomsättning: 1400 000\nAktiekapital: 35 000\nVerkst dir: Jonas R Olmårs\nEtableringsår: 1955.\n\nFRÖBERG AB, GUNNAR\n\nPnr 172 39\n\nSundbyberg, Humbleg 17. Tel\n08-290145. Postgiro 378571\nVerksamhet: Åkeri- o\nentreprenadverksamhet i Stor-Stockholm\nAntal anställda: 70\nÅrsomsättning: 20 000 000\nAktiekapital: 50 000\nStyrelse: Dir G Fröberg (ordf), dir\nB Berglund, aukt rev T Wiberg,\naukt rev O Jelf\nVerkst dir: Gunnar Fröberg\nV verkst dir: Björn Berglund\nEtableringsår: 1966.",
    "structured": {
        "0": {
            "company_name": "BÄCKLUND, AB NJ",
            "pnr": "90110",
            "address": "Umeå 10, Timotejv 59. Box 743",
            "phone_number": "090-1189 00",
            "bank_details": {
                "bankgiro": "759-9111",
                "postgiro": "28972-8"
            },
            "activity": "Järnvaror o byggnadsmaterial i parti o minut",
            "employees": 175,
            "annual_turnover": 72000000,
            "capital": 2500000,
            "key_personnel": [
                {
                    "name": "Sven Johansson",
                    "position": "Verkst din"
                }
            ],
            "establishment_year": 1861
        },
        "1": {
            "company_name": "BÄCKLUNDS METALLVARUFABRIK, AB V",
            "pnr": "931 00",
            "address": "Skellefteå, N Järnvägsg 56",
            "phone_number": "0910-11159, 101 59",
            "activity": "Tillverkar kokkärl av aluminium o skärmar för belysningsarmatur.",
            "establishment_year": 1860
        },
        "2": {
            "company_name": "LAGERFORS.ALSTERMO AB",
            "pnr": "540 51",
            "address": "Lagerfors bruk",
            "phone_number": "0506-540 00",
            "bank_details": {
                "bankgiro": "365-0496",
                "postgiro": "77855-5"
            },
            "activity": "Tillverkar konstläder-, pärm-, sko- o bokbindarpapp mm",
            "capital": 200000,
            "key_personnel": [
                {
                    "name": "E Langenskiöld",
                    "position": "Verkst dir"
                }
            ],
            "establishment_year": 1763
        },
        "3": {
            "company_name": "JOHANSSON GUMMI AB, JOHN",
            "pnr": "16126",
            "address": "Bromma 1, Ulvsundav 71. Box 86",
            "phone_number": "08-80 2840",
            "bank_details": {
                "bankgiro": "33-3105",
                "postgiro": "2005-7"
            },
            "activity": "Däck för bilar, traktorer, entreprenadmaskiner etc",
            "employees": 35,
            "capital": 80000,
            "key_personnel": [
                {
                    "name": "Sigge Ahlin",
                    "position": "Verkst dir"
                }
            ],
            "establishment_year": 1935
        },
        "4": {
            "company_name": "SVENSSONS ÄKERI AB, IVAN",
            "pnr": "661 00",
            "address": "Säffle, Box 44. Sundsg 7",
            "phone_number": "0533-105 43, 106 43",
            "bank_details": {
                "bankgiro": "114-9392",
                "postgiro": "361493-0"
            },
            "activity": "Utför alla slags transporter samt schakt- o planeringsarbeten",
            "employees": 26,
            "annual_turnover": 1500000,
            "capital": 150000,
            "key_personnel": [
                {
                    "name": "Ivan Svensson",
                    "position": "V verkst dir"
                },
                {
                    "name": "Wiktor Svensson",
                    "position": "förman"
                },
                {
                    "name": "Jenny Svensson",
                    "position": "fru"
                }
            ],
            "establishment_year": 1934
        },
        "5": {
            "company_name": "SVENSSON & BOURGHARDT, J",
            "pnr": "402 71",
            "address": "Göteborg 8, Angpanneg. Box 8847",
            "phone_number": "031-22 80 80",
            "bank_details": {
                "bankgiro": "50-0009",
                "postgiro": "12396"
            },
            "key_personnel": [
                {
                    "name": "Ake Bourghardt",
                    "position": "Chef"
                }
            ]
        },
        "6": {
            "company_name": "SVENSSONS METALLFABRIK AB, J A",
            "pnr": "550 02",
            "address": "Jönköping 2, Box 2078. Gelbgjutarg 18",
            "phone_number": "036-11 01 03. 1214 54",
            "postgiro": "9355",
            "activity": "Tillverkar armatur for gas, vatten, ånga o motorer. Gjutgods av mässing, rödgods, brons o aluminium",
            "employees": 20,
            "annual_turnover": 1500000,
            "capital": 150000,
            "key_personnel": [
                {
                    "name": "Sven Axelsson",
                    "position": "Verkst din Disp"
                }
            ],
            "establishment_year": 1875
        },
        "7": {
            "company_name": "BLIFA, AB",
            "pnr": "122 33",
            "address": "Enskede, Sandsborgsv 50",
            "phone_number": "08-59 02 80",
            "bank_details": {
                "bankgiro": "569-7222",
                "postgiro": "155667-9"
            },
            "activity": "Tillverkar o säljer kemtekniska produkter för rengöring, golvvård, disk- o handrengöringsmedel samt desinfektionsmedel."
        },
        "8": {
            "company_name": "BLINKFYRAR, AB",
            "pnr": "245 00",
            "address": "Staffanstorp, Industriv 6",
            "phone_number": "046-25 6 2 30",
            "bank_details": {
                "bankgiro": "875-9128",
                "postgiro": "536925-1"
            },
            "activity": "Säljer vägmärken o avstängningslampor",
            "capital": 200000
        },
        "9": {
            "company_name": "WICKSTRUM & SÖNER, AB",
            "pnr": "126 48",
            "address": "Hägersten, Hägerstensv 123",
            "phone_number": "08-45 1801",
            "bank_details": {
                "bankgiro": "413-6362",
                "postgiro": "194698-7"
            },
            "activity": "Tillverkar vävplast",
            "capital": 15000
        }
    }
}