{
    "original": "CAM-SERVICE AB\n\nPnr 12247\n\nEnskede, Fiskebyv 5. Tel\n08-915957, 9167 63. Bankgiro\n478-7875. Postgiro 657729-0\nVerksamhet: Beräkning,\nkonstruktion o tillverkning av kurvor\n(kammar) för automatsvarvar\nÅrsomsättning: 102 000\nAktiekapital: 30 000\nStyrelse: Fabr Runo Gustavsson\n(ordf), fru Gun Gustavsson\nEtableringsår: 1962\nOmbildat till aktiebolag 1964.\n\nCANADA BYGG AB\n\nPnr 17103\n\nSolna 3, Viktoriag 9. Box 344. Tel\n08-82 00 80. Bankgiro 235-2151.\nPostgiro 56008-5\nVerksamhet: Trä o\nbyggmaterialrörelse\n\nAvdelningskontor: Stockholm,\nLidingö, Vallentuna\nAntal anställda: 60\nÅrsomsättning: 20 000 000\nAktiekapital: 100 000\nVerkst dir: Sune Swartling\nEtableringsår: 1927.\n\nDORFH REKLAM AB, HANS\n\nPnr 13101\n\nNacka 1, Box 64. Alphyddev 45-47.\nTel 08-716 27 40. Bankgiro\n746-0868. Postgiro 258697-2\nVerksamhet: Konsulter i\nmarknadsföring. Försäljning o reklam\nAntal anställda: 13\nÅrsomsättning: 4 000 000\nAktiekapital: 40 000\nVerkst dir: Hans Dorfh\nEtableringsår: 1960.\n\nekenberg &amp; huldberg,ab\n\nPnr 20120\n\nMalmö 1, Murmansg 120. Box 27.\nTel 040-93 66 20. Bankgiro\n87-0116. Postgiro 38183. Tga\nHuldbergs\n\nVerksamhet: Säljer papper en gros\nAntal anställda: 27\nÅrsomsättning: 8 176 000\nAktiekapital: 450 000\nVerkst dlr: Paolo Pesciatini\nEtableringsår: 1907.\n\nekengren ab,\ningeniors-firma conrad\n\nPra- 18107\n\nLidingö 7, Box 744. Kosterv 3. Tel\n08-767 0185. Bankgiro 410-0137.\nPostgiro 242091-7. Tga Inkon ek.\nTelex 17331\n\nVerksamhet: säljer eldhärdiga\nugnsdetaljer, eldfasta massor, ugnar,\nultraljudutrustningar, utrustning för\nprocessregleringar,\nviskometerut-rustningar o teflon\nAktiekapital: 40 000\nStyrelse: Dir Conrad Ekengren\nfru Maj-Lise Ekengren\nVerkst dir: Conrad Ekengren\nEtableringsår: 1947\nOmbildat till aktiebolag 1961.\n\nekengärds\nmaskinfabrik ab\n\nPnr 294 50\n\nSölvesborg, Ysane. Tel\n0456-610 50, 610 51. Bankgiro 285-9569.\nPostgiro 164060-6\nVerksamhet: Tillverkar\nlantbruksmaskiner, traktorvagnar o hydrau\n-liska utrustningar\nAntal anställda: 50\nAktiekapital: 500 000\nVerkst dir: Bertil Nelson\nEtableringsår: 1939.\n\nABC ANNONSBYRÅ AB\n\nPnr 11181\n\nStockholm 1, Vasag 11. Box 1108.\n\nTel 08-23 46 60. Bankgiro 56-3573.\nPostgiro 559035. Tga\nABCAdverti-sing\n\nVerksamhet: Annonsbyrå\nAvdelningskontor: 40110 Göteborg,\nSten Sture g 4. Tel 031-20 08 50.\nChef: Dir Jan-Ake Tideman\n211 30 Malmö, Slussg 25. Tel\n040-10 05 75. Chef: Dir Gunnar Sandwall\nAntal anställda: 55\nÅrsomsättning: 19 900 000\nAktiekapital: 420 000\nStyrelse: Adv Mauritz Grönberger\n(ordf), dir Kurt Söderberg, dir\nGöran C-O Claesson, dir H Patric\nBergman, dir Lars Grönberger, dir\n\nJan-Ake Tideman\nVerkst din H Patric Bergman\nV Verkst dir: Lars Grünberger\nKamrer: Ewald Lundquist\nEtableringsår: 1958.\n\nVEGBORN, AB BRÖDERNA\n\nPnr 52011\n\nVegby, Box 11 Tel 0321-720 56.\nBankgiro 840-6647. Postgiro\n284435\n\nVerksamhet: Tillverkar sport- o\nfritidskläder samt jackor o byxor\nAntal anställda: 40\nÅrsomsättning: 2 300 000\nAktiekapital: 25 000\nVerkst din Olof Vegborn\nEtableringsån 1955.\n\nRAT\n\nRATIONELLA INDUSTRI.\nSYSTEM AB, RIAB\n\nPnr 127 32\n\nSkälholmen, Algrytev 19-21. Tel\n08-88 04 00. Bankgiro 713-1469.\nPostgiro 59595-9\nVerksamhet: Bedriver konsultativ\nverksamhet inom ADB-sektorn\nsåsom systemutformning,\nprojektledning, programmering,\nproduktionsadministration\nAntal anställda: 12\nÅrsomsättning: 1000 000\nAktiekapital: 20000\nVerkst dir: Lars Spångberg\nV verkst dir: Hans Attergren\nEtableringsån 1967.\n\nVOLTA, FÖRSÄLJNINGS AB\n\nPnr 103 42\n\nStockholm 40, Box 40070.\nKlara-bergsg 33. Tel 08-14 03 85.\nBankgiro 56-7083. Postgiro 949-8. Tga\nVolta\n\nVeiksamhet: Säljer elektr\ndammsugare\n\nAntal anställda: 25\nNettoförsäljning: 20 000 000\nAktiekapital: 200 000\nVerkst dir: Torkel Bragëe\nEtableringsår 1934.\n\nTRÄ\n\nTRYCKARE AB, FREDRIK\n\nPnr 17154\n\nSolna, Albyg 109. Tel 08-984601,\n9846 02. Bankgiro 202-8553.\nPostgiro 238300-8\n\nVerksamhet: Offsettryckeri\nVerkst dir: Fredrik Teiner\nEtableringsår: 1968.\n\nJÄMTENTREPRENAD AB\n\nPnr 83100\n\nÖstersund, Odensalag 39. Tel\n063-176 20. Bankgiro 51-1693.\nPostgiro 123130\n\nVerksamhet: Schaktning o\nvägbyggnader på entreprenad\nÅrsomsättning: 2 000 000\nAktiekapital: 25 000\nVerkst dir. Ing Erik Persson\nEtableringsår. 1967.\n\nSTILLE-WERNER, AB\n\nPnr 102 61\n\nStockholm 4, Box 4051. Bondeg 21.\nTel 08-44 92 00. Bankgiro 476-4783.\nPostgiro 3494-2. Tga Stille\nVerksamhet: Tillverkar kirurgiska\ninstrument, operationsmöbler,\nbandageartiklar, blöjor, blöjsnibbar\nsamt dambindor\nVarunamn: Bambino, Sanisept,\nStille\n\nAntal anstäUda: 665\nÅrsomsättning: 70 000 000\nAktiekapital: 1400 000\nStyrelse: Bankdir Sven Raab (ordf),\nfru Marga Hedberg, docent Sven\nRune Johnson, med dr Harald\nNil-sonne, bankdir Gösta Olson, prof\nEinar Perman, med dr Georg\nöhn-gren\n\nVerkst dir: Hans Hessner\nEkonomidir: Kurt Andersson\nEtableringsår: 1841.",
    "structured": {
        "firms": [
            {
                "company_name": "CAM-SERVICE AB",
                "pnr": "12247",
                "address": "Enskede, Fiskebyv 5",
                "phone_number": "08-915957, 9167 63",
                "bank_details": {
                    "bankgiro": "478-7875",
                    "postgiro": "657729-0"
                },
                "activity": "Beräkning, konstruktion o tillverkning av kurvor (kammar) för automatsvarvar",
                "annual_turnover": 102000,
                "capital": 30000,
                "key_personnel": [
                    {
                        "name": "Fabr Runo Gustavsson",
                        "position": "ordf"
                    },
                    {
                        "name": "fru Gun Gustavsson"
                    }
                ],
                "establishment_year": 1962
            },
            {
                "company_name": "CANADA BYGG AB",
                "pnr": "17103",
                "address": "Solna 3, Viktoriag 9, Box 344",
                "phone_number": "08-82 00 80",
                "bank_details": {
                    "bankgiro": "235-2151",
                    "postgiro": "56008-5"
                },
                "activity": "Trä o byggmaterialrörelse",
                "employees": 60,
                "annual_turnover": 20000000,
                "capital": 100000,
                "establishment_year": 1927
            },
            {
                "company_name": "DORFH REKLAM AB, HANS",
                "pnr": "13101",
                "address": "Nacka 1, Box 64, Alphyddev 45-47",
                "phone_number": "08-716 27 40",
                "bank_details": {
                    "bankgiro": "746-0868",
                    "postgiro": "258697-2"
                },
                "activity": "Konsulter i marknadsföring. Försäljning o reklam",
                "employees": 13,
                "annual_turnover": 4000000,
                "capital": 40000,
                "key_personnel": [
                    {
                        "name": "Hans Dorfh",
                        "position": "Verkst dir"
                    }
                ],
                "establishment_year": 1960
            },
            {
                "company_name": "ekenberg & huldberg,ab",
                "pnr": "20120",
                "address": "Malmö 1, Murmansg 120, Box 27",
                "phone_number": "040-93 66 20",
                "bank_details": {
                    "bankgiro": "87-0116",
                    "postgiro": "38183"
                },
                "activity": "Säljer papper en gros",
                "employees": 27,
                "annual_turnover": 8176000,
                "capital": 450000,
                "key_personnel": [
                    {
                        "name": "Paolo Pesciatini",
                        "position": "Verkst dlr"
                    }
                ],
                "establishment_year": 1907
            },
            {
                "company_name": "ekengren ab, ingeniors-firma conrad",
                "pnr": "18107",
                "address": "Lidingö 7, Box 744, Kosterv 3",
                "phone_number": "08-767 0185",
                "bank_details": {
                    "bankgiro": "410-0137",
                    "postgiro": "242091-7"
                },
                "activity": "säljer eldhärdiga ugnsdetaljer, eldfasta massor, ugnar, ultraljudutrustningar, utrustning för processregleringar, viskometerrustningar o teflon",
                "capital": 40000,
                "key_personnel": [
                    {
                        "name": "Dir Conrad Ekengren",
                        "position": "Verkst dir"
                    },
                    {
                        "name": "fru Maj-Lise Ekengren"
                    }
                ],
                "establishment_year": 1947
            },
            {
                "company_name": "ekengärds maskinfabrik ab",
                "pnr": "294 50",
                "address": "Sölvesborg, Ysane",
                "phone_number": "0456-610 50, 610 51",
                "bank_details": {
                    "bankgiro": "285-9569",
                    "postgiro": "164060-6"
                },
                "activity": "Tillverkar lantbruksmaskiner, traktorvagnar o hydrauliska utrustningar",
                "employees": 50,
                "capital": 500000,
                "key_personnel": [
                    {
                        "name": "Bertil Nelson",
                        "position": "Verkst dir"
                    }
                ],
                "establishment_year": 1939
            },
            {
                "company_name": "ABC ANNONSBYRÅ AB",
                "pnr": "11181",
                "address": "Stockholm 1, Vasag 11, Box 1108",
                "phone_number": "08-23 46 60",
                "bank_details": {
                    "bankgiro": "56-3573",
                    "postgiro": "559035"
                },
                "activity": "Annonsbyrå",
                "employees": 55,
                "annual_turnover": 19900000,
                "capital": 420000,
                "key_personnel": [
                    {
                        "name": "Adv Mauritz Grönberger",
                        "position": "ordf"
                    },
                    {
                        "name": "dir Kurt Söderberg"
                    },
                    {
                        "name": "dir Göran C-O Claesson"
                    },
                    {
                        "name": "dir H Patric Bergman"
                    },
                    {
                        "name": "dir Lars Grönberger"
                    },
                    {
                        "name": "dir Jan-Ake Tideman",
                        "position": "Verkst din"
                    }
                ],
                "establishment_year": 1958
            },
            {
                "company_name": "VEGBORN, AB BRÖDERNA",
                "pnr": "52011",
                "address": "Vegby, Box 11",
                "phone_number": "0321-720 56",
                "bank_details": {
                    "bankgiro": "840-6647",
                    "postgiro": "284435"
                },
                "activity": "Tillverkar sport- o fritidskläder samt jackor o byxor",
                "employees": 40,
                "annual_turnover": 2300000,
                "capital": 25000,
                "key_personnel": [
                    {
                        "name": "Olof Vegborn",
                        "position": "Verkst din"
                    }
                ],
                "establishment_year": 1955
            },
            {
                "company_name": "RATIONELLA INDUSTRI. SYSTEM AB, RIAB",
                "pnr": "127 32",
                "address": "Skälholmen, Algrytev 19-21",
                "phone_number": "08-88 04 00",
                "bank_details": {
                    "bankgiro": "713-1469",
                    "postgiro": "59595-9"
                },
                "activity": "Bedriver konsultativ verksamhet inom ADB-sektorn såsom systemutformning, projektledning, programmering, produktionsadministration",
                "employees": 12,
                "annual_turnover": 1000000,
                "capital": 20000,
                "key_personnel": [
                    {
                        "name": "Lars Spångberg",
                        "position": "Verkst dir"
                    },
                    {
                        "name": "Hans Attergren",
                        "position": "V verkst dir"
                    }
                ],
                "establishment_year": 1967
            },
            {
                "company_name": "VOLTA, FÖRSÄLJNINGS AB",
                "pnr": "103 42",
                "address": "Stockholm 40, Box 40070, Klara-bergsg 33",
                "phone_number": "08-14 03 85",
                "bank_details": {
                    "bankgiro": "56-7083",
                    "postgiro": "949-8"
                },
                "activity": "Säljer elektr dammsugare",
                "employees": 25,
                "annual_turnover": 20000000,
                "capital": 200000,
                "key_personnel": [
                    {
                        "name": "Torkel Bragëe",
                        "position": "Verkst dir"
                    }
                ],
                "establishment_year": 1934
            },
            {
                "company_name": "TRYCKARE AB, FREDRIK",
                "pnr": "17154",
                "address": "Solna, Albyg 109",
                "phone_number": "08-984601, 9846 02",
                "bank_details": {
                    "bankgiro": "202-8553",
                    "postgiro": "238300-8"
                },
                "activity": "Offsettryckeri",
                "key_personnel": [
                    {
                        "name": "Fredrik Teiner",
                        "position": "Verkst dir"
                    }
                ],
                "establishment_year": 1968
            },
            {
                "company_name": "JÄMTENTREPRENAD AB",
                "pnr": "83100",
                "address": "Östersund, Odensalag 39",
                "phone_number": "063-176 20",
                "bank_details": {
                    "bankgiro": "51-1693",
                    "postgiro": "123130"
                },
                "activity": "Schaktning o vägbyggnader på entreprenad",
                "annual_turnover": 2000000,
                "capital": 25000,
                "key_personnel": [
                    {
                        "name": "Ing Erik Persson",
                        "position": "Verkst dir"
                    }
                ],
                "establishment_year": 1967
            },
            {
                "company_name": "STILLE-WERNER, AB",
                "pnr": "102 61",
                "address": "Stockholm 4, Box 4051, Bondeg 21",
                "phone_number": "08-44 92 00",
                "bank_details": {
                    "bankgiro": "476-4783",
                    "postgiro": "3494-2"
                },
                "activity": "Tillverkar kirurgiska instrument, operationsmöbler, bandageartiklar, blöjor, blöjsnibbar samt dambindor",
                "employees": 665,
                "annual_turnover": 70000000,
                "capital": 1400000,
                "key_personnel": [
                    {
                        "name": "Hans Hessner",
                        "position": "Verkst dir"
                    },
                    {
                        "name": "Kurt Andersson",
                        "position": "Ekonomidir"
                    }
                ],
                "establishment_year": 1841
            }
        ]
    }
}