{
    "original": "AHLGREN, AB ALLAN\n\nPnr 330 33\n\nHillerstorp, Marieholmsbruk. Tel\n0370-93013\n\nVerksamhet: Tillverkar råttfällor\n(burfällor), fågelmatare,\nbärrens-ningssåll\n\nChef: Pabr Allan Ahlgren.\n\nAHLGRENS TEKN FABRIK\nAB, F\n\nPnr 800 04\n\nGävle 4, S Skeppsbron 26-28. Pack.\nTel 026-12 97 50. Bankgiro 78-3742.\nPostgiro 5123. Tga Läkerol\nVerksamhet: Tillverkar o försäljer\nLäkerol o konfektyrer\nAntal anställda: 223\nÅrsomsättning: 29 100 000\nAktiekapital: 800 000\nStyrelse: Adv Gunnar Lindh (ordf),\ndir Bengt Ahlgren, exportdir\nLennart Ahlgren, dir Robert Ahlgren,\nförsäljn-dir Sture Ahlgren, dir\nBirger Bellander, adv Ola Wettergren\nVerkst dir: Bengt Ahlgren\nV verkst dir: Robert Ahlgren\nEtableringsår: 1885.\n\nHAFIG, HANDELSFIRMA\n\nPnr 122 46\n\nEnskede, Getfotsv 1. Tel 08-\n\n59 25 30, 59 60 00. Bankgiro 74-5238.\n\nPostgiro 604120\n\nVerksamhet: Grossistförsäljning\ninom rörledningsbranchen\nAntal anställda: 8\nÅrsomsättning: 1250 000\nVerkst dir: Disp Gunnar Glitsing\nEtableringsår: 1956.\n\nKLICHÉANSTALTEN I SUNDS.\nVALL YNGVE JOHANSSON\n\nPnr 852 31\n\nSundsvall, Köpmang 5. Tel\n060-11 2116. Bankgiro 18-0311.\nPostgiro 82670\n\nVerksamhet: Tillverkar klichéer,\n\nteckningar, offsetplåtar samt\ngummiklichéer\n\nChef: Yngve Johansson\nEtableringsår: 1919.\n\nKLICHÉBOLAGET I\nJONKO-PING AB\n\nPnr 550 02\n\nJönköping 2, Syrgasv. Box 2182.\nTel 036-1273 19, 12 52 21\nVerksamhet: Tillverkar klichéer,\nförslag, teckningar o retuscher\nAntal anställda: 10\n.Aktiekapital: 30000\nFirmatecknare: Hans Hansson,\nIngvar Kiland, Ingvar Claesson\nEtableringsår: 1950.\n\nKLICHÉ-CENTRALEN I\nHÄLSINGBORG AB\n\nPnr 25104\n\nHelsingborg 1, Box 270. Ingenjörsg\n3. Tel 042-13 90 80. Bankgiro\n653-0398. Postgiro 135562-7\nVerksamhet: Klichétillverkning\nAktiekapital: 5 000\nVerkst dir: Björn Frick\nEtableringsår: 1937.\n\nGIBBS AB\n\nPnr 103 40\n\nStockholm 40, Sveav 9-11. Fack.\nTel 08-23 42 80, 23 26 50.\nTelex 1332 EXPEDO S\nVerksamhet: Tillverkar mun-,\nhår-o hudvårdsmedel samt tvål\nAktiekapital: 1000 000\nVerkst dir. Hans L N F Fries\nEtableringsår: 1933.\n\nWIDEX-AKUSTIK, AB\n\nPnr 21134\n\nMalmö, Lilla Torg 1. Tel\n040-111643,11 14 43. Bankgiro 87-0484.\nPostgiro 530386. Tga Widexakustik\nVerksamhet: Säljer hörapparater\nsamt batterier o reservdelar till\ndito. Reparationer o fullständig\nservice av hörapparater\nAktiekapital: 20 000\nStyrelse: Adv Stig E Jansson, dir\nEgon Jansson\nDisp: Arne Ericsson\nEtableringsår: 1958.\n\nOPERAKÄLLAREN, AB\n\nPnr 11186\n\nStockholm, Operahuset. Box 1616.\nTel 08-24 27 00\n\nFör vidare uppgifter se moderbolaget\nTöre Wretman Restauranger AB.\n\nOPPBOGA AB\n\nPnr 71041\n\nFellingsbro. Tel 0589-205 10.\nBankgiro 16-0323. Postgiro 163943.\nTelex 73341. Tga Oppoga, Arboga\nVerksamhet: Papp- o kartongbruk\nAntal anställda: 150\nÅrsomsättning: 22 850 000\nAktiekapital: 4 500 000\nVerkst dir: Disp Albrekt Werner\nEtableringsår: 1901.\n\nSILJANS SÅGVERKS AB\n\nPnr 790 50\n\nMora-Noret, Pack 7. Tel\n0250-135 10. Bankgiro 797-3548.\nPostgiro 6000-4. Tga Siljanwood, Mora.\nTelex 7750\n\nVeiksamhet: Tillverkar sågade o\nhyvlade trävaror\nAntal anställda: 100\nÅrsomsättning: 16 000 000\nAktiekapital: 215 500\nVerkst din Dir Stig Fredell\n(Stockholm)\nEtableringsån 1935.\n\nSILJANSNÄS SÅGVERKS.\nBOLAG, AB\n\nPnr 790 34\n\nSiljansnäs, Box 415. Tel\n0247-22110. Bankgiro 46-7220.\nPostgiro 79626\n\nVerksamhet: Tillverkar\nmonteringsfärdiga trähus o timmerstugor\nAntal anställda: 45\nÅrsomsättning: 2150 000\nAktiekapital: 32500\nVerkst din Disp Erik Skalk\nEtableringsàr: 1946.\n\nSILKETVINNERI, AB\n\nPnr 44100\n\nAlingsås, Sidenv. Tel 0322-190 30.\nBankgiro 889-7340. Postgiro\n11305-0. Tga Silketvinn\nVerksamhet: Tvinning av\ncrepe-nylongarn\nAntal anställda: 75\nÅrsomsättning: 10 000 000\nAktiekapital: 100000\nVerkst din W F Morawek\nEtableringsàr: 1953.\n\nSILK.SCREEN. COMPANY\n\nPnr 630 02\n\nEskilstuna 2, Box 2033. Nyforsg\n37. Tel 016-14 64 60. Postgiro\n9825 6-1\n\nVerksamhet: Silk-screentryckeri,\ndekalkomanier, skyltar, tryck på\npärmar samt boardskyltar\nAntal anställda: 6\nChefer. Fabr Ove Nilsson, fabr\nSivert Johansson\nEtableringsàr 1955.\n\nGULLANDER AB, LENNART\n\nPnr 12108\n\nJohanneshov 8, Storsjö v 19. Box\n807. Tel 08-91 0125. Bankgiro\n283-9603. Postgiro 503016-8. Tga\nEllgull. Telex 17547 ELLGULL S\nVerksamhet: Tillverkar o säljer\ntryekluftarmatur o\nindustriförnödenheter\n\nAvdelningskontor: Malmö,\nGlas-bruksg 4. Tel 040-16 0160\nAntal anställda: 15\nÅrsomsättning: 5 500 000\nAktiekapital: 75 000\nVerkst dir: Lennart Gullander\nEtableringsår: 1953.\n\nGULLASKRUFS\nGLAS-BRUKS AB\n\nPnr 38040\n\nOrrefors, Gullaskruv. Tel\n0481-320 80, 320 81. Postgiro 165600-8.\nTga Gullglas\n\nVerksamhet: Tillverkar hushålls-,\nprydnads-, tekniskt glas samt\nstrålkastarglas för bilar m m\nAntal anställda: 70\nÅrsomsättning: 4 000 000\nAktiekapital: 174 000\nStyrelse: Dr Rolf Jönsson (ordf),\nfru Marianne Andersson, dir\nLennart Andersson\nVerkst dir: Lennart Andersson\nEtableringsår: 1893\nOmbildat till aktiebolag 1927.\n\nGULLBERGS LIVSMEDEL, AB\n\nPnr 542 00\n\nMariestad, Nya Torget 4. Tel\n0501-17070. Bankgiro 174-8318.\nPost-|giro 329281-0\n\nVerksamhet: Tillverkar o säljer\nlivsmedel\n\nAntal anställda: 100\nÅrsomsättning: 28 800 000\nAktiekapital: 190 000\nVerkst dir: Per W Gullberg\nEtableringsår: 1891.\n\nGULLBERGS\nMASKINFABRIKS AB\n\nPnr 360 61\n\nLindås. Tel 0471-108 70. Bankgiro\n845-9339. Postgiro 191512-3. Tga\nLindverk, Emmaboda. Telex 43067\nVerksamhet: Tillverkar maskiner\nför byggnadsindustrin\nAntal anställda: 175\nÅrsomsättning: 12 000 000\nAktiekapital: 868 000\nStyrelse: Ing Lennart Hesselman\n(ordf), ing Edvin Johansson, dir\nL O Haggard, disp Edvin B\nJohanson\n\nVerkst dir: Edvin B Johanson\nEtableringsår: 1871.\n\nSKÅNE SÅG EN, AB\n\nPnr 275 00\n\nSjöbo, Söderg 4. Tel 0416-103 75,\n106 00. Bankgiro 662-7608.\nPostgiro 346740-4\n\nVerksamhet: Säljer sågade trävaror\nsamt byggnadsmateriel\nAntal anställda: 23\nÅrsomsättning: 2 900 000\nAktiekapital: 300 000\nVerkst din Nils Bernh Nilsson\nEtableringsår: 1946.\n\nINTERSVETS-FAGRELL AB\n\nPnr 102 60\n\nStockholm 4, Malmgårdsv 63. Fack.\nTel 08-44 00 95. Tga Intersvets\nVerksamhet: Säljer maskiner o\nutrustningar för motstånds- o\nbåg-svetsning, gassvetsning o skärning,\nplasmaskärning o bågluftmejsling.\nElektroder, svetstråd o\nsvetspulver. Manipulatorer. Alla slags\nsvetstillbehör. Maskiner för\nfogberedning o annan plåtbearbetning\nAktiekapital: 100 000\nVerkst dir O Hejdenberg.\n\nINTER-TEST MARKETING AB\n\nPnr 171 65\n\nSolna, Bagartorpsringen 80. Tel\n08-85 01 90. Telex 10896\nVerksamhet: Alla slags\nmarknadsundersökningar o tester\nAntal anstäUda: 17\nÅrsomsättning: 1 500 000\nAktiekapital: 5 000\nVerkst dir: Birgitta Winborg\nEtableringsår: 1955.",
    "structured": {
        "1": {
            "company_name": "AHLGREN, AB ALLAN",
            "activity": "Tillverkar råttfällor (burfällor), fågelmatare, bärrensningssåll",
            "establishment_year": 0
        },
        "2": {
            "company_name": "AHLGRENS TEKN FABRIK AB",
            "address": "Gävle 4, S Skeppsbron 26-28",
            "phone_number": "026-12 97 50",
            "bank_details": {
                "bankgiro": "78-3742",
                "postgiro": "5123"
            },
            "activity": "Tillverkar o försäljer Läkerol o konfektyrer",
            "employees": 223,
            "annual_turnover": 29100000,
            "capital": 800000,
            "key_personnel": [
                {
                    "name": "Adv Gunnar Lindh",
                    "position": "Ordförande"
                },
                {
                    "name": "dir Bengt Ahlgren",
                    "position": null
                },
                {
                    "name": "exportdir Lennart Ahlgren",
                    "position": null
                },
                {
                    "name": "dir Robert Ahlgren",
                    "position": null
                },
                {
                    "name": "försäljndir Sture Ahlgren",
                    "position": null
                },
                {
                    "name": "dir Birger Bellander",
                    "position": null
                },
                {
                    "name": "adv Ola Wettergren",
                    "position": null
                }
            ],
            "establishment_year": 1885
        },
        "3": {
            "company_name": "HAFIG, HANDELSFIRMA",
            "address": "Enskede, Getfotsv 1",
            "phone_number": "08-59 25 30, 59 60 00",
            "bank_details": {
                "bankgiro": "74-5238",
                "postgiro": "604120"
            },
            "activity": "Grossistförsäljning inom rörledningsbranchen",
            "employees": 8,
            "annual_turnover": 1250000,
            "establishment_year": 1956
        },
        "4": {
            "company_name": "KLICHÉANSTALTEN I SUNDS. VALL YNGVE JOHANSSON",
            "address": "Sundsvall, Köpmang 5",
            "phone_number": "060-11 2116",
            "bank_details": {
                "bankgiro": "18-0311",
                "postgiro": "82670"
            },
            "activity": "Tillverkar klichéer, teckningar, offsetplåtar samt gummiklichéer",
            "establishment_year": 1919
        },
        "5": {
            "company_name": "KLICHÉBOLAGET I JONKO-PING AB",
            "address": "Jönköping 2, Syrgasv. Box 2182",
            "phone_number": "036-1273 19, 12 52 21",
            "activity": "Tillverkar klichéer, förslag, teckningar o retuscher",
            "employees": 10,
            "capital": 30000,
            "establishment_year": 1950
        },
        "6": {
            "company_name": "KLICHÉ-CENTRALEN I HÄLSINGBORG AB",
            "address": "Helsingborg 1, Box 270",
            "phone_number": "042-13 90 80",
            "bank_details": {
                "bankgiro": "653-0398",
                "postgiro": "135562-7"
            },
            "activity": "Klichétillverkning",
            "capital": 5000,
            "establishment_year": 1937
        },
        "7": {
            "company_name": "GIBBS AB",
            "address": "Stockholm 40, Sveav 9-11",
            "phone_number": "08-23 42 80, 23 26 50",
            "telex": "1332 EXPEDO S",
            "activity": "Tillverkar mun-, hår-o hudvårdsmedel samt tvål",
            "capital": 1000000,
            "establishment_year": 1933
        },
        "8": {
            "company_name": "WIDEX-AKUSTIK, AB",
            "address": "Malmö, Lilla Torg 1",
            "phone_number": "040-111643,11 14 43",
            "bank_details": {
                "bankgiro": "87-0484",
                "postgiro": "530386"
            },
            "activity": "Säljer hörapparater samt batterier o reservdelar till dito. Reparationer o fullständig service av hörapparater",
            "capital": 20000,
            "key_personnel": [
                {
                    "name": "Adv Stig E Jansson",
                    "position": null
                },
                {
                    "name": "dir Egon Jansson",
                    "position": null
                }
            ],
            "establishment_year": 1958
        },
        "9": {
            "company_name": "OPERAKÄLLAREN, AB",
            "address": "Stockholm, Operahuset. Box 1616",
            "phone_number": "08-24 27 00",
            "additional_information": "För vidare uppgifter se moderbolaget Töre Wretman Restauranger AB."
        },
        "10": {
            "company_name": "OPPBOGA AB",
            "address": "Fellingsbro",
            "phone_number": "0589-205 10",
            "bank_details": {
                "bankgiro": "16-0323",
                "postgiro": "163943"
            },
            "telex": "73341",
            "activity": "Papp- o kartongbruk",
            "employees": 150,
            "annual_turnover": 22850000,
            "capital": 4500000,
            "key_personnel": [
                {
                    "name": "Disp Albrekt Werner",
                    "position": null
                }
            ],
            "establishment_year": 1901
        },
        "11": {
            "company_name": "SILJANS SÅGVERKS AB",
            "address": "Mora-Noret, Pack 7",
            "phone_number": "0250-135 10",
            "bank_details": {
                "bankgiro": "797-3548",
                "postgiro": "6000-4"
            },
            "activity": "Tillverkar sågade o hyvlade trävaror",
            "employees": 100,
            "annual_turnover": 16000000,
            "capital": 215500,
            "key_personnel": [
                {
                    "name": "Dir Stig Fredell (Stockholm)",
                    "position": null
                }
            ],
            "establishment_year": 1935
        },
        "12": {
            "company_name": "SILJANSNÄS SÅGVERKS. BOLAG, AB",
            "address": "Siljansnäs, Box 415",
            "phone_number": "0247-22110",
            "bank_details": {
                "bankgiro": "46-7220",
                "postgiro": "79626"
            },
            "activity": "Tillverkar monteringsfärdiga trähus o timmerstugor",
            "employees": 45,
            "annual_turnover": 2150000,
            "capital": 32500,
            "key_personnel": [
                {
                    "name": "Disp Erik Skalk",
                    "position": null
                }
            ],
            "establishment_year": 1946
        },
        "13": {
            "company_name": "SILKETVINNERI, AB",
            "address": "Alingsås, Sidenv",
            "phone_number": "0322-190 30",
            "bank_details": {
                "bankgiro": "889-7340",
                "postgiro": "11305-0"
            },
            "activity": "Tvinning av crepe-nylongarn",
            "employees": 75,
            "annual_turnover": 10000000,
            "capital": 100000,
            "key_personnel": [
                {
                    "name": "W F Morawek",
                    "position": null
                }
            ],
            "establishment_year": 1953
        },
        "14": {
            "company_name": "SILK.SCREEN. COMPANY",
            "address": "Eskilstuna 2, Box 2033. Nyforsg 37",
            "phone_number": "016-14 64 60",
            "postgiro": "9825 6-1",
            "activity": "Silk-screentryckeri, dekalkomanier, skyltar, tryck på pärmar samt boardskyltar",
            "employees": 6,
            "key_personnel": [
                {
                    "name": "Fabr Ove Nilsson",
                    "position": null
                },
                {
                    "name": "fabr Sivert Johansson",
                    "position": null
                }
            ],
            "establishment_year": 1955
        },
        "15": {
            "company_name": "GULLANDER AB, LENNART",
            "address": "Johanneshov 8, Storsjö v 19. Box 807",
            "phone_number": "08-91 0125",
            "bank_details": {
                "bankgiro": "283-9603",
                "postgiro": "503016-8"
            },
            "telex": "17547 ELLGULL S",
            "activity": "Tillverkar o säljer tryekluftarmatur o industriförnödenheter",
            "additional_information": "Avdelningskontor: Malmö, Glas-bruksg 4. Tel 040-16 0160",
            "employees": 15,
            "annual_turnover": 5500000,
            "capital": 75000,
            "key_personnel": [
                {
                    "name": "Lennart Gullander",
                    "position": null
                }
            ],
            "establishment_year": 1953
        },
        "16": {
            "company_name": "GULLASKRUFS GLAS-BRUKS AB",
            "address": "Orrefors, Gullaskruv",
            "phone_number": "0481-320 80, 320 81",
            "postgiro": "165600-8",
            "activity": "Tillverkar hushålls-, prydnads-, tekniskt glas samt strålkastarglas för bilar m m",
            "employees": 70,
            "annual_turnover": 4000000,
            "capital": 174000,
            "key_personnel": [
                {
                    "name": "Dr Rolf Jönsson",
                    "position": "Ordförande"
                },
                {
                    "name": "fru Marianne Andersson",
                    "position": null
                },
                {
                    "name": "dir Lennart Andersson",
                    "position": null
                }
            ],
            "establishment_year": 1893,
            "additional_information": "Ombildat till aktiebolag 1927."
        },
        "17": {
            "company_name": "GULLBERGS LIVSMEDEL, AB",
            "address": "Mariestad, Nya Torget 4",
            "phone_number": "0501-17070",
            "bank_details": {
                "bankgiro": "174-8318",
                "postgiro": "329281-0"
            },
            "activity": "Tillverkar o säljer livsmedel",
            "employees": 100,
            "annual_turnover": 28800000,
            "capital": 190000,
            "key_personnel": [
                {
                    "name": "Per W Gullberg",
                    "position": null
                }
            ],
            "establishment_year": 1891
        },
        "18": {
            "company_name": "GULLBERGS MASKINFABRIKS AB",
            "address": "Lindås",
            "phone_number": "0471-108 70",
            "bank_details": {
                "bankgiro": "845-9339",
                "postgiro": "191512-3"
            },
            "telex": "43067",
            "activity": "Tillverkar maskiner för byggnadsindustrin",
            "employees": 175,
            "annual_turnover": 12000000,
            "capital": 868000,
            "key_personnel": [
                {
                    "name": "Ing Lennart Hesselman",
                    "position": "Ordförande"
                },
                {
                    "name": "ing Edvin Johansson",
                    "position": null
                },
                {
                    "name": "dir L O Haggard",
                    "position": null
                },
                {
                    "name": "disp Edvin B Johanson",
                    "position": null
                },
                {
                    "name": "Verkst dir: Edvin B Johanson",
                    "position": null
                }
            ],
            "establishment_year": 1871
        },
        "19": {
            "company_name": "SKÅNE SÅGEN, AB",
            "address": "Sjöbo, Söderg 4",
            "phone_number": "0416-103 75, 106 00",
            "bank_details": {
                "bankgiro": "662-7608",
                "postgiro": "346740-4"
            },
            "activity": "Säljer sågade trävaror samt byggnadsmateriel",
            "employees": 23,
            "annual_turnover": 2900000,
            "capital": 300000,
            "key_personnel": [
                {
                    "name": "Nils Bernh Nilsson",
                    "position": null
                }
            ],
            "establishment_year": 1946
        },
        "20": {
            "company_name": "INTERSVETS-FAGRELL AB",
            "address": "Stockholm 4, Malmgårdsv 63",
            "phone_number": "08-44 00 95",
            "activity": "Säljer maskiner o utrustningar för motstånds- o båg-svetsning, gassvetsning o skärning, plasmaskärning o bågluftmejsling. Elektroder, svetstråd o svetspulver. Manipulatorer. Alla slags svetstillbehör. Maskiner för fogberedning o annan plåtbearbetning",
            "capital": 100000,
            "key_personnel": [
                {
                    "name": "Verkst dir O Hejdenberg",
                    "position": null
                }
            ]
        },
        "21": {
            "company_name": "INTER-TEST MARKETING AB",
            "address": "Solna, Bagartorpsringen 80",
            "phone_number": "08-85 01 90",
            "telex": "10896",
            "activity": "Alla slags marknadsundersökningar o tester",
            "employees": 17,
            "annual_turnover": 1500000,
            "capital": 5000,
            "key_personnel": [
                {
                    "name": "Birgitta Winborg",
                    "position": null
                }
            ],
            "establishment_year": 1955
        }
    }
}