{
    "original": "BYGGLEDARE AB\n\nPnr 13040\n\nStockholm 40, Pack. Mäster\nSamu-elsg 42. Tel 08-2413 90. Postgiro\n652200-7\n\nVerksamhet:\nByggnadsadministra-tion, tidsplanering, kalkyler,\nupphandling\n\nAntal anställda: 25\nÅrsomsättning: 2 600 000\nAktiekapital: 10 000\nVerkst din Civiling Lennart Rudin\nEtableringsår: 1957.\n\nEDSBYNS ELVERK, AB\n\nPnr 828 00\n\nEdsbyn, Box 82. Långg 28. Tel\n0271-21230. Bankgiro 415-5065.\nPostgiro 81717-1\nVerksamhet: Elproduktion,\neldistribution\nAntal anställda: 14\nÅrsomsättning: 3 100 000\nAktiekapital: 1140 000\nVerkst din Göran Lindén\nEtableringsår: 1918.\n\nEDSBYNS TRÄFüR.\nÄDLING AB\n\nPnr 828 00\n\nEdsbyn. Tel 0271-21200.\nBankgiro 19-3516. Postgiro 70438.\nTga Edsbyply. Telex 81166\nVerksamhet: Tillverkar o säljer\nplywood, lamellträ, spånskivor,\nsågade o hyvlade trävaror\nAntal anställda: 140\nÅrsomsättning: 22 000 000\nAktiekapital: 500 000\nVerkst dir: Disp Lars-Erik\nJärve-felt\n\nV verkst dir. Sune Häger\nEtableringsår: 1912.\n\nJONAX, AB\n\nPnr 182 02\n\nDanderyd 2, Kvarnv 10. Fack. Tel\n\n08-755 09 23,755 09 24.\nBankgiro72-7022. Postgiro 250500-6. Tga\nJonaxab\n\nVerksamhet: Säljer vantar,\nhandskar o broderier en gros\nAntal anställda: 4\nÅrsomsättning: 3 000 000\nAktiekapital: 100 000\nVerkst dir: Sven Johnsson\nEtableringsår: 1945.\n\nJOHNSON &amp; JOHNSON AB\n\nPnr 19184\n\nSollentuna, Staffans v 2. Tel\n08-754 0100. Bankgiro 730-4496.\nPostgiro 354920-1. Tga Jayanjay,\nStockholm. Telex 10915 JAYNJAY S\nVerksamhet: Tillverkar\nbabyprodukter, sjukvårdsprodukter,\nkirurgiska o farmaceutiska produkter\nAntal anställda: 135\nAktiekapital: 3 500 000\nVerkst dir: John P Andersen\nEtableringsår: 1956.\n\nEKO\n\nAntal anställda: 140\nVerkst dir: Stig Holmqvist\nEtableringsår: 1942.\n\nBARKMAN &amp; CO AB\n\nPnr 11425\n\nStockholm, Rådmansg 22. Tel\n08-23 24 00. Tga Cabanco.\nTelex 1433 CABANCO S\nVerksamhet: Cellulosa o trämassa\nAntal anställda: 10\nAktiekapital: 9000 000\nStyrelse: Ulf Barkman (ordf), Sven\nG Malmberg, Björn Barkman, Lars\nBarkman, Tom Barkman, Ake\nFredrikson\n\nVerkst dir: Ake Fredrikson\nEtableringsår: 1915\nOmbildat till aktiebolag 1922.\n\nBARLACH, AB R\n\nPnr 10121\n\nStockholm 1, Box 81. Stureg 1. Tel\n08-23 39 30. Bankgiro 483-4859.\nPostgiro 735-1. Tga Barlachab.\nTelex 10560 BARLACH S\nVerksamhet: Partihandel med\nkosmetiska, kemisk-tekniska artiklar o\nfarmaceutiska specialiteter\nNederlag: Linköping 4, Box 4080.\nTel 013-1299 59\n\nOrderkontor: Göteborg, N Gubberog\n22. Tel 031-80 23 85, 80 23 86\nMalmö, OTullg 1-3. Tel\n040-12 90 01, 12 90 91\nAntal anställda: 84\nAktiekapital: 1 125 000\nStyrelse: Adv G A Rising (ordf),\ndir Bruno Barlach, dir Curt Barlach\nVerkst dir: Bruno Barlach\nEtableringsår: 1909.\n\nBIGNER &amp; CO AB\n\nPnr 18103\n\nLidingö 3, Box 308. S Kungsv 326.\nTel 08-766 02 55. Bankgiro\n167-4266. Postgiro 357393-8. Tga\nBig-nerco. Telex 17171\nVerksamhet: Säljer\nrengöringsprodukter o ytbehandlingskemikalier\nför järn- o metallindustrin, plast-\n\n0\tfogmassor för karosseri-,\nbyggnads- samt varvsindustrin, färg o\nlack för industriellt\nbyggnadsunderhåll, sparbetmedel\n\nAntal anställda: 30\nÅrsomsättning: 5 000 000\nAktiekapital: 240 000\nStyrelse: Civiling Folke Bigner\n(ordf), ing Christian Bigner,\nnotarie Lennart Ramnek, J W Delanty\nVerkst dir: Christian Bigner\nFabrikschef: Civiling Angus Berg\nInköpschef: Marknadsekonom Sten\nRajalin\n\nEtableringsår: 1928.\n\nBIHAB BATTERICENTRALEN\n\n1\tHÄLSINGBORG AB\n\nPnr 250 02\n\nHelsingborg 2, Box 2019. Karl\nKrooksg 34. Tel 042-12 07 90. Bank-\n\ngiro 864-1086. Postgiro 29803-4\nVerksamhet: Säljer batterier,\nbiltillbehör o reservdelar engros o i\ndetalj\n\nAntal anställda: 16\nÅrsomsättning: 2 500 000\nAktiekapital: 50000\nVerkst dir: Georg Svensson\nEtableringsår: 1933\nOmbildat till aktiebolag 1944.\n\nBIL AB ANDERSSON &amp;\nSTROMSTEDT\n\nPnr 442 00\n\nKungälv, Trollhättev 18. Tel\n0303-114 50. Bankgiro 547-3434.\nPostgiro 414945-6\n\nVerksamhet: Säljer bilar. Utför\nbilreparationer o -lackeringar.\nÅterförsäljare för Scania\nlastbilar o Volkswagen personbilar\nAntal anställda: 70\nÅrsomsättning: 18 000 000\nAktiekapital: 600000\nVerkst dir: Sigvard Andersson\nEtableringsår: 1963.\n\nBIL AB NOHRLANDER &amp;\nANDERSSON\n\nse Nohrlander&amp; Andersson, Bil AB.\n\nBIL &amp; BUSS\nFÖRVALTNINGS AB\n\nPnr 79100\n\nFalun, Timmerv 4. Tel 023-188 50\nVerksamhet: Huvudkontor för Bil &amp;\nBuss-bolagen\nAntal anställda: 14\nAktiekapital: 2 500 000\nVerkst dir: Gösta Lindqvist\nEtableringsår: 1955.\n\nBOV\n\nVerksamhet: Spinneri, väveri o\nberedningsverk. Tillverkar bomulls- o\nsyntetvävnader, fållade varor o\ngardinlufter samt nylontrikå\nFabriker Borås, Skene, Veddige,\nBåstad o Väring\nAntal anställda: 1800\nÅrsomsättning: 120000 000\nAktiekapital: 25 000 000\nStyrelse: Ekon dr Ulf af Trolle\n(ordf), godsägare Karl Axel\nBergengren, dir Folke Pehrsson, dir Lars\nEnslöw, dir Bo Rydin, bankdir Olof\nKylberg\n\nVerkst dir: Lars Mauritzon\nEtableringsår: 1870\nDotterbolag: Mölnlycke Tuppen AB,\nLinje Hemma AB.\n\nBOSCH AB, ROBERT\n\nPnr 103 81\n\nStockholm 7, Box 7014. Birger\nJarlsg 25. Tel 08-2270 60.\nBankgiro 160-9577. Postgiro 852-4. Tga\nRoboswed. Telex 19170 BOSCH S\nVerksamhet: Grossiströrelse:\nFordonsutrustning, Blaupunkt radio/TV,\nhushållskapitalvaror, handverktyg\nm m\n\nFilialer: Göteborg, Malmö,\nNorrköping, Stockholm, Sundsvall\n.Antal anställda: 695\nÅrsomsättning: 244 000 000\nAktiekapital: 15 000 000\nVerkst dir: Rudolf Loeper\nEtableringsår: 1922\nEnsamförsäljare i Sverige for\nRobert Bosch GmbH, Stuttgart o AB\nRobo, Linköping.\n\nBOSEA\nLÄDERVARU-FABRIK, AB\n\nPnr 330 20\n\nAnderstorp, Brog 31. Tel\n0371-15160. Bankgiro 488-0811.\nPostgiro 144857-0\n\nVerksamhet: Tillverkar plånböcker\nm m\n\nAntal anställda: 15\nÅrsomsättning: 600 000\nAktiekapital: 5 000\nVerkst dir: Bengt Nilsson\nEtableringsår: 1939.\n\nekmans sängar ab\n\nPnr 56104\n\nHuskvarna 4, Kaxholmen. Box\n4008. Tel 036-500 02. Bankgiro\n150-1261. Postgiro 166180-0\nVerksamhet: Tillverkar o säljer\nsängar\n\nAntal anställda: 9\nÅrsomsättning: 1000 000\nAktiekapital: 10 000\nVerkst dir: Fredrik Ekman\nEtableringsår: 1938.\n\nTERSIN, AB ALLAN\n\nPnr 401 22\n\nGöteborg X, Drottningg 28. Box 163.\nTel 031-13 30 23. Bankgiro 84-7874.\nPostgiro 43262. Tga Tersintex\nVerksamhet: Textilagenturer\nAktiekapital: 5000\nVeikst dir Allan Tersin\nEtableringsår: 1932\nOmbildat till aktiebolag 1960.\n\nTERVEMASKINER, AB\n\nPnr 600 12\n\nNorrköping 12, Torsg 18. Box 12007.\nTel 011-12 90 45. Bankgiro 12-5359.\nPostgiro 176499. Telex TM 64119.\nTga Te em\n\nVerksamhet: Reparerar o säljer\nentreprenadmaskiner\nÅrsomsättning: 5000 000\nAktiekapital: 5 000\nChef: Civiling Birger Dott\nEtableringsår: 1939.",
    "structured": {
        "1": {
            "company_name": "BYGGLEDARE AB",
            "pnr": "13040",
            "address": "Stockholm 40, Pack. Mäster Samu-elsg 42",
            "phone_number": "08-2413 90",
            "bank_details": {
                "postgiro": "652200-7"
            },
            "activity": "Byggnadsadministration, tidsplanering, kalkyler, upphandling",
            "employees": 25,
            "annual_turnover": 2600000,
            "capital": 10000,
            "key_personnel": [
                {
                    "name": "Civiling Lennart Rudin",
                    "position": "Verkst din"
                }
            ],
            "establishment_year": 1957
        },
        "2": {
            "company_name": "EDSBYNS ELVERK, AB",
            "pnr": "828 00",
            "address": "Edsbyn, Box 82, Långg 28",
            "phone_number": "0271-21230",
            "bank_details": {
                "bankgiro": "415-5065",
                "postgiro": "81717-1"
            },
            "activity": "Elproduktion, eldistribution",
            "employees": 14,
            "annual_turnover": 3100000,
            "capital": 1140000,
            "key_personnel": [
                {
                    "name": "Göran Lindén",
                    "position": "Verkst din"
                }
            ],
            "establishment_year": 1918
        },
        "3": {
            "company_name": "EDSBYNS TRÄFöRÄDLING AB",
            "pnr": "828 00",
            "address": "Edsbyn",
            "phone_number": "0271-21200",
            "bank_details": {
                "bankgiro": "19-3516",
                "postgiro": "70438"
            },
            "activity": "Tillverkar o säljer plywood, lamellträ, spånskivor, sågade o hyvlade trävaror",
            "employees": 140,
            "annual_turnover": 22000000,
            "capital": 500000,
            "key_personnel": [
                {
                    "name": "Disp Lars-Erik Järve-felt",
                    "position": "Verkst dir"
                },
                {
                    "name": "Sune Häger",
                    "position": "V verkst dir"
                }
            ],
            "establishment_year": 1912
        },
        "4": {
            "company_name": "JONAX, AB",
            "pnr": "182 02",
            "address": "Danderyd 2, Kvarnv 10",
            "phone_number": "08-755 09 23,755 09 24",
            "bank_details": {
                "bankgiro": "72-7022",
                "postgiro": "250500-6"
            },
            "activity": "Säljer vantar, handskar o broderier en gros",
            "employees": 4,
            "annual_turnover": 3000000,
            "capital": 100000,
            "key_personnel": [
                {
                    "name": "Sven Johnsson",
                    "position": "Verkst dir"
                }
            ],
            "establishment_year": 1945
        },
        "5": {
            "company_name": "JOHNSON & JOHNSON AB",
            "pnr": "19184",
            "address": "Sollentuna, Staffans v 2",
            "phone_number": "08-754 0100",
            "bank_details": {
                "bankgiro": "730-4496",
                "postgiro": "354920-1"
            },
            "activity": "Tillverkar babyprodukter, sjukvårdsprodukter, kirurgiska o farmaceutiska produkter",
            "employees": 135,
            "capital": 3500000,
            "key_personnel": [
                {
                    "name": "John P Andersen",
                    "position": "Verkst dir"
                }
            ],
            "establishment_year": 1956
        },
        "6": {
            "company_name": "EKO",
            "employees": 140,
            "key_personnel": [
                {
                    "name": "Stig Holmqvist",
                    "position": "Verkst dir"
                }
            ],
            "establishment_year": 1942
        },
        "7": {
            "company_name": "BARKMAN & CO AB",
            "pnr": "11425",
            "address": "Stockholm, Rådmansg 22",
            "phone_number": "08-23 24 00",
            "bank_details": {
                "telex": "1433 CABANCO S"
            },
            "activity": "Cellulosa o trämassa",
            "employees": 10,
            "capital": 9000,
            "key_personnel": [
                "Ulf Barkman (ordf)",
                "Sven G Malmberg",
                "Björn Barkman",
                "Lars Barkman",
                "Tom Barkman",
                "Ake Fredrikson"
            ],
            "establishment_year": 1915
        },
        "8": {
            "company_name": "BARLACH, AB R",
            "pnr": "10121",
            "address": "Stockholm 1, Box 81, Stureg 1",
            "phone_number": "08-23 39 30",
            "bank_details": {
                "bankgiro": "483-4859",
                "postgiro": "735-1",
                "telex": "10560 BARLACH S"
            },
            "activity": "Partihandel med kosmetiska, kemisk-tekniska artiklar o farmaceutiska specialiteter",
            "branches": [
                "Linköping 4, Box 4080, 013-1299 59",
                "Göteborg, N Gubberog 22, 031-80 23 85, 80 23 86",
                "Malmö,  Tullg 1-3, 040-12 90 01, 12 90 91"
            ],
            "employees": 84,
            "capital": 1125000,
            "key_personnel": [
                "Adv G A Rising (ordf)",
                "dir Bruno Barlach",
                "dir Curt Barlach"
            ],
            "establishment_year": 1909
        },
        "9": {
            "company_name": "BIGNER & CO AB",
            "pnr": "18103",
            "address": "Lidingö 3, Box 308, S Kungsv 326",
            "phone_number": "08-766 02 55",
            "bank_details": {
                "bankgiro": "167-4266",
                "postgiro": "357393-8",
                "telex": "17171"
            },
            "activity": "Säljer rengöringsprodukter o ytbehandlingskemikalier för järn- o metallindustrin, plastfogmassor för karosseri-, byggnads- samt varvsindustrin, färg o lack för industriellt byggnadsunderhåll, sparbetmedel",
            "employees": 30,
            "annual_turnover": 5000000,
            "capital": 240000,
            "key_personnel": [
                "Civiling Folke Bigner (ordf)",
                "ing Christian Bigner",
                "notarie Lennart Ramnek",
                "J W Delanty"
            ],
            "establishment_year": 1928
        },
        "10": {
            "company_name": "BIHAB BATTERICENTRALEN HÄLSINGBORG AB",
            "pnr": "250 02",
            "address": "Helsingborg 2, Box 2019, Karl Krooksg 34",
            "phone_number": "042-12 07 90",
            "bank_details": {
                "bankgiro": "864-1086",
                "postgiro": "29803-4"
            },
            "activity": "Säljer batterier, biltillbehör o reservdelar engros o i detalj",
            "employees": 16,
            "annual_turnover": 2500000,
            "capital": 50000,
            "key_personnel": [
                "Georg Svensson",
                "Verkst dir"
            ],
            "establishment_year": 1933
        },
        "11": {
            "company_name": "BIL AB ANDERSSON & STROMSTEDT",
            "pnr": "442 00",
            "address": "Kungälv, Trollhättev 18",
            "phone_number": "0303-114 50",
            "bank_details": {
                "bankgiro": "547-3434",
                "postgiro": "414945-6"
            },
            "activity": "Säljer bilar. Utför bilreparationer o -lackeringar. Återförsäljare för Scania lastbilar o Volkswagen personbilar",
            "employees": 70,
            "annual_turnover": 18000000,
            "capital": 600000,
            "key_personnel": [
                "Sigvard Andersson",
                "Verkst dir"
            ],
            "establishment_year": 1963
        },
        "12": {
            "company_name": "BIL AB NOHRLANDER & ANDERSSON",
            "pnr": "442 00",
            "aliases": [
                "Nohrlander & Andersson, Bil AB"
            ]
        },
        "13": {
            "company_name": "BIL & BUSS FÖRVALTNINGS AB",
            "pnr": "79100",
            "address": "Falun, Timmerv 4",
            "phone_number": "023-188 50",
            "activity": "Huvudkontor för Bil & Buss-bolagen",
            "employees": 14,
            "capital": 2500000,
            "key_personnel": [
                "Gösta Lindqvist",
                "Verkst dir"
            ],
            "establishment_year": 1955
        },
        "14": {
            "company_name": "BOV",
            "activity": "Spinneri, väveri o beredningsverk. Tillverkar bomulls- o syntetvävnader, fållade varor o gardinlufter samt nylontrikå",
            "employees": 1800,
            "annual_turnover": 120000000,
            "capital": 25000000,
            "key_personnel": [
                "Ekon dr Ulf af Trolle (ordf)",
                "godsägare Karl Axel Bergengren",
                "dir Folke Pehrsson",
                "dir Lars Enslöw",
                "dir Bo Rydin",
                "bankdir Olof Kylberg",
                "Verkst dir: Lars Mauritzon"
            ],
            "establishment_year": 1870,
            "subsidiaries": [
                "Mölnlycke Tuppen AB",
                "Linje Hemma AB"
            ]
        },
        "15": {
            "company_name": "BOSCH AB, ROBERT",
            "pnr": "103 81",
            "address": "Stockholm 7, Box 7014, Birger Jarlsg 25",
            "phone_number": "08-2270 60",
            "bank_details": {
                "bankgiro": "160-9577",
                "postgiro": "852-4",
                "telex": "19170 BOSCH S"
            },
            "activity": "Grossiströrelse: Fordonsutrustning, Blaupunkt radio/TV, hushållskapitalvaror, handverktyg m m",
            "branches": [
                "Göteborg",
                "Malmö",
                "Norrköping",
                "Stockholm",
                "Sundsvall"
            ],
            "employees": 695,
            "annual_turnover": 244000000,
            "capital": 15000000,
            "key_personnel": [
                "Rudolf Loeper",
                "Verkst dir"
            ],
            "establishment_year": 1922,
            "exclusive_distributor": [
                "Robert Bosch GmbH, Stuttgart",
                "AB Robo, Linköping"
            ]
        },
        "16": {
            "company_name": "BOSEA LÄDERVARU-FABRIK AB",
            "pnr": "330 20",
            "address": "Anderstorp, Brog 31",
            "phone_number": "0371-15160",
            "bank_details": {
                "bankgiro": "488-0811",
                "postgiro": "144857-0"
            },
            "activity": "Tillverkar plånböcker m m",
            "employees": 15,
            "annual_turnover": 600000,
            "capital": 5000,
            "key_personnel": [
                "Bengt Nilsson",
                "Verkst dir"
            ],
            "establishment_year": 1939
        },
        "17": {
            "company_name": "EKMAN' SÄNGAR AB",
            "pnr": "56104",
            "address": "Huskvarna 4, Kaxholmen, Box 4008",
            "phone_number": "036-500 02",
            "bank_details": {
                "bankgiro": "150-1261",
                "postgiro": "166180-0"
            },
            "activity": "Tillverkar o säljer sängar",
            "employees": 9,
            "annual_turnover": 1000000,
            "capital": 10000,
            "key_personnel": [
                "Fredrik Ekman",
                "Verkst dir"
            ],
            "establishment_year": 1938
        },
        "18": {
            "company_name": "TERSIN, AB ALLAN",
            "pnr": "401 22",
            "address": "Göteborg X, Drottningg 28, Box 163",
            "phone_number": "031-13 30 23",
            "bank_details": {
                "bankgiro": "84-7874",
                "postgiro": "43262",
                "telex": "Tersintex"
            },
            "activity": "Textilagenturer",
            "capital": 5000,
            "key_personnel": [
                "Allan Tersin",
                "Verkst dir"
            ],
            "establishment_year": 1960
        },
        "19": {
            "company_name": "TERVEMASKINER, AB",
            "pnr": "600 12",
            "address": "Norrköping 12, Torsg 18, Box 12007",
            "phone_number": "011-12 90 45",
            "bank_details": {
                "bankgiro": "12-5359",
                "postgiro": "176499",
                "telex": "TM 64119"
            },
            "activity": "Reparerar o säljer entreprenadmaskiner",
            "annual_turnover": 5000000,
            "capital": 5000,
            "key_personnel": [
                "Civiling Birger Dott",
                "Chef"
            ],
            "establishment_year": 1939
        }
    }
}