{
    "original": "TROLLHÄTTEGLASSAB\n\nPnr 13102\n\nNacka 2, Ältav 52. Fack. Tel\n08-71628 00. Bankgiro 476-5046.\nPostgiro 194955. Tga\nTrollhätte-glass. Telex 1332\nVerksamhet: Tillverkar o säljer\nglass\n\nVarunamn: Trollhätteglass\nAktiekapital: 3 000 000\nVerkst dir: T Sundling\nNamnändring 1964 från Gille Glass.\n\nTROLLHÄTTEPLAST, AB\n\nPnr 461 01\n\nTrollhättan 1, Björkelund, Lextorp,\nBox 237. Tel 0520-360 50, 36052.\nBankgiro 713-1428. Postgiro\n11328-2\n\nStockholmskontor: Tel 08-19 56 56\n\nPLASTPÄRMAR\n\nPLASTFICKOR och PLASTFODRAL\nAKTMAPPAR och OFFERTMAPPAR\nUPPBLASBARA REKLAMARTIKLAR\n\nKLICHÉ- och SCREENTRYCK utföres\nPatentsökt konstruktion på Aktmappar,\nReklamflaggor och Vimplar\n\nVerksamhet: Industri för svetsade\n\nplastartiklar\n\nAntal anställda: 20\n\nÅrsomsättning: 2 200 000\n\nAktiekapital: 40 000\n\nVerkst dir: Ing Rune Westerlund\n\nEtableringsår: 1968.\n\nTROPIK MÖBELFABRIK AB\n\nPnr 730 73\n\nRansta, Fack 36. Tel 0224-202 1 0.\n\nBankgiro34-9841. Postgiro329168.\n\nTga Tropik, Sala\n\nVerksamhet: Tillverkar o säljer\n\nkorgmöbler samt stålmöbler för\n\nskolor, kontor, restauranter, kök o\n\nträdgårdar\n\nAntal anställda: 25\n\nÅrsomsättning: 1600 000\n\nAktiekapital: 60 000\n\nChefer: Fabr Ake Andersson, fabr\n\nBror Nyström\n\nEtableringsår 1947.\n\nBANKERYDSMEKANO AB\n\nPnr 560 23\n\nBanketyd, Tallv 1. Tel 036-776 21.\nBankgiro 836-9138. Postgiro\n591231-6\n\nVerksamhet: Utför svarvning,\nborrning, hyvling, plans lipning.\nTillverkar verktyg, press- o plastverktyg\nÄgare o chef: Olof Fäldt.\n\nBANKERYDS\nPENSELFABRIK AB\n\nPnr 560 23\n\nBankeryd, Box 120. Sjöåkrav. Tel\n036-77100. Bankgiro 836-9506.\nPostgiro 32197-6. Tga Penselberg\nVerksamhet: Tillverkar penslar,\nmålningsrullar o målningsverktyg\nAntal anställda: 80\nAktiekapital: 500 000\nVerkst dir: Bernt Damberg\nEtableringsår: 1946.\n\nCANON SVENSKA\nFÖRSÄLJNINGS AB\n\nPnr 12143\n\nJohanneshov, Huddingev 113. Tel\n08-49 28 10. Bankgiro 744-4386.\nPostgiro 256359-1\nVerksamhet: Kameror, elektroniska\nräknare, opto-elektroniska produkter\nAntal anställda: 48\nÅrsomsättning: 12 000 000\nAktiekapital: 50 000\nVerkst dir: Raymond T Pilotti\nEtableringsår: 1954.\n\nELMATIC AB\n\nPnr 104 22\n\nStockholm 22, Bergsg 22. Box\n22103. Tel 08-52 0060\n\nVerksamhet: Generalagent i\nSverige för Elna symaskiner\nAntal anställda: 100\nAktiekapital: 100 000\nEtableringsår: 1956.\n\nKRONSÅGAR, AB\n\nPnr 53101\n\nLidköping 1, Truveg. Box 101. Tel\n0510-220 60. Bankgiro 841-3791.\nPostgiro 6566-4. Tga Kronsågar\nVerksamhet: Tillverkar bågfilblad,\nmaskinsågblad o bandsågblad,\nbågfilställningar. Försäljningen\nhandhaves av Kronsågars\nFörsäljnings AB, Göteborg. Tel\n031-18 25 24\n\nAntal anställda: 50\nAktiekapital: 300 000\nVerkst dir: Bengt Pihlgren\nEtableringsår: 1914.\n\nKRONSÅGARS FÖRSÄLJ.\nNINGS AB\n\nPnr 41285\n\nGöteborg, Mölndalsv 85. Tel\n031-18 25 24. Bankgiro 443-1193.\nPostgiro 243810-9. Tga Kronsale\nVeiksamhet: Bågfilblad,\nmaskinsågblad, bandsågblad- o\nbågfilställningar\n\nAvdelningskontor: Malmö O,\nKru-seg 52. Tel 040-93 07 65\nStockholm C, Johannes plan 5.Tel\n08-113351, 1133 53\nAntal anställda: 8\nAktiekapital: 450 000\n\nVerkst dir: Bengt Pihlgren\nEtableringsår: 1947\nOmbildat till aktiebolag 1961.\n\nKROOK &amp; CO AB, VICTOR\n\nPnr 432 00\n\nVarberg, Tullhuset. Box 77. Tel\n0340-100 35, 108 65. Bankgiro\n425-1443. Postgiro 76380-5. Tga\nFraktkrook. Telex 3463\nVerksamhet: Speditions o\nskepps-mäkleri\n\nAntal anställda: 5\nAktiekapital: 75 000\nVerkst dir: Gunnar Ohm\nPlatschef: Valter Krook\nEtableringsår: 1885.\n\nBLOMQVIST, C G\n\nPnr 632 26\n\nEskilstuna, Sommarrog 13. Tel\n016-1311 34. Bankgiro 601-4062.\nPostgiro 346012-8\n\nVerksamhet: Tillverkar tälj- o\nslidknivar, korkskruvar samt\npota-tisskalare\n\nÄgare o chefer: Thore Blomqvist,\nElmer Blomqvist\nEtableringsår: 1915.\n\nmalmö strumpfabrik, ab\n\nPnr 20040\n\nMalmö 8, Fack. Trelleborgsv 12-14.\nTel 040-60140\n\nVerksamhet: Tillverkar dam- o\nbarnstrumpor, jerseyväv\nAktiekapital: 5 000 000\nVerkst dir: Karl Almström\nEtableringsår: 1926.\n\nmalmö ventilationsan..\nläggning ar ab\n\nPnr 21140\n\nMalmö, STullg 4 A. Tel 040-746 35.\nBankgiro 836-9910. Postgiro\n539596-7\n\nVerksamhet Säljer o installerar\nventilationsmaterial samt utför\nkompletta ventilationsanläggningar.\nRepresentant för Plåt-Mekano i\nKvänum AB\nAntal anställda: 4\nÅrsomsättning: 2 000 000\nAktiekapital: 10 000\nChef: Folke Tegmar\nEtableringsår: 1963.\n\nmalmohus läns central.\nkassa fur jordbruks.\nkredit\n\nPnr 203 11\n\nMalmö 4, Kanalg 5 B. Box 4088.\nTel 040-76350. Postgiro 537401\nVerksamhet: Bankrörelse\nAntal anställda: 21\nBalansomslutning: 316 684 000\nVerkst dir: S A Nilsson\nKamrerare: Karl Gunnar\nFrennes-son, Bertil Jörnklo\nEtableringsår: 1916.\n\nANDERSEN, AB HILMER\n\nPnr 54101\n\nSkövde 1, Box 60. Tel 05 00-180 20\nVerksamhet:\nRörledningsentreprenör\n\nAktiekapital: 200 000\nVerkst dir: Kåge Fredeby\nEtableringsår: 1884.\n\nMERCATOR TRADING CO AB\n\nPnr 11436\n\nStockholm, Stureg 38. Tel\n08-67 93 30. Bankgiro 72-3000.\nPost&gt;-giro 2258. Telex 17075. Tga\nMerc-trade\n\nVerksamhet Handels-,\ninvestment-o utvecklingsbolag inom flertalet\nbranscher. Utvecklar tekniska\nuppslag dels direkt o dels genom\ndot-terföretag. Samverkar med\ninternationella företag i USA, Sydamerika,\nAustralien o Japan\nAktiekapital: 500 000\nVerkst dir: O Arne Berglund\nEtableringsår: 1909\nFöretaget ingår i Mercator\nInternational Group AB.\n\nMERCON, AB\n\nPnr 104 40\n\nStockholm 14, Styrmansg 43. Box\n14051. Tel 08-67 70 90, 67 87 40.\nBankgiro 561-3187. Postgiro\n604205-5. Tga Merconab\nVerksamhet: Tillverkar o säljer\nutrustning samt specialmaskiner för\njärn-, stål- o cellulosaindustri\nAntal anstäUda: 15\nAktiekapital: 100 000\nVerkst dir: Bergsing Joachim\nMedin.\n\nMERCURI\nSEKRETERAR-INSTITUT\n\nPnr 116 30\n\nStockholm. Folkungag 122. Tel\n08-44 93 80. Bankgiro 168-9025.\nPostgiro 357434-0. Tga Mercontact\nVeiksamhet: Vidareutbildning för\nkontorstjänstemän.\n\nMERCUR l-INSTITUTET\n\nPnr 116 30\n\nStockholm, Folkungag 122. Tel\n08-44 93 80. Bankgiro 168-9025.\nPostgiro 357434-0. Tga Mercontact\nVerksamhet: Urval-, utbildning-,\nkonsultation-, huvudsakligen inom\nmarknadsföring- o\nförsäljningsområdet\n\nKontor: 413 03 Göteborg, Andra\nLångg 44. Tel 031-12 40 50\n21143 Malmö, S Förstadsg 58. Tel\n040-760 35\nAntal anstäUda: 52\nÅrsomsättning: 6 000 000\nAktiekapital: 50 000\nVerkst dir: Curt Abrahamsson\nOmbildat till aktiebolag 1964.\n\nMERKANTIL FACTORING AB\n\nPnr 103 43\n\nStockholm 40, Malmskillnadsg 25.\nBox 40110. Tel 08-23 00 75.\nBankgiro 44-7442. Postgiro 56616. Tga\nMerkfactor. Telex 1420 GOTBANK S\nVerksamhet: Dataservice o\nfinansiering av kundfordringar\nAntal anstäUda: 23\nAktiekapital: 1 000 000\nVerkst dir: Ake Rönn\nEtableringsår: 1965.\n\ngeneral foods ab\n\nPnr 117 43\n\nStockholm, Mejeriv 7. Tel\n08-45 26 00. Bankgiro 160-6847.\nPostgiro 51724-3. Tga Genfoods.\nTelex 1806\n\nVerksamhet: Livsmedelsföretag\nAktiekapital: 10 000 000\nVerkst dir: J P Mc Manus\nEtableringsår: 1917.\n\ngeneral motors\nnordiska ab\n\nPnr 104 60\n\nStockholm, Motorv 1. Tel\n08-44 01 80. Telex 1569. Tga\nStok-autoex\n\nVerksamhet: Distribuerar\nGM-kon-cernens tillverkningar: Bilar,\nreservdelar o tillbehör,\nindustrimotorer, komponenter för mek o elektr\nindustrier m m\n\nVarunamn: Bedford, Buick,\nCadillac, Chevrolet, GMC, Oldsmobile,\nOpel, Pontiac, Vauxhall, AC, AC\nDelco, Allison, Bedford Diesel,\nDelco Guide, Delco Harrison,\nDelco Hyatt, Delco Moraine, Delco New\nDeparture, Delco Packard, Delco\nProducts, Delco Radio, Delco\nRo-chester, Delco Remy, Detroit\nDiesel, Electro-Motive, Fitzgerald,\nInlite, Kent-Moore, Pedrick,\nSagi-naw, Toledo, Trainor, Walker\nAntal anställda: 585\nÅrsomsättning: 348 000000\nAktiekapital: 9 600 000\nVerkst dir: Gerald Y Genn\nInköpschef: Stig Holmin\nEtableringsår: 1927.\n\ngeneralstabens lito.\nGRAFISKA ANSTALT\n\nPnr 10124\n\nStockholm 1, Box 304. Vasag 16.\nTel 22 95 00. riks 08-22 95 40.\nTga Esseltemap.\nTelex 1598 ESSELTE S\nVerksamhet: Stadsplaner,\nturistkartor, atlaser, globkartor\nKartred: Bo Gramfors\nAnslutet till Esselte Kart AB.\n\ngeneralstabens\nlito-grafiska anstalt,\nkartforlaget\n\nPnr 10124\n\nStockholm 1, Box 304. Vasag 16.\nTel 22 95 00, riks 08-22 95 40.\nTga Esseltemap.\nTelex 1598 ESSELTE S\nVerksamhet: Kartor, böcker m m\nFörlagschef: Bertil Ahlström\nAnslutet till Esselte Kart AB.\n\ngenerator ab,\nmaskinaffären\n\nPnr 433 00\n\nParti lie, Box 95. Tel 031-44 09 20.\nBankgiro 848-2804. Postgiro\n47393-4. Tga Generator\nVerksamhet: Tillverkning o\nförsäljning av ångpannor,\nhetvattenpannor, hetoljepannor, tryckkärl\nAvdelningskontor: Stockholm. Tel\n08-38 73 10\n\nVarunamn: Eckrohr, Tubox\nAntal anställda: 150\nÅrsomsättning: 28 000 000\nAktiekapital: 500 000\nVerkst dir: Ingmar Edenholm\nEtableringsår: 1915.",
    "structured": {
        "1": {
            "company_name": "TROLLHÄTTEGLASSAB",
            "pnr": "13102",
            "address": "Nacka 2, Ältav 52",
            "phone_number": "08-71628 00",
            "bank_details": {
                "bankgiro": "476-5046",
                "postgiro": "194955"
            },
            "activity": "Tillverkar o säljer glass",
            "capital": 3000000,
            "key_personnel": [
                {
                    "name": "T Sundling",
                    "position": "Verkst dir"
                }
            ],
            "establishment_year": 1964
        },
        "2": {
            "company_name": "TROLLHÄTTEPLAST, AB",
            "pnr": "461 01",
            "address": "Trollhättan 1, Björkelund, Lextorp, Box 237",
            "phone_number": "0520-360 50, 36052",
            "bank_details": {
                "bankgiro": "713-1428",
                "postgiro": "11328-2"
            },
            "stockholmskontor": "Tel 08-19 56 56",
            "activity": "Industri för svetsade plastartiklar",
            "employees": 20,
            "annual_turnover": 2200000,
            "capital": 40000,
            "key_personnel": [
                {
                    "name": "Ing Rune Westerlund",
                    "position": "Verkst dir"
                }
            ],
            "establishment_year": 1968
        },
        "3": {
            "company_name": "TROPIK MÖBELFABRIK AB",
            "pnr": "730 73",
            "address": "Ransta, Fack 36",
            "phone_number": "0224-202 1 0",
            "bank_details": {
                "bankgiro": "34-9841",
                "postgiro": "329168"
            },
            "tga": "Tropik, Sala",
            "activity": "Tillverkar o säljer korgmöbler samt stålmöbler",
            "employees": 25,
            "annual_turnover": 1600000,
            "capital": 60000,
            "key_personnel": [
                {
                    "name": "Fabr Ake Andersson",
                    "position": "Chefer"
                },
                {
                    "name": "Fabr Bror Nyström",
                    "position": "Chefer"
                }
            ],
            "establishment_year": 1947
        },
        "4": {
            "company_name": "BANKERYDSMEKANO AB",
            "pnr": "560 23",
            "address": "Banketyd, Tallv 1",
            "phone_number": "036-776 21",
            "bank_details": {
                "bankgiro": "836-9138",
                "postgiro": "591231-6"
            },
            "activity": "Utför svarvning, borrning, hyvling, plans lipning. Tillverkar verktyg, press- o plastverktyg",
            "key_personnel": [
                {
                    "name": "Olof Fäldt",
                    "position": "Ägare o chef"
                }
            ],
            "establishment_year": "N/A"
        },
        "5": {
            "company_name": "BANKERYDS PENSELFABRIK AB",
            "pnr": "560 23",
            "address": "Bankeryd, Box 120",
            "phone_number": "036-77100",
            "bank_details": {
                "bankgiro": "836-9506",
                "postgiro": "32197-6"
            },
            "tga": "Penselberg",
            "activity": "Tillverkar penslar, målningsrullar o målningsverktyg",
            "employees": 80,
            "capital": 500000,
            "key_personnel": [
                {
                    "name": "Bernt Damberg",
                    "position": "Verkst dir"
                }
            ],
            "establishment_year": 1946
        },
        "6": {
            "company_name": "CANON SVENSKA FÖRSÄLJNINGS AB",
            "pnr": "12143",
            "address": "Johanneshov, Huddingev 113",
            "phone_number": "08-49 28 10",
            "bank_details": {
                "bankgiro": "744-4386",
                "postgiro": "256359-1"
            },
            "activity": "Kameror, elektroniska räknare, opto-elektroniska produkter",
            "employees": 48,
            "annual_turnover": 12000000,
            "capital": 50000,
            "key_personnel": [
                {
                    "name": "Raymond T Pilotti",
                    "position": "Verkst dir"
                }
            ],
            "establishment_year": 1954
        },
        "7": {
            "company_name": "ELMATIC AB",
            "pnr": "104 22",
            "address": "Stockholm 22, Bergsg 22, Box 22103",
            "phone_number": "08-52 0060",
            "activity": "Generalagent i Sverige för Elna symaskiner",
            "employees": 100,
            "capital": 100000,
            "establishment_year": 1956
        }
    }
}