{
    "original": "LDNSBODA SNICKERIFABRIK,\nALBIN JUNSSON\n\nPnr 280 70\n\nLönsboda, O Storg 4. Tel\n0479-20058. Bankgiro 279-3313.\nPostgiro 371220-5\n\nVerksamhet: Beställningssnickerier\nsåsom fönster- o dörrpartier\nAntal anställda: 10\nÅrsomsättning: 550 000\nChef: Fabr Albin Jönsson\nEtableringsår: 1910.\n\nLÖV- se även LÖF-\n\nLüVBERGA BETONG.\nGJUTERI, AB\n\nPnr 833 00\n\nStrömsund, Lövberga 32. Tel\n0670-21015. Postgiro 135845\nVerksamhet: Tillverkar muffrör,\nvägrör, vägräckesstolpar,\nbrunnsringar o betonghålsten\nEtableringsår: 1946.\n\nVEDKAMINER AB\n\nPnr 266 00\n\nRåå. Tel 042-210 01, 210 59.\nBankgiro 65-3170. Postgiro 90827\nVerksamhet: Tillverkar kaminer för\nskogskojor mm, bastuugnar\nAktiekapital: 20 000\nVerkst dir: Greve Gösta\nWachtmeister\n\nEtableringsår: 1934\nOmbildat till aktiebolag 1960.\n\nVEDUMS SNICKERIFABRIK AB\n\nPnr 530 10\n\nVedum. Tel 0512-404 1 0. Bankgiro\n20-0604. Postgiro 285477\nVerksamhet: Tillverkar o säljer\n\nköksinredningar, även färdigmålade\nAntal anställda: 45\nÅrsomsättning: 6 000 000\nAktiekapital: 100 000\nVerkst din Disp Eskil Lindberg\nEtableringsån 1919.\n\nKINDS YLLEFABRIKS AB\n\nPnr 510 96\n\nOlsremma, Box 39. Tel\n0321-620 51, 620 45. Bankgiro 53-2818.\nPostgiro 94746\n\nVerksamhet: Tillverkar yttertrikå\n\ni herr-, dam- o barnartiklar\n\nAktiekapital: 150 000\n\nÄgare o chefer: Jacob Jacobsson,\n\nIsaac Orre\n\nEtableringsår: 1934.\n\nKINDA SKOGSPRODUKTER,\nAB\n\nPnr 590 40\n\nKisa, Rådmansg 4. Box 4. Tel\n0494-110 10. Bankgiro 129-3695.\nPostgiro 570237\n\nVerksamhet: Skogsavverkningar,\nbarkning av massaved samt\nförsäljning o förmedling av timmer o\növriga skogsprodukter\nAntal anställda: 25\nÅrsomsättning: 10 000 000\nAktiekapital: 50 000\nVerkst dir: Per-Eric Järnland\nEtableringsår: 1960.\n\nKINDABETONG AB\n\nPnr 590 41\n\nRimforsa. Tel 0494-500 50, 500 35.\nBankgiro 12-9394. Postgiro 446718\nVerksamhet: Tillverkar o säljer\nbetong o betongvaror av alla slag,\ngrus, singel mm\nAntal anställda: 24\nÅrsomsättning: 2000 000\nAktiekapital: 80 000\nVerkst dir: John Walfridsson\nEtableringsår: 1946.\n\nSVE\n\nEtableringsår: 1907\n\nSockerbolaget ingår i\nCardo-kon-cernen (Investmentföretaget AB\nCardo med ett aktiekapital av\n135 000 000) som även omfattar\nbl a AB Felix, Hilleshögs Frö AB\no Säbyholms Jordbruks AB.\n\nSVENSKA SPECIAL.\nVERKTYG, AB\n\nPnr 703 58\n\nÖrebro, Myrmalmsg 8. Tel\n019-18 6930, 18 6931. Bankgiro\n815-7588. Postgiro 462178-5\nVerksamhet: Tillverkar verktyg o\nslitdetaljer av hårdmetall\nAktiekapital: 20 000\nPlatschef: Sven Ericsson\nEtableringsår: 1950.\n\nSVENSKA STANDARD.\nBOLAG AB\n\nPnr 79100\n\nFalun, Magasinsg 7. Tel\n023-180 70\n\nVerksamhet: Specialfirma för\naktiebolagsbildning o\naktiekapitalsökning\n\nFörsäljningskontor: 11121\nStockholm, Mäster Samuelsg 52. Tel\n08-20 46 00. Tidsbeställning\nVarunamn: S-bolag\nAntal anställda: 20\nAktiekapital: 150 000\nChef: Företagsekonom Sören\nThunström\n\nEtableringsår: 1954.\n\nSCHARINS SÖNER, AB\n\nPnr 930 31\n\nKlemensnäs. Tel 0910-30190.\nPostgiro 59000. Telex 6871. Tga\nScha-rins, Skellefteå\n\nVeiksamhet: Framställer torr mek\nträmassa o wallboard\nAntal anställda: 365\nÅrsomsättning: 40 000 000\nAktiekapital: 4 000 000\nVeikst dlr Lennart Strandberg\nEtableringsår: 1824.\n\nSJÖ\n\nBox 439. Tel 011-13 43 70.\nBankgiro 82-4373. Postgiro 125458\n\nsiiisili\n\nVeiksamhet: Utför\nstädningsarbeten, maskinell golvvård,\nfönster-putsning o mattvätt\nAvdelningskontor: Eskilstuna,\nFagersta, Linköping, Ludvika,\nNyköping, Oxelösund, Trollhättan,\nVästerås, Åtvidaberg\nAntal anställda: 950\nÅrsomsättning: 9 000 000\nAkUekapital: 30000\nStyrelse: Dir Gunnar Jerhammar, dir\nStig Jerhammar, fru Lisa Jerhammar\nEtableringsàr 1956.\n\nAGA AKTIEBOLAG\n\nPnr 181 20\n\nLidingö 1, Fack. Tel 08-775 00 20.\nPostgiro 591. Tga Agafaros.\nTelex 17780 AGALID S\n\nAGA\n\nVerksamhet: Tllverkar o säljer\ngaser för industriella o medicinska\nändamål. Utrustningar för svetsning,\nskärning, flamhärdning o lödning.\nSystem för frysning o kylning med\nnitrogen s k kryoteknik.\nGyroinstru-ment o kommunikationsradio för\nflygplan. Periskop, avståndsmätare\no elektro-optiska instrument.\nKamerasystem för infrarödfotografering,\nAGA Thermovision. Mobil\nkommunikationsradio o pejlapparater.\nMedicinska apparater såsom narkos-,\nandnings- o oxygenterapiapparater,\nhjärt-lungmaskin o automatisk\nanalysmaskin, AutoChemist, för\nklinisk kemi\n\nGas- o svetsrörelsen i Sverige:\nAdministration, Agneg 29, 112 29\nStockholm. Tel 08-54 03 60\nDistriktskontor för gas o svets:\n\nÖstradistiktet: AGA, Grimstag 160,\n162 27 Vällingby. Tel 08-89 0410\nVästra distriktet: AGA, Gustaf\nDa-lénsg 19. Box 8883, 402 72\nGöteborg 8. Tel 031-22 22 00\nBergslagsdistriktet: AGA, Agav,\n81100 Sandviken. Tel 026-25 50 30\nSödra distriktet: AGA, Sprintg 4.\nFack. 20110 Malmö 1. Tel\n040-9342 10\n\nMellansvenska distriktet: AGA,\nRadiatorv 14 , 7 0 2 27 Cfrebro. Tel\n019-13 02 20\n\nNorrlandsdistriktet: AGA,\nLands-vägsallén 13, 852 38 Sundsvall.\nTel 060-15 07 30\nDessutom finns ett stort antal\ndistributionsställen för gas och\nsvetsmaterial. Uppgift om dessa\nerhålles på distriktskontoren\nVarunamn: AGA\nAntal anställda: 3 600\n(moderbolaget)\n\nAktiekapital: 112 500 000\nStyrelse: Bankdir Rune Höglund\n(ordf), disp Töre Hedin, prof Sune\nCarlson, dir Ulf Styren, dir Lars\nWirström, dir Gudmund\nSilfverstolpe, dir Sven Agrup\nVerkst dir: Sven Agrup\nEtableringsår: 1904.\n\nUPLANDSKUBBEN\n\nPnr 112 61\n\nStockholm, Essingebrog 10. Tel\n08-1314 40\n\nVerksamhet; Bageri. Tillverkar\nmatbröd o konditorivaror\nAntal anställda: 80\nÅrsomsättning: 9 000 000\nAktiekapital: 85 000\nVerkst dir Carl-Otto Winnberg\nEtableringsår: 1929.\n\nUPPSALA, UPSALA\n\nUPSALA ADVOKATBYRÅ\n\nPnr 75106\n\nUppsala 1, Svartbäcksg 1 A. Box\n447. Tel 018-13 96 10. Bankgiro\n80-2216. Postgiro 95200-2\nVerksamhet: Advokatbyrå,\ninkasso-byrå o egendomsagentur\nAntal anställda: 15\nÄgare o chefer: Adv Bengt\nTönne-sen, adv Stig Sohlberg\nKontorschef: Kamrer Evert\nTörnqvist\n\nEtableringsår: 1898.\n\nUPSALA BYGGNADSVAROR,\nAB\n\nPnr 751 04\n\nUppsala 1, O Agatan 39. Box 215.\nTel 018-14 90 40. Bankgiro 23-0079.\nPostgiro 34504. Telex 7432\nVerksamhet: Byggmaterialhandel\no småhusförsäljning\nAntal anställda: 80\nAktiekapital: 400 000\nVerkst dir: Ake Roos\nEtableringsår: 1934.\n\nUPPSALA\nCEMENT-GJUTERI, AB\n\nPnr 752 28\n\nUppsala, Hällbyg 27. Tel\n018-12 03 55. Bankgiro 80-2259.\nPostgiro 93230\n\nVerksamhet; Tillverkar o säljer\nbetongvaror, betongsten\nAntal anställda: 90\nÅrsomsättning: 11000 000\nAktiekapital: 1000 000\nVerkst dir. Staffan Ekholm\nEtableringsår: 1936.\n\nUPPSALA ELEKTR\nLINDAREVERKSTAD AB\n\nPnr 753 31\n\nUppsala, Storg 30. Tel 018-13 19 02.\nBankgiro 80-5070. Postgiro 86910\nVerksamhet: Utför el mek arbeten\nsamt servicearbeten\nAntal anställda: 8\n\nAktiekapital: 30 000\nVerkst dir: Ing Lars Holmin\nEtableringsår: 1927.\n\nUPPSALA LÅDFABRIK &amp;\nTRÄ-VARUAFFÄR\n\nPnr 751 03\n\nUppsala 1, Kungsängsesplanaden 9.\nBox 7. Tel 018-12 03 30. Bankgiro\n23-0038. Postgiro 141745\nVeiksamhet: Säljer trävaror o\növrigt byggnadsmaterial samt\ntillverkar takstolar o grövre snickerier\nAntal anställda: 40\nÅrsomsättning: 6 000 000\nChef: Fabr Ingvar Pettersson\nEtableringsår: 1938.\n\nUPPSALA MASKINMEKANO,\nAB\n\nPnr 75251\n\nUppsala, Krickv 3.,Tel\n018-32 44 00. Bankgiro 802-5942.\nPostgiro 590465-1\n\nVerksamhet Tillverkar fotocellut-\n\nrustningar\n\nAktiekapital: 5 000\n\nVerkst dir: Paul Pernik\n\nEtableringsår: 1961.\n\nUPPSALA MASKIN- &amp;\nVERKTYGSAFFÄR AB\n\nPnr 753 32\n\nUppsala, Kungsg 6. Tel\n018-14 94 90. Bankgiro 802-1750.\nPostgiro 26064-6\n\nVerksamhet: Säljer verktyg o\nmaskiner till industri o hantverk.\nAuktoriserade försäljare för ESAB\nelektroder o ATLAS COPCO\nkompressorer o verktyg. Hyresstation\nför ATLAS kompressorer\nAntal anställda: 13\nÅrsomsättning: 4 000 000\nAktiekapital: 80 000\nVerkst dir. Bertil Johansson\nDisp: Holger Johansson\nEtableringsår: 1925.\n\nUPSALA NYA ARMATUR.\nFABRIK AB\n\nPnr 736 00\n\nKungsör, Box 56. Tel 0227-115 74.\nBankgiro 404-7726. Postgiro\n231732-9\n\nVerksamhet Tillverkar o säljer\nelektrisk belysningsarmatur\nAntal anställda: 20\nÅrsomsättning: 1000000\nAktiekapital: 10 000\nVerkst din A Spåre\nEtableringsår: 1915.\n\nNORDISKA GOLV AB\n\nPnr 11648\n\nStockholm, Svedenborgsg 7. Tel\n08^1 59 00, 43 9010. Bankgiro\n331-4911. Postgiro 550594-6\nVerksamhet: Säljer o lägger allt i\ngolv\n\nVerkst dir: L Djurberg.\n\nNORDISKA INDUSTRI AB\n(N.I.A.B.)\n\nPnr 42122\n\nVästra Frölunda 1, Box 141.\nFrö-ullsg. Tel 031-45 03 00. Bankgiro\n500-0872. Postgiro 41250-2. Tga\nNordindustri. Telex 20917 NI AB S\nVerksamhet: Tapisserivaror,\ngarner, gardiner, linnevaror,\npartiavdelning\n\nAvdelningskontor: Stockholm C,\nOlofsg 10. Tel 08-10 67 52. Förest:\nDisp Tor Hellström\nMalmö C, Kyrkog 3 A. Tel\n040-12 45 60. Avd-chef: Carleric Schödin\nAktiekapital: 8 000 000\nVerkst dir: C E Lidbeck\nV verkst dir: E af Sandeberg\nEtableringsår: 1879.\n\nNORDISKA INSTRUMENT\nWIBOM &amp; SON KB\n\nPnr 18162\n\nLidingö, S Kungsv 236. Tel\n08-76602 80. Bankgiro 73-1676.\nPostgiro 507865. Tga Norinab.\nTelex 1534\n\nVerksamhet: Säljer militärteknisk\nmateriel, elektroniska räknare o\nräknedekader, omkopplare,\nelektroniska o mekaniska regulatorer,\nser-vohydraulik\n\nVarunamn: Contraves, Multiswitch,\n\nRoband, Electromatic, Koehring,\n\nPegasus, Hartman\n\nStyrelse: Dir Bror Hansson (ordf),\n\nadv Staffan Serrander, dir Henrik\n\nWibom\n\nVerkst dir: Henrik Wibom\nEtableringsår: 1921.\n\nNORDISKA KAPSYLFABRIKS\nAB\n\nPnr 121 63\n\nJohanneshov, Bolidenv 18. Tel\n08-59 0120. Bankgiro 33-2079.\nPostgiro 53130. Tga Nordkapsyl\nVerksamhet: Tillverkar o säljer\nflaskförslutningar i aluminium.\nSpecialitet: Pilfer-Proof\nAntal anställda: 13\nAktiekapital: 150 000\nFabrikschef: Disp Carl Orrenius\nEtableringsår: 1927.\n\nBÖDA BRUKS AB\n\nPnr 360 65\n\nBöda glasbruk. Tel 0481-240 00.\nBankgiro 615-7200. Postgiro\n7775-0. Tga Bodaglas, Kalmar\nVerksamhet: Tillverkar\nkristallglas, smidesprodukter m m\nVerkst dir: Erik Rosén\nEtableringsår: 1864.",
    "structured": {
        "1": {
            "company_name": "LDNSBODA SNICKERIFABRIK",
            "activity": "Beställningssnickerier såsom fönster- o dörrpartier",
            "establishment_year": 1910
        },
        "2": {
            "company_name": "LüVBERGA BETONG. GJUTERI, AB",
            "activity": "Tillverkar muffrör, vägrör, vägräckesstolpar, brunnsringar o betonghålsten",
            "establishment_year": 1946
        },
        "3": {
            "company_name": "VEDKAMINER AB",
            "activity": "Tillverkar kaminer för skogskojor mm, bastuugnar",
            "capital": 20000,
            "key_personnel": [
                {
                    "name": "Greve Gösta Wachtmeister",
                    "position": "Verkst dir"
                }
            ],
            "establishment_year": 1934
        },
        "4": {
            "company_name": "VEDUMS SNICKERIFABRIK AB",
            "activity": "Tillverkar o säljer köksinredningar, även färdigmålade",
            "employees": 45,
            "annual_turnover": 6000000,
            "capital": 100000,
            "key_personnel": [
                {
                    "name": "Disp Eskil Lindberg"
                }
            ],
            "establishment_year": 1919
        },
        "5": {
            "company_name": "KINDS YLLEFABRIKS AB",
            "activity": "Tillverkar yttertrikå i herr-, dam- o barnartiklar",
            "capital": 150000,
            "key_personnel": [
                {
                    "name": "Jacob Jacobsson"
                },
                {
                    "name": "Isaac Orre"
                }
            ],
            "establishment_year": 1934
        },
        "6": {
            "company_name": "KINDA SKOGSPRODUKTER, AB",
            "activity": "Skogsavverkningar, barkning av massaved samt försäljning o förmedling av timmer o övriga skogsprodukter",
            "employees": 25,
            "annual_turnover": 10000000,
            "capital": 50000,
            "key_personnel": [
                {
                    "name": "Per-Eric Järnland",
                    "position": "Verkst dir"
                }
            ],
            "establishment_year": 1960
        },
        "7": {
            "company_name": "KINDABETONG AB",
            "activity": "Tillverkar o säljer betong o betongvaror av alla slag, grus, singel mm",
            "employees": 24,
            "annual_turnover": 2000000,
            "capital": 80000,
            "key_personnel": [
                {
                    "name": "John Walfridsson",
                    "position": "Verkst dir"
                }
            ],
            "establishment_year": 1946
        },
        "8": {
            "company_name": "SVE",
            "establishment_year": 1907
        },
        "9": {
            "company_name": "SVENSKA SPECIAL. VERKTYG, AB",
            "activity": "Tillverkar verktyg o slitdetaljer av hårdmetall",
            "capital": 20000,
            "key_personnel": [
                {
                    "name": "Sven Ericsson",
                    "position": "Platschef"
                }
            ],
            "establishment_year": 1950
        },
        "10": {
            "company_name": "SVENSKA STANDARD. BOLAG AB",
            "activity": "Specialfirma för aktiebolagsbildning o aktiekapitalsökning",
            "employees": 20,
            "capital": 150000,
            "key_personnel": [
                {
                    "name": "Företagsekonom Sören Thunström",
                    "position": "Chef"
                }
            ],
            "establishment_year": 1954
        },
        "11": {
            "company_name": "SCHARINS SÖNER, AB",
            "activity": "Framställer torr mek trämassa o wallboard",
            "employees": 365,
            "annual_turnover": 40000000,
            "capital": 4000000,
            "key_personnel": [
                {
                    "name": "Lennart Strandberg",
                    "position": "Veikst dlr"
                }
            ],
            "establishment_year": 1824
        },
        "12": {
            "company_name": "SJÖ",
            "activity": "Utför städningsarbeten, maskinell golvvård, fönster-putsning o mattvätt",
            "employees": 950,
            "annual_turnover": 9000000,
            "capital": 30000,
            "key_personnel": [
                {
                    "name": "Dir Gunnar Jerhammar"
                },
                {
                    "name": "Dir Stig Jerhammar"
                },
                {
                    "name": "fru Lisa Jerhammar"
                }
            ],
            "establishment_year": 1956
        },
        "13": {
            "company_name": "AGA AKTIEBOLAG",
            "activity": "Tillverkar o säljer gaser för industriella o medicinska ändamål, utrustningar för svetsning, skärning, flamhärdning o lödning, system för frysning o kylning med nitrogen s k kryoteknik, Gyroinstru-ment o kommunikationsradio för flygplan, Periskop, avståndsmätare o elektro-optiska instrument",
            "employees": 3600,
            "capital": 112500000,
            "key_personnel": [
                {
                    "name": "Bankdir Rune Höglund",
                    "position": "Styrelse"
                },
                {
                    "name": "disp Töre Hedin",
                    "position": "Styrelse"
                },
                {
                    "name": "prof Sune Carlson",
                    "position": "Styrelse"
                },
                {
                    "name": "dir Ulf Styren",
                    "position": "Styrelse"
                },
                {
                    "name": "dir Lars Wirström",
                    "position": "Styrelse"
                },
                {
                    "name": "dir Gudmund Silfverstolpe",
                    "position": "Styrelse"
                },
                {
                    "name": "dir Sven Agrup",
                    "position": "Styrelse, Verkst dir"
                }
            ],
            "establishment_year": 1904
        },
        "14": {
            "company_name": "UPLANDSKUBBEN",
            "activity": "Tillverkar matbröd o konditorivaror",
            "employees": 80,
            "annual_turnover": 9000000,
            "capital": 85000,
            "key_personnel": [
                {
                    "name": "Carl-Otto Winnberg",
                    "position": "Verkst dir"
                }
            ],
            "establishment_year": 1929
        },
        "15": {
            "company_name": "UPSALA ADVOKATBYRÅ",
            "activity": "Advokatbyrå, inkasso-byrå o egendomsagentur",
            "employees": 15,
            "key_personnel": [
                {
                    "name": "Adv Bengt Tönnesen"
                },
                {
                    "name": "adv Stig Sohlberg"
                },
                {
                    "name": "Kamrer Evert Törnqvist",
                    "position": "Kontorschef"
                }
            ],
            "establishment_year": 1898
        },
        "16": {
            "company_name": "UPSALA BYGGNADSVAROR, AB",
            "activity": "Byggmaterialhandel o småhusförsäljning",
            "employees": 80,
            "capital": 400000,
            "key_personnel": [
                {
                    "name": "Ake Roos",
                    "position": "Verkst dir"
                }
            ],
            "establishment_year": 1934
        },
        "17": {
            "company_name": "UPPSALA CEMENT-GJUTERI, AB",
            "activity": "Tillverkar o säljer betongvaror, betongsten",
            "employees": 90,
            "annual_turnover": 11000,
            "capital": 1000000,
            "key_personnel": [
                {
                    "name": "Staffan Ekholm",
                    "position": "Verkst dir"
                }
            ],
            "establishment_year": 1936
        },
        "18": {
            "company_name": "UPPSALA ELEKTR LINDAREVERKSTAD AB",
            "activity": "Utför el mek arbeten samt servicearbeten",
            "employees": 8,
            "capital": 30000,
            "key_personnel": [
                {
                    "name": "Ing Lars Holmin",
                    "position": "Verkst dir"
                }
            ],
            "establishment_year": 1927
        },
        "19": {
            "company_name": "UPPSALA LÅDFABRIK &amp; TRÄ-VARUAFFÄR",
            "activity": "Säljer trävaror o övrigt byggnadsmaterial samt tillverkar takstolar o grövre snickerier",
            "employees": 40,
            "annual_turnover": 6000000,
            "key_personnel": [
                {
                    "name": "Fabr Ingvar Pettersson",
                    "position": "Chef"
                }
            ],
            "establishment_year": 1938
        },
        "20": {
            "company_name": "UPPSALA MASKINMEKANO, AB",
            "activity": "Tillverkar fotocellut-rustningar",
            "capital": 5000,
            "key_personnel": [
                {
                    "name": "Paul Pernik",
                    "position": "Verkst dir"
                }
            ],
            "establishment_year": 1961
        },
        "21": {
            "company_name": "UPPSALA MASKIN- &amp; VERKTYGSAFFÄR AB",
            "activity": "Säljer verktyg o maskiner till industri o hantverk, Auktoriserade försäljare för ESAB elektroder o ATLAS COPCO kompressorer o verktyg, Hyresstation för ATLAS kompressorer",
            "employees": 13,
            "annual_turnover": 4000000,
            "capital": 80000,
            "key_personnel": [
                {
                    "name": "Bertil Johansson",
                    "position": "Verkst dir"
                },
                {
                    "name": "Holger Johansson",
                    "position": "Disp"
                }
            ],
            "establishment_year": 1925
        },
        "22": {
            "company_name": "UPSALA NYA ARMATUR. FABRIK AB",
            "activity": "Tillverkar o säljer elektrisk belysningsarmatur",
            "employees": 20,
            "annual_turnover": 1000000,
            "capital": 10000,
            "key_personnel": [
                {
                    "name": "A Spåre",
                    "position": "Verkst din"
                }
            ],
            "establishment_year": 1915
        },
        "23": {
            "company_name": "NORDISKA GOLV AB",
            "activity": "Säljer o lägger allt i golv",
            "key_personnel": [
                {
                    "name": "L Djurberg",
                    "position": "Verkst dir"
                }
            ]
        },
        "24": {
            "company_name": "NORDISKA INDUSTRI AB (N.I.A.B.)",
            "activity": "Tapisserivaror, garner, gardiner, linnevaror, partiavdelning",
            "capital": 8000000,
            "key_personnel": [
                {
                    "name": "C E Lidbeck",
                    "position": "Verkst dir"
                },
                {
                    "name": "E af Sandeberg",
                    "position": "V verkst dir"
                }
            ],
            "establishment_year": 1879
        },
        "25": {
            "company_name": "NORDISKA INSTRUMENT WIBOM &amp; SON KB",
            "activity": "Säljer militärteknisk materiel, elektroniska räknare o räknedekader, omkopplare, elektroniska o mekaniska regulatorer, servohydraulik",
            "key_personnel": [
                {
                    "name": "Henrik Wibom",
                    "position": "Verkst dir"
                }
            ],
            "establishment_year": 1921
        },
        "26": {
            "company_name": "NORDISKA KAPSYLFABRIKS AB",
            "activity": "Tillverkar o säljer flaskförslutningar i aluminium. Specialitet: Pilfer-Proof",
            "employees": 13,
            "capital": 150000,
            "key_personnel": [
                {
                    "name": "Disp Carl Orrenius",
                    "position": "Fabrikschef"
                }
            ],
            "establishment_year": 1927
        },
        "27": {
            "company_name": "BÖDA BRUKS AB",
            "activity": "Tillverkar kristallglas, smidesprodukter m m",
            "key_personnel": [
                {
                    "name": "Erik Rosén",
                    "position": "Verkst dir"
                }
            ],
            "establishment_year": 1864
        }
    }
}