{
    "original": "ORE\n\nVerksamhet: Tillverkar sylt o saft\nAntal anställda: 10\nÅrsomsättning: 3 000 000\nChef: Pabr Lars Edgren\nEtableringsår: 1955.\n\nANN\n\nplastbelagt papper o piastbelagd\nväv\n\nVarunamn: Annebergsduk, Annecal,\nCon-Rit, Korv-Takt, Printofix,\nStar-Fix, Wall-Rit Linne, Wall-Rit, Vinyl\nAntal anställda: 180\nÅrsomsättning: 21000 000\nAktiekapital: 550000\nStyrelse: Dir Bertil Turesson\n(ordf), dir Magnus Thorfinn, dir\nNils Alm\n\nVerkst dir: Nils Alm\nFtjrsäljn-chef: Thorsten Roos\nExportchef: Sigurd Wenneberg\nEtableringsår: 1966\nTidigare Svenska Vaxduks AB.\n\nANNEBERGS-HUS AB\n\nPnr 434 02\n\nKungsbacka 2, Box 150. Anneberg.\nTel 0300-21150. Bankgiro\n546-5257 , 435-644 0. Postgiro 394250-5.\nTga A-hus\n\nVerksamhet: Tillverkar\nmonteringsfärdiga trähus\nAntal anställda: 60\nÅrsomsättning: 9 000 000\nAktiekapital: 300 000\nVerkst dir: Ake Ericson\nEtableringsår: 1947.\n\nANN EL EL &amp; KOMPRESSOR\nAB, A F\n\nPnr 114 41\n\nStockholm, Nybrog 64. Tel\n08-60 40 05, 60 40 71. Bankgiro\n56-5305. Postgiro 2322. Tga Tenrock\nVerksamhet: Tillverkar\nfönster-torkare Speed\nAntal anställda: 5\nÅrsomsättning: 1000 000\nEtableringsår: 1953.\n\nANNONSBYRÅ\n\nse resp namn.\n\nANNONS-KRANTZ AB\n\nPnr 111 81\n\nStockholm 1, Box 1110, Vasag 16.\nTel 08-22 08 5 0. Bankgiro 48-2703.\nPostgiro 553-8. Tga Annonskrantz.\nTelex 10059\n\nVerksamhet: Auktoriserad\nannonsbyrå. Fullservicebyrå\nAktiekapital: 100000\nVerkst dir: Henry Toft\nEtableringsår: 1921.\n\nFORSSMAN &amp; HOLMGREN\n\nPnr 401 20\n\nGöteborg 1, Mårten Krakowg 3.\nBox 13. Tel 031-15 11 22, 15 28 27.\nBankgiro 847-7291. Postgiro\n12219-2. Tga Forssmans\nVerksamhet: Import o\nengrosför-säljning av industrikemikalier\nChef: Roland Henriksson\nEtableringsår: 1825.\n\nIMPULS, AB\n\nPnr 113 20\n\nStockholm, Sankt Eriksplan 7. Tel\n08-34 08 50. Bankgiro 165-2999.\nPostgiro 255299-0. Tga Impuls.\nTelex 1555 IMPULS S\nVeiksamhet: Elektr ingenjörsfirma\nmed agentur- o grosshandel\nVarunamn: Impuls\nAntal anställda: 10\nÅrsomsättning: 5 000 000\nAktiekapital: 100000\nEtableringsår 1946.\n\nJACOBSEN AB. JAC\n\nPnr 402 23\n\nGöteborg 5, Kràketorpsg 10 A. Box\n5144. Tel 031-87 04 20. Bankgiro\n44-3126. Postgiro 45986.\nTga JacJac. Telex 20788\nVerksamhet: Tillverkar Luxo 1001\no lättmetallmarkiser\nAntal anställda: 44\nÅrsomsättning: 5 000 000\nAktiekapital: 100 000\nVerkst dir: Disp C G Hellström\nEtableringsår: 1939.\n\nVIT\n\nVISBY MOTORCENTRAL, AB\n\nPnr 62104\n\nVisby 4, Lummelundsv 9. Box 443.\nTel 0498-153 45. Bankgiro 83-4932.\nTelex 4135. Tga Motorcentralen\nVerksamhet: Säljer bilar,\nreservdelar. bensin, oljor, båtmotorer\nAktiekapital: 250000\nVerkst dir: Uno Persson\nEtableringsån 1936.\n\nKARLBERGS BILAFFÄR, AB\n\nPnr 598 00\n\nVimmerby, Box 13. Stångåg 4. Tel\n0492-126 10. Bankgiro 857-5037.\nPostgiro 163835-2\nVerksamhet: Nya o begagnade\nperson- o lastbilar av märket Volvo\nAntal anställda: 115\nÅrsomsättning: 26 000 000\nAktiekapital: 125 000\nVerkst dir: Olof Karlberg\nEtableringsår: 1930.\n\nSDDERLUNDS RUR AB\n\nPnr 815 00\n\nTierp, Greveg 27. Tel 0293-117 10.\nBankgiro 80-6128. Postgiro 162610\nVerksamhet: Utför VVS-installa-\n\ntioner\n\nFilial: Orbyhus, Roslagsv 22. Tel\n0295-100 60\n\nSkyttorp. Tel 018-35 21 94\nAntal anställda: 50\nÅrsomsättning: 4 500 000\nAktiekapital: 100 000\nVerkst dir: Ing Nils Engström\nEtableringsår: 1896\nOmbildat till aktiebolag 1958.\n\nSDDERLUND &amp; CO AB, C H\n\nPnr 411 20\n\nGöteborg, Arsenalsg 8. Tel\n031-1123 65, 11 6345. Bankgiro\n420-4525. Postgiro 24 0848-2. Tga\nSoedercomp. Telex 20936\nVerksamhet: Handelsagenter textil\nm fi branscher\nAntal anställda: 4\nAktiekapital: 15000\nVerkst dir: H Söderlund\nEtableringsår: 1941.\n\nSÖDERMALMS NYA TRÄVARU\nAB\n\nPnr 116 44\n\nStockholm, Båtklubbsv.\nHenriksdals Industriområde. Tel\n08-41 22 44 , 41 22 99. Bankgiro\n476-4536. Postgiro 51163-4\nVerksamhet: Säljer trävaror o\nbyggnadsmaterial\nFilial: Hemmestavik. Tel\n0766-20519, 20191\n\nDjurhamn, Djurö Brädgård. Tel\n0766-51301\nAktiekapital: 300000\nVerkst dir: Bertil Eriksson\nEtableringsår: 1925.\n\nSÖDERMANS METALL. &amp;\nTEXTIL AB\n\nPnr 212 28\n\nMalmö, Emilstorpsg 11. Tel\n040-1244 21, 1244 26. Bankgiro\n874-3197. Postgiro 435431-2\nVerksamhet: Köper o säljer\navfallsprodukter\nChef: K E Söderman\nEtableringsår: 1953.\n\nSÖDERMANLANDS\nENTREPRENAD AB\n\nPnr 611 00\n\nNyköping, Folkungav 1. Tel 0155-\n\n810 20. Bankgiro 61-9217. Postgiro\n511400\n\nVerksamhet: Entreprenader inom\nanläggnings- o byggnadsindustrin\nAntal anställda: 3\nÅrsomsättning: 2000000\nAktiekapital: 30 000\nVerkst din Ing Sven Thege\nEtableringsår: 1959.\n\nSÖDERMANLANDS LÄNS\nLANDSTINGS\nARBETSVÄRDSVERKSTÄDER\n\nCentraladministrationen (CA)\nPnr 630 08\n\nEskilstuna 8, Box 8020.\nLager-kvistsg 2. Tel 016-1172 20.\nPostgiro 167939-8\n\nVerksamhet: Egentillverkar\nprydnadsvaror i bl a tennpatinerat\nutförande, brödrostar, elektriska\nström-ställare, skidtakhållare o rattkälkar.\nLegotillverkar snickeriarbeten\nsåsom brevhurtsar, hyllor o skåp,\ngunghästar, barnpussel,\nverktygsetuier samt element för\nteaterdekorationer. Utrustningar för\nrörelsehindrade, svarvnings-, fräs- o\nborrningsarbeten, skinpackning av kon-,\nsumentvaror, plastinbakningar samt\nlegoförpackning av skilda detaljer\ni plastpåsar\n\nVarunamn: Atve, Elva, Ico\nAntal anställda: 380\nÅrsomslutning: 14 000 000\n\nStyrelseordf: Rektor Bengt Hanson\nArbetsvårdschef: Erie Ericsson\nEtableringsår 1958\nUnderställd Södermanlands läns\nlandsting, Nyköping, som är\nhuvudman för verksamheten.\n\nSÖDERSTRÖMS\nKONSULT-BYRÄ AB\n\nPnr 600 11\n\nNorrköping 11, Box 11100.\nBrånne-stahus. Tel 011-10 03 70. Bankgiro\n824-4352. Postgiro 583755-4\nVerksamhet Auktoriserad\nreklamkonsult\n\nAntal anstäüda: 7\nStyrelse: Fra Marianne Söderström,\ndir Lennart Söderström, aukt\nrevisor Rolf Sandfridson\nVerkst dir: Lennart Söderström\nEtableringsår: 1956.\n\nSÖDERSTRÖMS SKEPPS.\nSTUVERI AB, A F\n\nPnr 104 65\n\nStockholm 15, Box 15055.\nSödermalmstorg 2. Tel 08-44 09 40.\nBankgiro 568-9468. Postgiro 50588-3.\nTga Remember\nVerksamhet: Skeppsstuveri\nAntal anstäUda: 177\nAktiekapital: 400 000\nVerkst dir: Ivar Söderström\nEtableringsår: 1849.\n\nVÄST E RÅSSP EDI TI ÖN, AB\n\nPnr 72103\n\nVästerås 1, Hamng 6. Box 1. Tel\n021-13 76 60. Bankgiro 23-2562.\n80-8658. Postgiro 75733. Telex\n40650, 40651. Tga Spedition\nVerksamhet: Skeppsklarerare,\nskeppsmäklare o spedltörer\nAktiekapital: 149 400\nVerkst dir: Konsul Arne Lindén\nEtableringsån 1918.\n\nAG\n\nag METALLFABRIKEN\nVERKTYG &amp; MASKINER\n\nPnr 631 07\n\nEskilstuna 1, Box 558. Köpmang\n46 (Godsadress). Tel 016-14 75 72,\n1156 90. Postgiro 391789-5\nVerksamhet: Utför drag- o\nexcen-terpressning. Tillverkar\nprydnadsartiklar i metall\nChef: Axel Granlund\nEtableringsår: 1948.",
    "structured": {
        "1": {
            "company_name": "ORE",
            "activity": "Tillverkar sylt o saft",
            "employees": 10,
            "annual_turnover": 3000000,
            "key_personnel": [
                {
                    "name": "Pabr Lars Edgren",
                    "position": "Chef"
                }
            ],
            "establishment_year": 1955
        },
        "2": {
            "company_name": "ANN",
            "activity": "plastbelagt papper o piastbelagd väv",
            "varunamn": [
                "Annebergsduk",
                "Annecal",
                "Con-Rit",
                "Korv-Takt",
                "Printofix",
                "Star-Fix",
                "Wall-Rit Linne",
                "Wall-Rit",
                "Vinyl"
            ],
            "employees": 180,
            "annual_turnover": 21000000,
            "capital": 550000,
            "key_personnel": [
                {
                    "name": "Dir Bertil Turesson",
                    "position": "Styrelseordf"
                },
                {
                    "name": "Nils Alm",
                    "position": "Verkst dir"
                },
                {
                    "name": "Thorsten Roos",
                    "position": "Ftjrsäljn-chef"
                },
                {
                    "name": "Sigurd Wenneberg",
                    "position": "Exportchef"
                }
            ],
            "establishment_year": 1966,
            "former_company_name": "Svenska Vaxduks AB"
        },
        "3": {
            "company_name": "ANNEBERGS-HUS AB",
            "pnr": "434 02",
            "address": "Box 150. Anneberg",
            "phone_number": "0300-21150",
            "bank_details": {
                "bankgiro": "546-5257",
                "postgiro": "435-644 0"
            },
            "activity": "Tillverkar monteringsfärdiga trähus",
            "employees": 60,
            "annual_turnover": 9000000,
            "capital": 300000,
            "key_personnel": [
                {
                    "name": "Ake Ericson",
                    "position": "Verkst dir"
                }
            ],
            "establishment_year": 1947
        },
        "4": {
            "company_name": "ANN EL EL & KOMPRESSOR AB, A F",
            "pnr": "114 41",
            "address": "Nybrog 64. Stockholm",
            "phone_number": [
                "08-60 40 05",
                "60 40 71"
            ],
            "bank_details": {
                "bankgiro": "56-5305",
                "postgiro": "2322"
            },
            "activity": "Tillverkar fönster-torkare Speed",
            "employees": 5,
            "annual_turnover": 1000000,
            "establishment_year": 1953
        },
        "5": {
            "company_name": "ANNONSBYRÅ"
        },
        "6": {
            "company_name": "ANNONS-KRANTZ AB",
            "pnr": "111 81",
            "address": "Box 1110, Vasag 16. Stockholm",
            "phone_number": "08-22 08 5 0",
            "bank_details": {
                "bankgiro": "48-2703",
                "postgiro": "553-8"
            },
            "activity": "Auktoriserad annonsbyrå. Fullservicebyrå",
            "capital": 100000,
            "key_personnel": [
                {
                    "name": "Henry Toft",
                    "position": "Verkst dir"
                }
            ],
            "establishment_year": 1921
        },
        "7": {
            "company_name": "FORSSMAN & HOLMGREN",
            "pnr": "401 20",
            "address": "Mårten Krakowg 3. Göteborg",
            "phone_number": [
                "031-15 11 22",
                "15 28 27"
            ],
            "bank_details": {
                "bankgiro": "847-7291",
                "postgiro": "12219-2"
            },
            "activity": "Import o engrosför-säljning av industrikemikalier",
            "key_personnel": [
                {
                    "name": "Roland Henriksson",
                    "position": "Chef"
                }
            ],
            "establishment_year": 1825
        },
        "8": {
            "company_name": "IMPULS, AB",
            "pnr": "113 20",
            "address": "Sankt Eriksplan 7. Stockholm",
            "phone_number": "08-34 08 50",
            "bank_details": {
                "bankgiro": "165-2999",
                "postgiro": "255299-0"
            },
            "activity": "Elektr ingenjörsfirma med agentur- o grosshandel",
            "varunamn": "Impuls",
            "employees": 10,
            "annual_turnover": 5000000,
            "capital": 100000,
            "establishment_year": 1946
        },
        "9": {
            "company_name": "JACOBSEN AB. JAC",
            "pnr": "402 23",
            "address": "Kràketorpsg 10 A. Göteborg",
            "phone_number": "031-87 04 20",
            "bank_details": {
                "bankgiro": "44-3126",
                "postgiro": "45986"
            },
            "activity": "Tillverkar Luxo 1001 o lättmetallmarkiser",
            "employees": 44,
            "annual_turnover": 5000000,
            "capital": 100000,
            "key_personnel": [
                {
                    "name": "Disp C G Hellström",
                    "position": "Verkst dir"
                }
            ],
            "establishment_year": 1939
        },
        "10": {
            "company_name": "VISBY MOTORCENTRAL, AB",
            "pnr": "62104",
            "address": "Lummelundsv 9. Visby",
            "phone_number": "0498-153 45",
            "bank_details": {
                "bankgiro": "83-4932"
            },
            "activity": "Säljer bilar, reservdelar. bensin, oljor, båtmotorer",
            "capital": 250000,
            "key_personnel": [
                {
                    "name": "Uno Persson",
                    "position": "Verkst dir"
                }
            ],
            "establishment_year": 1936
        },
        "11": {
            "company_name": "KARLBERGS BILAFFÄR, AB",
            "pnr": "598 00",
            "address": "Stångåg 4. Vimmerby",
            "phone_number": "0492-126 10",
            "bank_details": {
                "bankgiro": "857-5037",
                "postgiro": "163835-2"
            },
            "activity": "Nya o begagnade person- o lastbilar av märket Volvo",
            "employees": 115,
            "annual_turnover": 26000000,
            "capital": 125000,
            "key_personnel": [
                {
                    "name": "Olof Karlberg",
                    "position": "Verkst dir"
                }
            ],
            "establishment_year": 1930
        },
        "12": {
            "company_name": "SDDERLUNDS RUR AB",
            "pnr": "815 00",
            "address": [
                "Greveg 27. Tierp",
                "Roslagsv 22. Orbyhus",
                "Tel 0295-100 60",
                "Skyttorp. Tel 018-35 21 94"
            ],
            "phone_number": "0293-117 10",
            "bank_details": {
                "bankgiro": "80-6128",
                "postgiro": "162610"
            },
            "activity": "Utför VVS-installationer",
            "employees": 50,
            "annual_turnover": 4500000,
            "capital": 100000,
            "key_personnel": [
                {
                    "name": "Ing Nils Engström",
                    "position": "Verkst dir"
                }
            ],
            "establishment_year": 1896,
            "ombildat_till_aktiebolag_year": 1958
        },
        "13": {
            "company_name": "SDDERLUND & CO AB, C H",
            "pnr": "411 20",
            "address": "Arsenalsg 8. Göteborg",
            "phone_number": [
                "031-1123 65",
                "11 6345"
            ],
            "bank_details": {
                "bankgiro": "420-4525",
                "postgiro": "24 0848-2"
            },
            "activity": "Handelsagenter textil m fi branscher",
            "employees": 4,
            "capital": 15000,
            "key_personnel": [
                {
                    "name": "H Söderlund",
                    "position": "Verkst dir"
                }
            ],
            "establishment_year": 1941
        },
        "14": {
            "company_name": "SÖDERMALMS NYA TRÄVARU AB",
            "pnr": "116 44",
            "address": "Båtklubbsv. Henriksdals Industriområde. Stockholm",
            "phone_number": [
                "08-41 22 44",
                "41 22 99"
            ],
            "bank_details": {
                "bankgiro": "476-4536",
                "postgiro": "51163-4"
            },
            "activity": "Säljer trävaror o byggnadsmaterial",
            "filial": {
                "Hemmestavik": "0766-20519, 20191",
                "Djurhamn": "0766-51301"
            },
            "capital": 300000,
            "key_personnel": [
                {
                    "name": "Bertil Eriksson",
                    "position": "Verkst dir"
                }
            ],
            "establishment_year": 1925
        },
        "15": {
            "company_name": "SÖDERMANS METALL. & TEXTIL AB",
            "pnr": "212 28",
            "address": "Emilstorpsg 11, Malmö",
            "phone_number": [
                "040-1244 21",
                "1244 26"
            ],
            "bank_details": {
                "bankgiro": "874-3197",
                "postgiro": "435431-2"
            },
            "activity": "Köper o säljer avfallsprodukter",
            "key_personnel": [
                {
                    "name": "K E Söderman",
                    "position": "Chef"
                }
            ],
            "establishment_year": 1953
        },
        "16": {
            "company_name": "SÖDERMANLANDS ENTREPRENAD AB",
            "pnr": "611 00",
            "address": "Folkungav 1. Nyköping",
            "phone_number": "0155-810 20",
            "bank_details": {
                "bankgiro": "61-9217"
            },
            "activity": "Entreprenader inom anläggnings- o byggnadsindustrin",
            "employees": 3,
            "annual_turnover": 2000000,
            "capital": 30000,
            "key_personnel": [
                {
                    "name": "Ing Sven Thege",
                    "position": "Verkst din"
                }
            ],
            "establishment_year": 1959
        },
        "17": {
            "company_name": "SÖDERMANLANDS LÄNS LANDSTINGS ARBETSVÄRDSVERKSTÄDER",
            "pnr": "630 08",
            "address": "Lager-kvistsg 2. Eskilstuna",
            "phone_number": "016-1172 20",
            "postgiro": "167939-8",
            "activity": "Egentillverkar prydnadsvaror i bl a tennpatinerat utförande, brödrostar, elektriska ström-ställare, skidtakhållare o rattkälkar.",
            "styreleseordf": "Rektor Bengt Hanson",
            "arbetsvårdschef": "Erie Ericsson",
            "employees": 380,
            "annual_turnover": "14000000",
            "establishment_year": 1958
        },
        "18": {
            "company_name": "SÖDERSTRÖMS KONSULT-BYRÄ AB",
            "pnr": "600 11",
            "address": "Brånne-stahus. Norrköping",
            "phone_number": "011-10 03 70",
            "bank_details": {
                "bankgiro": "824-4352",
                "postgiro": "583755-4"
            },
            "activity": "Auktoriserad reklamkonsult",
            "employees": 7,
            "key_personnel": [
                {
                    "name": "Fra Marianne Söderström",
                    "position": "Styrelse"
                },
                {
                    "name": "Lennart Söderström",
                    "position": "Verkst dir"
                },
                {
                    "name": "Rolf Sandfridson",
                    "position": "aukt.revisor"
                }
            ],
            "establishment_year": 1956
        },
        "19": {
            "company_name": "SÖDERSTRÖMS SKEPPS. STUVERI AB, A F",
            "pnr": "104 65",
            "address": "Södermalmstorg 2. Stockholm",
            "phone_number": "08-44 09 40",
            "bank_details": {
                "bankgiro": "568-9468",
                "postgiro": "50588-3"
            },
            "activity": "Skeppsstuveri",
            "employees": 177,
            "capital": 400000,
            "key_personnel": [
                {
                    "name": "Ivar Söderström",
                    "position": "Verkst dir"
                }
            ],
            "establishment_year": 1849
        },
        "20": {
            "company_name": "VÄST E RÅSSP EDI TI ÖN, AB",
            "pnr": "72103",
            "address": "Hamng 6. Västerås",
            "phone_number": "021-13 76 60",
            "bank_details": {
                "bankgiro": "23-2562",
                "postgiro": "80-8658"
            },
            "activity": "Skeppsklarerare, skeppsmäklare o spedltörer",
            "capital": 149400,
            "key_personnel": [
                {
                    "name": "Konsul Arne Lindén",
                    "position": "Verkst dir"
                }
            ],
            "establishment_year": 1918
        },
        "21": {
            "company_name": "ag METALLFABRIKEN VERKTYG & MASKINER",
            "pnr": "631 07",
            "address": "Köpmang 46 (Godsadress). Eskilstuna",
            "phone_number": [
                "016-14 75 72",
                "1156 90"
            ],
            "postgiro": "391789-5",
            "activity": "Utför drag- o excen-terpressning. Tillverkar prydnadsartiklar i metall",
            "key_personnel": [
                {
                    "name": "Axel Granlund",
                    "position": "Chef"
                }
            ],
            "establishment_year": 1948
        }
    }
}