{
    "original": "STÅLDÖRRAR, AB\n\nPnr 145 57\n\nNorsborg, Alby Industriområde. Tel\n08-710 74 73,710 70 75. Bankgiro\n33-1461. Postgiro 160309\nVerksamhet: Tillverkar hissdörrar,\nhissfronter etc\nAntal anstäUda: 18\nÅrsomsättning: 1400 000\nAktiekapital: 50 000\nStyrelse: Ing Arne Gamrin (ordf),\ning Lennart Junborg, verkmäst\nOlof Nyström\n\nVerkst dir: Ing Lennart Junborg\nEtableringsår: 1957.\n\nUGNSBYGGNADSBYRÅN AB\n\nPnr 352 33\n\nVäxiö.Linnég 6 B.Tel0470-15379,\n15070. Tga Ugnsbyrån\nVerksamhet: Tillverkar elektriska\no oljeeldade ugnar för\nglasindu-stiln. Utför eldfasta murningar\nAntal anställda: 8\nÅrsomsättning: 700 000\nAktiekapital: 25 000\nVerkst dir: Henry Engström\nEtableringsår 1922\nOmbildat till aktiebolag 1954.\n\nUGNSMURNING AB\n\nPnr 730 50\n\nSkultuna, Vallonv 24. Tel\n021-700 39 , 24 1 62. Bankgiro 14-8308.\nPostgiro 675198\n\nVerksamhet: Utför kompletta\nmur-ningsarbeten av alla slag\nAntal anställda: 14\nÅrsomsättning: 600000\nAktiekapital: 10 000\nDir: Erik Brtinnel\nEtableringsår: 1965.\n\nROLITE AB\n\nPnr 183 03\n\nTäby 3, Box 3022. Djursholmsv 29.\nTel 08-756 0206. Bankgiro\n583-3496. Postgiro 156832-8. Tga\nIwa-print. Telex 17900\nVerksamhet: Lysvagn, flygfältsljus,\ndelar för elmotorer, trafokärnor\nAktiekapital: 5 000\nVerkst dir: Carl Lothigius\nEtableringsår 1967.\n\nAROSKRAFT, AB\n\nPnr 72103\n\nVästerås 1, Box 14. Carl Hennings\ng 2. Tel 021-16 00 00. Bankgiro\n730-5469. Postgiro 10525-4\nVerksamhet: Uppförande av\nkraftvärmeverk. Produktion av elektrisk\nenergi o värme\nAktiekapital: 30 000 000\nStyrelse: Dir Vilgot Lannér (ordf),\ndir Tage Arnell, dir Bengt Löf,\nkommunalråd Gustaf Olsson, dir\nErik Ternström\nVerkst dir: John Sintorn\nV verkst dir: Lars Netzler\nEtableringsår: 1965.\n\nAROSVERKEN, AB\n\nPnr 723 50\n\nVästerås, Fältmätarg 9. Tel\n021-11 01 75, 11 01 76. Bankgiro 63-0008.\nPostgiro 177449\n\nVerksamhet: Tillverkar excenter-\n\npressar\n\nAntal anställda: 60\nÅrsomsättning: 5 000 000\nAktiekapital: 300 000\nStyrelse: Adv Lennart Sparrin\n(ordf), dir Allan Roslund, dir Arne\nUllsten\n\nVerkst dir: Arne Ullsten\nEtableringsår: 1940.\n\nBRODD &amp; ALLERHOLM, AB\n\nPnr 57071\n\nBerga. Tel 0491-500 90, 503 30.\nBankgiro 14-9468. Postgiro 275746\nVerksamhet: Tillverkar sittmöbler\no förvaringsmöbler\nAntal anställda: 32\nÅrsomsättning: 1400 000\nAktiekapital: 30 000\nVerkst dir: Erik Allerholm\nEtableringsår: 1943.\n\nBREOX MÖBLER AB\n\nPnr 280 30\n\nOderljunga. Tel 0435-322 00.\nBankgiro 673-9122. Postgiro 323500-9\nVerksamhet: Tillverkar trämöbler,\nbokhyllserier, matbord o stolar\nFörsäljningskontor Stockholm VA.\nCarl Erie Stjerna, Torsg 48. Tel\n08-30 89 30, 34 7400\nVarunamn: Breox\nAntal anställda: 40\nÅrsomsättning: 5 000 000\nAktiekapital: 200 000\nChefer: Dir Harry Elowsson, dir\nHjalmar Jalmerot\nEtableringsår: 1946\nOmbildat till aktiebolag 1963.\n\nBRETTMAN &amp; CO, AB\n\nPnr 21124\n\nMalmö, Borrg 4. Tel 040-18 09 30.\nBankgiro 876-3286. Postgiro\n531659-1. Tga Breco\nVerksamhet: Utför o säljer\ngolvbeläggningar, väggbeklädnader,\nlaminatmontage, plattsättning,\nfog-ningsarbete. Heltäckningsmattor.\nCementmosaikgolv\nAntal anställda: 75\nÅrsomsättning: 7 000 000\nAktiekapital: 200000\nVerkst dir: Ing Stig Brettman\nEntrepr-chef: W Rönnerling\nEtableringsår: 1967.\n\nGRA\n\nGRAND HOTEL\n\nPnr 55102\n\nJönköping 1, Hovrättstorget. Box\n142. Tel 036-11 96 00. Bankgiro\n544-9285. Postgiro 126142-9. Tga\nGrand\n\nVerksamhet: Hotellrörelse,\nutställningssalar, uppackningsrum\nÄgare o chef: Sven Benér\nEtableringsår: 1904.\n\nBOSTROM SÄGVERKSBYRÄ, A\n\nPnr 360 61\n\nHelgevärma, Kungsv 8. Tel\n0470-60245. Bankgiro 357-0504. Posts\ngiro 379929-3\n\nVerksamhet; Tillverkar\nABO-luckan, samtliga typer samt\ntransportanordningar av alla slag för\nsågverksindustrin\nVarunamn: ABO-luckan\nÅrsomsättning: 450 000\nChef: Ing A Boström\nEtableringsår. 1953.\n\nBIA HÄRDPLAST AB\n\nPnr 73100\n\nKöping. Tel 0221-107 91, 133 91.\nBankgiro 811-2690. Postgiro\n576880-9. Tga Bia\nVerksamhet: Utför\nbeställningsarbeten för industrin i\nglasfiber-armerad plast. Specialitet: alla\nslag av skåp samt cisterner för\nolja, vatten o avlopp m m\nVarunamn: Bia\nAntal anställda: 17\nÅrsomsättning: 3 000 000\nAktiekapital: 20 000\nStyrelse: Fru Maja Elisabet\nNilsson (ordf), dir Einar Nilsson\nVerkst dir: Einar Nilsson\nEtableringsår: 1960.\n\nJONSSONS TAKPANNEFABRIK,\nBRÖDERNA\n\nPnr 93104\n\nSkellefteå 4, Rosg 59. Box 1246.\n\nTel 0910-132 33, 13216. Bankgiro\n\n764-1012. Postgiro 483783-7\n\nVerksamhet: Tillverkar takpannor\n\nav betong\n\nAntal anställda: 8\n\nÄgare o chefer: Töre Jonsson,\n\nMartin Jonsson\n\nEtableringsår: 1951.\n\nJONSSONS TORRDOCKA,\nBRÖDERNA\n\nPnr 53100\n\nLidköping, Trelleberg. Tel\n0510-101 22, 103 25. Bankgiro 21-2329.\nPostgiro 571670\n\nVerksamhet: Utför mindre\nfartygs-byggnader av stål\nAntal anställda: 17\nÅrsomsättning: 1000 000\nChef: Harry Jonsson\nEtableringsår: 1960.\n\nJONSSONS TRÄINDUSTRI AB,\nBRÖDERNA\n\nPnr 34010\n\nLidhult, Box 82. Tel 035-91048,\n913 48. Bankgiro 55-2416. Postgiro\n323108\n\nVerksamhet: Tillverkar\nköksinredningar, hörnskåp i allmoge,\nbarnsängar o barnhagar\nAntal anställda: 34\nÅrsomsättning: 1 500 000\nAktiekapital: 100 000\nVerkst dir. David Jonsson\nEtableringsår: 1944.",
    "structured": {
        "1": {
            "company_name": "STÅLDÖRRAR, AB",
            "pnr": "145 57",
            "address": "Norsborg, Alby Industriområde",
            "phone_number": "08-710 74 73,710 70 75",
            "bank_details": {
                "bankgiro": "33-1461",
                "postgiro": "160309"
            },
            "activity": "Tillverkar hissdörrar, hissfronter etc",
            "employees": 18,
            "annual_turnover": 1400000,
            "capital": 50000,
            "key_personnel": [
                {
                    "name": "Ing Arne Gamrin",
                    "position": "ordf"
                },
                {
                    "name": "Ing Lennart Junborg",
                    "position": ""
                },
                {
                    "name": "Olof Nyström",
                    "position": "verkmäst"
                }
            ],
            "establishment_year": 1957
        },
        "2": {
            "company_name": "UGNSBYGGNADSBYRÅN AB",
            "pnr": "352 33",
            "address": "Växiö.Linnég 6 B",
            "phone_number": "0470-15379, 15070",
            "activity": "Tillverkar elektriska o oljeeldade ugnar för glasindu-stiln. Utför eldfasta murningar",
            "employees": 8,
            "annual_turnover": 700000,
            "capital": 25000,
            "key_personnel": [
                {
                    "name": "Henry Engström",
                    "position": "Verkst dir"
                }
            ],
            "establishment_year": 1922
        },
        "3": {
            "company_name": "UGNSMURNING AB",
            "pnr": "730 50",
            "address": "Skultuna, Vallonv 24",
            "phone_number": "021-700 39 , 24 1 62",
            "bank_details": {
                "bankgiro": "14-8308",
                "postgiro": "675198"
            },
            "activity": "Utför kompletta murningsarbeten av alla slag",
            "employees": 14,
            "annual_turnover": 600000,
            "capital": 10000,
            "key_personnel": [
                {
                    "name": "Erik Brtinnel",
                    "position": "Dir"
                }
            ],
            "establishment_year": 1965
        },
        "4": {
            "company_name": "ROLITE AB",
            "pnr": "183 03",
            "address": "Täby 3, Box 3022. Djursholmsv 29",
            "phone_number": "08-756 0206",
            "bank_details": {
                "bankgiro": "583-3496",
                "postgiro": "156832-8"
            },
            "activity": "Lysvagn, flygfältsljus, delar för elmotorer, trafokärnor",
            "capital": 5000,
            "key_personnel": [
                {
                    "name": "Carl Lothigius",
                    "position": "Verkst dir"
                }
            ],
            "establishment_year": 1967
        },
        "5": {
            "company_name": "AROSKRAFT, AB",
            "pnr": "72103",
            "address": "Västerås 1, Box 14. Carl Hennings g 2",
            "phone_number": "021-16 00 00",
            "bank_details": {
                "bankgiro": "730-5469",
                "postgiro": "10525-4"
            },
            "activity": "Uppförande av kraftvärmeverk. Produktion av elektrisk energi o värme",
            "capital": 30000000,
            "key_personnel": [
                {
                    "name": "Dir Vilgot Lannér",
                    "position": "ordf"
                },
                {
                    "name": "dir Tage Arnell",
                    "position": "dir"
                },
                {
                    "name": "dir Bengt Löf",
                    "position": "dir"
                },
                {
                    "name": "kommunalråd Gustaf Olsson",
                    "position": "dir"
                },
                {
                    "name": "dir Erik Ternström",
                    "position": "dir"
                }
            ],
            "establishment_year": 1965
        },
        "6": {
            "company_name": "AROSVERKEN, AB",
            "pnr": "723 50",
            "address": "Västerås, Fältmätarg 9",
            "phone_number": "021-11 01 75, 11 01 76",
            "bank_details": {
                "bankgiro": "63-0008",
                "postgiro": "177449"
            },
            "activity": "Tillverkar excenter-pressar",
            "employees": 60,
            "annual_turnover": 5000000,
            "capital": 300000,
            "key_personnel": [
                {
                    "name": "Adv Lennart Sparrin",
                    "position": "ordf"
                },
                {
                    "name": "dir Allan Roslund",
                    "position": "dir"
                },
                {
                    "name": "dir Arne Ullsten",
                    "position": "dir"
                }
            ],
            "establishment_year": 1940
        },
        "7": {
            "company_name": "BRODD & ALLERHOLM, AB",
            "pnr": "57071",
            "address": "Berga",
            "phone_number": "0491-500 90, 503 30",
            "bank_details": {
                "bankgiro": "14-9468",
                "postgiro": "275746"
            },
            "activity": "Tillverkar sittmöbler o förvaringsmöbler",
            "employees": 32,
            "annual_turnover": 1400000,
            "capital": 30000,
            "key_personnel": [
                {
                    "name": "Erik Allerholm",
                    "position": "Verkst dir"
                }
            ],
            "establishment_year": 1943
        },
        "8": {
            "company_name": "BREOX MÖBLER AB",
            "pnr": "280 30",
            "address": "Oderljunga",
            "phone_number": "0435-322 00",
            "bank_details": {
                "bankgiro": "673-9122",
                "postgiro": "323500-9"
            },
            "activity": "Tillverkar trämöbler, bokhyllserier, matbord o stolar",
            "employees": 40,
            "annual_turnover": 5000000,
            "capital": 200000,
            "key_personnel": [
                {
                    "name": "Dir Harry Elowsson",
                    "position": "dir"
                },
                {
                    "name": "dir Hjalmar Jalmerot",
                    "position": "dir"
                }
            ],
            "establishment_year": 1946
        },
        "9": {
            "company_name": "BRETTMAN & CO, AB",
            "pnr": "21124",
            "address": "Malmö, Borrg 4",
            "phone_number": "040-18 09 30",
            "bank_details": {
                "bankgiro": "876-3286",
                "postgiro": "531659-1"
            },
            "activity": "Utför o säljer golvbeläggningar, väggbeklädnader, laminatmontage, plattsättning, fog-ningsarbete. Heltäckningsmattor. Cementmosaikgolv",
            "employees": 75,
            "annual_turnover": 7000000,
            "capital": 200000,
            "key_personnel": [
                {
                    "name": "Ing Stig Brettman",
                    "position": "Verkst dir"
                },
                {
                    "name": "W Rönnerling",
                    "position": "Entrepr-chef"
                }
            ],
            "establishment_year": 1967
        },
        "10": {
            "company_name": "GRAND HOTEL",
            "pnr": "55102",
            "address": "Jönköping 1, Hovrättstorget. Box 142",
            "phone_number": "036-11 96 00",
            "bank_details": {
                "bankgiro": "544-9285",
                "postgiro": "126142-9"
            },
            "activity": "Hotellrörelse, utställningssalar, uppackningsrum",
            "owner": "Sven Benér",
            "establishment_year": 1904
        },
        "11": {
            "company_name": "BOSTROM SÄGVERKSBYRÄ, A",
            "pnr": "360 61",
            "address": "Helgevärma, Kungsv 8",
            "phone_number": "0470-60245",
            "bank_details": {
                "bankgiro": "357-0504",
                "postgiro": "379929-3"
            },
            "activity": "Tillverkar ABO-luckan, samtliga typer samt transportanordningar av alla slag för sågverksindustrin",
            "annual_turnover": 450000,
            "key_personnel": [
                {
                    "name": "Ing A Boström",
                    "position": "Chef"
                }
            ],
            "establishment_year": 1953
        },
        "12": {
            "company_name": "BIA HÄRDPLAST AB",
            "pnr": "73100",
            "address": "Köping",
            "phone_number": "0221-107 91, 133 91",
            "bank_details": {
                "bankgiro": "811-2690",
                "postgiro": "576880-9"
            },
            "activity": "Utför beställningsarbeten för industrin i glasfiber-armerad plast. Specialitet: alla slag av skåp samt cisterner för olja, vatten o avlopp m m",
            "employees": 17,
            "annual_turnover": 3000000,
            "capital": 20000,
            "key_personnel": [
                {
                    "name": "Fru Maja Elisabet Nilsson",
                    "position": "ordf"
                },
                {
                    "name": "Einar Nilsson",
                    "position": "Verkst dir"
                }
            ],
            "establishment_year": 1960
        },
        "13": {
            "company_name": "JONSSONS TAKPANNEFABRIK, BRÖDERNA",
            "pnr": "93104",
            "address": "Skellefteå 4, Rosg 59. Box 1246.",
            "phone_number": "0910-132 33, 13216",
            "bank_details": {
                "bankgiro": "764-1012",
                "postgiro": "483783-7"
            },
            "activity": "Tillverkar takpannor av betong",
            "employees": 8,
            "key_personnel": [
                {
                    "name": "Töre Jonsson",
                    "position": "Ägare, chef"
                },
                {
                    "name": "Martin Jonsson",
                    "position": "chef"
                }
            ],
            "establishment_year": 1951
        },
        "14": {
            "company_name": "JONSSONS TORRDOCKA, BRÖDERNA",
            "pnr": "53100",
            "address": "Lidköping, Trelleberg",
            "phone_number": "0510-101 22, 103 25",
            "bank_details": {
                "bankgiro": "21-2329",
                "postgiro": "571670"
            },
            "activity": "Utför mindre fartygsbyggnader av stål",
            "employees": 17,
            "annual_turnover": 1000000,
            "key_personnel": [
                {
                    "name": "Harry Jonsson",
                    "position": "Chef"
                }
            ],
            "establishment_year": 1960
        },
        "15": {
            "company_name": "JONSSONS TRÄINDUSTRI AB, BRÖDERNA",
            "pnr": "34010",
            "address": "Lidhult, Box 82",
            "phone_number": "035-91048, 913 48",
            "bank_details": {
                "bankgiro": "55-2416",
                "postgiro": "323108"
            },
            "activity": "Tillverkar köksinredningar, hörnskåp i allmoge, barnsängar o barnhagar",
            "employees": 34,
            "annual_turnover": 1500000,
            "capital": 100000,
            "key_personnel": [
                {
                    "name": "David Jonsson",
                    "position": "Verkst dir"
                }
            ],
            "establishment_year": 1944
        }
    }
}