{
    "original": "SKURUP-VERKEN, AB\n\nPnr 274 00\n\nSkurup, Västerg. Box 64. Tel\n0411-41140. Bankgiro 663-3218.\nPostgiro 71165. Telex 3148\nVerksamhet: Tillverkar\nlantbruksmaskiner\n\nAntal anställda: 142\nÅrsomsättning: 14 000 000\nAktiekapital: 1000000\nVerkst dir: Torsten Kreij\nEtableringsår: 1892.\n\nTIN\n\nTIERPS REDSKAPSFABRIK\nAB\n\nPnr 81500\n\nTierp, Greveg 24. Tel 0293-100 22.\nBankgiro 23-6206. Postgiro 33161\nVerksamhet: Tillverkar\nlantbruksmaskiner o -redskap\nVarunamn: Cesar\nAktiekapital: 118 200\nVerkst dir. Folke E L Larsson\nEtableringsår 1895.\n\nBYGGKONSULT I OREBRO AB\n\nPnr 702 11\n\nÖrebro, Nyg 46. Tel 019-13 6255.\nBankgiro 614-7904. Postgiro\n22568 3-2\n\nVerksamhet: Projektledning,\nbyggledning o statiska konstruktioner\nAntal anställda: 25\nÅrsomsättning: 1 500000\nAktiekapital: 5 000\nVerkst dir Karl-Erik Berner\nEtableringsår. 1959.\n\nHANSEN AB, F H\n\nPnr 112 24\n\nStockholm, Plpersg 5. Tel\n08-51 3080, 51 36 38. Postgiro 51470-3\nTga Navalcos\n\nVerksamhet: Grossist- o\nagentur-rörelse\n\nAktiekapital: 10 000\nEtableringsår: 1921.\n\nHANSA, ATERFORSAKRINGS\nAB\n\nPnr 103 81\n\nStockholm 7, Box 7036. Arsenalsg\n8 C. Tel 08-14 00 60. Bankgiro\n700-0615. Postgiro 32-3. Tga Rehansa.\nTelex 1581 HANSA S\nVerksamhet: Aterförsäkring\nAktiekapital: 5000 000\nStyrelse: Dir O Karleby (ordf), dir\nG Arenander, dir L Dahlgren, dir\nS Finné, dir A Thorstensson\nVerkst dir: S Finné\nEtableringsår: Stella 1898, Svecia\n1949.\n\nHANSA ÖMSESIDIG\nSAK-FÖRSÄKRING\n\nPnr 10240\n\nStockholm 5, Fack. Tel 08-14 00 60.\nBankgiro 564-6112. Postgiro premier\n794-8, övrigt 32-3. Tga Trygghansa.\nTelex 1581 HANSA S\nStyrelse: Dir E Tunhammar (ordf),\nbruksdisp A Pihlgren (v ordf), dir\nL Dahlgren, adv T Flodin,\nlands-hövd E Huss, dir R Höglund, dir O\nKarleby, överstelöjtnant F\nLambert-Meuller, dir G Lindblom, ing N\nNes-sen, landstingsråd E Nilsson, dir O\nNyström, adv G Sjögren, bankdir A\nÅkerman, dir S Odner\nVerkst dir: O Karleby\nFörste v verkst dir: L Dahlgren\nV veikst dir:r: G Arenander, B\nOdén, O Wirström\nEtableringsår: Städemas 1828,\nHansa 1905, Fylgia 1881.\n\nHANSA-MOBLER\n\nPnr 543 02\n\nTibro 2, Box 328. Tel 0504-105 41.\nBankgiro 221-4047. Postgiro\n392606-0\n\nVerksamhet: Tillverkar\nkontorsmöbler\n\nAntal anställda: 12\nÅrsomsättning: 750 000\nÄgare o chef: Hans Carlsson\nEtableringsår: 1934.\n\nGAKO AB, KONSULTBYRÄN\n\nPnr 402 23\n\nGöteborg 5, Sankt Sigfridsg 85.\nBox 5130. Tel 031-40 00 60.\nBankgiro 337-6811. Postgiro 524271-4\nVerksamhet: Konsulterande\narkitekter o ingenjörer. Oljeförsäljning\n.Antal anställda: 107\nÅrsomsättning: 24 317 818\nAktiekapital: 525 000\nVetkst dir: Sven Gustafson\nArkitektkontor: Ark SAR Lars\nÅgren\n\nVVS-kontor: Civiling Bernt\nBäckström\n\nUtredningskontor: Fil kand Rune\nGustafsson\n\nParkeringskontor: Ing Einar\nMyhrman\n\nArbetsstudiekonton Ing Jan Roos\nEkonomiavdelning: Ekonomichef\nGeorg Petersson\nEtableringsår: 1957.\n\nLINDVALL, AB ERIC\n\nPnr 75106\n\nUppsala 1, Kungsg 60. Box 396.\nTel 018-13 9240. Bankgiro 80-2113.\nPostgiro 5368. Tga Lindvalls\nVerksamhet: Kafferosteri samt\nfabrikation av råvaror för bagerier\nAntal anställda: 40\nAktiekapital: 498 000\nVerkst dir: Hans Lindvall\nEtableringsår: 1893.\n\nVEMA, MASKIN AB\n\nPnr 10133\n\nStockholm 1, Box 911. Tel\n08-11 0911, 211409\nVerksamhet: Säljer maskiner o\nverktyg\n\nAktiekapital: 210 000\nVerkst dir: G A Wärnling\nEtableringsår: 1942.\n\nWEMAB, ELEKTRO &amp; MASKIN\nAB\n\nPnr 721 07\n\nVästerås 1, Box 314. Tel\n021-20160. Bankgiro 221-1837.\nPostgiro 103610-2. Tga Wemab\nVerksamhet: Agentur. Säljer rostr\nmaskiner o rosteriutrustningar för\nkaffe-, kakao- o kärnprodukter,\nkonservförslutningsmaskiner,\npaketeringsmaskiner, automatvågar o\ndoseringsmaskiner, maskiner för\nframställning av chokladartiklar\nsamt textilmaskiner\nAktiekapital: 5 000\nStyrelseordf: Ing Horst Wächter\nVerkst dir: Ing Horst Wächter\nEtableringsår: 1956\nOmbildat till aktiebolag 1968.\n\nWEMACO\n\nPnr 182 71\n\nStocksund, Fack. Tel 08-85 66 42,\n85 66 52. Bankgiro 167-8291.\nPostgiro 252853-7. Tga Electrosale\nVerksamhet: Säljer\nplastsvetsma-skiner, förpackningsfolier,\nplastfolier, lim för plastindustrin m m\nChefer: C F Waern, L M Waern\nEtableringsår: 1953.\n\nMÅRDSKOG &amp; LINDKVIST AB\n\nPnr 552 68\n\nJönköping, Kindgrensg 7. Tel\n036-1193 85. Bankgiro 544-6026.\nPostgiro 115977-1\n\nVerksamhet: Partiförsäljning av\nfärska, konserverade o djupfrysta\nlivsmedel samt förnödenheter o\ninventarier till gatukök,\nrestauranger o storkök\nVarunamn: Brewomatic, Sibylla\nAntal anstäUda: 22\nÅrsomsättning: 19000 000\nAktiekapital: 30000\nVerkst dir: Tage Mårdskog\nEkonomichef: Fredrik Lindkvist\nFörsäljningschef: Ove Magnusson\nFörsäljare: Egon Pettersson\nEtableringsår: 1961.\n\nMÅRTENSSON SNICKERI.\nFABRIK, BRUDERNA\n\nPnr 450 60\n\nFärgelanda, Assarbyn. Postl 1381.\nTel 0528-10088. Bankgiro 890-9186.\nPostgiro 498532-1\nVerksamhet: Tillverkar o säljer\nfönster o fönsterdörrar\nÄgare o chefen Paul Mårtensson,\nMårten Mårtensson\nEtableringsår. 1955.\n\nMÅRTENSSON BYGGNADS AB,\nERNST\n\nPnr 43138\n\nMölndal, Landshövdingeg 38 A.\nTel 031-20 66 46, 161982.\nBankgiro 410-0434. Postgiro 44846-4\nVerksamhet: Byggnadsörelse\nAntal anstäUda: 20\nÅrsomsättning: 1500 000\nAktiekapital: 50000\nVerkst dir: Byggmäst Ernst\nMårtensson\n\nEtableringsår: 1924.\n\nLAGERKOMPANIET AB\n\nPnr 104 25\n\nStockholm 30, Nordenflychtsv 62.\nBox 30009. Tel 08-5418 80.\nBankgiro 73-3837. Postgiro 451485.\nTelex 10637. Tga Lagercomp\nVerksamhet: Lagring, internationell\nspedition m m\nAntal anställda: 10\nAktiekapital: 50 000\nVerkst dir. P H Lager\nEtableringsår: 1950.\n\nSANDOZ AB\n\nPnr 183 20\n\nTäby 1, Fack. Tel 08-756 02 60.\nBankgiro 700-2900, 160-5922.\nPostgiro 450695-2. Tga Sandoprodukter,\nStockholm. Telex 10918\nVeiksamhet: Säljer Sandoz\nläkemedel\n\nAntal anställda: 50\nAktiekapital: 2000000\nVerkst dir: René HUgin\nEtableringsår: 1949.",
    "structured": {
        "1": {
            "company_name": "SKURUP-VERKEN, AB",
            "pnr": "274 00",
            "address": "Skurup, Västerg. Box 64",
            "phone_number": "0411-41140",
            "bank_details": {
                "bankgiro": "663-3218",
                "postgiro": "71165"
            },
            "activity": "Tillverkar lantbruksmaskiner",
            "employees": 142,
            "annual_turnover": 14000000,
            "capital": 1000000,
            "key_personnel": [
                {
                    "name": "Torsten Kreij",
                    "position": "Verkst dir"
                }
            ],
            "establishment_year": 1892
        },
        "2": {
            "company_name": "TIERPS REDSKAPSFABRIK AB",
            "pnr": "81500",
            "address": "Tierp, Greveg 24",
            "phone_number": "0293-100 22",
            "bank_details": {
                "bankgiro": "23-6206",
                "postgiro": "33161"
            },
            "activity": "Tillverkar lantbruksmaskiner o -redskap",
            "varunamn": "Cesar",
            "capital": 118200,
            "key_personnel": [
                {
                    "name": "Folke E L Larsson",
                    "position": "Verkst dir"
                }
            ],
            "establishment_year": 1895
        },
        "3": {
            "company_name": "BYGGKONSULT I OREBRO AB",
            "pnr": "702 11",
            "address": "Örebro, Nyg 46",
            "phone_number": "019-13 6255",
            "bank_details": {
                "bankgiro": "614-7904",
                "postgiro": "22568 3-2"
            },
            "activity": "Projektledning, byggledning o statiska konstruktioner",
            "employees": 25,
            "annual_turnover": 1500000,
            "capital": 5000,
            "key_personnel": [
                {
                    "name": "Karl-Erik Berner",
                    "position": "Verkst dir"
                }
            ],
            "establishment_year": 1959
        },
        "4": {
            "company_name": "HANSEN AB, F H",
            "pnr": "112 24",
            "address": "Stockholm, Plpersg 5",
            "phone_number": "08-51 3080, 51 36 38",
            "postgiro": "51470-3",
            "activity": "Grossist- o agentur-rörelse",
            "capital": 10000,
            "establishment_year": 1921
        },
        "5": {
            "company_name": "HANSA, ATERFORSAKRINGS AB",
            "pnr": "103 81",
            "address": "Stockholm 7, Box 7036. Arsenalsg 8 C",
            "phone_number": "08-14 00 60",
            "bank_details": {
                "bankgiro": "700-0615",
                "postgiro": "32-3"
            },
            "activity": "Aterförsäkring",
            "capital": 5000000,
            "key_personnel": [
                {
                    "name": "S Finné",
                    "position": "Verkst dir"
                }
            ],
            "establishment_year": 1949
        },
        "6": {
            "company_name": "HANSA ÖMSESIDIG SAK-FÖRSÄKRING",
            "pnr": "10240",
            "address": "Stockholm 5, Fack",
            "phone_number": "08-14 00 60",
            "bank_details": {
                "bankgiro": "564-6112",
                "postgiro": "premier 794-8, övrigt 32-3"
            },
            "activity": "Säljer plastsvetsma-skiner, förpackningsfolier, plastfolier, lim för plastindustrin m m",
            "establishment_year": 1905
        },
        "7": {
            "company_name": "HANSA-MOBLER",
            "pnr": "543 02",
            "address": "Tibro 2, Box 328",
            "phone_number": "0504-105 41",
            "bank_details": {
                "bankgiro": "221-4047",
                "postgiro": "392606-0"
            },
            "activity": "Tillverkar kontorsmöbler",
            "employees": 12,
            "annual_turnover": 750000,
            "key_personnel": [
                {
                    "name": "Hans Carlsson",
                    "position": "Ägare o chef"
                }
            ],
            "establishment_year": 1934
        },
        "8": {
            "company_name": "GAKO AB, KONSULTBYRÄN",
            "pnr": "402 23",
            "address": "Göteborg 5, Sankt Sigfridsg 85. Box 5130",
            "phone_number": "031-40 00 60",
            "bank_details": {
                "bankgiro": "337-6811",
                "postgiro": "524271-4"
            },
            "activity": "Konsulterande arkitekter o ingenjörer. Oljeförsäljning",
            "employees": 107,
            "annual_turnover": 24317818,
            "capital": 525000,
            "key_personnel": [
                {
                    "name": "Sven Gustafson",
                    "position": "Vetkst dir"
                }
            ],
            "establishment_year": 1957
        },
        "9": {
            "company_name": "LINDVALL, AB ERIC",
            "pnr": "75106",
            "address": "Uppsala 1, Kungsg 60. Box 396",
            "phone_number": "018-13 9240",
            "bank_details": {
                "bankgiro": "80-2113",
                "postgiro": "5368"
            },
            "activity": "Kafferosteri samt fabrikation av råvaror för bagerier",
            "employees": 40,
            "capital": 498000,
            "key_personnel": [
                {
                    "name": "Hans Lindvall",
                    "position": "Verkst dir"
                }
            ],
            "establishment_year": 1893
        },
        "10": {
            "company_name": "VEMA, MASKIN AB",
            "pnr": "10133",
            "address": "Stockholm 1, Box 911",
            "phone_number": "08-11 0911, 211409",
            "activity": "Säljer maskiner o verktyg",
            "capital": 210000,
            "key_personnel": [
                {
                    "name": "G A Wärnling",
                    "position": "Verkst dir"
                }
            ],
            "establishment_year": 1942
        },
        "11": {
            "company_name": "WEMAB, ELEKTRO & MASKIN AB",
            "pnr": "721 07",
            "address": "Västerås 1, Box 314",
            "phone_number": "021-20160",
            "bank_details": {
                "bankgiro": "221-1837",
                "postgiro": "103610-2"
            },
            "activity": "Agentur. Säljer rostr maskiner o rosteriutrustningar för kaffe-, kakao- o kärnprodukter, konservförslutningsmaskiner, paketeringsmaskiner, automatvågar o doseringsmaskiner, maskiner för framställning av chokladartiklar samt textilmaskiner",
            "capital": 5000,
            "key_personnel": [
                {
                    "name": "Ing Horst Wächter",
                    "position": "Styrelseordf, Verkst dir"
                }
            ],
            "establishment_year": 1956
        },
        "12": {
            "company_name": "WEMACO",
            "pnr": "182 71",
            "address": "Stocksund, Fack",
            "phone_number": "08-85 66 42, 85 66 52",
            "bank_details": {
                "bankgiro": "167-8291",
                "postgiro": "252853-7"
            },
            "activity": "Säljer plastsvetsma-skiner, förpackningsfolier, plastfolier, lim för plastindustrin m m",
            "establishment_year": 1953
        },
        "13": {
            "company_name": "MÅRDSKOG & LINDKVIST AB",
            "pnr": "552 68",
            "address": "Jönköping, Kindgrensg 7",
            "phone_number": "036-1193 85",
            "bank_details": {
                "bankgiro": "544-6026",
                "postgiro": "115977-1"
            },
            "activity": "Partiförsäljning av färska, konserverade o djupfrysta livsmedel samt förnödenheter o inventarier till gatukök, restauranger o storkök",
            "varunamn": "Brewomatic, Sibylla",
            "employees": 22,
            "annual_turnover": 19000,
            "capital": 30000,
            "key_personnel": [
                {
                    "name": "Tage Mårdskog",
                    "position": "Verkst dir"
                },
                {
                    "name": "Fredrik Lindkvist",
                    "position": "Ekonomichef"
                },
                {
                    "name": "Ove Magnusson",
                    "position": "Försäljningschef"
                },
                {
                    "name": "Egon Pettersson",
                    "position": "Försäljare"
                }
            ],
            "establishment_year": 1961
        },
        "14": {
            "company_name": "MÅRTENSSON SNICKERI. FABRIK, BRUDERNA",
            "pnr": "450 60",
            "address": "Färgelanda, Assarbyn. Postl 1381",
            "phone_number": "0528-10088",
            "bank_details": {
                "bankgiro": "890-9186",
                "postgiro": "498532-1"
            },
            "activity": "Tillverkar o säljer fönster o fönsterdörrar",
            "key_personnel": [
                {
                    "name": "Paul Mårtensson",
                    "position": "Ägare o chefen"
                },
                {
                    "name": "Mårten Mårtensson",
                    "position": ""
                }
            ],
            "establishment_year": 1955
        },
        "15": {
            "company_name": "MÅRTENSSON BYGGNADS AB, ERNST",
            "pnr": "43138",
            "address": "Mölndal, Landshövdingeg 38 A",
            "phone_number": "031-20 66 46, 161982",
            "bank_details": {
                "bankgiro": "410-0434",
                "postgiro": "44846-4"
            },
            "activity": "Byggnadsörelse",
            "employees": 20,
            "annual_turnover": 1500000,
            "capital": 50000,
            "key_personnel": [
                {
                    "name": "Byggmäst Ernst Mårtensson",
                    "position": "Verkst dir"
                }
            ],
            "establishment_year": 1924
        },
        "16": {
            "company_name": "LAGERKOMPANIET AB",
            "pnr": "104 25",
            "address": "Stockholm 30, Nordenflychtsv 62. Box 30009",
            "phone_number": "08-5418 80",
            "bank_details": {
                "bankgiro": "73-3837",
                "postgiro": "451485"
            },
            "activity": "Lagring, internationell spedition m m",
            "employees": 10,
            "capital": 50000,
            "key_personnel": [
                {
                    "name": "P H Lager",
                    "position": "Verkst dir"
                }
            ],
            "establishment_year": 1950
        },
        "17": {
            "company_name": "SANDOZ AB",
            "pnr": "183 20",
            "address": "Täby 1, Fack",
            "phone_number": "08-756 02 60",
            "bank_details": {
                "bankgiro": "700-2900",
                "postgiro": "450695-2"
            },
            "activity": "Säljer Sandoz läkemedel",
            "employees": 50,
            "capital": 2000000,
            "key_personnel": [
                {
                    "name": "René HUgin",
                    "position": "Verkst dir"
                }
            ],
            "establishment_year": 1949
        }
    }
}