{
    "original": "ARSANI, AB\n\nPnr 212 28\n\nMalmö, Scheeleg 13. Tel\n040-93 63 85. Bankgiro 874-7024.\nPostgiro 247153-9\n\nVerksamhet: Formsprutade\nmassartiklar i alla termoplaster.\nFormgivning, egen verktygstillverkning.\nSpecialitet: industridetaljer,\nhusgeråd o förpackningar\nAntal anställda: 30\nAktiekapital: 10 000\nVerkst dir: Poul Jensen\nEtableringsår: 1951.\n\nAR-SERVICE I\nSUNDSVALL AB\n\nPnr 852 33\n\nSundsvall, Bankg 10. Tel\n060-15 0710. Bankgiro 795-2443.\nPostgiro 693800-5\n\nVerksamhet: Konsulter inom\nadministrativ rationalisering såsom\norganisationsplanering,\nsystemrationalisering, programering,\nresursdimensionering, lokalplanering m m\n\nAntal anställda: 18\nÅrsomsättning: 1200000\nAktiekapital: 20 000\nStyrelse: Bankdir Börje Carlson\n(ordf), dir Jan Berglund, dir Olof\nLindbäck, dir Arne Wiklund\nVerkst dir: Arne Wiklund\nEtableringsår: 1967.\n\nARSTROM AB,\nATELIER FOLKE\n\nPnr 18141\n\nLidingö 1, Skogsv 5. Tel\n08-765 22 05, 765 23 05. Bankgiro\n74-3227. Postgiro 153553\nVerksamhet: Industriell\nformgivning. Specialitet: metall- o\nplastdesign\n\nAktiekapital: 5 000\n\nVerkst dir: Konstnär Folke Arström\n\nEtableringsår: 1933.\n\nVES\n\nTel 011-10 08 00. Bankgiro 60-9862.\nPostgiro 11095. Tga Westerholmsab\nVerksamhet: Grossist- o\nagenturrörelse i textil\nVerkst dir: Olof Kreuger\nEtableringsår: 1894.\n\nWESTERLINS MASKINFABRIK\nAB\n\nPnr 20046\n\nMalmö 24, Söderkullag 3. Box\n24002. Tel 040-813 63. Bankgiro\n874-4492. Postgiro 536295-9\nVerksamhet: Tillverkar maskiner\nför färg- o kemisk-teknisk industri\nAntal anställda: 12\nAktiekapital: 25 000\nVeikst dir: Björn Westerlin\nEtableringsår: 1928.\n\nPREDICTOR AB\n\nPnr 441 01\n\nAlingsås 1, Box 20. Tel\n0322-17 3 00, 183 20. Bankgiro 250-6251.\nPostgiro 23232-2\nFabrik: Tel 0322-185 20\nVerksamhet: Tillverkning av\nfasad-material, golvmassor, lim för PVC.\nRengöringsmedel. Godkända för\nutsläpp i kommunala avlopp\nAktiekapital: 15 000\nChefer: Disp Ingvar Aurell,\nciviling Thore Aurell\nEtableringsår: 1968.\n\nBEYRONDS AB\n\nPnr 214 50\n\nMalmö, N Grängesbergsg 26. Tel\n040-804 70. Bankgiro 87-4303.\nPostgiro 37592. Tga Bokbeyrond\nVerksamhet: Partibokbinderi o\ntryckeri\n\nAntal anställda: 150\nAktiekapital: 450 000\nVerkst dir: Robert Beyrond\nEtableringsår: 1916.\n\nmaskinteknik, ab\n\nPnr 102 44\n\nStockholm 5, Box 5193. Nybrog 44.\nTel 08-24 42 60. Bankgiro\n700-1019. Postgiro 350548-4. Tga\nMaskinteknik. Telex 10149\nVerksamhet: Säljer saxskär,\nlyftbord, lyftmagneter,\nmagnetappara-tur, lyftblock, vibrationsdämpare,\nindustriborstar, ’Alcotest’\nVarunamn: Alcotest, EET,\nKULLEN + MEZ, Herbert Morris,\nSchmachtenberg, Trepel\nAktiekapital: 50 000\nVerkst dir: Hugo Holsü\nEtableringsår: 1948.\n\nJUTEX AB\n\nPnr 330 33\n\nHillers torp. Tel 0370-220 58\n\nVerksamhet: Tillverkar\nhusgerådsartiklar o skyltställ i tråd,\ngalvani-serade o plastbelagda\nVerkst dir: Roland Karlsson\nEtableringsår: 1941.\n\nAMB, INDUSTRI-AB\n\nPnr 360 64\n\nBroakulla. Tel 0471-40177.\nBankgiro 146-6077. Postgiro 328172-2\nVerksamhet: Tillverkar\nplastdetaljer till elektr belysningsindustrin,\nkopplingsdosor för elektr\ninstallationer samt 1 egopressning av\nhärd-o termoplaster\nAntal anställda: 40\nAktiekapital: 100 000\nÄgare o chefer: Ragnar\nMagnusson, Osvald Astevall\nEtableringsår: 1946.\n\nLJUSDALS PATENTTÄLN.\nFABRIK, FURENINGEN\n\nPnr 827 00\n\nLjusdal. Tel 0651-112 19. Bankgiro\n78-8046. Postgiro 32771-8\nVerksamhet: Tillverkar\npatentsänk-tälnar o flöttälnar\nFörest: Bengt Engström\nEtableringsår: 1916.\n\nLJUSFALLSHAMMARS MUBEL.\nINDUSTRI AB\n\nPnr 61010\n\nLjusfallshammar, Box 31. Tel\n0122-402 10. Bankgiro 610-0218.\nPostgiro 115941-7. Tga Mia\nVerksamhet: Tillverkar bäddsoffor\nAntal anställda: 58\nÅrsomsättning: 4 500 000\nAktiekapital: 190 000\nVerkst dir: Harry Nyström\nEtableringsår: 1959.\n\nLJUSFALLSHAMMARS\nVERKSTADS AB\n\nPnr 61010\n\nLjusfallshammar. Tel 0122-402 05,\n400 21. Bankgiro 13-2766.\nPostgiro 33630\n\nVerksamhet: Tillverkningsföretag\nåt Stenbergs Maskinbyrå AB\nAntal anställda: 50\nAktiekapital: 320000\nVerkst dir: Carl Erik Orrblad\nEtableringsår: 1940.\n\nADEC-PLAST, AB\n\nPnr 370 34\n\nHolmsjö, Nävragöl. Tel 0455-92121.\nBankgiro 571-6873. Postgiro\n213490-3. Tga Adec\nVerksamhet: Tillverkar\nglasfiberbåtar samt vacuumformajde\ntermoplastprodukter\nAntal anställda: 20\nÅrsomsättning: 2 500 000\nStyrelse: Adv Sven Bengtsson\n(ordf), dir Sixten Persson, ing Bert\nGustafsson\n\nVerkst dir: Bert Gustafsson\nEtableringsår: 1969.\n\nELECTRA, GRAMMOFON AB\n\nPnr 171 23\n\nSolna 1, Ankdammsg 5 G. Box\n1178. Tel 08-8204 80. Telex 1561.\nTga Electragrammo\nVerksamhet: Grossiströrelse i\ngrammonfonskivor\nAktiekapital: 1000 000\nVerkst dir: Sixten Eriksson\nEtableringsår: 1956.\n\nELECTRIC,\nINGENJÖRS-FIRMAN\n\nPnr 116 35\n\nStockholm SO, Klippg 11. Tel\n08-40 64 48 Postgiro 547\nVerksamhet: Säljer elektr motorer\no kolvpumpar\nChef: Knut Ostfors\nEtableringsår: 1925.\n\nELECTRICA AB, INGENIORS.\nFIRMAN ASPLUNDS\nFÖRSÄLJNINGSBOLAG\n\nPnr 11647\n\nStockholm, Bellmansg 22 B. Tel\n08-23 26 10. Bankgiro 72-0010.\nPostgiro 650005. Telex 10585.\nTga Abelectrica\n\nVerksamhet: Aterförsäljning,\nmontage o service av elektr\nlågspän-ningsmateriel för industri, elverk\no elinstallatörer, härrörande från\nIngeniörsfirman Asplunds\ngeneralagenturer\n\nAktiekapital: 210 000\nVerkst dir: Rolf E Asplund\nEtableringsår: 1960.",
    "structured": {
        "1": {
            "company_name": "ARSANI, AB",
            "pnr": "212 28",
            "address": "Malmö, Scheeleg 13",
            "phone_number": "040-93 63 85",
            "bank_details": {
                "bankgiro": "874-7024",
                "postgiro": "247153-9"
            },
            "activity": "Formsprutade massartiklar i alla termoplaster. Formgivning, egen verktygstillverkning. Specialitet: industridetaljer, husgeråd o förpackningar",
            "employees": 30,
            "capital": 10000,
            "key_personnel": [
                {
                    "name": "Poul Jensen",
                    "position": "Verkst dir"
                }
            ],
            "establishment_year": 1951
        },
        "2": {
            "company_name": "AR-SERVICE I SUNDSVALL AB",
            "pnr": "852 33",
            "address": "Sundsvall, Bankg 10",
            "phone_number": "060-15 0710",
            "bank_details": {
                "bankgiro": "795-2443",
                "postgiro": "693800-5"
            },
            "activity": "Konsulter inom administrativ rationalisering såsom organisationsplanering, systemrationalisering, programering, resursdimensionering, lokalplanering m m",
            "employees": 18,
            "annual_turnover": 1200000,
            "capital": 20000,
            "key_personnel": [
                {
                    "name": "Arne Wiklund",
                    "position": "Verkst dir"
                }
            ],
            "establishment_year": 1967
        },
        "3": {
            "company_name": "ARSTROM AB, ATELIER FOLKE",
            "pnr": "18141",
            "address": "Lidingö 1, Skogsv 5",
            "phone_number": "08-765 22 05, 765 23 05",
            "bank_details": {
                "bankgiro": "74-3227",
                "postgiro": "153553"
            },
            "activity": "Industriell formgivning. Specialitet: metall- o plastdesign",
            "capital": 5000,
            "key_personnel": [
                {
                    "name": "Konstnär Folke Arström",
                    "position": "Verkst dir"
                }
            ],
            "establishment_year": 1933
        },
        "4": {
            "company_name": "VES",
            "phone_number": "011-10 08 00",
            "bank_details": {
                "bankgiro": "60-9862",
                "postgiro": "11095"
            },
            "activity": "Grossist- o agenturrörelse i textil",
            "key_personnel": [
                {
                    "name": "Olof Kreuger",
                    "position": "Verkst dir"
                }
            ],
            "establishment_year": 1894
        },
        "5": {
            "company_name": "WESTERLINS MASKINFABRIK AB",
            "pnr": "20046",
            "address": "Malmö 24, Söderkullag 3, Box 24002",
            "phone_number": "040-813 63",
            "bank_details": {
                "bankgiro": "874-4492",
                "postgiro": "536295-9"
            },
            "activity": "Tillverkar maskiner för färg- o kemisk-teknisk industri",
            "employees": 12,
            "capital": 25000,
            "key_personnel": [
                {
                    "name": "Björn Westerlin",
                    "position": "Veikst dir"
                }
            ],
            "establishment_year": 1928
        },
        "6": {
            "company_name": "PREDICTOR AB",
            "pnr": "441 01",
            "address": "Alingsås 1, Box 20",
            "phone_number": "0322-17 3 00, 183 20",
            "bank_details": {
                "bankgiro": "250-6251",
                "postgiro": "23232-2"
            },
            "activity": "Tillverkning av fasad-material, golvmassor, lim för PVC. Rengöringsmedel. Godkända för utsläpp i kommunala avlopp",
            "capital": 15000,
            "key_personnel": [
                {
                    "name": "Disp Ingvar Aurell",
                    "position": "Chefer"
                },
                {
                    "name": "civiling Thore Aurell",
                    "position": ""
                }
            ],
            "establishment_year": 1968
        },
        "7": {
            "company_name": "BEYRONDS AB",
            "pnr": "214 50",
            "address": "Malmö, N Grängesbergsg 26",
            "phone_number": "040-804 70",
            "bank_details": {
                "bankgiro": "87-4303",
                "postgiro": "37592"
            },
            "activity": "Partibokbinderi o tryckeri",
            "employees": 150,
            "capital": 450000,
            "key_personnel": [
                {
                    "name": "Robert Beyrond",
                    "position": "Verkst dir"
                }
            ],
            "establishment_year": 1916
        },
        "8": {
            "company_name": "maskinteknik, ab",
            "pnr": "102 44",
            "address": "Stockholm 5, Box 5193, Nybrog 44",
            "phone_number": "08-24 42 60",
            "bank_details": {
                "bankgiro": "700-1019",
                "postgiro": "350548-4"
            },
            "activity": "Säljer saxskär, lyftbord, lyftmagneter, magnetappara-tur, lyftblock, vibrationsdämpare, industriborstar, ’Alcotest’",
            "capital": 50000,
            "key_personnel": [
                {
                    "name": "Hugo Holsü",
                    "position": "Verkst dir"
                }
            ],
            "establishment_year": 1948
        },
        "9": {
            "company_name": "JUTEX AB",
            "pnr": "330 33",
            "address": "Hillers torp",
            "phone_number": "0370-220 58",
            "activity": "Tillverkar husgerådsartiklar o skyltställ i tråd, galvani-serade o plastbelagda",
            "key_personnel": [
                {
                    "name": "Roland Karlsson",
                    "position": "Verkst dir"
                }
            ],
            "establishment_year": 1941
        },
        "10": {
            "company_name": "AMB, INDUSTRI-AB",
            "pnr": "360 64",
            "address": "Broakulla",
            "phone_number": "0471-40177",
            "bank_details": {
                "bankgiro": "146-6077",
                "postgiro": "328172-2"
            },
            "activity": "Tillverkar plastdetaljer till elektr belysningsindustrin, kopplingsdosor för elektr installationer samt 1 egopressning av härd-o termoplaster",
            "employees": 40,
            "capital": 100000,
            "key_personnel": [
                {
                    "name": "Ragnar Magnusson",
                    "position": "Ägare o chefer"
                },
                {
                    "name": "Osvald Astevall",
                    "position": ""
                }
            ],
            "establishment_year": 1946
        },
        "11": {
            "company_name": "LJUSDALS PATENTTÄLN. FABRIK, FURENINGEN",
            "pnr": "827 00",
            "address": "Ljusdal",
            "phone_number": "0651-112 19",
            "bank_details": {
                "bankgiro": "78-8046",
                "postgiro": "32771-8"
            },
            "activity": "Tillverkar patentsänk-tälnar o flöttälnar",
            "key_personnel": [
                {
                    "name": "Bengt Engström",
                    "position": "Förest"
                }
            ],
            "establishment_year": 1916
        },
        "12": {
            "company_name": "LJUSFALLSHAMMARS MUBEL. INDUSTRI AB",
            "pnr": "61010",
            "address": "Ljusfallshammar, Box 31",
            "phone_number": "0122-402 10",
            "bank_details": {
                "bankgiro": "610-0218",
                "postgiro": "115941-7"
            },
            "activity": "Tillverkar bäddsoffor",
            "employees": 58,
            "annual_turnover": 4500000,
            "capital": 190000,
            "key_personnel": [
                {
                    "name": "Harry Nyström",
                    "position": "Verkst dir"
                }
            ],
            "establishment_year": 1959
        },
        "13": {
            "company_name": "LJUSFALLSHAMMARS VERKSTADS AB",
            "pnr": "61010",
            "address": "Ljusfallshammar",
            "phone_number": "0122-402 05, 400 21",
            "bank_details": {
                "bankgiro": "13-2766",
                "postgiro": "33630"
            },
            "activity": "Tillverkningsföretag åt Stenbergs Maskinbyrå AB",
            "employees": 50,
            "capital": 320000,
            "key_personnel": [
                {
                    "name": "Carl Erik Orrblad",
                    "position": "Verkst dir"
                }
            ],
            "establishment_year": 1940
        },
        "14": {
            "company_name": "ADEC-PLAST, AB",
            "pnr": "370 34",
            "address": "Holmsjö, Nävragöl",
            "phone_number": "0455-92121",
            "bank_details": {
                "bankgiro": "571-6873",
                "postgiro": "213490-3"
            },
            "activity": "Tillverkar glasfiberbåtar samt vacuumformajde termoplastprodukter",
            "employees": 20,
            "annual_turnover": 2500000,
            "key_personnel": [
                {
                    "name": "Adv Sven Bengtsson",
                    "position": "Styrelse"
                },
                {
                    "name": "dir Sixten Persson",
                    "position": ""
                },
                {
                    "name": "ing Bert Gustafsson",
                    "position": ""
                },
                {
                    "name": "Bert Gustafsson",
                    "position": "Verkst dir"
                }
            ],
            "establishment_year": 1969
        },
        "15": {
            "company_name": "ELECTRA, GRAMMOFON AB",
            "pnr": "171 23",
            "address": "Solna 1, Ankdammsg 5 G, Box 1178",
            "phone_number": "08-8204 80",
            "bank_details": {
                "bankgiro": "60-9862",
                "postgiro": "11095"
            },
            "activity": "Grossiströrelse i grammonfonskivor",
            "capital": 1000000,
            "key_personnel": [
                {
                    "name": "Sixten Eriksson",
                    "position": "Verkst dir"
                }
            ],
            "establishment_year": 1956
        },
        "16": {
            "company_name": "ELECTRIC, INGENJÖRS-FIRMAN",
            "pnr": "116 35",
            "address": "Stockholm SO, Klippg 11",
            "phone_number": "08-40 64 48",
            "bank_details": {
                "postgiro": "547"
            },
            "activity": "Säljer elektr motorer o kolvpumpar",
            "key_personnel": [
                {
                    "name": "Knut Ostfors",
                    "position": "Chef"
                }
            ],
            "establishment_year": 1925
        },
        "17": {
            "company_name": "ELECTRICA AB, INGENIORS. FIRMAN ASPLUNDS FÖRSÄLJNINGSBOLAG",
            "pnr": "11647",
            "address": "Stockholm, Bellmansg 22 B",
            "phone_number": "08-23 26 10",
            "bank_details": {
                "bankgiro": "72-0010",
                "postgiro": "650005"
            },
            "activity": "Aterförsäljning, montage o service av elektr lågspän-ningsmateriel för industri, elverk o elinstallatörer, härrörande från Ingeniörsfirman Asplunds generalagenturer",
            "capital": 210000,
            "key_personnel": [
                {
                    "name": "Rolf E Asplund",
                    "position": "Verkst dir"
                }
            ],
            "establishment_year": 1960
        }
    }
}