{
    "original": "säljarbrev, ab\n\nPnr 17104\n\nSolna 4, Kapellg 9 A. Box 414.\nTel 08-27 29 70. Bankgiro\n575-1722. Postgiro 580400-0\nVerksamhet: Kontorsoffset-tryckeri\nAntal anställda: 55\nÅrsomsättning: 4 000 000\nAktiekapital: 250 000\nVerkst din Bengt Berg\nEtableringsån 1961.\n\nsäljbolaget scandi.\nnavian sales forces ab\n\nPnr 13101\n\nNacka 1, Gamla Värmdö v 6. Box\n15. Tel 08-716 29 60. Bankgiro\n196-1697. Postgiro 121450-1\nVerksamhet: Fristående\nsäljorga-nisation för svenska o utländska\ndagligvaror. Dotterbolag i Danmark\no Norge\n\nAntal anställda: 135\nAktiekapital: 100000\nVerkst din Lennart Hattenbach\nEtableringsån 1963.\n\nsäljkonsult borje lind.\nberg, ab\n\nPnr 114 55\n\nStockholm, Grev Magnig 5. Tel\n08-6704 00. Bankgiro 572-9363.\nPostgiro 507391-1. Tga Salesconsult\nVerksamhet: Konsultation inom\nföretagsledning o marknadsföring\nAntal anställda: 17\nAktiekapital: 50 000\nVerkst dir: Börje Lindberg\nEtableringsår: 1954.\n\nGNOSJO PLÄTFORADLING, AB\n\nPnr 33030\n\nGnosjö. Tel 0370-912 40. Postgiro\n385966\n\nVerksamhet: Tillverkar\nverktygslådor för borr- o gängverktyg,\nbult-fack, förvaringsfack för skruv\nChef: H Boberg.\n\nGNOSJO\nTRÄ-MANUFAKTUR, AB\n\nPnr 33030\n\nGnosjö, Långg. Box 71. Tel\n0370-910 55, 910 30. Bankgiro 54-2494.\nPostgiro 493607. Tga Coathangers\nVerksamhet: Tillverkar alla slag av\nklädhängare\nAntal anställda: 14\nÅrsomsättning: 800 000\nAktiekapital: 30 000\nVerkst dir: Lennart Sigblad\nEtableringsår: 1925.\n\nMILETRYCK AB\n\nPnr 161 35\n\nBromma, Grindstuv 38. Tel\n08-26 08 00, 26 02 00. Bankgiro\n72-6156. Postgiro 55525\nVerksamhet Boktryck o offset.\nSpecialitet: etikettryck\nAntal anställda: 15\nÅrsomsättning: 800 000\nAktiekapital: 75 000\nVerkst dir: Emil Söderström\nEtableringsår: 1940.\n\nCOLLÉNS VERKSTADS AB\n\nPnr 11457\n\nStockholm, Riddarg 40. Tel\n08-63 52 55. Bankgiro 57-2948.\nPostgiro 151260\n\nVerksamhet: Utför grovplåts- o\n\nmek arbeten. Tillverkar\nhissanordningar\n\nAntal anställda: 18\nÅrsomsättning: 850 000\nAktiekapital: 30 000\nVerkst dir: Torsten Hammarlund\nVerkmäst: Lars Lindström\nEtableringsår: 1914.\n\nSKÅNSKA BANKEN\n\nPnr 20110\n\nMalmö 1, Söderg 10. Fack. Tel\n040-744 40. Tga Skånskabank.\nTelex 327 20 SYDBANK S\nAktiekapital: 34 000 000\nVerkst dir: Bankdir Axel Roos\nEtableringsår: 1896.\n\nSKÅNSKA BOMULLSKRUT.\nFABRIKS AB\n\nPnr 240 23\n\nDösjebro, Box 18. Tel 046-713 00.\nBankgiro 660-0969. Postgiro\n82330-2. Tga Normal\nVerksamhet: Tillverkar teknisk o\nfarmaceutisk eter o collodium\nÅrsomsättning: 200 000\nAktiekapital: 10 000\nVerkst dir: Yngve Wiberg\nEtableringsår: 1929.\n\nSKÅNSKA BRANDS\nINTECKNINGS AB\n\nPnr 22105\n\nLund 1, Tegnérsplatsen 4. Box\n1255. Tel 046-1170 50. Postgiro\n11010-6\n\nVerksamhet: Lånerörelse\nAktiekapital: 1100 000\nVerkst dir: Sven-Thorsten Frostell\nEtableringsår: 1934.\n\nARV\n\nsvet. Telex 2555\nVerksamhet:\nTextilförädlings-maskiner\n\nAntal anställda: 3\nAktiekapital: 25 000\nVerkst dir: Heinz-Dieter Scheube\nEtableringsår: 1961.\n\nTRANSMARK, REDERI.AB\n\nPnr 403 10\n\nGöteborg 2, Fack. Packhusplatsen\n3. Tel 031-17 67 00. Bankgiro\n500-5715. Postgiro 12107. Tga Nike.\nTelex 2300\n\nAktiekapital: 4 000000\nVerkst dir: Rolf Carlsson\nEtableringsår: 1928.\n\nINTERPARES, AB\n\nPnr 701 32\n\nÖrebro 1, Box 961. Olaig 9. Tel\n019-1248 80. Bankgiro 614-3564.\nPostgiro 279329-7. Tga Interpares.\nTelex 73229 IPIPIP S\nVerksamhet: Centralorgan för\nbyggmaterialdistributörer\nAntal anställda: 40\nÅrsomsättning: 135 000 000\nAktiekapital: 600 000\nVerkst dir: Sven Dingertz\nEtableringsår: 1944.\n\nBRATTBY SÅGVERKS AB\n\nPnr 910 10\n\nVännäsby. Tel 0935-20365.\nBankgiro 765-7083. Postgiro 60461-1\nVerksamhet: Sågade o hyvlade\nträvaror\n\nAntal anställda: 43\nÅrsomsättning: 10 000000\nAktiekapital: 600 000\nVerkst dir: Gustav Lundström\nEtableringsår: 1931.\n\nAM-MASKINER AB\n\nPnr 200 13\n\nMalmö 27, Box 27069. Bjurög 35-37.\nTel 040-18 0 1 70. Bankgiro\n260-0070. Postgiro 81786-6.\n\nTga Andermatts. Telex 32659\nVerksamhet: Import o\npartiförsäljning av maskiner o redskap för\nlantbruk o skogsbruk\nAntal anställda: 33\nÅrsomsättning: 9 800 000\nAktiekapital: 11545 000\nStyrelse: Bankdir Didrik Hamilton\n(ordf), dir Lennart Smith, dir Bengt\nKihlgren, grevinnan Monica Hamilton\nVerkst dir: Bengt Kihlgren\nDotterbolag: Anderson &amp; Mattson\nAB, Malmö. MAM-Makiner AB,\nMalmö. AB Melichar-Maskiner, Malmö.\nMelichar-Verkstäder AB, Malmö.\n\nAMP SCANDINAVIA AB\n\nPnr 175 00\n\nJakobsberg, Pack. Datav 5. Tel\n0758-104 00. Bankgiro 580-8001.\nPostgiro 407140-3. Tga Ampscan.\nTelex 10985\n\nVerksamhet: Tillverkar o\nmarknadsför elektr anslutningsdetaljer,\nprogrammeringsutrustningar, elektronikkomponenter m m. Ett 50-tal\nfabriker i USA, Europa, Mexico,\nAustralien o Japan\n\nAntal anställda: 50 (koncernen\n12 000)\n\nÅrsomsättning: 20 000 000\nAktiekapital: 250 000\nStyrelse: H U von der Esch (ordf),\nS Hellner, W C Lange\nVerkst dir: Bengt Wimrén\nEtableringsår: 1967\nSysterbolag i England, Frankrike,\nHolland, Italien Spanien, Tyskland.\n\nAMS RUR AB\n\nPnr 573 00\n\nTranås, Missionsg 7. Tel\n0140-141 80. Bankgiro 365-5040.\nPostgiro 11763-0. Tga Amsrör\nFilial: Boxholm. Tel 0142-504 62\n.Aktiekapital: 100 000\nVerkst dir: Ing Stig Carlsson\nEtableringsår: 1952.",
    "structured": {
        "1": {
            "company_name": "SÄLJARBREV, AB",
            "pnr": "17104",
            "address": "Solna 4, Kapellg 9 A. Box 414.",
            "phone_number": "08-27 29 70",
            "bank_details": {
                "bankgiro": "575-1722",
                "postgiro": "580400-0"
            },
            "activity": "Kontorsoffset-tryckeri",
            "employees": 55,
            "annual_turnover": 4000000,
            "capital": 250000,
            "key_personnel": [
                {
                    "name": "Bengt Berg",
                    "position": "Verkst din"
                }
            ],
            "establishment_year": 1961
        },
        "2": {
            "company_name": "SÄLJBOLAGET SCANDI. NAVIAN SALES FORCES AB",
            "pnr": "13101",
            "address": "Nacka 1, Gamla Värmdö v 6. Box 15.",
            "phone_number": "08-716 29 60",
            "bank_details": {
                "bankgiro": "196-1697",
                "postgiro": "121450-1"
            },
            "activity": "Fristående säljorga-nisation för svenska o utländska dagligvaror. Dotterbolag i Danmark o Norge",
            "employees": 135,
            "capital": 100000,
            "key_personnel": [
                {
                    "name": "Lennart Hattenbach",
                    "position": "Verkst din"
                }
            ],
            "establishment_year": 1963
        },
        "3": {
            "company_name": "SÄLJKONSULT BORJE LIND. BERG, AB",
            "pnr": "11455",
            "address": "Stockholm, Grev Magnig 5.",
            "phone_number": "08-6704 00",
            "bank_details": {
                "bankgiro": "572-9363",
                "postgiro": "507391-1"
            },
            "activity": "Konsultation inom företagsledning o marknadsföring",
            "employees": 17,
            "capital": 50000,
            "key_personnel": [
                {
                    "name": "Börje Lindberg",
                    "position": "Verkst dir"
                }
            ],
            "establishment_year": 1954
        },
        "4": {
            "company_name": "GNOSJO PLÄTFORADLING, AB",
            "pnr": "33030",
            "address": "Gnosjö",
            "phone_number": "0370-912 40",
            "postgiro": "385966",
            "activity": "Tillverkar verktygslådor för borr- o gängverktyg, bult-fack, förvaringsfack för skruv",
            "chief": "H Boberg"
        },
        "5": {
            "company_name": "GNOSJO TRÄ-MANUFAKTUR, AB",
            "pnr": "33030",
            "address": "Gnosjö, Långg. Box 71",
            "phone_number": "0370-910 55, 910 30",
            "bankgiro": "54-2494",
            "postgiro": "493607",
            "activity": "Tillverkar alla slag av klädhängare",
            "employees": 14,
            "annual_turnover": 800000,
            "capital": 30000,
            "key_personnel": [
                {
                    "name": "Lennart Sigblad",
                    "position": "Verkst dir"
                }
            ],
            "establishment_year": 1925
        },
        "6": {
            "company_name": "MILETRYCK AB",
            "pnr": "16135",
            "address": "Bromma, Grindstuv 38",
            "phone_number": "08-26 08 00, 26 02 00",
            "bankgiro": "72-6156",
            "postgiro": "55525",
            "activity": "Boktryck o offset. Specialitet: etikettryck",
            "employees": 15,
            "annual_turnover": 800000,
            "capital": 75000,
            "key_personnel": [
                {
                    "name": "Emil Söderström",
                    "position": "Verkst dir"
                }
            ],
            "establishment_year": 1940
        },
        "7": {
            "company_name": "COLLÉNS VERKSTADS AB",
            "pnr": "11457",
            "address": "Stockholm, Riddarg 40",
            "phone_number": "08-63 52 55",
            "bankgiro": "57-2948",
            "postgiro": "151260",
            "activity": "Utför grovplåts- o mek arbeten. Tillverkar hissanordningar",
            "employees": 18,
            "annual_turnover": 850000,
            "capital": 30000,
            "key_personnel": [
                {
                    "name": "Torsten Hammarlund",
                    "position": "Verkst dir"
                },
                {
                    "name": "Lars Lindström",
                    "position": "Verkmäst"
                }
            ],
            "establishment_year": 1914
        },
        "8": {
            "company_name": "SKÅNSKA BANKEN",
            "pnr": "20110",
            "address": "Malmö 1, Söderg 10",
            "phone_number": "040-744 40",
            "activity": "Bankdir Axel Roos",
            "capital": 34000000,
            "key_personnel": [
                {
                    "name": "Bankdir Axel Roos",
                    "position": "Verkst dir"
                }
            ],
            "establishment_year": 1896
        },
        "9": {
            "company_name": "SKÅNSKA BOMULLSKRUT. FABRIKS AB",
            "pnr": "24023",
            "address": "Dösjebro, Box 18",
            "phone_number": "046-713 00",
            "bankgiro": "660-0969",
            "postgiro": "82330-2",
            "activity": "Tillverkar teknisk o farmaceutisk eter o collodium",
            "annual_turnover": 200000,
            "capital": 10000,
            "key_personnel": [
                {
                    "name": "Yngve Wiberg",
                    "position": "Verkst dir"
                }
            ],
            "establishment_year": 1929
        },
        "10": {
            "company_name": "SKÅNSKA BRANDS INTECKNINGS AB",
            "pnr": "22105",
            "address": "Lund 1, Tegnérsplatsen 4. Box 1255",
            "phone_number": "046-1170 50",
            "postgiro": "11010-6",
            "activity": "Lånerörelse",
            "capital": 1100000,
            "key_personnel": [
                {
                    "name": "Sven-Thorsten Frostell",
                    "position": "Verkst dir"
                }
            ],
            "establishment_year": 1934
        },
        "11": {
            "company_name": "ARV SVET",
            "activity": "Textilförädlings-maskiner",
            "employees": 3,
            "capital": 25000,
            "key_personnel": [
                {
                    "name": "Heinz-Dieter Scheube",
                    "position": "Verkst dir"
                }
            ],
            "establishment_year": 1961
        },
        "12": {
            "company_name": "TRANSMARK, REDERI.AB",
            "pnr": "40310",
            "address": "Göteborg 2, Fack. Packhusplatsen 3",
            "phone_number": "031-176700",
            "bankgiro": "500-5715",
            "postgiro": "12107",
            "Capital": 4000000,
            "key_personnel": [
                {
                    "name": "Rolf Carlsson",
                    "position": "Verkst dir"
                }
            ],
            "establishment_year": 1928
        },
        "13": {
            "company_name": "INTERPARES, AB",
            "pnr": "70132",
            "address": "Örebro 1, Box 961. Olaig 9",
            "phone_number": "019-124880",
            "bankgiro": "614-3564",
            "postgiro": "279329-7",
            "activity": "Centralorgan för byggmaterialdistributörer",
            "employees": 40,
            "annual_turnover": 135000000,
            "capital": 600000,
            "key_personnel": [
                {
                    "name": "Sven Dingertz",
                    "position": "Verkst dir"
                }
            ],
            "establishment_year": 1944
        },
        "14": {
            "company_name": "BRATTBY SÅGVERKS AB",
            "pnr": "91010",
            "address": "Vännäsby",
            "phone_number": "0935-20365",
            "bankgiro": "765-7083",
            "postgiro": "60461-1",
            "activity": "Sågade o hyvlade trävaror",
            "employees": 43,
            "annual_turnover": 10000000,
            "capital": 600000,
            "key_personnel": [
                {
                    "name": "Gustav Lundström",
                    "position": "Verkst dir"
                }
            ],
            "establishment_year": 1931
        },
        "15": {
            "company_name": "AM-MASKINER AB",
            "pnr": "20013",
            "address": "Malmö 27, Box 27069. Bjurög 35-37",
            "phone_number": "040-180170",
            "bankgiro": "2600070",
            "postgiro": "81786-6",
            "activity": "Import o partiförsäljning av maskiner o redskap för lantbruk o skogsbruk",
            "employees": 33,
            "annual_turnover": 9800000,
            "capital": 11545000,
            "key_personnel": [
                {
                    "name": "Bankdir Didrik Hamilton",
                    "position": "ordf"
                },
                {
                    "name": "Lennart Smith",
                    "position": "dir"
                },
                {
                    "name": "Bengt Kihlgren",
                    "position": "dir"
                },
                {
                    "name": "Monica Hamilton",
                    "position": "grevinnan"
                },
                {
                    "name": "Bengt Kihlgren",
                    "position": "Verkst dir"
                }
            ],
            "establishment_year": "saknas"
        },
        "16": {
            "company_name": "AMP SCANDINAVIA AB",
            "pnr": "17500",
            "address": "Jakobsberg, Pack. Datav 5",
            "phone_number": "0758-104 00",
            "bankgiro": "580-8001",
            "postgiro": "407140-3",
            "activity": "Tillverkar o marknadsför elektr anslutningsdetaljer, programmeringsutrustningar, elektronikkomponenter m m. Ett 50-tal fabriker i USA, Europa, Mexico, Australien o Japan",
            "employees": 50,
            "annual_turnover": 20000000,
            "capital": 250000,
            "key_personnel": [
                {
                    "name": "H U von der Esch",
                    "position": "ordf"
                },
                {
                    "name": "S Hellner",
                    "position": "saknas"
                },
                {
                    "name": "W C Lange",
                    "position": "saknas"
                },
                {
                    "name": "Bengt Wimrén",
                    "position": "Verkst dir"
                }
            ],
            "establishment_year": 1967
        },
        "17": {
            "company_name": "AMS RUR AB",
            "pnr": "57300",
            "address": "Tranås, Missionsg 7",
            "phone_number": "0140-141 80",
            "bankgiro": "365-5040",
            "postgiro": "11763-0",
            "activity": "saknas",
            "capital": 100000,
            "key_personnel": [
                {
                    "name": "Ing Stig Carlsson",
                    "position": "Verkst dir"
                }
            ],
            "establishment_year": 1952
        }
    }
}