{
    "original": "BJORBO SNICKERIFABRIK AB\n\nPnr 780 45\n\nBjörbo. Tel 0241-232 60. Bankgiro\n79-4303. Postgiro 135219\nVerksamhet: Tillverkar\nköksinredningar\n\nAntal anställda: 75\nÅrsomsättning: 6 000 000\nAktiekapital: 400 000\nVerkst dir: Oscar Enmalm\nEtableringsår: 1925.\n\nFORSAKERS FABRIKER, AB\n\nPnr 43122\n\nMölndal 1, Kungsbackav 19. Box\n110. Tel 031-27 2 1 00, 27 4 6 24.\nBankgiro 43-9845. Postgiro\n45015-5. Tga Forsåkers\nVerksamhet: Tillverkar o säljer\ntrassel, skur- o torkdukar samt\nmoppar o putslappar\nAntal anstäUda: 15\nÅrsomsättning: 2500 000\nAktiekapital: 880 000\nVerkst dir: Mogens Willumsen\nEtableringsår: 1880.\n\nHALLBERG &amp; CO, AB\n\nPnr 25102\n\nHelsingborg 1, Box 105.\nGarni-sonsg 6. Tel 042-1201 20\nVerksamhet: Elekfr installationer o\nkonsultverksamhet.\nButiksförsäljning av el-apparater\nFilialer: 223 54 Lund, Tullg 16.\nTel 046-12 47 00\n\n261 32 Landskrona, Järnvägsg 24.\nTel 0418-11472\n\n24100 Eslöv, Malmg 4. Tel\n0413-104 54\n\nVerkst dir: Hans Hallberg\nEtableringsår: 1916.\n\nNIKE, DOMKRAFT AB\n\nPnr 63107\n\nEskilstuna 1, Box 544. Hejarg 1.\nTel 016-1172 60. Postgiro 85282-2.\nTga Nikedomkraft. Telex 40989\nVerksamhet: Tillverkar mek o\nhydrauliska domkrafter, frisörstolar,\nritbord, aducer- o\ntackjärnsgjut-gods\n\nAntal anställda: 550\nÅrsomsättning: 40 000 000\nAktiekapital: 550000\nVerkst dir: Yngve Flodin\nEtableringsån 1927.\n\nJEPPSSON AB, TORSTEN\n\nPnr 271 00\n\nYstad. Blyg 6. Tel 0411-137 75.\nBankgiro 670-3045. Postgiro\n9414-4\n\nVerksamhet: Blanketter,\nbroschyrer, etiketter o förpackningar\nAntal anställda: 76\nAktiekapital: 250 000\nVerkst dir: Torsten Jeppsson\nEtableringsår: 1957.\n\nVAMO AB\n\nPnr 53010\n\nVedum, Larv. Tel 0512-420 13.\nBankgiro 193-5675. Postgiro\n131822-9\n\nVerksamhet: Tillverkar harvar,\nvältar, skyffelkärror, pumpar mm\nAntal anställda: 18\nÅrsomsättning: 1500000\nAktiekapital: 5 000\nVeikst dir Ingemar Jakobsson\nEtableringsår: 1957.\n\nCHRISTIERNSSON, AB AXEL\n\nPnr 100 53\n\nStockholm 37, S Hamnv 22. Pack.\nTel 08-63 13 60. Bankgiro 728-\n\n0670. Postgiro 748-4. Tga\nChristian\n\nVerksamhet: Oljor, fett o\nindustri-förnödenheter. Fabrik i Värtan\nAntal anställda: 35\nÅrsomsättning: 8 200 000\nAktiekapital: 500000\nVerkst dir: Bo Ingelson\nEtableringsår 1888.\n\nCHRISTIERNSSON,\nGÖTE-BORGS AB AXEL\n\nPnr 403 13\n\nGöteborg 2, Stora Badhusg 20. Box\n2147. Tel 031-17 04 60. Bankgiro\n506-6220. Postgiro 12442-0. Tga\nBakuin\n\nVerksamhet: Säljer smörjoljor o\nsmörjfett av alla slag,\nindustriförnödenheter samt paraffin o växer.\nD A Stuart Oil Co, Chicago, USA.\nLiqui Moly GmbH, Ulm, Tyskland.\nMarston Lubricants Ltd, Liverpool,\nEngland. Quaker State Oil Refining\nCorp, Oil City, USA\nVarunamn: Royal, Quaker State\nFilial: 212 22 Malmö, S Bulltoftav\n17. Tel 040-93 62 90\nAktiekapital: 450 000\nVerkst dir: Bo Ingelson\nEtableringsår: 1931.\n\nCHRISTI ERNSSONS MASKIN AB\nACMA, AXEL\n\nPnr 11134\n\nStockholm, Sveav 31. Tel\n08-23 42 50. Telex 1404. Tga Acma-\n\ntool\n\nVerksamhet: Säljer\nverktygsmaskiner\n\nAktiekapital: 100 000\nVerkst dir: Ingemar Lundén\nEtableringsår: 1888.\n\nCHROMOS AB,\nFÄRGFABRIKEN\n\nPnr 212 30\n\nMalmö, Rönnbackeg 15. Tel\n040-49 03 72. Bankgiro 643-0854.\nPostgiro 430490-3. Tga Primocebex\nVerksamhet: Tillverkar o säljer\nfärger\n\nAktiekapital: 40 000\nVerst dir: Arnold Jogert\nEtableringsår: 1954.\n\nEXQ\n\nEWIKA, AB\n\nPnr 38100\n\nKalmar, S Långg 5. Tel 0480-14111.\nBankgiro 655-7474. Postgiro\n93466-1\n\nVerksamhet: Säljer bomulls-, ylle-,\nslike- o linnevävnader i parti\nAktiekapital: 100 300\nVerkst dir: Ernst W Johansson\nEtableringsår 1873\nOmbildat till aktiebolag 1935.\n\nEVO AB, METALLFABRIKEN\n\nPnr 330 30\n\nGnosjö. Tel 0370-91101. Postgiro\n95055\n\nVerksamhet: Tillverkar\nbyggnads-o båtbeslag, skolkrok, klädkrok,\nflagghållare. Specialitet:\npress-gjutning i lättmetall\nAktiekapital: 30 000\nVerkst dir: E Carlsson\nEtableringsår: 1960.\n\nSVENSKA TELEMEKANIK AB\n\nPnr 642 00\n\nFlen, Fack. Drottningg 22. Tel\n0157-12470. Bankgiro 82-8924.\nPostgiro 659680. Tga Telemek.\nTelex 64128\n\nVerksamhet: Säljer reläer,\nkontaktorer, startapparater,\nmanövertill-behör, tyristorströmriktare,\ntransi-storiserade styrsystem typ\nTele-static o Canalis kapslade\nkanalskenor för eldistribution.\nTillverkar elektr apparat- o\nautomatikutrustningar samt\nelektronikutrustningar\n\nVarunamn: Canalis, Telestatic\nAntal anställda: 70\nÅrsomsättning: 14 000 000\nAktiekapital: 2 600 000\nStyrelse: Dir Göran Hiort af Ornäs\n(ordf) dir Jacques Flatet, civiling\nCarl-Reinhold von Arnold\nVerkst dir Carl-Reinhold von\nArnold\n\nEtableringsår: 1962.\n\nORESTAD SVETSMEKANO AB\n\nPnr 244 00\n\nKävlinge, Bang 8. Tel 046-322 50.\nBankgiro 711-7260. Postgiro\n635895-6\n\nVerksamhet: Tillverkar\nhydraul-komponenter, cisterner,\nlantbruksmaskiner, svetskonstruktioner,\nvärmeväxlare. Komplett\nmaskinbearbetning. Montage- o\nreparationsarbeten, licenssvetsning. Utför\nsprutmålning, sandblästring, svarte\noxidering\nVarunamn: OSAB\nAntal anställda: 28\nÅrsomsättning: 1600 000\nVerkst dir: Gunnar Sjöstedt\n\nVerkstadsing: Kjell-Anders\nSjöstedt\n\nEtableringsår: 1968.",
    "structured": {
        "firms": [
            {
                "company_name": "BJORBO SNICKERIFABRIK AB",
                "pnr": "780 45",
                "address": "Björbo",
                "phone_number": "0241-232 60",
                "bank_details": {
                    "bankgiro": "79-4303",
                    "postgiro": "135219"
                },
                "activity": "Tillverkar köksinredningar",
                "employees": 75,
                "annual_turnover": 6000000,
                "capital": 400000,
                "key_personnel": [
                    {
                        "name": "Oscar Enmalm",
                        "position": "Verkst dir"
                    }
                ],
                "establishment_year": 1925
            },
            {
                "company_name": "FORSAKERS FABRIKER, AB",
                "pnr": "43122",
                "address": "Mölndal 1, Kungsbackav 19. Box 110",
                "phone_number": "031-27 2 1 00, 27 4 6 24",
                "bank_details": {
                    "bankgiro": "43-9845",
                    "postgiro": "45015-5"
                },
                "activity": "Tillverkar o säljer trassel, skur- o torkdukar samt moppar o putslappar",
                "employees": 15,
                "annual_turnover": 2500000,
                "capital": 880000,
                "key_personnel": [
                    {
                        "name": "Mogens Willumsen",
                        "position": "Verkst dir"
                    }
                ],
                "establishment_year": 1880
            },
            {
                "company_name": "HALLBERG & CO, AB",
                "pnr": "25102",
                "address": "Helsingborg 1, Box 105. Garni-sonsg 6",
                "phone_number": "042-1201 20",
                "activity": "Elekfr installationer o konsultverksamhet. Butiksförsäljning av el-apparater",
                "key_personnel": [
                    {
                        "name": "Hans Hallberg",
                        "position": "Verkst dir"
                    }
                ],
                "establishment_year": 1916
            },
            {
                "company_name": "NIKE, DOMKRAFT AB",
                "pnr": "63107",
                "address": "Eskilstuna 1, Box 544. Hejarg 1",
                "phone_number": "016-1172 60",
                "bank_details": {
                    "postgiro": "85282-2"
                },
                "activity": "Tillverkar mek o hydrauliska domkrafter, frisörstolar, ritbord, aducer- o tackjärnsgjut-gods",
                "employees": 550,
                "annual_turnover": 40000000,
                "capital": 550000,
                "key_personnel": [
                    {
                        "name": "Yngve Flodin",
                        "position": "Verkst dir"
                    }
                ],
                "establishment_year": 1927
            },
            {
                "company_name": "JEPPSSON AB, TORSTEN",
                "pnr": "271 00",
                "address": "Ystad",
                "phone_number": "0411-137 75",
                "bank_details": {
                    "bankgiro": "670-3045",
                    "postgiro": "9414-4"
                },
                "activity": "Blanketter, broschyrer, etiketter o förpackningar",
                "employees": 76,
                "capital": 250000,
                "key_personnel": [
                    {
                        "name": "Torsten Jeppsson",
                        "position": "Verkst dir"
                    }
                ],
                "establishment_year": 1957
            },
            {
                "company_name": "VAMO AB",
                "pnr": "53010",
                "address": "Vedum, Larv",
                "phone_number": "0512-420 13",
                "bank_details": {
                    "bankgiro": "193-5675",
                    "postgiro": "131822-9"
                },
                "activity": "Tillverkar harvar, vältar, skyffelkärror, pumpar mm",
                "employees": 18,
                "annual_turnover": 1500000,
                "capital": 5000,
                "key_personnel": [
                    {
                        "name": "Ingemar Jakobsson",
                        "position": "Veikst dir"
                    }
                ],
                "establishment_year": 1957
            },
            {
                "company_name": "CHRISTIERNSSON, AB AXEL",
                "pnr": "100 53",
                "address": "Stockholm 37, S Hamnv 22. Pack",
                "phone_number": "08-63 13 60",
                "bank_details": {
                    "bankgiro": "728-0670",
                    "postgiro": "748-4"
                },
                "activity": "Oljor, fett o industri-förnödenheter. Fabrik i Värtan",
                "employees": 35,
                "annual_turnover": 8200000,
                "capital": 500000,
                "key_personnel": [
                    {
                        "name": "Bo Ingelson",
                        "position": "Verkst dir"
                    }
                ],
                "establishment_year": 1888
            },
            {
                "company_name": "CHRISTIERNSSON, GÖTE-BORGS AB AXEL",
                "pnr": "403 13",
                "address": "Göteborg 2, Stora Badhusg 20. Box 2147",
                "phone_number": "031-17 04 60",
                "bank_details": {
                    "bankgiro": "506-6220",
                    "postgiro": "12442-0"
                },
                "activity": "Säljer smörjoljor o smörjfett av alla slag, industriförnödenheter samt paraffin o växer",
                "employees": null,
                "annual_turnover": null,
                "capital": 450000,
                "key_personnel": [
                    {
                        "name": "Bo Ingelson",
                        "position": "Verkst dir"
                    }
                ],
                "establishment_year": 1931
            },
            {
                "company_name": "CHRISTI ERNSSONS MASKIN AB ACMA, AXEL",
                "pnr": "11134",
                "address": "Stockholm, Sveav 31",
                "phone_number": "08-23 42 50",
                "activity": "Säljer verktygsmaskiner",
                "capital": 100000,
                "key_personnel": [
                    {
                        "name": "Ingemar Lundén",
                        "position": "Verkst dir"
                    }
                ],
                "establishment_year": 1888
            },
            {
                "company_name": "CHROMOS AB, FÄRGFABRIKEN",
                "pnr": "212 30",
                "address": "Malmö, Rönnbackeg 15",
                "phone_number": "040-49 03 72",
                "bank_details": {
                    "bankgiro": "643-0854",
                    "postgiro": "430490-3"
                },
                "activity": "Tillverkar o säljer färger",
                "capital": 40000,
                "key_personnel": [
                    {
                        "name": "Arnold Jogert",
                        "position": "Verst dir"
                    }
                ],
                "establishment_year": 1954
            },
            {
                "company_name": "EWIKA, AB",
                "pnr": "38100",
                "address": "Kalmar, S Långg 5",
                "phone_number": "0480-14111",
                "bank_details": {
                    "bankgiro": "655-7474",
                    "postgiro": "93466-1"
                },
                "activity": "Säljer bomulls-, ylle-, slike- o linnevävnader i parti",
                "capital": 100300,
                "key_personnel": [
                    {
                        "name": "Ernst W Johansson",
                        "position": "Verkst dir"
                    }
                ],
                "establishment_year": 1873
            },
            {
                "company_name": "EVO AB, METALLFABRIKEN",
                "pnr": "330 30",
                "address": "Gnosjö",
                "phone_number": "0370-91101",
                "bank_details": {
                    "postgiro": "95055"
                },
                "activity": "Tillverkar byggnads-o båtbeslag, skolkrok, klädkrok, flagghållare. Specialitet: press-gjutning i lättmetall",
                "capital": 30000,
                "key_personnel": [
                    {
                        "name": "E Carlsson",
                        "position": "Verkst dir"
                    }
                ],
                "establishment_year": 1960
            },
            {
                "company_name": "SVENSKA TELEMEKANIK AB",
                "pnr": "642 00",
                "address": "Flen, Fack. Drottningg 22",
                "phone_number": "0157-12470",
                "bank_details": {
                    "bankgiro": "82-8924",
                    "postgiro": "659680"
                },
                "activity": "Säljer reläer, kontaktorer, startapparater, manövertill-behör, tyristorströmriktare, transi-storiserade styrsystem",
                "employees": 70,
                "annual_turnover": 14000000,
                "capital": 2600000,
                "key_personnel": [
                    {
                        "name": "Göran Hiort af Ornäs",
                        "position": "Styrelse: Dir"
                    },
                    {
                        "name": "Jacques Flatet",
                        "position": "Styrelse: Dir"
                    },
                    {
                        "name": "Carl-Reinhold von Arnold",
                        "position": "Styrelse: civiling"
                    },
                    {
                        "name": "Carl-Reinhold von Arnold",
                        "position": "Verkst dir"
                    }
                ],
                "establishment_year": 1962
            },
            {
                "company_name": "ORESTAD SVETSMEKANO AB",
                "pnr": "244 00",
                "address": "Kävlinge, Bang 8",
                "phone_number": "046-322 50",
                "bank_details": {
                    "bankgiro": "711-7260",
                    "postgiro": "635895-6"
                },
                "activity": "Tillverkar hydraul-komponenter, cisterner, lantbruksmaskiner, svetskonstruktioner, värmeväxlare",
                "employees": 28,
                "annual_turnover": 1600000,
                "key_personnel": [
                    {
                        "name": "Gunnar Sjöstedt",
                        "position": "Verkst dir"
                    },
                    {
                        "name": "Kjell-Anders Sjöstedt",
                        "position": "Verkstadsing"
                    }
                ],
                "establishment_year": 1968
            }
        ]
    }
}