{
    "original": "NÄSSJÖ DECOUPEURFABRIK\n\nPnr 57100\n\nNässjö, Stureg 9. Tel 0380-10247,\n126 00\n\nVerksamhet: Intarsior för möbler,\nstilbyråer, inredningar o\nprydnadsföremål\n\nÄgare o chef: Fabr Olov Skoglund.\n\nNÄSSJÖ FANÉRFABRIK, AB\n\nPnr 57100\n\nNässjö, Ho reg 18. Tel 0380-11166\n\nVerksamhet: Tillverkar fanér o\nbatteriseparatorer\nAktiekapital: 100 000\nVerkst dir: Gunnar Byström\nEtableringsår: 1939.\n\nHURBY BRUK, AB\n\nPnr 242 00\n\nHörby. Tel 0415-114 4 0. Bankgiro\n654-9042. Postgiro 71215-8\nVerksamhet: Tillverkar skottkärror,\ntransportvagnar, specialkärror,\nvalvstämp o lekprodukter\nVarunamn: Ekeby-Kärran\nAntal anställda: 55\nÅrsomsättning: 6 000 000\nAktiekapital: 250 000\nStyrelse: Godsäg Karl Axel\nBergengren (ordf), godsäg Anders G\nBergengren\n\nPlatschef: Ing Lennart Book\nEtableringsår: 1949.\n\nHURE MEKANISKA\nVERKSTADS AB\n\nPnr 57100\n\nPostgiro 470913-5\n\nNässjö, Höreg 7.Tel 0380-129 22.\n\nKANTPRESSNING\nLICENSSVETSNING\n\nVerksamhet: Utför plåtarbeten,\nsvetsning, järnkonstruktioner, mek\narbeten, kantpressning,\nlicenssvetsning\n\nAktiekapital: 100 000\nVerkst dir: Erik Eriksson\nEtableringsår. 1956.\n\nHURGREN AB\nINTERNATIONELLA TRANSPORTER.\nGU ST A\n\nPnr 10121\n\nStockholm 1, Vasag 52. Box 95.\nTel 08-23 82 60. Telex 1468\nVerksamhet: Spedition,\nmagasinering. in- o utrikes flyttningar\nAntal anställda: 85\nÅrsomsättning: 16 000000\nAktiekapital: 50000\nVerkst dir. Gösta Hörgren\nEtableringsår: 1943.\n\nFJÄRRVÄRME, AB\n\nPnr 114 26\n\nStockholm, üstermalmsg 40. Tel\n08-22 14 70. Bankgiro 41-6005.\nPostgiro 450039-3\nVerksamhet: Konsulterande\ningenjörsfirma\n\nAntal anstäUda: 14\nÅrsomsättning: 1000 000\nAktiekapital: 50000\nVerkst dir: Civiling Ake Björk\nEtableringsår: 1948.\n\nISA\n\nISACSSON &amp; LYCKE, AB\n\nPnr 440 32\n\nYtterby, Box 375. Tel 0303-913 17.\n914 98. Tga Abisly\nVerksamhet: Tillverkar allt i\nse-gelmakeri för sjöfarten samt\ncampingtält\n\nAktiekapital: 105 000\nFirmatecknare: Ivan Isacsson,\nFolke Lycke\nEtableringsår: 1945.\n\nISACSONS WELLEMBALLAGE\nAB\n\nPnr 31070\n\nTorup, Brännögård. Tel\n0345-304 00. Tga Igi, Halmstad.\nTelex 38029\n\nVerksamhet: Tillverkning o\nförsäljning av wellpappemballage\nDistriktskontor: 11148 Stockholm,\nBlasieholmstorg 14. Tel 08-\n\n14 28 55. Chef: Sverre Isacson\n400 30 Göteborg, Sveag 27 A. Tel\n031-1261 07. Telex 20937. Chef:\nGösta Andersson\n\n200 44 Main», Brageg 22. Tel\n040-800 55. Telex 32584. Chef: Paul\nDerlow\n\n31070 Torup. Fack. Tel\n0345-300 40. Chef: Gunnar Persson\nAntal anställda: 285\nÅrsomsättning: 44 000000\nAktiekapital: 350000\nVerkst dir: Bengt Isacson\nEtableringsår: 1936.\n\nHÄL\n\nVerksamhet:Tillverkar o säljer\nhydrauliska järn- o stålsaxar,\nbock-ningsmaskiner, bock- o\nbygelapparater for bockning av armeringsjärn.\nRullbanor för kamjärn samt\nbocknycklar\n\nVerkstad: Stockholm VA.Upplandsg\n74. Tel 08-34 37 72\nVarunamn: Hållto\nAktiekapital: 5000\nVerkst dir: Stina Larsson\nEtableringsår: 1945.\n\nFAHLSTRÖM AB, I\n\nPnr 103 43\n\nStockholm 40, Kungsg 33. Box\n40114. Tel 08-24 02 00. Postgiro\n230824. Tga Talldo\nVerksamhet: Agenturer\nAktiekapital: 5 000\nVerkst dir: Fra Ingrid Fahlström\nEtableringsår: 1946.\n\nEPOX KOMMANDITBOLAG\n\nPnr 413 10\n\nGöteborg, Linnëplatsen 3. Tel\n031-13 6133. Bankgiro 50-0438.\nPostgiro 620492. Tga Debroen\nVerksamhet: Importerar o säljer\ntextilråvaror, garner,\nbyggnadsmaterial m m\n\nÅrsomsättning: 3 000 000\nChef: J H de Broen\nEtableringsår: 1959.\n\nPELLERIN/ZENITH, AB\n\nPnr 252 28\n\nHälsingborg, Zenitg 1. Tel\n042-1802 80. Bankgiro 640-0584.\nPostgiro 5550-9. Tga Pellerinzenith.\nTelex 72429 ZENITH S\nVerksamhet: Tillverkar hushålls- o\nbagerimargarin\n\nFörsäljning genom Margarinbolaget\n\nAB: 104 25 Stockholm 30. Fack. Tel\n08-5413 60\nAntal anställda: 219\nÅrsomsättning: 126000 000\nAktiekapital: 6 000 000\nStyrelse: Dir Bertil Thorburn (ordf),\ndir Lars Olof Bergman, dir Ingmar\nEidem, dir Per Ekström, dir Gunnar\nGlimstedt, dir Töre Lauritzson\nVerkst din Lars Olof Bergman\nV verkst dir: Bengt Ulf\nTekn dir: Agne Johnsson\nAdm-dir: Lars-Yngve Larson.\n\nPELLVIK, AB GUNNAR\n\nPnr 52101\n\nFalköping 1, Kyrkerörsg 11. Box\n79. Tel 0515-113 72, 146 90.\nBankgiro 213-7800. Postgiro 263924-3\nVerksamhet: Kartonger,\nförseglingsremsor o polyethylenepåsar\nAktiekapital: 5 000\nVerkst dir: Gunnar Pellvik\nEtableringsår: 1960.\n\nLILLJEQUIST &amp; SON, AB\n\nPnr 41121\n\nGöteborg, St Badhusg 28 A. Tel\n031-131642. Bankgiro 511-5084.\nPostgiro 12325-7. Tga Nabilos\nVerksamhet: Skeppsfurnering o\nlivsmedelshandel\nAntal anställda: 9\nÅrsomsättning: 1700 000\nAktiekapital: 30 000\nVerkst dir: Kurt Magnusson\nEtableringsår: 1926.\n\nANDERSSONS VÄRME, AB H\n\nPnr 17185\n\nSolna, Pyramidv 2. Tel 08-27 28 00\nVerksamhet:\nRörledningsentreprenör\n\nFilialen Boden, Läroverksg 32.\nTel 0921-12188, 113 34\nGällivare, Björkmansv 6. Tel\n0970-130 10\n\nHaparanda, Storg 65. Tel\n0922-102 07\n\nHärnösand, Kronholmen. Tel\n0611-124 21, 125 52\n\nKalix, Industrihuset. Tel\n0923-107 55\n\nKiruna, Hantverkscentrum. Tel\n0980-10688, 142 35\nKramfors. Tel 0612-107 70\nLuleå, Sandviksg 61. Tel\n0920-218 08, 120 69\n\nLycksele, Storg 18. Tel\n0950-10254, 10571\n\nPiteå, Hainng 63. Tel 0911-113 77,\n11877\n\nSkelleftehamn, S Hamng 35. Tel\n0910-31148\n\nSkellefteå, Storg 44. Tel\n0910-114 76, 114 77\nStrömsund. Tel 0670-107 98\nSundsvall, Storg 73. Tel 060-\n\n15 08 50\n\nSveg. Tel 0680-101 04\n\nTärnaby. Tel 58\n\nUmeå, Industri v 22. Tel 090-\n\n1185 00\n\nVilhelmina, Videv 63. Tel\n0940-10178\n\nÅnge. Tel 0690-108 66\nÅsele, Sotareg 3. Tel 73\nÄlvsbyn. Tel 0929-113 05\nÖrnsköldsvik, Strandg. Tel\n0660-177 50\n\nÖstersund, Prästg48. Tel 063-\n\n273 60\n\nVerkst dir: Jan Backmark\nEtableringsår: 1898\nOmbildat till aktiebolag 1918.\n\nANDERSSON, HANS\n\nPnr 23100\n\nTrelleborg. Alstad. Tel\n040-48 50 16, 48 51 16. Bankgiro\n665-9122. Postgiro 13801-6\nVerksamhet: Trävaror o\nbyggnadsmaterial, spannmål, foder, gödning\nFirmatecknare: Allan Andersson,\nMalte Andersson\nEtableringsår: 1850.",
    "structured": {
        "1": {
            "company_name": "NÄSSJÖ DECOUPEURFABRIK",
            "pnr": "57100",
            "address": "Nässjö, Stureg 9",
            "phone_number": "0380-10247",
            "activity": "Intarsior för möbler, stilbyråer, inredningar o prydnadsföremål",
            "key_personnel": [
                {
                    "name": "Fabr Olov Skoglund",
                    "position": "Ägare o chef"
                }
            ],
            "establishment_year": 0
        },
        "2": {
            "company_name": "NÄSSJÖ FANÉRFABRIK, AB",
            "pnr": "57100",
            "address": "Nässjö, Ho reg 18",
            "phone_number": "0380-11166",
            "activity": "Tillverkar fanér o batteriseparatorer",
            "capital": 100000,
            "key_personnel": [
                {
                    "name": "Gunnar Byström",
                    "position": "Verkst dir"
                }
            ],
            "establishment_year": 1939
        },
        "3": {
            "company_name": "HURBY BRUK, AB",
            "pnr": "242 00",
            "address": "Hörby",
            "phone_number": "0415-114 4 0",
            "bank_details": {
                "bankgiro": "654-9042",
                "postgiro": "71215-8"
            },
            "activity": "Tillverkar skottkärror, transportvagnar, specialkärror, valvstämp o lekprodukter",
            "employees": 55,
            "annual_turnover": 6000000,
            "capital": 250000,
            "key_personnel": [
                {
                    "name": "Godsäg Karl Axel Bergengren",
                    "position": "Styrelse (ordf)"
                },
                {
                    "name": "Godsäg Anders G Bergengren",
                    "position": "Styrelse"
                },
                {
                    "name": "Ing Lennart Book",
                    "position": "Platschef"
                }
            ],
            "establishment_year": 1949
        },
        "4": {
            "company_name": "HURE MEKANISKA VERKSTADS AB",
            "pnr": "57100",
            "phone_number": "0380-129 22",
            "bank_details": {
                "postgiro": "470913-5"
            },
            "activity": "Utför plåtarbeten, svetsning, järnkonstruktioner, mek arbeten, kantpressning, licenssvetsning",
            "capital": 100000,
            "key_personnel": [
                {
                    "name": "Erik Eriksson",
                    "position": "Verkst dir"
                }
            ],
            "establishment_year": 1956
        },
        "5": {
            "company_name": "HURGREN AB INTERNATIONELLA TRANSPORTER",
            "pnr": "10121",
            "address": "Stockholm 1, Vasag 52",
            "phone_number": "08-23 82 60",
            "activity": "Spedition, magasinering. in- o utrikes flyttningar",
            "employees": 85,
            "annual_turnover": 16000000,
            "capital": 50000,
            "key_personnel": [
                {
                    "name": "Gösta Hörgren",
                    "position": "Verkst dir"
                }
            ],
            "establishment_year": 1943
        }
    }
}