{
    "original": "HAG\n\nHAGA BLECK. &amp; PLÄT.\nSLAGERI AB\n\nPnr 411 22\n\nGöteborg C, Husarg 42. Tel\n031-1059 40, 10 59 41. Postgiro 42655\nVerksamhet: Rostfria inredningar\no byggnadsplåtslageri\nAntal anställda: 30\nÅrsomsättning: 950 000\nAktiekapital: 25 000\nÄgare o chef: Henry Hj Johanson\nEtableringsår: 1961.\n\nARY STÅLMOBLER AB\n\nPnr 380 43\n\nÖrsjö, Box 79. Tel 0481-202 00.\nBankgiro 856-1623. Postgiro\n570121-4. Tga Arytrade, Kalmar\nVerksamhet: Tillverkar kontors- o\nverkstadsstolar, kantin-, hotell-,\nrestaurant-, cafeteria- o\nskolmöb-ler. Utför legoarbeten i svetsade\nrörkonstruktioner\n\nFörsäljningskontor: Stockholm VA,\nBirger Jarlsg 71. Tel 08-10 2218,\nChef: Edgar Oiangen\nAntal anställda: 36\nÅrsomsättning: 3 500 000\nAktiekapital: 50 000\nStyrelse: Ryttmäst Fabian Wrede\n(ordf), disp Hans Bengtner, kamrer\nLinnea Edsenius\n\nVerkst din Ryttmäst Fabian Wrede\nVerkstadschef: Matz Persson\nEtableringsår: 1960.\n\nAS MEKANISKA\nVERK-STAD, AB\n\nPnr 330 10\n\nBredaryd, Västboås. Tel\n0371-700 81. Bankgiro 142-7582.\nPostgiro 387943-4\n\nVerksamhet: Formsprutning,\nindustriartiklar, gardin- o biltillbehör.\nVerktygsavdelning\nAktiekapital: 10 000\nStyrelse: B A H Wilhelmsson, E M\nWilhelmsson\n\nÄgare: B A H Wilhelmsson\nEtableringsår: 1948.\n\nSVENSK SJÖFARTS TIDNING\n\nPnr 400 14\n\nGöteborg 53, Kungsportsavenyn 1.\nBox 53090. Tel 031-17 85 40.\nBankgiro 420-5233. Postgiro 41114-0.\nTelex 20746 SWESHIP S.\nTga Shipgazette\n\nVerksamhet: Facktidskrift för\nsjöfart, rederi- o varvsnäring samt\nnärliggande områden\nAntal anställda: 10\nÅrsomsättning: 1 900 000\nChefred, ansvarig utgivare:\nThorsten Rinman\nAdm-red: Lars Linder\nEtableringsår: 1905\nÄges av Sveriges Redareförening.\n\nSVENSK SKALEX, AB\n\nPnr 686 00\n\nSunne, Verkstadsg 5. Box 161. Tel\n0565-11130. Postgiro 6086-3\nVerksamhet: Tillverkar formluckor\nför betongformar\nAntal anställda: 10\nAktiekapital: 15 000\nFirmatecknare: Folke Hallberg o\nGustav Johnson\nEtableringsår: 1949.\n\nHÖGANÄS AB\n\nPnr 263 00\n\nHöganäs. Tel 042-424 00. Telex\n72250. Tga Clayworks\nVerksamhet: Tillverkar järnpulver,\neldfast o syrafast keramiskt mat o\nrial, keramiska golv- o väggplattor,\nplaströr m m\nAntal anställda: 2 233\nÅrsomsättning: 178 000 000\nAktiekapital: 70 000 000\nVerkst dir Olov Herneryd\nEtableringsår: 1903.\n\nALFORT &amp; CRONHOLM, AB\n\nPnr 104 30\n\nStockholm 45, Saltmätarg 7. Box\n45006. Tel 34 00 60, riks\n08-340160. Tga Alf ort\nVerksamhet: Färgfabrikanter.\nGrossister o distributörer av\nkemikalier, kem-tekn artiklar o övriga\nfärghandelsvaror\n\nFabrik: Ulvsunda. Tel 08-26 28 60\nAvdelningskontor: Göteborg, Malmö,\nJönköping, Örebro, Sundsvall\nFirmamärke: Alcro\nAntal anställda: 800\nAktiekapital: 12 000 000\nVerkst dir: Karl E Åman\nEtableringsår: 1906.\n\nALFREDÉEN AB,\nINGENJÖRSFIRMA A\n\nPnr 124 46\n\nBandhagen, Götlundag 4. Tel\n08-47 28 80\n\nVerksamhet: Allmänna\nmaskinkonstruktioner, transportanordningar o\nverktyg etc. Konsulterande\nverksamhet o mek verkstad. Tillverkar\nmätverktyg o specialmaskiner\nAntal anställda: 95\nÅrsomsättning: 6 000 000\nAktiekapital: 200000\nStyrelse: Adv Hans Bagner (ordf),\ndir Uno Alfredéen, dir A Alfredéen,\ning Sture Berglund, frk B Luthman\nVerkst dir Uno Alfredéen\nEtableringsår: 1954.\n\nMÅL\n\nAntal anställda: 10\nÅrsomsättning: 1000 000\nAktiekapital: 30 000\nStyrelse: Bertil Normén (ordf),\nMartin Måhl\nChef: Bertil N armén\nEtableringsår: 1945.\n\nMÅLERI.\n\nse resp namn.\n\nMÅLERÅS GLASBRUK, AB\n\nPnr 38042\n\nMålerås. Tel 0481-311 00.\nPostgiro 82113. Tga Måleråsglas\nVerksamhet: Tillverkar konstglas,\nhushållsglas, servisglas o\npressglas\n\nAktiekapital: 360 000\nVerkst dir Olle Högström\nEtableringsår: 1923.\n\nMÅLMARKS TRÅD.\nFURÄDLINGS AB\n\nPnr 330 30\n\nGnosjö. Tel 0370-950 20. Postgiro\n29455-3\n\nVeiksamhet: Tillverkar öglad o\nspolad najtråd för armering,\ntrådmanufaktur, formstift, klädkrok,\ntubnycklar, säckbindningstråd m m.\nSpolad najtråd o adress\nlapps-hållare\n\nAntal anställda: 5\nÅrsomsättning: 1000 000\nAktiekapital: 50000\nVerkst dir Gösta Målmark\nEtableringsår: 1925\nOmbildat till aktiebolag 1951.\n\nMÅN SAR PS GJUTERI, AB\n\nPnr 560 22\n\nMånsarp, Box 46. Tel 036-643 39,\n644 93. Bankgiro 545-4228.\nPostgiro 174073-7\n\nVerksamhet: Framställer\ntackjärns-gjutgods, såväl hand som\nmaskinformat. Modelltillverkning\nAntal anstäUda: 12\nAktiekapital: 100000\nVerkst dir: Thage Hammarnäs\nEtableringsår: 1946\nOmbildat till aktiebolag 1952.\n\nMÅNSARPS MEKANISKA\nVERKSTAD AB\n\nPnr 560 22\n\nMånsarp, Box 10. Tel 036-645 30.\nBankgiro 545-4236. Postgiro\n340162-7\n\nVerksamhet: Tillverkar lyftblock,\nblockvagnar, traverser o vägghissar\nAntal anstäUda: 33\nÅrsomsättning: 3 000 000\nAktiekapital: 70 000\nEtableringsår 1955.\n\nBILDEVE I ALVESTA AB\n\nPnr 342 00\n\nAlvesta, Pabriksg 13. Tel\n0472-118 20\n\nVerksamhet: Tillverkar o säljer\nDeves hydrauliska hissar o lyftare\nVarunamn: Deves\nAntal anstäUda: 85\nÅrsomsättning: 11000 000\nAktiekapital: 150 000\nVerkst dir: Fabr Algot Viebke\nEtableringsår: 1956.\n\nHANÖ-PRODUKTER, AB\n\nPnr 290 51\n\nHällevik, Box 18. Tel 0456-525 00.\nBankgiro 37-2665. Postgiro 133262\nVerksamhet: Säljer färsk o rökt\nfisk. Speciellt lax o ål. Export med\negna tankvagnar till utlandet\nAntal anställda: 20\nÅrsomsättning: 8 000 000\nAktiekapital: 75 000\nVerkst dir: Hilbert Kullberg\nEtableringsår: 1906.\n\nCATZY PRODUKTER, AB\n\nPnr 25013\n\nHelsingborg 13, Pack. Tel\n042-12 01 40. Postgiro 162357-8\nVerksamhet: Kosmetiska preparat\nför hår- o hudvård\nAktiekapital: 100 000\nVerkst dir. Viktor Danielson\nEtableringsår: 1947.\n\nSVENSKA SHELL, AB\n\nPnr 104 32\n\nStockholm 19, Birger Jarlsg 64.\nFack. Tel 22 86 20, riks\n08-22 83 40. Postgiro 1450-6. Tga\nShell. Telex 1360 SHELL S\nVerksamhet: Säljer motorbränslen,\nfotogen, eldningsoljor, smörjmedel,\nasfalt- o kemiska produkter samt\npetroleumgas\n\nFörsäljningskontor: Göteborg 2,\nKungsg 18. Fack. Tel 031-17 44 20.\nSolna, Industriv 20. Fack, Sthlm\n19. Tel 08-83 03 20\n\nÖrnsköldsvik, Nyg 20. Fack. Tel\n0660-100 20\n\nKemiska produkter: Solna,\nVire-bergsv 19. Fack, Sthlm 19. Tel\n08-98 0300\n\nShellgas: Solna, Industriv 20. Fack,\nSthlm 19. Tel 08-83 03 20\nAntal anställda: 1 600\nÅrsomsättning: 1294 000 000\nAktiekapital: 100 000 000\nStyrelse: Prof Sune Carlson, dir\nH M C van Oosterzee, dir Tage\nUtter\n\nVerkst dir: H M C van Oosterzee\nEtableringsår: 1912.\n\nSVENSKA SIDEN.\nVÄVERIET, AB\n\nse Mitex Glasfiber AB.\n\nSVENSKA AB SIG\nFÖRPACKNINGSMASKINER\n\nPnr 102 73\n\nStockholm 9, Box 9184. Tel\n08-84 3611, 84 3612. Bankgiro\n56-3476. Postgiro 250943.\nTelex 10519 HAWASIG S\nVerksamhet: Agenturaffär i\nförpackningsmaskiner\nAktiekapital: 10 000\nEtableringsån 1944.\n\nSVENSKA SI KA.\nPRODUKTER, AB\n\nPnr 170 23\n\nBarkarby. Tel 08-36 26 40.\nBankgiro 333-2046. Postgiro 251078-2.\nTga Sikaproduct. Telex 74215\nVerksamhet: Tillverkning o\nförsäljning av cement- o betongtillsatser\nsamt material för bultfästning,\nfogtätning, fuktisolering o\nytbehandling\nVarunamn: Sika\nAktiekapital: 600 000\nVerkst dir: Kai Precht\nFörsäljn-chef: Bengt Westerholm\nFabr-chef: Heinz Pfister\nEtableringsår: 1950.\n\nSVENSKA SILIKAVERKEN\n\nFabriker: Animskog, Köping\nFörsäljningskontor: 114 40\nStockholm, Nybrog 53. Tel 08-63 57 55.\nTelex 19956\n\nVerksamhet: Tillverkar från egna\nfyndigheter av kvarts o kvartsit\neldfasta massor o cement, bl a\nstampmassor för induktionsugnar,\nskänkstampmassor, sprutmassor,\nkvarts o kvartsitmjöl. Gjut-,\nstamp-o sprutmassor på chamotte o\naloxidmaterialbas. Svensk\nensamrepresentant för.Veitscher\nMagne-sitwerke A G, Österrike\nChef: Bergsing Lars Setterberg\nEtableringsår: 1902.\n\nSVENSKA SKOMASKIN.\nIMPORTEN, AB\n\nPnr 21153\n\nMalmö, Friis g 12. Tel 040-12 44 85.\nBankgiro 348-2965. Postgiro\n14123-4. Tga Skomaskinimport\n\nVerksamhet: Skofabriks- o\nsko-makerimaskiner samt delar därtill,\nskomakeriförnödenheter\nAktiekapital: 11300\nVerkst dir: P Wallin\nEtableringsår. 1927.\n\nSVENSKA\nSKUM-SLÄCKNINGS AB\n\nPnr 442 00\n\nKungälv, Trollhättev. Box 32. Tel\n0303-114 35. Bankgiro 50-5744.\n\nPostgiro 55638. Tga Skumab.\nTelex 10781 SKUMAB S\nVerksamhet:\nSkumsläckningsut-rustningar\n\nMarinavdelning \"Kogge\": 416 57\n\nGöteborg, Nobelg 21. Tel\n031-19 60 21. Tga Ritoff\nAntal anställda: 35\nAktiekapital: 215 000\nVerkst dir: Mikael Jahn\nEtableringsår: 1933.",
    "structured": {
        "1": {
            "company_name": "HAGA BLECK. & PLÄT. SLAGERI AB",
            "pnr": "411 22",
            "address": "Göteborg C, Husarg 42",
            "phone_number": "031-1059 40, 10 59 41",
            "postgiro": "42655",
            "activity": "Rostfria inredningar o byggnadsplåtslageri",
            "employees": 30,
            "annual_turnover": 950000,
            "capital": 25000,
            "key_personnel": [
                {
                    "name": "Henry Hj Johanson",
                    "position": "Ägare o chef"
                }
            ],
            "establishment_year": 1961
        },
        "2": {
            "company_name": "ARY STÅLMOBLER AB",
            "pnr": "380 43",
            "address": "Örsjö, Box 79",
            "phone_number": "0481-202 00",
            "bankgiro": "856-1623",
            "postgiro": "570121-4",
            "activity": "Tillverkar kontors- o verkstadsstolar, kantin-, hotell-, restaurant-, cafeteria- o skolmöbler. Utför legoarbeten i svetsade rörkonstruktioner",
            "employees": 36,
            "annual_turnover": 3500000,
            "capital": 50000,
            "key_personnel": [
                {
                    "name": "Edgar Oiangen",
                    "position": "Chef"
                }
            ],
            "establishment_year": 1960
        },
        "3": {
            "company_name": "AS MEKANISKA VERK-STAD, AB",
            "pnr": "330 10",
            "address": "Bredaryd, Västboås",
            "phone_number": "0371-700 81",
            "bankgiro": "142-7582",
            "postgiro": "387943-4",
            "activity": "Formsprutning, industriartiklar, gardin- o biltillbehör. Verktygsavdelning",
            "capital": 10000,
            "key_personnel": [
                {
                    "name": "B A H Wilhelmsson",
                    "position": "Styrelse"
                },
                {
                    "name": "E M Wilhelmsson",
                    "position": "Styrelse"
                }
            ],
            "establishment_year": 1948
        },
        "4": {
            "company_name": "SVENSK SJÖFARTS TIDNING",
            "pnr": "400 14",
            "address": "Göteborg 53, Kungsportsavenyn 1. Box 53090",
            "phone_number": "031-17 85 40",
            "bankgiro": "420-5233",
            "postgiro": "41114-0",
            "telex": "20746 SWESHIP S",
            "activity": "Facktidskrift för sjöfart, rederi- o varvsnäring samt närliggande områden"
        },
        "employees": 10,
        "annual_turnover": 1900000,
        "key_personnel": [
            {
                "name": "Folke Hallberg",
                "position": "Firmatecknare"
            },
            {
                "name": "Gustav Johnson",
                "position": "Firmatecknare"
            }
        ],
        "establishment_year": 1949,
        "5": {
            "company_name": "SVENSK SKALEX, AB",
            "pnr": "686 00",
            "address": "Sunne, Verkstadsg 5. Box 161",
            "phone_number": "0565-11130",
            "postgiro": "6086-3",
            "activity": "Tillverkar formluckor för betongformar"
        },
        "capital": 15000
    }
}