{
    "original": "UNELKO AB\n\nPnr 212 25\n\nMalmö, A gatan 8. Tel 040-9358 20.\nBankgiro 641-3652. Postgiro\n3844 5-3. Tga Unelkab\nVerksamhet: Engrosförsäljning av\nelektrisk installationsmateriel\nFilialer: 421 21 Västra Frölunda,\nBox48. Tel 031-45 08 10\n38100 Kalmar, Södra v 11. Tel\n0480-282 20\nAktiekapital: 500 000\nVerkst dir: Hugo Johansson\nEtableringsår: 1917.\n\nREMBO SAND AB\n\nPnr 77400\n\nAvesta, Rembo. Tel 0226-220 50,\n22051. Bankgiro 794-0265.\nPostgiro 363906-9\n\nVerksamhet: Tillverkar\nfabriksbetong, murbruk o stenmaterial\nAntal anstäUda: 30\nÅrsomsättning: 3 000000\nAktiekapital: 500000\nVerkst dir: Ing Oscar Hyttfors\nEtableringsår: 1948.\n\nREMINGTON RAND,\nSPERRY RAND AB\n\nPnr 10381\n\nStockholm 7, Kungsg 2. Box 7024.\nTel 08-22 25 60. Telex 1440\nREMRAND S\n\nVerksamhet: Säljer kontorsmaskiner\no övrig kontorsutrustning\nVarunamn: Kaidex, Remington,\nSkandex, Verifax\nChef: Dir Olle Nordblom\nSe vidare Sperry Rand AB.\n\nREMINGTON, SPERRY RAND\nAB\n\nPnr 103 81\n\nStockholm 7, Kungsg 2. Box 7024.\nTel 08-22 25 60. Telex 1440\nREMRAND S\n\nVerksamhet: Säljer elektriska\nrakapparater, väckarur, väggur,\ntorkhuvar\n\nVarunamn: Remington\n\nChef: Dir John HjSiden (Köpenhamn)\n\nSe vidare Sperry Rand AB.\n\nREMKIL, AB\n\nPnr 577 00\n\nHultsfred, Box 145. Tel\n0495-120 40. Bankgiro 85-7509. Postgiro\n165725-3\n\nVerksamhet: Tillverkar\nkilremsski-vor\n\nAntal anstäUda: 40\nÅrsomsättning: 2 000000\nAküekapüal: 100 000\nVerkst dir. Ing I Sjölander\nEtableringsår: 1956.\n\nREMOTE CONTROL\nSWEDEN LTD AB\n\nPnr 79107\n\nFalun 7, Box 60120. Tel\n023-33810, 33811. Bankgiro 745-8011.\nPostgiro 508344-9. Telex 84062.\nTga Recotrol\n\nVerksamhet: Tillverkar o säljer\nutrustning för fjärrmanövrering\nAntal anstäUda: 15\nÅrsomsättning: 2 000 000\nAktiekapital: 5 000\nChef: Ing Bror Olsson\nEtableringsår: 1961.\n\nVÄROBACKAFISK, AB\n\nPnr 430 22\n\nVäröbacka, Box 7. Tel 0340-60012,\n60112. Bankgiro 354-8997.\nPostgiro 81197-6\n\nVerksamhet: Säljer fisk i parti, i\nhuvudsak sill av olika storlekar\nAntal anställda: 10\nÅrsomsättning: 3 000 000\nAktiekapital: 60 000\nVerkst dir: Boris Wiman\nEtableringsån 1918.\n\nSVENSKA UNITHERM AB\n\nPnr 11138\n\nStockholm, Johannesg 2. Tel 08-\n\n20 97 73, 20 97 74. Bankgiro\n670-8960. Postgiro 504540-6. Tga\nUni-therm\n\nVerksamhet: Säljer Unitherm\nbrandskyddsfärg för stålkonstruktioner.\nAgent för Spies, Hecker &amp; Co, Köln\nVarunamn: Unitherm\nAntal anställda: 3\nAktiekapital: 30 000\nStyrelse: Dir Gustav Lindquist\n(ordf), målarmäst Bertil Dahlquist,\ning Erik Ström\n\nVerkst dir: Målarmäst Bertil\nDahlquist\n\nEtableringsår: 1968.\n\nSVENSKA\nUTBILDNINGS-FÖRLAGET LIBER AB\n\nPnr 104 22\n\nStockholm 22, Norr Mälarstrand 24.\nFack. Tel 08-54 10 20. Bankgiro\n730-5162. Postgiro 52421-5\nVerksamhet: Bokförlag med\nhuvudsakligen pedagogisk litteratur\nAntal anställda: 200\nÅrsomsättning: 30 000 000\nAktiekapital: 2 000000\nVerkst dir: Civiling Lennart Öster\nEtableringsår: 1969.\n\nAND\n\nVerksamhet: Elinstallationer för\nkraft o belysning av alla slag\nAntal anställda: 74\nÅrsomsättning: 3 300 000\nAktiekapital: 85 000\nÄgare o chef: Ing Karl-Erik\nEriksson\n\nEtableringsår: 1927.\n\nANDERSSONS FINSLIPERI, AB\n\nSlip o mek\n\nPnr 930 31\n\nKlemensnäs. Tel 0910-30169.\nBankgiro 37-0819. Postgiro\n467797\n\nVerksamhet: Utför slipning,\nvärmebehandling, fräsning, svarvning,\njigg- o arborrning. Tillverkar\nspecialverktyg, jiggar, fixturer,\nhårdmetallfräsar o saxstèl samt\nflerspindliga borr hus,\ntransportanordningar o specialmaskiner för\nwallboardindustrin etc. Rit- o\nkonstruktionsavdelning\nAntal anställda: 23\nAktiekapital: 10 000\nVerkst dir L H Andersson\nIng: G Lundström\nVerkmäst: T Vågstedt\nEtableringsår: 1952.\n\nGOLVBOLAGET I BORÄS AB\n\nPnr 50247\n\nBorås, Källbäcksrydsg 6. Tel\n033-10 2175. Bankgiro 531-2384.\nPostgiro 477832-0\n\nVerksamhet: Säljer heltäckande\nmattor, plastmattor, parkett\nAntal anställda: 28\nÅrsomsättning: 2 500 000\nAktiekapital: 15 000\nVerkst dir. Nils Eriksson\nEtableringsår: 1955.\n\nSTENA AB\n\nPnr 403 17\n\nGöteborg 2, Kaserntorget 6. Box\n2507. Tel 031-17 35 40, 17 81 80.\nBankgiro 84-8033. Postgiro 46036.\nTga Stenametall, Stenaship.\nTelex 2388, 20860, 20986\nVerksamhet: Säljer metaller i tack-,\nor, järn- o metallskrot, tackjärn,\nferrolegeringar, järnplåt o\nbleckplåt. Tillverkar o exporterar\nrostfria rör\n\nRederi: Färjeförbindelser mellan\nSkandinavien o Tyskland.\nKryssningar\n\nAntal anställda: 800\nÅrsomsättning: 173 000 000\nAktiekapital: 1000 000\nStyrelse: Adv Dag Magnusson (ordf),\nskeppsredare Sten A Olsson, dir\nNils Berg, dir Helge Olofsson,\nekonomichef Wolfgang Neumann\nVerkst dir: Nils Berg\nEtableringsår 1939.\n\nHALMSTADS JÄRNVERKS AB\n\nPnr 301 03\n\nHalmstad 1, Stationsg 55. Box 119.\nTel 035-11 84 70. Bankgiro 423-5334.\nPostgiro 30537-5. Tga Welbond.\nTelex 38081\n\nVerksamhet: Martin- o\nelektrostål-verk, valsverk,\narmeringsverkstä-der. Tillverkning: armeringsstål,\nspänn- o fjäderståltråd, -tråd, -lina,\ninläggningsfärdig armering,\narme-ringsnät, spiralbyglar, stöd,\narme-ringsringar o annan\narmeringsmanu-faktur\n\nAnneringsverkstäder:\n\nJärna (Södertälje). Tel 0755-708 40\nGöteborg. Tel 031-520170\nUppåkra (Malmö). Tel 040-46 50 30\nLinköping. Tel 013-15 9300\nVarunamn: Halmstadstål\nAntal anställda: 1100\nÅrsomsättning: 175 000000\nAktiekapital: 18 000 000\nVerkst dir. Disp Erik Malmfors\nEtableringsår: 1916.\n\nHALMSTADS MURBRUKS.\nFABRIK, AB\n\nPnr 300 02\n\nHalmstad 2, Box 2012. Tel\n035-112143, 1200 20. Bankgiro\n15-3360. Postgiro 83035\n\nVerksamhet: Cementvaror, betong,\n\nmurbruk, grus, makadam\n\nAntal anställda: 35\n\nÅrsomsättning: 2 400 000\n\nAktiekapital: 35 000\n\nVerkst dir: Disp Birger Stael v\n\nHolstein\n\nEtableringsår: 1939.\n\nHALMSTADS PRESS.\nVERKTYG AB\n\nPnr 302 50\n\nHalmstad, Larsfridsv 18. Tel\n035-116188. Bankgiro 423-9992.\nPostgiro 383934-7\n\nVerksamhet: Tillverkar verktyg,\npressverktyg, jiggar o fixturer,\nspecialmaskiner\nAktiekapital: 5 000\nVerkst dir: Hans Olsson\nEtableringsår: 1945.\n\nHALMSTADS SNICKERI.\nFABRIK, AB\n\nPnr 30103\n\nHalmstad 1, Box 124. Amiralsg 2.\nTel 035-1109 46, 11 03 75. Bankgiro\n423-5362. Postgiro 263915-1\nVerksamhet: Tillverkar\nfönstersnickerier\nAntal anställda: 25\nÅrsomsättning: 1500 000\n.Aktiekapital: 10 000\nVerkst dir: Olof Blänning\nEtableringsår: 1926.\n\nTUR\n\nÅrsomsättning: 800000\nÄgare o chef: Mats Birgerson\nEtableringsår: 1933.\n\nOLSSON VINER AB, MARTIN\n\nPnr 100 28\n\nStockholm 49, Box 49005.\nIgeldammsg 22. Tel 08-54 12 80. Post-\n\ngiro 54560-8. Tga Martinolskaffe\nVerksamhet: Vin o sprit i parti\nAntal anställda: 5\nÅrsomsättning: 2 300 000\nAktiekapital: 10 000\nVerkst dir: Gunnar Oldmark\nEtableringsår: 1969.\n\nOLSSON, MASKIN.\nFIRMAN N E\n\nPnr 11636\n\nStockholm, Erstag 32-34. Tel\n08-23 40 05. Bankgiro 73-2388.\nPostgiro 257703\nVerksamhet: Tillverkar o säljer\nstationära o transportabla el-,\ngasol- o oljeeldade\nhögtrycksångpannor, helautomatiska\nbyggång-pannor\n\nVerkstad: Fittja, Alby Gård. Tel\n08-71073 80\n\nVarunamn: Loxmobil, Ang-Janne,\nAng-Jenny\nAntal anställda: 15\nÅrsomsättning: 3 000 000\nÄgare o chef: N E Olsson\nEtableringsår: 1953.",
    "structured": {
        "0": {
            "company_name": "UNELKO AB",
            "pnr": "212 25",
            "address": "Malmö, A gatan 8",
            "phone_number": "040-9358 20",
            "bank_details": {
                "bankgiro": "641-3652",
                "postgiro": "3844 5-3"
            },
            "activity": "Engrosförsäljning av elektrisk installationsmateriel",
            "establishment_year": 1917
        },
        "1": {
            "company_name": "REMBO SAND AB",
            "pnr": "77400",
            "address": "Avesta, Rembo",
            "phone_number": "0226-220 50, 22051",
            "bank_details": {
                "bankgiro": "794-0265",
                "postgiro": "363906-9"
            },
            "activity": "Tillverkar fabriksbetong, murbruk o stenmaterial",
            "employees": 30,
            "annual_turnover": 3000000,
            "capital": 500000,
            "establishment_year": 1948
        },
        "2": {
            "company_name": "REMINGTON RAND, SPERRY RAND AB",
            "pnr": "10381",
            "address": "Stockholm 7, Kungsg 2, Box 7024",
            "phone_number": "08-22 25 60",
            "telex": "1440 REMRAND S",
            "activity": "Säljer kontorsmaskiner o övrig kontorsutrustning",
            "varunamn": "Kaidex, Remington, Skandex, Verifax",
            "key_personnel": [
                {
                    "name": "Dir Olle Nordblom",
                    "position": "Chef"
                }
            ]
        },
        "3": {
            "company_name": "REMINGTON, SPERRY RAND AB",
            "pnr": "103 81",
            "address": "Stockholm 7, Kungsg 2, Box 7024",
            "phone_number": "08-22 25 60",
            "telex": "1440 REMRAND S",
            "activity": "Säljer elektriska rakapparater, väckarur, väggur, torkhuvar",
            "varunamn": "Remington",
            "key_personnel": [
                {
                    "name": "Dir John HjSiden",
                    "position": "Chef"
                }
            ]
        },
        "4": {
            "company_name": "REMKIL, AB",
            "pnr": "577 00",
            "address": "Hultsfred, Box 145",
            "phone_number": "0495-120 40",
            "bank_details": {
                "bankgiro": "85-7509",
                "postgiro": "165725-3"
            },
            "activity": "Tillverkar kilremsski-vor",
            "employees": 40,
            "annual_turnover": 2000000,
            "capital": 100000,
            "key_personnel": [
                {
                    "name": "Ing I Sjölander",
                    "position": "Verkst dir"
                }
            ],
            "establishment_year": 1956
        },
        "5": {
            "company_name": "REMOTE CONTROL SWEDEN LTD AB",
            "pnr": "79107",
            "address": "Falun 7, Box 60120",
            "phone_number": "023-33810, 33811",
            "bank_details": {
                "bankgiro": "745-8011",
                "postgiro": "508344-9"
            },
            "telex": "84062 Tga Recotrol",
            "activity": "Tillverkar o säljer utrustning för fjärrmanövrering",
            "employees": 15,
            "annual_turnover": 2000000,
            "capital": 5000,
            "key_personnel": [
                {
                    "name": "Ing Bror Olsson",
                    "position": "Chef"
                }
            ],
            "establishment_year": 1961
        },
        "6": {
            "company_name": "VÄROBACKAFISK, AB",
            "pnr": "430 22",
            "address": "Väröbacka, Box 7",
            "phone_number": "0340-60012, 60112",
            "bank_details": {
                "bankgiro": "354-8997",
                "postgiro": "81197-6"
            },
            "activity": "Säljer fisk i parti, i huvudsak sill av olika storlekar",
            "employees": 10,
            "annual_turnover": 3000000,
            "capital": 60000,
            "key_personnel": [
                {
                    "name": "Boris Wiman",
                    "position": "Verkst dir"
                }
            ],
            "establishment_year": 1918
        },
        "7": {
            "company_name": "SVENSKA UNITHERM AB",
            "pnr": "11138",
            "address": "Stockholm, Johannesg 2",
            "phone_number": "08-20 97 73, 20 97 74",
            "bank_details": {
                "bankgiro": "670-8960",
                "postgiro": "504540-6"
            },
            "telex": "Uni-therm",
            "activity": "Säljer Unitherm brandskyddsfärg för stålkonstruktioner. Agent för Spies, Hecker & Co, Köln",
            "employees": 3,
            "capital": 30000,
            "key_personnel": [
                {
                    "name": "Dir Gustav Lindquist",
                    "position": "Styrelse"
                },
                {
                    "name": "målarmäst Bertil Dahlquist",
                    "position": "Styrelse"
                },
                {
                    "name": "ing Erik Ström",
                    "position": "Styrelse"
                },
                {
                    "name": "Målarmäst Bertil Dahlquist",
                    "position": "Verkst dir"
                }
            ],
            "establishment_year": 1968
        },
        "8": {
            "company_name": "SVENSKA UTBILDNINGS-FÖRLAGET LIBER AB",
            "pnr": "104 22",
            "address": "Stockholm 22, Norr Mälarstrand 24",
            "phone_number": "08-54 10 20",
            "bank_details": {
                "bankgiro": "730-5162",
                "postgiro": "52421-5"
            },
            "activity": "Bokförlag med huvudsakligen pedagogisk litteratur",
            "employees": 200,
            "annual_turnover": 30000000,
            "capital": 2000000,
            "key_personnel": [
                {
                    "name": "Civiling Lennart Öster",
                    "position": "Verkst dir"
                }
            ],
            "establishment_year": 1969
        },
        "9": {
            "company_name": "ANDERSSONS FINSLIPERI, AB",
            "pnr": "930 31",
            "address": "Klemensnäs",
            "phone_number": "0910-30169",
            "bank_details": {
                "bankgiro": "37-0819",
                "postgiro": "467797"
            },
            "activity": "Utför slipning, värmebehandling, fräsning, svarvning, jigg- o arborrning. Tillverkar specialverktyg, jiggar, fixturer, hårdmetallfräsar o saxstèl samt flerspindliga borr hus, transportanordningar o specialmaskiner för wallboardindustrin etc. Rit- o konstruktionsavdelning",
            "employees": 23,
            "capital": 10000,
            "key_personnel": [
                {
                    "name": "L H Andersson",
                    "position": "Verkst dir"
                },
                {
                    "name": "G Lundström",
                    "position": "Ing"
                },
                {
                    "name": "T Vågstedt",
                    "position": "Verkmäst"
                }
            ],
            "establishment_year": 1952
        },
        "10": {
            "company_name": "GOLVBOLAGET I BORÄS AB",
            "pnr": "50247",
            "address": "Borås, Källbäcksrydsg 6",
            "phone_number": "033-10 2175",
            "bank_details": {
                "bankgiro": "531-2384",
                "postgiro": "477832-0"
            },
            "activity": "Säljer heltäckande mattor, plastmattor, parkett",
            "employees": 28,
            "annual_turnover": 2500000,
            "capital": 15000,
            "key_personnel": [
                {
                    "name": "Nils Eriksson",
                    "position": "Verkst dir"
                }
            ],
            "establishment_year": 1955
        },
        "11": {
            "company_name": "STENA AB",
            "pnr": "403 17",
            "address": "Göteborg 2, Kaserntorget 6, Box 2507",
            "phone_number": "031-17 35 40, 17 81 80",
            "bank_details": {
                "bankgiro": "84-8033",
                "postgiro": "46036"
            },
            "telex": "2388, 20860, 20986",
            "activity": "Säljer metaller i tack- o järn- o metallskrot, tackjärn, ferrolegeringar, järnplåt o bleckplåt. Tillverkar o exporterar rostfria rör. Rederi: Färjeförbindelser mellan Skandinavien o Tyskland. Kryssningar",
            "employees": 800,
            "annual_turnover": 173000000,
            "capital": 1000000,
            "key_personnel": [
                {
                    "name": "Adv Dag Magnusson",
                    "position": "Styrelse"
                },
                {
                    "name": "skeppsredare Sten A Olsson",
                    "position": "Styrelse"
                },
                {
                    "name": "dir Nils Berg",
                    "position": "Styrelse"
                },
                {
                    "name": "dir Helge Olofsson",
                    "position": "Styrelse"
                },
                {
                    "name": "ekonomichef Wolfgang Neumann",
                    "position": "Styrelse"
                },
                {
                    "name": "Nils Berg",
                    "position": "Verkst dir"
                }
            ],
            "establishment_year": 1939
        },
        "12": {
            "company_name": "HALMSTADS JÄRNVERKS AB",
            "pnr": "301 03",
            "address": "Halmstad 1, Stationsg 55, Box 119",
            "phone_number": "035-11 84 70",
            "bank_details": {
                "bankgiro": "423-5334",
                "postgiro": "30537-5"
            },
            "telex": "38081",
            "activity": "Martin- o elektrostål-verk, valsverk, armeringsverkstä-der. Tillverkning: armeringsstål, spänn- o fjäderståltråd, -tråd, -lina, inläggningsfärdig armering, arme-ringsnät, spiralbyglar, stöd, arme-ringsringar o annan armeringsmanu-faktur. Anneringsverkstäder: Järna (Södertälje), Göteborg, Uppåkra (Malmö), Linköping",
            "activity_second": "Halmstadstål",
            "employees": 1100,
            "annual_turnover": 175000000,
            "capital": 18000000,
            "key_personnel": [
                {
                    "name": "Disp Erik Malmfors",
                    "position": "Verkst dir"
                }
            ],
            "establishment_year": 1916
        },
        "13": {
            "company_name": "HALMSTADS MURBRUKS. FABRIK, AB",
            "pnr": "300 02",
            "address": "Halmstad 2, Box 2012",
            "phone_number": "035-112143, 1200 20",
            "bank_details": {
                "bankgiro": "15-3360",
                "postgiro": "83035"
            },
            "activity": "Cementvaror, betong, murbruk, grus, makadam",
            "employees": 35,
            "annual_turnover": 2400000,
            "capital": 35000,
            "key_personnel": [
                {
                    "name": "Disp Birger Stael v Holstein",
                    "position": "Verkst dir"
                }
            ],
            "establishment_year": 1939
        },
        "14": {
            "company_name": "HALMSTADS PRESS. VERKTYG AB",
            "pnr": "302 50",
            "address": "Halmstad, Larsfridsv 18",
            "phone_number": "035-116188",
            "bank_details": {
                "bankgiro": "423-9992",
                "postgiro": "383934-7"
            },
            "activity": "Tillverkar verktyg, pressverktyg, jiggar o fixturer, specialmaskiner",
            "capital": 5000,
            "key_personnel": [
                {
                    "name": "Hans Olsson",
                    "position": "Verkst dir"
                }
            ],
            "establishment_year": 1945
        },
        "15": {
            "company_name": "HALMSTADS SNICKERI. FABRIK, AB",
            "pnr": "30103",
            "address": "Halmstad 1, Box 124, Amiralsg 2",
            "phone_number": "035-1109 46, 11 03 75",
            "bank_details": {
                "bankgiro": "423-5362",
                "postgiro": "263915-1"
            },
            "activity": "Tillverkar fönstersnickerier",
            "employees": 25,
            "annual_turnover": 1500000,
            "capital": 10000,
            "key_personnel": [
                {
                    "name": "Olof Blänning",
                    "position": "Verkst dir"
                }
            ],
            "establishment_year": 1926
        },
        "16": {
            "company_name": "OLSSON VINER AB, MARTIN",
            "pnr": "100 28",
            "address": "Stockholm 49, Box 49005, Igeldammsg 22",
            "phone_number": "08-54 12 80",
            "postgiro": "54560-8",
            "activity": "Vin o sprit i parti",
            "employees": 5,
            "annual_turnover": 2300000,
            "capital": 10000,
            "key_personnel": [
                {
                    "name": "Gunnar Oldmark",
                    "position": "Verkst dir"
                }
            ],
            "establishment_year": 1969
        },
        "17": {
            "company_name": "OLSSON, MASKIN. FIRMAN N E",
            "pnr": "11636",
            "address": "Stockholm, Erstag 32-34",
            "phone_number": "08-23 40 05",
            "bank_details": {
                "bankgiro": "73-2388",
                "postgiro": "257703"
            },
            "activity": "Tillverkar o säljer stationära o transportabla el-, gasol- o oljeeldade högtrycksångpannor, helautomatiska byggång-pannor. Verkstad: Fittja, Alby Gård",
            "varunamn": "Loxmobil, Ang-Janne, Ang-Jenny",
            "employees": 15,
            "annual_turnover": 3000000,
            "key_personnel": [
                {
                    "name": "N E Olsson",
                    "position": "Ägare o chef"
                }
            ],
            "establishment_year": 1953
        }
    }
}