{
    "original": "THOMAS &amp; CO AB, W\n\nPnr 19500\n\nMärsta, Steninge. Tel 0 760-52160.\nPostgiro 58540. TgaThomasco\nVerksamhet: Engrosförsäljning av\nheltäckningsmattor o nålfilt Cikalon\nAktiekapital: 200 000\nVerkst dir: Olle Hammarström\nEtableringsår: 1935.\n\nTHOMÉES\nLANTBRUKS-MASKINER AB\n\nPnr 20110\n\nMalmö 1, Engelbrektsg 11. Pack.\nTel 040-707 60. Bankgiro 260-7851.\nPostgiro 630110-5. Tga Edwin.\nTelex 3104 EDWIN S\nVerksamhet: Tillverkar o säljer\nreservdelar o tillbehör till\nlantbruksmaskiner\n\nAntal anstäUda: 25\nAktiekapital: 250 000\nStyrelse: Dir Per Hjalmar\nFagerholm, adv Ake Wettermark\nVerkst dir Sven Broman\nTekn chef: Ing G Martinsson\nFörsäljn-chef: B O Engblom\nEtableringsår: 1963.\n\nWICKBERG &amp; LIF AB\n\nPnr 81106\n\nSandviken 6, Box 163. Klangtorget.\nTel 026-25 79 45. Bankgiro 78-8757.\nPostgiro 82 645\n\nVerksamhet: Rörentreprenörer\nAntal anställda: 25\nÅrsomsättning: 2 400 000\nAktiekapital: 50 000\nVerkst din Torsten Björklund.\n\nWICKBERG &amp; SÖNER, AB C G\n\nPnr 85105\n\nSundsvall 1, Sjög 4. Box 309. Tel\n060-1141 21. Postgiro 137600.\nTelex 71011. Tga Wickberg\nVerksamhet: Skeppsmäkleri,\nspedition o befraktning\nAktiekapital: 60 000\nVerkst dir: G Hillstedt\nEtableringsån 1879.\n\nTRYGG-HANSA\n\nKoncernen omfattar\nTrygg ömsesidig livförsäkring;\nHansa ömsesidig sakförsäkring;\nSjöförsäkringsaktiebolaget Hansa;\nAterförsäkringsbolaget Hansa.\nSe dessa bolag.\n\nTRYGG-PRODUKT, AB\n\nPnr 731 01\n\nKöping 1, Tunadalsg. Fack. Tel\n0221-135 80. Bankgiro 810-2518.\nPostgiro 30601. Tga Tryggbolaget\nVerksamhet: Tillverkar TT\nfruktträds- o trädgårdssprutor, motor- o\nhanddrivna , ürje torkställ\nVarunamn: TT\nAntal anstäUda: 30\nAktiekapital: 200 000\nVerkst dir: Disp Arne Bäckström\nEtableringsår 1928\nBolaget fungerar endast som\ntillverknings- o inköpsföretag till Orje\nJernmanufaktur, Köping.\n\nTHRYSINS MEK VERKSTAD,\nAB L\n\nPnr 590 40\n\nKisa, Storg. Tel 0494-106 85,\n108 31. Bankgiro 12-9404. Postgiro\n57183. Tga Gyrosko\nVerksamhet: Tillverkar start- o\nsäkerhetskopplingar för\nkraftöverföring, centrifugal- o lamellkopplingar,\n\"Gyros\", cylindriska kugghjul,\nkedjehjul. Utför kuggfräsning, mek\narbeten enl ritn o önskemål\nVarunamn: Gyros\nAktiekapital: 93 000\nVerkst dir: S Thrysin\nEtableringsår: 1934.\n\nHUSVAGNAR, AB\n\nPnr 665 00\n\nKil. Tel 0554-110 50. Bankgiro\n881-3131. Postgiro 160153-3\nVerksamhet: Tillverkar o säljer\nmanskaps-, kontors- o\nförläggningsvagnar, butiks- o skollokaler,\nbarndaghem samt transportabla\nbyggnadsenheter\nAntal anställda: 180\nÅrsomsättning: 21000 000\nAktiekapital: 2 000 000\nVerkst dir: Göran Ohlson\nEtableringsår: 1952\nOmbildat till aktiebolag 1957.\n\nHUSVAGN-SVENSSON AB\n\nPnr 53101\n\nLidköping 1, Box 407. Skarag 67.\nTel 0510-222 70. Bankgiro\n346-7024. Postgiro 563599-0\nVerksamhet: Säljer husvagnar\nAntal anställda: 20\nÅrsomsättning: 9 000 000\nAktiekapital: 25 000\nVerkst dir. Sven Ake Svensson\nEtableringsår: 1963.\n\nLüNNROTHS ELKONSULT AB\n\nPnr 183 54\n\nTäby, Eskaderv 36. Tel\n08-756 0 2 80. Bankgiro 62-5697.\nPostgiro 31919\n\nVerksamhet: Konsulterande inom\nel-branschen. Hissbesiktningar\nAntal anställda: 9\nÅrsomsättning: 380 000 ’\nAktiekapital: 10 000\nVerkst dir: K E Lönnroth\nEtableringsår: 1963.\n\nEKDAHLS MALERIFIRMA AB\n\nPnr 21363\n\nMalmö, Silverviksg 2. Tel\n040-94 63 50. Bankgiro 100-0010.\nPostgiro 148068-0\n\nVerksamhet: Måleriarbeten för\nnybyggnader samt reparationsmåleri\n.Antal anställda: 60\nÅrsomsättning: 2 500 000\nAktiekapital: 140 000\nVerkst dir: Målarmäst Gunnar Ekdahl\nEtableringsår 1938.\n\nVISUELL PLANERING. AB\n\nPnr 402 32\n\nGöteborg 7, Andra Långg 4 B.\nBox 7112. Tel 031-24 40 80,\n24 30 28. Bankgiro 799-8180.\nPostgiro 720055-3\n\nVerksamhet: Tillverkar o säljer\nmateriel för industriell lokal- o\nproduktionsplanering\nAntal anställda: 8\nAktiekapital: 10 000\nVerkst dir: Ing R Blidnäs\nEtableringsån 1956.\n\nERI\n\nÄgare o chefer: Allan Eriksson,\nTage Skoog\nEtableringsår: 1950.\n\nERIKSSON &amp; STARKS\nMEKANISKA VERKSTAD, AB\n\nPnr 16130\n\nBromma, Ekbacksv 42. Tel\n08-25 6133, 25 94 66. Bankgiro\n575-1268. Postgiro 13429-6. Tga\nSvabolag\n\nVerksamhet: Utför mekaniska\narbeten samt tillverkar verktyg\nVarunamn: Result, Poensgen\nAntal anställda: 55\nÅrsomsättning: 5 000 000\nAktiekapital: 30 000\nVerkst dir: Pabr Herbert Johansson\nFörsäljn-chef: Anders Kindahl\nEtableringsår. 1914.\n\nERIKSSON &amp; SVÄRD,\nSÅGBOLAGET\n\nPnr 330 23\n\nSmålandsstenar, Malmg 25. Tel\n0371-305 33, 306 33. Bankgiro\n42-7665. Postgiro 378204-2\nVerksamhet: Tillverkar sparrar,\nbjälkar, bräder, plank, reglar o läkt\nAntal anställda: 6\nÅrsomsättning: 500 000\nChefer: Evert Eriksson, Hilding\nSvärd\n\nEtableringsår: 1951.\n\nAKEMA AB\n\nPnr 127 40\n\nSkärholmen, Stångholmsbacken 61.\nTel 08-7100930. Bankgiro\n630-7409. Postgiro 258200-5\nVerksamhet: Rullstolar o\nhandikapphjälpmedel\nAntal anställda: 15\nVerkst dir: Bengt Älmeby\nEtableringsår: 1969.\n\nTEREDO MASKIN AB\n\nPnr 111 57\n\nStockholm C, Sveav 13-15. Tel\n08-2407 50. Bankgiro 56-0019.\nPostgiro 51640. Tga Teredo\nVerksamhet: Säljer grävmaskiner,\nlastmaskiner o mobilkranar\nAntal anställda: 15\nAktiekapital: 240 000\nVerkst dir: Ing Henning Leonard\nWiderdal\n\nEtableringsår: 1959.",
    "structured": {
        "1": {
            "company_name": "THOMAS & CO AB",
            "pnr": "19500",
            "address": "Märsta, Steninge",
            "phone_number": "0760-52160",
            "postgiro": "58540",
            "activity": "Engrosförsäljning av heltäckningsmattor o nålfilt Cikalon",
            "capital": 200000,
            "key_personnel": [
                {
                    "name": "Olle Hammarström",
                    "position": "Verkst dir"
                }
            ],
            "establishment_year": 1935
        },
        "2": {
            "company_name": "THOMÉES LANTBRUKS-MASKINER AB",
            "pnr": "20110",
            "address": "Malmö 1, Engelbrektsg 11",
            "phone_number": "040-70760",
            "bank_details": {
                "bankgiro": "260-7851",
                "postgiro": "630110-5"
            },
            "activity": "Tillverkar o säljer reservdelar o tillbehör till lantbruksmaskiner",
            "employees": 25,
            "capital": 250000,
            "key_personnel": [
                {
                    "name": "Per Hjalmar Fagerholm",
                    "position": "Dir"
                },
                {
                    "name": "Ake Wettermark",
                    "position": "adv"
                },
                {
                    "name": "Sven Broman",
                    "position": "Verkst dir"
                },
                {
                    "name": "Ing G Martinsson",
                    "position": "Tekn chef"
                },
                {
                    "name": "B O Engblom",
                    "position": "Försäljn-chef"
                }
            ],
            "establishment_year": 1963
        },
        "3": {
            "company_name": "WICKBERG & LIF AB",
            "pnr": "81106",
            "address": "Sandviken 6, Box 163, Klangtorget",
            "phone_number": "026-257945",
            "bank_details": {
                "bankgiro": "78-8757",
                "postgiro": "82645"
            },
            "activity": "Rörentreprenörer",
            "employees": 25,
            "annual_turnover": 2400000,
            "capital": 50000,
            "key_personnel": [
                {
                    "name": "Torsten Björklund",
                    "position": "Verkst din"
                }
            ]
        },
        "4": {
            "company_name": "WICKBERG & SÖNER, AB C G",
            "pnr": "85105",
            "address": "Sundsvall 1, Sjög 4, Box 309",
            "phone_number": "060-114121",
            "postgiro": "137600",
            "activity": "Skeppsmäkleri, spedition o befraktning",
            "capital": 60000,
            "key_personnel": [
                {
                    "name": "G Hillstedt",
                    "position": "Verkst dir"
                }
            ],
            "establishment_year": 1879
        },
        "5": {
            "company_name": "TRYGG-PRODUKT, AB",
            "pnr": "73101",
            "address": "Köping 1, Tunadalsg.",
            "phone_number": "0221-13580",
            "bank_details": {
                "bankgiro": "810-2518",
                "postgiro": "30601"
            },
            "activity": "Tillverkar TT fruktträds- o trädgårdssprutor, motor- o handdrivna , ürje torkställ",
            "employees": 30,
            "capital": 200000,
            "key_personnel": [
                {
                    "name": "Disp Arne Bäckström",
                    "position": "Verkst dir"
                }
            ],
            "establishment_year": 1928
        },
        "6": {
            "company_name": "THRYSINS MEK VERKSTAD, AB L",
            "pnr": "59040",
            "address": "Kisa, Storg.",
            "phone_number": "0494-10685, 10831",
            "bank_details": {
                "bankgiro": "12-9404",
                "postgiro": "57183"
            },
            "activity": "Tillverkar start- o säkerhetskopplingar för kraftöverföring, centrifugal- o lamellkopplingar, Gyros, cylindriska kugghjul, kedjehjul. Utför kuggfräsning, mek arbeten enl ritn o önskemål",
            "capital": 93000,
            "key_personnel": [
                {
                    "name": "S Thrysin",
                    "position": "Verkst dir"
                }
            ],
            "establishment_year": 1934
        },
        "7": {
            "company_name": "HUSVAGNAR, AB",
            "pnr": "66500",
            "address": "Kil",
            "phone_number": "0554-11050",
            "bank_details": {
                "bankgiro": "881-3131",
                "postgiro": "160153-3"
            },
            "activity": "Tillverkar o säljer manskaps-, kontors- o förläggningsvagnar, butiks- o skollokaler, barndaghem samt transportabla byggnadsenheter",
            "employees": 180,
            "annual_turnover": 21000000,
            "capital": 2000000,
            "key_personnel": [
                {
                    "name": "Göran Ohlson",
                    "position": "Verkst dir"
                }
            ],
            "establishment_year": 1952
        },
        "8": {
            "company_name": "HUSVAGN-SVENSSON AB",
            "pnr": "53101",
            "address": "Lidköping 1, Box 407, Skarag 67",
            "phone_number": "0510-22270",
            "bank_details": {
                "bankgiro": "346-7024",
                "postgiro": "563599-0"
            },
            "activity": "Säljer husvagnar",
            "employees": 20,
            "annual_turnover": 9000000,
            "capital": 25000,
            "key_personnel": [
                {
                    "name": "Sven Ake Svensson",
                    "position": "Verkst dir"
                }
            ],
            "establishment_year": 1963
        },
        "9": {
            "company_name": "LüNNROTHS ELKONSULT AB",
            "pnr": "18354",
            "address": "Täby, Eskaderv 36",
            "phone_number": "087560280",
            "bank_details": {
                "bankgiro": "62-5697",
                "postgiro": "31919"
            },
            "activity": "Konsulterande inom el-branschen. Hissbesiktningar",
            "employees": 9,
            "annual_turnover": 380000,
            "capital": 10000,
            "key_personnel": [
                {
                    "name": "K E Lönnroth",
                    "position": "Verkst dir"
                }
            ],
            "establishment_year": 1963
        },
        "10": {
            "company_name": "EKDAHLS MALERIFIRMA AB",
            "pnr": "21363",
            "address": "Malmö, Silverviksg 2",
            "phone_number": "040946350",
            "bank_details": {
                "bankgiro": "100-0010",
                "postgiro": "148068-0"
            },
            "activity": "Måleriarbeten för nybyggnader samt reparationsmåleri",
            "employees": 60,
            "annual_turnover": 2500000,
            "capital": 140000,
            "key_personnel": [
                {
                    "name": "Målarmäst Gunnar Ekdahl",
                    "position": "Verkst dir"
                }
            ],
            "establishment_year": 1938
        },
        "11": {
            "company_name": "VISUELL PLANERING. AB",
            "pnr": "40232",
            "address": "Göteborg 7, Andra Långg 4 B, Box 7112",
            "phone_number": "031244080, 243028",
            "bank_details": {
                "bankgiro": "799-8180",
                "postgiro": "720055-3"
            },
            "activity": "Tillverkar o säljer materiel för industriell lokal- o produktionsplanering",
            "employees": 8,
            "capital": 10000,
            "key_personnel": [
                {
                    "name": "Ing R Blidnäs",
                    "position": "Verkst dir"
                }
            ],
            "establishment_year": 1956
        },
        "12": {
            "company_name": "ERI",
            "key_personnel": [
                {
                    "name": "Allan Eriksson",
                    "position": "Ägare o chefer"
                },
                {
                    "name": "Tage Skoog",
                    "position": "Ägare o chefer"
                }
            ],
            "establishment_year": 1950
        },
        "13": {
            "company_name": "ERIKSSON & STARKS MEKANISKA VERKSTAD, AB",
            "pnr": "16130",
            "address": "Bromma, Ekbacksv 42",
            "phone_number": "08256133, 259466",
            "bank_details": {
                "bankgiro": "575-1268",
                "postgiro": "13429-6"
            },
            "activity": "Utför mekaniska arbeten samt tillverkar verktyg",
            "employees": 55,
            "annual_turnover": 5000000,
            "capital": 30000,
            "key_personnel": [
                {
                    "name": "Pabr Herbert Johansson",
                    "position": "Verkst dir"
                },
                {
                    "name": "Anders Kindahl",
                    "position": "Försäljn-chef"
                }
            ],
            "establishment_year": 1914
        },
        "14": {
            "company_name": "ERIKSSON & SVÄRD, SÅGBOLAGET",
            "pnr": "33023",
            "address": "Smålandsstenar, Malmg 25",
            "phone_number": "037130533, 30633",
            "bank_details": {
                "bankgiro": "42-7665",
                "postgiro": "378204-2"
            },
            "activity": "Tillverkar sparrar, bjälkar, bräder, plank, reglar o läkt",
            "employees": 6,
            "annual_turnover": 500000,
            "key_personnel": [
                {
                    "name": "Evert Eriksson",
                    "position": "Chefer"
                },
                {
                    "name": "Hilding Svärd",
                    "position": "Chefer"
                }
            ],
            "establishment_year": 1951
        },
        "15": {
            "company_name": "AKEMA AB",
            "pnr": "12740",
            "address": "Skärholmen, Stångholmsbacken 61",
            "phone_number": "087100930",
            "bank_details": {
                "bankgiro": "630-7409",
                "postgiro": "258200-5"
            },
            "activity": "Rullstolar o handikapphjälpmedel",
            "employees": 15,
            "key_personnel": [
                {
                    "name": "Bengt Älmeby",
                    "position": "Verkst dir"
                }
            ],
            "establishment_year": 1969
        },
        "16": {
            "company_name": "TEREDO MASKIN AB",
            "pnr": "11157",
            "address": "Stockholm C, Sveav 13-15",
            "phone_number": "08240750",
            "bank_details": {
                "bankgiro": "56-0019",
                "postgiro": "51640"
            },
            "activity": "Säljer grävmaskiner, lastmaskiner o mobilkranar",
            "employees": 15,
            "capital": 240000,
            "key_personnel": [
                {
                    "name": "Ing Henning Leonard Widerdal",
                    "position": "Verkst dir"
                }
            ],
            "establishment_year": 1959
        }
    }
}