{
    "original": "BERG KAFFEIMPORT AB, A\n\nPnr 402 31\n\nGöteborg 7, Box 7038. Nordhemsg\n25. Tel 031-124160\nVerksamhet: Kafferosteri o\nförsäljning av kaffe till storkök\nAntal anställda: 12\nÅrsomsättning: 6 000 000\nAktiekapital: 75 000\nVerkst dir: Gunnar Nilsson\nEtableringsår: 1895.\n\nBERG EFTR, MANUFAKTUR\nAB FILIP\n\nPnr 50108\n\nBorås 1, Götag 5. Box 518. Tel\n033-1136 20. Bankgiro 83-9416.\nPostgiro 225190-8\n\nVerksamhet: Manufakturvaror i\nparti\n\nAktiekapital: 10 000\nVerkst dir: Erik Larsson\nEtableringsår: 1959.\n\nBERG MATEMATISK\nINSTRUMENTFABRIK AB, FR J\n\nPnr 113 57\n\nStockholm, Kungstensg 18. Tel\n08-30 76 60. Bankgiro 403-1415.\nPostgiro 1968-7\n\nVerksamhet: Tillverkar o säljer\n\ngeodetiska instrument o längdmät-\n\nningsinstrument\n\nAktiekapital: 50 000\n\nVerkst dir: Civiling Johan Berg\n\nEtableringsår: 1850.\n\nKANTHAL, AB\n\nPnr 734 01\nHallstahammar\n\nFusioneras under 1971 med\nBulten-Kanthal AB men bedriver till\ndess verksamheten som juridisk\nperson under ovanstående firmanamn.\n\nSe i övrigt Bulten-Kanthal AB\n\nKanthaldivisionen resp\nGjutgods-di visionen.\n\nKAPITAL-KONTROLL AB\n\nPnr ill 22\n\nStockholm. Kungsg 56. Tel\n08-23 26 80. Postgiro 2626\nVerksamhet: Lämnar\nkreditupplysningar\n\nAntal anställda: 20\nAktiekapital: 20000\nVerkst dir: Ragnar Wigström\nEtableringsår: 1926\nOmbildat till aktiebolag 1946.\n\nKAPMAN AB\n\nPnr 430 20\n\nVeddige. Tel 0340-303 1 0-15.\nBankgiro 425-2631. Postgiro 244455-2.\nTga Kapman. Telex 3478\nVerksamhet: Metallsågblad,\nkap-skivor, navrondeller o slipskålar\nVarunamn: Kapman\nAntal anställda: 55\nÅrsomsättning: 5 000 000\nVerkst dir: A Wegeland\nEtableringsår: 1956.\n\nKARAKÄS-KIVIKS\nFRUKTODLINGAR &amp; MUSTER!\n\nPn r 270 57\n\nKivik. Tel 0414-700 4 9, 704 7 9.\nBankgiro 296-3239. Postgiro\n343366-1\n\nVerksamhet: Tillverkning av\nnaturrena fruktdrycker, juicer,\nhuvudsakligen av svenska frukter o bär\nAntal anställda: 20\nÅrsomsättning: 2 500 000\nChef: Fruktodlare Ingvar Åkesson\nKamrer: Erik Svensson\nEtableringsår: 1950.\n\nBJÄRNUM-PAPPER AB\n\nPnr 280 20\n\nBjämum, Box 10. Södra v. Tel\n0451-206 15. Bankgiro 265-3145.\nPostgiro 339072-1\nVerksamhet: Tillverkar alla slags\nblock\n\nAntal anställda: 35\nÅrsomsättning: 3 500 000\nAktiekapital: 10 200\nVerkst dir: Alv Herder\nEtableringsår. 1902.\n\nÅSBRINK EIKER AB\n\nPnr 222 38\n\nLund, Bondev 8. Tel 046-12 42 60.\nTga Sperco. Telex 32260\nVerksamhet: Tillverkar\nkompressorer, renhållningsmaskiner,\nsopmaskiner, snöröjningsmaskiner,\nslåttermaskiner för vägrenar,\ntippanordningar för lastbilar,\nhydrauliska anordningar,\nhydraulcy-lindrar o -ventiler\nAvdelningskontor: 402 52 Göteborg\n13. Gainlestadsv. Box 13070. Tel\n031-25 04 00\n\n14123 Huddinge, Sjödalsv 21. Box\n1121. Tel 08-757 28 80\nÅrsomsättning: 20000000\nAktiekapital: 500 000\nStyrelse: Dir Knut Linse (ordf),\nnotarie Jan Porkman, dir Thorsten\nPersson\n\nVerkst dir. Thorsten Persson\nEtableringsår 1931 (1946).\n\nTAUSON &amp; CO AB, D\n\nPnr 41101\n\nGöteborg, Friggag 4. Tel\n031-17 28 70. Bankgiro 50-8007.\nPost-giro 42227. Tga Tauco\nVerksamhet: Kolonialvaror i parti\nAktiekapital: 100 000\nVerkst dir: Dennis Tauson\nEtableringsår: 1931.\n\nINTERNATIONAL FINANCIAL\nADVISERS WAHLBERG &amp;\nWAHLBERG AB\n\nPnr 113 59\n\nStockholm, Sveav 59 A. Tel\n08-34 53 16. Tga Swedifator.\nTelex 19107 SWEDIFA S\nVerksamhet: Organisation o\netab-leringsservice\nAvdelningskontor.\n214 20 Malmö, Möllevångsg 32. Tel\n040-1116 00\n\nNederländerna: Honthorststraat 30,\nAmsterdam\n\nSchweiz: Accountants &amp; Financial\nAdvisers Ltd., 17, Rue des\nPier-res-du-Niton, 1207 Geneva\nU.K. Correspondents:\n55/61, Moorgate, London, E.C.2\nVerkst dir: Aukt revisor Töre\nWahlberg\n\n•Aktiekapital: 5 000\nEtableringsår. 1967.\n\nINTERNATIONAL FIREGUARD\nCORPORATION AB\n\nPnr 16139\n\nBromma, Ornbog 13. Tel 08-25 0148,\n26 4470. Bankgiro 56-3676.\nPostgiro 652626\n\nVerksamhet: Säljer eldsläckare.\nTillverkar pulver som är\nskumbildande för släckning av eld o skydd\nav eldhotade föremål\nAktiekapital: 70 000\nVerkst dir: Torsten Wieslander\nEtableringsår: 1962.\n\nINTERNATIONAL FLAVORS &amp;\nFRAGRANCES I.F.F.\n(SVERIGE) AB\n\nPnr 104 40\n\nStockholm 14, Grevg 14. Box 14056.\nTel 08-617934, 62 43 63. Tga\nInteriff\n\nVerksamhet: Import av smak- o\nluktämnen\nAntal anstäUda: 9\nAktiekapital: 5 000\nEtableringsår 1946.\n\nATLAS COPCO TOOLS AB\n\nPnr 104 60\n\nStockholm 20, Fack. Tel\n08-44 9 9 20. Bankgiro 160-4578.\nPostgiro 2576 8 2-5. Telex 17130\nVerksamhet: Utvecklar, tillverkar\no marknadsför pneumatiska\nkomponenter, verktyg o system för\nmaterialbearbetning o ytbehandling\nTillverknin gsenheter:\nInjectorverken, Stockholm\nEccoverken, Skara\n\nAntal anställda: 1100\nAktiekapital: 10 000 000\nStyrelse: Tekn dr Marcus\nWallenberg (ordf), envoyé Kurt-Allan\nBelfrage, bankdir Henry N Sporborg,\nbankdir Marc Wallenberg Jr, prof\nJan Hellner, dir Sture Odner, dir\nSture Ekefalk, dir öik Johnsson,\ndir Arne Ekholm, dir Peter\nWallenberg (suppl), dir Bengt Andersson\n(suppl), dir Gunnar Ruding (suppl)\nVerkst dir: Arne Ekholm\nEtableringsår: 1968\nDotterbolag till Atlas Copco AB,\nStockholm.\n\nATLAS MARIN AB\n\nPnr 401 26\n\nGöteborg 1, Box 400. Tel\n031-19 25 50. Tga Radek. Telex 2577\nVerksamhet: Säljer ekolod,\ngyro-kompasser, dieselmotorer,\ndäcksmaskiner, evaporatorer, filter,\nseparatorer, radar\nAntal anställda: 30\nAktiekapital: 350 000\nVerkst dir: Rune Fahlström\nV verkst dir: Jan Ungerfält\nEtableringsår: 1950.\n\nATLAS MEK VERKSTAD\nAB, N E\n\nPnr 212 25\n\nMalmö, Krusegränd. Tel\n040-93 68 30. Bankgiro 260-1706.\nPostgiro 38311-7\n\nVerksamhet: Tillverkar\nhögtryckskärl o utför legoarbeten i grov- o\ntunnplåt\n\nAntal anställda: 25\nÅrsomsättning: 1800 000\nAktiekapital: 50 000\nVerkst dir: Nils Erik Atlas\nEtableringsår: 1889.\n\nallgon\nantennspecialisten ab\n\nPnr 184 00\n\nAkersberga. Tel 0764-60120.\nBankgiro 743-0291. Postgiro 259941-3.\nTelex 10967\n\nVerksamhet: Tillverkar o säljer\nradiokommunikations antenner\nVarunamn: Allgon\nFilial: 778 02 Norberg, Kärrgruvan.\nTel 0223-206 00, 206 60\nAntal anställda: 80\nÅrsomsättning: 6 000 000\nAktiekapital: 1300 000\nVerkst dir: Sven Bringholm\nEtableringsår: 1946.\n\nINPLASTOR, AB\n\nPnr 59101\n\nMotala 1, Box 157. Marsg 4. Tel\n0141-164 20. Bankgiro 447-2387.\nPostgiro 707474-3. Tga Inplastor.\nTelex 55 94 INPLAST S\nVerksamhet: Tillverkar o säljer\nskyltar o reklamartiklar mm\nAntal anställda: 40\nÅrsomsättning: 4 500 000\nAktiekapital: 50 000\nVerkst dir: Ake Larsson\nEtableringsår: 1957.\n\nKONSULTPARTNER AB\n\nPnr 11439\n\nStockholm, Nybrog 39. Tel\n08-63 59 95. Bankgiro 48-1813.\nPostgiro 55537\n\nVerksamhet: Konsulter inom handel\no industri\n\nAntal anställda: 35\nÅrsomsättning: 1500 000\nAktiekapital: 75 000\nVerkst dir: Civiling Leif Wahlberg\n(Göteborg).\n\nKONSULTSTIFTELSEN FORE.\nTAGS RATIONALISERING\n\nPnr 184 00\n\nÄkersberga, Stationsg 4. Box 7.\nTel 0764-209 67. Postgiro 10821\nVerksamhet: Skatte- o\nbokföringsbyrå, konsulterande i\nföretagsrationalisering o företagsekonomi\nAvdelningskontor: Stockholm O,\nGrev Tur eg 15. Tel 08-6167 89,\n61 97 29\n\nAntal anställda: 6\n\nVerkst dir: Eva Tvede-Jensen\n\nEtableringsår: 1964.",
    "structured": {
        "1": {
            "company_name": "BERG KAFFEIMPORT AB",
            "pnr": "402 31",
            "address": "Göteborg 7, Box 7038. Nordhemsg 25",
            "phone_number": "031-124160",
            "activity": "Kafferosteri o försäljning av kaffe till storkök",
            "employees": 12,
            "annual_turnover": 6000000,
            "capital": 75000,
            "key_personnel": [
                {
                    "name": "Gunnar Nilsson",
                    "position": "Verkst dir"
                }
            ],
            "establishment_year": 1895
        },
        "2": {
            "company_name": "BERG EFTR, MANUFAKTUR AB FILIP",
            "pnr": "50108",
            "address": "Borås 1, Götag 5. Box 518",
            "phone_number": "033-1136 20",
            "bank_details": {
                "bankgiro": "83-9416",
                "postgiro": "225190-8"
            },
            "activity": "Manufakturvaror i parti",
            "capital": 10000,
            "key_personnel": [
                {
                    "name": "Erik Larsson",
                    "position": "Verkst dir"
                }
            ],
            "establishment_year": 1959
        },
        "3": {
            "company_name": "BERG MATEMATISK INSTRUMENTFABRIK AB, FR J",
            "pnr": "113 57",
            "address": "Stockholm, Kungstensg 18",
            "phone_number": "08-30 76 60",
            "bank_details": {
                "bankgiro": "403-1415",
                "postgiro": "1968-7"
            },
            "activity": "Tillverkar o säljer geodetiska instrument o längdmätningsinstrument",
            "capital": 50000,
            "key_personnel": [
                {
                    "name": "Civiling Johan Berg",
                    "position": "Verkst dir"
                }
            ],
            "establishment_year": 1850
        },
        "4": {
            "company_name": "KANTHAL, AB",
            "pnr": "734 01",
            "address": "Hallstahammar",
            "establishment_year": 1971
        },
        "5": {
            "company_name": "KAPITAL-KONTROLL AB",
            "pnr": "111 22",
            "address": "Stockholm, Kungsg 56",
            "phone_number": "08-23 26 80",
            "postgiro": "2626",
            "activity": "Lämnar kreditupplysningar",
            "employees": 20,
            "capital": 20000,
            "key_personnel": [
                {
                    "name": "Ragnar Wigström",
                    "position": "Verkst dir"
                }
            ],
            "establishment_year": 1926
        },
        "6": {
            "company_name": "KAPMAN AB",
            "pnr": "430 20",
            "address": "Veddige",
            "phone_number": "0340-303 1 0-15",
            "bank_details": {
                "bankgiro": "425-2631",
                "postgiro": "244455-2"
            },
            "activity": "Metallsågblad, kap-skivor, navrondeller o slipskålar",
            "annual_turnover": 5000000,
            "key_personnel": [
                {
                    "name": "A Wegeland",
                    "position": "Verkst dir"
                }
            ],
            "establishment_year": 1956
        },
        "7": {
            "company_name": "KARAKÄS-KIVIKS FRUKTODLINGAR & MUSTER!",
            "pnr": "270 57",
            "address": "Kivik",
            "phone_number": "0414-700 49, 704 79",
            "bank_details": {
                "bankgiro": "296-3239",
                "postgiro": "343366-1"
            },
            "activity": "Tillverkning av naturrena fruktdrycker, juicer, huvudsakligen av svenska frukter o bär",
            "employees": 20,
            "annual_turnover": 2500000,
            "key_personnel": [
                {
                    "name": "Fruktodlare Ingvar Åkesson",
                    "position": "Chef"
                },
                {
                    "name": "Erik Svensson",
                    "position": "Kamrer"
                }
            ],
            "establishment_year": 1950
        },
        "8": {
            "company_name": "BJÄRNUM-PAPPER AB",
            "pnr": "280 20",
            "address": "Bjämum, Box 10. Södra v",
            "phone_number": "0451-206 15",
            "bank_details": {
                "bankgiro": "265-3145",
                "postgiro": "339072-1"
            },
            "activity": "Tillverkar alla slags block",
            "employees": 35,
            "annual_turnover": 3500000,
            "capital": 10200,
            "key_personnel": [
                {
                    "name": "Alv Herder",
                    "position": "Verkst dir"
                }
            ],
            "establishment_year": 1902
        },
        "9": {
            "company_name": "ÅSBRINK EIKER AB",
            "pnr": "222 38",
            "address": "Lund, Bondev 8",
            "phone_number": "046-12 42 60",
            "activity": "Tillverkar kompressorer, renhållningsmaskiner, sopmaskiner, snöröjningsmaskiner, slåttermaskiner för vägrenar, tippanordningar för lastbilar, hydrauliska anordningar, hydraulcylindrar o -ventiler",
            "branches": [
                "402 52 Göteborg",
                "14123 Huddinge"
            ],
            "annual_turnover": 20000000,
            "capital": 500000,
            "key_personnel": [
                {
                    "name": "Thorsten Persson",
                    "position": "Verkst dir"
                }
            ],
            "establishment_year": "1931 (1946)"
        },
        "10": {
            "company_name": "TAUSON & CO AB, D",
            "pnr": "41101",
            "address": "Göteborg, Friggag 4",
            "phone_number": "031-17 28 70",
            "bank_details": {
                "bankgiro": "50-8007",
                "postgiro": "42227"
            },
            "activity": "Kolonialvaror i parti",
            "capital": 100000,
            "key_personnel": [
                {
                    "name": "Dennis Tauson",
                    "position": "Verkst dir"
                }
            ],
            "establishment_year": 1931
        },
        "11": {
            "company_name": "INTERNATIONAL FINANCIAL ADVISERS WAHLBERG & WAHLBERG AB",
            "pnr": "113 59",
            "address": "Stockholm, Sveav 59 A",
            "phone_number": "08-34 53 16",
            "activity": "Organisation o etableringsservice",
            "branches": [
                "214 20 Malmö",
                "Nederländerna: Honthorststraat 30, Amsterdam",
                "Schweiz: Accountants & Financial Advisers Ltd., 17, Rue des Pierres-du-Niton, 1207 Geneva",
                "U.K. Correspondents: 55/61, Moorgate, London, E.C.2"
            ],
            "key_personnel": [
                {
                    "name": "Aukt revisor Töre Wahlberg",
                    "position": "Verkst dir"
                }
            ],
            "capital": 5000,
            "establishment_year": 1967
        },
        "12": {
            "company_name": "INTERNATIONAL FIREGUARD CORPORATION AB",
            "pnr": "16139",
            "address": "Bromma, Ornbog 13",
            "phone_number": "08-25 0148, 26 4470",
            "bank_details": {
                "bankgiro": "56-3676",
                "postgiro": "652626"
            },
            "activity": "Säljer eldsläckare. Tillverkar pulver som är skumbildande för släckning av eld o skydd av eldhotade föremål",
            "key_personnel": [
                {
                    "name": "Torsten Wieslander",
                    "position": "Verkst dir"
                }
            ],
            "capital": 70000,
            "establishment_year": 1962
        },
        "13": {
            "company_name": "INTERNATIONAL FLAVORS & FRAGRANCES I.F.F. (SVERIGE) AB",
            "pnr": "104 40",
            "address": "Stockholm 14, Grevg 14. Box 14056",
            "phone_number": "08-617934, 62 43 63",
            "activity": "Import av smak- o luk",
            "employees": 9,
            "capital": 5000,
            "establishment_year": 1946
        },
        "14": {
            "company_name": "ATLAS COPCO TOOLS AB",
            "pnr": "104 60",
            "address": "Stockholm 20, Fack",
            "phone_number": "08-44 9 9 20",
            "bank_details": {
                "bankgiro": "160-4578",
                "postgiro": "2576 8 2-5"
            },
            "activity": "Utvecklar, tillverkar o marknadsför pneumatiska komponenter, verktyg o system för materialbearbetning o ytbehandling",
            "branches": [
                "Injectorverken, Stockholm",
                "Eccoverken, Skara"
            ],
            "employees": 1100,
            "capital": 10000000,
            "key_personnel": [
                {
                    "name": "Arne Ekholm",
                    "position": "Verkst dir"
                }
            ],
            "establishment_year": 1968,
            "ownership": "Dotterbolag till Atlas Copco AB, Stockholm"
        },
        "15": {
            "company_name": "ATLAS MARIN AB",
            "pnr": "401 26",
            "address": "Göteborg 1, Box 400",
            "phone_number": "031-19 25 50",
            "activity": "Säljer ekolod, gyro-kompasser, dieselmotorer, däcksmaskiner, evaporatorer, filter, separatorer, radar",
            "employees": 30,
            "capital": 350000,
            "key_personnel": [
                {
                    "name": "Rune Fahlström",
                    "position": "Verkst dir"
                },
                {
                    "name": "Jan Ungerfält",
                    "position": "V verkst dir"
                }
            ],
            "establishment_year": 1950
        },
        "16": {
            "company_name": "ATLAS MEK VERKSTAD AB, N E",
            "pnr": "212 25",
            "address": "Malmö, Krusegränd",
            "phone_number": "040-93 68 30",
            "bank_details": {
                "bankgiro": "260-1706",
                "postgiro": "38311-7"
            },
            "activity": "Tillverkar högtryckskärl o utför legoarbeten i grov- o tunnplåt",
            "employees": 25,
            "annual_turnover": 1800000,
            "capital": 50000,
            "key_personnel": [
                {
                    "name": "Nils Erik Atlas",
                    "position": "Verkst dir"
                }
            ],
            "establishment_year": 1889
        },
        "17": {
            "company_name": "ALLGON ANTENNSPECIALISTEN AB",
            "pnr": "184 00",
            "address": "Akersberga",
            "phone_number": "0764-60120",
            "bank_details": {
                "bankgiro": "743-0291",
                "postgiro": "259941-3"
            },
            "activity": "Tillverkar o säljer radiokommunikations antenner",
            "filial": "778 02 Norberg, Kärrgruvan",
            "employees": 80,
            "annual_turnover": 6000000,
            "capital": 1300000,
            "key_personnel": [
                {
                    "name": "Sven Bringholm",
                    "position": "Verkst dir"
                }
            ],
            "establishment_year": 1946
        },
        "18": {
            "company_name": "INPLASTOR, AB",
            "pnr": "59101",
            "address": "Motala 1, Box 157. Marsg 4",
            "phone_number": "0141-164 20",
            "bank_details": {
                "bankgiro": "447-2387",
                "postgiro": "707474-3"
            },
            "activity": "Tillverkar o säljer skyltar o reklamartiklar mm",
            "employees": 40,
            "annual_turnover": 4500000,
            "capital": 50000,
            "key_personnel": [
                {
                    "name": "Ake Larsson",
                    "position": "Verkst dir"
                }
            ],
            "establishment_year": 1957
        },
        "19": {
            "company_name": "KONSULTPARTNER AB",
            "pnr": "11439",
            "address": "Stockholm, Nybrog 39",
            "phone_number": "08-63 59 95",
            "bank_details": {
                "bankgiro": "48-1813",
                "postgiro": "55537"
            },
            "activity": "Konsulter inom handel o industri",
            "employees": 35,
            "annual_turnover": 1500000,
            "capital": 75000,
            "key_personnel": [
                {
                    "name": "Civiling Leif Wahlberg",
                    "position": "Verkst dir"
                }
            ]
        },
        "20": {
            "company_name": "KONSULTSTIFTELSEN FORE. TAGS RATIONALISERING",
            "pnr": "184 00",
            "address": "Äkersberga, Stationsg 4. Box 7",
            "phone_number": "0764-209 67",
            "postgiro": "10821",
            "activity": "Skatte- o bokföringsbyrå, konsulterande i företagsrationalisering o företagsekonomi",
            "branches": [
                "Stockholm O, Grev Tur eg 15"
            ],
            "employees": 6,
            "key_personnel": [
                {
                    "name": "Eva Tvede-Jensen",
                    "position": "Verkst dir"
                }
            ],
            "establishment_year": 1964
        }
    }
}