{
    "original": "LIDBOHOLMS AB\n\nPnr 360 42\n\nBraås. Tel 0474-300 07, 300 08.\nBankgiro 26-5618. Postgiro 73847.\nTga Lidboholm\n\nVerksamhet: Sågverk o hyvleri\nAntal anställda: 50\nÅrsomsättning: 5 500 000\nAktiekapital: 200 000\nVerkst dir: Sven Varde\nEtableringsår: 1930.\n\nFENNIA FÄRG AB\n\nPnr 13103\n\nNacka 3, Saltsjö Järla\nIndustricentrum. Fack. Tel 08-716 9260.\nBankgiro 36-4017. Postgiro 695930-8.\nTelex 10113. Tga Fenniacomp\nVerksamhet: Säljer färger\nKontor o lager Nacka,\nSaltsjö-Järla Industricentrum\nVarunamn: EPIREX\nAktiekapital: 240 000\nVerkst din Lars Malmström\nEtableringsår: 1967.\n\nHEEDE AB, B M\n\nPnr 16212\n\nVällingby 1, Sorterarg 12. Box 115.\nTel 08-89 03 00. Bankgiro 57-7435.\nPostgiro 459170. Telex 10288. Tga\nHeedeab\n\nVerksamhet: Säljer pumpar,\nmotorer, ventiler, cylindrar o\nkopplingar för hydraulik\n\nVarunamn: Anchor, Dynapower,\nFunk, Hamworthy, Hydreco, Marvel,\nPratt, Ruston\nAktiekapital: 225 000\nVerkst dir: Harald Adsjö\nEtableringsår: 1946.\n\nHEDEMORA\nCEMENTVARU-FABRIK, AB\n\nPnr 776 00\n\nHedemora, Fack 5. Tel 0225-10185,\n109 50. Bankgiro 79-5510. Postgiro\n492161\n\nVerksamhet: Tillverkar cementrör\no betongtakpannor\nAntal anställda: 18\nÅrsomsättning: 1000 000\nAktiekapital: 15 000\nVerkst dir: Bengt Reander\nEtableringsår: 1923.\n\nPLAMAKO AB\n\nPnr 33100\n\nVärnamo,Postg3.Tel0370-118 10.\nBankgiro 542-6267. Postgiro\n10090-9. Telex 70055\nVerksamhet: Försäljning av\nmaskiner o utrustningar för\nplastindustrin\n\nAntal anställda: 6\nÅrsomsättning: 4 000 000\nAktiekapital: 30 000\nVerkst dir: Anton Johansson\nEtableringsår: 1961.\n\nTHULE, INDUSTRI AB\n\nPnr 33033\n\nHill ers torp, Borgg. Box 201. Tel\n0370-220 62, 220 70. Bankgiro\n54-3211. Postgiro 363545. Telex 70173\nVerksamhet: Tillverkar takräck,\nskidhållare o snöskyfflar till bilar\nAntal anställda: 25\nÅrsomsättning: 4 000 000\nAktiekapital: 130 000\nStyrelse: Fabr Willis Thulin (ordf),\nfabr Jack Thulin\nVerkst dir: Fabr Jack Thulin\nEtableringsàr 1960.\n\nmaskinhjälp ab\n\nPnr 502 51\n\nBorås, Kransv 5. Tel 033-13 60 95.\nBankgiro 531-3937. Postgiro\n388052-3\n\nVeiksamhet: Uthyr, säljer o\nreparerar maskiner för byggnadsarbeten\nAntal anstäUda: 10\nAktiekapital: 20 000\nVeikst dir: Sven Birgersson\nEtableringsår: 1947\nOmbildat till aktiebolag 1959.\n\nmaskin.hydraulik, ab\n\nPnr 417 03\n\nGöteborg, Hisingsg 28. Tel\n031-23 91 47, 23 91 48. Bankgiro\n513-1750. Postgiro 621611-3. Tga\nHydroma\n\nVerksamhet: Hydrauliska\nutrustningar, konstruktion o försäljning\nav såväl kompletta anläggningar\nsom enstaka komponenter\n\nAktiekapital: 20 000\nVerkst dir: Ing Alf Sigurdsson\nEtableringsår: 1961.\n\nCLASE, AB SVEN\n\nPnr 21125\n\nMalmö, N Vallg 28. Tel 040-743 80.\nBankgiro 640-1848. Postgiro\n38726-6. Tga Svenclase.\nTelex 32529 CLASE S\nVerksamhet: Importerar o säljer\nöl o vin\n\nAntal anställda: 4\nÅrsomsättning: 5 000 000\nAktiekapital: 100 000\nVerkst dir: Sven Clase\nEtableringsår: 1932.\n\nELGE TRIKÅINDUSTRI\n\nPnr 780 42\n\nGagnef, Box 117. Tel 0241-610 24.\nBankgiro 79-5108. Postgiro 97064-0\nVerksamhet: Tillverkar\ndambenklä-der i interlock o Rib Jacquard\nAntal anställda: 20\nÅrsomsättning: 1000 000\nChef: Elis Lisell\nEtableringsår: 1943\n\nELGESTADSINGENJORSBYRÅ\nAB\n\nPnr 182 61\n\nDjursholm, Stockholmsv 109. Tel\n08-755 27 80. Bankgiro 743-0226.\nPostgiro 55499-8\nVerksamhet: VVS-konsult\nAntal anställda: 9\nÅrsomsättning: 440 000\nAktiekapital: 40000\nVerkst dir: Civiling Stig Elgestad\nEtableringsår: 1945.\n\nELGE-VERKEN, AB\n\nLinköpings Gjuteri &amp; Mek Verkstad\nPnr 58104\n\nLinköping 1, Box 384. Gjuterig 1.\nTel 013-1299 15. Bankgiro 276-5063.\nPostgiro 6065-7. Tga Elgeverken\nVerksamhet: Kabelskåp,\nkabelmuffar, gjutmassor, jordningsdon,\ntestapparater, skydds- o\ntestanordningar för arbete i ställverk o\nkabelskåp, djupjordare,\nåskledare-materiel, spännlinjaler samt\nhand-o maskinformat tackjärns gjutgods\nVarunamn: ELGE\nAktiekapital: 600 000\nVerkst dir: s Arbrandt\nEtableringsår: 1873\nOmbildat till aktiebolag 1909.\n\nELGO\nLÄDERVARU-FABRIK, AB\n\nPnr 332 00\n\nGislaved, Furuliden 2. Tel\n0371-110 93. Bankgiro 426-7134.\nPostgiro 287460-0\n\nVerksamhet: Tillverkar shopping-,\ndam-, barn- o skolväskor samt bags\nAntal anställda: 7\nAktiekapital: 25 000\nVerkst dir: Bertil Westergren\nEtableringsår: 1953\nOmbildat till aktiebolag 1960.\n\nEL-GRAVYR INDUSTRI AB\n\nPnr 141 21\n\nHuddinge 1, Klockarv 6. Box 1024.\nTel 08-757 32 72. Bankgiro\n62-6090. Postgiro 445696\nVerksamhet: Tillverkar o graverar\nskyltar, paneler o skalor i plast o\nmetall\n\nAntal anställda: 7\nAktiekapital: 25 000\nVerkst dir: Fabr Arne Lindström\nEtableringsår: 1948\nOmbildat till aktiebolag 1964.\n\nEL-HÅGE, AB\n\nPnr 95100\n\nLuleå, S Hamnen. Tel 0920-204 45.\nBankgiro 608-9056. Postgiro\n60352-2. TgaHåge\nVerksamhet: Säljer elektr\ninstallationsmateriel en gros\nAntal anställda: 15\nAktiekapital: 85 000\nChef: Rune Nordström\nEtableringsår: 1955.\n\nELIASSON &amp; LUND\nVERKSTADS AB\n\nPnr 423 00\n\nTorslanda, Industriv 2. Tel 031-\n\n92 09 21, 92 09 25. Postgiro\n424890-2\n\nVerksamhet: Bagerianläggningar,\nmaskin- o motordetaljer\nAntal anställda: 25\nÅrsomsättning: 1500 000\nAktiekapital: 15 000\nChef: B Eliasson\nEtableringsår: 1950.\n\nWINGÅRD, AB EUG\n\nPnr 211 24\n\nMalmö, Brännög 2. Tel\n040-93 50 50. Telex 3106. Tga Wingård\nVerksamhet: Färger, fernissor,\nmå-larutensilier, kemikalier, betser\nAktiekapital: 1081000\nVerkst din Allan Hultén\nEtableringsån 1889.\n\nBORÅS YÄSKINDUSTRI, AB\n\nPnr 50107\n\nBorås 1, Box 450. Göteborgsv 10.\nTel 033-12 90 50, 13 45 50.\nBankgiro 83-9430. Postgiro 495802\n\nTillverkar\n\nshoppingsväskor, sport-\n\n_o. resesäckar_\n\nAntal anställda: 34\nÄgare o chefer: Kurt Isaksson,\nElof Johansson\nEtableringsår: 1955.",
    "structured": {
        "1": {
            "company_name": "LIDBOHOLMS AB",
            "pnr": "360 42",
            "address": "Braås",
            "phone_number": "0474-300 07, 300 08",
            "bank_details": {
                "bankgiro": "26-5618",
                "postgiro": "73847"
            },
            "activity": "Sågverk o hyvleri",
            "employees": 50,
            "annual_turnover": 5500000,
            "capital": 200000,
            "key_personnel": [
                {
                    "name": "Sven Varde",
                    "position": "Verkst dir"
                }
            ],
            "establishment_year": 1930
        },
        "2": {
            "company_name": "FENNIA FÄRG AB",
            "pnr": "13103",
            "address": "Nacka 3, Saltsjö Järla Industricentrum",
            "phone_number": "08-716 9260",
            "bank_details": {
                "bankgiro": "36-4017",
                "postgiro": "695930-8"
            },
            "activity": "Säljer färger",
            "employees": null,
            "annual_turnover": null,
            "capital": 240000,
            "key_personnel": [
                {
                    "name": "Lars Malmström",
                    "position": "Verkst din"
                }
            ],
            "establishment_year": 1967
        },
        "3": {
            "company_name": "HEEDE AB, B M",
            "pnr": "16212",
            "address": "Vällingby 1, Sorterarg 12, Box 115",
            "phone_number": "08-89 03 00",
            "bank_details": {
                "bankgiro": "57-7435",
                "postgiro": "459170"
            },
            "activity": "Säljer pumpar, motorer, ventiler, cylindrar o kopplingar för hydraulik",
            "employees": null,
            "annual_turnover": null,
            "capital": 225000,
            "key_personnel": [
                {
                    "name": "Harald Adsjö",
                    "position": "Verkst dir"
                }
            ],
            "establishment_year": 1946
        },
        "4": {
            "company_name": "HEDEMORA CEMENTVARU-FABRIK, AB",
            "pnr": "776 00",
            "address": "Hedemora, Fack 5",
            "phone_number": "0225-10185, 109 50",
            "bank_details": {
                "bankgiro": "79-5510",
                "postgiro": "492161"
            },
            "activity": "Tillverkar cementrör o betongtakpannor",
            "employees": 18,
            "annual_turnover": 1000000,
            "capital": 15000,
            "key_personnel": [
                {
                    "name": "Bengt Reander",
                    "position": "Verkst dir"
                }
            ],
            "establishment_year": 1923
        },
        "5": {
            "company_name": "PLAMAKO AB",
            "pnr": "33100",
            "address": "Värnamo, Postg3",
            "phone_number": "0370-118 10",
            "bank_details": {
                "bankgiro": "542-6267",
                "postgiro": "10090-9"
            },
            "activity": "Försäljning av maskiner o utrustningar för plastindustrin",
            "employees": 6,
            "annual_turnover": 4000000,
            "capital": 30000,
            "key_personnel": [
                {
                    "name": "Anton Johansson",
                    "position": "Verkst dir"
                }
            ],
            "establishment_year": 1961
        },
        "6": {
            "company_name": "THULE, INDUSTRI AB",
            "pnr": "33033",
            "address": "Hillers torp, Borgg. Box 201",
            "phone_number": "0370-220 62, 220 70",
            "bank_details": {
                "bankgiro": "54-3211",
                "postgiro": "363545"
            },
            "activity": "Tillverkar takräck, skidhållare o snöskyflar till bilar",
            "employees": 25,
            "annual_turnover": 4000000,
            "capital": 130000,
            "key_personnel": [
                {
                    "name": "Fabr Willis Thulin",
                    "position": "ordf"
                },
                {
                    "name": "Fabr Jack Thulin",
                    "position": "Verkst dir"
                }
            ],
            "establishment_year": 1960
        },
        "7": {
            "company_name": "Maskinhjälp AB",
            "pnr": "502 51",
            "address": "Borås, Kransv 5",
            "phone_number": "033-13 60 95",
            "bank_details": {
                "bankgiro": "531-3937",
                "postgiro": "388052-3"
            },
            "activity": "Uthyr, säljer o reparerar maskiner för byggnadsarbeten",
            "employees": 10,
            "capital": 20000,
            "key_personnel": [
                {
                    "name": "Sven Birgersson",
                    "position": "Verkst dir"
                }
            ],
            "establishment_year": 1947
        },
        "8": {
            "company_name": "Maskin.hydraulik AB",
            "pnr": "417 03",
            "address": "Göteborg, Hisingsg 28",
            "phone_number": "031-23 91 47, 23 91 48",
            "bank_details": {
                "bankgiro": "513-1750",
                "postgiro": "621611-3"
            },
            "activity": "Hydrauliska utrustningar, konstruktion o försäljning av såväl kompletta anläggningar som enstaka komponenter",
            "capital": 20000,
            "key_personnel": [
                {
                    "name": "Ing Alf Sigurdsson",
                    "position": "Verkst dir"
                }
            ],
            "establishment_year": 1961
        },
        "9": {
            "company_name": "CLASE, AB SVEN",
            "pnr": "21125",
            "address": "Malmö, N Vallg 28",
            "phone_number": "040-743 80",
            "bank_details": {
                "bankgiro": "640-1848",
                "postgiro": "38726-6"
            },
            "activity": "Importerar o säljer öl o vin",
            "employees": 4,
            "annual_turnover": 5000000,
            "capital": 100000,
            "key_personnel": [
                {
                    "name": "Sven Clase",
                    "position": "Verkst dir"
                }
            ],
            "establishment_year": 1932
        },
        "10": {
            "company_name": "ELGE TRIKÅINDUSTRI",
            "pnr": "780 42",
            "address": "Gagnef, Box 117",
            "phone_number": "0241-610 24",
            "bank_details": {
                "bankgiro": "79-5108",
                "postgiro": "97064-0"
            },
            "activity": "Tillverkar dambenklä-der i interlock o Rib Jacquard",
            "employees": 20,
            "annual_turnover": 1000000,
            "key_personnel": [
                {
                    "name": "Elis Lisell",
                    "position": "Chef"
                }
            ],
            "establishment_year": 1943
        },
        "11": {
            "company_name": "ELGESTADSINGENJORSBYRÅ AB",
            "pnr": "182 61",
            "address": "Djursholm, Stockholmsv 109",
            "phone_number": "08-755 27 80",
            "bank_details": {
                "bankgiro": "743-0226",
                "postgiro": "55499-8"
            },
            "activity": "VVS-konsult",
            "employees": 9,
            "annual_turnover": 440000,
            "capital": 40000,
            "key_personnel": [
                {
                    "name": "Civiling Stig Elgestad",
                    "position": "Verkst dir"
                }
            ],
            "establishment_year": 1945
        },
        "12": {
            "company_name": "ELGE-VERKEN, AB Linköpings Gjuteri & Mek Verkstad",
            "pnr": "58104",
            "address": "Linköping 1, Box 384, Gjuterig 1",
            "phone_number": "013-1299 15",
            "bank_details": {
                "bankgiro": "276-5063",
                "postgiro": "6065-7"
            },
            "activity": "Kabelskåp, kabelmuffar, gjutmassor, jordningsdon, testapparater, skydds- o testanordningar för arbete i ställverk o kabelskåp, djupjordare, åskledare-materiel, spännlinjaler samt hand-o maskinformat tackjärns gjutgods",
            "capital": 600000,
            "key_personnel": [
                {
                    "name": "s Arbrandt",
                    "position": "Verkst dir"
                }
            ],
            "establishment_year": 1873
        },
        "13": {
            "company_name": "ELGO LÄDERVARU-FABRIK, AB",
            "pnr": "332 00",
            "address": "Gislaved, Furuliden 2",
            "phone_number": "0371-110 93",
            "bank_details": {
                "bankgiro": "426-7134",
                "postgiro": "287460-0"
            },
            "activity": "Tillverkar shopping-, dam-, barn- o skolväskor samt bags",
            "employees": 7,
            "capital": 25000,
            "key_personnel": [
                {
                    "name": "Bertil Westergren",
                    "position": "Verkst dir"
                }
            ],
            "establishment_year": 1953
        },
        "14": {
            "company_name": "EL-GRAVYR INDUSTRI AB",
            "pnr": "141 21",
            "address": "Huddinge 1, Klockarv 6, Box 1024",
            "phone_number": "08-757 32 72",
            "bank_details": {
                "bankgiro": "62-6090",
                "postgiro": "445696"
            },
            "activity": "Tillverkar o graverar skyltar, paneler o skalor i plast o metall",
            "employees": 7,
            "capital": 25000,
            "key_personnel": [
                {
                    "name": "Fabr Arne Lindström",
                    "position": "Verkst dir"
                }
            ],
            "establishment_year": 1948
        },
        "15": {
            "company_name": "EL-HÅGE, AB",
            "pnr": "95100",
            "address": "Luleå, S Hamnen",
            "phone_number": "0920-204 45",
            "bank_details": {
                "bankgiro": "608-9056",
                "postgiro": "60352-2"
            },
            "activity": "Säljer elektr installationsmateriel en gros",
            "employees": 15,
            "capital": 85000,
            "key_personnel": [
                {
                    "name": "Rune Nordström",
                    "position": "Chef"
                }
            ],
            "establishment_year": 1955
        },
        "16": {
            "company_name": "ELIASSON & LUND VERKSTADS AB",
            "pnr": "423 00",
            "address": "Torslanda, Industriv 2",
            "phone_number": "031-92 09 21, 92 09 25",
            "bank_details": {
                "postgiro": "424890-2"
            },
            "activity": "Bagerianläggningar, maskin- o motordetaljer",
            "employees": 25,
            "annual_turnover": 1500000,
            "capital": 15000,
            "key_personnel": [
                {
                    "name": "B Eliasson",
                    "position": "Chef"
                }
            ],
            "establishment_year": 1950
        },
        "17": {
            "company_name": "WINGÅRD, AB EUG",
            "pnr": "21124",
            "address": "Malmö, Brännög 2",
            "phone_number": "040-93 50 50",
            "bank_details": {
                "bankgiro": "640-1848",
                "postgiro": "38726-6"
            },
            "activity": "Färger, fernissor, må-larutensilier, kemikalier, betser",
            "capital": 1081000,
            "key_personnel": [
                {
                    "name": "Allan Hultén",
                    "position": "Verkst dir"
                }
            ],
            "establishment_year": 1889
        },
        "18": {
            "company_name": "BORÅS YÄSKINDUSTRI, AB",
            "pnr": "50107",
            "address": "Borås 1, Box 450, Göteborgsv 10",
            "phone_number": "033-12 90 50, 13 45 50",
            "bank_details": {
                "bankgiro": "83-9430",
                "postgiro": "495802"
            },
            "activity": "Tillverkar shoppingsväskor, sport- o. resesäckar",
            "employees": 34,
            "key_personnel": [
                {
                    "name": "Kurt Isaksson",
                    "position": "Ägare o chefer"
                },
                {
                    "name": "Elof Johansson",
                    "position": "Ägare o chefer"
                }
            ],
            "establishment_year": 1955
        }
    }
}