{
    "original": "SAFT- &amp; VINFABRIKEN, AB\n\nPnr 524 00\n\nHerrljunga, Box 63. Tel\n0513-10063. Bankgiro 84-1015. Postgiro\n9401\n\nVerksamhet: Tillverkar saft o\nalkoholfria festdrycker\n\nAntal anställda: 10\nÅrsomsättning: 1500 000\nAktiekapital: 135 000\nVerkst dir: Pabr Bertil Branmark\nEtableringsån 1911.\n\nFORSBLAD &amp; SON\n\nPnr 42102\n\nVästra Frölunda 2, Box 2029.\nFrö-klöversg 5. Tel 031-49 02 50.\nBankgiro 848-1103. Postgiro 40261-0.\nTelex 20704 FORSBLD S\nVerksamhet: Internationella\ntransporter per bil, järnväg, flyg o\nfartyg. Samlastnings- o\ncontainertrafik. Förtullnings- o\ndistributionsservice. Lagring\nAntal anstäUda: 29\nÅrsomsättning: 22 000 000\nChef: Dir Ingvar Dihné\nSped-chef: Morgan Alfredsson\nChef allmän importavd: Weine\nCarlsson\n\nChef Fjärran Ostern-import: Jan\n\nGunnarson\n\nChef exportavd: Erland Holmström\nEtableringsår: 1878.\n\nBER\n\nAntal anställda: 65\nAktiekapital: 50 000\nVerkst dir: Byggn-ing Hugo\nBerndts son\nEtableringsår: 1951.\n\nMYRESJOHUS, EGNA HEM AB\n\nPnr 570 13\n\nMyresjö. Tel 0383-91100.\nBankgiro 447-1918. Postgiro 275800-1.\nTga Myresjö hus, Vetlanda.\nTelex 3709\n\nVerksamhet: Monteringsfärdiga\nträhus, fönstersnickerier, trävaror,\nentreprenader\n\nFörsäljningsavdelning: Vetlanda,\nIndustrig 25. Tel 0383-140 00\nAntal anstäUda: 500\nÅrsomsättning: 65 000 000\n\nMÅKEBA.PLAST AB\n\nPnr 440 42\n\nAlafors. Tel 0303-412 52. Bankgiro\n46-8680. Postgiro 629324\nVerksamhet: Glober o\nbelysningskupor av akrylplast\nAntal anstäUda: 8\nAktiekapital: 25 000\nVerkst dir: Stig Mårtensson\nEtableringsår: 1966.\n\nTHERMOSCAN VÄRME AB\n\nPnr 21137\n\nMalmö, Stora Nyg 5. Tel\n040-1005 30. Bankgiro 875-6314.\nPost&gt;-giro 632849-6. Tga Thermoscan.\nTelex 32246 TRMSCAN S\nVerksamhet: Säljer värmepannor o\ntryckexpansionskärl för villor,\ncirkulationspumpar, oljefilter o\nvattenreningsfilter\nVarunamn: Thermoscan, Klemm,\nMicrosil\n\nAntal anställda: 4\n\nÅrsomsättning: 2 000 000\n\nAktiekapital: 15 000\nVerkst dir: G Laszlo\nEtableringsår: 1965.\n\nALBIN MOTOR AB\n\nPnr 68101\n\nKristinehamn 1, Fack. Tel\n0550-150 00. Bankgiro 819-9309.\nPostgiro 6692-8. Tga Albin. Telex\n66195\n\nVerksamhet: Tillverkar båtmotorer,\npumpar, brandsprutor, snäck- o\ntappväxlar, snäckväxelmotorer,\nkugghjul\n\nVarunamn: Albin\nAntal anställda: 250\nÅrsomsättning: 20 000 000\nAktiekapital: 700 000\nStyrelse: Dir Sven Widemar (ordf),\nflygdir Sture Edvardsson, dir Lars\nLarsson, bruksdisp Bo Risberg\nVerkst dir: Lars Larsson\nKamrer: Henrik Lindqvist\nInköpschef: O Andersson\nEtableringsår: 1900.\n\nDAHLSKOGS FÄRGHANDEL, G\n\nPnr 53100\n\nLidköping, Mellbyg 2. Tel\n0510-202 50. Bankgiro 84-1308.\nPostgiro 21032\n\nVerksamhet: Färger, tapeter o\nkem tekn artiklar i parti o minut\nAntal anställda: 6\nÄgare o chef: Färgh Gösta\nDahlskog\n\nEtableringsår: 1912.\n\nFEGENS SÅGVERKS AB\n\nPnr 310 62\n\nFegen. Tel 0346-610 80,61128.\nBankgiro 546-63625. Postgiro\n324655-0\n\nVerksamhet: Plank, bräder,\nspar-rar, pålar o långtimmer\nAntal anställda: 10\nÅrsomsättning: 1800 000\nAktiekapital: 100 000\nVerkst dir: Anders Andersson\nEtableringsår: 1961.\n\nFEINGOLD TERMOMETER.\nFABRIK AB, I\n\nPnr 63107\n\nEskilstuna 1, Box 554. Rinmansg\n7. Tel 016-13 7 7 25. Bankgiro\n369-3686. Postgiro 324811-9. TgalFT\nVerksamhet: Tillverkar\ntermometrar o maskintillverkade\nglasinstrument, pressade o automatsvarvade\nmetalldelar\nAntal anställda: 50\nÅrsomsättning: 3 000 000\n\nAktiekapital: 100 000\nVerkst dir: Fabr I Feingold\nEtableringsår: 1959.\n\nLEVY AB, HERBERT\n\nPnr 41108\n\nGöteborg, Kungsg 56. Tel\n031-13 90 80, 10 55 44. Bankgiro\n50-0794. Postgiro 48378. Tga Herlev.\nTelex 2589\n\nVerksamhet: Textilagenturer\nAktiekapital: 20 000\nVerkst dir: Gert Levy\nEtableringsår: 1946\nOmbildat till aktiebolag 1960.\n\nLEYBOLD-HERAEUSAB\n\nPnr 42131\n\nVästra Frölunda, Frökotteg 10. Tel\n031-49 04 05. Bankgiro 506-1981.\nPostgiro 623030-4. Tga Heravac.\nTelex 21193\n\nVerksamhet: Komplett program\ninom högvakuumtekniken\nVerkstad: Västra Frölunda.\nLey-bold-Heraeus Service AB, Frökotteg\n10. Tel 031-49 04 05\nVarunamn: Leybold-Heraeus\nAktiekapital: 100 000\nVerkst dir: Lars Erik Ekdahl\nEtableringsår: 1962.\n\nHAMMARGREN &amp; CO AB\n\nPnr 434 0 2\n\nKungsbacka 2, Box 68. Tel\n0300-21110. Bankgiro 426-4404.\nPostgiro 25444-1\n\nVerksamhet:\nFyrverkeripjäser,facklor, marschaller, pyroteknisk\nsignal-materiel, serpentiner,\njulgransbloss. Generalagent för\nWinches-ters, USA, vapen o ammunition\nAntal anstäUda: 100\nÅrsomsättning: 10 000 000\nAktiekapital: 175 000\nStyrelse: Adv Arne Hallman (ordf),\ndir Per Uno Hammargren, dir Rune\nSundberg, Richard Hammargren\nVerkst dir: Per Uno Hammargren\nV verkst dir: Rune Sundberg\nFabrikschef: Curt Andersson\nKamrer: Albin Larsson\nEtableringsår: 1879\nHelägt dotterbolag: Annebergs\nIndustrier AB, Anneberg.\n\nHAMMARGRENS STÄMPLAR\nAB\n\nPnr 20011\n\nMalmö 6, Norreg 3. Box 6027. Tel\n040-12 3153, 12 66 90. Bankgiro\n87-4850. Postgiro 38915\nVerksamhet: Tillverkar o säljer\nstämplar samt plast- o\ngummiklichéer\n\nAktiekapital: 20 000\nStyrelse: Dir Harald Johansson\n(ordf), Sixten Johansson\nVerkst dir: Harald Johansson\nEtableringsår: 1905.",
    "structured": {
        "1": {
            "company_name": "SAFT- & VINFABRIKEN, AB",
            "pnr": "524 00",
            "address": "Herrljunga, Box 63",
            "phone_number": "0513-10063",
            "bank_details": {
                "bankgiro": "84-1015"
            },
            "activity": "Tillverkar saft o alkoholfria festdrycker",
            "employees": 10,
            "annual_turnover": 1500000,
            "capital": 135000,
            "key_personnel": [
                {
                    "name": "Pabr Bertil Branmark",
                    "position": "Verkst dir"
                }
            ],
            "establishment_year": 1911
        },
        "2": {
            "company_name": "FORSBLAD & SON",
            "pnr": "42102",
            "address": "Västra Frölunda 2, Box 2029, Frö-klöversg 5",
            "phone_number": "031-49 02 50",
            "bank_details": {
                "bankgiro": "848-1103"
            },
            "activity": "Internationella transporter per bil, järnväg, flyg o fartyg. Samlastnings- o containertrafik. Förtullnings- o distributionsservice. Lagring",
            "employees": 29,
            "annual_turnover": 22000000,
            "establishment_year": 1878
        },
        "3": {
            "company_name": "BER",
            "employees": 65,
            "capital": 50000,
            "key_personnel": [
                {
                    "name": "Byggn-ing Hugo Berndts son",
                    "position": "Verkst dir"
                }
            ],
            "establishment_year": 1951
        },
        "4": {
            "company_name": "MYRESJOHUS, EGNA HEM AB",
            "pnr": "570 13",
            "address": "Myresjö, Tga Myresjö hus, Vetlanda",
            "phone_number": "0383-91100",
            "bank_details": {
                "bankgiro": "447-1918"
            },
            "activity": "Monteringsfärdiga trähus, fönstersnickerier, trävaror, entreprenader",
            "employees": 500,
            "annual_turnover": 65000000
        },
        "5": {
            "company_name": "MÅKEBA.PLAST AB",
            "pnr": "440 42",
            "address": "Alafors",
            "phone_number": "0303-412 52",
            "bank_details": {
                "bankgiro": "46-8680"
            },
            "activity": "Glober o belysningskupor av akrylplast",
            "employees": 8,
            "capital": 25000,
            "key_personnel": [
                {
                    "name": "Stig Mårtensson",
                    "position": "Verkst dir"
                }
            ],
            "establishment_year": 1966
        },
        "6": {
            "company_name": "THERMOSCAN VÄRME AB",
            "pnr": "21137",
            "address": "Malmö, Stora Nyg 5",
            "phone_number": "040-1005 30",
            "bank_details": {
                "bankgiro": "875-6314"
            },
            "activity": "Säljer värmepannor o tryckexpansionskärl för villor, cirkulationspumpar, oljefilter o vattenreningsfilter",
            "employees": 4,
            "annual_turnover": 2000000,
            "capital": 15000,
            "key_personnel": [
                {
                    "name": "G Laszlo",
                    "position": "Verkst dir"
                }
            ],
            "establishment_year": 1965
        },
        "7": {
            "company_name": "ALBIN MOTOR AB",
            "pnr": "68101",
            "address": "Kristinehamn 1, Fack",
            "phone_number": "0550-150 00",
            "bank_details": {
                "bankgiro": "819-9309"
            },
            "activity": "Tillverkar båtmotorer, pumpar, brandsprutor, snäck- o tappväxlar, snäckväxelmotorer, kugghjul",
            "employees": 250,
            "annual_turnover": 20000000,
            "capital": 700000,
            "key_personnel": [
                {
                    "name": "Lars Larsson",
                    "position": "Verkst dir"
                }
            ],
            "establishment_year": 1900
        },
        "8": {
            "company_name": "DAHLSKOGS FÄRGHANDEL, G",
            "pnr": "53100",
            "address": "Lidköping, Mellbyg 2",
            "phone_number": "0510-202 50",
            "bank_details": {
                "bankgiro": "84-1308"
            },
            "activity": "Färger, tapeter o kem tekn artiklar i parti o minut",
            "employees": 6,
            "key_personnel": [
                {
                    "name": "Färgh Gösta Dahlskog",
                    "position": "Ägare o chef"
                }
            ],
            "establishment_year": 1912
        },
        "9": {
            "company_name": "FEGENS SÅGVERKS AB",
            "pnr": "310 62",
            "address": "Fegen",
            "phone_number": "0346-610 80,61128",
            "bank_details": {
                "bankgiro": "546-63625"
            },
            "activity": "Plank, bräder, spar-rar, pålar o långtimmer",
            "employees": 10,
            "annual_turnover": 1800000,
            "capital": 100000,
            "key_personnel": [
                {
                    "name": "Anders Andersson",
                    "position": "Verkst dir"
                }
            ],
            "establishment_year": 1961
        },
        "10": {
            "company_name": "FEINGOLD TERMOMETER. FABRIK AB, I",
            "pnr": "63107",
            "address": "Eskilstuna 1, Box 554, Rinmansg 7",
            "phone_number": "016-13 7 7 25",
            "bank_details": {
                "bankgiro": "369-3686"
            },
            "activity": "Tillverkar termometrar o maskintillverkade glasinstrument, pressade o automatsvarvade metalldelar",
            "employees": 50,
            "annual_turnover": 3000000,
            "capital": 100000,
            "key_personnel": [
                {
                    "name": "Fabr I Feingold",
                    "position": "Verkst dir"
                }
            ],
            "establishment_year": 1959
        },
        "11": {
            "company_name": "LEVY AB, HERBERT",
            "pnr": "41108",
            "address": "Göteborg, Kungsg 56",
            "phone_number": "031-13 90 80, 10 55 44",
            "bank_details": {
                "bankgiro": "50-0794"
            },
            "activity": "Textilagenturer",
            "capital": 20000,
            "key_personnel": [
                {
                    "name": "Gert Levy",
                    "position": "Verkst dir"
                }
            ],
            "establishment_year": 1946
        },
        "12": {
            "company_name": "LEYBOLD-HERAEUSAB",
            "pnr": "42131",
            "address": "Västra Frölunda, Frökotteg 10",
            "phone_number": "031-49 04 05",
            "bank_details": {
                "bankgiro": "506-1981"
            },
            "activity": "Komplett program inom högvakuumtekniken",
            "employees": 100,
            "capital": 100000,
            "key_personnel": [
                {
                    "name": "Lars Erik Ekdahl",
                    "position": "Verkst dir"
                }
            ],
            "establishment_year": 1962
        },
        "13": {
            "company_name": "HAMMARGREN & CO AB",
            "pnr": "434 0 2",
            "address": "Kungsbacka 2, Box 68",
            "phone_number": "0300-21110",
            "bank_details": {
                "bankgiro": "426-4404"
            },
            "activity": "Fyrverkeripjäser, facklor, marschaller, pyroteknisk signal-materiel, serpentiner, julgransbloss. Generalagent för Winches-ters, USA, vapen o ammunition",
            "employees": 100,
            "annual_turnover": 10000000,
            "capital": 175000,
            "key_personnel": [
                {
                    "name": "Per Uno Hammargren",
                    "position": "Verkst dir"
                },
                {
                    "name": "Rune Sundberg",
                    "position": "V verkst dir"
                },
                {
                    "name": "Curt Andersson",
                    "position": "Fabrikschef"
                }
            ],
            "establishment_year": 1879
        },
        "14": {
            "company_name": "HAMMARGRENS STÄMPLAR AB",
            "pnr": "20011",
            "address": "Malmö 6, Norreg 3, Box 6027",
            "phone_number": "040-12 3153, 12 66 90",
            "bank_details": {
                "bankgiro": "87-4850"
            },
            "activity": "Tillverkar o säljer stämplar samt plast- o gummiklichéer",
            "capital": 20000,
            "key_personnel": [
                {
                    "name": "Harald Johansson",
                    "position": "Verkst dir"
                }
            ],
            "establishment_year": 1905
        }
    }
}