{
    "original": "TIDBECK AB, J H\n\nPnr 123 21\n\nFarsta 1, Edsvallabacken 20-24.\nBox 98. Tel 08-93 04 70. Bankgiro\n734-4039. Postgiro 3174-0.\nTelex 17467\n\nVerksamhet: Metallduksväveri o\nstålgallerfabrik. Tillverkar vävd\ntrådduk, krenelerade o pressade\ngaller, harpgaller, trådflätning samt\ntransportband\nAntal anställda: 50\nÅrsomsättning: 6 000 000\nAktiekapital: 900 000\nStyrelse: Disp Sture Tidbeck\n(ordf), fru Lisa Hellberg, dir Gösta\nTidbeck\n\nVerkst din Gösta Tidbeck\nEtableringsår: 1840.\n\nTIDEN.BARNÄNGEN\nTRYCKERIER AB\n\nPnr 102 62\n\nStockholm 4, Barnängsg 21 A. Box\n4128. Tel 08-68 00 60. Bankgiro\n33-1405. Postgiro 55273. Tga\nTibatryck\n\nVerksamhet: Bok-, offset- o\ndjuptryck, bokbinderi o datablanketter\nAntal anställda: 459\nÅrsomsättning: 42 000 000\nAktiekapital: 3 000 000\nVerkst din Töre Sohlström\nEtableringsån 1929-\n\nFRENDIN &amp; BORINDER AB\n\nPnr 11435\n\nStockholm, Stureg 4. Tel 08-\n\n23 37 30\n\nVerksamhet: Konsulter inom\nhusbyggnadsfacket.\n\nFREON.KYL AB\n\nPnr 402 74\n\nGöteborg 8, Box 8946. Hildebrandsg\n1. Tel 031-222215. Bankgiro\n848-2093. Postgiro 241517-2. Tga\nFre-onkyl. Telex 20097 FREOKYL S\n\nklimatstyrning\n\nVerksamhet: Carrier klimatstyrning,\nkyl- o frysanläggningar\nStockholmskontor: Tel 08-880270\nMalmökontor. Tel 040-101320\nVarunamn: Carrier\nAntal anställda: 54\nÅrsomsättning: 15 000 000\nAktiekapital: 200 000\nVetkst dir: Dir Richard W Peterson\nEtableringsår: 1946.\n\nSELARCO, AB\n\nPnr 102 30\n\nStockholm 6. Fack. Dalag 6. Tel\n08-24 04 20, 24 48 85. Bankgiro\n700-1472. Postgiro 4546-8. Tga Selarco\nVerksan*et: Importerar o säljer\ncigarettändare o pipor, gasbrännare\nAntal anställda: 24\nÅrsomsättning: 7 000 000\nAktiekapital: 75 000\nVeikst din Claës-Olof Carlsen\nEtableringsån 1939.\n\ngyl\n\ngyllo, industrifirman\n\nPnr 332 00\n\nGislaved, Baldersv 18. Tel\n0371-102 88. Bankgiro 14-3015. Postgiro\n130442\n\nVerksamhet: Delikatess snabbrök,\nfiskeväskor, campingmadrasser\nAntal anställda: 6\nÅrsomsättning: 250000\nChef: Polke Claesson.\n\ngyllsjd träindustri, ab\n\nPnr 264 00\n\nKlippan, KopparmöUan 5421. Tel\n0435-22010, 220 27. Bankgiro\n65-7333. Postgiro 468246\nVerksamhet: Tillverkar lastpallar,\npallramar o grövre emballage\nAntal anställda: 40\nÅrsomsättning: 3000000\nAktiekapital: 150000\nVerkst dir: Ivar Svensson\nEtableringsår: 1946.\n\nÅBERG AB, MÖBELFIRMAN G\n\nPnr 570 21\n\nMalmbäck, Agatan 7. Box 81. Tel\n\n0380-603 00, 603 01. Bankgiro\n14-5729. Postgiro 86189. Tga\nMöbel-Aberg\n\nVerksamhet:\nStoppmöbeltillverkning, bord\nAntal anställda: 21\nÅrsomsättning: 1500 000\nAktiekapital: 75 000\nVerkst dir: Hertha Åberg\nEtableringsår: 1932.\n\nÅBERG KONTORSMOBLER\nAB. GUNNAR\n\nPnr ill 31\n\nStockholm, öster långg 24. Tel\n08-1154 45, 2183 88. Bankgiro\n729-5256. Postgiro 50406-8\nVerksamhet: Säljer kontorsmöbler\nAktiekapital: 5 000\nVeikst dir: Stig Arenander\nEtableringsår: 1914.\n\nÅBERGS TRYCKERI AB,\nOSCAR\n\nPnr 273 00\n\nTomelilla. Tel 0417-10192, 103 52.\nBankgiro 35-1835, 67-0343.\nPost-giro 30517-7\n\nVerksamhet: Boktryck,\nrotationstryck, datablanketter, snabbiägg\nAntal anställda: 24\nÅrsomsättning: 1500 000\nAktiekapital: 75 000\nVerkst dir: Kaj Brorsson\nEtableringsår: 1921.\n\nMETRO-BUTIKERNA AB\n\nPnr 112 51\n\nStockholm, Strandbergs g 57. Tel\n08-54 0100\n\nVeiksamhet: Livsmedelsbutiker i\nStor-Stockholm o Stor-Göteborg\nAktiekapital: 6000 000\nVerkst dir: Carl Henrik Nordmark\nEtableringsår: 1890.\n\nTEANIK AB\n\nPnr 440 03\n\nFloda. Tel 0302-307 81, 307 82.\nBankgiro 547-7369. Postgiro\n623597-2\n\nVerksamhet: Tillverkar o säljer\nTeanik ridåväggar för temporär\navdelning av idrottshallar o\nliknande lokaler i två eller flera delar.\nHöj- o sänkbara entrépartier för\nvaruhus o andra affärslokaler.\nUtrustningar för teatrar såsom\nscen-belysning med\nbelysningskontroller, kulisshissar, ridåbanor, ridåer\no scentextilier. Hopskjutbara\npodier o sittplatsläktare\nAntal anställda: 22\nÅrsomsättning: 2000 000\nAktiekapital: 50 000\nVerkst dir: Bo Larsson\nEtableringsår: 1962.\n\nTEBECO\n\nINDUSTRIPRODUKTER\n\n(Konsortium)\n\nPnr 302 48\n\nHalmstad, Sperlingsg 1. Tel\n035-119075. Tga Tebeco\nDisp: Alf Thornberg. Ing: Lennart\nForslund, Malmö\n\n41137 Göteborg, Kristinelundsg 7.\nTel 031-16 89 06, 16 89 23. Tga\nTebeco. Disp: Tage Bornum\nGävle, pa 81042 Mackmyra. Box 7.\nTel 026-13 2275. Disp: Ake Lager\nVerksamhet: Maskiner o\nförnödenheter för gjuteri o mek\nverkstadsindustrin\n\nEtableringsår: 1966.\n\nNORDLJUS-VERKSTÄDERNA\n\nPnr 570 70\n\nHögsby. Tel 0491-204 86. Tga\nNordljus\n\nVerksamhet: Glasmåleri, armatur- o\nskyltindustri\nChef: Werner Queiser\nEtableringsår: 1956.\n\nBERG AB, J W\n\nPnr 430 93\n\nHälsö. Tel 031-79 13 00. Tga\nHälsö-berg. Telex 2436\nVerksamhet: Fartygsreparationer,\ndäcksutrustning mm\nAntal anställda: 70\nÅrsomsättning: 8 000 000\nAktiekapital: 200000\nVerkst dir: Stig Jonsson\nEtableringsår: 1926.\n\nHASKEL PROPAGANDA AB\n\nPnr 100 21\n\nStockholm 18, Hantverkarg 52.\nBox 18067. Tel 08-23 52 70.\nBankgiro 48-3126. Postgiro 114648.\nTga Haskelprop\n\nVerksamhet: Kompensauktoriserad\no förmedlingsnominerad reklambyrå\nAntal anstäUda: 21\nÅrsomsättning: 10 000 000\n\nAktiekapital: 125 000\nVerkst dir: Joel Haskel\nEtableringsår: 1957.\n\nHASSAB\n\nHANS HASSNERT AB\n\nPnr 430 80\n\nHovås, Postl 402. Tel 031-28 34 40,\n28 3441. Bankgiro 44-4326.\nPostgiro 46047\n\nVerksamhet: Anläggningsarbeten,\nasfaltbeläggningar,\nträdgårdsanläggningar\nAntal anstäUda: 35\nÅrsomsättning: 2 500 000\nAktiekapital: 25 000\nVerkst dir: Ing Hans Hassnert\nEtableringsår: 1965.",
    "structured": {
        "1": {
            "company_name": "TIDBECK AB",
            "activity": "Metallduksväveri och stålgallerfabrik. Tillverkar vävd trådduk, krenelerade och pressade galler, harpgaller, trådflätning samt transportband",
            "establishment_year": 1840,
            "employees": 50,
            "annual_turnover": 6000000,
            "capital": 900000,
            "key_personnel": [
                {
                    "name": "Disp Sture Tidbeck",
                    "position": "ordf"
                },
                {
                    "name": "fru Lisa Hellberg"
                },
                {
                    "name": "dir Gösta Tidbeck"
                }
            ]
        },
        "2": {
            "company_name": "TIDEN.BARNÄNGEN TRYCKERIER AB",
            "activity": "Bok-, offset- och djuptryck, bokbinderi och datablanketter",
            "establishment_year": 1929
        },
        "3": {
            "company_name": "FRENDIN & BORINDER AB",
            "activity": "Konsulter inom husbyggnadsfacket",
            "address": "Stockholm, Stureg 4",
            "phone_number": "08-23 37 30"
        },
        "4": {
            "company_name": "FREON.KYL AB",
            "activity": "Carrier klimatstyrning, kyl- och frysanläggningar",
            "establishment_year": 1946,
            "employees": 54,
            "annual_turnover": 15000000,
            "capital": 200000,
            "key_personnel": {
                "name": "Dir Richard W Peterson",
                "position": "Vetkst din"
            }
        },
        "5": {
            "company_name": "SELARCO, AB",
            "activity": "Importerar och säljer cigarettändare och pipor, gasbrännare",
            "establishment_year": 1939,
            "employees": 24,
            "annual_turnover": 7000000,
            "capital": 75000,
            "key_personnel": {
                "name": "Claës-Olof Carlsen",
                "position": "Veikst din"
            }
        },
        "6": {
            "company_name": "gyllö, industrifirman",
            "activity": "Delikatess snabbrök, fiskeväskor, campingmadrasser",
            "address": "Gislaved, Baldersv 18",
            "phone_number": "0371-102 88",
            "bank_details": {
                "bankgiro": "14-3015",
                "postgiro": "130442"
            },
            "employees": 6,
            "annual_turnover": 250000
        },
        "7": {
            "company_name": "gyllsjd träindustri, ab",
            "activity": "Tillverkar lastpallar, pallramar och grövre emballage",
            "address": "Klippan, KopparmöUan 5421",
            "phone_number": "0435-22010, 220 27",
            "bank_details": {
                "bankgiro": "65-7333",
                "postgiro": "468246"
            },
            "employees": 40,
            "annual_turnover": 3000000,
            "capital": 150000,
            "key_personnel": {
                "name": "Ivar Svensson",
                "position": "Verkst dir"
            },
            "establishment_year": 1946
        },
        "8": {
            "company_name": "ÅBERG AB, MÖBELFIRMAN G",
            "activity": "Stoppmöbeltillverkning, bord",
            "address": "Malmbäck, Agatan 7",
            "phone_number": "0380-603 00, 603 01",
            "bank_details": {
                "bankgiro": "14-5729",
                "postgiro": "86189"
            },
            "employees": 21,
            "annual_turnover": 1500000,
            "capital": 75000,
            "key_personnel": {
                "name": "Hertha Åberg",
                "position": "Verkst dir"
            },
            "establishment_year": 1932
        },
        "9": {
            "company_name": "ÅBERG KONTORSMOBLER AB. GUNNAR",
            "activity": "Säljer kontorsmöbler",
            "address": "Stockholm, öster långg 24",
            "phone_number": "08-1154 45, 2183 88",
            "bank_details": {
                "bankgiro": "729-5256",
                "postgiro": "50406-8"
            },
            "capital": 5000,
            "key_personnel": {
                "name": "Stig Arenander",
                "position": "Verkst dir"
            },
            "establishment_year": 1914
        },
        "10": {
            "company_name": "ÅBERGS TRYCKERI AB, OSCAR",
            "activity": "Boktryck, rotationstryck, datablanketter, snabbiägg",
            "address": "Tomelilla",
            "phone_number": "0417-10192, 103 52",
            "bank_details": {
                "bankgiro": "35-1835",
                "postgiro": "30517-7"
            },
            "employees": 24,
            "annual_turnover": 1500000,
            "capital": 75000,
            "key_personnel": {
                "name": "Kaj Brorsson",
                "position": "Verkst dir"
            },
            "establishment_year": 1921
        },
        "11": {
            "company_name": "METRO-BUTIKERNA AB",
            "activity": "Livsmedelsbutiker i Stor-Stockholm och Stor-Göteborg",
            "address": "Stockholm, Strandbergs g 57",
            "phone_number": "08-54 0100",
            "capital": 6000000,
            "key_personnel": {
                "name": "Carl Henrik Nordmark",
                "position": "Verkst dir"
            },
            "establishment_year": 1890
        },
        "12": {
            "company_name": "TEANIK AB",
            "activity": "Tillverkar och säljer Teanik ridåväggar för temporär avdelning av idrottshallar och liknande lokaler i två eller flera delar. Höj- och sänkbara entrépartier för varuhus och andra affärslokaler. Utrustningar för teatrar såsom scen-belysning med belysningskontroller, kulisshissar, ridåbanor, ridåer och scentextilier. Hopskjutbara podier och sittplatsläktare",
            "address": "Floda",
            "phone_number": "0302-307 81, 307 82",
            "bank_details": {
                "bankgiro": "547-7369",
                "postgiro": "623597-2"
            },
            "employees": 22,
            "annual_turnover": 2000000,
            "capital": 50000,
            "key_personnel": {
                "name": "Bo Larsson",
                "position": "Verkst dir"
            },
            "establishment_year": 1962
        },
        "13": {
            "company_name": "TEBECO INDUSTRIPRODUKTER (Konsortium)",
            "address": "Halmstad, Sperlingsg 1",
            "phone_number": "035-119075",
            "key_personnel": [
                {
                    "name": "Alf Thornberg",
                    "position": "Disp"
                },
                {
                    "name": "Lennart Forslund",
                    "position": "Ing",
                    "location": "Malmö"
                }
            ],
            "establishment_year": 1966
        },
        "14": {
            "company_name": "NORDLJUS-VERKSTÄDERNA",
            "activity": "Glasmåleri, armatur- och skyltindustri",
            "address": "Högsby",
            "phone_number": "0491-204 86",
            "chef": "Werner Queiser",
            "establishment_year": 1956
        },
        "15": {
            "company_name": "BERG AB, J W",
            "activity": "Fartygsreparationer, däcksutrustning mm",
            "address": "Hälsö",
            "phone_number": "031-79 13 00",
            "telex": "2436",
            "employees": 70,
            "annual_turnover": 8000000,
            "capital": 200000,
            "key_personnel": {
                "name": "Stig Jonsson",
                "position": "Verkst dir"
            },
            "establishment_year": 1926
        },
        "16": {
            "company_name": "HASKEL PROPAGANDA AB",
            "activity": "Kompensauktoriserad och förmedlingsnominerad reklambyrå",
            "address": "Stockholm 18, Hantverkarg 52",
            "phone_number": "08-23 52 70",
            "bank_details": {
                "bankgiro": "48-3126",
                "postgiro": "114648"
            },
            "employees": 21,
            "annual_turnover": 10000000,
            "capital": 125000,
            "key_personnel": {
                "name": "Joel Haskel",
                "position": "Verkst dir"
            },
            "establishment_year": 1957
        },
        "17": {
            "company_name": "HASSAB HANS HASSNERT AB",
            "activity": "Anläggningsarbeten, asfaltbeläggningar, trädgårdsanläggningar",
            "address": "Hovås, Postl 402",
            "phone_number": "031-28 34 40, 28 3441",
            "bank_details": {
                "bankgiro": "44-4326",
                "postgiro": "46047"
            },
            "employees": 35,
            "annual_turnover": 2500000,
            "capital": 25000,
            "key_personnel": {
                "name": "Ing Hans Hassnert",
                "position": "Verkst dir"
            },
            "establishment_year": 1965
        }
    }
}