{
    "original": "HÄLLARYDSTURBINER, AB\n\nPnr 574 00\n\nVetlanda, Postl 3006. Tel\n0383-51065. Postgiro 475509\nVerksamhet: Tillverkar o säljer\nvattenturbiner o regulatorer\nAntal anställda: 7\n\nAktiekapital: 40 000\nVerkst dir: Gösta Lundgren\nEtableringsår 1954.\n\nB LA\n\nAntal anställda: 31\nÅrsomsättning: 6 500 000\nAktiekapital: 320 000\nVerkst dir: Ake Heldeby\nEtableringsår: 1907.\n\nEMINENTVERKTYG, AB\n\nPnr 644 00\n\nTorshälla. Tel 016-557 40.\nBankgiro 828-0125. Postgiro 84626-1\nVerksamhet: Tillverkar\navloppsre-nare, bandsaxar, borrchuckar,\nborr-svängar, bågfilsställningar,\nkiljagare, isborrar, klädhängare för\nbalkonger, kvistsågar, ’Perman’\nfräs-chuckar oexpanderande dornar samt\n’Perman’ Quicklocksnabblås för\nverktygshållare, slangklämmor,\nspånkrokar, strykmått, ställbara\nhaknycklar, vinklar samt pressade,\nsvarvade, frästa, slipade\nmassartiklar\n\nVarunamn: Atlas, Eda, Eminent,\nEV, Handy, Perman\nAktiekapital: 100 000\nVetkst dir: Bertil Karlsson\nVerkstadschef: Ake Oqvist\nFörsäljn-chef: Curt Svensson\nEtableringsår: 1933\nOmbildat till aktiebolag 1950.\n\nEM-JI AB\n\nPnr 12162\n\nJohanneshov, Slakthuset. Tel\n08-59 02 00. Bankgiro 284-5097.\nPostgiro 190530-6\n\nVerksamhet: Styckning av kött o\nfläsk, grossistförsäljning\nAntal anställda: 40\nÅrsomsättning: 40 000000\nAktiekapital: 200000\nVerkst din Lars Hansson\nEtableringsår: 1945.\n\nCAMO-MEYER AB\n\nPnr 15010\n\nGnesta, O Storg 33. Box 123. Tel\n0158-100 95,114 95. Bankgiro\n60-7826. Postgiro 177508\nVerksamhet: Tillverkar\nreklam-ställ, inredning av guldsmeds- o\nurdiskar\n\nAntal anställda: 12\nÅrsomsättning: 500 000\nAktiekapital: 25 000\nVerkst dir: Einar Gustavsson\nEtableringsår: 1924.\n\nSTILDUKAR AB\n\nPnr 402 71\n\nGöteborg 8, Box 8803. Gamla Tuvev\n20. Tel 031-2282 55. Bankgiro\n851-7328. Postgiro 422267-5. Tga\nStildukab\n\nVerksamhet: Tillverkar o\nimporterar tryckta o sydda dukar\nAntal anställda: 60\nÅrsomsättning: 5 000 000\nAktiekapital: 135 000\nVerkst dir: Bertil Larsson\nEtableringsår: 1957.\n\nFLO\n\nförarstolar, patenterade\nsäkerhets-lås för bildörrar, solskydd,\ntakräcken o stegar m fi\nutrustningsdetaljer. Monterar o säljer tippar,\nlastapparater, boggielyfter m m för\nlastbilar\nVarunamn: Piab\nAntal anställda: 90\nÅrsomsättning: 5 000 000\nAktiekapital: 230 000\nStyrelse: Fru Alfhild Kringlund\n(ordf), handl Bengt Kringlund,\ndisp Erland Persson, fru Helga\nPersson\n\nVerkst dir: G E Persson\nEtableringsår: 1918\nOmbildat till aktiebolag 1928.\n\nFLOBY METALL AB\n\nPnr 520 40\n\nFloby. Tel 0515-402 24. Bankgiro\n542-1227. Postgiro 384523-7\nVerksamhet: Tillverkar armatur för\nvatten, värme o olja. Metallgjut.\ngods\n\nAntal anställda: 10\nÅrsomsättning: 700 000\nAktiekapital: 30 000\nVerkst dir. Erik Isaksson\nEtableringsån 1947.\n\nmaxes industriarmatur\n\nPnr 124 21\n\nBandhagen 1, Skebokvarnsv 324.\nBox 43. Tel 08-860165. Bankgiro\n74-6936. Postgiro 550979\nVerksamhet: Säljer armatur inom\nVVS-branschen\nVarunamn: Aswa, Westad\nChef: Ing Gunnar Maxe.\n\nmaximal, ab\n\nPnr 183 04\n\nTäby 4. Box 4069. Tel 08-7561540.\nPostgiro 502380. Tga Maximalbolag\nVerksamhet: Säljer maskiner o\nbyggvaror\n\nVarunamn: Temposchaler\nAktiekapital: 5 000\nVerkst dir: Claes Göran Elcar\nEtableringsår: 1953.\n\nFÄGERBLADS REPRO AB\n\nPnr 72103\n\nVästerås 1, Box 4. Stureg 12.\nTel 021-18 5040. Bankgiro 80-8704.\nPostgiro 139150\nVerksamhet: Tillverkar o säljer\nkemigrafiska o litografiska\nprodukter\n\nFilialer: Västerås, Stolpg 3. Tel\n021-18 5040\n\nGävle, Hattmakar eg 17. Tel\n026-18 9130\n\nSödertälje, Klockarv 94. Tel\n0755-653 00\n\nAntal anställda: 90\n\nÅrsomsättning: 6 500000\n\nAktiekapital: 5 000\n\nStyrelse: Fabr Stig Fägerblad (ordf),\n\nfabr Bo Fägerblad\n\nEtableringsår: 1931\n\nOmbildat till aktiebolag 1969.\n\nFÄGERSTEN &amp; CO, AB S\n\nPnr 414 74\n\nGöteborg, Varholmsg 5. Tel\n031-2417 22, 24 34 00. Bankgiro\n441-7176. Postgiro 244545-0\nVerksamhet: Formsprutning av\nindustriartiklar i termoplastmaterial.\nVerktygstillverkning\nAktiekapital: 50 000\nVerkst dir: Ing C A Sjöström\nEtableringsår: 1947.\n\nEJDERN, MÖBELFABRIKEN\n\nPnr 59800\n\nVimmerby, Storg 38. Box 29. Tel\n0492-107 79, 115 79. Bankgiro\n45-2026. Postgiro 25629\nVerksamhet: Inredningar för\nlaboratorier, sjukhus o skolor\nAntal anställda: 40\nÅrsomsättning: 2000 000\nChef: Pabr Karl Malmberg\nEtableringsån 1924.\n\n13 19 18, 13 19 88. Bankgiro\n80-2183. Postgiro 161857\nVerksamhet: Smides o mekanisk\nverkstad\n\nAntal anställda: 40\nÅrsomsättning: 2 500 000\nAktiekapital: 54 000\nChef: Artur Ek\nEtableringsår: 1940.\n\nNORRVEA, AB\n\nPnr 600 09\n\nNorrköping 9, Box 9045. Ljurag 5.\nTel 011-13 20 20, 18 16 20, Bankgiro\n826-0879. Postgiro 9281-7. Tga\nNorrvea\n\nVerksamhet: Tillverkar o säljer\nråvaror för bageri- o sötvaruindustrin\nFabrik: Norrköping. Norrköpings\nLivsmedelsindustri, Ljurag 5. Tel\n011-1816 20\nVerkst dir: Bo Hansare\nEtableringsår: 1956.",
    "structured": {
        "1": {
            "company_name": "HÄLLARYDSTURBINER, AB",
            "pnr": "574 00",
            "address": "Vetlanda, Postl 3006",
            "phone_number": "0383-51065",
            "postgiro": "475509",
            "activity": "Tillverkar o säljer vattenturbiner o regulatorer",
            "employees": 7,
            "capital": 40000,
            "key_personnel": [
                {
                    "name": "Gösta Lundgren",
                    "position": "Verkst dir"
                }
            ],
            "establishment_year": 1954
        },
        "2": {
            "company_name": "B LA",
            "employees": 31,
            "annual_turnover": 6500000,
            "capital": 320000,
            "key_personnel": [
                {
                    "name": "Ake Heldeby",
                    "position": "Verkst dir"
                }
            ],
            "establishment_year": 1907
        },
        "3": {
            "company_name": "EMINENTVERKTYG, AB",
            "pnr": "644 00",
            "address": "Torshälla",
            "phone_number": "016-557 40",
            "bankgiro": "828-0125",
            "postgiro": "84626-1",
            "activity": "Tillverkar avloppsre-nare, bandsaxar, borrchuckar, borr-svängar, bågfilsställningar",
            "employees": 0,
            "capital": 100000,
            "key_personnel": [
                {
                    "name": "Bertil Karlsson",
                    "position": "Verkst dir"
                },
                {
                    "name": "Ake Oqvist",
                    "position": "Verkstadschef"
                },
                {
                    "name": "Curt Svensson",
                    "position": "Försäljn-chef"
                }
            ],
            "establishment_year": 1933
        },
        "4": {
            "company_name": "EM-JI AB",
            "pnr": "12162",
            "address": "Johanneshov, Slakthuset",
            "phone_number": "08-59 02 00",
            "bankgiro": "284-5097",
            "postgiro": "190530-6",
            "activity": "Styckning av kött o fläsk, grossistförsäljning",
            "employees": 40,
            "capital": 200000,
            "key_personnel": [
                {
                    "name": "Lars Hansson",
                    "position": "Verkst din"
                }
            ],
            "establishment_year": 1945
        },
        "5": {
            "company_name": "CAMO-MEYER AB",
            "pnr": "15010",
            "address": "Gnesta, O Storg 33. Box 123",
            "phone_number": "0158-100 95,114 95",
            "bankgiro": "60-7826",
            "postgiro": "177508",
            "activity": "Tillverkar reklam-ställ, inredning av guldsmeds- o urdiskar",
            "employees": 12,
            "capital": 25000,
            "key_personnel": [
                {
                    "name": "Einar Gustavsson",
                    "position": "Verkst dir"
                }
            ],
            "establishment_year": 1924
        },
        "6": {
            "company_name": "STILDUKAR AB",
            "pnr": "402 71",
            "address": "Göteborg 8, Box 8803. Gamla Tuvev 20",
            "phone_number": "031-2282 55",
            "bankgiro": "851-7328",
            "postgiro": "422267-5",
            "activity": "Tillverkar o importerar tryckta o sydda dukar",
            "employees": 60,
            "capital": 135000,
            "key_personnel": [
                {
                    "name": "Bertil Larsson",
                    "position": "Verkst dir"
                }
            ],
            "establishment_year": 1957
        },
        "7": {
            "company_name": "FLO",
            "activity": "förarstolar, patenterade säkerhetslås för bildörrar, solskydd, takräcken o stegar m fi utrustningsdetaljer",
            "employees": 90,
            "annual_turnover": 5000000,
            "capital": 230000,
            "key_personnel": [
                {
                    "name": "G E Persson",
                    "position": "Verkst dir"
                }
            ],
            "establishment_year": 1918
        },
        "8": {
            "company_name": "FLOBY METALL AB",
            "pnr": "520 40",
            "address": "Floby",
            "phone_number": "0515-402 24",
            "bankgiro": "542-1227",
            "postgiro": "384523-7",
            "activity": "Tillverkar armatur för vatten, värme o olja. Metallgjutgods",
            "employees": 10,
            "annual_turnover": 700000,
            "capital": 30000,
            "key_personnel": [
                {
                    "name": "Erik Isaksson",
                    "position": "Verkst dir"
                }
            ],
            "establishment_year": 1947
        },
        "9": {
            "company_name": "maxes industriarmatur",
            "pnr": "124 21",
            "address": "Bandhagen 1, Skebokvarnsv 324. Box 43",
            "phone_number": "08-860165",
            "bankgiro": "74-6936",
            "postgiro": "550979",
            "activity": "Säljer armatur inom VVS-branschen",
            "key_personnel": [
                {
                    "name": "Ing Gunnar Maxe",
                    "position": "Chef"
                }
            ]
        },
        "10": {
            "company_name": "maximal, ab",
            "pnr": "183 04",
            "address": "Täby 4. Box 4069",
            "phone_number": "08-7561540",
            "postgiro": "502380",
            "activity": "Säljer maskiner o byggvaror",
            "capital": 5000,
            "key_personnel": [
                {
                    "name": "Claes Göran Elcar",
                    "position": "Verkst dir"
                }
            ],
            "establishment_year": 1953
        },
        "11": {
            "company_name": "FÄGERBLADS REPRO AB",
            "pnr": "72103",
            "address": "Västerås 1, Box 4. Stureg 12",
            "phone_number": "021-18 5040",
            "bankgiro": "80-8704",
            "postgiro": "139150",
            "activity": "Tillverkar o säljer kemigrafiska o litografiska produkter",
            "branches": {
                "Västerås": "Stolpg 3",
                "Gävle": "Hattmakar eg 17",
                "Södertälje": "Klockarv 94"
            },
            "employees": 90,
            "annual_turnover": 6500000,
            "capital": 5000,
            "key_personnel": [
                {
                    "name": "Fabr Stig Fägerblad",
                    "position": "Styrelse"
                },
                {
                    "name": "Fabr Bo Fägerblad",
                    "position": "Styrelse"
                }
            ],
            "establishment_year": 1931
        },
        "12": {
            "company_name": "FÄGERSTEN & CO, AB S",
            "pnr": "414 74",
            "address": "Göteborg, Varholmsg 5",
            "phone_number": "031-2417 22, 24 34 00",
            "bankgiro": "441-7176",
            "postgiro": "244545-0",
            "activity": "Formsprutning av industriartiklar i termoplastmaterial. Verktygstillverkning",
            "capital": 50000,
            "key_personnel": [
                {
                    "name": "Ing C A Sjöström",
                    "position": "Verkst dir"
                }
            ],
            "establishment_year": 1947
        },
        "13": {
            "company_name": "EJDERN, MÖBELFABRIKEN",
            "pnr": "59800",
            "address": "Vimmerby, Storg 38. Box 29",
            "phone_number": "0492-107 79, 115 79",
            "bankgiro": "45-2026",
            "postgiro": "25629",
            "activity": "Inredningar för laboratorier, sjukhus o skolor",
            "employees": 40,
            "annual_turnover": 2000000,
            "key_personnel": [
                {
                    "name": "Pabr Karl Malmberg",
                    "position": "Chef"
                }
            ],
            "establishment_year": 1924
        },
        "14": {
            "company_name": "NORRVEA, AB",
            "pnr": "600 09",
            "address": "Norrköping 9, Box 9045. Ljurag 5",
            "phone_number": "011-13 20 20, 18 16 20",
            "bankgiro": "826-0879",
            "postgiro": "9281-7",
            "activity": "Tillverkar o säljer råvaror för bageri- o sötvaruindustrin",
            "branches": {
                "Norrköping": "Norrköpings Livsmedelsindustri, Ljurag 5"
            },
            "key_personnel": [
                {
                    "name": "Bo Hansare",
                    "position": "Verkst dir"
                }
            ],
            "establishment_year": 1956
        }
    }
}