{
    "original": "KAFAK AB\n\nPnr 851 01\n\nSundsvall 1, Fack. Tel 060-15 44 20.\nBankgiro 774^1816. Postgiro\n399811-9. Tga Kafak.\nTelex 71050 KAFAK S\nVerksamhet: Tillverkning.\nTransversala ställverk- o ställverksgolv\nFörsäljningskontor: 411 15 Göteborg,\nKyrkog 40. Tel 031-11 12 04\n200 32 Malmö 18, Box 18085.\nSchee-leg 27. Tel 040-94 63 40\n100 72 Stockholm 43, Box 43007.\n\nLiljeholm storget 12. Tel08-45 91 32,\n19 05 40\n\n701 06 Örebro 1, Box 465. Abyv.\nTel 019-13 00 90\nVarunamn: Gibogi\nAntal anställda: 160\nÅrsomsättning: 20000 000\nAktiekapital: 300 000\nStyrelse: Dir Torsten Lindström\n(ordf), dir T Bergman, dir I\nStrömberg\n\nVerkst dir: T Bergman\nEtableringsår: 1952.\n\nPROMOTION REKLAM PR AB\n\nPnr 11631\n\nStockholm, Renstiernas g 12. Tel\n08-44 60 53, 44 60 54. Bankgiro\n33-0572. Postgiro 400188\nVerksamhet: Av Handelskamrarnas\nNämnd auktoriserad reklamkonsult\nAntal anställda: 5\nÅrsomsättning: 250 000\nAktiekapital: 5 000\nDirektion: Sven-Olof Bergström,\nTom R Gripe, Bertil Gripe\nEtableringsån 1965.\n\nPROVIDENTIA,\nFÖRVALTNINGS AB\n\nPnr 103 24\n\nStockholm 16, Wahrendorffsg 1.\nBox 16174. Tel 08-23 3790.\nBankgiro 16-0454\n\nVerksamhet: Förvaltningsrörelse\n\nAktiekapital: 60 000 000\nVerkst dir: Sven Ture Åberg\nEtableringsår: 1946.\n\nNOR-MASKINER, AB\n\nPnr 400 30\n\nGöteborg 11, Nordenskiöldsg 19.\nBox 11043. Tel 031-14 19 81,14 19 84.\nBankgiro 84-7954. Postgiro 43903.\nTga Normaskin\n\nVerksamhet: Säljer kylmaskiner\nmed tillbehör\nAntal anställda: 3\nÅrsomsättning: 800 000\nAktiekapital: 20 000\nVerkst dir: Bertil Lindh\nEtableringsår: 1947.\n\nAXE\n\nVerksamhet: Utför alla slags\nsmi-des-, plåt- o svetsningsarbeten\nÅrsomsättning: 2 500 000\nÄgare o chef: Fabr A Axelson.\n\nAXELSONS ROSTFRIA, AB\n\nPnr 732 00\n\nArboga, Box 120. Tel 0589-11129,\n130 28. Bankgiro 600-0152.\nPostgiro 389251-0\n\nVerksamhet: Tillverkar rostfria\nhushållsartiklar o sjukvårdsartiklar\nAntal anställda: 32\nÅrsomsättning: 2000 000\nAktiekapital: 50 000\nVerkst dir: Fabr Georg Axelson\nEtableringsår: 1950.\n\nAXELSSONS STAKETFABRIK\nAB\n\nPnr 260 80\n\nMunkaljungby. Tel 0431-304 50.\nBankgiro 896-0270. Postgiro\n381098-3\n\nVerksamhet; Tillverkar staket i trä,\nmed o utan tryckimpregnering,\nJÄ-GARSTAKET o PARAVIND\nSKÄRMSTAKET. Större staketarbeten efter\narkitektritningar\nVarunamn: Jägarstaket\nAntal anställda: 12\nÅrsomsättning: 900 000\nAktiekapital: 10 000\nVerkst dir: Göran Axelsson\nFörsäljn-chef: Curt Axelsson\nEtableringsår: 1964.\n\nATOMENERGI, AB\n\nPnr 61101\n\nNyköping I, Fack. Studsvik. Tel\n0155-800 00. Tga Aterg.\nTelex 64013 ATERG S\nVerksamhet: Forskning o\nutveckling inom kärnenergiområdet.\nIsotoper o nukleära instrument,\nmaterialprovning o analyser\nAntal anställda: 1100\nÅrsomsättning: 106 000 000\nAktiekapital: 14 000 000\nVerkst dir: Bo Aler\nEtableringsår: 1948.\n\nTEKNO OPTIK AB\n\nPnr 124 03\n\nBandhagen 3, Box 369. Tel\n08-99 11 67. Postgiro 254882-4\nVerksamhet: Säljer objektiv o\noptiska element för yrkesmässigt\no industriellt bruk (ej\nglasögonoptik)\n\nAktiekapital: 5 000\nVerkst dir. Märta Laurin\nEtableringsår. 1970.\n\nSVANSOM, AB\n\nPnr 511 04\n\nKinna 4, Box 4030. Tel\n0320-107 40, 106 60. Bankgiro 434-8934.\nPostgiro 674890-9. Tga Svansöm\nVerksamhet: Mjuka möbler o\ninredningar till daghem o sjukhus.\nMöbeldynor, madrasser, leksaker!\nskumplast\n\nAktiekapital: 10 000\n\nVerkst dir: Mats Fransson\nEtableringsår: 1966\nDotterbolag till Svensk Textil,\nMats Fransson AB.\n\nSVARENS TRIKÅ.\nFABRIKS AB, S\n\nPnr 500 07\n\nBorås 7, Box 1723. Herrljunga. Tel\n1276 60. Postgiro 93422-4\nVerksamhet: Tillverkar\ndamunderkläder samt korsetter o bysthållare\nVarunamn: Svarens\nÅrsomsättning: 5 000 000\nAktiekapital: 500 000\nStyrelse: Adv Kjell Holmqvist,\ndir Rune Mattsson\nFörsäljn-chef: Lars Löwing\nEtableringsår: 1930.\n\nELEKTROFON AB\n\nPnr 10031\n\nStockholm 21, Box 21038. Källv 1,\nSolna. Tel 08-27 28 85. Tga\nElek-trofon. Telex 10720\nVerksamhet: Elektroteknisk\ntillverkning för industrin\nAktiekapital: 50 000\nVerkst dir: Civiling Arvid\nUnner-stad\n\nEtableringsår: 1938.\n\nSVALAN CYKELFABRIK, AB\n\nPnr 79101\n\nFalun 1, Box 68. Tel 023-191 90,\n19191. Bankgiro 792-4715.\nPostgiro 278547-5. Tga Svalan\nVerksamhet: Tillverkar cyklar o\nmopeder vid egen fabrik i Falun\nAntal anställda: 70\nÅrsomsättning: 5 000 000\n\nAktiekapital: 200 000\nVerkst dir: Lennart Nordström\nEtableringsår: 1923.\n\nSPRAKAREDS EMALJ.\nVERK, AB\n\nPnr 51100\n\nKinna, Kinnahult. Tel 0320-100 45.\nBankgiro 43-4844. Postgiro 76776.\nTga Sprakaredemalj\nVerksamhet: Emaljerade skyltar,\nfasadplåtar, legoemaljering m m\nAktiekapital: 35 000\nVerkst dir: Disp Oscar W Swanberg\nEtableringsår: 1893.\n\nSPRINGFELDT ANNONS.\nBYRÅ AB\n\nPnr 722 12\n\nVästerås, Stora g 46. Tel\n021-1444 70. Bankgiro 80-8909.\nPostgiro 21121\n\nVerksamhet: Auktoriserad byrå med\nreklamproduktion, planering mm\nAntal anställda: 22\nÅrsomsättning: 17 000 000\nAktiekapital: 200000\nVerkst dir: Erie Springfeldt\nEtableringsår: 1959.",
    "structured": {
        "1": {
            "company_name": "KAFAK AB",
            "pnr": "851 01",
            "address": "Sundsvall 1, Fack",
            "phone_number": "060-15 44 20",
            "bank_details": {
                "bankgiro": "774^1816",
                "postgiro": "399811-9"
            },
            "activity": "Tillverkning",
            "employees": 160,
            "annual_turnover": 20000000,
            "capital": 300000,
            "key_personnel": [
                {
                    "name": "Torsten Lindström",
                    "position": "ordförande"
                },
                {
                    "name": "T Bergman",
                    "position": "direktör"
                },
                {
                    "name": "I Strömberg",
                    "position": "direktör"
                }
            ],
            "establishment_year": 1952
        },
        "2": {
            "company_name": "PROMOTION REKLAM PR AB",
            "pnr": "11631",
            "address": "Stockholm, Renstiernas g 12",
            "phone_number": "08-44 60 53, 44 60 54",
            "bank_details": {
                "bankgiro": "33-0572",
                "postgiro": "400188"
            },
            "activity": "Av Handelskamrarnas Nämnd auktoriserad reklamkonsult",
            "employees": 5,
            "annual_turnover": 250000,
            "capital": 5000,
            "key_personnel": [
                {
                    "name": "Sven-Olof Bergström",
                    "position": null
                },
                {
                    "name": "Tom R Gripe",
                    "position": null
                },
                {
                    "name": "Bertil Gripe",
                    "position": null
                }
            ],
            "establishment_year": 1965
        },
        "3": {
            "company_name": "PROVIDENTIA, FÖRVALTNINGS AB",
            "pnr": "103 24",
            "address": "Stockholm 16, Wahrendorffsg 1, Box 16174",
            "phone_number": "08-23 3790",
            "bank_details": {
                "bankgiro": "16-0454"
            },
            "activity": "Förvaltningsrörelse",
            "capital": 60000000,
            "key_personnel": [
                {
                    "name": "Sven Ture Åberg",
                    "position": "verkställande direktör"
                }
            ],
            "establishment_year": 1946
        },
        "4": {
            "company_name": "NOR-MASKINER, AB",
            "pnr": "400 30",
            "address": "Göteborg 11, Nordenskiöldsg 19, Box 11043",
            "phone_number": "031-14 19 81,14 19 84",
            "bank_details": {
                "bankgiro": "84-7954",
                "postgiro": "43903"
            },
            "activity": "Säljer kylmaskiner med tillbehör",
            "employees": 3,
            "annual_turnover": 800000,
            "capital": 20000,
            "key_personnel": [
                {
                    "name": "Bertil Lindh",
                    "position": "verkställande direktör"
                }
            ],
            "establishment_year": 1947
        },
        "5": {
            "company_name": "AXE",
            "activity": "Utför alla slags smides-, plåt- och svetsningsarbeten",
            "annual_turnover": 2500000,
            "key_personnel": [
                {
                    "name": "Fabr A Axelson",
                    "position": "ägare o chef"
                }
            ]
        },
        "6": {
            "company_name": "AXELSONS ROSTFRIA, AB",
            "pnr": "732 00",
            "address": "Arboga, Box 120",
            "phone_number": "0589-11129, 130 28",
            "bank_details": {
                "bankgiro": "600-0152",
                "postgiro": "389251-0"
            },
            "activity": "Tillverkar rostfria hushållsartiklar och sjukvårdsartiklar",
            "employees": 32,
            "annual_turnover": 2000000,
            "capital": 50000,
            "key_personnel": [
                {
                    "name": "Fabr Georg Axelson",
                    "position": "verkställande direktör"
                }
            ],
            "establishment_year": 1950
        },
        "7": {
            "company_name": "AXELSSONS STAKETFABRIK AB",
            "pnr": "260 80",
            "phone_number": "0431-304 50",
            "bank_details": {
                "bankgiro": "896-0270",
                "postgiro": "381098-3"
            },
            "activity": "Tillverkar staket i trä, med och utan tryckimpregnering",
            "employees": 12,
            "annual_turnover": 900000,
            "capital": 10000,
            "key_personnel": [
                {
                    "name": "Göran Axelsson",
                    "position": "verkställande direktör"
                },
                {
                    "name": "Curt Axelsson",
                    "position": "försäljningschef"
                }
            ],
            "establishment_year": 1964
        },
        "8": {
            "company_name": "ATOMENERGI, AB",
            "pnr": "61101",
            "address": "Nyköping I, Fack. Studsvik",
            "phone_number": "0155-800 00",
            "bank_details": {
                "bankgiro": "NotAvailable"
            },
            "activity": "Forskning och utveckling inom kärnenergiområdet",
            "employees": 1100,
            "annual_turnover": 106000000,
            "capital": 14000000,
            "key_personnel": [
                {
                    "name": "Bo Aler",
                    "position": "verkställande direktör"
                }
            ],
            "establishment_year": 1948
        },
        "9": {
            "company_name": "TEKNO OPTIK AB",
            "pnr": "124 03",
            "address": "Bandhagen 3, Box 369",
            "phone_number": "08-99 11 67",
            "bank_details": {
                "postgiro": "254882-4"
            },
            "activity": "Säljer objektiv och optiska element för yrkesmässigt och industriellt bruk (ej glasögonoptik)",
            "capital": 5000,
            "key_personnel": [
                {
                    "name": "Märta Laurin",
                    "position": "verkställande direktör"
                }
            ],
            "establishment_year": 1970
        },
        "10": {
            "company_name": "SVANSOM, AB",
            "pnr": "511 04",
            "address": "Kinna 4, Box 4030",
            "phone_number": "0320-107 40, 106 60",
            "bank_details": {
                "bankgiro": "434-8934",
                "postgiro": "674890-9"
            },
            "activity": "Mjuka möbler och inredningar till daghem och sjukhus. Möbeldynor, madrasser, leksaker och skumplast",
            "capital": 10000,
            "key_personnel": [
                {
                    "name": "Mats Fransson",
                    "position": "verkställande direktör"
                }
            ],
            "establishment_year": 1966
        },
        "11": {
            "company_name": "SVARENS TRIKÅ FABRIKS AB, S",
            "pnr": "500 07",
            "address": "Borås 7, Box 1723. Herrljunga",
            "phone_number": "1276 60",
            "bank_details": {
                "postgiro": "93422-4"
            },
            "activity": "Tillverkar damunderkläder samt korsetter och bysthållare",
            "employees": 0,
            "annual_turnover": 5000000,
            "capital": 500000,
            "key_personnel": [
                {
                    "name": "Lars Löwing",
                    "position": "försäljningschef"
                }
            ],
            "establishment_year": 1930
        },
        "12": {
            "company_name": "ELEKTROFON AB",
            "pnr": "10031",
            "address": "Stockholm 21, Box 21038. Källv 1, Solna",
            "phone_number": "08-27 28 85",
            "bank_details": {
                "bankgiro": "NotAvailable"
            },
            "activity": "Elektroteknisk tillverkning för industrin",
            "capital": 50000,
            "key_personnel": [
                {
                    "name": "Civiling Arvid Unnerstad",
                    "position": "verkställande direktör"
                }
            ],
            "establishment_year": 1938
        },
        "13": {
            "company_name": "SVALAN CYKELFABRIK AB",
            "pnr": "79101",
            "address": "Falun 1, Box 68",
            "phone_number": "023-191 90, 19191",
            "bank_details": {
                "bankgiro": "792-4715",
                "postgiro": "278547-5"
            },
            "activity": "Tillverkar cyklar och mopeder vid egen fabrik i Falun",
            "employees": 70,
            "annual_turnover": 5000000,
            "capital": 200000,
            "key_personnel": [
                {
                    "name": "Lennart Nordström",
                    "position": "verkställande direktör"
                }
            ],
            "establishment_year": 1923
        },
        "14": {
            "company_name": "SPRAKAREDS EMALJ VERK AB",
            "pnr": "51100",
            "address": "Kinna, Kinnahult",
            "phone_number": "0320-100 45",
            "bank_details": {
                "bankgiro": "NotAvailable",
                "postgiro": "76776"
            },
            "activity": "Emaljerade skyltar, fasadplåtar, legoemaljering med mera",
            "capital": 35000,
            "key_personnel": [
                {
                    "name": "Disp Oscar W Swanberg",
                    "position": "verkställande direktör"
                }
            ],
            "establishment_year": 1893
        },
        "15": {
            "company_name": "SPRINGFELDT ANNONS BYRÅ AB",
            "pnr": "722 12",
            "address": "Västerås, Stora g 46",
            "phone_number": "021-1444 70",
            "bank_details": {
                "bankgiro": "80-8909",
                "postgiro": "21121"
            },
            "activity": "Auktoriserad byrå med reklamproduktion, planering med mera",
            "employees": 22,
            "annual_turnover": 17000000,
            "capital": 200000,
            "key_personnel": [
                {
                    "name": "Erie Springfeldt",
                    "position": "verkställande direktör"
                }
            ],
            "establishment_year": 1959
        }
    }
}