{
    "original": "malm ab, annonsbyrån\n\nPnr 801 05\n\nGävle 1, Box 396. Tel 026-18 84 90.\nBankgiro 194-0261. Postgiro 296081\nVerksamhet: Fullständig\nannonsbyrårörelse samt fotoavdelning\nAntal anställda: 12\nÅrsomsättning: 1 000 000\nAktiekapital: 50 000\nStyrelseordf: Dir Arne Malm\nVerkst dir: Kjell Nygren\nArt director: Henk Brass\nReklamfotograf: Ture Hedberg\nEtableringsår: 1951\nOmbildat till aktiebolag 1963.\n\nmalm &amp; ståhl ab\n\nPnr 10311\n\nStockholm, Box 2004.\nKornhamnstorg 53. Tel 08-10 92 20, 201203.\nBankgiro 72-1722. Postgiro 55668.\nTga Masto\n\nVerksamhet: Agenturaffär i\nkolonialvaror, konserver, kaffe o frukt\nAktiekapital: 45 000\nVerkst dir: Ulf P Jörgensen\nEtableringsår: 1933.\n\nTRÄKOL, AB\n\nPnr 780 50\n\nVansbro. Tel 0281-100 55, 10 1 29.\nBankgiro 79-8906. Postgiro 8772.\nTga Träkol\n\nVerksamhet: Finare trälådoro\nlagerinredningar\nAntal anställda: 47\nÅrsomsättning: 3 000000\nAktiekapital: 750 000\nStyrelse: Bruksdisp Wilhelm Ekman\n(ordf), dir B O Berggren, dir Georg\nvon Heijne, dir Bert Henning\nVerkst dir: Arne Magg\nEtableringsår 1889\nDotterbolag till Uddeholms AB.\n\nTRÄMANUFAKTUR I INGA.\nTORP AB\n\nPnr 570 31\n\nIngatorp. Tel 0381-210 05.\nBankgiro 450-9147. Postgiro 492652-3\nVerksamhet: Tillverkar barnsängar,\nturistsängar\nAktiekapital: 150 000\nVerkst dir. Arthur Johansson\nEtableringsår: 1932.\n\nTRÄSPECIALEN C JOHANS.\nSON &amp; CO AB\n\nPnr 330 23\n\nSmålandsstenar, Industrig. Box 91.\nTel 0371-300 61. Bankgiro\n427-6671. Postgiro 86457-9\nVerksamhet: Tillverkar fällbara\nbord (Fixbord), hurtsbord,\nskrivbord, spelbord m m\nVarunamn: Fix\nAntal anställda: 42\nÅrsomsättning: 4 500 000\nAktiekapital: 20 0 000\nÄgare o chefer. Thore Johansson,\nKjell Johansson\nEtableringsår: 1934.\n\nCITYMODELLER AB\n\nPnr 500 03\n\nBorås3, Katrinedalsg 15. Box 1328.\nTel 033-10 20 3 0. Tga Citymodeller\nVerksamhet: Tillverkar o säljer\nklänningar\n\nFörsäljningskontor: Stockholm C,\nKungsg 17. Tel 08-20 25 45\nVerkst dir: Sören Wickström\nEtableringsår. 1950.\n\nTIBO, VERKSTADS AB\n\nPnr 15102\n\nSödertälje, Hertig Carls v 44. Tel\n075 5-60 3 90. Bankgiro 569-5598.\nPostgiro 159540-4.\nTelex 10916 TIBO S\nVerksamhet: Konstruerar o\ntillverkar hjälpmaskiner för\njärnindustrin\n\nAntal anställda: 70\nÅrsomsättning: 7 000 000\nAktiekapital: 500 000\nStyrelse: Dir K-E Tiblom (ordf),\ndir Olof Tiblom, dir Arne Thunander\nVerkst dir: Ragne Gabrielsson\nEtableringsår: 1941.\n\nWINNI.VERKEN AB\n\nPnr 243 00\n\nHöör, Industriområdet. Tel\n0413-20655, 206 15. Bankgiro 479-4368.\nPostgiro 290168-4\n\nVerksamhet: Tillverkar lastbryggor,\nbåtlandgångar o transportredskap\nVarunamn: Winni\nAntal anställda: 15\nÅrsomsättning: 1000 000\nAktiekapital: 45 000\nVerkst dir: Lennart Rosengren\nEtableringsår: 1921.\n\nWINROTH &amp; CO.\nVERKSTADS AB\n\nPnr 417 08\n\nGöteborg, Lindholmsv 25. Tel\n031-23 1991. 224819. Bankgiro\n441-2532. Postgiro 420933-4\nVerksamhet: Grovplåtslageri o mek\nverkstad. Järnkonstruktioner\nAntal anställda: 12\nÅrsomsättning: 1000 000\nAktiekapital: 5 000\nStyrelse ordf: Dir Olof Winroth\nVerkst dir: Olof Winroth\nEtableringsår: 1910.\n\nFREDRICSON AB, KARL\n\nPnr 232 00\n\nArlöv, Box 55. Lommav 62. Tel\n040-43 20 55. Bankgiro 156-4137.\nPostgiro 38850-4. Tga Karlfre\nVerksamhet: Säljer in- o utländskt\nädelträ, snickerifuru, plywood,\nbåt-plywood, lamell trä, spånplattor o\nfanér\n\nAntal anställda: 20\nAktiekapital: 300 000\nVerkst dir: Karl Gustav Fredricson\nDisp: Sven Olsson\nEtableringsår: 1923.\n\nFREDRIKSSON\nARKITEKT-KONTOR AB, STEN\n\nPnr 112 47\n\nStockholm, Alströmerg 20. Tel\n08-24 58 00. Postgiro 608247-3\nVerksamhet: Projekterar affärs o\nkontorshus, varuhus, industrier\nAntal anstäUda: 6\nÅrsomsättning: 500 000\nAktiekapital: 5 000\nVerkst dir: Ark SAR Sten\nFredriksson\n\nEtableringsår: 1960.\n\nFREIDLITZ MEK\nVERKSTAD, J\n\nPnr 44100\n\nAlingsås, Hallstorp. Tel\n0322-510 90. Bankgiro 436-5169.\nPostgiro 117441-6\n\nVerksamhet: Tillverkar\nvarmluft-pannor\n\nÄgare o chef: J Freidlitz\nEtableringsår: 1943.\n\nLJUSNAN, TRYCKERI AB\n\nPnr 82101\n\nBollnäs 1, Box 59. Stationsg 8.\nTel 0278-130 00. Bankgiro\n192-8423. Postgiro 6576-3.\nTelex 81003 LJUSNAN S\nVerksamhet: Tidningstryckeri.\nUtger tidningen Ljusnan\nAntal anställda: 190\nÅrsomsättning: 3 500000\nAktiekapital: 120 000\nVerkst din Fru Hildur Sköld\nEtableringsår. 1912.\n\nIGELFORSBRUKS AB\n\nPnr 612 00\n\nFinspång. Tel 0122-72100. Bankgiro\n62-4843. Postgiro 169590\n\nVerksamhet: Utför hejarsmidda\nbil-o traktordelar. Tillverkar även liar\no portar\n\nVarunamn: Banko, Bull, Kron,\nScan-Door\n\nAntal anstäUda: 100\nÅrsomsättning: 8000 000\nAktiekapital: 500000\nStyrelse: Dir Karl-Erik Tiblom\n(ordf), dir Yngve Johansson, dir\nOlof Tiblom\n\nVerkst dir: Yngve Johansson\nEtableringsår 1891.\n\nRONNQVIST &amp; SÖNER AB\n\nPnr 643 00\n\nVingåker,Box 112.Tel 0151-11540.\nBankgiro 624-7746. Postgiro\n90222-1\n\nVerksamhet: Tillverkar\nexcenter-o friktionsskruvpressar upp till 500\ntons presstryck, matbestick av\nrætfritt stål o nysilver, stansade\ndetaljer etc\nAntal anställda: 100\nÅrsomsättning: 4 000 000\nAktiekapital: 600 000\nStyrelse: Ing P O Rönnqvist (ordf),\ndir Rolf Rönnqvist, kamrer Allan\nÖsterlund\n\nVerkst dir: Ing Rolf Rönnqvist\nKamrer: Allan Österlund\nEtableringsår: 1894\nOmbildat till aktiebolag 1945.\n\nRÖNNMARKS PARTI- &amp;\nAGENTURAFFÄR, AB\n\nPnr 93101\n\nSkellefteå 1, Nyg 52. Box 195. Tel\n0910-100 55, 11055\nVerksamhet: Säljer tobak,\ntobaksutensilier o diverse kortvaror i parti\nAktiekapital: 50 000\nVerkst dir: Sven Forslund\nEtableringsår: 1944.\n\nELLESS MASKINFABRIK AB\n\nPnr 421 31\n\nVästra Frölunda, Fröknoppsg 2 C.\nTel 031-45 18 24, 45 18 40. Bankgiro\n50-9627. Postgiro 12479. Tga\nEliess\n\nVerksamhet: Tillverkar\niläggnings-apparaten Elless för tryckpressar\no andra arkbearbetande maskiner\nAntal anställda: 25\nAktiekapital: 20 000\nVerkst dir: Sture Danielson\nEtableringsår: 1901.\n\nELLNER&amp; JACOBSSON\nBETONG-o\nSTÅLKONSTRUKTIONER\n\nPnr 114 56\n\nStockholm, Banérg 4. Tel\n08-631470. Postgiro 613673\nVerksamhet: Konsulterande\ningenjörer\n\nAntal anställda: 13\nÅrsomsättning: 900 000\nVerkst dir: Ing Bengt Jacobsson\nEtableringsår: 1960.",
    "structured": {
        "1": {
            "company_name": "Malm Ab, Annonsbyrån",
            "activity": "Fullständig annonsbyråverksamhet samt fotoavdelning",
            "establishment_year": 1951,
            "employees": 12,
            "annual_turnover": 1000000,
            "capital": 50000,
            "key_personnel": [
                {
                    "name": "Dir Arne Malm",
                    "position": "Styrelseordförande"
                },
                {
                    "name": "Kjell Nygren",
                    "position": "Verkställande direktör"
                },
                {
                    "name": "Henk Brass",
                    "position": "Art director"
                },
                {
                    "name": "Ture Hedberg",
                    "position": "Reklamfotograf"
                }
            ]
        },
        "2": {
            "company_name": "Malm & Ståhl Ab",
            "establishment_year": 1933,
            "activity": "Agenturaffär i kolonialvaror, konserver, kaffe o frukt",
            "capital": 45000,
            "key_personnel": [
                {
                    "name": "Ulf P Jörgensen",
                    "position": "Verkställande direktör"
                }
            ]
        },
        "3": {
            "company_name": "Träkol, Ab",
            "establishment_year": 1889,
            "activity": "Finare trälådor och lagerinredningar",
            "employees": 47,
            "annual_turnover": 3000000,
            "capital": 750000,
            "key_personnel": [
                {
                    "name": "Wilhelm Ekman",
                    "position": "Styrelseordförande"
                },
                {
                    "name": "B O Berggren",
                    "position": "Verkställande direktör"
                },
                {
                    "name": "Georg von Heijne",
                    "position": "Verkställande direktör"
                },
                {
                    "name": "Bert Henning",
                    "position": "Verkställande direktör"
                },
                {
                    "name": "Arne Magg",
                    "position": "Verkställande direktör"
                }
            ]
        },
        "4": {
            "company_name": "Trämanufaktur I Inga, Torp Ab",
            "establishment_year": 1932,
            "activity": "Tillverkar barnsängar och turistsängar",
            "capital": 150000,
            "key_personnel": [
                {
                    "name": "Arthur Johansson",
                    "position": "Verkställande direktör"
                }
            ]
        },
        "5": {
            "company_name": "TräsPECIALen C Johansson & Co Ab",
            "establishment_year": 1934,
            "activity": "Tillverkar fällbara bord (Fixbord), hurtsbord, skrivbord, spelbord m.m",
            "employees": 42,
            "annual_turnover": 4500000,
            "capital": 200000,
            "key_personnel": [
                {
                    "name": "Thore Johansson",
                    "position": "Ägare och chef"
                },
                {
                    "name": "Kjell Johansson",
                    "position": "Ägare och chef"
                }
            ]
        },
        "6": {
            "company_name": "CityModeller Ab",
            "establishment_year": 1950,
            "activity": "Tillverkar och säljer klänningar",
            "key_personnel": [
                {
                    "name": "Sören Wickström",
                    "position": "Verkställande direktör"
                }
            ]
        },
        "7": {
            "company_name": "Tibo, Verkstads Ab",
            "establishment_year": 1941,
            "activity": "Konstruerar och tillverkar hjälpmaskiner för järnindustrin",
            "employees": 70,
            "annual_turnover": 7000000,
            "capital": 500000,
            "key_personnel": [
                {
                    "name": "K-E Tiblom",
                    "position": "Styrelseordförande"
                },
                {
                    "name": "Olof Tiblom",
                    "position": "Verkställande direktör"
                },
                {
                    "name": "Arne Thunander",
                    "position": "Verkställande direktör"
                },
                {
                    "name": "Ragne Gabrielsson",
                    "position": "Verkställande direktör"
                }
            ]
        },
        "8": {
            "company_name": "Winni.Verkens Ab",
            "establishment_year": 1921,
            "activity": "Tillverkar lastbryggor, båtlandgångar och transportredskap",
            "employees": 15,
            "annual_turnover": 1000000,
            "capital": 45000,
            "key_personnel": [
                {
                    "name": "Lennart Rosengren",
                    "position": "Verkställande direktör"
                }
            ]
        },
        "9": {
            "company_name": "Winroth & Co. Verkstads Ab",
            "establishment_year": 1910,
            "activity": "Grovplåtslageri och mekanisk verkstad, järnkonstruktioner",
            "employees": 12,
            "annual_turnover": 1000000,
            "capital": 5000,
            "key_personnel": [
                {
                    "name": "Olof Winroth",
                    "position": "Styrelseordförande och verkställande direktör"
                }
            ]
        },
        "10": {
            "company_name": "Fredricson Ab, Karl",
            "establishment_year": 1923,
            "activity": "Säljer in- och utländskt ädelträ, snickerifuru, plywood, båt-plywood, lamellträ, spånplattor, fanér",
            "employees": 20,
            "capital": 300000,
            "key_personnel": [
                {
                    "name": "Karl Gustav Fredricson",
                    "position": "Verkställande direktör"
                },
                {
                    "name": "Sven Olsson",
                    "position": "Disp"
                }
            ]
        },
        "11": {
            "company_name": "Fredriksson Arkitekt-Kontor Ab, Sten",
            "establishment_year": 1960,
            "activity": "Projekterar affärs- och kontorshus, varuhus, industrier",
            "employees": 6,
            "annual_turnover": 500000,
            "capital": 5000,
            "key_personnel": [
                {
                    "name": "Sten Fredriksson",
                    "position": "Verkställande direktör"
                }
            ]
        },
        "12": {
            "company_name": "Freidlitz Mek Verkstad, J",
            "establishment_year": 1943,
            "activity": "Tillverkar varmluft-pannor",
            "key_personnel": [
                {
                    "name": "J Freidlitz",
                    "position": "Ägare och chef"
                }
            ]
        },
        "13": {
            "company_name": "Ljusnan, Tryckeri Ab",
            "establishment_year": 1912,
            "activity": "Tidningstryckeri, utger tidningen Ljusnan",
            "employees": 190,
            "annual_turnover": 3500000,
            "capital": 120000,
            "key_personnel": [
                {
                    "name": "Fru Hildur Sköld",
                    "position": "Verkställande direktör"
                }
            ]
        },
        "14": {
            "company_name": "Igelforsbruks Ab",
            "establishment_year": 1891,
            "activity": "Utför hejarsmidda bil- och traktordelar, tillverkar även liar och portar",
            "employees": 100,
            "annual_turnover": 8000000,
            "capital": 500000,
            "key_personnel": [
                {
                    "name": "Karl-Erik Tiblom",
                    "position": "Styrelseordförande"
                },
                {
                    "name": "Yngve Johansson",
                    "position": "Verkställande direktör"
                },
                {
                    "name": "Olof Tiblom",
                    "position": "Verkställande direktör"
                }
            ]
        },
        "15": {
            "company_name": "Rönnqvist & Söner Ab",
            "establishment_year": 1894,
            "activity": "Tillverkar excenter- och friktionsskruvpressar upp till 500 tons presstryck, matbestick av rostfritt stål och nysilver, stansade detaljer etc",
            "employees": 100,
            "annual_turnover": 4000000,
            "capital": 600000,
            "key_personnel": [
                {
                    "name": "Ing P O Rönnqvist",
                    "position": "Styrelseordförande"
                },
                {
                    "name": "Rolf Rönnqvist",
                    "position": "Verkställande direktör"
                },
                {
                    "name": "Allan Österlund",
                    "position": "Kamrer"
                }
            ]
        },
        "16": {
            "company_name": "Rönnmarks Parti- & Agenturaffär Ab",
            "establishment_year": 1944,
            "activity": "Säljer tobak, tobaksutensilier och diverse kortvaror i parti",
            "capital": 50000,
            "key_personnel": [
                {
                    "name": "Sven Forslund",
                    "position": "Verkställande direktör"
                }
            ]
        },
        "17": {
            "company_name": "Elless Maskinfabrik Ab",
            "establishment_year": 1901,
            "activity": "Tillverkar iläggnings-apparaten Elless för tryckpressar och andra arkbearbetande maskiner",
            "employees": 25,
            "capital": 20000,
            "key_personnel": [
                {
                    "name": "Sture Danielson",
                    "position": "Verkställande direktör"
                }
            ]
        },
        "18": {
            "company_name": "Ellner & Jacobsson Betong- och Stålkonstruktioner",
            "establishment_year": 1960,
            "activity": "Konsulterande ingenjörer",
            "employees": 13,
            "annual_turnover": 900000,
            "key_personnel": [
                {
                    "name": "Ing Bengt Jacobsson",
                    "position": "Verkställande direktör"
                }
            ]
        }
    }
}