{
    "original": "flens grävmaskiner ab\n\nPnr 642 00\n\nFlen, Industriv 2. Box 35. Tel\n0157-12415. Bankgiro 82-8958.\nPostgiro 107690\n\nVerksamhet: Säljer grusprodukter.\nUthyr gräv- o lastmaskiner\nAntal anställda: 14\nÅrsomsättning: 1 800 000\nAktiekapital: 150 000\nVerkst dir: Arne Lundberg\nEtableringsår: 1954.\n\nSVENSKA STENATOR AB\n\nPnr 116 34\n\nStockholm, Bondeg 65. Tel\n08-44 9630. Bankgiro 745-7419.\nPostgiro 155511-9\n\nVerksamhet: Säljer Grundig\ndikte-ringsmaskiner\nAntal anställda: 6\nÅrsomsättning: 700 000\nAktiekapital: 5 000\nVerkst din Rikard Sveding\nEtableringsår 1954.\n\nSVENSKA STEN.\nRENOVERINGAR AB\n\nPnr 415 02\n\nGöteborg, Marieholmsg 66. Tel\n031-46 84 12, 46 84 14. Bankgiro\n362-2016. Postgiro 240118-0. Tga\nShipblasting\n\nVerksamhet: Sandblästring,\nme-tallisering, fasadblästring\nAntal anställda: 35\nÅrsomsättning: 2 500 000\nAktiekapital: 225 000\nVerkst dir: N J Eriksson\nEtableringsår: 1936.\n\nSVENSKA STEPHAN MASKIN\nAB\n\nPnr 126 31\n\nHägersten, Tombolav 6. Tel\n08-19 20 24, 1932 92. Bankgiro\n734-6380. Postgiro 400202-8. Tga\nStephanab\n\nVerksamhet: Agenturföretag. Säljer\nmaskiner o apparater för storkök o\nlivsmedelsindustrin\nVarunamn: Juno Convectomat,\nStephan\n\nAntal anställda: 3\n\nÅrsomsättning: 1000 000\nAktiekapital: 50000\nVerkst dir: Hans-Otto Ansker\nEtableringsår: 1965.\n\nMETZELER AB\n\nPnr 543 00\n\nTibro, Skövdev. Tel 0504-123 60.\nBankgiro 221-3759. Postgiro\n448910-0. Tga Metzpol. Telex 5046\nVerksamhet: Tillverkning av\npoly-eterprodukter för industri, handel,\nstatliga o kommunala inrättningar\nVarunamn: Vilette\nAntal anställda: 75\nÅrsomsättning: 15 000 000\nAktiekapital: 500 000\nEtableringsår: 1952.\n\nKONTORSCENTRALEN AB\n\nPnr 35103\n\nVäxjö 1, Box 44. Storg 14. Tel\n0470-100 60\n\nVerksamhet: Säljer skriv-,\nräkne-o kalkylmaskiner, kopierings-,\nduplicerings- o\nfrankeringsmaski-ner, kontorsmöbler samt möbler\nför offentlig miljö. Kaffe- o\nstill-drinksautomater, läskautomater,\nautomater för kall o varm mat m m\nVerkst dir: Birger Eidehall\nEtableringsår. 1951.\n\nBELLEVUE SMIDE o SVETS\n\nPnr 654 61\n\nKarlstad, Bromsg 6. Tel\n054-15 05 44. Bankgiro 472-8127.\nPostgiro 104242-1\n\nVerksamhet: Svarvning, svetsning\no reparationsarbeten\nChef: Lars Carlsson\nEtableringsår 1953.\n\nUPP\n\nUPPLANDSBETONG, AB\n\nPnr 751 03\n\nUppsala 1, V Järnvägsg 11. Tel\n018-10 02 50. Bankgiro 802-3491.\nPostgiro 545250-3\nVerksamhet: Tillverkar\nfabriksbetong o murbruk\nAntal anställda: 50\nÅrsomsättning: 20 000 000\nAktiekapital: 1000 000\nVerkst dir: Sture Johansson\nEtableringsår: 1960.\n\nTRÄ &amp; PAPPER, AB\n\nPnr 115 42\n\nStockholm, Storängskroken 22. Tel\n08-11 84 20, 21 7850. Bankgiro\n571-3755. Postgiro 199553-9. Tga\nWoodpaper\n\nVerksamhet: Handel med o\nsortering av pappersavfall\nAntal anställda: 15\nÅrsomsättning: 3 000 000\nAktiekapital: 25 000\nVerkst dir. Sven Lundegard\nEtableringsår: 1946.\n\nARBESKO AB\n\nPnr 70104\n\nÖrebro 1, Drottningg 35. Box 268.\nTel 019-11 98 25. Bankgiro\n822-7100. Postgiro 468280-3\nVerksamhet: Tillverkar o säljer\narbetarskyddsskor\nVarunamn: Stålex\nAktiekapital: 100 000\nDisp: Rune Edberg\nEtableringsår: 1952\nOmbildat till aktiebolag 1959.\n\nARBETARBLADET, AB\n\nPnr 80104\n\nGävle 1, Box 287. Hattmakarg 12.\nTel 026-12 93 00. Bankgiro\n336-7034. Postgiro 9118-1.\nTelex 81033 ABLADET S\nVerksamhet: Tidningstryckeri.\nUtger tidningen Arbetarbladet\nAntal anställda: 198\nÅrsomsättning: 14 700000\nAktiekapital: 360 000\nVerkst dir o adm-red: Bo Präntare\nChefred o ansvarig utgivare: Yngve\nMöller\n\nAnnonschef: Olle Ericsson\nAbonnemangschef: Evald Pettersson\nKontorschef: Bengt Tingsgård\nFaktor: Gunnar Nyström\nAnnonskonsulent för riksannonser:\nAnders Thunstedt\nEtableringsår: 1902.\n\n[-ARBETARSKYDDSMATERIAL-]\n\n{+ARBETARSKYDDS-\nMATERIAL+} AB\n\nPnr 213 63\n\nMalmö, Tujag 5. Tel 040-94 5120.\nBankgiro 260-7349. Postgiro\n630222-8\n\nVerksamhet: Säljer\narbetsskydds-material\n\n.Antal anställda: 23\nÅrsomsättning: 10 000 000\nAktiekapital: 90 000\nVerkst dir: Evert Antonius\nEtableringsår: 1964.\n\nKRONOS TITAN PIGMENT AB\n\nPnr 102 45\n\nStockholm 5, Nybrog 44. Box 5264.\nTel 08-67 09 00. Bankgiro 161-2266.\nPostgiro 157141-3. Tga Kronostitan.\nTelex 10575\n\nVeiksamhet: Försäljningsbolag för\ntitandioxid, organiska o oorganiska\ntitanföreningar, titanmetallpulver.\nStabilisatorer för plastindustrin,\nBentone gelbildare.\nRostskyddspigment\n\nAvdelningskonton 41110 Göteborg,\nO Hamng 15. Tel 031-17 54 20.\nTelex 20877\n\nVarunamn: Bentone, Dutch Boy,\nKronos, Oncor\n.Antal anställda: 5\nAktiekapital: 100 000\nVerkst dir: Civiling Lars Espelid\nEtableringsår: 1964.\n\nKRONOSTROMS\nSPEGEL-FABRIK, AB\n\nPnr 360 33\n\nRäppe. Tel 0470-609 03. Bankgiro\n655-9785. Postgiro 25700-6. Tga\nKronspegel\n\nVerksamhet: Tillverkar speglar,\nbadrumsspeglar, spegelbord,\ntoalettbord m m\n\nFabrik: Fröseke. Tel 0481-640 03\nAktiekapital: 90 000\nStyrelseordf: Disp Göran Bäckman\nVerkst dir: Carl Henrichson\nEtableringsår: 1927.\n\nEL-MEKO, VERKSTADS AB\n\nPnr 212 28\n\nMalmö, Industrig 37. Tel\n040-94 4300, 944301. Bankgiro\n645-2106. Postgiro 434325-7\nVerksamhet: Reparationer o\nomlind-ningar av elektr motorer o\napparater. Försäljning av reservdelar samt\nserviceagent för elektr handverktyg\n(Wolf, Flex, Hola-Her)\nVarunamn: Wolf\nAntal anställda: 10\nÅrsomsättning: 600000\nAktiekapital: 45 000\nChefer Lars Gunnar Harvyl, Rolf\nHarteli\n\nEtableringsår: 1950.",
    "structured": {
        "1": {
            "company_name": "Flens Grävmaskiner AB",
            "activity": "Säljer grusprodukter. Uthyr gräv- o lastmaskiner",
            "establishment_year": 1954,
            "employees": 14,
            "annual_turnover": 1800000,
            "capital": 150000,
            "key_personnel": [
                {
                    "name": "Arne Lundberg",
                    "position": "Verkst dir"
                }
            ]
        },
        "2": {
            "company_name": "Svenska Stenator AB",
            "activity": "Säljer Grundig dikte-ringsmaskiner",
            "establishment_year": 1954,
            "employees": 6,
            "annual_turnover": 700000,
            "capital": 5000,
            "key_personnel": [
                {
                    "name": "Rikard Sveding",
                    "position": "Verkst din"
                }
            ]
        },
        "3": {
            "company_name": "Svenska Stenrenoveringar AB",
            "activity": "Sandblästring, metallisering, fasadblästring",
            "establishment_year": 1936,
            "employees": 35,
            "annual_turnover": 2500000,
            "capital": 225000,
            "key_personnel": [
                {
                    "name": "N J Eriksson",
                    "position": "Verkst dir"
                }
            ]
        },
        "4": {
            "company_name": "Svenska Stephan Maskin AB",
            "activity": "Agenturföretag. Säljer maskiner o apparater för storkök o livsmedelsindustrin. Varunamn: Juno Convectomat, Stephan",
            "establishment_year": 1965,
            "employees": 3,
            "annual_turnover": 1000000,
            "capital": 50000,
            "key_personnel": [
                {
                    "name": "Hans-Otto Ansker",
                    "position": "Verkst dir"
                }
            ]
        },
        "5": {
            "company_name": "Metzeler AB",
            "activity": "Tillverkning av poly-eterprodukter för industri, handel, statliga o kommunala inrättningar. Varunamn: Vilette",
            "establishment_year": 1952,
            "employees": 75,
            "annual_turnover": 15000000,
            "capital": 500000
        },
        "6": {
            "company_name": "Kontorscentralen AB",
            "activity": "Säljer skriv-, räkne-o kalkylmaskiner, kopierings-, duplicerings- o frankeringsmaskiner, kontorsmöbler samt möbler för offentlig miljö. Kaffe- o still-drinksautomater, läskautomater, automater för kall o varm mat m m",
            "establishment_year": 1951
        },
        "7": {
            "company_name": "Bellevue Smide o Svets",
            "activity": "Svarvning, svetsning o reparationsarbeten",
            "establishment_year": 1953
        },
        "8": {
            "company_name": "Upplandsbetong AB",
            "activity": "Tillverkar fabriksbetong o murbruk",
            "establishment_year": 1960,
            "employees": 50,
            "annual_turnover": 20000000,
            "capital": 1000000,
            "key_personnel": [
                {
                    "name": "Sture Johansson",
                    "position": "Verkst dir"
                }
            ]
        },
        "9": {
            "company_name": "Trä & Papper AB",
            "activity": "Handel med o sortering av pappersavfall",
            "establishment_year": 1946,
            "employees": 15,
            "annual_turnover": 3000000,
            "capital": 25000,
            "key_personnel": [
                {
                    "name": "Sven Lundegard",
                    "position": "Verkst dir"
                }
            ]
        },
        "10": {
            "company_name": "Arbesko AB",
            "activity": "Tillverkar o säljer arbetarskyddsskor. Varunamn: Stålex",
            "establishment_year": 1952,
            "capital": 100000
        },
        "11": {
            "company_name": "Arbetarbladet AB",
            "activity": "Tidningstryckeri. Utger tidningen Arbetarbladet",
            "establishment_year": 1902,
            "employees": 198,
            "annual_turnover": 14700000,
            "capital": 360000,
            "key_personnel": {
                "verkst_dir_o_adm-red": "Bo Präntare",
                "chefred_o_ansvarig_ugivare": "Yngve Möller",
                "annonschef": "Olle Ericsson",
                "abonnemangschef": "Evald Pettersson",
                "kontorschef": "Bengt Tingsgård",
                "faktor": "Gunnar Nyström",
                "annonskonsulent_för_riksannonser": "Anders Thunstedt"
            }
        },
        "12": {
            "company_name": "Arbetarskyddsmaterial AB",
            "activity": "Säljer arbetsskydds-material",
            "establishment_year": 1964,
            "employees": 23,
            "annual_turnover": 10000000,
            "capital": 90000,
            "key_personnel": [
                {
                    "name": "Evert Antonius",
                    "position": "Verkst dir"
                }
            ]
        },
        "13": {
            "company_name": "Kronos Titan Pigment AB",
            "activity": "Försäljningsbolag för titandioxid, organiska o oorganiska titanföreningar, titanmetallpulver. Stabilisatorer för plastindustrin, Bentone gelbildare. Rostskyddspigment",
            "establishment_year": 1964,
            "employees": 5,
            "capital": 100000,
            "key_personnel": [
                {
                    "name": "Civiling Lars Espelid",
                    "position": "Verkst dir"
                }
            ]
        },
        "14": {
            "company_name": "Kronostroms Spegel-fabrik AB",
            "activity": "Tillverkar speglar, badrumsspeglar, spegelbord, toalettbord m m",
            "establishment_year": 1927,
            "capital": 90000,
            "key_personnel": [
                {
                    "name": "Disp Göran Bäckman",
                    "position": "Styrelseordf"
                },
                {
                    "name": "Carl Henrichson",
                    "position": "Verkst dir"
                }
            ]
        },
        "15": {
            "company_name": "El-Meko, Verkstads AB",
            "activity": "Reparationer o omlind-ningar av elektr motorer o apparater. Försäljning av reservdelar samt serviceagent för elektr handverktyg (Wolf, Flex, Hola-Her). Varunamn: Wolf",
            "establishment_year": 1950,
            "employees": 10,
            "annual_turnover": 600000,
            "capital": 45000,
            "key_personnel": {
                "chefer": "Lars Gunnar Harvyl, Rolf Harteli"
            }
        }
    }
}