{
    "original": "RUNESTENS EFTR AB\n\nPnr 57100\n\nNässjö, Anneforsv 18. Tel\n0380-134 25. Bankgiro 45-2776.\nPostgiro 7875-8\n\nVerksamhet: Säljer o saluför\nbyggnadsmaterial. Huvudförsäljare för\nBallingslöv, Eternit, Gyproc,\nLättbetong, Mexi, Rockwool,\nSp-snicke-rier\n\nAntal anställda: 12\nÅrsomsättning: 8 000 000\nAktiekapital: 50 000\nVeikst dir: Olof Lundberg\nOmbildat till aktiebolag 1967.\n\nRUNO AB, A G\n\nPnr 431 37\n\nMölndal, Flöjelbergsg 8 A. Tel\n031-87 32 00. Bankgiro 84-8070.\nPostgiro 426588. Tga Exportruno\nVerksamhet: Tillverkar\nborstbin-derimaskiner o syntetisk fiber\nAntal anställda: 25\nÅrsomsättning: 2 000 000\nAktiekapital: 75 000\nVerkst din Anders G Runo\nEtableringsån 1924.\n\nINDUSTRIGARN, AB\n\nPnr 50106\n\nBorås 1, Box 313. Arlag 7. Tel\n033-1278 00. Bankgiro 531-4695.\nPostgiro 583939-4. Tga\nIndustrigarn. Telex 36053 FRANG S\nVeiksamhet: Industrigarner, alla\nslag engros\nEtableringsår: 1939.\n\nALMGRENS STÄMPLAR AB\n\nPnr 70106\n\nÖrebro 1, O Bang 26. Box 478.\nTel 019-1160 39, 12 64 39.\nBankgiro 817-3031. Postgiro 91392-1\nVerksamhet: Tillverkar alla slags\nstämplar o gummiklichéer. Utför\ngravyr för pressverktyg, gravering\nav skyltar i plexiglas o rostfritt\nAktiekapital: 20000\nVerkst dir: Artur Almgren\nEtableringsår: 1924.\n\nALMGREN AB\nTRÄVARU-AGENTUR, ESKIL\n\nPnr 41104\n\nGöteborg, Gullbergs Strandg 2.\nTel 031-15 65 25. Tga Eskil\nVerksamhet: Trävaror i parti\nVerkst dir: Greta Holtz\nAntal anställda: 3\nÅrsomsättning: 12 000 000.\n\nALMKVIST, ALMQVIST\n\nALMQVIST &amp; ELIASSON AB\n\nPnr 280 22\n\nVittsjö, Emmaljunga. Tel\n0451-240 61. Bankgiro 279-5060.\nPostgiro 298963-0\n\nVerksamhet: Tillverkar sittmöbler\nfåtöljer o soffor\nAntal anställda: 12\nÅrsomsättning: 1100 000\nAktiekapital: 25 000\nVerkst dir: Ake Almqvist\nEtableringsår: 1945.\n\nALMQVIST &amp; WIKSELL\nBOK-HANDEL AB\n\nPnr 101 20\n\nStockholm 1, Gamla Brog 26. Box\n62. Tel 08-23 79 90. Bankgiro\n23-5216. Postgiro 350833. Tga\nAlmqvistbook\n\nVerksamhet: Svensk o utländsk\nbokhandel, vetenskaplig o tekn\nlitteratur, tidskriftsförmedling,\nexport av skandinavisk vetenskaplig\nlitteratur. Pappershandel\n\nDotterbolag:\n\nStockholm: AB Henrik Lindståhls\nBokhandel, Universitetsbokhandeln\nAlmqvist &amp; Wiksell AB, AB\nTidskriftscentralen, The Almqvist &amp;\nWiksell Periodical Co AB\nUppsala: AB Lundequistska\nBokhandeln, AB Norblads Bokhandel,\nAB Arvid Svenson\nGöteborg: AB Eckersteins\nBokhandel\n\n’Cfrebro: AB Albin Westling\nLinköping: AB P M Sahlströms\nBokhandel\nAntal anställda: 321\nÅrsomsättning: 56519 000\nAktiekapital: 1500 000\nVerkst dir: P Davids Thomsen\nEtableringsår: 1953.\n\nALMQVIST &amp; WIKSELLS\nBOK-TRYCKERI AB\n\nPnr 751 25\n\nUppsala 1, V Agatan 16. Box 616.\nTel 018-12 00 00. Tga Calendar\nVerksamhet: Bok- o offsettryckeri,\nbokbinderi samt almanacksförlag\nAvdelningskontor: Stockholm C,\nGamla Brog 26. Tel 08-22 91 80\nAntal anställda: 596\nAktiekapital: 12 000 000\nStyrelse: Dir H W Söderman (ordf),\nfrih C G Langenskiöld, prof Arne\nTiselius, prof Sune Carlson, dir\nGöran Z Haeggström\nVerkst dir: Göran Z Haeggström\nV verkst dir: Roland Adstedt\nFörsäljning, almanackor: Dir\nDetlof Sjögren\n\nFörsäljning, övriga produkten Disp\nGösta Nyström\nEtableringsår: 1839\nOmbildat till aktiebolag 1888.\nÄger Tryckeribolaget Ivar\nHaeggström AB, Almqvist &amp; Wiksell\nBokhandel AB Almqvist &amp; Wiksell\nFörlag AB, Stockholm.\n\nALMQVIST &amp; WIKSELL\nFORLAG AB\n\nPnr 101 22\n\nStockholm 1, Gamla Brog 26. Box\n159. Tel 08-22 9180. Bankgiro\n235-1757. Postgiro 758-3\nVerksamhet: Bokförlag\nAktiekapital: 1 500 000\nVerkst dir: Göran Z Haeggström\nEtableringsår: 1887\nOmbildat till aktiebolag 1928.\n\nALMQVIST &amp; CO AB, G\n\nPnr 201 22\n\nMalmö 1, Hans Michelsensg 2.\nBox 264. Tel 040-38410.\nBankgiro 640-1509. Postgiro 39320-7.\nTga Almship. Telex 3325\nVerksamhet: Auktoriserade\nskeppsmäklare o speditörer\nAktiekapital: 100 000\nVerkst dir: Skeppsmäkl Sune\nAlmqvist\n\nEtableringsår: 1932.\n\nGRANHOLM &amp; KRUGER AB\n\nPnr 10311\n\nStockholm 2, Västerlångg 75. Box\n2043. Tel 08-23 22 60. Bankgiro\n72-1792. Postgiro 55418. TgaSoftwater\nVerksamhet: Konsulterande\ningenjörsbyrå\n\nAktiekapital: 50 000\nVerkst dir: Gunnar Svensson\nEtableringsår: 1957.\n\nCAS\n\nCARL-PHILIPS VVS AB\n\nPnr 261 22\n\nLandskrona 1, Lilla Strandg 21. Box\n184. Tel 0418-168 00. Bankgiro\n10-1930. Postgiro 268580. Tga\nCarl-Philips\n\nVerksamhet: VVS- o\noljeeldningsinstallationer jämte service\nAntal anställda: 48\nÅrsomsättning: 3000 000\nAktiekapital: 25 000\nVerkst dir: Gunilla\nNilsson-Zätter-ström\n\nChef: Ing Alfons Olsson\nLagerchef: Karl Arne Hansson\nKamrer: Sven Mårtensson\nEtableringsår: 1967.\n\nARROS ARVID ROSLOV AB\n\nPnr 40043\n\nGöteborg 30, Pennygången 84. Fack.\nTel 031-416400. Bankgiro 33-7270.\nPostgiro 526960\nVerksamhet: Säljer byggnads- o\nskyddsrums material\nAntal anställda: 10\nÅrsomsättning: 3 500 000\nAktiekapital: 5 000\nVerkst dir: Arvid Roslöv\nEtableringsår 1956.\n\nPRI\n\nVarunamn: Montax, Nosink\nAntal anställda: 50\nAktiekapital: 200 000\nVerkst dir: E Tengelin\nTekn chef: Ing H Moeschlin\nEtableringsår: 1940.\n\nWESTERLIND, AB ANDERS\n\nPnr 413 03\n\nGöteborg, Tredje Långg 38. Tel\n031-12 46 90. Bankgiro 848-3174.\nPostgiro 243409-0\nVerksamhet: Tillverkar\ndamkonfektion\n\nAntal anställda: 200\nÅrsomsättning: 17 000 000\nAktiekapital: 100200\nVerkst dir Anders Westerlind.\n\nWESTERLUND, AB E\n\nPnr 55102\n\nJönköping 1, Box 2025. Kålgårdsg\n17. Tel 036-1183 25. Bankgiro\n271-8047. Postgiro 278627-5\nVerksamhet: Utför\nWS-anlägg-ningar\n\nAntal anställda: 30\nAktiekapital: 110 000\nVerkst dir: Ruben Westher\nEtableringsår: 1944.\n\n[-WESTERMARKSELEKTRO-VERKTYG,-]\n\n{+WESTERMARKSELEKTRO-\nVERKTYG,+} AB\n\nPnr 752 22\n\nUppsala, Fyrisg 12. Tel\n018-1445 96. Bankgiro 80-2157.\nPostgiro 476605\n\nVerksamhet: Tillverkar verktyg o\nutrustningar för elverk\nAntal anställda: 5\nÅrsomsättning: 700 000\nAktiekapital: 5 000\nVerkst dir: Eugen Westermark\nEtableringsår: 1955.\n\nBEVI, EL-AB\n\nPnr 384 00\n\nBlomstermåla, Storg 77. Tel\n0499-2 06 10. Bankgiro 293-8082.\nPostgiro 94059-3\n\nVerksamhet: El verkstads-,\ninstallations- o försäljningsrörelse\nAntal anställda: 26\nÅrsomsättning: 2392000\nAktiekapital: 110000\nVerkst dir: Edvin Pettersson\nEtableringsår 1931.\n\nKAFA GULDINDUSTRI, AB\n\nPnr 560 23\n\nBankeryd. Tel 036-770 88.\nBankgiro 804-3689. Postgiro 683041-8\nVerksamhet: Hårdförgyllning o\nför-silvring för industriellt ändamål\nÅrsomsättning: 600 000\nChef: Fabr Karl-Gustav Faxander\nEtableringsår: 1966.\nOmbildat till aktiebolag 1970.\n\nKAFAB, AB\n\nPnr 104 25\n\nStockholm 30, Sankt Göransg 159.\nBox 30003. Tel 08-520170. Tga\nKafab\n\nVerksamhet: Galvanotekniska\nförnödenheter o anläggningar,\nslipmaterial, import o export\nAktiekapital: 50 000\nVerkst dir: S Lövstedt\nEtableringsår: 1938.",
    "structured": {
        "1": {
            "company_name": "RUNESTENS EFTR AB",
            "pnr": "57100",
            "address": "Nässjö, Anneforsv 18",
            "phone_number": "0380-134 25",
            "bank_details": {
                "bankgiro": "45-2776",
                "postgiro": "7875-8"
            },
            "activity": "Säljer o saluför byggnadsmaterial. Huvudförsäljare för Ballingslöv, Eternit, Gyproc, Lättbetong, Mexi, Rockwool, Sp-snicke-rier",
            "employees": 12,
            "annual_turnover": 8000000,
            "capital": 50000,
            "key_personnel": [
                {
                    "name": "Olof Lundberg"
                }
            ],
            "establishment_year": 1967
        },
        "2": {
            "company_name": "RUNO AB, A G",
            "pnr": "431 37",
            "address": "Mölndal, Flöjelbergsg 8 A",
            "phone_number": "031-87 32 00",
            "bank_details": {
                "bankgiro": "84-8070",
                "postgiro": "426588"
            },
            "activity": "Tillverkar borstbin-derimaskiner o syntetisk fiber",
            "employees": 25,
            "annual_turnover": 2000000,
            "capital": 75000,
            "key_personnel": [
                {
                    "name": "Anders G Runo"
                }
            ],
            "establishment_year": 1924
        },
        "3": {
            "company_name": "INDUSTRIGARN, AB",
            "pnr": "50106",
            "address": "Borås 1, Box 313, Arlag 7",
            "phone_number": "033-1278 00",
            "bank_details": {
                "bankgiro": "531-4695",
                "postgiro": "583939-4"
            },
            "activity": "Industrigarner, alla slag engros",
            "establishment_year": 1939
        },
        "4": {
            "company_name": "ALMGRENS STÄMPLAR AB",
            "pnr": "70106",
            "address": "Örebro 1, O Bang 26, Box 478",
            "phone_number": "019-1160 39, 12 64 39",
            "bank_details": {
                "bankgiro": "817-3031",
                "postgiro": "91392-1"
            },
            "activity": "Tillverkar alla slags stämplar o gummiklichéer. Utför gravyr för pressverktyg, gravering av skyltar i plexiglas o rostfritt",
            "capital": 20000,
            "key_personnel": [
                {
                    "name": "Artur Almgren"
                }
            ],
            "establishment_year": 1924
        },
        "5": {
            "company_name": "ALMGREN AB TRÄVARU-AGENTUR, ESKIL",
            "pnr": "41104",
            "address": "Göteborg, Gullbergs Strandg 2",
            "phone_number": "031-15 65 25",
            "activity": "Trävaror i parti",
            "employees": 3,
            "annual_turnover": 12000000
        },
        "6": {
            "company_name": "ALMKVIST, ALMQVIST ALMQVIST &amp; ELIASSON AB",
            "pnr": "280 22",
            "address": "Vittsjö, Emmaljunga",
            "phone_number": "0451-240 61",
            "bank_details": {
                "bankgiro": "279-5060",
                "postgiro": "298963-0"
            },
            "activity": "Tillverkar sittmöbler fåtöljer o soffor",
            "employees": 12,
            "annual_turnover": 1100000,
            "capital": 25000,
            "key_personnel": [
                {
                    "name": "Ake Almqvist"
                }
            ],
            "establishment_year": 1945
        },
        "7": {
            "company_name": "ALMQVIST &amp; WIKSELL BOK-HANDEL AB",
            "pnr": "101 20",
            "address": "Stockholm 1, Gamla Brog 26, Box 62",
            "phone_number": "08-23 79 90",
            "bank_details": {
                "bankgiro": "23-5216",
                "postgiro": "350833"
            },
            "activity": "Svensk o utländsk bokhandel, vetenskaplig o tekn litteratur, tidskriftsförmedling, export av skandinavisk vetenskaplig litteratur. Pappershandel",
            "employees": 321,
            "annual_turnover": 56519000,
            "capital": 1500000,
            "key_personnel": [
                {
                    "name": "P Davids Thomsen"
                }
            ],
            "establishment_year": 1953
        },
        "8": {
            "company_name": "ALMQVIST &amp; WIKSELLS BOK-TRYCKERI AB",
            "pnr": "751 25",
            "address": "Uppsala 1, V Agatan 16, Box 616",
            "phone_number": "018-12 00 00",
            "activity": "Bok- o offsettryckeri, bokbinderi samt almanacksförlag",
            "employees": 596,
            "capital": 12000000,
            "key_personnel": [
                {
                    "name": "Göran Z Haeggström",
                    "position": "Verkst dir"
                },
                {
                    "name": "Roland Adstedt",
                    "position": "V verkst dir"
                },
                {
                    "name": "Detlof Sjögren",
                    "position": "Försäljning, almanackor Dir"
                },
                {
                    "name": "Gösta Nyström",
                    "position": "Försäljning, övriga produkten Disp"
                }
            ],
            "establishment_year": 1839
        },
        "9": {
            "company_name": "ALMQVIST &amp; WIKSELL FORLAG AB",
            "pnr": "101 22",
            "address": "Stockholm 1, Gamla Brog 26, Box 159",
            "phone_number": "08-22 9180",
            "bank_details": {
                "bankgiro": "235-1757",
                "postgiro": "758-3"
            },
            "activity": "Bokförlag",
            "capital": 1500000,
            "key_personnel": [
                {
                    "name": "Göran Z Haeggström"
                }
            ],
            "establishment_year": 1887
        },
        "10": {
            "company_name": "ALMQVIST &amp; CO AB, G",
            "pnr": "201 22",
            "address": "Malmö 1, Hans Michelsensg 2, Box 264",
            "phone_number": "040-38410",
            "bank_details": {
                "bankgiro": "640-1509",
                "postgiro": "39320-7"
            },
            "activity": "Auktoriserade skeppsmäklare o speditörer",
            "capital": 100000,
            "key_personnel": [
                {
                    "name": "Skeppsmäkl Sune Almqvist"
                }
            ],
            "establishment_year": 1932
        },
        "11": {
            "company_name": "GRANHOLM &amp; KRUGER AB",
            "pnr": "10311",
            "address": "Stockholm 2, Västerlångg 75, Box 2043",
            "phone_number": "08-23 22 60",
            "bank_details": {
                "bankgiro": "72-1792",
                "postgiro": "55418"
            },
            "activity": "Konsulterande ingenjörsbyrå",
            "capital": 50000,
            "key_personnel": [
                {
                    "name": "Gunnar Svensson",
                    "position": "Verkst dir"
                }
            ],
            "establishment_year": 1957
        },
        "12": {
            "company_name": "CARL-PHILIPS VVS AB",
            "pnr": "261 22",
            "address": "Landskrona 1, Lilla Strandg 21, Box 184",
            "phone_number": "0418-168 00",
            "bank_details": {
                "bankgiro": "10-1930",
                "postgiro": "268580"
            },
            "activity": "VVS- o oljeeldningsinstallationer jämte service",
            "employees": 48,
            "annual_turnover": 3000000,
            "capital": 25000,
            "key_personnel": [
                {
                    "name": "Gunilla Nilsson-Zätter-ström",
                    "position": "Verkst dir"
                },
                {
                    "name": "Alfons Olsson",
                    "position": "Chef"
                },
                {
                    "name": "Karl Arne Hansson",
                    "position": "Lagerchef"
                },
                {
                    "name": "Sven Mårtensson",
                    "position": "Kamrer"
                }
            ],
            "establishment_year": 1967
        },
        "13": {
            "company_name": "ARROS ARVID ROSLOV AB",
            "pnr": "40043",
            "address": "Göteborg 30, Pennygången 84, Fack",
            "phone_number": "031-416400",
            "bank_details": {
                "bankgiro": "33-7270",
                "postgiro": "526960"
            },
            "activity": "Säljer byggnads- o skyddsrums material",
            "employees": 10,
            "annual_turnover": 3500000,
            "capital": 5000,
            "key_personnel": [
                {
                    "name": "Arvid Roslöv",
                    "position": "Verkst dir"
                }
            ],
            "establishment_year": 1956
        },
        "14": {
            "company_name": "Pnr",
            "pnr": "NA"
        },
        "15": {
            "company_name": "WESTERLIND, AB ANDERS",
            "pnr": "413 03",
            "address": "Göteborg, Tredje Långg 38",
            "phone_number": "031-12 46 90",
            "bank_details": {
                "bankgiro": "848-3174",
                "postgiro": "243409-0"
            },
            "activity": "Tillverkar damkonfektion",
            "employees": 200,
            "annual_turnover": 17000000,
            "capital": 100200,
            "key_personnel": [
                {
                    "name": "Anders Westerlind",
                    "position": "Verkst dir"
                }
            ]
        },
        "16": {
            "company_name": "WESTERLUND, AB E",
            "pnr": "55102",
            "address": "Jönköping 1, Box 2025, Kålgårdsg 17",
            "phone_number": "036-1183 25",
            "bank_details": {
                "bankgiro": "271-8047",
                "postgiro": "278627-5"
            },
            "activity": "Utför WS-anlägg-ningar",
            "employees": 30,
            "capital": 110000,
            "key_personnel": [
                {
                    "name": "Ruben Westher",
                    "position": "Verkst dir"
                }
            ],
            "establishment_year": 1944
        },
        "17": {
            "company_name": "[-WESTERMARKSELEKTRO-VERKTYG,-] AB",
            "pnr": "752 22",
            "address": "Uppsala, Fyrisg 12",
            "phone_number": "018-1445 96",
            "bank_details": {
                "bankgiro": "80-2157",
                "postgiro": "476605"
            },
            "activity": "Tillverkar verktyg o utrustningar för elverk",
            "employees": 5,
            "annual_turnover": 700000,
            "capital": 5000,
            "key_personnel": [
                {
                    "name": "Eugen Westermark",
                    "position": "Verkst dir"
                }
            ],
            "establishment_year": 1955
        },
        "18": {
            "company_name": "BEVI, EL-AB",
            "pnr": "384 00",
            "address": "Blomstermåla, Storg 77",
            "phone_number": "0499-2 06 10",
            "bank_details": {
                "bankgiro": "293-8082",
                "postgiro": "94059-3"
            },
            "activity": "El verkstads-, installations- o försäljningsrörelse",
            "employees": 26,
            "annual_turnover": 2392000,
            "capital": 110000,
            "key_personnel": [
                {
                    "name": "Edvin Pettersson",
                    "position": "Verkst dir"
                }
            ],
            "establishment_year": 1931
        },
        "19": {
            "company_name": "KAFA GULDINDUSTRI, AB",
            "pnr": "560 23",
            "address": "Bankeryd",
            "phone_number": "036-770 88",
            "bank_details": {
                "bankgiro": "804-3689",
                "postgiro": "683041-8"
            },
            "activity": "Hårdförgyllning o för-silvring för industriellt ändamål",
            "annual_turnover": 600000,
            "key_personnel": [
                {
                    "name": "Fabr Karl-Gustav Faxander",
                    "position": "Chef"
                }
            ],
            "establishment_year": 1966
        },
        "20": {
            "company_name": "KAFAB, AB",
            "pnr": "104 25",
            "address": "Stockholm 30, Sankt Göransg 159, Box 30003",
            "phone_number": "08-520170",
            "activity": "Galvanotekniska förnödenheter o anläggningar, slipmaterial, import o export",
            "capital": 50000,
            "key_personnel": [
                {
                    "name": "S Lövstedt",
                    "position": "Verkst dir"
                }
            ],
            "establishment_year": 1938
        }
    }
}