{
    "original": "ZELANDER AB,HARRY\n\nPnr 41113\n\nGöteborg. Smedjeg 5. Tel\n031-118015, 118077. Bankgiro\n42-0204. Postgiro 48145. Tga Zeland\nVerksamhet: Tillverkar, köper o\nsäljer sågade o hyvlade trävaror\nAntal anstäUda: 75\nAktiekapital: 450 000\nVerkst dir: Sten Zelander\nEtableringsår: 1943.\n\nZETATRADE AB\n\n(Zethraeus trading ab)\n\nPrr 103 64\n\nStockholm 3, Box 3239.\nHollän-darg 9 A. Tel 08-24 48 50. Tga\nZetatrade. Telex 10804\nVerksamhet: Grossist- o\nagenturrörelse inom grafiska- o\nförgylleri-branschen, skinn, läder, plast,\nvarmplägning av folier,\nvarmpräg-lingsmaskiner\nAntal anstäUda: 19\nAktiekapital: 100 000\nVerkst dir: Yngve Zethraeus\nEtableringsår: 1917\nOmbildat till aktiebolag 1949.\n\nZETHRAEUS AB, CLAES W\n\nPnr 121 22\n\nJohanneshov 1, Paternosterv 52.\nBox 68. Tel 08-3904 35. Bankgiro\n72-0116. Postgiro 197719.\nTelex 17345 CLAZETA S.\nTga Claeszeta\n\nVerksamhet: Säljer material o mar\nskiner för den grafiska branschen\nAntal anstäUda: 10\nAktiekapital: 125 000\nVeikst dir Claes W Zethraeus\nEtableringsår 1949.\n\nBURSERYDS TRÄINDUSTRI, AB\n\nPnr 330 26\n\nSmålands Burseryd, Bureg 12. Box\n54. Tel 0371-50051, 501 15.\nBankgiro 550-7488. Postgiro 94045-2\nVerksamhet: Tillverkar o säljer\nekparkett\n\nAntal anställda: 30\nÅrsomsättning: 2 000 000\nAktiekapital: 450000\nVerkst dir: Valfrid Sandén\nEtableringsår: 1935.\n\nINDEX, AB\n\nPnr 103 40\n\nStockholm 40, Kungsg 33. Pack.\nTel 08-24 87 00. Tga Pindex\nVerksamhet: Industridammsugare\nAktiekapital: 7 000\nVerkst dir Sven Melin\nEtableringsår 1933.\n\nKRÅNGEDE AB\n\nPnr 103 80\n\nStockholm 7, Nybrog 9. Fack. Tel\n08-63 02 50. Postgiro 53006-3. Tga\nKrångedekraft\n\nVerksamhet: Kraftverksrörelse\nAntal anställda: 154\nÅrsomsättning: 145 000 000\nAktiekapital: 198000 000\nVerkst din Gösta Agrenius.\n\nK S VERKEN AB\n\nPnr 462 00\n\nVänersborg, Lilla Vassbotten. Tel\n0521-139 20. Bankgiro 88-8850.\nPostgiro 513120\n\nVerksamhet: Tillverkar plåt,\nprofil- o betongjärnsaxar,\nbetongjärns-böjare, revolverstansmaskiner,\nböj-apparater för järn samt cisterner,\njärnkonstruktioner o flänsar\nPlatschef: Ing Anders Hågnell\nEtableringsår: 1959\nDotterbolag till I Nejmans\nExportaffär, Trollhättan.\n\nKS-BOLAGEN\n\nPnr 113 39\n\nStockholm, Tomtebog 13. Tel\n08-32 77 22,32 33 03,32 36 20,32 88 08.\nBankgiro 726-2256. Postgiro\n195395-9. Tga Industrisund\nVerksamhet: Revision, bokföring,\ndeklarationer, skatteärenden,\nfastighetsförvaltning o översättningar\nAvdelningskontor: 175 00\nJakobsberg, Frihetsv 15. Tel 0758-305 83,\n31613, 556 90\nAntal anställda: 20\nÄgare o chef: Revisor Ingemar\nSundelius\n\nEtableringsår: 1944.\n\nKUGELBERGS\nBOK-TRYCKERI AB\n\nPnr 112 51\n\nStockholm, Franzéng 4. Tel\n08-526000, 526006. Bankgiro\n733-8064. Postgiro 59185-9\nVerksamhet: Utför färg-,\nreklam-o exporttrycksaker\nAntal anställda: 18\nÅrsomsättning: 2 000 000\nAktiekapital: 10 000\nVerkst dir: C F Kugelberg\nEtableringsår: 1946.\n\nBJERCKE AB, ALF\n\nPnr 421 22\n\nVästra Frölunda 1, Box 151.\nKlang-färgsg 13. Tel 031-29 21 10.\nBankgiro 41-0089. Postgiro 43085.\nTga Bjerckepaint.\nTelex 21068 BJERCKE S\nVerksamhet: Tillverkar o säljer\nfärger o fernissor, plastråvaror\nAntal anställda: 70\nÅrsomsättning: 23 000 000\nAktiekapital: 472 500\nVerkst dir: Olav Hauglid\nEtableringsår: 1930.\n\nHESSELMAN BIL-AERO AB\n\nPnr 12612 Sthlm 42\nHägersten, Elektrav 29. Box\n42073, Sthlm 42. Tel 08-19 02 60.\nBankgiro 171-9038. Postgiro\n77571-8. Tga Autoavia.\nTelex 10182\n\nVerksamhet: Grossist inom bil-,\nflyg-, marin- o industriprodukter\nAntal anställda: 140\nÅrsomsättning: 32 000 000\nAktiekapital: 2 250 000\nVerkst dir: Hans Bergström\nEtableringsår: 1931.\n\nHESSLOWS\nKONSTRUKTIONS-BY RÄ, AB\n\nPnr 302 43\n\nHalmstad, Storg 20. Tel\n035-12 7126. Bankgiro 530-4084.\nPostgiro 598922-3\n\nVerksamhet: Konsulterande\ningenjörsbyrå inom byggnadsbranschen\nAntal anställda: 10\nAktiekapital: 15 000\nAvd-chef: Civiling Ture Hesslow\nEtableringsår: 1962.\n\nSTÅLGRAVYR\n\nPnr 63106\n\nEskilstuna 1, Box 407. Nyg 41.\nTel016-14 0639. Postgiro 288061-5\nVerksamhet: Tillverkar alla slags\nstålstämplar\nChef: C Carlsson.\n\nSTÅLGRAVYR, AB\n\nPnr 280 70\n\nLönsboda, Box 109. Glimåkrav. Tel\n0479-206 55. Bankgiro 984-9894.\nPostgiro 130537-4\nVerksamhet: Tillverkar\nVVS-armatur i termoplast. Egen\nverktygstillverkning\nVarunamn: STG\nAntal anställda: 20\nÅrsomsättning: 1 100 000\nAktiekapital: 20 000\nStyrelse: Pabr Ragnar Nilsson\n(ordf), fabr Sten-Erik Karlsson,\nfabr Sven-Arne Svensson, fabr\nWilly Svensson\n\nVerkst dir: Sven-Arne Svensson\nÖvriga chefer: Pabr Sten-Erik\nKarlsson, fabr Willy Svensson\nEtableringsår: 1962\nOmbildat till aktiebolag 1965.\n\nSTÅLMONTERINGAR AB\nSTÅLAB\n\nPnr 46101\n\nTrollhättan 1, Box 34. Godsadress:\nIndustrig 10. Tel 0520-300 90.\nBankgiro 55-1867. Postgiro 445267\nVerksamhet: Uppför nyckelfärdiga\nbyggnader efter egna eller erhållna\nritningar, i kombinationer av stål,\nplåt o eventuellt trä, isolerade o\noisolerade. Mek verkstad, grovplåtr\nslageri o licenssvetsning\nAntal anstäUda: 50\nÅrsomsättning: 3 800 000\nAktiekapital: 300 000\nVerkst dir: Fabr Kjell Sjöström\nEtableringsår: 1954\nOmbildat till aktiebolag 1957.\n\nSTÅLNYLON AB\n\nPnr 46101\n\nTrollhättan 1, Box 190. Felterusg\n12. Tel 0520-154 40. Bankgiro\n892-6487. Postgiro 117436-6\nVerksamhet: Tillverkar strumpor o\nblåkläder i 100 % nylon\nAktiekapital: 10000\nFirmatecknare: A S Randhem\nEtableringsår: 1953.\n\nSTÅLPRODUKTER ERIK M\nLORENTZON AB\n\nPnr 82101\n\nBollnäs 1, Stationsg 8. Box 42. Tel\n0278-13015. Bankgiro 785-5414.\nPostgiro 143602-1. Tga Rapid\nVerksamhet: Lyftverktyg o\nlyftan-ordningar av alla slag\nVarunamn: MV, Rapid, Whippet\nAktiekapital: 50000\nVerkst dir: J-E Lorentzon\nEtableringsår: 1938.\n\nSTÅLPRODUKTER I\nGÖTE-BORG AB\n\nPnr 402 41\n\nGöteborg 12, Chapmansg 6. Box\n12011. Tel 031-1409 38, 141139.\nTelex 20636\n\nVerksamhet: Import o export av\njärn o stål samt metaller\nAktiekapital: 50 000\nEtableringsår: 1961.\n\nUGNSBYGGE, AB\n\nPnr 263 00\n\nHöganäs, Norreg. Tel 042-424 60.\nBankgiro 270-5622. Postgiro\n21469-2\n\nVerksamhet: Utför\nentreprenadarbeten i byggnader av ugnar o\nskorstenar för industrier etc.\nTillhandahåller även material såsom eldfast\ntegel, stampmassa o övriga\nprodukter som tillhör denna\nverksamhet\n\nAntal anställda: 100\nÅrsomsättning: 10 000 000\nAktiekapital: 5 000\nStyrelse: Dir Hugo Berg (ordf), fru\nElvy Berg\n\nVerkst dir Hugo Berg\n\nVerkmäst: Gösta Bergström\nVerkmäst: Bengt Lycksell\nEtableringsår 1965.\n\nROHLAND AB, GERHARD\n\nPnr 421 31\n\nVästra Frölunda, Frökotteg 23. Tel\n031-492162, 4921 76. Telex 20796.\nTga Talurit\n\nVerksamhet: Tillverkar patentlinlås\nAktiekapital: 5 000\nFirmatecknare: Gerhard Rohland\nEtableringsår: 1956.\n\nROLFERTS ELEKTRISKA\nINSTALLATIONSBYRÅ\n\nPnr 18160\n\nLidingö, S Kungs v 150. Tel\n08-766 28 00, 765 22 97. Postgiro 97239\nVerksamhet: Elektr\ninstallationsrörelse av stark- o svagström\nChef: Gunnar Rolfert\nEtableringsår: 1924.\n\nAROT, AB\n\nPnr 260 82\n\nSkälderviken, Box 43. Tel\n0431-20910. Bankgiro 672-3480.\nPostgiro 476496-5\n\nVerksamhet: Plasttillverkning av\nkableskydd, kabeldragningsrör,\nel-lister o -rör, salivsugare.\nSpecialitet: högmolekylära\npoly-etener\n\nFörsäljningskontor\nkabelskydds-produkter: 21136 Malmö, Baltzarsg\n31. Tel 040-9716 70\nVarunamn: Telet, Bonflex\nAntal anställda: 20\nÅrsomsättning: 3 000 000\nAktiekapital: 200 000\nVerkst dir: Civiling Björn\nNordstrand\n\nEtableringsår: 1958.",
    "structured": {
        "1": {
            "company_name": "ZELANDER AB",
            "pnr": "41113",
            "address": "Göteborg. Smedjeg 5",
            "phone_number": "031-118015, 118077",
            "bank_details": {
                "bankgiro": "42-0204",
                "postgiro": "48145"
            },
            "activity": "Tillverkar, köper o säljer sågade o hyvlade trävaror",
            "employees": 75,
            "capital": 450000,
            "key_personnel": [
                {
                    "name": "Sten Zelander",
                    "position": "Verkst dir"
                }
            ],
            "establishment_year": 1943
        },
        "2": {
            "company_name": "ZETATRADE AB",
            "pnr": "103 64",
            "address": "Stockholm 3, Box 3239. Hollän-darg 9 A",
            "phone_number": "08-24 48 50",
            "activity": "Grossist- o agenturrörelse inom grafiska- o förgylleri-branschen, skinn, läder, plast, varmplägning av folier, varmpräg-lingsmaskiner",
            "employees": 19,
            "capital": 100000,
            "key_personnel": [
                {
                    "name": "Yngve Zethraeus",
                    "position": "Verkst dir"
                }
            ],
            "establishment_year": 1917,
            "ombildat_till_aktiebolag_year": 1949
        },
        "3": {
            "company_name": "ZETHRAEUS AB, CLAES W",
            "pnr": "121 22",
            "address": "Johanneshov 1, Paternosterv 52. Box 68",
            "phone_number": "08-3904 35",
            "bank_details": {
                "bankgiro": "72-0116",
                "postgiro": "197719"
            },
            "activity": "Säljer material o mar skiner för den grafiska branschen",
            "employees": 10,
            "capital": 125000,
            "key_personnel": [
                {
                    "name": "Claes W Zethraeus",
                    "position": "Verkst dir"
                }
            ],
            "establishment_year": 1949
        },
        "4": {
            "company_name": "BURSERYDS TRÄINDUSTRI, AB",
            "pnr": "330 26",
            "address": "Smålands Burseryd, Bureg 12. Box 54",
            "phone_number": "0371-50051, 501 15",
            "bank_details": {
                "bankgiro": "550-7488",
                "postgiro": "94045-2"
            },
            "activity": "Tillverkar o säljer eklparkett",
            "employees": 30,
            "annual_turnover": 2000000,
            "capital": 450000,
            "key_personnel": [
                {
                    "name": "Valfrid Sandén",
                    "position": "Verkst dir"
                }
            ],
            "establishment_year": 1935
        },
        "5": {
            "company_name": "INDEX, AB",
            "pnr": "103 40",
            "address": "Stockholm 40, Kungsg 33. Pack",
            "phone_number": "08-24 87 00",
            "activity": "Industridammsugare",
            "capital": 7000,
            "key_personnel": [
                {
                    "name": "Sven Melin",
                    "position": "Verkst dir"
                }
            ],
            "establishment_year": 1933
        },
        "6": {
            "company_name": "KRÅNGEDE AB",
            "pnr": "103 80",
            "address": "Stockholm 7, Nybrog 9. Fack",
            "phone_number": "08-63 02 50",
            "postgiro": "53006-3",
            "activity": "Kraftverksrörelse",
            "employees": 154,
            "annual_turnover": 145000000,
            "capital": 198000000,
            "key_personnel": [
                {
                    "name": "Gösta Agrenius",
                    "position": "Verkst dir"
                }
            ]
        },
        "7": {
            "company_name": "K S VERKEN AB",
            "pnr": "462 00",
            "address": "Vänersborg, Lilla Vassbotten",
            "phone_number": "0521-139 20",
            "bank_details": {
                "bankgiro": "88-8850",
                "postgiro": "513120"
            },
            "activity": "Tillverkar plåt, profil- o betongjärnsaxar, betongjärns-böjare, revolverstansmaskiner, böj-apparater för järn samt cisterner, järnkonstruktioner o flänsar",
            "key_personnel": [
                {
                    "name": "Ing Anders Hågnell",
                    "position": "Platschef"
                }
            ],
            "establishment_year": 1959,
            "dotterbolag_till": "I Nejmans Exportaffär, Trollhättan"
        },
        "8": {
            "company_name": "KS-BOLAGEN",
            "pnr": "113 39",
            "address": "Stockholm, Tomtebog 13",
            "phone_number": "08-32 77 22, 32 33 03, 32 36 20, 32 88 08",
            "bank_details": {
                "bankgiro": "726-2256",
                "postgiro": "195395-9"
            },
            "activity": "Revision, bokföring, deklarationer, skatteärenden, fastighetsförvaltning o översättningar",
            "employees": 20,
            "key_personnel": [
                {
                    "name": "Ingemar Sundelius",
                    "position": "Ägare o chef"
                }
            ],
            "establishment_year": 1944
        },
        "9": {
            "company_name": "KUGELBERGS BOK-TRYCKERI AB",
            "pnr": "112 51",
            "address": "Stockholm, Franzéng 4",
            "phone_number": "08-526000, 526006",
            "bank_details": {
                "bankgiro": "733-8064",
                "postgiro": "59185-9"
            },
            "activity": "Utför färg-, reklam-o exporttrycksaker",
            "employees": 18,
            "annual_turnover": 2000000,
            "capital": 10000,
            "key_personnel": [
                {
                    "name": "C F Kugelberg",
                    "position": "Verkst dir"
                }
            ],
            "establishment_year": 1946
        },
        "10": {
            "company_name": "BJERCKE AB, ALFs",
            "pnr": "421 22",
            "address": "Västra Frölunda 1, Box 151, Klang-fägrsg 13",
            "phone_number": "031-29 21 10",
            "bank_details": {
                "bankgiro": "41-0089",
                "postgiro": "43085"
            },
            "activity": "Tillverkar o säljer färger o fernissor, plastråvaror",
            "employees": 70,
            "annual_turnover": 23000000,
            "capital": 472500,
            "key_personnel": [
                {
                    "name": "Olav Hauglid",
                    "position": "Verkst dir"
                }
            ],
            "establishment_year": 1930
        },
        "11": {
            "company_name": "HESSELMAN BIL-AERO AB",
            "pnr": "12612 Sthlm 42",
            "address": "Hägersten, Elektrav 29, Box 42073, Sthlm 42",
            "phone_number": "08-19 02 60",
            "bank_details": {
                "bankgiro": "171-9038",
                "postgiro": "77571-8"
            },
            "activity": "Grossist inom bil-, flyg-, marin- o industriprodukter",
            "employees": 140,
            "annual_turnover": 32000000,
            "capital": 2250000,
            "key_personnel": [
                {
                    "name": "Hans Bergström",
                    "position": "Verkst dir"
                }
            ],
            "establishment_year": 1931
        }
    }
}