{
    "original": "SJÖHOLM AB, ARTHUR\n\nPnr 401 25\n\nGöteborg 1, Slussplatsen 1. Box\n374. Tel 031-13 17 36, 13 93 27.\nBankgiro 50-0708. Postgiro\n44823-3. Tga Sjocomp. Telex 2286\nVerksamhet: Exporterar papper,\npapp, wallboard, plywood, trävaror\nAktiekapital: 120 000\nVerkst dir: R E Weinegren\nEtableringsån 1936.\n\nMODIGS MEKANISKA\nVERKSTAD\n\nPnr 570 80\n\nVirserum, Box 13. Hagabergsg. Tel\n0495-303 5 0, 307 4 0. Bankgiro\n857-8346. Postgiro 388490-5\nVerksamhet: Tillverkar W\nsnabbsvarvar, radialborrmaskiner\no universalborrmaskiner\nAntal anstäUda: 25\nÅrsomsättning: 2 500 000\nÄgare o chef: Fru Ulla Modig\nEtableringsår: 1947.\n\nHAMMARPLAST AB\n\nPnr 360 20\n\nTingsryd. Huvudkontor. Tel\n0477-108 00. Bankgiro 864-1623.\nPostgiro 384723-3. Tga Hammarplast\n\nmm\n\nTONGIVARE I PLAST\n\nESAS| HAMMARPLAST\n\nVerksamhet: Formsprutade\nplast-artiklan Hushålls-, trädgårds-,\ntoalett-, sport- o fritidsartiklar,\ntermoskärl, lådor, backar, förvarings- o\ntransportkärl. Formgjutna\nlättplast-artiklar (Styropor): Blomkrukor,\nbalkonglådor o emballage.\nEgen formtillverkning\nFabriker i Tingsryd o Skara\nFörsäljningsavdelning i Skara tör\nformgods i termoplast för industri.\nTel 0511-133 00\n\nVarunamn: Duroten, Hammarplast,\n\nKristallon\n\nAntal anställda: 500\n\nÅrsomsättning: 40 000 000\n\nAktiekapital: 4 000 000\n\nVerkst dir: Hugo Hammargren\n\nEkonomichef: Lars-Eric Broman\nTekn chef o platschef i Skara:\n\nNils Helldin\n\nFörsäljn-dir: Carl Hammargren\nFörsäljn-chef: Bo Bengtson\nExportchef: Ola Curtelius\nLegoförsäljn Skara: Knut Jonsson\nInköpschef: Sven Areland\nEtableringsår: 1947.\n\nHAMMARSTEDT VERKSTADS\nAB, BRÖDERNA\n\nPnr 35104\n\nVäxjö 1, Box 88. Arabyg. Tel\n0470-103 20. Bankgiro 292-6145.\nPostgiro 279789-2\n\nVerksamhet: Utför legoarbeten 1\nexcenter- o dragpressar\nAntal anstäUda: 200\nÅrsomsättning: 16 000 000\nAktiekapital: 600 000\nVerkst dir: Töre Hammarstedt\nEtableringsår: 1899.\n\nHAMMARSTEDT VERKSTADS\nAB, BENGT\n\nPnr 28100\n\nHässleholm. Tel 0451-800 85.\nBankgiro 866-3809. Postgiro\n79818-1. Tga Hammarbolag\nVerksamhet: Beställningsarbeten i\nplåt-, press- o maskinverkstad\nAntal anstäUda: 200\nÅrsomsättning: 17 000 000\nAktiekapital: 280 000\nVerkst dir: Bengt Hammarstedt\nEtableringsår: 1957.\n\nSTENMONTERING AB\n\nPnr 552 42\n\nJönköping, Odeng 24. Tel\n036-1108 65, 164470\n\nVerksamhet: Levererar o monterar\nall slags natursten\nVerkstad: Jönköping, Odeng 24.\nTel 036-1108 65. Bost Huskvarna,\nFlor ag 5. Tel 036-13 18 54\nAktiekapital: 10 000\nVerkst dir: Bror Carlsson\nEtableringsår: 1960.\n\nVAR\n\nVerksamhet; Generalagent i\nSverige för SABB diesel\nVarunamn: SABB diesel\nAktiekapital: 10 000\nVerkst dir: Ing Gösta Warlin\nEtableringsàr: 1957.\n\nVARMFORZINKNING, AB\n\nPnr 330 23\n\nSmålandsstenar, Box 159. Tel\n0371-314 20. Bankgiro 42-7653. Postgiro\n340830\n\nVerksamhet: Varmförzinkning av\njärn- o stålkonstruktioner.\nTillverkning av grundbultar o\nbelysningsstolpar\n\nAntal anställda: 30\nAktiekapital: 200 000\nFirmatecknare: Pabr Hans\nWeland-son, fabr A Ekström\nEtableringsàr: 1959.\n\nWARNER ELECTRIC AB\n\nPnr 127 02\n\nSkärholmen 2, Lilla Sällskapets v\n86. Box 2086. Tel 08-88 95 25.\nBankgiro 74-9702. Postgiro 156380.\nTga Warbrake. Telex 17735\nVerksamhet: Säljer\nelektromagnetiska kopplingar o bromsar,\nkul-mutterskruvar samt elkontroller för\ndessa\n\nVarunamn: Beaver, Warner\nAktiekapital: 100 000\nStyrelse: Bankdir Rolf Tjernström\n(ordf), mr Paul de Belay, ing Nils\nBesterman\n\nVerkst dir: Ing Nils Besterman\nEtableringsàr: 1965\nDotterbolag till Warner Electric\nBrake &amp; Clutch Company, Beloit,\nWisconsin, USA.\n\nWARNER-SERGEL FILM AB\n\nPnr 11183\n\nStockholm 1, Kungsg 44. Box 1326.\nTel 08-23 0740. Bankgiro\n722-4983. Postgiro 705620-3. Tga\nWarne rsergel\n\nVerksamhet: Filmuthyrning\nAntal anställda: 18\nÅrsomsättning: 3 841000\nAktiekapital: 5 000\nVerkst dir: Bernt Larsson\nEtableringsàr: 1964.\n\nVARNAS-FURETAG EN AB\n\nPnr 730 40\n\nKolbäck, Sörstafors Bruk. Tel\n0220-404 60\n\nVerksamhet: Tillverkar lätt- o\ntungmetallgjutgods i Kolbäck\n(Kolbäck Metall) o Eskilstuna\n(Bröd Söderberg) samt\ngråjärns-gjutgods i Tierp (Tierps Järnbruk)\nAntal anställda: 450\nÅrsomsättning: 40 000 000\nAktiekapital: 2 500 000\nVerkst dir: Allan Vamäs.\nTekn chef: Uno Heldert\nFörsäljn-chef: Emil Steinbrecher\nEkonomichef: Gustaf Eriksson\nInköpschef: Lars Malm\nUtveckling: Christer Varnäs.\n\nVARUHANTERING I\nGOT E BORG AB\n\nPnr 422 46\n\nHisings Backa, Backadalsmotet.\nTel 031-521943, 521944. Bank-\n\ngiro 513-6585. Postgiro 44441-4\n\nVerksamhet: Lastpallar, pallkragar,\n\nemballage\n\nAntal anställda: 12\n\nAktiekapital: 5 000\n\nVerkst din Rune Johansson\n\nEtableringsàr: 1963.\n\nVARUHUS\n\nse resp namn.\n\nVASA REGISTER AB\n\nPnr 17172\n\nSolna, Björnstigen 16. Tel\n08-85 88 10, 85 88 11. Bankgiro\n11-5831. Postgiro 706969\nVerksamhet: Databehandling,\nsystem, programmering\nAntal anställda: 15\nAktiekapital: 12 000\nVerkst dir: Evangelos Alamanos\nEtableringsàr: 1964.\n\nVASA RESEFFEKT AB\n\nPnr 412 53\n\nGöteborg S, Vadmansg 7. Tel\n031-20 85 98. Bankgiro 362-6538.\nPostgiro 40664-5\n\nVerksamhet: Specialväskor för fo\ntoutrustningar o instrument\nAntal anställda: 14\nÅrsomsättning: 700 000\nAktiekapital: 20 000\nVerkst din Stig Johansson\nEtableringsàr: 1923\nOmbildat till aktiebolag 1928.\n\nWASA STÄNGSEL AB\n\nPnr 424 35\n\nAngered, Bredfjällsg 20. Tel\n031-30 12 60. Bankgiro 631-9404.\nPostgiro 47770-3\n\nVerksamhet Leverans o\nuppsättning av stängselnät\nAntal anställda: 15\nÅrsomsättning: 625 000\nAktiekapital; 30 000\nVerkst dir. Benny Rosenblom\nEtableringsàr: 1969.\n\nVASA TRIKÄ AB\n\nPnr 51048\n\nBorgstena, Box 28. Tel 033-63109.\nBankgiro 531-1568. Postgiro\n136544-4\n\nVerksamhet: Tillverkar\ntrikåunder-kläder i dam, herr o goss, yttertrikå\nför damer o herrar, fritidströjor\nAntal anställda: 45\nÅrsomsättning: 3 000 000\nAktiekapital: 45 000\nStyrelse: Anders Andersson (ordf),\nSture Andersson, Ann-Britt\nAndersson\n\nVerkst dir: Sture Andersson\nEtableringsàr: 1947.\n\nWASA TRYCKKNAPPAR AB\n\nPnr 70105\n\nÖrebro 1, Box 336. Tel 019-912-70.\nBankgiro 463-1420. Postgiro\n122608-3\n\nVerksamhet: Tillverkar\ntryckknappar, nitar, skoringar o spännen\nAntal anställda: 35\nÅrsomsättning: 5 000 000\nAktiekapital; 40 000\n\nVeikst dir: Gösta Carlsson\nEtableringsån 1944\nOmbildat till aktiebolag 1965.\n\nWASABOLAGET AB\n\nPnr 115 28\n\nStockholm, Sandhamnsg 39. Tel\n08-67 97 00. Postgiro 1703-8. Tga\nWasaservice\n\nVerksamhet: Utför\nfönsterputsning-ar o städningar. Uthyr stegar o\nbyggnadsställningar av lättmetall\nAktiekapital: 200 000\nVerkst dir: Disp Evert Philipson\nV verkst dir Gunnar Philipson\nEtableringsàr: 1896\nOmbildat till aktiebolag 1940.\n\nWASABRÖD AB\n\nPnr 682 82\n\nFilipstad. Tel 0590-125 00. Telex\n5669. Tga Wasabread\nVerksamhet: Tillverkar o säljer\nknäckebröd o andra\nlivsmedelsprodukter\n\nFilialfabriker 580 06 Linköping 6,\nBox 6062. Tel 013-14 17 90.\nPlatschef: övering S Bressler\n780 20 Stora Tuna, Box 10. Tel\n0243-333 30. Platschef: fabrikschef\nP Cadefors\n\nFörsäljningskontor 16111 Bromma\n11, Fack. Tel 08-26 26 60.\nPlatschef: disp H Hedfors\n682 82 Filipstad. Tel 0590-125 00\n415 05 Göteborg, von Utfallsg 13.\nTel 031-26 21 60. Platschef:\ndistriktschef Stig Gunneling\n794 00 Orsa, Box 7. Tel\n0250-41317\n\n78020 Stora Tuna, Box 10. Tel\n0243-333 30\n\n753 23 Uppsala, Björkg 61-63. Tel\n018-1212 20\n\nÅrsomsättning: 193 000 000\nVerkst dir Finn Madison\nEtableringsàr: 1919.\n\nVASALAMPAN, AB\n\nPnr 12107\n\nJohanneshov 7, Bränning ev 22.\nFack. Tel 08-9100 60. Bankgiro\n47-8670. Postgiro 1781\nVerksamhet: Säljer glödlampor,\nlysrör etc\nVarunamn: Vasa\nAktiekapital : 100000\nStyrelse: Adv Nils Frodell (ordf),\ndir K G Rennerfelt, ing G Widén\nVerkst dir: KG Rennerfelt\nEtableringsàr: 1925.\n\nVASON PRINT\n\nPnr 21137\n\nMalmö, Stora Nyg 2. Tel\n040-32190, 323 93. Bankgiro 403-5580.\nPostgiro 539642-9\nVerksamhet Utför tryck på papper,\nplast o metall\n\nChef: Civilekonom Viktor\nAndersson\n\nEtableringsàr 1970.\n\nVOL\n\nVOLVO, AB\n\nPnr 405 08\n\nGöteborg. Tel 031-54 00 00.\nBankgiro 500-5954. Postgiro 42880-1.\nTga Volvo. Telex 2370\nVerksamhet: Tillverkar bilar,\nbussar\n\nAntal anställda: 20 863\nÅrsomsättning: 3 415 000\nAktiekapital: 342 000 000\nVerkst dir: Pehr G Gyllenhammar\nEtableringsår: 1927.\n\nMAS\n\nÅrsomsättning: 3 000 000\nAktiekapital: 50 000\nVerkst dir: Hans Karlsson\nEtableringsår: 1956.\n\nmaskin &amp; motor i\nsträngnäs ab\n\nPnr 15200\n\nSträngnäs, Malmby. Tel0152-250 18,\n25028. Bankgiro 62-1676. Postgiro\n579018\n\nVerksamhet: Tillverkar lastfordon\nför bilar o traktorer\nAntal anställda: 4\nAktiekapital: 10000\nVeikst dir: Arne Sjödin\nEtableringsår: 1960.\n\nmaskin &amp; motor östersund\nab\n\nPnr 83101\n\nÖstersund 1, Box 26. Kyrkg 70. Tel\n063-171 70. Bankgiro 25-0231.\nPostgiro 577220-7\nVerksamhet: Tillverkar plog- o\nboggilyftar. Säljer skogstraktorer,\ngräv- o snömaskiner. Representant\nför bl a Atlas Copco, Whitlock\nhy-draulgrävare o frontlastare\nVarunamn: Sno-Tric\nAntal anställda: 47\nÅrsomsättning: 23 000 000\nAktiekapital: 100000\nStyrelse: Dir Sven O Persson\n(ordf), dir Olle V Persson, kamrer\nSten Gösta Berglund\nVeikst dir: Sven O Persson\nDisp: Lars Persson\nKamrer: Bo Dahlén\nEtableringsår: 1961.\n\nHEDBERG &amp; HOLMGREN AB\n\nPnr 11122\n\nStockholm, Kungsg 51. Tel\n08-20 98 56, 20 98 76. Postgiro 58887\nVerksamhet: Hemtextilier i parti o\nminut\n\nFilialer: 175 00 Jakobsberg,\nJakobsbergs Centrum. Tel\n0758-37630, 376 50\n\n12436 Bandhagen, Högdalens\nCentrum. Tel 08-86 15 00, 86 15 85\nAktiekapital: 50 000\nVerkst dir: K E Linander\nEtableringsår: 1938.\n\nSMEDBOLAGET AB\n\nPnr 54102\n\nSkövde 2, Gustav Adolfsg 38. Box\n9268. Tel 0500-107 80. Bankgiro\n821-7242. Postgiro 699060-0\nVerksamhet: Tillverkar\nostlager-inredningar o brädgårdstruckar\n\nAntal anställda: 40\nÅrsomsättning: 4 000 000\nAktiekapital: 50 000\nVerkst dir: Karl Unghanse\nEtableringsår: 1901.\n\nGEFIX, INGENJÖRSFIRMA\n\nPnr 183 65\n\nTäby. Roslagsv 16. Tel\n08-756 25 70. Bankgiro 164-7478.\nPostgiro 74790-7\n\nVerksamhet: Mekanisk verkstad.\nLegotillverkning av svarvdetaljer\nChef: Jean Gelin\nEtableringsår: 1946.",
    "structured": {
        "1": {
            "company_name": "SJÖHOLM AB, ARTHUR",
            "address": "Göteborg 1, Slussplatsen 1. Box 374",
            "phone_number": "031-13 17 36, 13 93 27",
            "bank_details": {
                "bankgiro": "50-0708",
                "postgiro": "44823-3"
            },
            "activity": "Exporterar papper, papp, wallboard, plywood, trävaror",
            "capital": 120000,
            "key_personnel": [
                {
                    "name": "R E Weinegren",
                    "position": "Verkst dir"
                }
            ],
            "establishment_year": 1936
        },
        "2": {
            "company_name": "MODIGS MEKANISKA VERKSTAD",
            "address": "Virserum, Box 13. Hagabergsg",
            "phone_number": "0495-303 50, 307 40",
            "bank_details": {
                "bankgiro": "857-8346",
                "postgiro": "388490-5"
            },
            "activity": "Tillverkar Wsnabbsvarvar, radialborrmaskiner o universalborrmaskiner",
            "employees": 25,
            "annual_turnover": 2500000,
            "owner_and_chief": "Fru Ulla Modig",
            "establishment_year": 1947
        },
        "3": {
            "company_name": "HAMMARPLAST AB",
            "address": "Tingsryd",
            "phone_number": "0477-108 00",
            "bank_details": {
                "bankgiro": "864-1623",
                "postgiro": "384723-3"
            },
            "activity": "Formsprutade plast-artiklan Hushålls-, trädgårds-, toalett-, sport- o fritidsartiklar, termoskärl, lådor, backar, förvarings- o transportkärl. Formgjutna lättplast-artiklar (Styropor): Blomkrukor, balkonglådor o emballage",
            "employees": 500,
            "annual_turnover": 40000000,
            "capital": 4000000,
            "key_personnel": [
                {
                    "name": "Hugo Hammargren",
                    "position": "Verkst dir"
                },
                {
                    "name": "Lars-Eric Broman",
                    "position": "Ekonomichef"
                }
            ],
            "establishment_year": 1947
        },
        "4": {
            "company_name": "HAMMARSTEDT VERKSTADS AB, BRÖDERNA",
            "address": "Växjö 1, Box 88. Arabyg",
            "phone_number": "0470-103 20",
            "bank_details": {
                "bankgiro": "292-6145",
                "postgiro": "279789-2"
            },
            "activity": "Utför legoarbeten 1 excenter- o dragpressar",
            "employees": 200,
            "annual_turnover": 16000000,
            "capital": 600000,
            "key_personnel": [
                {
                    "name": "Töre Hammarstedt",
                    "position": "Verkst dir"
                }
            ],
            "establishment_year": 1899
        },
        "5": {
            "company_name": "HAMMARSTEDT VERKSTADS AB, BENGT",
            "address": "Hässleholm",
            "phone_number": "0451-800 85",
            "bank_details": {
                "bankgiro": "866-3809",
                "postgiro": "79818-1"
            },
            "activity": "Beställningsarbeten i plåt-, press- o maskinverkstad",
            "employees": 200,
            "annual_turnover": 17000000,
            "capital": 280000,
            "key_personnel": [
                {
                    "name": "Bengt Hammarstedt",
                    "position": "Verkst dir"
                }
            ],
            "establishment_year": 1957
        },
        "6": {
            "company_name": "STENMONTERING AB",
            "address": "Jönköping, Odeng 24",
            "phone_number": "036-1108 65, 164470",
            "activity": "Levererar o monterar all slags natursten",
            "capital": 10000,
            "key_personnel": [
                {
                    "name": "Bror Carlsson",
                    "position": "Verkst dir"
                }
            ],
            "establishment_year": 1960
        },
        "7": {
            "company_name": "VAR",
            "activity": "Generalagent i Sverige för SABB diesel",
            "capital": 10000,
            "key_personnel": [
                {
                    "name": "Ing Gösta Warlin",
                    "position": "Verkst dir"
                }
            ],
            "establishment_year": 1957
        },
        "8": {
            "company_name": "VARMFORZINKNING, AB",
            "address": "Smålandsstenar, Box 159",
            "phone_number": "0371-314 20",
            "bank_details": {
                "bankgiro": "42-7653",
                "postgiro": "340830"
            },
            "activity": "Varmförzinkning av järn- o stålkonstruktioner. Tillverkning av grundbultar o belysningsstolpar",
            "employees": 30,
            "capital": 200000,
            "key_personnel": [
                {
                    "name": "Pabr Hans Weland-son",
                    "position": "Firmatecknare"
                },
                {
                    "name": "fabr A Ekström",
                    "position": "Firmatecknare"
                }
            ],
            "establishment_year": 1959
        },
        "9": {
            "company_name": "WARNER ELECTRIC AB",
            "address": "Skärholmen 2, Lilla Sällskapets v 86. Box 2086",
            "phone_number": "08-88 95 25",
            "bank_details": {
                "bankgiro": "74-9702",
                "postgiro": "156380"
            },
            "activity": "Säljer elektromagnetiska kopplingar o bromsar, kul-mutterskruvar samt elkontroller för dessa",
            "capital": 100000,
            "key_personnel": [
                {
                    "name": "Rolf Tjernström",
                    "position": "Styrelse: Bankdir"
                },
                {
                    "name": "Paul de Belay",
                    "position": "Styrelse: mr"
                },
                {
                    "name": "Nils Besterman",
                    "position": "Verkst dir"
                }
            ],
            "establishment_year": 1965
        },
        "10": {
            "company_name": "WARNER-SERGEL FILM AB",
            "address": "Stockholm 1, Kungsg 44. Box 1326",
            "phone_number": "08-23 0740",
            "bank_details": {
                "bankgiro": "722-4983",
                "postgiro": "705620-3"
            },
            "activity": "Filmuthyrning",
            "employees": 18,
            "annual_turnover": 3841000,
            "capital": 5000,
            "key_personnel": [
                {
                    "name": "Bernt Larsson",
                    "position": "Verkst dir"
                }
            ],
            "establishment_year": 1964
        }
    }
}