{
    "original": "HOVMAN. KONFEKTIONS AB\n\nPnr 36051\n\nHovmantorp. Tel 0478-405 60\nVerksamhet: Tillverkar\nfritidskläder\n\nAntal anställda: 60\nÅrsomsättning: 5 000 000\nAktiekapital: 150 000\nVerkst dir: Fabr Sture Alberyd\nEtableringsår: 1947.\n\nHOVMANTORPS GLASBRUK\nBengtner &amp;Co AB\n\nPnr 360 51\n\nHovmantorp. Tel 0478-405 40.\nPostgiro 712840. Tga Nyabruket, Växjö\nVerksamhet: Tillverkar\nhushålls-o prydnadsglas i blåst, slipat o\ngraverat utförande\nAntal anställda: 50\nÅrsomsättning: 1 500 000\nAktiekapital: 100 000\nStyrelse: Dir Bengt Bengtner (ordf),\nförsäljn-chef K-O Lindberg\nVerkst dir: Bengt A R Bengtner\nEtableringsår: 1968.\n\nHOVMANTORPS\nSTEN-HUGGERI, AB\n\nPnr 360 51\n\nHovman torp. Tel 0478-400 68,\n400 91. Postgiro 134552\nVerksamhet: Tillverkar gravvårdar\nAktiekapital: 82 500\nFirmatecknare: B Y Johansson,\nM H Johansson\nEtableringsår: 1937.\n\nEKO\n\nChef: Lennart Eklöw\nDirektris: Clary Eklöw\nSömnadschef: Inga Henriksson\nLagerchef: Gösta Berntsson\nEtableringsår: 1956.\n\nIKEA.FORETAGEN\n\nPnr 343 00\n\nÄlmhult. Tel 0476-190 00. Bankgiro\n874-0003. Postgiro 842100-0. Tga\nTkea. Telex 6434 KANO S\nVerksamhet: Försäljning av möbler\no heminredningsartiklar\nAntal anställda: 1100\nÅrsomsättning: 280 000 000\nAktiekapital: 4 000 000\nVerkst dir: Ingvar Kamprad\nEtableringsår: 1953.\n\nSVE\n\nAntal anställda: 29\nÅrsomsättning: 3 000 000\nVerkst dir: Ivan Sjunnebo\nEtableringsàr: 1938.\n\nSVENSKA AGGHANDELS.\nFÖRBUNDET\n\nPnr 12162\n\nJohanneshov, Slakthusg 49. Tel\n08-59 03 40. Bankgiro 333-7094.\nPostgiro 55565-6. Tga Eggunion.\nTelex 1134\n\nVerksamhet: Marknadsför ägg\nAntal anställda: 180\nÅrsomsättning: 142 000 000\nChef: Dir Bertil Flygare\nEtableringsàr: 1932.\n\nSVENSKT ADHESIV\n\nPnr 64100\n\nKatrineholm, Stortorget 1. Tel 0150-\n\n102 03. Bankgiro 82-9366. Postgiro\n72945-9\n\nVerksamhet: Tillverkar\nadhesiv-papper\n\nChef: John Larsson\nEtableringsàr: 1947.\n\nSVENSKT FOTOREPORTAGE\n\nPnr 10126\n\nStockholm 1, Vasag 15-17. Box\n469. Tel 08-10 90 39, 10 70 92.\nPostgiro 56780-0\nVerksamhet: Industri-, reklam- o\nreportagefotografering\nChef: Ragnar Holmqvist\nEtableringsàr 1932.\n\nSWENNERFELT AB, E\n\nPnr 200 71\n\nMalmö 5, Box 5142. Tel 040-63165\nVerksamhet: Import o export av\nsågade lövträvaror i bok, ek, ask,\nlönn, valnöt etc.\nAktiekapital: 20 000\nChef: Ing Arne Månsson\nEtableringsår: 1952.\n\nSVENINGSON &amp; BJURSELL,\nAB\n\nPnr 560 20\n\nNorrahammar, Hammarv 53. Box 8.\nTel 036-610 10. Bankgiro 143-5049.\nPostgiro 295144-0\nVerksamhet: Tillverkar damkappor\no herrockar\nAntal anställda: 30\nÅrsomsättning: 1800 000\nAktiekapital: 20000\nEtableringsår: 1946\nOmbildat till aktiebolag 1960.\n\nSVENNINGSSONS MEK\nVERKSTAD, AB BRÖDERNA\n\nPnr 330 10\n\nBredaryd. Tel 0370-800 54. Postr\ngiro 690860\n\nVerksamhet: Tillverkar sågar för\nlådindustrin, transportörer,\nbalans-kapsågar, spåiv o torkfläktar\nAntal anställda: 10\nÅrsomsättning: 1000 000\nAktiekapital: 100 000\nStyrelse: Dir Gustaf Svenningsson\n(ordf), KAT Svenningsson, HAK\nSvenningsson\n\nVerkst dir: Pabr Gustaf\nSvenningsson.\n\nSVENO, AB\n\nPnr 172 06\n\nSundbyberg 6, Box 613. Ängsstigen\n8. Tel 08-2911 10, 2911 12.\nBankgiro 563-5743. Postgiro 1963-8.\nTelex 17094\n\nVerksamhet: Agentur o försäljning\nav värmeväxlare, kyltorn, pumpar,\nplaströr, kemisk apparatur, värmare,\nventilationsmaterial,\njärnvägsmateriel samt industrigummi\nAntal anställda: 5\nAktiekapital: 15 000\n\nStyrelse: Dir Håkon Meyer (ordf),\ning Hans Thörnroth, fru Christina\nMeyer, fru Birgitta Thörnroth\nVerkst dir: Ing Hans Thörnroth\nEtableringsår: 1952.\n\nSVENSK AFFÄRSINKASSO AB\n\nPnr 602 27\n\nNorrköping, Hospitalsg6 A. Tel\nOHIO 03 40, 18 31 00. Postgiro 31206.\nTga Affärsinkasso\nVerksamhet: Inkasso- o juridisk\nbyrå. Upplysningsverksamhet\nAntal anställda: 40\nÅrsomsättning: 1 500 000\nAktiekapital: 5 000\nVerkst dir: Curt Neldemar\nEtableringsår: 1961.\n\nSVENSK AKUSTIK.\nPLANERING AB\n\nPnr 400 43\n\nGöteborg 30, Dirigentg 2. Box\n30021. Tel 031-49 0410\nVerksamhet: Konsultverksamhet\ninom byggnadsakustik,\nbullerbekämpning, stadsplanering ur\nbullersynpunkt, audiologi, elektroakustik,\nvibrationsisolering. Informations- o\nkursverksamhet. Akustiska\nmätningar\n\nAvdelningskontor: Lund. Tel\n046-146030\n\nAktiekapital: 15 000\nStyrelse: Tekn dr, prof Tor\nKihl-man (ordf), med dr, docent Bertil\nNordlund, civiling Björn Lundquist\nVerkst dir: Civiling Björn\nLundquist\n\nEtableringsår: 1961.\n\nSVENSK BILPROVNING, AB\n\nPnr 162 10\n\nVällingby 1, Krossg 38. Fack. Tel\n08-89 00 80. Bankgiro 70-0531.\nPostgiro 706443-9. Tga Bilprov\nVerksamhet: Tekn fordonskontroll\n(kontroll-, registrerings-,\nkopplings- o konditionsbesiktningar)\nBilprovningsstationer se\ntelefonkatalogens yrkesregister\nAktiekapital: 1000 000\nVerkst dir: Alexej Pellijeff\nEtableringsår: 1963.\n\nARONSSON &amp; SÖNER, AB\n\nPnr 630 03\n\nEskilstuna 3, Box 30 3 3, Gillbergav\n1. Tel 016-1334 85. Bankgiro\n828-0810. Postgiro 36 2864-1\nVerksamhet: Tillverkar solur,\nflaggstångskulor, glöggpannor o\ngravlyktor\nAntal anställda: 8\nÅrsomsättning: 800000\nAktiekapital: 30 000\nStyrelse: Fabr Evald Aronsson\n(ordf), fabr Charles Aronsson\nVerkst dir: Charles Aronsson\nEtableringsår: 1935.\n\nJULINS EFTR, AB CARL\n\nPnr 690 50\n\nVretstorp, Askersundsv 26. Tel\n0582-600 03. Postgiro 37449-6\nVerksamhet: Säljer järn- o\nbyggnadsvaror\nAntal anställda: 5\nÅrsomsättning: 800 000\n\nAktiekapital: 25 000\nVerkst dir. Valter Jansson\nEtableringsår: 1925.\n\nWEJO JOHANSSON &amp; SON, AB\n\nPnr 412 64\n\nGöteborg S, Buråsliden 14. Tel\n\n031-187540. Bankgiro 505-7229.\n\nPostgiro 423935-6\n\nVerksamhet: Artiklar för gatu- o\n\nledningsarbeten\n\nAntal anställda: 5\n\nAktiekapital: 5 000\n\nVerkst dir: Erland Johansson\n\nEtableringsår: 1952\n\nOmbildat till aktiebolag 1960.\n\nVEJT &amp; NORDENHAKE AB\n\nse Kullgrens Handels AB.\n\nWELAND &amp; SÖNER AB\n\nPnr 330 23\n\nSmålandsstenar, Smedjeg. Box\n135. Tel 0371-311 10. Bankgiro\n42-7640. Postgiro\n369780.TgaWeland-durk. Telex 70167 WELAND S\nVerksamhet: Tillverkar gallerdurk,\ntrappsteg, spiraltrappor m m\nVarunamn: Weland\nAntal anstäUda: 67\nAktiekapital: 200 000\nVerkst dir: Weland Andersson\nEtableringsår: 1959.\n\nNÄSSJÖ INREDNINGAR AB\n\nPnr 57100\n\nNässjö, Fredriksdal. Tel\n0380-261 80. Postgiro 141470-5\nVerksamhet: Tillverkar inredningar\nför butiker, apotek, hotell samt\noffentliga miljöer\nAntal anställda: 40\nVerkst dir: Arne Lindomborg\nEtableringsår: 1938.\n\nNÄSSJÖ\nMETALLVERKSTAD, AB\n\nPnr 57100\n\nNässjö, Horeg 5. Tel 0380-140 69\nVerksamhet: Tillverkar\nmetallartiklar, beslag för inredningar\nÄgare o chef: Fabr P E Wenström.\n\nNÄSSJÖ STOLFABRIK, AB\n\nPnr 57100\n\nNässjö, Box 210. Fabriksg. Tel\n0380-180 00. Bankgiro 841-5002.\nPostgiro 11595-6. Tga Nesto\nVerksamhet: Tillverkar möbler\nAntal anställda: 200\nÅrsomsättning: 11000 000\nAktiekapital: 20000\nVeikst dlr: Disp Björn Stålsmeden\nEtableringsår: 1870.\n\nHUST AB, BERTIL\n\nPnr 260 32\n\nRamlösabrunn, Särög 16. Box 60.\nTel 042-965 75. Bankgiro 653-1800.\nPostgiro 70060-9\n\nVerksamhet: Trycksaker. Tillverkar\ntombolalotter samt kvicklotter.\nKuverterar reklam för storförbrukare\nAntal anställda: 30\nAktiekapital: 50 000\nÄgare o chef: Bertil Höst\nEtableringsår 1960.",
    "structured": {
        "1": {
            "company_name": "HOVMAN. KONFEKTIONS AB",
            "activity": "Tillverkar fritidskläder",
            "establishment_year": 1947,
            "employees": 60,
            "annual_turnover": 5000000,
            "capital": 150000,
            "key_personnel": [
                {
                    "name": "Fabr Sture Alberyd",
                    "position": "Verkst dir"
                }
            ]
        },
        "2": {
            "company_name": "HOVMANTORPS GLASBRUK Bengtner &amp;Co AB",
            "activity": "Tillverkar hushålls-o prydnadsglas i blåst, slipat o graverat utförande",
            "establishment_year": 1968,
            "employees": 50,
            "annual_turnover": 1500000,
            "capital": 100000,
            "key_personnel": [
                {
                    "name": "Bengt Bengtner",
                    "position": "Dir (ordf)"
                },
                {
                    "name": "K-O Lindberg",
                    "position": "försäljn-chef"
                },
                {
                    "name": "Bengt A R Bengtner",
                    "position": "Verkst dir"
                }
            ]
        },
        "3": {
            "company_name": "HOVMANTORPS STEN-HUGGERI, AB",
            "activity": "Tillverkar gravvårdar",
            "establishment_year": 1937,
            "capital": 82500,
            "key_personnel": [
                {
                    "name": "B Y Johansson",
                    "position": "Firmatecknare"
                },
                {
                    "name": "M H Johansson",
                    "position": "Firmatecknare"
                }
            ]
        },
        "4": {
            "company_name": "EKO",
            "establishment_year": 1956,
            "key_personnel": [
                {
                    "name": "Lennart Eklöw",
                    "position": "Chef"
                },
                {
                    "name": "Clary Eklöw",
                    "position": "Direktris"
                },
                {
                    "name": "Inga Henriksson",
                    "position": "Sömnadschef"
                },
                {
                    "name": "Gösta Berntsson",
                    "position": "Lagerchef"
                }
            ]
        },
        "5": {
            "company_name": "IKEA.FORETAGEN",
            "activity": "Försäljning av möbler o heminredningsartiklar",
            "establishment_year": 1953,
            "employees": 1100,
            "annual_turnover": 280000000,
            "capital": 4000000,
            "key_personnel": [
                {
                    "name": "Ingvar Kamprad",
                    "position": "Verkst dir"
                }
            ]
        },
        "6": {
            "company_name": "SVE",
            "establishment_year": 1938,
            "employees": 29,
            "annual_turnover": 3000000,
            "key_personnel": [
                {
                    "name": "Ivan Sjunnebo",
                    "position": "Verkst dir"
                }
            ]
        },
        "7": {
            "company_name": "SVENSKA AGGHANDELS. FÖRBUNDET",
            "activity": "Marknadsför ägg",
            "establishment_year": 1932,
            "employees": 180,
            "annual_turnover": 142000000,
            "key_personnel": [
                {
                    "name": "Bertil Flygare",
                    "position": "Chef (Dir)"
                }
            ]
        },
        "8": {
            "company_name": "SVENSKT ADHESIV",
            "activity": "Tillverkar adhesiv-papper",
            "establishment_year": 1947,
            "key_personnel": [
                {
                    "name": "John Larsson",
                    "position": "Chef"
                }
            ]
        },
        "9": {
            "company_name": "SVENSKT FOTOREPORTAGE",
            "activity": "Industri-, reklam- o reportagefotografering",
            "establishment_year": 1932,
            "key_personnel": [
                {
                    "name": "Ragnar Holmqvist",
                    "position": "Chef"
                }
            ]
        },
        "10": {
            "company_name": "SWENNERFELT AB, E",
            "activity": "Import o export av sågade lövträvaror i bok, ek, ask, lönn, valnöt etc.",
            "establishment_year": 1952,
            "key_personnel": [
                {
                    "name": "Ing Arne Månsson",
                    "position": "Chef"
                }
            ]
        },
        "11": {
            "company_name": "SVENINGSON &amp; BJURSELL, AB",
            "activity": "Tillverkar damkappor o herrockar",
            "establishment_year": 1946,
            "employees": 30,
            "annual_turnover": 1800000,
            "capital": 20000
        },
        "12": {
            "company_name": "SVENNINGSSONS MEK VERKSTAD, AB BRÖDERNA",
            "activity": "Tillverkar sågar för lådindustrin, transportörer, balans-kapsågar, spån o torkfläktar",
            "establishment_year": "NA",
            "employees": 10,
            "annual_turnover": 1000000,
            "capital": 100000,
            "key_personnel": [
                {
                    "name": "Gustaf Svenningsson",
                    "position": "Styrelse (ordf)"
                },
                {
                    "name": "KAT Svenningsson",
                    "position": "Styrelse"
                },
                {
                    "name": "HAK Svenningsson",
                    "position": "Styrelse"
                },
                {
                    "name": "Pabr Gustaf Svenningsson",
                    "position": "Verkst dir"
                }
            ]
        },
        "13": {
            "company_name": "SVENO, AB",
            "activity": "Agentur o försäljning av värmeväxlare, kyltorn, pumpar, plaströr, kemisk apparatur, värmare, ventilationsmaterial, järnvägsmateriel samt industrigummi",
            "establishment_year": 1952,
            "employees": 5,
            "capital": 15000,
            "key_personnel": [
                {
                    "name": "Håkon Meyer",
                    "position": "Styrelse (ordf)"
                },
                {
                    "name": "Hans Thörnroth",
                    "position": "Styrelse"
                },
                {
                    "name": "Christina Meyer",
                    "position": "Styrelse"
                },
                {
                    "name": "Birgitta Thörnroth",
                    "position": "Styrelse"
                },
                {
                    "name": "Hans Thörnroth",
                    "position": "Verkst dir"
                }
            ]
        },
        "14": {
            "company_name": "SVENSK AFFÄRSINKASSO AB",
            "activity": "Inkasso- o juridisk byrå. Upplysningsverksamhet",
            "establishment_year": 1961,
            "employees": 40,
            "annual_turnover": 1500000,
            "capital": 5000,
            "key_personnel": [
                {
                    "name": "Curt Neldemar",
                    "position": "Verkst dir"
                }
            ]
        },
        "15": {
            "company_name": "SVENSK AKUSTIK. PLANERING AB",
            "activity": "Konsultverksamhet inom byggnadsakustik, bullerbekämpning, stadsplanering ur bullersynpunkt, audiologi, elektroakustik, vibrationsisolering. Informations- o kursverksamhet. Akustiska mätningar",
            "establishment_year": 1961,
            "capital": 15000,
            "key_personnel": [
                {
                    "name": "Tor Kihl-man",
                    "position": "Styrelse (ordf)"
                },
                {
                    "name": "Bertil Nordlund",
                    "position": "Styrelse"
                },
                {
                    "name": "Björn Lundquist",
                    "position": "Styrelse"
                },
                {
                    "name": "Björn Lundquist",
                    "position": "Verkst dir"
                }
            ]
        },
        "16": {
            "company_name": "SVENSK BILPROVNING, AB",
            "activity": "Tekn fordonskontroll (kontroll-, registrerings-, kopplings- o konditionsbesiktningar)",
            "establishment_year": 1963,
            "capital": 1000000,
            "key_personnel": [
                {
                    "name": "Alexej Pellijeff",
                    "position": "Verkst dir"
                }
            ]
        },
        "17": {
            "company_name": "ARONSSON &amp; SÖNER, AB",
            "activity": "Tillverkar solur, flaggstångskulor, glöggpannor o gravlyktor",
            "establishment_year": 1935,
            "employees": 8,
            "annual_turnover": 800000,
            "capital": 30000,
            "key_personnel": [
                {
                    "name": "Evald Aronsson",
                    "position": "Fabr (ordf)"
                },
                {
                    "name": "Charles Aronsson",
                    "position": "Fabr"
                }
            ]
        },
        "18": {
            "company_name": "JULINS EFTR, AB CARL",
            "activity": "Säljer järn- o byggnadsvaror",
            "establishment_year": 1925,
            "employees": 5,
            "annual_turnover": 800000,
            "capital": 25000,
            "key_personnel": [
                {
                    "name": "Valter Jansson",
                    "position": "Verkst dir"
                }
            ]
        },
        "19": {
            "company_name": "WEJO JOHANSSON &amp; SON, AB",
            "activity": "Artiklar för gatu- o ledningsarbeten",
            "establishment_year": 1952,
            "employees": 5,
            "capital": 5000,
            "key_personnel": [
                {
                    "name": "Erland Johansson",
                    "position": "Verkst dir"
                }
            ]
        },
        "20": {
            "company_name": "VEJT &amp; NORDENHAKE AB",
            "activity": "NA",
            "establishment_year": "NA"
        },
        "21": {
            "company_name": "WELAND &amp; SÖNER AB",
            "activity": "Tillverkar gallerdurk, trappsteg, spiraltrappor m m",
            "establishment_year": 1959,
            "employees": 67,
            "capital": 200000,
            "key_personnel": [
                {
                    "name": "Weland Andersson",
                    "position": "Verkst dir"
                }
            ]
        },
        "22": {
            "company_name": "NÄSSJÖ INREDNINGAR AB",
            "activity": "Tillverkar inredningar för butiker, apotek, hotell samt offentliga miljöer",
            "establishment_year": 1938,
            "employees": 40,
            "key_personnel": [
                {
                    "name": "Arne Lindomborg",
                    "position": "Verkst dir"
                }
            ]
        },
        "23": {
            "company_name": "NÄSSJÖ METALLVERKSTAD, AB",
            "activity": "Tillverkar metallartiklar, beslag för inredningar",
            "establishment_year": "NA",
            "key_personnel": [
                {
                    "name": "P E Wenström",
                    "position": "Ägare o chef"
                }
            ]
        },
        "24": {
            "company_name": "NÄSSJÖ STOLFABRIK, AB",
            "activity": "Tillverkar möbler",
            "establishment_year": 1870,
            "employees": 200,
            "annual_turnover": 11000000,
            "capital": 20000,
            "key_personnel": [
                {
                    "name": "Björn Stålsmeden",
                    "position": "Veikst dlr (Disp)"
                }
            ]
        },
        "25": {
            "company_name": "HUST AB, BERTIL",
            "activity": "Trycksaker. Tillverkar tombolalotter samt kvicklotter. Kuverterar reklam för storförbrukare",
            "establishment_year": 1960,
            "employees": 30,
            "capital": 50000,
            "key_personnel": [
                {
                    "name": "Bertil Höst",
                    "position": "Ägare o chef"
                }
            ]
        }
    }
}