{
    "original": "TOLLOR AB\n\nPnr 402 72\n\nGöteborg 8, Stora Holm. Box 8863.\nTel 031-66 01 86. Bankgiro\n44-1197. Postgiro 46124\nVeiksamhet: Tillverkar portar,\ndörrar, väggar, fönster o fasader\nAntal anställda: 25\nÅrsomsättning: 2500 000\nAktiekapital: 30 000\nVerkst dir Nils Berglund\nEtableringsår: 1960.\n\nARONSSON, S\n\nPnr 301 02\n\nHalmstad 1, Bredg 5. Box 71. Tel\n035-11 81 41. Bankgiro 42-3786.\nPostgiro 324822 Tga Saronsson\nVerksamhet: Köper o säljer\navfallsråvaror\nAntal anställda: 20\nÄgare o chef: Grossh Bernhard\nAronsson\n\nEtableringsår: 1878.\n\nMOTORAMI I GOTEBORG AB\n\nPnr 40110\n\nGöteborg 1, Fack. Malmsjög 4.\nTel 031-25 00 90. Bankgiro 84-7703.\nPostgiro 40044\n\nVeiksamhet: Säljer nya o\nbegagnade bilar samt reservdelar\nAktiekapital: 250 000\nVeikst dir: Bertil Jidal\nEtableringsår: 1949.\n\nMOTORAMI I\nHÄLSINGBORG AB\n\nPnr 25007\n\nHelsingborg 7, Box 7042.\nÄngel-holmsv 10. Tel 042-12 02 50.\nBankgiro 863-4115. Postgiro 86420-7.\nTga Motorami\nVerksamhet: Bilfirma\nAntal anställda: 50\nÅrsomsättning: 10 000 000\nAktiekapital: 300 000\nVerkst din Bo Lundell\nEtableringsår: 1916.\n\nPETTERSSON &amp; CO, WALTER\n\nPnr 11153\n\nStockholm, V Trädgårdsg 11 B. Tel\n08-2143 63, 2139 35. Bankgiro\n33-0096. Postgiro 190081\nVerksamhet: Agentur för\nKarlsborgs o Lövholmens pappersbruks\ntillverkningar av oblekt o blekt\nkraftpapper samt kraftliner\nChef: Walter Pettersson\nEtableringsår: 1953.\n\nPETTERSONS\nBOK-INDUSTRI AB, VICTOR\n\nPnr 11136\n\nStockholm, Holländarg 10. Tel\n08-2288 70. Bankgiro 72-2344.\nPost-giro 939\n\nVerksamhet: Boktryckeri,\nbokbinderi, offsettryckeri o reklam\nAktiekapital: 1000000\nVerkst dir: Per Arne Ström\nEtableringsår: 1874\nOmbildat till aktiebolag 1901.\n\nPETTERSONS BOKINDUSTRI\nFÖRSÄLJNINGS KB, VICTOR\n\nPnr 11136\n\nStockholm, Holländarg 10. Tel\n08-2288 70. Bankgiro 72-2344.\nPostgiro 351433\n\nVerksamhet: Säljer bok- o\noffsettryck, bokband, kataloger,\nreklamtryck o klichéer\nVeikst dir: Per Arne Ström.\n\nPFAFF SYMASKINER AB\n\nPnr 211 25\n\nMalmö, N Vallg 34. Tel 040-713 25.\nBankgiro 87-0491. Postgiro\n531095-8\n\nVerksamhet: Säljer symaskiner i\nparti o detalj\nVarunamn: Pfaff, Kayser\nAntal anställda: 40\nÅrsomsättning: 4 000 000\nAktiekapital: 800000\nVerkst dir: Allan Cato\nEtableringsår: 1957.\n\nAROS NICKEL &amp; KROM, AB\n\nPnr 724 81\n\nVästerås, Brygghusg 2. Tel\n021-18 33 30. Bankgiro 15-0918.\nPostgiro 32710\n\nVerkstad: Björnöv 12\nVerksamhet: Utför förnickling,\nför-kromning o förzinkning\nAntal anställda: 4\nÅrsomsättning: 300 000\nAktiekapital: 5 000\nVerkst dir: Olle Bernerstedt\nEtableringsår: 1965.\n\nAROS PLÄT-&amp;\nMEK VERKSTAD AB\n\nPnr 651 06\n\nKarlstad 1, Box 380. Gjuteiig 11-13.\n380. Tel 054-11 75 27, 18 05 27.\nBankgiro 100-0637. Postgiro\n90691-7\n\nVerksamhet: Kranar, traverser,\nsand- o grussilos\nAntal anställda: 25\nÅrsomsättning: 2 500 000\nAktiekapital: 100 000\nVerkst dir: Ing Gunnar Jernberg\nEtableringsår: 1948.\n\nBRIO SCANDITOY AB\n\nPnr 283 00\n\nOsby, V Järnvägsg. Tel\n0479-119 00. Bankgiro 28-1636.\nPostgiro 6075. Tga Brio. Telex 4684\nVerksamhet: Tillverkar leksaker.\nAgenturer, grossiströrelse\nVerkst dir: Lars Hall.\n\nBRIO-HUS\n\nPnr 414 76\n\nGöteborg, Knipplag 8. Tel 031-\n\n2439 23\n\nVerksamhet; Tillverkar o säljer\nmonteringsfärdiga hus\nAntal anställda: 100\nChef: Dir Curt Lundahl\nEtableringsår: 1959.\n\nBRISSMANS\nBRANDREDSKAP AB\n\nPnr 300 02\n\nHalmstad 2, N vägen 31. Box\n2036. Tel 035-113333, 120633.\nBankgiro 53-0066. Postgiro 71732\nVerksamhet: Tillverkar o säljer\nbrand- o arbetsskyddsmateriel\nVarunamn: Brissman\nAntal anställda: 10\nÅrsomsättning: 2 000 000\nAktiekapital: 50 000\nVerkst dir: Olof Brissman\nEtableringsår: 1928\nOmbildat till aktiebolag 1958.\n\nBRINKENS VERKTYG\n\nPnr 591 00\n\nMotala, Strandv 10. Tel 0141-138 02.\nBankgiro 109-2485. Postgiro\n104147-4\n\nVerksamhet: Tillverkar verktyg.\nUtför experiment- o finmekaniska\narbeten\n\nChef: Karl Fransson\nEtableringsår 1957.\n\nBRINKMANN\nIMPORT-AGENTUR EFTR, ALBERT\n\nPnr 413 19\n\nGöteborg, Änggårdsg 24. Tel\n031-8293 55. Bankgiro 506-1239. Tga\nAlbert Brinkmann\nVerksamhet: Specialitet:\npaketeringsmaskiner o maskiner för\nchoklad- o karamellindustrin m m\nÄgare o chef: Lennart Brinkmann\nEtableringsår: 1908.\n\nBIFROST, REDERI AB\n\nPnr 403 14\n\nGöteborg 2, Packhusplatsen 2.\nBox 2234. Tel 031-13 37 79.\nBankgiro 42-0250. Postgiro 47638.\nTelex 2285. Tga Trappsons\nVerksamhet: Rederirörelse\nAntal anställda: 86\nBruttoinsegling: 8 000 000\nAktiekapital: 2 000 000\nVerkst dir: Jarl Trapp\nEtableringsår: 1932.\n\nLUNDBERG INDUSTRI AB, I\n\nPnr 580 03\n\nLinköping 3, Box 3078. Slöjdg 21.\n\nTel 013-14 62 10. Bankgiro\n120-0583. Postgiro 324893-7\nVeiksamhet: Automatdetaljer\nsamt legoarbeten i svarvar o\nfräsmaskiner. Snabbkopplingar för\ntryckluft\n\nÅrsomsättning: 1500 000\nAktiekapital: 50 000\nVerkst dir. Ingemar Lundberg\nEtableringsår. 1947.\n\nHESSLOW AB, GERMUND\n\nPnr 25104\n\nHelsingborg 1, Box 288. Järnvägsg\n7. Tel 042-1391 50. Bankgiro\n864-1409. Postgiro 22229-9. Tga\nHess-lowab. Telex 72355\nVerksamhet: Importerar o säljer\nklippnät, gallerdurk o putsnät i\nstål. Klippnät även i aluminium,\nrostfritt stål, mässing, koppar o\nplast. Säljer o monterar flyttbara o\nfasta mellanväggar: System Gehab\nFörsäljningskontor: Stockholm,\nSveav 13-15. Tel 08-10 33 16\nVarunamn: Expamet, Gehab\nAntal anställda: 9\nAktiekapital: 150 000\nStyrelse: Dir Lars-Erik Hesslow\n(ordf), adv Rolf Wistrand, Kathryn\nHesslow\n\nVerkst dir: Lars-Erik Hesslow\nEtableringsår: 1964.\n\nUMEÅ TRÅ AB\n\nPnr 902 33\n\nUmeå, Hagaplan 1. Tel\n090-12 22 75. Bankgiro 354-1901.\nPostgiro 577406-2. Tga Umeåwood.\nTelex 54019\n\nVerksamhet: Säljer sågade\nträvaror (även export) samt tillverkar\no säljer listverk i furu/gran,\nlövträ m m (även ytbehandlade)\nAntal anställda: 12\nÅrsomsättning: 15 000 000\nAktiekapital: 15 000\nVerkst dir. Lars Näsman\nEtableringsår: 1961.",
    "structured": {
        "1": {
            "company_name": "TOLLOR AB",
            "pnr": "402 72",
            "address": "Göteborg 8, Stora Holm. Box 8863.",
            "phone_number": "031-66 01 86",
            "bank_details": {
                "bankgiro": "44-1197",
                "postgiro": "46124"
            },
            "activity": "Tillverkar portar, dörrar, väggar, fönster o fasader",
            "employees": 25,
            "annual_turnover": 2500000,
            "capital": 30000,
            "key_personnel": [
                {
                    "name": "Nils Berglund",
                    "position": "Verkst dir"
                }
            ],
            "establishment_year": 1960
        },
        "2": {
            "company_name": "ARONSSON, S",
            "pnr": "301 02",
            "address": "Halmstad 1, Bredg 5. Box 71.",
            "phone_number": "035-11 81 41",
            "bank_details": {
                "bankgiro": "42-3786",
                "postgiro": "324822"
            },
            "activity": "Köper o säljer avfallsråvaror",
            "employees": 20,
            "key_personnel": [
                {
                    "name": "Grossh Bernhard Aronsson",
                    "position": "Ägare o chef"
                }
            ],
            "establishment_year": 1878
        },
        "3": {
            "company_name": "MOTORAMI I GOTEBORG AB",
            "pnr": "40110",
            "address": "Göteborg 1, Fack. Malmsjög 4.",
            "phone_number": "031-25 00 90",
            "bank_details": {
                "bankgiro": "84-7703",
                "postgiro": "40044"
            },
            "activity": "Säljer nya o begagnade bilar samt reservdelar",
            "capital": 250000,
            "key_personnel": [
                {
                    "name": "Bertil Jidal",
                    "position": "Veikst dir"
                }
            ],
            "establishment_year": 1949
        },
        "4": {
            "company_name": "MOTORAMI I HÄLSINGBORG AB",
            "pnr": "25007",
            "address": "Helsingborg 7, Box 7042. Ängel-holmsv 10.",
            "phone_number": "042-12 02 50",
            "bank_details": {
                "bankgiro": "863-4115",
                "postgiro": "86420-7"
            },
            "activity": "Bilfirma",
            "employees": 50,
            "annual_turnover": 10000000,
            "capital": 300000,
            "key_personnel": [
                {
                    "name": "Bo Lundell",
                    "position": "Verkst din"
                }
            ],
            "establishment_year": 1916
        },
        "5": {
            "company_name": "PETTERSSON & CO, WALTER",
            "pnr": "11153",
            "address": "Stockholm, V Trädgårdsg 11 B.",
            "phone_number": "08-2143 63, 2139 35",
            "bank_details": {
                "bankgiro": "33-0096",
                "postgiro": "190081"
            },
            "activity": "Agentur för Karlsborgs o Lövholmens pappersbruks tillverkningar av oblekt o blekt kraftpapper samt kraftliner",
            "key_personnel": [
                {
                    "name": "Walter Pettersson",
                    "position": "Chef"
                }
            ],
            "establishment_year": 1953
        },
        "6": {
            "company_name": "PETTERSSONS BOK-INDUSTRI AB, VICTOR",
            "pnr": "11136",
            "address": "Stockholm, Holländarg 10.",
            "phone_number": "08-2288 70",
            "bank_details": {
                "bankgiro": "72-2344",
                "postgiro": "939"
            },
            "activity": "Boktryckeri, bokbinderi, offsettryckeri o reklam",
            "capital": 1000000,
            "key_personnel": [
                {
                    "name": "Per Arne Ström",
                    "position": "Verkst dir"
                }
            ],
            "establishment_year": 1874
        },
        "7": {
            "company_name": "PETTERSSONS BOKINDUSTRI FÖRSÄLJINGS KB, VICTOR",
            "pnr": "11136",
            "address": "Stockholm, Holländarg 10.",
            "phone_number": "08-2288 70",
            "bank_details": {
                "bankgiro": "72-2344",
                "postgiro": "351433"
            },
            "activity": "Säljer bok- o offsettryck, bokband, kataloger, reklamtryck o klichéer",
            "key_personnel": [
                {
                    "name": "Per Arne Ström",
                    "position": "Veikst dir"
                }
            ]
        },
        "8": {
            "company_name": "PFAFF SYMASKINER AB",
            "pnr": "211 25",
            "address": "Malmö, N Vallg 34.",
            "phone_number": "040-713 25",
            "bank_details": {
                "bankgiro": "87-0491",
                "postgiro": "531095-8"
            },
            "activity": "Säljer symaskiner i parti o detalj",
            "annual_turnover": 4000000,
            "capital": 800000,
            "key_personnel": [
                {
                    "name": "Allan Cato",
                    "position": "Verkst dir"
                }
            ],
            "establishment_year": 1957
        },
        "9": {
            "company_name": "AROS NICKEL & KROM, AB",
            "pnr": "724 81",
            "address": "Västerås, Brygghusg 2.",
            "phone_number": "021-18 33 30",
            "bank_details": {
                "bankgiro": "15-0918",
                "postgiro": "32710"
            },
            "activity": "Utför förnickling, för-kromning o förzinkning",
            "employees": 4,
            "annual_turnover": 300000,
            "capital": 5000,
            "key_personnel": [
                {
                    "name": "Olle Bernerstedt",
                    "position": "Verkst dir"
                }
            ],
            "establishment_year": 1965
        },
        "10": {
            "company_name": "AROS PLÄT-& MEK VERKSTAD AB",
            "pnr": "651 06",
            "address": "Karlstad 1, Box 380. Gjuteiig 11-13. 380.",
            "phone_number": "054-11 75 27, 18 05 27",
            "bank_details": {
                "bankgiro": "100-0637",
                "postgiro": "90691-7"
            },
            "activity": "Kranar, traverser, sand- o grussilos",
            "employees": 25,
            "annual_turnover": 2500000,
            "capital": 100000,
            "key_personnel": [
                {
                    "name": "Ing Gunnar Jernberg",
                    "position": "Verkst dir"
                }
            ],
            "establishment_year": 1948
        },
        "11": {
            "company_name": "BRIO SCANDITOY AB",
            "pnr": "283 00",
            "address": "Osby, V Järnvägsg.",
            "phone_number": "0479-119 00",
            "bank_details": {
                "bankgiro": "28-1636",
                "postgiro": "6075"
            },
            "activity": "Tillverkar leksaker. Agenturer, grossiströrelse",
            "key_personnel": [
                {
                    "name": "Lars Hall",
                    "position": "Verkst dir"
                }
            ]
        },
        "12": {
            "company_name": "BRIO-HUS",
            "pnr": "414 76",
            "address": "Göteborg, Knipplag 8.",
            "phone_number": "031-2439 23",
            "activity": "Tillverkar o säljer monteringsfärdiga hus",
            "employees": 100,
            "key_personnel": [
                {
                    "name": "Dir Curt Lundahl",
                    "position": "Chef"
                }
            ],
            "establishment_year": 1959
        },
        "13": {
            "company_name": "BRISSMANS BRANDREDSKAP AB",
            "pnr": "300 02",
            "address": "Halmstad 2, N vägen 31. Box 2036.",
            "phone_number": "035-113333, 120633",
            "bank_details": {
                "bankgiro": "53-0066",
                "postgiro": "71732"
            },
            "activity": "Tillverkar o säljer brand- o arbetsskyddsmateriel",
            "employees": 10,
            "annual_turnover": 2000000,
            "capital": 50000,
            "key_personnel": [
                {
                    "name": "Olof Brissman",
                    "position": "Verkst dir"
                }
            ],
            "establishment_year": 1928
        },
        "14": {
            "company_name": "BRINKENS VERKTYG",
            "pnr": "591 00",
            "address": "Motala, Strandv 10.",
            "phone_number": "0141-138 02",
            "bank_details": {
                "bankgiro": "109-2485",
                "postgiro": "104147-4"
            },
            "activity": "Tillverkar verktyg. Utför experiment- o finmekaniska arbeten",
            "key_personnel": [
                {
                    "name": "Karl Fransson",
                    "position": "Chef"
                }
            ],
            "establishment_year": 1957
        }
    }
}