{
    "original": "FRA\n\nAktiekapital: 25 000\nVerkst dir; Hans Bergström\nEtableringsår: 1955.\n\nGLIM AB\n\nPnr 60101\n\nNorrköping 1, Trädgårdsg 42. Fack.\nTel 011-18 90 10, 10 00 40.\nBankgiro 824-6191. Postgiro 107600-9.\nTga Glim. Telex 64053\nVerksamhet: Import av trä, fanér,\nhandbilade timmerstugor,\nbyggnadsmateriel o verktyg. Export av\nbyggnadsmateriel o verktyg\nAktiekapital: 40 000\nVerkst dir G Crafoord\nInköp, försäljning: Bo Widholm\nEtableringsår: 1948.\n\nSCHRUDER AB, BERTEL\n\nPnr 104 22\n\nStockholm 22, Kungsholms\nHamnplan 3. Box 22085. Tel 08-54 47 60,\n5447 90\n\nVerksamhet: Säljer\nbyggnadssnickerier\nAktiekapital: 5 000\nVerkst dir: Bengt Schröder\nEtableringsår. 1925.\n\nMAT\n\nVerkst dir: Civiling Boris\nBlomgren\n\nProd-chef: Civiling Nils Wretlind\nEkonomichef: Civilekonom Sven\nLarsson\n\nAdm din Jan-Olov Bergenfeldt\nEtableringsår: 1944.\n\nmatssons handskfabrik\nab, s e\n\nPnr 782 00\n\nMalung, Box 2737. Tel 0280-10130.\nBankgiro 468-4874. Postgiro\n26193-3\n\nVerksamhet: Tillverkar\narbetshandskar o sporthandskar\nAntal anställda: 40\nÅrsomsättning: 1000 000\nAktiekapital: 40 000\nStyrelse: Fabr Sven-Erik Matsson\n(ordf), fru Dagny Matsson,\nkontorist Hans Matsson\nVerkst dir: Fabr Sven-Erik Matsson\nEtableringsår: 1954.\n\nNOR\n\nNORRMAN &amp; NILSSON AB\n\nPnr 10311\n\nStockholm 2, Skeppsbron 18. Box\n2036. Tel 08-23 38 90.\nBankgiro47-8211. Postgiro 51308. Tga Norrco.\nTelex 19173, 10090\nVerksamhet: Auktoriserade\nskeppsklarerare o speditörer\nAntal anställda: 50\nAktiekapital: 75 000\nVerkst dir: Ake Norrman\nEtableringsår: 1919.\n\nNORRMAN &amp; SON,\nBYGGNADS AB E E\n\nPnr 64100\n\nKatrineholm, Djulög 20. Tel\n0150-148 10, 158 10. Bankgiro 82-9350.\nPostgiro 493684\nVerksamhet: Byggnadsrörelse\nAktiekapital: 25 000\nVerkst dir: E E Norrman\nEtableringsår: 1955.\n\nNORRTELJE FÖRENADE\nVERKSTÄDER, AB\n\nPnr 761 00\n\nNorrtälje, Box 14. Baldersg 10. Tel\n0176-100 75. Bankgiro 805-3746.\nPostgiro 96120-1. Tga Verkstäderna\nVerksamhet: Tillverkar\nmaskin-gradsaxar\n\nAntal anställda: 12\nAktiekapital: 100 000\nVerkst dir: Ulf Holmén\nEtableringsår: 1942.\n\nKOANOBOLAGET\n\nPnr 42133\n\nVästra Frölunda, Radiomastg 9.\nTel 031-45 73 58, 2846 27. Bankgiro\n84-8273. Postgiro 243165\nVerksamhet: Tillverkning av\nträdgårdsgödseln KOANO, samt\nblomsterjord i konsumentförpackningar\nVarunamn: Koano, Trisel\nÄgare o chef: Gustav Ahlgren\nEtableringsår: 1957.\n\nBRANDAHL &amp; CO, AB ERIK\n\nPnr 43121\n\nMölndal 1, Box 76. Bergfotsg 9. Tel\n031-27 53 00. Bankgiro 439-8400.\nPostgiro 42206-3. Tga Brandahl\nVerksamhet: Tillverkar damväskor\ni skinn- o vinylmaterial\nVarunamn: Brandahl\nAntal anställda: 120\nÅrsomsättning: 7 000 000\nAktiekapital: 60 000\nVerkst dir: Jarl Schröder\nEtableringsår: 1924.\n\nINDUSTRIUNDERHÄLL, AB\n\nPnr 46101\n\nTrollhättan, Akersjöv 39. Box\n183. Tel 0520-302 80. Bankgiro\n551-9723. Postgiro 297494-7\nVerksamhet: Reparations- o\nanläggningsarbeten. Industribyggnader. Konsulterande uppdrag\nAntal anställda: 78\nÅrsomsättning: 2 500 000\nAktiekapital: 50 000\nVerkst dir: Lars Bertil Holmquist\nEtableringsår: 1965.\n\nGEMAG AB, INGENJÖRSFIRMA\n\nPnr 11135\n\nStockholm, Kungsg 32. Tel\n08-1138 61. 217575. Bankgiro\n195-6069. Postgiro 59466-3. Tga\nGun-mag. Telex 1533 IRON S\nVerksamhet: Försäljning av\nvattenventiler, rotationspumpar,\ntorrbläst-ringsmaskiner, blästermaterial\n(glaskulor)\n\nVarunamn: Ocean-Dieren, Viking,\nZero\n\nAntal anställda: 6\nAktiekapital: 50 000\nVerkst dir: Harry Scheja\nEtableringsår: 1947.\n\nCHEMATEX AB\n\nPnr 200 13\n\nMalmö 27, Box 27049. Koksg 18.\nTel 040-93 55 50. Bankgiro\n640-1954. Postgiro 247103-5. Tga\nChemex. Telex 3191 CHEMEX S\nVerksamhet: Säljer råvaror o\nmaskiner till bl a gummi- o\nkeramikindustrin\n\nAntal anställda: 30\nÅrsomsättning: 35 000 000\nAktiekapital: 500 000\nVerkst dir: Bent Bonrud-Arnesen\nEtableringsår. 1948.",
    "structured": {
        "0": {
            "company_name": "GLIM AB",
            "activity": "Import av trä, fanér, handbilade timmerstugor, byggnadsmateriel o verktyg. Export av byggnadsmateriel o verktyg",
            "establishment_year": 1948,
            "capital": 40000,
            "key_personnel": [
                {
                    "name": "G Crafoord",
                    "position": "Verkst dir"
                },
                {
                    "name": "Bo Widholm",
                    "position": "Inköp, försäljning"
                }
            ]
        },
        "1": {
            "company_name": "SCHRUDER AB, BERTEL",
            "activity": "Säljer byggnadssnickerier",
            "establishment_year": 1925,
            "capital": 5000,
            "key_personnel": [
                {
                    "name": "Bengt Schröder",
                    "position": "Verkst dir"
                }
            ]
        },
        "2": {
            "company_name": "MAT",
            "establishment_year": 1944,
            "key_personnel": [
                {
                    "name": "Civiling Boris Blomgren",
                    "position": "Verkst dir"
                },
                {
                    "name": "Civiling Nils Wretlind",
                    "position": "Prod-chef"
                },
                {
                    "name": "Civilekonom Sven Larsson",
                    "position": "Ekonomichef"
                },
                {
                    "name": "Jan-Olov Bergenfeldt",
                    "position": "Adm din"
                }
            ]
        },
        "3": {
            "company_name": "matssons handskfabrik ab, s e",
            "activity": "Tillverkar arbetshandskar o sporthandskar",
            "employees": 40,
            "annual_turnover": 1000000,
            "capital": 40000,
            "key_personnel": [
                {
                    "name": "Fabr Sven-Erik Matsson",
                    "position": "Styrelse (ordf)"
                },
                {
                    "name": "Dagny Matsson",
                    "position": "Styrelse"
                },
                {
                    "name": "Hans Matsson",
                    "position": "Kontorist"
                },
                {
                    "name": "Fabr Sven-Erik Matsson",
                    "position": "Verkst dir"
                }
            ],
            "establishment_year": 1954
        },
        "4": {
            "company_name": "NORRMAN & NILSSON AB",
            "activity": "Auktoriserade skeppsklarerare o speditörer",
            "employees": 50,
            "capital": 75000,
            "key_personnel": [
                {
                    "name": "Ake Norrman",
                    "position": "Verkst dir"
                }
            ],
            "establishment_year": 1919
        },
        "5": {
            "company_name": "NORRMAN & SON, BYGGNADS AB E E",
            "activity": "Byggnadsrörelse",
            "capital": 25000,
            "key_personnel": [
                {
                    "name": "E E Norrman",
                    "position": "Verkst dir"
                }
            ],
            "establishment_year": 1955
        },
        "6": {
            "company_name": "NORRTELJE FÖRENADE VERKSTÄDER, AB",
            "activity": "Tillverkar maskin-gradsaxar",
            "employees": 12,
            "capital": 100000,
            "key_personnel": [
                {
                    "name": "Ulf Holmén",
                    "position": "Verkst dir"
                }
            ],
            "establishment_year": 1942
        },
        "7": {
            "company_name": "KOANOBOLAGET",
            "activity": "Tillverkning av trädgårdsgödseln KOANO, samt blomsterjord i konsumentförpackningar",
            "employees": null,
            "capital": null,
            "key_personnel": [
                {
                    "name": "Gustav Ahlgren",
                    "position": "Ägare o chef"
                }
            ],
            "establishment_year": 1957
        },
        "8": {
            "company_name": "BRANDAHL & CO, AB ERIK",
            "activity": "Tillverkar damväskor i skinn- o vinylmaterial",
            "employees": 120,
            "annual_turnover": 7000000,
            "capital": 60000,
            "key_personnel": [
                {
                    "name": "Jarl Schröder",
                    "position": "Verkst dir"
                }
            ],
            "establishment_year": 1924
        },
        "9": {
            "company_name": "INDUSTRIUNDERHÄLL, AB",
            "activity": "Reparations- o anläggningsarbeten. Industribyggnader. Konsulterande uppdrag",
            "employees": 78,
            "annual_turnover": 2500000,
            "capital": 50000,
            "key_personnel": [
                {
                    "name": "Lars Bertil Holmquist",
                    "position": "Verkst dir"
                }
            ],
            "establishment_year": 1965
        },
        "10": {
            "company_name": "GEMAG AB, INGENJÖRSFIRMA",
            "activity": "Försäljning av vattenventiler, rotationspumpar, torrbläst-ringsmaskiner, blästermaterial (glaskulor)",
            "employees": 6,
            "capital": 50000,
            "key_personnel": [
                {
                    "name": "Harry Scheja",
                    "position": "Verkst dir"
                }
            ],
            "establishment_year": 1947
        },
        "11": {
            "company_name": "CHEMATEX AB",
            "activity": "Säljer råvaror o maskiner till bl a gummi- o keramikindustrin",
            "employees": 30,
            "annual_turnover": 35000000,
            "capital": 500000,
            "key_personnel": [
                {
                    "name": "Bent Bonrud-Arnesen",
                    "position": "Verkst dir"
                }
            ],
            "establishment_year": 1948
        }
    }
}