{
    "original": "BRE\n\n033-61350, 61351. Bankgiro\n531-6211. Postgiro 84010-8\nVerksamhet: Manufaktur o\nvävnader, postorderförsäljning per\nkatalog\n\nAntal anställda: 12\nVerkst dir: Torsten Bredström\nEtableringsår: 1919.\n\nDST\n\n7515, 981-6059. Postgiro 176162-6\nVerksamhet: Transporter,\nvägbyggen, vatten- o avloppsarbeten\nAntal anställda: 80\nÅrsomsättning: 10 000 000\nAktiekapital: 120 000\nVerkst din Torsten Johansson\nEtableringsàr: 1958.\n\nÖHRN KONSULTERANDE\nINGENJORSBYRÄ AB, ERIK\n\nPrr 117 26\n\nStockholm, Ansgarieg 8. Tel\n08-68 90 07, 68 90 95. Postgiro 350275\nVerksamhet: Konsulterande\ningenjörsbyrå, VVS\nAntal anställda: 4\nÅrsomsättning: 400 000\nAktiekapital: 5 000\nVerkst dir: Ing Erik öhrn\nEtableringsàr: 1947.\n\nOHRNELLS ELEKTRISKA AB\n\nPnr 65109\n\nKarlstad 1, Spärrg 4. Box 556. Tel\n054-15 69 00. Bankgiro 100-6611.\nPostgiro 25718-8. Tga Oehrnells.\nTelex 66047\n\nVerksamhet: Engrosförsäljning av\nelektrisk installationsmateriel\nFörsäljningskonton 400 43\nGöteborg 30. Pennygången 78. Box\n30054. Tel 031-4188 00\nAntal anställda: 24\nÅrsomsättning: 10 000000\nVerkst dir: Ing Rudolf ührnell.\n\nOHRNELL AB,\nINGENJÖRSFIRMAN R\n\nPnr 65109\n\nKarlstad 1, Spärrg 4. Box 556. Tel\n054-18 72 80. Bankgiro 118-1403.\nPostgiro 233868-9. Tga Oehrnells.\nTelex 66047\n\nVerksamhet: Försäljning av telfrar,\ntraverser, transformatorer, ställverk,\nhissar, motorer m m\nAntal anställda: 20\nÅrsomsättning: 5 000 000\nAktiekapital: 100 000\nVerkst dir: Ing Rudolf Ohrnell.\n\nÖRNEN, FABRIKS &amp;\nHANDELS-AB\n\nPnr 70105\n\nÖrebro 1, S Soflag 22. Box 324.\nTel 019-1100 59, 1112 75.\nBankgiro 81-5547. Postgiro 340137.\nTga Örnverktyg\n\nVerksamhet: Tillverkar o säljer\nmaskiner o verktyg\nÅrsomsättning: 1000 000\nÄgare o chef: Fru Henny Peterson\nEtableringsàr: 1949.\n\nORNMARKS MÅLERIFIRMA I\nSTOCKHOLM AB, L\n\nPrr 11450\n\nStockholm, östermalmsg 84. Tel\n08-67 03 40. Bankgiro 154-5565.\nPostgiro 509890-0\nVerksamhet: Målerientreprenader\nAntal anställda: 150\nÅrsomsättning: 11585 000\nAktiekapital: 50 000\nVerkst dir: Lennart Ctnmark\nEtableringsàr: 1948.\n\nORNSKOLDSVIKS MEKANISKA\nVERKSTAD, AB\n\nPnr 89100\n\nÖrnsköldsvik, Angermanlandsg 17.\nTel 0660-177 15. Bankgiro\n771-7754. Postgiro 225702-0\nVerksamhet: Utrustningar för\nkemiska, pappers- o\ncellulosaindustrier såsom reaktionskärl,\ndestil-lationskolonner, försöksapparater\nför forskning, tubvärme växlare,\ntubapparater, suglådor,\nskrubberanlägg-ningar, mixers, klorceller, cisterner.\nAnläggningar i titan o hastelloy till\nklor- o kloratfabriker samt blekerier\nAntal anställda: 97\nÅrsomsättning: 9000 000\nAktiekapital: 141000\nStyrelse: Dir Hugo Ekberg (ordf),\nfru Greta Ekberg, ing Hans Ekberg,\ning Börje Ekberg\nVerkst dir: Hugo Ekberg\nEtableringsàr: 1959\nOmbildat till aktiebolag 1961.\n\nORNSKOLDSVIKS\nSKOGSÄGARE FURENING EK FOR\n\nPnr 89101\n\nÖrnsköldsvik 1, Box 79. Ctnsköldsg\n6. Tel 0660-103 35. Bankgiro\n626-9021. Postgiro 63202-6. Tga\növiksskog\n\nVerksamhet: Säljer rundvirke såsom\nsågtimmer, stolpar o massaved samt\nbyggnadsmaterial. Tillverkar\nsågade trävaror o villor (egnahem)\nAntal anställda: 218\nÅrsomsättning: 39 800 000\nInsatskapital: 4 300 000\nChef: Disp Owe Larsson\nEtableringsàr: 1936.\n\nORNSKOLDSVIKS\nSNICKERIFABRIK AB\n\nPnr 89100\n\nÖrnsköldsvik, Viktoriaesplanaden\n21. Tel 0660-123 71. 115 34.\nBankgiro 188-6530. Postgiro 31516-8\nVerksamhet: Tillverkar\ninrednings-samt specialsnickerier\nAntal anställda: 8\nÅrsomsättning: 500 000\nÄgare o chef: Gustav Nylander\nEtableringsàr: 1913.\n\nORNÄS PRODUKTER AB\n\nPnr 190 50\n\nKungsängen. Tel 0758-52100.\n\nPostgiro 293853\nVerksamhet: Tillverkar frukta o\ngrönsakskonserver, sylter, safter o\nsyltade frukter\n\nFabriker: Kungsängen. Se ovan\nBro. Tel 0758-401 35\nFörsäljningskonton Göteborg. Tel\n031-16 50 00\nAktiekapital: 75 000\nVerkst dir: Richard Bodén\nEtableringsån 1935.\n\nGADD, BYGGNADS AB GÖSTA\n\nPnr 252 43\n\nHelsingborg, Hofverbergsg 2. Tel\n042-1207 80. Bankgiro 874-8964.\nPostgiro 475800-9\nVerksamhet: Byggnadsentreprenör\nAntal anställda: 100\nÅrsomsättning: 10 000 000\nAktiekapital: 25 000\nVerkst dir: Ing Hans Rösing\nArbetschefer: Erik Elhag, Sven R\nJohansson\nEtableringsår. 1953.\n\nGADELIUS &amp; CO\nAKTIEBOLAG\n\nPnr 114 30\n\nStockholm, Eriksbergsg 1 A. Tel\n08-23 28 00. Bankgiro 566-6276,\n16-0244. Postgiro 3648-3. Tga\nKnut-sius. Telex 17650\nVerksamhet: Ensamrepresentation\n(export) av ett flertal svenska\nindustriprodukter i Japan, Taiwan o\nSydkorea, samt import från Japan\nav optiska varor, elektroniska\nkomponenter o audio utrustning,\nmetaller m m\nAntal anstäUda: 41\nÅrsomsättning: 81000 000,\n230 000 000 Koncernen\nAktiekapital: 7 840 000\nStyrelse: Dir Taro Gadelius (ordf),\ndir Rune Lundqvist, dir Gustaf\nGadelius, dir Rune Hellman (suppl),\ndir Bror-Karl Gadelius\n\nVerkst dir: Rune Lundqvist\nExportchef o v vetkst dir: Dlr\n\nRune Hellman\nEtableringsår: 1890\nOmbildat till aktiebolag 1933.\nDotterbolag: Gadelius K. K., P.O.\nBox 1284, Tokyo C, Japan.\nGadelius K. K., P. O. Box 802, Kobe,\nJapan. Blomqvist» Verkstads AB,\nBox 2036, Södertälje. AB Nord\nAerob, Box 358, Lidingö 3.\n\nGAF SVENSKA AB\n\nPnr 104 6 2\n\nStockholm 17, Box 17100.\nKrukmakarg 24. Tel 08-6804 75.\nBankgiro 624-8868. Postgiro 53518-7.\nTga Gafswed. Telex 10636\nVerksamhet: Dotterbolag till\nGaf Corporation, New York.\nFörsäljning av GAF’s fotoprodukter,\nljuskopieringsmaskiner o -material\nsamt kemikalier\n\nFörsäljningskontor. 42121 Västra\nFrölunda, Box 56. Topasg 84 (repro)\n20041 Malmö, Box 8013. Uppsalag\n16 (kemi)\n\nAktiekapital: 300000\nVerkst din Ake Karlstrand\nEtableringsår: 1967.\n\nHANSA MYNTAUTOMATER\n\nPnr 414 81\n\nGöteborg, Dollarg 10. Tel\n031-414200. Bankgiro 26-8153.\nPostgiro 41895. Tga Hansaautomai\nVerksamhet: Grossiströrelse inom\nspel-, musik- o varuautomater\nsamt myntväxlingsapparater\nChef: Aatto Rantanen\nEtableringsår: 1957.\n\nADS-ANKER DATA\n5Y5TEM- AB\n\nPnr 10129\n\nStockholm 1, Box 649. Barnhusg 3.\nTel 08-24 74 30. Bankgiro 560-0242.\nPostgiro 150200-4. Tga Ankerdata\nVerksamhet: Säljer kassaregister,\ndatasystem o bokföringsmaskiner\nAntal anställda: 70\nAktiekapital: 480 000\nVerks t dir: Wolf Strössenreuter\nEtableringsår: 1955.\n\nADSELL MEK VERKSTAD AB,\n\nk g\n\nPnr 616 00\n\nÅby, Stockholmsv 33. Tel\n011-634 60. Bankgiro 826-1026.\nPostgiro 647166-8\n\nVerksamhet: Verkstadsrörelse.\nSpecialitet: Hydraulik o pneumatik,\nspecialmaskiner\nAntal anställda: 20\nÅrsomsättning: 1500 000\nAktiekapital: 20000\nVerkst dir: Klas Adsell\nEtableringsår: 1964.\n\nEFFEKTMASKINER AB\n\nPnr 190 70\n\nFjärdhundra, Stora v 29. Tel\n0171-91340, 913 41. Bankgiro 80-4308.\nPostgiro 679570\n\nVerksamhet: Säljer harvar, slungor,\nvinschar för lantbruk\nAntal anställda: 7\nÅrsomsättning: 1200 000\nAktiekapital: 26 000\nVerkst dir: Harry Holmström\nEtableringsår: 1965.\n\nEFFEKTO AB, KEMISKA\nFABRIKEN\n\nPnr 104 60\n\nStockholm 20, Rågg 7. Box 20080.\nTel 08-43 8945. Bankgiro 731-0667.\nPostgiro 152231-7. Tga Effekto\nVerksamhet: Tillverkar o\nlevererar lödvatten\nAntal anställda: 4\nÅrsomsättning: 500 000\nAktiekapital: 10 000\nVerkst dir: Kaj Engelberth\nEtableringsår: 1930.\n\nDAL\n\nVerksamhet: Husbyggnad o\nstadsplanering\n\nAvdelningskontor: 211 37 Malmö,\nSora Nyg 31. Tel 040-346 10\n.Antal anställda: 10\nÅrsomsättning: 800 000\nÄgare o chefer: Erik Dahl, Arne\nStrömdahl\n\nEtableringsår: 1952.\n\nARNIV MASKINER\n\nPnr 530 42\n\nVinninga. Tel 0510-50357.\nPostgiro 127431\n\nVerksamhet: Säljer\nlantbruksmaskiner, vapen o ammunition,\nmotorer, verktyg, kameror, radio, TV o\n\ntillbehör\n\nChef: Arne Ivarsson.\n\nARNMARKERS\nBOKFORINGS-BYRÅ AB\n\nPnr 440 20\n\nVårgårda, Parkg 10. Box 7. Tel\n0322-207 45. Bankgiro 89-4966.\nPostgiro 515285-5\nVerksamhet: Bokförings- o\nrevisionsbyrå\n\nAntal anställda: 10\nÅrsomsättning: 400 000\nAktiekapital: 5 000\nChef: Rev Gunnar Arnmarker\nEtableringsår: 1960.\n\nÅLSTA SÅGVERKS AB\n\nPnr 830 22\n\nFåker, Box 14. Tel 063-600 14.\nBankgiro 77-7911. Postgiro 83114.\nTga Sågverket\n\nVerksamhet: Tillverkar o säljer\nsågade o hyvlade trävaror\nAntal anställda: 35\nÅrsomsättning: 2 500000\nAktiekapital: 70 000\nFöretagsledare: Disp Algot\nAndersson, disp Einar Andersson\nKamrer: Gunnar Pettersson\nEtableringsår: 1929.\n\nSUNDSTRÖM AB, J\n\nPnr 400 64\n\nGoteborg 49, Box 49044. Tel\n031-25 6 8 4 3. Bankgiro 848-2630.\nPostgiro 47567-3. Tga Expanderpins\nVerksamhet: Expanderbussningar,\nfjädrande rörpinnar\nAktiekapital: 20 000\nEtableringsår: 1945.",
    "structured": {
        "1": {
            "company_name": "BRE",
            "activity": "Manufaktur o vävnader, postorderförsäljning per katalog",
            "employees": 12,
            "key_personnel": [
                {
                    "name": "Torsten Bredström",
                    "position": "Verkst dir"
                }
            ],
            "establishment_year": 1919
        },
        "2": {
            "company_name": "DST",
            "activity": "Transporter, vägbyggen, vatten- o avloppsarbeten",
            "employees": 80,
            "annual_turnover": 10000000,
            "capital": 120000,
            "key_personnel": [
                {
                    "name": "Torsten Johansson",
                    "position": "Verkst dir"
                }
            ],
            "establishment_year": 1958
        },
        "3": {
            "company_name": "ÖHRN KONSULTERANDE INGENJORSBYRÄ AB, ERIK",
            "address": "Ansgarieg 8, Stockholm",
            "phone_number": "08-68 90 07, 08-68 90 95",
            "activity": "Konsulterande ingenjörsbyrå, VVS",
            "employees": 4,
            "annual_turnover": 400000,
            "capital": 5000,
            "key_personnel": [
                {
                    "name": "Ing Erik öhrn",
                    "position": "Verkst dir"
                }
            ],
            "establishment_year": 1947
        },
        "4": {
            "company_name": "OHRNELLS ELEKTRISKA AB",
            "address": "Spärrg 4, Karlstad",
            "phone_number": "054-15 69 00",
            "bank_details": {
                "bankgiro": "100-6611",
                "postgiro": "25718-8"
            },
            "activity": "Engrosförsäljning av elektrisk installationsmateriel",
            "employees": 24,
            "annual_turnover": 10000000,
            "key_personnel": [
                {
                    "name": "Ing Rudolf ührnell",
                    "position": "Verkst dir"
                }
            ]
        },
        "5": {
            "company_name": "OHRNELL AB, INGENJÖRSFIRMAN R",
            "address": "Spärrg 4, Karlstad",
            "phone_number": "054-18 72 80",
            "bank_details": {
                "bankgiro": "118-1403",
                "postgiro": "233868-9"
            },
            "activity": "Försäljning av telfrar, traverser, transformatorer",
            "employees": 20,
            "annual_turnover": 5000000,
            "capital": 100000,
            "key_personnel": [
                {
                    "name": "Ing Rudolf Ohrnell",
                    "position": "Verkst dir"
                }
            ],
            "establishment_year": 1913
        },
        "6": {
            "company_name": "ÖRNEN, FABRIKS & HANDELS-AB",
            "address": "S Soflag 22, Örebro",
            "phone_number": "019-1100 59, 019-1112 75",
            "bank_details": {
                "bankgiro": "81-5547",
                "postgiro": "340137"
            },
            "activity": "Tillverkar o säljer maskiner o verktyg",
            "annual_turnover": 1000000,
            "key_personnel": [
                {
                    "name": "Fru Henny Peterson",
                    "position": "Ägare o chef"
                }
            ],
            "establishment_year": 1949
        },
        "7": {
            "company_name": "ORNMARKS MÅLERIFIRMA I STOCKHOLM AB, L",
            "address": "östermalmsg 84, Stockholm",
            "phone_number": "08-67 03 40",
            "bank_details": {
                "bankgiro": "154-5565",
                "postgiro": "509890-0"
            },
            "activity": "Målerientreprenader",
            "employees": 150,
            "annual_turnover": 11585000,
            "capital": 50000,
            "key_personnel": [
                {
                    "name": "Lennart Ctnmark",
                    "position": "Verkst dir"
                }
            ],
            "establishment_year": 1948
        },
        "8": {
            "company_name": "ORNSKOLDSVIKS MEKANISKA VERKSTAD, AB",
            "address": "Angermanlandsg 17, Örnsköldsvik",
            "phone_number": "0660-177 15",
            "bank_details": {
                "bankgiro": "771-7754",
                "postgiro": "225702-0"
            },
            "activity": "Utrustningar för kemiska, pappers- o cellulosaindustrier",
            "employees": 97,
            "annual_turnover": 9000000,
            "capital": 141000,
            "key_personnel": [
                {
                    "name": "Dir Hugo Ekberg",
                    "position": "Styrelse (ordf)"
                },
                {
                    "name": "Fru Greta Ekberg",
                    "position": "Styrelse"
                },
                {
                    "name": "Ing Hans Ekberg",
                    "position": "Styrelse"
                },
                {
                    "name": "Ing Börje Ekberg",
                    "position": "Styrelse"
                },
                {
                    "name": "Hugo Ekberg",
                    "position": "Verkst dir"
                }
            ],
            "establishment_year": 1959
        },
        "9": {
            "company_name": "ORNSKOLDSVIKS SKOGSÄGARE FURENING EK FOR",
            "address": "Box 79, Örnsköldsvik",
            "phone_number": "0660-103 35",
            "bank_details": {
                "bankgiro": "626-9021",
                "postgiro": "63202-6"
            },
            "activity": "Säljer rundvirke och byggnadsmaterial, Tillverkar sågade trävaror",
            "employees": 218,
            "annual_turnover": 39800000,
            "capital": 4300000,
            "key_personnel": [
                {
                    "name": "Disp Owe Larsson",
                    "position": "Chef"
                }
            ],
            "establishment_year": 1936
        },
        "10": {
            "company_name": "ORNSKOLDSVIKS SNICKERIFABRIK AB",
            "address": "Viktoriaesplanaden 21, Örnsköldsvik",
            "phone_number": "0660-123 71, 115 34",
            "bank_details": {
                "bankgiro": "188-6530",
                "postgiro": "31516-8"
            },
            "activity": "Tillverkar inrednings- samt specialsnickerier",
            "employees": 8,
            "annual_turnover": 500000,
            "key_personnel": [
                {
                    "name": "Gustav Nylander",
                    "position": "Ägare o chef"
                }
            ],
            "establishment_year": 1913
        },
        "11": {
            "company_name": "ORNÄS PRODUKTER AB",
            "address": "Kungsängen",
            "phone_number": "0758-52100",
            "postgiro": "293853",
            "activity": "Tillverkar frukta o grönsakskonserver, sylter, safter o syltade frukter",
            "key_personnel": [
                {
                    "name": "Richard Bodén",
                    "position": "Verkst dir"
                }
            ],
            "establishment_year": 1935
        },
        "12": {
            "company_name": "GADD, BYGGNADS AB GÖSTA",
            "address": "Helsingborg, Hofverbergsg 2",
            "phone_number": "042-1207 80",
            "bank_details": {
                "bankgiro": "874-8964",
                "postgiro": "475800-9"
            },
            "activity": "Byggnadsentreprenör",
            "employees": 100,
            "annual_turnover": 10000000,
            "capital": 25000,
            "key_personnel": [
                {
                    "name": "Ing Hans Rösing",
                    "position": "Verkst dir"
                },
                {
                    "name": "Erik Elhag",
                    "position": "Arbetschef"
                },
                {
                    "name": "Sven R Johansson",
                    "position": "Arbetschef"
                }
            ],
            "establishment_year": 1953
        },
        "13": {
            "company_name": "GADELIUS & CO AKTIEBOLAG",
            "address": "Eriksbergsg 1 A, Stockholm",
            "phone_number": "08-23 28 00",
            "bank_details": {
                "bankgiro": "566-6276, 16-0244",
                "postgiro": "3648-3"
            },
            "activity": "Ensamrepresentation (export) av ett flertal svenska industriprodukter i Japan, Taiwan o Sydkorea, samt import från Japan av optiska varor, elektroniska komponenter o audio utrustning, metaller m m",
            "employees": 41,
            "annual_turnover": 81000000,
            "capital": 7840000,
            "key_personnel": [
                {
                    "name": "Taro Gadelius",
                    "position": "Styrelse (ordf)"
                },
                {
                    "name": "Rune Lundqvist",
                    "position": "Verkst dir"
                }
            ],
            "establishment_year": 1890
        },
        "14": {
            "company_name": "GAF SVENSKA AB",
            "address": "Box 17100, Stockholm",
            "phone_number": "08-6804 75",
            "bank_details": {
                "bankgiro": "624-8868",
                "postgiro": "53518-7"
            },
            "activity": "Dotterbolag till Gaf Corporation, New York. Försäljning av GAF’s fotoprodukter, ljuskopieringsmaskiner o -material samt kemikalier",
            "capital": 300000,
            "key_personnel": [
                {
                    "name": "Ake Karlstrand",
                    "position": "Verkst dir"
                }
            ],
            "establishment_year": 1967
        },
        "15": {
            "company_name": "HANSA MYNTAUTOMATER",
            "address": "Dollarg 10, Göteborg",
            "phone_number": "031-414200",
            "bank_details": {
                "bankgiro": "26-8153",
                "postgiro": "41895"
            },
            "activity": "Grossiströrelse inom spel-, musik- o varuautomater samt myntväxlingsapparater",
            "key_personnel": [
                {
                    "name": "Aatto Rantanen",
                    "position": "Chef"
                }
            ],
            "establishment_year": 1957
        },
        "16": {
            "company_name": "ADS-ANKER DATA 5Y5TEM- AB",
            "address": "Box 649, Stockholm",
            "phone_number": "08-24 74 30",
            "bank_details": {
                "bankgiro": "560-0242",
                "postgiro": "150200-4"
            },
            "activity": "Säljer kassaregister, datasystem o bokföringsmaskiner",
            "employees": 70,
            "capital": 480000,
            "key_personnel": [
                {
                    "name": "Wolf Strössenreuter",
                    "position": "Verkst dir"
                }
            ],
            "establishment_year": 1955
        },
        "17": {
            "company_name": "ADSELL MEK VERKSTAD AB, k g",
            "address": "Stockholmsv 33, Åby",
            "phone_number": "011-634 60",
            "bank_details": {
                "bankgiro": "826-1026",
                "postgiro": "647166-8"
            },
            "activity": "Verkstadsrörelse. Specialitet: Hydraulik o pneumatik, specialmaskiner",
            "employees": 20,
            "annual_turnover": 1500000,
            "capital": 20000,
            "key_personnel": [
                {
                    "name": "Klas Adsell",
                    "position": "Verkst dir"
                }
            ],
            "establishment_year": 1964
        },
        "18": {
            "company_name": "EFFEKTMASKINER AB",
            "address": "Stora v 29, Fjärdhundra",
            "phone_number": "0171-91340, 013 41",
            "bank_details": {
                "bankgiro": "80-4308",
                "postgiro": "679570"
            },
            "activity": "Säljer harvar, slungor, vinschar för lantbruk",
            "employees": 7,
            "annual_turnover": 1200000,
            "capital": 26000,
            "key_personnel": [
                {
                    "name": "Harry Holmström",
                    "position": "Verkst dir"
                }
            ],
            "establishment_year": 1965
        },
        "19": {
            "company_name": "EFFEKTO AB, KEMISKA FABRIKEN",
            "address": "Rågg 7, Stockholm",
            "phone_number": "08-43 8945",
            "bank_details": {
                "bankgiro": "731-0667",
                "postgiro": "152231-7"
            },
            "activity": "Tillverkar o levererar lödvatten",
            "employees": 4,
            "annual_turnover": 500000,
            "capital": 10000,
            "key_personnel": [
                {
                    "name": "Kaj Engelberth",
                    "position": "Verkst dir"
                }
            ],
            "establishment_year": 1930
        },
        "20": {
            "company_name": "DAL",
            "activity": "Husbyggnad o stadsplanering",
            "address": "Sora Nyg 31, Malmö",
            "phone_number": "040-346 10",
            "employees": 10,
            "annual_turnover": 800000,
            "key_personnel": [
                {
                    "name": "Erik Dahl",
                    "position": "Ägare o chef"
                },
                {
                    "name": "Arne Strömdahl",
                    "position": "Ägare o chef"
                }
            ],
            "establishment_year": 1952
        },
        "21": {
            "company_name": "ARNIV MASKINER",
            "address": "Vinninga",
            "phone_number": "0510-50357",
            "postgiro": "127431",
            "activity": "Säljer lantbruksmaskiner, vapen o ammunition, motorer, verktyg, kameror, radio, TV o tillbehör",
            "key_personnel": [
                {
                    "name": "Arne Ivarsson",
                    "position": "Chef"
                }
            ]
        },
        "22": {
            "company_name": "ARNMARKERS BOKFORINGS-BYRÅ AB",
            "address": "Parkg 10, Vårgårda",
            "phone_number": "0322-207 45",
            "bank_details": {
                "bankgiro": "89-4966",
                "postgiro": "515285-5"
            },
            "activity": "Bokförings- o revisionsbyrå",
            "employees": 10,
            "annual_turnover": 400000,
            "capital": 5000,
            "key_personnel": [
                {
                    "name": "Rev Gunnar Arnmarker",
                    "position": "Chef"
                }
            ],
            "establishment_year": 1960
        },
        "23": {
            "company_name": "ÅLSTA SÅGVERKS AB",
            "address": "Box 14, Fåker",
            "phone_number": "063-600 14",
            "bank_details": {
                "bankgiro": "77-7911",
                "postgiro": "83114"
            },
            "activity": "Tillverkar o säljer sågade o hyvlade trävaror",
            "employees": 35,
            "annual_turnover": 2500000,
            "capital": 70000,
            "key_personnel": [
                {
                    "name": "Disp Algot Andersson",
                    "position": "Företagsledare"
                },
                {
                    "name": "Disp Einar Andersson",
                    "position": "Företagsledare"
                },
                {
                    "name": "Gunnar Pettersson",
                    "position": "Kamrer"
                }
            ],
            "establishment_year": 1929
        },
        "24": {
            "company_name": "SUNDSTRÖM AB, J",
            "address": "Box 49044, Goteborg",
            "phone_number": "031-25 6 8 4 3",
            "bank_details": {
                "bankgiro": "848-2630",
                "postgiro": "47567-3"
            },
            "activity": "Expanderbussningar, fjädrande rörpinnar",
            "capital": 20000,
            "establishment_year": 1945
        }
    }
}