{
    "original": "BOR DÖRREN AB\n\nPnr 330 15\nBor. Tel 0370-503 50\nVerksamhet: Specialitet:\nytterdörrar i teak, ek o fur\nVarunamn: Bor-Dörren\nAntal anställda: 45\nÅrsomsättning: 6 000 000\nAktiekapital: 300 000\nVeikst dir. Fabr Valter Svensson\nEtableringsår 1920.\n\nFOLKE &amp; CO AB, CARL\n\nPnr 103 85\n\nStockholm 7, Nybrog 3. Box 7303.\nTel 08-23 64 30. Bankgiro 16-0452.\nPostgiro 155056-5. Tga Kolfolke.\nTelex 1481\n\nVerksamhet: Importerar stenkol,\nkoks\n\nAntal anställda: 9\nÅrsomsättning: 70 000 000\nAktiekapital: 600 000\nStyrelse: Fru Birgit Folke (ordf),\ndir Bengt Folke, jur dr Bertil af\nKlercker\n\nVerkst dir: Bengt Folke\nEtableringsår: 1922.\n\nHÄRJE MEKANISKA, AB\n\nPnr 829 00\n\nSveg, Box 95. Industrig. Tel\n0680-10813. 108 24. Bankgiro 618-8049.\nPostgiro 697520-5\nVerksamhet: Grovplåtslageri- o\nsvetsningsarbeten, fräsning,\nsvarvning o planslipning.\nBalkkonstruktioner. Legoarbeten\nAntal anställda: 47\nÅrsomsättning: 3 000 000\nAktiekapital: 50 000\nVerkst dir. Sven Hjort\nKamrer. Asbjörn Marken\nEtableringsår 1967.\n\nGRUNFELD AB, ALEXANDER\n\nPnr 11146\n\nStockholm, Biblioteksg 11. Tel\n08-10 17 34,10 1 777. Bankgiro\n44-7034. Postgiro 158890. Telex 1849.\nTga Agid\n\nVerksamhet: Agenturföretag för all\nslags livsmedel\nAntal anstäUda: 5\n\nAktiekapital: 75 000\nVerkst dir: Alexander Grünfeld\nEtableringsår: 1942.\n\nPALMGREN AB, HÅKAN\n\nPnr 402 31\n\nGöteborg 7, Linnég 5. Box 7057.\nTel 031-24 68 00, 24 92 00.\nBankgiro 848-0030. Postgiro 40767-6.\nTga Agentpalm\n\nVerksamhet: Allt inom\nträvaru-branschen\nAntal anstäUda: 5\nAktiekapital: 45 000\nVerkst dir: Håkan Palmgren\nEtableringsår: 1918.\n\nMORA-KRANAR, AB\n\nPnr 792 00\n\nMora. Tel 0250-101 21. Bankgiro\n469-1648. Postgiro 295850-2\nVerksamhet Tillverkar\nsanitets-armatur. Utför varmpressning samt\nbearbetar detaljer i mässing o\nkoppar\n\nAntal anstäUda: 30\n\nÅrsomsättning: 3 000 000\nAktiekapital: 60 000\nVerkst dir: Gunnar Eriksson\nEtableringsår: 1945\nOmbildat till aktiebolag 1946.\n\nMORELL, ERIK\n\nPnr 792 00\n\nMora, Ostnor. Tel 0250-102 21\nVerksamhet: Tillverkar skepps- o\nvällingklockor, metallgjutgods\nefter ritningar o prov\nChef: Erik Morell\nEtableringsår 1936.\n\nJACOBOWSKYS HANDELS AB\n\nPnr 45101\n\nUddevalla 1. Osterg. Fack. Tel\n0522-14270. Bankgiro 42-8019.\nPostgiro 6157. Tga Jaco\nVerksamhet: Säljer textil- o\nkortvaror en gros\nAktiekapital: 500 000\nVeikst dir: Bengt Malmborg\nEtableringsår: 1874.\n\nWISEMAN &amp; CO AB. M\n\nPnr 402 41\n\nGöteborg 12, Chapmans torg 3. Box\n12013. Tel 031-24 75 72, 24 64 22.\nBankgiro 500-6887. Postgiro\n522020-7\n\nVerksamhet: Säljer glasögonoptik\nengros\n\nAktiekapital: 5 000\nVerkst dir: H Sender\nEtableringsår: 1956.\n\nFORSS-PARATOR AB\n\nPnr 595 00\n\nMjölby, Box 94. Kungsv 35. Tel\n0142-13100. Bankgiro 280-8160.\nPostgiro 143055-2. Tga\nFcrsstrai-ler. Telex 5568 FORSPAR S\n\nVerksamhet: Tillverkning av\nsläp-fcrdon o bilbyggnationer\nVarunamn: Forss-Parator\nAntal anstäUda: 500\nÅrsomsättning: 45 000 000\nAktiekapital: 12 000 000\nVeikst dir: Alvar Modin\nEtableringsår: 1938.\n\nIMO-INDUSTRI, AB\n\nPnr 12612 Sthlm 42\nHägersten, Västberga Allé50. Box\n42090, Sthlm 42. Tel 08-19 01 60.\nBankgiro 166-5470. Postgiro\n53845-4. Tga Imoindustri.\nTelex 19947\n\nVerksamhet: Tillverkar IMO\nskruv-pumpar o hydrauliska motorer,\nhydrauliska ventiler o vattenmätare\nVarunamn: IMO\nAntal anställda: 230\nÅrsomsättning: 21000 000\nAktiekapital: 4 000 000\nStyrelse: Dlr Fr Jacobsson\n(ordf), dir Sten Söderström, dir\nTorsten Montelius, dir Svante\nThunander\n\nVerkst dir: Torsten Montelius\nEtableringsår: 1931.",
    "structured": {
        "1": {
            "company_name": "BOR DÖRREN AB",
            "pnr": "330 15",
            "phone_number": "0370-503 50",
            "activity": "Specialitet: ytterdörrar i teak, ek o fur",
            "employees": 45,
            "annual_turnover": 6000000,
            "capital": 300000,
            "key_personnel": [
                {
                    "name": "Valter Svensson",
                    "position": "Veikst dir. Fabr"
                }
            ],
            "establishment_year": 1920
        },
        "2": {
            "company_name": "FOLKE & CO AB, CARL",
            "pnr": "103 85",
            "address": "Stockholm 7, Nybrog 3, Box 7303",
            "phone_number": "08-23 64 30",
            "bank_details": {
                "bankgiro": "16-0452",
                "postgiro": "155056-5"
            },
            "activity": "Importerar stenkol, koks",
            "employees": 9,
            "annual_turnover": 70000000,
            "capital": 600000,
            "key_personnel": [
                {
                    "name": "Birgit Folke",
                    "position": "Styrelse: Fru"
                },
                {
                    "name": "Bengt Folke",
                    "position": "Veikst dir"
                },
                {
                    "name": "Bertil af Klercker",
                    "position": "jur dr"
                }
            ],
            "establishment_year": 1922
        },
        "3": {
            "company_name": "HÄRJE MEKANISKA, AB",
            "pnr": "829 00",
            "address": "Sveg, Box 95, Industrig",
            "phone_number": "0680-10813",
            "bank_details": {
                "bankgiro": "618-8049",
                "postgiro": "697520-5"
            },
            "activity": "Grovplåtslageri- o svetsningsarbeten, fräsning, svarvning",
            "employees": 47,
            "annual_turnover": 3000000,
            "capital": 50000,
            "key_personnel": [
                {
                    "name": "Sven Hjort",
                    "position": "Verkst dir"
                },
                {
                    "name": "Asbjörn Marken",
                    "position": "Kamrer"
                }
            ],
            "establishment_year": 1967
        },
        "4": {
            "company_name": "GRUNFELD AB, ALEXANDER",
            "pnr": "11146",
            "address": "Stockholm, Biblioteksg 11",
            "phone_number": "08-10 17 34,10 1 777",
            "bank_details": {
                "bankgiro": "44-7034",
                "postgiro": "158890"
            },
            "activity": "Agenturföretag för all slags livsmedel",
            "employees": 5,
            "capital": 75000,
            "key_personnel": [
                {
                    "name": "Alexander Grünfeld",
                    "position": "Verkst dir"
                }
            ],
            "establishment_year": 1942
        },
        "5": {
            "company_name": "PALMGREN AB, HÅKAN",
            "pnr": "402 31",
            "address": "Göteborg 7, Linnég 5, Box 7057",
            "phone_number": "031-24 68 00, 24 92 00",
            "bank_details": {
                "bankgiro": "848-0030",
                "postgiro": "40767-6"
            },
            "activity": "Allt inom trävaru-branschen",
            "employees": 5,
            "capital": 45000,
            "key_personnel": [
                {
                    "name": "Håkan Palmgren",
                    "position": "Verkst dir"
                }
            ],
            "establishment_year": 1918
        },
        "6": {
            "company_name": "MORA-KRANAR, AB",
            "pnr": "792 00",
            "address": "Mora",
            "phone_number": "0250-101 21",
            "bank_details": {
                "bankgiro": "469-1648",
                "postgiro": "295850-2"
            },
            "activity": "Tillverkar sanitets-armatur. Utför varmpressning samt bearbetar detaljer i mässing o koppar",
            "employees": 30,
            "annual_turnover": 3000000,
            "capital": 60000,
            "key_personnel": [
                {
                    "name": "Gunnar Eriksson",
                    "position": "Verkst dir"
                }
            ],
            "establishment_year": 1945
        },
        "7": {
            "company_name": "MORELL, ERIK",
            "pnr": "792 00",
            "address": "Mora, Ostnor",
            "phone_number": "0250-102 21",
            "activity": "Tillverkar skepps- o vällingklockor, metallgjutgods efter ritningar o prov",
            "key_personnel": [
                {
                    "name": "Erik Morell",
                    "position": "Chef"
                }
            ],
            "establishment_year": 1936
        },
        "8": {
            "company_name": "JACOBOWSKYS HANDELS AB",
            "pnr": "45101",
            "address": "Uddevalla 1, Osterg. Fack",
            "phone_number": "0522-14270",
            "bank_details": {
                "bankgiro": "42-8019",
                "postgiro": "6157"
            },
            "activity": "Säljer textil- o kortvaror en gros",
            "capital": 500000,
            "key_personnel": [
                {
                    "name": "Bengt Malmborg",
                    "position": "Veikst dir"
                }
            ],
            "establishment_year": 1874
        },
        "9": {
            "company_name": "WISEMAN & CO AB, M",
            "pnr": "402 41",
            "address": "Göteborg 12, Chapmans torg 3, Box 12013",
            "phone_number": "031-24 75 72, 24 64 22",
            "bank_details": {
                "bankgiro": "500-6887",
                "postgiro": "522020-7"
            },
            "activity": "Säljer glasögonoptik engros",
            "capital": 5000,
            "key_personnel": [
                {
                    "name": "H Sender",
                    "position": "Verkst dir"
                }
            ],
            "establishment_year": 1956
        },
        "10": {
            "company_name": "FORSS-PARATOR AB",
            "pnr": "595 00",
            "address": "Mjölby, Box 94, Kungsv 35",
            "phone_number": "0142-13100",
            "bank_details": {
                "bankgiro": "280-8160",
                "postgiro": "143055-2"
            },
            "activity": "Tillverkning av släp-fcrdon o bilbyggnationer",
            "employees": 500,
            "annual_turnover": 45000000,
            "capital": 12000000,
            "key_personnel": [
                {
                    "name": "Alvar Modin",
                    "position": "Veikst dir"
                }
            ],
            "establishment_year": 1938
        },
        "11": {
            "company_name": "IMO-INDUSTRI, AB",
            "pnr": "12612 Sthlm 42",
            "address": "Hägersten, Västberga Allé50, Box 42090, Sthlm 42",
            "phone_number": "08-19 01 60",
            "bank_details": {
                "bankgiro": "166-5470",
                "postgiro": "53845-4"
            },
            "activity": "Tillverkar IMO skruv-pumpar o hydrauliska motorer, hydrauliska ventiler o vattenmätare",
            "employees": 230,
            "annual_turnover": 21000000,
            "capital": 4000000,
            "key_personnel": [
                {
                    "name": "Fr Jacobsson",
                    "position": "Styrelse: Dlr"
                },
                {
                    "name": "Sten Söderström",
                    "position": "dir"
                },
                {
                    "name": "Torsten Montelius",
                    "position": "Veikst dir"
                },
                {
                    "name": "Svante Thunander",
                    "position": "dir"
                }
            ],
            "establishment_year": 1931
        }
    }
}