{
    "original": "ELEKTROSANDBERG AB\n\nPnr 21124\n\nMalmö, Borrg 31. Tel 040-1809 40.\nBankgiro 875-5936. Postgiro\n531307-7\n\nVerksamhet: Elektr installatörer\nav hög-, låg- o\nsvagströmsanlägg-ningar\n\nFilialer: 25246 Helsingborg. Tel\n042-14 27 90, 14 69 50\n222 26 Lund. Tel 046-1173 80\n35231 Växjö. Tel 0470-175 10\nAntal anställda: 250\nÅrsomsättning: 18 000 000\nAktiekapital: 200 000\nVerkst din Gunnar Sandberg\nEtableringsår: 1959.\n\nHEDSTRÖM AB, G\n\nPnr 653 41\n\nKarlstad, Blockg 7. Tel\n054-1169 53, 11 69 57. Bankgiro\n438-8906. Postgiro 324788-9\nVerksamhet: Byggnadssmide,\nsvetsning samt gängning\nAntal anställda: 10\nChef: Fabr Gunnar Hedström\nEtableringsår: 1945.\n\nHEDSTRÖM, VÄRME.AB\nGUSTAV\n\nPnr 93101\n\nSkellefteå 1, S Järnvägsg 87. Box\n74. Tel 0910-144 90. Bankgiro\n764-0527. Postgiro 60406-6. Tga\nSkellefterör\n\nVerksamhet: VVS-installationer\nFilialer: Arvidsjaur, Skomakarg 22.\nTel 0960-10147\n\nJokkmokk, Wästfeltsg 43. Tel\n0971-10249\n\nUmeå. Tel 090-13 07 50\nMalå. Tel 0953-101 17\nAntal anställda: 65\nÅrsomsättning: 8 000 000\nAktiekapital: 240 000\nStyrelse: Ing Erik Hedman,\nkamrer Georg Hedman\nEtableringsår 1931.\n\nHEDSTRÖMS TRÄVARU AB,\nP A\n\nPnr 11146\n\nStockholm, Norrmalmstorg 1. Tel\n08-23 14 05. Bankgiro 700-0698.\nPostgiro 55110-1. Tga Hetab.\nTelex 10549 HETAB S\nVerksamhet: Säljer trävaror en gros\nAntal anstäUda: 3\nÅrsomsättning: 6 000 000\nAktiekapital: 75 000\nVerkst dir: Vidar Hedström\nEtableringsår: 1910.\n\nOLSSON TRADING, OLOF G\nOLSSON AB &amp; CO KB, O\n\nPnr 422 02\n\nHisings Backa 2, Balladg 5. Box\n2034. Tel 031-51 31 20. Tga\n01&amp;-trade\n\nVerksamhet: Generalagent för\nWhirlpool kemtvättautomater m m samt\nför Foss Electric analysinstrument\nför jordbruksprodukter\nAntal anställda: 8\nÅrsomsättning: 2 000 000\nAktiekapital: 25000\nÄgare o chef: Dir Olof Olsson\nEtableringsår 1967.\n\nOLSSON AB,\nINGENJÖRS-FIRMA OLOF\n\nPnr 161 30\n\nBromma, Ekbacksv 40. Tel\n08-8027 90. Bankgiro 332-0553.\nPostgiro 558772-0\n\nVerksamhet: Konstruktion o\ntillverkning av tryckerimaskiner\nAntal anställda: 15\nÅrsomsättning: 1000 000\nAktiekapital: 75 000\nVerkst dir Ing Olof Olsson\nEtableringsår: 1958.\n\nOLSSON FÖRSÄLJNINGS AB,\nOLOF V\n\nPnr 411 26\n\nGöteborg, Vasaplatsen 1. Tel\n031-11 12 70. Bankgiro 81-1839.\nPostgiro 48314. Tga Ovo\nVeiksamhet: Säljer OVO original\nfräsverktyg av hårdmetall o\nsnabbstål för träindustrin\nChef: O V Olsson.\n\nOLSSONS BYGGNADS.\nMATERIAL AB, OTTO\n\nPnr 240 36\n\nStehag, Box 102. Stationsv. Tel\n0413-403 40. Bankgiro 335-1780.\nPostgiro 43 8 373-3\nVerksamhet: Sågverk, hyvleri.\nSäljer byggmaterial\nAntal anställda: 25\nÅrsomsättning: 2700000\n\nAktiekapital: 15 000\nVerkst dir: Otto Olsson\nEtableringsår: 1932.\n\nWALLGREN, AB HARALD\n\nPnr 403 13\n\nGöteborg 2, Arsenalsg 4. Box\n2124. Tel 031-17 49 80- Bankgiro\n511-6413. Postgiro 40529-0. Tga\nWållgren\n\nVerksamhet: Grosshandel med\nradio o TV samt elektr materiel\nAktiekapital: 300 000\nVerkst din P A Wållgren\nEtableringsår: 1909.\n\nWAHLSTRUM &amp; CO\nYTBEHANDLING AB\n\nPnr 113 23\n\nStockholm, Hälsingeg 7. Tel\n08-32 9147. Bankgiro 476-1466.\nPostgiro 257243-6\n\nVerksamhet: Eloxering o färgning\nAktiekapital: 10 000\nÄgare o chef: Ing Birger Wåhlström\nEtableringsån 1947.\n\nVARGARDA ARMATUR.\nFABRIK. AB\n\nPnr 440 20\n\nVårgårda, Industrig. Box 69. Tel\n0322-21210. Bankgiro 89-4909.\nPostgiro 83760. Tga Armaturfabriken\nVerksamhet: Tillverkar armatur för\nvatten, ånga, gas o luft.\nSpecialitet: sanitetsarmatur för kök.\nbadrum, sjukhus, skolor mm. Utför\nsandgjutning, varmpressning,\npressgjutning o kokillgjutning,\nau-tomatsvarvning, förnickling o\nför-kromning\nVarunamn: VA\nAntal anställda: 275\nÅrsomsättning: 28 000 000\nAktiekapital: 450 000\nStyrelse: Disp Franz Hartmann\n(ordf), adv Johan Ramberg, dir\nNils Bake, disp Bo Risberg, dir\nSigurd Ljungcrantz\nVeikst din Sigurd Ljungcrantz\nPlatschef: Disp Gunnar\nWilhelmson\n\nFörsäljn-chef: Bror Norrman\nRitkontorschef: Gösta Jönsson\nEtableringsår: 1920\nOmbildat till aktiebolag 1924.\n\nVARGARDA BAND, AB\n\nPnr 440 20\n\nVårgårda, Wallentinsv. Box 35. Tel\n0322-203 42, 208 43. Bankgiro\n894-9307. Postgiro 320852-7\nVerksamhet: Tillverkar vävda band\no flätade linor i bomull, silke,\npolyester m fi material\nAntal anställda: 30\nÅrsomsättning: 1200 000\nAktiekapital: 60 000\nVerkst din Evald Klingström\nEtableringsår: 1946.\n\nESSGE-KONFEKTION, AB\n\nPnr 400 60\n\nGöteborg 6, N Kustbaneg 13. Box\n6094. Tel 031-19 2 0 60. Bankgiro\n44-4118. Postgiro 43164. Tga\nGa-reldress\n\nVerksamhet: Tillverkar herrkläder\nAntal anställda: 275\nÅrsomsättning: 12 000000\nAktiekapital: 500 000\nVerkst dir: Benno Garellick\nEtableringsår: 1936.\n\nAHLSELL &amp; ÅGREN AB\n\nPnr 104 60\n\nStockholm 20, Fack. Hammarbyv 37.\nTel 08-221500. Tga Ahlsells.\nTelex 1837 ALSEL S\nVerksamhet: Rör, värme- o\nsani-tetsmaterial, stål o metaller,\nindustriråvaror o kemikalier\nAvdelningskontor:\n402 5 0 Göteborg 13, Fack.\nMarie-holmsg 64. Tel 031-8013 80. Tga\nAhlsells. Telex 2280 ALSEL S.\n(Rör, värme- o sanitetsmaterial,\nstål o metaller, industriråvaror,\nkemikalier)\n\n20013 Malmö 27, Box 27007.\nBlidö-g 27, Industrih. Tel 040-18 00 00.\nTga Ahlsells. Telex 3370 ALSEL S\n(Rör, värme- o sanitetsmaterial,\nstål o metaller, industriråvaror)\n252 29 Helsingborg, Planteringsv 6.\nTel 042-12 09 30. Tga Ahlsells.\n(Rör, värme- o sanitetsmaterial)\n601 01 Norrköping 1, Fack.\nGästgivarehagen. Tel 011-10 62 40. Tga\nAhlsells. (Rör, värm©- o\nsanitetsmaterial)\n\n70104 Örebro 1, Aspholmsv 2-4.\nBox 295. Tel 019-11 95 40. Tga\nAhlsells. (Rör, värme- o\nsanitetsmaterial)\n\n650 02 Karlstad 2, Box 2037.\nBlock-g 29. Tel 054-15 02 80. Tga\nAhlsells. (Rör, värme- o\nsanitetsmaterial)\n\n38101 Kalmar 1. Box 198.\nFöle-hagsv 2. Tel 0480-224 20. Tga\nAhlsells. (Rör, värme- o\nsanitetsmaterial)\n\n803 59 Gävle, Strömsbrov 19. Tel\n026-18 82 00. Tga Ahlsells. (Rör,\nvärme- o sanitetsmaterial)\n87101 Härnösand 1, Kronholmen.\nBox 163. Tel 0611-15620. Tga\nAhlsells. (Rör, värme- o\nsanitetsmaterial)\n\n90110 Umeå, Box 800. Strömv 8.\nTel 090-13 22 50. Tga Ahlsells.\n(Rör, värme- o sanitetsmaterial)\nAntal anställda: 2100 (koncernen)\nÅrsomsättning: 1 000 000 000\n(koncernen)\n\nAktiekapital: 58 000000\nStyrelse: Bankdir Göte Engfors\n(ordf), adv S:son Ankarcrona,\nbankdir N E Granberg, doc Gunnar\nHammer, disp Gunnar Nobel, dir Sven\nSjölander, dir Stig Sunne, dir Sven\nÖstling\n\nVerkst dir: Sven Östling\nEtableringsår: 1877\nModerbolag för AR-Ventilation AB,\nAB Edvard Erikson Värmematerial,\nGöteborg, Axel H Ågrens Spedition\nAB, AB Frödéns Verkstäder,\nJönköping.\n\nAHLSSONS JÄRNHANDEL,\nAB\n\nPnr 58104\n\nLinköping 1, Box 430. Sankt Larsg\n32. Tel 013-12 97 20. Bankgiro\n276-5022. Postgiro 11427-6\nVerksamhet: Säljer järn,\nbyggnads-smide o husgerådsartiklar\nAntal anställda: 22\nÅrsomsättning: 3 700000\nAktiekapital: 100 000\nVerkst dir: Arnold Larsson\nEtableringsår: 1923.\n\nALSTERBRO\nBOBIN-FABRIK, AB\n\nPnr 382 00\n\nNybro. Tel 0481-11110.\nBankgiro 65-6102. Postgiro 169624. Tga\nAlbowood, Kalmar\nVerksamhet: Tillverkar all slags\nsvarvgods i trä, såsom\nleksaksdetaljer, bobiner, skaft, handtag,\nhopprepskaft, hemslöjdsartiklar,\nljusstakar, spelpjäser, trådrullar,\nrullcentra, knappar etc, trävita o\nlackerade\n\nAntal anställda: 20\nÅrsomsättning: 1000 000\nAktiekapital: 40 000\nVerkst dir: Ing Ulf Sampson\nEtableringsår: 1898.\n\nszabös revisionsbyrå ab\n\nPnr 774 01\n\nAvesta 1, Corneliusg 12. Box 109.\nTel 0226-509 74, 535 77. Postgiro\n586613-2\n\nSandviken, Svarvarg 7. Box 49.\nTel 026-25 13 80\n\nVerksamhet: Bokföring, förvaltning,\nrevision o organisation\nAktiekapital: 5 000\nEtableringsår: 1961.\n\nGOLV &amp; TRÅ AB\n\nPnr 23101\n\nTrelleborg 1, Box 89. Osterbrog 4.\nTel 0410-165 65. Bankgiro\n665-9460. Postgiro 537200-8\nVerksamhet: Tillverkar\ngolvbe-läggningsmaterial\nAntal anställda: 35\nÅrsomsättning: 4 500 000\nAktiekapital: 20000\nVerkst dir: Gösta Lövgren\nEtableringsår: 1960.\n\nVINYLPRODUKTER, AB\n\nPnr 261 22\n\nLandskrona 1, Fjärde Tvärg. Box\n67. Tel 0418-110 14, 143 14.\nBankgiro 868-6164. Postgiro 258900-0.\nTga Vinylprodukter\nVerksamhet: Tillverkar PVC-pastor,\nplastlacker, plastbelagda\ntrådartiklar o skyltställ. Plasthandskar\nAntal anstäUda: 20\nÅrsomsättning: 2 500 000\nAktiekapital: 200 000\nVerkst dir: Gustaf Jacobson\nPlatschef: Ing Lennart Nilsson\nEtableringsår: 1946.\n\nCOMFORT CON T ROL AB\n\nPnr 125 05\n\nÄlvsjö 5, Stamg 1-5. Fack. Tel\n08-8102 75. Bankgiro 114-4682.\nPostgiro 402290-1. Tga Comfortcontrol.\nTelex 17517\n\nVerksamhet: Oljeeldningstillbehör\no industriförnödenheter\nAktiekapital: 90 000\nVerkst dir Håkan Wellgren\nEtableringsår: 1945.",
    "structured": {
        "1": {
            "company_name": "ELEKTROSANDBERG AB",
            "pnr": "21124",
            "address": "Malmö, Borrg 31",
            "phone_number": "040-1809 40",
            "bank_details": {
                "bankgiro": "875-5936",
                "postgiro": "531307-7"
            },
            "activity": "Elektr installatörer av hög-, låg- o svagströmsanläggningar",
            "employees": 250,
            "annual_turnover": 18000000,
            "capital": 200000,
            "key_personnel": [
                {
                    "name": "Gunnar Sandberg",
                    "position": "Verkst din"
                }
            ],
            "establishment_year": 1959
        },
        "2": {
            "company_name": "HEDSTRÖM AB, G",
            "pnr": "653 41",
            "address": "Karlstad, Blockg 7",
            "phone_number": "054-1169 53, 11 69 57",
            "bank_details": {
                "bankgiro": "438-8906",
                "postgiro": "324788-9"
            },
            "activity": "Byggnadssmide, svetsning samt gängning",
            "employees": 10,
            "key_personnel": {
                "name": "Fabr Gunnar Hedström",
                "position": "Chef"
            },
            "establishment_year": 1945
        },
        "3": {
            "company_name": "HEDSTRÖM, VÄRME.AB GUSTAV",
            "pnr": "93101",
            "address": "Skellefteå 1, S Järnvägsg 87, Box 74",
            "phone_number": "0910-144 90",
            "bank_details": {
                "bankgiro": "764-0527",
                "postgiro": "60406-6"
            },
            "activity": "VVS-installationer",
            "employees": 65,
            "annual_turnover": 8000000,
            "capital": 240000,
            "establishment_year": 1931
        },
        "4": {
            "company_name": "HEDSTRÖMS TRÄVARU AB, P A",
            "pnr": "11146",
            "address": "Stockholm, Norrmalmstorg 1",
            "phone_number": "08-23 14 05",
            "bank_details": {
                "bankgiro": "700-0698",
                "postgiro": "55110-1"
            },
            "activity": "Säljer trävaror en gros",
            "employees": 3,
            "annual_turnover": 6000000,
            "capital": 75000,
            "key_personnel": {
                "name": "Vidar Hedström",
                "position": "Verkst dir"
            },
            "establishment_year": 1910
        },
        "5": {
            "company_name": "OLSSON TRADING, OLOF G OLSSON AB & CO KB, O",
            "pnr": "422 02",
            "address": "Hisings Backa 2, Balladg 5, Box 2034",
            "phone_number": "031-51 31 20",
            "activity": "Generalagent för Whirlpool kemtvättautomater m m samt för Foss Electric analysinstrument för jordbruksprodukter",
            "employees": 8,
            "annual_turnover": 2000000,
            "capital": 25000,
            "key_personnel": {
                "name": "Olof Olsson",
                "position": "Ägare o chef"
            },
            "establishment_year": 1967
        },
        "6": {
            "company_name": "OLSSON AB, INGENJÖRS-FIRMA OLOF",
            "pnr": "161 30",
            "address": "Bromma, Ekbacksv 40",
            "phone_number": "08-8027 90",
            "bank_details": {
                "bankgiro": "332-0553",
                "postgiro": "558772-0"
            },
            "activity": "Konstruktion o tillverkning av tryckerimaskiner",
            "employees": 15,
            "annual_turnover": 1000000,
            "capital": 75000,
            "key_personnel": [
                {
                    "name": "Ing Olof Olsson",
                    "position": "Verkst dir"
                }
            ],
            "establishment_year": 1958
        },
        "7": {
            "company_name": "OLSSON FÖRSÄLJNINGS AB, OLOF V",
            "pnr": "411 26",
            "address": "Göteborg, Vasaplatsen 1",
            "phone_number": "031-11 12 70",
            "bank_details": {
                "bankgiro": "81-1839",
                "postgiro": "48314"
            },
            "activity": "Säljer OVO original fräsverktyg av hårdmetall o snabbstål för träindustrin",
            "key_personnel": {
                "name": "O V Olsson",
                "position": "Chef"
            }
        },
        "8": {
            "company_name": "OLSSONS BYGGNADSMATERIAL AB, OTTO",
            "pnr": "240 36",
            "address": "Stehag, Box 102, Stationsv",
            "phone_number": "0413-403 40",
            "bank_details": {
                "bankgiro": "335-1780",
                "postgiro": "43 8 373-3"
            },
            "activity": "Sågverk, hyvleri. Säljer byggmaterial",
            "employees": 25,
            "annual_turnover": 2700000,
            "capital": 15000,
            "key_personnel": {
                "name": "Otto Olsson",
                "position": "Verkst dir"
            },
            "establishment_year": 1932
        },
        "9": {
            "company_name": "WALLGREN, AB HARALD",
            "pnr": "403 13",
            "address": "Göteborg 2, Arsenalsg 4, Box 2124",
            "phone_number": "031-17 49 80",
            "bank_details": {
                "bankgiro": "511-6413",
                "postgiro": "40529-0"
            },
            "activity": "Grosshandel med radio o TV samt elektr materiel",
            "capital": 300000,
            "key_personnel": {
                "name": "P A Wållgren",
                "position": "Verkst din"
            },
            "establishment_year": 1909
        },
        "10": {
            "company_name": "WAHLSTRUM & CO YTBEHANDLING AB",
            "pnr": "113 23",
            "address": "Stockholm, Hälsingeg 7",
            "phone_number": "08-32 9147",
            "bank_details": {
                "bankgiro": "476-1466",
                "postgiro": "257243-6"
            },
            "activity": "Eloxering o färgning",
            "capital": 10000,
            "key_personnel": {
                "name": "Ing Birger Wåhlström",
                "position": "Ägare o chef"
            },
            "establishment_year": 1947
        },
        "11": {
            "company_name": "VARGARDA ARMATUR FABRIK AB",
            "pnr": "440 20",
            "address": "Vårgårda, Industrig. Box 69",
            "phone_number": "0322-21210",
            "bank_details": {
                "bankgiro": "89-4909",
                "postgiro": "83760"
            },
            "activity": "Tillverkar armatur för vatten, ånga, gas o luft. Specialitet: sanitetsarmatur för kök. badrum, sjukhus, skolor mm. Utför sandgjutning, varmpressning, pressgjutning o kokillgjutning, au-tomatsvarvning, förnickling o för-kromning",
            "employees": 275,
            "annual_turnover": 28000000,
            "capital": 450000,
            "key_personnel": [
                {
                    "name": "Sigurd Ljungcrantz",
                    "position": "Veikst din"
                },
                {
                    "name": "Gunnar Wilhelmson",
                    "position": "Platschef"
                },
                {
                    "name": "Bror Norrman",
                    "position": "Försälj-chef"
                },
                {
                    "name": "Gösta Jönsson",
                    "position": "Ritkontorschef"
                }
            ],
            "establishment_year": 1920
        },
        "12": {
            "company_name": "VARGARDA BAND AB",
            "pnr": "440 20",
            "address": "Vårgårda, Wallentinsv. Box 35",
            "phone_number": "0322-203 42, 208 43",
            "bank_details": {
                "bankgiro": "894-9307",
                "postgiro": "320852-7"
            },
            "activity": "Tillverkar vävda band o flätade linor i bomull, silke, polyester m fi material",
            "employees": 30,
            "annual_turnover": 1200000,
            "capital": 60000,
            "key_personnel": {
                "name": "Evald Klingström",
                "position": "Verkst din"
            },
            "establishment_year": 1946
        },
        "13": {
            "company_name": "ESSGE-KONFEKTION AB",
            "pnr": "400 60",
            "address": "Göteborg 6, N Kustbaneg 13. Box 6094",
            "phone_number": "031-19 2 0 60",
            "activity": "Tillverkar herrkläder",
            "employees": 275,
            "annual_turnover": 12000000,
            "capital": 500000,
            "key_personnel": {
                "name": "Benno Garellick",
                "position": "Verkst dir"
            },
            "establishment_year": 1936
        },
        "14": {
            "company_name": "AHLSELL & ÅGREN AB",
            "pnr": "104 60",
            "address": "Stockholm 20, Fack. Hammarbyv 37",
            "phone_number": "08-221500",
            "activity": "Rör, värme- o sani-tetsmaterial, stål o metaller, industriråvaror o kemikalier",
            "employees": 2100,
            "annual_turnover": 1000000000,
            "capital": 580000000,
            "key_personnel": [
                {
                    "name": "Sven Östling",
                    "position": "Verkst dir"
                }
            ],
            "establishment_year": 1877
        },
        "15": {
            "company_name": "AHLSSONS JÄRNHANDEL AB",
            "pnr": "58104",
            "address": "Linköping 1, Box 430. Sankt Larsg 32",
            "phone_number": "013-12 97 20",
            "bank_details": {
                "bankgiro": "276-5022",
                "postgiro": "11427-6"
            },
            "activity": "Säljer järn, byggnads-smide o husgerådsartiklar",
            "employees": 22,
            "annual_turnover": 3700000,
            "capital": 100000,
            "key_personnel": {
                "name": "Arnold Larsson",
                "position": "Verkst dir"
            },
            "establishment_year": 1923
        },
        "16": {
            "company_name": "ALSTERBRO BOBIN-FABRIK AB",
            "pnr": "382 00",
            "address": "Nybro",
            "phone_number": "0481-11110",
            "bank_details": {
                "bankgiro": "65-6102",
                "postgiro": "169624"
            },
            "activity": "Tillverkar all slags svarvgods i trä",
            "employees": 20,
            "annual_turnover": 1000000,
            "capital": 40000,
            "key_personnel": {
                "name": "Ing Ulf Sampson",
                "position": "Verkst dir"
            },
            "establishment_year": 1898
        },
        "17": {
            "company_name": "szabös revisionsbyrå ab",
            "pnr": "774 01",
            "address": "Avesta 1, Corneliusg 12. Box 109",
            "phone_number": "0226-509 74, 535 77",
            "postgiro": "586613-2",
            "activity": "Bokföring, förvaltning, revision o organisation",
            "capital": 5000,
            "establishment_year": 1961
        },
        "18": {
            "company_name": "GOLV & TRÅ AB",
            "pnr": "23101",
            "address": "Trelleborg 1, Box 89. Osterbrog 4",
            "phone_number": "0410-165 65",
            "bank_details": {
                "bankgiro": "665-9460",
                "postgiro": "537200-8"
            },
            "activity": "Tillverkar golvbe-läggningsmaterial",
            "employees": 35,
            "annual_turnover": 4500000,
            "capital": 20000,
            "key_personnel": {
                "name": "Gösta Lövgren",
                "position": "Verkst dir"
            },
            "establishment_year": 1960
        },
        "19": {
            "company_name": "VINYLPRODUKTER AB",
            "pnr": "261 22",
            "address": "Landskrona 1, Fjärde Tvärg. Box 67",
            "phone_number": "0418-110 14, 143 14",
            "bank_details": {
                "bankgiro": "868-6164",
                "postgiro": "258900-0"
            },
            "activity": "Tillverkar PVC-pastor, plastlacker, plastbelagda trådartiklar o skyltställ. Plasthandskar",
            "employees": 20,
            "annual_turnover": 2500000,
            "capital": 200000,
            "key_personnel": [
                {
                    "name": "Gustaf Jacobson",
                    "position": "Verkst dir"
                },
                {
                    "name": "Ing Lennart Nilsson",
                    "position": "Platschef"
                }
            ],
            "establishment_year": 1946
        },
        "20": {
            "company_name": "COMFORT CONTROL AB",
            "pnr": "125 05",
            "address": "Älvsjö 5, Stamg 1-5. Fack",
            "phone_number": "08-8102 75",
            "bank_details": {
                "bankgiro": "114-4682",
                "postgiro": "402290-1"
            },
            "activity": "Oljeeldningstillbehör o industriförnödenheter",
            "capital": 90000,
            "key_personnel": {
                "name": "Håkan Wellgren",
                "position": "Verkst dir"
            },
            "establishment_year": 1945
        }
    }
}