{
    "original": "DUX MÖBEL AB\n\nPnr 23100\n\nTrelleborg, Strandridareg 10. Tel\n04 1 0-165 00. Tga Duxmoebel.\nTelex 32970\n\nVerksamhet: Tillverkar o säljer\nstopp- o trämöbler\nVarunamn: Dux\n\nFabrik: 570 20 Bodafors. Tel\n0380-304 00. Tga Möbelfabrikerna.\nTelex 3723\nAntal anställda: 445\nÅrsomsättning: 48 000 000\nAktiekapital: 1000 000\nVerkst dir: Disp Gösta Welwert\nEtableringsår: 1926\nDotterbolag till Bra Bohag AB.\n\nDUX SÄNGAR AB\n\nPnr 280 10\n\nSösdala, Box 142. Industrig. Tel\n0451-605 10. Tga Duxbed\nVerksamhet: Tillverkar\nspiralmadrasser o sovrumsmöbler\nVarunamn: Dux\nAntal anställda: 170\nÅrsomsättning: 20000 000\nAktiekapital: 1 000 000\nVerkst dir: Olle Nyberg\nEtableringsån 1926\nDotterbolag till Bra Bohag AB.\n\nDYMATIC AB,\nINGENJÖRSFIRMAN\n\nPnr 132 01\n\nSaltsjö-Boo 1, Box 78. Värmdöv\n103. Tel 08-7155206, 7155207.\nBankgiro 731-7423. Postgiro\n696000-9\n\nVerksamhet: Tillverkar, säljer o\nreparerar Porjuspumpen o\nPansarpumpen (dränkbara vattenpumpar\nför borrade brunnar, grävda\nbrunnar, sjöar, åar o älvar) samt\ntillbehör för dessa\n\nVarunamn: Porjuspumpen,\nPansarpumpen, Storebror\nAntal anställda: 7\nÅrsomsättning: 2 000 000\nAktiekapital: 15 000\nStyrelseordf: Dir Olle Pierrou\nVerkst dir: Olle Pierrou\nEtableringsår: 1963.\n\nBANKERYDS TRÄ AB\n\nPnr 560 23\n\nBankeryd, Box 67. Tel 036-725 30\nVerksamhet: Säljer sågade o\nhyvlade trävaror, listverk,\nträfiberplattor, plywood, snickerier,\nbyggnads-o golvmaterial, cementvaror m m\nAntal anställda: 35\nÅrsomsättning: 6000 000\nAktiekapital: 135 000\nStyrelse: Disp Gösta Johansson\n(ordf), I V Johansson\nVerkst dir: Disp Gösta Johansson\nEtableringsår 1955.\n\nCANI TRADING CO AB\n\nPnr 261 22\n\nLandskrona 1, Box 184. Lilla\nStrandg 21. Tel 0418-165 50.\nBankgiro 86-8504. Postgiro 291711\nVerksamhet: Importerar\nlantbruksmaskiner samt lätta\nindustrimaskiner\n\nAntal anställda: 50\nÅrsomsättning: 16 000 000\nAktiekapital: 200 000\nVerkst dir: Gunilla Zätterström\nEtableringsår: 1946.\n\nMONTGOMERY AB, HUGO\n\nPnr 122 21\n\nEnskede 1, Sandsborgsv 44. Box\n43. Tel 08-49 26 80. Bankgiro\n569-5226. Postgiro 52493-4. Tga\nDema-ter. Telex 1869\n\nVerksamhet: Telfrar, traverskranar,\nportalkranar, handlyftblock,\nmobilkranar, lagersystem, bromsmotorer,\naxelkopplingar, gripskopor,\nlyft-magneter, containerhantering\nAvdelningskontor: Hälsingborg,\nKungsg 8. Tel 042-14 2 4 20\nLinköping, Fjäderg 76. Tel\n013-10 17 00\n\nKarlstad, Kungsg 4 A. Tel\n054-18 7610\n\nKrylbo. Stationsg 39. Tel\n0226-129 00\n\nVarunamn: DEMAG, Conz, Felco,\nKeienburg, Cardeflex, Bibby, Elsi\nAntal anställda: 130\nAktiekapital: 2 250 000\nVerkst dir Hans J Andersen\nEtableringsår: 1918.\n\nALUNA, INDUSTRIBYGGARE\nAB\n\nPnr 116 20\n\nStockholm, Högbergsg 44. Tel\n08-44 96 55. Bankgiro 73-1040.\nPostgiro 151881\n\nVerksamhet:\nByggnadsentreprenörer\n\nAntal anställda: 50\nÅrsomsättning: 5 000 000\nAktiekapital: 200 000\nVerkst dir: Stig Lundquist\nEtableringsår: 1947.\n\nSÄVSJO SNICKERIFABRIK, AB\n\nPnr 576 00\n\nSävsjö, V Järnvägsg 16. Box 141.\nTel 0382-10117, 115 17. Bankgiro\n836-6205. Postgiro 136766-3\nVerksamhet: Tillverkar\nbyggnadssnickerier, fönster, dörrar\nAntal anställda: 26\nAktiekapital: 90 000\nVerkst din Fabr Sigvard Gustafsson\nEtableringsår: 1918.\n\nCEJN-PRODUCT AB\n\nPnr 20012\n\nMalmö 2. Box 2051. Kamrerg 17.\nTel 040-779 10. Bankgiro 48-3034.\nPostgiro 691818. Telex 3129\nCEJN S. Tga Cejn\nVerksamhet: Säljer CEJN\nsnabbkopplingar för tryckluft, hydraulik\no vatten samt nylonrör o\nanslutningar\n\nVarunamn: CEJN\nAntal anställda: 8\n\nÅrsomsättning: 6 000 000\nDir: Birger Olfalk\nExportchef: Paul Yman\nEtableringsår: 1965.\n\nSKA\n\nAktiekapital: 5 000\nVerkst dir: Malte Granstedt\nEtableringsàr: 1960.\n\nSKANDINAVISKA PIP.\nFABRIKEN AB\n\nPnr 45101\n\nUddevalla 1, Box 115. Tel\n0522-143 20. Bankgiro 42-8035. Postgiro\n97680. Tga Skapi\nVerksamhet: Tillverkar rökpipor\nAntal anställda: 20\nÅrsomsättning: 1000 000\nAktiekapital: 300 000\nVerkst dir: Ruben Rask\nEtableringsàr: 1936.\n\nSKANDINAVISKA SKORSTENS.\nBYGGNADS AB\n\nPnr 10340\n\nStockholm 40, Regeringsg 107.\nPack. Tel 08-22 60 40. Postgiro\n2650. Tga Skorstenbolag\nVerksamhet: Byggnadsfirma för\nskorstenar, sopförbränningsugnar,\nångpanneinfodringar o\nungsmur-ningar\n\nAntal anställda: 32\nÅrsomsättning: 3 000 000\nAktiekapital: 30 000\nStyrelse: Dir Ulf Widerström (ordf),\ning Ivar Bie\nChef: Ing Ivar Bie\nEtableringsàr: 1897\nDotterbolag till AB Skånska\nCe-mentgjuteriet, Stockholm.\n\nSKANDINAVISKA SOLENOID\nAB\n\nPnr 12612 ahlm 42\nHägersten, Västberga Allé 32. Box\n42097, Sthlm 42. Tel 08-18 83 30.\nBankgiro 650-0862. Postgiro\n653870-6.\n\nTga Skansolenoid, Stockholm.\nTelex 17123 SKANSOL S\nVerksamhet: Försäljning o\ntillverkning av Kraus &amp; Naimer\nström-ställare o kontaktorer\nVarunamn: Skansol, Kraus &amp; Naimer\nPlatsrepresentanter:\n212 28 Malmö, Scheeleg 27. Tel\n040-94 35 60\n\nGöteborg: Sture Holm i Stockholm,\nBox 42097. Tel 08-18 83 30\n702 32 Örebro. Ing Lennart Nyström.\nVäståstrand 3. Tel 019-14 29 77\nAntal anställda: 30\nAktiekapital: 400 000\nVerkst dir: Hans Federsel\nEtableringsàr: 1967.\n\nSKANDINAVISKA\nSOPLARIL AB\n\nPnr 114 57\n\nStockholm, Kaptensg 6. Tel\n08-67 92 00. Telex 1857 andrén s. Tga\nAndrénplast\n\nVerksamhet: Folie, slang o påsar\nav Rilsan (Nylon 11) o Orgamide\n(Nylon 6) för livsmedel o\nsterilisering\n\nAntal anställda: 4\nAktiekapital: 50 000\nVerkst dir: Bo Andrén\nEtableringsàr. 1960.\n\nSKANDINAVISKA SÄNGRESÅR.\nFABRIKEN, AB\n\nse Nordverk, AB.\n\nSKANDINAVISKA TALURIT AB\n\nPnr 421 31\n\nVästra Frölunda, Frökotteg 23. Tel\n031-4921 62, 4921 76. Telex 20796.\nTga Talurit\n\nVerksamhet: Tillverkar patentlås\nför stållinor\nAktiekapital: 57 000\nVerkst dir: Gerhard Rohland\nEtableringsàr: 1948.\n\nSKANDINAVISKA TE LE KOM.\nPANIET AB\n\nPnr 170 23\n\nBarkarby, Veddestav 14. Tel\n08-760 02 55. Telex 17337 TELTRAD S.\nTga Teletrade\n\nVerksamhet: Import o export av\nelektr komponenter o lödverktyg\nVarunamn: Adcola, Bonnella,\nCor-rex, C.G.S., Cherry, Crabtree,\nHi-vac, Magnetic Devices, Stirex,\nStiron\n\n.Antal anställda: 30\nÅrsomsättning: 3 500 000\nAktiekapital: 5 000\nVerkst dir: Göran Ygfors\nEtableringsàr: 1955-\n\nSKANDINAVISKA\nTEST-FURLAGET AB\n\nPnr 102 46\n\nStockholm 5, Box 5305. Stureg 56-\n\n58. Tel 08-67 91 45. Bankgiro 735-\n\n8500. Postgiro 556883-7\n\nVerksamhet: säljer psykologiskt\n\ntestmaterial\n\nAntal anställda: 14\n\nVerkst dir: Docent Lars Kebbon\n\nEtableringsàr: 1952.\n\nSKANDINAVISKA\nTRÄ-IMPORT AB\n\nPnr 100 53\n\nStockholm 37, Hangöv 9-15,\nVärtan. Fack. Tel 08-67 04 10.\nBankgiro 167-4241. Postgiro 1799-6. Tga\nTräimport. Telex 10174 TRAEIMP S\nVerksamhet: Handel med in- o\nutländska träslag ofanér. Fanërfabrik\no sågverk i Norrköping\nFilial: Malmö C, Mejselg 3. Tel\n040-93 53 20\n\nDotterbolag: Göteborg SV. F O\nStrömmans Träförädlings AB,\nMasthuggstorget. Tel 031-14 49 02\nNorrköping. Norrköpings Träimport\nAB, Slottsg 2-16. Tel 011-1344 50\nAntal anställda: 170\n.Aktiekapital: 3 000 000\nEtableringsàr: 1901.\n\nSKANDINAVISKA VERKTYGS.\nFABRIKS AB\n\nPnr 28200\n\nTyringe, Box 88. Tel 0451-509 00.\nBankgiro 288-9475. Postgiro\n7736-2. Tga Verktygsfabrik.\nTelex 4428 SVA S\n\nSVA\n\nVerksamhet: Tillverkar skärande\nverktyg för den mekaniska\nindustrin såsom frasar för\nmetallbearbetning, kuggbearbetingsverktyg,\nbrotschar o försänkare, gängverk-\n\ntyg, specialverktyg, sparskär samt\nvärmebehandling av stål m m\nVarunamn: SVA\nAntal anställda: 210\nÅrsomsättning: 11500 000\nAktiekapital: 1500 000\nVerkst dir: Civiling Harry E\nAnderson\n\nV verkst dir: Esbjörn Esbjörnson\nEtableringsàr: 1896.\n\nSKANDINAVISKA VOLUMAIR\nAB\n\nPnr 16154\n\nBromma, Färjestadsv 26. Tel 08-\n\n87 21 60. Postgiro 507010-7\n\nVerksamhet: Säljer sprutmålnings-\n\nutrustningar\n\nAktiekapital: 30 000\n\nVerkst dir: Ing Lennart Bergman\n\nEtableringsàr: 1964.\n\nSKANDINAVISK-AMERIKANSKA\nPETROLEUM AB\n\nPnr 115 41\n\nStockholm, s Kajen 15. Tel\n08-60 56 87. Tga Sapa\nVerksamhet: Smörjoljor\nEtableringsàr: 1932.\n\nSKANDINAVISK-CONTINEN.\nTAL HANDELS AB SKACO\n\nPnr 114 57\n\nStockholm, Riddarg 23 B. Tel\n08-6164 90. Tga Skaco\nVerksamhet: Import o export\nAktiekapital: 50 000\nVerkst dir: Bruno Reichwald\nEtableringsàr: 1945.\n\nSKANDITRÄ, AB\n\nPnr 21121\n\nMalmö, Västerg 22. Tel 040-717 25.\nBankgiro 870-3795. Postgiro\n246380-0. Tga Skanditrä.\nTelex 32438\n\nVerksamhet: Import av trävaror\nImportnederlag: Göteborg H,\nLindholmshamnen. Tel 031-51 20 74\nFörsäljningsnederlag: Vaggeryd.\nTel 0393-113 95, 111 97. Chef:\nPlatschef Sven-Uno Andersson.\nTel b ost 0393-105 42\nAktiekapital: 136 000\nVerkst dir: Gunnar Bååth\nEtableringsån 1941.\n\nSTRANNE &amp; ORESTEN, AB\n\nPnr 414 55\n\nGöteborg, Fiskhamnsg 10. Tel\n031-125848, 1217 90. Bankgiro\n44-0619. Postgiro 45258-1\nVerksamhet: Tillverkar trålar,\nsäljer stållinor\nAntal anställda: 11\nAktiekapital: 75 000\nVerkst dir: Wedel Stranne\nEtableringsår: 1936.\n\nEVERSHARP SWEDEN AB\n\nPnr 30103\n\nHalmstad 1, Box 143. S vägen. Tel\n035-118210. Bankgiro 859-5571.\nPostgiro 72288-4. Tga Everazor.\nTelex 38050 EVERAZ S\n\nVerksamhet: Tillverkar o säljer\nrakblad o rakhyvlar\nVarunamn: Schick\nAktiekapital: 600 000\nVerkst dir: Ake Svensson\nEtableringsår: 1930.",
    "structured": {
        "1": {
            "company_name": "DUX MÖBEL AB",
            "activity": "Tillverkar o säljer stopp- o trämöbler",
            "establishment_year": 1926,
            "employees": 445,
            "annual_turnover": 48000000,
            "capital": 1000000,
            "key_personnel": [
                {
                    "name": "Disp Gösta Welwert",
                    "position": "Verkst dir"
                }
            ]
        },
        "2": {
            "company_name": "DUX SÄNGAR AB",
            "activity": "Tillverkar spiralmadrasser o sovrumsmöbler",
            "establishment_year": 1926,
            "employees": 170,
            "annual_turnover": 20000000,
            "capital": 100000,
            "key_personnel": [
                {
                    "name": "Olle Nyberg",
                    "position": "Verkst dir"
                }
            ]
        },
        "3": {
            "company_name": "DYMATIC AB, INGENJÖRSFIRMAN",
            "activity": "Tillverkar, säljer o reparerar Porjuspumpen o Pansarpumpen",
            "establishment_year": 1963,
            "employees": 7,
            "annual_turnover": 2000000,
            "capital": 15000,
            "key_personnel": [
                {
                    "name": "Olle Pierrou",
                    "position": "Styrelseordf, Verkst dir"
                }
            ]
        },
        "4": {
            "company_name": "BANKERYDS TRÄ AB",
            "activity": "Säljer sågade o hyvlade trävaror, listverk, träfiberplattor, plywood, snickerier, byggnads-o golvmaterial, cementvaror m m",
            "establishment_year": 1955,
            "employees": 35,
            "annual_turnover": 6000000,
            "capital": 135000,
            "key_personnel": [
                {
                    "name": "Disp Gösta Johansson",
                    "position": "Styrelse"
                },
                {
                    "name": "I V Johansson",
                    "position": null
                }
            ]
        },
        "5": {
            "company_name": "CANI TRADING CO AB",
            "activity": "Importerar lantbruksmaskiner samt lätta industrimaskiner",
            "establishment_year": 1946,
            "employees": 50,
            "annual_turnover": 16000000,
            "capital": 200000,
            "key_personnel": [
                {
                    "name": "Gunilla Zätterström",
                    "position": "Verkst dir"
                }
            ]
        },
        "6": {
            "company_name": "MONTGOMERY AB, HUGO",
            "activity": "Telfrar, traverskranar, portalkranar, handlyftblock, mobilkranar, lagersystem, bromsmotorer, axelkopplingar, gripskopor, Lyft-magneter, containerhantering",
            "establishment_year": 1918,
            "employees": 130,
            "capital": 2250000,
            "key_personnel": [
                {
                    "name": "Hans J Andersen",
                    "position": "Verkst dir"
                }
            ]
        },
        "7": {
            "company_name": "ALUNA, INDUSTRIBYGGARE AB",
            "activity": "Byggnadsentreprenörer",
            "establishment_year": 1947,
            "employees": 50,
            "annual_turnover": 5000000,
            "capital": 200000,
            "key_personnel": [
                {
                    "name": "Stig Lundquist",
                    "position": "Verkst dir"
                }
            ]
        },
        "8": {
            "company_name": "SÄVSJO SNICKERIFABRIK, AB",
            "activity": "Tillverkar byggnadssnickerier, fönster, dörrar",
            "establishment_year": 1918,
            "employees": 26,
            "capital": 90000,
            "key_personnel": [
                {
                    "name": "Fabr Sigvard Gustafsson",
                    "position": "Verkst din"
                }
            ]
        },
        "9": {
            "company_name": "CEJN-PRODUCT AB",
            "activity": "Säljer CEJN snabbkopplingar för tryckluft, hydraulik o vatten samt nylonrör o anslutningar",
            "establishment_year": 1965,
            "employees": 8,
            "annual_turnover": 6000000,
            "key_personnel": [
                {
                    "name": "Birger Olfalk",
                    "position": "Dir"
                },
                {
                    "name": "Paul Yman",
                    "position": "Exportchef"
                }
            ]
        }
    }
}