{
    "original": "HEINEX, AB\n\nPnr 200 21\n\nMalmö 21, Kruseg 30. Box 21033.\nTel 040-93 53 70. Bankgiro\n640-5922. Postgiro 430870-6. Tga\nHeinex. Telex 32563 HEINEX S\nVerksamhet: Maskiner o apparater\nför pressning o strykning\nAktiekapital: 5 000\nVerkst dir: Sigurd Heintz\nEtableringsår: 1963.\n\nWALLA-TEGEL AB\n\nPnr 640 23\n\nValla, Box 13. Tel 0150-60500.\nBankgiro 624-4461. Postgiro\n7700-8. Tga Wallategel\nVerksamhet: Tillverkar fasad- o\nmurtegel\n\nAntal anställda: 76\nÅrsomsättning: 6 400 000\nAktiekapital: 507 500\nVerkst dir: Hans Grönkwist\nEtableringsår: 1898.\n\nKAR\n\nProduktion o inköp: Ing K E\nAnderson\n\nEtableringsår: 1953\nOmbildat till aktiebolag 1963.\n\nKARLEMARK, T\n\nPnr 41705\n\nGöteborg, Hildebrandsg 5. Tel\n031-23 50 80. Bankgiro 362-6918.\nPostgiro 423691-5.\nTelex 20021 KAMARK S\n\nRepresentant för\nSTORA KOPPARBERG\nSPECIALSTALVERKEN\nSURAHAMMARS BRUKS AB\n(pulverpressade detaljer)\nCARBOLOY\n\nAntal anställda: 15\nDir: T Karlemark\nEtableringsår: 1951.\n\nKARLGE AB,\nAUTOMO-bilfirman bröderna\n\nPnr 462 00\n\nVänersborg, O vägen 14. Tel\n0521-120 75. Postgiro 11982\nVerksamhet: General Motors bilar,\nservice o reservdelar\nAntal anställda: 47\nÅrsomsättning: 8 000 000\nAktiekapital: 300 000\nVerkst dir: Gunnar Lundin\nEtableringsår: 1929.\n\nsängfabriken, ab\n\nPnr 11143\n\nStockholm, Norrlandsg 16. Tel\n08-2317 95. Bankgiro 731-6227.\nPostgiro 1651-9. Tga Sängfabriken\nVerksamhet: Tillverkar o säljer\nsängar, sängkläder o rullande\nmateriel till sjukhus, sjukhem,\nålderdomshem mm. Säljer sängar mm\ntill möbelhandeln, varuhus mfl\nFabrik: Orbyhus. Smides &amp;\nJärnsängsfabriks AB. Tel 0295-106 10\nAntal anställda: 138\nÅrsomsättning: 7 500 000\nAktiekapital: 750 000\nStyrelse: Adv Clas Ostberg (ordf),\nherr Lars Ericsson, dir Töre\nEricsson\n\nVerkst dir: Töre Ericsson\nEtableringsår: 1899.\n\nRYDAHLSBOKTRYCKERI AB\n\nPnr 113 57\n\nStockholm, Kungstensg 18. Tel\n08-15 18 25, 15 18 26. Bankgiro\n235-2433. Postgiro 58774\nVerksamhet: Boktryckeri\nAntal anställda: 10\n\nÅrsomsättning: 1000 000\nAktiekapital: 25 000\nVerkst dir: Bertil Kring.\n\nRYDAHLSMANUFAKTUR AB\n\nPnr 510 33\n\nRydal. Tel 0320-430 11. Tga\nRydahlsbolaget, Borås\nVeiksamhet: Utför spinning samt\ntvinning\n\nAntal anställda: 125\nÅrsomsättning: 5 000 000\nAktiekapital: 3 520 000\nVeikst dir: Ragnar Erikson\nEtableringsår: 1853.\n\nRYDAHL BROMSBANDS.\nFABRIK, AB ERNST HJ\n\nPnr 65102\n\nKarlstad 1, Nyg 17. Box 12. Tel\n054-1106 20. Bankgiro 43-8841.\nPostgiro 85353. Tga Rydahl\nVerksamhet: Tillverkar o säljer\nbromsband o lamellbelägg samt\nsäljer nitar\n\nVarunamn: Dan-Block, Dantex,\nFiber, Friktionid, Roblock, Rofax\nAntal anställda: 13\nÅrsomsättning: 2 800 000\nAktiekapital: 60 000\nVerkst din Knut Rydahl\nEtableringsår: 1914.\n\nGNOSJO METALLGJUTERI\n\nPnr 330 30\n\nGnosjö. Tel 0370-912 64. Postgiro\n295718\n\nVerksamhet: Tillverkar sandformat\ngjutgods i mässing, rödgods o brons\nsamt färdiga maskin- o\nreklamskyltar i mässing o lättmetall\nÄgare o chef: JG Holger\nNordemark.\n\nGNOSJO METALLINDUSTRI\n\nPnr 33030\n\nGnosjö. Tel 0370-910 86\nVerksamhet: Tillverkar pressade o\nsvarvade elektr massartiklar\nÄgare o chefer: David Johansson,\nEgon Johansson\nEtableringsår: 1934.\n\nMIKRO.VERKTYG, AB\n\nPnr 151 23\n\nSödertälje 1, Box 281. Storg 40-46.\n\nMILES &amp; WARNBERG AB\n\nPnr 44100\n\nAlingsås, Sidenv. Tel 0322-14260.\nBankgiro 51-4326. Postgiro 41454.\nTga Miwabags.\nTelex 2457 MIWASNO S\nVerksamhet: Tillverkar damväskor\nProvrum: Göteborg S, Sten Stureg\n38. Tel 031-20 29 50, 20 29 00\nVarunamn: Guldhuvudet, TETE D’ OR\nAntal anställda: 250\nÅrsomsättning: 10 000 000\nAktiekapital: 250 000\nVerkst dir: Per Lennegren\nEtableringsår: 1939.\n\nCOLGATE-PALMOLIVE AB\n\nPnr 113 84\n\nStockholm 6, N Stationsg 79-81.\nBox 6605. Tel 08-34 96 10. Bankgiro\n167-0207. Postgiro 50285-6. Tga\nPalmolive. Telex 10419\nVerksamhet: Tillverkar o säljer\nkem tekn artiklar\nAntal anställda: 83\nÅrsomsättning: 42370000\nAktiekapital: 1000 000\nStyrelse: Adv Erie Köhler (ordf),\nadv Lennart Heijne, dir Björn\nJ:son-Stampe, ing Rune E Janerud,\ndir G H Lesch\n\nVerkst dir: Björn J:son-Stampe\nEkonomichef: Lars Lindgren\nTillverkningschef: Rune E Janerud\nEtableringsår: 1928.\n\nMEKAR, AB\n\nPnr 113 28\n\nStockholm, Upplandsg 41. Tel\n08-34 94 25. Bankgiro 16-8464.\nPostgiro 255969. Tga Mekar\nVerksamhet: Försäljning av\nverktygsmaskiner, Kaltenbach\nkap-maskiner för järn o metall, Loroch\nklingslipmaskiner o kyl- o skärolja\nMecanoil, kapklingor\nVarunamn: Kaltenbach\nAntal anställda: 10\nÅrsomsättning: 4 000 000\nAktiekapital: 100 000\nVerkst dir: Ake Olson\nEtableringsår: 1932\nDotterbolag till Palmer Lindberg\nSundsvall AB, Sundsvall.\n\nMEKOS, AB\n\nPnr 252 21\n\nHelsingborg, Drottningg 100. Tel\n042-12 7670\n\nVerksamhet: Säljer läkemedel\nÅrsomsättning: 8 500 000\nAktiekapital: 1000 000\nVerkst dir: Bo Chr Olsson\nEtableringsår 1959.\n\nNOR\n\nFörsäljningskontor: Malmö,\nStockholm, Sundsvall\nVerkstäder: Långserud, Amål\nAntal anstäUda: 700\nÅrsomsättning: 40 000 000\nAktiekapital: 3 000 000\nVerkst dir. Disp L Ullberg\nEtableringsàr 1945.",
    "structured": {
        "1": {
            "company_name": "HEINEX, AB",
            "pnr": "200 21",
            "address": "Malmö 21, Kruseg 30. Box 21033.",
            "phone_number": "040-93 53 70",
            "bank_details": {
                "bankgiro": "640-5922",
                "postgiro": "430870-6"
            },
            "activity": "Maskiner o apparater för pressning o strykning",
            "capital": 5000,
            "key_personnel": [
                {
                    "name": "Sigurd Heintz",
                    "position": "Verkst dir"
                }
            ],
            "establishment_year": 1963
        },
        "2": {
            "company_name": "WALLA-TEGEL AB",
            "pnr": "640 23",
            "address": "Valla, Box 13",
            "phone_number": "0150-60500",
            "bank_details": {
                "bankgiro": "624-4461",
                "postgiro": "7700-8"
            },
            "activity": "Tillverkar fasad- o murtegel",
            "employees": 76,
            "annual_turnover": 6400000,
            "capital": 507500,
            "key_personnel": [
                {
                    "name": "Hans Grönkwist",
                    "position": "Verkst dir"
                }
            ],
            "establishment_year": 1898
        },
        "3": {
            "company_name": "KAR",
            "establishment_year": 1953
        },
        "4": {
            "company_name": "KARLEMARK, T",
            "pnr": "41705",
            "address": "Göteborg, Hildebrandsg 5",
            "phone_number": "031-23 50 80",
            "bank_details": {
                "bankgiro": "362-6918",
                "postgiro": "423691-5"
            },
            "activity": "Representant för STORA KOPPARBERG SPECIALSTALVERKEN SURAHAMMARS BRUKS AB (pulverpressade detaljer) CARBOLOY",
            "employees": 15,
            "key_personnel": [
                {
                    "name": "T Karlemark",
                    "position": "Dir"
                }
            ],
            "establishment_year": 1951
        },
        "5": {
            "company_name": "KARLGE AB, AUTOMO-bilfirman bröderna",
            "pnr": "462 00",
            "address": "Vänersborg, O vägen 14",
            "phone_number": "0521-120 75",
            "postgiro": "11982",
            "activity": "General Motors bilar, service o reservdelar",
            "employees": 47,
            "annual_turnover": 8000000,
            "capital": 300000,
            "key_personnel": [
                {
                    "name": "Gunnar Lundin",
                    "position": "Verkst dir"
                }
            ],
            "establishment_year": 1929
        },
        "6": {
            "company_name": "sängfabriken, ab",
            "pnr": "11143",
            "address": "Stockholm, Norrlandsg 16",
            "phone_number": "08-2317 95",
            "bank_details": {
                "bankgiro": "731-6227",
                "postgiro": "1651-9"
            },
            "activity": "Tillverkar o säljer sängar, sängkläder o rullande materiel till sjukhus, sjukhem, ålderdomshem mm. Säljer sängar mm till möbelhandeln, varuhus mfl Fabrik: Orbyhus. Smides & Järnsängsfabriks AB. Tel 0295-106 10",
            "employees": 138,
            "annual_turnover": 7500000,
            "capital": 750000,
            "key_personnel": [
                {
                    "name": "Töre Ericsson",
                    "position": "Verkst dir"
                }
            ],
            "establishment_year": 1899
        },
        "7": {
            "company_name": "RYDAHLSBOKTRYCKERI AB",
            "pnr": "113 57",
            "address": "Stockholm, Kungstensg 18",
            "phone_number": "08-15 18 25, 15 18 26",
            "bank_details": {
                "bankgiro": "235-2433",
                "postgiro": "58774"
            },
            "activity": "Boktryckeri",
            "employees": 10,
            "annual_turnover": 1000000,
            "capital": 25000,
            "key_personnel": [
                {
                    "name": "Bertil Kring",
                    "position": "Verkst dir"
                }
            ]
        },
        "8": {
            "company_name": "RYDAHLSMANUFAKTUR AB",
            "pnr": "510 33",
            "address": "Rydal",
            "phone_number": "0320-430 11",
            "activity": "Utför spinning samt tvinning",
            "employees": 125,
            "annual_turnover": 5000000,
            "capital": 3520000,
            "key_personnel": [
                {
                    "name": "Ragnar Erikson",
                    "position": "Veikst dir"
                }
            ],
            "establishment_year": 1853
        },
        "9": {
            "company_name": "RYDAHL BROMSBANDS. FABRIK, AB ERNST HJ",
            "pnr": "65102",
            "address": "Karlstad 1, Nyg 17. Box 12",
            "phone_number": "054-1106 20",
            "bank_details": {
                "bankgiro": "43-8841",
                "postgiro": "85353"
            },
            "activity": "Tillverkar o säljer bromsband o lamellbelägg samt säljer nitar Varunamn: Dan-Block, Dantex, Fiber, Friktionid, Roblock, Rofax",
            "employees": 13,
            "annual_turnover": 2800000,
            "capital": 60000,
            "key_personnel": [
                {
                    "name": "Knut Rydahl",
                    "position": "Verkst din"
                }
            ],
            "establishment_year": 1914
        },
        "10": {
            "company_name": "GNOSJO METALLGJUTERI",
            "pnr": "330 30",
            "address": "Gnosjö",
            "phone_number": "0370-912 64",
            "postgiro": "295718",
            "activity": "Tillverkar sandformat gjutgods i mässing, rödgods o brons samt färdiga maskin- o reklamskyltar i mässing o lättmetall",
            "key_personnel": [
                {
                    "name": "JG Holger Nordemark",
                    "position": "Ägare o chef"
                }
            ]
        },
        "11": {
            "company_name": "GNOSJO METALLINDUSTRI",
            "pnr": "33030",
            "address": "Gnosjö",
            "phone_number": "0370-910 86",
            "activity": "Tillverkar pressade o svarvade elektr massartiklar",
            "key_personnel": [
                {
                    "name": "David Johansson",
                    "position": "Ägare o chef"
                },
                {
                    "name": "Egon Johansson",
                    "position": "Ägare o chefer"
                }
            ],
            "establishment_year": 1934
        },
        "12": {
            "company_name": "MIKRO.VERKTYG, AB",
            "pnr": "151 23",
            "address": "Södertälje 1, Box 281. Storg 40-46."
        },
        "13": {
            "company_name": "MILES & WARNBERG AB",
            "pnr": "44100",
            "address": "Alingsås, Sidenv.",
            "phone_number": "0322-14260",
            "bank_details": {
                "bankgiro": "51-4326",
                "postgiro": "41454"
            },
            "activity": "Tillverkar damväskor Provrum: Göteborg S, Sten Stureg 38 Varunamn: Guldhuvudet, TETE D’ OR",
            "employees": 250,
            "annual_turnover": 10000000,
            "capital": 250000,
            "key_personnel": [
                {
                    "name": "Per Lennegren",
                    "position": "Verkst dir"
                }
            ],
            "establishment_year": 1939
        },
        "14": {
            "company_name": "COLGATE-PALMOLIVE AB",
            "pnr": "113 84",
            "address": "Stockholm 6, N Stationsg 79-81. Box 6605",
            "phone_number": "08-34 96 10",
            "bank_details": {
                "bankgiro": "167-0207",
                "postgiro": "50285-6"
            },
            "activity": "Tillverkar o säljer kem tekn artiklar",
            "employees": 83,
            "annual_turnover": 42370000,
            "capital": 1000000,
            "key_personnel": [
                {
                    "name": "Björn J:son-Stampe",
                    "position": "Verkst dir"
                }
            ],
            "establishment_year": 1928
        },
        "15": {
            "company_name": "MEKAR, AB",
            "pnr": "113 28",
            "address": "Stockholm, Upplandsg 41",
            "phone_number": "08-34 94 25",
            "bank_details": {
                "bankgiro": "16-8464",
                "postgiro": "255969"
            },
            "activity": "Försäljning av verktygsmaskiner, Kaltenbach kap-maskiner för järn o metall, Loroch klingslipmaskiner o kyl- o skärolja Mecanoil, kapklingor Varunamn: Kaltenbach",
            "employees": 10,
            "annual_turnover": 4000000,
            "capital": 100000,
            "key_personnel": [
                {
                    "name": "Ake Olson",
                    "position": "Verkst dir"
                }
            ],
            "establishment_year": 1932
        },
        "16": {
            "company_name": "MEKOS, AB",
            "pnr": "252 21",
            "address": "Helsingborg, Drottningg 100",
            "phone_number": "042-12 7670",
            "activity": "Säljer läkemedel",
            "annual_turnover": 8500000,
            "capital": 1000000,
            "key_personnel": [
                {
                    "name": "Bo Chr Olsson",
                    "position": "Verkst dir"
                }
            ],
            "establishment_year": 1959
        },
        "17": {
            "company_name": "NOR",
            "activity": "Försäljningskontor: Malmö, Stockholm, Sundsvall Verkstäder: Långserud, Amål",
            "employees": 700,
            "annual_turnover": 40000000,
            "capital": 3000000,
            "key_personnel": [
                {
                    "name": "Disp L Ullberg",
                    "position": "Verkst dir"
                }
            ],
            "establishment_year": 1945
        }
    }
}