{
    "original": "CONSTRUCTA, BYGGNADS AB\n\nPnr 182 36\n\nDanderyd, Sätraängsv 8. Tel\n08-755 28 60. Bankgiro 29-0873\nVerksamhet: Byggnadsentreprenör\ninom bostads- o industrisektorn\nAntal anställda: 60\nÅrsomsättning: 16 500 000\nAktiekapital: 75 000\nStyrelseordf: Civiling Hans E\nOlsson\n\nVerkst dir: Civiling Hans E Olsson\nEkonomichef: Ossian Heidvall\nArbetschef: Hans Rigtorp\nEtableringsår: 1966.\n\nRIKS-B USSR E K LAM, AB\n\nPnr 11140\n\nStockholm, Tegnérg 15. Tel\n08-23 4 7 40. Bankgiro 16-0361.\nPostgiro 559401. Tga Riksbuss\nVerksamhet: Uthyrning av\nreklamplatser på o i bussar\nAntal anstäUda: 11\nÅrsomsättning: 3 500 000\nAktiekapital: 100 000\nVerkst dir: Thorsten Swenzén\nEtableringsår: 1958.\n\nRIKSOST SMR:s OST LAG ER.\nFÖRENING\n\nPnr 10110\n\nStockholm 1, Vasag 16. Fack. Tel\n08-23 81 80. Bankgiro 72-0820.\nPostgiro 154740. Tga Riksost\nVerksamhet: Ost i parti\nAntal anstäUda: 365\nÅrsomsättning: 353 919000\nInsatskapital: 7 756 000\nVerkst din Olle Riese\nEtableringsår: 1938.\n\nSJUKVIST KB, HELMER\n\nPnr 630 05\n\nEskilstuna 5. Box 5026. Svarvarg 1.\nTel 016-14 72 80. Bankgiro\n601-3858. Postgiro 32846-8\nVerksamhet: Tillverkar\nsmörjsprutor o smörjnipplar. Utför\nsvarv-ningar av alla slag. Specialitet:\nautomatsvarv ning.\n\nSJÖLANDERS\nBYGGNADSVAROR AB, DAVID\n\nPnr 72009\n\nVästerås 9, Tallmätarg 3. Box 9026.\nTel 021-137400. Bankgiro 46-0644.\nPostgiro 141519.\nTelex 40604 SJOEVTS S\nVerksamhet: Säljer\nbyggnadsmaterial. Utför golv-, plattsättnings- o\nstenarbeten\n\nFilialer Arboga, Klockargränd 4.\n\nTel 0589-138 30\n\nFagersta, Engelbrektsv 4. Tel\n\n0223-129 30\n\nAntal anställda: 120\n\nÅrsomsättning: 30 500 000\n\nAktiekapital: 136 000\n\nStyrelse: Dir Sven Sjölander (ordf),\n\ning Björn Sjölander\n\nDir Sven Sjölander\n\nEtableringsår. 1905.\n\nSJÖLANDERS MEK VERKST\nAB, DAVID\n\nPnr 72132\n\nVästerås 1, Navigatörg 6. Box 922.\nTel 021-14 43 00. Bankgiro\n460-6166. Postgiro 70 2 68-8. Tga Jomek.\nTelex 40608 SJOEVTS S\nVerksamhet: Utför\nmaskinbearbetningar, såsom svarvning, arborrning,\nfräsning, hyvling, slipning,\nborrning. Svetsningsarbeten, både tuni&gt;\no grovplåt samt montagearbeten.\nUtför alla slags maskinenheter\nefter kunders ritningar\nAntal anställda: 57\nÅrsomsättning: 5 000 000\nAktiekapital: 40 000\nVerkst dir: Björn Sjölander\nEtableringsår 1898.\n\nSJÖLANDER AB\nKONSULTERANDE INGENIORSBYRÄ\nFOR ELEKTROTEKNIK,\nGÖSTA\n\nPnr 104 60\n\nStockholm 20, Gotlandsg 43. Fack.\nTel 08-24 14 30, 44 91 20\nVerksamhet: Utför utredningar o\nprogram, kontroll o besiktningar\nAvdelningskontor: 416 64 Göteborg,\nN Kustbaneg 7. Tel 031-8017 00\n550 02 Jönköping 2. Box 2131.\nRänterigränd 1 B. Tel 036-11 95 60\n852 35 Sundsvall, Nybrog 29. Tel\n060-15 27 30\nEtableringsår 1946.\n\nSJÖLANDERS BYGGNADS\nAB, I\n\nPnr 117 25\n\nStockholm, Bastug 35. Tel\n08-44 0 2 40. Postgiro 157161-1\nVeiksamhet: Byggnadsentreprenör\n\nAntal anställda: 150\nÅrsomsättning: 10 000 000\nAktiekapital: 100 000\nÄgare o chef: Ing Ingvar Sjölander\nEtableringsår 1944.\n\nSJUBERG AB, A FERD\n\nPnr 80103\n\nGävle 1, N Stapeltorgsg 8. Box 137.\nTel 026-12 98 30. Bankgiro\n783-7677. Postgiro 21383-5. Tga\nSjöberg\n\nVerksamhet: Kam- o\nkardgarnsspin-neri jämte färgeri. Ryaavdelning\nAntal anställda: 85\nÅrsomsättning: 6 000 000\nAktiekapital: 900000\nVerkst dir: Sven Olving\nEtableringsår: 1874.\n\nROBERTS FABRIKER AB\n\nPnr 701 01\n\nÖrebro 1, Fack. Ornsrog 6. Tel\n019-1105 56. Bankgiro 815-7463.\nPostgiro 20744-9. Tga Roberts\nfabriker. Telex 73426 ROBERTS S\nVerksamhet: Tillverkar aromer o\nextrakter för läskedrycks- o\nsöt-varuindustrin\nAntal anställda: 18\nAktiekapital: 300 000\nVeikst din Arthur Roberts\nEtableringsår: 1910.\n\nAUTOTEMP\n\nPnr 340 14\n\nLagan. Tel 0372-30135, 303 35.\nBankgiro 276-8224. Postgiro\n91122-2. Tga Autotemp\nVerksamhet: Tillverkar ampére-,\ntemperatur- o oljetrycksmätare för\nbl a automobiler, traktorer o båtar,\nelvarvräknare. Hydro- o\nbimetall-termometrar\nAntal anställda: 22\nÅrsomsättning: 700 000\nÄgare o chef: Fabr Ruben\nAndersson, Inge Andersson\nEtableringsår: 1948.\n\nAUTOTRANSIT TRAILER\nEXPRESS AB\n\nPnr 41285\n\nGöteborg, Mölndalsv 85. Tel\n031-20 0400. Bankgiro 89-5987.\nPostgiro 629371. Telex 2588 ATAHK S\nVerksamhet: Internationella\ntran-porter, spedition\nAntal anställda: 127\nÅrsomsättning: 78 000 000\n.Aktiekapital: 2 000 000\nVerkst dir: Rolf Cavallius\nEtableringsår: 1969\nÄgare: AB Godstrafik &amp;\nBilspedi-tion, Göteborg.\n\nAUTO-TRYCK, AB\n\nPnr 113 57\n\nStockholm, Kungstensg 18. Tel\n08-1518 27, 15 18 28. Bankgiro\n235-2359. Postgiro 57219\nVerksamhet: Industri- o affärstryck\nAntal anställda: 5\nÅrsomsättning: 250 000\nAktiekapital: 9 800\nVerkst dir: Bertil Kring\nEtableringsår: 1934.\n\nSTEEN &amp; CO AB, LARS\n\nPnr 46400\n\nMellerud. Tel 0530-120 00\nVerksamhet: Tillverkar plaströr\nAntal anställda: 5\nAktiekapital: 25 000\nVerkst dir: Disp L Steen\nEtableringsår: 1969.\n\nNYVALL, AB ENOCH\n\nPnr 382 00\n\nNybro, Box 62. Madesjöv 3. Tel\n0481-11915. Bankgiro 856-1185.\nPostgiro 20557-5\n\nVerksamhet: Säljer bilar o\nbiltillbehör, bilreparationsverkstad\nAktiekapital: 75 000\nVerkst dir: Bengt Nyvall\nEtableringsår 1913.\n\nKUNDKREDIT AB\n\nPnr 104 30\n\nStockholm 45, Box 45103.\nDrottningg 97. Tel 08-24 27 30. Bankgiro\n722-2516. Postgiro 3450-4\nAktiekapital: 4 000 000\nVerkst dir: Fredrik Lettström\nEtableringsår: 1950.\n\nGÄVLE VAGNVERKSTAD, AB\n\nPnr 801 06\n\nGävle 1. Upplandsg 18. Box 497.\n\n6719. Postgiro 31878. Tga Age ve.\nTelex 81106 AGEVE S\nVerksamhet: Tillverkar\ngodsvagnar. cisternvagnar, gaffeltruckar,\nackumulator lok, kontaktledningslok,\ndieselhydrostatiska lok o\ngruvvagnar, tömningsstationer för\ngruvor samt utför grovplåts- o\nmaskinarbeten\nAntal anställda: 300\nÅrsomsättning: 55000 000\nAktiekapital: 950000\nStyrelse: Generaldir Lars Peterson\n(ordf), bankdir Wiking Belfrage,\ntekn dir J Frostberg, ekonomidir Mats\nHögberg, byråchef Sven Leffler\nVerkst dir: Svante Zetterholm\nEtableringsår: 1920.\n\nGEFLE VELOCIPED.\nFABRIK AB\n\nPnr 801 05\n\nGävle 1, Andra Magasinsg 3 B. Box\n356. Tel 026-12 95 60. Bankgiro\n603-5364. Postgiro 15336-1\nVerksamhet: Parti- o\nminutförsäljning av cyklar o sportartiklar\nAntal anställda: 25\nAktiekapital: 225 000\nVerkst dir: Rolf Pettersson\nEtableringsår: 1943.\n\nGÄVLE VERKTYGS.\nFABRIK, AB\n\n(Mircona AB)\n\nPnr 80133\n\nGävle 1, Lötängsg 5. Box 955. Tel\n026-1293 45. Bankgiro 783-9038.\nPostgiro 169900-8. Tga Mircona.\nTelex 81035\n\nVerksamhet: Tillverkar\nhårdmetallverktyg. Säljer hårdmetall\nVarunamn: Mircona\nAntal anställda: 25\nÅrsomsättning: 2500 000\nAktiekapital: 70 000\nVerkst dir: Wlajko Mihic\nEtableringsår: 1948.",
    "structured": {
        "1": {
            "company_name": "CONSTRUCTA, BYGGNADS AB",
            "pnr": "182 36",
            "address": "Danderyd, Sätraängsv 8",
            "phone_number": "08-755 28 60",
            "bank_details": {
                "bankgiro": "29-0873"
            },
            "activity": "Byggnadsentreprenör inom bostads- o industrisektorn",
            "employees": 60,
            "annual_turnover": 16500000,
            "capital": 75000,
            "key_personnel": [
                {
                    "name": "Civiling Hans E Olsson",
                    "position": "Styrelseordf"
                },
                {
                    "name": "Civiling Hans E Olsson",
                    "position": "Verkst dir"
                },
                {
                    "name": "Ossian Heidvall",
                    "position": "Ekonomichef"
                },
                {
                    "name": "Hans Rigtorp",
                    "position": "Arbetschef"
                }
            ],
            "establishment_year": 1966
        },
        "2": {
            "company_name": "RIKS-B USSR E K LAM, AB",
            "pnr": "11140",
            "address": "Stockholm, Tegnérg 15",
            "phone_number": "08-23 4 7 40",
            "bank_details": {
                "bankgiro": "16-0361",
                "postgiro": "559401"
            },
            "activity": "Uthyrning av reklamplatser på o i bussar",
            "employees": 11,
            "annual_turnover": 3500000,
            "capital": 100000,
            "key_personnel": [
                {
                    "name": "Thorsten Swenzén",
                    "position": "Verkst dir"
                }
            ],
            "establishment_year": 1958
        },
        "3": {
            "company_name": "RIKSOST SMR:s OST LAG ER. FÖRENING",
            "pnr": "10110",
            "address": "Stockholm 1, Vasag 16",
            "phone_number": "08-23 81 80",
            "bank_details": {
                "bankgiro": "72-0820",
                "postgiro": "154740"
            },
            "activity": "Ost i parti",
            "employees": 365,
            "annual_turnover": 353919000,
            "capital": 7756000,
            "key_personnel": [
                {
                    "name": "Olle Riese",
                    "position": "Verkst din"
                }
            ],
            "establishment_year": 1938
        },
        "4": {
            "company_name": "SJUKVIST KB, HELMER",
            "pnr": "630 05",
            "address": "Eskilstuna 5, Box 5026, Svarvarg 1",
            "phone_number": "016-14 72 80",
            "bank_details": {
                "bankgiro": "601-3858",
                "postgiro": "32846-8"
            },
            "activity": "Tillverkar smörjsprutor o smörjnipplar. Utför svarv-ningar av alla slag. Specialitet: automatsvarv ning",
            "establishment_year": null
        },
        "5": {
            "company_name": "SJÖLANDERS BYGGNADSVAROR AB, DAVID",
            "pnr": "72009",
            "address": "Västerås 9, Tallmätarg 3, Box 9026",
            "phone_number": "021-137400",
            "bank_details": {
                "bankgiro": "46-0644",
                "postgiro": "141519"
            },
            "activity": "Säljer byggnadsmaterial. Utför golv-, plattsättnings- o stenarbeten",
            "employees": 120,
            "annual_turnover": 30500000,
            "capital": 136000,
            "key_personnel": [
                {
                    "name": "Dir Sven Sjölander",
                    "position": "Styrelse (ordf)"
                },
                {
                    "name": "Björn Sjölander",
                    "position": "ing"
                },
                {
                    "name": "Sven Sjölander",
                    "position": "Dir"
                }
            ],
            "establishment_year": 1905
        },
        "6": {
            "company_name": "SJÖLANDERS MEK VERKST AB, DAVID",
            "pnr": "72132",
            "address": "Västerås 1, Navigatörg 6, Box 922",
            "phone_number": "021-14 43 00",
            "bank_details": {
                "bankgiro": "460-6166",
                "postgiro": "70 2 68-8"
            },
            "activity": "Utför maskinbearbetningar, såsom svarvning, arborrning, fräsning, hyvling, slipning, borrning. Svetsningsarbeten, både tuni&gt; o grovplåt samt montagearbeten. Utför alla slags maskinenheter efter kunders ritningar",
            "employees": 57,
            "annual_turnover": 5000000,
            "capital": 40000,
            "key_personnel": [
                {
                    "name": "Björn Sjölander",
                    "position": "Verkst dir"
                }
            ],
            "establishment_year": 1898
        },
        "7": {
            "company_name": "SJÖLANDER AB KONSULTERANDE INGENIORSBYRÄ FOR ELEKTROTEKNIK, GÖSTA",
            "pnr": "104 60",
            "address": "Stockholm 20, Gotlandsg 43",
            "phone_number": "08-24 14 30, 44 91 20",
            "activity": "Utför utredningar o program, kontroll o besiktningar",
            "establishment_year": 1946
        },
        "8": {
            "company_name": "SJÖLANDERS BYGGNADS AB, I",
            "pnr": "117 25",
            "address": "Stockholm, Bastug 35",
            "phone_number": "08-44 0 2 40",
            "postgiro": "157161-1",
            "activity": "Byggnadsentreprenör",
            "employees": 150,
            "annual_turnover": 10000000,
            "capital": 100000,
            "key_personnel": [
                {
                    "name": "Ing Ingvar Sjölander",
                    "position": "Ägare o chef"
                }
            ],
            "establishment_year": 1944
        },
        "9": {
            "company_name": "SJUBERG AB, A FERD",
            "pnr": "80103",
            "address": "Gävle 1, N Stapeltorgsg 8, Box 137",
            "phone_number": "026-12 98 30",
            "bank_details": {
                "bankgiro": "783-7677",
                "postgiro": "21383-5"
            },
            "activity": "Kam- o kardgarnsspin-neri jämte färgeri. Ryaavdelning",
            "employees": 85,
            "annual_turnover": 6000000,
            "capital": 900000,
            "key_personnel": [
                {
                    "name": "Sven Olving",
                    "position": "Verkst dir"
                }
            ],
            "establishment_year": 1874
        },
        "10": {
            "company_name": "ROBERTS FABRIKER AB",
            "pnr": "701 01",
            "address": "Örebro 1, Ornsrog 6",
            "phone_number": "019-1105 56",
            "bank_details": {
                "bankgiro": "815-7463",
                "postgiro": "20744-9"
            },
            "activity": "Tillverkar aromer o extrakter för läskedrycks- o söt-varuindustrin",
            "employees": 18,
            "capital": 300000,
            "key_personnel": [
                {
                    "name": "Arthur Roberts",
                    "position": "Veikst din"
                }
            ],
            "establishment_year": 1910
        },
        "11": {
            "company_name": "AUTOTEMP",
            "pnr": "340 14",
            "address": "Lagan",
            "phone_number": "0372-30135, 303 35",
            "bank_details": {
                "bankgiro": "276-8224",
                "postgiro": "91122-2"
            },
            "activity": "Tillverkar ampére-, temperatur- o oljetrycksmätare för bl a automobiler, traktorer o båtar, elvarvräknare. Hydro- o bimetall-termometrar",
            "employees": 22,
            "annual_turnover": 700000,
            "key_personnel": [
                {
                    "name": "Fabr Ruben Andersson"
                },
                {
                    "name": "Inge Andersson"
                }
            ],
            "establishment_year": 1948
        },
        "12": {
            "company_name": "AUTOTRANSIT TRAILER EXPRESS AB",
            "pnr": "41285",
            "address": "Göteborg, Mölndalsv 85",
            "phone_number": "031-20 0400",
            "bank_details": {
                "bankgiro": "89-5987",
                "postgiro": "629371"
            },
            "activity": "Internationella tran-sporter, spedition",
            "employees": 127,
            "annual_turnover": 78000000,
            "capital": 2000000,
            "key_personnel": [
                {
                    "name": "Rolf Cavallius",
                    "position": "Verkst dir"
                }
            ],
            "establishment_year": 1969
        },
        "13": {
            "company_name": "AUTO-TRYCK, AB",
            "pnr": "113 57",
            "address": "Stockholm, Kungstensg 18",
            "phone_number": "08-1518 27, 15 18 28",
            "bank_details": {
                "bankgiro": "235-2359",
                "postgiro": "57219"
            },
            "activity": "Industri- o affärstryck",
            "employees": 5,
            "annual_turnover": 250000,
            "capital": 9800,
            "key_personnel": [
                {
                    "name": "Bertil Kring",
                    "position": "Verkst dir"
                }
            ],
            "establishment_year": 1934
        },
        "14": {
            "company_name": "STEEN & CO AB, LARS",
            "pnr": "46400",
            "address": "Mellerud",
            "phone_number": "0530-120 00",
            "activity": "Tillverkar plaströr",
            "employees": 5,
            "capital": 25000,
            "key_personnel": [
                {
                    "name": "Disp L Steen",
                    "position": "Verkst dir"
                }
            ],
            "establishment_year": 1969
        },
        "15": {
            "company_name": "NYVALL, AB ENOCH",
            "pnr": "382 00",
            "address": "Nybro, Box 62, Madesjöv 3",
            "phone_number": "0481-11915",
            "bank_details": {
                "bankgiro": "856-1185",
                "postgiro": "20557-5"
            },
            "activity": "Säljer bilar o biltillbehör, bilreparationsverkstad",
            "capital": 75000,
            "key_personnel": [
                {
                    "name": "Bengt Nyvall",
                    "position": "Verkst dir"
                }
            ],
            "establishment_year": 1913
        },
        "16": {
            "company_name": "KUNDKREDIT AB",
            "pnr": "104 30",
            "address": "Stockholm 45, Box 45103, Drottningg 97",
            "phone_number": "08-24 27 30",
            "bank_details": {
                "bankgiro": "722-2516",
                "postgiro": "3450-4"
            },
            "capital": 4000000,
            "key_personnel": [
                {
                    "name": "Fredrik Lettström",
                    "position": "Verkst dir"
                }
            ],
            "establishment_year": 1950
        },
        "17": {
            "company_name": "GÄVLE VAGNVERKSTAD, AB",
            "pnr": "801 06",
            "address": "Gävle 1, Upplandsg 18, Box 497, 6719",
            "phone_number": "026-12 98 30",
            "postgiro": "31878",
            "activity": "Tillverkar godsvagnar, cisternvagnar, gaffeltruckar, ackumulator lok, kontaktledningslok, dieselhydrostatiska lok o gruvvagnar, tömningsstationer för gruvor samt utför grovplåts- o maskinarbeten",
            "employees": 300,
            "annual_turnover": 55000000,
            "capital": 950000,
            "key_personnel": [
                {
                    "name": "Svante Zetterholm",
                    "position": "Verkst dir"
                }
            ],
            "establishment_year": 1920
        },
        "18": {
            "company_name": "GEFLE VELOCIPED. FABRIK AB",
            "pnr": "801 05",
            "address": "Gävle 1, Andra Magasinsg 3 B, Box 356",
            "phone_number": "026-12 95 60",
            "bank_details": {
                "bankgiro": "603-5364",
                "postgiro": "15336-1"
            },
            "activity": "Parti- o minutförsäljning av cyklar o sportartiklar",
            "employees": 25,
            "capital": 225000,
            "key_personnel": [
                {
                    "name": "Rolf Pettersson",
                    "position": "Verkst dir"
                }
            ],
            "establishment_year": 1943
        },
        "19": {
            "company_name": "GÄVLE VERKTYGS. FABRIK, AB (Mircona AB)",
            "pnr": "80133",
            "address": "Gävle 1, Lötängsg 5, Box 955",
            "phone_number": "026-1293 45",
            "bank_details": {
                "bankgiro": "783-9038",
                "postgiro": "169900-8"
            },
            "activity": "Tillverkar hårdmetallverktyg. Säljer hårdmetall",
            "employees": 25,
            "annual_turnover": 2500000,
            "capital": 70000,
            "key_personnel": [
                {
                    "name": "Wlajko Mihic",
                    "position": "Verkst dir"
                }
            ],
            "establishment_year": 1948
        }
    }
}