{
    "original": "TOR\n\nAntal anställda: 12\nÅrsomsättning: 5 000 000\nAktiekapital: 100000\nVerkst dir: Ing Bengt Thorin\nEtableringsår: 1932\nOmbildat till aktiebolag 1964.\n\nTORIN, AB NILS\n\nPnr 41319\n\nGöteborg, Per Dubbsg 5. Tel\n031-821811. Bankgiro 515-8100.\nPostgiro 429060. Tga Torinab\nVerksamhet: Grafisk\nreproduktionsutrustning, reprokameror, film,\nkemikalier, montagematerial\nVarunamn: Adefo, Alos, Regu,\nSixt, Typon\nAktiekapital: 60 000\nVerkst din Nils Torin\nEtableringsår: 1935.\n\nAPLER, AB HANS\n\nPnr 414 59\n\nGöteborg V, Karl Johansg 29. Tel\n031-1283 30. Bankgiro 50-8745.\nPostgiro 243343\n\nVerksamhet: Tillverkar barnkläder\no flickklänningar\nAntal anställda: 50\nAktiekapital: 30 000\nVerkst dir: Hans Apler\nEtableringsår: 1957.\n\nAXO METALL AB\n\nPnr 330 33\n\nHillers torp. Tel 0370-822 30\nVerksamhet: Tillverkar rör o\ntrådartiklar\n\nAktiekapital: 200 000\nVerkst dir: Folke Axelsson\nEtableringsår: 1955.\n\nOREBRO PAPPERSBRUKS AB\n\nPnr 70130\n\nÖrebro 1, Box 926. Tel\n019-130900. Postgiro 8575. Tga\nPappersbruk. Telex 73217 OEMILLS S\nVerksamhet: I Örebro:\nPappersbruk, träsliperi, säckfabrik samt\nwellpappfabrik\n\nI Frövi: Sulfatmassafabrik o\npappersbruk\n\nTillverkning: Mekanisk massa o\noblekt sulfatmassa, MG o oglättat\nkraftpapper, kvistpapper,\nplastbe-lagt papper o kartong,\nbokbindar-papp, gipsplattekartong,\npapperssäckar, wellpapp samt\nwellpappkartonger\n\nAntal anställda: 1100\nÅrsomsättning: 160 000 000\nAktiekapital: 27 000 000\nStyrelse: Fil dr Carl M:son\nMannerfelt (ordf), överint Knut von Horn,\ndir Sven Dahlbäck, bankdir Bert\nLindström, disp Sven Johansson\nVerkst dir: Sven Johansson\nPlatschef i Frövifors: Overing Sune\nLundgren\n\növering i Örebro: Sune Albinsson\nMarknadsdir: Helge Janson\nFörsäljn-chefer:Per\nAkerlund(mas-sa o kraftpapper), Lars Berger o\nGösta Wittenström (kvistpapper,\npapp, plastbelagt papper o\nspecialkvaliteter)\n\nFörsäljn-chef för säckar o wellpapp:\n\nSven-Erik Eiikson\nMarknadschef för massa o papper:\n\nBo Mats torns\n\nMarknadschef för säckar o wellpapp:\n\nSven-Göran Wennerholm\nEkonomichef: Holger Göhle\nInköpschef: Göran Sandberg\nBefraktn-chef: Arne Kilhed\nEtableringsån 1901.\n\nGUMAELIUS MASKINAFFAR AB\n\nPnr 10242\n\nStockholm 5, Grev Tureg 27. Box\n5054. Tel 08-63 51 90. Bankgiro\n28-3865. Postgiro 2355. Tga\nGumælierna\n\nVerksamhet: Säljer maskiner o\nutensilier för grafiska industrin\nAntal anställda: 24\nAktiekapital: 1500000\nVerkst dir: Carl-Otto Ekroth\nEtableringsår: 1933.\n\nGUMMESSONS GRAFISKA\nGRUPP AB\n\nPnr 103 64\n\nStockholm 3, Tegnérg 8. Box 3238.\nTel 08-15 05 00. Bankgiro 541-6805.\nPostgiro 3841-4\n\nVerksamhet: Bok-, reklam-,\ntidskrifts- o accidenstryck\nDotterföretag: Brunnhages Förlag\nAB, Upplandsg 22, 113 60\nStockholm. Tel 08-34 98 90\nAB Egnellska Boktryckeriet.\nRosenlundsg 52, 11653 Stockholm.\nTel 08-69 08 00\n\nGummessons Boktryckeri i\nFalköping AB, Göteborgsv 2, 52100\nFalköping. Tel 0515-13110\nGummessons Offset i Falköping AB,\nVerkstadsg 6, 52100 Falköping.\nTel 0515-13110\n\nAB Gummessons Läromedel,\nPil-finksg 5. Fack, 400 21 Göteborg 16.\nTel 031-40 46 56\n\nBorgströms Tryckeri AB, Vinterg\n22. Box 31, 59101 Motala 1. Tel\n0141-163 55\n\nCARL SVANBERG AB:\nBokbinderi: 350 03 Växjö 1,\nBlästerg 4. Box 3002. Tel\n0470-123 73\n\nTryckeri: 35104 Växjö 1, Nyg 12.\nBox 91. Tel 0470-165 03\nAntal anställda: 410\nÅrsomsättning: 34 000 000\nAktiekapital: 2 200000\nStyrelse: Dir John Lorentzi (ordf),\ndir Hugo Edstam, dir Stig Franzén,\nbankdir Hans Gezelius,\nekonomichef Lars G Larson, missionssekr\nArvid Stenström, förlagschef\nJan-Erik Wikström\nVerkst dir: Stig Franzén\nEtableringsår. 1935.\n\nGUMMI FABRIKER\n\nse i övrigt resp namn.\n\nGUMMIFABRIKEN GISLAVED\nAB\n\nPnr 332 00\n\nGislaved. Tel 0371-115 00. Post\ngiro 22555.Telex70066.TgaRubber\nVerksamhet: Tillverkar bil- o\ncykelgummi, gummiskor,\nindustri-gummi, plastfolier, plastslangar o\nvinylskum\n\nAntal anställda: 1 700\n\nAktiekapital: 6 000 000\n\nVerkst dir: Curt Lidén\n\nEtableringsår: 1895\n\nÄges av Kooperativa Förbundet,\n\nStockholm.\n\nGUMPERTSSKOLMATERIEL\nAB\n\nPnr 40010\n\nGöteborg 3, Box 3038. Karl\nGus-tavsg 13. Tel 031-17 51 25.\nBankgiro 602-8005. Postgiro 506677-4\nVerksamhet: Tillverkar o säljer\nmateriel för skolor, huvudsakligen\nAV-materiel, fysik- o\nkemiapparatur\n\nExportavdelning: 104 30 Stockholm\n45, Box 45127. Drottningg 108. Tel\n08-34 29 19\nAntal anställda: 15\nÅrsomsättning: 4 000 000\nAktiekapital: 5 000\nChef: Kapten Gert Lindbom\nEtableringsår: 1967.\n\nGUMPERTS UNIVERSITETS.\nBOKHANDEL AB\n\nPnr 401 25\n\nGöteborg 1, Box 346. Tel\n031-23 54 80. Bankgiro 420-0598. Post-\n\ngiro 40101-8. Tga Gumperts.\nTelex 21178\n\nVerksamhet: Bok- o pappershandel.\nTidskriftsabonnemang\nButiker i Göteborg:\nUniversitetsbokhandel, N Hamng 26\nStudentbokhandel, Aschebergsg 23 A\nAntikvariat, Geijersg 14\nÖvriga butiker:\n\nJönköping, V Storg 16. Tel 036-\n\n1192 40\n\nKarlstad, Kungsg 20. Tel\n054-1151 65\n\nÖrebro: Drottningg 17. Tel\n019-1240 10\n\nVaruhuset Krämaren.Tel 019-13 08 00\nAntal anställda: 182\nÅrsomsättning: 33 000 000\nAktiekapital: 1000 000\nStyrelse: Adv Håkan Lindén, dir\nJohn Tengberg, dir Orvar Törnsten\nVerkst dir: John Tengberg\nChef boksektionen: C A Malmberg\nChef papperssektionen: C A Holmberg\nEtableringsår: 1808.\n\nFALU NYA BOKTRYCKERI AB\n\nPnr 791 01\n\nFalun 1, Box 20. Hälsingtorget.\nTel 023-183 21. Bankgiro 79-2572.\nPostgiro 8731\n\nVerksamhet: Utför bok- o\noffsettryck, tillverkar klichéer\nAntal anställda: 55\nAktiekapital: 100 000\nVerkst dir: Rudolf Bengtsson\nEtableringsår: 1875.\n\nPELLY FABRIKEN AB\n\nPnr 311 01\n\nFalkenberg 1, Box 37. Klockarg\n27. Tel 0346-142 50. Bankgiro\n425-7283. Postgiro 174064-6. Tga Pelly\n\n32x©HIl^r IFæilbiPfllteoini ®Ute&gt;\n\nVerksamhet: Inredningsdetaljer i\ntråd o stål för butiker,\nhemmaförvaringssystemet Pelly-Förvara\nVarunamn: Pelly\nAntal anställda: 200\nVerkst dir: Per Göranson\nEtableringsår: 1939.\n\nER AG HANDELS-AB\n\nPnr 111 22\n\nStockholm, Kungsg 65. Tel\n08-21 18 13, 2122 52. Bankgiro\n700-2108. Postgiro 191310-2. Tga\nEr agentur\n\nVerksamhet: Grosshandel: tillbehör\no verktyg för glasmästeri o\nramaffärer, skjutdörrsbeslag\n’Anticoro-dal’ o ’Delphin’, metallprofiler,\n’Chandos’ glasskärdiamanter,\ninramningsartiklar o glasmålningar\nAntal anställda: 5\nAktiekapital: 5 000\nVerkst dir. Regina Töreman\nEtableringsår: 1960.\n\nERAG HÄNDELS- &amp;\nAGENTURFIRMA\n\nPnr 11122\n\nStockholm, Kungsg 65. Tel\n08-21 22 52, 2118 13. Tga Er agentur\nVerksamhet: Glasagenturer\nVerkst dir: Egon Rauch\nEtableringsår: 1942.\n\nAND\n\nläggningar, felindikeringscentraler.\nSäljer elektriska komponenter\nsåsom manöverströmställare,\ninduktiva givare, fotoceller,\nprogrammeringstavlor, relän, elktroniska\ntidsrelän o kopplingsklämmor\nRepresentant: Leif Jostrand AB.\nBang 27, 41463 Göteborg. Tel\n031-4238 64\n\nAntal anställda: 30\nÅrsomsättning: 3 500 000\nAktiekapital: 150 000\nVerkst dir: Ing Göte Andersson\nEtableringsår: 1967.\n\nLILLSJU AB\n\nPnr 343 00\n\nÄlmhult, Skånev. Box 136. Tel 0476-\n\n122 85. Bankgiro 873-8197.\nPostgiro 321289-1\n\nVeiksamhet: Tillverkar köks- o\ngarderobskåp\nAntal anställda: 46\nÅrsomsättning: 6000 000\nAktiekapital: 40 300\nVerkst dir: Algot Svensson\nKamrer: Marianne Algotsson\nDisp: Rignaldo Appelgren\nFörsäljn-chef: Gunnar Ohlsson\nEtableringsår: 1946.",
    "structured": {
        "1": {
            "company_name": "TORIN, AB NILS",
            "pnr": "41319",
            "address": "Göteborg, Per Dubbsg 5",
            "phone_number": "031-821811",
            "bank_details": {
                "bankgiro": "515-8100",
                "postgiro": "429060"
            },
            "activity": "Grafisk reproduktionsutrustning, reprokameror, film, kemikalier, montagematerial",
            "employees": 12,
            "annual_turnover": 5000000,
            "capital": 60000,
            "key_personnel": [
                {
                    "name": "Nils Torin",
                    "position": "Verkst dir"
                }
            ],
            "establishment_year": 1935
        },
        "2": {
            "company_name": "APLER, AB HANS",
            "pnr": "414 59",
            "address": "Göteborg V, Karl Johansg 29",
            "phone_number": "031-1283 30",
            "bank_details": {
                "bankgiro": "50-8745",
                "postgiro": "243343"
            },
            "activity": "Tillverkar barnkläder o flickklänningar",
            "employees": 50,
            "capital": 30000,
            "key_personnel": [
                {
                    "name": "Hans Apler",
                    "position": "Verkst dir"
                }
            ],
            "establishment_year": 1957
        },
        "3": {
            "company_name": "AXO METALL AB",
            "pnr": "330 33",
            "address": "Hillers torp",
            "phone_number": "0370-822 30",
            "activity": "Tillverkar rör o trådartiklar",
            "capital": 200000,
            "key_personnel": [
                {
                    "name": "Folke Axelsson",
                    "position": "Verkst dir"
                }
            ],
            "establishment_year": 1955
        },
        "4": {
            "company_name": "OREBRO PAPPERSBRUKS AB",
            "pnr": "70130",
            "address": "Örebro 1, Box 926",
            "phone_number": "019-130900",
            "postgiro": "8575",
            "bank_details": {
                "postgiro": "8575"
            },
            "activity": "Pappersbruk, träsliperi, säckfabrik samt wellpappfabrik...",
            "employees": 1100,
            "annual_turnover": 160000000,
            "capital": 27000000,
            "key_personnel": [
                {
                    "name": "Sven Johansson",
                    "position": "Verkst dir"
                }
            ],
            "establishment_year": 1901
        },
        "5": {
            "company_name": "GUMAELIUS MASKINAFFAR AB",
            "pnr": "10242",
            "address": "Stockholm 5, Grev Tureg 27, Box 5054",
            "phone_number": "08-63 51 90",
            "bank_details": {
                "bankgiro": "28-3865",
                "postgiro": "2355"
            },
            "activity": "Säljer maskiner o utensilier för grafiska industrin",
            "employees": 24,
            "capital": 1500000,
            "key_personnel": [
                {
                    "name": "Carl-Otto Ekroth",
                    "position": "Verkst dir"
                }
            ],
            "establishment_year": 1933
        }
    }
}