{
    "original": "CENTRALTRYCKERIET\n\nPnr 902 44\n\nUmeå, Storg 113. Tel 090-110618,\n1106 19. Bankgiro 75-9819.\nPost-giro 296025\n\nVerksamhet: Civiltryckeri, bok- o\noffsettryck, bokbinderi\nEtableringsår 1934.\n\nCENTRAL-TRYCKERIET\nM SKYMAN\n\nPnr 44100\n\n■Alingsås, Plang 20. Tel\n0322-107 99. Bankgiro 889-6656.\nPostgiro 81299-0\n\nVerksamhet; Affärs-, industri-,\nblankett- o reklamtryck\nÅrsomsättning: 170 000\nChef: Boktr M Skyman\nEtableringsår: 1930.\n\nCENTRALTRYCKERIET,\nÅKE SVENSON AB\n\nPnr 50105\n\nBorås 1, Box 288. Druveforsv 8.\nTel 033-10 0260. Bankgiro\n839-1542. Postgiro 31183-7\nVerksamhet: Bok- o offsettryck\nAntal anställda: 25\nAktiekapital: 50 000\nVerkst dir: Ake Svenson\nEtableringsår 1919.\n\nCENTRALTRYCKERIETS\nSTÄMPELFABRIK AB\n\nPnr 105 31\n\nStockholm, Klara Vattugränd 1. Tel\n22 95 00, riks 08-22 95 40. Tga\nCentraltryck\n\nVerksamhet: Stämplar o tillbehör\n\nChef: Sture Nyberg\n\nAnsluten till Esselte Öbergs AB.\n\nCENTRALVÄRME, AB\n\nPnr 261 33\n\nLandskrona, Lundåkrag 17. Tel\n0418-165 60. Postgiro 30435-2\nVerksamhet: Värme-, vatten- o\navlopp, installationer\nAntal anställda: 28\nÅrsomsättning: 3 000 000\nAktiekapital: 45 000\nVerkst dir: Ing Malte Persson\nEtableringsår: 1949.\n\nRIDDARKONTOR, AB\n\nPnr 104 40\n\nStockholm, Box 14037. Riddarg 17.\nTel 08-22 3120. Bankgiro 235-2763.\nPostgiro 550145-7. Tga Nife,\nStockholm. Telex 1592 JUNGNER S\nVerksamhet: Uthyr möblerade\nkontorslokaler med service\nAntal anstäUda: 5\nÅrsomsättning: 350 000\nAktiekapital: 49 500\nVerkst dir: Tage örtegren\nIng: Bertil Asplund\nEtableringsår: 1964\nDotterbolag till Svenska\nAckumulator AB Jungner.\n\nRIEBER &amp; SON SVENSKA AB\n\nPnr 422 46\n\nHisings Backa, Importg 14. Tel\n031-52 0160. Bankgiro 45-5419.\nPostgiro 627701. Tga Rieberson.\nTelex 20049 RIEBERS S\nVerksamhet: Rikett\ngolvbeläggningar, plattor, plastfiltmattor,\nplastmattor, nålfiltmattor, mjuka\nmattor, profiler o\nduschmellanväggar\n\nChef: Civilekonom Jan-Erik\nErichsen\n\nEtableringsån 1963\nDotterbolag till Rieber &amp; Søn A/S\nBergen, Norge. Grundlagt 1839.\n\nRIETZ PAPPERS AB\n\nPnr 11135\n\nStockholm, Kungsg 18. Tel\n08-23 0150. Bankgiro 626-7454.\nPostgiro 1820-0. Tga Paperrietz\nVerksamhet: Säljer papper,\nkontors-o ritmateriel\nAntal anstäUda: 12\nÅrsomsättning: 3 500 000\nAktiekapital: 75 000\nVerkst dir: Gösta Fürstenbach\nEtableringsår: 1926.\n\nKUM\n\n702 11 Örebro, Nygatan 34-36. Tel\n019-1197 65\nAntal anställda: 2 000\nÅrsomsättning: 225 000 000\nAktiekapital: 1200 000\nStyrelse: civiling Yngve\nKullenberg (ordf), dir Frans Persson, prof\nBörje Kullenberg, dir Ake\nKullenberg\n\nVerkst dir: Ake Kullenberg\nEtableringsår: 1940.\n\nCASSEL &amp; NYSTROM, AB\n\nPnr 601 03\n\nNorrköping 1, Linnég 17. Box 122.\nTel 011-1063 60. Bankgiro\n125-2048. Postgiro 177208-6\nVerksamhet: Verkstad för alla slag\nav tryckkärl, oljeavskiljare,\noljefilter o ventilcentraler i rostfri o\nsyrafast plåt, kantpressning,\nkoordinat- o kopiernibbling, utför\nsvetsningar med gas, el, punkt,\nsöm o argonsvets,\nargonbågsvets-ning av aluminium o\naluminiumlegeringar\n\nStyrelse: Dir M Sörstadius (ordf),\nfabr E Hagelin\nVerkst dir: Erik Hagelin\nEtableringsår: 1954.\n\nCASSEL AB, INGENIORS.\nFIRMAN YNGVE\n\nPnr 11231\n\nStockholm, Gambrinusg 2. Tel\n08-5080 39. Bankgiro 72-3706.\nPostgiro 251701. Tga Subercus\nVerksamhet: Konsult, export o\nimport\n\nAktiekapital: 20 000\nVerkst dir: Yngve Cassel\nEtableringsår: 1945.\n\nDJURSHOLMS TRÅ, AB\n\nPnr 182 51\n\nDjursholm 1, Ostbergav 20. Pack\n27. Tel 08-755 2850. Bankgiro\n734-0995. Postgiro 85670-8\nVerksamhet: Säljer trävaror o\nbyggnadsmaterial\nAntal anställda: 15\nÅrsomsättning: 4 000 000\nAktiekapital: 50 000\nVerkst dir: Bois Bergstam\nEtableringsår: 1920.\n\nTRUMLINGSAKTIEBOLAGET\n\nPnr 171 22\n\nSolna 1, Industriv 18. Box 1081.\nTel 08-82 68 00, 27 67 00. Bankgiro\n33-2059. Postgiro 4865. Tga\nTrum-ling\n\nVerksamhet: Representerar Almco\nSupersheen med försäljning av\ntrumlingsutrustningar o\ntrumlings-medel. (I Skandinavien).\nTillverkning av trumlingsutrustningar.\nUtför legotrumling\n(precisionstrum-ling). Representerar Abrasive\nDev-elopments Ltd med försäljning av\nblästringsutrustningar (Vaqua\nprocessen) o blästringsmedia\nVerkst dir: Ing Lennart Ahlquist\nEtableringsår: 1953.\n\nSTOREYS of LANCASTER, AB\n\nPnr 100 72\n\nStockholm 43, Box 43024.\nLilje-holmsv 10. Tel 08-18 90 20,18 90 30.\nBankgiro 570-09449. Postgiro\n31778-4. Tga Storolan. Telex 10038\nVerksamhet: Säljer plastfolier,\nväv-buren plast, vävplasttapeter m m\nVarunamn: Decorene, Stormur\nAntal anställda: 27\nÅrsomsättning: 7 000 000\nAktiekapital: 100 000\nVerkst dir: Sigurd Enocson\nEtableringsår: 1957.\n\nBEJOHNS\n\nPnr 502 30\n\nBorås. Mariedalsg 7. Tel\n033-12 17 83. Bankgiro 360-8866.\nPostgiro 216858-1\n\nVerksamhet: Engros i byxor, trikå,\nstrumpor, pyjamas, skjortor,\nvantar, sockor, sängkläder m m\nÅrsomsättning: 1000 000\nÄgare o chef: Bror Johansson\nEtableringsår: 1948.\n\nWITRECO PLAST AB\n\nPnr 330 23\n\nSmålandsstenar, Box 10. S\nNissa-stigen 8. Tel 0371-314 10.\nBankgiro 653-7526. Postgiro 465005-7.\nTelex 70172 WITRECO S\nVerksamhet Tillverkar o säljer\nsvetsade, sydda o vävda produkter\nav plastfolier o plastlaminat\nså-som duschförhängen o övriga\nbadrumstillbehör. uppblåsbara\nklädhängare o reklamartiklar, fodral,\nplagg för korttidsbruk o vävda\nplastmattor\nVarunamn: Witreco\nAntal anställda: 80\nÅrsomsättning: 7 700 000\nAktiekapital: 150 000\nVerkst din K-E Wikström\nFörsäljn-chef: Jan Åström\nEtableringsår: 1926.\n\nVITSANDS KONSTSTENS.\nGJUTERI\n\nPnr 28010\n\nSösdala. Box 51. Tel 0451-607 85.\nBankgiro 286-3835. Postgiro\n483147-5\n\nVerksamhet: Tillverkar\nprefabricerade villayttertrappor samt\ndiverse betongprodukter\nAntal anställda: 18\nÅrsomsättning: 1500 000\nAktiekapital: 15 000\nChef: Fabr Vittorio Peruzzaro\nEtableringsån 1957.\n\nSIGNALTJÄNST ALARM AB\n\nPnr 17159\n\nSolna, Infanterig 5. Tel\n08-730 04 55. Bankgiro 233-9596.\nPostgiro 458710-1\n\nVerksamhet: Säkerhets- o alarm-\n\nsystem för banker, industri, handel,\n\nkontor o villor\n\nAntal anställda: 12\n\nAktiekapital: 5 000\n\nVerkst dir: Sune Eckerstrand\n\nEtableringsår 1957.",
    "structured": {
        "1": {
            "company_name": "CENTRALTRYCKERIET",
            "pnr": "902 44",
            "address": "Umeå, Storg 113",
            "phone_number": "090-110618",
            "bank_details": {
                "bankgiro": "75-9819",
                "postgiro": "296025"
            },
            "activity": "Civiltryckeri, bok- o offsettryck, bokbinderi",
            "establishment_year": 1934
        },
        "2": {
            "company_name": "CENTRAL-TRYCKERIET M SKYMAN",
            "pnr": "44100",
            "address": "Alingsås, Plang 20",
            "phone_number": "0322-107 99",
            "bank_details": {
                "bankgiro": "889-6656",
                "postgiro": "81299-0"
            },
            "activity": "Affärs-, industri-, blankett- o reklamtryck",
            "annual_turnover": 170000,
            "key_personnel": [
                {
                    "name": "M Skyman",
                    "position": "Boktr"
                }
            ],
            "establishment_year": 1930
        },
        "3": {
            "company_name": "CENTRALTRYCKERIET, ÅKE SVENSON AB",
            "pnr": "50105",
            "address": "Borås 1, Box 288, Druveforsv 8",
            "phone_number": "033-10 0260",
            "bank_details": {
                "bankgiro": "839-1542",
                "postgiro": "31183-7"
            },
            "activity": "Bok- o offsettryck",
            "employees": 25,
            "capital": 50000,
            "key_personnel": [
                {
                    "name": "Åke Svenson",
                    "position": "Verkst dir"
                }
            ],
            "establishment_year": 1919
        },
        "4": {
            "company_name": "CENTRALTRYCKERIETS STÄMPELFABRIK AB",
            "pnr": "105 31",
            "address": "Stockholm, Klara Vattugränd 1",
            "phone_number": "22 95 00, riks 08-22 95 40",
            "activity": "Stämplar o tillbehör",
            "key_personnel": [
                {
                    "name": "Sture Nyberg",
                    "position": "Chef"
                }
            ]
        },
        "5": {
            "company_name": "CENTRALVÄRME, AB",
            "pnr": "261 33",
            "address": "Landskrona, Lundåkrag 17",
            "phone_number": "0418-165 60",
            "postgiro": "30435-2",
            "activity": "Värme-, vatten- o avlopp, installationer",
            "employees": 28,
            "annual_turnover": 3000000,
            "capital": 45000,
            "key_personnel": [
                {
                    "name": "Ing Malte Persson",
                    "position": "Verkst dir"
                }
            ],
            "establishment_year": 1949
        },
        "6": {
            "company_name": "RIDDARKONTOR, AB",
            "pnr": "104 40",
            "address": "Stockholm, Box 14037, Riddarg 17",
            "phone_number": "08-22 3120",
            "bank_details": {
                "bankgiro": "235-2763",
                "postgiro": "550145-7"
            },
            "activity": "Uthyr möblerade kontorslokaler med service",
            "employees": 5,
            "annual_turnover": 350000,
            "capital": 49500,
            "key_personnel": [
                {
                    "name": "Tage örtegren",
                    "position": "Verkst dir"
                },
                {
                    "name": "Bertil Asplund",
                    "position": "Ing"
                }
            ],
            "establishment_year": 1964
        },
        "7": {
            "company_name": "RIEBER & SON SVENSKA AB",
            "pnr": "422 46",
            "address": "Hisings Backa, Importg 14",
            "phone_number": "031-52 0160",
            "bank_details": {
                "bankgiro": "45-5419",
                "postgiro": "627701"
            },
            "activity": "Rikett golvbeläggningar, plattor, plastfiltmattor, plastmattor, nålfiltmattor, mjuka mattor, profiler o duschmellanväggar",
            "key_personnel": [
                {
                    "name": "Civilekonom Jan-Erik Erichsen",
                    "position": "Chef"
                }
            ],
            "establishment_year": 1963
        },
        "8": {
            "company_name": "RIETZ PAPPERS AB",
            "pnr": "11135",
            "address": "Stockholm, Kungsg 18",
            "phone_number": "08-23 0150",
            "bank_details": {
                "bankgiro": "626-7454",
                "postgiro": "1820-0"
            },
            "activity": "Säljer papper, kontors-o ritmateriel",
            "employees": 12,
            "annual_turnover": 3500000,
            "capital": 75000,
            "key_personnel": [
                {
                    "name": "Gösta Fürstenbach",
                    "position": "Verkst dir"
                }
            ],
            "establishment_year": 1926
        },
        "9": {
            "company_name": "KUM",
            "address": "Örebro, Nygatan 34-36",
            "phone_number": "019-1197 65",
            "employees": 2000,
            "annual_turnover": 225000000,
            "capital": 1200000,
            "key_personnel": [
                {
                    "name": "civiling Yngve Kullenberg",
                    "position": "ordf"
                },
                {
                    "name": "dir Frans Persson",
                    "position": "dir"
                },
                {
                    "name": "prof Börje Kullenberg",
                    "position": "prof"
                },
                {
                    "name": "dir Ake Kullenberg",
                    "position": "Verkst dir"
                }
            ],
            "establishment_year": 1940
        },
        "10": {
            "company_name": "CASSEL & NYSTROM, AB",
            "pnr": "601 03",
            "address": "Norrköping 1, Linnég 17, Box 122",
            "phone_number": "011-1063 60",
            "bank_details": {
                "bankgiro": "125-2048",
                "postgiro": "177208-6"
            },
            "activity": "Verkstad för alla slag av tryckkärl, oljeavskiljare, oljefilter o ventilcentraler i rostfri o syrafast plåt, kantpressning, koordinat- o kopiernibbling, utför svetsningar med gas, el, punkt, söm o argonsvets, argonbågsvets-ning av aluminium o aluminiumlegeringar",
            "key_personnel": [
                {
                    "name": "M Sörstadius",
                    "position": "Dir (ordf)"
                },
                {
                    "name": "E Hagelin",
                    "position": "fabr"
                },
                {
                    "name": "Erik Hagelin",
                    "position": "Verkst dir"
                }
            ],
            "establishment_year": 1954
        },
        "11": {
            "company_name": "CASSEL AB, INGENIORS. FIRMAN YNGVE",
            "pnr": "11231",
            "address": "Stockholm, Gambrinusg 2",
            "phone_number": "08-5080 39",
            "bank_details": {
                "bankgiro": "72-3706",
                "postgiro": "251701"
            },
            "activity": "Konsult, export o import",
            "capital": 20000,
            "key_personnel": [
                {
                    "name": "Yngve Cassel",
                    "position": "Verkst dir"
                }
            ],
            "establishment_year": 1945
        },
        "12": {
            "company_name": "DJURSHOLMS TRÅ, AB",
            "pnr": "182 51",
            "address": "Djursholm 1, Ostbergav 20, Pack 27",
            "phone_number": "08-755 2850",
            "bank_details": {
                "bankgiro": "734-0995",
                "postgiro": "85670-8"
            },
            "activity": "Säljer trävaror o byggnadsmaterial",
            "employees": 15,
            "annual_turnover": 4000000,
            "capital": 50000,
            "key_personnel": [
                {
                    "name": "Bois Bergstam",
                    "position": "Verkst dir"
                }
            ],
            "establishment_year": 1920
        },
        "13": {
            "company_name": "TRUMLINGSAKTIEBOLAGET",
            "pnr": "171 22",
            "address": "Solna 1, Industriv 18, Box 1081",
            "phone_number": "08-82 68 00, 27 67 00",
            "bank_details": {
                "bankgiro": "33-2059",
                "postgiro": "4865"
            },
            "activity": "Representerar Almco Supersheen med försäljning av trumlingsutrustningar o trumlingsmedel. (I Skandinavien). Tillverkning av trumlingsutrustningar. Utför legotrumling (precisionstrum-ling). Representerar Abrasive Dev-elopments Ltd med försäljning av blästringsutrustningar (Vaqua processen) o blästringsmedia",
            "key_personnel": [
                {
                    "name": "Ing Lennart Ahlquist",
                    "position": "Verkst dir"
                }
            ],
            "establishment_year": 1953
        },
        "14": {
            "company_name": "STOREYS of LANCASTER, AB",
            "pnr": "100 72",
            "address": "Stockholm 43, Box 43024, Liljeholmsv 10",
            "phone_number": "08-18 90 20,18 90 30",
            "bank_details": {
                "bankgiro": "570-09449",
                "postgiro": "31778-4"
            },
            "activity": "Säljer plastfolier, väv-buren plast, vävplasttapeter m m",
            "key_personnel": [
                {
                    "name": "Sigurd Enocson",
                    "position": "Verkst dir"
                }
            ],
            "establishment_year": 1957
        },
        "15": {
            "company_name": "BEJOHNS",
            "pnr": "502 30",
            "address": "Borås, Mariedalsg 7",
            "phone_number": "033-12 17 83",
            "bank_details": {
                "bankgiro": "360-8866",
                "postgiro": "216858-1"
            },
            "activity": "Engros i byxor, trikå, strumpor, pyjamas, skjortor, vantar, sockor, sängkläder m m",
            "annual_turnover": 1000000,
            "key_personnel": [
                {
                    "name": "Bror Johansson",
                    "position": "Ägare o chef"
                }
            ],
            "establishment_year": 1948
        },
        "16": {
            "company_name": "WITRECO PLAST AB",
            "pnr": "330 23",
            "address": "Smålandsstenar, Box 10, S Nissastigen 8",
            "phone_number": "0371-314 10",
            "bank_details": {
                "bankgiro": "653-7526",
                "postgiro": "465005-7"
            },
            "activity": "Tillverkar o säljer svetsade, sydda o vävda produkter av plastfolier o plastlaminat så-som duschförhängen o övriga badrumstillbehör. uppblåsbara klädhängare o reklamartiklar, fodral, plagg för korttidsbruk o vävda plastmattor",
            "varunamn": "Witreco",
            "employees": 80,
            "annual_turnover": 7700000,
            "capital": 150000,
            "key_personnel": [
                {
                    "name": "K-E Wikström",
                    "position": "Verkst din"
                },
                {
                    "name": "Jan Åström",
                    "position": "Försäljn-chef"
                }
            ],
            "establishment_year": 1926
        },
        "17": {
            "company_name": "VITSANDS KONSTSTENS. GJUTERI",
            "pnr": "28010",
            "address": "Sösdala, Box 51",
            "phone_number": "0451-607 85",
            "bank_details": {
                "bankgiro": "286-3835",
                "postgiro": "483147-5"
            },
            "activity": "Tillverkar prefabricerade villayttertrappor samt diverse betongprodukter",
            "employees": 18,
            "annual_turnover": 1500000,
            "capital": 15000,
            "key_personnel": [
                {
                    "name": "Fabr Vittorio Peruzzaro",
                    "position": "Chef"
                }
            ],
            "establishment_year": 1957
        },
        "18": {
            "company_name": "SIGNALTJÄNST ALARM AB",
            "pnr": "17159",
            "address": "Solna, Infanterig 5",
            "phone_number": "08-730 04 55",
            "bank_details": {
                "bankgiro": "233-9596",
                "postgiro": "458710-1"
            },
            "activity": "Säkerhets- o alarm-system för banker, industri, handel, kontor o villor",
            "employees": 12,
            "capital": 5000,
            "key_personnel": [
                {
                    "name": "Sune Eckerstrand",
                    "position": "Verkst dir"
                }
            ],
            "establishment_year": 1957
        }
    }
}