{
    "original": "ENGMO, AB\n\nPnr 161 70\n\nBromma, Karlsbodav 14. Tel 08-\n\n2901 65. Bankgiro 588-9381.\nPostgiro 459999-9\n\nVerksamhet: Tillverkar o säljer\nkuddar, täcken o madrasser\nAntal anställda: 20\nÅrsomsättning: 3 000 000\nAktiekapital: 50 000\nVerkst din Thomas Mortensen\nEtableringsån 1952.\n\nENGSON\n\nENGSTRÖM &amp; NILSON\nMASKIN AB\n\nPnr 113 84\n\nStockholm 6, Hälsingeg 43. Box\n6604. Tel 08-24 16 00. Telex 1544\nVerksamhet: Generalagent för\nCaterpillar Tractor Co\nAktiekapital: 18 000 000\nVerkst dir: Bo Abrahamsson.\n\nENGSTEDT AB, FRED\n\nPnr 211 24\n\nMalmö, Brännög 4. Tel\n040-93 7180. 93 75 80. Bankgiro\n640-3471. Postgiro 245557-4. Tga\nPredeng\n\nVerksamhet: Trädgårds- o\nanläggningsmaskiner samt\nväxtskydds-sprutor o högtryckspumpar\nAntal anställda: 15\nÅrsomsättning: 1500 000\nChef: Fred Engstedt\nEtableringsår: 1946.\n\nHYGROTESTER, AB\n\nPnr 703 62\n\nÖrebro, Järnvägsg 15. Tel\n019-1296 00. Bankgiro 614-5650.\nPostgiro 430801-1. Tga Hygrotester\nVerksamhet: Projekterar o säljer\nfukthalts- o ytviktsmätapparatur,\nregleringsutrustningar samt\nsorter-maskiner för pappers- o\ncéllulosa-industrin. Kontinuerliga\nfukthaltsmätare för sågade trävaror.\nInfra-röda temperaturmätare.\nAntistatikut-rustningar för borttagning av\nstatisk elektricitet. Serviceverksamhet\nVarunamn: Heimann, Laucks,\nLippke, Simco\nAntal anställda: 6\nAktiekapital: 100 000\nVerkst dir: Tor-Björn Källström\nEtableringsår: 1950.\n\nWENNERHOLMS MASKIN AB\n\nPnr 30241\n\nHalmstad, Industriv 8. Tel\n035-12 8153\n\nVerksamhet: Tillverkar\ncenterless-slipmaskiner o specialmaskiner\nÅrsomsättning: 320 000\nAktiekapital: 15 000\nVeikst dir: Ing S Wennerholm\nEtableringsår: 1966.\n\nv adst e na/got a pump ab\n\nPnr 592 00\n\nVadstena, Skänningev. Tel\n0143-115 20. Bankgiro 169-7382. Post\ngiro 352506-0. Tga\nVadstenaverken\n\nVerksamhet: Tillverkar pumpar\nAvdelningskontor: Stockholm,\nGöteborg, Malmö, Sundsvall\nAntal anställda: 105\nAktiekapital: 400 000\nVerkst dir: Lars Hultman\nEtableringsår: 1946.\n\nLÖDÖSE VARF, AB\n\nPnr 460 10\n\nLödöse. Tel 0520-604 00. Bankgiro\n54-1141. Postgiro 21497.\nTelex 2428 OTERED S\nVerksamhet: Varvsrörelse. Utför\ngrovplåts- o maskinarbeten samt\nreparationer av fartyg\nAntal anställda: 230\nÅrsomsättning: 30 000 000\nAktiekapital: 702 000\nVerkst dir: Gösta Johansson\nEtableringsår: 1899.\n\nSÖDRA BRÄDGÅRDEN AB\n\nPnr 701 04\n\nÖrebro 1, Box 303. Tel\n019-160010. Postgiro 28379\nVerksamhet: Säljer trävaror o\nbyggmaterial\nAktiekapital: 100 000\nVerkst dir: Håkan Carlestam\nEtableringsår: 1926.\n\nSÖDRA MEKANISKA\nVERKSTADEN AB\n\nPnr 260 33\n\nPåarp, Industriområdet. Tel\n042-274 10. Bankgiro 445-3882.\nPost-giro 591980-8\n\nVerksamhet: Plåtslageri,\nmaskinarbeten, ytbehandling. Tillverkar\navfallscontainers,\ntryckerimaskiner o förpackningsmaskiner\nAntal anställda: 75\nÅrsomsättning: 4 400 000\nAktiekapital: 112 000\nVerkst dir: Malte Lundgren\nEtableringsår: 1960.\n\nTORNEDALENS\nBYGGNADS AB TBA\n\nPnr 950 90\n\nHedenäset, Box 7. Tel 0927-30032,\n300 80. Bankgiro 75-8149. Postgiro\n483777-9. Tga TBA\nVerksamhet: Uppför husbyggnader.\nUtför målnings- o VVS-arbeten\nAntal anställda: 50\nÅrsomsättning: 8 000 000\nAktiekapital: 96 000\nVerkst dir: G Sigurd Höjvall\nEtableringsår: 1958.\n\nHEBA PLAST, AB\n\nPnr 599 00\n\nOdeshög, Box 99. Tel 0144-11111.\nBankgiro 230-9672. Postgiro\n99542-3\n\nVerksamhet: Plastsvetsning.\nPlasttyg, plymåer mm\nAntal anstäUda: 60\nÅrsomsättning: 5 000 000\nAktiekapital: 20 000\nVerkst dir: Rolf Harryson\nFörsäljn-chef: Göran Svenson\nEtableringsår: 1948.\n\nparfymeri trading ab\n\nPnr 20123\n\nMalmö 1, Borrg 5. Box 320. Tel\n040-93 6200. Bankgiro 64-1455.\nPostgiro 435900. Tga Eson\nVerksamhet: Generalagenturer.\nKem-tekn o kosmetiska produkter\nAntal anställda: 80\nAktiekapital: 300000\nVeikst dir: Sven H Delbanco\nEtableringsår: 1954.\n\nparfymerier\n\nse i övrigt resp namn.\n\npark avenue hotel ab\n\nPnr 40016\n\nGöteborg 53, Kungsportsavenyn\n36-38. Box 53233. Tel 031-17 65 20.\nBankgiro 50-0798. Postgiro 420150.\nTga Parkavenue. Telex 2320\nVerksamhet: Hotell med 210 rum.\nRestauranter: Lorensberg, Belle\nAvenue, Tidbit. Festvåningar för\n10-600 personer. Konferens- o\nsammanträdesrum\nAntal anställda: 400\nÅrsomsättning: 20 000000\nAktiekapital: 5 200 000\nStyrelse: Dir Erik Wijk (ordf), dir\nK R Bökman, dir Per Carlsson,\ndir Gunnar Engellau, dir Orvar\nJanson, ing Lennart Ström\nVerkst dir: Per Persson\nDir K E Åberg\nEkonomichef: Stig Johansson\n\nReceptionschef: Frk G Söderberg\nProduktionschef: Allan Hult\nEtableringsår: 1950.\n\nMOL\n\nVerksamhet: Formpressning i\nglas-fiberarmerad polyester,\nkokkärlsbeslag i bakelit. Formsprutning i\ntermoplast o bakelit\nAktiekapital: 5 000\nVerkst dir: Nils Karlsson\nEtableringsàr: 1967.\n\nMÄHLQVISTS RDR AB, A\n\nPnr 643 00\n\nVingåker, Hantverksg 9- Tel\n0151-120 30. Bankgiro 624-8173.\nPostgiro 266236-9\n\nVerksamhet: värme-,\nventilalions-o sanitetsanläggningar\nAntal anställda: 40\nÅrsomsättning: 5 500 000\nAktiekapital: 75 000\nVerkst dir: Artur Mählqvist\nEtableringsàr: 1943.\n\nMÄRSTA FABRIKS.\nPRODUKTER, AB\n\nPnr 112 26\n\nStockholm, Flemingg 17. Tel\n08-511100, 51 54 00. Bankgiro 23-5245.\nPostgiro 333283\n\nVeiksamhet: Säljer byggvaror samt\npersonalvagnar o -bodar\nVerkst dir: Sven Axelsson\nEtableringsàr: 1948.\n\nMÄSTERBAGARNA AB\n\nPnr 831 00\n\nÖstersund, Midgårdsg 2. Tel\n063-172 20. Bankgiro 777-8384.\nPostgiro 10263-2\nVeiksamhet: Bageri\nAntal anställda: 200\nÅrsomsättning: 20 000 000\nAktiekapital: 350 000\nVerkst dir: Lars Nystedt\nEtableringsàr: 1951.\n\nMÖBELFABRIKER\n\nse resp namn.\n\nMÖBELINDUSTRIERNA I\nTIERP AB\n\nPnr 815 01\n\nTierp 1, Box 26. Greveg 19. Tel\n0293-114 90. Bankgiro 236-2192.\nPostgiro 32721-3\n\nVeiksamhet: Tillverkar\nkontorsmöbler, specialsnickerier, lådor\nFörsäljningskontor o utställning:\n171 58 Solna, Ängkärrsg 14. Tel\n08-7300390\n\nLådfabrik: 810 61 Månkarbo. Tel\n0293-510 1 5\nVarunamn: Mitab\nAntal anställda: 80\nÅrsomsättning: 5 000 000\nAktiekapital: 100 000\nVerkst dir: Lasse Pettersson\nEtableringsàr 1942.",
    "structured": {
        "1": {
            "company_name": "ENGMO, AB",
            "pnr": "161 70",
            "address": "Bromma, Karlsbodav 14",
            "phone_number": "08-2901 65",
            "bank_details": {
                "bankgiro": "588-9381",
                "postgiro": "459999-9"
            },
            "activity": "Tillverkar o säljer kuddar, täcken o madrasser",
            "employees": 20,
            "annual_turnover": 3000000,
            "capital": 50000,
            "key_personnel": [
                {
                    "name": "Verkst din Thomas Mortensen",
                    "position": "Unknown"
                }
            ],
            "establishment_year": 1952
        },
        "2": {
            "company_name": "ENGSON",
            "address": "Unknown",
            "phone_number": "Unknown",
            "activity": "Unknown",
            "capital": 18000000,
            "key_personnel": [
                {
                    "name": "Verkst dir: Bo Abrahamsson",
                    "position": "Unknown"
                }
            ],
            "establishment_year": "Unknown"
        },
        "3": {
            "company_name": "ENGSTEDT AB, FRED",
            "pnr": "211 24",
            "address": "Malmö, Brännög 4",
            "phone_number": "040-93 7180, 93 75 80",
            "bank_details": {
                "bankgiro": "640-3471",
                "postgiro": "245557-4"
            },
            "activity": "Trädgårds- o anläggningsmaskiner samt växtskydds-sprutor o högtryckspumpar",
            "employees": 15,
            "annual_turnover": 1500000,
            "key_personnel": [
                {
                    "name": "Chef: Fred Engstedt",
                    "position": "Unknown"
                }
            ],
            "establishment_year": 1946
        },
        "4": {
            "company_name": "HYGROTESTER, AB",
            "pnr": "703 62",
            "address": "Örebro, Järnvägsg 15",
            "phone_number": "019-1296 00",
            "bank_details": {
                "bankgiro": "614-5650",
                "postgiro": "430801-1"
            },
            "activity": "Projekterar o säljer fukthalts- o ytviktsmätapparatur, regleringsutrustningar samt sorter-maskiner för pappers- o céllulosa-industrin. Kontinuerliga fukthaltsmätare för sågade trävaror. Infra-röda temperaturmätare. Antistatikut-rustningar för borttagning av statisk elektricitet. Serviceverksamhet",
            "employees": 6,
            "annual_turnover": 100000,
            "capital": 100000,
            "key_personnel": [
                {
                    "name": "Verkst dir: Tor-Björn Källström",
                    "position": "Unknown"
                }
            ],
            "establishment_year": 1950
        },
        "5": {
            "company_name": "WENNERHOLMS MASKIN AB",
            "pnr": "30241",
            "address": "Halmstad, Industriv 8",
            "phone_number": "035-12 8153",
            "activity": "Tillverkar centerless-slipmaskiner o specialmaskiner",
            "annual_turnover": 320000,
            "capital": 15000,
            "key_personnel": [
                {
                    "name": "Veikst dir: Ing S Wennerholm",
                    "position": "Unknown"
                }
            ],
            "establishment_year": 1966
        },
        "6": {
            "company_name": "Vadstena/gota pump ab",
            "pnr": "592 00",
            "address": "Vadstena, Skänningev",
            "phone_number": "0143-115 20",
            "bank_details": {
                "bankgiro": "169-7382",
                "postgiro": "352506-0"
            },
            "activity": "Tillverkar pumpar",
            "employees": 105,
            "capital": 400000,
            "key_personnel": [
                {
                    "name": "Verkst dir: Lars Hultman",
                    "position": "Unknown"
                }
            ],
            "establishment_year": 1946
        },
        "7": {
            "company_name": "LÖDÖSE VARF, AB",
            "pnr": "460 10",
            "address": "Lödöse",
            "phone_number": "0520-604 00",
            "bank_details": {
                "bankgiro": "54-1141",
                "postgiro": "21497"
            },
            "activity": "Varvsrörelse. Utför grovplåts- o maskinarbeten samt reparationer av fartyg",
            "employees": 230,
            "annual_turnover": 30000000,
            "capital": 702000,
            "key_personnel": [
                {
                    "name": "Verkst dir: Gösta Johansson",
                    "position": "Unknown"
                }
            ],
            "establishment_year": 1899
        },
        "8": {
            "company_name": "SÖDRA BRÄDGÅRDEN AB",
            "pnr": "701 04",
            "address": "Örebro 1, Box 303",
            "phone_number": "019-160010",
            "postgiro": "28379",
            "activity": "Säljer trävaror o byggmaterial",
            "capital": 100000,
            "key_personnel": [
                {
                    "name": "Verkst dir: Håkan Carlestam",
                    "position": "Unknown"
                }
            ],
            "establishment_year": 1926
        },
        "9": {
            "company_name": "SÖDRA MEKANISKA VERKSTADEN AB",
            "pnr": "260 33",
            "address": "Påarp, Industriområdet",
            "phone_number": "042-274 10",
            "bank_details": {
                "bankgiro": "445-3882",
                "postgiro": "591980-8"
            },
            "activity": "Plåtslageri, maskinarbeten, ytbehandling. Tillverkar avfallscontainers, tryckerimaskiner o förpackningsmaskiner",
            "employees": 75,
            "annual_turnover": 4400000,
            "capital": 112000,
            "key_personnel": [
                {
                    "name": "Verkst dir: Malte Lundgren",
                    "position": "Unknown"
                }
            ],
            "establishment_year": 1960
        },
        "10": {
            "company_name": "TORNEDALENS BYGGNADS AB TBA",
            "pnr": "950 90",
            "address": "Hedenäset, Box 7",
            "phone_number": "0927-30032, 300 80",
            "bank_details": {
                "bankgiro": "75-8149",
                "postgiro": "483777-9"
            },
            "activity": "Uppför husbyggnader. Utför målnings- o VVS-arbeten",
            "employees": 50,
            "annual_turnover": 8000000,
            "capital": 96000,
            "key_personnel": [
                {
                    "name": "Verkst dir: G Sigurd Höjvall",
                    "position": "Unknown"
                }
            ],
            "establishment_year": 1958
        },
        "11": {
            "company_name": "HEBA PLAST, AB",
            "pnr": "599 00",
            "address": "Odeshög, Box 99",
            "phone_number": "0144-11111",
            "bank_details": {
                "bankgiro": "230-9672",
                "postgiro": "99542-3"
            },
            "activity": "Plastsvetsning. Plasttyg, plymåer mm",
            "employees": 60,
            "annual_turnover": 5000000,
            "capital": 20000,
            "key_personnel": [
                {
                    "name": "Verkst dir: Rolf Harryson",
                    "position": "Unknown"
                },
                {
                    "name": "Försäljn-chef: Göran Svenson",
                    "position": "Unknown"
                }
            ],
            "establishment_year": 1948
        },
        "12": {
            "company_name": "parfymeri trading ab",
            "pnr": "20123",
            "address": "Malmö 1, Borrg 5",
            "phone_number": "040-93 6200",
            "bank_details": {
                "bankgiro": "64-1455",
                "postgiro": "435900"
            },
            "activity": "Generalagenturer. Kem-tekn o kosmetiska produkter",
            "employees": 80,
            "capital": 300000,
            "key_personnel": [
                {
                    "name": "Verkst dir: Sven H Delbanco",
                    "position": "Unknown"
                }
            ],
            "establishment_year": 1954
        },
        "13": {
            "company_name": "park avenue hotel ab",
            "pnr": "40016",
            "address": "Göteborg 53, Kungsportsavenyn 36-38",
            "phone_number": "031-17 65 20",
            "bank_details": {
                "bankgiro": "50-0798",
                "postgiro": "420150"
            },
            "activity": "Hotell med 210 rum. Restauranter: Lorensberg, Belle Avenue, Tidbit. Festvåningar för 10-600 personer. Konferens- o sammanträdesrum",
            "employees": 400,
            "annual_turnover": 20000000,
            "capital": 5200000,
            "key_personnel": [
                {
                    "name": "Styrelse: Dir Erik Wijk",
                    "position": "ordf"
                },
                {
                    "name": "Dir K R Bökman",
                    "position": "Unknown"
                },
                {
                    "name": "Dir Per Carlsson",
                    "position": "Unknown"
                },
                {
                    "name": "Dir Gunnar Engellau",
                    "position": "Unknown"
                },
                {
                    "name": "Dir Orvar Janson",
                    "position": "Unknown"
                },
                {
                    "name": "ing Lennart Ström",
                    "position": "Unknown"
                },
                {
                    "name": "Verkst dir: Per Persson",
                    "position": "Unknown"
                },
                {
                    "name": "Dir K E Åberg",
                    "position": "Unknown"
                },
                {
                    "name": "Ekonomichef: Stig Johansson",
                    "position": "Unknown"
                },
                {
                    "name": "Receptionschef: Frk G Söderberg",
                    "position": "Unknown"
                },
                {
                    "name": "Produktionschef: Allan Hult",
                    "position": "Unknown"
                }
            ],
            "establishment_year": 1950
        },
        "14": {
            "company_name": "MOL",
            "activity": "Formpressning i glas-fiberarmerad polyester, kokkärlsbeslag i bakelit. Formsprutning i termoplast o bakelit",
            "capital": 5000,
            "key_personnel": [
                {
                    "name": "Verkst dir: Nils Karlsson",
                    "position": "Unknown"
                }
            ],
            "establishment_year": 1967
        },
        "15": {
            "company_name": "MÄHLQVISTS RDR AB, A",
            "pnr": "643 00",
            "address": "Vingåker, Hantverksg 9",
            "phone_number": "0151-120 30",
            "bank_details": {
                "bankgiro": "624-8173",
                "postgiro": "266236-9"
            },
            "activity": "värme-, ventilalions-o sanitetsanläggningar",
            "employees": 40,
            "annual_turnover": 5500000,
            "capital": 75000,
            "key_personnel": [
                {
                    "name": "Verkst dir: Artur Mählqvist",
                    "position": "Unknown"
                }
            ],
            "establishment_year": 1943
        },
        "16": {
            "company_name": "MÄRSTA FABRIKS. PRODUKTER, AB",
            "pnr": "112 26",
            "address": "Stockholm, Flemingg 17",
            "phone_number": "08-511100, 51 54 00",
            "bank_details": {
                "bankgiro": "23-5245",
                "postgiro": "333283"
            },
            "activity": "Säljer byggvaror samt personalvagnar o -bodar",
            "key_personnel": [
                {
                    "name": "Verkst dir: Sven Axelsson",
                    "position": "Unknown"
                }
            ],
            "establishment_year": 1948
        },
        "17": {
            "company_name": "MÄSTERBAGARNA AB",
            "pnr": "831 00",
            "address": "Östersund, Midgårdsg 2",
            "phone_number": "063-172 20",
            "bank_details": {
                "bankgiro": "777-8384",
                "postgiro": "10263-2"
            },
            "activity": "Bageri",
            "employees": 200,
            "annual_turnover": 20000000,
            "capital": 350000,
            "key_personnel": [
                {
                    "name": "Verkst dir: Lars Nystedt",
                    "position": "Unknown"
                }
            ],
            "establishment_year": 1951
        },
        "18": {
            "company_name": "MÖBELINDUSTRIERNA I TIERP AB",
            "pnr": "815 01",
            "address": "Tierp 1, Box 26, Greveg 19",
            "phone_number": "0293-114 90",
            "bank_details": {
                "bankgiro": "236-2192",
                "postgiro": "32721-3"
            },
            "activity": "Tillverkar kontorsmöbler, specialsnickerier, lådor",
            "employees": 80,
            "annual_turnover": 5000000,
            "capital": 100000,
            "key_personnel": [
                {
                    "name": "Verkst dir: Lasse Pettersson",
                    "position": "Unknown"
                }
            ],
            "establishment_year": 1942
        }
    }
}