{
    "original": "IND\n\nVaksamhet: All slags gravyr-,\nstilstämplar, skyltar m m\nAntal anställda: 12\nAktiekapital: 80000\nStyrelse: Ing B Kjellkvist, fru\nL Wadsten\n\nVeikst dir Einar Kjellkvist\nEtableringsår: 1919\nOmbildat till aktiebolag 1945.\n\nINDUSTRIGUMMI, AB\n\nPnr 104 60\n\nStockholm, Hammarby Pabriksv\n43 B. Tel 08-24 49 10. Bankgiro\n171-9079. Postgiro 353461-7\nVerksamhet: Tillverkar formgjorda\ngummidetaljer m m\nAntal anställda: 70\nÅrsomsättning: 5 000000\nAktiekapital: 10 000\nVeikst dir: K E Eriksson\nEtableringsår: 1948.\n\nGUSTAFSON, AB A C\n\nPnr 502 31\n\nBorås, Skolg 30. Tel 033-10 0140.\nPostgiro 53025-3. Tga\nMachine-gustav. Telex 36114 ACG S\nVerksamhet: Tillskärnings-,\nläggnings- o symaskiner för\nkonfektions-, trikå- o skoindustrin\nFilialer o ombud: Stockholm. Tel\n08-45 1150\n\nFalköping. Tel 0515-182 25\nGöteborg. Tel 031-1124 83\nMalmö. Tel 040-9274 10\nUlricehamn. Tel 0321-106 87\nVäxjö. Tel 0470-22150\nAntal anställda: 35\nÅrsomsättning: 7 500 000\nAktiekapital: 100 000\nStyrelse: K G Marcus, Anna-Lisa\nWallii\\, R Westerlind, K Adolfsson\nVerkst dir: R Westerlind\nEtableringsår: 1921\nOmbildat till aktiebolag 1931.\n\nGUSTAFSSON, FABRIKS AB\nANDERS\n\nPnr 543 01\n\nTibro 1, Fabriksg 3. Box 122. Tel\n0504-116 65. Bankgiro 22-1414.\nPostgiro 416300\n\nVerksamhet: Tillverkar\ninrednings-snickerier till varuhus, skolor,\nsjukhus etc samt radio- o\nTV-möb-ler samt byggbara bokhyllor\nAntal anställda: 200\nÅrsomsättning: 15 000 000\nAktiekapital: 100000\nVerkst dir: Anders Gustafsson\nEtableringsår: 1943.\n\nGUSTAFSSONS\nSNICKERI-FABRIK, AB BENGT\n\nPnr 45047\n\nBovallstrand. Tel 0523-510 71,\n510 72. Bankgiro 544-2090.\nPostgiro 275956-1\n\nVerksamhet: Tillverkar fönster,\nytterdörrar av tryckimpregnerad furu\nAntal anställda: 40\nÅrsomsättning: 3 000 000\nAktiekapital: 30 000\nVeikst dir: Bengt Gustafsson\nEtableringsår: 1943.\n\nGUSTAFSONS GRAVYR. &amp;\nMEK VERKSTAD, AB E\n\nPnr 104 3 5\n\nStockholm 23, Ynglingag 16. Box\n23001. Tel 08-34 0270. Bankgiro\n160-2291. Postgiro 4016-2\nVerksamhet: Handgravyr,\nmaskingravyr. Tillverkar bakelit-,\nplast-o pressgjutningsverktyg, klipp- o\nbockverktyg. Silkscreentryck\nAvdelningskontor: 11251 Stockholm,\nNordenflychtsv 64, Hornsberg. Tel\n08-54 08 45. Silksreen o gravyr\nVarunamn: Ge-Ge\nAntal anställda: 40\nÅrsomsättning: 3 000 000\nAktiekapital: 100 000\nVerkst dir: Per-Allan Gustafson\nEtableringsår: 1924\nOmbildat till aktiebolag 1962.\n\nGUSTAFSSON SKOFABRIK, E\n\nPnr 260 80\n\nMunkaljungby, Fabriksg 3. Box 8.\nTel 0431-307 80. Bankgiro\n294-1151. Postgiro 74752-7\nVerksamhet: Tillverkar sandaler o\nbarn- o herrskor av fritidstyp\nAntal anställda: 23\nÅrsomsättning: 1600 000\nChef: Fabr Egon Gustafsson\nEtableringsår: 1922.\n\nGUSTAFSSONS BYGGNADS\nAB, G ALBERT\n\nPnr 411 08\n\nGöteborg C, Stora Nyg 15. Tel\n031-171190. Tga Galbhus\nVeiksamhet: Byggnadsentreprenörer\nAntal anställda: 200\nÅrsomsättning: 15 000 000\nAktiekapital: 100 000\nEtableringsår: 1916.\n\nGUSTAFSONS\nEMBALLAGE-FABRIK, GIDEON\n\nPnr 136 21\n\nHanden 1, Dalarö v 1. Box 24. Tel\n08-77717 22. 777 67 49. Bankgiro\n332-2062. Postgiro 168599-9\nVerksamhet: Tillverkar\nplywood-emballage\nAntal anställda: 12\nÅrsomsättning: 850 000\nChef: Fru Annie Gustafson\nVerkmäst: Walle Averståhl\nEtableringsår: 1930.\n\nGUSTAVSSON,\nBYGGNADS-FIRMA GUNNAR OCH SVEN\n\nPnr 502 31\n\nBorås, Kungsg 50. Tel 033-10 23 50.\nBankgiro 843-4425. Postgiro\n140025-8\n\nVerksamhet: Bygger lasarett,\nskolor, bostäder, badhus, radhus m m\nAntal anställda: 200\nÅrsomsättning: 17 000 000\nChefer: Byggmäst Gunnar\nGustavsson, byggmäst Sven Gustavsson,\nbyggmäst Frithiof Gustavsson\nEtableringsår: 1938.\n\nGUSTAFSSONS MEK\nVERKSTAD AB, GÖSTA\n\nPnr 732 00\n\n.Arboga, Nor lund. Tel 0589-133 80.\nBankgiro 809-9228. Postgiro\n583606\n\nVerksamhet: Legotillverkar\nsvetsade maskindetaljer i plåt\nAntal anställda: 13\nÅrsomsättning: 1000 000\nAktiekapital: 6 000\nVerkst dir: Gösta Gustafsson\nEtableringsår: 1961.\n\nMcCann günther &amp; bäck ab\n\nPnr 103 64\n\nStockholm 3, Box 3225. Luntmakarg\n66. Tel 08-24 6080. Tga\nAdver-agency. Telex 10866\nVerksamhet: Fullservicebyrå inom\nreklam o marknadsföring\nAktiekapital: 800 000\nVerkst dir: Rolf Nedeby\nEtableringsår: 1944.\n\nmazetti ab\n\nPnr 200 42\n\nMalmö 7, Skolg 24. Fack. Tel\n040-706 10. Bankgiro 640-1418.\nPostgiro 10050-3. Tga Mazetti.\nTelex 32566\n\nVerksamhet: Tillverkar\ncacaopul-ver, choklad, konfektyrer,\nvanil-linsocker o bageriartiklar\nAntal anställda: 555\nÅrsomsättning: 85 000 000\nAktiekapital: 3 450 000\nVerkst dir: Töre Nordenskjöld\nEtableringsår: 1888.\n\nFÅGLAVIKS GLASBRUK, AB\n\nPnr 520 32\n\nFåglavik. Tel 0513-30130.\nBankgiro 42-0057. Postgiro 40718. Tga\nFåglavlksglas\n\nVerksamhet: Tekniskt glas o\nbelysningsglas\nAktiekapital: 600 000\nVerkst dir: Civiling A W Anderberg\nEtableringsår: 1874.\n\nTRILACK AB\n\nPnr 41509\n\nGöteborg, Dagjämningsg 9. Tel\n031^6 03 50. Bankgiro 85-2677.\nPostgiro 526655. Tga Trilack\nVerksamhet: Projekterar o\nlevererar kompletta\nlackeringsanläggningar\n\nChefer: Gösta Edström, Bengt\nMalke\n\nEtableringsår: 1964.\n\nEKS I SMALANDSSTENAR AB\n\nPnr 330 23\n\nSmålandsstenar, Ljungg. Box 96.\nTel 0371-31125. Bankgiro\n427-6093. Postgiro 325711-0. Tga Eks.\nTelex 70176\n\nVerksamhet: Tillverkar\nhushålls-vågar, barnvågskålar, personvågar.\nKonservöppnare\nAntal anställda: 65\nÅrsomsättning: 10 000000\nAktiekapital: 200000\nÄgare o chef: Pabr Karl Gustaf Ek\nEtableringsår: 1945.\n\nEKS SNICKERIFABRIK,\nAB ERIK\n\nPnr 211 52\n\nMalmö, Andrëelundsv 3 A. Tel\n040-72250. Bankgiro 26-4211.\nPostgiro 38974\n\nVerksamhet: Tillverkar fåtöljer,\nsoffor, bord o byråar\n.Antal anställda: 25\nÅrsomsättning: 3 000000\nAktiekapital: 33 000\nVerkst dir: Erik Ek\nEtableringsår: 1937.\n\nNORRVIKENS SKOFABRIK, AB\n\nPnr 450 90\n\nSkee, Box 65. Tel 0526-213 00.\nBankgiro 551-3619. Postgiro\n162667-0\n\nVerksamhet: Tillverkar rand- o\nbecksömsydda samt vulkaniserade\nsport- o arbetsskor\nAntal anställda: 55\nÅrsomsättning: 4 000 000\nAktiekapital: 90 000\nStyrelse: Dir Mats Johansson (ordf),\nkamrer Uno Bergenholtz,\nkommu-nalnämndsordf Kjell Mattson\nVerkst dir: Fabr Mats Johansson\nEtableringsår: 1942.\n\nBJORNVERKEN, AB\n\nPnr 41705\n\nGöteborg, Gamla Tuvev 7. Tel\n031-23 23 00, 2255 21\nVerksamhet: Tillverkar o säljer\nventilatorer o fläkthjul, slirskydd\nför traktorer samt växellådor\nVarunamn: Björnhjulet, Polem\nAntal anställda: 10\nÅrsomsättning: 1 300 000\nAktiekapital: 10 000\nVerkst dir: Ing Sven Janson\nEtableringsår 1944.\n\nVILETTE AB\n\nPnr 543 00\n\nTi bro, Skövdev. Tel 0504-123 65.\nBankgiro 746-9950. Postgiro\n350503-9. Telex 67046\nVerksamhet; Färdigprodukter av\npolyeter skum, madrasser, kuddar,\ndagbäddar, mjukmöbler, mjuka\nleksaker. svampar m m\nVarunamn: Vilette\nFilial: 265 02 Åstorp, Box 52. Tel\n042-543 70\nAktiekapital: 30 000\nVerkst dir: Tage Abrahamsson\nEtableringsår: 1964.\n\nWILHELMSSONS BOK.\nTRYCKERI, AB\n\nPnr 104 30\n\nStockholm 45, Tegnérg 37. Box\n45055. Tel 08-24 44 85. Bankgiro\n57-5739. Postgiro 156160\nVerksamhet: Boktryckeri o\nbokförlag\n\nAntal anställda: 20\nÅrsomsättning: 1702 000\nAktiekapital: 75 000\nVerkst dir: Algot Lindén.\n\nVILHELMSON &amp; CO AB\n\nPnr 104 22\n\nStockholm 22, Box 22026. Tel\n08-5201 10. Bankgiro 560-5571.\nPostgiro 2325-9. Tga Vesonco\nVerksamhet; Trädgårdsmaskiner o\nuniversal traktorer\nAntal anställda: 66\nÅrsomsättning: 9 800 000\nAktiekapital: 300 000\nVerkst dir: Einar Vilhelmson\nEtableringsår: 1929.\n\nWILHELMSSON BRAND.\nREDSKAP, EWERT\n\nPnr 15014\n\nVagnhärad, Gamla Prostgården. Tel\n0156-100 29. 104 29. Bankgiro\n624-0113. Postgiro 137018-8. Tga\nWilhelmsson. Telex 10275 FIRE S\nVerksamhet: Brandredskap,\nbrand-släckningsapparater o -pumpar m m\nÄgare o chef: f V konsul Ewert\nWilhelmsson\nEtableringsår: 1951.\n\nWILKENSON\nHANDSK-MAKARN AB\n\nPnr 70104\n\nÖfre bro 1, Box 283. Klerkg 16. Tel\n019-12 41 15. Bankgiro 633-1466.\n\nPostgiro 161911-3\nVerksamhet: Tillverkar o säljer\nhandskar o väskor. 28 butiker\nAntal anställda: 130\nÅrsomsättning: 8 000 000\nAktiekapital: 450 000\nVerkst din S Forsberg\nEtableringsår: 1940.\n\nWILLI AB, CHOKLAD &amp;\nDRAGEFABRIKEN\n\nPnr 23100\n\nTrelleborg, Alstad. Tel\n040-48 50 09. Bankgiro 640-4172.\nPostgiro 245142-5\n\nVerksamhet: Tillverkar\ngeléartiklar, skumartiklar, dragéer,\ntugg-gummi, strössel\nAntal anställda: 30\nÅrsomsättning: 2 200 000\nAktiekapital: 21000\nVerkst dir: Ing Henry Lindulf\nEtableringsår: 1945.\n\nELEKTROELEMENT AB\n\nPnr 172 38\n\nSundbyberg, Högklintav 6. Tel\n08-29 10 24, 29 10 25. Bankgiro\n74-3632. Postgiro 554291\nVerksamhet: Tillverkar elektr\nvärmeutrustning tör industriellt\nbehov\n\nAntal anställda: 8\nÅrsomsättning: 750 000\nAktiekapital: 5 000\nStyrelse: Fabr Erland Freidling\n(ordf), ing Karl Erik Nisséus\nVerkst dir: Ing Karl Erik Nisséus\nEtableringsår: 1960.",
    "structured": {
        "1": {
            "company_name": "Vaksamhet",
            "address": "Stockholm, Hammarby Pabriksv 43 B",
            "phone_number": "08-24 49 10",
            "bank_details": {
                "bankgiro": "171-9079",
                "postgiro": "353461-7"
            },
            "activity": "Tillverkar formgjorda gummidetaljer m m",
            "employees": 70,
            "annual_turnover": 5000000,
            "capital": 10000,
            "key_personnel": [
                {
                    "name": "K E Eriksson",
                    "position": "Veikst dir"
                }
            ],
            "establishment_year": 1948
        },
        "2": {
            "company_name": "GUSTAFSON, AB A C",
            "address": "Borås, Skolg 30",
            "phone_number": "033-10 0140",
            "postgiro": "53025-3",
            "activity": "Tillskärnings-, läggnings- o symaskiner för konfektions-, trikå- o skoindustrin",
            "employees": 35,
            "annual_turnover": 7500000,
            "capital": 100000,
            "key_personnel": [
                {
                    "name": "K G Marcus",
                    "position": "Styrelse"
                },
                {
                    "name": "Anna-Lisa Wallii",
                    "position": "Styrelse"
                },
                {
                    "name": "R Westerlind",
                    "position": "Styrelse"
                },
                {
                    "name": "K Adolfsson",
                    "position": "Styrelse"
                },
                {
                    "name": "R Westerlind",
                    "position": "Verkst dir"
                }
            ],
            "establishment_year": 1921
        },
        "3": {
            "company_name": "GUSTAFSSON, FABRIKS AB ANDERS",
            "address": "Tibro 1, Fabriksg 3, Box 122",
            "phone_number": "0504-116 65",
            "bankgiro": "22-1414",
            "postgiro": "416300",
            "activity": "Tillverkar inrednings-snickerier till varuhus, skolor, sjukhus etc samt radio- o TV-möb-ler samt byggbara bokhyllor",
            "employees": 200,
            "annual_turnover": 15000000,
            "capital": 100000,
            "key_personnel": [
                {
                    "name": "Anders Gustafsson",
                    "position": "Verkst dir"
                }
            ],
            "establishment_year": 1943
        },
        "4": {
            "company_name": "GUSTAFSSONS SNICKERI-FABRIK, AB BENGT",
            "address": "Bovallstrand",
            "phone_number": "0523-510 71, 510 72",
            "bankgiro": "544-2090",
            "postgiro": "275956-1",
            "activity": "Tillverkar fönster, ytterdörrar av tryckimpregnerad furu",
            "employees": 40,
            "annual_turnover": 3000000,
            "capital": 30000,
            "key_personnel": [
                {
                    "name": "Bengt Gustafsson",
                    "position": "Veikst dir"
                }
            ],
            "establishment_year": 1943
        },
        "5": {
            "company_name": "GUSTAFSONS GRAVYR. & MEK VERKSTAD, AB E",
            "address": "Stockholm 23, Ynglingag 16, Box 23001",
            "phone_number": "08-34 0270",
            "bankgiro": "160-2291",
            "postgiro": "4016-2",
            "activity": "Handgravyr, maskingravyr. Tillverkar bakelit-, plast-o pressgjutningsverktyg, klipp- o bockverktyg. Silkscreentryck",
            "employees": 40,
            "annual_turnover": 3000000,
            "capital": 100000,
            "key_personnel": [
                {
                    "name": "Per-Allan Gustafson",
                    "position": "Verkst dir"
                }
            ],
            "establishment_year": 1924
        },
        "6": {
            "company_name": "GUSTAFSSON SKOFABRIK, E",
            "address": "Munkaljungby",
            "phone_number": "0431-307 80",
            "bankgiro": "294-1151",
            "postgiro": "74752-7",
            "activity": "Tillverkar sandaler o barn- o herrskor av fritidstyp",
            "employees": 23,
            "annual_turnover": 1600000,
            "key_personnel": [
                {
                    "name": "Fabr Egon Gustafsson",
                    "position": "Chef"
                }
            ],
            "establishment_year": 1922
        },
        "7": {
            "company_name": "GUSTAFSSONS BYGGNADS AB, G ALBERT",
            "address": "Göteborg C, Stora Nyg 15",
            "phone_number": "031-171190",
            "activity": "Byggnadsentreprenörer",
            "employees": 200,
            "annual_turnover": 15000000,
            "capital": 100000,
            "establishment_year": 1916
        },
        "8": {
            "company_name": "GUSTAFSONS EMBALLAGE-FABRIK, GIDEON",
            "address": "Handen 1, Dalarö v 1, Box 24",
            "phone_number": "08-77717 22, 777 67 49",
            "bankgiro": "332-2062",
            "postgiro": "168599-9",
            "activity": "Tillverkar plywood-emballage",
            "employees": 12,
            "annual_turnover": 850000,
            "key_personnel": [
                {
                    "name": "Fru Annie Gustafson",
                    "position": "Chef"
                },
                {
                    "name": "Walle Averståhl",
                    "position": "Verkmäst"
                }
            ],
            "establishment_year": 1930
        }
    }
}