{
    "original": "MOLLBERGS ROSTFRIA AB\n\nPnr 652 21\n\nKarlstad, Sågverksg 19. Tel\n054-15 67 1 5. Bankgiro 881-3883.\nPostgiro 470489-6\n\nVerksamhet* Utför allt i koppar.\n\nmässing, aluminium o rostfritt\nVerkst dir: Göran Mollberg\nEtableringsàr: 1953.\n\nMOLLENBORGS INGENJÖRS.\nBYRA AB\n\nPnr 41114\n\nGöteborg, S Hamng 5. Tel\n031-1346 85, 1188 84. Bankgiro\n154-4253. Postgiro 520386-4\nVerksamhet: Konsulterande\ningenjörsbyrå för VVS-teknik\nAntal anställda: 6\nÅrsomsättning: 250 000\nAktiekapital: 5 000\nVerkst dir: Civiling Axel Nilsson\nEtableringsàr: 1929.\n\nMOLLERS ARMATURFABRIK\n\nPnr 633 46\n\nEskilstuna, Lagerkvistg 6. Tel\n016-13 14 37. Bankgiro 60-1614.\nPostgiro 116183\n\nVerksamhet:\nHembelysningsarmatur\n\nAntal anstäUda: 50\nÅrsomsättning: 2 000 000\nÄgare o chef: Fabr Kjell Möller\nEtableringsàr 1956.\n\npark system ab\n\nPnr 433 00\n\nPartilie, Mellbyv 21-23. Tel\n031-444950, 444940. Bankgiro\n231-0373. Postgiro 240761-7. Tga\nCurex\n\nVerksamhet: Tillverkar o säljer\nparkeringsbiljetter enligt egna\npatent \"Park system\"\nAntal anställda: 4\nVerkst dir: Sture Nottorp\nEtableringsår: 1962.\n\nparnëus\nelektromekaniska, ab\n\nPnr 632 29\n\nEskilstuna, Hejarg 7. Tel\n016-13 8102. Bankgiro 828-1552.\nPostgiro 362785-8\n\nVerksamhet: Tillverkar elektr\nlödkolvar o brödrostar\nVarunamn: Ge-Pe\nAntal anställda: 15\nAktiekapital: 25 000\nVerkst dir: Ing Gunnar Parnéus\nEtableringsår: 1948\nOmbildat till aktiebolag 1956.\n\npartille härdkrom.\nverk, ab\n\nPnr 433 00\n\nPartille, Kung Göstas väg. Tel\n031-44 0127, 4417 40. Bankgiro\n55-0507. Postgiro 429892-3\n\nElektrolytisk och\n\nKemisk ytbehandling\n\nAntal anställda: 25\nÅrsomsättning: 1500 000\nAktiekapital: 25 000\nStyrelse: Dir Edv Ahlén (ordf), ing\nArnold Sundqvist\nVeikst dir: Edv Ahlén\nTekn chef: Ing Arnold Sundqvist\nEtableringsår: 1955.\n\npartille lastbil.\ncentral ek for\n\nPnr 433 00\n\nPartille, Box 38. Järnstångsv 1. ’\nTel 031-44 44 46 , 44 44 47.\nBankgiro 550-5086. Postgiro 361764-4\nVerksamhet: Transporter\nAntal anställda: 5\nÅrsomsättning: 4 500 000\nChef: Donald Persson\nEtableringsår: 1942.\n\nSÖDRA SVERIGES TIDNINGAR\n\nPnr 29101\n\nKristianstad 1, Box 114. Nya\nBoulevarden 4. Tel 044-1155 40.\nBankgiro 658-0229. Postgiro 160455-2.\nTga SST. Telex 4471\nVerksamhet: Utger\nKristianstadsbladet o Mellersta Skåne\nAntal anställda: 150\nÅrsomsättning: 14 000 000\nChef: Jägmäst Nils J G Larsson.\n\nSÖDRA TRÄ, H KNUTSSON &amp;\nCO\n\nPnr 252 28\n\nHelsingborg, N Ljungg 16. Tel\n042-1109 92. Bankgiro 269-0899.\nPostgiro 98143-1\n\nVerksamhet: Tillverkar\nbyggnadssnickerier, köksinredningar mm\nAntal anställda: 5\nÅrsomsättning: 350 000\nChef: Fabr Henry Knutsson\nEtableringsår: 1945.\n\nSÖDRA VI BYGGNADS.\nSNICKERIER\n\nPnr 590 80\n\nSödra Vi. Tel 0492-200 84, 20154\nVerksamhet: Tillverkar\nbyggnadssnickerier, säljer byggnadsmaterial\nAntal anställda: 46\nÅrsomsättning: 3 000 000\nChef: Disp Gillis Brorsson\nEtableringsår: 1935.\n\nWENNERSTRÖM &amp; CO AB,\nJOHN\n\nPnr 17158\n\nSolna, Polhemsg 6. Tel 08-27 92 70,\n27 88 70. Bankgiro 746-2146.\nPostgiro 191121-3\n\nVerksamhet: Grosshandel med\nskriv-, rit- o kontorsmateriel\nVerkst dir: Bertil Wennerström\nEtableringsår: 1882.\n\nBRATT AB, GUST F\n\nPnr 401 20\n\nGöteborg 1, Box 33. Tel 031-\n\n13\t9146, 13 93 43. Bankgiro\n500-6978. Postgiro 41304-7. TgaAgent.\nTelex 21038\n\nVerksamhet: Agenturer i livsmedel\nAntal anställda: 10\nAktiekapital: 30 000\nVerkst dir: Carl W Stenhammar\nEtableringsår: 1882.\n\nSATIVA, AB\n\nPnr 114 34\n\nStockholm, Birger Jarlsg 8. Tel\n08-23 06 95. Bankgiro 700-3387. Post-\n\ngiro 553839-2. Tga Sativa.\nTelex 10411\n\nVeiksamhet: Säljer fågelfröer o\nliknande artiklar\nAktiekapital: 5 000\nStyrelse: Dir Uno Grindby (ordf),\nfru Brita Grindby\nVeikst dir: Uno Grindby\nV veikst dir: Torsten Olsson\nKamrer: Hans Malmström\nEtableringsår: 1956\nDotterbolag till AB Risenta,\nStockholm. Se även detta bolag.\n\nSATT ELEKTRONIK AB\n\nPnr 12611\n\nStockholm 32, Box 32006.\nTellus-bcrgsv 90-94, Hägersten. Tel\n08-81 01 00. Tga Satt.\nTelex 10884 SATTEL S\nVeiksamhet: Tillverkar o säljer\nteleteknisk materiel\nAktiekapital: 300 000\nPlatschef: Dir K-E Werner\nEtableringsår: 1921.\n\nREKOLID, AB\n\nPnr 113 30\n\nStockholm, Hudiksvallsg 8. Tel\n08-2310 90. Bankgiro 47-6876. Post\ngiro 258343. Tga Rekolid\nVerksamhet: Arkivfotografering,\nljuskopiering o fotoreproduktion\nAvdelningskontor: Stockholm O,\nRiddarg 11 B. Tel 08-67 04 35\nAktiekapital: 100 000\nVerkst dir: Fru Greta Wästberg\nEtableringsån 1947.\n\nPERSSON AB, RAGNAR\n\nPnr 17102 Solna 2\nSundbyberg, Götg 3. Box 203,\nSolna 2. Tel 08-28 28 15. Bankgiro\n747-6229. Postgiro 452610-9.\nTga Hobbing. Telex 10745\nVerksamhet: Säljer\nvertygsmaski-ner o verktyg för den mekaniska\nindustrin\n\nAktiekapital: 60000\nVerkst din Ragnar Persson\nEtableringsår: 1951.\n\nÖST\n\nÅrsomsättning: 2 800 000\nAktiekapital: 343 000\nVerkst dir: Jan Hj Österman\nEtableringsår. 1907\nOmbildat till aktiebolag 1917.\n\nOSTERSJOKOMPANIET, AB\n\nPrr 11139\n\nStockholm, Regerings g 85. Tel\n08-21 63 00, 2165 00. Bankgiro\n483-4834. Postgiro 2708-6\nVerksamhet: Export o import av\nläderimitationer, biltyger,\nsufflett-väv, celluloid mm\nAntal anställda: 3\nAktiekapital: 5 000\nEtableringsår: 1919\nOmbildat till aktiebolag 1967.\n\nÖSTERSUNDS BRYGGERI AB\n\nPnr 83100\n\nÖstersund. Tbl 063-171 20.\nBankgiro 25-0181. Postgiro 77400. Tga\nTillbeer\n\nVerksamhet: Tillverkar malt- o\nläskedrycker\n\nAntal anställda: 130\nÅrsomsättning: 26 300 000\nAktiekapital: 60 000\nStyrelse: Civiling G Englund\nVerkst din Civiling Bengt Agerberg\nEtableringsår: 1881.\n\nÖSTERSUNDS KYLAR.\nSERVICE, AB\n\nPnr 83100\n\nÖstersund, Odenskogsv 38. Tel\n063-16100, 103 26. Bankgiro\n250-1617. Postgiro 449445-6\nVerksamhet: Renovering o\ntillverkning av kylare, värmeelement etc.\nPressning o tillverkning av\ntunnplåtsdetaljer\nAntal anställda: 44\nÅrsomsättning: 3 500 000\nAktiekapital: 55 000\nVerkst dir: Sven Lenes\nVerkstadschef: Bo Jonsson\nEtableringsår: 1954.\n\nÖSTERSUNDS REDSKAPS.\nHANDEL, AB\n\nPnr 831 01\n\nÖstersund 1, Box 114. Bangårdsg\n31. Tel 063-275 00. Bankgiro\n25-0200. Postgiro 21419-7. Tga\nRedskapshandeln\n\nVerksamhet: Säljer järnvaror o\nbyggnadsmateriel\nVarunamn: Trolla\nAntal anställda: 40\nAktiekapital: 300 000\nVerkst dir: N Tjernberg\nEtableringsår: 1906.\n\nÖSTERSUNDS ROSTFRIA\nVERKSTADSAKTIEBOLAG\n\nPnr 831 00\n\nÖstersund, Tjalmarg 8. Tel\n063-176 30. Bankgiro 37-0438. Postgiro\n141442-4. Tga OERVE\nVeiksamhet: Tillverkar rostfri\nsjukhusutrustning, köksventilatorer o\ncentralfläktsystem\nAntal anställda: 52\nÅrsomsättning: 4 800 000\nAktiekapital: 50 000\nVerkst dir: Civiling Klas Hallström\nEtableringsår: 1938.\n\nOSTERSUNDS.POSTENS\nTRYCKERI AB\n\nPnr 83100\n\nÖstersund, Kyrkg 52. Tel\n063-248 60\n\nVerksamhet: Tidningstryckeri\nAktiekapital: 900 000\nStyrelse: Bengt Magnusson, Sven\nWallin, Erik Olof Sundin, Thure\nSveiby, Olof Nilsson\nVerkst dir: Sven Wallin\nEtableringsån 1887.\n\nOSTERTÄLJE SNICKERI- &amp;\nTRÄVARU AB\n\nPnr 15136\n\nSödertälje, Badhusg 16. Tel\n0755-31153. Bankgiro 830-3315.\nPostgiro 34008-3. Tga Bosal\nVerksamhet: Levererar trävara’\no all annan byggnadsmateriel till\nsportstugor\nAktiekapital: 100 000\nVerkst dir: Sven Tibblin\nEtableringsår: 1937.\n\nÖSTGÖTA BRANDSTODS.\nBOLAG\n\nPnr 58104\n\nLinköping l.Vasav 8. Box 400.Tel\n013-14 63 40. Bankgiro 12-0240.\nPostgiro 6221-6\n\nVaksamhet: Brand- o övriga\nsakförsäkringar\n\nVerkst dir: Bengt Ingmanson\nEtableringsår: 1841.\n\nÖSTGÖTA CORRESPON.\nDENTEN, AB\n\nPnr 58189\n\nLinköping, Badhusg 5. Tel\n013-1292 00. Bankgiro 120-1995.\nPostgiro 6555-7. Telex 64009\nVerksamhet: Tidningstryckeri,\nciviltryckeri o bokbinderi\nAntal anställda: 498\nÅrsomsättning: 20 000 000\n.Aktiekapital: 1500000\nVerkst dir: Jur kand Ingvar Arén\nEtableringsår: 1887.\n\nSKÅNSK BYGGINDUSTRI, AB\n\nPnr 26134\n\nLandskrona, Seminarieg 4. Tel\n0418-123 90, 148 90. Bankgiro 868-6040.\nPostgiro 165672-7\nVerksamhet: Uppför bostads- o\nindustribyggnader\nAntal anställda: 46\nÅrsomsättning: 2 800 000\nAktiekapital: 30 000\nVerkst din Göthe Persson\nEtableringsår: 1954.",
    "structured": {
        "1": {
            "company_name": "MOLLBERGS ROSTFRIA AB",
            "pnr": "652 21",
            "address": "Karlstad, Sågverksg 19",
            "phone_number": "054-15 67 1 5",
            "bank_details": {
                "bankgiro": "881-3883",
                "postgiro": "470489-6"
            },
            "activity": "Utför allt i koppar, mässing, aluminium o rostfritt",
            "key_personnel": [
                {
                    "name": "Göran Mollberg",
                    "position": "Verkst dir"
                }
            ],
            "establishment_year": 1953
        },
        "2": {
            "company_name": "MOLLENBORGS INGENJÖRS. BYRA AB",
            "pnr": "41114",
            "address": "Göteborg, S Hamng 5",
            "phone_number": "031-1346 85, 1188 84",
            "bank_details": {
                "bankgiro": "154-4253",
                "postgiro": "520386-4"
            },
            "activity": "Konsulterande ingenjörsbyrå för VVS-teknik",
            "employees": 6,
            "annual_turnover": 250000,
            "capital": 5000,
            "key_personnel": [
                {
                    "name": "Civiling Axel Nilsson",
                    "position": "Verkst dir"
                }
            ],
            "establishment_year": 1929
        },
        "3": {
            "company_name": "MOLLERS ARMATURFABRIK",
            "pnr": "633 46",
            "address": "Eskilstuna, Lagerkvistg 6",
            "phone_number": "016-13 14 37",
            "bank_details": {
                "bankgiro": "60-1614",
                "postgiro": "116183"
            },
            "activity": "Hembelysningsarmatur",
            "employees": 50,
            "annual_turnover": 2000000,
            "key_personnel": [
                {
                    "name": "Fabr Kjell Möller",
                    "position": "Ägare o chef"
                }
            ],
            "establishment_year": 1956
        },
        "4": {
            "company_name": "park system ab",
            "pnr": "433 00",
            "address": "Partilie, Mellbyv 21-23",
            "phone_number": "031-444950, 444940",
            "bank_details": {
                "bankgiro": "231-0373",
                "postgiro": "240761-7"
            },
            "activity": "Tillverkar o säljer parkeringsbiljetter enligt egna patent \"Park system\"",
            "employees": 4,
            "key_personnel": [
                {
                    "name": "Sture Nottorp",
                    "position": "Verkst dir"
                }
            ],
            "establishment_year": 1962
        },
        "5": {
            "company_name": "parnëus elektromekaniska, ab",
            "pnr": "632 29",
            "address": "Eskilstuna, Hejarg 7",
            "phone_number": "016-13 8102",
            "bank_details": {
                "bankgiro": "828-1552",
                "postgiro": "362785-8"
            },
            "activity": "Tillverkar elektr lödkolvar o brödrostar",
            "annual_production_value": "Varunamn: Ge-Pe",
            "employees": 15,
            "capital": 25000,
            "key_personnel": [
                {
                    "name": "Ing Gunnar Parnéus",
                    "position": "Verkst dir"
                }
            ],
            "establishment_year": 1948
        },
        "6": {
            "company_name": "partille härdkrom. verk, ab",
            "pnr": "433 00",
            "address": "Partille, Kung Göstas väg",
            "phone_number": "031-44 0127, 4417 40",
            "bank_details": {
                "bankgiro": "55-0507",
                "postgiro": "429892-3"
            },
            "activity": "Elektrolytisk och Kemisk ytbehandling",
            "employees": 25,
            "annual_turnover": 1500000,
            "capital": 25000,
            "key_personnel": [
                {
                    "name": "Dir Edv Ahlén",
                    "position": "Styrelse"
                },
                {
                    "name": "Ing Arnold Sundqvist",
                    "position": "Tekn chef"
                }
            ],
            "establishment_year": 1955
        }
    }
}