{
    "original": "FRANCAISE, PARFUMERIE\n\nPnr 600 06\n\nNorrköping 6, Box 6036. Bangårdsg\n6. Tel 011-120718, 138328.\nBankgiro 824-2844. Postgiro 84020-7\nVerksamhet: Grosshandel med kem\ntekn artiklar o frisörutensilier\nVarunamn: Pe-Ef, Top-Set\nAntal anställda: 8\nÅrsomsättning: 1500 000\nÄgare o chef: Arvid Lindblad\nEtableringsår: 1901.\n\nARDO AB\n\nPnr 121 68\n\nJohanneshov, Bråviksv 39. Tel\n08-81 2019. 9190 71. Bankgiro\n56-0013. Postgiro 153701-8. Tga\nArdoplastic\n\nVerksamhet: Ventilationer för\nindustri o tunnlar. Rördragning,\ndragskåp. utsughuvar, batteriskåp.\ntankar, pumpar\nAntal anställda: 10\nÅrsomsättning: 500 000\nAktiekapital: 50 000\nVerkst dir: Axel Hansson\nEtableringsår: 1947.\n\nARE INREDNINGAR, AB\n\nStockholm i, Box 4016. Gotlandsg\n61. Tel 08-22 63 60. Bankgiro\n33-3717. Postgiro 609515. Tga\nArekon-cernen. Telex 10534 AREBOL S\nVerksamhet: Säljer kontorsmöbler,\nmattor, textilier o kontorssystem.\nUtför ombyggnadsarbeten o\ninredningar även för offentliga lokaler\nChef: Dir Lars Lindhe\nEtableringsår: 1953.\n\nHALLSBERGSTEGEL AB\n\nPnr 694 00\n\nHallsberg, Fack 39. Tel\n0582-111 35. Bankgiro 46-3112. Postgiro\n475650\n\nVerksamhet: Tillverkar o säljer\nrött fasadtegel samt murtegel\nAntal anställda: 37\nÅrsomsättning: 4000 000\nAktiekapital: 1000 000\nVerkst dir: Disp Lennart\nHammarmark\n\nEtableringsår: 1954.\n\nHALLQVIST, AB A P\n\nPnr 701 02\n\nÖrebro 1, Klosterg 3. Box 95. Tel\n019-119170. Bankgiro 81-5451.\nPostgiro 20786. Tga Läder, Leather\nVerksamhet: Agenturer i skodon,\nläderhandel i parti\nAktiekapital: 500 000\nVerkst dir: c G Hallqvist\nEtableringsår: 1874.\n\nSUD\n\nVerksamhet: Tillverkar vaddtäcken,\nkuddar, madrasser o sovsäckar\nAntal anställda: 25\nÅrsomsättning: 2 500 000\nAktiekapital: 100 000\nVerkst dir: Erie Blomqvist\nEtableringsår: 1946.\n\nTUMBA BRUK, AB\n\nPnr 147 00\n\nTumba. Tel 0753-310 30. Postgiro\n35602-2. Tga Tumbapaper,\nStockholm. Telex 10280 TUMBAB S\nVerksamhet: Pappersbruket:\ntillverkar sedelpapper samt\nhögklassigt finpapper med\nhuvudinriktning på följande kvaliteter:\nsäkerhetspapper, arkivpapper,\nbrevpapper (Sweden Bond), ritpapper o\npannåer, broschyrpapper,\nkonstnärspapper, försättspapper (Ingres)\nTryckeriet: Produktion av\nvärdetryck såsom sedlar, pass, aktier m m\nAntal anställda: 200\nÅrsomsättning: 11000 000\nAktiekapital: 25 000 000\nStyrelse: Riksbankschef Per\nAs-brink (ordf), riksdagsman Nils-Eric\nGustafsson, dir Bengt Mossberg,\nbankofullmäktige Erik Wärnberg,\ndocent Lennart Schotte, dir Gunnar\nSvärd\n\nVerkst dir Docent Lennart Schotte\nProduktchef för sedeltryckeriet:\nDir S Gideon\n\nTillverkning vid pappersbruket:\n\nDriftsing A Davoust\nFörsäljning: W Petri\nEkonomi o administration: Kamrer\nL Nyström\n\nVerkstad: Ing G Ohlson\nLaboratoriet: Kontrolling AHongslo\nEtableringsår 1963 (1755)\nÄges av Sveriges Riksbank,\nStockholm.\n\nTUMBAVERKEN, AB\n\nPnr 147 00\n\nTumba, Box 48. Tvärv 2. Tel\n0753-31130. Postgiro 355049. Tga\nTumbaverken, Stockholm\nVerksamhet; Tillverkar\nelektroniska apparater\nAntal anställda: 30\nÅrsomsättning: 2 000 000\nAktiekapital; 50 000\nVerkst dir Civiling Lew Lefterow\nEtableringsår 1946.\n\nGUTENBERGHUSREKLAM AB\n\nPnr 115 28\n\nStockholm, Sandhamn’g 67. Tel\n08-24 67 25. Bankgiro 16 -2027.\nPostgiro 705282-2.\nTelex 17317 GRSTO S\nVerksamhet: Nominerad o\nauktoriserad reklambyrå\n\nAvdelningskontor: 20110 Malmö 1,\nFack. Tel 040-10 03 00. Telex\n32666 REMA S\nAntal anställda: 26\nÅrsomsättning: 9500 000\nAktiekapital: 1000 000\nVerkst dir: Urban Bjerkehag.\n\nGUTEX PRODUKTER AB\n\nPnr 15105\n\nSödertälje 5, Box 5025. Tel\n0755-603 05. Bankgiro 622-0786.\nPostgiro 619191-0\n\nVerksamhet: Tillverkar o säljer\nslip- o polermaterial\nVarunamn: Glansit, Gutex, Sitex,\nVentipol\n\nAntal anställda: 20\nÅrsomsättning: 1000 000\nAktiekapital: 20 000\nVerkst dir: Carl Fredrik Neiglick\nEtableringsår: 1941.\n\nEL-SPIRALER, AB\n\nPnr 302 50\n\nHalmstad, Svarvareg 6. Tel\n035-10 00 80. Bankgiro 53-0009.\nPostgiro 395074\n\nBastuaggregat\n\nVerksamhet: Tillverkar elektr\nbastuaggregat, rörelement o\nelement-utrustningar. Vedeld bastuugn.\nMini-bastu. Duschar\nVarunamn: Tylö\nAntal anställda: 40\nÅrsomsättning: 12000 000\nAktiekapital: 100 000\nVerkst dir: S O Janson\nEtableringsår: 1952.\n\nHAMEX AB\n\nPnr 42131\n\nVästra Fröluida, Prörensareg 2.\nTel 031-47 53 01, 47 53 02.\nBankgiro 44-4914. Postgiro 48369\nVerksamhet: Tillverkning av\nhårdmetallverktyg\nAntal anställda: 8\nAktiekapital: 25 000\nVeikst dir: K Stolt\nEtableringsår: 1965.\n\nmalma-betong ab\n\nPnr 640 32\n\nMalmköping, Box 93. Tel\n0157-20815. Bankgiro 222-8666.\nPostgiro 133535\n\nVerksamhet: Tillverkar\nfärdigblandad betong, betongrör, betongsten,\nbjälklagselement samt olika slags\nväggelement\nAktiekapital: 50 000\nVerkst dir: Lars-Erik Andersson\nEtableringsår: 1968.\n\nFALU SPISBRODSFABRIK AB\n\nPnr 791 00\n\nFalun, Gammelv 16. Tel 023-107 50.\nBankgiro 79-2575. Postgiro 160013\nVerksamhet: Tillverkar knäckebröd\n\nAntal anställda: 32\nÅrsomsättning: 3 500 000\nAktiekapital: 500 000\nStyrelseordf: Dir Ragnar Johansson\nFabrikschef: Dir Ragnar Johansson\nEtableringsår: 1939\nOmbildat till aktiebolag 1947.\n\nFALU TRÄINDUSTRI AB\n\nPnr 791 00\n\nFalun, Slagg 10. Tel kontor\n023-123 20. Leveransadress o fabrik\nKorsnäs, Industriområdet. Tel\n023-32158. Bankgiro 153-1540.\nPostgiro 492850-3\n\nVerksamhet: Tillverkar\nspecialsnickerier i alla träslag\nAntal anställda: 8\nAktiekapital: 15 000\nÄgare o chef: Arne Wiman\nEtableringsår: 1965.\n\nFAMA AB, INGENJÖRS.\nFIRMAN\n\nPnr 11138\n\nStockholm, Johannesg 2. Tel\n08-20 97 73, 20 97 74. Postgiro 393381.\nTga Andrexag\n\nVerksamhet: Säljer rostskydds- o\nytlacker, handtvättmedel,\nkemikalier o slippasta\nVarunamn: Rensolett\nEtableringsår: 1949\nOmbildat till aktiebolag 1955.\n\nFAMACO AB\n\nPnr 102 71\n\nStockholm 9, Box 9007.\nSjöviksbacken 19. Tel 08-18 58 40.\nPostgiro 414159. Tga Famacofarma.\nTelex 1655\n\nVerksamhet: Agenturverksamhet\ninom läkemedelsbranschen\nAntal anställda: 15\nÅrsomsättning: 5 000 000\nAktiekapital: 200 000\nVerkst din Bernt Hammargren\nEtableringsår: 1962\nDotterbolag till AB Fortia.\n\nFAME-PRODUKTER\n\nPnr 151 04\n\nSödertälje 4, Erikshällsg 6 C. Box\n4037. Tel 0755-183 84. Bankgiro\n10-1293. Postgiro 671874\nVerksamhet: Tillverkar o säljer\npersienner\nChef: Gerd Meinking\nEtableringsår: 1966.",
    "structured": {
        "1": {
            "company_name": "FRANCAISE, PARFUMERIE",
            "activity": "Grosshandel med kem tekn artiklar o frisörutensilier",
            "establishment_year": 1901,
            "employees": 8,
            "annual_turnover": 1500000,
            "key_personnel": [
                {
                    "name": "Arvid Lindblad"
                }
            ]
        },
        "2": {
            "company_name": "ARDO AB",
            "address": "Johanneshov, Bråviksv 39",
            "phone_number": "08-81 2019",
            "bank_details": {
                "bankgiro": "56-0013",
                "postgiro": "153701-8"
            },
            "activity": "Ventilationer för industri o tunnlar. Rördragning, dragskåp, utsughuvar, batteriskåp, tankar, pumpar",
            "establishment_year": 1947,
            "employees": 10,
            "annual_turnover": 500000,
            "capital": 50000,
            "key_personnel": [
                {
                    "name": "Axel Hansson",
                    "position": "Verkst dir"
                }
            ]
        },
        "3": {
            "company_name": "ARE INREDNINGAR, AB",
            "address": "Stockholm i, Box 4016. Gotlandsg 61",
            "phone_number": "08-22 63 60",
            "bank_details": {
                "bankgiro": "33-3717",
                "postgiro": "609515"
            },
            "activity": "Säljer kontorsmöbler, mattor, textilier o kontorssystem. Utför ombyggnadsarbeten o inredningar även för offentliga lokaler",
            "establishment_year": 1953,
            "key_personnel": [
                {
                    "name": "Lars Lindhe",
                    "position": "Chef"
                }
            ]
        },
        "4": {
            "company_name": "HALLSBERGSTEGEL AB",
            "address": "Hallsberg, Fack 39",
            "phone_number": "0582-111 35",
            "bank_details": {
                "bankgiro": "46-3112",
                "postgiro": "475650"
            },
            "activity": "Tillverkar o säljer rött fasadtegel samt murtegel",
            "establishment_year": 1954,
            "employees": 37,
            "annual_turnover": 4000000,
            "capital": 1000000,
            "key_personnel": [
                {
                    "name": "Disp Lennart",
                    "position": "Verkst dir"
                }
            ]
        },
        "5": {
            "company_name": "HALLQVIST, AB A P",
            "address": "Örebro 1, Klosterg 3. Box 95",
            "phone_number": "019-119170",
            "bank_details": {
                "bankgiro": "81-5451",
                "postgiro": "20786"
            },
            "activity": "Agenturer i skodon, läderhandel i parti",
            "establishment_year": 1874,
            "capital": 500000,
            "key_personnel": [
                {
                    "name": "c G Hallqvist",
                    "position": "Verkst dir"
                }
            ]
        },
        "6": {
            "company_name": "SUD",
            "activity": "Tillverkar vaddtäcken, kuddar, madrasser o sovsäckar",
            "establishment_year": 1946,
            "employees": 25,
            "annual_turnover": 2500000,
            "capital": 100000,
            "key_personnel": [
                {
                    "name": "Erie Blomqvist",
                    "position": "Verkst dir"
                }
            ]
        },
        "7": {
            "company_name": "TUMBA BRUK, AB",
            "address": "Tumba",
            "phone_number": "0753-310 30",
            "postgiro": "35602-2",
            "activity": "Pappersbruket: tillverkar sedelpapper samt högklassigt finpapper med huvudinriktning på följande kvaliteter: säkerhetspapper, arkivpapper, brevpapper (Sweden Bond), ritpapper o pannåer, broschyrpapper, konstnärspapper, försättspapper (Ingres) Tryckeriet: Produktion av värdetryck såsom sedlar, pass, aktier m m",
            "establishment_year": 1755,
            "employees": 200,
            "annual_turnover": 11000000,
            "capital": 25000000,
            "key_personnel": [
                {
                    "name": "Docent Lennart Schotte",
                    "position": "Verkst dir"
                }
            ]
        },
        "8": {
            "company_name": "TUMBAVERKEN, AB",
            "address": "Tumba, Box 48. Tvärv 2",
            "phone_number": "0753-31130",
            "postgiro": "355049",
            "activity": "Tillverkar elektroniska apparater",
            "establishment_year": 1946,
            "employees": 30,
            "annual_turnover": 2000000,
            "capital": 50000,
            "key_personnel": [
                {
                    "name": "Civiling Lew Lefterow",
                    "position": "Verkst dir"
                }
            ]
        },
        "9": {
            "company_name": "GUTENBERGHUSREKLAM AB",
            "address": "Stockholm, Sandhamn’g 67",
            "phone_number": "08-24 67 25",
            "bank_details": {
                "bankgiro": "16 -2027",
                "postgiro": "705282-2"
            },
            "activity": "Nominerad o auktoriserad reklambyrå",
            "establishment_year": null,
            "employees": 26,
            "annual_turnover": 9500000,
            "capital": 100000,
            "key_personnel": [
                {
                    "name": "Urban Bjerkehag",
                    "position": "Verkst dir"
                }
            ]
        },
        "10": {
            "company_name": "GUTEX PRODUKTER AB",
            "address": "Södertälje 5, Box 5025",
            "phone_number": "0755-603 05",
            "bank_details": {
                "bankgiro": "622-0786",
                "postgiro": "619191-0"
            },
            "activity": "Tillverkar o säljer slip- o polermaterial",
            "establishment_year": 1941,
            "employees": 20,
            "annual_turnover": 1000000,
            "capital": 20000,
            "key_personnel": [
                {
                    "name": "Carl Fredrik Neiglick",
                    "position": "Verkst dir"
                }
            ]
        },
        "11": {
            "company_name": "EL-SPIRALER, AB",
            "address": "Halmstad, Svarvareg 6",
            "phone_number": "035-10 00 80",
            "bank_details": {
                "bankgiro": "53-0009",
                "postgiro": "395074"
            },
            "activity": "Tillverkar elektr bastuaggregat, rörelement o element-utrustningar. Vedeld bastuugn, Mini-bastu, Duschar",
            "establishment_year": 1952,
            "employees": 40,
            "annual_turnover": 12000000,
            "capital": 100000,
            "key_personnel": [
                {
                    "name": "S O Janson",
                    "position": "Verkst dir"
                }
            ]
        },
        "12": {
            "company_name": "HAMEX AB",
            "address": "Västra Fröluida, Prörensareg 2",
            "phone_number": "031-47 53 01, 47 53 02",
            "bank_details": {
                "bankgiro": "44-4914",
                "postgiro": "48369"
            },
            "activity": "Tillverkning av hårdmetallverktyg",
            "establishment_year": 1965,
            "employees": 8,
            "capital": 25000,
            "key_personnel": [
                {
                    "name": "K Stolt",
                    "position": "Verkst dir"
                }
            ]
        },
        "13": {
            "company_name": "malma-betong ab",
            "address": "Malmköping, Box 93",
            "phone_number": "0157-20815",
            "bank_details": {
                "bankgiro": "222-8666",
                "postgiro": "133535"
            },
            "activity": "Tillverkar färdigblandad betong, betongrör, betongsten, bjälklagselement samt olika slags väggelement",
            "establishment_year": 1968,
            "capital": 50000,
            "key_personnel": [
                {
                    "name": "Lars-Erik Andersson",
                    "position": "Verkst dir"
                }
            ]
        },
        "14": {
            "company_name": "FALU SPISBRODSFABRIK AB",
            "address": "Falun, Gammelv 16",
            "phone_number": "023-107 50",
            "bank_details": {
                "bankgiro": "79-2575",
                "postgiro": "160013"
            },
            "activity": "Tillverkar knäckebröd",
            "establishment_year": 1939,
            "employees": 32,
            "annual_turnover": 3500000,
            "capital": 500000,
            "key_personnel": [
                {
                    "name": "Ragnar Johansson",
                    "position": "Styrelseordf"
                }
            ]
        },
        "15": {
            "company_name": "FALU TRÄINDUSTRI AB",
            "address": "Falun, Slagg 10",
            "phone_number": "023-123 20",
            "bank_details": {
                "bankgiro": "153-1540",
                "postgiro": "492850-3"
            },
            "activity": "Tillverkar specialsnickerier i alla träslag",
            "establishment_year": 1965,
            "employees": 8,
            "capital": 15000,
            "key_personnel": [
                {
                    "name": "Arne Wiman",
                    "position": "Ägare o chef"
                }
            ]
        },
        "16": {
            "company_name": "FAMA AB, INGENJÖRS. FIRMAN",
            "address": "Stockholm, Johannesg 2",
            "phone_number": "08-20 97 73, 20 97 74",
            "postgiro": "393381",
            "activity": "Säljer rostskydds- o ytlacker, handtvättmedel, kemikalier o slippasta",
            "establishment_year": 1949
        },
        "17": {
            "company_name": "FAMACO AB",
            "address": "Stockholm 9, Box 9007. Sjöviksbacken 19",
            "phone_number": "08-18 58 40",
            "postgiro": "414159",
            "activity": "Agenturverksamhet inom läkemedelsbranschen",
            "establishment_year": 1962,
            "employees": 15,
            "annual_turnover": 5000000,
            "capital": 200000,
            "key_personnel": [
                {
                    "name": "Bernt Hammargren",
                    "position": "Verkst dir"
                }
            ]
        },
        "18": {
            "company_name": "FAME-PRODUKTER",
            "address": "Södertälje 4, Erikshällsg 6 C. Box 4037",
            "phone_number": "0755-183 84",
            "bank_details": {
                "bankgiro": "10-1293",
                "postgiro": "671874"
            },
            "activity": "Tillverkar o säljer persienner",
            "establishment_year": 1966,
            "employees": null,
            "capital": null,
            "key_personnel": [
                {
                    "name": "Gerd Meinking",
                    "position": "Chef"
                }
            ]
        }
    }
}