{
    "original": "UDDEVALLAFLAGG, AB\n\nPnr 451 00\n\nUddevaUa, N Hamng 6. Tel kontor\n0522-360 50, fabrik 16012. Postgiro\n225627. Tga Charles. Telex 42070\nVerksamhet: Flaggtillverkning\nAntal anstäUda: 5\nÅrsomsättning: 150 000\nAktiekapital: 10000\nVerkst dir: Sjökapten K\nNorden-dorph\n\nEtableringsår: 1959.\n\nJUKON, AB\n\nPnr 402 31\n\nGöteborg 7, Tredje Långg 43. Box\n7052. Tel 031-12 75 68, 125668.\nBankgiro 508-8026. Postgiro\n12247-3. Tga Timberman\nVerksamhet: Tillverkar Jukon\nsårsalva\n\nVarunamn: Jukon\nAntal anställda: 5\nÅrsomsättning: 350 000\nAktiekapital: 50 000\nVeikst dir; C F Åhlander\nEtableringsår: 1937.\n\nSNABBTELEFON E J URELL\n\nPnr 104 60\n\nStockholm 20, Hammaryv 28. Tel\n08-44 90 80. Bankgiro 670-8200,\n476-1763. Postgiro 254101-9\nVerksamhet: Snabbtelefoner\nFiüaler: 413 09 Göteborg,\nNorden-skiöldsg 19. Tel 031-12 4415\n21152 Malmö. Föreningsg 61.\nTel 040-1166 87\n\n360 51 Hovmantorp, Centralplan 1.\nTel 0478-408 00\n852 47 Sundsvall, Bergsg 101.\nTel 060-12 60 60\nAntal anställda: 103\nÅrsomsättning: 7 833 600\nVerkst dir: E J Orell\nEtableringsår: 1946.\n\nBOHLIN &amp; STRÖMBERG AB\n\nPnr 17121\n\nSolna 1, Box 1013.\nBibliotekstorget 8. Tel 08-83 44 60.\nBankgiro 160-5237. Postgiro 255076-2.\nTga B so. Telex 10755 BSO S\nVerksamhet: Uppdrag i\nföretagsledning i form av konsultativ\nrådgivning eller operativt ledarskap\ninom områdena:\nLångsiktsplanering, marknads- o produktplanering,\nföretags- o förvaltningsanalys,\nekonomisk planering,\nprogrambud-getering, målstyrning,\norganisationsplanering, beslutsrationalisering, samverkanformer,\nadministrativ rationalisering, kontorets\nfunktioner, dokumentstyrning,\nfunktionell kontorsplanering\nAvdelningskontor: 41110\nGöteborg, O Hamng 17. Tel 031-17 65 60\n212 14 Malmö. Industrig 13. Tel\n040-18 03 45\nAntal anställda: 25\nÅrsomsättning: 3 000 000\nAktiekapital: 80 000\nVerkst din Civilekonom Bengt\nHöög\n\nEtableringsår: 1960.\n\nWELANDER AB, INGENJÖR K\n\nPnr 291 00\n\nKristianstad, Industrig 66. Tel\n044-1233 30. Bankgiro 102-6962.\nPostgiro 437103-5.\nTelex 48032 WSTEEL S\nVerksamhet: Säljer stålverktyg\no hårdmetall\nAntal anstäUda: 8\nÅrsomsättning: 2 500 000\nAktiekapital: 5 000\nStyrelse: Ing Kjell Welander (ordf),\nkontorschef Sune Lundblad, fru\nMaja-Greta Welander\nVerkst din Kjell Welander\nEtableringsår: 1956.\n\nWELANDER AGENTURER,\nÅKE\n\nPnr 121 21\n\nJohanneshov 1, Borensv 1. Box 36.\nTel 08-91 54 34, 91 89 81. Bankgiro\n885-2576. Postgiro 198185. Tga\n\nWelagent\n\nVerksamhet: Säljer dam-, tonårs-\n\no herrkonfektion\n\nÄgare o chef: Ake Welander.\n\nWELIN &amp; CO AB, A\n\nPnr 114 58\n\nStockholm, Kommendörsg 34. Tel\n08-60 1940, 6179 49. Bankgiro\n726-5812. Postgiro 57939-1. Tga\nVetra-bolag\n\nVerksamhet: Säljer KEIM-färger\no WATCO golvpreparat\nAktiekapital: 30 000\nVerkst dir: Arne Welin\nEtableringsår: 1938.\n\nCALAMO, AB\n\nPnr 660 60\n\nMolkom, Box 46. Tel 0553-105 20.\nBankgiro 11-1607. Postgiro 26393.\nTga Calamo\n\nVerksamhet: Spiralrörsvetsverk.\nSpiralsvetsade rör, svetsade\nrördelar, anläggningar för elektrolytisk\npolering. Legopolering\nVarunamn: Calamo\nAntal anställda: 85\nAktiekapital: 180 000\nVerkst dir: Ingvar Larsson\nEtableringsår: 1918.\n\nLAHEGA AB\n\nPnr 25104\n\nHelsingborg 1, Box 268. Rausv. Tel\n042-6 2 2 5 5. Bankgiro 438-1687.\nPostgiro 9706-3\n\nVerksamhet: Tillverkar kemiska o\ntekniska produkter\n\nFilialer: Borås. Tel 033-1192 09\nLinköping. Tel 013-10 05 60\nStockholm. Tel 08-2126 08\nVarunamn: Kalkosan, Serit, BN\nVerkst dir: Nils Hegelund\nEtableringsår: 1958.\n\nGAMBRO, AB\n\nPnr 220 10\n\nLund 10, Box 10015. Magistratsv\n16. Tel 046-1177 00. Bankgiro\n660-8830. Postgiro 636465-7. Telex\n3144\n\nVerksamhet: Tillverkar medicinska\napparater o specialinstrument för\nvetenskapliga ändamål. Specialitet:\nperfusionsapparater,\ndialysutrust-ningar (monitorer, dialysatorer,\nblodslangar etc). Intensivvårds\nutrustningar\nVarunamn: Lundia\nAktiekapital: 15 000\nEtableringsår: 1964.\n\nVÄRMEKRAFT, AB\n\nPnr 126 12 Sthlm 42\nHägersten, Elektrav 73. Box 42021,\nSthlm 42. Tel 08-69 02 90.\nBankgiro 13-6224. Postgiro 553636. Tga\nVärmekraft\n\nVerksamhet: Tillverkar, säljer o\nmonterar oljeeldningsanläggningar\nAktiekapital: 200 000\nEtableringsår: 1947.\n\nFRACTIONATOR\n\nPnr 113 29\n\nStockholm, Vegag 8. Tel\n08-34 23 10. Bankgiro 78-9622.\nPostgiro 582300. Tga Fapico.\nTelex 19083\n\nVerksamhet: Fiberfraktionering,\nfiberåtervinning, vattenrening\nChef: Ing Bengt Janson\nEtableringsår: 1960.\n\nFRAKTARNA FÖRSÄLJNINGS\nAB\n\nPnr 251 04\n\nHelsingborg 1, Box 280. Karlsg\n3-5. Tel 042-14 4150. Bankgiro\n40-1050. Postgiro 262626\nVerksamhet: Driftsförnödenheter\ntill transportörer i fj ärrtrafik\nAntal anställda: 5\nÅrsomsättning: 2 000 000\nAktiekapital: 5 000\nVerkst dir: Ingemar Pemer\nEtableringsår: 1969.\n\nFRAKTARNA\nGODSTRANSPORT AB\n\nPnr 25104\n\nHelsingborg 1, Box 280. Karlsg\n3-5. Tel 042-14 4150. Bankgiro\n401-0500. Postgiro 262626-5\nVerksamhet: Inrikes\nfjärrgods-transporter\nAntal anställda: 70\nÅrsomsättning: 30 000 000\nAktiekapital: 350 000\nVerkst dir: Ingemar Pemer\nDisp: Raoul Nordbergh\nEtableringsår: 1969.\n\nFRAM, AB CYKELFABRIKEN\n\nPnr 750 03\n\nUppsala 3, Verkstadsg 8. Box3005.\nTel 018-1394 80. Bankgiro 23-0007.\nPostgiro 26135. Tga Fram\nVerksamhet: Tillverkar cyklar,\nmopeder o delar därtill\nAntal anställda: 110\nÅrsomsättning: 12 000 000\nAktiekapital: 1000 000\nVerkst dir: Stig Jonsson.\n\nFRAM-KING-BOLAGEN\n\nPnr 60103\n\nNorrköping 1, Box 123. Tel\n011-12 97 75. Bankgiro 824-3008.\nPostgiro 27953-9\n\nVerksamhet: Partiförsäljning av\ncyklar o mopeder samt tillbehör\nAntal anställda: 6\nÅrsomsättning: 2 000 000\nAktiekapital: 147000\nVerkst dir: Lars Jonsson.\n\nFRAM-K ING IMPORT AB\n\nPnr 250 05\n\nHelsingborg 5, Box 5005. Häst&gt;\nhagsv 1. Tel 042-138500, 138600.\nBankgiro 675-6100. Postgiro\n599300-1. Tga Framking\nVerksamhet: Import av scooters o\nmopeder\n\nVarunamn: Vespa\nÅrsomsättning: 2 450 000\nAktiekapital: 50 000\nVerkst dir: Nils H Jonsson\nEtableringsår: 1962.",
    "structured": {
        "1": {
            "company_name": "UDDEVALLAFLAGG, AB",
            "address": "UddevaUa, N Hamng 6",
            "phone_number": "0522-360 50",
            "bank_details": {
                "postgiro": "225627"
            },
            "activity": "Flaggtillverkning",
            "employees": 5,
            "annual_turnover": 150000,
            "capital": 10000,
            "key_personnel": [
                {
                    "name": "Sjökapten K Norden-dorph",
                    "position": "Verkst dir"
                }
            ],
            "establishment_year": 1959
        },
        "2": {
            "company_name": "JUKON, AB",
            "address": "Göteborg 7, Tredje Långg 43",
            "phone_number": "031-12 75 68",
            "bank_details": {
                "bankgiro": "508-8026",
                "postgiro": "12247-3"
            },
            "activity": "Tillverkar Jukon sårsalva",
            "employees": 5,
            "annual_turnover": 350000,
            "capital": 50000,
            "key_personnel": [
                {
                    "name": "C F Åhlander",
                    "position": "Veikst dir"
                }
            ],
            "establishment_year": 1937
        },
        "3": {
            "company_name": "SNABBTELEFON E J URELL",
            "address": "Stockholm 20, Hammaryv 28",
            "phone_number": "08-44 90 80",
            "bank_details": {
                "bankgiro": "670-8200",
                "postgiro": "476-1763"
            },
            "activity": "Snabbtelefoner",
            "employees": 103,
            "annual_turnover": 7833600,
            "key_personnel": [
                {
                    "name": "E J Orell",
                    "position": "Verkst dir"
                }
            ],
            "establishment_year": 1946
        },
        "4": {
            "company_name": "BOHLIN & STRÖMBERG AB",
            "address": "Solna 1, Box 1013, Bibliotekstorget 8",
            "phone_number": "08-83 44 60",
            "bank_details": {
                "bankgiro": "160-5237",
                "postgiro": "255076-2"
            },
            "activity": "Uppdrag i företagsledning i form av konsultativ rådgivning eller operativt ledarskap",
            "employees": 25,
            "annual_turnover": 3000000,
            "capital": 80000,
            "key_personnel": [
                {
                    "name": "Civilekonom Bengt Höög",
                    "position": "Verkst din"
                }
            ],
            "establishment_year": 1960
        },
        "5": {
            "company_name": "WELANDER AB, INGENJÖR K",
            "address": "Kristianstad, Industrig 66",
            "phone_number": "044-1233 30",
            "bank_details": {
                "bankgiro": "102-6962",
                "postgiro": "437103-5"
            },
            "activity": "Säljer stålverktyg o hårdmetall",
            "employees": 8,
            "annual_turnover": 2500000,
            "capital": 5000,
            "establishment_year": 1956
        },
        "6": {
            "company_name": "WELANDER AGENTURER, ÅKE",
            "address": "Johanneshov 1, Borensv 1, Box 36",
            "phone_number": "08-91 54 34",
            "bank_details": {
                "bankgiro": "885-2576",
                "postgiro": "198185"
            },
            "activity": "Säljer dam-, tonårs- o herrkonfektion",
            "owner_chef": "Åke Welander"
        },
        "7": {
            "company_name": "WELIN & CO AB, A",
            "address": "Stockholm, Kommendörsg 34",
            "phone_number": "08-60 1940",
            "bank_details": {
                "bankgiro": "726-5812",
                "postgiro": "57939-1"
            },
            "activity": "Säljer KEIM-färger o WATCO golvpreparat",
            "capital": 30000,
            "key_personnel": [
                {
                    "name": "Arne Welin",
                    "position": "Verkst dir"
                }
            ],
            "establishment_year": 1938
        },
        "8": {
            "company_name": "CALAMO, AB",
            "address": "Molkom, Box 46",
            "phone_number": "0553-105 20",
            "bank_details": {
                "bankgiro": "11-1607",
                "postgiro": "26393"
            },
            "activity": "Spiralrörsvetsverk. Spiralsvetsade rör",
            "varunamn": "Calamo",
            "employees": 85,
            "capital": 180000,
            "key_personnel": [
                {
                    "name": "Ingvar Larsson",
                    "position": "Verkst dir"
                }
            ],
            "establishment_year": 1918
        },
        "9": {
            "company_name": "LAHEGA AB",
            "address": "Helsingborg 1, Box 268, Rausv",
            "phone_number": "042-6 2 2 5 5",
            "bank_details": {
                "bankgiro": "438-1687",
                "postgiro": "9706-3"
            },
            "activity": "Tillverkar kemiska o tekniska produkter",
            "filialer": [
                {
                    "name": "Borås",
                    "phone_number": "033-1192 09"
                },
                {
                    "name": "Linköping",
                    "phone_number": "013-10 05 60"
                },
                {
                    "name": "Stockholm",
                    "phone_number": "08-2126 08"
                }
            ],
            "key_personnel": {
                "name": "Nils Hegelund",
                "position": "Verkst dir"
            },
            "establishment_year": 1958
        },
        "10": {
            "company_name": "GAMBRO, AB",
            "address": "Lund 10, Box 10015, Magistratsv 16",
            "phone_number": "046-1177 00",
            "bank_details": {
                "bankgiro": "660-8830",
                "postgiro": "636465-7"
            },
            "activity": "Tillverkar medicinska apparater o specialinstrument för vetenskapliga ändamål",
            "specialitet": "perfusionsapparater, dialysutrust-ningar (monitorer, dialysatorer, blodslangar etc). Intensivvårds utrustningar",
            "varunamn": "Lundia",
            "capital": 15000,
            "establishment_year": 1964
        },
        "11": {
            "company_name": "VÄRMEKRAFT, AB",
            "address": "Hägersten, Elektrav 73, Box 42021, Sthlm 42",
            "phone_number": "08-69 02 90",
            "bank_details": {
                "bankgiro": "13-6224",
                "postgiro": "553636"
            },
            "activity": "Tillverkar, säljer o monterar oljeeldningsanläggningar",
            "capital": 200000,
            "establishment_year": 1947
        },
        "12": {
            "company_name": "FRACTIONATOR",
            "address": "Stockholm, Vegag 8",
            "phone_number": "08-34 23 10",
            "bank_details": {
                "bankgiro": "78-9622",
                "postgiro": "582300"
            },
            "activity": "Fiberfraktionering, fiberåtervinning, vattenrening",
            "chef": "Ing Bengt Janson",
            "establishment_year": 1960
        },
        "13": {
            "company_name": "FRAKTARNA FÖRSÄLJNINGS AB",
            "address": "Helsingborg 1, Box 280, Karlsg 3-5",
            "phone_number": "042-14 4150",
            "bank_details": {
                "bankgiro": "40-1050",
                "postgiro": "262626"
            },
            "activity": "Driftsförnödenheter till transportörer i fj ärrtrafik",
            "employees": 5,
            "annual_turnover": 2000000,
            "capital": 5000,
            "key_personnel": {
                "name": "Ingemar Pemer",
                "position": "Verkst dir"
            },
            "establishment_year": 1969
        },
        "14": {
            "company_name": "FRAKTARNA GODSTRANSPORT AB",
            "address": "Helsingborg 1, Box 280, Karlsg 3-5",
            "phone_number": "042-14 4150",
            "bank_details": {
                "bankgiro": "401-0500",
                "postgiro": "262626-5"
            },
            "activity": "Inrikes fjärrgods-transporter",
            "employees": 70,
            "annual_turnover": 30000000,
            "capital": 350000,
            "key_personnel": [
                {
                    "name": "Ingemar Pemer",
                    "position": "Verkst dir"
                },
                {
                    "name": "Raoul Nordbergh",
                    "position": "Disp"
                }
            ],
            "establishment_year": 1969
        },
        "15": {
            "company_name": "FRAM, AB CYKELFABRIKEN",
            "address": "Uppsala 3, Verkstadsg 8, Box 3005",
            "phone_number": "018-1394 80",
            "bank_details": {
                "bankgiro": "23-0007",
                "postgiro": "26135"
            },
            "activity": "Tillverkar cyklar, mopeder o delar därtill",
            "employees": 110,
            "annual_turnover": 12000000,
            "capital": 1000000,
            "key_personnel": {
                "name": "Stig Jonsson",
                "position": "Verkst dir"
            }
        },
        "16": {
            "company_name": "FRAM-KING-BOLAGEN",
            "address": "Norrköping 1, Box 123",
            "phone_number": "011-12 97 75",
            "bank_details": {
                "bankgiro": "824-3008",
                "postgiro": "27953-9"
            },
            "activity": "Partiförsäljning av cyklar o mopeder samt tillbehör",
            "employees": 6,
            "annual_turnover": 2000000,
            "capital": 147000,
            "key_personnel": {
                "name": "Lars Jonsson",
                "position": "Verkst dir"
            }
        },
        "17": {
            "company_name": "FRAM-K ING IMPORT AB",
            "address": "Helsingborg 5, Box 5005, Häst&gt;hagsv 1",
            "phone_number": "042-138500",
            "bank_details": {
                "bankgiro": "675-6100",
                "postgiro": "599300-1"
            },
            "activity": "Import av scooters o mopeder",
            "varunamn": "Vespa",
            "annual_turnover": 2450000,
            "capital": 50000,
            "key_personnel": {
                "name": "Nils H Jonsson",
                "position": "Verkst dir"
            },
            "establishment_year": 1962
        }
    }
}