{
    "original": "INT\n\nINTER ELECTRONIC\nR OLIN AB\n\nPnr 123 21\n\nFarsta 1, Box 79. Forshagag 28.\nTel 08-93 84 98, 93 01 35.\nBankgiro 617-4270. Postgiro 509775-3\nVerksamhet: Grossiströrelse inom\nelektroniska industrin\nAntal anställda: 4\nÅrsomsättning: 2 000 000\nAktiekapital: 50 000\nVerkst dir: Robert Olin\nEtableringsår: 1969.\n\nELI\n\ngränslägesbrytare, kopplingslàdor,\nelektromek räkneverk, elektroniska\nförvalsräknare, magnetventiler\nVarunamn: Elrotti, Elres\nAktiekapital: 5 000\nEtableringsàr. 1947.\n\nELICOND TILLVERKNINGS AB\n\nPnr 430 50\n\nKållered, Box 75. Tel 031-75 14 50,\n75 14 52. Tga Elicondab\nVerksamhet: Manövertavlor,\nmanöverskåp\nAntal anställda: 10\nÅrsomsättning: 900000\nAktiekapital: 15 000\nVerkst dir: Sven Ake Ohlsson\nEtableringsàr: 1969.\n\nEHLINS ÅKERI AB, GUSTAF\n\nPnr 80103\n\nGävle 1, Industrig 12. Box 123. Tel\n026-1158 80. Bankgiro 783-7933.\nPostgiro 291419-0\nVerksamhet: Utför alla slag av\ntransporter o entreprenadarbeten\nAntal anställda: 140\nÅrsomsättning: 10 0 00 0 00\n.Aktiekapital: 200 000\nVerkst dir: Gustaf Ehlin\nEtableringsàr: 1930.\n\nEL-INDUKTRA AB\n\nPnr 695 01\n\nLaxå 1, Lars Lindahlsv 2. Box 16.\nTel 0584-108 70. Bankgiro 461-6702.\nPostgiro 22099-6\nVerksamhet: Tillverkar o säljer\ninduktorer o transformatorer\nFörsäljningskontor: 191 21\nSollentuna, Svalgången 5. Box 118. Tel\n08-3517 43, 96 30 60\nAntal anställda: 85\nÅrsomsättning: 7 000 000\nAktiekapital: 150 000\nStyrelse: Ing Boge Lindblom (ordf),\ning Johan Vangstad, ing Jan-Eric\nHellberg, ing Paul Wåhleman\nVerkst dir: Ing Johan Vangstad\nProd-chef: Ing Paul Wåhleman\nKonstr-chef: Ing Johan Vangstad\nFörsäljn-chef: Ing Boge Lindblom\nEtableringsàr: 1965.\n\nEL-INDUSTRI I FRISTAD AB\n\nPnr 510 47\n\nFristad. Tel 033-610 40. Bankgiro\n401-0617. Postgiro 275212-9\nVerksamhet: Belysningsarmatur\nAntal anställda: 28\nÅrsomsättning: 4 500 000\nAktiekapital: 100 000\nVerkst dir: Sven Nyrén\nEtableringsàr. 1948.\n\nELIT FILIP WESTLUND\n\nPnr 330 20\n\nAnderstorp. Tel 0371-15207,\n154 51. Postgiro 173887\nVerksamhet: Säljer sportartiklar,\ncykelutensilier samt lädervaror\nChef: Filip Westlund\nEtableringsàr: 1941.\n\nELIT, ELEKTRISKA\nINSTRUMENT AB\n\nPnr 16112\n\nBromma 12, Box 1237. Lövåsv 42.\nTel 08-26 27 20. Bankgiro 70-0295.\n\nPostgiro 252167. Tga\nElitinstrument. Telex 19093\nVerksamhet: Ingenjörsfirma. Säljer\nelektr mätinstrument\nFörsäljningskontor: 400 3 0 Göteborg\n11. Box 11026. Tel 031-42 3300\nAntal anställda: 25\nAktiekapital: 100 000\nVerkst dir: Lars Lönnborg\nEtableringsàr: 1945.\n\nELIT, AB\nKLICHE-CENTRALEN\n\nPnr 50107\n\nBorås 1, Allég 59. Box 404. Tel\n033-115148, 1138 74. Bankgiro\n843-4367. Postgiro 278068-2\nVerksamhet: Kliché- o offsetplåtar\nAktiekapital: 20 000\nVerkst dir: Berndt Janson\nEtableringsàr: 1945.\n\nELIT, AB TRIKAFABRIKEN\n\nPnr 50105\n\nBorås 1, Box 290. Göteborgsv 4.\nTel 033-1178 55. Bankgiro\n843-4375. Postgiro 84940-6\nVerksamhet: Tillverkar under- o\nyttertrikå samt jerseyväv\nVarunamn: Elit-Trikå\nAntal anställda: 80\nAktiekapital: 250 000\nVerkst dir: Oscar Segelmark\nEtableringsàr: 1927.\n\nELIT-EMBALLAGE, AB\n\nPnr 660 10\n\nDals Långed. Tel 0532-231 00.\nBankgiro 431-9117. Postgiro\n141529-8. Tga Elit. Telex 5319\nVerksamhet: Tillverkar hylsor o rör\nför pappers-, textil- o\nbyggnadsindustrin, cylindriska emballage,\nburkar, tunnor, fodral, stafetter etc\nAntal anställda: 40\nAktiekapital: 30 000\nVerkst dir: Civiling Karl Johan\nEnderlein\nDir: Mörten Perleff\nEtableringsàr: 1951.\n\nELJO PLASTINDUSTRI, AB\n\nPnr 260 90\n\nBåstad. Tel 0431-710 15. Bankgiro\n478-6752. Postgiro 75717-9. Tga\nEljoplast. Telex 10529 ELJOEL S\nVerksamhet: Tillverkar elektr\ninstallationsmateriel\nAktiekapital: 165 000\nVerkst dir: Nils-Ivar Gärtner\nEtableringsàr: 1946.\n\nELKINGTON AB\n\nPnr 111 56\n\nStockholm, Kungsg 37. Tel\n08-24 42 20. Bankgiro 569-3577.\nPost-giro 609393-4. Tga Elkingtrade\nVerksamhet: Säljer gjutjärnslock o\ngaller\n\nAntal anställda: 4\n\nAktiekapital: 50 000\n\nVerkst dir: Jur kand frih Axel von\n\nPlaten\n\nEtableringsàr: 1960.\n\nELKONSULT AB\n\nPnr 78101\n\nBorlänge 1, Box 161. Borganäsv 38.\n\nTel 0243-141 50. Bankgiro\n465-1774. Postgiro 397954-9\nVerksamhet: Konsulterande\nelektroteknisk byrå\n\nAvdelningskontor: 79100 Falun,\nKanslibacken 3. Tel 023-148 00\nAntal anställda: 29\nÅrsomsättning: 1500 000\nAktiekapital: 16000\nStyrelse: Civiling Olle Wiman (ordf),\nciviling Uno Sandström, övering\nTure Jonsson\n\nVerkst dir: övering Ture Jonsson\nEtableringsàr: 1951\nDotterbolag till Ingenjörsfirman\nBergman &amp; Co AB, Stockholm.\n\nELKONSULT STIG\nBERGSTRÖM AB\n\nPnr 200 90\n\nMalmö, ABC-Husen, John\nEricssons v. Tel 040-768 10. Postgiro\n149011\n\nVerksamhet: Konstruktion av\nelanläggningar\nAntal anställda: 16\nÄgare o chef: Ing Stig Bergström\nEtableringsàr 1943.\n\nVIN\n\nWINDSOR DOOR AB\n\nPnr 42103\n\nVästra Frölunda 3. Pack. Tel\n031-4763 00. 47 68 00. Bankgiro\n632-1798. Postgiro 47950-1\nVerksamhet: Tillverkning o\nförsäljning av industri- o\ngarage-portar\n\nAktiekapital: 25 000\nChef: Disp Töre Bergström\nEtableringsår: 1969.\n\nBON\n\nFANER\n\nBloms termåla\n\nVerksamhet: Tillverkar faner av\nin-o utländska träslag, ekämnen o\nparkettstav, möbelämnen\nAntal anställda: 200\nÅrsomsättning: 25 000 000\nAktiekapital: 510000\nStyrelse: Sten Larson (ordf),\nför-säljn-chef Ingvar Nilsson, dir Ulf\nBeskow, fru Greta Beskow, disp\nSven-Helge Beskow, adv Göran\nOdevall\n\nVerkst dir. Ulf Beskow\nInköpschef: Ulf Beskow\nFörsäljn-chef: Ingvar Nilsson\nDriftsing: Lars-Gunnar Wijkman\nKamrer: Sture Bjernstad\nEtableringsår: 1897\nOmbildat till aktiebolag 1904.\nÄgare: AB Utländskt Trä, Göteborg.\n\nBOMAN TRADING AB\n\nPnr 40312\n\nGöteborg 2, Kungsg 32. Box 2061.\nTel 031-13 5100. Bankgiro\n500-9741. Postgiro 626893-2. Tga\nBotrade. Telex 20732 BO TRADE S\nVerksamhet: Utländska\ntextilagen-turer för konfektionsindustrln\nAntal anställda: 4\nVerkst dir: Gösta Boman\nEtableringsår: 1953.\n\nNEIKTER AB, JOHN\n\nPnr 36013\n\nUrshult, Postl 312. Tel\n0477-20017, 200 59. Bankgiro 28-6562.\nPostgiro 96679\n\nVerksamhet: Sågade o hyvlade\nträvaror i parti o minut\nAntal anställda: 20\nÅrsomsättning: 2 300 000\nAktiekapital: 50 000\nVerkst din John Neikter\nEtableringsår: 1929.\n\nNE|MO AB,\nPRODUKTIONSANALYS\n\nPnr 59100\n\nMotala, Knipphammarv 15. Tel\n0141-185 51. Bankgiro 683-4212.\nPostgiro 717070-7\nVerksamhet: Konsultation för\narbetsstudier m m\nAktiekapital: 5 000\nVerkst dir: Ing Viktor Neilan\nEtableringsår: 1957.\n\nNEJMANS EXPORTAFFÄR\nAB, I\n\nPnr 461 00\n\nTrollhättan, Stallbacka. Tel\n0520-18240. Bankgiro 892-5976.\nPostgiro 72371-8. Tga Nejmanab.\nTelex 42093\n\nI. NEJMANS\nEXPORTAFFÄR AB\n\nTel. 18240\nTROLLHÄTTAN\n\nVerksamhet: Säljer alla slags\nhandelsjärn, plåt etc. Import o export\nav avfallsartiklar, järn- o\nmetallskrot\n\nAntal anställda: 250\nAktiekapital: 300 000\nVerkst dir Sigvard Nejman\nEtableringsår 1913\nDotterföretag: Handelsbolaget\nNejmans Exportaffär, Gävle, Uppsala\no Linköping, Nejmans Exportaffär\nKB, Arboga.\n\nNELSONS STENINDUSTRI AB\n\nPnr 580 03\n\nLinköping 3, Box 3137. Slöjdg 29.\nTel 013-13 02 45. Bankgiro\n608-0345. Postgiro 113575-5\nVerksamhet: Tillverkning,\nförsäljning o montering av byggnadssten,\nträdgårdsplattor, entrétrappor av\nnatursten o prefab betong\nAntal anställda: 9\nÅrsomsättning: 1 300 000\nAktiekapital: 30 000\nVerkst dir: Bo Dereby\nEtableringsår: 1863\nOmbildat till aktiebolag 1950.\n\nNEPTUN, BERGNINGS- och\nDYKERI-AB\n\nPnr 104 65\n\nStockholm 15, Katarinav 20. Box\n15054. Tel 08-44 06 70. Bankgiro\n166-5215. Postgiro 687-4.\nTga Neptun. Telex 10508\nVerksamhet: Bärgning, bogsering,\nisbrytning o dykning\nAntal anställda: 85\nAktiekapital: 1500 000\n\nStyrelse: Skeppsredare Dan-Axel\nBroström (ordf), dir Stig Björn,\nkapten Gösta Bothén, dir Sven\nBrusewitz, skeppsredare Karl R\nBökman, dir Stig Danielson, dir\nCurt Högberg, bergsing Axel Ax:son\nJohnson, kapten Thorsten\nSöder-hielm\n\nVerkst dir: Stig Björn\nEtableringsår 1870.\n\nNEPTUNUS AB,\nHÄNDELS-AGENTUREN\n\nPnr 41458\n\nGöteborg, Fiskhamnen. Tel\n031-127348, 1439 00. Postgiro 620950.\nTga Neptunustrade\nVeiksamhet: Säljer, köper o\nutrustar motor-fiskefartyg\nAntal anställda: 3\nÅrsomsättning: 5 000 000\nAktiekapital: 275 000\nVerkst dir Herbert Barlind\nEtableringsår. 1960.\n\nRIVE STANDARD, AB\n\nPnr 411 33\n\nGöteborg, Aschebergsg 35. Tel\n031-128300, 20 33 89. Postgiro\n\n428548. Tga Skeppsapotek\nVeiksamhet: Grosshandel med\nmedicinska förnödenheter\nAntal anställda: 4\nÅrsomsättning: 250 000\nAktiekapital: 10 000\nVeikst din Hugo Nygren\nEtableringsår: 1939.\n\nURWITZ, AB GABRIEL\n\nPnr 114 58\n\nStockholm, Skepparg 49 B. Tel\n08-23 12 60. Bankgiro 29-6128.\nPostgiro 53577-3. Tga Gabriellabelt\nVerksamhet: Tillverkar bälten o\nmode varor\n\nFabrik: Ängelholm. Tel 0431-137 45\nVarunamn: Gabri, Gabriella\nAntal anställda: 70\nAktiekapital: 144 000\nEtableringsår: 1905.\n\nKJELLSTROM &amp; CO, G\n\nPnr 701 05\n\nÖrebro 1, Skolg 20. Box 325. Tel\n019-11 0484, 121584. Bankgiro\n81-5469. Postgiro 297347. Telex\n73237. Tga Gerhard\nVerksamhet: Säljer halvfabrikat av\njärn, stål, aluminium, koppar o\nmässing. Rörelsen till stor del\nbaserad på importaffärer\nAntal anställda: 7\nVerkst dir: Per M Kjellström\nEtableringsår: 1938.\n\nTIDKORT, AB\n\nPnr 17148\n\nSolna, Fabriksv 9. Tel 08-83 01 20.\nBankgiro 238-6365. Postgiro\n152859-5\n\nVerksamhet: Tillverkar tidkort,\ntid-stämplingskort i löpande bana.\nHålkort\n\nAntal anställda: 10\nAktiekapital: 10000\nVerkst dir: Boktryckare Erik\nLindberg\n\nEtableringsår: 1940.\n\nTIDNINGARNAS TELEGRAM.\nBYRÅ AB\n\nPnr 10512\n\nStockholm, Sveav 17. Tel 2244 80,\nriks 08-22 54 80. Telex 19168\nVerksamhet: Svenska pressens\ncentralorgan för nyhetsförmedling,\nvaluta o varubörsnoteringar\nAntal anställda: 180\nAktiekapital: 500 000\nVerkst din J-O Modig\nEtableringsån 1921.\n\nTIDNINGSBRUKEN\n\nSvenska Tidningspappersbrukens\nFörening u p a\nPnr 11187\n\nStockholm 1, Box 1710. Stureplan\n19. Tel 08-23 06 05. Bankgiro\n576-8825. Postgiro 3104-7. Tga\nTidningsbruken. Telex 1661\nVerksamhet: Försäljning av\ntidningspapper i Sverige\nVeikst din Svante Vinell\nEtableringsån 1917.\n\nTIDSTRANDS YLLEFABRIKER\nAB\n\nPnr 790 22\n\nSågmyra. Tel 023-593 00.\nPost-giro 8468-1. Tga Tidstrand.\nTelex 84035\n\nVerksamhet: Tillverkar filtar,\nplädar. hemtextilier o möbeltyg\nAntal anställda: 350\nÅrsomsättning: 18 000 000\nAktiekapital: 3 375 000\nVerkst dir. Sverre Larsson\nEtableringsår: 1916.\n\nSVE\n\nSVENSKA LANTMÄNNENS\nRIKSFÖRBUND F U P A\n\nPnr 102 26\n\nStockholm 12, Box 12238. Sankt\nGöransg 160 A. Tel 08-1315 00.\nBankgiro 330-0274. Postgiro\n58470-6. Tga Riksförbundet.\nTelex 1460\n\nVerksamhet: Köper o säljer\nspannmål, foder- o gödselmedel, fröer,\nutsäde, potatis, kemikalier o oljor.\nMaskiner, redskap o byggnadsmar\nteiial säljes genom AB Slöörs\nMaskiner\n\nStyrelseordf: Nils Larsson\nVerkst dir: Paul Hökfelt\nV verkst dir: Carl-Arne Samuelson\nOrganisationschef: Dir Yngwe\nHej-neman\n\nEtableringsàr: 1905.\n\nSVENSKA LASTBIL AB\n\nPnr 100 41\n\nStockholm 26, Pack. üstermalmsg\n47. Tel 08-14 02 00. Postgiro\n358771-4. Tga Svelastbil\nVerksamhet: Transporter,\nmagasinering\n\nAntal anställda: 1400\nÅrsomsättning: 90 000 000\nAktiekapital: 11000 000\nVerkst dir: Nils Olof Landeberg\nEtableringsàr: 1937.\n\nSVENSKA AB LE CARBONE\n\nPnr 172 21\n\nSundbyberg 1, Box 20. Karlsbodav\n45, Bromma. Tel 08-28 2615.\nBankgiro 743-5233. Postgiro 51208-7.\nTga Lecarbone, Stockholm.\nTelex 10379\n\nVerksamhet: Tillverkar elborstar,\npumpklaffar, tätringar o\nelektrotekniska kolprodukter samt torr- o\nvåtelement. Säljer elektrotekniska\no kemotekniska grafitprodukter samt\nmetallurgiska specialprodukter\nVarunamn: Carbone, Lorraine, AD,\nUgine-Carbone\nAntal anställda: 40\nÅrsomsättning: 9 000 000\nAktiekapital: 500 000\nStyrelse: Adv G A Rising (ordf),\nciviling K E Algovik, dir W Gast,\nciviling W Ramsay\nVerkst dir: Civiling Karl E\nAlgovik\n\nEtableringsàr: 1931.\n\nSVENSKA LEDSTÅNGS.\nFABRIKEN\n\nPnr 57400\n\nVetlanda, Magasinsg 35. Tel\n0383-103 26\n\nVerksamhet: Ledstångstillverkning\nÄgare o chef: Disp N E Noryd.\n\nSVENSKA LEGO AB\n\nPnr 443 01\n\nLerum 1, Pack. Tel 0302-226 58,\n226 59. Bankgiro 54-7750.\nPostgiro 422933-2\n\nVerksamhet: Generalagent för Lego\nSystem, leksaksbyggsats i plast\nAntal anställda: 10\nÅrsomsättning: 6 000 000\nAktiekapital: 150 000\nVerkst dir: Bror Åsberg\nEtableringsàr: 1959.\n\nSVENSKA LIMÄMNES.\nFABRIKEN AB\n\nPnr 26122\n\nLandskrona 1, Box 193. Gasverksg.\nTel 0418-160 70. Bankgiro\n660-0985. Postgiro 23170-4. Tga\nAt-lantine\n\nVerksamhet: Tillverkar dextrin o\nlimämnen, hartslim,\ntextilhjälpmedel, stärkelser mm\nFilialkontor: 19140 Sollentuna, Alv\n64. Tel 08-35 07 07\nAntal anställda: 60\nÅrsomsättning: 9 000 000\nAktiekapital: 1000 000\nVerkst dir. Disp Herbert Lundius\nEtableringsàr: 1901.\n\nSVENSKA LLOYD, REDERI AB\n\nPnr 403 13\n\nGöteborg 2, Skeppsbron 5-6. Box\n2125. Tel 031-17 43 00. Bankgiro\n500-5517. Postgiro 12500. Tga\nLloyd. Telex 2208\nVerksamhet: Bedriver in- o utrikes\nfrakt- o passagerartrafik\nAntal anställda: 867\nÅrsomsättning: 154 787 000\nAktiekapital: 18 479 850\nVerkst dir: Torgeir Christoffersen\nEtableringsàr. 1869.\n\nSVENSKA LUFTFILTER AB\n\nPnr 14146\n\nHuddinge, Centralv 7. Tel\n08-711 26 80. Bankgiro 56-9762.\nPostgiro 259550-2. Tga Luftfilter\nVerksamhet: Tillverkar luftfilter,\nfläktar o stoftavskiljare. Utför\nanläggningar för pneumatisk\ntransport o stoftavskiljning\nAntal anställda: 30\nÅrsomsättning: 3 000 000\nAktiekapital: 150 000\nVerkst dir: B östlund\nEtableringsàr 1947.",
    "structured": {
        "1": {
            "company_name": "INTER ELECTRONIC R OLIN AB",
            "address": "Farsta 1, Box 79. Forshagag 28.",
            "phone_number": "08-93 84 98, 93 01 35",
            "bank_details": {
                "bankgiro": "617-4270",
                "postgiro": "509775-3"
            },
            "activity": "Grossiströrelse inom elektroniska industrin",
            "employees": 4,
            "annual_turnover": 2000000,
            "capital": 50000,
            "key_personnel": [
                {
                    "name": "Robert Olin",
                    "position": "Verkst dir"
                }
            ],
            "establishment_year": 1969
        },
        "2": {
            "company_name": "ELI",
            "activity": "Gränslägesbrytare, kopplingslådor, elektromek räkneverk, elektroniska förvalsräknare, magnetventiler",
            "capital": 5000,
            "establishment_year": 1947
        },
        "3": {
            "company_name": "ELICOND TILLVERKNINGS AB",
            "address": "Kållered, Box 75",
            "phone_number": "031-75 14 50, 75 14 52",
            "activity": "Manövertavlor, manöverskåp",
            "employees": 10,
            "annual_turnover": 900000,
            "capital": 15000,
            "key_personnel": [
                {
                    "name": "Sven Ake Ohlsson",
                    "position": "Verkst dir"
                }
            ],
            "establishment_year": 1969
        },
        "4": {
            "company_name": "EHLINS ÅKERI AB, GUSTAF",
            "address": "Gävle 1, Industrig 12. Box 123",
            "phone_number": "026-1158 80",
            "bank_details": {
                "bankgiro": "783-7933",
                "postgiro": "291419-0"
            },
            "activity": "Utför alla slag av transporter o entreprenadarbeten",
            "employees": 140,
            "annual_turnover": 10000000,
            "capital": 200000,
            "key_personnel": [
                {
                    "name": "Gustaf Ehlin",
                    "position": "Verkst dir"
                }
            ],
            "establishment_year": 1930
        },
        "5": {
            "company_name": "EL-INDUKTRA AB",
            "address": "Laxå 1, Lars Lindahlsv 2. Box 16",
            "phone_number": "0584-108 70",
            "bank_details": {
                "bankgiro": "461-6702",
                "postgiro": "22099-6"
            },
            "activity": "Tillverkar o säljer induktorer o transformatorer",
            "sales_office_address": "191 21 Sollentuna, Svalgången 5. Box 118",
            "sales_office_phone": "08-3517 43, 96 30 60",
            "employees": 85,
            "annual_turnover": 7000000,
            "capital": 150000,
            "key_personnel": [
                {
                    "name": "Ing Boge Lindblom",
                    "position": "Styrelse ordf"
                },
                {
                    "name": "Ing Johan Vangstad",
                    "position": "Prod-chef"
                }
            ],
            "establishment_year": 1965
        },
        "6": {
            "company_name": "EL-INDUSTRI I FRISTAD AB",
            "address": "Fristad",
            "phone_number": "033-610 40",
            "bank_details": {
                "bankgiro": "401-0617",
                "postgiro": "275212-9"
            },
            "activity": "Belysningsarmatur",
            "employees": 28,
            "annual_turnover": 4500000,
            "capital": 100000,
            "key_personnel": [
                {
                    "name": "Sven Nyrén",
                    "position": "Verkst dir"
                }
            ],
            "establishment_year": 1948
        },
        "7": {
            "company_name": "ELIT FILIP WESTLUND",
            "address": "Anderstorp",
            "phone_number": "0371-15207, 154 51",
            "activity": "Säljer sportartiklar, cykelutensilier samt lädervaror",
            "chief": "Filip Westlund",
            "establishment_year": 1941
        },
        "8": {
            "company_name": "ELIT, ELEKTRISKA INSTRUMENT AB",
            "address": "Bromma 12, Box 1237. Lövåsv 42",
            "phone_number": "08-26 27 20",
            "bank_details": {
                "bankgiro": "70-0295",
                "postgiro": "252167"
            },
            "activity": "Ingenjörsfirma. Säljer elektr mätinstrument",
            "sales_office_address": "400 3 0 Göteborg 11. Box 11026",
            "sales_office_phone": "031-42 3300",
            "employees": 25,
            "capital": 100000,
            "key_personnel": [
                {
                    "name": "Lars Lönnborg",
                    "position": "Verkst dir"
                }
            ],
            "establishment_year": 1945
        },
        "9": {
            "company_name": "ELIT, AB KLICHE-CENTRALEN",
            "address": "Borås 1, Allég 59",
            "phone_number": "033-115148, 1138 74",
            "bank_details": {
                "bankgiro": "843-4367",
                "postgiro": "278068-2"
            },
            "activity": "Kliché- o offsetplåtar",
            "capital": 20000,
            "key_personnel": [
                {
                    "name": "Berndt Janson",
                    "position": "Verkst dir"
                }
            ],
            "establishment_year": 1945
        },
        "10": {
            "company_name": "ELIT, AB TRIKAFABRIKEN",
            "address": "Borås 1, Box 290. Göteborgsv 4",
            "phone_number": "033-1178 55",
            "bank_details": {
                "bankgiro": "843-4375",
                "postgiro": "84940-6"
            },
            "activity": "Tillverkar under- o yttertrikå samt jerseyväv",
            "product_name": "Elit-Trikå",
            "employees": 80,
            "capital": 250000,
            "key_personnel": [
                {
                    "name": "Oscar Segelmark",
                    "position": "Verkst dir"
                }
            ],
            "establishment_year": 1927
        }
    }
}