{
    "original": "SÄRENHOLM, AB CARL\n\nPnr 631 05\n\nEskilstuna 1, Strandg 6. Box 347.\nTel 016-13 0213, 13 13 13.\nBankgiro 82-8066. Postgiro 10802. Tga\nSärenholms\n\nVerksamhet: Tillverkar som\nspecialitet pressade o automatsvarvade\nmassartiklar i järn o metall, även\ni precisionsutförande.\nStandardartiklar: pappersklämmor, krattor o\nfönsterbeslag\nAktiekapital: 600 000\nEtableringsår: 1895\nOmbildat till aktiebolag 1934.\n\nSÄTERS VÄVERI AB\n\nPnr 783 00\n\nSäter. Tel 0225-511 00. Bankgiro\n798-7282. Postgiro 27754-1. Tga\nVäveriet. Telex 7521 VAVERIET S\nVerksamhet: Tillverkar gardin-,\ndraperi-, överkast- o möbeltyger\nVarunamn: Säterjäntan\nAntal anställda: 125\nÅrsomsättning: 10 000 000\nAktiekapital: 1300 000\nStyrelse: Adv Bo Johansson (ordf),\ning Carl Gustav Kellman, ing\nManfred Titz\n\nVerkst dir: Ing Manfred Titz\nEtableringsår: 1914.\n\nÅrsomsättning: 38 000 000\nAktiekapital: 3 000 000\nVerkst dir: Elvir Berggren.\n\nJUNGNER, SVENSKA\nACKUMULATOR AB\n\nPnr 572 01\n\nOskarshamn 1, Box 3. Tel\n0491-160 00. Bankgiro 195-6549.\nPostgiro 1547-9. Tga Nife. Telex 4982\n\nJUNGNER\n\nVerksamhet: Tillverkar NIFE\nalkaliska nickel-kadmium batterier,\nNIFE växelriktare, NIFEFLEX\nströmförsörjningssystem för alla\ntyper av reserv- o nödkraft med\nbatteri, batteriladdare, likriktare,\nNIFE lyktor o signalutrustning.\nBorosilikatglas (eldfast) för\nindustriapplikationer, laboratorieglas\n\n0\ttekniskt glas, samt diverse\nkonstglas (sodaglas). Generalagent för\nBEREC torrbatterier\nAckumulatorfabrik o mek verkstad\n\n1\tOskarshamn o kem tekn fabrik i\nFliseryd. AB Ruda Glasbruk i Ruda\nAvdelningskontor: 114 57 Stockholm,\nRiddarg 17. Tel 08-22 23 40\n\n16130 Bromma, Ranhammarsv 28.\nTel 08-28 01 10, 2844 30\n42131 Västra Frölunda, Fröullsg.\nTel 031-47 36 00\n\n213 63 Malmö, Silverviksg 7. Tel\n040-94 6110 , 94 61 20\n852 33 Sundsvall, Strandg 4. Tel\n060-1128 66\n\nVarunamn: Berec, Ruda, NIFE/\nJungner, Nifeflex\nAntal anställda: 800\nAktiekapital: 20 154 400\nStyrelse: Bankdir Peder Bonde\n(ordf), viceamiral Erik Anderberg,\ndir Gustaf Piehl, dir Tage Ortegren,\ndir Karl Robert Ameln\nVerkst dir: Civiling Karl Robert\nAmeln\n\nEtableringsår 1910.\n\nHar egna fabriker o\nförsäljningsorganisationer i ett flertal länder.\nÄger följande Svenska dotterbolag:\nAB Ruda Glasbruk, AB\nRiddar-kontor, AB Nobel-Accumulator, AB\nNife, AB Saaj, AB Thorsens\nRadiatorer, Elektro-Hermas AB.\n\nJUNO, KÖKSUTRUSTNINGS AB\n\nPnr 11457\n\nStockholm, Riddarg 47. Tel\n08-63 5130. Bankgiro 330-1777.\nPostgiro 500066-6. Tga Junobol\nVerksamhet: Säljer kompletta\nrestaurangutrustningar\nAntal anställda: 22\nÅrsomsättning: 5 500000\nAktiekapital: 80 000\nVerkst dir: Martin Lindenbaum\nEtableringsår: 1952.\n\nGUTO TRYCK, AB\n\nPnr 25103\n\nHelsingborg 1, Box 115.\nGarni-sonsg 10. Tel 042-18 03 30.\nBankgiro 863-9338. Postgiro 84207-0\nVerksamhet: Reklamtryck, offset,\nblanketter, självhäftande etiketter,\nfraktsedlar, adresslappar o\nföljesedlar\n\nAktiekapital: 500 000\n\nVerkst dir: Disp Gunnar Ohlsson\n\nEtableringsår: 1945.\n\nHALLQUISTH&amp;HARDWICK AB\n\nPnr 113 58\n\nStockholm, Luntmakarg 63. Tel\n08-314180, 314105. Bankgiro\n21-1199. Postgiro 504777. Tga\nHa-wicktex\n\nVerksamhet: Agentur o\nengros-rörelse i ylletyger\nAntal anställda: 8\nÅrsomsättning: 5 000 000\nAktiekapital: 50 000\nVerkst dir: Roland Hardwick\nEtableringsår: 1954.\n\nHALLQVIST &amp; SON AB,\nELBO LAGET\n\nPnr 19901\n\nEnköping 1, Idrottsallén 4. Box 40.\nTel 0171-382 50. Bankgiro 804-2343.\nPostgiro 10268-1\n\nVerksamhet: Elektr entreprenader,\nelektr service, säljer\ninstallationsmateriel o hushållsmaskiner\nAffär: Enköping, Torgg 22\nAntal anställda: 28\nÅrsomsättning: 3000 000\nAktiekapital: 50 000\nVerkst dir: Töre Hallqvist\nEtableringsår: 1950.\n\nsmålädervaror. Säljer skinnkläder\nVarunamn: Bialitt\nAntal anställda: 5\nÅrsomsättning: 800 000\nAktiekapital: 200000\nVerkst dir: Staffan Jahnke\nEtableringsår: 1874.\n\nFLAVA INDUSTRI\n\nPnr 41126\n\nGöteborg, Erik Dahlbergsg 8.\nTel 031-1158 25, 1177 80.\nPostgiro 42661\n\nVerksamhet: Tillverkar o säljer\nkosmetika\nVarunamn: Flava\nÄgare o chef: Farm kand fru\nHedvig Sjöstedt\nEtableringsår: 1934.\n\nWENDEL AB,GEORG\n\nPnr 411 10\n\nGöteborg, O Hamng 15. Tel\n031-173160. Bankgiro 84-7929.\nPost-giro 45770. Tga Lednew.\nTelex 21159\n\nVerksamhet: Agentur för kemikalier\no råvaror\n\nAktiekapital: 5 000\n\nÄgare o chefer: Sölve Sundin, Nils\nLundberg\n\nEtableringsår: 1958.\n\nLINJEBYGGNAD, AB\n\nPnr 103 61\n\nStockholm 3, Brunnsg 21 B. Box\n3100. Tel 08-23 38 40. Bankgiro\n727-0887. Postgiro 157251-0.\nTelex 10675 LIN TRÅ S\nVerksamhet: Projektering, materiel\no montage av kraftledningar o\nställverk, transformatorkiosker\nAktiekapital: 1920 000\nVerkst dir: Karl-Fredrik Åkerström\nEtableringsår: 1939.\n\nÄNG\n\nÄNG PANN E FÖRENINGEN\n\nPnr 10131\n\nStockholm 1, Flemingg 7. Box 783.\nTel 08-2346 00. Bankgiro 48-3452.\nPostgiro 815. Tga Ångpanna.\nTelex 10361 ENERGI S\n\nÅNGPANNEFÖRENINGEN\n\nVerksamhet: Besiktnings- o\nkonsul-teringsverksamhet angående\nång-o värmeanläggningar, elektr\nanläggningar, hissanläggningar,\nVVS-an-läggningar, kraftavtal mm\nFilialkontor. Falun, Gävle,\nGöteborg, Halmstad, Jönköping,\nKarlstad, Kristianstad, Luleå, Malmö,\nNorrköping, Skellefteå, Sundsvall,\nUmeå, Växjö\nVerkst dir: Folke Petri.\n\nÅNGPANNOR &amp; STO K ERS, AB\n\nPnr 400 30\n\nGöteborg 11, Angg 5. Box 11077.\nTel 031-114152, 1141 53, 119155.\nBankgiro 546-6156, 107-7601.\nPostgiro 523191-5. Tga Stokers.\nTelex 20890 STOKERS S\nVerksamhet: Säljer från eget lager\no verkslager:\n\nKupade gavlar av alla typer o\nkvaliteter\nEldrör\n\nHand-, huvud- o manluckor för\nångpannor. tryck- o luftbehållare\nRörböjar. rörändar, formstycken,\nkonor. tudelade rörklammor o\nrörpendlar\n\nRörkompens atorer\nSnäckskruvelement för\nskruvtransportörer\n\nFlänsar o varmhållfast bult\nVarunamn: A &amp; S, OAB\nAktiekapital: 50000\nVerkst dir: Ing Erie Wångmark\nEtableringsår. 1956.\n\nSCHÉLE, AB TH\n\nPnr 30102\n\nHalmstad 1, Bredg 2. Box 92. Tel\n035-10 04 4 0. Bankgiro 530-0447.\nPostgiro 33551. Tga Schéle.\nTelex 38071\n\nVerksamhet: Skeppsmäkleri,\nbefraktning, spedition, lagring\nAntal anstäUda: 31\nAktiekapital: 80000\nVerkst dir C Y Roland\nChristianson\n\nEtableringsàr. 1884.\n\nSCHENKER &amp; CO\nTRANSPORT AB\n\nPnr 103 13\n\nStockholm 2, Kornhamnstorg6. Box\n2120. Tel 08-23 6850. Postgiro\n502692. Telex 1567. Tga\nSkan-schenker\n\nVerksamhet: Internationell\nspedition, flyttningar o magasinering\nÅrsomsättning: 15 500 000\nAktiekapital: 300 000\nEtableringsàr 1953.\n\nmaskin-tellus, ab\n\nPnr 186 00\n\nVaUentuna, Industriv. Tel\n0762-241 25. Tga Maskintellus,\nStockholm. Telex 10227\nVerksamhet: Transportmateriel\nAntal anstäUda: 200\nÅrsomsättning: 17 000 000\nAktiekapital: 600 000\nVerkst dir: Gösta Lindahl\nEtableringsår: 1947.",
    "structured": {
        "firms": [
            {
                "company_name": "SÄRENHOLM, AB CARL",
                "address": "Eskilstuna 1, Strandg 6. Box 347.",
                "phone_number": "016-13 0213, 13 13 13",
                "bank_details": {
                    "bankgiro": "82-8066",
                    "postgiro": "10802"
                },
                "activity": "Tillverkar som specialitet pressade o automatsvarvade massartiklar i järn o metall, även i precisionsutförande. Standardartiklar: pappersklämmor, krattor o fönsterbeslag",
                "capital": 600000,
                "establishment_year": 1895
            },
            {
                "company_name": "SÄTERS VÄVERI AB",
                "address": "Säter",
                "phone_number": "0225-511 00",
                "bank_details": {
                    "bankgiro": "798-7282",
                    "postgiro": "27754-1"
                },
                "activity": "Tillverkar gardin-, draperi-, överkast- o möbeltyger",
                "employees": 125,
                "annual_turnover": 10000000,
                "capital": 1300000,
                "key_personnel": [
                    {
                        "name": "Adv Bo Johansson",
                        "position": "ordf"
                    },
                    {
                        "name": "ing Carl Gustav Kellman",
                        "position": ""
                    },
                    {
                        "name": "ing Manfred Titz",
                        "position": ""
                    }
                ],
                "establishment_year": 1914
            },
            {
                "company_name": "JUNGNER, SVENSKA ACKUMULATOR AB",
                "address": "Oskarshamn 1, Box 3",
                "phone_number": "0491-160 00",
                "bank_details": {
                    "bankgiro": "195-6549",
                    "postgiro": "1547-9"
                },
                "activity": "Tillverkar NIFE alkaliska nickel-kadmium batterier, NIFE växelriktare, NIFEFLEX strömförsörjningssystem för alla typer av reserv- o nödkraft med batteri, batteriladdare, likriktare, NIFE lyktor o signalutrustning. Borosilikatglas (eldfast) för industriapplikationer, laboratorieglas o tekniskt glas, samt diverse konstglas (sodaglas). Generalagent för BEREC torrbatterier Ackumulatorfabrik o mek verkstad Oskarshamn o kem tekn fabrik i Fliseryd. AB Ruda Glasbruk i Ruda Avdelningskontor: 114 57 Stockholm, Riddarg 17.",
                "employees": 800,
                "capital": 20154400,
                "key_personnel": [
                    {
                        "name": "Bankdir Peder Bonde",
                        "position": "ordf"
                    },
                    {
                        "name": "viceamiral Erik Anderberg",
                        "position": ""
                    },
                    {
                        "name": "dir Gustaf Piehl",
                        "position": ""
                    },
                    {
                        "name": "dir Tage Ortegren",
                        "position": ""
                    },
                    {
                        "name": "dir Karl Robert Ameln",
                        "position": ""
                    }
                ],
                "establishment_year": 1910
            },
            {
                "company_name": "JUNO, KÖKSUTRUSTNINGS AB",
                "address": "Stockholm, Riddarg 47",
                "phone_number": "08-63 5130",
                "bank_details": {
                    "bankgiro": "330-1777",
                    "postgiro": "500066-6"
                },
                "activity": "Säljer kompletta restaurangutrustningar",
                "employees": 22,
                "annual_turnover": 5500000,
                "capital": 80000,
                "key_personnel": [
                    {
                        "name": "Martin Lindenbaum",
                        "position": ""
                    }
                ],
                "establishment_year": 1952
            },
            {
                "company_name": "GUTO TRYCK, AB",
                "address": "Helsingborg 1, Box 115.",
                "phone_number": "042-18 03 30",
                "bank_details": {
                    "bankgiro": "863-9338",
                    "postgiro": "84207-0"
                },
                "activity": "Reklamtryck, offset, blanketter, självhäftande etiketter, fraktsedlar, adresslappar o följesedlar",
                "capital": 500000,
                "key_personnel": [
                    {
                        "name": "Disp Gunnar Ohlsson",
                        "position": ""
                    }
                ],
                "establishment_year": 1945
            },
            {
                "company_name": "HALLQUISTH&HARDWICK AB",
                "address": "Stockholm, Luntmakarg 63",
                "phone_number": "08-314180, 314105",
                "bank_details": {
                    "bankgiro": "21-1199",
                    "postgiro": "504777"
                },
                "activity": "Agentur o engros-rörelse i ylletyger",
                "employees": 8,
                "annual_turnover": 5000000,
                "capital": 50000,
                "key_personnel": [
                    {
                        "name": "Roland Hardwick",
                        "position": ""
                    }
                ],
                "establishment_year": 1954
            },
            {
                "company_name": "HALLQVIST & SON AB, ELBO LAGET",
                "address": "Enköping 1, Idrottsallén 4. Box 40",
                "phone_number": "0171-382 50",
                "bank_details": {
                    "bankgiro": "804-2343",
                    "postgiro": "10268-1"
                },
                "activity": "Elektr entreprenader, elektr service, säljer installationsmateriel o hushållsmaskiner",
                "employees": 28,
                "annual_turnover": 3000000,
                "capital": 50000,
                "key_personnel": [
                    {
                        "name": "Töre Hallqvist",
                        "position": ""
                    }
                ],
                "establishment_year": 1950
            },
            {
                "company_name": "HULTMAN & ERIKSSON AB",
                "address": "Malmö, Davidshallstorg 5",
                "phone_number": "040-19 29 20",
                "activity": "Handel med fotogen samt tillverkning av sidentofflor o smålädervaror. Säljer skinnkläder",
                "employees": 5,
                "annual_turnover": 800000,
                "capital": 200000,
                "key_personnel": [
                    {
                        "name": "Staffan Jahnke",
                        "position": ""
                    }
                ],
                "establishment_year": 1874
            },
            {
                "company_name": "FLAVA INDUSTRI",
                "address": "Göteborg, Erik Dahlbergsg 8",
                "phone_number": "031-1158 25, 1177 80",
                "postgiro": "42661",
                "activity": "Tillverkar o säljer kosmetika",
                "owner": "Farm kand fru Hedvig Sjöstedt",
                "establishment_year": 1934
            },
            {
                "company_name": "WENDEL AB,GEORG",
                "address": "Göteborg, O Hamng 15",
                "phone_number": "031-173160",
                "bank_details": {
                    "bankgiro": "84-7929",
                    "postgiro": "45770"
                },
                "activity": "Agentur för kemikalier o råvaror",
                "capital": 5000,
                "owners": [
                    {
                        "name": "Sölve Sundin",
                        "position": ""
                    },
                    {
                        "name": "Nils Lundberg",
                        "position": ""
                    }
                ],
                "establishment_year": 1958
            },
            {
                "company_name": "LINJEBYGGNAD, AB",
                "address": "Stockholm 3, Brunnsg 21 B. Box 3100",
                "phone_number": "08-23 38 40",
                "bank_details": {
                    "bankgiro": "727-0887",
                    "postgiro": "157251-0"
                },
                "activity": "Projektering, materiel o montage av kraftledningar o ställverk, transformatorkiosker",
                "capital": 1920000,
                "key_personnel": [
                    {
                        "name": "Karl-Fredrik Åkerström",
                        "position": ""
                    }
                ],
                "establishment_year": 1939
            },
            {
                "company_name": "ÄNG",
                "address": "Stockholm 1, Flemingg 7. Box 783",
                "phone_number": "08-2346 00",
                "bank_details": {
                    "bankgiro": "48-3452",
                    "postgiro": "815"
                },
                "activity": "Besiktnings- o konsul-teringsverksamhet angående ång-o värmeanläggningar, elektr anläggningar, hissanläggningar, VVS-an-läggningar, kraftavtal mm",
                "owner": "ÅNGPANNEFÖRENINGEN",
                "establishment_year": null
            },
            {
                "company_name": "ÅNGPANNOR & STOKERS, AB",
                "address": "Göteborg 11, Angg 5. Box 11077",
                "phone_number": "031-114152, 1141 53, 119155",
                "bank_details": {
                    "bankgiro": "546-6156",
                    "postgiro": "523191-5"
                },
                "activity": "Säljer från eget lager o verkslager: Kupade gavlar av alla typer o kvaliteter Eldrör Hand-, huvud- o manluckor för ångpannor. tryck- o luftbehållare Rörböjar. rörändar, formstycken, konor. tudelade rörklammor o rörpendlar Rörkompens atorer Snäckskruvelement för skruvtransportörer Flänsar o varmhållfast bult",
                "capital": 50000,
                "key_personnel": [
                    {
                        "name": "Ing Erie Wångmark",
                        "position": ""
                    }
                ],
                "establishment_year": 1956
            },
            {
                "company_name": "SCHÉLE, AB TH",
                "address": "Halmstad 1, Bredg 2. Box 92",
                "phone_number": "035-10 04 4 0",
                "bank_details": {
                    "bankgiro": "530-0447",
                    "postgiro": "33551"
                },
                "activity": "Skeppsmäkleri, befraktning, spedition, lagring",
                "employees": 31,
                "capital": 80000,
                "key_personnel": [
                    {
                        "name": "C Y Roland Christianson",
                        "position": ""
                    }
                ],
                "establishment_year": 1884
            },
            {
                "company_name": "SCHENKER & CO TRANSPORT AB",
                "address": "Stockholm 2, Kornhamnstorg6. Box 2120",
                "phone_number": "08-23 6850",
                "postgiro": "502692",
                "activity": "Internationell spedition, flyttningar o magasinering",
                "annual_turnover": 15500000,
                "capital": 300000,
                "establishment_year": 1953
            },
            {
                "company_name": "maskintellus, ab",
                "address": "VaUentuna, Industriv",
                "phone_number": "0762-241 25",
                "postgiro": "10227",
                "activity": "Transportmateriel",
                "employees": 200,
                "annual_turnover": 17000000,
                "capital": 600000,
                "key_personnel": [
                    {
                        "name": "Gösta Lindahl",
                        "position": ""
                    }
                ],
                "establishment_year": 1947
            }
        ]
    }
}