{
    "original": "TESON, VERKSTADS AB\n\nPnr 600 04\n\nNorrköping 4, Finspångsv 142. Box\n4004. Tel 011-1116 60. Bankgiro\n125-4291. Postgiro 297412-9\nVerksamhet: Mek verkstad. Utför\nlegotillverkning o\nmaskinbearbetning.Tillverkning av\nklordoserings-ventil för avloppsrening\nEtableringsår: 1964.\n\nBRODD AB, BRÖDERNA\n\nPnr 596 00\n\nSkänninge, Idrottsv. Tel\n0142-41050. Bankgiro 130-0185.\nPostgiro 131121-6\n\nVerksamhet: Tillverkar\nsopmaskiner för industrin o kommuner\nAntal anställda: 45\nÅrsomsättning: 6 000 000\nAktiekapital: 100 000\nVerkst dir: Thure Brodd\nEtableringsår: 1890.\n\nBRENDLER &amp; ÅKERBERG AB\n\nPnr 12612\n\nStockholm 42, Box 42116. Elektrav\n53, Hägersten. Tel 08-180390.\nBankgiro 196-0574. Postgiro\n251457-8. Tga Focussing\nVerksamhet: Säljer fotografiska\nartiklar en gros\nÅrsomsättning: 7 000 000\nAktiekapital: 100 000\nVerkst dir: Folke Åkerberg\nEtableringsår: 1945\nOmbildat till aktiebolag 1966.\n\nBREO, AB\n\nPnr 17104\n\nSolna 4, Box 475. Krysshammarv\n10. Tel 08-82 03 80. Bankgiro\n63-2817. Postgiro 707970-0. Tga\nBreobolaget. Telex 10761\nVerksamhet: Importerar o säljer\ntillbehör till tvätterier\nAntal anställda: 6\nÅrsomsättning: 2 500 000\nAktiekapital: 60 000\nVerkst dir. Ingvar Gullwander\nEtableringsår. 1966.\n\nBIBER AB, MAURITZ\n\nPnr 11441\n\nStockholm, Nybrog 66. Tel\n08-67 82 00, 67 60 50. Bankgiro\n11-1991.Postgiro 252820. TgaEmbiber\nVerksamhet: Kontorsmaskinfirma\nAktiekapital: 10 000\nÄgare o chef: Dir Mauritz E Biber.\n\nBIBLIOTEKSTJÄNST AB\n\nPnr 221 01\n\nLund 1, Fack. Tornav 9. Tel\n046-14 04 80. Bankgiro 86-9214.\nPosfc-giro 433587. Telex 32200 BTJLUND S\nVerksamhet: Förmedling av\nbiblioteksbundna böcker, katalogisering\no klassificering av i Sverige\nut-givna böcker samt tryckning o\nförsäljning av katalogkort, utgivande\nav bibliotekslitteratur, försäljning\nav biblioteksmateriel samt en\nkomplett inredningsservice\nAntal anställda: 160\n\nÅrsomsättning: 25 000000\nAktiekapital: 300 000\nVerkst dir: Jan Gumpert\nEtableringsår: 1951.\n\nBIERREGAARD &amp; CO EFTR,\nAB E\n\nPnr 211 20\n\nMalmö, N Neptunig 17-19. Tel\n040-707 80. Bankgiro 87-0108. Postgiro\n38515. Tga Bierregaard.\nTelex 32447 BGAARDS S\nVerksamhet: En gros-handel med\nVVS-tillbehör, oljeeldningsmateriel,\ntekn isoleringsmaterial o -tillbehör,\nmaskinförnödenheter,\nindustrispecialiteter, pneumatik o hydraulik,\nindustrigummi o packningar.\nTillverkar industrispecialiteter,\npackningar o tätningselement\nÅrsomsättning: 10 000 000\nAktiekapital: 720 000\nVerkst dir: Oscar Strid\nDisp: Sigfrid Kihlberg\nDir-ass: Göran Renée\nEtableringsår: 1931.\n\nBOSÄGENS AB\n\nPnr 81600\n\nOckelbo, Nordanåsbo 3285. Tel\n0297-440 31, 440 09. Bankgiro\n23-7905. Postgiro 31997\nVerksamhet: Såg o hyvleri.\nTillverkar o säljer sågade o hyvlade\nträvaror samt fritidshus\nAntal anställda: 25\nÅrsomsättning: 1100 000\nAktiekapital: 150000\nVerkst dir: Rune Mark\nEtableringsår: 1928.\n\nSVENSKA FOODCO, AB\n\nPnr 290 34\n\nFjälkinge, Box 45. Tel 044-504 40.\nBankgiro 344-9857. Postgiro\n291001-6\n\nVerksamhet: Konsulterande\ningenjörsfirma för maskinutrustningar\ninom livsmedelsindustrin,\nspeciellt maskiner för hantering o\nförädling av potatis.\nTillverkar o exporterar\nskalanläggningar, stek- o\nfriteringsan-läggningar, kontinuerliga kokare,\nkontinuerliga sterilisatorer,\nkontinuerliga burkkylare,\nkontinuerliga tryck-kokare, ångkokare,\nvattenblanschörer, kokgrytor med\nrörverk, svävbäddstorkor,\npneumatiska torkor, blandare av\ndobbel ribbon type,\nkonditione-ringsutrustning för potatislager,\nrökanläggningar\nVarunamn: Foodco\nAntal anställda: 15\nAktiekapital: 5 000\nStyrelse: Dir Sixten Holmquist\n(ordf), ing Sven Gunnar Grufstedt\nVerkst din Sven Gunnar Grufstedt\nEtableringsår: 1965.\n\nTOL LO PUMPINDUSTRI\n\nPnr 400 30\n\nGöteborg 11, Box 11036. Tel\n031-13 75 30. Bankgiro 446-1828.\nPostgiro 424487-7. Tga Tollo\nVerksamhet: Pumpar för livsmedel\no frätande syror\nChef: Dir Christina Olsson\nEtableringsår: 1957.\n\nSTOCKHOLMS SPARBANK\n\nPnr 103 26\n\nStockholm 16, Box 16318. Fredsg 9.\n\nTel 08-24 60 60. Bankgiro 981-3270.\n\nPostgiro 1201-3\n\nVerksamhet: Bankrörelse\n\nAntal anstäUda: 529\n\nVerkst dir: Bankdir Bertil Sjöstrand\n\nEtableringsår: 1821.\n\nINDUSTRIFILTER AB\n\nPnr 50103\n\nBorås 1, Göteborgsv. Box 155. Tel\n033-548 60. Bankgiro 533-6110.\nPostgiro 47236-5. Tga\nIndustri-filter. Telex 36070 INFIL S\n\nVerksamhet: Tillverkar apparater\no anläggningar för stoftavskiljning\no rökgasrening, stålskorstenar,\nventilations- o industrifläktar,\nluftfUter av olika slag samt\ninblås-ningsorgan o standarddetaljer för\nventilationsanläggningar\n\n[-INDUSTRIGAS-FURENINGEN-]\n\n{+INDUSTRIGAS-\nFURENINGEN+} UPA\n\nPnr 113 21\n\nStockholm, Torsg 24. Tel\n08-22 30 60. Bankgiro 63-1023.\nPostgiro 1213. Tga Gasapparat\nVerksamhet: Försäljning,\nkonsultation, gasapparater av alla slag\nVerkst dir: Civiling Claes Lindgren\nFörsäljn-ing:r: Björn Andersson,\nGeorg Engnes, Bengt Sundberg\nEtableringsår: 1938.\n\nEDSTRÖM AB, SIMON\n\nPnr 201 23\n\nMalmö 1, Skeppsbron 7. Box 366.\nTel 040-718 10. Bankgiro 640-1137\nPostgiro 14173-9. Tga Edström.\nTelex 32310, 32610 (befraktning)\n\nVerksamhet: Auktoriserade\nspedi-törer o skeppsklarerare.\nBefraktning\n\nAntal anställda: 150\nAktiekapital: 750 000\nVerkst dir: Ake Widner\nFtableringsår: 1919.\n\nEDWARDS &amp; CO AB, HJ\n\nPnr 403 13\n\nGöteborg 2, Stora Badhusg 20.\nBox 2131. Tel 031-17 02 05.\nPostgiro 40757. Telex 2365\nedwards-comp gbg. Tga Edwardscomp\nVerksamhet: Järn, stål,\nfartygsmaterial, tunn-, medium- o grovplåt\nAntal anställda: 25\nÅrsomsättning: 65 000 000\nAktiekapital: 1000 000\nVerkst dir: Gustaf Svensson\nEtableringsår: 1938.",
    "structured": {
        "1": {
            "company_name": "TESON, VERKSTADS AB",
            "pnr": "600 04",
            "address": "Norrköping 4, Finspångsv 142, Box 4004",
            "phone_number": "011-1116 60",
            "bank_details": {
                "bankgiro": "125-4291",
                "postgiro": "297412-9"
            },
            "activity": "Mek verkstad. Utför legotillverkning och maskinbearbetning. Tillverkning av klordoserings-ventil för avloppsrening",
            "establishment_year": 1964
        },
        "2": {
            "company_name": "BRODD AB, BRÖDERNA",
            "pnr": "596 00",
            "address": "Skänninge, Idrottsv.",
            "phone_number": "0142-41050",
            "bank_details": {
                "bankgiro": "130-0185",
                "postgiro": "131121-6"
            },
            "activity": "Tillverkar sopmaskiner för industrin och kommuner",
            "employees": 45,
            "annual_turnover": 6000000,
            "capital": 100000,
            "establishment_year": 1890
        },
        "3": {
            "company_name": "BRENDLER & ÅKERBERG AB",
            "pnr": "12612",
            "address": "Stockholm 42, Box 42116, Elektrav 53, Hägersten",
            "phone_number": "08-180390",
            "bank_details": {
                "bankgiro": "196-0574",
                "postgiro": "251457-8"
            },
            "activity": "Säljer fotografiska artiklar en gros",
            "annual_turnover": 7000000,
            "capital": 100000,
            "establishment_year": 1945
        },
        "4": {
            "company_name": "BREO, AB",
            "pnr": "17104",
            "address": "Solna 4, Box 475, Krysshammarv 10",
            "phone_number": "08-82 03 80",
            "bank_details": {
                "bankgiro": "63-2817",
                "postgiro": "707970-0"
            },
            "activity": "Importerar och säljer tillbehör till tvätterier",
            "employees": 6,
            "annual_turnover": 2500000,
            "capital": 60000,
            "establishment_year": 1966
        },
        "5": {
            "company_name": "BIBER AB, MAURITZ",
            "pnr": "11441",
            "address": "Stockholm, Nybrog 66",
            "phone_number": "08-67 82 00, 67 60 50",
            "bank_details": {
                "bankgiro": "11-1991",
                "postgiro": "252820"
            },
            "activity": "Kontorsmaskinfirma",
            "capital": 10000
        },
        "6": {
            "company_name": "BIBLIOTEKSTJÄNST AB",
            "pnr": "221 01",
            "address": "Lund 1, Fack. Tornav 9",
            "phone_number": "046-14 04 80",
            "bank_details": {
                "bankgiro": "86-9214",
                "postgiro": "433587"
            },
            "activity": "Förmedling av biblioteksbundna böcker, katalogisering och klassificering av i Sverige utgivna böcker samt tryckning och försäljning av katalogkort, utgivande av bibliotekslitteratur, försäljning av biblioteksmateriel samt en komplett inredningsservice",
            "employees": 160,
            "annual_turnover": 25000000,
            "capital": 300000,
            "establishment_year": 1951
        },
        "7": {
            "company_name": "BIERREGAARD & CO EFTR, AB E",
            "pnr": "211 20",
            "address": "Malmö, N Neptunig 17-19",
            "phone_number": "040-707 80",
            "bank_details": {
                "bankgiro": "87-0108",
                "postgiro": "38515"
            },
            "activity": "En gros-handel med VVS-tillbehör, oljeeldningsmateriel, tekn isoleringsmaterial och -tillbehör, maskinförnödenheter, industrispecialiteter, pneumatik och hydraulik, ind.  JsonResponse: ustriegummi och packningar. Tillverkar industrispecialiteter, packningar och tätningselement",
            "annual_turnover": 10000000,
            "capital": 720000,
            "establishment_year": 1931
        },
        "8": {
            "company_name": "BOSÄGENS AB",
            "pnr": "81600",
            "address": "Ockelbo, Nordanåsbo 3285",
            "phone_number": "0297-440 31, 440 09",
            "bank_details": {
                "bankgiro": "23-7905",
                "postgiro": "31997"
            },
            "activity": "Såg och hyvleri. Tillverkar och säljer sågade och hyvlade trävaror samt fritidshus",
            "employees": 25,
            "annual_turnover": 1100000,
            "capital": 150000,
            "establishment_year": 1928
        },
        "9": {
            "company_name": "SVENSKA FOODCO, AB",
            "pnr": "290 34",
            "address": "Fjälkinge, Box 45",
            "phone_number": "044-504 40",
            "bank_details": {
                "bankgiro": "344-9857",
                "postgiro": "291001-6"
            },
            "activity": "Konsulterande ingenjörsfirma för maskinutrustningar inom livsmedelsindustrin, speciellt maskiner för hantering och förädling av potatis. Tillverkar och exporterar skalanläggningar, stek- och friteringsanläggningar, kontinuerliga kokare, kontinuerliga sterilisatorer, kontinuerliga burkkylare, kontinuerliga tryck-kokare, ångkokare, vattenblanschörer, kokgrytor med rörverk, svävbäddstorkor, pneumatiska torkor, blandare av dobbel ribbon type, konditioneringsutrustning för potatislager, rökanläggningar",
            "employees": 15,
            "capital": 5000,
            "establishment_year": 1965
        },
        "10": {
            "company_name": "TOL LO PUMPINDUSTRI",
            "pnr": "400 30",
            "address": "Göteborg 11, Box 11036",
            "phone_number": "031-13 75 30",
            "bank_details": {
                "bankgiro": "446-1828",
                "postgiro": "424487-7"
            },
            "activity": "Pumpar för livsmedel och frätande syror",
            "key_personnel": [
                {
                    "name": "Christina Olsson",
                    "position": "Chef"
                }
            ],
            "establishment_year": 1957
        },
        "11": {
            "company_name": "STOCKHOLMS SPARBANK",
            "pnr": "103 26",
            "address": "Stockholm 16, Box 16318, Fredsg 9",
            "phone_number": "08-24 60 60",
            "bank_details": {
                "bankgiro": "981-3270",
                "postgiro": "1201-3"
            },
            "activity": "Bankrörelse",
            "employees": 529,
            "capital": 0,
            "establishment_year": 1821
        },
        "12": {
            "company_name": "INDUSTRIFILTER AB",
            "pnr": "50103",
            "address": "Borås 1, Göteborgsv. Box 155",
            "phone_number": "033-548 60",
            "bank_details": {
                "bankgiro": "533-6110",
                "postgiro": "47236-5"
            },
            "activity": "Tillverkar apparater och anläggningar för stoftavskiljning och rökgasrening, stålskorstenar, ventilationsoch industrifläktar, luftfilter av olika slag samt inblåsningsorgan och standarddetaljer för ventilationsanläggningar"
        },
        "13": {
            "company_name": "INDUSTRIGAS-FURENINGEN UPA",
            "pnr": "113 21",
            "address": "Stockholm, Torsg 24",
            "phone_number": "08-22 30 60",
            "bank_details": {
                "bankgiro": "63-1023",
                "postgiro": "1213"
            },
            "activity": "Försäljning, konsultation, gasapparater av alla slag",
            "establishment_year": 1938
        },
        "14": {
            "company_name": "EDSTRÖM AB, SIMON",
            "pnr": "201 23",
            "address": "Malmö 1, Skeppsbron 18, Box 366",
            "phone_number": "040-718 10",
            "bank_details": {
                "bankgiro": "640-1137",
                "postgiro": "14173-9"
            },
            "activity": "Auktoriserade speditörer och skeppsklarerare. Befraktning",
            "employees": 150,
            "capital": 750000,
            "establishment_year": 1919
        },
        "15": {
            "company_name": "EDWARDS & CO AB, HJ",
            "pnr": "403 13",
            "address": "Göteborg 2, Stora Badhusg 20, Box 2131",
            "phone_number": "031-17 02 05",
            "postgiro": "40757",
            "activity": "Järn, stål, fartygsmaterial, tunn-, medium- och grovplåt",
            "employees": 25,
            "annual_turnover": 65000000,
            "capital": 1000000,
            "establishment_year": 1938
        }
    }
}