{
    "original": "MERKANTIL TEXTIL AB\n\nPnr 112 34\n\nStockholm, Sankt Eriks g 48. Tel\n08-23 02 55. Tga Mercantile\nVerksamhet Levererar jumpers o\nkoftor till detaljister över hela landet\nVerkst dir: Bernhard Schutterman\nEtableringsår: 1945.\n\nLENNARTSFORS AB\n\nPnr 672 00\n\nÅrjäng, Lennartsfors. Tel\n0573-30200. Bankgiro 10-0032. Postgiro\n84905-9. Tga Biesert, Arvika\nVerksamhet: Kraftverk o\nel-distri-bution\n\nAntal anställda: 32\nÅrsomsättning: 2 200 000\nAktiekapital: 630 000\nStyrelse: Bankdir Olof Erlandson\n(ordf), disp Nils Biesèrt,\nsocialläkare C-G Berglin, fru Jenny\nFärn-ström, greve Gustaf Bonde\nVerkst dir. Ingvar Johannesson\nEtableringsår: 1911.\n\nLENNARTSFORS MEKANISKA\nVERKSTAD, AB\n\nPnr 67200\n\nÅrjäng, Lennartsfors. Tel\n0573-302 00. Bankgiro 100-0900.\nPostgiro 387590-3. Tga Biesert\nVerksamhet: Tillverkar\nduplice-ringsmaskiner, detaljer till\nbokförings- o räknemaskiner, drag- o\ntryckfjädrar\nAntal anställda: 105\nÅrsomsättning: 5 100000\nAktiekapital: 500 000\nStyrelse: Dir Gunnar Ericsson\n(ordf), dir Gunnar Larsson, dir\nLennart von Kantzow, disp Nils\nBiesèrt, socialläkare C-G Berglin,\ndir Ingvar Johannesson\nVerkst dir. Ingvar Johannesson\nEtableringsår: 1947.\n\nLENNCO-PLAST\nINGENJÖRSFIRMAN\n\nPnr 43104\n\nMölndal 4, Videbog 4. Box 4018.\nTel 031-27 46 66. Bankgiro\n550-1036. Postgiro 628758-5\nVerksamhet: Tillverkar o säljer\nplastdetaljer. Designavdelning\nChef: Ing Allan Lennerbert\nEtableringsår: 1965.\n\nLENNQVIST MEK VERKSTAD,\nAB ROLF\n\nPnr 690 72\n\nSköllersta, Björka. Tel\n019-23 62 00, 23 62 63\nVerksamhet: Järn o\nstålkonstruktioner\n\nAktiekapital: 10 000\nVerkst dir: Ing Rolf Lennqvist\nEtableringsår: 1959.\n\nmalmqvist ab, fritz\n\nPnr 251 02\n\nHelsingborg 1, Box 7. Trädgårdsg\n15. Tel 042-1206 40. Bankgiro\n863-9676. Postgiro 23219-9\nVerksamhet: Importerar textil,\nmanufaktur o enklare konfektion\nAntal anställda: 20\nÅrsomsättning: 3 300 000\nAktiekapital: 112 500\nVerkst dir: Carl Henrik Johnsson\nEtableringsår: 1871.\n\nCONSIVA AB\n\nPnr 421 22\n\nVästra Frölunda 1, Box 125.\nFrö-husg 8. Tel 031-45 00 70. Tga\nAda-company. Telex 20833 ADACO S\nVerksamhet: Moderbolag för bl a\nAdaco AB, Ateka AB, Mavello AB ,\nScandistor AB, AB Fransk-Svenska\nParfymkompaniet, Adaco AS,\nKöpenhamn, Adaco Oy AB,\nHelsingfors\n\nAntal anställda: 270\nÅrsomsättning: 175 000 000\nAktiekapital: 1500 000\nStyrelseordf: Dir Tage Nyström\nVerkst dir: Civilekonom Owe\nSandegren\n\nDotterbolag till AB Fortia.\n\nCON SOL I DATOR, AB\n\nPnr 11143\n\nStockholm, Kungsg 6. Tel\n08-21 99 77. Postgiro 54071-6\nVerksamhet: Värdepapperförvaltning\nAktiekapital: 750 000\nVerkst dir: Adv Töre Flodin\nEtableringsår: 1914.\n\nCONSOLIT AB,\nINGENIORSFIRMA\n\nPnr 104 22\n\nStockholm 22, Kungsholms\nHamnplan 2. Fack. Tel 08-54 04 45.\nBankgiro 72-3635. Postgiro\n159752-5. Tga Consolit.\nTelex 19952\n\nVerksamhet: Tillverkar maskiner\nför tråddragerier\nAntal anställda: 8\nÅrsomsättning: 800 000\nAktiekapital: 15 000\nVerkst dir: Ing Conrad Solitair\nEtableringsår: 1941.\n\nge-pe verken\n\nPnr 801 03\n\nGävle 1, Sjätte Tvärg 31. Box 212.\nTel 026-1194 00. Bankgiro\n78-3745. Postgiro 572125. Tga\nGepe-verken\n\nVerksamhet: Tillverkar fönster,\npersienner o ridåer mellan glas\nÄgare o chef: Arne Ottefalk\nEtableringsår: 1949.\n\nGOTE-MOBLER I NÄSSJÖ AB\n\nPnr 571 00\n\nNässjö, Industrig 40. Box 188.\nTel 0380-181 60. Bankgiro\n452-9574. Postgiro 297472-3\nVerksamhet: Tillverkar o säljer\nstoppmöbler\nAntal anställda: 50\nÅrsomsättning: 6 000 000\n.Aktiekapital: 100 000\nVerkst dir: Göte Ohrskog\nEtableringsår: 1953.\n\nRIFINN.TRYCK\n\nPnr 686 00\n\nSunne, Ekbyv 16. Box 85. Tel\n0565-105 85. Bankgiro 88-2812. Postgiro\n331614-8\n\nVerksamhet: Utför affärs- o\nreklamtryck\nChef: Knut E Nilsson\nEtableringsår: 1946.\n\nSJUBERG &amp; CO AB, IVAN\n\nPnr 60103\n\nNorrköping 1, Hospitalsg 15. Box\n174. Tel 011-1233 55, 188803.\nBankgiro 609-8495. Postgiro\n206662-9. Tga Ilsco.\nTelex 64339 ILSCO S\nVerksamhet: Agenturer i textilvar\nror, såsom vävnader, trikå o\nkonfektion\n\nAntal anställda: 6\n\nAktiekapital: 25 000\nVeikst dir: Lars Aronsson\nEtableringsår. 1915.\n\nSJUBLOM &amp; SUN ER\nMEK VERKSTAD och\nFURNICKLINGSFABRIK\n\nPnr 890 30\n\nHöglandssjön, Box 5294. Tel\n0660-129 78, 11992. Bankgiro 77-1591.\nPostgiro 366443\n\nVerksamhet: Förnicklingsarbeten\nÄgare o chefer: Gösta Sjöblom,\nLennart Sjöblom.\n\nSJUBLOM KB, IVAR\n\nPnr 102 52\n\nStockholm 27, Banérg 77. Box\n27130. Tel 08-63 1650. Bankgiro\n700-1506. Postgiro 150890-2. Tga\nSjoblomaskin. Telex 10680\nVerksamhet: Maskinförsäljning.\nTryckluftmateriel: kompressorer,\nblåsmaskiner, tryckluft verktyg.\nFilter. Pressar, gradsaxar,\nstansverktyg, koordinatstansmaskiner.\nUt-rustningar för avloppsvattenrening.\nCementinjektionspumpar,\ncolloidce-mentblandare\n\nLager Stockholm VA, Sveav 107.\nTel 08-3205 22\n\nVarunamn: Broomwade, Böhler,\nColcrete, Deka, Desoutter, Fico,\nHäny, Klein, Raskin, Schumacher,\nSimplex, Sioux, Strippit-Contimec\nChefer: Gunnar Ljung, Ivar\nÖsterholm\n\nEtableringsår 1931.\n\nSUN\n\nÅrsomsättning: 2100 000\nVerkst dir: Oscar Sundin\nEtableringsår: 1933.\n\nA-C-T PRODUKTER AB\n\nPnr 441 00\n\nAlingsås, Nya Nolhaga. Tel\n0322-14175. Bankgiro 100-5119.\nPostgiro 30733-0\n\nVerksamhet: Klubbor, karameller,\ncocos o chokladbollar m m\nAntal anställda: 25\nÅrsomsättning: 5 000 000\nAktiekapital: 30 000\nVerkst dir: Axel Ternblom\nEtableringsår: 1951.",
    "structured": {
        "1": {
            "company_name": "MERKANTIL TEXTIL AB",
            "address": "Stockholm, Sankt Eriks g 48",
            "phone_number": "08-23 02 55",
            "activity": "Levererar jumpers o koftor till detaljister över hela landet",
            "key_personnel": [
                {
                    "name": "Bernhard Schutterman",
                    "position": "Verkst dir"
                }
            ],
            "establishment_year": 1945
        },
        "2": {
            "company_name": "LENNARTSFORS AB",
            "address": "Årjäng, Lennartsfors",
            "phone_number": "0573-30200",
            "bank_details": {
                "bankgiro": "10-0032",
                "postgiro": "84905-9"
            },
            "activity": "Kraftverk o el-distribution",
            "employees": 32,
            "annual_turnover": 2200000,
            "capital": 630000,
            "key_personnel": [
                {
                    "name": "Olof Erlandson",
                    "position": "Bankdir"
                },
                {
                    "name": "Nils Biesèrt",
                    "position": "disp"
                },
                {
                    "name": "C-G Berglin",
                    "position": "socialläkare"
                },
                {
                    "name": "Jenny Färn-ström",
                    "position": "fru"
                },
                {
                    "name": "Gustaf Bonde",
                    "position": "greve"
                },
                {
                    "name": "Ingvar Johannesson",
                    "position": "Verkst dir"
                }
            ],
            "establishment_year": 1911
        },
        "3": {
            "company_name": "LENNARTSFORS MEKANISKA VERKSTAD, AB",
            "address": "Årjäng, Lennartsfors",
            "phone_number": "0573-302 00",
            "bank_details": {
                "bankgiro": "100-0900",
                "postgiro": "387590-3"
            },
            "activity": "Tillverkar duplice-ringsmaskiner, detaljer till bokförings- o räknemaskiner, drag- o tryckfjädrar",
            "employees": 105,
            "annual_turnover": 5100000,
            "capital": 500000,
            "key_personnel": [
                {
                    "name": "Gunnar Ericsson",
                    "position": "Dir"
                },
                {
                    "name": "Gunnar Larsson",
                    "position": "dir"
                },
                {
                    "name": "Lennart von Kantzow",
                    "position": "dir"
                },
                {
                    "name": "Nils Biesèrt",
                    "position": "disp"
                },
                {
                    "name": "C-G Berglin",
                    "position": "socialläkare"
                },
                {
                    "name": "Ingvar Johannesson",
                    "position": "Verkst dir"
                }
            ],
            "establishment_year": 1947
        },
        "4": {
            "company_name": "LENNCO-PLAST INGENJÖRSFIRMAN",
            "address": "Mölndal 4, Videbog 4. Box 4018",
            "phone_number": "031-27 46 66",
            "bank_details": {
                "bankgiro": "550-1036",
                "postgiro": "628758-5"
            },
            "activity": "Tillverkar o säljer plastdetaljer. Designavdelning",
            "key_personnel": [
                {
                    "name": "Ing Allan Lennerbert",
                    "position": "Chef"
                }
            ],
            "establishment_year": 1965
        },
        "5": {
            "company_name": "LENNQVIST MEK VERKSTAD, AB ROLF",
            "address": "Sköllersta, Björka",
            "phone_number": "019-23 62 00, 23 62 63",
            "activity": "Järn o stålkonstruktioner",
            "capital": 10000,
            "key_personnel": [
                {
                    "name": "Ing Rolf Lennqvist",
                    "position": "Verkst dir"
                }
            ],
            "establishment_year": 1959
        },
        "6": {
            "company_name": "malmqvist ab, fritz",
            "address": "Helsingborg 1, Box 7. Trädgårdsg 15",
            "phone_number": "042-1206 40",
            "bank_details": {
                "bankgiro": "863-9676",
                "postgiro": "23219-9"
            },
            "activity": "Importerar textil, manufaktur o enklare konfektion",
            "employees": 20,
            "annual_turnover": 3300000,
            "capital": 112500,
            "key_personnel": [
                {
                    "name": "Carl Henrik Johnsson",
                    "position": "Verkst dir"
                }
            ],
            "establishment_year": 1871
        },
        "7": {
            "company_name": "CONSIVA AB",
            "address": "Västra Frölunda 1, Box 125. Frö-husg 8",
            "phone_number": "031-45 00 70",
            "activity": "Moderbolag för bl a Adaco AB, Ateka AB, Mavello AB, Scandistor AB, AB Fransk-Svenska Parfymkompaniet, Adaco AS, Köpenhamn, Adaco Oy AB, Helsingfors",
            "employees": 270,
            "annual_turnover": 175000000,
            "capital": 1500000,
            "key_personnel": [
                {
                    "name": "Tage Nyström",
                    "position": "Styrelseordf"
                },
                {
                    "name": "Owe Sandegren",
                    "position": "Verkst dir"
                }
            ]
        },
        "8": {
            "company_name": "CON SOL I DATOR, AB",
            "address": "Stockholm, Kungsg 6",
            "phone_number": "08-21 99 77",
            "postgiro": "54071-6",
            "activity": "Värdepapperförvaltning",
            "capital": 750000,
            "key_personnel": [
                {
                    "name": "Adv Töre Flodin",
                    "position": "Verkst dir"
                }
            ],
            "establishment_year": 1914
        },
        "9": {
            "company_name": "CONSOLIT AB, INGENIORSFIRMA",
            "address": "Stockholm 22, Kungsholms Hamnplan 2",
            "phone_number": "08-54 04 45",
            "bank_details": {
                "bankgiro": "72-3635",
                "postgiro": "159752-5"
            },
            "activity": "Tillverkar maskiner för tråddragerier",
            "employees": 8,
            "annual_turnover": 800000,
            "capital": 15000,
            "key_personnel": [
                {
                    "name": "Ing Conrad Solitair",
                    "position": "Verkst dir"
                }
            ],
            "establishment_year": 1941
        },
        "10": {
            "company_name": "ge-pe verken",
            "address": "Gävle 1, Sjätte Tvärg 31. Box 212",
            "phone_number": "026-1194 00",
            "bank_details": {
                "bankgiro": "78-3745",
                "postgiro": "572125"
            },
            "activity": "Tillverkar fönster, persienner o ridåer mellan glas",
            "key_personnel": [
                {
                    "name": "Arne Ottefalk",
                    "position": "Ägare o chef"
                }
            ],
            "establishment_year": 1949
        },
        "11": {
            "company_name": "GOTE-MOBLER I NÄSSJÖ AB",
            "address": "Nässjö, Industrig 40. Box 188",
            "phone_number": "0380-181 60",
            "bank_details": {
                "bankgiro": "452-9574",
                "postgiro": "297472-3"
            },
            "activity": "Tillverkar o säljer stoppmöbler",
            "employees": 50,
            "annual_turnover": 6000000,
            "capital": 100000,
            "key_personnel": [
                {
                    "name": "Göte Ohrskog",
                    "position": "Verkst dir"
                }
            ],
            "establishment_year": 1953
        },
        "12": {
            "company_name": "RIFINN.TRYCK",
            "address": "Sunne, Ekbyv 16. Box 85",
            "phone_number": "0565-105 85",
            "bank_details": {
                "bankgiro": "88-2812",
                "postgiro": "331614-8"
            },
            "activity": "Utför affärs- o reklamtryck",
            "key_personnel": [
                {
                    "name": "Knut E Nilsson",
                    "position": "Chef"
                }
            ],
            "establishment_year": 1946
        },
        "13": {
            "company_name": "SJUBERG & CO AB, IVAN",
            "address": "Norrköping 1, Hospitalsg 15. Box 174",
            "phone_number": "011-1233 55, 188803",
            "bank_details": {
                "bankgiro": "609-8495",
                "postgiro": "206662-9"
            },
            "activity": "Agenturer i textilvar ror, såsom vävnader, trikå o konfektion",
            "employees": 6,
            "capital": 25000,
            "key_personnel": [
                {
                    "name": "Lars Aronsson",
                    "position": "Veikst dir"
                }
            ],
            "establishment_year": 1915
        },
        "14": {
            "company_name": "SJUBLOM & SUN ER MEK VERKSTAD och FURNICKLINGSFABRIK",
            "address": "Höglandssjön, Box 5294",
            "phone_number": "0660-129 78, 11992",
            "bank_details": {
                "bankgiro": "77-1591",
                "postgiro": "366443"
            },
            "activity": "Förnicklingsarbeten",
            "key_personnel": [
                {
                    "name": "Gösta Sjöblom",
                    "position": "Ägare o chefer"
                },
                {
                    "name": "Lennart Sjöblom",
                    "position": "Ägare o chefer"
                }
            ]
        },
        "15": {
            "company_name": "SJUBLOM KB, IVAR",
            "address": "Stockholm 27, Banérg 77. Box 27130",
            "phone_number": "08-63 1650",
            "bank_details": {
                "bankgiro": "700-1506",
                "postgiro": "150890-2"
            },
            "activity": "Maskinförsäljning. Tryckluftmateriel: kompressorer, blåsmaskiner, tryckluft verktyg. Filter. Pressar, gradsaxar, stansverktyg, koordinatstansmaskiner. Ut-rustningar för avloppvattenrening. Cementinjektionspumpar, colloidce-mentblandare",
            "key_personnel": [
                {
                    "name": "Gunnar Ljung",
                    "position": "Chefer"
                },
                {
                    "name": "Ivar Österholm",
                    "position": "Chefer"
                }
            ],
            "establishment_year": 1931
        },
        "16": {
            "company_name": "SUN",
            "annual_turnover": 2100000,
            "key_personnel": [
                {
                    "name": "Oscar Sundin",
                    "position": "Verkst dir"
                }
            ],
            "establishment_year": 1933
        },
        "17": {
            "company_name": "A-C-T PRODUKTER AB",
            "address": "Alingsås, Nya Nolhaga",
            "phone_number": "0322-14175",
            "bank_details": {
                "bankgiro": "100-5119",
                "postgiro": "30733-0"
            },
            "activity": "Klubbor, karameller, cocos o chokladbollar m m",
            "employees": 25,
            "annual_turnover": 5000000,
            "capital": 30000,
            "key_personnel": [
                {
                    "name": "Axel Ternblom",
                    "position": "Verkst dir"
                }
            ],
            "establishment_year": 1951
        }
    }
}