{
    "original": "ÅLO-MASKINER, AB\n\nPnr 905 90\n\nUmeå, Brännland. Tel 090-30100.\nBankgiro 35-4 174. Postgiro 460515.\nTelex 6768. Tga Alomachine\nVerksamhet: Tillverkar\nhydrauliska frontlastare för traktorer\nAntal anställda: 130\nÅrsomsättning: 13 000 000\nAktiekapital: 325 000\nVerkst din K R Åström\nEtableringsån 1950.\n\nTOFTANSSÅGVERK. AB\n\nPnr 790 15\n\nSundbom, Postl 1966. Tel\n023-61040. Bankgiro 464-2690.\nPostgiro 21431-2\n\nVerksamhet: Köper skog på rot,\ntimmer o massaved. Tillverkar o\nsäljer sågade o hyvlade trävaror\nAntal anställda: 25\nÅrsomsättning: 3 000 000\nAktiekapital: 100 000\nStyrelse: f Disp E J Lindberg\n(ordf), ing Tage Lindberg, fru\nKarin Lindberg\nVerkst dlr: Tage Lindberg\nEtableringsån 1923.\n\nMARMOR, AB\n\nPnr 16171\n\nBromma, Bällstav 65. Tel\n08-28 3644, 29 90 16. Bankgiro74-3584.\nPostgiro 163161-3.\nTgaMarble-works, Stockholm\nVerksamhet: Tillverkar o säljer\ntrappor, golv o fönsterbänkar\nAktiekapital: 10 000\nVerkst dir: H I Bergenborg\nEtableringsår: 1939.\n\nSUNDSTRÖM &amp; SON AB, C G\n\nPnr 11123\n\nStockholm, Dalag 6.Tel 08-23 3310.\nBankgiro 560-5100. Postgiro 3461-1.\nTga Klaede. Telex 17575\nVerksamhet: Säljer ylletyger,\nlinne- o bomullsvaror en gros\nAntal anställda: 20\nÅrsomsättning: 4 350 000\nAktiekapital: 350 000\nStyrelse: Adv Olof Christner (ordf),\ndlr Gösta Qvennerstedt, dir Sven\nQvennerstedt\n\nVerkst dir: Gösta Qvennerstedt\nEtableringsår: 1839.\n\nSUNDSTRUM AB, BYGGNADS.\nFIRMAN ESKIL\n\nPnr 775 01\n\nKrylbo 1, Stationsg 31. Box 57. Tel\n0226-118 00. Bankgiro 23-3542.\nPostgiro 265087\nVerksamhet: Husbyggnad\nAntal anställda: 70\nÅrsomsättning: 6 000 000\nAktiekapital: 100 000\nVerkst dir: Eskil Sundström\nEtableringsår: 1939.\n\nSUNDSTRÖMS BOKTRYCKERI\no BOK FURLAG, HJ\n\nPnr 116 53\n\nStockholm, Rosenlundsg 52. Tel\n08-84 76 48, 84 76 49. Bankgiro\n537-0192. Postgiro 601045-8\nVerksamhet: Boktryck,\nblanketttryck, reklamtryck o tidskrifter\nEtableringsår: 1920.\n\nSALTIMPORTEN, Ab\n\nPnr 201 21\n\nMalmö 1, Box 187. Grimsbyg 24.\nTel 040-703 00. Bankgiro 852-6188.\nPostgiro 41232-0. Tga Saltimport\nVerksamhet: Säljer allt i salt,\nklorcalcium, lantbrukskemikalier,\nsnäckskal, foderkalk o soda\nAktiekapital: 180 000\nVerkst dir: Per Olof Hanson\nEtableringsår: 1916.\n\nSUM\n\nÄgare o chefer: Lennart Frödell,\nJohn P Landing\nEtableringsår 1961.\n\nSTÅNGA TAKTEGELFABRIK,\nBERGSTRÖM &amp; CO\n\nPnr 620 13\n\nStånga, Box 29. Tel 0498-824 29.\nPostgiro 90524\n\nVerksamhet: Betongrör o ringar\nsamt cementhålsten\nAntal anställda: 12\nÅrsomsättning: 600 000\nÄgare o chef: Rune Bergström\nEtableringsår: 1924.\n\nHULTGREN &amp; CO, AB ERIC\n\nPnr 40316\n\nGöteborg 2, Skeppsbron 4. Box\n2409. Tel 031-17 25 65. Bankgiro\n511-6280. Postgiro 41166-0. Tga\nGrenhult. Telex 2576 GRENHUL S\nVerksamhet: Spedition,\nskepps-mäkleri\n\nAktiekapital: 100000\nVerkst dir: Albert Sprimont\nEtableringsår: 1917.\n\nHULTGRENS JÄRN- &amp;\nMETALLTRADSFABRIK, I\n\nPnr 115 34\n\nStockholm, Armfeltsg 26. Tel\n08-67 7125\n\nVerksamhet: Reklamartiklar, allt\nförekommande i branschen\ntillverkade av järntråd o järn\nChef: Ingemar Hultgren.\n\nHULTGRENS\nMÖBEL-FABRIKER AB, J\n\nPnr 560 27\n\nTenhult, Box 33. Tel 036-916 05\nVerksamhet: Tillverkar byråar,\nhurtsar o toilettbord\nAntal anstäUda: 45\nÅrsomsättning: 5 000 000\nAktiekapital: 94 000\nVerkst dir: Josef Hultgren\nEtableringsår: 1943.\n\nHULTGRENS MÖBELFABRIK,\nAB SETH\n\nPnr 57100\n\nNässjö, Egnahemsg 27. Tel\n0380-113 49. Bankgiro 452-7388.\nPostgiro 271663-7\n\nVerksamhet: Tillverkar bäddsoffor\nAntal anställda: 12\nÅrsomsättning: 900 000\nAktiekapital: 30 000\nVerkst dir: Seth Hultgren\nEtableringsår: 1942.\n\nEtableringsår. 1967\nSysterbolag: Folke Nordins\nRevisionsbyrå AB, Göteborg.\n\nHULTMANSPATENTBYRÅ AB\n\nPnr 102 44\n\nStockholm 5, Linnég 15. Box 5165.\nTel 08-67 52 03, 67 52 04. Bankgiro\n745-4382. Postgiro 261015-2\nVerksamhet: Patent- o\nvarumärkesombuds verksamhet\nAntal anstäUda: 8\nAktiekapital: 15000\nVerkst dir Ing Bengt\nAvellan-Hultman\n\nEtableringsår 1965.\n\nTOT\n\nTOTEBO INDUSTRIER, AB\n\nPnr 590 91\n\nHjorted, Totebo. Tel 0490-61000,\n610 01, 610 02. Bankgiro 452-0409.\nPostgiro 36464-6\nVerksamhet: Tillverkar radio- o\nTV-möbler samt hemmöbler\nAntal anställda: 190\nÅrsomsättning: 9 000 000\nAktiekapital: 110 000\nVerkst dir: Ing C-H Larsson\nFörsäljn-chef: Ing C H Larsson\nInköpschef: Olof Järesjö\nEtableringsår: 1912.\n\nPRESTOVERKENI\nMOTALA AB\n\nPnr 591 00\n\nMotala, Norrsten. Tel 0141-31112.\nTga Presto\n\nVerksamhet: Tillverkar\nvärmeledningspannor o varmvattenberedare\nVarunamn: Presto\nÅrsomsättning: 1000 000\nVerkst dir: Ivar Werner\nEtableringsår: 1926.\n\nHERTZ &amp; CO, AB\n\nPnr 400 20\n\nGöteborg 14, Mölndalsv 93. Fack.\nTel 031-2002 20. Tga Hertzco.\nTelex 2549\n\nVerksamhet: Dambeklädnads- o\nheminredningstyger en gros\nFilialer: Stockholm o Malmö\nAntal anställda: 100\nAktiekapital: 450 000\nStyrelse: Bankdir Ted Mannheimer\n(ordf), dir Torsten Lundvall, fru\nAnn-Mari Lundvall\nVerkst dir: Torsten Lundvall\nEtableringsår: 1836.",
    "structured": {
        "1": {
            "company_name": "ÅLO-MASKINER, AB",
            "address": "Umeå, Brännland",
            "phone_number": "090-30100",
            "bank_details": {
                "bankgiro": "35-4 174",
                "postgiro": "460515"
            },
            "activity": "Tillverkar hydrauliska frontlastare för traktorer",
            "employees": 130,
            "annual_turnover": 13000000,
            "capital": 325000,
            "key_personnel": [
                {
                    "name": "Verkst dir: K R Åström"
                }
            ],
            "establishment_year": 1950
        },
        "2": {
            "company_name": "TOFTANSSÅGVERK. AB",
            "address": "Sundbom, Postl 1966",
            "phone_number": "023-61040",
            "bank_details": {
                "bankgiro": "464-2690",
                "postgiro": "21431-2"
            },
            "activity": "Köper skog på rot, timmer o massaved. Tillverkar o säljer sågade o hyvlade trävaror",
            "employees": 25,
            "annual_turnover": 3000000,
            "capital": 100000,
            "key_personnel": [
                {
                    "name": "Styrelse: f Disp E J Lindberg (ordf), ing Tage Lindberg, fru Karin Lindberg",
                    "position": "Verkst dlr: Tage Lindberg"
                }
            ],
            "establishment_year": 1923
        },
        "3": {
            "company_name": "MARMOR, AB",
            "address": "Bromma, Bällstav 65",
            "phone_number": "08-28 3644, 29 90 16",
            "bank_details": {
                "bankgiro": "74-3584",
                "postgiro": "163161-3"
            },
            "activity": "Tillverkar o säljer trappor, golv o fönsterbänkar",
            "capital": 10000,
            "key_personnel": [
                {
                    "name": "Verkst dir: H I Bergenborg"
                }
            ],
            "establishment_year": 1939
        },
        "4": {
            "company_name": "SUNDSTRÖM & SON AB, C G",
            "address": "Stockholm, Dalag 6",
            "phone_number": "08-23 3310",
            "bank_details": {
                "bankgiro": "560-5100",
                "postgiro": "3461-1"
            },
            "activity": "Säljer ylletyger, linne- o bomullsvaror en gros",
            "employees": 20,
            "annual_turnover": 4350000,
            "capital": 350000,
            "key_personnel": [
                {
                    "name": "Styrelse: Adv Olof Christner (ordf), dlr Gösta Qvennerstedt, dir Sven Qvennerstedt",
                    "position": "Verkst dir: Gösta Qvennerstedt"
                }
            ],
            "establishment_year": 1839
        },
        "5": {
            "company_name": "SUNDSTRUM AB, BYGGNADS. FIRMAN ESKIL",
            "address": "Krylbo 1, Stationsg 31, Box 57",
            "phone_number": "0226-118 00",
            "bank_details": {
                "bankgiro": "23-3542",
                "postgiro": "265087"
            },
            "activity": "Husbyggnad",
            "employees": 70,
            "annual_turnover": 6000000,
            "capital": 100000,
            "key_personnel": [
                {
                    "name": "Verkst dir: Eskil Sundström"
                }
            ],
            "establishment_year": 1939
        },
        "6": {
            "company_name": "SUNDSTRÖMS BOKTRYCKERI o BOK FURLAG, HJ",
            "address": "Stockholm, Rosenlundsg 52",
            "phone_number": "08-84 76 48, 84 76 49",
            "bank_details": {
                "bankgiro": "537-0192",
                "postgiro": "601045-8"
            },
            "activity": "Boktryck, blanketttryck, reklamtryck o tidskrifter",
            "establishment_year": 1920
        },
        "7": {
            "company_name": "SALTIMPORTEN, Ab",
            "address": "Malmö 1, Box 187, Grimsbyg 24",
            "phone_number": "040-703 00",
            "bank_details": {
                "bankgiro": "852-6188",
                "postgiro": "41232-0"
            },
            "activity": "Säljer allt i salt, klorcalcium, lantbrukskemikalier, snäckskal, foderkalk o soda",
            "capital": 180000,
            "key_personnel": [
                {
                    "name": "Verkst dir: Per Olof Hanson"
                }
            ],
            "establishment_year": 1916
        },
        "8": {
            "company_name": "STÅNGA TAKTEGELFABRIK, BERGSTRÖM & CO",
            "address": "Stånga, Box 29",
            "phone_number": "0498-824 29",
            "postgiro": "90524",
            "activity": "Betongrör o ringar samt cementhålsten",
            "employees": 12,
            "annual_turnover": 600000,
            "key_personnel": [
                {
                    "name": "Ägare o chef: Rune Bergström"
                }
            ],
            "establishment_year": 1924
        },
        "9": {
            "company_name": "HULTGREN & CO, AB ERIC",
            "address": "Göteborg 2, Skeppsbron 4, Box 2409",
            "phone_number": "031-17 25 65",
            "bank_details": {
                "bankgiro": "511-6280",
                "postgiro": "41166-0"
            },
            "activity": "Spedition, skepps-mäkleri",
            "capital": 100000,
            "key_personnel": [
                {
                    "name": "Verkst dir: Albert Sprimont"
                }
            ],
            "establishment_year": 1917
        },
        "10": {
            "company_name": "HULTGRENS JÄRN- & METALLTRADSFABRIK, I",
            "address": "Stockholm, Armfeltsg 26",
            "phone_number": "08-67 7125",
            "activity": "Reklamartiklar, allt förekommande i branschen tillverkade av järntråd o järn",
            "key_personnel": [
                {
                    "name": "Chef: Ingemar Hultgren"
                }
            ]
        },
        "11": {
            "company_name": "HULTGRENS MÖBEL-FABRIKER AB, J",
            "address": "Tenhult, Box 33",
            "phone_number": "036-916 05",
            "activity": "Tillverkar byråar, hurtsar o toilettbord",
            "employees": 45,
            "annual_turnover": 5000000,
            "capital": 94000,
            "key_personnel": [
                {
                    "name": "Verkst dir: Josef Hultgren"
                }
            ],
            "establishment_year": 1943
        },
        "12": {
            "company_name": "HULTGRENS MÖBELFABRIK, AB SETH",
            "address": "Nässjö, Egnahemsg 27",
            "phone_number": "0380-113 49",
            "bank_details": {
                "bankgiro": "452-7388",
                "postgiro": "271663-7"
            },
            "activity": "Tillverkar bäddsoffor",
            "employees": 12,
            "annual_turnover": 900000,
            "capital": 30000,
            "key_personnel": [
                {
                    "name": "Verkst dir: Seth Hultgren"
                }
            ],
            "establishment_year": 1942
        },
        "13": {
            "company_name": "HULTMANSPATENTBYRÅ AB",
            "address": "Stockholm 5, Linnég 15, Box 5165",
            "phone_number": "08-67 52 03, 67 52 04",
            "bank_details": {
                "bankgiro": "745-4382",
                "postgiro": "261015-2"
            },
            "activity": "Patent- o varumärkesombuds verksamhet",
            "employees": 8,
            "capital": 15000,
            "key_personnel": [
                {
                    "name": "Verkst dir: Ing Bengt Avellan-Hultman"
                }
            ],
            "establishment_year": 1965
        },
        "14": {
            "company_name": "TOTEBO INDUSTRIER, AB",
            "address": "Hjorted, Totebo",
            "phone_number": "0490-61000, 610 01, 610 02",
            "bank_details": {
                "bankgiro": "452-0409",
                "postgiro": "36464-6"
            },
            "activity": "Tillverkar radio- o TV-möbler samt hemmöbler",
            "employees": 190,
            "annual_turnover": 9000000,
            "capital": 110000,
            "key_personnel": [
                {
                    "name": "Verkst dir: Ing C-H Larsson",
                    "position": "Försäljn-chef: Ing C H Larsson, Inköpschef: Olof Järesjö"
                }
            ],
            "establishment_year": 1912
        },
        "15": {
            "company_name": "PRESTOVERKENI MOTALA AB",
            "address": "Motala, Norrsten",
            "phone_number": "0141-31112",
            "activity": "Tillverkar värmeledningspannor o varmvattenberedare",
            "varunamn": "Presto",
            "annual_turnover": 1000000,
            "key_personnel": [
                {
                    "name": "Verkst dir: Ivar Werner"
                }
            ],
            "establishment_year": 1926
        },
        "16": {
            "company_name": "HERTZ & CO, AB",
            "address": "Göteborg 14, Mölndalsv 93, Fack",
            "phone_number": "031-2002 20",
            "bank_details": {
                "bankgiro": "N/A",
                "postgiro": "N/A"
            },
            "activity": "Dambeklädnads- o heminredningstyger en gros",
            "filialer": "Stockholm o Malmö",
            "employees": 100,
            "capital": 450000,
            "key_personnel": [
                {
                    "name": "Styrelse: Bankdir Ted Mannheimer (ordf), dir Torsten Lundvall, fru Ann-Mari Lundvall",
                    "position": "Verkst dir: Torsten Lundvall"
                }
            ],
            "establishment_year": 1836
        }
    }
}