{
    "original": "SJUBERG AB, BO-E\n\nPnr 552 46\n\nJönköping, Gullregnsbacken 10.\nTel 036-1147 0 0, 1147 01.\nBankgiro 642-1960. Postgiro 343480-0.\nTelex 70037 SJÖBERG S\nVeiksamhet: Kompletta\nanläggningar för tillverkning av spånskivor\nAntal anställda: 4\nAktiekapital: 5 000\nVeikst dir: Bo-E Sjöberg\nEtableringsår: 1968.\n\nSJUBERGS BOKBINDERI AB,\nC J\n\nPnr 113 52\n\nStockholm, Döbelnsg 36 A. Tel\n08-32 55 52, 3255 53. Bankgiro\n724-7059. Postgiro 156263-6\nVerksamhet: Partibokbinderi,\nspecialitet: broschyrarbeten\nAntal anställda: 18\nChef: Disp Lennart Åkerlund\nEtableringsår: 1925.\n\nSJUBERGS\nFISKREDSKAPSFABRIK, AB E\n\nPnr 79100\n\nFalun. Vikav 147. Tel 023-700 14,\n700 66. Bankgiro 336-4338.\nPostgiro 24110-9. Tga Fiskredskap\nVeiksamhet: Tillverkar ryssjor,\nfisknotar, kräftredskap,\nlångrevslådor, sänkhåvar, fisknät mm\nAntal anställda: 11\nÅrsomsättning: 700 000\nAktiekapital: 90 000\nStyrelse: Disp Olle Hagman (ordf),\nherr Jan-Olov Hagman, fabr Artur\nSjöberg\n\nVeikst din Disp Olle Hagman\nEtableringsår 1907\nOmbildat till aktiebolag 1944.\n\nSJUBERGS JÄRNHANDEL AB,\nGOTTFRID\n\nPnr 920 60\n\nStoruman, Järnvägsg 6. Box 1.\nTel 0951-100 25, 101 25. Bankgiro\n765-0245. Postgiro 74533-1\nVerksamhet: Järn- o byggnadsvaror\nAntal anställda: 9\nÅrsomsättning: 2 210 000\nAktiekapital: 50000\nVerkst dir: R Jonsson\nEtableringsår 1929.\n\nSJU\n\nÄgare o chefer Fabr Bertil\nSjökvist, Evert Sjökvist\nKamrer: G Strandberg\nEtableringsår: 1942.\n\nACO AB, INGENJÖRSFIRMAN\n\nPnr 11458\n\nStockholm, Kommendörsg 34. Tel\n08-62 53 78, 62 53 88. Bankgiro\n195-9055. Postgiro 151318-3. Tga\nAcofirm\n\nVerksamhet: Säljer\noljeeldningsarmatur\n\nÅrsomsättning: 530 000\nAktiekapital: 21000\nEtableringsår: 1946.\n\nvakuumsystem ab\n\nPnr 17144\n\nSolna. Skytteholmsv 2. Tel\n08-27 28 55. Postgiro 406385\nVerksamhet: Vakuumavloppssystem\nsamt avloppsreningsutrustning\nAntal anställda: 11\nAktiekapital: 200 000\nStyrelse: Håkan Birke (ordf),\nKjeld Paus, Hans Werthén, Bo\nBroms\n\nVerkst dir: Bengt Leine\nEtableringsår: 1967.\n\nBYGGBESLAG, AB\n\nPnr 65109\n\nKarlstad 1, Box 546. Blockg 11.\nTel 054-18 50 70. Bankgiro 881-4139.\nPostgiro 21360-3\n\nVerksamhet: Engrosförsäljning av\nbyggnadsbeslag. Städset 67,\nBygg-Hyll 69, Hatthylla Bygg 66\nAntal anställda: 21\nÅrsomsättning: 10 000 000\nAktiekapital: 90 000\nVerkst dir: Sven H Fredriksson\nEtableringsår: 1957.\n\nBYGGBRODERNA I\nFALKENBERG AB\n\nPnr 31101\n\nFalkenberg 1, Box 194. Nyg 58.\nTel 0346-140 70. Bankgiro\n361-4575. Postgiro 590301-8\nVerksamhet: Uppför bostadshus,\nindustribyggnader, skolor m m\nAntal anställda: 100\nÅrsomsättning: 8 900 000\nAktiekapital: 25 000\nVerkst dir. Byggmäst Erland\nBengtsson\nEtableringsår. 1962.\n\nBYGGCENTRUM\nGOTEBORG AB\n\nPnr 412 51\n\nGöteborg, ürgrytev 2. Mässhuset.\nTel 031-81 00 85. Bankgiro\n510-2637. Postgiro 521600-7\nVerksamhet: Permanent utställning\no central för objektiv information\ntill byggfackmän o allmänhet\nAntal anställda: 15\nÅrsomsättning: 2000 000\nAktiekapital: 109 200\nVerkst dir: Ing Svante Palmquist\nEtableringsår: 1955.\n\nBYGGE, E BENGTSSON\nAB, FIRMA\n\nPnr 582 31\n\nLinköping, Alkag 4. Tel\n013-13 03 20. Bankgiro 60-7863.\nPostgiro 327 1 2\n\nVerksamhet: Byggvaror i parti o\nminut\n\nFilial: Motala. Firma Bygges\nBygg-köp, Drakv. Tel 0141-500 70. Säljer\nträ- o byggvaror. Platschef: Börje\nWelander\n\nDotterbolag: Firma Bygges Betong\nAB, Firma Bygges Specialarbeten\nAB, Linköping\nAktiekapital: 300 000\nChef: Dir Gerhard Gustafsson\nEtableringsår: 1937\nDotterbolag till E Bengtsson &amp;\nCo AB, Trollhättan.\n\nBYGGES BETONG\nAB, FIRMA\n\nPnr 582 31\n\nLinköping, Alkag 4. Tel\n013-13 03 20. Bankgiro 60-7829.\nPost-giro 411314\n\nVerksamhet: Säljer färdig betong\nAktiekapital: 10 000\nClief: Dir Gerhard Gustafsson\nEtableringsår: 1958.\n\nRINGSJU.HUS, AB\n\nPnr 24036\n\nStehag, Box 102. Tel 0413-40340.\nPostgiro 249672\n\nVerksamhet: Tillverkar\nmonterings-färdiga trähus\nAktiekapital: 30000\nVerkst dir: Otto Olsson\nEtableringsån 1946.\n\nWILTAX AB\n\nPnr 25013\n\nHelsingborg 13, Box 13012.\nMuskötg 10. Tel 042-18 02 50.\nBankgiro 86-3743. Postgiro\n591010-4. Telex 72336\nVerksamhet: Säljer mattor.\nSpecialitet: heltäckningsmattor\nAntal anställda: 27\nÅrsomsättning: 13 000000\nAktiekapital: 400000\nVerkst dir. Kurt Aulin\nEtableringsàr: 1962.\n\nVIMMERBY TIDNING\n\nPnr 598 00\n\nVimmerby, Stångàg 46. Tel\n0492-12150\n\nVerksamhet: Tidningen utkommer 6\nggr i veckan, annonspris 88-100\nöre pr mm\n\nChefred: Ingmar Karlsson.\n\nVIMMERBYORTENS\nLASTBIL-CENTRAL EK FOR\n\nPnr 598 00\n\nVimmerby, Box 113. V Tullen. Tel\n0492-12 1 45. Bankgiro 367-4322.\nPostgiro 175296-3\nVerksamhet Transportförmedling\nAntal anställda: 7\nÅrsomsättning: 5 500 000\nFöreståndare: Stig Bergsten\nEtableringsån 1941.\n\nKLI\n\nexploatering, lantmäteriteknik,\ngeoteknik, väg- o\nvattenbyggnadsteknik, byggnadsprojektering,\nbostäder, industriprojektering,\nlantbruksprojektering, byggledning,\ndriftservice. Experter för VVS-, el- o\nkylteknik. 40-tal kontor i 20 län\nAntal anställda: 1 200\nÅrsomsättning: 80 000 000\nVertist dir: Ark SAR Bengt T\nThelander\n\nEtableringsår: 1939.\n\nMOWICO, AB\n\nPnr 43102\n\nMölndal 2, Box 2014. Abäcksg 6.\nTel 031-16 15 25. 16 25 20.\nBankgiro 819-0316. Postgiro 428850-2.\nTga Mowiskol\n\nVerksamhet: Säljer skol- o\nundervisningsmateriel i parti\nAntal anställda: 5\nAktiekapital: 40 000\nVerkst dir: Göte Ackert.\n\nMOVING AB\n\nPnr 265 01\n\nÅstorp 1, Box 119. Tel 042-516 65.\nBankgiro 112-4791. Postgiro\n262980-6. Tga Moving.\nTelex 72433 MOVING S\nVerksamhet: Tillverkar\ntransport-o lyftanordningar, vagnar o hjul.\nImportrörelse i samma bransch\nAntal anställda: 25\nÅrsomsättning: 4 000 000\nAktiekapital: 75 000\nVerkst dir: Ing Bengt Franzén\nEtableringsår: 1969.\n\nCORN PRODUCTS AB\n\nPnr 291 02\n\nKristianstad 2, Fack. Tegelbruksv\n18. Tel 044-1158 10. Bankgiro\n657-7993. Postgiro 870-6. Tga Carnpro.\nTelex 4444 CORNPRO S\nVerksamhet: Säljer KNORR soppor,\nbuljonger o såser, AROM AT,\nMA-ZOLA majsolja, MAIZENA,\nDEX-TROPUR, DEXTROSOL.\nTillverkar o säljer WINBORGS sill, krämer,\nsallader o ättika\nAntal anställda: 300\nÅrsomsättning: 50 000 000\nAktiekapital: 200 000\nVerkst dir: Rolf Axelsson\nEtableringsår: 1960.",
    "structured": {
        "1": {
            "company_name": "SJUBERG AB",
            "activity": "Kompletta anläggningar för tillverkning av spånskivor",
            "establishment_year": 1968,
            "employees": 4,
            "capital": 5000,
            "key_personnel": [
                {
                    "name": "Bo-E Sjöberg",
                    "position": "Veikst dir"
                }
            ]
        },
        "2": {
            "company_name": "SJUBERGS BOKBINDERI AB",
            "establishment_year": 1925,
            "activity": "Partibokbinderi, specialitet: broschyrarbeten",
            "employees": 18
        },
        "3": {
            "company_name": "SJUBERGS FISKREDSKAPSFABRIK, AB E",
            "activity": "Tillverkar ryssjor, fisknotar, kräftredskap, långrevslådor, sänkhåvar, fisknät mm",
            "establishment_year": 1907,
            "employees": 11,
            "annual_turnover": "700 000",
            "capital": "90 000",
            "key_personnel": [
                {
                    "name": "Disp Olle Hagman",
                    "position": "Styrelse (ordf)"
                },
                {
                    "name": "Jan-Olov Hagman",
                    "position": "herr"
                },
                {
                    "name": "Artur Sjöberg",
                    "position": "fabr"
                }
            ]
        },
        "4": {
            "company_name": "SJUBERGS JÄRNHANDEL AB",
            "activity": "Järn- o byggnadsvaror",
            "establishment_year": 1929,
            "employees": 9,
            "annual_turnover": "2 210 000",
            "capital": "50000",
            "key_personnel": [
                {
                    "name": "R Jonsson",
                    "position": "Verkst dir"
                }
            ]
        },
        "5": {
            "company_name": "ACO AB, INGENJÖRSFIRMAN",
            "establishment_year": 1946,
            "activity": "Säljer oljeeldningsarmatur",
            "annual_turnover": "530 000",
            "capital": "21000"
        },
        "6": {
            "company_name": "vakuumsystem ab",
            "activity": "Vakuumavloppssystem samt avloppsreningsutrustning",
            "establishment_year": 1967,
            "employees": 11,
            "capital": "200 000",
            "key_personnel": [
                {
                    "name": "Håkan Birke",
                    "position": "Styrelse (ordf)"
                },
                {
                    "name": "Kjeld Paus",
                    "position": ""
                },
                {
                    "name": "Hans Werthén",
                    "position": ""
                },
                {
                    "name": "Bo Broms",
                    "position": ""
                },
                {
                    "name": "Bengt Leine",
                    "position": "Verkst dir"
                }
            ]
        },
        "7": {
            "company_name": "BYGGBESLAG, AB",
            "activity": "Engrosförsäljning av byggnadsbeslag. Städset 67, Bygg-Hyll 69, Hatthylla Bygg 66",
            "establishment_year": 1957,
            "employees": 21,
            "annual_turnover": "10 000 000",
            "capital": "90 000",
            "key_personnel": [
                {
                    "name": "Sven H Fredriksson",
                    "position": "Verkst dir"
                }
            ]
        },
        "8": {
            "company_name": "BYGGBRODERNA I FALKENBERG AB",
            "activity": "Uppför bostadshus, industribyggnader, skolor m m",
            "establishment_year": 1962,
            "employees": 100,
            "annual_turnover": "8 900 000",
            "capital": "25 000",
            "key_personnel": [
                {
                    "name": "Byggmäst Erland Bengtsson",
                    "position": "Verkst dir"
                }
            ]
        },
        "9": {
            "company_name": "BYGGCENTRUM GOTEBORG AB",
            "activity": "Permanent utställning o central för objektiv information till byggfackmän o allmänhet",
            "establishment_year": 1955,
            "employees": 15,
            "annual_turnover": "2000 000",
            "capital": "109 200",
            "key_personnel": [
                {
                    "name": "Ing Svante Palmquist",
                    "position": "Verkst dir"
                }
            ]
        },
        "10": {
            "company_name": "BYGGE, E BENGTSSON AB, FIRMA",
            "activity": "Byggvaror i parti o minut",
            "establishment_year": 1937,
            "capital": "300 000",
            "key_personnel": [
                {
                    "name": "Dir Gerhard Gustafsson",
                    "position": "Chef"
                }
            ]
        },
        "11": {
            "company_name": "BYGGES BETONG AB, FIRMA",
            "activity": "Säljer färdig betong",
            "establishment_year": 1958,
            "capital": "10 000",
            "key_personnel": [
                {
                    "name": "Dir Gerhard Gustafsson",
                    "position": "Clief"
                }
            ]
        },
        "12": {
            "company_name": "RINGSJU.HUS, AB",
            "activity": "Tillverkar monterings-färdiga trähus",
            "establishment_year": 1946,
            "capital": "30000",
            "key_personnel": [
                {
                    "name": "Otto Olsson",
                    "position": "Verkst dir"
                }
            ]
        },
        "13": {
            "company_name": "WILTAX AB",
            "activity": "Säljer mattor. Specialitet: heltäckningsmattor",
            "establishment_year": 1962,
            "employees": 27,
            "annual_turnover": "13 000000",
            "capital": "400000",
            "key_personnel": [
                {
                    "name": "Kurt Aulin",
                    "position": "Verkst dir"
                }
            ]
        },
        "14": {
            "company_name": "VIMMERBY TIDNING",
            "activity": "Tidningen utkommer 6 ggr i veckan, annonspris 88-100 öre pr mm",
            "key_personnel": [
                {
                    "name": "Ingmar Karlsson",
                    "position": "Chefred"
                }
            ]
        },
        "15": {
            "company_name": "VIMMERBYORTENS LASTBIL-CENTRAL EK FOR",
            "activity": "Transportförmedling",
            "establishment_year": 1941,
            "employees": 7,
            "annual_turnover": "5 500 000",
            "key_personnel": [
                {
                    "name": "Stig Bergsten",
                    "position": "Föreståndare"
                }
            ]
        },
        "16": {
            "company_name": "KLI",
            "activity": "Exploatering, lantmäteriteknik, geoteknik, väg- o vattenbyggnadsteknik, byggnadsprojektering, bostäder, industriprojektering, lantbruksprojektering, byggledning, driftservice. Experter för VVS-, el- o kylteknik. 40-tal kontor i 20 län",
            "establishment_year": 1939,
            "employees": 1200,
            "annual_turnover": "80 000 000",
            "key_personnel": [
                {
                    "name": "Ark SAR Bengt T Thelander",
                    "position": "Vertist dir"
                }
            ]
        },
        "17": {
            "company_name": "MOWICO, AB",
            "activity": "Säljer skol- o undervisningsmateriel i parti",
            "establishment_year": 0,
            "employees": 5,
            "capital": "40 000",
            "key_personnel": [
                {
                    "name": "Göte Ackert",
                    "position": "Verkst dir"
                }
            ]
        },
        "18": {
            "company_name": "MOVING AB",
            "activity": "Tillverkar transport-o lyftanordningar, vagnar o hjul. Importrörelse i samma bransch",
            "establishment_year": 1969,
            "employees": 25,
            "annual_turnover": "4 000 000",
            "capital": "75 000",
            "key_personnel": [
                {
                    "name": "Ing Bengt Franzén",
                    "position": "Verkst dir"
                }
            ]
        },
        "19": {
            "company_name": "CORN PRODUCTS AB",
            "activity": "Säljer KNORR soppor, buljonger o såser, AROM AT, MA-ZOLA majsolja, MAIZENA, DEX-TROPUR, DEXTROSOL. Tillverkar o säljer WINBORGS sill, krämer, sallader o ättika",
            "establishment_year": 1960,
            "employees": 300,
            "annual_turnover": "50 000 000",
            "capital": "200 000",
            "key_personnel": [
                {
                    "name": "Rolf Axelsson",
                    "position": "Verkst dir"
                }
            ]
        }
    }
}