{
    "original": "AMACO MASKIN AB\n\nPnr 235 00\n\nV eliinge. Tel 040-42 07 50.\nBank-giro 643-5259. Postgiro 39755-4.\nTga Amaco. Telex 32213\nVerksamhet: Tillverkar, säljer o\nhyr ut byggnadsmaskiner\nAktiekapital: 1000000\nVerkst dir: Bertil Mauritzson\nEtableringsår: 1952.\n\nWIDÉN &amp; WIGLE, AB\n\nPnr 70011\n\nÖrebro 11, Box 11077. Tel\n019-22 5150. Bankgiro 46-3305.\nPostgiro 199010\n\nVerksamhet: Tillverkar o säljer\nundertakskonstruktioner av metall\nFörsäljningskontor: Nacka, Per\nHallströms v 4. Tel 08-7167310\nVarunamn: Sanacoustic, Sanalit\nAntal anställda: 200\nÅrsomsättning: 20 000 000\nAktiekapital: 420 000\nStyrelse: Disp Anders Widén (ordf),\nfru Wanja Wigle, fru Yvonne\nRingblom, ing Anders von Plomgren o\ning Gösta Eriksson\nVerkst dir Anders Widén\nEtableringsår: 1955.\n\nHOLMLUNDS FABRIKER, AB\n\nPnr 89101\n\nÖrnsköldsvik 1, Bodum. Box 129.\nTel 0660-400 75,40133. Bankgiro\n188-4428. Postgiro 63150-7\nVerksamhet: Import o\npartiförsäljning av bindgarn, tågvirke, tejp,\nbyggfolie, polyetenpåsar\nAntal anstäUda: 10\nÅrsomsättning: 2 000 000\nAktiekapital: 50 000\nVerkst dir: Ing Erland Holmlund\nEtableringsår: 1955.\n\nTHULIN AB, C W\n\nPnr 104 30\n\nStockholm 45. Box 45141.\nVäst-mannag 15. Tel 08-24 82 70.\nBankgiro 561-1652. Postgiro 704840-8.\nTga Cewetebolag. Telex 10773\nVerksamhet: Importerar järn- o\nstålhalvfabrikat, stålrör, metaller,\nmetallhalvfabrikat. Bl a\nensamförsäljare i Sverige för diverse\nvästeuropeiska stålrörs- o metallverk.\nLagerhåller stålrör i Stockholm.\nÄven för hydraulik o pneumatik\nAntal anställda: 14\nÅrsomsättning: 12 000000\nAktiekapital: 60 000\nStyrelseordf: Dir Curt Thulin\nVerkst dir Curt Thulin\nFörsäljn-dir: Kjell Sjödin\nEtableringsår: 1964.\n\nALFA ROR AB\n\nPnr 14148\n\nHuddinge, Solfagrav 33. Tel\n08-774 02 60. Bankgiro 116-1467.\nPostgiro 685110-9\n\nVerksamhet: Marknadsför betongrör\nAktiekapital: 8 000\nVerkst dir: Ingvar Bladh\nEtableringsår: 1966.\n\nSVENSK NATTVAKT, AB\n\nPnr 10231\n\nStockholm 6, Box 6607. Kammakarg\n39. Tel 08-24 78 00. Bankgiro\n575-9279. Postgiro 52750-7\n\nETT SECURITAS-FÖRETAG\n\nVerksamhet: Bevakning\nAntal anställda: 1100\nÅrsomsättning: 33 000 000\nAktiekapital: 500 000\nVeikst dir: Hj Stenbeck\nEtableringsår: 1910.\n\nÅRJÄNGS JÄRN AB\n\nPnr 672 00\n\nÅrjäng, Box 71. Storg 60. Tel\n0573-110 40. Bankgiro 117-3129.\nPostgiro 394378-4\nVerksamhet: Säljer järn-, bygg- o\nmaskinvaror, kyl-, tvätt- o\nfrysenheter samt husgeråd. Utför\nrörarbeten. Tillverkar cementsten\nAntal anställda: 30\nÅrsomsättning: 3 500000\nAktiekapital: 80 000\nVerkst dir. Paul Andersson\nEtableringsår: 1950.\n\nNILSSON, AB LINDE\n\nPnr 360 30\n\nLammhult, Box 106. Tel 0472-600 55,\n604 64. Bankgiro 275-4141.\nR&gt;st-giro 265183-4\n\nVerksamhet: Tillverkar o säljer\nstolar, fåtöljstommar m m\nAntal anställda: 12\nÅrsomsättning: 700000\nAktiekapital: 15 000\nVerkst dir: Fabr Linde Nilsson\nEtableringsår: 1946.\n\nNILSSONS TRÄINDUSTRI AB,\nMAURITZ\n\nPnr 286 02\n\nörkelljunga 2, Box 385. Tel\n0435-802 60, 802 73. Bankgiro 34-0522.\nPostgiro 31186\n\nVerksamhet: Tillverkar lastpallar,\npallramar o grövre emballage\nAntal anställda: 40\nÅrsomsättning: 4 000 000\nAktiekapital: 50 000\nVerkst dir: Olle Nilsson\nEtableringsår: 1952.\n\nGRÄNGESMETALOCK AB\n\nPnr 40110\n\nGöteborg 1, Marieholmsg 10. Pack.\nTel 031-19 7055. Bankgiro\n500-7950. Postgiro 422411-9. Tga\nMet-lokcast. Telex 2515 PULLMAX S\nVerksamhet: Maskin- o\napparatmontage. Industriunderhåll.\nOrdertillverkning av plåtkonstruktio\nner. Svets- o andra\nreparationsarbeten\n\nFilialverkstäder:\n\nStockholm. Tel 08-45 78 11\n\nMalmö. Tel 040-93 77 36\n\nGävle. Tel 026-18 77 70\n\nAntal anställda: 325\n\nÅrsomsättning: 19 000 000\n\nAktiekapital: 250000\n\nStyrelse: Dir Bertil Liljeqvist, dir\n\nSven Sandgren, dir Sten Porsmark\n\nVerkst dir: Sten Porsmark\n\nEtableringsån 1950.\n\nHelägt dotterbolag till Gränges.\n\nGRÄNGES STÅL\nOXELDSUNDSJÄRNVERK\n\nPnr 613 01\n\nOxelösund 1, Pack. Tel\n0155-306 10. Postgiro 71560. Telex\n64160. Tga Järnverket\nVerksamhet: Tillverkar o säljer\ngrov- o mediumplåt, tackjärn för\ngjuterier o stålverk, järnsvamp,\nkoks. Biprodukter som\nstenkolstjära, råbensol o ammoniumsulfat\nförsäljes genom GOKEF, Stockholm\nVarunamn: ÖJA, OX\nAntal anställda: 3 000\nChef: Jan Wachtmeister\nFörsäljn-dir: Ingemar Gustafsson\nFörsäljningsintendenter: Bo\nFrendin (fartygsplåt), Ernst\nMarkström (industriplåt), Gösta\nLundgren (råvaror)\nTekn dir: Sten Gunnarsson\nProduktionsdir: Erik Banell\nEkonomichef: Erik österberg\nAdm- o personalchef: Gunnar\nJonzën\n\nInköpsdir: (för Gränges Stål)\nSven-Eric Wickström\nEtableringsår: 1913\nSedan 1957 ingår Oxelösunds\nJärnverk i Gränges. Sedan 1969 bildar\nOxelösunds Järnverk tillsammans\nmed gruvorna i Grängesberg o\nStråssa, TGOJ med Oxelösunds\nhamn o Nyby Bruks AB Gränges\nStål.\n\nGRÄNGES STÅL NYBY BRUK\n\nPnr 640 44\n\nNyby bruk. Tel 016-557 00. Postgiro\n15454. Tga Nybybruk, Eskilstuna.\nTelex 40973\n\nVerksamhet: Tillverkar rostfri plåt,\nrostfria rör o rördelar\nAntal anställda: 1700\n\nÅrsomsättning: 310 000 000\nAktiekapital: 32 000 000\nStyrelse: Dir Johan Åkerman (ordf),\ndir Ulf Magnusson, bruksdisp Per\nKiellarson\n\nVerkst dir: Per Kiellarson\nProduktionsdir: Y Appelgren\nTekn dir: Göran Molinder\nMarknadsdir: Bengt Lundgren\nChef Gir utländska dotterbolag:\nH A Wachtmeister\nEkonomidir: Hj Björklund\nInköpschef: N Hennum\nEtableringsår: 1872\nSedan 1965 ingår Nyby Bruk i\nGränges.\n\nGRÄNGESBERGS\nBRYGGERI AB\n\nPnr 772 00\n\nGrängesberg. Tel 0240-215 80\nAktiekapital: 500 000\nVerkst dir: J P Spendrup\nEtableringsår: 1961.\n\nGRÄNGESBERGS\nINDUSTRI-VARU AB\n\nPnr 772 01\n\nGrängesberg 1, Kopparbergsv 46 A.\nBox 59. Tel 0240-215 00. Bankgiro\n79-5319. Postgiro 389019. Tga\nIndustrivaror. Telex 73447 GIA S\nVerksamhet: Säljer diesellok,\ndie-selkompressorer, flaktruckar,\ndieselmotorer, bergtransportvagnar,\nfjärrkontrollutrustningar,\nanrikningsmaterial, stålgjutgods,\nrälsbundna vagnar av alla slag samt\nstålkonstruktioner, rälselement av\nalla slag, tryckluftsmaskiner,\ntrycklufts- o renblåsningsarmatur,\nfyllhammare o malmfat,\nsäkerhetsmaterial, räls o rälstillbehör,\nspårväxlar o domkrafter, förnödenheter för\nbergrumsarbeten, malkroppar,\nkvarnbult, dammavskiljare,\nskyddskläder, grävmaskin, superspett\nVarunamn: Gia, Jenbach, Sig,\nMenzl\n\nAntal anställda: 60\nÅrsomsättning: 12 000 000\nAktiekapital: 200 000\nStyrelse: Adv Helmer Lindh (ordf),\ndir C O Larsson, dir Sture Sjöberg,\ndisp Jens-Fredrik Spendrup\nVerkst dir: Disp Stig Almér\nV verkst dir: Jan Melander\nKamrer: M G Gaum\nEtableringsår: 1880\nOmbildat till aktiebolag 1953.\n\nGRÄNNA BYGGMATERIAL AB\n\nPnr 560 30\n\nGränna. Tel 0390-10416, 10417\nVerksamhet: Säljer allt från grund\ntill tak. Sågverk o hyvleri i\nörse-rum\n\nAktiekapital: 25 000\nVerkst dir: Erik Olofsson.\n\nGRÄNSFORS BRUKS AB\n\nPnr 820 70\n\nBergsjö, Box 36. Tel 0652-10205,\n140 02. Bankgiro 78-5313. Postgiro\n30389. Tga Bruket\nVerksamhet: Tillverkar yxor.\nExport på utlandet\nAntal anställda: 18\nÅrsomsättning: 1300 000\nAktiekapital: 112 400\nVerkst dir: Lars Eriksson\nEtableringsår: 1902.\n\nTÅSANS KRAFT AB\n\nPnr 65107\n\nKarlstad 1, Box 480. Orrholmsg 7.\nTel 054-15 66 00. Bankgiro\n100-2591. Postgiro 8174-5\nVerksamhet: Elkraftproduktion\nÅrsomsättning: 3 300 000\nAktiekapital: 2400 000\nVerkst dir: Overing Erie Möller\nEtableringsår. 1947.",
    "structured": {
        "1": {
            "company_name": "AMACO MASKIN AB",
            "pnr": "235 00",
            "address": "Veliinge",
            "phone_number": "040-42 07 50",
            "bank_details": {
                "bankgiro": "643-5259",
                "postgiro": "39755-4"
            },
            "activity": "Tillverkar, säljer o hyr ut byggnadsmaskiner",
            "capital": 1000000,
            "key_personnel": [
                {
                    "name": "Bertil Mauritzson",
                    "position": "Verkst dir"
                }
            ],
            "establishment_year": 1952
        },
        "2": {
            "company_name": "WIDÉN & WIGLE, AB",
            "pnr": "70011",
            "address": "Örebro 11, Box 11077",
            "phone_number": "019-22 5150",
            "bank_details": {
                "bankgiro": "46-3305",
                "postgiro": "199010"
            },
            "activity": "Tillverkar o säljer undertakskonstruktioner av metall",
            "employees": 200,
            "annual_turnover": 20000000,
            "capital": 420000,
            "key_personnel": [
                {
                    "name": "Anders Widén",
                    "position": "Disp"
                },
                {
                    "name": "Wanja Wigle",
                    "position": "fru"
                },
                {
                    "name": "Yvonne Ringblom",
                    "position": "fru"
                },
                {
                    "name": "Anders von Plomgren",
                    "position": "ing"
                },
                {
                    "name": "Gösta Eriksson",
                    "position": "ing"
                }
            ],
            "establishment_year": 1955
        },
        "3": {
            "company_name": "HOLMLUNDS FABRIKER, AB",
            "pnr": "89101",
            "address": "Örnsköldsvik 1, Bodum, Box 129",
            "phone_number": "0660-400 75, 40133",
            "bank_details": {
                "bankgiro": "188-4428",
                "postgiro": "63150-7"
            },
            "activity": "Import o partiförsäljning av bindgarn, tågvirke, tejp, byggfolie, polyetenpåsar",
            "employees": 10,
            "annual_turnover": 2000000,
            "capital": 50000,
            "key_personnel": [
                {
                    "name": "Ing Erland Holmlund",
                    "position": "Verkst dir"
                }
            ],
            "establishment_year": 1955
        },
        "4": {
            "company_name": "THULIN AB, C W",
            "pnr": "104 30",
            "address": "Stockholm 45, Box 45141, Väst-mannag 15",
            "phone_number": "08-24 82 70",
            "bank_details": {
                "bankgiro": "561-1652",
                "postgiro": "704840-8"
            },
            "activity": "Importerar järn- o stålhalvfabrikat, stålrör, metaller, metallhalvfabrikat. Lagerhåller stålrör i Stockholm. Även för hydraulik o pneumatik",
            "employees": 14,
            "annual_turnover": 12000000,
            "capital": 60000,
            "key_personnel": [
                {
                    "name": "Curt Thulin",
                    "position": "Styrelseordf, Verkst dir"
                },
                {
                    "name": "Kjell Sjödin",
                    "position": "Försäljn-dir"
                }
            ],
            "establishment_year": 1964
        },
        "5": {
            "company_name": "ALFA ROR AB",
            "pnr": "14148",
            "address": "Huddinge, Solfagrav 33",
            "phone_number": "08-774 02 60",
            "bank_details": {
                "bankgiro": "116-1467",
                "postgiro": "685110-9"
            },
            "activity": "Marknadsför betongrör",
            "capital": 8000,
            "key_personnel": [
                {
                    "name": "Ingvar Bladh",
                    "position": "Verkst dir"
                }
            ],
            "establishment_year": 1966
        },
        "6": {
            "company_name": "SVENSK NATTVAKT, AB",
            "pnr": "10231",
            "address": "Stockholm 6, Box 6607, Kammakarg 39",
            "phone_number": "08-24 78 00",
            "bank_details": {
                "bankgiro": "575-9279",
                "postgiro": "52750-7"
            },
            "activity": "Bevakning",
            "employees": 1100,
            "annual_turnover": 33000000,
            "capital": 500000,
            "key_personnel": [
                {
                    "name": "Hj Stenbeck",
                    "position": "Veikst dir"
                }
            ],
            "establishment_year": 1910
        },
        "7": {
            "company_name": "ÅRJÄNGS JÄRN AB",
            "pnr": "672 00",
            "address": "Årjäng, Box 71, Storg 60",
            "phone_number": "0573-110 40",
            "bank_details": {
                "bankgiro": "117-3129",
                "postgiro": "394378-4"
            },
            "activity": "Säljer järn-, bygg- o maskinvaror, kyl-, tvätt- o frysenheter samt husgeråd. Utför rörarbeten. Tillverkar cementsten",
            "employees": 30,
            "annual_turnover": 3500000,
            "capital": 80000,
            "key_personnel": [
                {
                    "name": "Paul Andersson",
                    "position": "Verkst dir"
                }
            ],
            "establishment_year": 1950
        },
        "8": {
            "company_name": "NILSSON, AB LINDE",
            "pnr": "360 30",
            "address": "Lammhult, Box 106",
            "phone_number": "0472-600 55, 604 64",
            "bank_details": {
                "bankgiro": "275-4141",
                "postgiro": "265183-4"
            },
            "activity": "Tillverkar o säljer stolar, fåtöljstommar m m",
            "employees": 12,
            "annual_turnover": 700000,
            "capital": 15000,
            "key_personnel": [
                {
                    "name": "Fabr Linde Nilsson",
                    "position": "Verkst dir"
                }
            ],
            "establishment_year": 1946
        },
        "9": {
            "company_name": "NILSSONS TRÄINDUSTRI AB, MAURITZ",
            "pnr": "286 02",
            "address": "örkelljunga 2, Box 385",
            "phone_number": "0435-802 60, 802 73",
            "bank_details": {
                "bankgiro": "34-0522",
                "postgiro": "31186"
            },
            "activity": "Tillverkar lastpallar, pallramar o grövre emballage",
            "employees": 40,
            "annual_turnover": 4000000,
            "capital": 50000,
            "key_personnel": [
                {
                    "name": "Olle Nilsson",
                    "position": "Verkst dir"
                }
            ],
            "establishment_year": 1952
        },
        "10": {
            "company_name": "GRÄNGESMETALOCK AB",
            "pnr": "40110",
            "address": "Göteborg 1, Marieholmsg 10, Pack",
            "phone_number": "031-19 7055",
            "bank_details": {
                "bankgiro": "500-7950",
                "postgiro": "422411-9"
            },
            "activity": "Maskin- o apparatmontage. Industriunderhåll. Ordertillverkning av plåtkonstruktioner. Svets- o andra reparationsarbeten",
            "employees": 325,
            "annual_turnover": 19000000,
            "capital": 250000,
            "key_personnel": [
                {
                    "name": "Bertil Liljeqvist",
                    "position": "Styrelse"
                },
                {
                    "name": "Sven Sandgren",
                    "position": "Styrelse"
                },
                {
                    "name": "Sten Porsmark",
                    "position": "Styrelse, Verkst dir"
                }
            ],
            "establishment_year": 1950
        },
        "11": {
            "company_name": "GRÄNGES STÅL OXELDSUNDSJÄRNVERK",
            "pnr": "613 01",
            "address": "Oxelösund 1, Pack",
            "phone_number": "0155-306 10",
            "postgiro": "71560",
            "activity": "Tillverkar o säljer grov- o mediumplåt, tackjärn för gjuterier o stålverk, järnsvamp, koks",
            "employees": 3000,
            "key_personnel": [
                {
                    "name": "Jan Wachtmeister",
                    "position": "Chef"
                },
                {
                    "name": "Ingemar Gustafsson",
                    "position": "Försäljn-dir"
                }
            ],
            "establishment_year": 1913
        },
        "12": {
            "company_name": "GRÄNGES STÅL NYBY BRUK",
            "pnr": "640 44",
            "address": "Nyby bruk",
            "phone_number": "016-557 00",
            "postgiro": "15454",
            "activity": "Tillverkar rostfri plåt, rostfria rör o rördelar",
            "employees": 1700,
            "annual_turnover": 310000000,
            "capital": 32000000,
            "key_personnel": [
                {
                    "name": "Johan Åkerman",
                    "position": "Styrelse"
                },
                {
                    "name": "Ulf Magnusson",
                    "position": "Styrelse"
                },
                {
                    "name": "Per Kiellarson",
                    "position": "Bruksdisp"
                },
                {
                    "name": "Per Kiellarson",
                    "position": "Verkst dir"
                }
            ],
            "establishment_year": 1872
        },
        "13": {
            "company_name": "GRÄNGESBERGS BRYGGERI AB",
            "pnr": "772 00",
            "address": "Grängesberg",
            "phone_number": "0240-215 80",
            "capital": 500000,
            "key_personnel": [
                {
                    "name": "J P Spendrup",
                    "position": "Verkst dir"
                }
            ],
            "establishment_year": 1961
        },
        "14": {
            "company_name": "GRÄNGESBERGS INDUSTRI-VARU AB",
            "pnr": "772 01",
            "address": "Grängesberg 1, Kopparbergsv 46 A, Box 59",
            "phone_number": "0240-215 00",
            "bank_details": {
                "bankgiro": "79-5319",
                "postgiro": "389019"
            },
            "activity": "Säljer diesellok, dieselmotorer, bergtransportvagnar, anrikningsmaterial, stålgjutgods, rälsbundna vagnar av alla slag samt stålkonstruktioner",
            "employees": 60,
            "annual_turnover": 12000000,
            "capital": 200000,
            "key_personnel": [
                {
                    "name": "Adv Helmer Lindh",
                    "position": "Styrelseordf"
                },
                {
                    "name": "Stig Almér",
                    "position": "Disp, V verkst dir"
                }
            ],
            "establishment_year": 1880
        },
        "15": {
            "company_name": "GRÄNNA BYGGMATERIAL AB",
            "pnr": "560 30",
            "address": "Gränna",
            "phone_number": "0390-10416, 10417",
            "activity": "Säljer allt från grund till tak. Sågverk o hyvleri i Örserum",
            "capital": 25000,
            "key_personnel": [
                {
                    "name": "Erik Olofsson",
                    "position": "Verkst dir"
                }
            ]
        },
        "16": {
            "company_name": "GRÄNSFORS BRUKS AB",
            "pnr": "820 70",
            "address": "Bergsjö, Box 36",
            "phone_number": "0652-10205, 140 02",
            "bank_details": {
                "bankgiro": "78-5313",
                "postgiro": "30389"
            },
            "activity": "Tillverkar yxor. Export på utlandet",
            "employees": 18,
            "annual_turnover": 1300000,
            "capital": 112400,
            "key_personnel": [
                {
                    "name": "Lars Eriksson",
                    "position": "Verkst dir"
                }
            ],
            "establishment_year": 1902
        },
        "17": {
            "company_name": "TÅSANS KRAFT AB",
            "pnr": "65107",
            "address": "Karlstad 1, Box 480, Orrholmsg 7",
            "phone_number": "054-15 66 00",
            "bank_details": {
                "bankgiro": "100-2591",
                "postgiro": "8174-5"
            },
            "activity": "Elkraftproduktion",
            "annual_turnover": 3300000,
            "capital": 2400000,
            "key_personnel": [
                {
                    "name": "Overing Erie Möller",
                    "position": "Verkst dir"
                }
            ],
            "establishment_year": 1947
        }
    }
}