{
    "original": "DREWS &amp; CO AB, PAUL\n\nPnr 41121\n\nGöteborg, Skeppsbron 5-6. Tel\n031-13 7 0 26, 1108 66. Bankgiro\n50-0177. Postgiro 44971-0.\nTga Swedcotton. Telex 2264\n\nVerksamhet: Agenturrörelse med\nbomull, textila avfallsråvaror,\nnatursten, jute, ull m m\nÅrsomsättning: 17 000 000\nÄgare o chefer: Jan Drews, Hans\nDrews\n\nEtableringsår: 1934.\n\nDRIFTSINSTRUKTIONER\nEL-VVS, AB\n\nPnr 200 25\n\nMalmö 16, Box 16040.\nJohannes-lustg 1. Tel 040-18 67 30. Bankgiro\n615-5048. Postgiro 438700-7\nVerksamhet: Konsulterande\ningenjörer inom EL-VVS\nVerkst dir: Arne Bjuvholt.\n\nDRIFTSKONTROLL\nEL- VVS, AB\n\nPnr 200 25\n\nMalmö 16, Box 16040. Sailerupsv\n130. Tel 040-93 58 30. Bankgiro\n633-1110. Postgiro 357 220-3\nVerksamhet: Konsulterande\ningenjörer inom EL-VVS\nVerkst dir: H Jönsson.\n\nDRIVTEKNIK, AB\n\nPnr 117 44\n\nStockholm, Nybo hovsbacken 85-89.\nTel 08-45 25 55. Bankgiro 56-9547.\nPostgiro 559431. Tga Drlvteknik.\nTelex 1532\n\nVerksamhet: Säljer mek\ndrivutrust-ningar o transmissionsdetaljer för\nvarje industriellt behov\nVarunamn: Dierking, Prym, Union,\nWülfel\n\nVerkst dir: Ing Per Lindberg\nEtableringsår: 1959.\n\nTERNACO, AB\n\nPnr 11122\n\nStockholm C, Kungsg 53. Tel\n08-204295.20 9191. Bankgiro\n48-3558. Postgiro 402150. Tga Nordian\nVerksamhet: Agentur i skinn, läder\no animaliska produkter\nAktiekapital: 10 000\nVerkst dir: Hugo M Frosch\nEtableringsår: 1966.\n\nKJ BESLAG AB\n\nPnr 653 41\n\nKarlstad. Spärrg 6. Tel 054-18 50 50.\nBankgiro 615-2300. Postgiro\n8760-1\n\nVerksamhet: Säljer\nbyggnadsbeslag, vipportar o pivåfönster\nVaninamn: Higå, KJ-Vipp, Sola\nAktiekapital: 15 000\nStyrelseordf: Disp Bengt Ohlsson\nChef: Disp Bengt Ohlsson\nEtableringsår: 1970.\n\nKJELL, KJÄLL\n\nKJÄLL MASKINER &amp; VERKTYG\nAB, ARNE\n\nPnr 46100\n\nTrollhättan, Box 214. Drottningg\n63. Tel 0520-369 00 , 369 01.\nBankgiro 225-1916. Postgiro 691192-9\nVerksamhet: Säljer verktyg,\nmaskiner, svetsaggregat o\nsvetselektroder, hydraul- o industrislang,\nmätverktyg\n\nAntal anställda: 5\nAktiekapital: 30 000\nVerkst dir: Arne Kjäll\nEtableringsår: 1968.\n\nÅHMANS MÖBELFABRIK AB, G\n\nPnr 290 20\n\nÅhus, Box 41. Tel 044-24 10 20.\n\nBankgiro 873-6308\n\nVerksamhet: Tillverkar möbler o\n\ninredningar\n\nVerkst din G Åhman\n\nEtableringsån 1860.\n\nCONRADS KONFEKTIONS AB\n\nPnr 500 02\n\nBorås 2, Box 22032. Grönbog 4.\nTel 033-1272 35. Bankgiro\n53-1164. Postgiro 163733. Tga\nConrads\n\nVerksamhet: Damklänningar\nAntal anställda: 40\nAktiekapital: 210 000\nVerkst dir: Disp Conrad\nConradson\n\nEtableringsår: 1943.\n\nARNELL AB,AND\n\nPnr 510 22\n\nHyssna. Tel 0320-390 04, 392 40.\nBankgiro 436-2299. Postgiro\n83333-5\n\nVerksamhet: Tillverkar o säljer\nhem- o fabriksstickade strumpor\nÅrsomsättning: 1500 000\nAktiekapital: 50 000\nVerkst dir: Olof Arnell\nEtableringsår: 1874.\n\nGOTEBORGS MAKADAM AB\n\nPnr 430 50\n\nKåUered. Tel 031-75 12 20.\nBankgiro 42-0064. Postgiro 146763.\nTga Makadambolaget, Göteborg.\nTelex 2421\n\nVerksamhet: Tillverkar makadam,\nbetong o oljegrus samt\nprecisions-graderat, såväl färgat som ofärgat\nstenmaterial o torrbruk för mur- o\nputs ändamål, betongplattor,\nfabriks-tillverkad matjord ’Humutex’\nMakadamfabriker: Angered,\nKålle-red. Torslanda\n\nBetongfabriker: Mölndal, Kållered,\nKungsbacka, Torslanda (Gbg) o\nVarberg\n\nAntal anstäUda: 260\nAktiekapital: 3000000\nVerkst dir: Lennart Albihn\nEtableringsår: 1939.\n\nGOTEBORGS MOSS.\nFABRIKS AB\n\nPnr 414 59\n\nGöteborg. Karl Johansg 29. Tel\n031-24 81 10. 2482 40. Bankgiro\n510-5713. Postgiro 12081-6\nVerksamhet: Tillverkar alla slags\nsydda huvudbonader\nVarunamn: Ankarmössan\nAntal anstäUda: 52\nÅrsomsättning: 1500 000\nAktiekapital: 300 000\nStyrelse: Ing Sten Göransson(ordf),\ntjänsteman Lennart Göransson\nVerkst dir: Nils Göransson\nEtableringsår: 1877.\n\nGOTEBORGS NEON\nRÖRFABRIK GÖTA-NEON AB\n\nPnr 400 13\n\nGöteborg 36. Box 36016. Kilsg 10.\nTel 031-1967 10, 196711.\nBankgiro 420-3212. Postgiro 428383-4\nVerksamhet: Tillverkar o reparerar\nneonskyltar. Eget glasblåseri\nAntal anstäUda: 8\nÅrsomsättning: 800 000\nChef: Fabr Gunnar W Fagberg\nEtableringsår: 1954.\n\nTOTTIE &amp; CO, CHARLES\n\nPnr 11148\n\nStockholm, Nybrokajen 7. Tel\n08-1197 20, 1197 30. Postgiro\n4720. Tga Cuaco\nVerksamhet: Försäkringsrörelse.\nSvenska direktionen för\nCommer-cial Union Ass Co Ltd London\nAntal anställda: 10\nÄgare o chefer Dir Lars Stenberg,\nciviling Ivar Körner\nEtableringsår: 1920\nCommercial Union Assurance Co\nLtd, grundat 1861, startade sin\nverksamhet i Sverige 1863.\n\nTOUR AGENTURER AB\n\nPnr 12172\n\nJohanneshov, Svärdlångsv 46. Tel\n08-910100. Telex 1599. Tga\nTour-agent\n\nAvdelningskontor i: Göteborg,\nMalmö, Norrköping, Sundsvall, Umeå,\nÖrebro\n\nAntal anställda: 300\nÅrsomsättning: 50 000 000\nAktiekapital: 1500 000\nVerkst din Bertil Regnér\nEtableringsån 1925.\n\nHULTGREN AB,VERNER\n\nPnr 652 25\n\nKarlstad, Hamng 22. Tel\n054-1800 75. Bankgiro 671-8381.\nPostgiro 522071-0\n\nVerksamhet: Revision, bokslut,\nbokföring, skatteärenden,\nekonomisk planering o data-service\nAntal anstäUda: 6\nÅrsomsättning: 200 000\nAktiekapital: 40 000\nVerkst dir. Revisor Lars V\nHultgren\n\nIng: Bengt Hultgren\nRevisorassistenter: Ingemar\nJonsson, Thomas Kennerstad\n\nHULTSFREDS\nSKOGSPRODUKTER, AB\n\nPnr 400 10\n\nGöteborg 3. Box 3015. Karl\nGus-tavsg 1 A. Tel 031-1120 95.\nBankgiro 50-1047. Postgiro 163478-1\nVerksamhet: Exporterar trävaror\nAntal anstäUda: 3\nÅrsomsättning: 3 500 000\nAktiekapital: 35 000\nVerkst dir Vilh Werner\nEtableringsår: 1936.\n\nSUNDQVIST &amp; WINDT AB\n\nPnr 42014\n\nSäve. Tel 031-9605 00. Bankgiro\n441-1575. Postgiro 43182-5\nVerksamhet: Serietillverkning av\nträ-, board- o plywooddetaljer\nFabrik: Högsäter. Tel 0528-402 60\nAntal anställda: 175\nÅrsomsättning: 14 000 000\nAktiekapital: 100 000\nÄgare o chefer: E Sundqvist,\nA Windt\n\nEtableringsår: 1946.\n\nSUNDQVIST CHOKLAD. &amp;\nKONFEKTFABRIK, K G\n\nPnr 414 55\n\nGöteborg, Karl Johansg 57. Tel\n031-12 3946, 12 39 48. Bankgiro\n512-9408. Postgiro 46398-4\nVerksamhet: Tillverkar choklad,\nkonfekt o marsipan\nÄgare o chef: K G Sundqvist\nEtableringsår: 1933.",
    "structured": {
        "1": {
            "company_name": "DREWS & CO AB",
            "pnr": "41121",
            "address": "Göteborg, Skeppsbron 5-6",
            "phone_number": "031-13 7 0 26, 1108 66",
            "bank_details": {
                "bankgiro": "50-0177",
                "postgiro": "44971-0"
            },
            "activity": "Agenturrörelse med bomull, textila avfallsråvaror, natursten, jute, ull m m",
            "employees": null,
            "annual_turnover": 17000000,
            "capital": null,
            "key_personnel": [
                {
                    "name": "Jan Drews",
                    "position": null
                },
                {
                    "name": "Hans Drews",
                    "position": null
                }
            ],
            "establishment_year": 1934
        },
        "2": {
            "company_name": "DRIFTSINSTRUKTION EL-VVS, AB",
            "pnr": "200 25",
            "address": "Malmö 16, Box 16040, Johannes-lustg 1",
            "phone_number": "040-18 67 30",
            "bank_details": {
                "bankgiro": "615-5048",
                "postgiro": "438700-7"
            },
            "activity": "Konsulterande ingenjörer inom EL-VVS",
            "employees": null,
            "annual_turnover": null,
            "capital": null,
            "key_personnel": [
                {
                    "name": "Arne Bjuvholt",
                    "position": null
                }
            ],
            "establishment_year": null
        },
        "3": {
            "company_name": "DRIFTSKONTROLL EL- VVS, AB",
            "pnr": "200 25",
            "address": "Malmö 16, Box 16040, Sailerupsv 130",
            "phone_number": "040-93 58 30",
            "bank_details": {
                "bankgiro": "633-1110",
                "postgiro": "357 220-3"
            },
            "activity": "Konsulterande ingenjörer inom EL-VVS",
            "employees": null,
            "annual_turnover": null,
            "capital": null,
            "key_personnel": [
                {
                    "name": "H Jönsson",
                    "position": null
                }
            ],
            "establishment_year": null
        },
        "4": {
            "company_name": "DRIVTEKNIK, AB",
            "pnr": "117 44",
            "address": "Stockholm, Nybo hovsbacken 85-89",
            "phone_number": "08-45 25 55",
            "bank_details": {
                "bankgiro": "56-9547",
                "postgiro": "559431"
            },
            "activity": "Säljer mek drivutrust-ningar o transmissionsdetaljer för varje industriellt behov",
            "employees": null,
            "annual_turnover": null,
            "capital": null,
            "key_personnel": [
                {
                    "name": "Ing Per Lindberg",
                    "position": null
                }
            ],
            "establishment_year": 1959
        },
        "5": {
            "company_name": "TERNACO, AB",
            "pnr": "11122",
            "address": "Stockholm C, Kungsg 53",
            "phone_number": "08-204295.20 9191",
            "bank_details": {
                "bankgiro": "48-3558",
                "postgiro": "402150"
            },
            "activity": "Agentur i skinn, läder o animaliska produkter",
            "employees": null,
            "annual_turnover": null,
            "capital": 10000,
            "key_personnel": [
                {
                    "name": "Hugo M Frosch",
                    "position": null
                }
            ],
            "establishment_year": 1966
        },
        "6": {
            "company_name": "KJ BESLAG AB",
            "pnr": "653 41",
            "address": "Karlstad, Spärrg 6",
            "phone_number": "054-18 50 50",
            "bank_details": {
                "bankgiro": "615-2300",
                "postgiro": "8760-1"
            },
            "activity": "Säljer byggnadsbeslag, vipportar o pivåfönster",
            "employees": null,
            "annual_turnover": null,
            "capital": 15000,
            "key_personnel": [
                {
                    "name": "Disp Bengt Ohlsson",
                    "position": "Styrelseordf"
                },
                {
                    "name": "Disp Bengt Ohlsson",
                    "position": "Chef"
                }
            ],
            "establishment_year": 1970
        },
        "7": {
            "company_name": "KJELL, KJÄLL MASKINER & VERKTYG AB, ARNE",
            "pnr": "46100",
            "address": "Trollhättan, Box 214, Drottningg 63",
            "phone_number": "0520-369 00 , 369 01",
            "bank_details": {
                "bankgiro": "225-1916",
                "postgiro": "691192-9"
            },
            "activity": "Säljer verktyg, maskiner, svetsaggregat o svetselektroder, hydraul- o industrislang, mätverktyg",
            "employees": 5,
            "annual_turnover": null,
            "capital": 30000,
            "key_personnel": [
                {
                    "name": "Arne Kjäll",
                    "position": "Verkst dir"
                }
            ],
            "establishment_year": 1968
        },
        "8": {
            "company_name": "ÅHMANS MÖBELFABRIK AB, G",
            "pnr": "290 20",
            "address": "Åhus, Box 41",
            "phone_number": "044-24 10 20",
            "bank_details": {
                "bankgiro": "873-6308",
                "postgiro": null
            },
            "activity": "Tillverkar möbler o inredningar",
            "employees": null,
            "annual_turnover": null,
            "capital": null,
            "key_personnel": [
                {
                    "name": "G Åhman",
                    "position": "Verkst din"
                }
            ],
            "establishment_year": 1860
        },
        "9": {
            "company_name": "CONRADS KONFEKTIONS AB",
            "pnr": "500 02",
            "address": "Borås 2, Box 22032, Grönbog 4",
            "phone_number": "033-1272 35",
            "bank_details": {
                "bankgiro": "53-1164",
                "postgiro": "163733"
            },
            "activity": "Damklänningar",
            "employees": 40,
            "annual_turnover": null,
            "capital": 210000,
            "key_personnel": [
                {
                    "name": "Disp Conrad Conradson",
                    "position": "Verkst dir"
                }
            ],
            "establishment_year": 1943
        },
        "10": {
            "company_name": "ARNELL AB,AND",
            "pnr": "510 22",
            "address": "Hyssna",
            "phone_number": "0320-390 04, 392 40",
            "bank_details": {
                "bankgiro": "436-2299",
                "postgiro": "83333-5"
            },
            "activity": "Tillverkar o säljer hem- o fabriksstickade strumpor",
            "employees": null,
            "annual_turnover": 1500000,
            "capital": 50000,
            "key_personnel": [
                {
                    "name": "Olof Arnell",
                    "position": "Verkst dir"
                }
            ],
            "establishment_year": 1874
        },
        "11": {
            "company_name": "GOTEBORGS MAKADAM AB",
            "pnr": "430 50",
            "address": "KåUered",
            "phone_number": "031-75 12 20",
            "bank_details": {
                "bankgiro": "42-0064",
                "postgiro": "146763"
            },
            "activity": "Tillverkar makadam, betong o oljegrus samt precisions-graderat, såväl färgat som ofärgat stenmaterial o torrbruk för mur- o puts ändamål, betongplattor, fabriks-tillverkad matjord ’Humutex’",
            "employees": 260,
            "annual_turnover": null,
            "capital": 3000000,
            "key_personnel": [
                {
                    "name": "Lennart Albihn",
                    "position": "Verkst dir"
                }
            ],
            "establishment_year": 1939
        },
        "12": {
            "company_name": "GOTEBORGS MOSS. FABRIKS AB",
            "pnr": "414 59",
            "address": "Göteborg, Karl Johansg 29",
            "phone_number": "031-24 81 10, 2482 40",
            "bank_details": {
                "bankgiro": "510-5713",
                "postgiro": "12081-6"
            },
            "activity": "Tillverkar alla slags sydda huvudbonader",
            "employees": 52,
            "annual_turnover": 1500000,
            "capital": 300000,
            "key_personnel": [
                {
                    "name": "Nils Göransson",
                    "position": "Verkst dir"
                }
            ],
            "establishment_year": 1877
        },
        "13": {
            "company_name": "GOTEBORGS NEON RÖRFABRIK GÖTA-NEON AB",
            "pnr": "400 13",
            "address": "Göteborg 36, Box 36016, Kilsg 10",
            "phone_number": "031-1967 10, 196711",
            "bank_details": {
                "bankgiro": "420-3212",
                "postgiro": "428383-4"
            },
            "activity": "Tillverkar o reparerar neonskyltar. Eget glasblåseri",
            "employees": 8,
            "annual_turnover": 800000,
            "capital": null,
            "key_personnel": [
                {
                    "name": "Fabr Gunnar W Fagberg",
                    "position": "Chef"
                }
            ],
            "establishment_year": 1954
        },
        "14": {
            "company_name": "TOTTIE & CO, CHARLES",
            "pnr": "11148",
            "address": "Stockholm, Nybrokajen 7",
            "phone_number": "08-1197 20, 1197 30",
            "bank_details": null,
            "activity": "Försäkringsrörelse. Svenska direktionen för Commer-cial Union Ass Co Ltd London",
            "employees": 10,
            "annual_turnover": null,
            "capital": null,
            "key_personnel": [
                {
                    "name": "Dir Lars Stenberg",
                    "position": null
                },
                {
                    "name": "civiling Ivar Körner",
                    "position": null
                }
            ],
            "establishment_year": 1920
        },
        "15": {
            "company_name": "TOUR AGENTURER AB",
            "pnr": "12172",
            "address": "Johanneshov, Svärdlångsv 46",
            "phone_number": "08-910100",
            "bank_details": null,
            "activity": "Avdelningskontor i: Göteborg, Malmö, Norrköping, Sundsvall, Umeå, Örebro",
            "employees": 300,
            "annual_turnover": 50000000,
            "capital": 1500000,
            "key_personnel": [
                {
                    "name": "Bertil Regnér",
                    "position": "Verkst din"
                }
            ],
            "establishment_year": 1925
        },
        "16": {
            "company_name": "HULTGREN AB,VERNER",
            "pnr": "652 25",
            "address": "Karlstad, Hamng 22",
            "phone_number": "054-1800 75",
            "bank_details": {
                "bankgiro": "671-8381",
                "postgiro": "522071-0"
            },
            "activity": "Revision, bokslut, bokföring, skatteärenden, ekonomisk planering o data-service",
            "employees": 6,
            "annual_turnover": 200000,
            "capital": 40000,
            "key_personnel": [
                {
                    "name": "Lars V Hultgren",
                    "position": "Verkst dir"
                },
                {
                    "name": "Bengt Hultgren",
                    "position": "Ing"
                },
                {
                    "name": "Ingemar Jonsson",
                    "position": "Revisorassistenter"
                },
                {
                    "name": "Thomas Kennerstad",
                    "position": "Revisorassistenter"
                }
            ],
            "establishment_year": null
        },
        "17": {
            "company_name": "HULTSFREDS SKOGSPRODUKTER, AB",
            "pnr": "400 10",
            "address": "Göteborg 3, Box 3015, Karl Gus-tavsg 1 A",
            "phone_number": "031-1120 95",
            "bank_details": {
                "bankgiro": "50-1047",
                "postgiro": "163478-1"
            },
            "activity": "Exporterar trävaror",
            "employees": 3,
            "annual_turnover": 3500000,
            "capital": 35000,
            "key_personnel": [
                {
                    "name": "Vilh Werner",
                    "position": "Verkst dir"
                }
            ],
            "establishment_year": 1936
        },
        "18": {
            "company_name": "SUNDQVIST & WINDT AB",
            "pnr": "42014",
            "address": "Säve",
            "phone_number": "031-9605 00",
            "bank_details": {
                "bankgiro": "441-1575",
                "postgiro": "43182-5"
            },
            "activity": "Serietillverkning av trä-, board- o plywooddetaljer",
            "employees": 175,
            "annual_turnover": 14000000,
            "capital": 100000,
            "key_personnel": [
                {
                    "name": "E Sundqvist",
                    "position": "Ägare"
                },
                {
                    "name": "A Windt",
                    "position": "Ägare"
                }
            ],
            "establishment_year": 1946
        },
        "19": {
            "company_name": "SUNDQVIST CHOKLAD. & KONFEKTFABRIK, K G",
            "pnr": "414 55",
            "address": "Göteborg, Karl Johansg 57",
            "phone_number": "031-12 3946, 12 39 48",
            "bank_details": {
                "bankgiro": "512-9408",
                "postgiro": "46398-4"
            },
            "activity": "Tillverkar choklad, konfekt o marsipan",
            "employees": null,
            "annual_turnover": null,
            "capital": null,
            "key_personnel": [
                {
                    "name": "K G Sundqvist",
                    "position": "Ägare o chef"
                }
            ],
            "establishment_year": 1933
        }
    }
}