{
    "original": "JUNEFRUKT, AB\n\nPnr 552 40\n\nJönköping, Aspholmsg 11. Tel\n036-1195 90. Bankgiro 10-60452.\nPostgiro 470040\n\nVerksamhet: Partiaffär i färsk\nsvensk o utländsk frukt samt\ngrönsaker\n\nAntal anställda: 6\nAktiekapital: 20 000\nFirmatecknare: Ragnar Sandén,\nAxel Sandén, David Sandén\nEtableringsår: 1952.\n\nVEL\n\nPostgiro 3143. Telex 19995\nVEGETE S. Tga Vegetebolagen\nVerksamhet: Koncernbeteckning\nför Försäkringsbolaget Göta,\nömsesidigt av 1876;\nFörsäkringsaktiebolaget Svenska Veritas;\nEuropeiska Varu- och\nResgodsförsäkringsaktiebolaget; Försäkringsbolaget Liv-Göta, ömsesidigt\nAntal anställda: 520\nÅrsomsättning:\nGöta 71000 000\nSvenska Veritas 33 000 000\nEuropeiska 17 000000\nLiv-Göta 46 000 000\nAktiekapital:\n\nSvenska Veritas 1 250 000\nEuropeiska 200 000\nVerkst dir: Ake Molin\nEtableringsår:\nGöta 1876\n\nSvenska Veritas 1924\nEuropeiska 1920\nLiv-Göta 1942.\n\nWE|BER MASKIN AB, S\n\nPnr 21152\n\nMalmö, Skolg 19. Tel 040-709 60.\nBankgiro 348-3112. Postgiro\n539411. Tga Swemaskin\nVerksamhet: Säljer\nverktygsmaskiner o verktyg\nAntal anställda: 5\nAktiekapital: 50 000\nVerkst dir: Ing Sten-Sture Weiber\nEtableringsår: 1963.\n\nAMB\n\nALVELINS\nBYGGNADS-STÄLLNINGAR, AB\n\nPnr 41106\n\nGöteborg, Köpmansg 9 B. Tel\n031-11 72 95 , 22 78 79. Bankgiro\n848-0782. Postgiro 241382-1\nVerksamhet: Monterar o uthyr\nbyggnadsställningar för revetering\nav fastigheter o alla slags\nmålnings o reparationsarbeten\nAntal anställda: 30\nÅrsomsättning: 1300 000\nAktiekapital: 50 000\nVerkst din Sigfrid Hofmann\nEtableringsår: 1946.\n\nKUMLA FRUKTINDUSTRI, AB\n\nPnr 692 00\n\nKumla, V Drottningg 33. Box 18.\nTel 019-79220. Bankgiro 606-1824.\nPostgiro 91689-0. Tgä Kumlafrukt.\nTelex 73381 KUMFRU S\nVerksamhet: Saft- o\nsylttillverk-ning\n\nAntal anställda: 123\nÅrsomsättning: 36000 000\nAktiekapital: 1000 000\nVerkst dir: Frank Olof Jansson\nEtableringsår: 1949.\n\nTOFTERSTRYCKERI AB\n\nPnr 74046\n\nOk te rv åla. Tel 0292-105 30.\nBankgiro 81-2614. Postgiro 73439-2\nVerksamhet: Högtryck o\noffsettryck. Bokbinderiavdelning. Utför\nsystemblanketter, reklamtryck,\nbroschyrer o böcker\nFilial: Uppsala. Wretmans\nboktryckeri AB, O Agatan 33. Tel\n018-10 0060\nAntal anställda: 55\nÅrsomsättning: 3 000 000\nAktiekapital: 35 000\nVeikst dir: Simon Tofters\nEtableringsår: 1918.\n\nTOLEDO-RE LIANCE\nSCANDINAVIA AB\n\nPnr 116 24\n\nStockholm, Asög 142. Tel\n08-24 24 25. Bankgiro 283-8506.\nPostgiro 154040-0. Tga Tolswede\nVerksamhet: Industrivågar,\nautomatiska vägningssystem, elmotorer\nmed styrutrustningar o industriella\nreglersystem\nAntal anställda: 49\nÅrsomsättning: 7 000 000\nAktiekapital: 50 000\nStyrelse: Adv Ake Kron, Mr T O\nMetcalf, civiling Carl-Erik Sjöström,\nciviling B-A Erikson\nVerkst dir: Civiling Bengt-Ake\nErikson\n\nEtableringsår: 1926.\n\nTHOLÉN &amp; STENBERG\nBYGGNADS AB\n\nPnr 416 64\n\nGöteborg, Anders Perssonsg 14.\nTel 031-80 02 80. Bankgiro\n42-0457. Postgiro 243515\nVerksamhet: Utför brobyggnader,\nhusbyggnader, Industribyggnader\nAntal anställda: 70\nÅrsomsättning: 7 000 000\nAktiekapital: 100 000\nVerkst dir: Ing Ragnar Stenberg\nEtableringsår: 1948.\n\nTOLFS\nKOPIERINGS-SERVICE, AB\n\nPnr 552 40\n\nJönköping. Museig 7. Tel\n036-16 84 81. Postgiro 274868-9\nVerksamhet: Kopieringsanstalt\nAktiekapital: 5 000\nVerkst dir: Bertil Tolf\nEtableringsår: 1969.\n\nTOLF AB, BOKFORINGS.\nBYRÅN B\n\nPnr 55240\n\nJönköping. Museig 7. Tel 036-\n\n1242 02, 12 94 55\n\nBOKSLUT, REVISIONER\nBOUPPTECKNINGAR\n\nVerksamhet: Utför bokslut,\nrevisioner , bouppteckningar o\nbolagsbildningar\nAntal anställda: 7\nAktiekapital: 10 000\nVerkst dir Bertil Tolf\nEtableringsår: 1961.\n\nSVENSK BYGGTJÄNST, AB\n\nPnr 11184\n\nStockholm 1, Mäster Samuelsg 38.\nBox 1403. Tel 08-24 28 60.\nBankgiro 722-3696. Postgiro 54033-6.\nTga Bygginform\n\nVerksamhet: Informationscentral\nför byggnadsfacket\nAntal anställda: 65\nÅrsomsättning: 11000 000\nAktiekapital: 504 400\nStyrelse: Dir Nils Nessen (ordf),\ndir Hardy Bengtsson, övering Harry\nBernhard, övering Gunnar Essunger,\ndir Stig Göthlin, prof Gunnar\nHenriksson, förbundssekr Tage\nJönsson, dir Sten Källenius, adv Kjell\nSjöstedt, civiling Evert Strokirk,\nciviling Sven Tyrén\nVerkst dir: Civiling Ingvar Karlen\nEtableringsår: 1934.\n\nSVENSK CELLULOID.\nINDUSTRI AB\n\nPnr 332 00\n\nGislaved. Tel 0371-116 00.\nBankgiro 42-6745. Postgiro 99562. Telex\n70007. Tga Celluloid\n\niraon\ni plast\n\nVerksamhet: Formsprutade\nprecisionsdetaljer i termoplast för\nindustrin. Skumplast i block, bearbetade\ndetaljer för industrin samt\nmadrasser m m (Dröm Vila)\nVarunamn: DrömVila, Carpetfix\nAntal anställda: 350\nÅrsomsättning: 35 000 000\nAktiekapital: 1000 000\nStyrelse: Disp Thure Mårtenson\n(ordf), dlr Georg Jergelius,\nverk-mäst Bengt Mårtenson, nämndeman\nHarry Norin, dir Lars Stendahl\nVerkst dir: Georg Jergelius\nEkonomichef: Sture Schill\nFörsäljn-chefer: (Skumplast): Folke\nMuller (Termoplast): Erik\nGustavson\n\nInköpschef: Klas Hallin\nEtableringsår: 1920.\n\nSVENSK ELEKTRONIK.\nKONSULT\n\nPnr 400 64\n\nGöteborg 49, Box 49025.\nHantverkshuset Stampen, N Agatan 10. Tel\n031-15 55 30. Postgiro 524428-0\nVerksamhet: Medicinsk o\nindustriell elektronisk mätteknik. Laborar\ntorium\n\nÄgare o chef: Civiling Carl-Axel\n\nWannerskog\n\nEtableringsår: 1958.\n\nVARGLÄDERFABRIKEN AB\n\nPnr 45101\n\nUddevalla 1, Strömstads v 30. Box\n\n52. Tel 0522-16106, 126 83.\nBankgiro 428-1754. Postgiro 279828-8.\nTga Vargläder\n\nVerksamhet: Partihandel med råa\nhudar o skinn\nAntal anställda: 7\nÅrsomsättning: 6 000 000\nAktiekapital: 50 000\nVerkst dir: Stellan Ljungberg\nEtableringsår: 1944.\n\nHERNIA, AB\n\nPnr 600 12\n\nNorrköping 12, Borgs\nindustriområde. Box 12033. Tel 011-13 97 00.\nBankgiro 125-0851. Postgiro\n11214-4. Tga Hernia. Telex 64336\nVerksamhet: TUlverkar lim, klister,\ndextrin m m\n\nAvdelningskontor: 21427 Malmö,\nAhlmansg 7. Tel 040-96 2194\n421 31 Västra Frölunda, Frökotteg\n19. Tel 031-49 37 96\n172 03 Sundbyberg 3, Landsv 28.\nTel 08-28 33 51\n.Antal anställda: 110\nÅrsomsättning: 19 000 000\nAktiekapital: 800 000\nVerkst dir: B Hofverberg\nEtableringsår: 1920\nOmbildat till aktiebolag 1943.\n\nHERNO BRYGGERI AB\n\nPnr 87100\n\nHärnösand. Tel 0611-105 55.\nBankgiro 18-5831. Postgiro 28837\nVerksamhet: Malt- o\nläskedrycks-tillverkning\nAntal anstäUda: 30\nÅrsomsättning: 3 500 000\nAktiekapital: 445 500\nVerkst dir: Disp Lennart Valentin\nEtableringsår: 1888.\n\nHEROLFS KONSTRUKTIONS.\nBYRÅ AB\n\nPnr 113 54\n\nStockholm, Roslagsg 56. Tel\n08-3188 30, 34 25 99. Bankgiro\n47-7702. Postgiro 151004\nVerksamhet: Konsulterande inom\nbyggnadsbranschen\nAntal anställda: 4\nÅrsomsättning: 200 000\nAktiekapital: 5 000\nVerkst dir: Civiling Erik Herolf\nEtableringsår: 1965.\n\nHEROLF KONSULTERANDE\nINGENJORSBYRA AB, ERIK\n\nPnr85102\n\nSundsvall 1, Box 38. S Järnvägsg\n\n31. Tel 060-1257 00. Bankgiro\n180-1422. Postgiro 336065-8\nVerksamhet: Konstruktioner,\ngrund undersökningar, kontroller\nAntal anstäUda: 50\nÅrsomsättning: 2 000 000\nAktiekapital: 5 000\nVerkst dir: Civiling Erik Herolf\nEtableringsår: 1948.\n\nHERRLJUNGA\nGUMMI-VERKSTAD AB\n\nPnr 524 00\n\nHerr ljunga, Box 98. Storg 31. Tel\n0513-110 15. Bankgiro 84-1037.\nPostgiro 93733\n\nVerksamhet: Regummering av\nbilringar, Nynäs bensinstation\nAntal anställda: 12\nÅrsomsättning: 1500 000\nAktiekapital: 100 000\nVerkst dir: Gunnar Sandin\nEtableringsår: 1933.\n\nHERRLJUNGA LEDSTÅNGS.\nFABRIK, AB\n\nPnr 524 00\n\nHerr ljunga, Söderg. Tel 0513-103 70\nVerksamhet: Ledstänger o\nhandledare\n\nAntal anställda: 14\nÅrsomsättning: 900 000\nAktiekapital: 80 000\nVerkst dir: Henry Svensson\nEtableringsår: 1945.\n\nHERRLJUNGA METALL.\nFABRIK AB\n\nPnr 524 00\n\nHerrljunga. Tel 0513-104 29.\nPostgiro 381600\n\nVerksamhet: TUlverkar armatur för\nvatten, värme o ånga\nAntal anstäUda: 6\n■Aktiekapital: 25 000\nVerkst dir: Barthold Johansson\nEtableringsår: 1946.\n\nHERRLJUNGA MÖBEL.\nFABRIK AB\n\nPnr 524 00\n\nHerrljunga. Tel 0513-11055.\nBankgiro 84-1008. Postgiro 72950\nVerksamhet: Bäddmöbler\nAktiekapital: 225 000\nVerkst dir: Gösta Karbing\nEtableringsår: 1918.\n\nHUD\n\nHORNS SÅG &amp; HYVLERI\nPETTERSSON &amp; CO\n\nPnr 590 42\n\nHom, Box 38. Tel 0494-300 38,\n30103. Bankgiro 12-9436.\nPostgiro 369252\n\nVerksamhet: Tillverkar fritidshus,\nbaracker, garage o rastkojor\nAntal anställda: 20\nÅrsomsättning: 1000 000\nChef: Ingvar Pettersson\nEtableringsår: 1954.\n\nHORNGRENS EFTR,\nAB FREDR\n\nPnr 103 14\n\nStockholm 2, Stora Nyg 45 026. Box\n2133. Tel 08-11 21 77. 11 21 78.\nBankgiro 568-9195. Postgiro\n55660-5. Tga Horngloves\nVerksamhet: Partiförsäljning av\nar-betsskyddsmaterial (handskar)\nAntal anställda: 13\nAktiekapital: 100 000\nÄgare o chef: Nils Rehnström\nEtableringsår 1858\nOmbildat till aktiebolag 1960.\n\nHORREDS MÖBELINDUSTRI AB\n\nPnr510 10\n\nHorred. Tel 0320-600 9 2 , 803 34.\nPostgiro 138051\n\nVerksamhet: Tillverkar bokhyllor\nAntal anställda: 70\nÅrsomsättning: 9 000 000\nAktiekapital: 100000\nVerkst dir: Fabr Sven Johansson\nEtableringsår: 1936.\n\nHORWITZ FÖRSÄLJNINGS\nAB, GUSTAF\n\nPnr 115 37\n\nStockholm, Lidingöv 75. Tel\n08-67 94 50. Bankgiro 732-0492.\nPostgiro 34-9. Tga Texzeta.\nTelex 10613 TEXZETA S\nVerksamhet: Säljer Jockey\nherrkläder i Sverige o Finland\nVarunamn: Jockey\nAntal anställda: 40\nÅrsomsättning: 16000 000\nAktiekapital: 100 000\nVerkst dir. Göran Horwitz\nEtableringsår: 1880.\n\nSVE\n\nAntal anställda: 16\nÅrsomsättning: 1500000\nAktiekapital: 30 000\nVerkst dir: Ing Erik Svedberg\nEtableringsàr: 1946.\n\nSVEDBERGS I DALSTORP AB\n\nPnr 510 95\n\nDalstorp. Tel 0321-600 15, 603 05.\nBankgiro 98-1638. Postgiro 447047\nVerksamhet: Specialitet: moderna\nbadrumsskåp o låsbara medicinskåp.\nTillbehör, tvättställsbänkar\nAntal anställda: 20\nAktiekapital: 150 000\nÄgare o chefer: Stig Svedberg o\nSune Svedberg\nEtableringsàr: 1920.\n\nSWEDBERG &amp; KRONBERG\nRESEBYRÅ AB\n\nPnr 85102\n\nSundsvall 1, Stora torget. Box 76.\nTel 060-15 03 50,15 43 50. Bankgiro\n55-0396. Postgiro 713300-2. Tga\nSwedtravel. Telex 71013\nVerksamhet: Fullständig\nresebyråverksamhet\nAntal anställda: 13\nFöreståndare: Per O Hammarström\nEtableringsàr: 1935.\n\nSVEDBERG, AB C H\n\nPnr 71200\n\nHällefors, Brandtv 1 C. Box 42.\nTel 0591-11551, 12345. Bankgiro\n60-5846. Postgiro 107430-1\nVerksamhet: Entreprenader med\nlastmaskiner o dumprar samt\nkrossning av bergavfall från gruvor\nAntal anställda: 6\nÅrsomsättning: 500 000\nAktiekapital: 5 000\nStyrelse: Dir Hugo Svedberg (ordf),\nfru Anna Svedberg\nVerkst dir: Carl Hugo Svedberg\nArbetschef: Kjell-Arne Svedberg\nVerkmäst: Lars R B Svedberg\nEtableringsàr: 1962.\n\nSWEDBERG AB, HARALD\n\nPnr 113 58\n\nStockholm, Döbelnsg 16 A. Tel\n08-15 13 50. Postgiro 199008.\nTga Agentswed. Telex 10785\nVerksamhet: Agenturfirma i\nleksaker, toalettvaror o klockor\nAntal anställda: 10\nÅrsomsättning: 10 000 000\nAktiekapital: 20 000\nVerkst dir: Harald Swedberg\nEtableringsàr: 1944.\n\nSVEDBOMSGULDSMEDS AB,\nHOVJUVELERARE\n\nPnr 57401\n\nVetlanda 1, Kanalg 7. Box 52. Tel\n0383-100 96, 109 60. Bankgiro\n28-9711. Postgiro 25191. Tga\nSved-boms\n\nVerksamhet: Tillverkar guld, silver\no tennvaror\nAntal anställda: 100\nÅrsomsättning: 9 000 000\nAktiekapital: 832 000\nVerkst dir: Ake Svedbom\nEtableringsàr: 1905.\n\nSWEDEX, AB\n\nPnr 203 11\n\nMalmö 4, Box 4013. Storg 9. Tel\n040-743 85. Bankgiro 348-3583.\nPostgiro 149494-7. Tga Heidexag\nVerksamhet: Säljer kuvert, pärmar\no tejp\n\nAktiekapital: 25 000\nVerkst dir: K Heide\nEtableringsàr: 1944.\n\nSVEDIA DENTAL.\nINDUSTRI AB\n\nPnr 199 01\n\nEnköping 1, Box 71. Tel\n0171-333 00. Bankgiro 80-4310. Postgiro\n56378. Tga Svedia\nVerksamhet: Tillverkar kem dei&gt;\ntalpreparat, instrument o utensilier\nför dentaländamål samt\nuniversalmotorer för industriellt bruk\nAntal anställda: 32\nÅrsomsättning: 3 500 000\nAktiekapital: 40 000\nStyrelse: Disp Harald Nordin (ordf),\nbankdir Erik Murén, tandl Jarl\nSynnefors\n\nVerkst dir: Bengt Schyllberg\nEtableringsàr: 1927\nOmbildat till aktiebolag 1933.\nNuvarande namn 1939. Äger Svedion\nCo AB oSvediaverken AB, Enköping.\n\nSWEDISH CONTAINER AB\n\nPnr 402 71\n\nGöteborg 8, Box 8804. Gamla Tuvev\n3. Tel 031-26 50 20, 23 82 30.\nBankgiro 337-7355. Postgiro\n244045-1\n\nVerksamhet: Pallboxar,\nspecialemballage i plywood, trä o stål\nÅrsomsättning: 325 000\nAktiekapital: 10 000\nVerkst dir: Ing Odd Nyman\nEtableringsàr: 1963.\n\nEtableringsàr: 1837\nOmbildat till aktiebolag 1925.\nDotterbolag: Swedish Trading Co\nLtd, Hong Kong, Kuala Lumpur o\nSingapore, Streco AB, Stockholm.\n\nSWEDPRESS AB\n\nPnr 127 04\n\nSkärholmen 4, Box 4044.\nStång-holmsbacken 63-77. Tel\n08-710 00 60. Bankgiro 540-5584.\nPostgiro 450670-5\n\nVerksamhet: Utger Teknik för Alla,\nKonsumentGUIDE m fi\nAntal anställda: 20\nÅrsomsättning: 6 000 000\nAktiekapital: 65 000\nVerkst dir: Bo Djörke\nEtableringsàr: 1968.\n\nSWEDSTAB AB\n\nPnr 823 00\n\nKilafors, Box 54. Sibo. Tel\n0278-504 00. Bankgiro 150-8829.\nPostgiro 383887-7. Tga Swedstab.\nTelex 81148 SWEDKOL S\nVerksamhet: Tillverkar o säljer\nmetalltvålar, huvudsakligen\nstearater samt stabilisatorer för\nPVC\n\nAntal anställda: 10\nÅrsomsättning: 1500 000\nAktiekapital: 150 000\nVerkst dir: ing Helmer Elfström\nEtableringsàr: 1968.\n\nSVEGEA BOKTRYCKERI, AB\n\nPnr 45101\n\nUddevalla 1, Junog 5. Box 339. Tel\n0522-165 00, 165 01. Bankgiro\n42-8114. Postgiro 31447\nVerksamhet: Tryckerirörelse\nAntal anställda: 23\nAktiekapital: 65 000\nVerkst dir: Sven Andersson.\n\nSWEDISH RAIL SYSTEM\nAB S R 5\n\nPnr 17121\n\nSolna 1, Sommarv 3. Box 1031. Tel\n08-83 06 60.\n\nTga Railsystem, Stockholm.\nTelex 10406 RAIL S\nVerksamhet: Levererar material\ntill o bygger spår av alla slag.\nÅtager sig spårunderhåll på\nlångtidskontrakt, projektering o konsultar\ntioner i spårfrågor\nAktiekapital: 250 000\nVerkst dir: Ingvar Svensson\nEtableringsàr: 1960.\n\nSWEDISH TRADING\nCOMPANY AB\n\nPnr 103 26\n\nStockholm 16, Arsenalsg 2. Box\n16302. Tel 08-23 0175. Bankgiro\n160-4313. Postgiro 53519-5. Tga\nSwedetrade. Telex 19085\nVerksamhet: Importerar\ntransport-o sopmaskiner. Exporterar stål,\nkullager, telefoner, maskiner o\nmaskinförnödenheter\nAvdelningskontor: Göteborg 36,\nPartihallarna. Box 36066. Tel\n031-192640\n\nMalmö, Borrg 3. Tel 040-18 58 60\nVarunamn: LansingBagnall, Wayne\nAktiekapital: 400000\nVerkst dir: Lennart Larsson\n\nSWEGMARK FABRIKS AB, H\n\nPnr 50105\n\nBorås 1, Herr ljung ag. Box 281. Tel\n033-10 23 10. Bankgiro 36-0856.\nPostgiro 134799.\nTelex 36110 SWEFAB S\nVerksamhet: Tillverkar behå o\nkorsettartiklar\n\nVarunamn: Splendide, Swegmark of\nSweden\n\nAntal anställda: 275\nÅrsomsättning: 16 000000\nAktiekapital: 1000 000\nStyrelseordf: Dir Harry Swegmark\nVerkst dir: Civiling Gösta\nSwegmark\n\nEtableringsàr: 1937.\n\nSWEMA\n\nSvenska Mätapparater F A B\n\nPnr 123 05\n\nFarsta 5, Pepparv 27. Fack. Tel\n08-94 00 90. Tga Swemacontrol,\nStockholm. Telex 17671 SWEMA S\nVerksamhet: Tillverkar elektr\nmätinstrument o -apparater\nAktiekapital: 160 000\nVerkst dir: Axel Th Carlander\nEtableringsàr 1944.",
    "structured": {
        "1": {
            "company_name": "JUNEFRUKT, AB",
            "activity": "Partiaffär i färsk svensk o utländsk frukt samt grönsaker",
            "establishment_year": 1952,
            "employees": 6,
            "capital": 20000
        },
        "2": {
            "company_name": "VEL",
            "activity": "Koncernbeteckning för Försäkringsbolaget Göta, ömsesidigt av 1876; Försäkringsaktiebolaget Svenska Veritas; Europeiska Varu- och Resgodsförsäkringsaktiebolaget; Försäkringsbolaget Liv-Göta, ömsesidigt",
            "establishment_year": null,
            "employees": 520,
            "annual_turnover": {
                "Göta": 71000000,
                "Svenska Veritas": 33000000,
                "Europeiska": 17000000,
                "Liv-Göta": 46000000
            },
            "capital": {
                "Svenska Veritas": 1250000,
                "Europeiska": 200000
            },
            "key_personnel": [
                {
                    "name": "Ake Molin",
                    "position": "Verkst dir"
                }
            ]
        },
        "3": {
            "company_name": "WE|BER MASKIN AB, S",
            "activity": "Säljer verktygsmaskiner o verktyg",
            "establishment_year": 1963,
            "employees": 5,
            "capital": 50000,
            "key_personnel": [
                {
                    "name": "Ing Sten-Sture Weiber",
                    "position": "Verkst dir"
                }
            ]
        },
        "4": {
            "company_name": "AMB ALVELINS BYGGNADS-STÄLLNINGAR, AB",
            "activity": "Monterar o uthyr byggnadsställningar för revetering av fastigheter o alla slags målnings o reparationsarbeten",
            "establishment_year": 1946,
            "employees": 30,
            "annual_turnover": 1300000,
            "capital": 50000,
            "key_personnel": [
                {
                    "name": "Sigfrid Hofmann",
                    "position": "Verkst din"
                }
            ]
        },
        "5": {
            "company_name": "KUMLA FRUKTINDUSTRI, AB",
            "activity": "Saft- o sylttillverk-ning",
            "establishment_year": 1949,
            "employees": 123,
            "annual_turnover": 36000000,
            "capital": 100000,
            "key_personnel": [
                {
                    "name": "Frank Olof Jansson",
                    "position": "Verkst dir"
                }
            ]
        },
        "6": {
            "company_name": "TOFTERSTRYCKERI AB",
            "activity": "Högtryck o offsettryck. Bokbinderiavdelning. Utför systemblanketter, reklamtryck, broschyrer o böcker",
            "establishment_year": 1918,
            "employees": 55,
            "annual_turnover": 3000000,
            "capital": 35000,
            "key_personnel": [
                {
                    "name": "Simon Tofters",
                    "position": "Verkst dir"
                }
            ]
        },
        "7": {
            "company_name": "TOLEDO-RE LIANCE SCANDINAVIA AB",
            "activity": "Industrivågar, automatiska vägningssystem, elmotorer med styrutrustningar o industriella reglersystem",
            "establishment_year": 1926,
            "employees": 49,
            "annual_turnover": 7000000,
            "capital": 50000,
            "key_personnel": [
                {
                    "name": "Civiling Bengt-Ake Erikson",
                    "position": "Verkst dir"
                }
            ]
        },
        "8": {
            "company_name": "THOLÉN & STENBERG BYGGNADS AB",
            "activity": "Utför brobyggnader, husbyggnader, Industribyggnader",
            "establishment_year": 1948,
            "employees": 70,
            "annual_turnover": 7000000,
            "capital": 100000,
            "key_personnel": [
                {
                    "name": "Ing Ragnar Stenberg",
                    "position": "Verkst dir"
                }
            ]
        },
        "9": {
            "company_name": "TOLF AB, BOKFORINGS. BYRÅN B",
            "activity": "Utför bokslut, revisioner , bouppteckningar o bolagsbildningar",
            "establishment_year": 1961,
            "employees": 7,
            "capital": 10000,
            "key_personnel": [
                {
                    "name": "Bertil Tolf",
                    "position": "Verkst dir"
                }
            ]
        },
        "10": {
            "company_name": "SVENSK BYGGTJÄNST, AB",
            "activity": "Informationscentral för byggnadsfacket",
            "establishment_year": 1934,
            "employees": 65,
            "annual_turnover": 11000000,
            "capital": 504400,
            "key_personnel": [
                {
                    "name": "Civiling Ingvar Karlen",
                    "position": "Verkst dir"
                }
            ]
        },
        "11": {
            "company_name": "SVENSK CELLULOID. INDUSTRI AB",
            "activity": "Formsprutade precisionsdetaljer i termoplast för industrin. Skumplast i block, bearbetade detaljer för industrin samt madrasser m m (Dröm Vila)",
            "establishment_year": 1920,
            "employees": 350,
            "annual_turnover": 35000000,
            "capital": 1000000,
            "key_personnel": [
                {
                    "name": "Disp Thure Mårtenson",
                    "position": "Styrelseordf"
                },
                {
                    "name": "verk-mäst Bengt Mårtenson",
                    "position": null
                },
                {
                    "name": "nämndeman Harry Norin",
                    "position": null
                },
                {
                    "name": "dir Lars Stendahl",
                    "position": null
                },
                {
                    "name": "Georg Jergelius",
                    "position": "Styrelse"
                }
            ]
        },
        "12": {
            "company_name": "SVENSK ELEKTRONIK. KONSULT",
            "activity": "Medicinsk o industriell elektronisk mätteknik. Laborar torium",
            "establishment_year": 1958,
            "employees": null,
            "capital": null,
            "key_personnel": [
                {
                    "name": "Civiling Carl-Axel Wannerskog",
                    "position": "Ägare o chef"
                }
            ]
        }
    }
}