{
    "original": "FAGERSANNA VERKEN AB\n\nPnr 54030\n\nFagersanna. Tel 0504-200 10\nVerksamhet: Tillverkar sågade o\nhyvlade trävaror\nAntal anställda: 40\nÅrsomsättning: 5 000 000\nAktiekapital: 20 000\nVerkst dir: Berndt Frisk\nEtableringsår: 1878.\n\nLJU\n\nLJUNGGRENS PAPPERS.\nINDUSTRI AB\n\nPnr 212 29\n\nMalmö, Danska v 53 A. Tel\n040-94 48 00. Bankgiro 640-4008.\nPostgiro 435532-7\n\nVerksamhet: Tillverkar\nlyxembal-lage, huvudsakligen av transparent\nmaterial\n\nÄgare o chef: Hans Curt\nLjunggren\n\nEtableringsår: 1954.\n\nALVENIUS INDUSTRIER, AB\n\nPnr 63107\n\nEskilstuna 1, Kungsg 75. Box 522.\nTel 016-1101 60. Bankgiro 60-1417.\nPostgiro 396050. Telex 40976. Tga\nAlvenius\n\nVerksamhet: Snabbkopplingsrör,\nrörinstallationer (prefab),\nrörtillverkning (spiral), klädfack,\nbalkongtillverkning (prefab)\nFilial: 114 31 Stockholm. Park\nHotell, Karlav 43. Tel 08-22 9620\nÅrsomsättning: 55 000 000\nAktiekapital: 1575 000\nStyrelse: Bankdir Yngwe Anderson\n(ordf), dir Johan Alvenius, övering\nJohn Alvenius, ing Erik Alvenius,\ndir Arne Jansson, disp Sten Ärver,\ndir Tage Nilsson\nVerkst dir: Arne Jansson\nEtableringsår: 1951.\n\nCASTINGS, AB\n\nPnr 230 30\n\nOxie, Blekekullsv 45. Tel\n040-44 94 10. Bankgiro 870-8430.\nPostgiro 633513-0\n\nVerksamhet: Säljer gjut-,\nstål-gjut- o aducergjutgods, segjärn\nAntal anställda: 10\nÅrsomsättning: 8 000 000\nAktiekapital: 40 000\nChefer: Ing Allan Persson, Sam\nGiselsson\n\nEtableringsår: 1965.\n\nIRSTA KAROSSERIFABRIK AB\n\nPnr 725 90\n\nVästerås, Irsta. Tel 021-200 66.\nBankgiro 985-3086. Postgiro\n36410-9\n\nVerksamhet: Tillverkar o reparerar\nkarosserier. Specialitet: skjutbara\nkapellstativ\nAntal anstäUda: 5\nÅrsomsättning: 330 000\nAktiekapital: 7 500\nVeikst dir: Roland Gardh\nEtableringsår: 1954.\n\nIRU AB, INTERNATIONELL\nREKLAM &amp; UTSTÄLLNINGAR\n\nPnr 41116\n\nGöteborg C. Vallg 21. Tel 031-\n\n17 41 60. Postgiro 479208. Tga\nIru-reklam\n\nVerksamhet: Reklam o\nutställningar\n\nAntal anstäUda: 10\n\nÅrsomsättning: 750 000\nAktiekapital: 50 000\nVerkst dir Claus U Priwin\nEtableringsår: 1960.\n\nSVENSKA SECOVA AB\n\nPnr 11138\n\nStockholm, Johannesg 2. Tel\n08-20 97 73, 20 97 74. Postgiro 707810.\nTga Svensksecova\nVerksamhet: Utför rostskydds- o\nunderhållsmålning\nAktiekapital: 15 000\nVerkst dir: Bertil Dahlqvist\nEtableringsån 1964.\n\nSVENSK OLJEIMPORT, AB\n\nPnr 200 12\n\nMalmö 2, Kamrerg 32. Box 2078.\nTel 040-120111, 1174 30. Bankgiro\n15-6451. Postgiro 38423. TgaSvol\nVerksamhet: Säljer bil-, traktor- o\nindustrioljor, smörjfett o\npresenningar\n\nAktiekapital: 100 000\nVerkst dir: Philip Sandström\nEtableringsår: 1911.\n\nSVENSK PAPPERSINDUSTRI,\nJÄRNFORS &amp; HALL AB\n\nPnr 510 40\n\nSandared. Tel 033-55150. Bankgiro\n53-3619.Postgiro 170167.Tga Par\npertube, Borås\n\nVerksamhet: Tillverkar\npapperstuber, textilhylsor, flänsrullar,\nstörre pappburkar o drums\nAntal anställda: 150\nÅrsomsättning: 6 000 000\nAktiekapital: 200 000\nChefer: Disp Albert Hall, fabr-chef\nGösta Järnfors\nEtableringsår: 1935\nOmbildat till aktiebolag 1942.\n\nSVENSK PETROLEUM\nFUR-VALTNING AB\n\nPnr 113 59\n\nStockholm, Sveav 76. Tel 08-\n\n23 02 20. Bankgiro 560-1711.\nPostgiro 353000-3\n\nVerksamhet: Beredskapslagring av\npetroleumprodukter\nAntal anställda: 12\nAktiekapital: 100 000\nVerkst dir: Hans Rockström\nEtableringsår: 1960.\n\nSVENSK\nPETROLEUMADMINISTRATION, AB\n\nPnr 113 59\n\nStockholm, Sveav 76. Tel\n08-23 02 20. Bankgiro 561-1520.\nPostgiro 197400-5.\n\nVerksamhet: Beredskapslagring av\npetroleumprodukter\nAntal anställda: 23\nAktiekapital: 500 000\nVerkst din Hans Rockström\nEtableringsår: 1963.\n\nHOGS TEGEL AB\n\nPnr 244 00\n\nKävlinge. Tel 046-392 90.\nBankgiro 660-9002. Postgiro 97429-5\nVerksamhet: Tillverkar fasadtegel\nAntal anställda: 30\nÅrsomsättning: 4 000 000\nAktiekapital: 205 000\nVerkst dir Thord Ahlström\nEtableringsår 1923.\n\nHOGALIDS METALL.\nFABRIK AB\n\nPnr 330 30\n\nGnosjö. Tel 0370-95048.\nBankgiro 54-2596. Postgiro 265080\nVerksamhet: Tillverkar\ntryckmä-tarkranar samt andra kikkranar\nVerkst dir Harald Knuts son\nEtableringsår: 1934.\n\nALFAX AB\n\nPnr 20110\n\nMalmö 1, Larocheg 4. Fack. Tel\n040-708 60. Bankgiro 640-5252.\nPostgiro 538928-3. Tga Alfax.\nTelex 32504 ALFAX S\nVerksamhet: Tillverkar syrgas,\nacetylen, kvävgas, flytande kväve,\nsvetsargon, specialsvetsgaser.\nAndningsoxygen, lustgas m fi\nmedicinska gaser. Helium o\növriga ädelgaser, högrena gaser o\nprecisa gasblandningar.\nFörsäljning av Kryoteknisk utrustning.\nGasarmatur, svetsarmatur o\nmembrankompressorer\nVarunamn: Alfax\nFabrikskontor 212 24 Malmö,\nLundav 147. Tel 040-708 60\n232 00 Ar löv, Testv. Tel\n040-43 2810\n\n26135 Landskrona, Ostpiren. Tel\n0418-15313, 265 40\n291 02 Kristianstad,\nIndustriområdet, Näsby. Tel 044-12 0818,\n125752\n\n373 00 Kallinge. Tel 0457-243 60\nGöteborg. Postl 705, pa 424 02\nAngered. Tel 031-70 30 70, 70 34 50\n571 00 Nässjö. Tel 0380-189 30\n721 36 Västerås 1, Kraftlinjeg 14.\nBox 961. Tel 021-12 22 90, 12 30 90\n691 00 Karlskoga. Tel 0586-533 83\nAntal anställda: 112\nAktiekapital: 7 000 000\nVerkst dir: Jörgen Faxe\nDir Hans Beckvid\nTekn-dir: A Ekstrand\nKamrer: Gunnar Lestrup\nFörsäljn-chef: Arne Pålson\nEtableringsår: 1911.\n\nBIL &amp; BUSS I ORSA AB\n\nPnr 794 00\n\nOrsa, Box 28. Tel 0250-409 10\nVerksamhet: Bilar, reservdelar o\nbilverkstad\nAntal anställda: 68\nÅrsomsättning: 15 580 000\nAktiekapital: 250 000\nVerkst dir: Gösta Lindqvist\nEtableringsår: 1952.",
    "structured": {
        "1": {
            "company_name": "FAGERSANNA VERKEN AB",
            "pnr": "54030",
            "address": "Fagersanna",
            "phone_number": "0504-200 10",
            "activity": "Tillverkar sågade o hyvlade trävaror",
            "employees": 40,
            "annual_turnover": 5000000,
            "capital": 20000,
            "key_personnel": [
                {
                    "name": "Berndt Frisk",
                    "position": "Verkst dir"
                }
            ],
            "establishment_year": 1878
        },
        "2": {
            "company_name": "LJUNGGRENS PAPPERS. INDUSTRI AB",
            "pnr": "212 29",
            "address": "Malmö, Danska v 53 A",
            "phone_number": "040-94 48 00",
            "bank_details": {
                "bankgiro": "640-4008",
                "postgiro": "435532-7"
            },
            "activity": "Tillverkar lyxembal-lage, huvudsakligen av transparent material",
            "key_personnel": [
                {
                    "name": "Hans Curt Ljunggren",
                    "position": "Ägare o chef"
                }
            ],
            "establishment_year": 1954
        },
        "3": {
            "company_name": "ALVENIUS INDUSTRIER, AB",
            "pnr": "63107",
            "address": "Eskilstuna 1, Kungsg 75",
            "phone_number": "016-1101 60",
            "bank_details": {
                "bankgiro": "60-1417",
                "postgiro": "396050"
            },
            "activity": "Snabbkopplingsrör, rörinstallationer (prefab), rörtillverkning (spiral), klädfack, balkongtillverkning (prefab)",
            "employees": 0,
            "annual_turnover": 55000000,
            "capital": 1575000,
            "key_personnel": [
                {
                    "name": "Bankdir Yngwe Anderson",
                    "position": "Styrelse ordf"
                },
                {
                    "name": "dir Johan Alvenius",
                    "position": "Verkst dir"
                }
            ],
            "establishment_year": 1951
        },
        "4": {
            "company_name": "CASTINGS, AB",
            "pnr": "230 30",
            "address": "Oxie, Blekekullsv 45",
            "phone_number": "040-44 94 10",
            "bank_details": {
                "bankgiro": "870-8430",
                "postgiro": "633513-0"
            },
            "activity": "Säljer gjut-, stål-gjut- o aducergjutgods, segjärn",
            "employees": 10,
            "annual_turnover": 8000000,
            "capital": 40000,
            "key_personnel": [
                {
                    "name": "Ing Allan Persson",
                    "position": "Chefer"
                },
                {
                    "name": "Sam Giselsson",
                    "position": "Chefer"
                }
            ],
            "establishment_year": 1965
        },
        "5": {
            "company_name": "IRSTA KAROSSERIFABRIK AB",
            "pnr": "725 90",
            "address": "Västerås, Irsta",
            "phone_number": "021-200 66",
            "bank_details": {
                "bankgiro": "985-3086",
                "postgiro": "36410-9"
            },
            "activity": "Tillverkar o reparerar karosserier. Specialitet: skjutbara kapellstativ",
            "employees": 5,
            "annual_turnover": 330000,
            "capital": 7500,
            "key_personnel": [
                {
                    "name": "Roland Gardh",
                    "position": "Verkst dir"
                }
            ],
            "establishment_year": 1954
        },
        "6": {
            "company_name": "IRU AB, INTERNATIONELL REKLAM & UTSTÄLLNINGAR",
            "pnr": "41116",
            "address": "Göteborg C, Vallg 21",
            "phone_number": "031-17 41 60",
            "bank_details": {
                "postgiro": "479208"
            },
            "activity": "Reklam o utställningar",
            "employees": 0,
            "annual_turnover": 750000,
            "capital": 50000,
            "key_personnel": [
                {
                    "name": "Claus U Priwin",
                    "position": "Verkst dir"
                }
            ],
            "establishment_year": 1960
        },
        "7": {
            "company_name": "SVENSKA SECOVA AB",
            "pnr": "11138",
            "address": "Stockholm, Johannesg 2",
            "phone_number": "08-20 97 73, 20 97 74",
            "bank_details": {
                "postgiro": "707810"
            },
            "activity": "Utför rostskydds- o underhållsmålning",
            "capital": 15000,
            "key_personnel": [
                {
                    "name": "Bertil Dahlqvist",
                    "position": "Verkst dir"
                }
            ],
            "establishment_year": 1964
        },
        "8": {
            "company_name": "SVENSK OLJEIMPORT, AB",
            "pnr": "200 12",
            "address": "Malmö 2, Kamrerg 32, Box 2078",
            "phone_number": "040-120111, 1174 30",
            "bank_details": {
                "bankgiro": "15-6451",
                "postgiro": "38423"
            },
            "activity": "Säljer bil-, traktor- o industrioljor, smörjfett o presenningar",
            "capital": 100000,
            "key_personnel": [
                {
                    "name": "Philip Sandström",
                    "position": "Verkst dir"
                }
            ],
            "establishment_year": 1911
        },
        "9": {
            "company_name": "SVENSK PAPPERSINDUSTRI, JÄRNFORS & HALL AB",
            "pnr": "510 40",
            "address": "Sandared",
            "phone_number": "033-55150",
            "bank_details": {
                "bankgiro": "53-3619",
                "postgiro": "170167"
            },
            "activity": "Tillverkar papperstuber, textilhylsor, flänsrullar, större pappburkar o drums",
            "employees": 150,
            "annual_turnover": 6000000,
            "capital": 200000,
            "key_personnel": [
                {
                    "name": "Disp Albert Hall",
                    "position": "Chefer"
                }
            ],
            "establishment_year": 1935
        },
        "10": {
            "company_name": "SVENSK PETROLEUM FUR-VALTNING AB",
            "pnr": "113 59",
            "address": "Stockholm, Sveav 76",
            "phone_number": "08-23 02 20",
            "bank_details": {
                "bankgiro": "560-1711",
                "postgiro": "353000-3"
            },
            "activity": "Beredskapslagring av petroleumprodukter",
            "employees": 12,
            "capital": 100000,
            "key_personnel": [
                {
                    "name": "Hans Rockström",
                    "position": "Verkst dir"
                }
            ],
            "establishment_year": 1960
        },
        "11": {
            "company_name": "SVENSK PETROLEUMADMINISTRATION, AB",
            "pnr": "113 59",
            "address": "Stockholm, Sveav 76",
            "phone_number": "08-23 02 20",
            "bank_details": {
                "bankgiro": "561-1520",
                "postgiro": "197400-5"
            },
            "activity": "Beredskapslagring av petroleumprodukter",
            "employees": 23,
            "capital": 500000,
            "key_personnel": [
                {
                    "name": "Hans Rockström",
                    "position": "Verkst dir"
                }
            ],
            "establishment_year": 1963
        },
        "12": {
            "company_name": "HOGS TEGEL AB",
            "pnr": "244 00",
            "address": "Kävlinge",
            "phone_number": "046-392 90",
            "bank_details": {
                "bankgiro": "660-9002",
                "postgiro": "97429-5"
            },
            "activity": "Tillverkar fasadtegel",
            "employees": 30,
            "annual_turnover": 4000000,
            "capital": 205000,
            "key_personnel": [
                {
                    "name": "Thord Ahlström",
                    "position": "Verkst dir"
                }
            ],
            "establishment_year": 1923
        },
        "13": {
            "company_name": "HOGALIDS METALL. FABRIK AB",
            "pnr": "330 30",
            "address": "Gnosjö",
            "phone_number": "0370-95048",
            "bank_details": {
                "bankgiro": "54-2596",
                "postgiro": "265080"
            },
            "activity": "Tillverkar tryckmä-tarkranar samt andra kikkranar",
            "key_personnel": [
                {
                    "name": "Harald Knutsson",
                    "position": "Verkst dir"
                }
            ],
            "establishment_year": 1934
        },
        "14": {
            "company_name": "ALFAX AB",
            "pnr": "20110",
            "address": "Malmö 1, Larocheg 4, Fack",
            "phone_number": "040-708 60",
            "bank_details": {
                "bankgiro": "640-5252",
                "postgiro": "538928-3"
            },
            "activity": "Tillverkar syrgas, acetylen, kvävgas, flytande kväve, svetsargon, specialsvetsgaser. Andningsoxygen, lustgas m fi medicinska gaser. Helium o övriga ädelgaser, högrena gaser o precisa gasblandningar",
            "employees": 112,
            "capital": 7000000,
            "key_personnel": [
                {
                    "name": "Jörgen Faxe",
                    "position": "Verkst dir"
                }
            ],
            "establishment_year": 1911
        },
        "15": {
            "company_name": "BIL & BUSS I ORSA AB",
            "pnr": "794 00",
            "address": "Orsa, Box 28",
            "phone_number": "0250-409 10",
            "activity": "Bilar, reservdelar o bilverkstad",
            "employees": 68,
            "annual_turnover": 15580000,
            "capital": 250000,
            "key_personnel": [
                {
                    "name": "Gösta Lindqvist",
                    "position": "Verkst dir"
                }
            ],
            "establishment_year": 1952
        }
    }
}