{
    "original": "FAL\n\nAktiekapital: 40 000\nVerkst dir: Gunnar Fager\nEtableringsår: 1925.\n\nBÄCK-DAHLGREN AB\n\nPnr 11160\n\nStockholm, Drottningg 81 B. Tel\n08-20 57 26. Bankgiro 56-5245.\nPostgiro 25 1 328-1. Tga Bedeco\nVerksamhet: Agenturfirma i\nkemikalier\n\nAktiekapital: 10 000\nVerkst dir: Uno Dahlgren\nEtableringsår: 1945.\n\nBÄCKEFORS BRUKS AB\n\nse Mustad AB, J.\n\nBÄCKHAMMARS BRUK AB\n\nse Vänerindustrier AB,\nSkogsägarnas.\n\nBÄCKLINS GLASMÄSTERI AB\n\nPnr 116 48\n\nStockholm, Mariatorget 1. Tel\n08-43 18 21,43 92 82. Bankgiro\n57-1215. Postgiro 4815\nVerksamhet: Glasmästeri.\nGlassli-peri. Byggnads- o\ninredningsglas-ning. Säljer glas, speglar, ramar\no konst\n\nAktiekapital: 46 300\n\nVerkst dir: Vilhelm Svennewall\n\nEtableringsår: 1913.\n\nALVESTA PRESSVERKTYG AB\n\nPnr 342 00\n\nAlvesta, Snickaregränd 6. Tel\n0472-104 72. Bankgiro 147-1184.\nPostgiro 392723-1\nVerksamhet: Tillverkar\nformverktyg för bakelit- o plastindustri\nAktiekapital: 40 000\nVerkst dir: Lennart Fransson\nEtableringsår: 1954.\n\nALVESTA SPEGELFABRIK &amp;\nGLASSLIPERI AB\n\nPnr 342 00\n\nAlvesta. Tel 0472-100 58, 100 78.\nBankgiro 334-4306. Postgiro\n86818-2. Tga Spegelfabriken\n\nDetaljer för butiksinredningar\nGlasslipning\n\nSpegelfoliering\n\nVerksamhet: Tillverkar\nglasmontrar, skjutdörrar, bordsglas,\nspeglar m m\n\nAntal anställda: 8\nÅrsomsättning: 1000 000\nAktiekapital: 50 000\nVerkst dir: B Ströberg.\n\nALVESTA TRÄFURÄDLING &amp;\nMEKANISKA VERKSTAD, AB\n\nPnr 342 00\n\nAlvesta, Box 100. Gjutareg 1. Tel\n0472-130 55. Bankgiro 334-4074.\nPostgiro 34216-2. Tga Alvestaträ.\nTelex 4682\n\nVerksamhet: Sågverk o mekanisk\nverkstad\n\nAntal anställda: 70\nÅrsomsättning: 9 000 000\n\nAktiekapital: 200 000\nVerkst dir: Evald Andersson\nEtableringsår: 1911.\n\nJÄMJO TRÄINDUSTRI AB\n\nPnr 370 40\n\nJämjöslätt, Box42. Tel0455-500 8 0,\n50009. Bankgiro 861-3309.\nPostgiro 36953-8\n\nVerksamhet: Förädling av trävaror\no försäljning av byggnadsmaterial\nAntal anställda: 38\nÅrsomsättning: 2 700 000\nAktiekapital: 125 000\nVerkst dir: Allan Håkansson\nEtableringsår: 1905.\n\nBAR\n\nAktiekapital: 8 000\nVerkst dir: Fjalar Barck\nEtableringsår: 1963.\n\nVERKMETALL, AB\n\nPnr 102 61\n\nStockholm 4, Siarg 9. Box 4081.\nTel 08-44 79 75. Bankgiro 73-1071.\nPostgiro 553390. Telex 19939. Tga\nVerkmetall\n\nVerksamhet: Säljer rörflänsar.\nSpecialitet: centrifugalgjutna stål- o\nmetallflänsar\nÅrsomsättning: 2 000 000\nAktiekapital: 90 000\nVerkst dir: Bertil Svirsky\nEtableringsår: 1956\nOmbildat till aktiebolag 1957.\n\nVERKSTADSSERVICE HÄL.\nSINGBORG AB, MASKINFIRMA\n\nPnr 252 27\n\nHelsingborg, Gåsebäcksv 10. Tel\n042-18 03 55. Bankgiro 445-3270.\nPostgiro 395951-7\nVerksamhet: Säljer maskiner,\nverktyg o verkstadsförnödenheter\nAntal anställda: 15\nÅrsomsättning: 5 000 000\nAktiekapital: 180 000\nVerkst dir: Kamrer Inge Jönsson\nEtableringsår: 1951\nOmbildat till aktiebolag 1959.\n\nVERKTYGS AGENTUREN AB\n\nPnr 126 22\n\nHägersten 1, Box 92. Slalomv 1-5.\nTel 08-46 26 15. Bankgiro 56-9583.\nPostgiro 3617. Tga Vaabtool\nVerksamhet: Köper o säljer\nmaskiner o verktyg\nAntal anställda: 6\nAktiekapital: 30 000\nVerkst dir: Ing I Rydergård\nEtableringsår : 1959.\n\nVERKTYGSBOLAGET SEGER.\nBERG &amp; CO AB\n\nPnr 65106\n\nKarlstad 1, Rederig 5, Inre Hamnen.\nBox 408. Tel 054-15 67 00.\nBankgiro 881-4907. Postgiro 494800-6.\nTelex 66071 VERKBOL S. Tga\nVerkbol\n\nVerksamhet: Säljer verktyg o\nmaskiner för industrin o mek\nverkstäder\n\nAntal anställda: 35\nÅrsomsättning: 12 000 000\nAktiekapital: 54 000\nVerkst dir: Stig Segerberg\nEtableringsår: 1956\nDotterföretag: Maskinaktiebolaget\nAKMA, Kalmar, Jönköping, Malmö.\n\nVERKTYGSMEKANO I\nMOTALA AB\n\nPnr 59100\n\nMotala, Vinterg 5. Tel 0141-134 42.\nBankgiro 822-0097. Postgiro\n441429-8\n\nVerksamhet: Tillverkar\nplastverktyg\n\nAntal anställda: 22\nÅrsomsättning: 1500 000\nAktiekapital: 10 000\nVerkst dir: Carl Andersson\nEtableringsår: 1957.\n\nKINNAHULTS VÄFVERI AB\n\nPnr 51104\n\nKinna 4. Tel 0320-130 10. Bankgiro\n434-8173. Postgiro 9346-8\nVeiksamhet: Vävning av\nhemtextilier\n\nAntal anställda: 55\nÅrsomsättning: 6 500 000\nAktiekapital: 300 000\nVerkst dir: Ingmar Eliason\nEtableringsår: 1961.\n\nJERNMANUFAKTUR AB RACO\n\nPnr 123 57\n\nFarsta, Piprensarv 32. Tel\n08-93 28 00 , 93 2 9 00. Bankgiro\n747-0701. Postgiro 356885-4. Tga\nJern-raco, Stockholm\n\nVerksamhet: Importerar o säljer\nRapid kolv- o bultpistoler,\nstålspik o slagspik, Rapid-Anker\nsjälvborrande stålplugg, KEM-borr med\nhàrdmetallskär o träborr, Tox\nCom-bi o Tox Fenplastplugg, Euromat\n3lagborrmaskin, Pero blindnit,\nKnipping gipssnabbskruv, Helfer\nskruvdrag are\nAvdelningskontor:\nGöteborg. Tel 031-16 9411\nMalmö. Tel 040-12 6 0 41\nVarunamn: Euromat, Pero, KEM,\nRapid, TOX\nAntal anställda: 17\nÅrsomsättning: 4 000 000\nAktiekapital: 25 000\nVerkst dir: Svante Malmgren\nEtableringsår: 1951\nOmbildat 1963.\n\nDotterbolag: AB Jernraco, Farsta.\n\nJÄRNMONTERING, AB\n\nPnr 200 61\n\nMalmö 30, Geijersg 1. Box 30132.\nTel 040-15 3 0 40. Bankgiro\n869-0133. Postgiro 39225-8\nVerksamhet: Tillverkar o monterar\nstålkonstruktioner för hus- o\nindustribyggnader, broar, cisterner,\n\ndammluckor, master, skorstenar etc,\npråmar o pontoner samt allmänna\nplåt- o maskinkonstruktioner\nAntal anställda: 350\nÅrsomsättning: 35 000 000\nAktiekapital: 500 000\nVerkst dir: Einar Johanson\nEtableringsår: 1938.\n\nHTH INDUSTRIER AB\n\nPnr 577 00\n\nHultsfred. Tel 0495-122 63, 106 60.\nBankgiro 12-9442. Postgiro 73290\nVerksamhet: Betongvarufabrik samt\ntegelbruk\n\nAntal anställda: 22\nÅrsomsättning: 2 000 000\nAktiekapital: 70 000\nVerkst dir: Harald Linderson\nEtableringsår: 1940.\n\nekman &amp; co ab\n\nPnr 401 23\n\nGöteborg 1, Stora Nyg 29. Box 230.\nTel 031-17 45 80. Bankgiro\n510-6745. Postgiro 44600-5.\nTga Ekmans. Telex 2353\nVerksamhet: Export av cellulosa,\npapper, stål, maskiner m m.Import\nav textilier, ur, radio, foto, optik,\nmineral, malmer\nAntal anställda: 90\nAktiekapital: 6 600 000\nStyrelse: Dir Harald Boman (ordf),\ndir Börje Gawell, dir Arne\nLundberg, dir Sverker Ljungren, bankdir\nLennart Holmström, dir Bengt\nDunér, dir Gunnar Glimstedt (suppl)\nVerkst dir: Börje Gawell\nCellulosa: Dir Låge Westman, dir\nG Flood\n\nPapper: Dir Sten C: son Lindberg\nImport o teknisk avdelning: Dir\nLars-Erik Backseli\nEtableringsår: 1802.",
    "structured": {
        "1": {
            "company_name": "BÄCK-DAHLGREN AB",
            "establishment_year": 1945,
            "activity": "Agenturfirma i kemikalier"
        },
        "2": {
            "company_name": "BÄCKEFORS BRUKS AB"
        },
        "3": {
            "company_name": "BÄCKHAMMARS BRUK AB"
        },
        "4": {
            "company_name": "BÄCKLINS GLASMÄSTERI AB",
            "pnr": "116 48",
            "address": "Stockholm, Mariatorget 1",
            "phone_number": "08-43 18 21, 43 92 82",
            "bank_details": {
                "bankgiro": "57-1215",
                "postgiro": "4815"
            },
            "activity": "Glasmästeri. Glasslipning. Byggnads- o inredningsglas-ning. Säljer glas, speglar, ramar o konst",
            "employees": 0,
            "capital": 46300,
            "establishment_year": 1913
        },
        "5": {
            "company_name": "ALVESTA PRESSVERKTYG AB",
            "pnr": "342 00",
            "address": "Alvesta, Snickaregränd 6",
            "phone_number": "0472-104 72",
            "bank_details": {
                "bankgiro": "147-1184",
                "postgiro": "392723-1"
            },
            "activity": "Tillverkar formverktyg för bakelit- o plastindustri",
            "capital": 40000,
            "establishment_year": 1954
        },
        "6": {
            "company_name": "ALVESTA SPEGELFABRIK & GLASSLIPERI AB",
            "pnr": "342 00",
            "address": "Alvesta",
            "phone_number": "0472-100 58, 100 78",
            "bank_details": {
                "bankgiro": "334-4306",
                "postgiro": "86818-2"
            },
            "activity": "Tillverkar glasmontrar, skjutdörrar, bordsglas, speglar m m",
            "employees": 8,
            "annual_turnover": 1000000,
            "capital": 50000
        },
        "7": {
            "company_name": "ALVESTA TRÄFURÄDLING & MEKANISKA VERKSTAD, AB",
            "pnr": "342 00",
            "address": "Alvesta, Box 100, Gjutareg 1",
            "phone_number": "0472-130 55",
            "bank_details": {
                "bankgiro": "334-4074",
                "postgiro": "34216-2"
            },
            "activity": "Sågverk o mekanisk verkstad",
            "employees": 70,
            "annual_turnover": 9000000,
            "capital": 200000,
            "establishment_year": 1911
        },
        "8": {
            "company_name": "JÄMJO TRÄINDUSTRI AB",
            "pnr": "370 40",
            "address": "Jämjöslätt, Box42",
            "phone_number": "0455-500 8 0, 50009",
            "bank_details": {
                "bankgiro": "861-3309",
                "postgiro": "36953-8"
            },
            "activity": "Förädling av trävaror o försäljning av byggnadsmaterial",
            "employees": 38,
            "annual_turnover": 2700000,
            "capital": 125000,
            "establishment_year": 1905
        },
        "9": {
            "company_name": "BAR",
            "capital": 8000,
            "establishment_year": 1963
        },
        "10": {
            "company_name": "VERKMETALL, AB",
            "pnr": "102 61",
            "address": "Stockholm 4, Siarg 9, Box 4081",
            "phone_number": "08-44 79 75",
            "bank_details": {
                "bankgiro": "73-1071",
                "postgiro": "553390"
            },
            "activity": "Säljer rörflänsar. Specialitet: centrifugalgjutna stål- o metallflänsar",
            "annual_turnover": 2000000,
            "capital": 90000,
            "establishment_year": 1956
        },
        "11": {
            "company_name": "VERKSTADSSERVICE HÄL. SINGBORG AB, MASKINFIRMA",
            "pnr": "252 27",
            "address": "Helsingborg, Gåsebäcksv 10",
            "phone_number": "042-18 03 55",
            "bank_details": {
                "bankgiro": "445-3270",
                "postgiro": "395951-7"
            },
            "activity": "Säljer maskiner, verktyg o verkstadsförnödenheter",
            "employees": 15,
            "annual_turnover": 5000000,
            "capital": 180000,
            "establishment_year": 1951
        },
        "12": {
            "company_name": "VERKTYGS AGENTUREN AB",
            "pnr": "126 22",
            "address": "Hägersten 1, Box 92, Slalomv 1-5",
            "phone_number": "08-46 26 15",
            "bank_details": {
                "bankgiro": "56-9583",
                "postgiro": "3617"
            },
            "activity": "Köper o säljer maskiner o verktyg",
            "employees": 6,
            "capital": 30000,
            "establishment_year": 1959
        },
        "13": {
            "company_name": "VERKTYGSBOLAGET SEGER. BERG & CO AB",
            "pnr": "65106",
            "address": "Karlstad 1, Rederig 5, Inre Hamnen, Box 408",
            "phone_number": "054-15 67 00",
            "bank_details": {
                "bankgiro": "881-4907",
                "postgiro": "494800-6"
            },
            "activity": "Säljer verktyg o maskiner för industrin o mek verkstäder",
            "employees": 35,
            "annual_turnover": 12000000,
            "capital": 54000,
            "establishment_year": 1956
        },
        "14": {
            "company_name": "VERKTYGSMEKANO I MOTALA AB",
            "pnr": "59100",
            "address": "Motala, Vinterg 5",
            "phone_number": "0141-134 42",
            "bank_details": {
                "bankgiro": "822-0097",
                "postgiro": "441429-8"
            },
            "activity": "Tillverkar plastverktyg",
            "employees": 22,
            "annual_turnover": 1500000,
            "capital": 10000,
            "establishment_year": 1957
        },
        "15": {
            "company_name": "KINNAHULTS VÄFVERI AB",
            "pnr": "51104",
            "address": "Kinna 4",
            "phone_number": "0320-130 10",
            "bank_details": {
                "bankgiro": "434-8173",
                "postgiro": "9346-8"
            },
            "activity": "Vävning av hemtextilier",
            "employees": 55,
            "annual_turnover": 6500000,
            "capital": 300000,
            "establishment_year": 1961
        },
        "16": {
            "company_name": "JERNMANUFAKTUR AB RACO",
            "pnr": "123 57",
            "address": "Farsta, Piprensarv 32",
            "phone_number": "08-93 28 00 , 93 2 9 00",
            "bank_details": {
                "bankgiro": "747-0701",
                "postgiro": "356885-4"
            },
            "activity": "Importerar o säljer Rapid kolv- o bultpistoler, stålspik o slagspik m.m.",
            "employees": 17,
            "annual_turnover": 4000000,
            "capital": 25000,
            "establishment_year": 1951
        },
        "17": {
            "company_name": "JÄRNMONTERING, AB",
            "pnr": "200 61",
            "address": "Malmö 30, Geijersg 1, Box 30132",
            "phone_number": "040-15 3 0 40",
            "bank_details": {
                "bankgiro": "869-0133",
                "postgiro": "39225-8"
            },
            "activity": "Tillverkar o monterar stålkonstruktioner för hus- o industribyggnader, broar, cisterner, dammluckor, master, skorstenar etc, pråmar o pontoner samt allmänna plåt- o maskinkonstruktioner",
            "employees": 350,
            "annual_turnover": 35000000,
            "capital": 500000,
            "establishment_year": 1938
        },
        "18": {
            "company_name": "HTH INDUSTRIER AB",
            "pnr": "577 00",
            "address": "Hultsfred",
            "phone_number": "0495-122 63, 106 60",
            "bank_details": {
                "bankgiro": "12-9442",
                "postgiro": "73290"
            },
            "activity": "Betongvarufabrik samt tegelbruk",
            "employees": 22,
            "annual_turnover": 2000000,
            "capital": 70000,
            "establishment_year": 1940
        },
        "19": {
            "company_name": "EKMAN & CO AB",
            "pnr": "401 23",
            "address": "Göteborg 1, Stora Nyg 29, Box 230",
            "phone_number": "031-17 45 80",
            "bank_details": {
                "bankgiro": "510-6745",
                "postgiro": "44600-5"
            },
            "activity": "Export av cellulosa, papper, stål, maskiner m.m. Import av textilier, ur, radio, foto, optik, mineral, malmer",
            "employees": 90,
            "capital": 6600000,
            "establishment_year": 1802
        }
    }
}