{
    "original": "KALMAR BRYGGERI\n\nPnr 38101\n\nKalmar 1, Storg 52. Box 66. Tel\n0480-15315\n\nVerksamhet: Tillverkar malt- o\nläskedrycker\n\nSe Pripp-Bryggerierna AB.\n\nKALMAR FINMEKANISKA\n\nPnr 381 00\n\nKalmar, Svanebergsg 8. Tel 0480-\n\n178 49\n\nVerksamhet: Säljer Halda\ntaxametrar o Speed Pilot även service på\nautomater, adressmaskiner,\nhushållsmaskiner o vågar\ndief: S E Hagström\nEtableringsår: 1953.\n\nKALMAR GLAS EXPORT\nCO AB\n\nPnr 38101\n\nKalmari, O Vallg 5.Box 10. Tel\n0480-102 33, 127 41. Bankgiro\n272-3492. Postgiro 291388-7. Tga\nExportglass\n\nVerksamhet: Export av glasvaror,\nimport av råvaror för glasindustri\nÄgare o chefer: Carl Eklund,\nLennart Hansson\nEtableringsår: 1931.\n\nSIGARTH\n\nPnr 330 33\n\nHillerstorp. Tel 0370-222 76, 224 76.\nBankgiro 543-2216. Postgiro\n340843-2\n\nVerksamhet: Tillverkar\nmekanismer för arkivpärmar,\nkantskoning-ar för brev- o fakturapärmar,\nbrevkorgar, radiatordetaljer, pressade\no svetsade artiklar i tråd o plåt\nenligt ritning eller prov\nÄgare o chefer: Sigurd Hageberg,\nLennart Hageberg.\n\nSIGETT AB\n\nPnr 200 21\n\nMalmö 21, Box 21047. Lundav 55.\nTel 040-93 07 57, 18 42 02. Bankgiro\n876-8046. Postgiro 147998-9\nVerksamhet: Specialtryckeri för\netiketter av alla slag\nVarunamn: Sigett\nChef: Curt Åkerman\nEtableringsår 1948.\n\nÖSTERBERG, AB HUGO\n\nPnr 103 22\n\nStockholm 16, Hovslagarg 5 B. Box\n16093. Tel 08-231630. Postgiro\n656\n\nVerksamhet: Agenter o importörer\nAktiekapital: 375 000\nVerkst din Tom österberg\nEtableringsån 1919.\n\nÖSTERBERGS INGENIORS.\nBYRA AB, JOEL\n\nPnr 200 12\n\nMalmö 2, Henrik Smithsg 15. Box\n2052. Tel 040-384 00. Bankgiro\n260-2829. Postgiro 148045-8\nVerksamhet: Konsulterande\ningen-jörsbyrå i WS-teknik\nFilialer: 252 27 Hälsingborg, Söderg\n128. Tel 042-14 43 70\n552 40 Jönköping, O Storg 10. Tel\n036-16 53 20\n\n223 61 Lund, O Mårtensg 16. Tel\n046-12 60 90\nAntal anställda: 78\nÅrsomsättning: 4 844 000\nAktiekapital: 500 000\nVerkst dir: Göran Österberg\nV verkst dir Eskil Emander\nEtableringsår 1932\nOmbildat till aktiebolag 1956.\n\nÖSTERBERG, AB RUDOLF\n\nPnr ill 30\n\nStockholm, Skeppsbron 16. Tel\n08-231705. Bankgiro 23-5253. Postr\ngiro 50876. Tga Rosmarin\n\nVerksamhet: Båttillbehör en gros\no i detalj\n\nVerkst dir: Ernst Bernstrand.\n\nÖSTERBY SVETS. &amp;\nSMIDESVERKSTAD AB\n\nPnr 740 63\n\nÖsterby bruk, Ängsv 18. Tel\n0295-200 91. Bankgiro 804-1253.\nPostgiro 573442-1\n\nVerksamhet: Tillverkar patenterade\nfjädrande belastningsvikter för\nbergborrmaskiner. Säljer Göma\nvikter o lantbruksmaskiner.\nEntrétrappor\n\nÅrsomsättning: 200 000\n.Aktiekapital: 10 000\nChef: Göte Mattsson\nEtableringsår: 1960.\n\nÖSTERGÖTLANDS\nANDELS-SLAKTERIFÖRENING U P A\n\nPir 58101\n\nLinköping 1, Fack. Platensg 27.\nTel 013-13 04 40. Bankgiro 12-0061.\nPostgiro 87331-5. Telex 64950\nVerksamhet: Slakterier o charku-\n\nterifabriker\n\nKontrollslakterier: Linköping. Tel\n013-13 04 40. Disp: David Runemark\nVimmerby. Tel 0492-120 80. Disp:\nLars Windolf\nAntal anställda: 350\nÅrsomsättning: 150 000 000\nStyrelseordf: Riksdagsman Ivan\nSvanström\n\nVerkst dir: Torsten Sallnäs\nEtableringsår 1931.\n\nÖSTERGÖTLANDS ENSKILDA\nBANK\n\nPnr 58103\n\nLinköping 1, Storg 23. Box 328.\nTel 013-12 9 1 00. Bankgiro\n120-0013. Postgiro 54 65-0. Tga\nöstgötabanken. Telex 64952 OEBANK S\nAntal anställda: 302\nAktiekapital: 27 040 000\nVerkst dir: Bankdir John Nylén\nEtableringsår: 1837.\n\nÖSTERGÖTLANDS\nMASKIN-AFFÄR, AB\n\nPnr 58102\n\nLinköping 1, Sankt Larsg 22. Box\n203. Tel 013-12 02 90. Bankgiro\n347-0937. Postgiro 11321-7. Tga\nOmaskiner\n\nVerksamhet: Säljer kullager,\nkilrep, kilrepskivor, svetselektroder,\nverktyg av alla slag,\nmaskinförnödenheter, elektr handverktyg,\nsvetsaggregat etc\nAntal anställda: 4\nÅrsomsättning: 800 000\nAktiekapital: 50000\nStyrelse: Ake Bark\nVerkst dir: Ake Bark\nEtableringsår: 1895\nOmbildat till aktiebolag 1945.\n\nÖSTERLENS LASTVAGNS AB\n\nPnr 273 00\n\nTomelilla, Box 110. Industrig. Tel\n0417-116 60. Bankgiro 287-2711.\nPostgiro 673647-4\nVerksamhet: Försäljning av\nlast-vagnär o bussar med tillhörande\nreservdelar o service.\nÅterförsäljare för Volvo\n\nAntal anställda: 30\nÅrsomsättning: 7 000 000\nAktiekapital: 300 000\nStyrelse: Dir Carl Persson (ordf),\ndir G Henry Bengtsson, dir\nAxel-Evert Winquist\nVerkst dir: G H Bengtsson\nPlatschef: Wiggo Kemstedt\nEkonomichef: Heinz Persson\nReservdelschef: Bengt Karlsson\nVerkstadschef: Gunnar Olsson\nEtableringsår: 1965.\n\nBÄC\n\nBÄCKSTRÖM MÅLERI &amp;\nBILLACKERING AB, CURT\n\nPnr 85104\n\nSundsvall 1, Fabriksg 14. Box 217.\nTel 060-15 07 60. Bankgiro\n350-9379. Postgiro 141984-5\nVerksamhet: Yrkesmåleri. Målning\nav bostadshus, fabriker m m\nAntal anställda: 80\nAktiekapital: 50 000\nVerkst dir: Curt Bäckström\nEtableringsår. 1936.\n\nENBORG AB, GUSTAF\n\nPnr 781 01\n\nBorlänge 1, Box 26. Sockenv 112.\nGylletorget. Tel 0243-103 15, 19101.\nBankgiro 465-1253. Postgiro\n28705-2\n\nVerksamhet: Säljer omslagspapper,\npåsar o säckar, bindgarn,\nförseglingsremsor, tape, papp, kartonger,\nindustriemballage (wellpapp,\nperi-pac) samt finpappersvaror\nAktiekapital: 10 000\nVerkst dir: Stig Enborg\nEtableringsår: 1916\nOmbildat till aktiebolag 1963.\n\nENDERLEIN &amp; CO, AB\n\nPnr 660 10\n\nDals Långed. Box 45. Tel\n0532-23100. Bankgiro 431-9430.\nPostgiro 28652-6. Tga Enderlein. Telex\n5319\n\nVerksamhet: Utrustning för\npappers* o cellulosaindustrin samt\nför wellpappindustrin.\nCentri-pellerpumpar, kranar o traverser\nAktiekapital: 5 000\nVerkst dir: Civiling Karl Johan\nEnderlein.\n\nENDRESS+ HAUSER AB\n\nPnr 112 51\n\nStockholm, Nordenflychtsv 62.\nTel 08-520390. Bankgiro\n810-4259. Postgiro 683172-1\nVerksamhet: Försäljning o service\nelektroniska instrument för\nindustriellt bruk\n\nVarunamn: Endress+ Hauser,\nCoster, Müller Steurgräte, Fiessler,\nDaester-Fairtec, Panametrics,\nAlb. Measurements\nAntal anställda: 10\nAktiekapital: 100000\nStyrelse: Adv E T Bendz, herr H\nArns, dir Anders Sundberg\nVerkst dir: Anders Sundberg\nEtableringsår: 1967.\n\nTURESSONS METALL AB\n\nPnr 33030\n\nGnosjö. Tel 0370-970 45, 97145.\nBankgiro 542-4593. Postgiro\n347429-3\n\nVerksamhet: Tillverkar klädhängare,\nkjol- o byxhängareiplast o metall\nVarunamn: Tema\nAntal anställda: 20\nÅrsomsättning: 2500 000\nAktiekapital: 25 000\nStyrelse: Fabr Sven Turesson\n(ordf), kamrer Birgit Turesson\nVerkst dir: Sven Turesson\nEtableringsår: 1958.\n\nALUMINIUMFASADER.\nALUFA-AB\n\nPnr 280 50\n\nStrömsnäsbruk 1, Bang. Box 66. Tel\n0433-205 8 5. Bankgiro 986-1337.\nPostgiro 673866-0. Tga Alufa\n\nVerksamhet: Tillverkar o säljer\n\naluminium- o ståldörrar, fönster,\n\nentrépartier, butiksfasader m m\n\nVarunamn: Alufa\n\nAntal anställda: 45\n\nÅrsomsättning: 5 000 000\n\nAktiekapital: 60000\n\nStyrelse: Ing Herbert Juhrich (ordf),\n\ndir Börje Olsson\n\nVerkst dir. Herbert Juhrich\n\nEtableringsår 1965.\n\nTABOUGNAR, AB\n\nPnr 10271\n\nStockholm 9, Box 9026.\nLövholms-brinken 2 B. Tel 08-45 25 05,\n1802 95. Bankgiro 56-9537.\nPost-giro 252025. Tga Tabougnar.\nTelex 17493\n\nVerksamhet: Tillverkar o säljer\nindustriugnar, industribrännare,\ndestruktionsugnar o\nsopförbränningsugnar\nVarunamn: Tabo\nAntal anställda: 80\nÅrsomsättning: 11000 000\nAktiekapital: 350 000\nStyrelse: Adv Sten Sandell (ordf),\növering Olle V Borgkvist, dir Erik\nOhlin\n\nVerkst dir. Erik Ohlin\nFörsäljn-dir. Erie Pagergren\nTekn chef: Folke Ericsson\nInköpschef: Lars Sjökvist\nKamrer: Lennart Wrannvik\nEtableringsår: 1945.\n\nLINKÖPINGS MASKININDUSTRI\n\nPnr 582 57\n\nLinköping, Söderleden 1 o 6. Tel\n013-12 59 95, 12 42 76. Bankgiro\n82-1979. Postgiro 339816\nVerksamhet: Tillverkar\nautomat-svarvade o pressade massartiklar\nAntal anställda: 10\nChefer: Ing Tommy Wizén, ing\nBertil Wizén\nEtableringsår: 1949.\n\nLINKÖPINGS METALL» &amp;\nSKROTAFFÄR, AB\n\nPnr 58102\n\nLinköping 1, Oskarsg 17. Box 55.\nTel 013-1248 94. Bankgiro\n347-0234. Postgiro 262780-0\nVerksamhet: Handel med järn- o\nmetallskrot\nAktiekapital: 20 000\nVeikst dir: Herbert Andersson\nEtableringsår: 1936.\n\nSTORM &amp; HEIER AB\n\nPnr 400 40\n\nGöteborg 4, Oscarsg 9,\nAmerikahuset. Box 4085. Tel 031-1240 75.\nBankgiro 420-1729. Postgiro\n48342-0. Tga Stormtex. Telex 20630\nVerksamhet: Säljer\nspinnerimaskiner, väverimaskiner,\nstrumpmaski-ner, trikåmaskiner,\nindustrisymaskiner samt delar o nålar till dessa\nAntal anställda: 10\nÅrsomsättning: 7 000 000\nAktiekapital: 20 000\nStyrelse: Adv Gunnar Forssenius\n(ordf), dir Knut N Heier, dir L-A\nLarson\n\nVerkst dir: L-A Larson\nEtableringsår: 1937.\n\nSTORM &amp; CO SKEPPSRADIO,\nAB K\n\nPnr 401 25\n\nGöteborg 1, Ceresg 26. Box 328.\nTel 031-23 51 30. Bankgiro\n420-5076. Postgiro 422717-9. Tga\nStormco.\n\nTelex 20893 TELEKON S\nVeiksamhet: Installation o service\nav radioutrustningar å fartyg.\nKommunikationsradio. Säljer o\ninstallerar elektroniska utrustningar\nAntal anställda: 10\nÅrsomsättning: 1000 000\nAktiekapital: 30 000\nVerkst dir: Civiling Veine\nAndersson\n\nEtableringsår: 1950.\n\nSTORSTOCKHOLMS LOKAL.\nTRAFIK, AB\n\nPnr 113 81\n\nStockholm 6. Box 6301. Tegnérg\n2 A. Tel 08-23 60 00. Bankgiro\n160-1624. Postgiro 53636-7. Tga\nStock-transit\n\nVerksamhet: Kollektiv trafik inom\nStockholms län\nAntal anställda: 6167\nAktiekapital: 17 600 000\nVerkst dir: Helge Berglund\nEtableringsår: 1877.\n\nSTORVIKS JÄRN &amp;\nPLÄT-INDUSTRI\n\nPnr 812 00\n\nStorvik. Box 63. Tel 0290-107 48,\n107 78. Postgiro 396780-9\nVerksamhet: Grovplåtslageri,\nbygg-nadssmide\n\nÅrsomsättning: 150 000\nAktiekapital: 15 000\nÄgare o chef: Stig Br ymer\nEtableringsår: 1951.",
    "structured": {
        "1": {
            "company_name": "KALMAR BRYGGERI",
            "pnr": "38101",
            "address": "Kalmar 1, Storg 52. Box 66",
            "phone_number": "0480-15315",
            "activity": "Tillverkar malt- o läskedrycker",
            "establishment_year": 0
        },
        "2": {
            "company_name": "KALMAR FINMEKANISKA",
            "pnr": "381 00",
            "address": "Kalmar, Svanebergsg 8",
            "phone_number": "0480-178 49",
            "activity": "Säljer Halda taxametrar o Speed Pilot även service på automater, adressmaskiner, hushållsmaskiner o vågar",
            "key_personnel": [
                {
                    "name": "S E Hagström",
                    "position": "dief"
                }
            ],
            "establishment_year": 1953
        },
        "3": {
            "company_name": "KALMAR GLAS EXPORT CO AB",
            "pnr": "38101",
            "address": "Kalmari, O Vallg 5.Box 10",
            "phone_number": "0480-102 33, 127 41",
            "bank_details": {
                "bankgiro": "272-3492",
                "postgiro": "291388-7"
            },
            "activity": "Export av glasvaror, import av råvaror för glasindustri",
            "establishment_year": 1931
        },
        "4": {
            "company_name": "SIGARTH",
            "pnr": "330 33",
            "address": "Hillerstorp",
            "phone_number": "0370-222 76, 224 76",
            "bank_details": {
                "bankgiro": "543-2216",
                "postgiro": "340843-2"
            },
            "activity": "Tillverkar mekanismer för arkivpärmar, kantskoning-ar för brev- o fakturapärmar, brevkorgar, radiatordetaljer, pressade o svetsade artiklar i tråd o plåt enligt ritning eller prov",
            "key_personnel": [
                {
                    "name": "Sigurd Hageberg",
                    "position": "Ägare"
                },
                {
                    "name": "Lennart Hageberg",
                    "position": "Chefer"
                }
            ]
        },
        "5": {
            "company_name": "SIGETT AB",
            "pnr": "200 21",
            "address": "Malmö 21, Box 21047, Lundav 55",
            "phone_number": "040-93 07 57, 18 42 02",
            "bank_details": {
                "bankgiro": "876-8046",
                "postgiro": "147998-9"
            },
            "activity": "Specialtryckeri för etiketter av alla slag",
            "key_personnel": [
                {
                    "name": "Curt Åkerman",
                    "position": "Chef"
                }
            ],
            "establishment_year": 1948
        },
        "6": {
            "company_name": "ÖSTERBERG, AB HUGO",
            "pnr": "103 22",
            "address": "Stockholm 16, Hovslagarg 5 B. Box 16093",
            "phone_number": "08-231630",
            "activity": "Agenter o importörer",
            "capital": 375000,
            "key_personnel": [
                {
                    "name": "Tom Österberg",
                    "position": "Verkst din"
                }
            ],
            "establishment_year": 1919
        }
    }
}