{
    "original": "ARWIDSON, AB DONALD\n\nPnr 751 03\n\nUppsala 1, Box 6. Fyrisvallsg 26.\nTel 018-10 20 35. Bankgiro 62-8303.\nPostgiro 469490\n\nVerksamhet: Säljer som grossist\nbiltillbehör o reservdelar till\nbensinstationer o bilverkstäder\nAntal anställda: 8\nÅrsomsättning: 2 000 000\nAktiekapital: 25 000\nVerkst dir: Donald Arwidson\nEtableringsår: 1964.\n\nVIC\n\nWEXIÖ\n\nse Växjö.\n\nWEZÄTA AB\n\nPnr 402 22\n\nGöteborg 5, Grafiska v. Box 5057.\nTel 031-40 0140. Postgiro 41206-4.\nTga Wezätamelins. Telex 20872\nVerksamhet: Beställningstryck,\nredaktionell service, fotostudio,\nprov kö k\n\nFörsäljningskonton 104 62\nStockholm 17, Box 17085. Tel 08-69 0140\n203 12 Malmö 4, Box 4140. Tel\n040-121610\n\nVerkst dir: Jonas Forssman\nDisp:r: Erland Petersen, Gustaf\nBondeson, Lars Loid.\n\nWEZÄTA FÖRLAG AB\n\nPnr 402 22\n\nGöteborg 5, Grafiska v. Box 5057.\nTel 031-400140.Postgiro241177-5.\nTga Wezätamelins. Telex 20872\nVerkst din Jonas Forssman\nFörlagschef: Arne Arvidsson.\n\nWEZÄTA PRESENT.\nREKLAM AB\n\nPnr 402 22\n\nGöteborg 5, Grafiska v. Box 5057.\nTel 031-4 0 0 1 40.Postgiro527075-6.\nTga Wezätamelins. Telex 20872\nFörsäljningskontor: 104 62\nStockholm 17, Box 17085. Tel 08-69 0140\nVerkst dir: Jonas Forssman\nDisp: Stig-L Alehammar.\n\nWEZÄTA-MELINS AB\n\nPnr 402 22\n\nGöteborg 5, Grafiska v. Box 5057.\nTel 031-400140. Postgiro 46361-2.\nTga Wezätamelins. Telex 20872\nVerksamhet: Tryckeri, förlag,\npappershandels- o presentartiklar\nAntal anställda: 600\nÅrsomsättning: 60 000 000\nVerkst dir: Jonas Forssman\nInköpschef: Lars Karlinder.\n\nVFS INDUSTRIER AB\n\nse Vänerindustrier AB,\nSkogsägarnas .\n\nVIAK AB\n\nPnr 162 10\n\nVällingby 1, Fack. Vällingbyplan\n26. Tel 08-87 00 80. Bankgiro\n577-4880. Postgiro 157841-8. Tga\nIng-viak. Telex 17507 INGVIAK S\nVerksamhet: Konsulterande i\nvattenförsörjning, avlopp o\navfallshantering, vattenkemi, trafikteknik,\ngator, vägar o broar, geoteknik,\nkartframställning,\nsamhällsplanering\n\nDistriktskontor: Boden, Falun,\nGöteborg, Jönköping, Karlstad,\nLinköping, Malmö, Nyköping,\nVisby, Vänersborg, Västerås, Örebro,\nOslo, Bergen, Köpenhamn\nAntal anställda: 800\nÅrsomsättning: 55 000 000\nAktiekapital: 450 000\nVerkst dir: G Naeslund\nEtableringsår: 1930.\n\nSKÅNSKA BYGGMASKINER AB\n\nPnr 21611\n\nMalmö, Polg 32. Tel 040-16 06 00.\nBankgiro 64-6665\n\nVerksamhet: Försäljning o service\nför entreprenadmaskiner\nVerkst dir: Sven-Olov Holm\nEtableringsår: 1965.\n\nFINNÉS AB\n\nPnr 81032\n\nLingbo. Tel 0297-500 00. Bankgiro\n78-8609. Postgiro 73654. TgaFinnés\nVerksamhet: Tillverkar dörrar o\n\nfönster\n\nAntal anstäUda: 116\nÅrsomsättning: 6000 000\nAktiekapital: 609 000\nVerkst dir: Disp Anders Finné\nEtableringsår: 1894.\n\nNIL\n\nAktiekapital: 480 000\nVeikst dir: Fru Lisa Nilsson\nEtableringsår: 1921.\n\nNILSSON &amp; FORLIN\nKONTORSMASKINER, AB\n\nPnr 41103\n\nGöteborg, Odinsg 22. Tel\n031-1997 35. 19 9721. Bankgiro\n202-9429. Postgiro 240486-1\nVerksamhet: Säljer\nkontorsförnödenheter samt nya o begagnade\nkontorsmaskiner, uthyrning\nÄgare o chefer. Bengt Andersson,\nLeif Svensson\nEtableringsår: 1945.\n\nNILSSONS\nINDUSTRIEMBALLAGE AB\n\nPnr 330 27\n\nHestra, Mog 9. Tel 0370-35290\nVerksamhet: Tillverkar pallramar,\nlastpallar, kabeltrummor o\nindustriemballage\n\nAntal anställda: 110\nÅrsomsättning: 16000000\nAktiekapital: 500000\nFirmatecknare: Mats Nilsson, Rune\nNilsson\n\nEtableringsår: 1919.\n\nNILSSONS INDUSTRIER,\nBRUDERNA\n\nPnr 286 02\n\nOrkelljunga 2, Asljunga. Box 2068\nTel 0435-603 00. Bankgiro 67-2619\nPostgiro 283512. Tga Korgnilsson\nVerksamhet: Tillverkar\nträdgårds-möbler, rottingmöbler,\nstålrörsmöb-ler, köksmöbler o lunchrumsmöbler\nÄgare o chef: Ake Nilsson, Bertil\nNilsson\n\nEtableringsår: 1944.\n\nREKLAMLITO\n\nPnr 21143\n\nMalmö, S Förstadsg 18. Tel\n040-333 39, 333 75. Bankgiro 870-6533\nVerksamhet: Offsettryckeri med\nrepro- o bokbinderiavdelningar.\nSpecialitet: skolböcker,\nreklamtrycksaker\nAntal anställda: 25\nÅrsomsättning: 3 000 000\nChef: Arne Woin\nFaktor: Leif Hultgren\nEtableringsår: 1954.\n\nDÄUMICHEN, AB MAX\n\nPnr 114 55\n\nStockholm, Storg 30. Tel\n08-62 8182. Bankgiro 565-4884.\nPostgiro 50217-9. Tga Däumichen.\nTelex 19057\n\nVerksamhet Agenturfirma i järn\no metaller\nAktiekapital: 5 000\nVerkst din Herbert Däumichen\nEtableringsån 1895.\n\ndanielson stål ab, j\n\nPnr 115 28\n\nStockholm, Sandhamnsg 29. Tel\n08-63 0410. Bankgiro 56-7515.\nPostgiro 198300. Telex 10101.\nTga Danostal\n\nVerksamhet: Generalagenter i\nSverige för DEW Magnetfabrik\nDortmund m fi, Västtyskland\nVarunamn: DEW, Oerstit, Oxit\nAntal anställda: 5\nAktiekapital: 50000\nVerkst dir: Ing Robert Lundberg\nEtableringsår: 1955\nDotterbolag,till J Danielson &amp; Co\nAB, Stockholm.\n\ndanielson, ab s d\n\nPnr 662 00\n\nAmål, Box 41. Drottning Kristinas\nväg 6. Tel 0532-12050. Bankgiro\n534-6077. Postgiro 91801-1\nVerksamhet: Hyvleri o\nförsäljning av byggnadsmaterial\nAntal anställda: 20\nÅrsomsättning: 3 500 000\nAktiekapital: 62 500\nVerkst dir: Disp Holger Gustafson\nEtableringsår: 1922.\n\nBRATTSTROM CO AB, ALLAN\n\nPnr 114 54\n\nStockholm, Styrmansg 45. Tel\n08-67 63 47, 67 63 48. Bankgiro\n28-3843. Postgiro 52917. Tga\nAbece-machine\n\nVerksamhet: Maskiner för\nkonserv-o livsmedelsindustrierna, såsom\ncharkuterimaskiner,\nfiskfileterings-maskiner o bryggerimaskiner\nAktiekapital: 25 000\nVerkst dir: Allan Brattström\nEtableringsår: 1922\nOmbildat till aktiebolag 1942.\n\nBRAUN ELECTRIC\nSVENSKA AB\n\nPnr 42122\n\nVästra Frölunda 1, Fröhusg 4. Box\n134. Tel 031-45 05 50. Bankgiro\n420-2628. Postgiro 49954-1. Tga\nInterbraun\n\nVerksamhet: Engrosförsäljning av\nelektriska o batterirakapparater,\nelektriska hushållsapparater,\nfotoprodukter, elektroniska\ncigarettändare samt HIFI-stereoanläggningar\nAntal anställda: 55\nÅrsomsättning: 18 000 000\nAktiekapital: 400 000\nVerkst din Richard S Rohe\nEtableringsår: 1950.\n\nELEKTROKEB, AB\n\nPnr 85103\n\nSundsvall 1, Björneborgsg 25. Box\n149. Tel 060-15 02 80. Bankgiro\n180-1034. Postgiro 345578-9\nVerksamhet: Säljer elmateriel\nengros\n\nAntal anställda: 70\nÅrsomsättning: 36000 000\nAktiekapital: 300 000\nVerkst dir: Karl Erik Bruneflod\nEtableringsår: 1950.",
    "structured": {
        "1": {
            "company_name": "ARWIDSON, AB DONALD",
            "activity": "Säljer som grossist biltillbehör o reservdelar till bensinstationer o bilverkstäder",
            "establishment_year": 1964,
            "employees": 8,
            "annual_turnover": 2000000,
            "capital": 25000,
            "key_personnel": [
                {
                    "name": "Donald Arwidson",
                    "position": "Verkst dir"
                }
            ]
        },
        "2": {
            "company_name": "WEZÄTA AB",
            "address": "Göteborg 5, Grafiska v. Box 5057",
            "phone_number": "031-40 0140",
            "bank_details": {
                "postgiro": "41206-4"
            },
            "activity": "Beställningstryck, redaktionell service, fotostudio, prov kö k",
            "key_personnel": [
                {
                    "name": "Jonas Forssman",
                    "position": "Verkst dir"
                }
            ]
        },
        "3": {
            "company_name": "WEZÄTA FÖRLAG AB",
            "address": "Göteborg 5, Grafiska v. Box 5057",
            "phone_number": "031-400140",
            "bank_details": {
                "postgiro": "241177-5"
            },
            "key_personnel": [
                {
                    "name": "Jonas Forssman",
                    "position": "Verkst dir"
                },
                {
                    "name": "Arne Arvidsson",
                    "position": "Förlagschef"
                }
            ]
        },
        "4": {
            "company_name": "WEZÄTA PRESENT. REKLAM AB",
            "address": "Göteborg 5, Grafiska v. Box 5057",
            "phone_number": "031-4 0 0 1 40",
            "bank_details": {
                "postgiro": "527075-6"
            },
            "key_personnel": [
                {
                    "name": "Jonas Forssman",
                    "position": "Verkst dir"
                },
                {
                    "name": "Stig-L Alehammar",
                    "position": "Disp"
                }
            ]
        },
        "5": {
            "company_name": "WEZÄTA-MELINS AB",
            "address": "Göteborg 5, Grafiska v. Box 5057",
            "phone_number": "031-400140",
            "bank_details": {
                "postgiro": "46361-2"
            },
            "activity": "Tryckeri, förlag, pappershandels- o presentartiklar",
            "employees": 600,
            "annual_turnover": 60000000,
            "key_personnel": [
                {
                    "name": "Jonas Forssman",
                    "position": "Verkst dir"
                },
                {
                    "name": "Lars Karlinder",
                    "position": "Inköpschef"
                }
            ]
        },
        "6": {
            "company_name": "VFS INDUSTRIER AB",
            "activity": "se Vänerindustrier AB, Skogsägarnas"
        },
        "7": {
            "company_name": "VIAK AB",
            "address": "Vällingby 1, Fack. Vällingbyplan 26",
            "phone_number": "08-87 00 80",
            "bank_details": {
                "bankgiro": "577-4880",
                "postgiro": "157841-8"
            },
            "activity": "Konsulterande i vattenförsörjning, avlopp o avfallshantering, vattenkemi, trafikteknik, gator, vägar o broar, geoteknik, kartframställning, samhällsplanering",
            "employees": 800,
            "annual_turnover": 55000000,
            "capital": 450000,
            "key_personnel": [
                {
                    "name": "G Naeslund",
                    "position": "Verkst dir"
                }
            ]
        },
        "8": {
            "company_name": "SKÅNSKA BYGGMASKINER AB",
            "address": "Malmö, Polg 32",
            "phone_number": "040-16 06 00",
            "bank_details": {
                "bankgiro": "64-6665"
            },
            "activity": "Försäljning o service för entreprenadmaskiner",
            "key_personnel": [
                {
                    "name": "Sven-Olov Holm",
                    "position": "Verkst dir"
                }
            ]
        },
        "9": {
            "company_name": "FINNÉS AB",
            "address": "Lingbo",
            "phone_number": "0297-500 00",
            "bank_details": {
                "bankgiro": "78-8609",
                "postgiro": "73654"
            },
            "activity": "Tillverkar dörrar o fönster",
            "employees": 116,
            "annual_turnover": 6000000,
            "capital": 609000,
            "key_personnel": [
                {
                    "name": "Disp Anders Finné",
                    "position": "Verkst dir"
                }
            ]
        },
        "10": {
            "company_name": "NIL",
            "capital": 480000,
            "key_personnel": [
                {
                    "name": "Fru Lisa Nilsson",
                    "position": "Veikst dir"
                }
            ]
        },
        "11": {
            "company_name": "NILSSON & FORLIN KONTORSMASKINER, AB",
            "address": "Göteborg, Odinsg 22",
            "phone_number": "031-1997 35, 19 9721",
            "bank_details": {
                "bankgiro": "202-9429",
                "postgiro": "240486-1"
            },
            "activity": "Säljer kontorsförnödenheter samt nya o begagnade kontorsmaskiner, uthyrning",
            "key_personnel": [
                {
                    "name": "Bengt Andersson",
                    "position": "Ägare o chef"
                },
                {
                    "name": "Leif Svensson",
                    "position": "Ägare o chef"
                }
            ]
        },
        "12": {
            "company_name": "NILSSONS INDUSTRIEMBALLAGE AB",
            "address": "Hestra, Mog 9",
            "phone_number": "0370-35290",
            "activity": "Tillverkar pallramar, lastpallar, kabeltrummor o industriemballage",
            "employees": 110,
            "annual_turnover": 16000000,
            "capital": 500000,
            "key_personnel": [
                {
                    "name": "Mats Nilsson",
                    "position": "Firmatecknare"
                },
                {
                    "name": "Rune Nilsson",
                    "position": "Firmatecknare"
                }
            ]
        },
        "13": {
            "company_name": "NILSSONS INDUSTRIER, BRUDERNA",
            "address": "Orkelljunga 2, Asljunga. Box 2068",
            "phone_number": "0435-603 00",
            "bank_details": {
                "bankgiro": "67-2619",
                "postgiro": "283512"
            },
            "activity": "Tillverkar trädgårds-möbler, rottingmöbler, stålrörsmöb-ler, köksmöbler o lunchrumsmöbler",
            "key_personnel": [
                {
                    "name": "Ake Nilsson",
                    "position": "Ägare o chef"
                },
                {
                    "name": "Bertil Nilsson",
                    "position": "Ägare o chef"
                }
            ]
        },
        "14": {
            "company_name": "REKLAMLITO",
            "address": "Malmö, S Förstadsg 18",
            "phone_number": "040-333 39, 333 75",
            "bank_details": {
                "bankgiro": "870-6533"
            },
            "activity": "Offsettryckeri med repro- o bokbinderiavdelningar. Specialitet: skolböcker, reklamtrycksaker",
            "employees": 25,
            "annual_turnover": 3000000,
            "key_personnel": [
                {
                    "name": "Arne Woin",
                    "position": "Chef"
                },
                {
                    "name": "Leif Hultgren",
                    "position": "Faktor"
                }
            ]
        },
        "15": {
            "company_name": "DÄUMICHEN, AB MAX",
            "address": "Stockholm, Storg 30",
            "phone_number": "08-62 8182",
            "bank_details": {
                "bankgiro": "565-4884",
                "postgiro": "50217-9"
            },
            "activity": "Agenturfirma i järn o metaller",
            "capital": 5000,
            "key_personnel": [
                {
                    "name": "Herbert Däumichen",
                    "position": "Verkst din"
                }
            ]
        },
        "16": {
            "company_name": "danielson stål ab, j",
            "address": "Stockholm, Sandhamnsg 29",
            "phone_number": "08-63 0410",
            "bank_details": {
                "bankgiro": "56-7515",
                "postgiro": "198300"
            },
            "activity": "Generalagenter i Sverige för DEW Magnetfabrik Dortmund m fi, Västtyskland",
            "employees": 5,
            "annual_turnover": 0,
            "capital": 50000,
            "key_personnel": [
                {
                    "name": "Ing Robert Lundberg",
                    "position": "Verkst dir"
                }
            ]
        },
        "17": {
            "company_name": "danielson, ab s d",
            "address": "Amål, Box 41. Drottning Kristinas väg 6",
            "phone_number": "0532-12050",
            "bank_details": {
                "bankgiro": "534-6077",
                "postgiro": "91801-1"
            },
            "activity": "Hyvleri o försäljning av byggnadsmaterial",
            "employees": 20,
            "annual_turnover": 3500000,
            "capital": 62500,
            "key_personnel": [
                {
                    "name": "Disp Holger Gustafson",
                    "position": "Verkst dir"
                }
            ]
        },
        "18": {
            "company_name": "BRATTSTROM CO AB, ALLAN",
            "address": "Stockholm, Styrmansg 45",
            "phone_number": "08-67 63 47, 67 63 48",
            "bank_details": {
                "bankgiro": "28-3843",
                "postgiro": "52917"
            },
            "activity": "Maskiner för konserv-o livsmedelsindustrierna, såsom charkuterimaskiner, fiskfileterings-maskiner o bryggerimaskiner",
            "capital": 25000,
            "key_personnel": [
                {
                    "name": "Allan Brattström",
                    "position": "Verkst dir"
                }
            ]
        },
        "19": {
            "company_name": "BRAUN ELECTRIC SVENSKA AB",
            "address": "Västra Frölunda 1, Fröhusg 4. Box 134",
            "phone_number": "031-45 05 50",
            "bank_details": {
                "bankgiro": "420-2628",
                "postgiro": "49954-1"
            },
            "activity": "Engrosförsäljning av elektriska o batterirakapparater, elektriska hushållsapparater, fotoprodukter, elektroniska cigarettändare samt HIFI-stereoanläggningar",
            "employees": 55,
            "annual_turnover": 18000000,
            "capital": 400000,
            "key_personnel": [
                {
                    "name": "Richard S Rohe",
                    "position": "Verkst din"
                }
            ]
        },
        "20": {
            "company_name": "ELEKTROKEB, AB",
            "address": "Sundsvall 1, Björneborgsg 25. Box 149",
            "phone_number": "060-15 02 80",
            "bank_details": {
                "bankgiro": "180-1034",
                "postgiro": "345578-9"
            },
            "activity": "Säljer elmateriel engros",
            "employees": 70,
            "annual_turnover": 36000000,
            "capital": 300000,
            "key_personnel": [
                {
                    "name": "Karl Erik Bruneflod",
                    "position": "Verkst dir"
                }
            ]
        }
    }
}