{
    "original": "WIHLBORG &amp; SON,\nBYGGNADS AB O P\n\nPnr 21225\n\nMalmö, Stillmansg 10. Tel\n040-93 44 10. Bankgiro 87-019 2.\nPostgiro 148008. Tga Opewihlborg\nVerksamhet: Byggnadsfirma,\nbetongelementfabrik . trähusfabriker\nAntal anställda: 350\nÅrsomsättning: 35 000 000\nAktiekapital: 300 000\nVerkst dir: Byggn-ing Willy\nWihlborg\n\nEtableringsår: 1924.\n\nWILD HEERBRUGG SVENSKA\nAB\n\nPnr 11143\n\nStockholm, Kungsg 7. Tel\n08-23 28 85. Bankgiro 152-3000.\nPostgiro 502120-9. Tga Wildheerbrugg\nVerksamhet: Försäljning o\nreparation av geodetiska,\nfotogrammet-riska o h.ydrometriska instrument\nsamt mikroskop\nAntal anställda: 20\nAktiekapital: 560 000\nVerkst dir: Lennart Olsson\nEtableringsår: 1968.\n\nENE\n\nAntal anställda: 75\nAktiekapital: 1200 000\nVerkst dir: Törd Nilson\nEtableringsår: 1924.\n\nENEQUIST KOLIMPORT, AB\nJOHN\n\nPnr 100 53\n\nStockholm 37, Hamnpirsv 1. Pack.\nTel 08-63 52 20. Bankgiro 56-9307.\nPostgiro 1498. Tga Johnquist\nVerksamhet: Lager- o\nengroshan-del i eldningsoljor, koks, stenkol\nAntal anställda: 28\nÅrsomsättning: 10 000 000\nAktiekapital: 1000 000\nVerkst dir: Friedrich Hermann\nEtableringsår: 1902.\n\nENE RYD A\nTRÄFOR-ÄDLING AB\n\nPnr 340 22\n\nEneryda. Tel 0476-22138, 222 48.\nBankgiro 276-1187. Postgiro\n398027-3. Tga Enewood\nVerksamhet: Tillverkar sågade o\nhyvlade trävaror\nAntal anställda: 35\nÅrsomsättning: 5000 000\nAktiekapital: 150 000\nVerkst dir: Riksdagsman Torsten\nMattsson\n\nEtableringsår: 1940.\n\nENGBERG\nPLÅTSLAGERIVERKSTÄDER, ERNST\n\nPnr 113 48\n\nStockholm, Hagag 12. Tel\n08-34 93 50. Bankgiro 57-6137.\nPostgiro 52951\n\nVerkst dir: Olle Engberg\nEtableringsår: 1912.\n\nENGBERGS VERKSTADS AB,\nERNST\n\nPnr 16130\n\nBromma, Karlsbodav 10. Tel\n08-28 29 40. Bankgiro 23-8706.\nPostgiro 199582\n\nVerksamhet: Tillverkar o monterar\nalla slag av byggnadssmide\nAntal anställda: 50\nÅrsomsättning: 3 000 000\nAktiekapital: 150 000\nÄgare o chef: Dir Olle Engberg\nEtableringsår: 1944.\n\nENGBLAD &amp; CO\nTAPETFABRIKER AB\n\n(AB Tapetinvest)\n\nPnr 60102\n\nNorrköping 1, Box 26. Malmg. Tel\n011-106340. Tga Tapet\nVerksamhet: Tillverkar tapeter\nAntal anställda: 200\nAktiekapital: 1500 000\nVerkst dir: H H Rasmussen\nEtableringsår: 1966\nNamnändring 1969.\nAnslutna fabriker:\nEngblads Tapetfabrik K/B\nAB Göteborgs Tapetfabrik\nAB Kalmar Nya Tapetfabrik\nAB Ljungqvists Tapetfabrik\nAB Norrköping Tapetfabrik.\n\nENGBLADSTAPETFABRIK KB\n\nPnr 601 02\n\nNorrköping 1, Box 26. Malmg. Tel\n\n011-106340. Bankgiro 50-0051.\nPostgiro 4 0681. Tga Tapet\nVerksamhet: Tillverkar tapeter\nVarunamn: Lotura\nVerkst dir: H H Rasmussen\nEtableringsår: 1929\nTillhör Engblad &amp; Co\nTapet-fabriker AB, Norrköping.\n\nENGBLOM &amp; CO AB, ALEX\n\nPnr 50103\n\nBorås 1, Kellgrensg 22. Box 108.\nTel 033-12 24 32, 12 24 33. Bankgiro\n839-1708. Postgiro 116737-8. Tga\nDyeco\n\nVerksamhet: Import av kemikalier,\n\nanilinfärger samt skyttlar o\nspol-pipor\n\nAntal anställda: 4\n\nÅrsomsättning: 3 200 000\nAktiekapital: 60 000\nStyrelse: Distr-chef Rune\nBjörklund (ordf), dir H P Hässelby, fru\nMärtha Hässelby\nVerkst dir: Håkan Hässelby\nEtableringsår: 1949.\n\nEXPO TRÄFORÄDLING AB\n\nPnr 33010\n\nBredaryd. Lanna. Tel 0370-83032.\nBankgiro 54-2459. Postgiro 166867\nVerksamhet: Tillverkar smådetaljer\ni trä, speciellt detaljer för elektr\narmaturfabriker\nAntal anställda: 15\nÅrsomsättning: 480 000\nVerkst dir: Pabr Gösta Johansson\nEtableringsår: 1939.\n\nVÄSTERÅS HATTFABRIK AB\n\nPnr 720 12\n\nVästerås 12, Box 12050. Kaserng\n4-6. Tel 021-13 76 10. Bankgiro\n232-5462. Postgiro 22833-8. Tga\nHatt fabriken\n\nVerksamhet: Tillverkar\nhuvudbonader i tyg, strå. päls o övriga\naktuella material för damer o barn\nAntal anställda: 110\nÅrsomsättning: 6 300 000\n\nAktiekapital: 300 000\n\nVeikst dir: Gösta Kruhsberg\nDisp: Willy Liljegren\nInköpschef: Lars Kruhsberg\nFörsäljn-chef: Bengt Kruhsberg\nFabrikschef: Claes Sjöström\nEtableringsån 1920.\n\nVÄSTERÅS JURIDISKA BYRÅ,\nADVOKATFIRMAN\n\nPnr 72215\n\nVästerås, Köpmang 3. Tel\n021-18 03 55. Bankgiro 808-7314.\nPost-giro 329538-3\n\nVerksamhet: Affärsjuridisk\nverksamhet\n\nAntal anställda: 8\nChefer: Adv Sven Lagerholm.\nJan Elfström\nEtableringsår: 1924.\n\nBOMAN AB, EMIL R\n\nPnr 103 12\n\nStockholm 2, Box 2054. Skeppsbron\n44. Tel 08-24 95 00. Bankgiro\n721-7060. Postgiro 4883-5. Tga\nBomans, Bomanchart.\nTelex 19348 BOMANS S,\n10550 BOCHRT S\nVerksamhet: Auktoriserade\nskeppsklarerare, linje- o\nbefraktnings-agenter. Lloyd’s Agents\nGodsterminal: Stockholm SV.\nBoman-Distribunalen, Upplagsv 25.\nBox 43025, 10072 Sthlm 43. Tel\n08-18 75 00\nAntal anställda: 50\nVerkst dir: B Tägtmeijer\nEtableringsår: 1795.\n\nBOMANS\nKONSTRUKTIONSBYRÅ AB, GEORG\n\nPnr 552 55\n\nJönköping, Brunnsg 17. Tel\n036-1145 18, 12 29 87. Bankgiro\n140-2346\n\nVerksamhet: Värme-,\nventilations-o sanitetsteknik\nAktiekapital: 10 000\nVerkst dir: Ingemar Boman\nEtableringsår: 1959.\n\nBOMANS MOSSFABRIK AB,\nKNUT\n\nPnr 415 05\n\nGöteborg, Malmsjög 14. Tel\n031-25 0 0 75. Bankgiro 50-6506.\nPostgiro 40532. Tga Bomo\nVerksamhet: Tillverkar\nhuvudbonader speciellt för damer o barn\nAntal anställda: 50\nÅrsomsättning: 2 000 000\nAktiekapital: 60 000\nVerkst dir: Robert Stenquist\nEtableringsår 1906.\n\nPAPPERSINKOP, AB\n\nPnr 103 62\n\nStockholm 3, Kungsg 34. Box 3125.\nTel 08-110815, 1108 16. Bankgiro\n731-6342. Postgiro 151820-8. Tga\nPyrit\n\nVerksamhet: Export o import av\ncellulosamjöl, malmer o mineral\nAktiekapital: 10 000\nVerkst dir: Erik Sunesson.\n\nPAPPERSTJÄNST, AB\n\nPnr 41104\n\nGöteborg, Mårten Krakowg 7. Tel\n031-80 22 50, 80 22 51. Bankgiro\n50-6641. Postgiro 241078\nVerksamhet: Säljer papper, påsar\nmm\n\nAntal anställda: 8\nÅrsomsättning: 3 000 000\nAktiekapital: 10 000\nVerkst dir: Arne Agnäs\nEtableringsår: 1946.\n\nLZ-VERKEN I LAMMHULT AB\n\nPnr 360 30\n\nLammhult. Tel 0472-602 55, 606 55.\nBankgiro 275-5015. Postgiro\n322750\n\nVerksamhet: Tillverkar\nsågverksutrustningar, sorteringsverk,\nbot-tentömmande pallådor, containers\nsamt simbassänger i aluminium.\nSvetsade konstruktioner i aluminium\no stål\n\nAntal anställda: 8\nÅrsomsättning: 600 000\nAktiekapital: 100 000.\n\nLÅNG AB, CA\n\nPnr 214 34\n\nMalmö, Palmg 13. Tel 040-92 2130.\nBankgiro 26-0590. Postgiro\n148015-1. Tga Viltlång\nVerksamhet Importerar o\nexporterar vilt, tamfågel, delikatesser,\n\nskaldjur, lax, sjötunga m m samt\nfinare kött\n\nButik: Malmö, Adelg 2\nAntal anställda: 20\nÅrsomsättning: 5 000 000\nAktiekapital: 60000\nVerkst dir. C G Lång\nDisp: Ernst Blom\nFörsäljn-chef: Gunnar Säv eros\nEtableringsår: 1878\nOmbildat till aktiebolag 1966.\nGeneralagent för Limfjords Osters\nKompagniet, Danmark.\n\nLÅNGSHYTTE TRÄVARU AB\n\nPnr 770 70\n\nLångshyttan. Tel 0225-60163.\n606 63. Postgiro 97504\nVerksamhet: Sågverk, hyvleri o\nlimträtillverkning\nAntal anställda: 45\nÅrsomsättning: 7 000 000\nAktiekapital: 48 000\nVerkst dir: Rune Wåger\nEtableringsår: 1945.\n\nGRAHAM &amp; SON\n\nPnr 11220\n\nStockholm, Norr Mälarstrand 34.\nTel 08-50 8180. Bankgiro 166-0273.\nPostgiro 151809-1. Tga Gramson\nVerksamhet: Säljer stötdämpare\no transportlådor\nCJief: Civiling Edward Graham.\n\nGRAKO AB\n\nPnr 13101\n\nNacka 1, Ryssviksv 2. Fack. Tel\n08-716 29 70. Postgiro 41207-2. Tga\nGrakoswe\n\nVerksamhet: Konstförlag.\nSpecialitet: kort o presentpapper\nVerkst dir: Jonas Forssman\nDisp: Janis Muchks.\n\nGRAM, AB CARL\n\nPnr 271 00\n\nV stad, Hamng 16. Box 105. Tel\n0411-180 65. Bankgiro 670-1056.\nPostgiro 718211-6. Tga Gram.\nTelex 32396 GRAM S\nVerksamhet: Skeppsklarerare,\nspe-ditörer, haveri- o\nförsäkringsagenter. Färjetrafik Ystad-Rönne\nAntal anställda: 7\nAktiekapital: 19 000\nVerkst dir: Disp Enoch Andersson\nAvd-chef: Kapten Per Adner\nEtableringsår: 1827.\n\nRIXSKYLT\n\nPnr 330 30\n\nGnosjö. Tel 0370-91131\nVerksamhet: Tillverkar gjutna\nmaskinskyltar o provrörsställ\nÄgare o chef: Gunnar Salüén.\n\nRLSPRODUKTER AB\n\nPnr 112 23\n\nStockholm, Pilg 17. Tel 08-52 53 14,\n5253 15. Bankgiro 72-3793.\nPost-giro 255320\n\nVeiksamhet: Boktryck, offsettryck\no kartonnage\nAntal anställda: 6\nÅrsomsättning: 3 500 000\nAktiekapital: 15 000\nVeikst dir: Gunnar Rosén\nEtableringsår: 1952.\n\nSTEFA INDUSTRI AB\n\nPnr 261 20\n\nLandskrona 1, Kontor o lager\nKungsg 16. Pack. Inköp o verkstad\nStenorsv. Tel 0418-169 70.\nBankgiro 530-0496. Postgiro 31812-1.\nTga Stefa. Telex 72205 STEPA S\nVerksamhet: Tillverkar radial- o\naxialtätringar för roterande axlar.\nHP-tätringar, O-ringar, X-ringar,\nstyrelement o avstrykare för fram- o\nåtergående axlar inom\nhydraulik-o pneumatik. Glidringstätnlngar.\nOlika slags tillbehör såsom\nstatiska tätringar, box- o\nmaskinpackningar, spårringar, skyddshylsor av\nplast etc. Specialdetaljer i\nvulkol-lan, PTPE o PEP\nVarunamn: Stefa\nAntal anställda: 160\nÅrsomsättning: 23 000 000\nAktiekapital: 4 000 000\nVerkst dir: O Afzelius\nEtableringsår: 1890\nDotterbolag till Trelleborgs\nGummifabriks AB.\n\nSTEGFABRIKEN\nLUNDSTRUM&amp; OHLSSON\n\nPnr 104 32\n\nStockholm 19, Box 19062.\nSur-brunnsg 40. Tel 08-3188 59.\nBankgiro 295-8734. Postgiro 550637-3\nVerksamhet: Tillverkar \"T-stegen\"\nFirmatecknare: O T Ohlsson\nEtableringsår: 1919.",
    "structured": {
        "1": {
            "company_name": "WIHLBORG & SON, BYGGNADS AB O P",
            "pnr": "21225",
            "address": "Malmö, Stillmansg 10",
            "phone_number": "040-93 44 10",
            "bank_details": {
                "bankgiro": "87-019 2",
                "postgiro": "148008"
            },
            "activity": "Byggnadsfirma, betongelementfabrik, trähusfabriker",
            "employees": 350,
            "annual_turnover": 35000000,
            "capital": 300000,
            "key_personnel": [
                {
                    "name": "Willy Wihlborg",
                    "position": "Verkst dir"
                }
            ],
            "establishment_year": 1924
        },
        "2": {
            "company_name": "WILD HEERBRUGG SVENSKA AB",
            "pnr": "11143",
            "address": "Stockholm, Kungsg 7",
            "phone_number": "08-23 28 85",
            "bank_details": {
                "bankgiro": "152-3000",
                "postgiro": "502120-9"
            },
            "activity": "Försäljning o reparation av geodetiska, fotogrammet-riska o hydro-metriska instrument samt mikroskop",
            "employees": 20,
            "capital": 560000,
            "key_personnel": [
                {
                    "name": "Lennart Olsson",
                    "position": "Verkst dir"
                }
            ],
            "establishment_year": 1968
        },
        "3": {
            "company_name": "ENE",
            "employees": 75,
            "capital": 1200000,
            "key_personnel": [
                {
                    "name": "Törd Nilson",
                    "position": "Verkst dir"
                }
            ],
            "establishment_year": 1924
        },
        "4": {
            "company_name": "ENEQUIST KOLIMPORT, AB JOHN",
            "pnr": "100 53",
            "address": "Stockholm 37, Hamnpirsv 1. Pack",
            "phone_number": "08-63 52 20",
            "bank_details": {
                "bankgiro": "56-9307",
                "postgiro": "1498"
            },
            "activity": "Lager- o engroshan-del i eldningsoljor, koks, stenkol",
            "employees": 28,
            "annual_turnover": 10000000,
            "capital": 1000000,
            "key_personnel": [
                {
                    "name": "Friedrich Hermann",
                    "position": "Verkst dir"
                }
            ],
            "establishment_year": 1902
        },
        "5": {
            "company_name": "ENE RYD A TRÄFOR-ÄDLING AB",
            "pnr": "340 22",
            "address": "Eneryda",
            "phone_number": "0476-22138, 222 48",
            "bank_details": {
                "bankgiro": "276-1187",
                "postgiro": "398027-3"
            },
            "activity": "Tillverkar sågade o hyvlade trävaror",
            "employees": 35,
            "annual_turnover": 5000000,
            "capital": 150000,
            "key_personnel": [
                {
                    "name": "Riksdagsman Torsten Mattsson",
                    "position": "Verkst dir"
                }
            ],
            "establishment_year": 1940
        },
        "6": {
            "company_name": "ENGBERG PLÅTSLAGERIVERKSTÄDER, ERNST",
            "pnr": "113 48",
            "address": "Stockholm, Hagag 12",
            "phone_number": "08-34 93 50",
            "bank_details": {
                "bankgiro": "57-6137",
                "postgiro": "52951"
            },
            "key_personnel": [
                {
                    "name": "Olle Engberg",
                    "position": "Verkst dir"
                }
            ],
            "establishment_year": 1912
        },
        "7": {
            "company_name": "ENGBERGS VERKSTADS AB, ERNST",
            "pnr": "16130",
            "address": "Bromma, Karlsbodav 10",
            "phone_number": "08-28 29 40",
            "bank_details": {
                "bankgiro": "23-8706",
                "postgiro": "199582"
            },
            "activity": "Tillverkar o monterar alla slag av byggnadssmide",
            "employees": 50,
            "annual_turnover": 3000000,
            "capital": 150000,
            "key_personnel": [
                {
                    "name": "Dir Olle Engberg",
                    "position": "Ägare o chef"
                }
            ],
            "establishment_year": 1944
        },
        "8": {
            "company_name": "ENGBLAD & CO TAPETFABRIKER AB (AB Tapetinvest)",
            "pnr": "60102",
            "address": "Norrköping 1, Box 26. Malmg",
            "phone_number": "011-106340",
            "bank_details": {
                "bankgiro": "50-0051",
                "postgiro": "4 0681"
            },
            "activity": "Tillverkar tapeter",
            "employees": 200,
            "capital": 1500000,
            "key_personnel": [
                {
                    "name": "H H Rasmussen",
                    "position": "Verkst dir"
                }
            ],
            "establishment_year": 1966,
            "additional_info": "Namnändring 1969. Anslutna fabriker: Engblads Tapetfabrik K/B, AB Göteborgs Tapetfabrik, AB Kalmar Nya Tapetfabrik, AB Ljungqvists Tapetfabrik, AB Norrköping Tapetfabrik"
        },
        "9": {
            "company_name": "ENGBLADSTAPETFABRIK KB",
            "pnr": "601 02",
            "address": "Norrköping 1, Box 26. Malmg",
            "phone_number": "011-106340",
            "bank_details": {
                "bankgiro": "50-0051",
                "postgiro": "4 0681"
            },
            "activity": "Tillverkar tapeter",
            "varunamn": "Lotura",
            "key_personnel": [
                {
                    "name": "H H Rasmussen",
                    "position": "Verkst dir"
                }
            ],
            "establishment_year": 1929,
            "additional_info": "Tillhör Engblad & Co Tapet-fabriker AB, Norrköping"
        },
        "10": {
            "company_name": "ENGBLOM & CO AB, ALEX",
            "pnr": "50103",
            "address": "Borås 1, Kellgrensg 22. Box 108",
            "phone_number": "033-12 24 32, 12 24 33",
            "bank_details": {
                "bankgiro": "839-1708",
                "postgiro": "116737-8"
            },
            "activity": "Import av kemikalier, anilinfärger samt skyttlar o spol-pipor",
            "employees": 4,
            "annual_turnover": 3200000,
            "capital": 60000,
            "key_personnel": [
                {
                    "name": "Håkan Hässelby",
                    "position": "Verkst dir"
                }
            ],
            "establishment_year": 1949
        },
        "11": {
            "company_name": "EXPO TRÄFORÄDLING AB",
            "pnr": "33010",
            "address": "Bredaryd. Lanna",
            "phone_number": "0370-83032",
            "bank_details": {
                "bankgiro": "54-2459",
                "postgiro": "166867"
            },
            "activity": "Tillverkar smådetaljer i trä, speciellt detaljer för elektr armaturfabriker",
            "employees": 15,
            "annual_turnover": 480000,
            "key_personnel": [
                {
                    "name": "Pabr Gösta Johansson",
                    "position": "Verkst dir"
                }
            ],
            "establishment_year": 1939
        },
        "12": {
            "company_name": "VÄSTERÅS HATTFABRIK AB",
            "pnr": "720 12",
            "address": "Västerås 12, Box 12050. Kaserng 4-6",
            "phone_number": "021-13 76 10",
            "bank_details": {
                "bankgiro": "232-5462",
                "postgiro": "22833-8"
            },
            "activity": "Tillverkar huvudbonader i tyg, strå, päls o övriga aktuella material för damer o barn",
            "employees": 110,
            "annual_turnover": 6300000,
            "capital": 300000,
            "key_personnel": [
                {
                    "name": "Gösta Kruhsberg",
                    "position": "Veikst dir"
                },
                {
                    "name": "Willy Liljegren",
                    "position": "Disp"
                },
                {
                    "name": "Lars Kruhsberg",
                    "position": "Inköpschef"
                },
                {
                    "name": "Bengt Kruhsberg",
                    "position": "Försäljn-chef"
                },
                {
                    "name": "Claes Sjöström",
                    "position": "Fabrikschef"
                }
            ],
            "establishment_year": 1920
        },
        "13": {
            "company_name": "VÄSTERÅS JURIDISKA BYRÅ, ADVOKATFIRMAN",
            "pnr": "72215",
            "address": "Västerås, Köpmang 3",
            "phone_number": "021-18 03 55",
            "bank_details": {
                "bankgiro": "808-7314",
                "postgiro": "329538-3"
            },
            "activity": "Affärsjuridisk verksamhet",
            "employees": 8,
            "key_personnel": [
                {
                    "name": "Adv Sven Lagerholm",
                    "position": "Chefer"
                },
                {
                    "name": "Jan Elfström",
                    "position": "Chefer"
                }
            ],
            "establishment_year": 1924
        },
        "14": {
            "company_name": "BOMAN AB, EMIL R",
            "pnr": "103 12",
            "address": "Stockholm 2, Box 2054. Skeppsbron 44",
            "phone_number": "08-24 95 00",
            "bank_details": {
                "bankgiro": "721-7060",
                "postgiro": "4883-5"
            },
            "activity": "Auktoriserade skeppsklarerare, linje- o befraktnings-agenter. Lloyd’s Agents",
            "employees": 50,
            "key_personnel": [
                {
                    "name": "B Tägtmeijer",
                    "position": "Verkst dir"
                }
            ],
            "establishment_year": 1795
        },
        "15": {
            "company_name": "BOMANS KONSTRUKTIONSBYRÅ AB, GEORG",
            "pnr": "552 55",
            "address": "Jönköping, Brunnsg 17",
            "phone_number": "036-1145 18, 12 29 87",
            "bank_details": {
                "bankgiro": "140-2346"
            },
            "activity": "Värme-, ventilationso sanitetsteknik",
            "capital": 10000,
            "key_personnel": [
                {
                    "name": "Ingemar Boman",
                    "position": "Verkst dir"
                }
            ],
            "establishment_year": 1959
        },
        "16": {
            "company_name": "BOMANS MOSSFABRIK AB, KNUT",
            "pnr": "415 05",
            "address": "Göteborg, Malmsjög 14",
            "phone_number": "031-25 0 0 75",
            "bank_details": {
                "bankgiro": "50-6506",
                "postgiro": "40532"
            },
            "activity": "Tillverkar huvudbonader speciellt för damer o barn",
            "employees": 50,
            "annual_turnover": 2000000,
            "capital": 60000,
            "key_personnel": [
                {
                    "name": "Robert Stenquist",
                    "position": "Veikst dir"
                }
            ],
            "establishment_year": 1906
        },
        "17": {
            "company_name": "PAPPERSINKOP, AB",
            "pnr": "103 62",
            "address": "Stockholm 3, Kungsg 34. Box 3125",
            "phone_number": "08-110815, 1108 16",
            "bank_details": {
                "bankgiro": "731-6342",
                "postgiro": "151820-8"
            },
            "activity": "Export o import av cellulosamjöl, malmer o mineral",
            "capital": 10000,
            "key_personnel": [
                {
                    "name": "Erik Sunesson",
                    "position": "Veikst dir"
                }
            ]
        },
        "18": {
            "company_name": "PAPPERSTJÄNST, AB",
            "pnr": "41104",
            "address": "Göteborg, Mårten Krakowg 7",
            "phone_number": "031-80 22 50, 80 22 51",
            "bank_details": {
                "bankgiro": "50-6641",
                "postgiro": "241078"
            },
            "activity": "Säljer papper, påsar mm",
            "employees": 8,
            "annual_turnover": 3000000,
            "capital": 10000,
            "key_personnel": [
                {
                    "name": "Arne Agnäs",
                    "position": "Veikst dir"
                }
            ],
            "establishment_year": 1946
        },
        "19": {
            "company_name": "LZ-VERKEN I LAMMHULT AB",
            "pnr": "360 30",
            "address": "Lammhult",
            "phone_number": "0472-602 55, 606 55",
            "bank_details": {
                "bankgiro": "275-5015",
                "postgiro": "322750"
            },
            "activity": "Tillverkar sågverksutrustningar, sorteringsverk, bottentömmande pallådor, containers samt simbassänger i aluminium. Svetsade konstruktioner i aluminium o stål",
            "employees": 8,
            "annual_turnover": 600000,
            "capital": 100000
        },
        "20": {
            "company_name": "LÅNG AB, CA",
            "pnr": "214 34",
            "address": "Malmö, Palmg 13",
            "phone_number": "040-92 2130",
            "bank_details": {
                "bankgiro": "26-0590",
                "postgiro": "148015-1"
            },
            "activity": "Importerar o exporterar vilt, tamfågel, delikatesser, skaldjur, lax, sjötunga m m samt finare kött. Butik: Malmö, Adelg 2",
            "employees": 20,
            "annual_turnover": 5000000,
            "capital": 60000,
            "key_personnel": [
                {
                    "name": "C G Lång",
                    "position": "Verkst dir"
                },
                {
                    "name": "Ernst Blom",
                    "position": "Disp"
                },
                {
                    "name": "Gunnar Säv eros",
                    "position": "Försäljn-chef"
                }
            ],
            "establishment_year": 1878
        }
    }
}