{
    "original": "ACME, FÄRG AB\n\nPnr 17141\n\nSolna, Englundav 3-5. Tel\n08-28 60 90. Postgiro 156450-9.\nTga Proflex\n\nVerksamhet: Säljer färger o läcker.\nGeneralrepresentant för Acme\nQuali-ty Paints Inc., Newark, N J\nVarunamn: Fleet-X, Proxlin\nAktiekapital: 60 000\nVerkst dir: Folke Stigen\nEtableringsår: 1939.\n\nPORLA BRUNNS AB\n\nPnr 695 00\n\nLaxå. Tel 0584-300 10, 300 11.\nBankgiro 46-1628. Postgiro 36220\nVerksamhet: Mineralvattenfabrik.\nTillverkar o säljer Porla\nbordsvatten\n\nVarunamn: Porla\nAntal anställda: 15\nAktiekapital: 400 000\nVerkst dir: Gunnar Gahn\nEtableringsår 1874\nOmbildat 1943.\n\nPORONYL\n\nPnr 782 00\n\nMalung. Tel 0280-40208.Bankgiro\n79-7021. Postgiro 206673\nVerksamhet: Tillverkar cellplasts\nmaterial för isoleringsändamål\nVarunamn: Poronyl\nAntal anställda: 10\nÅrsomsättning: 600 000\nProduktionschef: Henry J Jansson\nEtableringsår: 1958\nÄgare: AB S P Persson m fi.\n\nPOR-PAC PLAST AB\n\nPnr 71100\n\nLindesberg, Stadsskogsv 1-5. Tel\n0581-125 90. Bankgiro 821-3878.\nPostgiro 396367-5. Telex 73408\nVerksamhet: Tillverkar\ncellplastemballage o plasthandskar\nVarunamn: Kid, Por-Pac\nÅrsomsättning: 12 000 000\nAktiekapital: 435 000\nVerkst dir: K I Davidson\nFörsäljn-dir: Thor Hammarbäck\nEtableringsår: 1950.\n\nPORSANDER REKLAMBYRÅ\nAB, HANS\n\nPnr 703 61\n\nÖrebro, Olaig 9. Tel 019-1400 50.\nBankgiro 46-3474. Postgiro 678742\nVerksamhet: Auktoriserad\nreklamkonsult. Nominerad av Svenska\nTidningsutgivareföreningen\nAntal anställda: 11\nÅrsomsättning: 2 300 000\nAktiekapital: 50 000\nVerkst dir: Hans Porsander\nEtableringsår: 1966.\n\nPERFEKTA.TRYCK, AB\n\nPnr 232 00\n\nArlöv, Hantverkareg 4. Tel\n040-43 05 00. Bankgiro 65-0313.\nPostgiro 537265\n\nVerksamhet: Affärs- o\nreklamtryck, kataloger o tidskrifter\nAntal anställda: 80\nÅrsomsättning: 6000 000\nAktiekapital: 110 000\nVerkst dir: Frans Nilsson\nEtableringsår: 1931.\n\nKÄCK &amp; HEDBYS SMIDES AB\n\nPnr 793 00\n\nLeksand, Åkerö. Box 5385. Tel\n0247-100 83. Bankgiro 79-6319.\nPostgiro 72132\n\nVerksamhet: Tillverkar\nbyggnads-o konstsmide\nAktiekapital: 25 000\nVerkst dir: Valter Källgård\nEtableringsår: 1922.\n\nKÄLARNE ELEKTRISKA SÄG\n&amp; KVARN AB\n\nPnr 840 64\n\nKälarne, Box 45. Tel 0696-404 00.\nBankgiro 25-1209. Postgiro 138944.\nTga Kälarnesågen\nVerksamhet: Tillverkar sågade o\nhyvlade trävaror\n\nAntal anställda: 40\nÅrsomsättning: 6 000 000\nAktiekapital: 32 800\nVerkst dir: Hadar Nygren\nEtableringsår: 1912.\n\nLINDH, BRÖDERNA\n\nPnr 56012\n\nVaggeryd. Tel 0393-107 50\nVerksamhet: Tillverkar klänningar\no damskyddsrockar\nÄgare o chefer: Fabr Artur Lindh,\nfabr Bengt Lindh\nEtableringsår: 1932.\n\nOHLSSON &amp; LIND, AB\n\nPnr 63002\n\nEskilstuna 2, Asg 14. Box 2025.\nTel 016-13 05 51, 13 32 51. Bankgiro\n369-3660. Postgiro 10794-6\nVerksamhet: Tillverkar\nsamlingspärmar\n\nAntal anställda: 20\nÅrsomsättning: 1 000 000\nAktiekapital: 50 000\nVerkst dir: Disp Eugén Palmgren\nEtableringsår: 1919.\n\nESKILSTUNA\nCEMENTVARU-F AB RIK, AB\n\nPnr 63104\n\nEskilstuna 1, Gärdesv 4. Box 290.\nTel 016-91340, 200 89. Bankgiro\n369-3843. Postgiro 140764-2\nVerksamhet: Tillverkar betongrör,\nkantsten, gångbaneplattor, balkar,\npelare, väggelement, bjälklag o\ntakelement\nAntal anstäUda: 45\nÅrsomsättning: 4 000 000\nAktiekapital: 100 000\nVeikst dir: Gustaf Johansson\nEtableringsår: 1939.\n\nPLM\n\nPnr 201 10\n\nMalmö 1, Djäkneg 16. Fack. Tel\n040-759 00. Bankgiro 870-2375.\nPostgiro 1601-4. Tga PLM.\nTelex 32456 PLMHK S\nVerksamhet: Tillverkar plåt-,\nglas-o plastförpackningar\n\nHuvudkontor: Malmö\nTiUverkningsstäUen: Malmö,\nLysekil, Nybro, Surte, Hammar,\nLimmared, Lidköping\n\nDanmark: Odense, Langeskov\nHolland: Dongen\n\nDistriktkontor: 40123 Göteborg 1,\nFredsg 6. Box 211. Tel 031-17 5240\n102 31 Stockholm 6, Dalag 34. Box\n6006. Tel 08-23 53 60\nAntal anstäUda: 5 700\nÅrsomsättning: 590 000 000\nAktiekapital: 97 300 000\nStyrelseordf: Adv Sten Lindskog\nVerkst dir: Ulf Laurin\nEtableringsår: 1919.\n\nPET\n\nPETIT, AB KLICHÉ.\nANSTALTEN\n\nPnr 40126\n\nGöteborg 1, Odinsg 2. Box 439.\nTel 031-15 22 63, 19 09 09.\nBankgiro 107-6787. Postgiro 40475-6\nVerksamhet: Tillverkar klichéer.\nUtför teckningar o retuscher\nAntal anställda: 30\nÅrsomsättning: 1300 000\nAktiekapital: 25 000\nVerkst dir C B Schönander\nEtableringsår: 1920.\n\nKOL &amp; TRÄ I SUNDSVALL AB\n\nPnr 85105\n\nSundsvall 1, N Kajen 1. Box 360.\nTel 060-15 55 60. Postgiro\n327830-6. Tga Kolträ\nVerksamhet: Driver handel med\nfasta bränslen\nÅrsomsättning: 500 000\nAktiekapital: 100 000\nVerkst dir: Erik Björnback\nEtableringsår: 1947.\n\nKOLBÄCKS CEMENT.\nGJUTERI, AB\n\nPnr 730 40\n\nKolbäck, Box 85. Tel 0220-40470.\nBankgiro 810-9118. Postgiro\n81751-0\n\nVerksamhet: Tillverkar o säljer\nbe-tongrör, betongkantstöd mm\nAntal anställda: 45\nÅrsomsättning: 5 000 000\nAktiekapital: 75 000\nVerkst dir: Nils Ryberg\nEtableringsår: 1923.",
    "structured": {
        "1": {
            "company_name": "ACME, FÄRG AB",
            "address": "Solna, Englundav 3-5",
            "phone_number": "08-28 60 90",
            "bank_details": {
                "postgiro": "156450-9"
            },
            "activity": "Säljer färger o läcker",
            "capital": 60000,
            "key_personnel": [
                {
                    "name": "Folke Stigen",
                    "position": "Verkst dir"
                }
            ],
            "establishment_year": 1939
        },
        "2": {
            "company_name": "PORLA BRUNNS AB",
            "address": "Laxå",
            "phone_number": "0584-300 10, 300 11",
            "bank_details": {
                "bankgiro": "46-1628",
                "postgiro": "36220"
            },
            "activity": "Mineralvattenfabrik",
            "annual_production_value": "Porla bordsvatten",
            "employees": 15,
            "capital": 400000,
            "key_personnel": [
                {
                    "name": "Gunnar Gahn",
                    "position": "Verkst dir"
                }
            ],
            "establishment_year": 1874
        },
        "3": {
            "company_name": "PORONYL",
            "address": "Malung",
            "phone_number": "0280-40208",
            "bank_details": {
                "bankgiro": "79-7021",
                "postgiro": "206673"
            },
            "activity": "Tillverkar cellplasts material för isoleringsändamål",
            "annual_production_value": "Poronyl",
            "employees": 10,
            "annual_turnover": 600000,
            "key_personnel": [
                {
                    "name": "Henry J Jansson",
                    "position": "Produktionschef"
                }
            ],
            "establishment_year": 1958
        },
        "4": {
            "company_name": "POR-PAC PLAST AB",
            "address": "Lindesberg, Stadsskogsv 1-5",
            "phone_number": "0581-125 90",
            "bank_details": {
                "bankgiro": "821-3878",
                "postgiro": "396367-5"
            },
            "activity": "Tillverkar cellplastemballage o plasthandskar",
            "annual_turnover": 12000000,
            "capital": 435000,
            "key_personnel": [
                {
                    "name": "K I Davidson",
                    "position": "Verkst dir"
                },
                {
                    "name": "Thor Hammarbäck",
                    "position": "Försäljn-dir"
                }
            ],
            "establishment_year": 1950
        },
        "5": {
            "company_name": "PORSANDER REKLAMBYRÅ AB, HANS",
            "address": "Örebro, Olaig 9",
            "phone_number": "019-1400 50",
            "bank_details": {
                "bankgiro": "46-3474",
                "postgiro": "678742"
            },
            "activity": "Auktoriserad reklamkonsult",
            "employees": 11,
            "annual_turnover": 2300000,
            "capital": 50000,
            "key_personnel": [
                {
                    "name": "Hans Porsander",
                    "position": "Verkst dir"
                }
            ],
            "establishment_year": 1966
        },
        "6": {
            "company_name": "PERFEKTA.TRYCK, AB",
            "address": "Arlöv, Hantverkareg 4",
            "phone_number": "040-43 05 00",
            "bank_details": {
                "bankgiro": "65-0313",
                "postgiro": "537265"
            },
            "activity": "Affärs- o reklamtryck, kataloger o tidskrifter",
            "employees": 80,
            "annual_turnover": 6000000,
            "capital": 110000,
            "key_personnel": [
                {
                    "name": "Frans Nilsson",
                    "position": "Verkst dir"
                }
            ],
            "establishment_year": 1931
        }
    }
}