{
    "original": "FAMORIT AB\n\nPnr 113 51\n\nStockholm, Odeng 25. Tel\n08-10 03 30\n\nVerksamhet: Utför\ngolvbeläggningar i massa, mosaik, betong,\nplastbetong o heltäckande mattor\nAntal anställda: 13\nAktiekapital: 10 000\nVeikst dir: Carl Sixten Ehrenpohl\nEtableringsår: 1962.\n\nHAFO MASKIN AB\n\nPnr 417 07\n\nGöteborg H. Bessemerg 3. Tel\n031-225203. Bankgiro 44-1314.\nPostgiro 48659\n\nVerksamhet: Tillverkar\ntransportvagnar m m\nAntal anställda: 20\nAktiekapital: 150 000\nVerkst dir: Walter Jansson\nEtableringsår: 1945.\n\nC0NT1TRADE AB\n\nPnr 400 42\n\nGöteborg 26, Pack. Stenklevsg 5.\nTel 031-12 45 00. Bankgiro\n442-3190. Postgiro 420475-6.\nTelex 20675 CONTAB S\nVerksamhet: Säljer\nvulkaniserings-o reparationsmaterial,\nregumme-ringsmaskiner, balanseringsutrust-ning, hissar, domkrafter,\nbatteriladdare, biltillbehör o\nbilvårdsutrustning såsom tändstift,\nstrålkastare, glödlampor, vax o polish\nFilial: 12156 Johanneshov,\nVik-stensv 61. Tel 08-48 83 85\nFörsäljningskontor: 12142\nJohanneshov, Skagersv 17. Tel\n08-48 93 85\n\nAntal anställda: 44\nÅrsomsättning: 11000 000\nAktiekapital: 150 000\nVerkst dir: Alexis Westberg\nEtableringsår: 1949.\n\nSVENSKA AB TROLL-ULL\n\nPnr 452 00\n\nStrömstad, Svinesund. Tel\n0526-40148. Bankgiro 55-1418. Postgiro\n660733\n\nVerksamhet: Säljer Troll-Ull\nstålull o verktyg till järnvarubranschen\nVarunamn: Troll-Ull, Oyo\nAntal anställda: 4\nVerkst dir: Arthur Beyer-Olsen\nDisp: Henrik Beyer-Olsen\n\nFörsäljn-chef: Reidar Nielsen\nEtableringsår: 1961\nDotterbolag till Trollullfabrikken\nA/S, Mysen, Oslo.\n\nSVENSKA\nTRYCK-CENTRALEN AB\n\nPnr 101 27\n\nStockholm 1, Torsg 2. Box 576.\nTel 08-22 21 80. Bankgiro 566-0360.\nPostgiro 250804-2\n\nVerksamhet: Rotationstryckerier för\ntidningar o tidskrifter i boktryck o\noffset\n\nAntal anställda: 100\n\nÅrsomsättning: 14 000 000\nAktiekapital: 2400 000\nVerkst dir: Ingvar Guldstrand\nEtableringsår 1960.\n\nSVENSKA TRÄIMPREGNE.\nRINGS AB STAB\n\nPnr 77101\n\nLudvika 1, Box 76. Tel 0240-136 20.\nPostgiro 7879. Tga Stab\nVerksamhet: Impregnerade\nkraftledningsstolpar, sliprar o virke,\nkreosotolja mm\n\nFilial: Stugsund, Strandg 8 C. Tel\n0270-54118\nAntal anställda: 70\nÅrsomsättning: 8 800 000\nAktiekapital: 1 200 000\nStyrelse: Adv Hugo Stenbeck (ordf),\ndisp Lars Hedenlund, ing Måns\nHedenlund, herr Magnus Lundström,\ndisp Ulf Lönn\n\nVerkst dir: Disp Lars Hedenlund\nEtableringsår: 1924.\n\nSVENSKA TRÄMJOLS.\nFABRIKERNA AB\n\nPnr 422 46\n\nHisings Backa. Tel 031-52 20 70.\nBankgiro 33-2177. Postgiro 4715.\nTga Rerfass.\nTelex 20870 RERFASS S\nVerksamhet: Tillverkar\ncellulosamjöl o trämjöl\nVarunamn: Cepo\nAntal anställda: 35\nÅrsomsättning: 4 000 000\nVerkst dir Claes Lindbom\nEtableringsår: 1923.\n\nEWOS, AB\n\nPnr 15120\n\nSödertälje 1, Pack. Svalängsv 1.\nTel 0755-340 80. Bankgiro\n170-6183. Postgiro 4773-8. Tga Evos.\nTelex 10222 EWEX S\nVerksamhet: Tillverkning o\nmarknadsföring av fodersupplement o\nspecialfoder\n\nLokalkontor o lager Malmö. Tel\n040-9355 60\nVerkst dir: Sven Strand\nSe vidare Astra-Ewos AB.\n\nEXAKTAFJÄDRAR, AB\n\nPnr 14124\n\nHuddinge 1, Dalhemsv 30. Box\n1162. Tel 08-71177 9 5 , 71177 9 6.\nBankgiro 748-2086. Postgiro\n443290-2\n\nVerksamhet: Tillverkar fjädrar för\nindustriändamål\nAntal anställda: 30\nÅrsomsättning: 1700 000\nAktiekapital: 30 000\nVeikst dir: Bo Almén\nEtableringsår: 1953.\n\nGISEBO VAGNINDUSTRI AB\n\nPnr 561 00\n\nHuskvarna. Tel 036-501 75.\nBankgiro 083-0238. Postgiro 699730\nVerksamhet: Tillverkar o säljer\ntransportvagnar\nAntal anställda: 28\nÅrsomsättning: 4 000 000\nAktiekapital: 45 000\nVerkst dir: Gunnar Nilsson\nEtableringsår: 1967.\n\nHYKON-PATENT AB\n\nPnr 223 68\n\nLund, Byggmästaregården, O Torn.\nTel 046-14 69 75. Bankgiro\n570-6957. Tga Hykon\nVerksamhet: Patent o licenser\ninom VVS, uppfinningar. Bokförlag.\nSäljer industriartiklar för\nbyggnadsbranschen\n\nVarunamn: Purus, Prewa\nAntal anställda: 4\nÅrsomsättning: 2 000 000\nAktiekapital: 150000\nVerkst dir. Byggmäst Harry\nKarlsson\n\nEtableringsår: 1967.\n\nHULLERT BIL. &amp; MASKIN.\nFIRMA, AB\n\nPnr 534 00\n\nVara. Tel 0512-115 00. Postgiro\n287773. TgaHyno. Telex 42100\n\nVerksamhet: Tillverkar WARRAS\nhelhydrauliska grävmaskiner.\nRepresentant för Fuchs\nhydraul-grävmaskiner, John Deere\nhjullastare, hjultraktorer samt Saab,\nChrysler o Dodge personbilar\nVarunamn: Deutz, Fuchs, Warras\nFilial: Lane-Herrestad. Tel\n0522-664 44\n\n.Antal anställda: 45\nÅrsomsättning: 9 500 000\nAktiekapital: 100 000\nVerkst dir: L Hüllert\n\nFörsäljn-chef: Sune Eriksson\nKamrer: Arvid Olsson\nEtableringsår: 1945.\n\nENGSTRÖMS FORLAG, AB\n\nPnr 111 36\n\nStockholm, Drottningg 67. Tel\n08-1135 98. Postgiro 3295-3\nVerksamhet: Samlingspärmar,\nlös-bladsböcker\nAktiekapital: 10000\nVerkst dir: Knut G Lundell\nEtableringsår: 1943.\n\nENGSTRÖMS MEKANISKA\nVERKSTAD AB\n\nPnr 711 00\n\nLindesberg. Tel 0581-125 55.\nBankgiro 82-1453. Postgiro 142614\nVerksamhet: Tillverkar\ntvättcentri-fuger, televisionsantenner samt\nelektriska kallvalsmanglar o\npo-tatisskalare för hushållsbruk\nAntal anställda: 60\nÅrsomsättning: 5 000000\nAktiekapital: 25 000\nVerkst dir: S-O Landström\nEtableringsår 1938.\n\nENGSTRÖMS\nSKINNVARUFABRIK AB\n\nPnr 782 00\n\nMalung. Tel 0280-108 34. 120 50.\nBankgiro 468-5137. Postgiro\n268658-2\n\nVerksamhet: Tillverkar kappor,\ndräkter o sportplagg för dam o herr\nAntal anställda: 35\nÅrsomsättning: 2000 000\nAktiekapital: 100000\nVerkst dir: Jonas Engström\nEtableringsår. 1939.\n\nödman ab, karl\n\nPnr 502 32\n\nBorås. Allég 62. Tel 033-10 2185.\nBankgiro 53-1288. Postgiro 91720\nVerksamhet: Glasmästeri, bilrutor,\nblyinfattningar, inramningar\nAktiekapital: 30000\nVerkst din Olof Axelson\nEtableringsån 1928.\n\nOMNI - PAC AB\n\nPnr 113 31\n\nStockholm, Hälsingehöjden 1. Tel\n08-34 9750. Bankgiro 721-8134.\nPostgiro 1943 80-2. Tga Omnipacab\nVerksamhet: Säljer emballage för\nförpackning av färskt kött, frukt,\ngrönsaker o ägg samt\nförpackningsmaskiner o engångsförkläden\nVarunamn: Foodtainer\nAntal anställda: 5\nÅrsomsättning: 4 000 000\nAktiekapital: 50 000\nStyrelseordf: Adv Rolf Magre 11\nVerkst dir: H B Edwards\nEtableringsår: 1964\nNamnändring 1964 från AB\nPenn-Cross till Omni-Pac AB.\n\nOPE-PRODUKTER AB\n\nPnr 644 00\n\nTorshälla, Sågg 9. Tel 016-558 66.\nBankgiro 62-3604. Postgiro\n545226-3\n\nVerksamhet: Hyvelbänkbeslag,\nemballage o byggnadsbeslag\nAntal anställda: 5\nÄgare o chef: Ing Sven Olov\nPersson\n\nEtableringsår: 1964.",
    "structured": {
        "1": {
            "company_name": "FAMORIT AB",
            "pnr": "113 51",
            "address": "Stockholm, Odeng 25",
            "phone_number": "08-10 03 30",
            "activity": "Utför golvbeläggningar i massa, mosaik, betong, plastbetong o heltäckande mattor",
            "employees": 13,
            "capital": 10000,
            "key_personnel": [
                {
                    "name": "Carl Sixten Ehrenpohl",
                    "position": "Veikst dir"
                }
            ],
            "establishment_year": 1962
        },
        "2": {
            "company_name": "HAFO MASKIN AB",
            "pnr": "417 07",
            "address": "Göteborg H. Bessemerg 3",
            "phone_number": "031-225203",
            "bank_details": {
                "bankgiro": "44-1314",
                "postgiro": "48659"
            },
            "activity": "Tillverkar transportvagnar m m",
            "employees": 20,
            "capital": 150000,
            "key_personnel": [
                {
                    "name": "Walter Jansson",
                    "position": "Verkst dir"
                }
            ],
            "establishment_year": 1945
        },
        "3": {
            "company_name": "C0NT1TRADE AB",
            "pnr": "400 42",
            "address": "Göteborg 26, Pack. Stenklevsg 5",
            "phone_number": "031-12 45 00",
            "bank_details": {
                "bankgiro": "442-3190",
                "postgiro": "420475-6"
            },
            "activity": "Säljer vulkaniserings-o reparationsmaterial, regumme-ringsmaskiner, balanseringsutrust-ning, hissar, domkrafter, batteriladdare, biltillbehör o bilvårdsutrustning såsom tändstift, strålkastare, glödlampor, vax o polish",
            "employees": 44,
            "annual_turnover": 11000000,
            "capital": 150000,
            "key_personnel": [
                {
                    "name": "Alexis Westberg",
                    "position": "Verkst dir"
                }
            ],
            "establishment_year": 1949
        },
        "4": {
            "company_name": "SVENSKA AB TROLL-ULL",
            "pnr": "452 00",
            "address": "Strömstad, Svinesund",
            "phone_number": "0526-40148",
            "bank_details": {
                "bankgiro": "55-1418",
                "postgiro": "660733"
            },
            "activity": "Säljer Troll-Ull stålull o verktyg till järnvarubranschen",
            "employees": 4,
            "key_personnel": [
                {
                    "name": "Arthur Beyer-Olsen",
                    "position": "Verkst dir"
                },
                {
                    "name": "Henrik Beyer-Olsen",
                    "position": "Disp"
                },
                {
                    "name": "Reidar Nielsen",
                    "position": "Försäljn-chef"
                }
            ],
            "establishment_year": 1961
        },
        "5": {
            "company_name": "SVENSKA TRYCK-CENTRALEN AB",
            "pnr": "101 27",
            "address": "Stockholm 1, Torsg 2",
            "phone_number": "08-22 21 80",
            "bank_details": {
                "bankgiro": "566-0360",
                "postgiro": "250804-2"
            },
            "activity": "Rotationstryckerier för tidningar o tidskrifter i boktryck o offset",
            "employees": 100,
            "annual_turnover": 14000000,
            "capital": 2400000,
            "key_personnel": [
                {
                    "name": "Ingvar Guldstrand",
                    "position": "Verkst dir"
                }
            ],
            "establishment_year": 1960
        },
        "6": {
            "company_name": "SVENSKA TRÄIMPRÄGNERINGS AB STAB",
            "pnr": "77101",
            "address": "Ludvika 1, Box 76",
            "phone_number": "0240-136 20",
            "bank_details": {
                "postgiro": "7879",
                "tga": "Stab"
            },
            "activity": "Impregnerade kraftledningsstolpar, sliprar o virke, kreosotolja mm",
            "employees": 70,
            "annual_turnover": 8800000,
            "capital": 1200000,
            "key_personnel": [
                {
                    "name": "Adv Hugo Stenbeck",
                    "position": "ordf"
                },
                {
                    "name": "Lars Hedenlund",
                    "position": "disp"
                },
                {
                    "name": "Måns Hedenlund",
                    "position": "ing"
                },
                {
                    "name": "Magnus Lundström",
                    "position": "herr"
                },
                {
                    "name": "Ulf Lönn",
                    "position": "disp"
                }
            ],
            "establishment_year": 1924
        },
        "7": {
            "company_name": "SVENSKA TRÄIMJOLSFABRIKERNA AB",
            "pnr": "422 46",
            "address": "Hisings Backa",
            "phone_number": "031-52 20 70",
            "bank_details": {
                "bankgiro": "33-2177",
                "postgiro": "4715",
                "tga": "Rerfass"
            },
            "activity": "Tillverkar cellulosamjöl o trämjöl",
            "employees": 35,
            "annual_turnover": 4000000,
            "key_personnel": [
                {
                    "name": "Claes Lindbom",
                    "position": "Verkst dir"
                }
            ],
            "establishment_year": 1923
        },
        "8": {
            "company_name": "EWOS, AB",
            "pnr": "15120",
            "address": "Södertälje 1, Pack. Svalängsv 1",
            "phone_number": "0755-340 80",
            "bank_details": {
                "bankgiro": "170-6183",
                "postgiro": "4773-8",
                "tga": "Evos"
            },
            "activity": "Tillverkning o marknadsföring av fodersupplement o specialfoder",
            "local_office_lager": "Malmö",
            "local_office_lager_phone": "040-9355 60",
            "key_personnel": [
                {
                    "name": "Sven Strand",
                    "position": "Verkst dir"
                }
            ]
        },
        "9": {
            "company_name": "EXAKTAFJÄDRAR, AB",
            "pnr": "14124",
            "address": "Huddinge 1, Dalhemsv 30, Box 1162",
            "phone_number": "08-71177 9 5 , 71177 9 6",
            "bank_details": {
                "bankgiro": "748-2086",
                "postgiro": "443290-2"
            },
            "activity": "Tillverkar fjädrar för industriändamål",
            "employees": 30,
            "annual_turnover": 1700000,
            "capital": 30000,
            "key_personnel": [
                {
                    "name": "Bo Almén",
                    "position": "Veikst dir"
                }
            ],
            "establishment_year": 1953
        },
        "10": {
            "company_name": "GISEBO VAGNINDUSTRI AB",
            "pnr": "561 00",
            "address": "Huskvarna",
            "phone_number": "036-501 75",
            "bank_details": {
                "bankgiro": "083-0238",
                "postgiro": "699730"
            },
            "activity": "Tillverkar o säljer transportvagnar",
            "employees": 28,
            "annual_turnover": 4000000,
            "capital": 45000,
            "key_personnel": [
                {
                    "name": "Gunnar Nilsson",
                    "position": "Verkst dir"
                }
            ],
            "establishment_year": 1967
        },
        "11": {
            "company_name": "HYKON-PATENT AB",
            "pnr": "223 68",
            "address": "Lund, Byggmästaregården, O Torn",
            "phone_number": "046-14 69 75",
            "bank_details": {
                "bankgiro": "570-6957"
            },
            "activity": "Patent o licenser inom VVS, uppfinningar. Bokförlag. Säljer industriartiklar för byggnadsbranschen",
            "varunamn": "Purus, Prewa",
            "employees": 4,
            "annual_turnover": 2000000,
            "capital": 150000,
            "key_personnel": [
                {
                    "name": "Byggmäst Harry Karlsson",
                    "position": "Verkst dir"
                }
            ],
            "establishment_year": 1967
        },
        "12": {
            "company_name": "HULLERT BIL. & MASKIN. FIRMA, AB",
            "pnr": "534 00",
            "address": "Vara",
            "phone_number": "0512-115 00",
            "bank_details": {
                "postgiro": "287773",
                "tga": "Hyno"
            },
            "activity": "Tillverkar WARRAS helhydrauliska grävmaskiner. Representant för Fuchs hydraul-grävmaskiner, John Deere hjullastare, hjultraktorer samt Saab, Chrysler o Dodge personbilar",
            "varunamn": "Deutz, Fuchs, Warras",
            "filial": "Lane-Herrestad",
            "filial_phone": "0522-664 44",
            "employees": 45,
            "annual_turnover": 9500000,
            "capital": 100000,
            "key_personnel": [
                {
                    "name": "L Hüllert",
                    "position": "Verkst dir"
                },
                {
                    "name": "Sune Eriksson",
                    "position": "Försäljn-chef"
                },
                {
                    "name": "Arvid Olsson",
                    "position": "Kamrer"
                }
            ],
            "establishment_year": 1945
        },
        "13": {
            "company_name": "ENGSTRÖMS FORLAG, AB",
            "pnr": "111 36",
            "address": "Stockholm, Drottningg 67",
            "phone_number": "08-1135 98",
            "bank_details": {
                "postgiro": "3295-3"
            },
            "activity": "Samlingspärmar, lös-bladsböcker",
            "capital": 10000,
            "key_personnel": [
                {
                    "name": "Knut G Lundell",
                    "position": "Verkst dir"
                }
            ],
            "establishment_year": 1943
        },
        "14": {
            "company_name": "ENGSTRÖMS MEKANISKA VERKSTAD AB",
            "pnr": "711 00",
            "address": "Lindesberg",
            "phone_number": "0581-125 55",
            "bank_details": {
                "bankgiro": "82-1453",
                "postgiro": "142614"
            },
            "activity": "Tillverkar tvättcentri-fuger, televisionsantenner samt elektriska kallvalsmanglar o po-tatisskalare för hushållsbruk",
            "employees": 60,
            "annual_turnover": 5000000,
            "capital": 25000,
            "key_personnel": [
                {
                    "name": "S-O Landström",
                    "position": "Verkst dir"
                }
            ],
            "establishment_year": 1938
        },
        "15": {
            "company_name": "ENGSTRÖMS SKINNVARUFABRIK AB",
            "pnr": "782 00",
            "address": "Malung",
            "phone_number": "0280-108 34, 120 50",
            "bank_details": {
                "bankgiro": "468-5137",
                "postgiro": "268658-2"
            },
            "activity": "Tillverkar kappor, dräkter o sportplagg för dam o herr",
            "employees": 35,
            "annual_turnover": 2000000,
            "capital": 100000,
            "key_personnel": [
                {
                    "name": "Jonas Engström",
                    "position": "Verkst dir"
                }
            ],
            "establishment_year": 1939
        },
        "16": {
            "company_name": "ÖDMAN AB, KARL",
            "pnr": "502 32",
            "address": "Borås, Allég 62",
            "phone_number": "033-10 2185",
            "bank_details": {
                "bankgiro": "53-1288",
                "postgiro": "91720"
            },
            "activity": "Glasmästeri, bilrutor, blyinfattningar, inramningar",
            "capital": 30000,
            "key_personnel": [
                {
                    "name": "Olof Axelson",
                    "position": "Verkst din"
                }
            ],
            "establishment_year": 1928
        },
        "17": {
            "company_name": "OMNI - PAC AB",
            "pnr": "113 31",
            "address": "Stockholm, Hälsingehöjden 1",
            "phone_number": "08-34 9750",
            "bank_details": {
                "bankgiro": "721-8134",
                "postgiro": "1943 80-2",
                "tga": "Omnipacab"
            },
            "activity": "Säljer emballage för förpackning av färskt kött, frukt, grönsaker o ägg samt förpackningsmaskiner o engångsförkläden",
            "varunamn": "Foodtainer",
            "employees": 5,
            "annual_turnover": 4000000,
            "capital": 50000,
            "key_personnel": [
                {
                    "name": "Adv Rolf Magre 11",
                    "position": "Styrelseordf"
                },
                {
                    "name": "H B Edwards",
                    "position": "Verkst dir"
                }
            ],
            "establishment_year": 1964
        },
        "18": {
            "company_name": "OPE-PRODUKTER AB",
            "pnr": "644 00",
            "address": "Torshälla, Sågg 9",
            "phone_number": "016-558 66",
            "bank_details": {
                "bankgiro": "62-3604",
                "postgiro": "545226-3"
            },
            "activity": "Hyvelbänkbeslag, emballage o byggnadsbeslag",
            "employees": 5,
            "key_personnel": [
                {
                    "name": "Ing Sven Olov Persson",
                    "position": "Ägare o chef"
                }
            ],
            "establishment_year": 1964
        }
    }
}