{
    "original": "ROR OCH BLÄSTRING\n\nPnr 603 58\n\nNorrköping, Vrinnevig 61. Tel\n011-13 05 95, 45130. Bankgiro\n610-2529. Postgiro 161416-3\nVerksamhet: Sandblästring o\nsprut-målning. Rensning av vattenrör.\nRenovering av fasader\nChef: Alrik Hillerås\nEtableringsår: 1942.\n\nROR. &amp; KONSTRUKTIONS.\nSVETS, AB\n\nPnr 40313\n\nGöteborg 2, Box 2173. Magasinsg\n3. Tel 031-13 01 28. Bankgiro\n33-7574. Postgiro 244731\n\nVerksamhet: Rörledningar för\nindustrier o oljedepåer\nAntal anställda: 80\nAktiekapital: 30 000\nVerkst dir: Rune Widström\nEtableringsår 1955.\n\nGUNNARSSON &amp; CO AB\n\nPnr 828 00\n\nEdsbyn, Box 75. Tel 0271-20131,\n217 25. Bankgiro 786-0091.\nPostgiro 124938-2\n\nVerksamhet: Tillverkar o säljer\nvilla- o radgarage\nVarunamn: Edsby-Electronic,\nEdsby-Garaget, Edsby-Porten\nAntal anställda: 42\nÅrsomsättning: 3 500 000\nAktiekapital: 100 000\nVerkst dir: Ake Gunnarsson\nEtableringsår 1951.\n\nGUNNARSSONS SNICKERI.\nFABRIK, BRÖDERNA\n\nPnr 560 10\n\nSkillingaryd, Ljungafors. Tel\n0370-73046. Bankgiro 98-1810.\nPostgiro 129194-7\n\nVerksamhet: Tillverkar lastpallar,\npallramar samt specialemballage\nÅrsomsättning: 200000\nÄgare o chef: Sven Gunnarsson\nEtableringsår: 1912.\n\nLJUSKOPIA, AB\n\nPnr 104 30\n\nStockholm 45, Pack. Drottningg\n89-93. Tel 08-23 84 20. Bankgiro\n605-1593. Postgiro 177550-1\nVerksamhet: Ljuskopiering,\nfoto-reprografi, offsettryckning\n.Antal anställda: 190\nÅrsomsättning: 8 000 000\nAktiekapital: 80 000\nVerkst dir: Hans B Pettersson\nprod-chef ljuskopiering: Ingemar\nStååhl\n\nProd-chef tekn avd: Rune wirdfors\nEtableringsår: 1935.\n\nANNONSREGISTRET AB\n\nPnr 412 75\n\nGöteborg, Ostg 12-18. Tel\n031-40 60 61, 40 60 62. Bankgiro\n51-4392. Postgiro 41512\nVerksamhet: Annonstidskrift inom\nverkstadsindustrin\nAntal anställda: 5\nÅrsomsättning: 900 000\nAnsvarig utgivare: Ing Gerhard\nWinterfeld\n\nEtableringsår: 1957.\n\nSAL\n\nSABIMA AB\n\nPnr 16115\n\nBromma 15, Västerled 14. Box\n15015. Tel 08-262900. Bankgiro\n744-1009. Postgiro 365400-1\nVerksamhet: Byggkonsult,\nentreprenadbeskrivningar, byggnadsbeskrivningar, mängdförteckningar\nAntal anställda: 45\nÅrsomsättning: 2 000 000\nAktiekapital: 10 000\nVerkst dir: Byggn-ing SBR Kurt\nPalmqvist\n\nÖvering: Byggn-ing SBR Sune\nAndersson\nEtableringsàr: 1949\nOmbildat till aktiebolag 1963.\n\nSABROE KYLINDUSTRI, AB\n\nPnr 400 42\n\nGöteborg 26, Dahlströmsg 52.Pack.\nTel 031-42 0630. Bankgiro\n848-1582. Postgiro 49465-8. Tga\nSab-roe. Telex 20760\nVerksamhet: Industriella o\nkommersiella kylanläggningar av alla\nslag, kylanläggningar för fartyg etc.\nKylutrustningar för\nluftkonditionering o konstisbanor m m\nAvdelningskontor: 113 20\nStockholm, Atlasg 12. Telex 17743. Tel\n08-32 3510\n\n211 21 Malmö, Västerg 22. Telex\n32696. Tel 040-723 60\nVarunamn: Sabroe\nAntal anställda: 53\nÅrsomsättning: 14 000000\nAktiekapital: 100 000\nStyrelse: Dir Gustaf Terling (ordf),\ndir Aage Korsgaard, dir Alf Malm\nVerkst dlr: Alf Malm\nEtableringsàr: 1945\nDotterbolag till AS Thomas Ths\nSabroe, Aarhus, Danmark.\n\nSADS MEKANISKA\nVERKSTAD AB\n\nPnr 605 90\n\nNorrköping, Klippbacken. Tel\n011-430 01, 43019. Bankgiro 34-9190.\nPostgiro 392476\nVerksamhet: Utför legoarbeten\nAntal anställda: 18\nÅrsomsättning: 1500000\nAktiekapital: 30 000\nVerkst dir: Birger Arkesten\nEtableringsàr: 1949.\n\nSADOLINS FÄRGFABRIK, AB\n\nPnr 124 21\n\nBandhagen 1, Stallarholmsv 52. Box\n78. Tel 08-86 0150. Bankgiro\n16-6515. Postgiro 254273. Tga\nSado-Uns\n\nVerksamhet: Tryckfärger, kulörta o\nsvarta, grafiska hjälpmedel\nVarunamn: Sadolins\nAntal anställda: 52\nÅrsomsättning: 7100 000\nAktiekapital: 800 000\nVerkst dir: N E Oppelstrup\nEtableringsån 1946.\n\nmalm, ab oscar\n\nPnr 112 24\n\nStockholm K, Kungsholms\nKyrko-plan 5. Tel 08-51 16 35. Bankgiro\n73-1219. Postgiro 50546\nVerksamhet: Säljer\nsanitetsarma-tur, packningar o gummislangar\nÅrsomsättning: 500 000\nAktiekapital: 40 000\nEtableringsår: 1923.\n\nFAMMARPS TRÄDGÅRD, AB\n\nPnr 30104\n\nHalmstad 1, Box 189. Söndrum.\nTel 035-30510. Bankgiro 42-3521.\nPostgiro 86364\n\nVerksamhet: Odling o konservering\nav champignoner\nAntal anställda: 200\nÅrsomsättning: 10 100 000\nAktiekapital: 600000\nVerkst dir: Bo Wendler\nEtableringsår: 1933.\n\nHÄLLOFISK, AB\n\nPnr 450 43\n\nSmögen Tel 0523-312 26, 314 26.\nBankgiro 551-0078. Postgiro\n360192-9. Tga Haafisk\nVeiksamhet: Tillverkar\nskaldjurskonserver, främst räkor i\nglasburkar\n\nVarunamn: Skagerack\nAntal anställda: 30\nÅrsomsättning: 3 500 000\nÄgare o chefer: Töre Stenman,\nRune Jonsson, Leif Stenman\nEtableringsår: 1946.\n\nPENA PURA 01L AB\n\nPnr 235 00\n\nVellinge. Tel 040-421104.\nBankgiro 874-8709. Postgiro 38821-5\nVerksamhet: Tillverkar o säljer\nsmörjoljor o smörjmedel\n\nVarunamn: Anticorit, Ingralen,\nIng-ralin\n\nVerkst dir: Ing Ingemar\nChristoffersson\n\nEtableringsår: 1957.\n\nEPEGE-TRYCKERIERNA AB\n\nPnr 11661\n\nStockholm SO, Ringv 86. Tel\n08-44 08 80. Bankgiro 33-2185.\nPostgiro 57734\n\nVerksamhet: Boktryck o offset,\nmestadels färgreklam\nAntal anställda: 25\nÅrsomsättning: 2 200 000\nAktiekapital: 150 000\nEtableringsår: 1941.",
    "structured": {
        "1": {
            "company_name": "ROR OCH BLÄSTRING",
            "address": "Norrköping, Vrinnevig 61",
            "phone_number": "011-13 05 95",
            "bank_details": {
                "bankgiro": "610-2529",
                "postgiro": "161416-3"
            },
            "activity": "Sandblästring o sprut-målning. Rensning av vattenrör. Renovering av fasader",
            "key_personnel": [
                {
                    "name": "Alrik Hillerås",
                    "position": "Chef"
                }
            ],
            "establishment_year": 1942
        },
        "2": {
            "company_name": "ROR. & KONSTRUKTIONS. SVETS, AB",
            "address": "Göteborg 2, Box 2173, Magasinsg 3",
            "phone_number": "031-13 01 28",
            "bank_details": {
                "bankgiro": "33-7574",
                "postgiro": "244731"
            },
            "activity": "Rörledningar för industrier o oljedepåer",
            "employees": 80,
            "capital": 30000,
            "key_personnel": [
                {
                    "name": "Rune Widström",
                    "position": "Verkst dir"
                }
            ],
            "establishment_year": 1955
        },
        "3": {
            "company_name": "GUNNARSSON & CO AB",
            "address": "Edsbyn, Box 75",
            "phone_number": "0271-20131, 217 25",
            "bank_details": {
                "bankgiro": "786-0091",
                "postgiro": "124938-2"
            },
            "activity": "Tillverkar o säljer villa- o radgarage",
            "employees": 42,
            "annual_turnover": 3500000,
            "capital": 100000,
            "key_personnel": [
                {
                    "name": "Ake Gunnarsson",
                    "position": "Verkst dir"
                }
            ],
            "establishment_year": 1951
        },
        "4": {
            "company_name": "GUNNARSSONS SNICKERI. FABRIK, BRÖDERNA",
            "address": "Skillingaryd, Ljungafors",
            "phone_number": "0370-73046",
            "bank_details": {
                "bankgiro": "98-1810",
                "postgiro": "129194-7"
            },
            "activity": "Tillverkar lastpallar, pallramar samt specialemballage",
            "annual_turnover": "200000",
            "key_personnel": [
                {
                    "name": "Sven Gunnarsson",
                    "position": "Ägare o chef"
                }
            ],
            "establishment_year": 1912
        },
        "5": {
            "company_name": "LJUSKOPIA, AB",
            "address": "Stockholm 45, Pack. Drottningg 89-93",
            "phone_number": "08-23 84 20",
            "bank_details": {
                "bankgiro": "605-1593",
                "postgiro": "177550-1"
            },
            "activity": "Ljuskopiering, foto-reprografi, offsettryckning",
            "employees": 190,
            "annual_turnover": 8000000,
            "capital": 80000,
            "key_personnel": [
                {
                    "name": "Hans B Pettersson",
                    "position": "Verkst dir"
                },
                {
                    "name": "Ingemar Stååhl",
                    "position": "prod-chef ljuskopiering"
                },
                {
                    "name": "Rune wirdfors",
                    "position": "Prod-chef tekn avd"
                }
            ],
            "establishment_year": 1935
        },
        "6": {
            "company_name": "ANNONSREGISTRET AB",
            "address": "Göteborg, Ostg 12-18",
            "phone_number": "031-40 60 61, 40 60 62",
            "bank_details": {
                "bankgiro": "51-4392",
                "postgiro": "41512"
            },
            "activity": "Annonstidskrift inom verkstadsindustrin",
            "employees": 5,
            "annual_turnover": 900000,
            "key_personnel": [
                {
                    "name": "Ing Gerhard Winterfeld",
                    "position": "Ansvarig utgivare"
                }
            ],
            "establishment_year": 1957
        },
        "7": {
            "company_name": "SAL SABIMA AB",
            "address": "Bromma 15, Västerled 14, Box 15015",
            "phone_number": "08-262900",
            "bank_details": {
                "bankgiro": "744-1009",
                "postgiro": "365400-1"
            },
            "activity": "Byggkonsult, entreprenadbeskrivningar, byggnadsbeskrivningar, mängdförteckningar",
            "employees": 45,
            "annual_turnover": 2000000,
            "capital": 10000,
            "key_personnel": [
                {
                    "name": "Byggn-ing SBR Kurt Palmqvist",
                    "position": "Verkst dir"
                },
                {
                    "name": "Byggn-ing SBR Sune Andersson",
                    "position": "Övering"
                }
            ],
            "establishment_year": 1949
        },
        "8": {
            "company_name": "SABROE KYLINDUSTRI, AB",
            "address": "Göteborg 26, Dahlströmsg 52.Pack",
            "phone_number": "031-42 0630",
            "bank_details": {
                "bankgiro": "848-1582",
                "postgiro": "49465-8"
            },
            "activity": "Industriella o kommersiella kylanläggningar av alla slag, kylanläggningar för fartyg etc. Kylutrustningar för luftkonditionering o konstisbanor m m",
            "employees": 53,
            "annual_turnover": 14000000,
            "capital": 100000,
            "key_personnel": [
                {
                    "name": "Gustaf Terling",
                    "position": "Styrelse: Dir (ordf)"
                },
                {
                    "name": "Aage Korsgaard",
                    "position": "Styrelse: Dir"
                },
                {
                    "name": "Alf Malm",
                    "position": "Verkst dlr"
                }
            ],
            "establishment_year": 1945
        },
        "9": {
            "company_name": "SADS MEKANISKA VERKSTAD AB",
            "address": "Norrköping, Klippbacken",
            "phone_number": "011-430 01, 43019",
            "bank_details": {
                "bankgiro": "34-9190",
                "postgiro": "392476"
            },
            "activity": "Utför legoarbeten",
            "employees": 18,
            "annual_turnover": 1500000,
            "capital": 30000,
            "key_personnel": [
                {
                    "name": "Birger Arkesten",
                    "position": "Verkst dir"
                }
            ],
            "establishment_year": 1949
        },
        "10": {
            "company_name": "SADOLINS FÄRGFABRIK, AB",
            "address": "Bandhagen 1, Stallarholmsv 52, Box 78",
            "phone_number": "08-86 0150",
            "bank_details": {
                "bankgiro": "16-6515",
                "postgiro": "254273"
            },
            "activity": "Tryckfärger, kulörta o svarta, grafiska hjälpmedel",
            "employees": 52,
            "annual_turnover": 7100000,
            "capital": 800000,
            "key_personnel": [
                {
                    "name": "N E Oppelstrup",
                    "position": "Verkst dir"
                }
            ],
            "establishment_year": 1946
        },
        "11": {
            "company_name": "malm, ab oscar",
            "address": "Stockholm K, Kungsholms Kyrko-plan 5",
            "phone_number": "08-51 16 35",
            "bank_details": {
                "bankgiro": "73-1219"
            },
            "activity": "Säljer sanitetsarma-tur, packningar o gummislangar",
            "annual_turnover": 500000,
            "capital": 40000,
            "establishment_year": 1923
        },
        "12": {
            "company_name": "FAMMARPS TRÄDGÅRD, AB",
            "address": "Halmstad 1, Box 189, Söndrum",
            "phone_number": "035-30510",
            "bank_details": {
                "bankgiro": "42-3521",
                "postgiro": "86364"
            },
            "activity": "Odling o konservering av champignoner",
            "employees": 200,
            "annual_turnover": 10100000,
            "capital": 600000,
            "key_personnel": [
                {
                    "name": "Bo Wendler",
                    "position": "Verkst dir"
                }
            ],
            "establishment_year": 1933
        },
        "13": {
            "company_name": "HÄLLOFISK, AB",
            "address": "Smögen",
            "phone_number": "0523-312 26, 314 26",
            "bank_details": {
                "bankgiro": "551-0078",
                "postgiro": "360192-9"
            },
            "activity": "Tillverkar skaldjurskonserver, främst räkor i glasburkar",
            "employees": 30,
            "annual_turnover": 3500000,
            "key_personnel": [
                {
                    "name": "Töre Stenman",
                    "position": "Ägare o chefer"
                }
            ],
            "establishment_year": 1946
        },
        "14": {
            "company_name": "PENA PURA 01L AB",
            "address": "Vellinge",
            "phone_number": "040-421104",
            "bank_details": {
                "bankgiro": "874-8709",
                "postgiro": "38821-5"
            },
            "activity": "Tillverkar o säljer smörjoljor o smörjmedel",
            "key_personnel": [
                {
                    "name": "Ing Ingemar Christoffersson",
                    "position": "Verkst dir"
                }
            ],
            "establishment_year": 1957
        },
        "15": {
            "company_name": "EPEGE-TRYCKERIERNA AB",
            "address": "Stockholm SO, Ringv 86",
            "phone_number": "08-44 08 80",
            "bank_details": {
                "bankgiro": "33-2185",
                "postgiro": "57734"
            },
            "activity": "Boktryck o offset, mestadels färgreklam",
            "employees": 25,
            "annual_turnover": 2200000,
            "capital": 150000,
            "establishment_year": 1941
        }
    }
}