{
    "original": "ASP-HOLMBLAD AB\n\nPnr 212 15\n\nMalmö, Nobelv 129 B. Tel\n040-755 55. Tga Asplys\nVerksamhet: Tillverkar ljus,\nsötningsmedel, syntetisk bomull o\nkemisk tekniska artiklar\nAvdelningskontor o lagen\nStockholm SO, Ringv 56. Tel 08-84 31 31\nAktiekapital: 375 000\nVerkst dir: Stig Holmström\nEtableringsår: 1777.\n\nNILSSON, AB GOTTHARD\n\nPnr 343 00\n\nÄlmhult Huvudkontor. Tel\n0476-12200. Bankgiro 873-8551.\nPostgiro 30260-4. Tga Gotthard.\nTelex 4695\n\nVerksamhet: Driver engrosrörelse\nmed järn- o metallskrot,\nspårmaterial, textilavfall o ull. Industriell\nförädling av råmaterial till textil-,\npappers-, järn- o metallindustrier.\nTillverkar metallegeringar i tackor\nsamt rivull, rivbomull o rivvadd.\nHar filialrörelser på ett 20-tal\nplatser i landet\nAntal anstäUda: 300\nVerkst dir: Gösta Ehrnst\nEtableringsår: 1862\nOmbUdat tül aktiebolag 1915.\n\nNILSSON, AB GUNNAR\n\nPnr 37101\n\nKarlskrona 1, Box 6. Bredg 14. Tel\n0455-110 14, 141 56. Bankgiro\n861-3895. Postgiro 6095-4. Tga Genils\nVerksamhet: Syfabrik o\nmetallindustri\n\nAntal anstäUda: 100\nAktiekapital: 375 000\n\nVerkst dir: Sixten Elmqvist\nEtableringsår: 1915.\n\nFARTYGSUTRUSTNINGEN, AB\n\nPnr 421 76\n\nVästra Frölunda, Käringbergsg 1.\nTel 031-29 50 61, 29 50 62. Bankgiro\n234-7946. Postgiro 24 2901-7. Tga\nBirbal\n\nVerksamhet: Skeppsfournering\nAntal anställda: 3\nAktiekapital: 30 000\nStyrelse: Ing Birger Baltzersen\n(ordf), fru Inga-Stina Baltzersen\nVerkst dir: Ing Birger Baltzersen\nEtableringsår: 1947.\n\nVÄRNAMO NYHETER, AB\n\nPnr 331 01\n\nVärnamo 1, Box 88. Centralplan.\nTel 0370-119 50. Banngiro\n291-7011. Postgiro 71743-9\nVerksamhet: Tidningsutgivning\nAntal anställda: 55\nÅrsomsättning: 6 500000\nAktiekapital: 46 400\nVerkst dir: Karl-Erik Johansson\nEtableringsår: 1930.\n\nVÄRNAMO\nPLÅT-FORÄDLING, AB\n\nPnr 33101\n\nVärnamo 1, Fredsg 21. Box 47. Tel\n037 0-101 83. Bankgiro 141-8201.\nPostgiro 9320-3\n\nVerksamhet: Tillverkar\nfoderång-kokare, vattenvärmare,\nasfaltkokare, cisterner, sjukhusvagnar,\nsvetsade järnkonstruktioner o\nbetongfickor\n\nAntal anställda: 25\nÅrsomsättning: 1 800 000\nAktiekapital: 150000\nVeikst dir: Disp Göran Cedbjörk\nEtableringsån 1923.\n\nEXPONITE AB\n\nPnr 25102\n\nHälsingborg 1, Springpostgränden\n3. Box 26. Tel 042-1128 79,\n12 8 6 35. Bankgiro 65-3003.\nPostgiro 380110\n\nVerksamhet: Tillverkar\ndamförkläden, hyllbård, dukar m m i plast\nAntal anställda: 30\nÅrsomsättning: 1 300 000\nAktiekapital: 100 000\nVerkst dir: Walter Krantz\nEtableringsår: 1947.\n\nEXPORTFÖRENINGENS\nSERVICEAKTIEBOLAG\n\nPnr 114 85\n\nStockholm 5, Storg 19. Box 5513.\nTel 08-63 05 80. Tga Export.\nTelex 1620\n\nVerksamhet: Service till\nmedlemmarna i Sveriges Allmänna\nExportförening\n\nVerkst dir: Stig Ramel\nEtableringsår: 1963.\n\nENGDAHL AB, HANS\n\nPnr 112 51\n\nStockholm, Strandbergsg 47. Tel\n08-13 0230. Telex 17238\nVerksamhet: Försäljning av\nbyggmaterial\n\nAvdelningskontor och lager\n\nKors v 32, Snöstorp. Box 8005,\n300 08 Halmstad 8. Tel 035-10 42 60\nVarunamn: Hanedahl, Dawant,\nDawant Lux, Rolacklon,\nContinental. Dromara, Vanguard, TOP 323,\nSeaforde, Buflon, Evergrass, Modul\nAntal anställda: 30\nAktiekapital: 250000\nStyrelse: Lennart Segerlund (ordf),\nHans Engdahl, Bengt Norrman\nVerkst dir: Hans Engdahl\nEtableringsår: 1968.\n\nENGDAHL,\nINGENJÖRSFIRMAN SETH\n\nPnr 560 25\n\nBottnaryd, Aspholmen. Tel\n036-230 24. Postgiro 413278-3\nVerksamhet: Konstruktionsbyrå för\nventilationstekniska apparater o\nanläggningar\n\nÄgare o chef: Overing Seth\nEngdahl\n\nEtableringsår: 1958.\n\nVÄSTERÅS ELKONSULT AB\n\nPnr 724 66\n\nVästerås. Hammarby Centrum. Tel\n021-110160. Bankgiro 330-3997.\nPostgiro 474100-5\nVerksamhet: Elektrotekniska\nuppdrag\n\nAntal anställda: 25\n\nÅrsomsättning: 1 200 000\n\nAktiekapital: 5 000\n\nStyrelse: Ing Håkan Cederlöf(ordf),\n\ning Sigvard Dahlquist\n\nVerkst dir: Sigvard Dahlquist\n\nEtableringsår: 1955.\n\nHEIMER &amp; CO, JÄRNVARU AB\n\nPnr 212 25\n\nMalmö, Strö mg 15. Tel 040-93 5 9 00.\n\nBankgiro 870-2144: Postgiro\n14003-8. Tga Heimers\nVerksamhet: Säljer järnvaror,\nbyggnadsbeslag, maskiner o verktyg\nÅrsomsättning: 16 000 000\nAktiekapital: 450 000\nDir: Bertil Wollter\nEtableringsår: 1905.\n\nWALLANDER, BRÖDERNA H\n\nPnr 91001\n\nNordmaling, Nyg 5. Tel\n0930-107 40. Tga Wallanders\nVerksamhet: Tillverkar\nmasonite-lackplattor, Wallanderplattan,\nWa-nyl samt Bewal plastlaminat\nAntal anställda: 40\nÅrsomsättning: 3 000 000\nÄgare o chefer: Bengt Wallander,\nM Wallander\nEtableringsår: 1927.\n\nRYDS GRÄVMASKIN ER AB\n\nPnr 36010\n\nRyd, Mossbrohult. Tel 0459-801 91,\n806 84. Bankgiro 603-7600.\nPost-giro 568116-8\n\nVerksamhet: Utför grävnings- o\nplaneringsarbeten\nAntal anställda: 20\nÅrsomsättning: 2 000 000\nAktiekapital: 25 000\nStyrelse: Ture Johansson,\nChrister Johansson\nVerkst dir: Ture Johansson\nEtableringsån 1950\nOmbildat till aktiebolag 1961.\n\nRYDS INDUSTRI AB\n\nPnr 36010\n\nRyd, Box 97. Tel 0459-805 10.\nBankgiro 668-1183. Postgiro\n171935-0. Tga Riab\nVerksamhet: Tillverkar\nfritidsartiklar. Specialitet:\nbågskytteartiklar o båtar av glasfiberarmerad\nplast. Skridskor.\nEngrosförsälj-ning av bågskyttetillbehör samt\nvint ersport artiklar\nAntal anställda: 85\nÅrsomsättning: 10 000 000\nAktiekapital: 250 000\nVerkst dir: Gunnar Petersson\nEtableringsår: 1949.",
    "structured": {
        "firms": [
            {
                "company_name": "ASP-HOLMBLAD AB",
                "pnr": "212 15",
                "address": "Nobelvägen 129 B, Malmö",
                "phone_number": "040-755 55",
                "activity": "Tillverkar ljus, sötningsmedel, syntetisk bomull och kemisk tekniska artiklar",
                "capital": 375000,
                "key_personnel": [
                    {
                        "name": "Stig Holmström",
                        "position": "Verkställande direktör"
                    }
                ],
                "establishment_year": 1777
            },
            {
                "company_name": "NILSSON, AB GOTTHARD",
                "pnr": "343 00",
                "address": "Älmhult Huvudkontor",
                "phone_number": "0476-12200",
                "bank_details": {
                    "bankgiro": "873-8551",
                    "postgiro": "30260-4"
                },
                "activity": "Driver engrosrörelse med järn- och metallskrot, spårmaterial, textilavfall och ull. Industriell förädling av råmaterial till textil-, pappers-, järn- och metallindustrier. Tillverkar metallegeringar i tackor samt rivull, rivbomull och rivvadd. Har filialrörelser på ett 20-tal platser i landet",
                "employees": 300,
                "key_personnel": [
                    {
                        "name": "Gösta Ehrnst",
                        "position": "Verkställande direktör"
                    }
                ],
                "establishment_year": 1862
            },
            {
                "company_name": "NILSSON, AB GUNNAR",
                "pnr": "37101",
                "address": "Karlskrona 1, Box 6, Bredgatan 14",
                "phone_number": "0455-110 14, 141 56",
                "bank_details": {
                    "bankgiro": "861-3895",
                    "postgiro": "6095-4"
                },
                "activity": "Syfabrik och metallindustri",
                "employees": 100,
                "capital": 375000,
                "key_personnel": [
                    {
                        "name": "Sixten Elmqvist",
                        "position": "Verkställande direktör"
                    }
                ],
                "establishment_year": 1915
            },
            {
                "company_name": "FARTYGSUTRUSTNINGEN, AB",
                "pnr": "421 76",
                "address": "Käringbergsgatan 1, Västra Frölunda",
                "phone_number": "031-29 50 61, 29 50 62",
                "bank_details": {
                    "bankgiro": "234-7946",
                    "postgiro": "242901-7"
                },
                "activity": "Skeppsfournering",
                "employees": 3,
                "capital": 30000,
                "key_personnel": [
                    {
                        "name": "Ing Birger Baltzersen",
                        "position": "Styrelseordförande"
                    },
                    {
                        "name": "Fru Inga-Stina Baltzersen",
                        "position": "Styrelsemedlem"
                    }
                ],
                "establishment_year": 1947
            },
            {
                "company_name": "VÄRNAMO NYHETER, AB",
                "pnr": "331 01",
                "address": "Värnamo 1, Box 88, Centralplan",
                "phone_number": "0370-119 50",
                "bank_details": {
                    "bankgiro": "291-7011",
                    "postgiro": "71743-9"
                },
                "activity": "Tidningsutgivning",
                "employees": 55,
                "annual_turnover": 6500000,
                "capital": 46400,
                "key_personnel": [
                    {
                        "name": "Karl-Erik Johansson",
                        "position": "Verkställande direktör"
                    }
                ],
                "establishment_year": 1930
            },
            {
                "company_name": "VÄRNAMO PLÅT-FORÄDLING, AB",
                "pnr": "33101",
                "address": "Värnamo 1, Fredsgatan 21, Box 47",
                "phone_number": "0370-101 83",
                "bank_details": {
                    "bankgiro": "141-8201",
                    "postgiro": "9320-3"
                },
                "activity": "Tillverkar foderång-kokare, vattenvärmare, asfaltkokare, cisterner, sjukhusvagnar, svetsade järnkonstruktioner och betongfickor",
                "employees": 25,
                "annual_turnover": 1800000,
                "capital": 150000,
                "key_personnel": [
                    {
                        "name": "Disp Göran Cedbjörk",
                        "position": "Verkställande direktör"
                    }
                ],
                "establishment_year": 1923
            },
            {
                "company_name": "EXPONITE AB",
                "pnr": "25102",
                "address": "Hälsingborg 1, Springpostgränden 3, Box 26",
                "phone_number": "042-1128 79, 12 8 6 35",
                "bank_details": {
                    "bankgiro": "65-3003",
                    "postgiro": "380110"
                },
                "activity": "Tillverkar damförkläden, hyllbårder, dukar med mera i plast",
                "employees": 30,
                "annual_turnover": 1300000,
                "capital": 100000,
                "key_personnel": [
                    {
                        "name": "Walter Krantz",
                        "position": "Verkställande direktör"
                    }
                ],
                "establishment_year": 1947
            },
            {
                "company_name": "EXPORTFÖRENINGENS SERVICEAKTIEBOLAG",
                "pnr": "114 85",
                "address": "Stockholm 5, Storgatan 19, Box 5513",
                "phone_number": "08-63 05 80",
                "activity": "Service till medlemmarna i Sveriges Allmänna Exportförening",
                "key_personnel": [
                    {
                        "name": "Stig Ramel",
                        "position": "Verkställande direktör"
                    }
                ],
                "establishment_year": 1963
            },
            {
                "company_name": "ENGDAHL AB, HANS",
                "pnr": "112 51",
                "address": "Stockholm, Strandbergsgatan 47",
                "phone_number": "08-13 0230",
                "activity": "Försäljning av byggmaterial",
                "employees": 30,
                "capital": 250000,
                "key_personnel": [
                    {
                        "name": "Hans Engdahl",
                        "position": "Verkställande direktör"
                    }
                ],
                "establishment_year": 1968
            },
            {
                "company_name": "ENGDAHL, INGENJÖRSFIRMAN SETH",
                "pnr": "560 25",
                "address": "Bottnaryd, Aspholmen",
                "phone_number": "036-230 24",
                "postgiro": "413278-3",
                "activity": "Konstruktionsbyrå för ventilationstekniska apparater och anläggningar",
                "owner": "Overing Seth Engdahl",
                "establishment_year": 1958
            },
            {
                "company_name": "VÄSTERÅS ELKONSULT AB",
                "pnr": "724 66",
                "address": "Västerås, Hammarby Centrum",
                "phone_number": "021-110160",
                "bank_details": {
                    "bankgiro": "330-3997",
                    "postgiro": "474100-5"
                },
                "activity": "Elektrotekniska uppdrag",
                "employees": 25,
                "annual_turnover": 1200000,
                "capital": 5000,
                "key_personnel": [
                    {
                        "name": "Ing Håkan Cederlöf",
                        "position": "Styrelseordförande"
                    },
                    {
                        "name": "Ing Sigvard Dahlquist",
                        "position": "Styrelseledamot"
                    },
                    {
                        "name": "Sigvard Dahlquist",
                        "position": "Verkställande direktör"
                    }
                ],
                "establishment_year": 1955
            },
            {
                "company_name": "HEIMER & CO, JÄRNVARU AB",
                "pnr": "212 25",
                "address": "Malmö, Strömgatan 15",
                "phone_number": "040-93 5 9 00",
                "bank_details": {
                    "bankgiro": "870-2144",
                    "postgiro": "14003-8"
                },
                "activity": "Säljer järnvaror, byggnadsbeslag, maskiner och verktyg",
                "annual_turnover": 16000000,
                "capital": 450000,
                "key_personnel": [
                    {
                        "name": "Bertil Wollter",
                        "position": "Verkställande direktör"
                    }
                ],
                "establishment_year": 1905
            },
            {
                "company_name": "WALLANDER, BRÖDERNA H",
                "pnr": "91001",
                "address": "Nordmaling, Nygatan 5",
                "phone_number": "0930-107 40",
                "activity": "Tillverkar masonite-lackplattor, Wallanderplattan, Wa-nyl samt Bewal plastlaminat",
                "employees": 40,
                "annual_turnover": 3000000,
                "key_personnel": [
                    {
                        "name": "Bengt Wallander",
                        "position": "Ägare och chef"
                    },
                    {
                        "name": "M Wallander",
                        "position": "Ägare och chef"
                    }
                ],
                "establishment_year": 1927
            },
            {
                "company_name": "RYDS GRÄVMASKINER AB",
                "pnr": "36010",
                "address": "Ryd, Mossbrohult",
                "phone_number": "0459-801 91, 806 84",
                "bank_details": {
                    "bankgiro": "603-7600",
                    "postgiro": "568116-8"
                },
                "activity": "Utför grävnings- och planeringsarbeten",
                "employees": 20,
                "annual_turnover": 2000000,
                "capital": 25000,
                "key_personnel": [
                    {
                        "name": "Ture Johansson",
                        "position": "Styrelseordförande"
                    },
                    {
                        "name": "Christer Johansson",
                        "position": "Styrelseledamot"
                    },
                    {
                        "name": "Ture Johansson",
                        "position": "Verkställande direktör"
                    }
                ],
                "establishment_year": 1950
            },
            {
                "company_name": "RYDS INDUSTRI AB",
                "pnr": "36010",
                "address": "Ryd, Box 97",
                "phone_number": "0459-805 10",
                "bank_details": {
                    "bankgiro": "668-1183",
                    "postgiro": "171935-0"
                },
                "activity": "Tillverkar fritidsartiklar. Specialitet: bågskytteartiklar och båtar av glasfiberarmerad plast. Skridskor. Engrosförsäljning av bågskyttetillbehör samt vintersportartiklar",
                "employees": 85,
                "annual_turnover": 10000000,
                "capital": 250000,
                "key_personnel": [
                    {
                        "name": "Gunnar Petersson",
                        "position": "Verkställande direktör"
                    }
                ],
                "establishment_year": 1949
            }
        ]
    }
}