{
    "original": "ANDERSEN EFTR, AB GEORG\n\nPnr 25102\n\nHelsingborg 1, Box 17. Järnvägsg\n29. Tel 042-12 42 00, 13 42 00.\nBankgiro 652-8038. Postgiro 399813-5\nVerksamhet: Säljer pennor,\npresent- o reklamartiklar engros.\nGeneralagent för Montblanc\nAntal anställda: 20\nVerkst dir: Helge Sölvkjär\nEtableringsår: 1952.\n\nADA\n\nADAMSON &amp; NYSTRUM AB\n\nPnr 41119\n\nGöteborg, Kungsg 5. Tel\n031-11 97 98, 11 97 94. Postgiro 40811\nVerksamhet: Kem tekn artiklar\n\nengros\n\nAntal anställda: 4\nAktiekapital: 66 400\nVerks t dir: Hans Nyström\nEtableringsår: 1919.\n\nADAMSONS SNICKERIFABRIK,\nAB E A\n\nPnr 733 00\n\nSala, Josefsdal. Box 7. Tel\n0224-10710, 147 40. Bankgiro 34-9802.\nPostgiro 4076\n\nVerksamhet: Tillverkar inredningar\no utför snickeriarbeten\nAktiekapital: 45 000\nVerkst dir: Thure Skoglund\nEtableringsår: 1917.\n\nESEA TRICOT AB\n\nPnr 51010\n\nHorred. Tel 0320-800 01. Bankgiro\n43-5803. Postgiro 172472. Tga Esea\nVerksamhet: Tillverkar yttertrikå\nför herr o dam\nAntal anställda: 80\nAktiekapital: 300 000\nVeikst dir: Per Ekelund\nEtableringsår: 1939.\n\nSBM\n\nVeiksamhet: Internationella\nmässor, fackmässor, kongresser\nVerkst dir: Civiling Bengt R Hult\nEtableringsår: 1943.\n\nSANKT RAGNHILD AB,\nFABRIKEN\n\nPnr 614 00\n\nSöderköping, Vintervadet 2. Tel\n0121-10215. Postgiro 76383\nVerksamhet: Tillverkar o säljer\nhårnålar, locknålar o luggnålar\nAntal anställda: 3\nÅrsomsättning: 100000\nAktiekapital: 21000\nVerkst dir: Fabr Gunnar Svensson\nEtableringsår: 1921.\n\nKUNDKONTROLL, AB\n\nPnr 127 85\n\nSkärholmen. Tel 08-710 7100.\nBankgiro 196-1382. Postgiro 454300-5.\nTga Kundkontroll\nVerksamhet: Inkasso, upplysning,\nresekontrabevakning\nAntal anställda: 100\nÅrsomsättning: 6 000 000\nAktiekapital: 100 000\nStyrelse: Adv Anders R Öhman\n(ordf), dir Hasse Albin, adv Måns\nSilfvers ward\nVeikst din Hasse Albin\nV veikst dir: Gerhard Larsen\nEtableringsår: 1962.\n\nVARGARDA TRYCKERI\n\nPnr 440 20\n\nVårgårda. Tel 0322-202 61.\nBankgiro 894-9471. Postgiro 281063-8\nVerksamhet: Trycksaker för\nhandel o industri\nAntal anställda: 3\nÄgare o chef: Henry Wallentin\nEtableringsån 1944.\n\nVARGARDA\nTRÄVARU-AFFÄR. AB\n\nPnr 440 20\n\nVårgårda, Industrig 11. Box 81.\nTel 0322-207 15. Bankgiro\n894-9315. Postgiro 265399-6\nVerksamhet: Tillverkar trävita o\nfabrikslackerade \"Vårgårda Kök\"\nVarunamn: Vårgårda Kök\nAntal anställda: 110\nÅrsomsättning: 9 000 000\nAktiekapital: 200 000\nStyrelse: Bankkamrer Sten\nNorström (ordf), fabr Helge Attebring,\ndisp Lennart Gustavsson\nVerkst dir: Disp Lennart\nGustavsson\n\nEtableringsån 1915\nOmbildat till aktiebolag 1955.\n\nVÄDERSTADS\nTRÄ-FORÄDLING. AB\n\nPnr 590 21\n\nVäderstad, Vallsberg. Box 5. Tel\n0142-700 61. Bankgiro 12-8390.\nPostgiro 282580\nVerksamhet: Såg o hyvleri samt\nförsäljning av byggnadsmaterial\nAntal anställda: 15\nÅrsomsättning: 800 000\nAktiekapital: 60 000\nVerkst dir: Oskar Sjögren\nEtableringsår: 1944.\n\nHED\n\nHEDIN, AB KARL\n\nPnr 773 00\n\nFagersta, Bergslagsv 49. Tel\n0223-105 50. Tga Karl. Telex 7541\nVerksamhet: Sågverk o hyvleri\ni Fagersta o Karbenning\nAntal anställda: 100\nAktiekapital: 150 300\nVeikst dir: Lars Hedin\nEtableringsår 1935.\n\nNYTTOVERKTYG, AB\n\nPnr 142 01\n\nTrångsund 1, Box 6. Nynäsv 537.\nTel 08-771 91 25. Bankgiro\n745-2162. Postgiro 453647-0\nVerksamhet: Vertygstillverkning\nför industrin\n\nÅrsomsättning: 5 000 000\nVerkst dir: Olof Gutelid\nEtableringsår: 1950.\n\nfalkhammar, ab eric\n\nPnr 102 61\n\nStockholm 4, Box 4104. Tjärhovsg\n12-14. Tel 08-44 55 55. Bankgiro\n56-9703. Postgiro 2538 49-4. Tga\nQfalk. Telex 10552\nVerksamhet: Säljer utländska\nlindnings- o träbearbetningsmaskiner,\nplastspolar, specialslipmaskiner\nAntal anställda: 4\nÅrsomsättning: 8 700 000\nAktiekapital: 190000\nVerkst dir: Erie Falkhammar\nEtableringsår 1946.\n\nLYFT &amp; TRANSPORT\n\nPnr 217 57\n\nMalmö, Sergels v 9 A. Tel\n040-91 55 25. 91 64 28. Bankgiro\n644-9672. Postgiro 539548-8\nVerksamhet: Projekterar o salufor\negna tillverkningar omfattande\nhydrauliska lyftbord, rullbanor,\ntransportörer o kompletta\nanläggningar\n\nVarunamn: Liftman\nVerkstad: Ljungby. Liftman AB.\nTel 0372-141 68\nÅrsomsättning: 2 500 000\nChef: Ing Ake Andersson\nEtableringsår: 1964.",
    "structured": {
        "1": {
            "company_name": "ANDERSEN EFTR, AB GEORG",
            "pnr": "25102",
            "address": "Helsingborg 1, Box 17. Järnvägsg 29",
            "phone_number": "042-12 42 00, 13 42 00",
            "bank_details": {
                "bankgiro": "652-8038",
                "postgiro": "399813-5"
            },
            "activity": "Säljer pennor, present- o reklamartiklar engros. Generalagent för Montblanc",
            "employees": 20,
            "establishment_year": 1952
        },
        "2": {
            "company_name": "ADAMSON & NYSTRUM AB",
            "pnr": "41119",
            "address": "Göteborg, Kungsg 5",
            "phone_number": "031-11 97 98, 11 97 94",
            "bank_details": {
                "postgiro": "40811"
            },
            "activity": "Kem tekn artiklar engros",
            "employees": 4,
            "capital": 66400,
            "establishment_year": 1919
        },
        "3": {
            "company_name": "ADAMSONS SNICKERIFABRIK, AB E A",
            "pnr": "733 00",
            "address": "Sala, Josefsdal. Box 7",
            "phone_number": "0224-10710, 147 40",
            "bank_details": {
                "bankgiro": "34-9802",
                "postgiro": "4076"
            },
            "activity": "Tillverkar inredningar o utför snickeriarbeten",
            "capital": 45000,
            "establishment_year": 1917
        },
        "4": {
            "company_name": "ESEA TRICOT AB",
            "pnr": "51010",
            "address": "Horred",
            "phone_number": "0320-800 01",
            "bank_details": {
                "bankgiro": "43-5803",
                "postgiro": "172472"
            },
            "activity": "Tillverkar yttertrikå för herr o dam",
            "employees": 80,
            "capital": 300000,
            "establishment_year": 1939
        },
        "5": {
            "company_name": "SBM",
            "activity": "Internationella mässor, fackmässor, kongresser",
            "key_personnel": [
                {
                    "name": "Civiling Bengt R Hult",
                    "position": "Verkst dir"
                }
            ],
            "establishment_year": 1943
        },
        "6": {
            "company_name": "SANKT RAGNHILD AB, FABRIKEN",
            "pnr": "614 00",
            "address": "Söderköping, Vintervadet 2",
            "phone_number": "0121-10215",
            "bank_details": {
                "postgiro": "76383"
            },
            "activity": "Tillverkar o säljer hårnålar, locknålar o luggnålar",
            "employees": 3,
            "annual_turnover": 100000,
            "capital": 21000,
            "establishment_year": 1921
        },
        "7": {
            "company_name": "KUNDKONTROLL, AB",
            "pnr": "127 85",
            "address": "Skärholmen",
            "phone_number": "08-710 7100",
            "bank_details": {
                "bankgiro": "196-1382",
                "postgiro": "454300-5"
            },
            "activity": "Inkasso, upplysning, resekontrabevakning",
            "employees": 100,
            "annual_turnover": 6000000,
            "capital": 100000,
            "key_personnel": [
                {
                    "name": "Adv Anders R Öhman",
                    "position": "ordf"
                },
                {
                    "name": "dir Hasse Albin",
                    "position": "V verkst dir"
                },
                {
                    "name": "adv Måns Silfvers ward",
                    "position": "rdst dir"
                }
            ],
            "establishment_year": 1962
        },
        "8": {
            "company_name": "VARGARDA TRYCKERI",
            "pnr": "440 20",
            "address": "Vårgårda",
            "phone_number": "0322-202 61",
            "bank_details": {
                "bankgiro": "894-9471",
                "postgiro": "281063-8"
            },
            "activity": "Trycksaker för handel o industri",
            "employees": 3,
            "key_personnel": [
                {
                    "name": "Henry Wallentin",
                    "position": "Ägare o chef"
                }
            ],
            "establishment_year": 1944
        },
        "9": {
            "company_name": "VARGARDA TRÄVARU-AFFÄR. AB",
            "pnr": "440 20",
            "address": "Vårgårda, Industrig 11. Box 81",
            "phone_number": "0322-207 15",
            "bank_details": {
                "bankgiro": "894-9315",
                "postgiro": "265399-6"
            },
            "activity": "Tillverkar trävita o fabrikslackerade \"Vårgårda Kök\"",
            "employees": 110,
            "annual_turnover": 9000000,
            "capital": 200000,
            "key_personnel": [
                {
                    "name": "Bankkamrer Sten Norström",
                    "position": "ordf"
                },
                {
                    "name": "fabr Helge Attebring",
                    "position": "st dir"
                },
                {
                    "name": "disp Lennart Gustavsson",
                    "position": "Verkst dir"
                }
            ],
            "establishment_year": 1915,
            "ombildat_till_aktiebolag_year": 1955
        },
        "10": {
            "company_name": "VÄDERSTADS TRÄ-FORÄDLING. AB",
            "pnr": "590 21",
            "address": "Väderstad, Vallsberg. Box 5",
            "phone_number": "0142-700 61",
            "bank_details": {
                "bankgiro": "12-8390",
                "postgiro": "282580"
            },
            "activity": "Såg o hyvleri samt försäljning av byggnadsmaterial",
            "employees": 15,
            "annual_turnover": 800000,
            "capital": 60000,
            "key_personnel": [
                {
                    "name": "Oskar Sjögren",
                    "position": "Verkst dir"
                }
            ],
            "establishment_year": 1944
        },
        "11": {
            "company_name": "HEDIN, AB KARL",
            "pnr": "773 00",
            "address": "Fagersta, Bergslagsv 49",
            "phone_number": "0223-105 50",
            "activity": "Sågverk o hyvleri i Fagersta o Karbenning",
            "employees": 100,
            "capital": 150300,
            "key_personnel": [
                {
                    "name": "Lars Hedin",
                    "position": "Verkst dir"
                }
            ],
            "establishment_year": 1935
        },
        "12": {
            "company_name": "NYTTOVERKTYG, AB",
            "pnr": "142 01",
            "address": "Trångsund 1, Box 6. Nynäsv 537",
            "phone_number": "08-771 91 25",
            "bank_details": {
                "bankgiro": "745-2162",
                "postgiro": "453647-0"
            },
            "activity": "Vertygstillverkning för industrin",
            "annual_turnover": 5000000,
            "key_personnel": [
                {
                    "name": "Olof Gutelid",
                    "position": "Verkst dir"
                }
            ],
            "establishment_year": 1950
        },
        "13": {
            "company_name": "falkhammar, ab eric",
            "pnr": "102 61",
            "address": "Stockholm 4, Box 4104. Tjärhovsg 12-14",
            "phone_number": "08-44 55 55",
            "bank_details": {
                "bankgiro": "56-9703",
                "postgiro": "2538 49-4"
            },
            "activity": "Säljer utländska lindnings- o träbearbetningsmaskiner, plastspolar, specialslipmaskiner",
            "employees": 4,
            "annual_turnover": 8700000,
            "capital": 190000,
            "key_personnel": [
                {
                    "name": "Erie Falkhammar",
                    "position": "Verkst dir"
                }
            ],
            "establishment_year": 1946
        },
        "14": {
            "company_name": "LYFT & TRANSPORT",
            "pnr": "217 57",
            "address": "Malmö, Sergels v 9 A",
            "phone_number": "040-91 55 25, 91 64 28",
            "bank_details": {
                "bankgiro": "644-9672",
                "postgiro": "539548-8"
            },
            "activity": "Projekterar o salufor egna tillverkningar omfattande hydrauliska lyftbord, rullbanor, transportörer o kompletta anläggningar",
            "varunamn": "Liftman",
            "verkstad": "Ljungby. Liftman AB. Tel 0372-141 68",
            "annual_turnover": 2500000,
            "chief": "Ing Ake Andersson",
            "establishment_year": 1964
        }
    }
}