{
    "original": "mb-produkter ab\n\nPnr 560 41\n\nMullsjö, Furudal. Tel 0392-104 70,\n104 02. Bankgiro 549-1386.\nPostgiro 119402-6. Tga MB-Produkter\nVerksamhet: Tillverkar\nhögtrycks-oljebrännare o oljefilter\nAntal anställda: 20\nÅrsomsättning: 3 000 000\nChef: Fabr Olle Wernald\nEtableringsår: 1953.\n\nSUNEX SÄKERHETSGLAS AB\n\nPnr 453 00\n\nLysekU, Box 35. Tel 0523-13010.\nBankgiro 235-2086. Postgiro\n54404-9. Tga Sunexglas\nVerksamhet: Glasförädlingsindustri.\nTillverkar härdat säkerhetsglas\nAntal anstäUda: 125\nÅrsomsättning: 18 000 000\n\nAktiekapital: 59 500\nVerkst dir: Patrich Furlong\nEtableringsår: 1932.\n\nSUTAB, AB\n\nPnr 16107\n\nBromma 7, Dr Abrahams v 53. Fack.\nTel 08-37 52 00, 37 89 00. Bankgiro\n560-5670. Postgiro 170085-5\nVerksamhet: Geodesi, geoteknik\nAntal anställda: 12\nÅrsomsättning: 900 000\nAktiekapital: 5 000\nVerkst dir: Civiling Ingvar Höök\nEtableringsår: 1962.\n\nSPORRONG PRESENTER AB\n\nPnr 11143\n\nStockholm, Kungsg 17. Tel\n08-22 56 60. Bankgiro 41-1405.\nPostgiro 1405. Telex 19076. Tga\nSporrongs\n\nVerksamhet: Försäljning av\nexklusiva presenter till allmänheten via\negen butik o till företag,\norganisationer, institutioner o vissa\ndetaljister via leveransavdelning\n\nAntal anställda: 10\nChef: Disp Hans Lennig\nEtableringsår: 1969.\n\nLEKHAMMAR ARKITEKT.\nKONTOR AB, BENGT\n\nPnr 852 30\n\nSundsvall, Storg 32. Tel 060-\n\n15 05 85. Bankgiro 180-0580.\nPostgiro 393798-4\n\nVerksamhet: Arkitektrörelse\nAntal anställda: 13\nVerkst dir: Ark SAR Bengt\nLekhammar\n\nEtableringsår: 1949.\n\nDAL\n\nDAHLBERG &amp; CO,\nTRYCKERI AB\n\nPnr 104 60\n\nStockholm 20, Hammarby Fabriksv\n29-31. Tel 08-44 07 00. Bankgiro\n73-3802. Postgiro 151880\nVerksamhet: Boktryck, offset o\nreklam\n\nAktiekapital: 75 000\nVerkst dir: Gustav Dahlberg\nEtableringsår: 1937.\n\nDAHLBERGS GROSSHANDELS\nAB, EDE- BOLAGET ERIK\n\nPnr 85102\n\nSundsvall 1, Box 65. Trafikg 54.\nTel 060-11 12 13. 11 34 54.\nBankgiro 180-0366. Postgiro 86949-5\nVerksamhet: Säljer livsmedel\nengros för bl a storkök, även\ndjupfrysta. Specialitet: konfektyrer\nAntal anställda: 15\nÅrsomsättning: 13 000000\nAktiekapital: 200 000\nVerkst dir: Erik Dahlberg\nV verkst dir: Carl-Erik Dahlberg\nEtableringsår: 1892.\n\nINDUSTRIKREDIT, AB\n\nPnr 11451\n\nStockholm O, Strandv 5 A. Tel 08-\n\n63 0880. Bankgiro 845-5172 . 5\n60-2099, 700-0797, 330-0126. Postgiro\n159346-6\n\nVerksamhet: Kreditgivning\nAktiekapital: 16 000 000\nStyrelse: Bankdir Arne Callans\n(crdf), bankdir Folke Fessé, adv\nTure Bengtsson, landshövd Karl\nFrithiofson, dir Karl Erik Gillberg,\ndir Hans Grundström, ombudsman\nErie Mossberger, bankdir John\nNylén, bankdir Lars Nyrén,\nbankdir Gösta Olson\n\nVerkst dir: Carl-Oscar Olkrantz\nEtableringsår: 1934.\n\nINDUSTRI LAGRET KINNA AB\n\nPw 51101\n\nKinna l.Box 118. Tel 0320-106 25.\nPostgiro 281105\n\nVerksamhet: Glas, porslin, leksaker\nengros\n\nAntal anställda: 17\nFirmatecknare: Roland Larsson,\nLennart Wigéll\nEtableringsår: 1960.\n\nBERNTS INDUSTRIER\n\nPnr 54014\n\nUlvåker. Tel 0500-601 03.\nBankgiro 364-9613. Postgiro 343253-1\nVerksamhet: Tillverkar köks- o\nmatbord, soff-, hörn- o lampbord\nÅrsomsättning: 900 000\nChef: Fabr Bernt Degervik.\n\nBERNVINGS VERKSTADS AB\n\nPnr 332 00\n\nGislaved, Box 34. Hagag 7. Tel\n0371-112 55\n\nVerksamhet: Tillverkning av\nspecialmaskiner. Legotillverkning\nAntal anställda: 8\nÅrsomsättning: 500 000\nAktiekapital: 50 000\nVerkst dir: Ing Roland Bemving\nEtableringsår: 1969.\n\nSKOGSMATERIEL AB\n\nPnr 102 25\n\nStockholm 12, Sankt Eriksg 20. Box\n12199. Tel 08-2208 90. Postgiro\n55553. Tga Skogsmateriel.\nTelex 1407 SSR S\nVerksamhet: Säljer\nskogsförnödenheter i detalj o parti\nAntal anställda: 13\nÅrsomsättning: 6000 000\nAktiekapital: 50 000\nDisp: Håkan Petrén\nEtableringsår: 1926\nOmbildat till aktiebolag 1952.\nNamnändring 1967.\n\nSKOGSTORPS BOBIN AB\n\nPnr 382 00\n\nNybro, Postl 5200.Tel 0480-530 35.\nBankgiro 661-9522. Postgiro\n393821-4\n\nVerksamhet: Tillverkar handtag för\nverktyg, dörrhandtag,\nmöbelknoppar, hemslöjdsartiklar, ljusstakar,\nschackspelpjäser, leksaksdetaljer\netc, trävita o lackerade\nAntal anställda: 10\nAktiekapital: 75 000\nVerkst dir: Gustaf Jonsson\nÖvrig chef: Fabr Gunnar Andersson\nEtableringsår: 1942.\n\nSKOGSTROM &amp; JOHANSSON\nBIL AB\n\nPnr 351 03\n\nVäxjö 1, Box 30. Ringv 7. Tel\n0470-13455, 12979. Bankgiro\n668-1241. Postgiro 342983-4\nVerksamhet: Återförsäljare för\nMercedes Benz, Audi o Simca\n.Antal anställda: 31\nÅrsomsättning: 9 351 800\nAktiekapital: 100 000\nVerkst dir: Hilmer Johansson\nEtableringsår: 1950.\n\nSUM\n\nMalmö C, Borrg 27 B. Tel\n040-9312 03\n\nJohanneshov, Märgv 15-19. Tel\n08-59 22 78\n\nAktiekapital: 275 000\nVerkst dir: Ingvar Eriksson\nEtableringsår: 1938\nKommissionärsbolag för AB\nCentrava, Stockholm.\n\nSUMEX AB\n\nPnr 41122\n\nGöteborg, Husarg 22. Tel\n031-112011, 18 4279. Postgiro 721564.\nTga Sumex\n\nVerksamhet: Export,\nexportkonsultation\n\nAntal anställda: 5\n\nVerkst dir: Ing Ake E Andréasson\n\nEtableringsår: 1969.\n\nSUNCO, AB\n\nse Astra-Wallco AB.\n\nSUNDS AB\n\nPnr 85101\n\nSundsvall 1, Pack. Huvudkontor: Tel\n060-67 2 00.Bankgiro 77-4381.\nPostgiro 392800. Telex 71053. Tga\nSunds\n\nVerksamhet: Tillverkar i\nSundsbruk: maskinell utrustning för\ncellulosa-, pappers-, board-,\nviskos- o stålindustrin. Vid\nEMBA-avdelningen i Örebro tillverkas\nmaskiner för wellpappindustrin,\nförpackningsmaskiner o\nplast-maskiner\n\nEmbaavdelningen: 700 02 Örebro 2,\nBox 2067. Tel 019-12 49 20.\nBankgiro 61-5406. Postgiro 336576.\nTelex 73301. Tga Emba, Örebro.\nPlatschef: Stig Carlsson\nFörsäljning:\n\nWellpappmaskiner: Hans Ekbom\nFörpackning o plast: Martin Holm\nVarunamn: Emba, Sund\nAntal anställda: 825\nÅrsomsättning: 125 000 000\nAktiekapital: 10 000 000\nStyrelse: Eije Mossberg (ordf),\nJan-Eric Bladh, Rune Hellerquist,\nBertil Schèle\n\nVerkst dir: Jan-Eric Bladh\nEkonomichef: Inge Nises\nPersonalchef: Ulf Sundh\nMarknadschef: Dir Erik Sjunnesson\nExportchef: Cvering Stig Almroth\nFörsäljning Norden: Försäljn-chef\nSten Kjellberg\nPlatschef i Sundsvall: Disp\nLennart Edström\nEtableringsår. 1868\nDotterbolag till Svenska Cellulosa\nAB, Sundsvall.\n\nSUNDAHLS MASKINAFFÄR AB\n\nPnr 352 46\n\nVäxjö, Mörners v 108. Tel\n0470-26045. Bankgiro 668-1365. Postgiro\n473490-1\n\nVerksamhet: Säljer traktorer,\nskogs-o industrimaskiner, skördetröskor\n.Antal anställda: 28\nÅrsomsättning: 5 455 000\nAktiekapital: 100 000\nVerkst dir: Karl Sundahl\nEtableringsår: 1960.",
    "structured": {
        "1": {
            "company_name": "mb-produkter ab",
            "address": "Mullsjö, Furudal",
            "phone_number": "0392-104 70, 104 02",
            "bank_details": {
                "bankgiro": "549-1386",
                "postgiro": "119402-6"
            },
            "activity": "Tillverkar högtrycks-oljebrännare o oljefilter",
            "employees": 20,
            "annual_turnover": 3000000,
            "key_personnel": [
                {
                    "name": "Fabr Olle Wernald",
                    "position": "Chef"
                }
            ],
            "establishment_year": 1953
        },
        "2": {
            "company_name": "SUNEX SÄKERHETSGLAS AB",
            "address": "LysekU, Box 35",
            "phone_number": "0523-13010",
            "bank_details": {
                "bankgiro": "235-2086",
                "postgiro": "54404-9"
            },
            "activity": "Glasförädlingsindustri. Tillverkar härdat säkerhetsglas",
            "employees": 125,
            "annual_turnover": 18000000,
            "capital": 59500,
            "key_personnel": [
                {
                    "name": "Patrich Furlong",
                    "position": "Verkst dir"
                }
            ],
            "establishment_year": 1932
        },
        "3": {
            "company_name": "SUTAB, AB",
            "address": "Bromma 7, Dr Abrahams v 53",
            "phone_number": "08-37 52 00, 37 89 00",
            "bank_details": {
                "bankgiro": "560-5670",
                "postgiro": "170085-5"
            },
            "activity": "Geodesi, geoteknik",
            "employees": 12,
            "annual_turnover": 900000,
            "capital": 5000,
            "key_personnel": [
                {
                    "name": "Civiling Ingvar Höök",
                    "position": "Verkst dir"
                }
            ],
            "establishment_year": 1962
        },
        "4": {
            "company_name": "SPORRONG PRESENTER AB",
            "address": "Stockholm, Kungsg 17",
            "phone_number": "08-22 56 60",
            "bank_details": {
                "bankgiro": "41-1405",
                "postgiro": "1405"
            },
            "activity": "Försäljning av exklusiva presenter till allmänheten via egen butik o till företag, organisationer, institutioner o vissa detaljister via leveransavdelning",
            "employees": 10,
            "key_personnel": [
                {
                    "name": "Disp Hans Lennig",
                    "position": "Chef"
                }
            ],
            "establishment_year": 1969
        },
        "5": {
            "company_name": "LEKHAMMAR ARKITEKT. KONTOR AB, BENGT",
            "address": "Sundsvall, Storg 32",
            "phone_number": "060-15 05 85",
            "bank_details": {
                "bankgiro": "180-0580",
                "postgiro": "393798-4"
            },
            "activity": "Arkitektrörelse",
            "employees": 13,
            "key_personnel": [
                {
                    "name": "Ark SAR Bengt Lekhammar",
                    "position": "Verkst dir"
                }
            ],
            "establishment_year": 1949
        },
        "6": {
            "company_name": "DAL DAHLBERG & CO, TRYCKERI AB",
            "address": "Stockholm 20, Hammarby Fabriksv 29-31",
            "phone_number": "08-44 07 00",
            "bank_details": {
                "bankgiro": "73-3802",
                "postgiro": "151880"
            },
            "activity": "Boktryck, offset o reklam",
            "capital": 75000,
            "key_personnel": [
                {
                    "name": "Gustav Dahlberg",
                    "position": "Verkst dir"
                }
            ],
            "establishment_year": 1937
        },
        "7": {
            "company_name": "DAHLBERGS GROSSHANDELS AB, EDE- BOLAGET ERIK",
            "address": "Sundsvall 1, Box 65",
            "phone_number": "060-11 12 13, 11 34 54",
            "bank_details": {
                "bankgiro": "180-0366",
                "postgiro": "86949-5"
            },
            "activity": "Säljer livsmedel engros för bl a storkök, även djupfrysta. Specialitet: konfektyrer",
            "employees": 15,
            "annual_turnover": 13000000,
            "capital": 200000,
            "key_personnel": [
                {
                    "name": "Erik Dahlberg",
                    "position": "Verkst dir"
                },
                {
                    "name": "Carl-Erik Dahlberg",
                    "position": "V verkst dir"
                }
            ],
            "establishment_year": 1892
        },
        "8": {
            "company_name": "INDUSTRIKREDIT, AB",
            "address": "Stockholm O, Strandv 5 A",
            "phone_number": "08-63 0880",
            "bank_details": {
                "bankgiro": "845-5172",
                "postgiro": "159346-6"
            },
            "activity": "Kreditgivning",
            "capital": 16000000,
            "key_personnel": [
                {
                    "name": "Carl-Oscar Olkrantz",
                    "position": "Verkst dir"
                }
            ],
            "establishment_year": 1934
        },
        "9": {
            "company_name": "INDUSTRI LAGRET KINNA AB",
            "address": "Kinna l.Box 118",
            "phone_number": "0320-106 25",
            "postgiro": "281105",
            "activity": "Glas, porslin, leksaker engros",
            "employees": 17,
            "key_personnel": [
                {
                    "name": "Roland Larsson",
                    "position": "Firmatecknare"
                },
                {
                    "name": "Lennart Wigéll",
                    "position": "Firmatecknare"
                }
            ],
            "establishment_year": 1960
        },
        "10": {
            "company_name": "BERNTS INDUSTRIER",
            "address": "Ulvåker",
            "phone_number": "0500-601 03",
            "bank_details": {
                "bankgiro": "364-9613",
                "postgiro": "343253-1"
            },
            "activity": "Tillverkar köks- o matbord, soff-, hörn- o lampbord",
            "annual_turnover": 900000,
            "key_personnel": [
                {
                    "name": "Fabr Bernt Degervik",
                    "position": "Chef"
                }
            ]
        },
        "11": {
            "company_name": "BERNVINGS VERKSTADS AB",
            "address": "Gislaved, Box 34, Hagag 7",
            "phone_number": "0371-112 55",
            "activity": "Tillverkning av specialmaskiner. Legotillverkning",
            "employees": 8,
            "annual_turnover": 500000,
            "capital": 50000,
            "key_personnel": [
                {
                    "name": "Ing Roland Bemving",
                    "position": "Verkst dir"
                }
            ],
            "establishment_year": 1969
        },
        "12": {
            "company_name": "SKOGSMATERIEL AB",
            "address": "Stockholm 12, Sankt Eriksg 20, Box 12199",
            "phone_number": "08-2208 90",
            "postgiro": "55553",
            "activity": "Säljer skogsförnödenheter i detalj o parti",
            "employees": 13,
            "annual_turnover": 6000000,
            "capital": 50000,
            "key_personnel": [
                {
                    "name": "Håkan Petrén",
                    "position": "Disp"
                }
            ],
            "establishment_year": 1926,
            "name_change_year": 1967
        },
        "13": {
            "company_name": "SKOGSTORPS BOBIN AB",
            "address": "Nybro, Postl 5200",
            "phone_number": "0480-530 35",
            "bank_details": {
                "bankgiro": "661-9522",
                "postgiro": "393821-4"
            },
            "activity": "Tillverkar handtag för verktyg, dörrhandtag, möbelknoppar, hemslöjdsartiklar, ljusstakar, schackspelpjäser, leksaksdetaljer etc, trävita o lackerade",
            "employees": 10,
            "capital": 75000,
            "key_personnel": [
                {
                    "name": "Gustaf Jonsson",
                    "position": "Verkst dir"
                },
                {
                    "name": "Gunnar Andersson",
                    "position": "Övrig chef"
                }
            ],
            "establishment_year": 1942
        },
        "14": {
            "company_name": "SKOGSTROM & JOHANSSON BIL AB",
            "address": "Växjö 1, Box 30, Ringv 7",
            "phone_number": "0470-13455, 12979",
            "bank_details": {
                "bankgiro": "668-1241",
                "postgiro": "342983-4"
            },
            "activity": "Återförsäljare för Mercedes Benz, Audi o Simca",
            "employees": 31,
            "annual_turnover": 9351800,
            "capital": 100000,
            "key_personnel": [
                {
                    "name": "Hilmer Johansson",
                    "position": "Verkst dir"
                }
            ],
            "establishment_year": 1950
        },
        "15": {
            "company_name": "SUM",
            "address": "Malmö C, Borrg 27 B",
            "phone_number": "040-9312 03"
        },
        "16": {
            "company_name": "SUM",
            "address": "Johanneshov, Märgv 15-19",
            "phone_number": "08-59 22 78",
            "capital": 275000,
            "key_personnel": [
                {
                    "name": "Ingvar Eriksson",
                    "position": "Verkst dir"
                }
            ],
            "establishment_year": 1938
        },
        "17": {
            "company_name": "SUMEX AB",
            "address": "Göteborg, Husarg 22",
            "phone_number": "031-112011, 18 4279",
            "postgiro": "721564",
            "activity": "Export, exportkonsultation",
            "employees": 5,
            "key_personnel": [
                {
                    "name": "Ing Ake E Andréasson",
                    "position": "Verkst dir"
                }
            ],
            "establishment_year": 1969
        },
        "18": {
            "company_name": "SUNCO, AB",
            "address": "se Astra-Wallco AB."
        },
        "19": {
            "company_name": "SUNDS AB",
            "address": "Sundsvall 1, Pack. Huvudkontor",
            "phone_number": "060-67 2 00",
            "bank_details": {
                "bankgiro": "77-4381",
                "postgiro": "392800"
            },
            "activity": "Tillverkar i Sundsbruk: maskinell utrustning för cellulosa-, pappers-, board-, viskos- o stålindustrin. Vid EMBA-avdelningen i Örebro tillverkas maskiner för wellpappindustrin, förpackningsmaskiner o plast-maskiner",
            "emba_location": "700 02 Örebro 2, Box 2067",
            "emba_phone_number": "019-12 49 20",
            "emba_bank_details": {
                "bankgiro": "61-5406",
                "postgiro": "336576"
            },
            "emba_telex": "73301",
            "employees": 825,
            "annual_turnover": 125000000,
            "capital": 10000000,
            "directors": [
                {
                    "name": "Eije Mossberg",
                    "position": "Ordf"
                },
                {
                    "name": "Jan-Eric Bladh",
                    "position": "Styrelse"
                },
                {
                    "name": "Rune Hellerquist",
                    "position": "Styrelse"
                },
                {
                    "name": "Bertil Schèle",
                    "position": "Styrelse"
                }
            ],
            "executive_directors": [
                {
                    "name": "Stig Carlsson",
                    "position": "Platschef"
                },
                {
                    "name": "Hans Ekbom",
                    "position": "Försäljning"
                },
                {
                    "name": "Martin Holm",
                    "position": "Försäljning"
                }
            ],
            "establishment_year": 1868,
            "parent_company": "Svenska Cellulosa AB, Sundsvall"
        },
        "20": {
            "company_name": "SUNDAHLS MASKINAFFÄR AB",
            "address": "Växjö, Mörners v 108",
            "phone_number": "0470-26045",
            "bank_details": {
                "bankgiro": "668-1365",
                "postgiro": "473490-1"
            },
            "activity": "Säljer traktorer, skogs-o industrimaskiner, skördetröskor",
            "employees": 28,
            "annual_turnover": 5455000,
            "capital": 100000,
            "key_personnel": [
                {
                    "name": "Karl Sundahl",
                    "position": "Verkst dir"
                }
            ],
            "establishment_year": 1960
        }
    }
}