{
    "original": "HEYCO AB\n\nPnr 102 45\n\nStockholm 5, Nybrog 74. Box 5239.\nTel 08-63 52 35. Bankgiro 446-6603.\nPostgiro 54471-8. Tga Kamasagent.\nTelex 17158 KAM ASA S\nVerksamhet: Import o\nengrosför-säljning av maskiner o verktyg\nAntal anställda: 22\nAktiekapital: 100 000\nVerkst dir: Z J Kamasa\nEtableringsår: 1952.\n\nROC\n\nAktiekapital: 1000 000\nVerkst dir: Ambjörn de Carro\nEtableringsår: 1922.\n\nJACOBSON &amp; GERLE, AB\n\nPnr 402 32\n\nGöteborg, Andréeg 20. Tel\n031-1245 50. Bankgiro 508-7689.\nPostgiro 25585-1. Tga Leopold\nVerksamhet: Importerar o säljer\nsill o konserver\nAktiekapital: 280 000\nVeikst dir: Fritiof Wallström\nEtableringsår: 1890.\n\nJAKOBSSONS SMIDES- &amp;\nBYGGNADSFIRMA AB\n\nPnr 730 30\n\nKolsva, Odensviv 34. Tel\n0221-50289, 504 40. Bankgiro 62-8911.\nPostgiro 396097\n\nVerksamhet: Byggnadssmiden,\noljetankar o svetsningar\nAntal anställda: 10\nÅrsomsättning: 500 000\nAktiekapital: 15 000\nVeikst dir: Gösta Jakobsson\nEtableringsår: 1947.\n\nJAKOBSSON &amp; SVENSK,\nBYGGNADS AB\n\nPnr 82401\n\nHudiksvall 1. Tomteg 9. Box 160.\nTel 0650-150 45. Bankgiro\n234-8092. Postgiro 26720-3\nVerksamhet: Byggnadsrörelse\nAntal anställda: 54\nÅrsomsättning: 5 800 000\nAktiekapital: 20000\nStyrelse: Byggmäst Karl Jakobsson\n(ordf), byggmäst Arthur Svensk\nVerkst dir: Byggmäst Arthur Svensk\nEtableringsår: 1959.\n\nKON\n\nAktiekapital: 7 500 000\n\nVerkst dir: Karl Gunnar Skottsborg\n\nEtableringsår: 1917.\n\nKONFEKTIONS KOMPANIET\nAB\n\nPnr 280 40\n\nSkånes Fagerhult. Tel 0433-302 60\nVerksamhet: Tillverkar kostymer,\njackets o byxor\nAntal anställda: 300\nAktiekapital: 1 200 000\nDotterbolag till Junex Konfektions\nAB, Huskvarna.\n\nKONFEKTIONS.\n\nse i övrigt resp namn.\n\nKONFEKTIONSDETALJER, AB\n\nPnr 64100\n\nKatrineholm, Box 144. Tel\n0150-161 40. Tga Kodeta\nVerksamhet: Tillverkar\naxelvaddar, underkragsmaterial o band\nAntal anställda: 100\nÅrsomsättning: 3 000 000\nAktiekapital: 100 000\nVerkst dir: N J Jonsson\nEtableringsår: 1938.\n\nINA NÅLLAGER AB\n\nPnr 18107\n\nLidingö 7, Box 745. Kosterv 3. Tel\n08-767 03 95. Bankgiro 370-0291.\nPostgiro 30620-9. Tga Inanalen.\nTelex 17432\n\nVaksamhet: Konsulter o teknisk\nrådgivning. Återförsäljare av\nnållager, speciallager, rullager\nVarunamn: INA, Elges\nAntal anställda: 7\nÅrsomsättning: 600 000\nAktiekapital: 5 000\nStyrelseordf: Prof Folke Blomberg\nChef: Overing Mihkel Mathiesen\nEtableringsår: 1968\nDotterbolag till Industriewerk\nSchaeffler oHG, Herzogenaurach,\nVästtyskland.\n\nINBRI, AB\n\nPnr 11446\n\nStockholm. Grev Tureg 10. Tel\n08-110615, 10 59 80. Bankgiro\n727-0010. Postgiro 2817-5. Tga Kolibri.\nTelex 1607\n\nVeiksamhet: Säljer kol o koks\nAktiekapital: 100 000\nVerkst dir: Hugo Nilsson\nEtableringsår: 1936.\n\nBJURKLINT AB, BERNT\n\nPnr 31040\n\nHarplinge. Tel 035-501 96, 50046.\nBankgiro 431-4209. Postgiro\n368346-3\n\nVerksamhet: Säljer sylt, saft o\nmarmelad engros samt specialartiklar\nför stor kök o bagerier\nAntal anställda: 6\nÅrsomsättning: 1300 000\nAktiekapital: 10 000\nVerkst dir: Bernt Bjurklint\nEtableringsår: 1942\nOmbildat till aktiebolag 1960.\n\nBJURMAN &amp; CO AB\n\nPnr 21612\n\nMalmö, Strand g 50. Tel\n040-16 00 60. Bankgiro 641-3116.\nPostgiro 147625-8. Tga Bjurman.\nTelex 3125\n\nVerksamhet: Bruksagenter. Säljer\nkemikalier o råvaror till industrin\nAktiekapital: 100 000\nStyrelse: Adv Ake Wettermark(ordf),\nkonsul Torsten Bjurman, fru\nGudrun Bjurman, dir Olle Westerlund\nVerkst dir: Konsul Torsten\nBjurman\n\nEtableringsår: 1934.\n\nBRÄCKE EMBALLAGE AB\n\nPnr 840 60\n\nBräcke, Box 88. Tel 0693-105 00.\nBankgiro 370-4301. Postgiro\n583768-7\n\nVerksamhet: Tillverkar olika slags\nskyddsemballage av vulkanfiber,\nplast, plastfolie, nylon, latexbelagt\npapper, board o trä\nVarunamn: BEAB\nAntal anstäUda: 80\nÅrsomsättning: 6 000 000\nAktiekapital: 80 000\n\nStyrelse: Fru Ingrid Thorsman\n(ordf), kamrer Rolf Johanson, dir\nCurt Thorsman\nVerkst dir: Curt Thorsman\nEtableringsår: 1961.\n\nB RANDSTRÖM,\nTEXTILAGENTUR KURT A\n\nPnr 11143\n\nStockholm, Norrlandsg 22. Tel\n08-210319,10 00 39. Bankgiro 57-6893\nPostgiro 554169-3. Tga Kabtextil\nVerksamhet: Representant för\nutländska fabrikanter i hemtextilier\nEtableringsår: 1957.\n\nSKOGAHOLMS BRUD, AB\n\nPnr 630 05\n\nEskilstuna 5, Hejarg 6. Box 5025.\nTel 016-13 7510. Bankgiro 60-4405.\nPostgiro 398660\n\nVerksamhet: Tillverkar mjukt\nmatbröd, kaffebröd o småbröd\nAntal anställda: 1 200\nÅrsomsättning: 100 000 000\nAktiekapital: 2 000 000\nVerkst dir: Knut Eriksson\nEtableringsår: 1926.\n\nSVE\n\nFilialer: Eskilstuna, Falun, Gävle,\nGöteborg, Jönköping, Kalmar,\nKarlstad, Luleå, Malmö,\nNorrköping, Skövde, Stockholm,\nSundsvall, Uddevalla, Umeå, Uppsala,\nVästerås, Växjö o Örebro\nVerkstäder: Jönköping, Växjö,\nSöderköping, Järna o Holmsund\nAntal anställda: 3 900\nÅrsomsättning: 316 000 000\nAktiekapital: 60 000 000\nStyrelse: Dir Karl Nilsson (ordf),\ntekn dr Ake T Vrethem, dir\nKurt-Allan Belfrage, dir Olof Leffler,\ndir Bengt Berg, dir Göran\nStarbäck (suppl)\nVerkst dir: Bengt Berg\nV verkst dinn Göran Starbäck,\nLennart Malmort, Bertil\nDanielsson, Bengt Ake Larsson\nEtableringsår: 1920.\n\nPHA\n\n0150-100 58, 10059. Bankgiro\n363-9036. Postgiro 11226-8\nVerksamhet: Kommissionär för\nSvenska Bokförläggareföreningen\nAktiekapital: 20 000\nVerkst din Ake Hjalmarson\nEtableringsår: 1902.",
    "structured": {
        "1": {
            "company_name": "HEYCO AB",
            "pnr": "102 45",
            "address": "Stockholm 5, Nybrog 74. Box 5239.",
            "phone_number": "08-63 52 35",
            "bank_details": {
                "bankgiro": "446-6603",
                "postgiro": "54471-8"
            },
            "activity": "Import o engrosför-säljning av maskiner o verktyg",
            "employees": 22,
            "capital": 100000,
            "key_personnel": [
                {
                    "name": "Z J Kamasa",
                    "position": "Verkst dir"
                }
            ],
            "establishment_year": 1952
        },
        "2": {
            "company_name": "ROC",
            "capital": 1000000,
            "key_personnel": [
                {
                    "name": "Ambjörn de Carro",
                    "position": "Verkst dir"
                }
            ],
            "establishment_year": 1922
        },
        "3": {
            "company_name": "JACOBSON & GERLE, AB",
            "pnr": "402 32",
            "address": "Göteborg, Andréeg 20.",
            "phone_number": "031-1245 50",
            "bank_details": {
                "bankgiro": "508-7689",
                "postgiro": "25585-1"
            },
            "activity": "Importerar o säljer sill o konserver",
            "capital": 280000,
            "key_personnel": [
                {
                    "name": "Fritiof Wallström",
                    "position": "Veikst dir"
                }
            ],
            "establishment_year": 1890
        },
        "4": {
            "company_name": "JAKOBSSONS SMIDES- & BYGGNADSFIRMA AB",
            "pnr": "730 30",
            "address": "Kolsva, Odensviv 34.",
            "phone_number": "0221-50289, 504 40",
            "bank_details": {
                "bankgiro": "62-8911",
                "postgiro": "396097"
            },
            "activity": "Byggnadssmiden, oljetankar o svetsningar",
            "employees": 10,
            "annual_turnover": 500000,
            "capital": 15000,
            "key_personnel": [
                {
                    "name": "Gösta Jakobsson",
                    "position": "Veikst dir"
                }
            ],
            "establishment_year": 1947
        },
        "5": {
            "company_name": "JAKOBSSON & SVENSK, BYGGNADS AB",
            "pnr": "82401",
            "address": "Hudiksvall 1. Tomteg 9. Box 160.",
            "phone_number": "0650-150 45",
            "bank_details": {
                "bankgiro": "234-8092",
                "postgiro": "26720-3"
            },
            "activity": "Byggnadsrörelse",
            "employees": 54,
            "annual_turnover": 5800000,
            "capital": 20000,
            "key_personnel": [
                {
                    "name": "Byggmäst Karl Jakobsson",
                    "position": "Styrelse(ordf)"
                },
                {
                    "name": "Byggmäst Arthur Svensk",
                    "position": "Verkst dir"
                }
            ],
            "establishment_year": 1959
        },
        "6": {
            "company_name": "KON",
            "capital": 7500000,
            "key_personnel": [
                {
                    "name": "Karl Gunnar Skottsborg",
                    "position": "Verkst dir"
                }
            ],
            "establishment_year": 1917
        },
        "7": {
            "company_name": "KONFEKTIONS KOMPANIET AB",
            "pnr": "280 40",
            "address": "Skånes Fagerhult.",
            "phone_number": "0433-302 60",
            "activity": "Tillverkar kostymer, jackets o byxor",
            "employees": 300,
            "capital": 1200000,
            "establishment_year": "Dotterbolag till Junex Konfektions AB, Huskvarna."
        },
        "8": {
            "company_name": "KONFEKTIONSDETALJER, AB",
            "pnr": "64100",
            "address": "Katrineholm, Box 144.",
            "phone_number": "0150-161 40",
            "activity": "Tillverkar axelvaddar, underkragsmaterial o band",
            "employees": 100,
            "annual_turnover": 3000000,
            "capital": 100000,
            "key_personnel": [
                {
                    "name": "N J Jonsson",
                    "position": "Verkst dir"
                }
            ],
            "establishment_year": 1938
        },
        "9": {
            "company_name": "INA NÅLLAGER AB",
            "pnr": "18107",
            "address": "Lidingö 7, Box 745. Kosterv 3.",
            "phone_number": "08-767 03 95",
            "bank_details": {
                "bankgiro": "370-0291",
                "postgiro": "30620-9"
            },
            "activity": "Konsulter o teknisk rådgivning. Återförsäljare av nållager, speciallager, rullager",
            "varunamn": "INA, Elges",
            "employees": 7,
            "annual_turnover": 600000,
            "capital": 5000,
            "key_personnel": [
                {
                    "name": "Prof Folke Blomberg",
                    "position": "Styrelseordf"
                },
                {
                    "name": "Overing Mihkel Mathiesen",
                    "position": "Chef"
                }
            ],
            "establishment_year": 1968,
            "dotterbolag": "Dotterbolag till Industriewerk Schaeffler oHG, Herzogenaurach, Västtyskland."
        },
        "10": {
            "company_name": "INBRI, AB",
            "pnr": "11446",
            "address": "Stockholm. Grev Tureg 10.",
            "phone_number": "08-110615, 10 59 80",
            "bank_details": {
                "bankgiro": "727-0010",
                "postgiro": "2817-5"
            },
            "activity": "Säljer kol o koks",
            "capital": 100000,
            "key_personnel": [
                {
                    "name": "Hugo Nilsson",
                    "position": "Verkst dir"
                }
            ],
            "establishment_year": 1936
        },
        "11": {
            "company_name": "BJURKLINT AB, BERNT",
            "pnr": "31040",
            "address": "Harplinge.",
            "phone_number": "035-501 96, 50046",
            "bank_details": {
                "bankgiro": "431-4209",
                "postgiro": "368346-3"
            },
            "activity": "Säljer sylt, saft o marmelad engros samt specialartiklar för stor kök o bagerier",
            "employees": 6,
            "annual_turnover": 1300000,
            "capital": 10000,
            "key_personnel": [
                {
                    "name": "Bernt Bjurklint",
                    "position": "Verkst dir"
                }
            ],
            "establishment_year": "Ombildat till aktiebolag 1960."
        },
        "12": {
            "company_name": "BJURMAN & CO AB",
            "pnr": "21612",
            "address": "Malmö, Strand g 50.",
            "phone_number": "040-16 00 60",
            "bank_details": {
                "bankgiro": "641-3116",
                "postgiro": "147625-8"
            },
            "activity": "Bruksagenter. Säljer kemikalier o råvaror till industrin",
            "capital": 100000,
            "key_personnel": [
                {
                    "name": "Dir Torsten Bjurman",
                    "position": "Verkst dir"
                }
            ],
            "establishment_year": 1934
        },
        "13": {
            "company_name": "BRÄCKE EMBALLAGE AB",
            "pnr": "840 60",
            "address": "Bräcke, Box 88.",
            "phone_number": "0693-105 00",
            "bank_details": {
                "bankgiro": "370-4301",
                "postgiro": "583768-7"
            },
            "activity": "Tillverkar olika slags skyddsemballage av vulkanfiber, plast, plastfolie, nylon, latexbelagt papper, board o trä",
            "varunamn": "BEAB",
            "employees": 80,
            "annual_turnover": 6000000,
            "capital": 80000,
            "key_personnel": [
                {
                    "name": "Fru Ingrid Thorsman",
                    "position": "Styrelse(ordf)"
                },
                {
                    "name": "Dir Curt Thorsman",
                    "position": "Verkst dir"
                }
            ],
            "establishment_year": 1961
        },
        "14": {
            "company_name": "BRÄCKE EMBALLAGE AB",
            "pnr": "840 60",
            "address": "Bräcke, Box 88.",
            "phone_number": "0693-105 00",
            "bank_details": {
                "bankgiro": "370-4301",
                "postgiro": "583768-7"
            },
            "activity": "Tillverkar olika slags skyddsemballage av vulkanfiber, plast, plastfolie, nylon, latexbelagt papper, board o trä",
            "varunamn": "BEAB",
            "employees": 80,
            "annual_turnover": 6000000,
            "capital": 80000,
            "key_personnel": [
                {
                    "name": "Fru Ingrid Thorsman",
                    "position": "Styrelse(ordf)"
                },
                {
                    "name": "Dir Curt Thorsman",
                    "position": "Verkst dir"
                }
            ],
            "establishment_year": 1961
        },
        "15": {
            "company_name": "B RANDSTRÖM, TEXTILAGENTUR KURT A",
            "pnr": "11143",
            "address": "Stockholm, Norrlandsg 22.",
            "phone_number": "08-210319,10 00 39",
            "bank_details": {
                "bankgiro": "57-6893",
                "postgiro": "554169-3"
            },
            "activity": "Representant för utländska fabrikanter i hemtextilier",
            "establishment_year": 1957
        },
        "16": {
            "company_name": "SKOGAHOLMS BRUD, AB",
            "pnr": "630 05",
            "address": "Eskilstuna 5, Hejarg 6. Box 5025.",
            "phone_number": "016-13 7510",
            "bank_details": {
                "bankgiro": "60-4405",
                "postgiro": "398660"
            },
            "activity": "Tillverkar mjukt matbröd, kaffebröd o småbröd",
            "employees": 1200,
            "annual_turnover": 100000000,
            "capital": 2000000,
            "key_personnel": [
                {
                    "name": "Knut Eriksson",
                    "position": "Verkst dir"
                }
            ],
            "establishment_year": 1926
        },
        "17": {
            "company_name": "SVE",
            "filialer": "Eskilstuna, Falun, Gävle, Göteborg, Jönköping, Kalmar, Karlstad, Luleå, Malmö, Norrköping, Skövde, Stockholm, Sundsvall, Uddevalla, Umeå, Uppsala, Västerås, Växjö o Örebro",
            "verkstäder": "Jönköping, Växjö, Söderköping, Järna o Holmsund",
            "employees": 3900,
            "annual_turnover": 316000000,
            "capital": 60000000,
            "key_personnel": [
                {
                    "name": "Karl Nilsson",
                    "position": "Styrelse(ordf)"
                },
                {
                    "name": "Ake T Vrethem",
                    "position": "Tekn dr"
                },
                {
                    "name": "Kurt-Allan Belfrage",
                    "position": "Dir"
                },
                {
                    "name": "Olof Leffler",
                    "position": "Dir"
                },
                {
                    "name": "Bengt Berg",
                    "position": "Dir"
                },
                {
                    "name": "Göran Starbäck",
                    "position": "Dir (suppl)"
                }
            ],
            "verkst_dir": "Bengt Berg, Göran Starbäck, Lennart Malmort, Bertil Danielsson, Bengt Ake Larsson",
            "establishment_year": 1920
        },
        "18": {
            "company_name": "PHA",
            "phone_number": "0150-100 58, 10059",
            "bank_details": {
                "bankgiro": "363-9036",
                "postgiro": "11226-8"
            },
            "activity": "Kommissionär för Svenska Bokförläggareföreningen",
            "capital": 20000,
            "key_personnel": [
                {
                    "name": "Ake Hjalmarson",
                    "position": "Verkst din"
                }
            ],
            "establishment_year": 1902
        }
    }
}