{
    "original": "HEL\n\nVeiksamhet: Säljer trävaror,\nbyggnadsmaterial o betongvaror\nChefer: J R Hedström, Ragnar\nBoije.\n\nHEDSTRDMS MOTOR AB\n\nPnr 75103\n\nUppsala 1, Bergsbrunnag 28. Box\n57. Tel 018-14 9190. Bankgiro\n23-0126. Postgiro 339144. Tga\nHed-strommotor. Telex 7497\nVerksamhet: Generalagent o\nimportör för lastvagnar av märket\nHanomag/Henschel\nAntal anställda: 101\nÅrsomsättning: 40 000 000\nAktiekapital: 1000 000\nStyrelse: Fru Karin Olsson (ordf),\ndir Olle Olsson, herr Per Olsson\nVerkst dir Olle Olssön\nEtableringsår: 1949.\n\nfalkenbergs varv ab\n\nPnr 31100\n\nFalkenberg, Hamnv. Box 89. Tel\n0346-14150. Bankgiro 425-7150.\nPostgiro 320892-3. Tga Falkvarv.\nTelex 38066\n\nVerksamhet: Utför\nfartygsnybyggnader, fartygs- o\nmaskinreparationer samt allmänna\njärnkonstruktioner. Specialitet: Gastankers\nAntal anställda: 225\nVerkst dir: Civiling Valter Nilsson\nEkonomichef: Göran Forster\nRitkontorschef: Einar Andersson\nVarvsing:r: S-E Bogren, O\nMagnusson\n\nInköpschef: Björn Nyman\nEtableringsår: 1947.\n\nLYKA AB\n\nPnr 17108\n\nSolna 8, Törnbacken 8. Box 810.\nTel 08-85 26 45, 85 26 46. Bankgiro\n66-6104. Postgiro 572770. Tga\nInwifus\n\nVerksamhet: Tillverkar o säljer\nkirurgiska o medicinska instrument\nAntal anställda: 10\nÅrsomsättning: 400 000\nAktiekapital: 5 000\nDin Karen Wismar\nEtableringsår: 1967.\n\nPANTBELÄNING, AB\n\nPnr 102 42\n\nStockholm 5, Sibylleg 24. Box 5084.\nTel 08-67 02 00. Postgiro 4624-3\nVerksamhet Varubelåningsrörelse\nAntal anställda: 38\nÅrsomsättning: 44 500 000\nAktiekapital: 550 000\nVerkst dir: Bo A Stålbo\nEtableringsår: 1885.\n\nBO-MARKNAD AB\n\nPnr 200 41\n\nMalmö 8, Box 8067. Per Albin\nHanssons v 40. Tel 040-92 21 10.\nBankgiro 488-2009. Postgiro\n37770-5\n\nVerksamhet: Försäljning av möbler,\nmattor, gardiner, sängkläder,\nhemtextilier o belysningsarmatur\nAntal anställda: 250\nÅrsomsättning: 70 000 000\n(koncernen)\n\nAktiekapital: 500 000\nStyrelse: Dir Sten Ahlberg (ordf),\ndir Jacques Gustavsson, dir Allan\nHedberg, dir Per Arne Nilsson\nVerkst dir: Jacques Gustavsson\n(Stockholm)\n\nMarknadschef: Per Arne Nilsson\nInköpschef: Leif Karlsson\nEkonomichef: Siri Winberg\nEtableringsår: 1967\nDotterbolag: Ahlbergs Möbler AB,\nHedbergs i Vinslöv AB, Per Nilssons\nMöbel AB, Åstorp, Mobilia AB,\nMalmö, Zackrissons Möbel AB,\nMölndal. Ahlbergs affärer finns i\nStockholm, Skärholmen, Sundbyberg,\nVästerås, Örebro, Luleå o\nHelsingborg.\n\nBONA, AB\n\nPnr 212 25\n\nMalmö, Murmansg 128. Tel\n040-93 56 50. Bankgiro 870-1112.\nPostgiro 37792-9. Tga Bona. Telex\n32377\n\nVerksamhet: Lack-, lim- o kemisk\nindustri\n\nAvdelningskontor: 112 29 Stockholm,\nWargentinsg 7. Tel 08-50 7071,,.\n5060 54\t’■ r\n\n41118 Göteborg, Magasinsg 15-17.\nTel 031-137252, 1182 39\nAntal anställda: 50\nÅrsomsättning: 12 000 000\nAktiekapital: 480 000\nVerkst dir: C G Edner\nEtableringsår: 1919.\n\nBONDERSBY\nTRÄFOR-ÄDLINGS AB\n\nPnr 95044\n\nBondersbyn. Tel 0923-27004.\nBankgiro 60-3071. Postgiro 68308\nVerksamhet: Säljer sågade o\nhyvlade trävaror i parti o minut\nAntal anställda: 13\nÅrsomsättning: 600 000\nAktiekapital: 50 000\nVerkst dir: Driftschef John\nHäggström\n\nEtableringsår: 1932.\n\nROBERG AB, TYCHO\n\nPnr 400 20\n\nGöteborg 14, Box 14117. Tel\n031-8106 30. Bankgiro 42-0153. Postgiro\n257988. Tga Roberg.\nTelex 21036 ROBERG S\nVeiksamhet: Tillverkar, säljer o\ninstallerar oljebrännare o\noljeutrustning för större panncentraler,\nsjukhus, skolor, industrier etc\nFilial: 11-3 43 Stockholm, Eugeniav\n3. Tel 08-33 57 01\nVarunamn: Hamworthy, Hauck,\nOertli, Peabody, PU, Tyro\nAntal anställda: 100\nÅrsomsättning: 10000 000\nAktiekapital: 445 000\nVerkst dir: Bertil Lagerberg\nEtableringsår: 1876.\nTillhör Peabody Galron, USA.\n\nROBERGS SPEDITIONS AB,\nTYCHO\n\nPnr 403 20\n\nGöteborg 2, Fack. Packhus plats en\n2. Tel 031-17 06 30. Bankgiro\n42-0420. Postgiro 46400. Tga\nSped-roberg. Telex 2510\nVeiksamhet: Spedition,\ninternationella transporter, flygfrakt\nVerkst dir: Carl Smith\nEtableringsår: 1940.\n\nGRAFISK MEKANIK AB\n\nPnr 414 74\n\nGöteborg, Knipplag 12. Tel\n031-24 88 50. Verkstad o lager: Fotög 11.\nBankgiro 853-0396. Postgiro\n498783-0\n\nVerksamhet: Flyttningar,\nmonteringar o reparationer inom den\ngrafiska branschen. Säljer begagnade\nmaskiner\n\nAntal anstäUda: 6\nÅrsomsättning: 800 000\nAktiekapital: 50000\nVerkst dir: Ing Lennart Lindell\nEtableringsår: 1956.\n\nGRAFISK REKLAM I\nSTOCKHOLM AB\n\nPnr 117 43\n\nStockholm, Årsta Skolgränd 10.\nTel 08-18 8120\n\nVerksamhet: Annons- o\nreklambyrå\n\nAktiekapital: 5 000\nVerkst dir: Per Ollén\nEtableringsår: 1946.\n\nAUTRONICA SVENSKA AB\n\nPnr 42131\n\nVästra Frölunda, Frötallsg 7. Tel\n031-49 03 35. Tga Autronica\nVerksamhet: Kombinerade alarm- o\növervakningsutrustningar\nAktiekapital: 5 000\nVerkst dir: Ing Ivan Ek\nEtableringsår: 1963.\n\nAWA PATENT\n\nPATENTBYRÄN A W ANDERSON\n\nPnr 20122\n\nMalmö 1, Box 226. Bellevuev 46.\nTel 040-716 20. Bankgiro 610-6009.\nPostgiro 37981-8. Tga Awapatent.\nTelex 32407 AWAPAT S\nVarunamn: Awapatent\nAvdelningskontor: 103 81\nStockholm 7, Box 7032. Kungsg 16-18.\nTel 08-10 95 03, 11 95 03. Tga\nAwapatent. Telex 10897 AWAPAT S\nAntal anställda: 115\nChef: Dir Gunnar Hansson\n\nÖvriga chefer: Ing John Wallin, dir\nKarl-Erik Åström, civiling Lars\nGrefberg\n\nEtableringsår: 1897.\n\nAWAB, ANDERSTORPS\nWERKSTADS AB\n\nPnr 330 20\n\nAnderstorp. Tel 0371-16160.\nBankgiro 488-0779. Postgiro 345989-8\n\n/üMB\n\nVerksamhet: Tillverkar\nslang-klämmor, dragna o pressade\nartiklar, tapetklistringsmaskinen Wall\nSpeed, Awab husmodersstol med\ntillbehör, vilstolen Tricombi, elektr\nkamflänselement, campingset,\nhand- o motorgräsklippare\nVerkstadsfilialer: Jönköping. Tel\n036-12 18 85\n\nUrs hult. Tel 0477-205 06\nVarunamn: Awab, Wall Speed\nAktiekapital: 500 000\nVerkst dir: Ingemar Svenningsson\nEtableringsår: 1948.\n\nAVANCE AB,\nINGENIÖRSFIRMAN\n\nPnr 402 22\n\nGöteborg 5, Box 5091. Berzeliig\n13. Tel 031-16 8106. Bankgiro\n362-6496. Postgiro 240095-0.\nTga Avance\n\nVerksamhet: Oljebrännare o\nkontrollapparatur\nAktiekapital: 5 000\nVerkst dir: Per-Olof Ahrman\nEtableringsår: 1944\nOmbildat till aktiebolag 1960.\n\nAVANT, AB\n\nPnr 150 30\n\nMariefred, Stallarholmsv 2. Tel\n0159-112 01. Tga Avant\nVerksamhet: Tillverkar skyltställ,\npresentartiklar, pipställ o tillbehör\nAktiekapital: 150 000\nVerkst dir: A Hultberg\nEtableringsår: 1945.\n\nsy v\n\nsyversenssegelmakeri\nab\n\nPnr 450 43\n\nSmögen, Box 36. Tel 0523-309 75.\nBankgiro 551-0417. Postgiro\n31958-2. Tga Syversen\nVerksamhet: Tillverkar yachtsegel,\ntrålar o sportnät. Skeppshandel\nAntal anställda: 25\nÅrsomsättning: 2 000 000\nAktiekapital: 75 000\nVerkst dir: Ingemar Syversen\nEtableringsår: 1888.\n\nWIKSTRÖM &amp; CO, HERBERT\n\nPnr 16139\n\nBromma, Alviksv 236. Tel 08-\n\n25 46 33. Postgiro 46689. Tga Herb-\n\nwik. Telex 17041\n\nVerksamhet: Export-, import- o\n\nhandelsrörelse\n\nChef: Herbert Wikström\n\nEtableringsår: 1948.",
    "structured": {
        "0": {
            "company_name": "HEDSTRDMS MOTOR AB",
            "pnr": "75103",
            "address": "Uppsala 1, Bergsbrunnag 28, Box 57",
            "phone_number": "018-14 9190",
            "bank_details": {
                "bankgiro": "23-0126",
                "postgiro": "339144"
            },
            "activity": "Säljer trävaror, byggnadsmaterial o betongvaror",
            "employees": 101,
            "annual_turnover": 40000000,
            "capital": 1000000,
            "key_personnel": [
                {
                    "name": "J R Hedström",
                    "position": "Generalagent o importör"
                },
                {
                    "name": "Ragnar Boije",
                    "position": ""
                }
            ],
            "establishment_year": 1949
        },
        "1": {
            "company_name": "falkenbergs varv ab",
            "pnr": "31100",
            "address": "Falkenberg, Hamnv, Box 89",
            "phone_number": "0346-14150",
            "bank_details": {
                "bankgiro": "425-7150",
                "postgiro": "320892-3"
            },
            "activity": "Utför fartygsnybyggnader, fartygs- o maskinreparationer samt allmänna järnkonstruktioner",
            "employees": 225,
            "key_personnel": [
                {
                    "name": "Civiling Valter Nilsson",
                    "position": "Verkst dir"
                },
                {
                    "name": "Göran Forster",
                    "position": "Ekonomichef"
                },
                {
                    "name": "Einar Andersson",
                    "position": "Ritkontorschef"
                },
                {
                    "name": "S-E Bogren",
                    "position": "Varvsing:r"
                },
                {
                    "name": "O Magnusson",
                    "position": "Varvsing:r"
                },
                {
                    "name": "Björn Nyman",
                    "position": "Inköpschef"
                }
            ],
            "establishment_year": 1947
        },
        "2": {
            "company_name": "LYKA AB",
            "pnr": "17108",
            "address": "Solna 8, Törnbacken 8, Box 810",
            "phone_number": "08-85 26 45, 85 26 46",
            "bank_details": {
                "bankgiro": "66-6104",
                "postgiro": "572770"
            },
            "activity": "Tillverkar o säljer kirurgiska o medicinska instrument",
            "employees": 10,
            "annual_turnover": 400000,
            "capital": 5000,
            "key_personnel": [
                {
                    "name": "Karen Wismar",
                    "position": ""
                }
            ],
            "establishment_year": 1967
        },
        "3": {
            "company_name": "PANTBELÄNING, AB",
            "pnr": "102 42",
            "address": "Stockholm 5, Sibylleg 24, Box 5084",
            "phone_number": "08-67 02 00",
            "bank_details": {
                "postgiro": "4624-3"
            },
            "activity": "Varubelåningsrörelse",
            "employees": 38,
            "annual_turnover": 44500000,
            "capital": 550000,
            "key_personnel": [
                {
                    "name": "Bo A Stålbo",
                    "position": "Verkst dir"
                }
            ],
            "establishment_year": 1885
        },
        "4": {
            "company_name": "BO-MARKNAD AB",
            "pnr": "200 41",
            "address": "Malmö 8, Box 8067, Per Albin Hanssons v 40",
            "phone_number": "040-92 21 10",
            "bank_details": {
                "bankgiro": "488-2009",
                "postgiro": "37770-5"
            },
            "activity": "Försäljning av möbler, mattor, gardiner, sängkläder, hemtextilier o belysningsarmatur",
            "employees": 250,
            "annual_turnover": 70000000,
            "capital": 500000,
            "key_personnel": [
                {
                    "name": "Sten Ahlberg",
                    "position": "Styrelseordförande"
                },
                {
                    "name": "Jacques Gustavsson",
                    "position": "Verkst dir"
                },
                {
                    "name": "Per Arne Nilsson",
                    "position": "Marknadschef"
                },
                {
                    "name": "Leif Karlsson",
                    "position": "Inköpschef"
                },
                {
                    "name": "Siri Winberg",
                    "position": "Ekonomichef"
                }
            ],
            "establishment_year": 1967
        },
        "5": {
            "company_name": "BONA, AB",
            "pnr": "212 25",
            "address": "Malmö, Murmansg 128",
            "phone_number": "040-93 56 50",
            "bank_details": {
                "bankgiro": "870-1112",
                "postgiro": "37792-9"
            },
            "activity": "Lack-, lim- o kemisk industri",
            "employees": 50,
            "annual_turnover": 12000000,
            "capital": 480000,
            "key_personnel": [
                {
                    "name": "C G Edner",
                    "position": "Verkst dir"
                }
            ],
            "establishment_year": 1919
        },
        "6": {
            "company_name": "BONDERSBY TRÄFOR-ÄDLINGS AB",
            "pnr": "95044",
            "address": "Bondersbyn",
            "phone_number": "0923-27004",
            "bank_details": {
                "bankgiro": "60-3071",
                "postgiro": "68308"
            },
            "activity": "Säljer sågade o hyvlade trävaror i parti o minut",
            "employees": 13,
            "annual_turnover": 600000,
            "capital": 50000,
            "key_personnel": [
                {
                    "name": "Driftschef John Häggström",
                    "position": "Verkst dir"
                }
            ],
            "establishment_year": 1932
        },
        "7": {
            "company_name": "ROBERG AB, TYCHO",
            "pnr": "400 20",
            "address": "Göteborg 14, Box 14117",
            "phone_number": "031-8106 30",
            "bank_details": {
                "bankgiro": "42-0153",
                "postgiro": "257988"
            },
            "activity": "Tillverkar, säljer o installerar oljebrännare o oljeutrustning för större panncentraler, sjukhus, skolor, industrier etc",
            "employees": 100,
            "annual_turnover": 10000000,
            "capital": 445000,
            "key_personnel": [
                {
                    "name": "Bertil Lagerberg",
                    "position": "Verkst dir"
                }
            ],
            "establishment_year": 1876
        },
        "8": {
            "company_name": "ROBERGS SPEDITIONS AB, TYCHO",
            "pnr": "403 20",
            "address": "Göteborg 2, Fack. Packhus plats en 2",
            "phone_number": "031-17 06 30",
            "bank_details": {
                "bankgiro": "42-0420",
                "postgiro": "46400"
            },
            "activity": "Spedition, internationella transporter, flygfrakt",
            "employees": null,
            "annual_turnover": null,
            "capital": null,
            "key_personnel": [
                {
                    "name": "Carl Smith",
                    "position": "Verkst dir"
                }
            ],
            "establishment_year": 1940
        },
        "9": {
            "company_name": "GRAFISK MEKANIK AB",
            "pnr": "414 74",
            "address": "Göteborg, Knipplag 12",
            "phone_number": "031-24 88 50",
            "bank_details": {
                "bankgiro": "853-0396",
                "postgiro": "498783-0"
            },
            "activity": "Flyttningar, monteringar o reparationer inom den grafiska branschen. Säljer begagnade maskiner",
            "employees": 6,
            "annual_turnover": 800000,
            "capital": 50000,
            "key_personnel": [
                {
                    "name": "Ing Lennart Lindell",
                    "position": "Verkst dir"
                }
            ],
            "establishment_year": 1956
        },
        "10": {
            "company_name": "GRAFISK REKLAM I STOCKHOLM AB",
            "pnr": "117 43",
            "address": "Stockholm, Årsta Skolgränd 10",
            "phone_number": "08-18 8120",
            "activity": "Annons- o reklambyrå",
            "employees": null,
            "annual_turnover": null,
            "capital": 5000,
            "key_personnel": [
                {
                    "name": "Per Ollén",
                    "position": "Verkst dir"
                }
            ],
            "establishment_year": 1946
        },
        "11": {
            "company_name": "AUTRONICA SVENSKA AB",
            "pnr": "42131",
            "address": "Västra Frölunda, Frötallsg 7",
            "phone_number": "031-49 03 35",
            "activity": "Kombinerade alarm- o övervakningsutrustningar",
            "employees": null,
            "annual_turnover": null,
            "capital": 5000,
            "key_personnel": [
                {
                    "name": "Ing Ivan Ek",
                    "position": "Verkst dir"
                }
            ],
            "establishment_year": 1963
        },
        "12": {
            "company_name": "AWA PATENT PATENTBYRÄN A W ANDERSON",
            "pnr": "20122",
            "address": "Malmö 1, Box 226, Bellevuev 46",
            "phone_number": "040-716 20",
            "bank_details": {
                "bankgiro": "610-6009",
                "postgiro": "37981-8"
            },
            "activity": "Patentbyrå",
            "employees": 115,
            "key_personnel": [
                {
                    "name": "Dir Gunnar Hansson",
                    "position": "Chef"
                },
                {
                    "name": "Ing John Wallin",
                    "position": "Övrig chef"
                },
                {
                    "name": "dir Karl-Erik Åström",
                    "position": "Övrig chef"
                },
                {
                    "name": "civiling Lars Grefberg",
                    "position": "Övrig chef"
                }
            ],
            "establishment_year": 1897
        },
        "13": {
            "company_name": "AWAB, ANDERSTORPS WERKSTADS AB",
            "pnr": "330 20",
            "address": "Anderstorp",
            "phone_number": "0371-16160",
            "bank_details": {
                "bankgiro": "488-0779",
                "postgiro": "345989-8"
            },
            "activity": "Tillverkar slangklämmor, dragna o pressade artiklar, tapetklistringsmaskinen Wall Speed, Awab husmodersstol med tillbehör, vilstolen Tricombi, elektr kamflänselement, campingset, hand- o motorgräsklippare",
            "employees": null,
            "annual_turnover": null,
            "capital": 500000,
            "key_personnel": [
                {
                    "name": "Ingemar Svenningsson",
                    "position": "Verkst dir"
                }
            ],
            "establishment_year": 1948
        },
        "14": {
            "company_name": "AVANCE AB, INGENIÖRSFIRMAN",
            "pnr": "402 22",
            "address": "Göteborg 5, Box 5091, Berzeliig 13",
            "phone_number": "031-16 8106",
            "bank_details": {
                "bankgiro": "362-6496",
                "postgiro": "240095-0"
            },
            "activity": "Oljebrännare o kontrollapparatur",
            "employees": null,
            "annual_turnover": null,
            "capital": 5000,
            "key_personnel": [
                {
                    "name": "Per-Olof Ahrman",
                    "position": "Verkst dir"
                }
            ],
            "establishment_year": 1944
        },
        "15": {
            "company_name": "AVANT, AB",
            "pnr": "150 30",
            "address": "Mariefred, Stallarholmsv 2",
            "phone_number": "0159-112 01",
            "activity": "Tillverkar skyltställ, presentartiklar, pipställ o tillbehör",
            "employees": null,
            "annual_turnover": null,
            "capital": 150000,
            "key_personnel": [
                {
                    "name": "A Hultberg",
                    "position": "Verkst dir"
                }
            ],
            "establishment_year": 1945
        },
        "16": {
            "company_name": "SYVERSEN SEGELMAKERI AB",
            "pnr": "450 43",
            "address": "Smögen, Box 36",
            "phone_number": "0523-309 75",
            "bank_details": {
                "bankgiro": "551-0417",
                "postgiro": "31958-2"
            },
            "activity": "Tillverkar yachtsegel, trålar o sportnät. Skeppshandel",
            "employees": 25,
            "annual_turnover": 2000000,
            "capital": 75000,
            "key_personnel": [
                {
                    "name": "Ingemar Syversen",
                    "position": "Verkst dir"
                }
            ],
            "establishment_year": 1888
        },
        "17": {
            "company_name": "WIKSTRÖM & CO, HERBERT",
            "pnr": "16139",
            "address": "Bromma, Alviksv 236",
            "phone_number": "08-25 46 33",
            "bank_details": {
                "postgiro": "46689"
            },
            "activity": "Export-, import- o handelsrörelse",
            "employees": null,
            "annual_turnover": null,
            "capital": null,
            "key_personnel": [
                {
                    "name": "Herbert Wikström",
                    "position": "Chef"
                }
            ],
            "establishment_year": 1948
        }
    }
}