{
    "original": "LOFAMATIC AB\n\nPnr 113 46\n\nStockholm, Vanadisv 24. Tel\n08-24 23 30, 335799. Postgiro\n552281-8\n\nVerksamhet Automatikutrustningar\nför starkström o elektronik\nAntal anställda: 10\nÅrsomsättning: 1000 000\nAktiekapital: 50 000\nVerkst dir. P O Löfgren\nEtableringsån 1968.\n\npark &amp; co, ab\n\nPnr 400 70\n\nGöteborg 9, Polstjärneg 10. Fack.\nTel 031-22 2100. Bankgiro 45-0000.\nPostgiro 41804\n\nVerksamhet: Grossistfirma i rör-,\nvärme- o sanitetstekniska\nbranschen\n\nAktiekapital: 600000\nVerkst dir: Eskil Wiberg\nEtableringsår: 1890.\n\npark hotel ab,\nstockholm\n\nPnr 102 45\n\nStockholm 5, Karlav 43. Box 5255.\nTel 08-22 96 20. Bankgiro 713-4737.\nPostgiro 456810-1. Tga Parkhotel.\nTelex 10666\n\nVeiksamhet: Hotell o restaurang\nVerkst dir: Otto Herzog\nEtableringsår: 1968.\n\nMÖBEL LÄS, AB\n\nPnr 63102\n\nEskilstuna 1, Köpmang 7. Box 92.\nTel 016-13 75 05. Bankgiro\n601-5093. Postgiro 6690-2. Tga\nMöbel-lås\n\nVerksamhet: Tillverkar lås o\nnycklar för möbler, dörrar, inredningar,\nfartyg o kassafack\nVarunamn: Möbellås\nAntal anställda: 31\nÅrsomsättning: 1 500 000\n\nAktiekapital: 75 000\nVerkst din Fru Margareta\nJohansson\n\nFabrikschef: Ing Gunnar Johansson\nEtableringsàr: 1918.\n\nMÖCKELN AB\n\nPnr 343 00\n\nÄlmhult, Box 170. Tel 0476-120 60.\nBankgiro 873-9211. Postgiro\n97908-8. Tga Möckeln.\nTelex 4670 MÖCKELN S\nVerksamhet: Tillverkar grus- o\nste nsorteringsanläg gningar\nAntal anställda: 60\nÅrsomsättning: 8 000 000\nAktiekapital: 223 000\nVerkst dir: Erik Nilsson.\n\nMOCKELNS SÅGVERK, AB\n\nPnr 343 00\n\nÄlmhult, Box 170. Tel 0476-120 60.\nTga Möckeln.\nTelex 4670 MÖCKELN S\nVeiksamhet: Sågverk\nAntal anställda: 45\nÅrsomsättning: 6 000 000\nAktiekapital: 90 000\nVeikst dir: Erik Nilsson\nEtableringsàr 1953.\n\nSEG\n\nSECRETARIAL SERVICE\n\nPnr 21121\n\nMalmö, Västerg 22. Tel 040-30010,\n1135 00. Postgiro 6323 23-2\nVerksamhet: Sekreterartjänst,\növersättningar, trycksaker\nChefer: Disp Sven Welith, fru\nChristina Wulff\nEtableringsår: 1965.\n\nH D F-BOLAGEN AB\n\nPnr 30103\n\nHalmstad l.Köpmansg 23. Box 135.\nTel 035-11 82 20. Bankgiro 42-3534.\nPostgiro 9518. Tga Hadefbol.\nTelex 38048\n\nVerksamhet: Grossist i\njärnmanufaktur, verktyg, hushållsartiklar,\nbadrumsinredningar,\nbyggnadsbeslag, sport, fiske, vapen,\nträdgårdsredskap m m\n\nFabrik: Halmstad. Aug Hansons\nGjuteri. Tel 035-11 92 20. Telex\n38048. Tillverkar gjutgods, pumpar\no rördelar. Verkstadschef: disp B\nBredenfeldt\n\nVarunamn: Black &amp; Decker,\nRe-mington\n\nAntal anställda: 400\nÅrsomsättning: 70 000 000\nAktiekapital: 1800 000\nStyrelse: Överste Evert Cavalli\n(ordf), dir P H Cavalli, civiling\nNils Kjellström, bankdir Ragnar\nSiwers, dir Lare Ågren, disp Sven\nÅgren, disp Per Halberg, adv Hans\nVinge\n\nVerkst dir: Lars Ågren\nV verkst dir: P H Cavalli\nEtableringsår: 1906\nFöretag ingående i HDF-bolagen AB:\nHalmstads Järnvaru AB, Halmstad,\nWilh Denninghoff AB, Mölndal,\nSolna, AB Järnvarufirman HDF,\nMalmö, Fehrlins Handels- &amp;\nFabriks AB, Halmstad, Solna, Malmö,\nMölndal, Aug Hansons Gjuteri,\nHalmstad.\n\nHEBA BYGGNADS AB\n\nPnr 102 52\n\nStockholm 27, Gyllenstiernsg 4.\nBox 27197. Tel 08-60 12 20,\n6015 50. Postgiro 501565\nVerksamhet: Byggnadsrörelse o\nfastighetsförvaltning\nAntal anställda: 26\nÅrsomsättning: 7100 000\nAktiekapital: 1200 000\nVerkst dir: Kåge Holmberg\nEtableringsår. 1952.\n\nTORNBORG &amp; LUNDBERG AB\n\nPnr 102 71\n\nStockholm 9, Arstadalshamnen.\nLiljeholmen. Box 9047. Tel\n08-45 27 00. Postgiro 51240. Telex\n10017. Tga Tornborgs\nVerksamhet: Säljer byggnads- o\nanläggningsmaskiner samt\nmobilkranar\n\nAvdelningskontor: Göteborg H,\nMagnetg 6. Tel 031-235270\n\nLuleå, Spantg 20 (Notviken). Tel\n0920-107 55\n\nMalmö C, Borrg 29. Tel\n040-93 48 60\n\nSundsvall, Bergsg 118. Tel\n060-15 04 00\n\nVarunamn: Ammann, Aveling-Bar-\n\nford, Bucyrus-Erie, Coles,\nInternational Hough, International\nHar-vester, Magni, Ruston-Bucyrus,\nTolu, Torno\nAntal anställda: 366\nÅrsomsättning: 72 000 000\nAktiekapital: 5 800 000\nStyrelse: Ing C L Hesselman(ordf),\ndir L O Haggård, disp E B\nJohanson, häradshövd K-F Pfeiffer, dir\nL Ståhl (suppl)\nVerkst dir: L Ståhl\nEtableringsår: 1882\nOmbildat till aktiebolag 1907.\n\nTORNE AB, SIXTEN\n\nPnr 211 55\n\nMalmö, Amiralsg 6. Tel 040-760 80.\nBankgiro 875-5308. Postgiro\n39132-6. Tga Sitorne.\nTelex 32475 SITORNE S\nVerksamhet: Säljer maskiner o\napparater till livsmedelsindustrin\n(inkl dryckesindustrin), kemiska o\nkem tekn fabriker (inkl kosmetiska\nindustrin) samt farmaceutiska\nindustrin. Utrustningar för interna\ntransporter o emballagehantering\nAntal anställda: 12\nAktiekapital: 100 000\nVerkst dir: Sixten Torne\nEtableringsår: 1935.\n\nINVICTA AB\n\nPnr 402 24\n\nGöteborg 5, Box 5214. Berzeliig 24.\nTel 031-208510. Bankgiro\n848-3588. Postgiro 429200-9. Tga\nInvicta\n\nVeiksamhet: Import o agenturer.\nGeneralagenter för Invicta\nslang-klämmor\n\nVarunamn: Invicta\nAktiekapital: 5 000\nÄgare o chef: Rolf von Bothmer\nEtableringsår: 1963.\n\nI PC INTERNATIONAL\nPUBLISHING CO\n\nPnr 70106\n\nÖrebro 1, Box 404. Karl Johans\ntorg 15. Tel 019-12 3445, 1898 38.\nBankgiro 614-3705. Postgiro\n77226-9\n\nVeiksamhet: Bokförlag\nAntal anstäUda: 4\nÅrsomsättning: 1 800 000\nChef: Bokförl Ake Andersson\nEtableringsår 1956.\n\nFANÈRIMPORTEN AB\n\nPnr 576 00\n\nSävsjö, V Järnvägsg. Box 32. Tel\n0382-113 25. Bankgiro 83-6619.\ngiro 257365. Tga Lindfanér\nVerksamhet: Säljer fanér,\nspånplattor, lamellträ o plywood\nAntal anställda: 10\nÅrsomsättning: 3 200 000\nAktiekapital: 50 000\nVerkst dir: Sven Eklund\nEtableringsår: 1947.\n\nSVENSKA TÄNDSTICKS AB\n\nPnr 551 02\n\nJönköping 1, Box 608. V Storg 18 A.\nTel 036-11 96 4 0. Bankgiro\n140-0761. Postgiro 86 76-9. Tga\nMatchco. Telex 70044\nVerksamhet: Moderbolag i\nSTAB-koncernen, som omfattar ca 100\nforetag i ett 30-tal länder o som är\nverksam inom tändsticks-,\nbyggmaterial-, pappers-,\nförpacknings-o verkstadsbranscherna\nAntal koncemanställda: ca 32 500\n(varav i Sverige 7 600)\nÅrsomsättning 1969: 1 908 900 000\nAktiekapital: 235 000 000\nStyrelse: Ekon dr Jacob Wallenberg\n(ordf), dir Ake Bergqvist, talman\nErik Boheman, dir Holger Crafoord,\ndir Rolf Deinoff, dir Bo Ehrner, dir\nCarl de Geer, bankdir Rudolf\nPfen-ninger, bankdir Lars-Erik\nThun-holm, hovauditör Sune Wetter,\nmr Derek L d’A Willis\nVerkst dir: Rolf Deinoff.\n\nSVENSKA TÄNDSTICKSBO.\nLAGETS FÖRSÄLJNINGS AB\n\nPnr 103 22\n\nStockholm 16, V Trädgårdsg 15.\nBox 16100. Tel 08-22 06 20.\nBankgiro 160-8108, 560-5076. Postgiro\n2004-0. Tga Tändstickor.\nTelex 1454\n\nVerksamhet: Säljer tändstickor\nfrån tändsticksfabriker tillhörande\nAB Jönköping-Vulcan\nAntal anställda: 6\nAktiekapital: 300 000\nStyrelse: Dir Sven Wallgren (ordf),\ndir Nils Fredholm, dir Arne\nHallgren\n\nVerkst dir. Arne Hallgren\nEtableringsår 1919.\n\nANDERSSON &amp; JOHNSSON AB\n\nPnr 330 23\n\nSmålandsstenar. Tel 0371-305 18.\nBankgiro 14-3107. Postgiro 92087\nVerksamhet: Tillverkar\nstoppmöbler\n\nAntal anställda: 10\nÅrsomsättning: 1500 000\n.Aktiekapital: 30000\nVerkst dir: Claes Andersson\nEtableringsår: 1953.\n\nANDERSSON, LARSSON &amp; CO\nAB\n\nPnr 462 00\n\nVänersborg, L Vassbotten. Tel\n0521-106 69, 112 69. Bankgiro\n35-9802. Postgiro 90202\nVerksamhet: Säljer trävaror,\nbyggnadsmaterial, koks, eldningsolja\nAntal anställda: 21\nÅrsomsättning: 2 900 000\nAktiekapital: 100 000\nStyrelse: H Berger (ordf), B\nLandberg\n\nVerkst dir: H Berger\nEtableringsår: 1924.",
    "structured": {
        "1": {
            "company_name": "LOFAMATIC AB",
            "pnr": "113 46",
            "address": "Stockholm, Vanadisv 24",
            "phone_number": "08-24 23 30",
            "bank_details": {
                "postgiro": "552281-8"
            },
            "activity": "Automatikutrustningar för starkström o elektronik",
            "employees": 10,
            "annual_turnover": 1000000,
            "capital": 50000,
            "key_personnel": [
                {
                    "name": "P O Löfgren",
                    "position": "Verkst dir"
                }
            ],
            "establishment_year": 1968
        },
        "2": {
            "company_name": "park & co, ab",
            "pnr": "400 70",
            "address": "Göteborg 9, Polstjärneg 10",
            "phone_number": "031-22 2100",
            "bank_details": {
                "bankgiro": "45-0000",
                "postgiro": "41804"
            },
            "activity": "Grossistfirma i rör-, värme- o sanitetstekniska branschen",
            "capital": 600000,
            "key_personnel": [
                {
                    "name": "Eskil Wiberg",
                    "position": "Verkst dir"
                }
            ],
            "establishment_year": 1890
        },
        "3": {
            "company_name": "park hotel ab",
            "pnr": "102 45",
            "address": "Stockholm 5, Karlav 43, Box 5255",
            "phone_number": "08-22 96 20",
            "bank_details": {
                "bankgiro": "713-4737",
                "postgiro": "456810-1"
            },
            "activity": "Hotell o restaurang",
            "key_personnel": [
                {
                    "name": "Otto Herzog",
                    "position": "Verkst dir"
                }
            ],
            "establishment_year": 1968
        },
        "4": {
            "company_name": "MÖBEL LÄS, AB",
            "pnr": "63102",
            "address": "Eskilstuna 1, Köpmang 7, Box 92",
            "phone_number": "016-13 75 05",
            "bank_details": {
                "bankgiro": "601-5093",
                "postgiro": "6690-2"
            },
            "activity": "Tillverkar lås o nycklar för möbler, dörrar, inredningar, fartyg o kassafack",
            "annual_turnover": "1 500 000",
            "capital": 75000,
            "key_personnel": [
                {
                    "name": "Fru Margareta Johansson",
                    "position": "Verkst din"
                }
            ],
            "establishment_year": 1918
        },
        "5": {
            "company_name": "MÖCKELN AB",
            "pnr": "343 00",
            "address": "Älmhult, Box 170",
            "phone_number": "0476-120 60",
            "bank_details": {
                "bankgiro": "873-9211",
                "postgiro": "97908-8"
            },
            "activity": "Tillverkar grus- o stensorteringsanläggningar",
            "employees": 60,
            "annual_turnover": "8 000 000",
            "capital": 223000,
            "key_personnel": [
                {
                    "name": "Erik Nilsson",
                    "position": "Verkst dir"
                }
            ]
        },
        "6": {
            "company_name": "MOCKELNS SÅGVERK, AB",
            "pnr": "343 00",
            "address": "Älmhult, Box 170",
            "phone_number": "0476-120 60",
            "activity": "Sågverk",
            "employees": 45,
            "annual_turnover": "6 000 000",
            "capital": 90000,
            "key_personnel": [
                {
                    "name": "Erik Nilsson",
                    "position": "Veikst dir"
                }
            ],
            "establishment_year": 1953
        },
        "7": {
            "company_name": "SEG SECRETARIAL SERVICE",
            "pnr": "21121",
            "address": "Malmö, Västerg 22",
            "phone_number": "040-30010, 1135 00",
            "bank_details": {
                "postgiro": "6323 23-2"
            },
            "activity": "Sekreterartjänst, översättningar, trycksaker",
            "key_personnel": [
                {
                    "name": "Disp Sven Welith",
                    "position": "Chefer"
                },
                {
                    "name": "fru Christina Wulff",
                    "position": "Chefer"
                }
            ],
            "establishment_year": 1965
        },
        "8": {
            "company_name": "H D F-BOLAGEN AB",
            "pnr": "30103",
            "address": "Halmstad l.Köpmansg 23, Box 135",
            "phone_number": "035-11 82 20",
            "bank_details": {
                "bankgiro": "42-3534",
                "postgiro": "9518"
            },
            "activity": "Grossist i järnmanufaktur, verktyg, hushållsartiklar, badrumsinredningar, byggnadsbeslag, sport, fiske, vapen, trädgårdsredskap m m",
            "employees": 400,
            "annual_turnover": "70 000 000",
            "capital": 1800000,
            "key_personnel": [
                {
                    "name": "Överste Evert Cavalli",
                    "position": "Styrelse ordf."
                },
                {
                    "name": "dir P H Cavalli",
                    "position": "V verkst dir"
                }
            ],
            "establishment_year": 1906
        },
        "9": {
            "company_name": "HEBA BYGGNADS AB",
            "pnr": "102 52",
            "address": "Stockholm 27, Gyllenstiernsg 4, Box 27197",
            "phone_number": "08-60 12 20, 6015 50",
            "bank_details": {
                "postgiro": "501565"
            },
            "activity": "Byggnadsrörelse o fastighetsförvaltning",
            "employees": 26,
            "annual_turnover": "7100 000",
            "capital": 1200000,
            "key_personnel": [
                {
                    "name": "Kåge Holmberg",
                    "position": "Verkst dir"
                }
            ],
            "establishment_year": 1952
        },
        "10": {
            "company_name": "TORNBORG & LUNDBERG AB",
            "pnr": "102 71",
            "address": "Stockholm 9, Arstadalshamnen, Liljeholmen, Box 9047",
            "phone_number": "08-45 27 00",
            "bank_details": {
                "postgiro": "51240"
            },
            "activity": "Säljer byggnads- o anläggningsmaskiner samt mobilkranar",
            "branches": {
                "Göteborg": "H, Magnetg 6. Tel 031-235270",
                "Luleå": "Spantg 20 (Notviken). Tel 0920-107 55",
                "Malmö": "C, Borrg 29. Tel 040-93 48 60",
                "Sundsvall": "Bergsg 118. Tel 060-15 04 00"
            },
            "varunamn": "Ammann, Aveling-Barford, Bucyrus-Erie, Coles, International Hough, International Har-vester, Magni, Ruston-Bucyrus, Tolu, Torno",
            "employees": 366,
            "annual_turnover": "72 000 000",
            "capital": 5800000,
            "key_personnel": [
                {
                    "name": "Ing C L Hesselman",
                    "position": "Styrelse ordf."
                }
            ],
            "establishment_year": 1882
        },
        "11": {
            "company_name": "TORNE AB, SIXTEN",
            "pnr": "211 55",
            "address": "Malmö, Amiralsg 6",
            "phone_number": "040-760 80",
            "bank_details": {
                "bankgiro": "875-5308",
                "postgiro": "39132-6"
            },
            "activity": "Säljer maskiner o apparater till livsmedelsindustrin (inkl dryckesindustrin), kemiska o kem tekn fabriker (inkl kosmetiska industrin) samt farmaceutiska industrin. Utrustningar för interna transporter o emballagehantering",
            "employees": 12,
            "capital": 100000,
            "key_personnel": [
                {
                    "name": "Sixten Torne",
                    "position": "Verkst dir"
                }
            ],
            "establishment_year": 1935
        },
        "12": {
            "company_name": "INVICTA AB",
            "pnr": "402 24",
            "address": "Göteborg 5, Box 5214, Berzeliig 24",
            "phone_number": "031-208510",
            "bank_details": {
                "bankgiro": "848-3588",
                "postgiro": "429200-9"
            },
            "activity": "Import o agenturer. Generalagenter för Invicta slang-klämmor",
            "varunamn": "Invicta",
            "capital": 5000,
            "key_personnel": [
                {
                    "name": "Rolf von Bothmer",
                    "position": "Ägare o chef"
                }
            ],
            "establishment_year": 1963
        },
        "13": {
            "company_name": "I PC INTERNATIONAL PUBLISHING CO",
            "pnr": "70106",
            "address": "Örebro 1, Box 404, Karl Johans torg 15",
            "phone_number": "019-12 3445, 1898 38",
            "bank_details": {
                "bankgiro": "614-3705",
                "postgiro": "77226-9"
            },
            "activity": "Bokförlag",
            "employees": 4,
            "annual_turnover": "1 800 000",
            "key_personnel": [
                {
                    "name": "Bokförl Ake Andersson",
                    "position": "Chef"
                }
            ],
            "establishment_year": 1956
        },
        "14": {
            "company_name": "FANÈRIMPORTEN AB",
            "pnr": "576 00",
            "address": "Sävsjö, V Järnvägsg, Box 32",
            "phone_number": "0382-113 25",
            "bank_details": {
                "bankgiro": "83-6619",
                "postgiro": "257365"
            },
            "activity": "Säljer fanér, spånplattor, lamellträ o plywood",
            "employees": 10,
            "annual_turnover": "3 200 000",
            "capital": 50000,
            "key_personnel": [
                {
                    "name": "Sven Eklund",
                    "position": "Verkst dir"
                }
            ],
            "establishment_year": 1947
        },
        "15": {
            "company_name": "SVENSKA TÄNDSTICKS AB",
            "pnr": "551 02",
            "address": "Jönköping 1, Box 608, V Storg 18 A",
            "phone_number": "036-11 96 4 0",
            "bank_details": {
                "bankgiro": "140-0761",
                "postgiro": "86 76-9"
            },
            "activity": "Moderbolag i STAB-koncernen, som omfattar ca 100 foretag i ett 30-tal länder o som är verksam inom tändsticks-, byggmaterial-, pappers-, förpacknings-o verkstadsbranscherna",
            "employees": 32500,
            "annual_turnover": 1908900000,
            "capital": 235000000,
            "key_personnel": [
                {
                    "name": "Ekon dr Jacob Wallenberg",
                    "position": "Styrelse ordf."
                },
                {
                    "name": "Rolf Deinoff",
                    "position": "Verkst dir"
                }
            ]
        },
        "16": {
            "company_name": "SVENSKA TÄNDSTICKSBO.LAGETS FÖRSÄLJNINGS AB",
            "pnr": "103 22",
            "address": "Stockholm 16, V Trädgårdsg 15, Box 16100",
            "phone_number": "08-22 06 20",
            "bank_details": {
                "bankgiro": "160-8108, 560-5076",
                "postgiro": "2004-0"
            },
            "activity": "Säljer tändstickor från tändsticksfabriker tillhörande AB Jönköping-Vulcan",
            "employees": 6,
            "capital": 300000,
            "key_personnel": [
                {
                    "name": "Sven Wallgren",
                    "position": "Styrelse ordf."
                },
                {
                    "name": "Arne Hallgren",
                    "position": "Verkst dir"
                }
            ],
            "establishment_year": 1919
        },
        "17": {
            "company_name": "ANDERSSON & JOHNSSON AB",
            "pnr": "330 23",
            "address": "Smålandsstenar",
            "phone_number": "0371-305 18",
            "bank_details": {
                "bankgiro": "14-3107",
                "postgiro": "92087"
            },
            "activity": "Tillverkar stoppmöbler",
            "employees": 10,
            "annual_turnover": "1500 000",
            "capital": 30000,
            "key_personnel": [
                {
                    "name": "Claes Andersson",
                    "position": "Verkst dir"
                }
            ],
            "establishment_year": 1953
        },
        "18": {
            "company_name": "ANDERSSON, LARSSON & CO AB",
            "pnr": "462 00",
            "address": "Vänersborg, L Vassbotten",
            "phone_number": "0521-106 69, 112 69",
            "bank_details": {
                "bankgiro": "35-9802",
                "postgiro": "90202"
            },
            "activity": "Säljer trävaror, byggnadsmaterial, koks, eldningsolja",
            "employees": 21,
            "annual_turnover": "2 900 000",
            "capital": 100000,
            "key_personnel": [
                {
                    "name": "H Berger",
                    "position": "Styrelse ordf."
                }
            ],
            "establishment_year": 1924
        }
    }
}