{
    "original": "NOR\n\nVerksamhet: Kreditupplysningar o\ninkassouppdrag\n\nStyrelse: Bankdir Folke\nLinde-ström (ordf), dir James Johanson,\nkonsul Gösta Mossberg\nKamrer: Erik Sjöberg\nEtableringsår: 1907.\n\nNORRKOPINGS MARKIS- &amp;\nPRESENNINGSFABRIK\n\nPnr 602 20\n\nNorrköping, Kungsg 12. Tel\n011-12 66 44, 13 8140. Bankgiro\n610-0358. Postgiro 373883-8\nVerksamhet: Tillverkar o säljer\nmarkiser, mörkrumsanläggningar,\nskyddsdraperier med tillbehör m m\nÅrsomsättning: 275 000\nChef: Fabr Göte Lagerqvist\nEtableringsår: 1966.\n\nNORRKOPINGS MEK\nVERKSTAD\n\nPnr 600 12\n\nNorrköping 12, Vagng 15. Box\n12054. Tel \"011-18 02 55. Bankgiro\n609-9949. Postgiro 297549-8\nVerksamhet: Tillverkar\nverktygs-slipmaskiner, tygläggningsmaskiner\no specialmaskiner. Legotillverkning.\nDränkbara länspumpar\nAntal anställda: 70\nÅrsomsättning: 4 000 000\nVerkst dir: Fabr Stig Trybom\nKamrer: Gunnar Östergren\nEtableringsår: 1945.\n\nNORRKOPINGS NYA\nGRAVMASKINS AB\n\nPnr 602 29\n\nNorrköping, Gustav Adolfsg 21. Tel\n011-18 0140. Postgiro 464826\nVerksamhet: Schaktnings- o\nplaneringsarbeten\nAntal anställda: 11\nÅrsomsättning: 850 000\nAktiekapital: 50 000\nVerkst dir: Stig Andersson\nEtableringsår: 1962.\n\nNORRKOPINGS REM- &amp;\nSKIDSTAVSFABRIK\n\nPnr 600 03\n\nNorrköping3, Kungsg 34. Box 3055.\nTel 011-12 16 26. Postgiro 85380.\nTga Remfabriken\n\nVerksamhet: Tillverkar drivremmar\nalla slag samt skidstavar. Säljer\nremmar, skidstavar o tennisrackets\nAntal anställda: 5\nÅrsomsättning: 150 000\nÄgare o chef: Arne Kock\nEtableringsår: 1924.\n\nNORRKOPINGS SKEPPS.\nFOURNERING, AB\n\nPnr 601 03\n\nNorrköping 1, Box 101. Flemingg\n30. Tel 011-12 06 74, 12 06 56.\nBankgiro 824-3479. Postgiro\n79700-1\n\nVerksamhet: Säljer båttillbehör.\nIndustriförnödenheter\nAktiekapital: 90 000\nEtableringsår: 1914.\n\nNORRKOPINGS SODA.\nFABRIKS AB\n\nPnr 601 05\n\nNorrköping 1, Flemingg 22.Box440.\nTel 011-12 02 22, 12 02 94. Bankgiro\n12-5117. Postgiro 21326. Tga\nSodafabriken\n\nVerksamhet: Tillverkar\nkristallsoda, kem ren soda, färgkritor,\nakvarellfärger, märkkritor o ljus\nAktiekapital: 150 000\nVerkst dir: Stig Appeltofft\nEtableringsår: 1892.\n\nNORRKOPINGS SPRUT.\nBETONG\n\nPnr 605 90\n\nNon-köping, Kärrv 5, Dagsberg. Tel\n011-402 89. Bankgiro 18-4016.\nPostgiro 685174. Tga Norrsprut\nVerksamhet: Generalagent för\nKley-ers plastpooler o tillbehör\nAntal anställda: 6\nÅrsomsättning: 250 000\nChef: Betongsprutare Agne\nStåhl-roos\n\nEtableringsår: 1966.\n\nNORRKUPINGS STEN.\nINDUSTRI AB\n\nPnr 603 63\n\nNorrköping, Torsg 7. Tel\n011-22 13 80. Bankgiro 986-2996.\nPostgiro 672115-3\nVerksamhet: Stenförädling\nAntal anställda: 6\nÅrsomsättning: 600 000\nChef: Fabr Gösta Nilsson\nEtableringsår: 1965.\n\nFORSERUMS INDUSTRI AB\n\nPnr 570 22\n\nForserum. Tel 0380-203 30. Tga\nFoamlatex\n\nVerksamhet: Skumgummifabrik.\nTillverkar skumgummiartiklar o\npolyeter\n\nFabrik o kontor: Vällingby,\nGrim-stag 164. Tel 08-89 03 30.\nTillverkar Ukriktare o d\nAktiekapital: 555 000\nVerkst dir: Nils Sterner\nEtableringsår: 1919\nOmbildat till aktiebolag 1950.\n\nFORSERUMS\nTRÄFORÄD-LING, AB\n\nPnr 570 22\n\nForserum, Box 147. Tel\n0380-20184, 20180\n\nVerksamhet: Tillverkar klädhängare\n\ni trä, stål o plast\n\nÄgare o chefer: H Sörmander, G V\n\nÅstrand.\n\nFORSERUMS VERKTYGS.\nINDUSTRI, AB\n\nPnr 570 22\n\nForserum, Sveav 11. Tel\n0380-20 1 67. Bankgiro 452-9814.\nPostgiro 337451-9\n\nVerksamhet: Tillverkar\npressverktyg\n\nAktiekapital: 15 000\nFirmatecknare: R C Jansson, B V\nG Hallenborg\nEtableringsår: 1954.\n\nFORSGRENS\nBOKFORINGS-och REVISIONSBYRÅ\n\nPrr 90244\n\nUmeå, Storg 67. Tel 090-1159 26\nVerksamhet: Bokföring,\nbolagsrevisioner, utredningar, skatteärenden,\nförmedling, bolagsbildning m m\nAntal anställda: 8\nChef: Stig Forsgrén\nEtableringsår: 1954.\n\nFORSGRENS\nMASKIN-GRÄVNINGAR AB\n\nPnr 83100\n\nÖstersund, Rådhusg 36 B. Tel\n063-16102. Bankgiro 25-0028. Postgiro\n346604-2\n\nVerksamhet: Uthyrning av kranar o\ngrävmaskiner på entreprenad\nAntal anstäUda: 10\nÅrsomsättning: 837 500\nAktiekapital: 10 000\nVerkst dir: Aug Forsgrén\nEtableringsår: 1967.\n\nmea ab\n\nPnr 11187\n\nStockholm 1, Hamng 15. Box 1750.\nTel 08-2243 00. Bankgiro 560-3071.\nPostgiro 1155-1. Tga MEA\nVerksamhet: Varuhus med\nfullständig herr- o damekipering, herr- o\ndamkonfektion, herrskrädderi,\nreseffekter, skor, handskar o parfymer\nAntal anställda: 220\nÅrsomsättning: 20 000 000\nAktiekapital: 1765 000\nVerkst dir: Olle Brolin\nEtableringsår: 1883.\n\nHEDBERGS SUCCESSORS AB\n\nPnr 11451\n\nStockholm, Strandv 5 A. Tel\n08-6200 11. Tga Success\nVerksamhet: Import o export\nAktiekapital: 150 000\nEtableringsår: 1943.\n\nSCIAKY SCANDIA AB\n\nPnr 41106\n\nGöteborg, N Hamng 36. Tel 031-\n\n1168 30, 13 1735. Bankgiro 84-\n\n8474. Postgiro 626252.\n\nTga Sciakyscan. Telex 20783\n\nVerksamhet: Försäljning av Sciaky\n\nprodukter\n\nVarunamn: Sciaky\n\nAktiekapital: 5 000\n\nChef: Civiling N O Wiebe\n\nEtableringsàr 1964.\n\nARMATOR, AB\n\nPnr 111 45\n\nStockholm, Birger Jarlsg 37. Tel\n08-23 18 90. Bankgiro 72-6807.\nPostgiro 52213-6. Tga Abarmator\nVerksamhet: Entreprenörfinna för\nbostads- o industribyggnader\nAntal anställda: 250\nÅrsomsättning: 20 000 000\nAktiekapital: 300 000\nVerkst dir Lars Om\nEtableringsår: 1922.\n\nARMATUR-\n\nse i övrigt resp namn.\n\nARMATUR-&amp; BEVATTNINGS AB\n\nPnr 162 21\n\nVällingby, Vällingbyv 152. Tel\n08-87 56 78, 87 5679. Bankgiro\n57-7520. Postgiro 651471. Tga\nOlopro-dukt. Telex 17452 ARMATUR S\nVerksamhet: Säljer armatur för\navlopp, gas, vatten, ånga etc,\nsnabbkopplingsrör o bevattningsmaterial\nAktiekapital: 50000\nVerkst dir: Olle Åkerberg\nEtableringsår: 1953\nOmbildat till aktiebolag 1960.\n\nARMATURJONSSON AB\n\nPnr 42131\n\nVästra Frölunda, Fröodlareg 9. Tel\n031-49 01 00. Bankgiro 42-0227.\nPostgiro 43534. Tga\nArmaturjonsson. Telex 2517 ARMATUR S\nVerksamhet: Armatur för avlopp,\ngas, olja, vatten, värme o ånga\nVerkst dir: Bertil Lindvall\nEtableringsår: 1949.\n\nMODEFA AB\n\nPnr 268 00\n\nSvalöv, Box 42. Tel 0418-63030.\nTga Modefa. Telex 72414\nVerksamhet: Tillverkar o säljer\nförpackningar av företrädesvis\ntransparenta material samt\npoly-etensäckar\nAntal anställda: 35\nÅrsomsättning: 8 000 000\nAktiekapital: 300 000\nVerkst dir: Curt Sjöquist\nEtableringsår: 1966.\n\nRADINGS ORTOPEDISKA AB\n\nPnr 412 54\n\nGöteborg, Södra v 10. Tel\n031-18 09 97, 18 09 51. Bankgiro 36-2755.\nPostgiro 376567. Tga Radoped\nVerksamhet: Ortopediska o fotr\nvårdsartiklar\nAntal anställda: 30\nVerkst dir: Theodor Rading\nEtableringsår: 1957.\n\nRADIO ENGINEERING PRO.\nDUCTS EUROPE AB\n\nPnr 183 21\n\nTäby 1, Bergtorps v 68. Box 75. Tel\n08-756 50 40, 756 50 30. Bankgiro\n146-4296. Postgiro 683400-6. Tga\nRadenpro\n\nVeiksamhet: Representerar\nmoderbolaget REP, Montreal, Canada\nAntal anställda: 6\nÅrsomsättning: 1500 000\nAktiekapital: 25 000\nVerkst dir: Lars-Gunnar Ekberg\nEtableringsår: 1966.\n\nSTENQVIST AB, J D\n\nPnr 260 60\n\nKvidinge. Tel 0435-204 00.\nBankgiro 67-1359. Postgiro 15040.\nTelex 7247 3 JDS S\nVerksamhet: Påsfabrik,\nkartongfabrik, förpackningsindustri, bok-,\ndjup- o offsettryckeri, papper\nengros\n\nChef: Dir Bengt Sundfeldt\n(Ströms-näsbruk’)\n\nPlatschef: Dir Sverker Erlandson\nEtableringsår: 1927\nSe vidare Emballagegruppen,\nSkogsägarnas Industri AB, Växjö.\nHelägt dotterföretag till\nSkogsägarnas Industri AB, Växjö.\n\nSTENLUND &amp; SÖNER AB,\nERIK\n\nPnr 930 31\n\nKlemensnäs. Tel 0910-306 60,\n307 60, 308 60. Bankgiro 764-1509.\nPostgiro 486433-6\n\n\n\nVerksamhet: Tillverkar akustik- o\n\nperforeringsmaskiner, formatsågar,\n\nritsmaskiner, huggmaskiner för\n\nboard, slipmaskiner för huggstål o\n\nspecialmaskiner för wallboard- o\n\nträindustrin\n\nAntal anställda: 30\n\nÄgare o chef: Erik Stenlund\n\nIng:r: Sten Erik Stenlund, Eskil\n\nHolmlund, Gunder Marklund\n\nEtableringsår: 1955.\n\nFÄLTMAN &amp; MALMÉN AB\n\nPnr 115 38\n\nStockholm, Kampementsg 36. Tel\n08-63 1615. Postgiro 446-9003\nVerksamhet: Annonsbyrå. Konsulter\ninom reklam\nAntal anställda: 8\nÅrsomsättning: 2100 000\nAktiekapital: 10 000\nEtableringsår: 1965.",
    "structured": {
        "1": {
            "company_name": "NOR",
            "activity": "Kreditupplysningar o inkassouppdrag",
            "establishment_year": 1907
        },
        "2": {
            "company_name": "NORRKOPINGS MARKIS- &amp; PRESENNINGSFABRIK",
            "pnr": "602 20",
            "address": "Norrköping, Kungsg 12",
            "phone_number": "011-12 66 44, 13 8140",
            "bank_details": {
                "bankgiro": "610-0358",
                "postgiro": "373883-8"
            },
            "activity": "Tillverkar o säljer markiser, mörkrumsanläggningar, skyddsdraperier med tillbehör m m",
            "annual_turnover": 275000,
            "capital": 1966,
            "key_personnel": [
                {
                    "name": "Fabr Göte Lagerqvist"
                }
            ]
        },
        "3": {
            "company_name": "NORRKOPINGS MEK VERKSTAD",
            "pnr": "600 12",
            "address": "Norrköping 12, Vagng 15, Box 12054",
            "phone_number": "011-18 02 55",
            "bank_details": {
                "bankgiro": "609-9949",
                "postgiro": "297549-8"
            },
            "activity": "Tillverkar verktygs-slipmaskiner, tygläggningsmaskiner o specialmaskiner. Legotillverkning. Dränkbara länspumpar",
            "employees": 70,
            "annual_turnover": 4000000,
            "establishment_year": 1945
        },
        "4": {
            "company_name": "NORRKOPINGS NYA GRAVMASKINS AB",
            "pnr": "602 29",
            "address": "Norrköping, Gustav Adolfsg 21",
            "phone_number": "011-18 0140",
            "bank_details": {
                "postgiro": "464826"
            },
            "activity": "Schaktnings- o planeringsarbeten",
            "employees": 11,
            "annual_turnover": 850000,
            "capital": 50000,
            "key_personnel": [
                {
                    "name": "Stig Andersson",
                    "position": "Verkst dir"
                }
            ]
        },
        "5": {
            "company_name": "NORRKOPINGS REM- &amp; SKIDSTAVSFABRIK",
            "pnr": "600 03",
            "address": "Norrköping3, Kungsg 34, Box 3055",
            "phone_number": "011-12 16 26",
            "bank_details": {
                "postgiro": "85380"
            },
            "activity": "Tillverkar drivremmar alla slag samt skidstavar. Säljer remmar, skidstavar o tennisrackets",
            "employees": 5,
            "annual_turnover": 150000,
            "establishment_year": 1924
        },
        "6": {
            "company_name": "NORRKOPINGS SKEPPS. FOURNERING, AB",
            "pnr": "601 03",
            "address": "Norrköping 1, Box 101, Flemingg 30",
            "phone_number": "011-12 06 74, 12 06 56",
            "bank_details": {
                "bankgiro": "824-3479",
                "postgiro": "79700-1"
            },
            "activity": "Säljer båttillbehör. Industriförnödenheter",
            "capital": 90000,
            "establishment_year": 1914
        }
    }
}