{
    "original": "GULLFIBER AB\n\nPnr 260 50\n\nBillesholm. Tel 042-730 00.\nBankgiro 86-3703. Postgiro 84350-8.\nTga Gullfiber.\nTelex 72287 GULLBIL,\norder 72493\n\nVerksamhet: Tillverkar mineralull\no isoleringsprodukter härav,\nhuvudsakligen för värme-, kyl- o\nljudisolering. Specialprodukter av\nglasfibrer såsom stapelfiber o\nhörselskydd. Ensamförsäljare för\nMin-wool mineralull\n\nFörsäljningskontor: Billesholm.\nTel 042-730 00\nSöråker. Tel 060-403 00\nStockholm. Krossg 30,pa Vällingby.\nTel 08-89 04 80\n\nGöteborg, Eklandag 55. Tel\n031-20 02 90\n\nGävle, N Köpmang \"&gt;2 B. Tel\n026-1818 99\n\nLuleå, Malmuddsv 68. Tel\n0920-25148\n\nMalmö, Bellevuev 60. Tel\n040-15 80 65\n\nVarunamn: Gullfiber\nAntal anställda: 1 000\nAktiekapital: 10 000 000\n\nVerkst dir: Malte Johansson\nEtableringsår: 1933.\n\nOLTRONIX AB\n\nPnr 162 20\n\nVällingby, Jämtlandsg 125. Tel\n08-87 03 30. Bankgiro 33-3002.\nPostgiro 359932. Tga Oltronix\nVerksamhet: Tillverkar\nelektroniska laboratorieinstrument\nAktiekapital: 150000\nVerkst dir: Civiling Carl-Olof\nOlsson\n\nEtableringsår 1950.\n\nOLUMA AB,\nPENSELFABRIKEN\n\nPnr 150 30\n\nMariefred, Kärnbog 9. Box 38. Tel\n0159-100 86. Bankgiro 61-8724.\nPostgiro 75457. Tga Oluma\nVerksamhet: Tillverkar penslar o\nborstar\n\nAntal anställda: 8\nAktiekapital: 50 000\nVerkst dir: Otto Luthin\nEtableringsår: 1929.\n\nPERSSON BIL AB, HANS\n\nPnr 774 00\n\nAvesta, Bergsnäsg 2. Tel\n0226-53030. Bankgiro 233-5628.\nPostgiro 213100-1\n\nVerksamhet: Återförsäljare för AB\nVolvo av person- o lastbilar\nAntal anställda: 150\nÅrsomsättning: 40 000 000\nAktiekapital: 300000\nVerkst dir: Hans Persson\nDisp: Gunnar Thörnlund\nEtableringsår: 1955.\n\nSVENSKA TOTAL AB\n\nPnr 11135\n\nStockholm, Kungsg 30. Tel\n08-24 9 9 3 0\n\nVerksamhet:\nBrandsläckningsappa-rater, pulveraggregat,\nskumsläck-ningsutrustning\n\nFilial: 414 72 Göteborg, Majstångsg\n20; Tel 031-24 35 64\nSe vidare AB Brand &amp;\nSäkerhetstjänst, Stockholm.\n\nSVENSKA TRAKTOR AB\n\nPnr 102 20 Sthlm 12\nBarkarby, Äggelundav 7. Fack,\nSthlm 12. Tel 08-760 0100.\nPostgiro 159783. Telex 19013. Tga\nSvensktrak\n\nVerksamhet: Entreprenad- o\nvägbyggnadsmaskiner, vägbeläggnings-maskiner, grävmaskiner,\njordbrukstraktorer, kranar, gaffel- o\ngrensle-truckar, tunga transportfordon,\ndieselmotorer. Reservdelar o\nverkstadsrörelse\n\nDistriktskontor: Gävle, Göteborg,\nJönköping, Karlstad, Leksand,\nLuleå, Malmö, Norrköping, Uppsala,\nVäxjö, Älvsbyn, Örnsköldsvik\nVarunamn: Allis-Chalmers,\nBarber-Greene, Cummins, Dart, Etnyre,\nFiat, Gradall, Hyster, Komatsu,\nMarshall, Michigan, Munck, O &amp; K,\nP &amp; H, Pegson, Valmet\nAntal anställda: 375\nAktiekapital: 3 000 000\nVerkst dir: Bengt Rywe\nEtableringsår: 1935\nOmbildat till aktiebolag 1941.\n\nSVENSKA TRAUB AB\n\nPnr 41451\n\nGöteborg, Banehagsg 1, uppg 14.\nTel 031-14 65 40, 14 65 35, 24 37 09.\nBankgiro 84-8287. Postgiro 559482.\nTelex 2566\n\nVerksamhet: Traub automatsvarvar,\nStrohm längdsvarvningsautomater\nVarunamn: Strohm, Traub\nAktiekapital: 1000 000\nVerkst dir Yngve Johansson\nEtableringsår 1963.\n\nEXPEDO TRADING CO AB\n\nPnr 103 40\n\nStockholm 40, Pack. sveav 9-11.\nTel 08-22 66 40. Bankgiro 56-0114.\nPostgiro 352863. TgaExpedo.\nTelex 1332\n\nVerksamhet: Export o import\nAntal anställda: 24\nAktiekapital: 700 000\nVerkst dir: S-E Ståhle\nEtableringsår: 1948.\n\nNYA BOKFURLAGS AB\n\nPnr 102 41\n\nStockholm 5, Box 5020. Sibylleg\n18. Tel 08-67 0155. Bankgiro\n821-8521. Postgiro 4616-9\nVeiksamhet: Bokförlag, tidskriften\nRätt Kurs\nAntal anställda: 4\nÅrsomsättning: 400 000\nAktiekapital: 90 000\nVerkst dir: K E Hellberg\nEtableringsår: 1873.\n\nNYA CIVILTRYCKERIET I\nGDTEBORG AB\n\nPnr 40241\n\nGöteborg 12, Box 12084. Banehagsg\n1. Tel 031-14 9408, 14 94 10.\nBankgiro 400-4800. Postgiro 629637-0\nVerksamhet: Bok-, offsettryck,\nstamsatser, tidskrifter, kataloger,\nbroschyrer samt övrigt reklamtryck\nAntal anstäUda: 21\nÅrsomsättning: 1600000\nAktiekapital: 50 000\nStyrelse: Adv Oswald Jacobsson\n(ordf), dir Lilly Johansson, faktor\nOlle Sjöbring, herr Karl-Erik\nBlomgren, herr Mats Härin, herr Nils\nSvensson, fru Ingrid Sundström\nVerkst dir: Fru Lilly Johansson\nFaktor: Olle Sjöbring\nFaktor: Lennart Wammén\nEtableringsår: 1932\nOmbildat till aktiebolag 1959.\n\nNYA GRAND HÖT EL, AB\n\nPnr 103 20\n\nStockholm 16, Fack. S\nBlasieholms-hamnen 8. Tel 08-22 10 20, 2217 20.\nBankgiro 700-1324. Postgiro\n3455-3. Tga Grand. Telex 1500\nVerksamhet: Hotell- o\nrestaurant-rörelse\n\nAktiekapital: 1000 000\nEtableringsår: 1874.\n\nFAM\n\nAntal anställda: 8\nÅrsomsättning: 600 000\nAktiekapital: 35 000\nVeikst dir: Axel Monthan\nEtableringsår: 1946.\n\nANDERSSON SHIPPING AB\n\nPnr 25102\n\nHelsingborg 1, Box61. Hamntorget\n5. Tel 042-1275 60. Bankgiro\n437-8048. Postgiro 137908-0.\nTgaHeni-son. Telex 7 2242, 7 2246\nVerksamhet: Auktoriserade\nskeppsklarerare o speditörer,\nlinjeagenter, befraktning, magasinering o\npresenningsuthyrning\nAntal anställda: 24\nAktiekapital: 500 000\nStyrelse: Fru Margit Nilsson (ordf),\nsped-chef Gösta Lundgren,\nskeppsklarerare Bengt Nilsson,\nskepps-mäkl Henry Nilsson\nVerkst dir: Skeppsmäkl Henry\nNilsson\n\nEtableringsår: 1932.\n\nSKEPPSHULTSBRUKS AB\n\nPnr 330 24\n\nSkeppshult. Tel 0371-360 01,36174.\nBankgiro 42-7625. Postgiro\n75120-6, Tga Bruket\nVerksamhet: Tråddrageri,\nspikfabrik, kraftverk, hyvlade trävaror\nAntal anställda: 18\nAktiekapital: 500 000\nVerkst dir: Svante Pettersson\nEtableringsår: 1917.\n\nSCANAUTO, AB\n\nPnr 20023\n\nMalmö 12, Lundav 72. Fack. Tel\n040-93 4 6 30. Bankgiro 870-1534.\nPostgiro 245073-2. Tga Scanmotor\nVerksamhet: Försäljning o service\nför BMC, Jaguar, Rover o Triumph\nAntal anställda: 80\nÅrsomsättning: 12 000 000\nAktiekapital: 225 000\nVerkst dir. Vakant\nPlatschef: P A Sandström\nEtableringsår: 1945.",
    "structured": {
        "1": {
            "company_name": "GULLFIBER AB",
            "pnr": "260 50",
            "address": "Billesholm",
            "phone_number": "042-730 00",
            "bank_details": {
                "bankgiro": "86-3703",
                "postgiro": "84350-8"
            },
            "activity": "Tillverkar mineralull och isoleringsprodukter härav, huvudsakligen för värme-, kyl- och ljudisolering. Specialprodukter av glasfibrer såsom stapelfiber och hörselskydd. Ensamförsäljare för Min-wool mineralull",
            "employees": 1000,
            "capital": 10000000,
            "key_personnel": [
                {
                    "name": "Malte Johansson",
                    "position": "Verkst dir"
                }
            ],
            "establishment_year": 1933
        },
        "2": {
            "company_name": "OLTRONIX AB",
            "pnr": "162 20",
            "address": "Vällingby, Jämtlandsg 125",
            "phone_number": "08-87 03 30",
            "bank_details": {
                "bankgiro": "33-3002",
                "postgiro": "359932"
            },
            "activity": "Tillverkar elektroniska laboratorieinstrument",
            "capital": 150000,
            "key_personnel": [
                {
                    "name": "Civiling Carl-Olof Olsson",
                    "position": "Verkst dir"
                }
            ],
            "establishment_year": 1950
        },
        "3": {
            "company_name": "OLUMA AB, PENSELFABRIKEN",
            "pnr": "150 30",
            "address": "Mariefred, Kärnbog 9, Box 38",
            "phone_number": "0159-100 86",
            "bank_details": {
                "bankgiro": "61-8724",
                "postgiro": "75457"
            },
            "activity": "Tillverkar penslar och borstar",
            "employees": 8,
            "capital": 50000,
            "key_personnel": [
                {
                    "name": "Otto Luthin",
                    "position": "Verkst dir"
                }
            ],
            "establishment_year": 1929
        },
        "4": {
            "company_name": "PERSSON BIL AB, HANS",
            "pnr": "774 00",
            "address": "Avesta, Bergsnäsg 2",
            "phone_number": "0226-53030",
            "bank_details": {
                "bankgiro": "233-5628",
                "postgiro": "213100-1"
            },
            "activity": "Återförsäljare för AB Volvo av person- och lastbilar",
            "employees": 150,
            "annual_turnover": 40000000,
            "capital": 300000,
            "key_personnel": [
                {
                    "name": "Hans Persson",
                    "position": "Verkst dir"
                }
            ],
            "establishment_year": 1955
        },
        "5": {
            "company_name": "SVENSKA TOTAL AB",
            "pnr": "11135",
            "address": "Stockholm, Kungsg 30",
            "phone_number": "08-24 9 9 3 0",
            "activity": "Brandsläckningsapparater, pulveraggregat, skumsläckningsutrustning",
            "establishment_year": "N/A"
        },
        "6": {
            "company_name": "SVENSKA TRAKTOR AB",
            "pnr": "102 20 Sthlm 12",
            "address": "Barkarby, Äggelundav 7, Fack, Sthlm 12",
            "phone_number": "08-760 0100",
            "postgiro": "159783",
            "activity": "Entreprenad- och vägbyggnadsmaskiner, vägbeläggningsmaskiner, grävmaskiner, jordbrukstraktorer, kranar, gaffel- och grensletruckar, tunga transportfordon, dieselmotorer. Reservdelar och verkstadsrörelse",
            "employees": 375,
            "capital": 3000000,
            "key_personnel": [
                {
                    "name": "Bengt Rywe",
                    "position": "Verkst dir"
                }
            ],
            "establishment_year": 1935
        },
        "7": {
            "company_name": "SVENSKA TRAUB AB",
            "pnr": "41451",
            "address": "Göteborg, Banehagsg 1, uppg 14",
            "phone_number": "031-14 65 40, 14 65 35, 24 37 09",
            "bank_details": {
                "bankgiro": "84-8287",
                "postgiro": "559482"
            },
            "activity": "Traub automatsvarvar, Strohm längdsvarvningsautomater",
            "capital": 1000000,
            "key_personnel": [
                {
                    "name": "Yngve Johansson",
                    "position": "Verkst dir"
                }
            ],
            "establishment_year": 1963
        },
        "8": {
            "company_name": "EXPEDO TRADING CO AB",
            "pnr": "103 40",
            "address": "Stockholm 40, Pack. sveav 9-11",
            "phone_number": "08-22 66 40",
            "bank_details": {
                "bankgiro": "56-0114",
                "postgiro": "352863"
            },
            "activity": "Export and import",
            "employees": 24,
            "capital": 700000,
            "key_personnel": [
                {
                    "name": "S-E Ståhle",
                    "position": "Verkst dir"
                }
            ],
            "establishment_year": 1948
        },
        "9": {
            "company_name": "NYA BOKFURLAGS AB",
            "pnr": "102 41",
            "address": "Stockholm 5, Box 5020, Sibylleg 18",
            "phone_number": "08-67 0155",
            "bank_details": {
                "bankgiro": "821-8521",
                "postgiro": "4616-9"
            },
            "activity": "Bokförlag, tidskriften Rätt Kurs",
            "employees": 4,
            "annual_turnover": 400000,
            "capital": 90000,
            "key_personnel": [
                {
                    "name": "K E Hellberg",
                    "position": "Verkst dir"
                }
            ],
            "establishment_year": 1873
        },
        "10": {
            "company_name": "NYA CIVILTRYCKERIET I GDTEBORG AB",
            "pnr": "40241",
            "address": "Göteborg 12, Box 12084, Banehagsg 1",
            "phone_number": "031-14 9408, 14 94 10",
            "bank_details": {
                "bankgiro": "400-4800",
                "postgiro": "629637-0"
            },
            "activity": "Bok-, offsettryck, stamsatser, tidskrifter, kataloger, broschyrer samt övrigt reklamtryck",
            "employees": 21,
            "annual_turnover": 1600000,
            "capital": 50000,
            "key_personnel": [
                {
                    "name": "Fru Lilly Johansson",
                    "position": "Verkst dir"
                },
                {
                    "name": "Olle Sjöbring",
                    "position": "Faktor"
                },
                {
                    "name": "Lennart Wammén",
                    "position": "Faktor"
                }
            ],
            "establishment_year": 1932
        },
        "11": {
            "company_name": "NYA GRAND HÖT EL, AB",
            "pnr": "103 20",
            "address": "Stockholm 16, Fack. S Blasieholms-hamnen 8",
            "phone_number": "08-22 10 20, 2217 20",
            "bank_details": {
                "bankgiro": "700-1324",
                "postgiro": "3455-3"
            },
            "activity": "Hotell- och restaurangrörelse",
            "employees": 8,
            "annual_turnover": 600000,
            "capital": 35000,
            "key_personnel": [
                {
                    "name": "Axel Monthan",
                    "position": "Verkst dir"
                }
            ],
            "establishment_year": 1946
        },
        "12": {
            "company_name": "ANDERSSON SHIPPING AB",
            "pnr": "25102",
            "address": "Helsingborg 1, Box 61, Hamntorget 5",
            "phone_number": "042-1275 60",
            "bank_details": {
                "bankgiro": "437-8048",
                "postgiro": "137908-0"
            },
            "activity": "Auktoriserade skeppsklarerare och speditörer, linjeagenter, befraktning, magasinering och presenningsuthyrning",
            "employees": 24,
            "capital": 500000,
            "key_personnel": [
                {
                    "name": "Skeppsmäkl Henry Nilsson",
                    "position": "Verkst dir"
                }
            ],
            "establishment_year": 1932
        },
        "13": {
            "company_name": "SKEPPSHULTSBRUKS AB",
            "pnr": "330 24",
            "address": "Skeppshult",
            "phone_number": "0371-360 01,36174",
            "bank_details": {
                "bankgiro": "42-7625",
                "postgiro": "75120-6"
            },
            "activity": "Tråddrageri, spikfabrik, kraftverk, hyvlade trävaror",
            "employees": 18,
            "capital": 500000,
            "key_personnel": [
                {
                    "name": "Svante Pettersson",
                    "position": "Verkst dir"
                }
            ],
            "establishment_year": 1917
        },
        "14": {
            "company_name": "SCANAUTO, AB",
            "pnr": "20023",
            "address": "Malmö 12, Lundav 72, Fack",
            "phone_number": "040-93 4 6 30",
            "bank_details": {
                "bankgiro": "870-1534",
                "postgiro": "245073-2"
            },
            "activity": "Försäljning och service för BMC, Jaguar, Rover och Triumph",
            "employees": 80,
            "annual_turnover": 12000000,
            "capital": 225000,
            "key_personnel": [
                {
                    "name": "P A Sandström",
                    "position": "Platschef"
                }
            ],
            "establishment_year": 1945
        }
    }
}