{
    "original": "SVENSK RUBBER, AB\n\nPnr 330 15\n\nBor. Tel 0370-503 70\nVerksamhet: Gummiindustri,\ntillverkar slitbanegummi, tekniska\nartiklar i gummi, oljefast gummi\nAntal anställda: 70\nÅrsomsättning: 8 500 000\nAktiekapital: 400 000\nVerkst dir: Ing Sture Andersson\nEtableringsår: 1950.\n\nALFTA JÄRNHANDEL AB\n\nPnr 822 00\n\nAlfta, Box 18. Tel 0271-104 00.\nBankgiro 193-3076. Postgiro\n133959-7\n\nVerksamhet: Järnhandel.\nVVS-för-säljning o installationer. Tillverkar\nfiskmjärdar\nAntal anställda: 18\nÅrsomsättning: 4 000 000\nAktiekapital: 60 000\nVerkst dir: G Svärdhagen\nEtableringsår: 1937.\n\nBIL &amp; TRAKTOR\n\nPnr 54100\n\nSkövde, Mariestadsv 86. Tel\n0500-180 15. Bankgiro 210-3216.\nPostgiro 417011-4\n\nVeiksamhet: Säljer\nlantbruksmaskiner, traktorer o träskor\nAntal anställda: 15\nÅrsomsättning: 4 000 000\nChef: Dir Gunnar Karlén.\n\nBIL &amp; TRUCK, AB\n\nPnr 40110\n\nGöteborg 1, Odinsplatsen 9. Pack\n1517. Tel 031-8004 00. Tga\nBil-truck\n\nVerksamhet: Säljer personbilar,\nlastbilar, reservdelar\nAntal anstäUda: 740\nÅrsomsättning: 163 000 000\nAktiekapital: 4 750 000\nVerkst dir: Bertil Hälleby\nEtableringsår: 1930.\n\nBIL &amp; TRUCK\nÖRNSKÖLDSVIK AB\n\nPnr 89101\n\n107 50. Bankgiro 626-9039. Postgiro\n207898-8. Telex 6042 BOT AB S\nVerksamhet: Återförsäljare för AB\nVolvo, Göteborg\nAntal anstäUda: 83\n\nÅrsomsättning: 19 500 000\nAktiekapital: 500 000\nVerkst dir: Sven Johansson\nEtableringsår: 1959.\n\nSVE\n\nAktiekapital: 100000\nVerkst dir: K T Friedrichs\nEtableringsår: 1932\nDotterbolag: AB Nordisk\nHelio-textil, ödsmål.\n\nSVENSKA BILFABRIKEN, AB\n\nPnr 13101\n\nNacka 1, Fack. Augustendalsv. Tel\n08-716 25 25. Bankgiro 568-9765.\nPostgiro 2304-4\n\nVerksamhet: Motorrenoverings- o\nmekanisk verkstad\nAktiekapital: 100 000\nEtableringsår: 1928.\n\nSVENSKA BILGUMMIDEPÅN,\nAB\n\nPnr 103 61\n\nStockholm 3, Sveav 52. Box 3094.\nTel 08-2234 60. Bankgiro 136-2490.\nPostgiro 354496-2\nVerksamhet:\nGummiverkstadsser-vice med försäljning o regummering\nAktiekapital: 5 000\nVerkst dir: Carl Axel Seth\nEtableringsår: 1955.\n\nSVENSKA BILPACKNINGS.\nFABRIKEN H SÖDERSTRÖM AB\n\nPnr 31201\n\nLaholm 1, Box 21. Mäster Nilsg 11.\nTel 0430-12010. Bankgiro\n659-1754. Postgiro 176313-5\nVerksamhet: Tillverkar\npackningsmaterialet Svedoit samt tätningar,\nringar, planpackningar, mellanlägg,\nshims, kederlist m m\nVarunamn: Svedoit\nAntal anställda: 50\nÅrsomsättning: 3 000 000\nAktiekapital: 100 000\nVerkst dir: Fabr Henry Söderström\nProd-chef o försäljn-chef: Bertil\nSöderström\n\nKamrer o inköpschef: Bengt-Ake\n\nJohansson\n\nEtableringsår: 1925.\n\nSVENSKA BP\nOLJE-AKTIEBOLAG\n\nPnr 102 51\n\nStockholm 27, Värtav 67. Box\n27088. Tel 08-22 30 40. Bankgiro\n16-8788. Postgiro 3109.\nTga Beepee. Telex 1388\nVerksamhet: Säljer bensin,\neldningsolja o andra\npetroleumprodukter\n\nAntal anställda: 1160\nÅrsomsättning: 1044 000\nAktiekapital: 50 000 000\nVerkst dir: Greger Lewenhaupt\nEtableringsår: 1927\nDotterbolag till The British\nPetroleum Company, Ltd, London.\n\nSVENSKA BROMSBANDS.\nFABRIKEN AB\n\nPnr 435 00\n\nMölnlycke. Tel 031-73 02 70,\n\n73 0 4 70. Bankgiro 848-0097.\nPost-girq 99398-0. Tga Svebrofa\nVerksamhet: Tillverkar o säljer\nfriktionsmaterial för alla ändamål\nsåsom bromsband o lamellbelägg\nför motorfordon o industriändamål\nVarunamn: SBF\nAntal anställda: 25\nÅrsomsättning: 2 000 000\n\nAktiekapital: 50000\nVerkst dir: John A Andersson\nFabrikschef: Ing Bengt Starling\nEtableringsår: 1934\nOmbildat till aktiebolag 1941.\n\nSVENSKA AB\nBROMS-REGULATOR\n\nPnr 20123\n\nMalmö 1, Box 306. N Vallg 54. Tel\n040-738 80. Bankgiro 26-3449. Postr\ngiro 39039-3. Tga Bromsregulator.\nTelex 32413 SABROMS S\nVerksamhet: Exploatering av\nuppfinningar o licensgivning.\nTillverkar o säljer bromsregulatorer,\nlastbromsutrustningar o fjädrande\nhjul för rälsfordon samt\nbromsregulatorer för tyngre vägfordon\nVarunamn: SAB\nAntal anställda: 125\n■Aktiekapital: 7 200 000\nStyrelse: Bankdir Axel Roos (ordf),\nbruksdisp Lars De Geer, civiling C\nA Nilsson, dir Stig Törnebohm, adv\nAke Wettermark\n\nVerkst dir: Civiling Stig\nTörnebohm\n\nEtableringsår: 1916\n\nDotterbolag: AB Thulinverken,\nLandskrona.\n\nSVENSKA AB BRllEL &amp;\nKJAER\n\nPnr 14145\n\nHuddinge, Kvarnbergsv 25. Tel\n08-711 27 30. Bankgiro 729-5579.\nPostgiro 501645-6. Tga Svebkamet.\nTelex 10250 DECIBEL S\nVerksamhet: Säljer elektroniska o\nakustiska mätinstrument\nAntal anställda: 8\nAktiekapital: 75 000\nVerkst dir: Börge M Ravn\nEtableringsår: 1952.\n\nHARA AKTIEBOLAG\n\nPnr 83100\n\nÖstersund, Odenskogsv 35. Tel\n063-246 20. Bankgiro 264-8285.\nPostgiro 688570-1. Tga Caway\nVerksamhet: Traktorhytter,\nlastmaskiner, axelsatser, hydraulik\nAntal anställda: 120\nÅrsomsättning: 13 000 000\nAktiekapital: 100 000\nStyrelse: Dir Käll Sandberg,\nekonomichef Kjell Gisslén, adv Bo\nVictor, åkeriägare Ruben Sandberg\nVerkst dir: Käll Sandberg\nEkonomichef: Kjell Gisslén\nVerkstadschef: Knut Ohlsson\nInköpschef: Bo Tengström\nEtableringsår: 1966.\n\nSVENSK FOTOKONST, AB\n\nPnr 702 23\n\nÖrebro, Frykstensg 2-6. Tel\n019-1194 85. Bankgiro 822-7027.\nPostgiro 84102-3. Tga Fotokonst\nVerksamhet: Fotografisk\nkopieringsanstalt, fotografiska artiklar\nen gros\n\nAntal anställda: 50\nÅrsomsättning: 5 000 000\nAktiekapital: 200 000\nVerkst dir: Elof Eliasson\nEtableringsår: 1933\nOmbildat till aktiebolag 1939.\n\nSVENSK FÄRGINDUSTRI, KB\n\nPnr 594 00\n\nGamleby. Tel 0493-115 60.\nBankgiro 732-4007. Postgiro 150265-7.\nTga Svenskfärg\n\nVerksamhet: Tillverkar\nindustrifärger o polyvinylkloridpastor.\nPlastpulver\nAntal anställda: 57\nÅrsomsättning: 8 700 000\nVerkst dir: Ing P O Lundin\nEtableringsår: 1938\nDotterbolag till Kema Nord AB,\nStockholm.\n\nSVENSK FORETAGS GARANTI\nAB\n\nPnr 102 61\n\nStockholm 4, Box 4049. Peter\nMyn-des Backe 12-14. Tel 08-22 91 60.\nBankgiro 980-0095\nVerksamhet: Genom ställande av\ngarantier för krediter medverka till\nfinansiering av sådana\ninvesteringar inom näringslivet som inriktas\npå rationalisering,\nstrukturanpassning o utveckling av mindre o\nmedelstora företag\nAktiekapital: 4 000 000\nStyrelse: Bankdir .Arne Callans\n(ordf), bankdir Sven Lindblad,\nbankdir Birger Lönnquist,\ncivilekonom Carl-Axel Zackrisson\nVerkst din Bankdir All Wikström\nEtableringsår: 1968.\n\nSVENSK GRAMMOFON.\nINDUSTRI, AB\n\nPnr 11157\n\nStockholm, Sveav 17. Tel\n08-10 63 67. Bankgiro 57-9721.\nPostgiro 39941. Tga Grammomatris\nVerksamhet: Tillverkar SiS-märkta\nPEL-rör\n\nFabrik o dotterbolag: Bro. AB\nBroplast. Tel 0758-400 88, 40168\nAktiekapital: 120 000\nVerkst dir: Tage Andersson\nEtableringsår: 1938.\n\nSVENSK GRUNDUNDERSOK.\nNING AB\n\nPnr 232 00\n\nArlöv, Företagsv 26. Tel\n040-43 40 40. Bankgiro 641-6176.\nPostgiro 637804-6\n\nVerksamhet: Utför\ngrundläggningsarbeten, grundundersökningar samt\nteknisk-ekonomiska utredningar\nAvdelningskontor: Solna,\nKristine-lundsv 2. Tel 08-83 7130\nVerkst dir: Ing Karl-Erik Nyman\nEtableringsår: 1965.\n\nSVENSK HEMSLÖJD U P A,\nFÖRENINGEN\n\nPnr 11134\n\nStockholm, Sveav 44. Tel\n08-23 21 15. Postgiro 1755-8\nVerksamhet: Säljer möbler,\ninredningar, textilier o konsthantverk\nVerkst dir: Thorild Wennerholm\nEtableringsår: 1899.\n\nSVENSK IDROTTSPLATS.\nMATERIAL AB SIMAB\n\nPnr 614 00\n\nSöderköping, Dockan. Tel\n0121-113 46. 124 20. Bankgiro 127-7797.\nPostgiro 344120-1\n\nVerksamhet: Tillverkar\nidrottsplatsredskap o säljer sportmateriel\nVarunamn: SIMAB\nAktiekapital: 10 000\nVerkst dir: Ing Hannes Sjöblom\nEtableringsår: 1939.\n\nISABERGSSALESAB\n\nPnr 18121\n\nLidingö 1, Box 137. Grenstigen\n2 A. Tel 08-765 28 85.\nTelex 17163\n\nVerksamhet: Försäljning av\nIsa-bergs Verkstads AB hela\ntülverk-ning\n\nAntal anstäUda: 9\nAktiekapital: 80 000\nVeikst dir: Simon Brick\nDisp: Olle Westerlund\nEtableringsår: 1970.\n\nCATINUS-GRYTHYTTAN AB\n\nPnr 703 69\n\nÖrebro, Bettorpsg 8. Tel\n019-1192 90. Bankgiro 103-5484.\nPost-giro 694952-3. Tga Catinus.\nTelex 73438 CATINUS S\n\n112\n\nVerksamhet: Utvecklar o\nmarknadsför distributionssystemen\nCombi-tainer o Expotainer\nVarunamn: Combitainer, Expotainer\nAktiekapital: 100 000\nVerkst dir: Ralf Borg\nEtableringsår: 1967\nSysterbolag till AB Grythyttans\nStålmöbler.\n\nCATOS GJUTERI AB\n\nPnr 280 70\n\nLönsboda, Glimåkrav. Tel 04\n79-208 75. Bankgiro 281-6601.\nPostgiro 338480-7. Telex 4644 OPIO S\nVerksamhet: Gråjärnsgjuteri\nAntal anställda: 25\nÅrsomsättning: 2000 000\nAktiekapital: 100 000\nVerkst dir: Hugo Cato\nEtableringsår: 1966.\n\nLINDVALL, AB EMIL\n\nPnr 382 00\n\nNybro, Box 40. S Industrig 7. Tel\n0481-100 31, 10313. Bankgiro\n661-9092. Postgiro 20544-3. Tga\nBobi-ner\n\nVerksamhet: Tillverkar hemmöbler\n\no svarvsaker\n\nAktiekapital: 60 000\n\nVerkst dir: Disp Göran Göransson\n\nEtableringsår: 1920.\n\nT EM\n\ngiro 19-5996. Postgiro 659855-2.\nTelex 10555\n\nVerksamhet Tillverkar\nelektronisk utrustning, skymningsreläer,\nvarningslampor för vägarbete samt\nvärme- o ljusreglering\nAntal anställda: 9\nÅrsomsättning: 1700 000\nAktiekapital: 110 000\nVerkst dir. Jakob Kinhult\nEtableringsår. 1958.",
    "structured": {
        "1": {
            "company_name": "SVENSK RUBBER, AB",
            "pnr": "330 15",
            "phone_number": "0370-503 70",
            "activity": "Gummiindustri, tillverkar slitbanegummi, tekniska artiklar i gummi, oljefast gummi",
            "employees": 70,
            "annual_turnover": 8500000,
            "capital": 400000,
            "key_personnel": [
                {
                    "name": "Ing Sture Andersson",
                    "position": "Verkst dir"
                }
            ],
            "establishment_year": 1950
        },
        "2": {
            "company_name": "ALFTA JÄRNHANDEL AB",
            "pnr": "822 00",
            "address": "Alfta, Box 18",
            "phone_number": "0271-104 00",
            "bank_details": {
                "bankgiro": "193-3076",
                "postgiro": "133959-7"
            },
            "activity": "Järnhandel, VVS-för-säljning o installationer, Tillverkar fiskmjärdar",
            "employees": 18,
            "annual_turnover": 4000000,
            "capital": 60000,
            "key_personnel": [
                {
                    "name": "G Svärdhagen",
                    "position": "Verkst dir"
                }
            ],
            "establishment_year": 1937
        },
        "3": {
            "company_name": "BIL & TRAKTOR",
            "pnr": "54100",
            "address": "Skövde, Mariestadsv 86",
            "phone_number": "0500-180 15",
            "bank_details": {
                "bankgiro": "210-3216",
                "postgiro": "417011-4"
            },
            "activity": "Säljer lantbruksmaskiner, traktorer o träskor",
            "employees": 15,
            "annual_turnover": 4000000,
            "key_personnel": [
                {
                    "name": "Dir Gunnar Karlén",
                    "position": "Chef"
                }
            ]
        },
        "4": {
            "company_name": "BIL & TRUCK, AB",
            "pnr": "40110",
            "address": "Göteborg 1, Odinsplatsen 9, Pack 1517",
            "phone_number": "031-8004 00",
            "activity": "Säljer personbilar, lastbilar, reservdelar",
            "employees": 740,
            "annual_turnover": 163000000,
            "capital": 4750000,
            "key_personnel": [
                {
                    "name": "Bertil Hälleby",
                    "position": "Verkst dir"
                }
            ],
            "establishment_year": 1930
        },
        "5": {
            "company_name": "BIL & TRUCK ÖRNSKÖLDSVIK AB",
            "pnr": "89101",
            "bank_details": {
                "bankgiro": "626-9039",
                "postgiro": "207898-8"
            },
            "activity": "Återförsäljare för AB Volvo, Göteborg",
            "employees": 83,
            "annual_turnover": 19500000,
            "capital": 500000,
            "key_personnel": [
                {
                    "name": "Sven Johansson",
                    "position": "Verkst dir"
                }
            ],
            "establishment_year": 1959
        },
        "6": {
            "company_name": "SVE",
            "capital": 100000,
            "key_personnel": [
                {
                    "name": "K T Friedrichs",
                    "position": "Verkst dir"
                }
            ],
            "establishment_year": 1932,
            "description": "Dotterbolag: AB Nordisk Helio-textil, ödsmål"
        },
        "7": {
            "company_name": "SVENSKA BILFABRIKEN, AB",
            "pnr": "13101",
            "address": "Nacka 1, Fack. Augustendalsv",
            "phone_number": "08-716 25 25",
            "bank_details": {
                "bankgiro": "568-9765",
                "postgiro": "2304-4"
            },
            "activity": "Motorrenoverings- o mekanisk verkstad",
            "capital": 100000,
            "establishment_year": 1928
        },
        "8": {
            "company_name": "SVENSKA BILGUMMIDEPÅN, AB",
            "pnr": "103 61",
            "address": "Stockholm 3, Sveav 52, Box 3094",
            "phone_number": "08-2234 60",
            "bank_details": {
                "bankgiro": "136-2490",
                "postgiro": "354496-2"
            },
            "activity": "Gummiverkstadsservice med försäljning o regummering",
            "capital": 5000,
            "key_personnel": [
                {
                    "name": "Carl Axel Seth",
                    "position": "Verkst dir"
                }
            ],
            "establishment_year": 1955
        },
        "9": {
            "company_name": "SVENSKA BILPACKNINGS. FABRIKEN H SÖDERSTRÖM AB",
            "pnr": "31201",
            "address": "Laholm 1, Box 21, Mäster Nilsg 11",
            "phone_number": "0430-12010",
            "bank_details": {
                "bankgiro": "659-1754",
                "postgiro": "176313-5"
            },
            "activity": "Tillverkar packningsmaterialet Svedoit samt tätningar, ringar, planpackningar, mellanlägg, shims, kederlist m m",
            "varunamn": "Svedoit",
            "employees": 50,
            "annual_turnover": 3000000,
            "capital": 100000,
            "key_personnel": [
                {
                    "name": "Fabr Henry Söderström",
                    "position": "Verkst dir"
                },
                {
                    "name": "Bertil Söderström",
                    "position": "Prod-chef o försäljn-chef"
                },
                {
                    "name": "Bengt-Ake Johansson",
                    "position": "Kamrer o inköpschef"
                }
            ],
            "establishment_year": 1925
        },
        "10": {
            "company_name": "SVENSKA BP OLJE-AKTIEBOLAG",
            "pnr": "102 51",
            "address": "Stockholm 27, Värtav 67, Box 27088",
            "phone_number": "08-22 30 40",
            "bank_details": {
                "bankgiro": "16-8788",
                "postgiro": "3109"
            },
            "activity": "Säljer bensin, eldningsolja o andra petroleumprodukter",
            "employees": 1160,
            "annual_turnover": 1044000,
            "capital": 50000000,
            "key_personnel": [
                {
                    "name": "Greger Lewenhaupt",
                    "position": "Verkst dir"
                }
            ],
            "establishment_year": 1927,
            "description": "Dotterbolag till The British Petroleum Company, Ltd, London"
        }
    }
}