{
    "original": "BÖRJES BYGGNADS AB\n\nPnr 795 00\n\nRättvik, Torgg 7. Tel 0248-110 80.\nBankgiron 469-9989, 789-0410.\nPostgiro 343134-3\nVerksamhet: Byggnadsentreprenör\nAntal anställda: 110\nÅrsomsättning: 11000 000\nAktiekapital: 20 000\nStyrelse: Byggmäst Hans Börjes\n(ordf), verkmäst John Skött\nChef: Byggmäst Hans Börjes\nEtableringsår: 1953.\n\nVRETSTORP-VERKEN, AB\n\nPnr 690 50\n\nVretstorp, Askersundsv 34. Box 36.\nTel 0582-604 70. Bankgiro 43-8877.\nPostgiro 13991-5. Tga Veve. Telex\n73247\n\nVeiksamhet: Konstruerar o tillverkar\nnärtransportanläggningar.\nTillverkar byggnadskranar\nAntal anställda: 140\nÅrsomsättning: 11000 000\nAktiekapital: 1 000 000\nStvrelse: Adv Lars Samzelius, dir\nHans Westberg, dir C J Westberg\nVerkst din Diploming C J Westberg\nEtableringsår: 1923\nDotterbolag till AB Nilssén &amp;\nWestberg, Karlstad.\n\nWRIGLEY SCANDINAVIA AB\n\nPnr 183 50\n\nTäby, Näsby Allé 6. Tel\n08-756 00 35. Bankgiro 700-0524.\nPostgiro 606920-7. Tga Spearmint\nVerksamhet: Huvuddistributör av\nWi-isley’s tuggummi i Slandinavien\nAntal anställda: 27\nVerkst dir: Ake Frisk\nEtableringsår: 1960.\n\nNORDISKA KOPEX AB\n\nPnr 11135\n\nStockholm, Kungsg 48. Tel\n08-2153 33, 109212. Bankgiro\n477-6811. Postgiro 256140-5. Tga\nClient\n\nVerksamhet: Säljer\nskorstensinsatser i syrafast stål, ventilationsrör\nAktiekapital: 5 000\nVerkst dir: Paul Isberg\nEtableringsår: 1964.\n\nNORDISKA LATEX AB,\nGUMMIFABRIKEN\n\nPnr 26093\n\nTorekov, Box 63. Tel 0431-633 45.\nBankgiro 65-0816. Postgiro 145422.\nTga Nolato\n\nVerksamhet: Tillverkar formgjorda,\nsprutade o stansade gummiartiklar\ni såväl natur- som syntetiskt gummi\nsamt doppade artiklar i latex.\nTillverkning sker av specialartiklar till\nindustrier samt standardartiklar till\nindustrier o grossister\nVarunamn: Nolato\nAntal anställda: 77\nÅrsomsättning: 5 000 000\nAktiekapital: 400 000\nStyrelse: Adv Bengt Linders (ordf),\nfabr Sven Boström, disp Krister\nJorlén\n\nVerkst dir: Krister Jorlén\nEtableringsår: 1938\nOmbildat till aktiebolag 1961.\n\nNORDISKA MASKINFILT\nAKTIEBOLAGET\n\nPnr 30103\n\nHalmstad 1, Box 161. Gamletullsg\n3. Tel 035-1040 00. Bankgiro\n423-7350, 530-1445. Postgiro 20577-5.\nTga Nordiskafilt.\nTelex 38058 NMA S\n\nNORDISKAPILT\n\nVerksamhet:\n\nMaskinbeklädnads gruppen:\nMaskinbeklädnad för pappers- o\ncellulosaindustrin\n\nIndustritextiliegruppen: Vävda,\nnålade o stampade produkter,\nheltäckande syntetfibermattor samt\nväggbeklädnad\n\nVarunamn:\n(maskinbeklädnadsgruppen): Combitex, Duratex, Duratex\nSpecial, Innertex, Novotex,\nPerma-tex, Porotex, Screentex, Shrinktex,\nThermotex, Thermotex Special\n(industritextiliegruppen): Bolltex,\nNorretex, Väggtex\nAntal anställda: 700\nÅrsomsättning: 70 000 000\nAktiekapital: 19 200 000\nStyrelse: Disp Erie Leander (ordf),\ndir Stig Eliasson, dir Birger\nEriksson, dir Erik Tenfält, dir Sven H\nManne, adv Per Håkan Osvald\nVerkst dir: Stig Eliasson\nEtableringsår: 1904.\n\nNORDISKA\nMATERIAL-BOLAGET\n\nPnr 104 65\n\nStockholm 15, Urvädersgränd 13.\nBox 15007. Tel 08-43 14 46.\nBankgiro 720-8564. Postgiro 158546-2\nVerksamhet: Agenturförsäljning av\nemballage o fritidsartiklar\nChef: Fru Marianne Gullström\nEtableringsår: 1908.\n\nBOBERG AB, BRÖDERNA\n\nPnr 791 00\n\nFalun, Matsarvsv 7. Tel 023-11514,\n232 90\n\nVerksamhet: Bok- o offsettryckeri.\nSpecialitet: Blankettryck o\nsnabbset\n\nAktiekapital: 75 000\nChef: E L Boberg\nEtableringsår: 1920.\n\nSONESSON AB, WILH\n\nPnr 211 24\n\nMalmö. Huvudkontor Styrsög 4. Tel\n040-93 50 00. Bankgiro 640-1103.\nPostgiro 37713-5. Tga Sonessons.\nTelex 3180 SONESON S\nFörsäljningsavdelning: 21613\nMalmö, Limhamnsv 108-110. Tel\n040-15 50 20\n\nVerksamhet: Transport o\nmaterialhantering. VVS-agenturer\nFörsäljningskontor: 116 21\nStockholm, Tjärhovsg 8. Tel 08-44 96 90\nMölndal, Krokslätts Parkg. Box\n5049, 402 21 Göteborg 5. Tel\n031-2002 40\n\n851 06 Sundsvall 1, Bankg 19. Box\n380. Tel 060-15 75 65\nVarunamn: Bassick, Geberit,\nKuglostatÆurotherm, Sonessons,\nSono\n\nAntal anställda: 740 (koncernen)\nÅrsomsättning: 102 000 000\n(koncernen)\n\nAktiekapital: 13 300000\nStyrelse: Bankdir Hans\nCavalli-Björkman (ordf), dir Sigvard\nHelle-stam, prof Folke Kristensson, disp\nErie Ljung, dir Alf Lüning\nVerkst dir: Alf Lüning\nEtableringsår: 1892\nOmbildat till aktiebolag 1912.\nWilh Sonesson AB är moderföretag\ninom Sonessonkoncernen där\ndessutom ingår Sonesson Pumpindustri\nAB Göteborg, Gothia Maskin AB,\nHöör, Sonesson Inredningar AB,\nMalmö, Sonesson Plast AB, Malmö,\nTraryd Filfabrik AB, Traiyd,\nSchmidts Boktryckeri AB,\nHälsingborg.\n\nSONET GRAMMOFON AB\n\nPnr 100 54\n\nStockholm 39, Artemisg 8. Box\n39062. Tel 08-67 05 40. Bankgiro\n\n721-3499. Postgiro 3742-4.\nTga Sonetmusic.\nTelex 10037 SONET S\nVerksamhet: Produktion av\ngrammofonskivor, konsertbureau,\nmusikförlag\n\nVarunamn: Sonet\nAntal anställda: 9\nÅrsomsättning: 7 000 000\nAktiekapital: 50 000\nVerkst dir: Gunnar Bergström\nEtableringsån 1956.\n\nRUNDVIRKE, AB\n\nPnr 826 02\n\nSöderhamn 2, Norralag 4 B. Box\n1020. Tel 0270-165 00. Bankgiro\n78-9529. Postgiro 289902. Tga\nRundvirke. Telex 81006\nVerksamhet: Sågverk o hyvleri.\nPlatsförsäljning av trävaror o\nbyggnadsmaterial. Export av\ntelegrafstolpar, special timmer, stammwaren\nAktiekapital: 200 000\nVerkst din Jägmäst Sven Ohlson\nEtableringsår: 1945.\n\nSYDSVENSK NEON AB\n\nPnr 212 28\n\nMalmö, Industrig 37. Tel 040-\n\n94 53 90. Bankgiro 64-4082.\nPostgiro 247313\n\nVerksamhet: Tillverkar plast- o\n\nneonskyltar\n\nAntal anställda: 10\n\nÅrsomsättning: 900 000\n\nAktiekapital: 10 000\n\nVeikst dir: Erwin Muhl\n\nEtableringsår: 1950.\n\nSYDSVENSKA DAGBLADET\nSNÄLLPOSTEN\n\nPnr 201 21 ’\n\nMalmö 1, Kruseg 19. Box 145. Tel\n040-93 6000. Postgiro 24550. Tga\nSydsvenskan\n\nVerksamhet: Daglig tidning\n(me-delnettoupplaga l:a halvåret 1970:\nvardagar 114 538 ex, söndagar\n153 722 ex)\n\nAvdelningskontor o red: 111 87\n\nStockholm, Birger Jarlsg 13. Box\n1728. Tel 08-23 34 50\nFilialer: Eslöv, Malmg 2. Tel\n0413-108 04\n\nHelsingborg, Järnvägsg 15. Tel\n042-18 02 90\n\nHässleholm, Andra Avenyn 5. Tel\n0451-102 21\n\nKristianstad. V Storg 49. Tel\n044-1161 80\n\nLandskrona, Storg 29. Tel\n0418-100 23\n\nLund, Kyrkog 17. Tel 046-14 0110\nTrelleborg, Alg 1. Tel 0410-102 80\nYstad, Hamng 12. Tel 0411-108 81\nAntal anställda: 1 532\nÅrsomsättning: 95 220 000\nAktiekapital: 2 400 000\nVerkst dir: Olof Wahlgren\nEtableringsår: 1870\nÄgare: Sydsvenska Dagbladets AB.\n\nSYDSVENSKA INGENJÖRS.\nBYRÅN AB\n\nPnr 217 42\n\nMalmö, Kronoborgsv 1 B. Tel\n040-392 00. Bankgiro 640-2960.\nPostgiro 248737-9. Tga Sydkonsult\nVerksamhet: Konsulterande\ningenjörsbyrå\n\nAktiekapital: 60 000\nVerkst dir: Bertil Rylander\nEtableringsår 1949.\n\nSYDSVENSKA KLICHÉ &amp;\nTRYCKERI AB\n\nPnr 211 25\n\nMalmö, N Vallg 16. Tel\n040-12 16 60, 12 19 60. Bankgiro\n641-2274. Postgiro 24587-8\nAntal anställda: 20\nÅrsomsättning: 90 0 000\nAktiekapital: 50 000\nVerkst dir Boktr Emil NielsSn\nEtableringsår: 1902.\n\nRÄP\n\nAktiekapital: 400 000\nVerkst dir: Gunnar Rydén\nEtableringsår: 1904.\n\nFALL, AB C I\n\nPnr 632 29\n\nEskilstuna, Hejarg 2. Tel 016-\n\n13 05 83. 13 65 83. Bankgiro\n601-3395. Postgiro 10784-7. Tga\nFallab\n\nVerksamhet: Tillverkar borrar för\nträbearbetning samt skruvmejslar\nAktiekapital: 250 000\nVerkst dir: Fabr Isidor Fall\nEtableringsår: 1894.\n\ndahrenträd, ab\n\nPnr 46040\n\nNossebro. Tel 0512-460 80.\nBankgiro 215-4888. Postgiro 42788-0.\nTelex 4 2064\n\nVerksamhet: Lindningstråd o elektr\nisolermaterial\n\nFilialer: Stockholm, Göteborg,\nMalmö, Sundsvall\nAntal anställda: 107\nÅrsomsättning: 40 000 000\nAktiekapital: 1900 000\nVerkst dir: Civiling S Dahrén\nEtableringsår: 1945.\n\ndarlins mek verkstad ab,\nbruderna\n\nPnr 290 62\n\nVilshult. Tel 0454-712 50\nVerksamhet: Tillverkar\nfrys-produk-ter, torkskåp o tvättmaskiner\nAntal anställda: 77\nÅrsomsättning: 11000 000\nAktiekapital: 80000\nVerkst din Gösta Darlin (Osby)\nEtableringsår: 1956.",
    "structured": {
        "swedish_firms": [
            {
                "company_name": "BÖRJES BYGGNADS AB",
                "pnr": "795 00",
                "address": "Rättvik, Torgg 7",
                "phone_number": "0248-110 80",
                "bank_details": {
                    "bankgiro": "469-9989",
                    "postgiro": "789-0410"
                },
                "activity": "Byggnadsentreprenör",
                "employees": 110,
                "annual_turnover": 11000000,
                "capital": 20000,
                "key_personnel": [
                    {
                        "name": "Byggmäst Hans Börjes",
                        "position": "ordf"
                    },
                    {
                        "name": "John Skött",
                        "position": "verkmäst"
                    }
                ],
                "establishment_year": 1953
            },
            {
                "company_name": "VRETSTORP-VERKEN, AB",
                "pnr": "690 50",
                "address": "Vretstorp, Askersundsv 34, Box 36",
                "phone_number": "0582-604 70",
                "bank_details": {
                    "bankgiro": "43-8877",
                    "postgiro": "13991-5"
                },
                "activity": "Konstruerar o tillverkar närtransportanläggningar. Tillverkar byggnadskranar",
                "employees": 140,
                "annual_turnover": 11000000,
                "capital": 1000000,
                "establishment_year": 1923
            },
            {
                "company_name": "WRIGLEY SCANDINAVIA AB",
                "pnr": "183 50",
                "address": "Täby, Näsby Allé 6",
                "phone_number": "08-756 00 35",
                "bank_details": {
                    "bankgiro": "700-0524",
                    "postgiro": "606920-7"
                },
                "activity": "Huvuddistributör av Wi-isley’s tuggummi i Slandinavien",
                "employees": 27,
                "establishment_year": 1960
            },
            {
                "company_name": "NORDISKA KOPEX AB",
                "pnr": "11135",
                "address": "Stockholm, Kungsg 48",
                "phone_number": "08-2153 33, 109212",
                "bank_details": {
                    "bankgiro": "477-6811",
                    "postgiro": "256140-5"
                },
                "activity": "Säljer skorstensinsatser i syrafast stål, ventilationsrör",
                "capital": 5000,
                "key_personnel": [
                    {
                        "name": "Paul Isberg",
                        "position": "Verkst dir"
                    }
                ],
                "establishment_year": 1964
            },
            {
                "company_name": "NORDISKA LATEX AB, GUMMIFABRIKEN",
                "pnr": "26093",
                "address": "Torekov, Box 63",
                "phone_number": "0431-633 45",
                "bank_details": {
                    "bankgiro": "65-0816",
                    "postgiro": "145422"
                },
                "activity": "Tillverkar formgjorda, sprutade o stansade gummiartiklar i såväl natur- som syntetiskt gummi samt doppade artiklar i latex. Tillverkning sker av specialartiklar till industrier samt standardartiklar till industrier o grossister",
                "employees": 77,
                "annual_turnover": 5000000,
                "capital": 400000,
                "key_personnel": [
                    {
                        "name": "Adv Bengt Linders",
                        "position": "ordf"
                    },
                    {
                        "name": "Sven Boström",
                        "position": "fabr"
                    },
                    {
                        "name": "Krister Jorlén",
                        "position": "disp"
                    }
                ],
                "establishment_year": 1938
            },
            {
                "company_name": "NORDISKA MASKINFILT AKTIEBOLAGET",
                "pnr": "30103",
                "address": "Halmstad 1, Box 161, Gamletullsg 3",
                "phone_number": "035-1040 00",
                "bank_details": {
                    "bankgiro": "423-7350, 530-1445",
                    "postgiro": "20577-5"
                },
                "activity": "Maskinbeklädnads gruppen: Maskinbeklädnad för pappers- o cellulosaindustrin. Industritextiliegruppen: Vävda, nålade o stampade produkter, heltäckande syntetfibermattor samt väggbeklädnad",
                "employees": 700,
                "annual_turnover": 70000000,
                "capital": 19200000,
                "key_personnel": [
                    {
                        "name": "Disp Erie Leander",
                        "position": "ordf"
                    },
                    {
                        "name": "Stig Eliasson",
                        "position": "dir"
                    }
                ],
                "establishment_year": 1904
            }
        ]
    }
}