{
    "original": "AKTIV-FISCHER AB\n\nPnr 740 41\n\nMorgongåva. Tel 0224-602 60. Tga\nAktiv. Telex 7533\nVerksamhet: Tillverkar\nslåttermaskiner, skördetröskor o snöfordon\nVarunamn: Aktiv, Aros, Snow-Trac,\nSnow-Tric, Trac-Master\nAktiekapital: 1 340 000\nVerkst dir: Peter Sahlin\nEtableringsår 1874\nOmbildat till aktiebolag 1908.\n\nAKUMA AB\n\nPnr 282 00\n\nTyringe. Tel 0451-509 60\nVerksamhet: Träindustri. Butiks-,\nsjukhus- o skolinredningar\nAntal anställda: 160\nÅrsomsättning: 15 000 000\nAktiekapital: 200 000\nVerkst dir: Bo Svahn\nEtableringsår: 1933.\n\nWISKANIA. SKO AB\n\nPnr 500 06\n\nBorås 6. Box 66091. Gässlösav 28.\nTel 033-12 77 60. Bankgiro\n531-2111\n\nVerksamhet: Tillverkar skor\nAktiekapital: 10 000\nVerkst dir: Gottfrid Rangert\nEtableringsår: 1948.\n\nBORJESON &amp; CO,\nHANDELSBOLAGET BRYNOLF\n\nPnr 182 36\n\nDanderyd, Enebybergsv 16. Tel\n08-755 28 20. Tga Bryson\nVerksamhet: Grossist- o\nagentur-firma i skrivmateriel,\ntelexmateri-el o registreringspapper för\nmätinstrument\n\nBolagsmän: Börje Börjeson, Lars\nBörjeson\n\nEtableringsår: 1917.\n\nEKELUND &amp; CO\n\nPnr 570 80\n\nVirserum. Tel 0495-31045.\nBankgiro 857-8254. Postgiro 14772-8\nVerksamhet: Tillverkar\nsittgrupper o fåtöljer\nAntal anställda: 40\nChef: Disp Lars Ekelund\nEtableringsår 1924.\n\nLOVSJO, AB ESKIL\n\nPnr 590 20\n\nMantorp. Tel 0142-209 2 0. Bankgiro\n120-1656. Postgiro 25060-5. Tga\nElab\n\nVerksamhet: Tillverkar\nkristall-armaturer samt EUox skyddslock\nför el-spisplattor\nVarunamn: Ellox\nAntal anställda: 45\nÅrsomsättning: 3 500 000\nAktiekapital: 300 000\nVerkst dir: Disp Eskil Lövsjö\nExportchef: Göran Fogelström\nEtableringsår: 1953.\n\nKIMSTADVERKEN AB\n\nPnr 610 20\n\nKimstad, Melby gård. Tel\n011-541 50. Bankgiro 824-6092.\nPostgiro 137840-5\n\nVerksamhet: Tillverkar balk- o\ngrovplåtskonstruktioner, detaljer\nför flyghinder, spannmålssilor o\ntorkar. Utför gas- o elsvetsning\nsamt mekaniska arbeten\n\nAntal anställda: 56\nÅrsomsättning: 4 500 000\nAktiekapital: 50 000\nVerkst dir: Karl Ake Magnusson\nEtableringsår: 1966.\n\nDAKOMA, AB\n\nPnr 21135\n\nMalmö, Själbodg 2 C. Tel\n040-339 93, 38250. Bankgiro 260-0732.\nPostgiro 245397-5. Tga Dakoma\nVerksamhet: Import o försäljning\nav kontorsmaskiner\nAntal anställda: 8\nAktiekapital: 10 000\nVerkst dir: Erik Hingström\nEtableringsår: 1946.\n\nDAL, DAHL\n\nDAHL AB, BRÖDERNA\n\nPnr 415 02\n\nGöteborg, von Holtensg 9. Tel\n031-15 9883, 15 9890. Bankgiro\n848-0162. Postgiro 240926-6\nVerksamhet: Tillverkar, säljer o\nuthyr presenningar\nVerkst dir: Ake Dahl\nEtableringsår: 1945.\n\nSTRÅBRUKEN AB\n\nPnr 100 41\n\nStockholm 26, Villag 6. Fack. Tel\n08-24 82 00. Bankgiro 330-0310.\nPostgiro 1275-7. Tga Rockproducts.\nTelex 10134\n\nVerksamhet: Tillverkar o säljer\nbyggnadsmaterial o eldfast\ninfod-ringsmaterial för stålindustrin.\nGrus rörelse\n\nRegionskonton 203 14 Malmö 4,\n\nMalmborgsg 4. Box 4288. Tel\n040-93 20 10, 93 2011\n\n42121 Västra Frölunda 1, Topasg\n40. Box 52. Tel 031-45 46 27\n70103 Örebro 1, Slöjdg 8. Box 114.\nTel 019-1102 25\n\n851 03 Sundsvall 1, Kyrkog 21. Box\n128. Tel 060-1244 80, 124481\nAntal anställda: 450\nÅrsomsättning: 50 000 000\nAktiekapital: 4 000 000\nVerkst dir: Olof Andersson\nEtableringsår: 1906.\n\nBANDINDUSTRI, AB\n\nPnr 692 00\n\nKumla. Tel 019-709 15. Tga Bandi\nVerksamhet: Elastiska o oelastiska\ntextilband, skoband o spets\nAktiekapital: 1 350 000\nVerkst dir: Anders Medin\nEtableringsår: 1938.\n\nARA\n\nARA NORDSVENSKA AB\n\nPnr 94101\n\nPiteå 1, Box 43. Tel 0911-680 00.\nBankgiro 400-7571. Postgiro\n66950-7\n\nVerksamhet: Säljer eldnings-,\ndiesel- o smörjoljor\nAktiekapital: 5 000\nEtableringsår: 1968.",
    "structured": {
        "1": {
            "company_name": "AKTIV-FISCHER AB",
            "pnr": "740 41",
            "address": "Morgongåva",
            "phone_number": "0224-602 60",
            "activity": "Tillverkar slåttermaskiner, skördetröskor o snöfordon",
            "capital": 1340000,
            "key_personnel": [
                {
                    "name": "Peter Sahlin",
                    "position": "Verkst dir"
                }
            ],
            "establishment_year": 1874
        },
        "2": {
            "company_name": "AKUMA AB",
            "pnr": "282 00",
            "address": "Tyringe",
            "phone_number": "0451-509 60",
            "activity": "Träindustri. Butiks-, sjukhus- o skolinredningar",
            "employees": 160,
            "annual_turnover": 15000000,
            "capital": 200000,
            "key_personnel": [
                {
                    "name": "Bo Svahn",
                    "position": "Verkst dir"
                }
            ],
            "establishment_year": 1933
        },
        "3": {
            "company_name": "WISKANIA. SKO AB",
            "pnr": "500 06",
            "address": "Borås 6. Box 66091. Gässlösav 28",
            "phone_number": "033-12 77 60",
            "bank_details": {
                "bankgiro": "531-2111"
            },
            "activity": "Tillverkar skor",
            "capital": 10000,
            "key_personnel": [
                {
                    "name": "Gottfrid Rangert",
                    "position": "Verkst dir"
                }
            ],
            "establishment_year": 1948
        },
        "4": {
            "company_name": "BORJESON & CO, HANDELSBOLAGET BRYNOLF",
            "pnr": "182 36",
            "address": "Danderyd, Enebybergsv 16",
            "phone_number": "08-755 28 20",
            "activity": "Grossist- o agentur-firma i skrivmateriel, telexmateri-el o registreringspapper för mätinstrument",
            "key_personnel": [
                {
                    "name": "Börje Börjeson"
                },
                {
                    "name": "Lars Börjeson"
                }
            ],
            "establishment_year": 1917
        },
        "5": {
            "company_name": "EKELUND & CO",
            "pnr": "570 80",
            "address": "Virserum",
            "phone_number": "0495-31045",
            "bank_details": {
                "bankgiro": "857-8254",
                "postgiro": "14772-8"
            },
            "activity": "Tillverkar sittgrupper o fåtöljer",
            "employees": 40,
            "key_personnel": [
                {
                    "name": "Disp Lars Ekelund",
                    "position": "Chef"
                }
            ],
            "establishment_year": 1924
        },
        "6": {
            "company_name": "LOVSJO, AB ESKIL",
            "pnr": "590 20",
            "address": "Mantorp",
            "phone_number": "0142-209 2 0",
            "bank_details": {
                "bankgiro": "120-1656",
                "postgiro": "25060-5"
            },
            "activity": "Tillverkar kristall-armaturer samt EUox skyddslock för el-spisplattor",
            "employees": 45,
            "annual_turnover": 3500000,
            "capital": 300000,
            "key_personnel": [
                {
                    "name": "Disp Eskil Lövsjö",
                    "position": "Verkst dir"
                },
                {
                    "name": "Göran Fogelström",
                    "position": "Exportchef"
                }
            ],
            "establishment_year": 1953
        },
        "7": {
            "company_name": "KIMSTADVERKEN AB",
            "pnr": "610 20",
            "address": "Kimstad, Melby gård",
            "phone_number": "011-541 50",
            "bank_details": {
                "bankgiro": "824-6092",
                "postgiro": "137840-5"
            },
            "activity": "Tillverkar balk- o grovplåtskonstruktioner, detaljer för flyghinder, spannmålssilor o torkar. Utför gas- o elsvetsning samt mekaniska arbeten",
            "employees": 56,
            "annual_turnover": 4500000,
            "capital": 50000,
            "key_personnel": [
                {
                    "name": "Karl Ake Magnusson",
                    "position": "Verkst dir"
                }
            ],
            "establishment_year": 1966
        },
        "8": {
            "company_name": "DAKOMA, AB",
            "pnr": "21135",
            "address": "Malmö, Själbodg 2 C",
            "phone_number": "040-339 93, 38250",
            "bank_details": {
                "bankgiro": "260-0732",
                "postgiro": "245397-5"
            },
            "activity": "Import o försäljning av kontorsmaskiner",
            "employees": 8,
            "capital": 10000,
            "key_personnel": [
                {
                    "name": "Erik Hingström",
                    "position": "Verkst dir"
                }
            ],
            "establishment_year": 1946
        },
        "9": {
            "company_name": "DAL, DAHL",
            "pnr": "415 02",
            "address": "Göteborg, von Holtensg 9",
            "phone_number": "031-15 9883, 15 9890",
            "activity": "Tillverkar, säljer o uthyr presenningar",
            "key_personnel": [
                {
                    "name": "Ake Dahl",
                    "position": "Verkst dir"
                }
            ],
            "establishment_year": 1945
        },
        "10": {
            "company_name": "STRÅBRUKEN AB",
            "pnr": "100 41",
            "address": "Stockholm 26, Villag 6",
            "phone_number": "08-24 82 00",
            "bank_details": {
                "bankgiro": "330-0310",
                "postgiro": "1275-7"
            },
            "activity": "Tillverkar o säljer byggnadsmaterial o eldfast infod-ringsmaterial för stålindustrin. Grus rörelse",
            "regionskonton": {
                "203 14 Malmö 4": {
                    "address": "Malmborgsg 4. Box 4288",
                    "phone_number": "040-93 20 10, 93 2011"
                },
                "42121 Västra Frölunda 1": {
                    "address": "Topasg 40. Box 52",
                    "phone_number": "031-45 46 27"
                },
                "70103 Örebro 1": {
                    "address": "Slöjdg 8. Box 114",
                    "phone_number": "019-1102 25"
                },
                "851 03 Sundsvall 1": {
                    "address": "Kyrkog 21. Box 128",
                    "phone_number": "060-1244 80, 124481"
                }
            },
            "employees": 450,
            "annual_turnover": 50000000,
            "capital": 4000000,
            "key_personnel": [
                {
                    "name": "Olof Andersson",
                    "position": "Verkst dir"
                }
            ],
            "establishment_year": 1906
        },
        "11": {
            "company_name": "BANDINDUSTRI, AB",
            "pnr": "692 00",
            "address": "Kumla",
            "phone_number": "019-709 15",
            "activity": "Elastiska o oelastiska textilband, skoband o spets",
            "capital": 1350000,
            "key_personnel": [
                {
                    "name": "Anders Medin",
                    "position": "Verkst dir"
                }
            ],
            "establishment_year": 1938
        },
        "12": {
            "company_name": "ARA",
            "pnr": "94101",
            "address": "Piteå 1, Box 43",
            "phone_number": "0911-680 00",
            "bank_details": {
                "bankgiro": "400-7571",
                "postgiro": "66950-7"
            },
            "activity": "Säljer eldnings-, diesel- o smörjoljor",
            "capital": 5000,
            "establishment_year": 1968
        }
    }
}