{
    "original": "haby industri ab\n\nPnr 450 50\n\nMunkedal, Postl 2840. Tel\n0524-23050, 23180. Bankgiro 439-4268.\nPostgiro 284593-1\nVerksamhet: Flaggstänger o\ntrap-por 1 stål, maii: kapsvagnar samt\nhast- o traktorvagnar\nAntal anställda: 45\nÅrsomsättning: 250000U\nAktiekapital: 100 000\nVerkst dir: Matts V Samuelsson\nEtableringsår: 1945.\n\nFRIGOSCANDIA CONTRACTING\nAB\n\nPnr 251 01\n\nHelsingborg 1, Fack. Tel\n042-12 6170. Bankgiro 269-1319.\nPostgiro 468044-3. Tga Frigoscand.\nTelex 72332 FRICON S\nVerksamhet: Konstruerar o säljer\nkontinuerliga\ninfrysningsanlägg-ningar för livsmedelsindustrin\nsamt säljer konsulttjänster inom\nfryshusprojektering o -byggnation\nVarunamn: Flofreeze, Gyrofreeze,\nCartofreeze, Pellofreeze,\nTiro-freeze\n\nVerkst dir: Civiling Per-Oskar\nPersson\n\nEtableringsår: 1962.\n\nFRIGOSCANDIA TRANSPORT\nAB\n\nPnr 25101\n\nHelsingborg 1, Fack. Landskronav\n11. Tel 042-1261 30. Bankgiro\n269-0410. Postgiro 83240-2. Tga\nFreeze. Telex 72261\nVerksamhet: Utför inrikes o\nutrikes landsvägs- o\njärnvägstransporter med för frystransport\nspecialbyggda högisolerade bilar o\njärnvägsvagnar samt värmetransporter.\nTemperaturer från -30° - + 20° C.\nTemperaturgaranti\nAntal anställda: 19\nAktiekapital: 500 000\nVerkst dir: Klas Ericsson\nEtableringsår: 1956\nNamnändring 1968.\n\nFRIMA, AB\n\nPnr 14123\n\nHuddinge 1, Box 1147. Dalhemsv\n44. Tel 08-774 47 20. Bankgiro\n131-5359. Postgiro 350575-7.\nTelex 10595\n\nVerksamhet: Säljer fontäner,\nbassänger, trädgårdsbelysningar\no tillbehör\n\nVerkst dir: Rune Runbjer\nEtableringsår: 1954.\n\nTVÅ SOMMAR E, AB\n\nPnr 414 80\n\nGöteborg, Axel Dahlströms torg 1.\nTel 031-418846, 418847.\nBankgiro 853-0081. Postgiro 240480-4\nVerksamhet Tillverkar bad- o\nfritidsartiklar\nAntal anställda: 20\nAktiekapital: 30 000\nVerkst din Ing Erik Berglund\nEtableringsån 1969.\n\nTVÄRSKOGS TRÄINDUSTRI,\nAB\n\nPnr 380 20\n\nLjunghyholm, Postl 3646. Tel\n0480-342 70. Bankgiro 853-6179.\nPostgiro 139377-6\n\nVeiksamhet: Tillverkar o säljer\nsågade o hyvlade trävaror på inland o\nexport\n\nAntal anställda: 24\nÅrsomsättning: 4 000000\nAktiekapital: 300 000\nVerkst dir: Ake L Olsson\nEtableringsån 1934.\n\nLAXÅ PAPPERSBRUK, AB\n\nPnr 695 00\n\nLaxå. Tel 0584-108 90. Telex 1258.\nTga Laxåpaper\n\nVerksamhet: Tillverkar TH\nfinpapper o kartong, tapetpapper\nAntal anställda: 100\nÅrsomsättning: 8 000 000\nAktiekapital: 550 000\nStyrelse: Tekn dr Marcus\nWallenberg (ordf), dir Einar Harald, disp\nSigge Rudengren\nVerkst dir: Sigge Rudengren\nEtableringsår: 1938.\n\nLAXÅ SVETS- &amp; MEK\nVERKSTAD AB\n\nPnr 69501\n\nLaxå 1, Box 8. Tel 0584-100 98,\n110 98. Bankgiro 461-6074. Postgiro\n165532-3\n\nVerksamhet: Tillverkar lastbankar\no hydraulisk vändskivelyft\nVarunamn: Laxå-Banken\nAntal anställda: 23\nÅrsomsättning: 1500000\nAktiekapital: 45 000\nVerkst dir: Ing Ake Persson\nEtableringsår: 1947.\n\nGASTRO AB\n\nPnr 116 48\n\nStockholm, Bengt Ekehjelmsg 2.\nTel 08-44 44 80, 4418 44. Bankgiro\n578-9896. Postgiro 654960^\nVerksamhet: Partiförsäljning av\nlax, fågel o kött\nAntal anstäUda: 4\nÅrsomsättning: 2000 000\nAktiekapital: 10 000\nVerkst dir: Rolf Olsson\nEtableringsår: 1961.\n\nÅKERLUND &amp; RAUSING, AB\n\nPnr 22101\n\nLund 1, Fack. S Industriområdet.\nTel 046-12 4 2 00. Postgiro\n14100-2. Tga Akerlundrausing.\nTelex 3350\n\nVerksamhet: Tillverkar\nkonsumentförpackningar av papper, kartong,\nplast o aluminium samt\nkombinationer av dessa material\nAntal anställda: 1 800\nÅrsomsättning: 215 000 000\nAktiekapital: 20 000 000\nVeikst dir: Bertil Turesson\nEtableringsån 1928.\n\nÅKERLUND MÅLERIFIRMA\nAB, LENNART\n\nPnr 17104\n\nSolna 4, Box 401. Storg 9. Tel\n08-82 00 05. Bankgiro 332-1338.\nPostgiro 157015-9\n\nVerksamhet; Utför reparations-,\nombyggnads- o nybyggnadsmålning\nAntal anställda: 120\nÅrsomsättning: 7 000 000\nAktiekapital: 75 000\nVerkst din Lennart Åkerlund\nEtableringsån 1931.\n\nLEC\n\nAktiekapital: 500 000\nVerkst dir: Börje Leckner\nEtableringsår: 1946.\n\nSWANBERG, AB W R\n\nPnr 45101\n\nUddevalla 1, N Hamng 1. Box 24.\nTel 0522-148 00. Bankgiro 42-8038.\nPostgiro 47218. Tga Swanship.\nTelex 42075\n\nVerksamhet: Skeppsmäkleri,\nbefraktning o spedition\nAntal anställda: 11\nAktiekapital: 100 000\nVerkst dir: Yngve Olofson\nEtableringsår: 1876\nOmbildat till aktiebolag 1942.\n\nSWANBOARD AB\n\nPnr 40127\n\nGöteborg 1, Viktor Rydbergsg 10.\nBox 460. Tel 031-20 0140. Bankgiro\n500-6572. Postgiro 49280.\nTga Swanboard. Telex 2253\nVerksamhet: Säljer wallboard o\npapp på hemmamarknad o export\nför Svaneholms AB, Svanskog\nVarunamn: Swanboard\nAntal anställda: 20\nÅrsomsättning: 30 000 000\nAktiekapital: 500 000\nVerkst dir: Leif Brynteson\nEtableringsår: 1944.\n\nSVANBORG &amp; HOLMQVIST\nVERKSTAD\n\nPnr 942 00\n\nAlvsbyn, Box 57. Tel 0929-12271,\n122 72. Bankgiro 37-3005. Postgiro\n386801\n\nVerksamhet: Tillverkar\nhelautomatiska bastukaminer samt rostfria\nprodukter såsom expansionskärl,\nbåttankar o båtbeslag\nVarunamn: Sisu\nAntal anställda: 14\nÅrsomsättning: 1500 000\nChef: Sune Holmqvist\nEtableringsår: 1963.\n\nALBA TIMBER CO, AB\n\nPnr 660 51\n\nNorsbron. Tel 054-410 75. Tga Alba\nVerksamhet: Förmedlar o\nexporterar pappersved, timmer, stolpar,\nprops m m samt sågade o hyvlade\nträvaror\n\nAktiekapital: 15 000\nVerkst dir: Per Hammarberg\nEtableringsår: 1953.\n\nSPÅNGA ROSTFRITT, AB\n\nPnr 175 00\n\nJakobsberg, Nettov 5. Tel\n0758-310 00. Bankgiro 576-2968.\nPostgiro 361219-9\n\nVerksamhet: Tillverkar rostfria\nin-redningdetaljer m m till byggnads-,\nlivsmedels- samt kem-tekn industri\nAntal anstäUda: 23\nAktiekapital: 5 000\nVerkst dir: Olle Engberg\nEtableringsår: 1956.",
    "structured": {
        "1": {
            "company_name": "HABY INDUSTRI AB",
            "pnr": "450 50",
            "address": "Munkedal, Postl 2840",
            "phone_number": "0524-23050, 23180",
            "bank_details": {
                "bankgiro": "439-4268",
                "postgiro": "284593-1"
            },
            "activity": "Flaggstänger o trap-por 1 stål, maii: kapsvagnar samt hast- o traktorvagnar",
            "employees": 45,
            "annual_turnover": 250000,
            "capital": 100000,
            "key_personnel": [
                {
                    "name": "Matts V Samuelsson",
                    "position": "Verkst dir"
                }
            ],
            "establishment_year": 1945
        },
        "2": {
            "company_name": "FRIGOSCANDIA CONTRACTING AB",
            "pnr": "251 01",
            "address": "Helsingborg 1, Fack",
            "phone_number": "042-12 6170",
            "bank_details": {
                "bankgiro": "269-1319",
                "postgiro": "468044-3"
            },
            "activity": "Konstruerar o säljer kontinuerliga infrysningsanlägg-ningar för livsmedelsindustrin samt säljer konsulttjänster inom fryshusprojektering o -byggnation",
            "establishment_year": 1962
        },
        "3": {
            "company_name": "FRIGOSCANDIA TRANSPORT AB",
            "pnr": "25101",
            "address": "Helsingborg 1, Fack. Landskronav 11",
            "phone_number": "042-1261 30",
            "bank_details": {
                "bankgiro": "269-0410",
                "postgiro": "83240-2"
            },
            "activity": "Utför inrikes o utrikes landsvägs- o järnvägstransporter med för frystransport specialbyggda högisolerade bilar o järnvägsvagnar samt värmetransporter. Temperaturer från -30° - + 20° C. Temperaturgaranti",
            "employees": 19,
            "capital": 500000,
            "key_personnel": [
                {
                    "name": "Klas Ericsson",
                    "position": "Verkst dir"
                }
            ],
            "establishment_year": 1956
        },
        "4": {
            "company_name": "FRIMA, AB",
            "pnr": "14123",
            "address": "Huddinge 1, Box 1147. Dalhemsv 44",
            "phone_number": "08-774 47 20",
            "bank_details": {
                "bankgiro": "131-5359",
                "postgiro": "350575-7"
            },
            "activity": "Säljer fontäner, bassänger, trädgårdsbelysningar o tillbehör",
            "key_personnel": [
                {
                    "name": "Rune Runbjer",
                    "position": "Verkst dir"
                }
            ],
            "establishment_year": 1954
        },
        "5": {
            "company_name": "TVÅ SOMMAR E, AB",
            "pnr": "414 80",
            "address": "Göteborg, Axel Dahlströms torg 1",
            "phone_number": "031-418846, 418847",
            "bank_details": {
                "bankgiro": "853-0081",
                "postgiro": "240480-4"
            },
            "activity": "Tillverkar bad- o fritidsartiklar",
            "employees": 20,
            "capital": 30000,
            "key_personnel": [
                {
                    "name": "Ing Erik Berglund",
                    "position": "Verkst din"
                }
            ],
            "establishment_year": 1969
        },
        "6": {
            "company_name": "TVÄRSKOGS TRÄINDUSTRI, AB",
            "pnr": "380 20",
            "address": "Ljunghyholm, Postl 3646",
            "phone_number": "0480-342 70",
            "bank_details": {
                "bankgiro": "853-6179",
                "postgiro": "139377-6"
            },
            "activity": "Tillverkar o säljer sågade o hyvlade trävaror på inland o export",
            "employees": 24,
            "annual_turnover": "4 000000",
            "capital": 300000,
            "key_personnel": [
                {
                    "name": "Ake L Olsson",
                    "position": "Verkst dir"
                }
            ],
            "establishment_year": 1934
        },
        "7": {
            "company_name": "LAXÅ PAPPERSBRUK, AB",
            "pnr": "695 00",
            "address": "Laxå",
            "phone_number": "0584-108 90",
            "telex": "1258",
            "activity": "Tillverkar TH finpapper o kartong, tapetpapper",
            "employees": 100,
            "annual_turnover": "8 000 000",
            "capital": 550000,
            "key_personnel": [
                {
                    "name": "Sigge Rudengren",
                    "position": "Verkst dir"
                }
            ],
            "establishment_year": 1938
        },
        "8": {
            "company_name": "LAXÅ SVETS- & MEK VERKSTAD AB",
            "pnr": "69501",
            "address": "Laxå 1, Box 8",
            "phone_number": "0584-100 98, 110 98",
            "bank_details": {
                "bankgiro": "461-6074",
                "postgiro": "165532-3"
            },
            "activity": "Tillverkar lastbankar o hydraulisk vändskivelyft",
            "employees": 23,
            "annual_turnover": 1500000,
            "capital": 45000,
            "key_personnel": [
                {
                    "name": "Ing Ake Persson",
                    "position": "Verkst dir"
                }
            ],
            "establishment_year": 1947
        },
        "9": {
            "company_name": "GASTRO AB",
            "pnr": "116 48",
            "address": "Stockholm, Bengt Ekehjelmsg 2",
            "phone_number": "08-44 44 80, 4418 44",
            "bank_details": {
                "bankgiro": "578-9896",
                "postgiro": "654960^"
            },
            "activity": "Partiförsäljning av lax, fågel o kött",
            "employees": 4,
            "annual_turnover": "2000 000",
            "capital": 10000,
            "key_personnel": [
                {
                    "name": "Rolf Olsson",
                    "position": "Verkst dir"
                }
            ],
            "establishment_year": 1961
        },
        "10": {
            "company_name": "ÅKERLUND & RAUSING AB",
            "pnr": "22101",
            "address": "Lund 1, Fack. S Industriområdet",
            "phone_number": "046-12 4 2 00",
            "postgiro": "14100-2",
            "activity": "Tillverkar konsumentförpackningar av papper, kartong, plast o aluminium samt kombinationer av dessa material",
            "employees": 1800,
            "annual_turnover": "215 000 000",
            "capital": 20000000,
            "key_personnel": [
                {
                    "name": "Bertil Turesson",
                    "position": "Verkst dir"
                }
            ],
            "establishment_year": 1928
        },
        "11": {
            "company_name": "ÅKERLUND MÅLERIFIRMA AB, LENNART",
            "pnr": "17104",
            "address": "Solna 4, Box 401. Storg 9",
            "phone_number": "08-82 00 05",
            "bank_details": {
                "bankgiro": "332-1338",
                "postgiro": "157015-9"
            },
            "activity": "Utför reparations-, ombyggnads- o nybyggnadsmålning",
            "employees": 120,
            "annual_turnover": "7 000 000",
            "capital": 75000,
            "key_personnel": [
                {
                    "name": "Lennart Åkerlund",
                    "position": "Verkst din"
                }
            ],
            "establishment_year": 1931
        },
        "12": {
            "company_name": "LEC",
            "capital": 500000,
            "key_personnel": [
                {
                    "name": "Börje Leckner",
                    "position": "Verkst dir"
                }
            ],
            "establishment_year": 1946
        },
        "13": {
            "company_name": "SWANBERG, AB W R",
            "pnr": "45101",
            "address": "Uddevalla 1, N Hamng 1. Box 24",
            "phone_number": "0522-148 00",
            "bank_details": {
                "bankgiro": "42-8038",
                "postgiro": "47218"
            },
            "activity": "Skeppsmäkleri, befraktning o spedition",
            "employees": 11,
            "capital": 100000,
            "key_personnel": [
                {
                    "name": "Yngve Olofson",
                    "position": "Verkst dir"
                }
            ],
            "establishment_year": 1876
        },
        "14": {
            "company_name": "SWANBOARD AB",
            "pnr": "40127",
            "address": "Göteborg 1, Viktor Rydbergsg 10. Box 460",
            "phone_number": "031-20 0140",
            "bank_details": {
                "bankgiro": "500-6572",
                "postgiro": "49280"
            },
            "activity": "Säljer wallboard o papp på hemmamarknad o export för Svaneholms AB, Svanskog",
            "employees": 20,
            "annual_turnover": "30 000 000",
            "capital": 500000,
            "key_personnel": [
                {
                    "name": "Leif Brynteson",
                    "position": "Verkst dir"
                }
            ],
            "establishment_year": 1944
        },
        "15": {
            "company_name": "SVANBORG & HOLMQVIST VERKSTAD",
            "pnr": "942 00",
            "address": "Alvsbyn, Box 57",
            "phone_number": "0929-12271, 122 72",
            "bank_details": {
                "bankgiro": "37-3005",
                "postgiro": "386801"
            },
            "activity": "Tillverkar helautomatiska bastukaminer samt rostfria produkter såsom expansionskärl, båttankar o båtbeslag",
            "employees": 14,
            "annual_turnover": "1500 000",
            "key_personnel": [
                {
                    "name": "Sune Holmqvist",
                    "position": "Chef"
                }
            ],
            "establishment_year": 1963
        },
        "16": {
            "company_name": "ALBA TIMBER CO, AB",
            "pnr": "660 51",
            "address": "Norsbron",
            "phone_number": "054-410 75",
            "activity": "Förmedlar o exporterar pappersved, timmer, stolpar, props m m samt sågade o hyvlade trävaror",
            "capital": 15000,
            "key_personnel": [
                {
                    "name": "Per Hammarberg",
                    "position": "Verkst dir"
                }
            ],
            "establishment_year": 1953
        },
        "17": {
            "company_name": "SPÅNGA ROSTFRITT, AB",
            "pnr": "175 00",
            "address": "Jakobsberg, Nettov 5",
            "phone_number": "0758-310 00",
            "bank_details": {
                "bankgiro": "576-2968",
                "postgiro": "361219-9"
            },
            "activity": "Tillverkar rostfria in-redningdetaljer m m till byggnads-, livsmedels- samt kem-tekn industri",
            "employees": 23,
            "capital": 5000,
            "key_personnel": [
                {
                    "name": "Olle Engberg",
                    "position": "Verkst dir"
                }
            ],
            "establishment_year": 1956
        }
    }
}