{
    "original": "WALLGRENS KYL AB\n\nPnr 403 13\n\nGöteborg 2, Arsenalsg 4. Box\n2124. Tel 031-134311, 1343 12.\nTga Elwall\n\nVerksamhet: Kylskåp, kyldiskar o\nkylanläggningar\nAktiekapital: 60 000\nVerkst dir: B Persson\nEtableringsår: 1946.\n\nESSEMVE, VERKSTADS AB\n\nPnr 70010\n\nÖrebro 10, Box 10010. Tel\n019-24 40 00. Bankgiro 463-1438.\nPostgiro 120 337-1\n\nVerksamhet: Tillverkar husvagnar\n(camping vagnar)\nAntal anställda: 60\nÅrsomsättning: 5 000000\nAktiekapital: 40 000\nVerkst dir: Mats Berglund\nEtableringsår: 1936.\n\nsagteknik, ab\n\nPnr 611 00\n\nNyköping, Högbrunnsv 2. Tel\n0155-850 90. Bankgiro 827-4193.\nPostgiro 660451-6. Tga Sawtechnic\nVerksamhet: Säljer\nsågverksmaskiner (timmersorteringar, torkar,\nlängdsorterings- o\npaketeringsverk, ströläggningsmaskiner,\nsåg-ramar m m)\nAntal anställda: 4\nÅrsomsättning: 3 000 000\nAktiekapital: 30000\nStyrelse: Disp Lars-Erik Afors\n(ordf), ing Bertil Andersson,\nbank-dir Lars Johan Hemberg\nVerkst dir: Ing Bertil Andersson\nEtableringsår: 1964.\n\nsågverkens biprodukter\nsåbi, ab\n\nPnr 552 40\n\nJönköping, S Strandg 5. Tel\n036-1654 80. Bankgiro 341-9181.\nPostgiro 590965-0. Telex 70052 SAW S\nVerksamhet: Verkställande organ för\nFöreningen Sågverkens Biprodukter\nÅrsomsättning: 40 000 000\nAktiekapital: 500 000\nEtableringsår: 1964.\n\nsäfs industri och\nbyggvaru ab\n\nPnr 85103\n\nSundsvall 1, Björneborgsg 41. Box\n120. Tel 060-15 58 60\nVerksamhet: Säljer\nbyggnadsmateriel, villor, fritidshus o tomter samt\nsågade o tryckimpregnerade varor\nImpregneringsverk: Ustavall. Tel\n0690-500 06\n\nLugnvik. Tel 063-178 19\n\nSågverk: Bergsåkers Såg. Tel 060-\n\n63102\n\nStode Ångsåg. Tel 0691-100 49\nHandelsträdgård: Lugnvik. Tel\n063-178 19\nAntal anställda: 125\nÅrsomsättning: 20 000 000\nVerkst dir Disp E Wikner\nEtableringsån 1930.\n\nsaffle gjuteri &amp;\nmekaniska verkstad, ab\n\nPnr 66100\n\nSäffle, Verkst ad sg 1-5. Tel\n0533-12430. Bankgiro 114-9442.\nPostgiro 81589-4. Tga Verkstaden\nVerksamhet: Apparater för\npappers-o cellulosaindustri. Rör o\nrördelar i svart o rostfritt samt gjuU\njärn. Diverse service- o\nlegoarbe-ten såsom gjutgods,\ngrovplåtarbeten samt maskinbearbetning\nVerkst dir: Karl-Eric Larsson\nInköpschef: Ing Kurt Larsson\nEtableringsår: 1894.\n\nsäffle lastbilcentral\nförening upa\n\nPnr 66100\n\nSäffle, Box 113. Järnvägsg 4. Tel\n0533-126 50. Bankgiro 114-9459.\nPostgiro 444727-2\nVerksamhet: Transportförmedling\nsamt tillhandahåller grus o singel\nAntal anställda: 10\nÅrsomsättning: 3 200 000\nInsatskapital: 300 000\nVertist dir: Sven Rudberg\nEtableringsån 1937.\n\nseffle motorverkstad,\nab\n\nPnr 661 00\n\nSäffle, Box 84. Tel 0533-126 20.\nBankgiro 115-0036. Postgiro\n25733-7. Tga Brucemotor.\nTelex 5302\n\nVerksamhet: Tillverkar\npropellrar o styrmaskiner för fartyg\nAntal anställda: 120\nÅrsomsättning: 6 500 000\nAktiekapital: 800 000\nVertist dir: Johan B Bruce\nEtableringsår: 1908.\n\nALSBERG, AB ERNST\n\nPnr 104 30\n\nStockholm 45, Box 45047. Sveav 76.\nTel 08-23 48 20. Bankgiro 44-7798.\nPostgiro 473. Tga Gants\nVerksamhet: Tillverkar o säljer\nhandskar o vantar en gros\nAktiekapital: 100 000\nVerkst dir: Frank Möller\nEtableringsår: 1939.\n\nGODDY.CHOKLAD AB\n\nPnr 216 13\n\nMalmö, Västanv 3. Tel 040-15 13 13.\nBankgiro 221-7156. Postgiro\n636845-0\n\nVerksamhet: Chokladfabrik\nAntal anställda: 15\nÅrsomsättning: 800 000\nAktiekapital: 200 000\nVerkst dir: Disp Kjell Jakobsson.\n\nGODINGS KONSERVER, KB\n\nPnr 17010\n\nEkerö, Bergvik. Tel 0756-230 20.\nBankgiro 33-3214. Postgiro 80520\nVerksamhet: Tillverkar\ngrönsakskonserver, speciellt av gurka,\nrödbetor o syltade tomater\nAntal anställda: 40\n\nÅrsomsättning: 5 000 000\nChef: Fabr Otto Bergstrand\nEtableringsår: 1940.\n\nGOKEF, GAS. och KOKS.\nVERKENS EKONOMISKA\nFÖRENING U P A\n\nPnr 102 41\n\nStockholm 5, Box 5044. Villag 5.\nTel 08-23 4055. Bankgiro 567-5301.\nPostgiro 2035-4. Tga Gokef\nVerksamhet: Försäljning av gas- o\nkoksverksbiprodukter\nCistemanläggningar: Södertälje,\nSkelleftehamn, Visby o Åhus\nAntal anställda: 22\nÅrsomsättning: 13 000 000\nAktiekapital: 130000\nVerkst dir: Civiling Nils B\nBjörkström\nEtableringsår: 1918\nÄges av svenska stadsgasverk\nsamt\nGrängesbergsbolaget/Oxelösunds järnverk.\n\nGOLJE &amp; CO AB, SIGURD\n\nPnr 19107\n\nSollentuna 7, Fack. Ebba Brahes v\n6. Tel 08-754 11 92. 754 11 93.\nPostgiro 11613\n\nVerksamhet: Tillverkar\npatentgum-merat papper\nAntal anställda: 14\nÅrsomsättning: 1200000\nAktiekapital: 100 000\nVerkst dir: Henry Linde\nEtableringsår: 1914.\n\nVINAS INDUSTRI AB\n\nPnr 792 00\n\nMora, Fack 20. Tel 0250-300 12,\n30067. Bankgiro 46-9136.\nPostgiro 82246\n\nVerksamhet: Tillverkar o säljer\nfönster o fönsterelement\nAntal anställda: 32\nÅrsomsättning: 2 300 000\nAktiekapital: 175 000\nVerkst dir: Disp Claes Nordström\nEtableringsår: 1937.\n\nCENTRAL LACKERING, AB\n\nPnr 163 21\n\nSpånga 1, Box 16. Värstagårdsv 37.\nTel 08-36 46 07, 36 46 08. Bankgiro\n23-6035. Postgiro 322065\nVerksamhet; Lackering av\nindustriprodukter. Ugnslackering\nAntal anställda: 4\nÅrsomsättning: 400 000\nAktiekapital: 25 000\nVerkst dir: Hans Bertil Hansson\nEtableringsår: 1945.\n\nCENTRALBOLAGET FOR\nKEMISKA INDUSTRIER AB\n\nPnr 150 14\n\nVagnhärad, Västerljung. Tel\n0156-200 50, 20110. Bankgiro 19-5934,\n83-0996. Postgiro 193104. Tga\nKemindustri\n\nVerksamhet; Tillverkar o säljer\napparater för dammfri blästring\nAntal anställda: 11\nÅrsomsättning: 1 000 000\nAktiekapital: 80 000\n\nVerkst dir: Teknologie dr Ragnar\nB:son Winbladh\nEtableringsår: 1940.\n\nSALÉN AB, SVEN\n\nPnr 104 40\n\nStockholm 14, Styrmansg 4. Box\n14018. Tel 08-63 55 60. Tga\nSalenship. Telex 19196 SALEN S\nVerksamhet: Skeppsmäkleri o\nskeppsklarering\n\nAvdelningskontor: 400 80 Göteborgs\nFrihamn, Pack. Bananterminalen,\nKajskjul 102-103. Tel 031-51 37 30.\nTga Salenship. Telex 21140 SSAB S\nVerkst dir Sven H Salén\nEtableringsår: 1923.\n\nCOMMENTO AB\n\nPnr 183 51\n\nTäby, Taltrastv 8. Tel 08-75610 01.\nBankgiro 104-6796. Postgiro\n693686-8\n\nVerksamhet: Processteknik inom\npappers- o trämasseindustrin\nAktiekapital: 5 000\nChef: Civiling Gunnar Gavelin\nEtableringsår: 1960.\n\nBILPRODUKTER I UMEÅ AB\n\nPnr 901 02\n\nUmeå 1, Box 66.\nRenmarksesplana-den 1 (Thulehuset). Tel 090-1182 30.\nBankgiro 347-8666. Postgiro 64990-5\nVerksamhet: Bilelektr reservdelar\no tillbehör. Stationära o marina\nmotorer\n\nAntal anställda: 13\nÄgare o chefer: Einar Lindholm,\nTöre Jacobsson\nEtableringsår: 1967.",
    "structured": {
        "1": {
            "company_name": "WALLGRENS KYL AB",
            "pnr": "403 13",
            "address": "Göteborg 2, Arsenalsg 4. Box 2124",
            "phone_number": "031-134311, 1343 12.",
            "activity": "Kylskåp, kyldiskar o kylanläggningar",
            "capital": 60000,
            "key_personnel": [
                {
                    "name": "B Persson",
                    "position": "Verkst dir"
                }
            ],
            "establishment_year": 1946
        },
        "2": {
            "company_name": "ESSEMVE, VERKSTADS AB",
            "pnr": "70010",
            "address": "Örebro 10, Box 10010",
            "phone_number": "019-24 40 00",
            "bank_details": {
                "bankgiro": "463-1438",
                "postgiro": "120 337-1"
            },
            "activity": "Tillverkar husvagnar (camping vagnar)",
            "employees": 60,
            "annual_turnover": 5000000,
            "capital": 40000,
            "key_personnel": [
                {
                    "name": "Mats Berglund",
                    "position": "Verkst dir"
                }
            ],
            "establishment_year": 1936
        },
        "3": {
            "company_name": "sagteknik, ab",
            "pnr": "611 00",
            "address": "Nyköping, Högbrunnsv 2",
            "phone_number": "0155-850 90",
            "bank_details": {
                "bankgiro": "827-4193",
                "postgiro": "660451-6"
            },
            "activity": "Säljer sågverksmaskiner",
            "employees": 4,
            "annual_turnover": 3000000,
            "capital": 30000,
            "key_personnel": [
                {
                    "name": "Ing Bertil Andersson",
                    "position": "Styrelse"
                },
                {
                    "name": "Disp Lars-Erik Afors",
                    "position": "ordf"
                },
                {
                    "name": "bank-dir Lars Johan Hemberg",
                    "position": null
                },
                {
                    "name": "Ing Bertil Andersson",
                    "position": "Verkst dir"
                }
            ],
            "establishment_year": 1964
        },
        "4": {
            "company_name": "sågverkens biprodukter såbi, ab",
            "pnr": "552 40",
            "address": "Jönköping, S Strandg 5",
            "phone_number": "036-1654 80",
            "bank_details": {
                "bankgiro": "341-9181",
                "postgiro": "590965-0"
            },
            "activity": "Verkställande organ för Föreningen Sågverkens Biprodukter",
            "annual_turnover": 40000000,
            "capital": 500000,
            "establishment_year": 1964
        },
        "5": {
            "company_name": "säfs industri och byggvaru ab",
            "pnr": "85103",
            "address": "Sundsvall 1, Björneborgsg 41. Box 120",
            "phone_number": "060-15 58 60",
            "activity": "Säljer byggnadsmateriel, villor, fritidshus o tomter samt sågade o tryckimpregnerade varor",
            "employees": 125,
            "annual_turnover": 20000000,
            "key_personnel": [
                {
                    "name": "Disp E Wikner",
                    "position": "Verkst dir"
                }
            ],
            "establishment_year": 1930
        },
        "6": {
            "company_name": "saffle gjuteri & mekaniska verkstad, ab",
            "pnr": "66100",
            "address": "Säffle, Verkst ad sg 1-5",
            "phone_number": "0533-12430",
            "bank_details": {
                "bankgiro": "114-9442",
                "postgiro": "81589-4"
            },
            "activity": "Apparater för pappers-o cellulosaindustri. Rör o rördelar i svart o rostfritt samt gjutgods, grovplåtarbeten samt maskinbearbetning",
            "key_personnel": [
                {
                    "name": "Karl-Eric Larsson",
                    "position": "Verkst dir"
                },
                {
                    "name": "Ing Kurt Larsson",
                    "position": "Inköpschef"
                }
            ],
            "establishment_year": 1894
        },
        "7": {
            "company_name": "säffle lastbilcentral förening upa",
            "pnr": "66100",
            "address": "Säffle, Box 113. Järnvägsg 4",
            "phone_number": "0533-126 50",
            "bank_details": {
                "bankgiro": "114-9459",
                "postgiro": "444727-2"
            },
            "activity": "Transportförmedling samt tillhandahåller grus o singel",
            "employees": 10,
            "annual_turnover": 3200000,
            "capital": 300000,
            "key_personnel": [
                {
                    "name": "Sven Rudberg",
                    "position": "Vertist dir"
                }
            ],
            "establishment_year": 1937
        },
        "8": {
            "company_name": "seffle motorverkstad, ab",
            "pnr": "661 00",
            "address": "Säffle, Box 84",
            "phone_number": "0533-126 20",
            "bank_details": {
                "bankgiro": "115-0036",
                "postgiro": "25733-7"
            },
            "activity": "Tillverkar propellrar o styrmaskiner för fartyg",
            "employees": 120,
            "annual_turnover": 6500000,
            "capital": 800000,
            "key_personnel": [
                {
                    "name": "Johan B Bruce",
                    "position": "Vertist dir"
                }
            ],
            "establishment_year": 1908
        },
        "9": {
            "company_name": "ALSBERG, AB ERNST",
            "pnr": "104 30",
            "address": "Stockholm 45, Box 45047. Sveav 76",
            "phone_number": "08-23 48 20",
            "bank_details": {
                "bankgiro": "44-7798",
                "postgiro": "473"
            },
            "activity": "Tillverkar o säljer handskar o vantar en gros",
            "capital": 100000,
            "key_personnel": [
                {
                    "name": "Frank Möller",
                    "position": "Verkst dir"
                }
            ],
            "establishment_year": 1939
        },
        "10": {
            "company_name": "GODDY.CHOKLAD AB",
            "pnr": "216 13",
            "address": "Malmö, Västanv 3",
            "phone_number": "040-15 13 13",
            "bank_details": {
                "bankgiro": "221-7156",
                "postgiro": "636845-0"
            },
            "activity": "Chokladfabrik",
            "employees": 15,
            "annual_turnover": 800000,
            "capital": 200000,
            "key_personnel": [
                {
                    "name": "Disp Kjell Jakobsson",
                    "position": "Verkst dir"
                }
            ]
        },
        "11": {
            "company_name": "GODINGS KONSERVER, KB",
            "pnr": "17010",
            "address": "Ekerö, Bergvik",
            "phone_number": "0756-230 20",
            "bank_details": {
                "bankgiro": "33-3214",
                "postgiro": "80520"
            },
            "activity": "Tillverkar grönsakskonserver, speciellt av gurka, rödbetor o syltade tomater",
            "employees": 40,
            "annual_turnover": 5000000,
            "key_personnel": [
                {
                    "name": "Fabr Otto Bergstrand",
                    "position": "Chef"
                }
            ],
            "establishment_year": 1940
        },
        "12": {
            "company_name": "GOKEF, GAS. och KOKS. VERKENS EKONOMISKA FÖRENING U P A",
            "pnr": "102 41",
            "address": "Stockholm 5, Box 5044. Villag 5",
            "phone_number": "08-23 4055",
            "bank_details": {
                "bankgiro": "567-5301",
                "postgiro": "2035-4"
            },
            "activity": "Försäljning av gas- o koksverksbiprodukter",
            "employees": 22,
            "annual_turnover": 13000000,
            "capital": 130000,
            "key_personnel": [
                {
                    "name": "Civiling Nils B Björkström",
                    "position": "Verkst dir"
                }
            ],
            "establishment_year": 1918
        },
        "13": {
            "company_name": "GOLJE & CO AB, SIGURD",
            "pnr": "19107",
            "address": "Sollentuna 7, Fack. Ebba Brahes v 6",
            "phone_number": "08-754 11 92",
            "activity": "Tillverkar patentgum-merat papper",
            "employees": 14,
            "annual_turnover": 1200000,
            "capital": 100000,
            "key_personnel": [
                {
                    "name": "Henry Linde",
                    "position": "Verkst dir"
                }
            ],
            "establishment_year": 1914
        },
        "14": {
            "company_name": "VINAS INDUSTRI AB",
            "pnr": "792 00",
            "address": "Mora, Fack 20",
            "phone_number": "0250-300 12, 30067",
            "bank_details": {
                "bankgiro": "46-9136",
                "postgiro": "82246"
            },
            "activity": "Tillverkar o säljer fönster o fönsterelement",
            "employees": 32,
            "annual_turnover": 2300000,
            "capital": 175000,
            "key_personnel": [
                {
                    "name": "Disp Claes Nordström",
                    "position": "Verkst dir"
                }
            ],
            "establishment_year": 1937
        },
        "15": {
            "company_name": "CENTRAL LACKERING, AB",
            "pnr": "163 21",
            "address": "Spånga 1, Box 16. Värstagårdsv 37",
            "phone_number": "08-36 46 07, 36 46 08",
            "bank_details": {
                "bankgiro": "23-6035",
                "postgiro": "322065"
            },
            "activity": "Lackering av industriprodukter. Ugnslackering",
            "employees": 4,
            "annual_turnover": 400000,
            "capital": 25000,
            "key_personnel": [
                {
                    "name": "Hans Bertil Hansson",
                    "position": "Verkst dir"
                }
            ],
            "establishment_year": 1945
        },
        "16": {
            "company_name": "CENTRALBOLAGET FOR KEMISKA INDUSTRIER AB",
            "pnr": "150 14",
            "address": "Vagnhärad, Västerljung",
            "phone_number": "0156-200 50, 20110",
            "bank_details": {
                "bankgiro": "19-5934",
                "postgiro": "83-0996"
            },
            "activity": "Tillverkar o säljer apparater för dammfri blästring",
            "employees": 11,
            "annual_turnover": 1000000,
            "capital": 80000,
            "key_personnel": [
                {
                    "name": "Teknologie dr Ragnar B:son Winbladh",
                    "position": "Verkst dir"
                }
            ],
            "establishment_year": 1940
        },
        "17": {
            "company_name": "SALÉN AB, SVEN",
            "pnr": "104 40",
            "address": "Stockholm 14, Styrmansg 4. Box 14018",
            "phone_number": "08-63 55 60",
            "activity": "Skeppsmäkleri o skeppsklarering",
            "establishment_year": 1923
        },
        "18": {
            "company_name": "COMMENTO AB",
            "pnr": "183 51",
            "address": "Täby, Taltrastv 8",
            "phone_number": "08-75610 01",
            "bank_details": {
                "bankgiro": "104-6796",
                "postgiro": "693686-8"
            },
            "activity": "Processteknik inom pappers- o trämasseindustrin",
            "capital": 5000,
            "key_personnel": [
                {
                    "name": "Civiling Gunnar Gavelin",
                    "position": "Chef"
                }
            ],
            "establishment_year": 1960
        },
        "19": {
            "company_name": "BILPRODUKTER I UMEÅ AB",
            "pnr": "901 02",
            "address": "Umeå 1, Box 66. Renmarksesplana-den 1 (Thulehuset)",
            "phone_number": "090-1182 30",
            "bank_details": {
                "bankgiro": "347-8666",
                "postgiro": "64990-5"
            },
            "activity": "Bilelektr reservdelar o tillbehör. Stationära o marina motorer",
            "employees": 13,
            "establishment_year": 1967
        }
    }
}