{
    "original": "HELLBERG &amp; SUNDQVIST AB\n\nPnr 117 20\n\nStockholm, Pryssgränd 10 B. Tel\n08-40 06 09, 40 86 87. Bankgiro\n720-0025. Postgiro 1198-1\nVerksamhet: Plåtslageri\nAktiekapital: 30 000\nEtableringsår: 1930.\n\nEXTRUDING, AB\n\nPnr 240 30\n\nMarieholm, Box 80. Tegel v. Tel\n0413-705 10. Bankgiro 274-9778.\nPostgiro 433183-1\nVerksamhet: Tillverkar\npolyeten-påsar, formblåsta industridetaljer\nsamt sugrör\nAntal anställda: 52\nÅrsomsättning: 5 000 000\nAktiekapital: 150 000\nVerkst dir: Rune G Hjalmarsson\nEtableringsår: 1955.\n\nRYDS GLASBRUK AB\n\nPnr 360 10\n\nRyd. Tel 0459-80077. Postgiro\n22517-7\n\nVerksamhet: Tillverkar tekn\nmedicin-, restaurang- o hushållsglas\nAktiekapital: 50 000\nVerkst dir Jarl Johansson\nEtableringsår 1918.\n\nDAHLINS MASKINER AB\n\nPnr 16132\n\nBromma, Svartviks v 21. Tel\n08-80 06 10. Bankgiro 745-8581.\nPostgiro 652756-8\n\nVerksamhet: Agenturaffär i\nmaskiner o verktyg\nAktiekapital: 5 000\nChef: Ing S Dahlin\nEtableringsår: 1967.\n\nDAHLINS EFTR BOKBINDERI,\nAB C G\n\nPnr 652 25\n\nKarlstad, Tingvallag 19. Tel\n054-110281,110118. Bankgiro 88-1353.\nPostgiro 73527\n\nVerksamhet: Utför broschyr- o\nkatalogarbeten\nAntal anställda: 12\nÅrsomsättning: 350 000\nAktiekapital: 50 000\nVerkst dir: Axel Karlsson\nEtableringsår: 1837.\n\nJÄRN &amp; METALL AB\n\nPnr 56010\n\nSkillingaryd. Tel 0370-708 50,\n705 35. Bankgiro 141-362. Postgiro\n72020\n\nVerksamhet: Försäljning av plåt i\nband o format. Tillverkar i\nMariestad: plåt- o mek arbeten.\nExcenter-, drag- o kantpressning. Egen\nverktygstillverkning\nAktiekapital: 50 000\nVerkst dir: Folke Carlström\nEtableringsår: 1956.\n\nJÄRN och METALL,\nB E WISTING &amp; CO\n\nPnr 30104\n\nHalmstad, Syskonhamnsg 4. Box\n265. Tel 035-1155 89. Bankgiro\n33-8974. Postgiro 475518-7\nVerksamhet: Järngrossist\nVerkst dir. B E Wisting\nEtableringsår: 1954.\n\nBACKA STRUMPFABRIK, AB\n\nPnr 434 01\n\nKungsbacka 1, Box 5. Tel\n0300-130 20. Bankgiro 42-6421. Postgiro\n479467\n\nVerksamhet: Tillverkar strumpor,\nsockor o vantar\nAntal anställda: 10\nAktiekapital: 25 000\nVerkst dir: Bengt Åström\nEtableringsår: 1962.\n\nBACKA SÅG- o\nTEGELVERKS AB\n\nPnr 791 00\n\nFalun, Korsnäs. Tel 023-621 70\nVerksamhet: Tillverkar fasad o\nmurtegel\n\nEtableringsår: 1919.\n\nEWEBE, AB\n\nPnr 593 00\n\nVästervik, Strand v 5. Tel\n0490-156 00, 156 04. Bankgiro 858-2490.\nPostgiro 58066-2. Tga Plastics.\nTelex 3922\n\nVerksamhet: Säljer som\ngeneralagent pressmassor, laminat,\nhartser, cellulosaacetat, sprutmassor,\nformsprutmaskiner, pressar,\nextru-ders, valsverk, kalandrar\nAntal anställda: 3\nAktiekapital: 20 000\nStyrelse: Ing Gunnar Eklund\n(ordf), rev Harry Brolin\nVerkst dir: Ing Gunnar Eklund\nEtableringsår: 1939.\n\nLUN\n\nbanderoller, hängetiketter m m\nÄgare: Fru Karna Lundén-Lofall\nChef: Disp Gunnar Lofall\nEtableringsår: 1931.\n\nLUNDGRENS FORMVERKTYG\nAB\n\nPnr 27400\n\nSkurup, Box 43. Tel 0411-411 30.\nVerksamhet: Tillverkar press\ngjut-ningsverktyg o plastverktyg\nAntal anställda: 50\nÅrsomsättning: 2 000 000\nAktiekapital: 50 000\nVerkst dir: Sixten Lundgren\nEtableringsår: 1953.\n\nLUNDGRENS\nMASKIN-FURNUDENHETER AB\n\nPnr 402 52\n\nGöteborg 13, von Holtensg 11. Box\n13114. Tel 031-19 2155. Bankgiro\n444-7769. Postgiro 420306-3. Tga\nGummilundgren\n\nVerksamhet: Specialitet:\nGummi-o vävslangar, gummiduk,\npackningar, remmar, hydraulslangar\nAntal anställda: 15\nÅrsomsättning: 4 000 000\nAktiekapital: 100 000\nVerkst dir: Sture Lundgren\nEtableringsår: 1949.\n\nLUNDGRENS MEK\nVERKSTAD, AB\n\nPnr 214 44\n\nMalmö, Kopparbergsg 5. Tel\n040-804 20. Bankgiro 644-0192.\nPostgiro 14198-6\n\nVerksamhet: Tillverkar o reparerar\nmaskiner för gummi-, kabel-,\nläder-, kem tekn-, m fi industrier,\nel-drivna industrigrindar, el-drivna\nvändskivor for fordon\nAntal anställda: 3 5\nÅrsomsättning: 2 600 000\nAktiekapital: 75 000\nVerkst dir: Sven Jönsson\nEtableringsår: 1912\nOmbildat till aktiebolag 1939.\n\nLUNDGREN &amp; CO FINMEKANISK\nVERKSTAD AB, E\n\nPnr 415 10\n\nGöteborg, Kortedala torg 3. Tel\n031-46 52 25, 46 52 36. Bankgiro\n442-9288. Postgiro 620618-9\nVerksamhet: Legotillverkning av\nverktyg o experimentarbeten\nAntal anställda: 25\nÅrsomsättning: 2 000 000\nAktiekapital: 90000\nVerkst dir: Ing Erling Karlsson\nEtableringsår: 1960.\n\nLUNDGRENS ELEKTRISKA\nAB, EMIL\n\nPnr 41705\n\nGöteborg, Långängen 5. Tel\n031-513130. Bankgiro 441-1435.\nPost-giro 41890-5\n\nVerksamhet: Elektr\ninstallationsrörelse\n\nFilial: Mölndal, Lerbrännarg 5 K.\nTel 031-27 87 05\nAntal anställda: 220\nÅrsomsättning: 15 800 000\nAktiekapital: 500 000\nVerkst dir: Ing Harry Lundgren\nEtableringsår: 1919.\n\nOSKARSTRUMS ROSTFRIA, AB\n\nPnr 313 00\n\nOskarström, Box 118. Tel\n035-605 14. Bankgiro 427-3538.\nPostgiro 677440-0\n\nVerksamhet: Utför arbeten i\nrostfri plåt\n\nAntal anställda: 14\n\nÅrsomsättning: 900 000\nAktiekapital: 50 000\nVerkst dir: Karl Arne Larsson\nEtableringsår: 1947.\n\nULANDS-SANDVIKS BRUKS AB\n\nPnr 380 73\n\nPersnäs. Tel 0485-26275. Bankgiro\n85-4645. Postgiro 13576. Tga\nStenbild\n\nVerksamhet: Tillverkar o monterar\nbyggnadssten. Levererar\nträdgårds-sten. Marmor, kalksten o skiffer\nAntal anställda: 80\nAktiekapital: 150 000\nVerkst dir: Disp Tage Sjösten\nEtableringsår: 1942.",
    "structured": {
        "1": {
            "company_name": "HELLBERG & SUNDQVIST AB",
            "pnr": "117 20",
            "address": "Stockholm, Pryssgränd 10 B",
            "phone_number": "08-40 06 09, 40 86 87",
            "bank_details": {
                "bankgiro": "720-0025",
                "postgiro": "1198-1"
            },
            "activity": "Plåtslageri",
            "capital": 30000,
            "establishment_year": 1930
        },
        "2": {
            "company_name": "EXTRUDING, AB",
            "pnr": "240 30",
            "address": "Marieholm, Box 80",
            "phone_number": "0413-705 10",
            "bank_details": {
                "bankgiro": "274-9778",
                "postgiro": "433183-1"
            },
            "activity": "Tillverkar polyeten-påsar, formblåsta industridetaljer samt sugrör",
            "employees": 52,
            "annual_turnover": 5000000,
            "capital": 150000,
            "key_personnel": [
                {
                    "name": "Rune G Hjalmarsson",
                    "position": "Verkst dir"
                }
            ],
            "establishment_year": 1955
        },
        "3": {
            "company_name": "RYDS GLASBRUK AB",
            "pnr": "360 10",
            "address": "Ryd",
            "phone_number": "0459-80077",
            "postgiro": "22517-7",
            "activity": "Tillverkar tekn medicin-, restaurang- o hushållsglas",
            "capital": 50000,
            "key_personnel": {
                "name": "Jarl Johansson",
                "position": "Verkst dir"
            },
            "establishment_year": 1918
        },
        "4": {
            "company_name": "DAHLINS MASKINER AB",
            "pnr": "16132",
            "address": "Bromma, Svartviks v 21",
            "phone_number": "08-80 06 10",
            "bank_details": {
                "bankgiro": "745-8581",
                "postgiro": "652756-8"
            },
            "activity": "Agenturaffär i maskiner o verktyg",
            "capital": 5000,
            "key_personnel": {
                "name": "Ing S Dahlin",
                "position": "Chef"
            },
            "establishment_year": 1967
        },
        "5": {
            "company_name": "DAHLINS EFTR BOKBINDERI, AB C G",
            "pnr": "652 25",
            "address": "Karlstad, Tingvallag 19",
            "phone_number": "054-110281,110118",
            "bank_details": {
                "bankgiro": "88-1353",
                "postgiro": "73527"
            },
            "activity": "Utför broschyr- o katalogarbeten",
            "employees": 12,
            "annual_turnover": 350000,
            "capital": 50000,
            "key_personnel": {
                "name": "Axel Karlsson",
                "position": "Verkst dir"
            },
            "establishment_year": 1837
        },
        "6": {
            "company_name": "JÄRN & METALL AB",
            "pnr": "56010",
            "address": "Skillingaryd",
            "phone_number": "0370-708 50, 705 35",
            "bank_details": {
                "bankgiro": "141-362",
                "postgiro": "72020"
            },
            "activity": "Försäljning av plåt i band o format. Tillverkar i Mariestad: plåt- o mek arbeten. Excenter-, drag- o kantpressning. Egen verktygstillverkning",
            "capital": 50000,
            "key_personnel": {
                "name": "Folke Carlström",
                "position": "Verkst dir"
            },
            "establishment_year": 1956
        },
        "7": {
            "company_name": "JÄRN och METALL, B E WISTING & CO",
            "pnr": "30104",
            "address": "Halmstad, Syskonhamnsg 4. Box 265",
            "phone_number": "035-1155 89",
            "bank_details": {
                "bankgiro": "33-8974",
                "postgiro": "475518-7"
            },
            "activity": "Järngrossist",
            "key_personnel": {
                "name": "B E Wisting",
                "position": "Verkst dir"
            },
            "establishment_year": 1954
        },
        "8": {
            "company_name": "BACKA STRUMPFABRIK, AB",
            "pnr": "434 01",
            "address": "Kungsbacka 1, Box 5",
            "phone_number": "0300-130 20",
            "bank_details": {
                "bankgiro": "42-6421",
                "postgiro": "479467"
            },
            "activity": "Tillverkar strumpor, sockor o vantar",
            "employees": 10,
            "capital": 25000,
            "key_personnel": {
                "name": "Bengt Åström",
                "position": "Verkst dir"
            },
            "establishment_year": 1962
        },
        "9": {
            "company_name": "BACKA SÅG- o TEGELVERKS AB",
            "pnr": "791 00",
            "address": "Falun, Korsnäs",
            "activity": "Tillverkar fasad o murtegel",
            "establishment_year": 1919
        },
        "10": {
            "company_name": "EWEBE, AB",
            "pnr": "593 00",
            "address": "Västervik, Strand v 5",
            "phone_number": "0490-156 00, 156 04",
            "bank_details": {
                "bankgiro": "858-2490",
                "postgiro": "58066-2"
            },
            "activity": "Säljer som generalagent pressmassor, laminat, hartser, cellulosaacetat, sprutmassor, formsprutmaskiner, pressar, extru-ders, valsverk, kalandrar",
            "employees": 3,
            "capital": 20000,
            "key_personnel": [
                {
                    "name": "Ing Gunnar Eklund",
                    "position": "Styrelse (ordf)"
                },
                {
                    "name": "Harry Brolin",
                    "position": "rev"
                },
                {
                    "name": "Ing Gunnar Eklund",
                    "position": "Verkst dir"
                }
            ],
            "establishment_year": 1939
        },
        "11": {
            "company_name": "LUN",
            "activity": "banderoller, hängetiketter m m",
            "establishment_year": 1931,
            "key_personnel": [
                {
                    "name": "Fru Karna Lundén-Lofall",
                    "position": "Ägare"
                },
                {
                    "name": "Gunnar Lofall",
                    "position": "Disp Chef"
                }
            ]
        },
        "12": {
            "company_name": "LUNDGRENS FORMVERKTYG AB",
            "pnr": "27400",
            "address": "Skurup, Box 43",
            "phone_number": "0411-411 30",
            "activity": "Tillverkar press gjut-ningsverktyg o plastverktyg",
            "employees": 50,
            "annual_turnover": 2000000,
            "capital": 50000,
            "key_personnel": {
                "name": "Sixten Lundgren",
                "position": "Verkst dir"
            },
            "establishment_year": 1953
        },
        "13": {
            "company_name": "LUNDGRENS MASKIN-FURNUDENHETER AB",
            "pnr": "402 52",
            "address": "Göteborg 13, von Holtensg 11. Box 13114",
            "phone_number": "031-19 2155",
            "bank_details": {
                "bankgiro": "444-7769",
                "postgiro": "420306-3"
            },
            "activity": "Specialitet: Gummi-o vävslangar, gummiduk, packningar, remmar, hydraulslangar",
            "employees": 15,
            "annual_turnover": 4000000,
            "capital": 100000,
            "key_personnel": {
                "name": "Sture Lundgren",
                "position": "Verkst dir"
            },
            "establishment_year": 1949
        },
        "14": {
            "company_name": "LUNDGRENS MEK VERKSTAD AB",
            "pnr": "214 44",
            "address": "Malmö, Kopparbergsg 5",
            "phone_number": "040-804 20",
            "bank_details": {
                "bankgiro": "644-0192",
                "postgiro": "14198-6"
            },
            "activity": "Tillverkar o reparerar maskiner för gummi-, kabel-, läder-, kem tekn-, m fi industrier, el-drivna industrigrindar, el-drivna vändskivor for fordon",
            "employees": 35,
            "annual_turnover": 2600000,
            "capital": 75000,
            "key_personnel": {
                "name": "Sven Jönsson",
                "position": "Verkst dir"
            },
            "establishment_year": 1912,
            "additional_information": "Ombildat till aktiebolag 1939"
        },
        "15": {
            "company_name": "LUNDGRENS & CO FINMEKANISK VERKSTAD AB, E",
            "pnr": "415 10",
            "address": "Göteborg, Kortedala torg 3",
            "phone_number": "031-46 52 25, 46 52 36",
            "bank_details": {
                "bankgiro": "442-9288",
                "postgiro": "620618-9"
            },
            "activity": "Legotillverkning av verktyg o experimentarbeten",
            "employees": 25,
            "annual_turnover": 2000000,
            "capital": 90000,
            "key_personnel": {
                "name": "Ing Erling Karlsson",
                "position": "Verkst dir"
            },
            "establishment_year": 1960
        },
        "16": {
            "company_name": "LUNDGRENS ELEKTRISKA AB, EMIL",
            "pnr": "41705",
            "address": "Göteborg, Långängen 5",
            "phone_number": "031-513130",
            "bank_details": {
                "bankgiro": "441-1435",
                "postgiro": "41890-5"
            },
            "activity": "Elektr installationsrörelse",
            "filial": {
                "location": "Mölndal, Lerbrännarg 5 K",
                "phone_number": "031-27 87 05"
            },
            "employees": 220,
            "annual_turnover": 15800000,
            "capital": 500000,
            "key_personnel": {
                "name": "Ing Harry Lundgren",
                "position": "Verkst dir"
            },
            "establishment_year": 1919
        },
        "17": {
            "company_name": "OSKARSTRUMS ROSTFRIA, AB",
            "pnr": "313 00",
            "address": "Oskarström, Box 118",
            "phone_number": "035-605 14",
            "bank_details": {
                "bankgiro": "427-3538",
                "postgiro": "677440-0"
            },
            "activity": "Utför arbeten i rostfri plåt",
            "employees": 14,
            "annual_turnover": 900000,
            "capital": 50000,
            "key_personnel": {
                "name": "Karl Arne Larsson",
                "position": "Verkst dir"
            },
            "establishment_year": 1947
        },
        "18": {
            "company_name": "ULANDS-SANDVIKS BRUKS AB",
            "pnr": "380 73",
            "address": "Persnäs",
            "phone_number": "0485-26275",
            "bank_details": {
                "bankgiro": "85-4645",
                "postgiro": "13576"
            },
            "activity": "Tillverkar o monterar byggnadssten. Levererar trädgårds-sten. Marmor, kalksten o skiffer",
            "employees": 80,
            "capital": 150000,
            "key_personnel": {
                "name": "Tage Sjösten",
                "position": "Disp Verkst dir"
            },
            "establishment_year": 1942
        }
    }
}