{
    "original": "SVENSKA TULIP AB\n\nPnr 41253\n\nGöteborg, Berzeliig 18. Tel\n031-2009 20: Bankgiro 420-6363.\nPostgiro 621083-5. Tga Tulip\nVerksamhet: Försäljning av kött,\nfläsk, konserver for Tulip, Vejle,\nDanmark\n\nFabrik: Danmark. Tulip, Box 127,\nVejle. Tel 00945-582 40 00\nVarunamn: Tulip\nAntal anställda: 11\nÅrsomsättning: 50 000 000\nAktiekapital: 5 000\nVerkst dir: Ake Tufvesson\nEtableringsår: 1962.\n\nHYLLINGE GLASHYTTA AB\n\nPnr 260 61\n\nHyllinge. Tel 042-251 85. Tga\nHyl-lingeglas, Helsingborg\nVerksamhet: Tillverkar\nbelysningsglas samt konst- o prydnadsglas\nAntal anställda: 50\nÅrsomsättning: 2 000 000\nAktiekapital: 600 000\nVerkst dir: Sune Hermansson\nEtableringsår: 1962.\n\nHYLLINGE MASKIN- &amp; LAST\n-BILSÅKERI AB\n\nPnr 260 61\n\nHyllinge, Åkareg. Box 58. Tel\n042-25008, 250 85. Bankgiro 810-0703.\nPostgiro 686860-8\nVerksamhet: Lastbilsåkeri o\nentreprenadverksamhet. Bulktransporter\nAntal anställda: 15\nÅrsomsättning: 1800 000\nAktiekapital: 20 000\nChefer: Sten Nilsson, Villy\nSvante sson\n\nEtableringsår 1966.\n\nGIP CHEMICAL AB\n\nPnr 464 00\n\nMellerud, Industriområdet. Tel\n0530-11400. Bankgiro 439-9648.\nPostgiro 626541-7\nVerksamhet: Tillverkar\navfettnings-o avkalkningsmedel,\nrengöringsmedel, polish\nVarunamn: S-I, Hågesan\nAntal anställda: 30\nAktiekapital: 170 000\nVerkst dir: Håkan Gip\nEtableringsår: 1964.\n\nVIK\n\nVerksamhet: Konfektionsfabrik\nAktiekapital: 5 000\nVerkst dir: V Ljungström\nEtableringsår: 1877.\n\nodmans ingeniorsbyrå ab\n\nPnr 502 55\n\nBorås, Trymsg 6. Tel 033-1145 14,\n1323 33. Bankgiro 839-4413.\nPost-giro 571575-0\nVerksamhet: Elkonsult\nAntal anställda: 5\nÅrsomsättning: 290 000\nAktiekapital: 5 000\nVerkst dir: Ing Karl-Olof ödman\nEtableringsån 1960.\n\nENGSTRÖMS ELEKTRISKA AB,\nBRÖDERNA\n\nPnr 104 25\n\nStockholm 30, Franzéng 3. Box\n\n30053. Tel 08-54 01 60. Bankgiro\n33-1002. Postgiro 3635. Tga\nElekt-roström\n\nVerksamhet: Elektr materiel i\nparti\n\nAntal anställda: 210\nÅrsomsättning: 74 000 000\n\nAktiekapital: 840 000\nVerkst dir: Hans Engström\nEtableringsår: 1919.\n\nOMNI BUS RESEARCH AB\n\nPnr 17165\n\nSolna, Bagartorpsringen 80. Tel\n08-85 02 85. Telex 10896\nVerksamhet: Kontinuerliga\nmarknads- o indexundersökningar\nÅrsomsättning: 800000\nAktiekapital: 5000\nVerkst dir; Rolf Johansson\nEtableringsår: 1965.\n\nGULLRINGSHUS AB\n\nPnr 590 81\n\nGullringen. Tel 0492-222 00.\nPostgiro 23470. Telex 3918. Tga\nGull-ringshus\n\nVerksamhet: Tillverkar\nmonteringsfärdiga trähus, snickerier o båtar,\nsäljer o köper sågade trävaror för\nhemmamarknad o export\nFilial: Byske. Byske Träförädling\nAB. Tel 0912-105 50\nAntal anställda: 600\nÅrsomsättning: 100 000000\nAktiekapital: 1200 000\nVerkst dir: Dir Bengt\nAnsgarius-Svensson\n\nEtableringsår: 1909.\n\nBERG-BOLINDER AB\n\nPnr 102 43\n\nStockholm 5, Ostermalmsg 39. Box\n5134. Tel 08-24 0100. Bankgiro\n560-0473. Postgiro 252794-0. Tga\nBebosystem\n\nVerksamhet: Säljer\nkontorsmaskiner o datautrustning\nFilialer: Borås. Tel 033-1195 00\nGöteborg. Tel 031-813080\nJönköping. Tel 036-12 96 78\nKarlstad. Tel 054-15 14 83\nMalmö. Tel 040-1013 80\nLinköping. Tel 013-111460\nSundsvall. Tel 060-1212 70\nVästerås. Tel 021-12 0191\nÖrebro. Tel 019-147810\nVarunamn: Adler, Agavox, Eichner,\nElliott, Itel, Lumoprint, Ormig,\nRicoh, Thermograph, Thomas,\nToshiba, Walther\nAntal anstäUda: 100\nAktiekapital: 300 000\nStyrelse: Dir Sönke Nissen (ordf),\ndir Birger Strid, dir Nils Undall\nVerkst dir: Nils Undall.\n\nBERGBOM &amp; CO AB,\nMASKIN-OCH ARMATURFABRIK\n\nPnr 21214\n\nMalmö, Celsiusg 40. Tel\n040-93 57 60. Bankgiro 870-4116.\nPostgiro 147939-3. Tga Pingvinen\n\nVerksamhet: Tillverkar o säljer\nelektrisk belysningsarmatur samt\npotatismosmaskiner\nUtställning:\n\n115 34 Stockholm. Bergbom &amp; Co AB,\nEl Belysningsarmatur, Svensk\nMöbelcenter, Storängsv 10. Tel\n08-60 32 36\n\nVarunamn: Pingvinen, Rotoflex,\nKristaflex\nAntal anstäUda: 55\nÅrsomsättning: 8 000 000\nAktiekapital: 250 000\nStyrelse: Dir Henry Ljung (ordf),\ndir Henry Ljung, dir Per-Henrik\nLjung\n\nVerkst dir: Per-Henrik Ljung\nEtableringsår: 1940.\n\nKLICHÉPRODUKTION AB\n\nPnr 11249\n\nStockholm, Igeldammsg 20. Tel\n08-52 64 63, 52 38 97. Bankgiro\n567-0336. Postgiro 198611-6\nVerksamhet: Tillverkar färg- o\nsvart-vita klichéer, plana o runda\nsamt offsetplåtar o tryckta kretsar\n■Aktiekapital: 180 000\nVerkst dir: Gustaf Sköldefors.\nEtableringsår: 1944\nOmbildat till aktiebolag 1962.\n\nKLICHÉTEKNIK, AB\n\nPnr 111 23\n\nStockholm.Torsg 2. Tel 08-20 55 31,\n20 55 63. Bankgiro 482-7192.\nPostgiro 55033-5\n\nVerksamhet: Klichéer, repro, offset.\nUtför teckningar, retuscher samt\ntermiska förlappningar\n/Antal anställda: 27\nÅrsomsättning: 1700 000\nAktiekapital: 180 000\nVerkst dir: Gösta Malm\nEtableringsår: 1932.",
    "structured": {
        "1": {
            "company_name": "SVENSKA TULIP AB",
            "pnr": "41253",
            "address": "Göteborg, Berzeliig 18",
            "phone_number": "031-2009 20",
            "bank_details": {
                "bankgiro": "420-6363",
                "postgiro": "621083-5"
            },
            "activity": "Försäljning av kött, fläsk, konserver for Tulip, Vejle, Danmark",
            "employees": 11,
            "annual_turnover": 50000000,
            "capital": 5000,
            "key_personnel": [
                {
                    "name": "Ake Tufvesson",
                    "position": "Verkst dir"
                }
            ],
            "establishment_year": 1962
        },
        "2": {
            "company_name": "HYLLINGE GLASHYTTA AB",
            "pnr": "260 61",
            "address": "Hyllinge",
            "phone_number": "042-251 85",
            "activity": "Tillverkar belysningsglas samt konst- o prydnadsglas",
            "employees": 50,
            "annual_turnover": 2000000,
            "capital": 600000,
            "key_personnel": [
                {
                    "name": "Sune Hermansson",
                    "position": "Verkst dir"
                }
            ],
            "establishment_year": 1962
        },
        "3": {
            "company_name": "HYLLINGE MASKIN- & LAST-BILSÅKERI AB",
            "pnr": "260 61",
            "address": "Hyllinge, Åkareg. Box 58",
            "phone_number": "042-25008, 250 85",
            "bank_details": {
                "bankgiro": "810-0703",
                "postgiro": "686860-8"
            },
            "activity": "Lastbilsåkeri o entreprenadverksamhet. Bulktransporter",
            "employees": 15,
            "annual_turnover": 1800000,
            "capital": 20000,
            "key_personnel": [
                {
                    "name": "Sten Nilsson",
                    "position": "Chefer"
                },
                {
                    "name": "Villy Svantes son",
                    "position": "Chefer"
                }
            ],
            "establishment_year": 1966
        },
        "4": {
            "company_name": "GIP CHEMICAL AB",
            "pnr": "464 00",
            "address": "Mellerud, Industriområdet",
            "phone_number": "0530-11400",
            "bank_details": {
                "bankgiro": "439-9648",
                "postgiro": "626541-7"
            },
            "activity": "Tillverkar avfettnings-o avkalkningsmedel, rengöringsmedel, polish",
            "employees": 30,
            "capital": 170000,
            "key_personnel": [
                {
                    "name": "Håkan Gip",
                    "position": "Verkst dir"
                }
            ],
            "establishment_year": 1964
        },
        "5": {
            "company_name": "VIK",
            "activity": "Konfektionsfabrik",
            "capital": 5000,
            "key_personnel": [
                {
                    "name": "V Ljungström",
                    "position": "Verkst dir"
                }
            ],
            "establishment_year": 1877
        },
        "6": {
            "company_name": "odmans ingeniorsbyrå ab",
            "pnr": "502 55",
            "address": "Borås, Trymsg 6",
            "phone_number": "033-1145 14, 1323 33",
            "bank_details": {
                "bankgiro": "839-4413",
                "postgiro": "571575-0"
            },
            "activity": "Elkonsult",
            "employees": 5,
            "annual_turnover": 290000,
            "capital": 5000,
            "key_personnel": [
                {
                    "name": "Ing Karl-Olof ödman",
                    "position": "Verkst dir"
                }
            ],
            "establishment_year": 1960
        },
        "7": {
            "company_name": "ENGSTRÖMS ELEKTRISKA AB, BRÖDERNA",
            "pnr": "104 25",
            "address": "Stockholm 30, Franzéng 3",
            "phone_number": "08-54 01 60",
            "bank_details": {
                "bankgiro": "33-1002",
                "postgiro": "3635"
            },
            "activity": "Elektr materiel i parti",
            "employees": 210,
            "annual_turnover": 74000000,
            "capital": 840000,
            "key_personnel": [
                {
                    "name": "Hans Engström",
                    "position": "Verkst dir"
                }
            ],
            "establishment_year": 1919
        },
        "8": {
            "company_name": "OMNI BUS RESEARCH AB",
            "pnr": "17165",
            "address": "Solna, Bagartorpsringen 80",
            "phone_number": "08-85 02 85",
            "activity": "Kontinuerliga marknads- o indexundersökningar",
            "annual_turnover": 800000,
            "capital": 5000,
            "key_personnel": [
                {
                    "name": "Rolf Johansson",
                    "position": "Verkst dir"
                }
            ],
            "establishment_year": 1965
        },
        "9": {
            "company_name": "GULLRINGSHUS AB",
            "pnr": "590 81",
            "address": "Gullringen",
            "phone_number": "0492-222 00",
            "postgiro": "23470",
            "activity": "Tillverkar monteringsfärdiga trähus, snickerier o båtar, säljer o köper sågade trävaror för hemmamarknad o export",
            "filial": "Byske. Byske Träförädling AB. Tel 0912-105 50",
            "employees": 600,
            "annual_turnover": 100000000,
            "capital": 1200000,
            "key_personnel": [
                {
                    "name": "Dir Bengt Ansgarius-Svensson",
                    "position": "Verkst dir"
                }
            ],
            "establishment_year": 1909
        },
        "10": {
            "company_name": "BERG-BOLINDER AB",
            "pnr": "102 43",
            "address": "Stockholm 5, Ostermalmsg 39",
            "phone_number": "08-24 0100",
            "bank_details": {
                "bankgiro": "560-0473",
                "postgiro": "252794-0"
            },
            "activity": "Säljer kontorsmaskiner o datautrustning",
            "filialer": [
                "Borås. Tel 033-1195 00",
                "Göteborg. Tel 031-813080",
                "Jönköping. Tel 036-12 96 78",
                "Karlstad. Tel 054-15 14 83",
                "Malmö. Tel 040-1013 80",
                "Linköping. Tel 013-111460",
                "Sundsvall. Tel 060-1212 70",
                "Västerås. Tel 021-12 0191",
                "Örebro. Tel 019-147810"
            ],
            "varunamn": [
                "Adler",
                "Agavox",
                "Eichner",
                "Elliott",
                "Itel",
                "Lumoprint",
                "Ormig",
                "Ricoh",
                "Thermograph",
                "Thomas",
                "Toshiba",
                "Walther"
            ],
            "employees": 100,
            "capital": 300000,
            "key_personnel": [
                {
                    "name": "Nils Undall",
                    "position": "Styrelse & Verkst dir"
                }
            ],
            "establishment_year": 1919
        },
        "11": {
            "company_name": "BERGBOM & CO AB, MASKIN-OCH ARMATURFABRIK",
            "pnr": "21214",
            "address": "Malmö, Celsiusg 40",
            "phone_number": "040-93 57 60",
            "bank_details": {
                "bankgiro": "870-4116",
                "postgiro": "147939-3"
            },
            "activity": "Tillverkar o säljer elektrisk belysningsarmatur samt potatismosmaskiner",
            "utställning": "115 34 Stockholm. Bergbom & Co AB, El Belysningsarmatur, Svensk Möbelcenter, Storängsv 10. Tel 08-60 32 36",
            "varunamn": [
                "Pingvinen",
                "Rotoflex",
                "Kristaflex"
            ],
            "employees": 55,
            "annual_turnover": 8000000,
            "capital": 250000,
            "key_personnel": [
                {
                    "name": "Henry Ljung",
                    "position": "Styrelse & Verkst dir"
                }
            ],
            "establishment_year": 1940
        },
        "12": {
            "company_name": "KLICHÉPRODUKTION AB",
            "pnr": "11249",
            "address": "Stockholm, Igeldammsg 20",
            "phone_number": "08-52 64 63, 52 38 97",
            "bank_details": {
                "bankgiro": "567-0336",
                "postgiro": "198611-6"
            },
            "activity": "Tillverkar färg- o svart-vita klichéer, plana o runda samt offsetplåtar o tryckta kretsar",
            "capital": 180000,
            "key_personnel": {
                "name": "Gustaf Sköldefors",
                "position": "Verkst dir"
            },
            "establishment_year": 1944
        },
        "13": {
            "company_name": "KLICHÉTEKNIK, AB",
            "pnr": "111 23",
            "address": "Stockholm.Torsg 2",
            "phone_number": "08-20 55 31,20 55 63",
            "bank_details": {
                "bankgiro": "482-7192",
                "postgiro": "55033-5"
            },
            "activity": "Klichéer, repro, offset. Utför teckningar, retuscher samt termiska förlappningar",
            "employees": 27,
            "annual_turnover": 1700000,
            "capital": 180000,
            "key_personnel": {
                "name": "Gösta Malm",
                "position": "Verkst dir"
            },
            "establishment_year": 1932
        }
    }
}