{
    "original": "SVENSK TRÄFINESS, AB\n\nPnr 582 21\n\nLinköping, Gamla Tullhuset. Tel\n013-12 52 36, 12 52 38. Bankgiro\n607-9396. Postgiro 133720-3\nVerksamhet: Finsnickeri för\ntillverkning av reklampresentartiklar\nsamt skyltar o skyltställ\nAntal anställda: 25\nAktiekapital: 10000\nStyrelse: Disp Stig Kåhre (ordf),\nfabr Gusten Egerud\nVerkst dir: Disp Stig Kåhre\nEtableringsår: 1945\nOmbildat till aktiebolag 1948.\n\nSVENSK TRÄVARU.\nTIDNING, AB\n\nPnr 11187\n\nStockholm 1, Kungsg 17. Box 1724.\nTel 08-23 05 15. Bankgiro 476-8859.\nPostgiro 177-6. Tga Trätidning\nVerksamhet: Tidskrifts- o bokförlag\nVerkst dir: Chefred Sven Lyrholm\nEtableringsår: 1885.\n\nSVENSK UPPLYSNINGS.\nTJÄNST, AB\n\nPnr 20122\n\nMalmö 1, Sankt Gertrudsg 3. Box\n244. Tel 040-729 00. Bankgiro\n870-1625. Postgiro 246211-7.\nTelex 3157\n\nVerksamhet: Inkasso- o\nkreditupplysning srörelse\n\nAvdelningskontor: Göteborg C,Karl\nGustavsg 17. Tel 031-17 76 50\nStockholm K, Sankt Eriksg 41. Tel\n08-50 55 51\nAktiekapital: 40 000\nEtableringsår: 1947.\n\nFRÖLÉN KROSS AB\n\nPnr 852 57\n\nSundsvall. Box 3520. Tel\n060-66040, 666 40. Bankgiro 184-1840.\nPostgiro 81875-7\nVerksamhet: Utför grus- o\nberg-krossning på entreprenad\nAntal anställda: 5\nÅrsomsättning: 1500 000\nAktiekapital: 10 000\nStyrelse: Dir Sture Frölén, fru\nChristina Frölén, kamrer Alf\nSöderholm\n\nVerkst dir: Sture Frölén\nEtableringsår: 1966.\n\nKUGGHJUL, AB\n\nPnr 15133\n\nSödertälje, Storg40. Tel 0755-399 10\nVerksamhet: Tillverkar koniska o\ncylindriska kugghjul, mek verkstad\nAktiekapital: 800 000\nVerkst dir: Sven Gustafson\nEtableringsår: 1922.\n\nBJA\n\nBJARKO VERKTYGS AB\n\nPnr 213 63\n\nMalmö, Pinjeg 4. Tel 040-94 64 5 0.\nBankgiro 642-9997. Postgiro\n246166-3\n\nVerksamhet: Grossist i maskiner o\nverktyg. Specialitet: trycklufts\nverktyg\n\nGeneralagent för: Vessel Tool Co\nLtd, Japan\n\nGebriider Rhodius Slipmaterialverk,\n\nVästtyskland\n\nAntal anställda: 14\n\nAktiekapital: 50 000\n\nVerkst dir: Töre Thomasson\n\nEtableringsår: 1947.\n\nHONEYWELL AB\n\nPnr 127 86\n\nSkärholmen, Storsätragränd 5. Tel\nHuvud-kont 08-88 0000. Bankgiro\n56-9511. Postgiro 154263. Telex\n10673\n\nVerksamhet: Försäljning,\nreparation o service av industriella\nmätinstrument o regulatorer, värme-,\nventilations- o\nluftkonditioneringsautomatik, värmeautomatik för\nbostadsfastigheter, medicinska\nmätinstrument, MICRO-brytare,\nmätinstrument för forskning, vetenskap\no utbildning\nAntal anstäUda: 430\nÅrsomsättning: 60 000 000\n\nAktiekapital: 40 000\nVerkst dir: r sörenson\nEtableringsår: 1938.\n\nc\n\nC\n\nC &amp; M\nFÄRGFOTOLABORATORIUM AB\n\nPnr 42120\n\nVästra Frölunda 1, Fack. Fröhusg\n3. Tel 031-49 0140. Bankgiro\n508-6228. Postgiro 529443-4\nVerksamhet: Fotografiskt\nlaboratorium\n\nAntal anställda: 45\nÅrsomsättning: 3 500 000\nAktiekapital: 10 000\nVerkst dir: Ragnar Cedhagen\nEtableringsår: 1959.\n\nCERAND, R\n\nPnr 112 23\n\nStockholm, Scheeleg 3. Tel\n08-50 8876. Postgiro 2970-2\nVerksamhet: Finmek verkstad.\nKa-beländhylsor, bokstödo etikettramar\nVarunamn: Majus, Stabil.\n\nCERAPID AB,\nINGENJÖRSFIRMAN\n\nPnr 11647\n\nStockholm. Hornsg 1. Tel\n08-44 53 44. Postgiro 404949-9. Tga\nCerapiding\n\nVerksamhet: Northwest\ngrävmaskiner o kranar, tillverkar skopor\nAntal anställda: 6\nAktiekapital: 100 000\nÄgare o chef: Ing R Skolin\nEtableringsår: 1951.\n\nHALLANDS FROKONTOR, AB\n\nPnr 310 44\n\nGetinge. Tel 035-544 00\nVerksamhet: Fröer o\nutsädesspannmål m m\n\nAktiekapital: 2 000 000\nVerkst dir: Gösta Gränström\nEtableringsår: 1897.\n\nmathiasen ab, georg e\n\nPnr 200 10\n\nMalmö 17, Regementsg 8. Box 17083.\nTel 040-771 90. Bankgiro 64-0060.\nPostgiro 4795. Tga Gemsvea\nVerksamhet: Maskinfabrik o\ningenjörsbyrå\n\nÅrsomsättning: 3 000 000\nAktiekapital: 100 000\nVerkst dir: Nils Juul\nEtableringsår: 1910.\n\nASSA-STENMAN AB\n\nPnr 631 05\n\nEskilstuna 1, Drottningg 12. Box\n371. Tel 016-117100. Bankgiro\n160-0618. Postgiro 8368-3. Tga\nStenman. Telex 40986\nVerksamhet: Tillverkar o säljer\nfönsterbeslag, spanjoletter,\ngardinstänger med behör,\ngångjärn,.reglar, ASSA-lås, ASSA-trycken,\nhandtag, träskruv, järngängad skruv,\nsjälvgängande skruv, muttrar samt\nmässingsöverdragna rör, DP rör o\nplastöverdragna svetsade järnrör.\nSkeppsbeslag. Dörrstängare\nFabriker i: Eskilstuna, Alingsås o\nLycksele\n\nFörsäljningskontor o lager:\nStockholm. Huddingev 107, pa\nJohannes-hov. Tel 08-49 27 50\nGöteborg SV, Nordenskiöldsg 19.\nTel 031-12 46 30\n\nSundsvall, Trädgårdsg 19. Tel\n060-1255 00\n\nVarunamn: Assa, Teka\nAktiekapital: 5 000 000\nStyrelseordf: Dir Sture Nilsson\nVerkst dir: Sten Nilsson\nProd-dir: Gösta Björklund\nFörsäljningsledning: Dir Stig\nJern-gren, dir Sven Rydungh\nInköpschef: Fred Gilledal\nEtableringsår: 1881.\nDotterbolag till GKN-Stenman AB,\ntidigare Aug Stenman AB.\n\nASSER METALL\nMANUFAKTUR, AB\n\nPnr 16111\n\nBromma 11, Ranhammarsv 25. Box\n11013. Tel 08-25 25 55. Bankgiro\n16-0864. Postgiro 56567. Tga\n\nAsser\n\nVerksamhet: Tillverkar\nprecisionsdetaljer i seriefabrikation\nAntal anställda: 75\nÅrsomsättning: 5 000 000\nAktiekapital: 250 000\nVerkst dir: Ing Ake Johansson\nEtableringsår: 1934.\n\nASSERBÄCKS\nBYGGPRODUKTER\n\nPnr 402 24\n\nGöteborg 5, Box 5219. Södra v 12.\nTel 031-20 07 30. Bankgiro\n337-6068. Postgiro 42091-9\nVerksamhet: Utför inläggning av\nparkett- o plastgolv\nAntal anställda: 40\nÅrsomsättning: 10000 000\nChef: Rolf A Asserbäck\nEtableringsår: 1940.",
    "structured": {
        "1": {
            "company_name": "SVENSK TRÄFINESS, AB",
            "pnr": "582 21",
            "address": "Linköping, Gamla Tullhuset",
            "phone_number": "013-12 52 36, 12 52 38",
            "bank_details": {
                "bankgiro": "607-9396",
                "postgiro": "133720-3"
            },
            "activity": "Finsnickeri för tillverkning av reklampresentartiklar samt skyltar o skyltställ",
            "employees": 25,
            "capital": 10000,
            "key_personnel": [
                {
                    "name": "Disp Stig Kåhre",
                    "position": "ordf"
                },
                {
                    "name": "fabr Gusten Egerud",
                    "position": ""
                },
                {
                    "name": "Disp Stig Kåhre",
                    "position": "Verkst dir"
                }
            ],
            "establishment_year": 1945
        },
        "2": {
            "company_name": "SVENSK TRÄVARU. TIDNING, AB",
            "pnr": "11187",
            "address": "Stockholm 1, Kungsg 17. Box 1724",
            "phone_number": "08-23 05 15",
            "bank_details": {
                "bankgiro": "476-8859",
                "postgiro": "177-6"
            },
            "activity": "Tidskrifts- o bokförlag",
            "establishment_year": 1885
        },
        "3": {
            "company_name": "SVENSK UPPLYSNINGS. TJÄNST, AB",
            "pnr": "20122",
            "address": "Malmö 1, Sankt Gertrudsg 3. Box 244",
            "phone_number": "040-729 00",
            "bank_details": {
                "bankgiro": "870-1625",
                "postgiro": "246211-7"
            },
            "activity": "Inkasso- o kreditupplysningsrörelse",
            "establishment_year": 1947
        },
        "4": {
            "company_name": "FRÖLÉN KROSS AB",
            "pnr": "852 57",
            "address": "Sundsvall. Box 3520",
            "phone_number": "060-66040, 666 40",
            "bank_details": {
                "bankgiro": "184-1840",
                "postgiro": "81875-7"
            },
            "activity": "Utför grus- o berg-krossning på entreprenad",
            "employees": 5,
            "annual_turnover": 1500000,
            "capital": 10000,
            "key_personnel": [
                {
                    "name": "Dir Sture Frölén",
                    "position": ""
                },
                {
                    "name": "fru Christina Frölén",
                    "position": ""
                },
                {
                    "name": "kamrer Alf Söderholm",
                    "position": ""
                },
                {
                    "name": "Sture Frölén",
                    "position": "Verkst dir"
                }
            ],
            "establishment_year": 1966
        },
        "5": {
            "company_name": "KUGGHJUL, AB",
            "pnr": "15133",
            "address": "Södertälje, Storg40",
            "phone_number": "0755-399 10",
            "activity": "Tillverkar koniska o cylindriska kugghjul, mek verkstad",
            "capital": 800000,
            "key_personnel": [
                {
                    "name": "Sven Gustafson",
                    "position": "Verkst dir"
                }
            ],
            "establishment_year": 1922
        },
        "6": {
            "company_name": "BJARKO VERKTYGS AB",
            "pnr": "213 63",
            "address": "Malmö, Pinjeg 4",
            "phone_number": "040-94 64 5 0",
            "bank_details": {
                "bankgiro": "642-9997",
                "postgiro": "246166-3"
            },
            "activity": "Grossist i maskiner o verktyg. Specialitet: trycklufts verktyg. Generalagent för: Vessel Tool Co Ltd, Japan, Gebriider Rhodius Slipmaterialverk, Västtyskland",
            "employees": 14,
            "capital": 50000,
            "key_personnel": [
                {
                    "name": "Töre Thomasson",
                    "position": "Verkst dir"
                }
            ],
            "establishment_year": 1947
        },
        "7": {
            "company_name": "HONEYWELL AB",
            "pnr": "127 86",
            "address": "Skärholmen, Storsätragränd 5",
            "phone_number": "Huvud-kont 08-88 0000",
            "bank_details": {
                "bankgiro": "56-9511",
                "postgiro": "154263"
            },
            "activity": "Försäljning, reparation o service av industriella mätinstrument o regulatorer, värme-, ventilations- o luftkonditioneringsautomatik, värmeautomatik för bostadsfastigheter, medicinska mätinstrument, MICRO-brytare, mätinstrument för forskning, vetenskap o utbildning",
            "employees": 430,
            "annual_turnover": 60000000,
            "capital": 40000,
            "key_personnel": [
                {
                    "name": "r sörenson",
                    "position": "Verkst dir"
                }
            ],
            "establishment_year": 1938
        },
        "8": {
            "company_name": "C & M FÄRGFOTOLABORATORIUM AB",
            "pnr": "42120",
            "address": "Västra Frölunda 1, Fack. Fröhusg 3",
            "phone_number": "031-49 0140",
            "bank_details": {
                "bankgiro": "508-6228",
                "postgiro": "529443-4"
            },
            "activity": "Fotografiskt laboratorium",
            "employees": 45,
            "annual_turnover": 3500000,
            "capital": 10000,
            "key_personnel": [
                {
                    "name": "Ragnar Cedhagen",
                    "position": "Verkst dir"
                }
            ],
            "establishment_year": 1959
        },
        "9": {
            "company_name": "CERAND, R",
            "pnr": "112 23",
            "address": "Stockholm, Scheeleg 3",
            "phone_number": "08-50 8876",
            "postgiro": "2970-2",
            "activity": "Finmek verkstad. Ka-beländhylsor, bokstödo etikettramar",
            "establishment_year": 0
        },
        "10": {
            "company_name": "CERAPID AB, INGENJÖRSFIRMAN",
            "pnr": "11647",
            "address": "Stockholm. Hornsg 1",
            "phone_number": "08-44 53 44",
            "postgiro": "404949-9",
            "activity": "Northwest grävmaskiner o kranar, tillverkar skopor",
            "employees": 6,
            "capital": 100000,
            "key_personnel": [
                {
                    "name": "Ing R Skolin",
                    "position": "Ägare o chef"
                }
            ],
            "establishment_year": 1951
        },
        "11": {
            "company_name": "HALLANDS FROKONTOR, AB",
            "pnr": "310 44",
            "address": "Getinge",
            "phone_number": "035-544 00",
            "activity": "Fröer o utsädesspannmål m m",
            "capital": 2000000,
            "key_personnel": [
                {
                    "name": "Gösta Gränström",
                    "position": "Verkst dir"
                }
            ],
            "establishment_year": 1897
        },
        "12": {
            "company_name": "mathiasen ab, georg e",
            "pnr": "200 10",
            "address": "Malmö 17, Regementsg 8. Box 17083",
            "phone_number": "040-771 90",
            "bank_details": {
                "bankgiro": "64-0060",
                "postgiro": "4795"
            },
            "activity": "Maskinfabrik o ingenjörsbyrå",
            "annual_turnover": 3000000,
            "capital": 100000,
            "key_personnel": [
                {
                    "name": "Nils Juul",
                    "position": "Verkst dir"
                }
            ],
            "establishment_year": 1910
        },
        "13": {
            "company_name": "ASSA-STENMAN AB",
            "pnr": "631 05",
            "address": "Eskilstuna 1, Drottningg 12. Box 371",
            "phone_number": "016-117100",
            "bank_details": {
                "bankgiro": "160-0618",
                "postgiro": "8368-3"
            },
            "activity": "Tillverkar o säljer fönsterbeslag, spanjoletter, gardinstänger med behör, gångjärn,.reglar, ASSA-lås, ASSA-trycken, handtag, träskruv, järngängad skruv, självgängande skruv, muttrar samt mässingsöverdragna rör, DP rör o plastöverdragna svetsade järnrör. Skeppsbeslag. Dörrstängare",
            "capital": 5000000,
            "key_personnel": [
                {
                    "name": "Dir Sture Nilsson",
                    "position": "Styrelseordf"
                },
                {
                    "name": "Sten Nilsson",
                    "position": "Verkst dir"
                },
                {
                    "name": "Gösta Björklund",
                    "position": "Prod-dir"
                },
                {
                    "name": "Stig Jern-gren",
                    "position": "Försäljningsledning"
                },
                {
                    "name": "Sven Rydungh",
                    "position": "Försäljningsledning"
                },
                {
                    "name": "Fred Gilledal",
                    "position": "Inköpschef"
                }
            ],
            "establishment_year": 1881
        },
        "14": {
            "company_name": "ASSER METALL MANUFAKTUR, AB",
            "pnr": "16111",
            "address": "Bromma 11, Ranhammarsv 25. Box 11013",
            "phone_number": "08-25 25 55",
            "bank_details": {
                "bankgiro": "16-0864",
                "postgiro": "56567"
            },
            "activity": "Tillverkar precisionsdetaljer i seriefabrikation",
            "employees": 75,
            "annual_turnover": 5000000,
            "capital": 250000,
            "key_personnel": [
                {
                    "name": "Ing Ake Johansson",
                    "position": "Verkst dir"
                }
            ],
            "establishment_year": 1934
        },
        "15": {
            "company_name": "ASSERBÄCKS BYGGPRODUKTER",
            "pnr": "402 24",
            "address": "Göteborg 5, Box 5219. Södra v 12",
            "phone_number": "031-20 07 30",
            "bank_details": {
                "bankgiro": "337-6068",
                "postgiro": "42091-9"
            },
            "activity": "Utför inläggning av parkett- o plastgolv",
            "employees": 40,
            "annual_turnover": 10000000,
            "key_personnel": [
                {
                    "name": "Rolf A Asserbäck",
                    "position": "Chef"
                }
            ],
            "establishment_year": 1940
        }
    }
}