{
    "original": "NORDEMANS BIL AB, FW\n\nPnr 89101\n\nÖrnsköldsvik 1, Box 232.\nAnger-manlandsg 21. Tel 0660-105 60.\nBankgiro 77-1575. Postgiro 28952-0\nVerksamhet: Säljer nya o begagnade\nperson- o lastbilar\nAntal anställda: 70\nÅrsomsättning: 11000 000\nAktiekapital: 307 000\nVerkst dir: Nils Nordeman\nEtableringsår: 1955.\n\nNORDEMANS JERNHANDEL,\nAB F W\n\nPnr 891 01\n\nÖrnsköldsvik 1, Box 50.\nViktoria-eplanaden 6. Tel 0660-102 70.\nBankgiro 771-6822. Postgiro\nPostgiro 62233-2. Tga Nordemans.\nTelex 6046\n\nVerksamhet: Järnvaror o\nbyggnadsmaterial i parti o minut\nAntal anställda: 30\nÅrsomsättning: 8 500 000\nAktiekapital: 250000\nVerkst dir: Hans Nordeman\nEtableringsår: 1900.\n\nNORD-EMBALLAGE,\nFOR-PACKNINGS-AB\n\nPnr 271 00\n\nYstad, Hamng 15. Tel 0411-17180,\n171 81. Bankgiro 713-4927\nVerksamhet: Säljer\nkartongförpackningar, etiketter o blanketter.\nEget tryckeri\n\nChefer: Boktryckare Bror Månsson,\nboktryckare Göran Jeppsson\nEtableringsår: 1968.\n\nNORDEMO, BYGGNADS AB\nGÖSTA\n\nPnr 116 62\n\nStockholm, Götg 96. Tel 08-44 04 95.\nBankgiro 573-3746. Postgiro\n50 1 34 3-8\n\nVerksamhet: Fastighetsförvaltning.\n\nUtför reparationer\n\nAntal anställda: 50\n\nÅrsomsättning: 5 000 000\n\nAktiekapital: 100000\n\nVerkst dir: Byggnadsing Gösta\n\nNordemo\n\nEtableringsår: 1937.\n\nCOOLA FILM &amp; FORM AB\n\nPnr 114 53\n\nStockholm, Grevg 23. Tel\n08-1152 25, 60 37 74. Bankgiro\n661-2576. Postgiro 555140-3\nVerksamhet: Specialitet: tecknad\no trickad animerad film. Reklam,\nPR o informationsfilm\nChef: Formgivare Ola Lindahl\nEtableringsår 1966.\n\nANDERSSON, AB VIKTOR\n\nPnr 21120\n\nMalmö, Vinterg 12. Tel 040-709 70.\n\nTga Vason\n\nVerksamhet: Maskiner, verktyg o\nmaskinförnödenheter\nAktiekapital: 150 000\nVerkst din Gösta Andersson\nEtableringsår: 1902.\n\nANDERSSON\nTRÄVARUEXPORT, AB WICTOR\n\nPnr 292 00\n\nKarlshamn, Hamng 6. Box 137. Tel\n0454-13135,13136. Bankgiro\n65-6628. Postgiro 273130. Telex 4512.\nTga Anwood\n\nVerksamhet: Sågverk o\nträvaruexport\n\nAntal anställda: 40\nÅrsomsättning: 6 000 000\nAktiekapital: 100 000\nVerkst din Wictor Andersson\nEtableringsår: 1935.\n\nANDERSONS METALLFABRIK\nAB, VILH\n\nPnr 112 27\n\nStockholm, Kungsg 84. Tel\n08-546701. Bankgiro 16-6520.\nPost-giro 3539\n\nVerksamhet: Utför\nbeställningsarbeten i järn o metall\nAntal anställda: 9\nÅrsomsättning: 363 000\nAktiekapital: 15 000\nFirmatecknare: Bertil Almerfors\nEtableringsår: 1914.\n\nCONSTRUO\n\nPnr 114 27\n\nStockholm, Valhallav 86. Tel\n08-1168 85. Bankgiro 167-0793.\nPostgiro 195663-1\n\nVerksamhet: Golvbrunnar syrafasta\nÅrsomsättning: 200 000\nÄgare o chef: Ing Birger Lindqvist\nEtableringsår: 1948.\n\nGEN\n\nAktiekapital: 30000\nVerkst dir: Fru Anna Persson\nEtableringsår: 1941.\n\nCEL\n\nSO,-utrustningar för kemiska\nindustrin\n\nVarunamn: Rebeater, Vorject\nAntal anställda: 40\nÅrsomsättning: 15 000 000\nAktiekapital: 132 000\nVerkst dir: Erik Backteman\nEtableringsàr: 1936\nÄges av Alfa-Laval, Tumba.\n\nCELLOPLAST, AB\n\nPnr 601 04\n\nNorrköping 1. Tullhusg 11. Box 297.\nTel 011-12 97 80. Bankgiro 60-9803.\nPostgiro 373341. Tga Cello.\nTelex 64329\n\nVerksamhet: Tillverkar Wettex\nsvampduk, polyetenfolier o\nprodukter därav såsom påsar etc, tape,\nformar av polystyren,\ncellulosa-acetatfilm\n\nVarunamn: Alofan, Alofilm, Diofan,\nKänguru, Tenofilm, Wettex\nAntal anställda: 1000\nÅrsomsättning: 100 000 000\nAktiekapital: 10 000 000\nVerkst dir. Civiling Curt Lindquist\nEtableringsàr: 1951.\n\nCELLVABRUKEN AB\n\nPnr 104 40\n\nStockholm 14, Strandv 35. Box\n14038. Tel 08-63 03 50. Bankgiro\n136-3076. Postgiro 552860-9. Tga\nSwecellfab. Telex 10385\nVerksamhet; Säljer blöjor o\nmjuk-pappersprodukter\nVerkst dir: Bengt Lyberg\nEtableringsàr: 1961\nÄgare: Mo och Domsjö AB.\n\nCEMA KONSTSTENSGJUTERI,\nAB\n\nPnr 440 06\n\nGråbo, Box 2243. Tel 0302-401 55,\n405 95. Bankgiro 51-3602. Postgiro\n42105-7\n\nVerksamhet; Tillverkar\nfasadelement i betong\nAntal anställda: 22\nÅrsomsättning: 2 000 000\nAktiekapital: 51 300\nStyrelse: Dir Olof Lindström\n(ordf), byggmäst Erik Lindberg\nVerkst dir: Olof Lindström\nEtableringsàr: 1937.\n\nCEMENTA, AB\n\nPnr 20110\n\nMalmö 1, Stormg 14. Pack. Tel\n040-736 60. Tga Cementa. Telex 32316\nModerbolag i Cementakoncernen\n\nStyrelse:\n\nDir Elam Tunhammar (ordf),\nhovrättsrådet Sven Hammarskiöld,\ngreve Carl-Gustaf Klingspor,\növerstelöjtnant Polke Nyström,\ndir Ragnar Sundén,\nbankdir Lars-Erik Thunholm,\ndir Donovan Werner,\nambassadör Sten Lindh\n\nKoncernledning:\nVerkst dir: Sten Lindh\n\nV\tverkst dir: Walter Wredenfors\n\nV\tverkst dir: Stig Sunne\n\nV\tverkst dir: Gunnar Rosenborg\nDir Tor Blomquist\n\nDir Stig Lindblom\nDir Ingemar Rehnberg\n\nI Cementakoncernen ingår bl a:\nCementfabriker i Hällekis, Köping,\nLimhamn, Stora Vika, Slite o\nDegerhamn\n\nGöteborgs Sand, Göteborg\nNorrköpings Sand, Norrköping\n\nAB Iföverken, Bromölla\nIfö Stålpressnings AB, Bromölla\nArmaturfabriken Trio AB, Lönsboda\nVärme &amp; Sanitets ABIdo, Stockholm\nAB Installationsmateriel, Vimmerby\nWolfes &amp; Weisse GmbH,\nVästtyskland\n\nAB Cementa Bygg, Malmö\nAB Eternitrör, Varberg\nAB Gyproc, Malmö, Varberg o Bälsta\nSkandinaviska Eternit AB, Lomma\no Köping\n\nSiporex AB, Stockholm, Dalby,\nSödertälje o Skelleftehamn\nNorddeutsche Siporex GmbH,\nSchneverdingen\nSiporex Brabant, S A, Bryssel\nSiporex Maisse S A, Paris\n\nAB Bostadsforskning, Stockholm\nAB Elementhus, Mockfjärd\nAB Konstharts, Simrishamn\nAB Vibro-Verken, Solna,\nKarlskrona o Ljungby\n\nVerksamhet i moderbolaget:\n\nTillverkar o försäljer cement- o\nkalkprodukter\n\nProduktgruppchef: V verkst dir\nWalter Wredenfors\nMarknadsavdelningen: Dir Hans\nRiiter\n\nTekniska avdelningen: Dir Gunnar\nChr Laurell\n\nFabriker:\n\nHällekis. Disp Olof Rosenqvist\nKöping. Disp Per Sylvan\nLimhamn. Disp Ragnar Troell\nStora Vika. Disp Karl-Erik Eriksson\nSlite. Disp Yngve Barkell\nDegerhamn. Disp Låge Themner\nStockholm. Disp Ivar Bodegård\n\nFörsäljningskontor:\n\nMalmö. Disp Töre Lindskog\nGöteborg. Disp Torsten Lönnqvist\nStockholm. Disp Erik Dahlbeck\nUmeå. Disp Ake Hammarstedt\n\nVerksamhet i koncernen:\n\nSe under respektive företag\n\nAntal anställda: 3015 Moderbolaget\n11600 Koncernen\n\nÅrsomsättning: 360 000 000\nModerbolaget\n\n1080 000 000 Koncernen\nAktiekapital: 276 721000\nEtableringsàr: 1871\nNuvarande namn sedan 1-9-69.\n\nCEMENTA BYGG, AB\n\nIngår i Cementakoncernen\n\nPnr 20013\n\nMalmö 27, Hanög 8. Box 27047. Tel\n040-18 0040. Bankgiro 64-0485.\nPostgiro 43 0429. Tga Tilefixing\nVerksamhet: Entreprenörer för\nplattsättnings-, golvläggnings-,\nmellanväggs- o fogningsarbeten\nm m samt försäljare av\nbyggnadsmaterial\n\nAvdelningskontor: 412 85 Göteborg,\nMö Indals v 85. Tel 031-8133 90.\nPlatschef: Lars Schreiter\n\nArbetschef: Karl E Peterson\n104 22 Stockholm 22, Box 22045.\nNorr Mälarstrand 22. Tel\n08-54 1100\n\nAntal anställda: 420\nÅrsomsättning: 40 000 000\nAktiekapital: 100 000\nVerkst dir: Alvar Ericsson\nKamrer: Erik Stenquist\nFörsäljn-chef: Börje Persson\nArbetschefer: Arthur Pettersson,\nLennart Hansson\nEtableringsàr: 1950.\n\nCEMENTOL, AB\n\nPnr 402 72\n\nGöteborg 8, Box 8866. Ruskvädersg\n18. Tel 031-54 04 40. Bankgiro\n441-1161. Postgiro 12277-0. Tga\nCementol. Telex 20037\nVerksamhet: Isolerings- o\nplåtarbeten\n\nAntal anställda: 110\nÅrsomsättning: 6 000 000\nAktiekapital: 34 750\nVerkst dir Disp Birger Sylvan\nEtableringsàr 1918.\n\nCEMENTVARU-\n\nse resp namn.\n\nCEMENTVARUBOLAGET I\nSTOCKHOLM AB\n\nPnr 141 49\n\nHuddinge, Glömstav 31. Tel\n08-757 28 20\n\nVerksamhet: Cementvaror o\nbyggnadsmaterial\n\nCementgjuterier: Huddinge.\nHuddinge Cementgjuteri, Glömstav 31.\nTel 08-757 28 20\n\nSorunda. Södertörns Cementgjuteri.\nTel 0753-40150\nAntal anställda: 70\nAktiekapital: 400 000\nEtableringsàr 1935\nNuvarande namn 1941.\n\nCEMENTVARUMASKINER, AB\n\nPnr 610 53\n\nEnstaberga, Pack. Tel 0155-573 50.\nBankgiro 61-9123. Postgiro284008.\nTga Abece. Telex 64163 ABECE S\nVerksamhet: Tillverkar o säljer\nmaskiner o utrustningar för\nbe-tongvaruindustrien\nAntal anstäUda: 60\nAktiekapital: 15 000\nStyrelse: Adv H Heilborn (ordf),\ning Bernt Jidell, disp Bertil\nBoström\n\nVerkst dir: Bernt Jidell\nEtableringsàr 1944.\n\nSJÖSTRAND AB, ALLAN\n\nPnr 25102\n\nHelsingborg 1, Box 22. Drottningg\n148. Tel 042-13 9190. Bankgiro\n653-3103. Postgiro 507210-3\nVerksamhet: Kemiska produkter,\nparfymer, laboratorieutrustning mm\nAntal anstäUda: 4\nÅrsomsättning: 15 000 000\nAktiekapital: 5 000\nVerkst dir: Allan Sjöstrand\nEtableringsår: 1951.\n\nVIN\n\nAntal anställda: 60\nVerkst dir: K Karlström\nEtableringsår: 1875.\n\nRICHTER AB, LEONARD\n\nPnr 25102\n\nHelsingborg 1, Box 33. Järnvägsg\n19. Tel 042-11 17 00,11 43 22.\nBankgiro 86-3986. Postgiro 8148. Tga\nAj nos\n\nVerksamhet:Säljer spannmål, foder,\ngödning o stärkelse\nVerkst dir: Sven Richter\nEtableringsår: 1910.\n\nRICKARDSSON, AB\nBRÖDERNA\n\nPnr 73200\n\nArboga, Industrig 14. Box 38. Tel\n0589-15020. Bankgiro 809-8303.\nPostgiro 287894-0. Telex 73401\nVerksamhet: Tillverkar släpvagnar\nAntal anstäUda: 80\nÅrsomsättning: 13 000 000\nAktiekapital: 225000\nVeikst dir: Georg Rickardsson\nEtableringsår: 1955.\n\nWERBA, AB\n\nPnr 15133\n\nSödertälje, Storg 44. Tel\n0755-399 70. Bankgiro 170-6894. Post-\n\ngiro 670170-0. Tga Werba.\nTelex 10911\n\nVerksamhet: Säljer verktyg o\nmaskinförnödenheter\nAntal anställda: 9\nÅrsomsättning: 3 500 000\nAktiekapital: 100 000\nEtableringsår: 1965.",
    "structured": {
        "1": {
            "company_name": "NORDEMANS BIL AB",
            "activity": "Säljer nya o begagnade person- o lastbilar",
            "establishment_year": 1955,
            "employees": 70,
            "annual_turnover": 11000000,
            "capital": 307000,
            "key_personnel": [
                {
                    "name": "Nils Nordeman",
                    "position": "Verkst dir"
                }
            ]
        },
        "2": {
            "company_name": "NORDEMANS JERNHANDEL, AB F W",
            "activity": "Järnvaror o byggnadsmaterial i parti o minut",
            "establishment_year": 1900,
            "employees": 30,
            "annual_turnover": 8500000,
            "capital": 250000,
            "key_personnel": [
                {
                    "name": "Hans Nordeman",
                    "position": "Verkst dir"
                }
            ]
        },
        "3": {
            "company_name": "NORD-EMBALLAGE, FOR-PACKNINGS-AB",
            "activity": "Säljer kartongförpackningar, etiketter o blanketter. Eget tryckeri",
            "establishment_year": 1968,
            "key_personnel": [
                {
                    "name": "Boktryckare Bror Månsson",
                    "position": "Chefer"
                },
                {
                    "name": "Boktryckare Göran Jeppsson",
                    "position": "Chefer"
                }
            ]
        },
        "4": {
            "company_name": "NORDEMO, BYGGNADS AB GÖSTA",
            "activity": "Fastighetsförvaltning. Utför reparationer",
            "establishment_year": 1937,
            "employees": 50,
            "annual_turnover": 5000000,
            "capital": 100000,
            "key_personnel": [
                {
                    "name": "Byggnadsing Gösta Nordemo",
                    "position": "Verkst dir"
                }
            ]
        },
        "5": {
            "company_name": "COOLA FILM & FORM AB",
            "activity": "Specialitet: tecknad o trickad animerad film. Reklam, PR o informationsfilm",
            "establishment_year": 1966,
            "key_personnel": [
                {
                    "name": "Formgivare Ola Lindahl",
                    "position": "Chef"
                }
            ]
        },
        "6": {
            "company_name": "ANDERSSON, AB VIKTOR",
            "activity": "Maskiner, verktyg o maskinförnödenheter",
            "establishment_year": 1902,
            "key_personnel": [
                {
                    "name": "Gösta Andersson",
                    "position": "Verkst dir"
                }
            ]
        },
        "7": {
            "company_name": "ANDERSSON TRÄVARUEXPORT, AB WICTOR",
            "activity": "Sågverk o trävaruexport",
            "establishment_year": 1935,
            "employees": 40,
            "annual_turnover": 6000000,
            "capital": 100000,
            "key_personnel": [
                {
                    "name": "Wictor Andersson",
                    "position": "Verkst dir"
                }
            ]
        },
        "8": {
            "company_name": "ANDERSONS METALLFABRIK AB, VILH",
            "activity": "Utför beställningsarbeten i järn o metall",
            "establishment_year": 1914,
            "employees": 9,
            "annual_turnover": 363000,
            "capital": 15000,
            "key_personnel": [
                {
                    "name": "Bertil Almerfors",
                    "position": "Firmatecknare"
                }
            ]
        },
        "9": {
            "company_name": "CONSTRUO",
            "activity": "Golvbrunnar syrafasta",
            "establishment_year": 1948,
            "key_personnel": [
                {
                    "name": "Ing Birger Lindqvist",
                    "position": "Ägare o chef"
                }
            ]
        },
        "10": {
            "company_name": "GEN",
            "capital": 30000,
            "key_personnel": [
                {
                    "name": "Fru Anna Persson",
                    "position": "Verkst dir"
                }
            ],
            "establishment_year": 1941
        },
        "11": {
            "company_name": "CEL",
            "activity": "SO,-utrustningar för kemiska industrin",
            "varunamn": "Rebeater, Vorject",
            "employees": 40,
            "annual_turnover": 15000000,
            "capital": 132000,
            "key_personnel": [
                {
                    "name": "Erik Backteman",
                    "position": "Verkst dir"
                }
            ],
            "ownership": "Äges av Alfa-Laval, Tumba",
            "establishment_year": 1936
        },
        "12": {
            "company_name": "CELLOPLAST, AB",
            "activity": "Tillverkar Wettex svampduk, polyetenfolier o produkter därav såsom påsar etc, tape, formar av polystyren, cellulosa-acetatfilm",
            "varunamn": "Alofan, Alofilm, Diofan, Känguru, Tenofilm, Wettex",
            "employees": 1000,
            "annual_turnover": 100000000,
            "capital": 10000000,
            "key_personnel": [
                {
                    "name": "Civiling Curt Lindquist",
                    "position": "Verkst dir"
                }
            ],
            "establishment_year": 1951
        },
        "13": {
            "company_name": "CELLVABRUKEN AB",
            "activity": "Säljer blöjor o mjuk-pappersprodukter",
            "key_personnel": [
                {
                    "name": "Bengt Lyberg",
                    "position": "Verkst dir"
                }
            ],
            "ownership": "Ägare: Mo och Domsjö AB",
            "establishment_year": 1961
        },
        "14": {
            "company_name": "CEMA KONSTSTENSGJUTERI, AB",
            "activity": "Tillverkar fasadelement i betong",
            "employees": 22,
            "annual_turnover": 2000000,
            "capital": 51300,
            "key_personnel": [
                {
                    "name": "Olof Lindström",
                    "position": "Styrelse - Ordf"
                },
                {
                    "name": "Erik Lindberg",
                    "position": "Styrelse - Byggmäst"
                },
                {
                    "name": "Olof Lindström",
                    "position": "Verkst dir"
                }
            ],
            "establishment_year": 1937
        },
        "15": {
            "company_name": "CEMENTA, AB",
            "activity": "Tillverkar o försäljer cement- o kalkprodukter",
            "employees": 3015,
            "annual_turnover": 360000000,
            "capital": 276721000,
            "establishment_year": 1871,
            "nuvarande_namn": "Nuvarande namn sedan 1-9-69"
        },
        "16": {
            "company_name": "CEMENTA BYGG, AB",
            "activity": "Entreprenörer för plattsättnings-, golvläggnings-, mellanväggs- o fogningsarbeten m m samt försäljare av byggnadsmaterial",
            "employees": 420,
            "annual_turnover": 40000000,
            "capital": 100000,
            "key_personnel": [
                {
                    "name": "Alvar Ericsson",
                    "position": "Verkst dir"
                },
                {
                    "name": "Erik Stenquist",
                    "position": "Kamrer"
                },
                {
                    "name": "Börje Persson",
                    "position": "Försäljn-chef"
                },
                {
                    "name": "Arthur Pettersson",
                    "position": "Arbetschef"
                },
                {
                    "name": "Lennart Hansson",
                    "position": "Arbetschef"
                }
            ],
            "establishment_year": 1950
        },
        "17": {
            "company_name": "CEMENTOL, AB",
            "activity": "Isolerings- o plåtarbeten",
            "employees": 110,
            "annual_turnover": 6000000,
            "capital": 34750,
            "key_personnel": [
                {
                    "name": "Disp Birger Sylvan",
                    "position": "Verkst dir"
                }
            ],
            "establishment_year": 1918
        },
        "18": {
            "company_name": "CEMENTVARUBOLAGET I STOCKHOLM AB",
            "activity": "Cementvaror o byggnadsmaterial",
            "employees": 70,
            "capital": 400000,
            "establishment_year": 1935,
            "nuvarande_namn": "Nuvarande namn 1941"
        },
        "19": {
            "company_name": "CEMENTVARUMASKINER, AB",
            "activity": "Tillverkar o säljer maskiner o utrustningar för be-tongvaruindustrien",
            "employees": 60,
            "capital": 15000,
            "key_personnel": [
                {
                    "name": "Adv H Heilborn",
                    "position": "Styrelse - Ordf"
                },
                {
                    "name": "Bernt Jidell",
                    "position": "Verkst dir"
                }
            ],
            "establishment_year": 1944
        },
        "20": {
            "company_name": "SJÖSTRAND AB, ALLAN",
            "activity": "Kemiska produkter, parfymer, laboratorieutrustning mm",
            "employees": 4,
            "annual_turnover": 15000000,
            "capital": 5000,
            "key_personnel": [
                {
                    "name": "Allan Sjöstrand",
                    "position": "Verkst dir"
                }
            ],
            "establishment_year": 1951
        },
        "21": {
            "company_name": "VIN",
            "employees": 60,
            "key_personnel": [
                {
                    "name": "K Karlström",
                    "position": "Verkst dir"
                }
            ],
            "establishment_year": 1875
        },
        "22": {
            "company_name": "RICHTER AB, LEONARD",
            "activity": "Säljer spannmål, foder, gödning o stärkelse",
            "key_personnel": [
                {
                    "name": "Sven Richter",
                    "position": "Verkst dir"
                }
            ],
            "establishment_year": 1910
        },
        "23": {
            "company_name": "RICKARDSSON, AB BRÖDERNA",
            "activity": "Tillverkar släpvagnar",
            "employees": 80,
            "annual_turnover": 13000000,
            "capital": 225000,
            "key_personnel": [
                {
                    "name": "Georg Rickardsson",
                    "position": "Verkst dir"
                }
            ],
            "establishment_year": 1955
        },
        "24": {
            "company_name": "WERBA, AB",
            "activity": "Säljer verktyg o maskinförnödenheter",
            "employees": 9,
            "annual_turnover": 3500000,
            "capital": 100000,
            "establishment_year": 1965
        }
    }
}