{
    "original": "WILSON &amp; CO\n\nPnr 402 32\n\nGöteborg 7, Första Långg 22. Box\n7091. Tel 031-124580. Telex 20629\nWILSON S. Tga Wilsonco\nVerksamhet; Rederiagentur,\nskeppsklarering, stuveri,\nskepps-mäkleri o befraktning\nEtableringsår: 1843.\n\nAUTOCODE AB\n\nPnr 17143\n\nSolna, Ankdammsg 40. Tel 08-\n\n83 43 95\n\nVerksamhet: Systemuppläggning o\nprogrammering.\nRealtidstillämpningar för minidatorer med\nelektronikutveckling. Servicebyråverksamhet för reaktionell\ninformationsbehandling med typografisk output\n(filmsättning) o för datorassisterad\nföretagsadministration\nVarunamn: MACT\nAntal anställda: 18\nVerkst dir: Lennart von Sydow\nEtableringsår: 1956.\n\nHK AB, HANDELSKOMPANIET\n\nPnr 551 02\n\nJönköping 1, Box 620. Osterängsv\n4. Tel 036-16 5 1 00. Bankgiro\n143-6104. Postgiro 6739-7\nVerksamhet: Säljer livsmedel en gros\n(VIVO-grossist)\nAntal anställda: 275\nÅrsomsättning: 200 000 000\nAktiekapital: 1000 000\nVerkst dir: Bengt Fritz\nEtableringsår: 1919.\n\nSVEAS TRIKÄSTICKERI\n\nPnr 51100\n\nKinna. Tel 0320-103 31. Bankgiro\n43-4751. Postgiro 88761\nVerksamhet: Tillverkar trikåvaror i\nylle o bomull, strumpor, jumpers,\nkoftor, cardigan, västar o pullovers\nAntal anställda: 50\nÅrsomsättning: 2 000 000\nÄgare o chef: Karl Skotth\nEtableringsår: 1927.\n\nELEKTROBORG, AB\n\nPnr 171 52\n\nSolna, Gärdsv 2-4. Tel 08-27 25 60.\nBankgiro 620-7161. Postgiro\n257901-9. Tga Borgelektro.\nTelex 10347 CIBES S\n\n\n\nVerksamhet: Tillverkar o säljer\nvaruhissar, svängkranar, lyftblock,\nvinschar, strömledningsmaterial,\ntransportlådor, stålinredningar\nVarunamn: Cibes, Gluma\nAntal anställda: 30\nAktiekapital: 50 000\nVerkst dir: Ing Arne Mellquist\nEtableringsår: 1947.\n\nELEKTROBYRAN, AB\n\nPnr 761 00\n\nNorrtälje, Hantverkarg 6. Tel\n0176-125 90. Bankgiro 80-5215. Postgiro\n13385\n\nVerksamhet: Utför elektr installar\ntioner\n\nAntal anställda: 175\nÅrsomsättning: 15 000 000\nAktiekapital: 25000\nVerkst dir: Ing Ragnar Agering\nEtableringsår: 1935.\n\nFRANCOLOR SVENSKA AB\n\nPnr 50102\n\nBorås 1, Box 43. Kungsg 40. Tel\n033-1014 31, 10 14 32. Bankgiro\n22-4433. Postgiro 688950-5\nVerksamhet: Säljer anilinfärger,\npigment o hjälpmedelsprodukter\nAntal anställda: 6\nÅrsomsättning: 2 000 000\nAktiekapital: 100 000\nVerkst dir: Ing Arne Smerige\nEtableringsår: 1967.\n\nAXLUND,\nINGENIÖRSFIRMAN O T\n\nPnr 162 10\n\nVällingby 1, Kross g 32. Fack. Tel\n08-38 00 40. Tga Ifax. Telex 19064\nVerksamhet: Sjukhussignaler,\nhotellsignaler, elektriska ur,\ntidredovisning, lokaltelefon, snabbtelefon,\nljuddistribution, märksystem för\nelektriska ledningar,\nförläggnings-materiel, reläer, elektroniska\nräkneverk, tidreläer\nAntal anställda: 80\nÄgare o chef: Ing O T Axlund\nEtableringsår: 1933.\n\nDIABAS, AB\n\nPnr 11161\n\nStockholm, Tegnérlunden 3. Tel\n08-2367 40. Bankgiro 830-3018.\nPostgiro 345863-5\nVerksamhet: Säljer makadam\nMakadamfabrik: Lilleskog. Tel\n0521-20030. Platschef: G Ahlberg\nAntal anställda: 27\nAktiekapital: 200 000\nVerkst dir: S Ahlberg\nEtableringsår: 1950.\n\nDIAMANTKOMPANIET,\nEK-STEDT &amp; CO AB\n\nPnr 590 30\n\nBorensberg. Box 85. Tel\n0141-408 40. Tga Diamantkomp.\nTelex 5557 DIAMANT S\nVerksamhet: Agenturförsäljning o\negen tillverkning av\ndiamantverktyg, diamantslipskivor,\ndiamant-bergborrkronor, diamantdragskivor,\ndiamantpulver, Timesaver o\nTime-cutter inslipningspulver samt\nservice, dvs omfattningar o\nomslip-ningar av diamantverktyg\nVarunamn: Ekstedt, Citco, Brussin,\nTimecutter, Timesaver\nAntal anställda: 13\nAktiekapital: 45 000\nVerkst dir: Erik Henning Ekstedt\nEtableringsår: 1946\nOmbildat till aktiebolag 1962.\n\nDIAMANTPRODUKTER AB\n\nPnr 126 53\n\nHägersten, Jakobsdalsv 14-16. Tel\n08-45 27 75. Bankgiro 569-8147.\nPostgiro 359287-0. Tga\nDiamantprodukt, Stockholm\nVerksamhet: Tillverkar\nhandfilma-skinen Diprofil samt verktyg till\ndenna\n\nVarunamn: Diprofil\nAntal anställda: 25\nÅrsomsättning: 3 500 000\nAktiekapital: 60 000\nVerkst dir: Sten Ekberg\nEtableringsår: 1949.\n\nZAC\n\nZACCO &amp; CO EFTR AB\n\nPnr 101 22\n\nStockholm 1, Dalatrappan 4. Box\n161. Tel 08-106292, 207444.\nBankgiro 722-2490. Postgiro\n50049-6. Tga Zeta\nVerksamhet: Lyftverktyg\notransport-materiel samt transmissioner\nAntal anställda: 5\nAktiekapital: 100 000\nVerkst dir: Sven E Krantz\nEtableringsår 1871\nOmbildat till aktiebolag 1950.\n\nZACHAU’S FLAGGFABRIK\nAB. GRETA\n\nPnr 116 64\n\nStockholm 90, Ostgötag 73 B. Tel\n4103 09, riks 08-44 25 50.\nBankgiro 573-4355. Postgiro 150857-1\nVerksamhet: Tillverkar svenska o\nutländska flaggor, fanor o vimplar,\nbordsflaggor o standar\n.Antal anställda: 10\nAktiekapital: 10000\nÄgare o chef: Greta Zachau-Ryd\nEtableringsår 1957.\n\nALBAN| AB\n\nPnr 591 00\n\nMotala, Agneshögsg. Tel\n0141-16 4 90. Bankgiro 134-2641.\nPostgiro 70363-7\n\nVerksamhet: Galvanisk industri.\nSpecialitet: hårdförkromning av\nkolvstänger. Kemisk förnickling\nAktiekapital: 240000\nVerkst dir: Bengt Danielson\nEtableringsår: 1945.",
    "structured": {
        "1": {
            "company_name": "WILSON & CO",
            "address": "Göteborg 7, Första Långg 22. Box 7091",
            "phone_number": "031-124580",
            "bank_details": {
                "bankgiro": "",
                "postgiro": ""
            },
            "activity": "Rederiagentur, skeppsklarering, stuveri, skepps-mäkleri o befraktning",
            "establishment_year": 1843
        },
        "2": {
            "company_name": "AUTOCODE AB",
            "address": "Solna, Ankdammsg 40",
            "phone_number": "08-83 43 95",
            "activity": "Systemuppläggning o programmering. Realtidstillämpningar för minidatorer med elektronikutveckling. Servicebyråverksamhet för reaktionell informationsbehandling med typografisk output (filmsättning) o för datorassisterad företagsadministration",
            "employees": 18,
            "establishment_year": 1956
        },
        "3": {
            "company_name": "HK AB, HANDELSKOMPANIET",
            "address": "Jönköping 1, Box 620. Osterängsv 4",
            "phone_number": "036-16 5 1 00",
            "bank_details": {
                "bankgiro": "143-6104",
                "postgiro": "6739-7"
            },
            "activity": "Säljer livsmedel en gros (VIVO-grossist)",
            "employees": 275,
            "annual_turnover": 200000000,
            "capital": 1000000,
            "establishment_year": 1919
        },
        "4": {
            "company_name": "SVEAS TRIKÄSTICKERI",
            "address": "Kinna",
            "phone_number": "0320-103 31",
            "bank_details": {
                "bankgiro": "43-4751",
                "postgiro": "88761"
            },
            "activity": "Tillverkar trikåvaror i ylle o bomull, strumpor, jumpers, koftor, cardigan, västar o pullovers",
            "employees": 50,
            "annual_turnover": 2000000,
            "establishment_year": 1927
        },
        "5": {
            "company_name": "ELEKTROBORG, AB",
            "address": "Solna, Gärdsv 2-4",
            "phone_number": "08-27 25 60",
            "bank_details": {
                "bankgiro": "620-7161",
                "postgiro": "257901-9"
            },
            "activity": "Tillverkar o säljer varuhissar, svängkranar, lyftblock, vinschar, strömledningsmaterial, transportlådor, stålinredningar",
            "employees": 30,
            "capital": 50000,
            "establishment_year": 1947
        },
        "6": {
            "company_name": "ELEKTROBYRAN, AB",
            "address": "Norrtälje, Hantverkarg 6",
            "phone_number": "0176-125 90",
            "bank_details": {
                "bankgiro": "80-5215",
                "postgiro": "13385"
            },
            "activity": "Utför elektr installationer",
            "employees": 175,
            "annual_turnover": 15000000,
            "capital": 25000,
            "establishment_year": 1935
        },
        "7": {
            "company_name": "FRANCOLOR SVENSKA AB",
            "address": "Borås 1, Box 43. Kungsg 40",
            "phone_number": "033-1014 31, 10 14 32",
            "bank_details": {
                "bankgiro": "22-4433",
                "postgiro": "688950-5"
            },
            "activity": "Säljer anilinfärger, pigment o hjälpmedelsprodukter",
            "employees": 6,
            "annual_turnover": 2000000,
            "capital": 100000,
            "establishment_year": 1967
        },
        "8": {
            "company_name": "AXLUND, INGENIÖRSFIRMAN O T",
            "address": "Vällingby 1, Kross g 32",
            "phone_number": "08-38 00 40",
            "activity": "Sjukhussignaler, hotellsignaler, elektriska ur, tidredovisning, lokaltelefon, snabbtelefon, ljuddistribution, märksystem för elektriska ledningar, förläggnings-materiel, reläer, elektroniska räkneverk, tidreläer",
            "employees": 80,
            "establishment_year": 1933
        },
        "9": {
            "company_name": "DIABAS, AB",
            "address": "Stockholm, Tegnérlunden 3",
            "phone_number": "08-2367 40",
            "bank_details": {
                "bankgiro": "830-3018",
                "postgiro": "345863-5"
            },
            "activity": "Säljer makadam. Makadamfabrik: Lilleskog. Tel 0521-20030. Platschef: G Ahlberg",
            "employees": 27,
            "capital": 200000,
            "establishment_year": 1950
        },
        "10": {
            "company_name": "DIAMANTKOMPANIET, EK-STEDT & CO AB",
            "address": "Borensberg. Box 85",
            "phone_number": "0141-408 40",
            "bank_details": {
                "bankgiro": "",
                "postgiro": ""
            },
            "activity": "Agenturförsäljning o egen tillverkning av diamantverktyg, diamantslipskivor, diamant-bergborrkronor, diamantdragskivor, diamantpulver, Timesaver o Time-cutter inslipningspulver samt service, dvs omfattningar o omslip-ningar av diamantverktyg",
            "employees": 13,
            "capital": 45000,
            "establishment_year": 1946
        },
        "11": {
            "company_name": "DIAMANTPRODUKTER AB",
            "address": "Hägersten, Jakobsdalsv 14-16",
            "phone_number": "08-45 27 75",
            "bank_details": {
                "bankgiro": "569-8147",
                "postgiro": "359287-0"
            },
            "activity": "Tillverkar handfilma-skinen Diprofil samt verktyg till denna",
            "employees": 25,
            "annual_turnover": 3500000,
            "capital": 60000,
            "establishment_year": 1949
        },
        "12": {
            "company_name": "ZAC ZACCO & CO EFTR AB",
            "address": "Stockholm 1, Dalatrappan 4. Box 161",
            "phone_number": "08-106292, 207444",
            "bank_details": {
                "bankgiro": "722-2490",
                "postgiro": "50049-6"
            },
            "activity": "Lyftverktyg o transport-materiel samt transmissioner",
            "employees": 5,
            "capital": 100000,
            "establishment_year": 1871
        },
        "13": {
            "company_name": "ZACHAU’S FLAGGFABRIK AB. GRETA",
            "address": "Stockholm 90, Ostgötag 73 B",
            "phone_number": "4103 09, riks 08-44 25 50",
            "bank_details": {
                "bankgiro": "573-4355",
                "postgiro": "150857-1"
            },
            "activity": "Tillverkar svenska o utländska flaggor, fanor o vimplar, bordsflaggor o standar",
            "employees": 10,
            "capital": 10000,
            "establishment_year": 1957
        },
        "14": {
            "company_name": "ALBAN| AB",
            "address": "Motala, Agneshögsg",
            "phone_number": "0141-16 4 90",
            "bank_details": {
                "bankgiro": "134-2641",
                "postgiro": "70363-7"
            },
            "activity": "Galvanisk industri. Specialitet: hårdförkromning av kolvstänger. Kemisk förnickling",
            "capital": 240000,
            "establishment_year": 1945
        }
    }
}