{
    "original": "ELEKTROKEMISKA AB\n\nPnr 445 00\n\nBohus. Tel 031-98 05 20. Bankgiro\n500-8149. Postgiro 8870-8. Tga\nElektrokemiska, Göteborg.\nTelex 2435 EKAGBG S\nVerksamhet: Tillverkar o säljer\nkemikalier\n\nAktiekapital: 23 000 000\nVerkst dir: John-Gabriel\nMontgomery\n\nFörsäljning: De nordiska länderna:\nIntendent Ake Larsson\n\nÖvriga länder: Intendent Bertil\nLindqvist\n\nEkonomi o administration:\nEkonomichef Stig Larsson\nEtableringsår: 1895.\n\nELEKTROKONSULT\nCIVILINGENJÖR LARS SVENSSON\nAB, INGENJORSBYRAN\n\nPnr 42152\n\nVästra Frölunda, Klangfärgsg 11.\nTel 031-29 2220. Bankgiro 18-3903.\nPostgiro 621020\n\nVerksamhet: Konsulterande i\nelektroteknik\n\nAntal anställda: 30\nAktiekapital: 5 000\nVerkst dir: Civiling Lars Svensson\nEtableringsår: 1961.\n\nVOLVO PENTA, AB\n\nPnr 401 26\n\nGöteborg 1. Box 392. Tel\n031-2354 60. Bankgiro 500232.\nPostgiro 43660. Telex 20755. Tga Penta\nVerksamhet: Tillverkning av\nmarin-o industrimotorer i bensin- o\ndieselutförande samt\ngeneratoraggregat\n\nVarunamn: Volvo Penta\nAktiekapital: 5000\nVerkst dir: Harald Wiklund\n\nEtableringsår: 1935\nDotterbolag till AB Volvo.\nGöteborg.\n\nVOLVOFINANS, AB\n\nPnr 400 71\n\nGöteborg 21, Kyrkbytorget. Box\n21044. Tel 031-51 33 70. Bankgiro\n101-1907. Postgiro 626695-1\nVerksamhet: Finansiering inom\nVolvohandel\nAntal anställda: 11\nAktiekapital: 3 000 000\nVerkst dir: Claes-Ake Nygren\nEtableringsår 1959.\n\nEGON, REDERI AB\n\nPnr 20123\n\nMalmö 1, Box 334. Carlsg 54. Tel\n040-380 77. Bankgiro 870-2086.\nPostgiro 434035-2. Tga Stjernan.\nTelex 32331 STJERNA S\nVerksamhet: Rederirörelse\nVerkst dir: Egon Stjerna\nEtableringsår: 1917.\n\nBORNANDERS INDUSTRI AB\n\nPnr 560 20\n\nNorrahammar, Box 21. Tel\n036-600 58. Bankgiro 545-4517.\nPostgiro 266004-1\n\nVerksamhet: Tillverkar\nbordsunderreden, byråsocklar,\npiano-pallar, svarvade massartiklar m m\nAntal anställda: 18\nÅrsomsättning: 1500 000\nAktiekapital: 45 000\nStyrelseordf: Fabr Ulf Bornander\nVerkst din Fabr Ulf Bornander\nEtableringsår: 1957.\n\nKALKKONTORET AB\n\nPnr 52100\n\nFalköping, Sankt Olovsg 3. Tel\n0515-10280, 10281. Bankgiro\n54-1547. Postgiro 23594. Tga\nKalkkontoret\n\nVerksamhet: Säljer bränd\nstyckekalk, bränd målen jordbrukskalk,\nbränd släckt \"hydrat\",\nkalkstens-mjöl, filler o stenmaterial\n(makadam), vägkalk\n\nVerkst dir: Everth Johnsson\nEtableringsår: 1911.\n\nKALLAX BETONG och GRUS\nAB\n\nPnr 95100\n\nLuleå. Residensg 1. Tel\n0920-155 85, 145 36. Bankgiro 369-6077.\nPostgiro 60697-0\nVerksamhet: Tillverkar o säljer\nfabriksblandad betongmassa\nAntal anställda: 30\nÅrsomsättning: 5 000 000\nAktiekapital: 50 000\nVerkst dir: Lars Forsman\nEtableringsår: 1947.\n\nKALMAR BETONGINDUSTRI,\nAB\n\nPnr 38100\n\nKalmar, Verkstadsg 27. Tel\n0480-22070\n\nVerksamhet: Tillverkar o säljer\nbetong- o lecavaror\nAntal anställda: 38\nAktiekapital: 400 000\nVerkst dir: E Claesson\nEtableringsår: 1949.\n\nLUNDGREN, AB K A\n\nPnr 402 51\n\nGöteborg 13. Box 13045. Tel\n031-19 26 30. Bankgiro 514-3250.\nPostgiro 41067-0. Tga Slaktprodukt.\nTelex 2590\n\nVerksamhet: Tarmar,\nslakteriprodukter, rostfritt, vågar o\ncharkuteri-maskiner, paketerings- o\ninslag-ningsmaskiner, förpackningar såsom\naluminium, plast, polyeten,\ncellofan, Saran, Isy-Wrap, Isy-Nät m m\nAvdelningskontor: Stockholm SÖ,\nMalmgårdsv 63 B. Tel 08-41 93 93\nAntal anställda: 40\nÅrsomsättning: 12000 000\nAktiekapital: 350000\nStyrelse: Björn Lundgren, Krister\nLundgren\n\nVerkst dir: Björn Lundgren\nEtableringsår: 1902\nOmbildat till aktiebolag 1918.\nGeneralagent Globe Slicing Co,\nA. E. Higginbottom Co Ltd.\n\nLUNDGRENS REVISIONSBYRÅ\nAB, KURT G\n\nPnr 722 12\n\nVästerås, Hantverkarg 2 B. Tel\n021-14 41 80. Bankgiro 68-1822.\nPostgiro 177485-0\nVerksamhet: Revisionsbyrå\nAntal anstäUda: 25\nÅrsomsättning: 1300 000\nAktiekapital: 5 000\nVerkst din Revisor Kurt Lundgren\nEtableringsår. 1941.\n\nDAHLGREN &amp; CO, AB R A\n\nPnr 53100\n\nLidköping 1, Box 15. Tel\n0510-660 50. Postgiro 111601. Tga\nDahlco\n\nVerksamhet: Generalagent för\nBray lastmaskiner, Hydromac\ngrävmaskiner, Hanomg traktorer,\nösterrikiska, tyska, belgiska o danska\nlantbruksmaskiner\nAntal anställda: 30\nÅrsomsättning: 7 000 000\nAktiekapital: 300 000\nFirmatecknare: Gunnar Göranson\nEtableringsår: 1954.\n\nWOLRATHS BIL AB\n\nPnr 750 03\n\nUppsala 3, Björkg 4. Box 3015.\nTel 018-13 97 90. Bankgiro\n802-3129. Postgiro 464724-4\nVerksamhet: Nya o begagnade\nbilar, bilreparationer o reservdelar\nAntal anställda: 100\nÅrsomsättning: 25 000 000\nAktiekapital: 2 000 000\nVeikst dir: Töre Modén.\n\nWOLRATHS BIL I ÖREBRO AB\n\nPnr 70106\n\nÖrebrol.Radiatorv l.Box 435. Tel\nTel 019-12 43 30. Bankgiro\n815-8883. Postgiro 360280-2\nVerksamhet: Återförsäljare av\nChevrolet, Opel o Bedford\nAntal anställda: 100\nÅrsomsättning: 20 000 000\nAktiekapital: 500 000\nVerkst dir. Erik Vernét\nEtableringsår: 1947.\n\nSVENSKA IWACO AB\n\nPnr 183 03\n\nTätay 3, Box 3015. Djursholmsv 29.\nTel 08-756 02 00. Bankgiro\n720-1700. Postgiro 152970-0. Tga\nIwa-print\n\nVerksamhet: Säljer etiketter,\nbutiksreklam samt storoffset\nAktiekapital: 10 000\nVerkst dir. Otto Oest\nEtableringsår: 1957.\n\nFLOBYVERKEN, AB\n\nPnr 520 40\n\nFloby. Tel 0515-40300. Postgiro\n240825-0\n\nVerksamhet: Tillverkar gallerdurk,\nslitsdurk, trappor,\ntryckluftsbehål-lare, ånglådor, mek arbeten,\nsvetsning, grov o tunnplåtsarbeten,\njärn o stålkonstruktioner,\nrörbock-ning mm\n\nFörsäljningskontor: Göteborg C.\nAB Calvert &amp; Co, O Hamng 19.\nTel 031-17 2040\nVarunamn: Ce-Ce\nAntal anställda: 45\nÅrsomsättning: 2500 000\nAktiekapital: 100 000\nStyrelse: Bankdir Arne Nilsson\n(ordf), dir Erik Abrahamsson,\nkamrer Greger Calvert, civiling\nHenrik Weilenmann\nVerkst dir: Erik Abrahamsson\nEtableringsår: 1945.\n\nFLODA PAPPERS.\nINDUSTRI AB\n\nPnr 440 03\n\nFloda 1. Box 131. Tel 0302-228 46.\nBankgiro 847-9289. Postgiro\n520211-4\n\nVerksamhet: Tillverkar\nkontorsartiklar o trycksaker\nÄgare o chefer: Bertil Samuelson,\nJan Samuelson\nEtableringsår: 1955\nOmbildat till aktiebolag 1961.\n\nFLODINS INDUSTRI AB\n\nPnr 453 00\n\nLysekil, Rinkenäs. Tel\n0523-118 30. Bankgiro 548-2245.\nPostgiro 474999-0. Tga Fiab. Telex\n42051\n\nVerksamhet: Plastsvetsmaskiner,\nluftreningsaggregat, gasmasker för\nmilitära o civila ändamål\nAntal anställda: 100\nVerkst dir: Bengt Flodin\nEtableringsår: 1950.",
    "structured": {
        "1": {
            "company_name": "ELEKTROKEMISKA AB",
            "pnr": "445 00",
            "address": "Bohus",
            "phone_number": "031-98 05 20",
            "bank_details": {
                "bankgiro": "500-8149",
                "postgiro": "8870-8"
            },
            "activity": "Tillverkar o säljer kemikalier",
            "capital": 23000000,
            "key_personnel": [
                {
                    "name": "John-Gabriel Montgomery",
                    "position": "Verkst dir"
                },
                {
                    "name": "Ake Larsson",
                    "position": "Intendent"
                },
                {
                    "name": "Bertil Lindqvist",
                    "position": "Intendent"
                },
                {
                    "name": "Stig Larsson",
                    "position": "Ekonomichef"
                }
            ],
            "establishment_year": 1895
        },
        "2": {
            "company_name": "ELEKTROKONSULT CIVILINGENJÖR LARS SVENSSON AB, INGENJORSBYRAN",
            "pnr": "42152",
            "address": "Västra Frölunda, Klangfärgsg 11",
            "phone_number": "031-29 2220",
            "bank_details": {
                "bankgiro": "18-3903"
            },
            "activity": "Konsulterande i elektroteknik",
            "employees": 30,
            "capital": 5000,
            "key_personnel": [
                {
                    "name": "Civiling Lars Svensson",
                    "position": "Verkst dir"
                }
            ],
            "establishment_year": 1961
        },
        "3": {
            "company_name": "VOLVO PENTA, AB",
            "pnr": "401 26",
            "address": "Göteborg 1, Box 392",
            "phone_number": "031-2354 60",
            "bank_details": {
                "bankgiro": "500232",
                "postgiro": "43660"
            },
            "activity": "Tillverkning av marin-o industrimotorer i bensin- o dieselutförande samt generatoraggregat",
            "capital": 5000,
            "key_personnel": [
                {
                    "name": "Harald Wiklund",
                    "position": "Verkst dir"
                }
            ],
            "establishment_year": 1935
        },
        "4": {
            "company_name": "VOLVOFINANS, AB",
            "pnr": "400 71",
            "address": "Göteborg 21, Kyrkbytorget, Box 21044",
            "phone_number": "031-51 33 70",
            "bank_details": {
                "bankgiro": "101-1907",
                "postgiro": "626695-1"
            },
            "activity": "Finansiering inom Volvohandel",
            "employees": 11,
            "capital": 3000000,
            "key_personnel": [
                {
                    "name": "Claes-Ake Nygren",
                    "position": "Verkst dir"
                }
            ],
            "establishment_year": 1959
        },
        "5": {
            "company_name": "EGON, REDERI AB",
            "pnr": "20123",
            "address": "Malmö 1, Box 334, Carlsg 54",
            "phone_number": "040-380 77",
            "bank_details": {
                "bankgiro": "870-2086",
                "postgiro": "434035-2"
            },
            "activity": "Rederirörelse",
            "key_personnel": [
                {
                    "name": "Egon Stjerna",
                    "position": "Verkst dir"
                }
            ],
            "establishment_year": 1917
        },
        "6": {
            "company_name": "BORNANDERS INDUSTRI AB",
            "pnr": "560 20",
            "address": "Norrahammar, Box 21",
            "phone_number": "036-600 58",
            "bank_details": {
                "bankgiro": "545-4517",
                "postgiro": "266004-1"
            },
            "activity": "Tillverkar bordsunderreden, byråsocklar, piano-pallar, svarvade massartiklar m m",
            "employees": 18,
            "annual_turnover": 1500000,
            "capital": 45000,
            "key_personnel": [
                {
                    "name": "Fabr Ulf Bornander",
                    "position": "Styrelseordf, Verkst dir"
                }
            ],
            "establishment_year": 1957
        },
        "7": {
            "company_name": "KALKKONTORET AB",
            "pnr": "52100",
            "address": "Falköping, Sankt Olovsg 3",
            "phone_number": "0515-10280, 10281",
            "bank_details": {
                "bankgiro": "54-1547",
                "postgiro": "23594"
            },
            "activity": "Säljer bränd styckekalk, bränd målen jordbrukskalk, bränd släckt 'hydrat', kalkstens-mjöl, filler o stenmaterial (makadam), vägkalk",
            "key_personnel": [
                {
                    "name": "Everth Johnsson",
                    "position": "Verkst dir"
                }
            ],
            "establishment_year": 1911
        },
        "8": {
            "company_name": "KALLAX BETONG och GRUS AB",
            "pnr": "95100",
            "address": "Luleå, Residensg 1",
            "phone_number": "0920-155 85, 145 36",
            "bank_details": {
                "bankgiro": "369-6077",
                "postgiro": "60697-0"
            },
            "activity": "Tillverkar o säljer fabriksblandad betongmassa",
            "employees": 30,
            "annual_turnover": 5000000,
            "capital": 50000,
            "key_personnel": [
                {
                    "name": "Lars Forsman",
                    "position": "Verkst dir"
                }
            ],
            "establishment_year": 1947
        },
        "9": {
            "company_name": "KALMAR BETONGINDUSTRI, AB",
            "pnr": "38100",
            "address": "Kalmar, Verkstadsg 27",
            "phone_number": "0480-22070",
            "activity": "Tillverkar o säljer betong- o lecavaror",
            "employees": 38,
            "capital": 400000,
            "key_personnel": [
                {
                    "name": "E Claesson",
                    "position": "Verkst dir"
                }
            ],
            "establishment_year": 1949
        },
        "10": {
            "company_name": "LUNDGREN, AB K A",
            "pnr": "402 51",
            "address": "Göteborg 13, Box 13045",
            "phone_number": "031-19 26 30",
            "bank_details": {
                "bankgiro": "514-3250",
                "postgiro": "41067-0"
            },
            "activity": "Tarmar, slakteriprodukter, rostfritt, vågar o charkuteri-maskiner, paketerings- o inslag-ningsmaskiner, förpackningar såsom aluminium, plast, polyeten, cellofan, Saran, Isy-Wrap, Isy-Nät m m",
            "employees": 40,
            "annual_turnover": 12000000,
            "capital": 350000,
            "key_personnel": [
                {
                    "name": "Björn Lundgren",
                    "position": "Styrelseordf, Verkst dir"
                },
                {
                    "name": "Krister Lundgren",
                    "position": "Styrelse"
                }
            ],
            "establishment_year": 1902
        },
        "11": {
            "company_name": "LUNDGRENS REVISIONSBYRÅ AB, KURT G",
            "pnr": "722 12",
            "address": "Västerås, Hantverkarg 2 B",
            "phone_number": "021-14 41 80",
            "bank_details": {
                "bankgiro": "68-1822",
                "postgiro": "177485-0"
            },
            "activity": "Revisionsbyrå",
            "employees": 25,
            "annual_turnover": 1300000,
            "capital": 5000,
            "key_personnel": [
                {
                    "name": "Revisor Kurt Lundgren",
                    "position": "Verkst dir"
                }
            ],
            "establishment_year": 1941
        },
        "12": {
            "company_name": "DAHLGREN & CO, AB R A",
            "pnr": "53100",
            "address": "Lidköping 1, Box 15",
            "phone_number": "0510-660 50",
            "postgiro": "111601",
            "activity": "Generalagent för Bray lastmaskiner, Hydromac grävmaskiner, Hanomg traktorer, österrikiska, tyska, belgiska o danska lantbruksmaskiner",
            "employees": 30,
            "annual_turnover": 7000000,
            "capital": 300000,
            "key_personnel": [
                {
                    "name": "Gunnar Göranson",
                    "position": "Firmatecknare"
                }
            ],
            "establishment_year": 1954
        },
        "13": {
            "company_name": "WOLRATHS BIL AB",
            "pnr": "750 03",
            "address": "Uppsala 3, Björkg 4, Box 3015",
            "phone_number": "018-13 97 90",
            "bank_details": {
                "bankgiro": "802-3129",
                "postgiro": "464724-4"
            },
            "activity": "Nya o begagnade bilar, bilreparationer o reservdelar",
            "employees": 100,
            "annual_turnover": 25000000,
            "capital": 2000000,
            "key_personnel": [
                {
                    "name": "Töre Modén",
                    "position": "Verkst dir"
                }
            ]
        },
        "14": {
            "company_name": "WOLRATHS BIL I ÖREBRO AB",
            "pnr": "70106",
            "address": "Örebro l.Radiatorv l.Box 435",
            "phone_number": "019-12 43 30",
            "bank_details": {
                "bankgiro": "815-8883",
                "postgiro": "360280-2"
            },
            "activity": "Återförsäljare av Chevrolet, Opel o Bedford",
            "employees": 100,
            "annual_turnover": 20000000,
            "capital": 500000,
            "key_personnel": [
                {
                    "name": "Erik Vernét",
                    "position": "Verkst dir"
                }
            ],
            "establishment_year": 1947
        },
        "15": {
            "company_name": "SVENSKA IWACO AB",
            "pnr": "183 03",
            "address": "Tätay 3, Box 3015, Djursholmsv 29",
            "phone_number": "08-756 02 00",
            "bank_details": {
                "bankgiro": "720-1700",
                "postgiro": "152970-0"
            },
            "activity": "Säljer etiketter, butiksreklam samt storoffset",
            "capital": 10000,
            "key_personnel": [
                {
                    "name": "Otto Oest",
                    "position": "Verkst dir"
                }
            ],
            "establishment_year": 1957
        },
        "16": {
            "company_name": "FLOBYVERKEN, AB",
            "pnr": "520 40",
            "address": "Floby",
            "phone_number": "0515-40300",
            "postgiro": "240825-0",
            "activity": "Tillverkar gallerdurk, slitsdurk, trappor, tryckluftsbehål-lare, ånglådor, mek arbeten, svetsning, grov o tunnplåtsarbeten, järn o stålkonstruktioner, rörbock-ning mm",
            "employees": 45,
            "annual_turnover": 2500000,
            "capital": 100000,
            "key_personnel": [
                {
                    "name": "Erik Abrahamsson",
                    "position": "Verkst dir"
                }
            ],
            "establishment_year": 1945
        },
        "17": {
            "company_name": "FLODA PAPPERS. INDUSTRI AB",
            "pnr": "440 03",
            "address": "Floda 1, Box 131",
            "phone_number": "0302-228 46",
            "bankgiro": "847-9289",
            "postgiro": "520211-4",
            "activity": "Tillverkar kontorsartiklar o trycksaker",
            "key_personnel": [
                {
                    "name": "Bertil Samuelson",
                    "position": "Ägare o chefer"
                },
                {
                    "name": "Jan Samuelson",
                    "position": "Ägare o chefer"
                }
            ],
            "establishment_year": 1955
        },
        "18": {
            "company_name": "FLODINS INDUSTRI AB",
            "pnr": "453 00",
            "address": "Lysekil, Rinkenäs",
            "phone_number": "0523-118 30",
            "bankgiro": "548-2245",
            "postgiro": "474999-0",
            "activity": "Plastsvetsmaskiner, luftreningsaggregat, gasmasker för militära o civila ändamål",
            "employees": 100,
            "key_personnel": [
                {
                    "name": "Bengt Flodin",
                    "position": "Verkst dir"
                }
            ],
            "establishment_year": 1950
        }
    }
}