{
    "original": "COLLY COMPANY AB\n\nPnr 181 07\n\nLidingö 7, Box 724. Bodalsv 2 A.\nTel 08-765 25 55. Bankgiro 74-6511.\nPostgiro 554141-2. Tga\nColly-company. Telex 17421 COLLCO S\nVerksamhet: Säljer\nindustriförnödenheter. Representerar som\ngeneralagent företag i Tyskland,\nEngland o USA\nAntal anställda: 20\nAktiekapital: 100 000\nStyrelse: Ekonomichef Stig\nHoff-ner (ordf), ing Fred Lindgren, fru\nIngrid Lindgren\n\nTeknisk chef: Ingvar Fagerberg\n\nEkonomichef: Stig Hoffner\nFörsäljn-chef: Owe Bergius\nEtableringsår: 1957.\n\nLINDMARK &amp; CO AB, H\n\nPnr 11129\n\nStockholm, Järntorget 83. Tel\n08-1111 43, 20 95 43. Bankgiro\n478-2595. Postgiro 250464-5.\nTga Lindbroker.\nTelex 19331 LINDBRO S\nVerksamhet: Auktoriserade\nskeppsklarerare\n\nAktiekapital: 25 000\nVerkst dir: Staffan Broms\nEtableringsår: 1945.\n\nLINDNERS PELSVARU.\nINDUSTRI, AB C J\n\nPnr 114 34\n\nStockholm, Birger Jarls g 18. Tel\n08-67 0 2 7 5. Bankgiro 476-8107.\nPostgiro 2495-0. Tga Ilindner\nVerksamhet: Tillverkar o säljer\npälsvaror\nAntal anställda: 9\nAktiekapital: 60 000\nVerkst dir: Curt Lindner\nEtableringsår: 1882.\n\nhemi plast ab\n\nPnr 59100\n\nMotala, Drakv 6. Tel 0141-520 80.\nPostgiro 48641. Tga Hemiab\nVerksamhet: Tillverkar\nbabyartiklar o driver grossiströrelse\nVerkst dir: A H Hemmingsson\nEtableringsår: 1947.\n\nHjort, dir Thomas Svantesson, dir\nArne Eckerwall\nEtableringsår: 1921.\n\nhempel’s marine\n\nPAINTS, AB\n\nPnr 402 32\n\nGöteborg 7, Box 7075. O\nSänk-verksg 2. Tel 031-42 02 70. Tga\nHempaturi. Telex 2363\nVerksamhet: Säljer fartygs- o\nindustrifärger\nAktiekapital: 305 000\nVerkst dir: Lennart Davidsson\nEtableringsår: 1939.\n\nhendeberg ab,\ningeniörsfirman j s\n\nPnr 77101\n\nLudvika 1, Box 120. Valhallav 13.\nTel 0240-138 90\n\nVerksamhet: Hushållsmaskiner,\nradio o TV. Utför elinstallationer\nAntal anställda: 30\nÅrsomsättning: 3 000 000\nAktiekapital: 190 000\nVerkst dir: Harry Funke\nEtableringsår: 1928.\n\nGOL\n\nÅrsomsättning: 300 000\nAktiekapital: 60000\nVerkst dir: Hans Gustafsson\nEtableringsår: 1931.\n\nGNOSJO ARMATURFABRIK,\nAB\n\nPnr 330 30\n\nGnosjö. Tel 0370-911 14.\nPostgiro 173823-6\n\nVerksamhet: Tillverkar\nutluftnings-ventiler för\nvärmeledningsradiatorer samt utför automatsvarvning\nÄgare o chef: Fabr Bror Hyltén\nEtableringsår: 1932.\n\nGNOSJO BLECK. &amp;\nP LÄTS LAGERI, AB\n\nPnr 330 30\n\nGnosjö. Tel 0370-910 40. Postgiro\n143818\n\nVerksamhet: Tillverkar\nplåtslageriarbeten, plåtpressningar,\nsvetsning, ugnslackering\nFirmatecknare: Bertrand Johansson\nEtableringsår: 1905.\n\nGNOSJO GELBGJUTERI\nRJACOBSON\n\nPnr 330 30\n\nGnosjö. Tel 0370-910 14. Bankgiro\n983-0746. Postgiro 72104-3\nVerksamhet Tillverkar båtbeslag.\nLegoarbeten\n\nFirmatecknare: R Jacobson.\n\nGNOSJO JÄRNINDUSTRI\nBRÖDERNA MOBERG &amp; CO\n\nPnr 330 30\n\nGnosjö. Tel 0370-91209\nVerksamhet: Tillverkar fasta\nskruvmejslar, prylar, ritspetsar, pressade\nmassartiklar\n\nÄgare o chefer: Georg Moberg o\nKarl Moberg.\n\nGNOSJO KONSTSMIDE AB\n\nPnr 33030\n\nGnosjö. Tel 0370-914 00.\nPostgiro 265361-6\n\nVerksamhet: Tillverkar elektr\nbelysningsarmatur\nAktiekapital: 90 000\nVerkst dir: Lennart Johansson\nEtableringsår: 1942.\n\nGNOSJO LÄDER &amp; PLAST.\nVARUFABRIK\n\nPnr 330 30\n\nGnosjö, Hallanäsv 12. Tel\n0370-91215. Postgiro 411351-0\nVerksamhet: Tillverkar\nsmåartik-lar i läder o plast, plånböcker,\nbörsar samt reklamartiklar\nChef: Holger Larsson\nEtableringsår: 1958.\n\nRYBERG, KARL ERIK\n\nPnr 431 36\n\nMölndal, Rådavl6. Tel 031-27 32 68,\n27 34 78 .Bankgiro 50-0341 .Postgiro\n244111-1. Tga Ryberos\nVerksamhet: Kemikalier o råvaror\ni parti\n\nÄgare o chef: Karl Erik Ryberg\nEtableringsår 1950.\n\nHELINOS, AB\n\nPnr 440 60\n\nSkärhamn, Box 46. Tel 0304-7 0 2 24.\nBankgiro 43-7122. Postgiro 475370.\nTga Helinos\n\nVerksamhet: Tillverkar autoklaver,\nnylonfolie, plastartiklar för\nsjukvård, injektionspistoler,\nsteriliser-behållare, injektionskanyler o\nelek-tromedicinska apparater\nAntal anställda: 21\nÅrsomsättning: 2500 000\nAktiekapital: 10 000\nVerkst dir: Civiling Per Engström\nEtableringsår: 1955.\n\nHELIOS KEMISK-TEKNISKA\nFABRIKER, AB\n\nPnr 12611 Sthlm 32\n\nHägersten, Tellusborgsv 100. Fack,\n\nSthlm 32. Tel 08-19 03 80. Postgiro\n\n1470. Telex 1490. Tga Helioskemi\n\nVerksamhet: Tillverkar o säljer\n\ntvätt-, disk- o rengöringsmedel för\n\nhushåll o industrier\n\nAntal anställda: 381\n\nÅrsomsättning: 183000000\n\nAktiekapital: 1000 000\n\nVerkst dir: E A A Wallëus\n\nEtableringsår: 1925\n\nÄges av Kooperativa Förbundet,\n\nStockholm.\n\nHELIX INGENJÖRSFIRMA\n\nPnr 400 31\n\nGöteborg 25, Doktor Fries Torg 8.\nBox 25070. Tel 031-82 10 00.\nBankgiro 65-3999. Postgiro 49999\nVerksamhet: Försäljning av\nelektronikapparater o instrument\nVarunamn: Helix\nÄgare o chef: Kaj Hansson\nEtableringsår: 1960.\n\nHELLBERGS MEK VERKSTAD\nAB\n\nPnr 42011\n\nHisings Kärra. Tel 031-67 03 65\nVerksamhet: Tillverkar skrotsaxar\no skrotpressar\nVerkst dir: B Hellberg\nEtableringsår: 1932\nOmbildat till aktiebolag 1959.\n\nHELLBERG &amp; OLSSON, AB\n\nPnr 212 29\n\nMalmö, Danska v 57. Tel\n040-94 65 10. Bankgiro 875-5241.\nPostgiro 247352. Tga Hello. Telex 32429\nVerksamhet: Säljer förpackningar\nAntal anställda: 35\nÅrsomsättning: 17 000 000\nAktiekapital: 200 000\nVerkst dir: Birger Hellberg\nEtableringsår: 1952.\n\nEXTRACO AB\n\nPnr 100 61\n\nStockholm 11, Box 11007. Tel\n08-44 90 40. Bankgiro 733-4329.\nPostgiro 1185-8. Tga Extracoab.\nTelex 17996 EXTRACO S\nFabriker:\n\nNykvarnsverken, Nykvarn. Tel\n0755-402 20. Tillverkar matnyttigt\n\nfett, raffinerade fetter, fettsyror o\nfodervaror\n\nStidsvigsverken, Stidsvig. Tel\n0435-22200. Tillverkar matgelatin,\nlim o fodervaror\nAktiekapital: 12 000 000\nVerkst dir: Hans-Ola Larsson\nEtableringsår: 1889.\n\nEXPLOATOR, AB\n\nPnr 800 06\n\nGävle 6, Box 6070. Akarg 43. Tel\n026-18 82 30. Bankgiro 237-2985.\nPostgiro 543695-1\n\nVerksamhet; Projektering,\ntillverkning o uppförande av villor, radhus\no hallbyggnader\n\nAvdelningskontor för\nbyggnadsavdelning: 730 73 Ransta. Tel\n0224-203 13\n\nTrähusfabrik: 730 73 Ransta,\nRan-staby. Tel 0224-200 86\nVarunamn: ABX-Hus\nAntal anställda: 67\nÅrsomsättning: 9 000 000\nAktiekapital: 50 000\nVerkst din Erie Berglund\nInköpschef byggnadsavdelning: Ing\nGunnar Lindberg\nEtableringsån 1965.\n\nPER\n\ngiro 42-3600. Postgiro 71661. Tga\nGunnar\n\nVerksamhet: Export av trävaror\nÅrsomsättning: 2 200 000\nAktiekapital: 75000\nDisp: G Bengtsson\nEtableringsår: 1923.\n\nSIBELL, AB\n\nPnr 400 13\n\nGöteborg 36, Partihallarna, Box\n36040. Tel 031-80 09 25.\nBankgiro 852-6261. Postgiro 423888-7\n\n[-BLOMSTERHANDELSARTIKLAR-]\n\n{+BLOMSTERHANDELS-\nARTIKLAR+} I PARTI\n\nAntal anställda: 7\nÅrsomsättning: 3 000 000\nAktiekapital: 50 000\nVerkst dir: Olof Larsson\nEtableringsår 1951.",
    "structured": {
        "1": {
            "company_name": "COLLY COMPANY AB",
            "pnr": "181 07",
            "address": "Lidingö 7, Box 724. Bodalsv 2 A.",
            "phone_number": "08-765 25 55",
            "bank_details": {
                "bankgiro": "74-6511",
                "postgiro": "554141-2"
            },
            "activity": "Säljer industriförnödenheter. Representerar som generalagent företag i Tyskland, England och USA",
            "employees": 20,
            "capital": 100000,
            "key_personnel": [
                {
                    "name": "Stig Hoff-ner",
                    "position": "ordf"
                },
                {
                    "name": "Fred Lindgren",
                    "position": "ing"
                },
                {
                    "name": "Ingrid Lindgren",
                    "position": "fru"
                },
                {
                    "name": "Ingvar Fagerberg",
                    "position": "Teknisk chef"
                },
                {
                    "name": "Stig Hoffner",
                    "position": "Ekonomichef"
                },
                {
                    "name": "Owe Bergius",
                    "position": "Försäljn-chef"
                }
            ],
            "establishment_year": 1957
        },
        "2": {
            "company_name": "LINDMARK & CO AB, H",
            "pnr": "11129",
            "address": "Stockholm, Järntorget 83",
            "phone_number": "08-1111 43, 20 95 43",
            "bank_details": {
                "bankgiro": "478-2595",
                "postgiro": "250464-5"
            },
            "activity": "Auktoriserade skeppsklarerare",
            "capital": 25000,
            "key_personnel": [
                {
                    "name": "Staffan Broms",
                    "position": "Verkst dir"
                }
            ],
            "establishment_year": 1945
        },
        "3": {
            "company_name": "LINDNERS PELSVARU. INDUSTRI, AB C J",
            "pnr": "114 34",
            "address": "Stockholm, Birger Jarls g 18",
            "phone_number": "08-67 0 2 7 5",
            "bank_details": {
                "bankgiro": "476-8107",
                "postgiro": "2495-0"
            },
            "activity": "Tillverkar och säljer pälsvaror",
            "employees": 9,
            "capital": 60000,
            "key_personnel": [
                {
                    "name": "Curt Lindner",
                    "position": "Verkst dir"
                }
            ],
            "establishment_year": 1882
        },
        "4": {
            "company_name": "hemi plast ab",
            "pnr": "59100",
            "address": "Motala, Drakv 6",
            "phone_number": "0141-520 80",
            "postgiro": "48641",
            "activity": "Tillverkar babyartiklar och driver grossiströrelse",
            "employees": 30,
            "capital": 190000,
            "key_personnel": [
                {
                    "name": "A H Hemmingsson",
                    "position": "Verkst dir"
                },
                {
                    "name": "Harry Funke",
                    "position": "Verkst dir"
                }
            ],
            "establishment_year": 1947
        },
        "5": {
            "company_name": "hempel’s marine PAINTS, AB",
            "pnr": "402 32",
            "address": "Göteborg 7, Box 7075. O Sänk-verksg 2",
            "phone_number": "031-42 02 70",
            "bank_details": {
                "bankgiro": "983-0746",
                "postgiro": "72104-3"
            },
            "activity": "Säljer fartygs- och industrifärger",
            "capital": 305000,
            "key_personnel": [
                {
                    "name": "Lennart Davidsson",
                    "position": "Verkst dir"
                }
            ],
            "establishment_year": 1939
        },
        "6": {
            "company_name": "hendeberg ab, ingenjörsfirman j s",
            "pnr": "77101",
            "address": "Ludvika 1, Box 120. Valhallav 13",
            "phone_number": "0240-138 90",
            "activity": "Hushållsmaskiner, radio och TV. Utför elinstallationer",
            "employees": 30,
            "annual_turnover": 3000000,
            "capital": 190000,
            "key_personnel": [
                {
                    "name": "Harry Funke",
                    "position": "Verkst dir"
                }
            ],
            "establishment_year": 1928
        }
    }
}