{
    "original": "EKSJÖ SÄG, AB\n\nPnr 643 00\n\nVingåker, Postl 8135. Tel\n0151-200 33. Bankgiro 83-0929. Postgiro\n448986-0\n\nVerksamhet: Tillverkar sågade o\nhyvlade trävaror. Byggnadsmateriel\nAntal anställda: 14\nÅrsomsättning: 2 000 000\nAktiekapital: 100 000\nVerkst dir: Bror Karlsson\nEtableringsån 1898.\n\nCARLSTROM &amp; SON, AB E J\n\nPnr 381 00\n\nKalmar, Sandåsg 1. Tel 0480-106 14,\n10300. Postgiro 25127-2\nVerksamhet: Bilförsäljning o\n-reparationer\n\nAktiekapital: 160 000\nVerkst dir: E Andersson\nEtableringsår: 1882.\n\nHAGLUND &amp; SÖNER AB\n\nPnr 52101\n\nFalköping 1, Parkg 25. Box 44. Tel\n0515-134 00. Bankgiro 213-7446.\nPostgiro 10478-6. Tga Haglunds\nVerksamhet: Tillverkar mek\nrullgardinskäppar, rullgardiner o\nmöbler. Mjuka mattor i parti\nFörsäljningskontor:\nStockholm. Tel 08-2114 61\nVarunamn: Eclipse, Garduenne\nAntal anställda: 200\nÅrsomsättning: 19 00 000\nAktiekapital: 1 242 000\nVerkst dir: Göran Haglund\nEtableringsår: 1885.\n\nHAGLUNDS VERKSTAD, AB\nG &amp; E\n\nPnr 52010\n\nGällstad. Tel 0321-700 31.\nBankgiro 602-5266. Postgiro 270067-2\nVerksamhet: Tillverkar kyldiskar,\nfrysdiskar, kyl- o frysskåp,\nkonditoriskåp o montrar samt rostfria\ninredningar\nAntal anställda: 12\nAktiekapital: 50 000\nChefer: Gunnar Haglund, Erik\nHaglund\n\nEtableringsår: 1913.\n\nHAGLUND FÄRGINDUSTRI,\nAB N\n\nPnr 402 24\n\nGöteborg 5,Berzeliig 25.Box 5215.\nTel 031-810595. Bankgiro\n509-6318. Postgiro 41605-7. Tga\nVarnish\n\nVerksamhet: Tillverkar o säljer till\nmåleriyrket hörande artiklar. Säljer\nbillacker, målarutensilier m m\nFabrik: Partilie, Kung Göstas v 1\nAktiekapital: 300 000\nVerkst dir: Töre Aspenberg\nEtableringsår: 1918.\n\nHAGLOFS MEKANISKA\nVERKST ADS-AB\n\nPnr 792 00\n\nMora. Selbecksv 1. Tel 0250-109 09.\nBankgiro 46-9151. Postgiro 146101\nVerksamhet: Tillverkar\nstämpelyxor, färgmärkningshammare,\ntillväxtborrar o redskap för\nsmåtrak-torer\n\nAktiekapital: 40 000\nVerkst dir: Anders Haglöf\nEtableringsår: 1950.\n\nHAGLOFS RYGGSÄCKS.\nFABRIK AB\n\nPnr 781 00\n\nBorlänge, Tylla. Tel 0243-60016.\nBankgiro 794-5801. Postgiro\n26 324-4\n\nVerksamhet: Tillverkar ryggsäckar\no bärmesar\nAntal anställda: 18\nÅrsomsättning: 1000 000\nAktiekapital: 60000\nVeikst dir: Rolf Haglöf\nEtableringsår 1914.\n\nBYGGNADSSNICKERIER\nFALUN AB\n\nPnr 79100\n\nFalun, Centralplan. Tel 023-185 60.\nBankgiro 46-4220. Postgiro 293 19\nVerksamhet: Säljer\nbyggnads-Verksamhet: Säljer\nmonteringsfärdiga trähus o byggnadssnickerier\nÅrsomsättning: 12 000 000\nAktiekapital: 25 000\nVerkst dir: Ing Rolf Rågsveden\nEtableringsår 1953.\n\nGRANLUND &amp; CO, AB H\n\nPnr 63105\n\nEskilstuna 1, Kungsg 90. Box 377.\n016-14 71 00. Bankgiro 369-3058.\nPostgiro 290065-2. Tga\nGranlundverktyg. Telex 40961\nVerksamhet: Tillverkar\nprecisionsverktyg o maskiner\nAktiekapital: 75 0 000\nVerkst dir: Börje Gyllhamn\nEtableringsår: 1945.\n\nLAGAN PRESS AB\n\nPnr 34014\n\nLagan, Industrig 6, Tel 0372-30375.\nBankgiro 146-0435. Postgiro\n646820-1\n\nVerksamhet: Tillverkar hydrauliska\ndragpress ar\nAntal anställda: 25\nÅrsomsättning: 3 300 000\n.Aktiekapital: 100 000\nVerkst dir: Bertil Åberg\nPlatschef: Ing Nils Dalros\nEtableringsår: 1962\nOmbildat till aktiebolag 1964.\n\nLAGBERGS REVISIONSBYRÅ\nAB, KARL Y\n\nPnr 50103\n\nBorås 1, Box 123. Alvestag 31.\nTel 033-116129, 1150 69.\nPostgiro 170592-0\n\nVerksamhet: Revisionsbyrå\nAntal anställda: 23\nÅrsomsättning: 1200 000\nAktiekapital: 10 000\nAukt revisor: Karl Y Lagberg\nEtableringsår: 1940.\n\nLAGERBLADS BOKTRYCKERI,\nAB RAGNAR\n\nPnr 292 00\n\nKarlshamn, Boktryckareg 1. Box\n77. Tel 0454-150 00. Bankgiro\n65-6570. Postgiro 30276\nVerksamhet: Utför tryckning av\nbokarbeten, tidskrifter, kataloger mm\nAntal anställda: 40\nÅrsomsättning: 2 800 000\nAktiekapital: 165 000\nVerkst dir: Disp Erie Ericsson\nEtableringsår: 1864.\n\ndalu bolagen ab\n\nPnr 60103\n\nNorrköping 1, Saltängsg 13. Box\n196. Tel 011-1879 30, 187931.\nBankgiro 826-1638. Postgiro\n678038-1\n\nVerksamhet: Säljer swimmingpooler\nVarunamn: Poolman\nAktiekapital: 10 000\nVerkst dir: Sture Dahlstedt\nEtableringsår: 1965.\n\nTERRATEST AB\n\nPnr 16111\n\nBromma 11, Box 11068. Tel\n08-8 0 27 20. Telex 17106 TERTEST S.\nTga Prospecting. Stockholm\nVerksamhet: Utför vattenborrningar\nsamt injektionstätningsarbeten\nAntal anställda: 220\nAktiekapital: 4 000 000\nVerkst dir: Harry Nilsson\nEtableringsår: 1923.\n\nTERRING INGENIORSBYRA\nAB, G\n\nPnr 127 04\n\nSkärholmen 4, Box 4050. Tel\n08-71007 50. Postgiro 470041\nVerksamhet: Värme-, ventilations-,\nkyl- o sanitetsteknik\nAntal anställda: 18\nAktiekapital: 50 000\nVerkst dir Gösta Terring\nEtableringsår: 1952.\n\nekonomiisolering, ab\n\nPnr 56101\n\nHuskvarna 1, Box 131. Hakarpsv\n123. Tel 036-13 2 8 40. Bankgiro\n837-6063. Postgiro 596070-3\nVerksamhet: Tillverkar isolerade\nväggelement till byggnadsindustrin.\nIsoleringsentreprenader inom\nVVS-branschen. Isolerar kyl- o frysrum.\nMonterar plåt- o isoleringsmaterial\npå prefabricerade stommar av stål,\nträ eller betong\n\nAvdelningskontor: Växjö. Norre\nkvarn Tegnaby, 36044 Ingelstad.\nTel 0470-64140\nAntal anställda: 30\nÅrsomsättning: 3 000 000\nAktiekapital: 25 000\nVerkst din Ing Lars Lundqvist\nEtableringsår. 1962.\n\nekonomisk fastighets.\nplanering ab ekf\n\nPnr 11145\n\nStockholm, Birger Jarlsg 43. Tel\n08-23 24 30\n\nVerksamhet: Konsulterande i\nbyggnadsadministration\nAktiekapital: 30 000\nVerkst dir: Ake Magnusson\nEtableringsår: 1964.\n\nALMKVIST, RAGNAR\n\nPnr 644 00\n\nTorshälla, Eskilstunav 19. Tel\n016-555 66. Bankgiro 623-5931\nVerksamhet: Tillverkar\npressverktyg o borrjiggar\n\nÄgare o chef: Tryggve Almkvist\nEtableringsår: 1948.",
    "structured": {
        "1": {
            "company_name": "EKSJÖ SÄG, AB",
            "pnr": "643 00",
            "address": "Vingåker, Postl 8135",
            "phone_number": "0151-200 33",
            "bank_details": {
                "bankgiro": "83-0929",
                "postgiro": "448986-0"
            },
            "activity": "Tillverkar sågade o hyvlade trävaror. Byggnadsmateriel",
            "employees": 14,
            "annual_turnover": 2000000,
            "capital": 100000,
            "key_personnel": [
                {
                    "name": "Bror Karlsson",
                    "position": "Verkst dir"
                }
            ],
            "establishment_year": 1898
        },
        "2": {
            "company_name": "CARLSTROM & SON, AB E J",
            "pnr": "381 00",
            "address": "Kalmar, Sandåsg 1",
            "phone_number": "0480-106 14",
            "bank_details": {
                "postgiro": "25127-2"
            },
            "activity": "Bilförsäljning o -reparationer",
            "capital": 160000,
            "key_personnel": [
                {
                    "name": "E Andersson",
                    "position": "Verkst dir"
                }
            ],
            "establishment_year": 1882
        },
        "3": {
            "company_name": "HAGLUND & SÖNER AB",
            "pnr": "52101",
            "address": "Falköping 1, Parkg 25, Box 44",
            "phone_number": "0515-134 00",
            "bank_details": {
                "bankgiro": "213-7446",
                "postgiro": "10478-6"
            },
            "activity": "Tillverkar mek rullgardinskäppar, rullgardiner o möbler. Mjuka mattor i parti",
            "employees": 200,
            "annual_turnover": 1900000,
            "capital": 1242000,
            "key_personnel": [
                {
                    "name": "Göran Haglund",
                    "position": "Verkst dir"
                }
            ],
            "establishment_year": 1885
        },
        "4": {
            "company_name": "HAGLUNDS VERKSTAD, AB G & E",
            "pnr": "52010",
            "address": "Gällstad",
            "phone_number": "0321-700 31",
            "bank_details": {
                "bankgiro": "602-5266",
                "postgiro": "270067-2"
            },
            "activity": "Tillverkar kyldiskar, frysdiskar, kyl- o frysskåp, konditoriskåp o montrar samt rostfria inredningar",
            "employees": 12,
            "capital": 50000,
            "key_personnel": [
                {
                    "name": "Gunnar Haglund",
                    "position": "Chefer"
                },
                {
                    "name": "Erik Haglund",
                    "position": "Chefer"
                }
            ],
            "establishment_year": 1913
        },
        "5": {
            "company_name": "HAGLUND FÄRGINDUSTRI, AB N",
            "pnr": "402 24",
            "address": "Göteborg 5, Berzeliig 25, Box 5215",
            "phone_number": "031-810595",
            "bank_details": {
                "bankgiro": "509-6318",
                "postgiro": "41605-7"
            },
            "activity": "Tillverkar o säljer till måleriyrket hörande artiklar. Säljer billacker, målarutensilier m m",
            "capital": 300000,
            "key_personnel": [
                {
                    "name": "Töre Aspenberg",
                    "position": "Verkst dir"
                }
            ],
            "establishment_year": 1918
        },
        "6": {
            "company_name": "HAGLOFS MEKANISKA VERKST ADS-AB",
            "pnr": "792 00",
            "address": "Mora, Selbecksv 1",
            "phone_number": "0250-109 09",
            "bank_details": {
                "bankgiro": "46-9151",
                "postgiro": "146101"
            },
            "activity": "Tillverkar stämpelyxor, färgmärkningshammare, tillväxtborrar o redskap för småtrak-torer",
            "capital": 40000,
            "key_personnel": [
                {
                    "name": "Anders Haglöf",
                    "position": "Verkst dir"
                }
            ],
            "establishment_year": 1950
        },
        "7": {
            "company_name": "HAGLOFS RYGGSÄCKS. FABRIK AB",
            "pnr": "781 00",
            "address": "Borlänge, Tylla",
            "phone_number": "0243-60016",
            "bank_details": {
                "bankgiro": "794-5801",
                "postgiro": "26324-4"
            },
            "activity": "Tillverkar ryggsäckar o bärmesar",
            "employees": 18,
            "annual_turnover": 1000000,
            "capital": 60000,
            "key_personnel": [
                {
                    "name": "Rolf Haglöf",
                    "position": "Veikst dir"
                }
            ],
            "establishment_year": 1914
        },
        "8": {
            "company_name": "BYGGNADSSNICKERIER FALUN AB",
            "pnr": "79100",
            "address": "Falun, Centralplan",
            "phone_number": "023-185 60",
            "bank_details": {
                "bankgiro": "46-4220",
                "postgiro": "293 19"
            },
            "activity": "Säljer monteringsfärdiga trähus o byggnadssnickerier",
            "annual_turnover": 12000000,
            "capital": 25000,
            "key_personnel": [
                {
                    "name": "Ing Rolf Rågsveden",
                    "position": "Verkst dir"
                }
            ],
            "establishment_year": 1953
        },
        "9": {
            "company_name": "GRANLUND & CO, AB H",
            "pnr": "63105",
            "address": "Eskilstuna 1, Kungsg 90, Box 377",
            "phone_number": "016-14 71 00",
            "bank_details": {
                "bankgiro": "369-3058",
                "postgiro": "290065-2"
            },
            "activity": "Tillverkar precisionsverktyg o maskiner",
            "capital": 750000,
            "key_personnel": [
                {
                    "name": "Börje Gyllhamn",
                    "position": "Verkst dir"
                }
            ],
            "establishment_year": 1945
        },
        "10": {
            "company_name": "LAGAN PRESS AB",
            "pnr": "34014",
            "address": "Lagan, Industrig 6",
            "phone_number": "0372-30375",
            "bank_details": {
                "bankgiro": "146-0435",
                "postgiro": "646820-1"
            },
            "activity": "Tillverkar hydrauliska dragpress ar",
            "employees": 25,
            "annual_turnover": 3300000,
            "capital": 100000,
            "key_personnel": [
                {
                    "name": "Bertil Åberg",
                    "position": "Verkst dir"
                },
                {
                    "name": "Ing Nils Dalros",
                    "position": "Platschef"
                }
            ],
            "establishment_year": 1962
        },
        "11": {
            "company_name": "LAGBERGS REVISIONSBYRÅ AB, KARL Y",
            "pnr": "50103",
            "address": "Borås 1, Box 123, Alvestag 31",
            "phone_number": "033-116129, 1150 69",
            "bank_details": {
                "postgiro": "170592-0"
            },
            "activity": "Revisionsbyrå",
            "employees": 23,
            "annual_turnover": 1200000,
            "capital": 10000,
            "key_personnel": [
                {
                    "name": "Karl Y Lagberg",
                    "position": "Aukt revisor"
                }
            ],
            "establishment_year": 1940
        },
        "12": {
            "company_name": "LAGERBLADS BOKTRYCKERI, AB RAGNAR",
            "pnr": "292 00",
            "address": "Karlshamn, Boktryckareg 1, Box 77",
            "phone_number": "0454-150 00",
            "bank_details": {
                "bankgiro": "65-6570",
                "postgiro": "30276"
            },
            "activity": "Utför tryckning av bokarbeten, tidskrifter, kataloger mm",
            "employees": 40,
            "annual_turnover": 2800000,
            "capital": 165000,
            "key_personnel": [
                {
                    "name": "Disp Erie Ericsson",
                    "position": "Verkst dir"
                }
            ],
            "establishment_year": 1864
        },
        "13": {
            "company_name": "dalu bolagen ab",
            "pnr": "60103",
            "address": "Norrköping 1, Saltängsg 13, Box 196",
            "phone_number": "011-1879 30, 187931",
            "bank_details": {
                "bankgiro": "826-1638",
                "postgiro": "678038-1"
            },
            "activity": "Säljer swimmingpooler",
            "capital": 10000,
            "key_personnel": [
                {
                    "name": "Sture Dahlstedt",
                    "position": "Verkst dir"
                }
            ],
            "establishment_year": 1965
        },
        "14": {
            "company_name": "TERRATEST AB",
            "pnr": "16111",
            "address": "Bromma 11, Box 11068",
            "phone_number": "08-8 0 27 20",
            "telex": "17106 TERTEST S",
            "activity": "Utför vattenborrningar samt injektionstätningsarbeten",
            "employees": 220,
            "capital": 4000000,
            "key_personnel": [
                {
                    "name": "Harry Nilsson",
                    "position": "Verkst dir"
                }
            ],
            "establishment_year": 1923
        },
        "15": {
            "company_name": "TERRING INGENIORSBYRA AB, G",
            "pnr": "127 04",
            "address": "Skärholmen 4, Box 4050",
            "phone_number": "08-71007 50",
            "postgiro": "470041",
            "activity": "Värme-, ventilations-, kyl- o sanitetsteknik",
            "employees": 18,
            "capital": 50000,
            "key_personnel": [
                {
                    "name": "Gösta Terring",
                    "position": "Verkst dir"
                }
            ],
            "establishment_year": 1952
        },
        "16": {
            "company_name": "ekonomiisolering, ab",
            "pnr": "56101",
            "address": "Huskvarna 1, Box 131, Hakarpsv 123",
            "phone_number": "036-13 2 8 40",
            "bank_details": {
                "bankgiro": "837-6063",
                "postgiro": "596070-3"
            },
            "activity": "Tillverkar isolerade väggelement till byggnadsindustrin. Isoleringsentreprenader inom VVS-branschen. Isolerar kyl- o frysrum. Monterar plåt- o isoleringsmaterial på prefabricerade stommar av stål, trä eller betong",
            "employees": 30,
            "annual_turnover": 3000000,
            "capital": 25000,
            "key_personnel": [
                {
                    "name": "Ing Lars Lundqvist",
                    "position": "Verkst din"
                }
            ],
            "establishment_year": 1962
        },
        "17": {
            "company_name": "ekonomisk fastighets. planering ab ekf",
            "pnr": "11145",
            "address": "Stockholm, Birger Jarlsg 43",
            "phone_number": "08-23 24 30",
            "activity": "Konsulterande i byggnadsadministration",
            "capital": 30000,
            "key_personnel": [
                {
                    "name": "Ake Magnusson",
                    "position": "Verkst dir"
                }
            ],
            "establishment_year": 1964
        },
        "18": {
            "company_name": "ALMKVIST, RAGNAR",
            "pnr": "644 00",
            "address": "Torshälla, Eskilstunav 19",
            "phone_number": "016-555 66",
            "bank_details": {
                "bankgiro": "623-5931"
            },
            "activity": "Tillverkar pressverktyg o borrjiggar",
            "key_personnel": [
                {
                    "name": "Tryggve Almkvist",
                    "position": "Ägare o chef"
                }
            ],
            "establishment_year": 1948
        }
    }
}