{
    "original": "SALUBRIN- DRUVAN\n\nPnr 241 00\n\nEslöv, Box 51. Järnvägsg 3. Tel\n0413-16040. Bankgiro 651-5787.\nPostgiro 3705-4. Tga Ättikfabriken\nVerksamhet: Tillverkar kem-tekn\nartiklar, spritättika, senap, soya\nAntal anstäUda: 42\nÅrsomsättning: 6 500 000\nAktiekapital: 100 000\nVerkst dir: Gösta Wingertz\nEtableringsår 1874.\n\nSUNDSTRAND HYDRAULIC AB\n\nPnr 14123\n\nHuddinge 1, Fabrik: Förråds v 10.\nBox 1132. Tel 08-7740100.\nBankgiro 160-6979. Postgiro 5399-1.\nTga Sundpump. Telex 10281\nVerksamhet: Tillverkar o säljer\noljebrännarpumpar o\nvarmvattenpumpar\n\nVarunamn: Sundstrand\nAntal anställda: 450\nÅrsomsättning: 55 000 000\nAktiekapital: 3 000 000\nStyrelse: Greve Carl Johan\nBernadotte (ordf), dir Martin Björklind,\n\nadv Ola Wettergren, mr Carl Sadler,\nmr Bruce Olson, dir Gunnar\nBergström\n\nVerkst dir: Gunnar Bergström\nEkonomichef: Martin Hjelmstedt\nFörsäljn-chef Skandinavien:\nRaoul Lejeborg\nEtableringsår: 1954.\n\nT L V, VERKSTADS AB\n\nPnr 598 00\n\nVimmerby, Sevedeg 1-3. Box 9.\nTel 0492-107 02, 110 60, 12210.\nBankgiro 857-5292. Postgiro\n27848-1. Tga Tiv\nVerksamhet: Tillverkar\nverkstads-o reparationssvarvar samt\nspecialmaskiner\nVarunamn: TLV\nAntal anställda: 40\nÅrsomsättning: 2 500000\nAktiekapital: 175 000\nStyrelse: Ing Sven Nyman (ordf),\ning Jean Bergvall, dir Lars Termén\nVerkst dir: Lars Termén\nProd-chef: Ing Jean Bergvall\nKonstr-chef: Ing Sven Nyman\nFörsäljn-chef: Lars Termén\nEtableringsår: 1912.\n\nTOBAKSHANDLARNAS RIKS.\nFÖRBUNDS ENGROS AB\n(TREAB)\n\nPnr 126 53\n\nHägersten, Instrumentv 10. Tel\n08-81 0160. Bankgiro 168-8407.\nPostgiro 2277-2. Tga Treab\nVerksamhet: Partiförsäljning till\ntobakshandeln\nAntal anställda: 55\nÅrsomsättning: 32 000 000\nAktiekapital: 900 000\nVerkst dir. Lars Akrans\nEtableringsår: 1916.\n\nSKURUPSSPARBANK\n\nPnr 274 00\n\nSkurup, Torget 10. Tel\n0411-400 35. Bankgiro 981-2959.\nPostgiro 292626-9\n\nVerksamhet: Sparbanksrörelse\nAntal anställda: 11\nÅrsomsättning: 85 000 000\nVerkst dir: Ake Bokander\nEtableringsår: 1881.\n\nTIERPS TRYCKERI AB\n\nPnr 815 01\n\nTierp 1, Greveg 6. Box 23. Tel\n0293-114 35. Bankgiro 23-6212.\nPostgiro 8842\n\nVerksamhet: Trycksaker i offset o\nboktryck. Specialitet: reklamtryck,\nblanketter, kataloger i offsettryck\nAntal anställda: 17\nÅrsomsättning: 1 200 000\nAktiekapital: 78 600\nStyrelse: Dir Torsten Ekström\n(ordf), dir Göran Claesson, dir C W\nLundhammar, disp Georg Wahlström\nVerkst dir: Disp Georg Wahlström\nEtableringsår: 1887\nOmbildat till aktiebolag 1920.\n\nTHIGERS ELEKTRISKA KON.\nSTRUKTIONSBYRÄ AB\n\nPnr 89101\n\nÖrnsköldsvik 1, Box 220.\nLasa-rettsg 12. Tel 0660-104 55.\nBankgiro 233-4902. Postgiro 487713-0\nVerksamhet: Konsulterande\nverksamhet inom elektrotekniska facket\nFilial: Umeå 5, Riksv 2. Tel\n090-124091, 124092\nSundsvall, Storg 26. Tel\n060-1280 80\n\nGävle, Karlav 4. Tel 026-18 01 79\nLuleå, Smedjeg 26. Tel 0920-.\n29020\n\nAntal anställda: 40\nChef: Ing Lewi Thiger\nEtableringsår. 1954.\n\nHANSA, SJÖFÖRSÄKRINGS AB\n\nPnr 103 81\n\nStockholm 7. Box 7036. Arsenalsg\n8 C. Tel 08-14 00 60. Bankgiro\n726-5325. Postgiro premier 59138-8,\növrigt 104-0. Tga Hansamarine.\nTelex 1581 HANSA S\nVerksamhet: Sjö-, land- o\nlufttransportförsäkring\n\nAktiekapital: 5000 000\nStyrelse: Dir O Karleby (ordf),\nskeppsredare C Salén (v ordf), dir T\nAndersson, bankdir E Brändström,\ndir S Carlborn, dir A Jonson, dir D\nSundén-Cullberg, adv C Swartling,\ndir A Thorstensson\nVerkst dir: A Thorstensson\nV verkst dir: R Hornborg\nEtableringsår: 1918.\n\nGAILIS MEK VERKSTAD, AB\n\nPnr 170 23\n\nBarkarby, Poppelv 23. Box 30. Tel\n08-36 52 62. Postgiro 443487\nVerksamhet Eloxerade\nlättmetall-möbler, elektr artiklar, nipplar mm\nAktiekapital: 10000\nVerkst dir: Civiling F Gailis\nEtableringsår: 1953.\n\nBYGGKONSULT VÄSTERÅS AB\n\nPnr 722 15\n\nVästerås, Vasag 32. Tel\n021-1102 40. Bankgiro 808-6118.\nPostgiro 116238-7\n\nVerksamhet Industriprojektering,\nbyggnadskonstruktioner m m\nAntal anställda: 21\nÅrsomsättning: 1400000\nAktiekapital: 10 000\nVerkst dir: Tekn lic Göran Larsson\nEtableringsår: 1956.\n\nBYGG-KONTROLLEN I\nMALMÖ AB\n\nPnr 21121\n\nMalmö, Västerg 20. Tel 040-756 55.\nBankgiro 876-1066. Postgiro\n531868-8\n\nVerksamhet: Byggadministration,\nbyggledning för industribyggen\nAktiekapital: 5 000\nVerkst dir: Ing Günther Schaedel\nEtableringsår 1959.\n\nKOPPVARIATORER AB\n\nPnr 41107\n\nGöteborg, Drottningg 68. Tel\n031-178155. Bankgiro 420-5928.\nPostgiro 622798-7. Tga Koppspeed.\nTelex 20836\n\nVerksamhet: Mekaniska\nvarvtals-variatorer, servosystem,\nhydrauliska o elastiska kopplingar,\nbromsar, kuggväxelmotorer,\nsnäckväxel-motorer, planetväxlar, tappväxlar,\nvinkelväxlar\n\nVarunamn: ,Axo, Electropower, IMT,\nJacoflex, Jolly, Kopp, Merger,\nSie-gerland. Strong, Turbostart\nAntal anställda: 8\nAktiekapital: 75 000\nStyrelse: Adv Otto Setterberg (ordf),\nciviling R Bierkelund, dir B Lind\nJacobsen, dir P Junger, mr Austin\nD Smith\n\nVerkst dir: Civiling R Bjerkelund\nEtableringsår: 1961\n\nModerbolag: Allspeeds Ltd,\nAcc-rington, Lancs, England.\n\nKORALL\n\nPnr 453 00\n\nLysekil, Drottningg 42. Tel\n0523-108 58. Postgiro 31659\nVerksamhet: Tillverkar o säljer\nkemisk-tekniska artiklar\nÅrsomsättning: 80 000\nÄgare: Disp B Molander\nEtableringsår: 1957.\n\nJAC\n\nVerksamhet: Engrosförsäljning av\nsmörjmedel, verktyg, bultvaror o\ndyl\n\nÅrsomsättning: 1500 000\nAktiekapital: 120 000\nVerkst dir: JN Jacobsson\nEtableringsår 1930\nOmbildat till aktiebolag 1953.\n\nJACOBSON AB, OSCAR\n\nPnr 501 07\n\nBorås 1, Box 444. Alingsàsv 9. Tel\n033-12 7150. Bankgiro 531-3556.\nPostgiro 417040-3. Tga Ojac\nVerksamhet: Tillverkar kostymer,\nblazer, överrockar o byxor\nAntal anställda: 400\nÅrsomsättning: 20 000 000\nAktiekapital: 2016 000\nVerkst dir: Anders Jacobson\nEtableringsår 1929.",
    "structured": {
        "1": {
            "company_name": "SALUBRIN- DRUVAN",
            "pnr": "241 00",
            "address": "Eslöv, Box 51, Järnvägsg 3",
            "phone_number": "0413-16040",
            "bank_details": {
                "bankgiro": "651-5787",
                "postgiro": "3705-4"
            },
            "activity": "Tillverkar kem-tekn artiklar, spritättika, senap, soya",
            "employees": 42,
            "annual_turnover": 6500000,
            "capital": 100000,
            "key_personnel": [
                {
                    "name": "Gösta Wingertz",
                    "position": "Verkst dir"
                }
            ],
            "establishment_year": 1874
        },
        "2": {
            "company_name": "SUNDSTRAND HYDRAULIC AB",
            "pnr": "14123",
            "address": "Huddinge 1, Fabrik: Förråds v 10, Box 1132",
            "phone_number": "08-7740100",
            "bank_details": {
                "bankgiro": "160-6979",
                "postgiro": "5399-1"
            },
            "activity": "Tillverkar o säljer oljebrännarpumpar o varmvattenpumpar",
            "employees": 450,
            "annual_turnover": 55000000,
            "capital": 3000000,
            "key_personnel": [
                {
                    "name": "Grev Carl Johan Bernadotte",
                    "position": "Styrelse (ordf)"
                },
                {
                    "name": "Martin Björklind",
                    "position": "Verkst dir"
                }
            ],
            "establishment_year": 1954
        },
        "3": {
            "company_name": "T L V, VERKSTADS AB",
            "pnr": "598 00",
            "address": "Vimmerby, Sevedeg 1-3, Box 9",
            "phone_number": "0492-107 02, 110 60, 12210",
            "bank_details": {
                "bankgiro": "857-5292",
                "postgiro": "27848-1"
            },
            "activity": "Tillverkar verkstads-o reparationssvarvar samt specialmaskiner",
            "employees": 40,
            "annual_turnover": 2500000,
            "capital": 175000,
            "key_personnel": [
                {
                    "name": "Ing Sven Nyman",
                    "position": "Styrelse (ordf)"
                },
                {
                    "name": "Lars Termén",
                    "position": "Verkst dir, Försäljn-chef"
                }
            ],
            "establishment_year": 1912
        },
        "4": {
            "company_name": "TOBAKSHANDLARNAS RIKS. FÖRBUNDS ENGROS AB (TREAB)",
            "pnr": "126 53",
            "address": "Hägersten, Instrumentv 10",
            "phone_number": "08-81 0160",
            "bank_details": {
                "bankgiro": "168-8407",
                "postgiro": "2277-2"
            },
            "activity": "Partiförsäljning till tobakshandeln",
            "employees": 55,
            "annual_turnover": 32000000,
            "capital": 900000,
            "key_personnel": [
                {
                    "name": "Lars Akrans",
                    "position": "Verkst dir"
                }
            ],
            "establishment_year": 1916
        },
        "5": {
            "company_name": "SKURUPSSPARBANK",
            "pnr": "274 00",
            "address": "Skurup, Torget 10",
            "phone_number": "0411-400 35",
            "bank_details": {
                "bankgiro": "981-2959",
                "postgiro": "292626-9"
            },
            "activity": "Sparbanksrörelse",
            "employees": 11,
            "annual_turnover": 85000000,
            "key_personnel": [
                {
                    "name": "Ake Bokander",
                    "position": "Verkst dir"
                }
            ],
            "establishment_year": 1881
        },
        "6": {
            "company_name": "TIERPS TRYCKERI AB",
            "pnr": "815 01",
            "address": "Tierp 1, Greveg 6, Box 23",
            "phone_number": "0293-114 35",
            "bank_details": {
                "bankgiro": "23-6212",
                "postgiro": "8842"
            },
            "activity": "Trycksaker i offset o boktryck, Specialitet: reklamtryck, blanketter, kataloger i offsettryck",
            "employees": 17,
            "annual_turnover": 1200000,
            "capital": 78600,
            "key_personnel": [
                {
                    "name": "Torsten Ekström",
                    "position": "Styrelse (ordf)"
                },
                {
                    "name": "Georg Wahlström",
                    "position": "Verkst dir"
                }
            ],
            "establishment_year": 1887
        }
    }
}