{
    "original": "JÄM\n\nAvdelningskontor: 293 00\nOlofström. Tel 0454-408 90. Förest:\nKamrer Tore Andersson\n29040 Näsum. Tel 045 6-24 1 00.\nFörest: Kamrer Hugo Ankarloo\n290 64 Gränumsby. Tel\n0454-432 36. Förest: Syster Persson\nAntal anställda: 20\nÅrsomsättning: 85 000 000\nStyrelse: Lantbr Uno Mathiasson\n(crdf), bankdir Ake Hallberg\nVerkst dir: Ake Hallberg\nKamrer: Lars Inge Bengtsson\nEtableringsår: 1838.\n\nNORBERGS INDUSTRIBYRÅ\n\nPnr 890 10\n\nB jästa. Tel 0660-350 25, 352 25.\nBankgiro 76-8710. Postgiro 460411.\nTga Nibåteknik\n\nVerksamhet: Tillverkar\ngolvslip-nings- o golvhyvlingsmaskiner\nÄgare o chefer: Eriz Norberg, Knut\nNorberg, Léon Norberg\nEtableringsår: 1950.\n\nNORBERGS MEK VERKSTAD,\nAB\n\nPnr 778 00\n\nNorberg. Tel 0223-217 80. Bankgiro\n23-1607. Postgiro 94110. Tga\nVerkstaden\n\njsns/rv\n\nVerksamhet: Gruv- o\njärnverksmaskiner, spårbundna o mobila\nvagnar, transportanordningar,\npermanent* o elektromagnetiska\nseparatorer, kuggväxelmotorer, tapp- o\nsnäckväxlar\nVarunamn: NMV\nAntal anställda: 65\nÅrsomsättning: 6 000 000\nAktiekapital: 400 000\nStyrelse: Adv Ulf Nohre (ordf),\ndir Georg Hammarqvist, ing Bo\nHammar qvist\n\nVerkst dir: Georg Hammarqvist\nIng: Bo Hammarqvist\nKamrer: Gottfrid Thomsson\nEtableringsår: 1890.\n\nNORBERGS SPAD. &amp; RED.\nSKAPSFABRIKER, AB\n\nPnr 59100\n\nMotala, Vinterg 7. Tel 0141-500 65.\nBankgiro 82-1989. Postgiro 31467\nVerksamhet: Alla slags\nhandred-skap såsom spadar, skyfflar m m\nAntal anstäUda: 39\nAktiekapital: 400000\nVerkst dir: Paul Stenlund\nEtableringsår: 1890.\n\nNORBERG ANNONS AB,\nBALTZAR\n\nPnr 11259\n\nStockholm, Rålambsv 7. Tel\n08-534341, 53 4351. Bankgiro\n72-0832. Postgiro 558199\nVeiksamhet: Annonsbyrå. Marketing,\nförsäljning o reklam\nAntal anstäUda: 12\nÅrsomsättning: 5 500 000\nAktiekapital: 5 000\nStyrelseordf: Dir Baltzar Norberg\nVeikst dir: Baltzar Norberg\nEtableringsår: 1958.\n\nNORBERGER &amp; LISSHAMMAR\nAB, BOKFDRINGSBYRÄN\n\nPnr 46101\n\nTrollhättan 1, Torgg 3. Box 170.\nTel 0520-127 60. Bankgiro\n892-5513. Postgiro 8690-0\nVerksamhet: Bokföring, bokslut,\ndeklarationer, skattefrågor etc\nAntal anställda: 30\nÅrsomsättning: 1100 000\nAktiekapital: 5 000\nChefer: Revisor Gunnar Norberger,\nrevisor Orvar Lisshammar\nEtableringsår: 1946.\n\nDELTA, ELEKTRISKA AB\n\nPnr 21130\n\nMalmö, Slussg 25. Tel 040-706 75.\nBankgiro 673-1111. Postgiro\n430909-9. Tga Elektrodelta\nVerksamhet: Tillverkar\nhögspännings- o kontrollutrustning\nFabriker: Arlöv. Tel 040-43 06 85\nÖstra Ljungby. Tel 043 5-213 44\nAntal anställda: 55\nÅrsomsättning: 9000 000\nAktiekapital: 150 000\nVerkst dir: Erik Feuk\nKamrer: Kjell Lager\nTekn chef: Elon Johansson\nEtableringsår: 1951.\n\nSTILJNDUSTRI, AB\n\nPnr 440 20\n\nVårgårda, Box 68. Tel0322-207 40.\nBankgiro 36-0257. Postgiro 577221.\nTga Stilindustri\n\nVerksamhet: Beslag till\nsäkerhetsbälten. Byggnadsbeslag.\nMotor-värmare till bilar\nAntal anställda: 60\nÅrsomsättning: 6 000 000\n\nSTJ\n\nAktiekapital: 150 000\nVerkst dir: Stig Lindblad\nEtableringsår: 1955\nOmbildat till aktiebolag 1961.\n\nSTILLE, AB NILS\n\nPnr 114 58\n\nStockholm, Grevg 50. Tel\n08-67 01 80. Bankgiro 564-6096.\nPostgiro 50907-5. Tga Maskin-Stille\nVerksamhet: Bult- o kolvpistoler,\nnylonplugg, elektr slagborrmaskiner\nAktiekapital: 100 000\nVeikst dir: Frk Anita Johansson\nEtableringsår: 1941.\n\nHÅL\n\nAktiekapital: 208 000\nVeikst dir Knuth Ostlund\nEtableringsår: 1902\nOmbildat till aktiebolag 1920.\n\nHÄGGLUNDS AB, MARIA\n\nPnr 103 13\n\nStockholm 2, Stortorget 18-20. Box\n2099. Tel 08-1119 28. Bankgiro\n446-6595. Postgiro 52146-8. Telex\n10438\n\nVerksamhet: Tillverkar o säljer\nsoya\n\nFabrik: Råå, Osterg 41. Tel\n042-60312\n\nAntal anställda: 4\n\nÅrsomsättning: 500 000\nAktiekapital: 40 000\nVerkst dir: Gunnar Lindquist\nEtableringsår: 1890\nOmbildat till aktiebolag 1942.\n\nHÄGGLUND, AB N H\n\nPnr 890 32\n\nJärved. Tel 0660-404 60. Postgiro\n62227\n\nVerksamhet: Säljer skor,\nskinnkläder o manufakturvaror i parti\nAktiekapital: 300 000\nVerkst dir: Curt Hägglund\nEtableringsår: 1950.\n\nHÄGGLUND AB,\nMÅLERIFIRMAN OLOF\n\nPnr 11124\n\nStockholm, Välling 18. Tel\n08-24 84 50. Bankgiro 613-1486.\nPost-giro 459760-5. Tga Mästerolof\nVerksamhet: Rostskyddsmålning,\nnybyggnads- o reparationsmålning\nVerkst dir Bengt Hägglund\nEtableringsår: 1873.\n\nGYL\n\nGUSTAFSSONS INDUSTRIER,\nAB KLAES\n\nPnr 343 00\n\nÄlmhult. Tel 0476-10012, 118 42.\nBankgiro 67-1743. Postgiro 337571\nVerksamhet: Tillverkar soff- o\nfåtöljstommar, resårkärnor\nAntal anställda: 25\nÅrsomsättning: 800 000\nAktiekapital: 150000\nVerkst dir: Bengt Gustafsson\nEtableringsår: 1924.\n\nGUSTAFSSON &amp; CO\nBl REDSKAPSFABRIK AB,\nOSCAR\n\nPnr 432 00\n\nVarberg, Postl 438 5, Tofta. Tel\n0340-200 21, 203 21. Bankgiro\n42-5195. Postgiro 25324\nVerksamhet: Tillverkar o säljer\nutrustningar o förnödenheter för\nbiskötsel, vaxkakor o bivax\nAntal anställda: 16\nÅrsomsättning: 600 000\nVerkst dir: Gösta Gustafsson\nEtableringsår: 1892.\n\nGUSTAVSSON\nMASKIN-FORNODENHETER, P O\n\nPnr 400 62\n\nGöteborg 29, Box 29003. Torkelsg\n4 B. Tel 031-1958 56, 195865.\nBankgiro 444-3206. Postgiro\n527471-7\n\nVerksamhet: Säljer slangar o\npackningar\n\nAntal anställda: 5\nÅrsomsättning: 2 000 000\nChef: Per-Olof Gustavsson\nEtableringsår: 1959.\n\nGUSTAFSSON BYGGNADS AB,\nREINHOLD\n\nPnr 104 30\n\nStockholm 45, Tegnérg 34. Box\n45023. Tel 08-23 5125. Bankgiro\n20-3025. Postgiro 409004\nVerksamhet: Uppför bostads-,\naffärs-o industribyggnader\nAktiekapital: 500 000\nVerkst dir: Reinhold Gustafsson\nEtableringsår: 1968.\n\nGUSTAFSSON, BYGGNADS.\nINGENJÖR REINHOLD\n\nPnr 104 30\n\nStockholm 45, Tegnérg 34. Box\n45023. Tel 08-23 51 25. Bankgiro\n57-8209. Postgiro 255699\nVerksamhet: Uppför bostads-,\naffärs- o industribyggnader\nAntal anställda: 350\nÅrsomsättning: 35 000 000\nChef: Byggn-ing Reinhold\nGustafsson\n\nEtableringsår: 1956.\n\nGUSTAFSSON MEK VERKSTAD\nAB, V\n\nPnr 112 23\n\nStockholm, Bergsg 5. Tel\n08-50 12 74 , 50 14 14. Bankgiro\n723-7407. Postgiro 194761-3\nVerksamhet: Verkstadsindustri.\nLegoarbeten\nAntal anställda: 14\nÅrsomsättning: 800 000\n\nAktiekapital: 30 000\nVerkst dir: Ing David Geller\nEtableringsår: 1929.\n\nDAFGÅRD AB, GUNNAR\n\nPnr 530 61\n\nKällby. Tel 0510-41170.\nBankgiro 841-3676. Postgiro 178623-5.\nTga Dafgàrds.\nTelex 67059 DAFGARD S\n\nGunnar Dafgård ab\n\n53061 KÄLLBY\n\nVerksamhet: Styckar, tillverkar o\ndjupfryser kött- o\ncharkuteriproduk-ter. Säljer dessa samt djupfrysta\nbär, grönsaker, fisk m m üll\nkonserv- o livsmedelsindustrier,\nstorhushåll, butikskedjor o grossister.\nImporterar o exporterar livsmedel\nFilialfabrik: Helsingborg,\nKvarn-stensg 15. Tel 042-13 05 66\n\nAllivsaffär: Lidköping, Nya Stadens\nTorg 8. Tel 0510-209 65\nInköp o försäljning: Danmark.\nHelsingör. Swedish Food Co A/S,\nMarienlyst allé 9. Tel 214818\nAntal anställda: 350\nÅrsomsättning: 130 000000\nAktiekapital: 3000 000\nStyrelse: Fru Nancy Dafgård (ordf),\ndir Gunnar Dafgård, Nils\nFredriksson\n\nVerkst dir: Gunnar Dafgård\nFabriken i Källby: Ekonomidir Nils\nFredriksson, inköpschef Rolf\nJohansson, försäljn-chef Allan\nOhlsson, tekn dir Bo Silow,\ninformationschef Sten Svensson\nFabriken i Helsingborg: Disp Elof\nDafgård\n\nAffären i Lidköping: Butikschef\nIngemar Dafgård\n\nKontoret i Helsingör: Disp Kjeld\nDamgaard\n\nEtableringsår: 1937\nOmbildat till aktiebolag 1961.\n\nDAGENS HUSHÅLL\n\nPnr 400 15\n\nGöteborg 53, Köpmännens hus,\nVa-sag 52. Box 53200. Tel\n031-17 26 40. Postgiro 423841\nVerksamhet: Internationell\nkonsument utställning varje år i\nseptember månad. Arrangör: Göteborgs\nKöpmannaförbund.\n\nDAGENS NYHETERS AB\n\nPnr 105 15\n\nStockholm, Rålambsv 15-17. Tel\n2240 00, riks 08-22 40 20. Bankgiro\n164-5308. Postgiro 1616-2. Tga\nDagsnyheter\n\nVerksamhet: Utger tidningarna\nDagens Nyheter o Expressen\nCiviltryckeri: 112 51 Stockholm,\nFranzéng 6. Tel 08-52 85 20\nAnnonskontor: Göteborg, S Hamng\n45. Box 358, 40125 Göteborg 1.\nTel 031-17 02 85\nMalmö, Söderg 20. Box 4063,\n20311 Malmö 4. Tel 040-10 0170\nAntal anställda: 3 100\nÅrsomsättning: 392 000 000\nAktiekapital: 53 900 000\nStyrelse: Bokförl Albert Bonnier Jr,\nbokförl Gerard Bonnier, dir Erik\nHuss, prof Erik Lundberg,\nchefred Sven Erik Larsson, chefred\nPer Wrigstad\nVerkst dir: Erik Huss\nEtableringsår: 1864\nOmbildat till aktiebolag 1874.\n\nDAGONATT FABRIKER AB\n\nPnr 951 00\n\nLuleå, Gammelstadsv 7. Tel\n0920-102 50. Bankgiro 75-2527. Postgiro\n65092\n\nVerksamhet: Tillverkar\nmonteringsfärdiga trähus o byggnadssnickerier\nAntal anställda: 230\nÅrsomsättning: 25 000 000\nAktiekapital: 1500 000\nVerkst dir: Rolf Krispinsson\nEtableringsår: 1894.\n\nEMMABODA GLASVERK, AB\n\nPnr 36100\n\nEmmaboda. Tel 0471-108 00. Tga\nGlasverket. Telex 43076\nVerksamhet: Tillverkar\nmaskinglas o isolerrutor\nAntal anställda: 600\nÅrsomsättning: 57 000 000\nAktiekapital: 2 700 000\nVerkst dir: Jan Afors\nEtableringsår: 1933.\n\nEMMABODA HUSINREDE, AB\n\nse MAS AB.\n\nEMMA BOD A\nMÖBELFABRIK, AB\n\nPnr 36100\n\nEmmaboda. Box 37. Tel\n0471-108 35. Bankgiro 85-4969. Postgiro\n22492\n\nVerksamhet: Tillverkar soffbord,\nkombinerade matbord o sängar\nAntal anställda: 40\nÅrsomsättning: 2 600 000\nAktiekapital: 130 000\nVerkst dir: Osvald Carlsson\nEtableringsår: 1907.\n\nEMMA LJUNGA\nBARNVAGNSFABRIK AB\n\nPnr 28 0 22\n\nVittsjö, Fack. Tel 0451-240 90.\nBankgiro 279-5342. Postgiro 31622-4\nVerksamhet: Tillverkar barn- o\ndockvagnar\n\nAntal anställda: 90\nÅrsomsättning: 7 900 000\nAktiekapital: 750 000\nVerkst dir: Låge Persson\nEtableringsår: 1925.\n\nTUV\n\nWistrand, frk Lena Sparring\nVerkst dir: Fru Ulla Sparring\nEtableringsån 1949.\n\nMONU IDÉREKLAM, AB RUNE\n\nPnr 114 22\n\nStockholm, Valhallav 55. Tel\n08-325260. Bankgiro 20-0103.\nPostgiro 23570\n\nVerksamhet: Konsulenter för\nreklam, information o PR\nAktiekapital: 5 000\nVerkst dir: L Boisen\nEtableringsår: 1968.\n\nMONU INDUSTRIDESIGN,\nAB RUNE\n\nPnr 183 54\n\nTäby, Eskaderv 4. Tel 08-756 44 44,\n756 44 45. Bankgiro 815-7737.\nPostgiro 252277-9. Tga Swedesign\nVerksamhet: Konsulter för\nprodukt-o miljödesign, grafisk formgivning\nAntal anställda: 6\nÅrsomsättning: 300 000\nAktiekapital: 10 000\nVerkst dir: Ing Rune Monö\nEtableringsår 1957.",
    "structured": {
        "1": {
            "company_name": "JÄM",
            "establishment_year": 1838,
            "employees": 20,
            "annual_turnover": 85000000
        },
        "2": {
            "company_name": "NORBERGS INDUSTRIBYRÅ",
            "pnr": "890 10",
            "establishment_year": 1950
        },
        "3": {
            "company_name": "NORBERGS MEK VERKSTAD, AB",
            "pnr": "778 00",
            "establishment_year": 1890,
            "employees": 65,
            "annual_turnover": 6000000,
            "capital": 400000
        },
        "4": {
            "company_name": "NORBERGS SPAD. & RED. SKAPSFABRIKER, AB",
            "pnr": "59100",
            "establishment_year": 1890,
            "employees": 39,
            "capital": 400000
        },
        "5": {
            "company_name": "NORBERG ANNONS AB, BALTZAR",
            "pnr": "11259",
            "establishment_year": 1958,
            "employees": 12,
            "annual_turnover": 5500000,
            "capital": 5000
        },
        "6": {
            "company_name": "NORBERGER & LISSHAMMAR AB, BOKFDRINGSBYRÄN",
            "pnr": "46101",
            "establishment_year": 1946,
            "employees": 30,
            "annual_turnover": 1100000,
            "capital": 5000
        },
        "7": {
            "company_name": "DELTA, ELEKTRISKA AB",
            "pnr": "21130",
            "establishment_year": 1951,
            "employees": 55,
            "annual_turnover": 9000000,
            "capital": 150000
        },
        "8": {
            "company_name": "STILJNDUSTRI, AB",
            "pnr": "440 20",
            "establishment_year": 1955,
            "employees": 60,
            "annual_turnover": 6000000,
            "capital": 150000
        },
        "9": {
            "company_name": "STILLE, AB NILS",
            "pnr": "114 58",
            "establishment_year": 1941,
            "capital": 100000
        },
        "10": {
            "company_name": "HÄGGLUNDS AB, MARIA",
            "pnr": "103 13",
            "establishment_year": 1890,
            "employees": 4,
            "annual_turnover": 500000,
            "capital": 40000
        },
        "11": {
            "company_name": "HÄGGLUND, AB N H",
            "pnr": "890 32",
            "establishment_year": 1950,
            "capital": 300000
        },
        "12": {
            "company_name": "HÄGGLUND AB, MÅLERIFIRMAN OLOF",
            "pnr": "11124",
            "establishment_year": 1873
        },
        "13": {
            "company_name": "GYL GUSTAFSSONS INDUSTRIER, AB KLAES",
            "pnr": "343 00",
            "establishment_year": 1924,
            "employees": 25,
            "annual_turnover": 800000,
            "capital": 150000
        },
        "14": {
            "company_name": "GUSTAFSSON & CO Bl REDSKAPSFABRIK AB, OSCAR",
            "pnr": "432 00",
            "establishment_year": 1892,
            "employees": 16,
            "annual_turnover": 600000
        },
        "15": {
            "company_name": "GUSTAVSSON MASKIN-FORNODENHETER, P O",
            "pnr": "400 62",
            "establishment_year": 1959,
            "employees": 5,
            "annual_turnover": 2000000,
            "capital": 30000
        },
        "16": {
            "company_name": "GUSTAFSSON BYGGNADS AB, REINHOLD",
            "pnr": "104 30",
            "establishment_year": 1968,
            "capital": 500000
        },
        "17": {
            "company_name": "GUSTAFSSON, BYGGNADS. INGENJÖR REINHOLD",
            "pnr": "104 30",
            "establishment_year": 1956,
            "employees": 350,
            "annual_turnover": 35000000
        },
        "18": {
            "company_name": "GUSTAFSSON MEK VERKSTAD AB, V",
            "pnr": "112 23",
            "establishment_year": 1929,
            "employees": 14,
            "annual_turnover": 800000,
            "capital": 30000
        },
        "19": {
            "company_name": "DAFGÅRD AB, GUNNAR",
            "pnr": "530 61",
            "establishment_year": 1937,
            "employees": 350,
            "annual_turnover": 130000000,
            "capital": 3000000
        },
        "20": {
            "company_name": "DAGENS HUSHÅLL",
            "pnr": "400 15"
        },
        "21": {
            "company_name": "DAGENS NYHETERS AB",
            "pnr": "105 15",
            "establishment_year": 1864,
            "employees": 3100,
            "annual_turnover": 392000000,
            "capital": 53900000
        },
        "22": {
            "company_name": "DAGONATT FABRIKER AB",
            "pnr": "951 00",
            "establishment_year": 1894,
            "employees": 230,
            "annual_turnover": 25000000,
            "capital": 1500000
        },
        "23": {
            "company_name": "EMMABODA GLASVERK, AB",
            "pnr": "36100",
            "establishment_year": 1933,
            "employees": 600,
            "annual_turnover": 57000000,
            "capital": 2700000
        },
        "24": {
            "company_name": "EMMA BOD A MÖBELFABRIK, AB",
            "pnr": "36100",
            "establishment_year": 1907,
            "employees": 40,
            "annual_turnover": 2600000,
            "capital": 130000
        },
        "25": {
            "company_name": "EMMA LJUNGA BARNVAGNSFABRIK AB",
            "pnr": "28 0 22",
            "establishment_year": 1925,
            "employees": 90,
            "annual_turnover": 7900000,
            "capital": 750000
        },
        "26": {
            "company_name": "MONU IDÉREKLAM, AB RUNE",
            "pnr": "114 22",
            "establishment_year": 1968,
            "capital": 5000
        },
        "27": {
            "company_name": "MONU INDUSTRIDESIGN, AB RUNE",
            "pnr": "183 54",
            "establishment_year": 1957,
            "employees": 6,
            "annual_turnover": 300000,
            "capital": 10000
        }
    }
}