{
    "original": "HOL\n\nVerksamhet: Tillverkar sängar av\nstålrör, utför stålrörskonstruktioner\nÄgare o chef: Johan Holmberg.\n\nHOLMBERG I GOTENE AB,\nKARL\n\nPnr 533 00\n\nGötene, Box 92. Tel 0511-506 20\nVerksamhet: Snickerifabrik.\nTillverkning o grossistförsäljning av\nhushållsartiklar i trä\nAntal anställda: 90\nÅrsomsättning: 5 000 000\nAktiekapital: 840 000\nVeikst dir: Fabr Karl-Erik\nHolmberg\n\nEtableringsår: 1923.\n\nGULLBERGS SKINNVARU, AB\n\nPnr 692 00\n\nKumla, Box 39. Kvarng 20. Tel\n019-715 72. Bankgiro 606-1600.\nPostgiro 289616-5\n\nVerksamhet: Tillverkar accessoarer\nför sko- o beklädnadsindustrin i\nskinn o plast samt hyttinredningar\nför lastbilar o traktorer\nAntal anställda: 5\nÅrsomsättning: 200 000\nAktiekapital: 30 000\nStyrelseordf: Karl Axel Sigge\nVerkst dir: Karl Axel Sigge\nEtableringsår: 1962.\n\nOPTIMAL AB\n\nPnr 436 00\n\nAskim, Värslev 8. Tel 031-28 62 32.\nBankgiro 51-5820. Postgiro 44521\nVerksamhet: Konsultering,\nrationalisering, organisation\n\nAntal anställda: 5\nÅrsomsättning: 300 000\nAktiekapital: 5 000\nChef: Torsten Abrahamson\nEtableringsår: 1963.\n\nSIK\n\nSIKSTRUM, AB ULF A\n\nPnr 11135\n\nStockholm, Kungsg 32. Tel\n08-10 72 50, 20 74 74. Bankgiro\n746-6022. Postgiro 165403-7. Tga\nLe-dersik\n\nVerksamhet: Säljer skodon\nAntal anställda: 5\nÅrsomsättning: 1000 000\nAktiekapital: 50 000\nVerkst din Ulf Sikström\nEtableringsàr: 1954.\n\nSI L1 KEMI AB\n\nPnr 65107\n\nKarlstad 1, O Torgg 11. Box 414.\nTel 054-1111 23. Bankgiro\n881-3768. Postgiro 171331-2\nVerksamhet: Tillverkar vattenglas\no kristallsoda\n\nFabrik: Skattkärr. Tel 054-60113\nAktiekapital: 5 000\nVeikst din Hilding Ledel\nEtableringsån 1937.\n\nSCH\n\nningar, armatur för industriella o\nallmänna ändamål,\nindustrirörledningar o kvalitetsgjutgods i stål o\ngråjärn\n\nAktiekapital: 25 000\nVerkst dir: Jur dr A Sonek\nEtableringsår: 1969.\n\nSJA, AB\n\nPnr 10123\n\nStockholm 1, Box 235. Kammakarg\n62. Tel 08-714 01 30. Bankgiro\n728-738 6. Postgiro 454377-3.\nTga Teknozym.\n\nTelex 10936 SCANTEC S\nVeiksamhet: Roterande vacuumfilter\nför jäst o andra ändamål\nEtableringsàr: 1938.\nDotterbolag tiE AB Fannyudde.\n\nSJUCO AB\n\nPnr 402 24\n\nGöteborg 5, Box 5247. Kärrag 5,\nMölndal. Tel 031-87 02 00. Bankgiro\n506-29 22. Postgiro 628030-9. Tga\nSjucoab. Telex 20887 MEDITEC S\nVerksamhet: Produktutveckling o\nförsäljning av\nröntgenkontrastmedel, suturmaterial, engångsartiklar\nför sjukhus, nylonfolie samt\nnäringsfysiologiska preparat\nVaiunamn: Broli, Ready-One,\nSani-Pac, Sani Temp, Steri-Temp\nVerkst dir: Kaj Jacobsson\nDotterbolag till Astra-Meditec AB,\nGöteborg.\n\nSe vidare Astra-Meditec AB.\n\nSJUHARADSBYGDENS\nTRYCKERI AB\n\nPnr 50102\n\nBorås, Allég 59. Box 53. Tel\n033-11 70 30. Bankgiro 360-8502.\nPostgiro 343110-3. Telex 36103 VEDE S\n\nTidningar, Tidskrifter,\nBok-Offset- och Rotationstryck\n\nAntal anstäUda: 135\nÅrsomsättning: 9 300 000\nAktiekapital: 1243 650\nVerkst dir: Henry Snygg\nEtableringsàr: 1926.\n\nSJUNTORP, AB\n\nPnr 460 20\n\nSjuntorp. Tel 0520-402 00.\nPostgiro 9080\n\nVeiksamhet: Spinneri, väveri,\nfärgeri, bandfabrik o\nvävplasttill-verkning\n\nAvdelningskontor: 11148\nStockholm, Nybrokajen 7. Tel 08-20 60 54\ntelefons varare\n\n502 64 Borås, Västmannag 16. Tel\n033-10 29 66\nAntal anstäUda: 400\nÅrsomsättning: 23 000 000\nAkUekapital: 2 400000\nDir Rudolf Berg\nEtableringsàr 1813\nOmbildat till aktiebolag 1882.\n\nSJOO FABRIKS AB\n\nPnr 17148\n\nSolna, Industriv 15. Tel 08-82 0100\nVerksamhet: Utför storköks- o\nrestauranginredningar.\nSpecialverkstad för rostfri plåt. Snickerifabrik\nAntal anstäUda: 85\nÅrsomsättning: 9 000 000\nAkUekapital: 1000 000\nVerkst dir: Evert Sjöö\nEtableringsàr 1928.\n\nINLANDS AB\n\nPnr 463 00\n\nLilla Edet. Tel 0520-506 20.\nTga Indju, Trollhättan. Telex 42099\nVerksamhet: Papp- o kartongfabrik.\nTillverkar papp o kartong\nAntal anställda: 200\nAktiekapital: 3 000 000\nStyrelse: Adv Sture Hovden (ordf),\ndir Göran Langenskiöld, dir Gösta\nLönn, bankdir Harald Magnusson\nVerkst dir: Gösta Lönn (Kallinge)\nPlatschef o tekn avd: Sune Wattman\nInköpsavd: Leif Milling\nFörsäljnings- o ekonomiavd: Se\nDjupafors Fabriks AB\nEtableringsår: 1894\nOmbildat till aktiebolag 1913.\n\nINLAND.DJUPAFORS\n\nFörsäljningsavdelning: se\nDjupafors Fabriks AB.\n\nINMONT AB\n\nPnr 104 20\n\nStockholm 8, Fack. Agneg 36. Tel\n08-54 55 11, 54 80 80. Bankgiro\n220-7330. Postgiro 408810\nVerksamhet: Tillverkar, säljer o\nmonterar inredningar samt\nutvändiga solskydd till kontor, banker,\nsjukhus, skolor etc\nAntal anställda: 16\nAktiekapital: 10 000\nVerkst dir: Ing H Söderlund\nEtableringsår: 1969.\n\nRYWI, KONFEKTIONS.AB\n\nPnr 523 00\n\nUlricehamn,Tegelbrukg 8. Tel\n0321-106 85. Bankgiro 53-2821.\nPostgiro 81030\n\nVerksamhet: Tillverkar\nherrkostymer, blazer o byxor\nAntal anstäUda: 40\nÅrsomsättning: 2 000 000\nAktiekapital: 70 000\nVerkst dir Gösta Rylander\nEtableringsår 1939.\n\nAGENTA PRODUKTER AB\n\nPnr 113 44\n\nStockholm, Upplandsg 79. Tel\n08-2313 90. Bankgiro 74-7210. Postgiro\n657360. Telex 10509 AGENTA S\nVerksamhet: Säljer\nkopieringsmaskiner o kopieringsapparater\nAntal anställda: 3\nÅrsomsättning: 1000 000\nAktiekapital: 100 000\nVerkst dir: Gunnar af Klintberg\nEtableringsår: 1962.\n\nKON\n\nKONSULTERNA FOR\nINDUSTRI och HANDEL, AB\n\nPnr 182 61\n\nDjursholm, Henrik Palmes Alle 16.\nTel 08-755 28 90. Bankgiro\n106-2717\n\nVerksamhet:\nOrganisationskonsulter\n\nAntal anställda: 20\nÅrsomsättning: 1500000\nAktiekapital: 100000\nVerkst dir: Hans Hindersson\nEtableringsår: 1957.",
    "structured": {
        "1": {
            "company_name": "HOLMBERG I GOTENE AB",
            "activity": "Tillverkar sängar av stålrör, utför stålrörskonstruktioner",
            "establishment_year": 1923
        },
        "2": {
            "company_name": "GULLBERGS SKINNVARU, AB",
            "activity": "Tillverkar accessoarer för sko- o beklädnadsindustrin i skinn o plast samt hyttinredningar för lastbilar o traktorer",
            "employees": 5,
            "annual_turnover": 200000,
            "capital": 30000,
            "establishment_year": 1962
        },
        "3": {
            "company_name": "OPTIMAL AB",
            "activity": "Konsultering, rationalisering, organisation",
            "employees": 5,
            "annual_turnover": 300000,
            "capital": 5000,
            "establishment_year": 1963
        },
        "4": {
            "company_name": "SIKSTRUM, AB ULF A",
            "activity": "Säljer skodon",
            "employees": 5,
            "annual_turnover": 1000000,
            "capital": 50000,
            "establishment_year": 1954
        },
        "5": {
            "company_name": "SI L1 KEMI AB",
            "activity": "Tillverkar vattenglas o kristallsoda",
            "capital": 5000,
            "establishment_year": 1937
        },
        "6": {
            "company_name": "SCH",
            "establishment_year": 1969
        },
        "7": {
            "company_name": "SJA, AB",
            "activity": "Roterande vacuumfilter för jäst o andra ändamål",
            "establishment_year": 1938
        },
        "8": {
            "company_name": "SJUCO AB",
            "activity": "Produktutveckling o försäljning av röntgenkontrastmedel, suturmaterial, engångsartiklar för sjukhus, nylonfolie samt näringsfysiologiska preparat",
            "key_personnel": [
                {
                    "name": "Kaj Jacobsson",
                    "position": "Verkst dir"
                }
            ]
        },
        "9": {
            "company_name": "SJUHARADSBYGDENS TRYCKERI AB",
            "activity": "Tidningar, Tidskrifter, Bok-Offset- och Rotationstryck",
            "employees": 135,
            "annual_turnover": 9300000,
            "capital": 1243650,
            "establishment_year": 1926
        },
        "10": {
            "company_name": "SJUNTORP, AB",
            "activity": "Spinneri, väveri, färgeri, bandfabrik o vävplasttillverkning",
            "employees": 400,
            "annual_turnover": 23000000,
            "capital": 2400000,
            "establishment_year": 1813
        },
        "11": {
            "company_name": "SJOO FABRIKS AB",
            "activity": "Utför storköks- o restauranginredningar. Specialverkstad för rostfri plåt. Snickerifabrik",
            "employees": 85,
            "annual_turnover": 9000000,
            "capital": 100000,
            "establishment_year": 1928
        },
        "12": {
            "company_name": "INLANDS AB",
            "activity": "Papp- o kartongfabrik. Tillverkar papp o kartong",
            "employees": 200,
            "capital": 3000000,
            "establishment_year": 1894
        },
        "13": {
            "company_name": "INMONT AB",
            "activity": "Tillverkar, säljer o monterar inredningar samt utvändiga solskydd till kontor, banker, sjukhus, skolor etc",
            "employees": 16,
            "capital": 10000,
            "establishment_year": 1969
        },
        "14": {
            "company_name": "RYWI, KONFEKTIONS.AB",
            "activity": "Tillverkar herrkostymer, blazer o byxor",
            "employees": 40,
            "annual_turnover": 2000000,
            "capital": 70000,
            "establishment_year": 1939
        },
        "15": {
            "company_name": "AGENTA PRODUKTER AB",
            "activity": "Säljer kopieringsmaskiner o kopieringsapparater",
            "employees": 3,
            "annual_turnover": 1000000,
            "capital": 100000,
            "establishment_year": 1962
        },
        "16": {
            "company_name": "KONKONSULTERNA FOR INDUSTRI och HANDEL, AB",
            "activity": "Organisationskonsulter",
            "employees": 20,
            "annual_turnover": 1500000,
            "capital": 100000,
            "establishment_year": 1957
        }
    }
}