{
    "original": "SKOGSBRUKSMASKINER, AB\n\nPnr 64100\n\nKatrineholm. Tel0150-162 20.\nBankgiro 56-3553. Postgiro 353067. Tga\nSkogsmaskiner\n\nVerksamhet: Import,\nlegotillverkning o försäljning av skogs- o\nsågverksmaskiner\nAntal anställda: 20\nÅrsomsättning: 7 000 000\nAktiekapital: 150 000\nVerkst dir: Ake Carlson\nEtableringsår: 1948.\n\nSKOGSLUNDS FABRIKS AB\n\nPnr 330 30\n\nGnosjö. Tel 0370-914 85. Postgiro\n29694\n\nVerksamhet: Tillverkar stansade o\nbockade detaljer i järn o stål\nAktiekapital: 308 000\nÄgare o chef: Carl-Eric Ericsson\nEtableringsår: 1924.\n\n01E\n\nVerksamhet: Tillverkning av\nmedicinsk o industriell elektronisk\napparatur\n\nAktiekapital: 5 000\n\nÄgare o chef: Civiling Carl-Axel\n\nWannerekog\n\nEtableringsår: 1965.\n\nBURTRÄSK MEKANISKA, AB\n\nPnr 930 20\n\nBurträsk, Box 60. Tel 0914-103 02.\nBankgiro 76-1629. Postgiro\n349882-1\n\nVerksamhet: Tillverkar frontlastare,\nbrandpostluckor o mindre\nreningsverk. Utför legotillverkning\nAntal anställda: 8\nÅrsomsättning: 500 000\nAktiekapital: 5 000\nVerkst dir: Gunnar Wincent\nVerkmäst: Efon Söderström\nIng: Alf Wincent\nEtableringsår: 1948.\n\nCGP FÄRG, AB\n\nPnr 70211\n\nÖrebro, Nyg 13-15. Tel 019-118197,\n1101 37. Bankgiro 815-7265.\nPostgiro 9127-2\n\nVerksamhet: Säljer färger,\nfernissor o kemikalier i parti\nAntal anställda: 10\nÅrsomsättning: 2 000 000\nAktiekapital: 140000\nChef: Dir Erik Otterlid\nEtableringsår: 1877.\n\nTRO\n\nTRIMMER, AB\n\nPnr 113 51\n\nStockholm, Odeng 40. Tel\n08-343657, 343658. Postgiro 380060\nVerksamhet: Export av trä- o\nmetallprodukter. Import av\nisoleringsmaterial för elektr industrin\nAntal anställda: 6\nÅrsomsättning: 2500 000\nAktiekapital: 50 000\nVerkst dir: Nils Johansson\nEtableringsår: 1946.\n\nTRIO AB, ARMATUR.\nFABRIKEN\n\nIngår i Cementakoncernen\nPnr 280 70\n\nLönsboda. Tel 0479-205 10.\nBankgiro 569-6117. Postgiro 154659-7\nVerksamhet: Vattenarmatur,\nauto-matsvarvade detaljer,\nelektrolytisk ytbehandling\nAntal anställda: 125\nÅrsomsättning: 11000 000\nAktiekapital: 900000\nStyrelse: Dir Stig Sunne, dir Bengt\nLund, dir Harald Sundström\nVerkst din Bengt Lund\nEtableringsån 1938.\n\nTRIOFRAKT EKONOMISK\nFÖRENING\n\nPnr 732 00\n\nArboga, Hamng 6-8. Box 54. Tel\n0589-150 50. Bankgiro 600-1333.\nPostgiro 267345-7\nVerksamhet: Transportförmedling\nsamt leverans av vägmaterial\nAvdelningskontor: Kungsör,\nFYedsg 33. Tel 0227-102 25\nKöping, Fabriksg 11. Tel\n0221-125 00\n\nAntal anställda: 8\nÅrsomsättning: 9 000 000\nChef: Disp Lars Gullberg\nKamrer: Ake Sjögren\nEtableringsår: 1965\nTriofrakt ekonomisk förening har\nuppkommit genom sammanslagning\nav lastbilcentraler.\n\nTRIOPLAST AB\n\nPnr 330 23\n\nSmålandsstenar, Idrottsg. Box 141.\nTel 0371-310 25. Bankgiro 42-7698.\nPostgiro 647188\n\nVerksamhet: Tillverkar folie, säckar\no påsar i polyeten, även med tryck.\nSpecialitet: krympfolier\nAntal anställda: 35\nÅrsomsättning: 8 000 000\nAktiekapital: 150 000\nVerkst dir. Vilhelm Larsson\nEtableringsån 1963.\n\nKNU\n\nVarunamn: Nima\nAntal anställda: 65\nÅrsomsättning: 4 500 000\nAktiekapital: 70000\nStyrelse: Sture Larsson, ing K G\nMalm, ing Jan Malm\nVerkst dir: Ing Jan Malm\nEtableringsår: 1924.\n\nKNUTSSON AB, INGENJÖRS.\nFIRMAN BO\n\nPnr 171 40\n\nSolna, Sommarv 2. Tel 08-83 06 80.\nBankgiro 332-0520. Postgiro\n455325-1. Tga Ingbekon.\nTelex 10034 INGBEKO S\nVerksamhet: Representanter för\nutländska tillverkare av\nkomponenter o tillbehör för elektronik,\nradio- o TV-industrin\nAntal anställda: 13\nÅrsomsättning: 12 000 000\nAktiekapital: 80 000\nVerkst dir: Ing Bo Knutsson\nEtableringsår: 1951\nOmbildat till aktiebolag 1961.\n\nKNUTSSON BYGGNADS AB,\nGUNNAR\n\nPnr 332 00\n\nGislaved, Mårtensg 26. Box 123.\nTel 0371-120 20. Bankgiro\n426-7142. Postgiro 331696-5\nVerksamhet: Byggnadsentreprenör\nför bostadshus, skolor, kommunala\ninstitutioner, sjukhus, hotell,\nfolkets hus, ålderdomshem, kyrkor,\nindustrier samt kyrko- o\nindustrirestaureringar\nAntal anställda: 150\nÅrsomsättning: 10 000 000\nAktiekapital: 50 000\nVerkst dir: Ing Gunnar Knutsson\nEtableringsår: 1946.\n\nFURNATOR FÄRG AB\n\nPnr 510 80\n\nTranemo. Tel 0325-70775. Bankgiro\n55-3218. Postgiro 179040\nVerksamhet: Försäljning av\nrödfärg, linolje- o plastfärger\nChef: Disp Erie Österlund\nEtableringsår: 1941.\n\nSCH\n\ngiro 863-9882. Postgiro 393755-4.\nTga Wilmatex\n\nVerksamhet: Importerar o säljer\nfiltar, plädar, påslakan, frotté,\nhanddukar, dukar, mattor\n(avpassade o heltäckande), gardiner,\nsängöverkast\n\nVarunamn: Botex, Danrya, Plorex,\nFraling, Irisette, Polar, Zoeppritz\nAktiekapital: 100 000\nStyrelse: Disp Harry Hamnäs, fru\nBarbro Hamnäs\nChef: Disp Harry Hamnäs.\n\nSCHNEIDER AB, ARTHUR\n\nPnr 21149\n\nMalmö, Sankt Pauli Kyrkog 21.\nTel 040-11 11 87, 11 35 16. Bankgiro\n801-7394. Postgiro 247559-8. Tga\nJarob. Telex 3190 JAROB S\nVeiksamhet: Agenturfirma för\nhalvfabrikat inom glas-, metall- o\nbelysningsindustrin\nAktiekapital: 30 000\nVeikst din Fru Gusti Schneider\nEtableringsår. 1929\nOmbildat till aktiebolag 1949.\n\nSCHNEIDER, AB J\n\nPnr 11124\n\nStockholm, Västmannag 1. Tel\n08-11 6451, 11 64 52\nVerksamhet: Import o export\nVarunamn: Trädgårdsspecialisten\nAktiekapital: 40 000\nVerkst din M Grosse\nEtableringsån 1929.\n\nK ÅJO KONFEKTION AB\n\nPnr 310 63\n\nAlvsered, Fack 20. Tel\n0325-310 51. Bankgiro 55-28 40.\nPostgiro 593927\n\nVerksamhet: Tillverkar barnkläder\no utför lönsömnad\nAntal anställda: 21\nÅrsomsättning: 650 000\nAktiekapital: 15 000\nVerkst dir: Rolf Karlsson\nEtableringsår: 1963.\n\nBOHUSBANKEN, AB\n\nPnr 401 21\n\nGöteborg 1, Drottningg 30. Box 87.\nTel 031-1759 20. Bankgiro\n410-0012. Postgiro 40222-2. Tga\nBohusbanken\nVerksamhet: Bankrörelse\nAntal anställda: 13\nAktiekapital: 3 000 000\nVerkst dir: Gunnar Hanson\nEtableringsår: 1918.\n\nBOHUSLÄNS KOOP\n\nSTENINDUSTRI,\n\nANDELSFÖRENINGEN\n\nPnr 45040\n\nKungshamn, Stenhuggareg 12.\nPostl 817. Tel 0523-308 14.\nBankgiro 54-3430. Postgiro 168351\nVerksamhet: Tillverkar kantsten,\ngatsten o blocksten\nAntal anställda: 95\nInsatskapital: 140 000\nChef: Dick Svanberg\nEtableringsår: 1926\nDotterbolag: AB Lysekils\nStenindustri.\n\nBOHUSLÄNS ST EN\nFORÄDLING, AB\n\nPnr 450 46\n\nHunnebostrand, Box 68. Tel\n0523-504 90. Bankgiro 544-20 25.\nPostgiro 1338 76-3\n\nVerksamhet: Tillverkar\nbyggnadssten, gravvårdar, gatsten o kanststen.\nAntal anställda: 100\nÅrsomsättning: 4 000 000\nAktiekapital: 200000\nÄgare o chefer: Dir Hjalmar Höij,\ndir Evald Bäckman\nEtableringsår: 1937.",
    "structured": {
        "1": {
            "company_name": "SKOGSBRUKSMASKINER, AB",
            "pnr": "64100",
            "phone_number": "0150-162 20",
            "bank_details": {
                "bankgiro": "56-3553",
                "postgiro": "353067"
            },
            "activity": "Import, legotillverkning o försäljning av skogs- o sågverksmaskiner",
            "employees": 20,
            "annual_turnover": 7000000,
            "capital": 150000,
            "key_personnel": [
                {
                    "name": "Ake Carlson",
                    "position": "Verkst dir"
                }
            ],
            "establishment_year": 1948
        },
        "2": {
            "company_name": "SKOGSLUNDS FABRIKS AB",
            "pnr": "330 30",
            "phone_number": "0370-914 85",
            "postgiro": "29694",
            "activity": "Tillverkar stansade o bockade detaljer i järn o stål",
            "capital": 308000,
            "key_personnel": [
                {
                    "name": "Carl-Eric Ericsson",
                    "position": "Ägare o chef"
                }
            ],
            "establishment_year": 1924
        },
        "3": {
            "company_name": "01E",
            "activity": "Tillverkning av medicinsk o industriell elektronisk apparatur",
            "capital": 5000,
            "key_personnel": [
                {
                    "name": "Civiling Carl-Axel Wannerekog",
                    "position": "Ägare o chef"
                }
            ],
            "establishment_year": 1965
        },
        "4": {
            "company_name": "BURTRÄSK MEKANISKA, AB",
            "pnr": "930 20",
            "address": "Box 60",
            "phone_number": "0914-103 02",
            "bank_details": {
                "bankgiro": "76-1629",
                "postgiro": "349882-1"
            },
            "activity": "Tillverkar frontlastare, brandpostluckor o mindre reningsverk. Utför legotillverkning",
            "employees": 8,
            "annual_turnover": 500000,
            "capital": 5000,
            "key_personnel": [
                {
                    "name": "Gunnar Wincent",
                    "position": "Verkst dir"
                },
                {
                    "name": "Efon Söderström",
                    "position": "Verkmäst"
                },
                {
                    "name": "Alf Wincent",
                    "position": "Ing"
                }
            ],
            "establishment_year": 1948
        },
        "5": {
            "company_name": "CGP FÄRG, AB",
            "pnr": "70211",
            "address": "Nyg 13-15",
            "phone_number": "019-118197, 1101 37",
            "bank_details": {
                "bankgiro": "815-7265",
                "postgiro": "9127-2"
            },
            "activity": "Säljer färger, fernissor o kemikalier i parti",
            "employees": 10,
            "annual_turnover": 2000000,
            "capital": 140000,
            "key_personnel": [
                {
                    "name": "Dir Erik Otterlid",
                    "position": "Chef"
                }
            ],
            "establishment_year": 1877
        },
        "6": {
            "company_name": "TRO TRIMMER, AB",
            "pnr": "113 51",
            "address": "Odeng 40",
            "phone_number": "08-343657, 343658",
            "postgiro": "380060",
            "activity": "Export av trä- o metallprodukter. Import av isoleringsmaterial för elektr industrin",
            "employees": 6,
            "annual_turnover": 2500000,
            "capital": 50000,
            "key_personnel": [
                {
                    "name": "Nils Johansson",
                    "position": "Verkst dir"
                }
            ],
            "establishment_year": 1946
        }
    }
}