{
    "original": "TRAFIK. &amp; VÄGMÄRKEN AB\n\nPnr 103 42\n\nStockholm 40, Sveav 24-26. Box\n40075. Tel 08-24 47 00. Postgiro\n156633. Tga Vägmärken\nVerksamhet: Säljer vägmärken,\nparkeringsmätare o trafiksignaler\nAntal anställda: 20\nAktiekapital: 450 000\nVerkst din Clas Otto Ruben\nEtableringsår. 1932.\n\nTRAFIK.BORE, ÖMSESIDIGT,\nFÖRSÄKRINGSBOLAGET\n\nPnr 18211\n\nDanderyd X, Mysingsv 5. Box 50.\nTel 08-753 00 00. Postgiro 3444.\nTga Trafikförsäkra\nVerksamhet: Försäkringsrörelse\nAntal anställda: 455\nÅrsomsättning: 107 000 000\nVerkst dir: Jan Borgenhard\nEtableringsår: 1927.\n\nTRANELLSVAGNFABRIK\nEFTR\n\nPnr 740 40\n\nHeby, Box 104. Tel 0224-30004.\nBankgiro 81-0715. Postgiro 98451.\nVerksamhet: Utför plåtarbeten,\nsmide o svetsning\nAntal anställda: 30\nÅrsomsättning: 1500 000\nChef: Bertil Wallin\nEtableringsår 1917.\n\nTRANEMO\nCEMENTVARU-AKTIEBOLAG\n\nPnr 510 80\n\nTranemo, Box 73. Tel 0325-701 50.\nBankgiro 553-1728. Postgiro\n81450-9\n\nVerksamhet: Tillverkning av\nförekommande betongvaror i\nstandardutförande, reservoarer för\nvattenförsörjning, brandsläckning,\nreningsanläggningar, ensilage o\nflytgödsel. TA-element för brotrummor,\nkör- o gångtunnlar samt ko-portar.\nALF A-rör, kantstöd,\nstödmursele-ment. Betongelementet ’Grisen’\nför avgränsningar vid\nparkeringsplatser o d. Trädgårds-,\ntrottoar-o gallerplattor\nAntal anställda: 50\nÅrsomsättning: 4 500 000\nAktiekapital: 300 000\nStyrelse: Fru Anna Hermanson,\nfrk Gunvor Hermanson, fru Eva\nAronowitsch, fabrikschef Per\nAnders Hermanson\nVerkst dir: Fru Anna Hermanson\nFabrikschef: Per Anders\nHerman-son\n\nEtableringsår 1923.\n\nSTÄLLBERGSBOLAGEN\n\nPnr 771 01\n\nLudvika 1, Box 84. Tel 0240-138 50.\nBankgiro 23-1226. Postgiro 94183.\nTga Ställbergab\n\nVerksamhet: Produktion o\nförsäljning av manganhaltig järnmalm o\nmull, fosforfattig malm o mull,\nsili-ciös fosforfattig malm, fosforhaltig\nstyckemalm o mull. Makadam\nAntal anställda: 250 (koncernen)\nÅrsomsättning: 20 000 000\n(koncernen)\n\nAktiekapital: 11 900 000\n(moderbolaget)\n\nStyrelse: Adv Hugo Stenbeck (ordf),\nadv Sten S:son Ankarcrona, disp\nFolke Franzén, prof Ingvar\nJanelid, frih Baltzar Klingspor, frih\nFritz Klingspor, frih Stig\nKlingspor, frih Knut Leijonhufvud\nVerkst dir: Disp Folke Franzén\nTekn dir: Björn Andersson\nEtableringsår: 1881 (moderbolaget)\nModerbolag: Ställbergs Grufve AB\nDotterbolag: Idkerbergets Gruf AB,\nIdkerberget, Forsbo Gruv AB, Stora\nSkedvi, AB Järnmalm, Stripa Gruv\nAB, Storå.\n\nSTÄNGSELNÄT I\nRYDS-GÅRD, AB\n\nPnr 270 12\n\nRydsgård. Tel 0411-443 80.\nBankgiro 86-3945. Postgiro 143027. Tga\nStängselnät\n\nVerksamhet: Tråddrageri, nätfabrik,\ndukväveri, spikfabrik,\nkättingfa-brik, galvaniseringsverk\nAntal anstäUda: 170\nÅrsomsättning: 15 000 000\nAktiekapital: 1000 000\nStyrelse: Adv Henning Dahlin\n(ordf), dir John Nygren, dir John\nE Vifot, dir Allan Nilsson, disp\nOlle Barchan, adv L O Dahlin\nVerkst dir: Disp Olle Barchan\nOvering: Olle Granér\nFörsäljn-chef: Bengt Janzon\nKamrer: Caj Barchan\nEtableringsår: 1911.\n\nSUNDLING AB, H\n\nPnr 573 00\n\nTranås, Trehörnav. Box 101. Tel\n0140-122 64. Bankgiro 36-5683.\nPostgiro 144046\nVerksamhet: Tillverkar möbler.\nSpecialitet: stilmöbler\nAntal anställda: 30\nÅrsomsättning: 1700 000\nAktiekapital: 78 000\nVeikst din Disp Gösta Sundling\nEtableringsår: 1915.\n\nMARIN INDUSTRI AB\n\nPnr 414 51\n\nGöteborg, Banehagsg 1. Tel\n031-42 2100, 42 21 01. Bankgiro\n506-5321. Postgiro 521398-8. Tga\nMarinindustri\n\nVerksamhet: Specialverkstad för\nbränslepumpar, ventiler o spridare\nVerkst dir: Civilekonom Kjell\nBaarlid\n\nEtableringsår. 1956.\n\nMARKNADS-TEST AB\n\nPnr 181 07\n\nLidingö 7, Box 717. Barkassv 17.\nTel 08-767 04 25. Bankgiro\n565-2979. Postgiro 11689-7\nVerksamhet: Konsulter i\nmarknadsföring\n\nAntal anställda: 25\nÅrsomsättning: 3 000 000\nAktiekapital: 5 000\nVerkst dir: Civilekonom Kjell\nBolin\n\nEtableringsår: 1964.\n\nTOL\n\nVerksamhet: Tillverkar hydrauliska\npressar\n\nAktiekapital: 15 000\nVerkst dir: John Sjölin\nEtableringsår: 1946.\n\nFOR\n\nAktiekapital: 45000\nVerkst dir: Gösta Johansson\nEtableringsàr: 1953.\n\nFÖRENADE\nSUPERFOSFAT-FABRIKER, AB &amp; AB SVENSKA\nSALPETERVERKEN\n\nPnr 26120\n\nLandskrona, Storg 24. Tel\n0418-16040. Bankgiro 863-6649.\nPostgiro 170786-8. Tga Posfaten.\nTelex 72417 SUPER S\nVerksamhet: Tillverkar o säljer\nhandelsgödselmedel av olika slag\nsåsom superfosfat, N-, P-, NP-,\nPK- o NPK-gödselmedel\nFabriker: Landskrona, Norrköping,\nKöping, Kvarntorp\nVarunamn: Superfosfat, Super NPK,\nSuper PK, Superba, Tg-Växupp,\nUrea, Kalkammonsalpeter-Köping,\nKalksalpeter-Köping, NP-Köping,\nNPK-Köping\nAntal anställda: 1300\nÅrsomsättning: 320 000 000\nStyrelseordf: Riksdagsman Nils\nLarsson\n\nVerkst dir: Polke Mårtensson\nAdministrativ dir: Ake Tydén\nFörsäljningsdir: Rune Hedlund\nMarknadsdir: Nils Lagerholm\nPersonaldir. Orvar Jedeur-Palmgren\nTeknisk dir: Ingemar Wennberg\nEtableringsàr: 1931\nDotterbolag: Svenska Superfosfat\nFörsäljnings AB, NPK-Engrais\nS.A.T.\n\nFÖRENADE SÄNGKLÄDERS.\nFABRIKERNA AB\n\nPnr 600 05\n\nNorrköping 5, Almg 10. Box 5039.\nTel 011-13 26 62. Bankgiro 82-4333.\nPostgiro 383530. Tga Tebe\nVerksamhet: Tillverkar\nmadrassöverdrag\n\nAntal anställda: 35\nÅrsomsättning: 2 300 000\nAktiekapital: 350 000\nVerkst dir: Urban Caap\nEtableringsàr: 1901.\n\nFÖRENADE TAK AB\n\nPnr 25101\n\nHelsingborg 1, Fack. Landskronav 9.\nTel 042-12 05 50. Bankgiro\n500-4585. Postgiro 527700-9.\nTga Roofing\n\nVeiksamhet: Försäljning av\nbyggpapp, takfönster, takbrunnar m m.\nEntreprenadarbeten avseende\ntaktäckning o isolering\nVarunamn: Evrisol, Höganäs,\nMunksjö\n\nAvdelningskontor:\n\nGöteborg. Tel 031-22 21 55\nJönköping. Tel 036-1600 80\nSkellefteå. Tel 0910-185 15\nStockholm. Tel 08-23 68 30\nSundsvall. Tel 060-12 57 10\nÖrebro. Tel 019-13 0140\nAntal anställda: 550\nVerkst dir: Sven Bjelland\nEtableringsàr: 1968.\n\nFÖRENADE TVÄTT, AB\n\nPnr 16131\n\nBromma, Johannesfredsv 7. Tel\n08-25 2640. Bankgiro 16-0707.\nPostgiro 151656. Tga Afti\nVerksamhet: Utför vittvätt, kem\n\ntvätt o mattrenovering. Säljer o\nuthyr Hygiedo handduksskåp,\nHygi-alo pappersskåp o Zalpon\ntvålautomater. Dust Tex städmaterial.\nOveralluthyrning. Försäljning av\nDunicel dukar, servetter o gardiner.\nAntal anställda: 250\nÅrsomsättning: 10 500 000\nAktiekapital: 800 000\nVerkst dir: Bertil Backlund\nEtableringsàr 1936.\n\nPRESSENS BILD\n\nPnr 101 30\n\nStockholm 1, Rålamb sv 15-17. Box\n707. Tel arkiv 08-24 5 0 40. red\n13 14 26, telefoto 24 16 30.\nBankgiro 446-9896. Postgiro 59222-0.\nTga Bildpress. Telex 1649\nVeiksamhet: Bildbyrå\nAntal anställda: 30\nChef: Nils Wikner\nEtableringsår: 1935\nÄges av Dagens Nyheter AB.\n\nPRESSMETALL, AB\n\nPnr 731 01\n\nKöping 1, Box 1225. Tel\n0221-18030. Bankgiro 606-7300.\nPostgiro 175575-0. Tga Pressmetall\nVerksamhet: Varmsmidda ämnen av\nmässing o koppar, bearbetning av\nvarmsmidda ämnen, automats\nvärvning, ventiler för gasol\nAntal anställda: 70\nVerkst dir: R Ryström\nEtableringsår: 1948.\n\nPRESSO MEKANISKA\nAHLGREN &amp; CO AB\n\nPnr 560 10\n\nSkillingaryd, Industrig 3.\nTel0370-704 96. Bankgiro 14-1370. Postgiro\n462926-7\n\nVerksamhet: Tillverkar underläggs-\n\nbrickor typ: SRB, BRB, NB, S4B,\n4BB, dragpressning,\nkarosseri-brickor, pressade massartiklar\nAntal anställda: 35\nAktiekapital: 90 000\nVerkst dir: Henrik Ahlgren\nEtableringsår: 1950.\n\nBYG\n\nBYGGNADSKERAMIK AB\n\nPnr 431 02\n\nMölndal 2, Box 20 26. Göteborgsv\n119. Tel 031-16 03 94, 16 03 95.\nBankgiro 500-0882. Postgiro\n421435-9\n\nVerksamhet:\nPlattsättningsentre-prenader. Säljer keramiska plattor\nAntal anställda: 20\nÅrsomsättning: 1700 000\nAktiekapital: 25 000\nVerkst dir: Folke Wederbrand\nEtableringsår: 1962.\n\nCAR-PARK AB\n\nPnr 103 42\n\nStockholm 40, Box 40062. Sergelg\n19. Tel 08-14 18 60. Bankgiro\n579-7170. Postgiro 554830-0\nVerksamhet: Parkerings- o garage-\n\nrörelse\n\nAntal anställda: 62\nÅrsomsättning: 8 500 000\nAktiekapital: 1 000 000\nVerkst dir: Georg Szekely\nEtableringsår: 1944.\n\nCARPING, HANDELS &amp;\nFABRIKS AB HUGO\n\nPnr 232 00\n\nArlöv. Tel 040-43 15 70. Tga\nAr-lövhåce\n\nVerksamhet: Säljer\nmaskinförnödenheter i parti m m\nAktiekapital: 150 000\nFirmatecknare: Fru Frida Carping\nEtableringsår 1947.",
    "structured": {
        "1": {
            "company_name": "TRAFIK. & VÄGMÄRKEN AB",
            "pnr": "103 42",
            "address": "Stockholm 40, Sveav 24-26. Box 40075",
            "phone_number": "08-24 47 00",
            "bank_details": {
                "postgiro": "156633"
            },
            "activity": "Säljer vägmärken, parkeringsmätare o trafiksignaler",
            "employees": 20,
            "capital": 450000,
            "key_personnel": [
                {
                    "name": "Clas Otto Ruben",
                    "position": "Verkst din"
                }
            ],
            "establishment_year": 1932
        },
        "2": {
            "company_name": "TRAFIK.BORE, ÖMSESIDIGT, FÖRSÄKRINGSBOLAGET",
            "pnr": "18211",
            "address": "Danderyd X, Mysingsv 5. Box 50",
            "phone_number": "08-753 00 00",
            "bank_details": {
                "postgiro": "3444"
            },
            "activity": "Försäkringsrörelse",
            "employees": 455,
            "annual_turnover": 107000000,
            "key_personnel": [
                {
                    "name": "Jan Borgenhard",
                    "position": "Verkst dir"
                }
            ],
            "establishment_year": 1927
        },
        "3": {
            "company_name": "TRANELLSVAGNFABRIK EFTR",
            "pnr": "740 40",
            "address": "Heby, Box 104",
            "phone_number": "0224-30004",
            "bank_details": {
                "bankgiro": "81-0715",
                "postgiro": "98451"
            },
            "activity": "Utför plåtarbeten, smide o svetsning",
            "employees": 30,
            "annual_turnover": "1500000",
            "key_personnel": [
                {
                    "name": "Bertil Wallin",
                    "position": "Chef"
                }
            ],
            "establishment_year": 1917
        },
        "4": {
            "company_name": "TRANEMO CEMENTVARU-AKTIEBOLAG",
            "pnr": "510 80",
            "address": "Tranemo, Box 73",
            "phone_number": "0325-701 50",
            "bank_details": {
                "bankgiro": "553-1728",
                "postgiro": "81450-9"
            },
            "activity": "Tillverkning av förekommande betongvaror i standardutförande",
            "employees": 50,
            "annual_turnover": "4500000",
            "capital": 300000,
            "key_personnel": [
                {
                    "name": "Fru Anna Hermanson",
                    "position": "Styrelse"
                },
                {
                    "name": "frk Gunvor Hermanson",
                    "position": "Styrelse"
                },
                {
                    "name": "fru Eva Aronowitsch",
                    "position": "Styrelse"
                },
                {
                    "name": "Per Anders Hermanson",
                    "position": "Fabrikschef"
                }
            ],
            "establishment_year": 1923
        },
        "5": {
            "company_name": "STÄLLBERGSBOLAGEN",
            "pnr": "771 01",
            "address": "Ludvika 1, Box 84",
            "phone_number": "0240-138 50",
            "bank_details": {
                "bankgiro": "23-1226",
                "postgiro": "94183"
            },
            "activity": "Produktion o försäljning av manganhaltig järnmalm o mull",
            "employees": 250,
            "annual_turnover": "20000000",
            "capital": 11900000,
            "key_personnel": [
                {
                    "name": "Adv Hugo Stenbeck",
                    "position": "Styrelseordf"
                },
                {
                    "name": "disp Folke Franzén",
                    "position": "Verkst dir"
                }
            ],
            "establishment_year": 1881
        },
        "6": {
            "company_name": "STÄNGSELNÄT I RYDS-GÅRD, AB",
            "pnr": "270 12",
            "address": "Rydsgård",
            "phone_number": "0411-443 80",
            "bank_details": {
                "bankgiro": "86-3945",
                "postgiro": "143027"
            },
            "activity": "Tråddrageri, nätfabrik, dukväveri, spikfabrik, kättingfabrik, galvaniseringsverk",
            "employees": 170,
            "annual_turnover": "15000000",
            "capital": 1000000,
            "key_personnel": [
                {
                    "name": "Adv Henning Dahlin",
                    "position": "Styrelseordf"
                },
                {
                    "name": "Disp Olle Barchan",
                    "position": "Verkst dir"
                }
            ],
            "establishment_year": 1911
        }
    }
}