{
    "original": "GOMÈR &amp; ANDERSSON AB\n\nPnr 581 04\n\nLinköping 1, Sankt Larsg 31. Box\n405. Tel 013-12 93 80. Bankgiro\n346-9905. Postgiro 88973-3\nVerksamhet: Fasüghetsmäkleri,\nauktionsrörelse, boutredningar,\nvärderingar av fastigheter,\ninventarier mm\n\nAntal anställda: 16\nAktiekapital: 300 000\nVerkst dir: Nils Andersson\nEtableringsår: 1929.\n\nGOODYEAR GUMMI\nFABRIKS AB\n\nPnr 102 51\n\nStockholm 27, Karlav 115. Box\n27030. Tel 08-63 02 80. Bankgiro\n16-0246. Postgiro 4604. Telex\n10163. Tga Goodyear\nVerksamhet: Däck,\nregummerings-material, transportband,\nförpackningsfilm, industrigummi\nAntal anställda: 1500\n.Aktiekapital: 20 000 000\nVerkst dir: Lennart F Swedberg\nEtableringsår: 1926.\n\nGORDON AB, HÄNDELS- &amp;\nAGENTURFIRMA G\n\nPnr 172 22\n\nSundbyberg 1, Landsv 47. Box 56.\nTel 08-28 93 55. Bankgiro 56-7019.\nPostgiro 150535. Tga Gordonel\nVerksamhet: Etiketter, tape,\npris-märkningsmaskiner o skyltdockor\nAntal anställda: 16\n\nAktiekapital: 100 000\nVerkst din Karsten Bratt\nEtableringsår: 1951.\n\nGORDON, GUNNAR\n\nse Albrechtson-Hasse AB.\n\nGORVAK AB\n\nPnr 112 66\n\nStockholm, Essingetorget 42.\nTel 08-56 44 00, 56 22 88.\nBankgiro 72-4861. Postgiro 196196.\nTga Gorvak\n\nVerksamhet: Plastartiklar av\nsträngsprutad PVC såsom slang,\nrör, bult, band, byggnadsprofiler,\nfogband, tätningslister, krympslang,\narmerad slang samt\nel-isolations-material, tejp, plastspiral,\nskumplast. Tillverkning efter ritning\nVarunamn: Gorvaplast\nAntal anställda: 10\nVerkst dir: E Friström\nFörsäljning: Disp Nils Friström\nEtableringsår: 1944.\n\nGOTENIUS VARV och\nMEK VERKSTAD, AB\n\nPnr 417 07\n\nGöteborg H, Manufakturg 3. Tel\n031-2203 32, 22 85 32. Bankgiro\n42-0534. Postgiro 421774\nVerksamhet: Skeppsvarv för\nnybyggnader o reparationer\nAntal anställda: 20\nAktiekapital: 75 000\nVerkst dir: Vilhelm Gotenius\nEtableringsår: 1950.\n\nGOTHIA MASKIN\nAKTIEBOLAG\n\nPnr 243 00\n\nHöör, Fredsg 8. Box 19. Tel\n0413-22030. Bankgiro 271-3287.\nPostgiro 266384-7. Tga Maskingothia.\nTelex 32494\n\nVerksamhet: Tillverkar pumpar för\nsjöfart o industri\nVarunamn: Gothia\nAktiekapital: 600 000\nVerkst dir: Ing Allan Håkansson\nEtableringsår: 1916.\n\nGOTLAND, REDERI.\nAKTIEBOLAGET\n\nPnr 62101\n\nVisby 1, Hamng 1. Box 8. Tel\n0498-119 00. Bankgiro 833-3395.\nPostgiro 189388-2. Tga\nGotland-ship. Telex 4133\n\nVerksamhet: Rederirörelse.\nPassagerare- o godstrafik mellan Visby\no hamnar på fastlandet\nAntal anställda: 180\nÅrsomsättning: 25 000 000\nAktiekapital: 4 200 000\nStyrelse: Konsul Kjell Wiman(ordf),\nbankdir Bertil Odelfelt (v ordf),\nlantbr Yngve Ahlsten, dir Sven\nAxelsson, adv Gunnar Kjällman,\ndir Karl-Erik Kärnekull, skeppsred\nRobert Myrsten, bankdir Erik\nSjöberg\n\nVerkst dir: Erie D Nilsson\nKamrer: Jan Helleberg\nFartygsinsp: Per Modig\nEtableringsår: 1865.\n\nGOTLANDS ALLEHANDAS\nTRYCKERI AB\n\nPnr 62101\n\nVisby 1, Mellang 23. Box 99. Tel\n0498-190 80. Bankgiro 83-3355.\nPostgiro 189186-0\nVerksamhet: Tidningsutgivning\nmed civiltryckeri. Resebyrå\nAntal anställda: 45\nÅrsomsättning: 3 500 000\nAktiekapital: 100 000\nVerkst dir: Alex Medin\nChefred: Tor väld Lönnefalk\nEtableringsår: 1872.\n\nGOTLANDS FÖRENADE\nKALK-BROTT, AB\n\nPnr 620 34\n\nLärbro, Storugns. Tel 0498-27100.\nTga Gutekalksten\nVerksamhet: Kalkstensbrytning o\nfoderkalkstillverkning vid Storugns\nKalkbrott, Lärbro\nVarunamn: Bungekalk, Gotlandsör\nAntal anställda: 120\nÅrsomsättning: 12 000 000\nAktiekapital: 2 000 000\nVerkst dir: Nils Wiberg\nKamrer: Arthur Hallquist\nEtableringsår: 1955.\n\nJÄMTLANDS FOLKBANK\n\nPnr 83101\n\nÖstersund X, Box 65. Prästg 39.\nTel 063-173 90. Bankgiro 25-0001.\nPostgiro 5060-9. Tga Folkbanken\nVerksamhet: Bankrörelse\nAvdelningskontor: Frösön. Tel\n063-110 27\n\nFunäsdalen. Tel 0684-21172\nGäddede. Tel 0672-101 06\nKälarne. Tel 0696-400 20\nStockholm, Kungsg 31. Tel\n08-10 1377, 10 79 72, 113180\nStrömsund, Lövbergav 6. Tel\n0670-100 43, 10173\nSveg. Tel 0680-100 58\nYtterhogdal. Tel 0680-60017\nOdensala. Tel 063-265 50\nAntal anställda: 45\nBalansomslutning: 212 858 000\nAktiekapital: 6 000 000\nVerkst dir: Nils F Uddegård\nV verkst dir: Kamrer G Norlén\nEtableringsår: 1874.\n\nABBA FYRTORNET AB\n\nPnr 102 52\n\nStockholm 27, Box 27106. Malmv\n15. Tel 08-22 66 20. Bankgiro\n23-5103. Postgiro 2210-3. Tga\nAbba-food. Telex 1990? ABB ÄST S\nVerksamhet: Sill, fiskkonserver,\näven för export\nAntal anställda: 1000\nÅrsomsättning: 100 000 000\nAktiekapital: 8 000 000\nVerkst dir: Christian G Ameln\nEtableringsår: 1898.\n\nEKE\n\nEKBLAD &amp; REIMERS\nEFTR, AB\n\nPnr 701 02\n\nÖrebro 1, Box 12. Köpmang 9. Tel\n019-1192 20\n\nVerksamhet: Säljer järnvaror i\nparti\n\nAktiekapital: 300000\nVerkst dir: H Sjögren\nEtableringsår: 1949.\n\nBALLOGRAF BIC AB\n\nPnr 402 42 Gbg 12\nVästra Frölunda, Klangfärgsg 4-6.\nBox 12103, Gbg 12. Tel 031-29 2200.\nTga Ballograf.\nTelex 2349 BALLOGR S\nVerksamhet: Tillverkar kulpennor\no patroner för desamma\nVarunamn: Ballograf, Bic\n■Antal anställda: 200\nÅrsomsättning: 25 000000\nAktiekapital: 2 200 000\nVerkst dir: Bengt Johansson\nEtableringsår: 1945.\n\nDONSO TRÄL o VADBINDER|\n\nPnr 430 82\n\nDonsö, Hus nr 73 B. Tel\n031-77 0302, 77 0288. Bankgiro\n55-5128. Postgiro 185585\nVerksamhet: Fisktrålar,\nsnurre-vadar, silltrålar, trålwire\nAntal anställda: 5\nÅrsomsättning: 500 000\nÄgare o chefer: K P Lorentsson,\nL O Lorentsson\nEtableringsår: 1932.\n\nHÄLLER AB, JARL\n\nPnr 50105\n\nBorås 1, Box 275. Bryggareg 16-20.\nTel 033-127230. Bankgiro\n531-1618. Postgiro 255636-3\nVerksamhet: Tillverkar o säljer\ndamkonfektion\nAntal anställda: 50\nÅrsomsättning: 5 000000\nAktiekapital: 40 000\nVerkst dir: Jarl Häller\nEtableringsår: 1952.\n\nEHN, AB GUSTAV\n\nPnr 360 70\n\nAseda, Lillg 3. Tel 0474-103 68.\n109 68\n\nVerksamhet;\nByggnadsentreprenörer, schakt- o anläggningar\nAntal anställda: 25\nÅrsomsättning: 2 000 000\nVerkst dir. Gustav Ehn\nEtableringsår: 1968.\n\nROS\n\nRON DO RF AB,\nMASKINFIRMA C\n\nPnr 104 22\n\nStockholm 22, Kungsholms\nHamnplan 2. Pack. Tel 08-54 04 45.\nBankgiro 723-6573. Postgiro\n52675-6. Tga Maskinrondorf.\nTelex 19952\n\nVeiksamhet: Tillverkar rikt-,\nkap-o tråddragningsmaskiner\nAntal anstäUda: 8\nÅrsomsättning: 3 000 000\nÄgare o chef: Ing Conrad Solitair\nEtableringsàr 1909.\n\nRONEO VICKERS SVENSKA\nAB\n\nPnr 12109\n\nJohanneshov 9, Brunnbyv 15. Box\n9043. Tel 08-8 1 04 20. Bankgiro\n87-2860. Postgiro 407660. Tga\nRoneo-vickers\n\nVerksamhet: Försäljning av\ndupli-ceringsmaskiner o stenciler\nAntal anstäUda: 12\nÅrsomsättning: 2000 000\nAktiekapital: 5 000\nVerkst dir: Jan-Erik Bouchette\nEtableringsàr: 1967.\n\nRONI AB\n\nPnr 102 33\n\nStockholm 6, Gävleg 12 A. Box\n6194. Tel 08-33 92 31, 33 92 41.\nBankgiro 47-61169. Postgiro\n54725-7. Tga Ronisto\nTga Ronisto\n\nVeiksamhet: Tillverkar damväskor\no säljer lädervaror\nAntal anställda: 50\nÅrsomsättning: 3000 000\nAktiekapital: 50000\nVerkst dir Tryggve Lindberg\nEtableringsàr 1942.\n\nTUNIS AB, FABRIKEN\n\nPnr 33100\n\nVärnamo, Malmöv. Tel 0370-104 99,\n13606. Bankgiro 141-8284.\nPostgiro 144095-7\n\nVi utställer pä\nSWED-EXPO\n\nVerksamhet: Tillverkningsprogram:\nbandsågar, träsvarvar, borrmaskiner\nsamt maskiner för hobby o\nfritidsbruk. Specialitet: luckor för alla\nslag av värmepannor, egen\nbrättill-verkning. Legoarbeten, fräsning,\nborrning, slipning o svarvning\nÅrsomsättning: 3 500 000\nAktiekapital: 90 000\nVerkst dir: Fru Ingrid Nilsson\nEtableringsår: 1936\nOmbildat till aktiebolag 1949.\n\nTUNNELBANEREKLAM, AB\n\nPnr 111 27\n\nStockholm, Munkbrog 4. Tel 08-\n\n22 63 60. Bankgiro 333-7177.\nPostgiro 609515-2\n\nVerksamhet: Reklamförmedling i\ntunnelbanan\nAktiekapital: 300 000\nVerkst din Ernst Nilsson\nEtableringsår: 1952.",
    "structured": {
        "1": {
            "company_name": "GOMÈR & ANDERSSON AB",
            "pnr": "581 04",
            "address": "Linköping 1, Sankt Larsg 31. Box 405.",
            "phone_number": "013-12 93 80",
            "bank_details": {
                "bankgiro": "346-9905",
                "postgiro": "88973-3"
            },
            "activity": "Fasüghetsmäkleri, auktionsrörelse, boutredningar, värderingar av fastigheter, inventarier mm",
            "employees": 16,
            "capital": 300000,
            "key_personnel": [
                {
                    "name": "Nils Andersson",
                    "position": "Verkst dir"
                }
            ],
            "establishment_year": 1929
        },
        "2": {
            "company_name": "GOODYEAR GUMMI FABRIKS AB",
            "pnr": "102 51",
            "address": "Stockholm 27, Karlav 115. Box 27030",
            "phone_number": "08-63 02 80",
            "bank_details": {
                "bankgiro": "16-0246",
                "postgiro": "4604"
            },
            "activity": "Däck, regummerings-material, transportband, förpackningsfilm, industrigummi",
            "employees": 1500,
            "capital": 20000000,
            "key_personnel": [
                {
                    "name": "Lennart F Swedberg",
                    "position": "Verkst dir"
                }
            ],
            "establishment_year": 1926
        },
        "3": {
            "company_name": "GORDON AB, HÄNDELS- & AGENTURFIRMA G",
            "pnr": "172 22",
            "address": "Sundbyberg 1, Landsv 47. Box 56",
            "phone_number": "08-28 93 55",
            "bank_details": {
                "bankgiro": "56-7019",
                "postgiro": "150535"
            },
            "activity": "Etiketter, tape, pris-märkningsmaskiner o skyltdockor",
            "employees": 16,
            "capital": 100000,
            "key_personnel": [
                {
                    "name": "Karsten Bratt",
                    "position": "Verkst din"
                }
            ],
            "establishment_year": 1951
        },
        "4": {
            "company_name": "GORVAK AB",
            "pnr": "112 66",
            "address": "Stockholm, Essingetorget 42",
            "phone_number": "08-56 44 00, 56 22 88",
            "bank_details": {
                "bankgiro": "72-4861",
                "postgiro": "196196"
            },
            "activity": "Plastartiklar av strängsprutad PVC såsom slang, rör, bult, band, byggnadsprofiler, fogband, tätningslister, krympslang, armerad slang samt el-isolations-material, tejp, plastspiral, skumplast. Tillverkning efter ritning",
            "employees": 10,
            "establishment_year": 1944
        },
        "5": {
            "company_name": "GOTENIUS VARV och MEK VERKSTAD, AB",
            "pnr": "417 07",
            "address": "Göteborg H, Manufakturg 3",
            "phone_number": "031-2203 32, 22 85 32",
            "bank_details": {
                "bankgiro": "42-0534",
                "postgiro": "421774"
            },
            "activity": "Skeppsvarv för nybyggnader o reparationer",
            "employees": 20,
            "capital": 75000,
            "key_personnel": [
                {
                    "name": "Vilhelm Gotenius",
                    "position": "Verkst dir"
                }
            ],
            "establishment_year": 1950
        },
        "6": {
            "company_name": "GOTHIA MASKIN AKTIEBOLAG",
            "pnr": "243 00",
            "address": "Höör, Fredsg 8. Box 19",
            "phone_number": "0413-22030",
            "bank_details": {
                "bankgiro": "271-3287",
                "postgiro": "266384-7"
            },
            "activity": "Tillverkar pumpar för sjöfart o industri",
            "capital": 600000,
            "key_personnel": [
                {
                    "name": "Ing Allan Håkansson",
                    "position": "Verkst dir"
                }
            ],
            "establishment_year": 1916
        },
        "7": {
            "company_name": "GOTLAND, REDERI. AKTIEBOLAGET",
            "pnr": "62101",
            "address": "Visby 1, Hamng 1. Box 8",
            "phone_number": "0498-119 00",
            "bank_details": {
                "bankgiro": "833-3395",
                "postgiro": "189388-2"
            },
            "activity": "Rederirörelse. Passagerare- o godstrafik mellan Visby o hamnar på fastlandet",
            "employees": 180,
            "annual_turnover": 25000000,
            "capital": 4200000,
            "key_personnel": [
                {
                    "name": "Erie D Nilsson",
                    "position": "Verkst dir"
                },
                {
                    "name": "Jan Helleberg",
                    "position": "Kamrer"
                },
                {
                    "name": "Per Modig",
                    "position": "Fartygsinsp"
                }
            ],
            "establishment_year": 1865
        },
        "8": {
            "company_name": "GOTLANDS ALLEHANDAS TRYCKERI AB",
            "pnr": "62101",
            "address": "Visby 1, Mellang 23. Box 99",
            "phone_number": "0498-190 80",
            "bank_details": {
                "bankgiro": "83-3355",
                "postgiro": "189186-0"
            },
            "activity": "Tidningsutgivning med civiltryckeri. Resebyrå",
            "employees": 45,
            "annual_turnover": 3500000,
            "capital": 100000,
            "key_personnel": [
                {
                    "name": "Alex Medin",
                    "position": "Verkst dir"
                },
                {
                    "name": "Tor väld Lönnefalk",
                    "position": "Chefred"
                }
            ],
            "establishment_year": 1872
        },
        "9": {
            "company_name": "GOTLANDS FÖRENADE KALK-BROTT, AB",
            "pnr": "620 34",
            "address": "Lärbro, Storugns",
            "phone_number": "0498-27100",
            "activity": "Kalkstensbrytning o foderkalkstillverkning vid Storugns Kalkbrott, Lärbro",
            "employees": 120,
            "annual_turnover": 12000000,
            "capital": 2000000,
            "key_personnel": [
                {
                    "name": "Nils Wiberg",
                    "position": "Verkst dir"
                },
                {
                    "name": "Arthur Hallquist",
                    "position": "Kamrer"
                }
            ],
            "establishment_year": 1955
        },
        "10": {
            "company_name": "JÄMTLANDS FOLKBANK",
            "pnr": "83101",
            "address": "Östersund X, Box 65. Prästg 39",
            "phone_number": "063-173 90",
            "bank_details": {
                "bankgiro": "25-0001",
                "postgiro": "5060-9"
            },
            "activity": "Bankrörelse",
            "employees": 45,
            "annual_turnover": 212858000,
            "capital": 6000000,
            "key_personnel": [
                {
                    "name": "Nils F Uddegård",
                    "position": "Verkst dir"
                },
                {
                    "name": "Kamrer G Norlén",
                    "position": "V verkst dir"
                }
            ],
            "establishment_year": 1874
        },
        "11": {
            "company_name": "ABBA FYRTORNET AB",
            "pnr": "102 52",
            "address": "Stockholm 27, Box 27106. Malmv 15",
            "phone_number": "08-22 66 20",
            "bank_details": {
                "bankgiro": "23-5103",
                "postgiro": "2210-3"
            },
            "activity": "Sill, fiskkonserver, även för export",
            "employees": 1000,
            "annual_turnover": 100000000,
            "capital": 8000000,
            "key_personnel": [
                {
                    "name": "Christian G Ameln",
                    "position": "Verkst dir"
                }
            ],
            "establishment_year": 1898
        },
        "12": {
            "company_name": "EKBLAD & REIMERS EFTR, AB",
            "pnr": "701 02",
            "address": "Örebro 1, Box 12. Köpmang 9",
            "phone_number": "019-1192 20",
            "activity": "Säljer järnvaror i parti",
            "capital": 300000,
            "key_personnel": [
                {
                    "name": "H Sjögren",
                    "position": "Verkst dir"
                }
            ],
            "establishment_year": 1949
        },
        "13": {
            "company_name": "BALLOGRAF BIC AB",
            "pnr": "402 42 Gbg 12",
            "address": "Västra Frölunda, Klangfärgsg 4-6. Box 12103, Gbg 12",
            "phone_number": "031-29 2200",
            "activity": "Tillverkar kulpennor o patroner för desamma",
            "employees": 200,
            "annual_turnover": 25000000,
            "capital": 2200000,
            "key_personnel": [
                {
                    "name": "Bengt Johansson",
                    "position": "Verkst dir"
                }
            ],
            "establishment_year": 1945
        },
        "14": {
            "company_name": "DONSO TRÄL o VADBINDER",
            "pnr": "430 82",
            "address": "Donsö, Hus nr 73 B",
            "phone_number": "031-77 0302, 77 0288",
            "bank_details": {
                "bankgiro": "55-5128",
                "postgiro": "185585"
            },
            "activity": "Fisktrålar, snurre-vadar, silltrålar, trålwire",
            "employees": 5,
            "annual_turnover": 500000,
            "key_personnel": [
                {
                    "name": "K P Lorentsson",
                    "position": "Ägare o chefer"
                },
                {
                    "name": "L O Lorentsson",
                    "position": "Ägare o chefer"
                }
            ],
            "establishment_year": 1932
        },
        "15": {
            "company_name": "HÄLLER AB, JARL",
            "pnr": "50105",
            "address": "Borås 1, Box 275. Bryggareg 16-20",
            "phone_number": "033-127230",
            "bank_details": {
                "bankgiro": "531-1618",
                "postgiro": "255636-3"
            },
            "activity": "Tillverkar o säljer damkonfektion",
            "employees": 50,
            "annual_turnover": 5000000,
            "capital": 40000,
            "key_personnel": [
                {
                    "name": "Jarl Häller",
                    "position": "Verkst dir"
                }
            ],
            "establishment_year": 1952
        },
        "16": {
            "company_name": "EHN, AB GUSTAV",
            "pnr": "360 70",
            "address": "Aseda, Lillg 3",
            "phone_number": "0474-103 68",
            "bank_details": {
                "bankgiro": "55-5128",
                "postgiro": "185585"
            },
            "activity": "Byggnadsentreprenörer, schakt- o anläggningar",
            "employees": 25,
            "annual_turnover": 2000000,
            "key_personnel": [
                {
                    "name": "Gustav Ehn",
                    "position": "Verkst dir"
                }
            ],
            "establishment_year": 1968
        },
        "17": {
            "company_name": "RON DO RF AB, MASKINFIRMA C",
            "pnr": "104 22",
            "address": "Stockholm 22, Kungsholms Hamnplan 2. Pack",
            "phone_number": "08-54 04 45",
            "bank_details": {
                "bankgiro": "723-6573",
                "postgiro": "52675-6"
            },
            "activity": "Tillverkar rikt-, kap-o tråddragningsmaskiner",
            "employees": 8,
            "annual_turnover": 3000000,
            "key_personnel": [
                {
                    "name": "Ing Conrad Solitair",
                    "position": "Ägare o chef"
                }
            ],
            "establishment_year": 1909
        },
        "18": {
            "company_name": "RONEO VICKERS SVENSKA AB",
            "pnr": "12109",
            "address": "Johanneshov 9, Brunnbyv 15. Box 9043",
            "phone_number": "08-8 1 04 20",
            "bank_details": {
                "bankgiro": "87-2860",
                "postgiro": "407660"
            },
            "activity": "Försäljning av dupliceringsmaskiner o stenciler",
            "employees": 12,
            "annual_turnover": 2000000,
            "capital": 5000,
            "key_personnel": [
                {
                    "name": "Jan-Erik Bouchette",
                    "position": "Verkst dir"
                }
            ],
            "establishment_year": 1967
        },
        "19": {
            "company_name": "RONI AB",
            "pnr": "102 33",
            "address": "Stockholm 6, Gävleg 12 A. Box 6194",
            "phone_number": "08-33 92 31, 33 92 41",
            "bank_details": {
                "bankgiro": "47-61169",
                "postgiro": "54725-7"
            },
            "activity": "Tillverkar damväskor o säljer lädervaror",
            "employees": 50,
            "annual_turnover": 3000000,
            "capital": 50000,
            "key_personnel": [
                {
                    "name": "Tryggve Lindberg",
                    "position": "Verkst dir"
                }
            ],
            "establishment_year": 1942
        },
        "20": {
            "company_name": "TUNIS AB, FABRIKEN",
            "pnr": "33100",
            "address": "Värnamo, Malmöv",
            "phone_number": "0370-104 99, 13606",
            "bank_details": {
                "bankgiro": "141-8284",
                "postgiro": "144095-7"
            },
            "activity": "Tillverkningsprogram: bandsågar, träsvarvar, borrmaskiner samt maskiner för hobby o fritidsbruk. Specialitet: luckor för alla slag av värmepannor, egen brät-till-verkning. Legoarbeten, fräsning, borrning, slipning o svarvning",
            "annual_turnover": 3500000,
            "capital": 90000,
            "key_personnel": [
                {
                    "name": "Fru Ingrid Nilsson",
                    "position": "Verkst dir"
                }
            ],
            "establishment_year": 1936
        },
        "21": {
            "company_name": "TUNNELBANEREKLAM, AB",
            "pnr": "111 27",
            "address": "Stockholm, Munkbrog 4",
            "phone_number": "08-22 63 60",
            "bank_details": {
                "bankgiro": "333-7177",
                "postgiro": "609515-2"
            },
            "activity": "Reklamförmedling i tunnelbanan",
            "capital": 300000,
            "key_personnel": [
                {
                    "name": "Ernst Nilsson",
                    "position": "Verkst dir"
                }
            ],
            "establishment_year": 1952
        }
    }
}