{
    "original": "AUTO-PRODUCTS AB\n\nPnr 100 31\n\nStockholm 21, Sankt Eriksg 106.\nFack. Tel 08-34 02 30. Bankgiro\n575-7067. Postgiro 254557-2.\nTga AEScandinav. Telex 1829\nVerksamhet: Säljer motor- o\nchassidelar\n\nVarunamn: Borg &amp; Beck, Glacier,\nHepolite, Lockheed, Purolator,\nRockford\n\nAntal anställda: 100\n\nAktiekapital: 40 000\n\nStyrelse: Adv Arthur Boström, dir\n\nIngemar Jörnberger\n\nVerkst dir: Ingemar Jörnberger\n\nEtableringsår: 1946\n\nSe även A E Scandinavla AB.\n\nAUTOROPA AB\n\nPnr 21124\n\nMalmö, Kräng 1. Tel 040-93 67 60.\nBankgiro 874-7362. Postgiro\n39411-4. Tga Autoropa. Telex 32460\nVerksamhet: Importerar o säljer\nperson- o lastbilar\nAntal anställda: 50\nÅrsomsättning: 10 000 000\nAktiekapital: 265 000\nVerkst dir: Kjell Thulin\nEtableringsår: 1934.\n\nHED MURNINGS AB, ERIK\n\nPnr 14148\n\nHuddinge, Vikingav 13. Tel\n08-7575250, 774 38 28. Bankgiro\n481-1519. Postgiro 72385-8\nVerksamhet: Utför murnings- o\nputsningsarbeten\nAntal anställda: 35\nÅrsomsättning: 3 500 000\nAktiekapital: 10 000\nFinnatecknare: Erik Hed, Jan-Erik\nHed\n\nEtableringsår: 1964.\n\nHAMDAHL &amp; CO, AB\n\nPnr 400 60\n\nGöteborg 6, Hökeg 12. Box 6054.\nTel 031-19 24 50, 19 24 51.\nBankgiro 42-0074. Postgiro 25562. Tga\nHamdahlco\n\nVerksamhet: Laxrökeri,\ntarmsor-teringsanstalt o grosshandel\nAntal anställda: 17\nÅrsomsättning: 6 000 000\nAktiekapital: 90 000\nVerkst dir: Ivar Hamdahl\nEtableringsår: 1928.\n\nTÖRNQVIST AB. FRANS\n\nPnr 261 22\n\nLandskrona 1, Gasverksg. Box\n129. Tel 0418-16585. Bankgiro\n660-1066. Postgiro 14544-1\nVerksamhet: Säljer järn, balk, plåt\no byggnadsmateriel\nAktiekapital: 200 000\nVerkst dir: Bo Christiansson\nEtableringsår: 1950.\n\nTINGSTA AKTIEBOLAG\n\nPnr 361 00\n\nEmmaboda, Box 105. Tel\n0471-108 20. Bankgiro 854-9818.\nPostgiro 103020-4. Tga Tingsta\nVerksamhet: Tillverkar o säljer\nheltäckande mattor\nAntal anställda: 21\nÅrsomsättning: 7 500 000\nAktiekapital: 300 000\nVerkst dir: Ejne Gunhamn.\n\nTINGSTAD, HAMN.\nAKTIEBOLAGET\n\nPnr 41114\n\nGöteborg, S Hamng 23. Tel\n031-13 4259, 13 6649. Bankgiro\n42-0187. Postgiro 42497. Telex 2548.\nTga Tingshamn\n\nVerksamhet: Speditionsrörelse o\nmagasinering\nAntal anställda: 17\nAktiekapital: 460 000\nVerkst dir: B Helidén\nEtableringsår: 1924.\n\nLINDMAN &amp; CO AB\n\nPnr 182 33\n\nDanderyd, Kevingeringen 3. Tel\n08-755 30 40, 755 10 20. Bankgiro\n48-2402. Postgiro 53284. Telex\n17274. Tga Lindmanimport\nVerksamhet: Säljer djupfrysta\nlivsmedel samt konserver, viner o\nspirituösa\n\nÅrsomsättning: 4 000 000\nAktiekapital: 5 000\nVerkst dir: Yngve Lindman\nEtableringsår: 1932.\n\nLINDMARKS MASKINAFFÄR,\nAB\n\nPnr 96100\n\nBoden, Brog 8. Tel 0921-136 50.\nTga Lindmarks Maskin\nVerksamhet: Säljer maskiner, mar\nskinförnödenheter o verktyg\nFilial: Luleå, Spantg 16. Tel\n0920-10165\n\nÅrsomsättning: 10 000 000\nAktiekapital: 96 000\nVerkst dir: sten Brand\nEtableringsår: 1903.\n\nhemefa, fabriks ab\n\nPnr 263 00\n\nHöganäs, Metallg 4. Tel 042-\n\n400 59. Bankgiro 654-5826. Postgiro\n\n324934^9\n\nVerksamhet: Utför pressgjutning.\nTillverkar identitetsbrickor för\nmänniskor o djur\nAntal anställda: 10\nÅrsomsättning: 1000 000\nChef: Ing E Hellberg\nEtableringsår: 1946.\n\nEXQ\n\nVerksamhet: Tillverkar o säljer\nplastklädda järntrådsartiklar såsom\ndisk- o badrumsartiklar\nVarunamn: Sonja-Serien\nÅrsomsättning: 800 000\nVerkst dir: Bengt Julin\nDisp: G-A Ekehammar\nEtableringsår: 1946.\n\nFINTLINGS, AB\n\nPnr 113 54\n\nStockholm, Roslagsg 33. Tel\n08-15 19 50. Bankgiro 57-2230.\nPost-giro 2744. Tga Nickelfint\nVerksamhet: Kemisk o elektrolytisk\nytbehandling av metaller\nAntal anställda: 60\nÅrsomsättning: 4 200 000\nAktiekapital: 400 000\nVerkst dir: Per Ernmark\nEtableringsår: 1893.\n\nFINVERKO METALL. &amp;\nMEK VERKSTAD\n\nPnr 252 42\n\nHelsingborg, Grubbag 28. Tel\n042-1183 68, 1812 70. Bankgiro\n652-8657. Postgiro 441870-3\nVerksamhet: Verktygs- o\nformtillverkning, precisionsarbete,\nkonstruktionsuppdrag, kopierfräsning,\nprofilslipning o jiggslipning\nÄgare o chef: Carl Nilsson\nEtableringsår: 1953.\n\nVOLVO FLYGMOTOR AB\n\nPnr 46101\n\nTrollhättan 1, Pack. Tel\n0520-301 00. Tga Flygmotor. Telex 42040\nVerksamhet: Tillverkning av\njetmotorer o hydraulpumpar\nAntal anställda: 2 400\nÅrsomsättning: 178 000 000\nAktiekapital: 36 000 000\nStyrelse: Dir Gunnar Engellau, dir\nInge Löjdquist, dir Per Ekström,\ndir Svante Simonsson, dir Ebbe\nSvensson\n\nVerkst dir. Inge Löjdquist\nV verkst dir.n Ekonomidir Bengt\nEriksson, tekn dir Gustaf\nGud-mundson\n\nProd-chef: Dir Arne Hallin\nInköpschef: Claes Öberg\nFörsäljningschefer:\n\nFlygprodukter: Overing Arne\nCarlsson\n\nHydraulik: Civiling Sven Schriwer\nEtableringsår. 1930.\n\nVOLVO, AB\nOLOFSTROMS-VERKEN\n\nPnr 293 00\n\nOlofström. Tel 0454-413 00.\nBankgiro 151-6699. Postgiro 7841-0.\nTga Olofström. Karlshamn.\nTelex 4565\n\nOLOFSTRÖM\n\nVerksamhet: Tillverkar bilkarosser\no andra pressade o svetsade\nplåtdetaljer till person- o lastbilar,\nbussar o traktorer. Tillverkar\nkylare o bilvärmare, press- o\nklippverktyg, fixturer o specialmaskiner för\nsvetsning o hopsättning\nAntal anställda: 5 000\nÅrsomsättning: 400 000 000\nPlatschef: Bertil Axler\nTekn dir: Lars Lindblad\nMaterialchef: Johan Widerstrand\nFörsäljn o inköp: Kjell Claesson\nEkonomidir: Gunnar Lindmar\nEtableringsår: 1887.",
    "structured": {
        "1": {
            "company_name": "AUTO-PRODUCTS AB",
            "pnr": "100 31",
            "address": "Stockholm 21, Sankt Eriksg 106",
            "phone_number": "08-34 02 30",
            "bank_details": {
                "bankgiro": "575-7067",
                "postgiro": "254557-2"
            },
            "activity": "Säljer motor- o chassidelar",
            "employees": 100,
            "capital": 40000,
            "key_personnel": [
                {
                    "name": "Adv Arthur Boström",
                    "position": "Styrelse"
                },
                {
                    "name": "Ingemar Jörnberger",
                    "position": "Styrelse, Verkst dir"
                }
            ],
            "establishment_year": 1946
        },
        "2": {
            "company_name": "AUTOROPA AB",
            "pnr": "21124",
            "address": "Malmö, Kräng 1",
            "phone_number": "040-93 67 60",
            "bank_details": {
                "bankgiro": "874-7362",
                "postgiro": "39411-4"
            },
            "activity": "Importerar o säljer person- o lastbilar",
            "employees": 50,
            "annual_turnover": 10000000,
            "capital": 265000,
            "key_personnel": [
                {
                    "name": "Kjell Thulin",
                    "position": "Verkst dir"
                }
            ],
            "establishment_year": 1934
        },
        "3": {
            "company_name": "HED MURNINGS AB, ERIK",
            "pnr": "14148",
            "address": "Huddinge, Vikingav 13",
            "phone_number": "08-7575250, 774 38 28",
            "bank_details": {
                "bankgiro": "481-1519",
                "postgiro": "72385-8"
            },
            "activity": "Utför murnings- o putsningsarbeten",
            "employees": 35,
            "annual_turnover": 3500000,
            "capital": 10000,
            "key_personnel": [
                {
                    "name": "Erik Hed",
                    "position": "Finnatecknare"
                },
                {
                    "name": "Jan-Erik Hed",
                    "position": "Finnatecknare"
                }
            ],
            "establishment_year": 1964
        },
        "4": {
            "company_name": "HAMDAHL & CO, AB",
            "pnr": "400 60",
            "address": "Göteborg 6, Hökeg 12, Box 6054",
            "phone_number": "031-19 24 50, 19 24 51",
            "bank_details": {
                "bankgiro": "42-0074",
                "postgiro": "25562"
            },
            "activity": "Laxrökeri, tarmsor-teringsanstalt o grosshandel",
            "employees": 17,
            "annual_turnover": 6000000,
            "capital": 90000,
            "key_personnel": [
                {
                    "name": "Ivar Hamdahl",
                    "position": "Verkst dir"
                }
            ],
            "establishment_year": 1928
        },
        "5": {
            "company_name": "TÖRNQVIST AB. FRANS",
            "pnr": "261 22",
            "address": "Landskrona 1, Gasverksg. Box 129",
            "phone_number": "0418-16585",
            "bank_details": {
                "bankgiro": "660-1066",
                "postgiro": "14544-1"
            },
            "activity": "Säljer järn, balk, plåt o byggnadsmateriel",
            "capital": 200000,
            "key_personnel": [
                {
                    "name": "Bo Christiansson",
                    "position": "Verkst dir"
                }
            ],
            "establishment_year": 1950
        },
        "6": {
            "company_name": "TINGSTA AKTIEBOLAG",
            "pnr": "361 00",
            "address": "Emmaboda, Box 105",
            "phone_number": "0471-108 20",
            "bank_details": {
                "bankgiro": "854-9818",
                "postgiro": "103020-4"
            },
            "activity": "Tillverkar o säljer heltäckande mattor",
            "employees": 21,
            "annual_turnover": 7500000,
            "capital": 300000,
            "key_personnel": [
                {
                    "name": "Ejne Gunhamn",
                    "position": "Verkst dir"
                }
            ],
            "establishment_year": 0
        },
        "7": {
            "company_name": "TINGSTAD, HAMN. AKTIEBOLAGET",
            "pnr": "41114",
            "address": "Göteborg, S Hamng 23",
            "phone_number": "031-13 4259, 13 6649",
            "bank_details": {
                "bankgiro": "42-0187",
                "postgiro": "42497"
            },
            "activity": "Speditionsrörelse o magasinering",
            "employees": 17,
            "capital": 460000,
            "key_personnel": [
                {
                    "name": "B Helidén",
                    "position": "Verkst dir"
                }
            ],
            "establishment_year": 1924
        },
        "8": {
            "company_name": "LINDMAN & CO AB",
            "pnr": "182 33",
            "address": "Danderyd, Kevingeringen 3",
            "phone_number": "08-755 30 40, 755 10 20",
            "bank_details": {
                "bankgiro": "48-2402",
                "postgiro": "53284"
            },
            "activity": "Säljer djupfrysta livsmedel samt konserver, viner o spirituösa",
            "annual_turnover": 4000000,
            "capital": 5000,
            "key_personnel": [
                {
                    "name": "Yngve Lindman",
                    "position": "Verkst dir"
                }
            ],
            "establishment_year": 1932
        },
        "9": {
            "company_name": "LINDMARKS MASKINAFFÄR, AB",
            "pnr": "96100",
            "address": "Boden, Brog 8",
            "phone_number": "0921-136 50",
            "activity": "Säljer maskiner, mar skinförnödenheter o verktyg",
            "annual_turnover": 10000000,
            "capital": 96000,
            "key_personnel": [
                {
                    "name": "Sten Brand",
                    "position": "Verkst dir"
                }
            ],
            "establishment_year": 1903
        },
        "10": {
            "company_name": "MEFA, FABRIKS AB",
            "pnr": "263 00",
            "address": "Höganäs, Metallg 4",
            "phone_number": "042-400 59",
            "bank_details": {
                "bankgiro": "654-5826",
                "postgiro": "324934^9"
            },
            "activity": "Utför pressgjutning. Tillverkar identitetsbrickor för människor o djur",
            "employees": 10,
            "annual_turnover": 1000000,
            "key_personnel": [
                {
                    "name": "Ing E Hellberg",
                    "position": "Chef"
                }
            ],
            "establishment_year": 1946
        },
        "11": {
            "company_name": "EXQ",
            "activity": "Tillverkar o säljer plastklädda järntrådsartiklar såsom disk- o badrumsartiklar",
            "annual_turnover": 800000,
            "key_personnel": [
                {
                    "name": "Bengt Julin",
                    "position": "Verkst dir"
                },
                {
                    "name": "G-A Ekehammar",
                    "position": "Disp"
                }
            ],
            "establishment_year": 1946
        },
        "12": {
            "company_name": "FINTLINGS, AB",
            "pnr": "113 54",
            "address": "Stockholm, Roslagsg 33",
            "phone_number": "08-15 19 50",
            "bank_details": {
                "bankgiro": "57-2230",
                "postgiro": "2744"
            },
            "activity": "Kemisk o elektrolytisk ytbehandling av metaller",
            "employees": 60,
            "annual_turnover": 4200000,
            "capital": 400000,
            "key_personnel": [
                {
                    "name": "Per Ernmark",
                    "position": "Verkst dir"
                }
            ],
            "establishment_year": 1893
        },
        "13": {
            "company_name": "FINVERKO METALL. & MEK VERKSTAD",
            "pnr": "252 42",
            "address": "Helsingborg, Grubbag 28",
            "phone_number": "042-1183 68, 1812 70",
            "bank_details": {
                "bankgiro": "652-8657",
                "postgiro": "441870-3"
            },
            "activity": "Verktygs- o formtillverkning, precisionsarbete, konstruktionsuppdrag, kopierfräsning, profilslipning o jiggslipning",
            "key_personnel": [
                {
                    "name": "Carl Nilsson",
                    "position": "Ägare o chef"
                }
            ],
            "establishment_year": 1953
        },
        "14": {
            "company_name": "VOLVO FLYGMOTOR AB",
            "pnr": "46101",
            "address": "Trollhättan 1, Pack",
            "phone_number": "0520-301 00",
            "bank_details": {
                "bankgiro": "N/A",
                "postgiro": "N/A"
            },
            "activity": "Tillverkning av jetmotorer o hydraulpumpar",
            "employees": 2400,
            "annual_turnover": 178000000,
            "capital": 36000000,
            "key_personnel": [
                {
                    "name": "Gunnar Engellau",
                    "position": "Styrelse"
                },
                {
                    "name": "Inge Löjdquist",
                    "position": "Styrelse, Verkst dir"
                },
                {
                    "name": "Per Ekström",
                    "position": "Styrelse"
                },
                {
                    "name": "Svante Simonsson",
                    "position": "Styrelse"
                },
                {
                    "name": "Ebbe Svensson",
                    "position": "Styrelse"
                },
                {
                    "name": "Arne Hallin",
                    "position": "Prod-chef"
                },
                {
                    "name": "Claes Öberg",
                    "position": "Inköpschef"
                }
            ],
            "establishment_year": 1930
        },
        "15": {
            "company_name": "VOLVO, AB OLOFSTROMS-VERKEN",
            "pnr": "293 00",
            "address": "Olofström",
            "phone_number": "0454-413 00",
            "bank_details": {
                "bankgiro": "151-6699",
                "postgiro": "7841-0"
            },
            "activity": "Tillverkar bilkarosser o andra pressade o svetsade plåtdetaljer till person- o lastbilar, bussar o traktorer. Tillverkar kylare o bilvärmare, press- o klippverktyg, fixturer o specialmaskiner för svetsning o hopsättning",
            "employees": 5000,
            "annual_turnover": 400000000,
            "key_personnel": [
                {
                    "name": "Bertil Axler",
                    "position": "Platschef"
                },
                {
                    "name": "Lars Lindblad",
                    "position": "Tekn dir"
                },
                {
                    "name": "Johan Widerstrand",
                    "position": "Materialchef"
                },
                {
                    "name": "Kjell Claesson",
                    "position": "Ekonomidir"
                }
            ],
            "establishment_year": 1887
        }
    }
}