{
    "original": "ÖST\n\nOSTLUND, BRÖDERNA\n\nPnr 68015\n\nBäckalund, Box 240. Tel\n0565-200 16. Bankgiro 11-3855. Postgiro\n285558\n\nVerksamhet: Entreprenadfirma för\nvatten- o\navloppsanläggningar,brobyggnader, brunnsborrning m m\nChefer: E L Ostlund. P A Ostlund.\nN G Ostlund. R E Ostlund\nEtableringsår: 1944.\n\nUTTERSTRDM MASKIN AB, A\n\nPnr 12164\n\nJohanneshov, Vättersv 39. Tel\n08-4806 12, 4806 13. Bankgiro\n295-1416. Postgiro 550167-1. Tga\nUmabon\n\nVerksamhet Verktygsmaskiner o\nverktyg till verkstadsindustrin\nAntal anställda: 10\nÅrsomsättning: 3 000 000\nAktiekapital: 100 000\nVerkst dir: Arne Utterström\nEtableringsår: 1955.\n\nRISÄNGS TRIKÄVÄVERI\n\nPnr 51100\n\nKinna. Tel 0320-10133. Bankgiro\n434-7480. Postgiro 125403-6\nVerksamhet: Tillverkar\nraschel-vävda artiklar\nChef: Fabr Einar Rudhner.\n\nRISÄNGSVERKEN, KB\n\nPnr 600 06\n\nNorrköping 6, Box 6055. Exportg\n26. Tel 011-100130. Bankgiro\n786-4176. Postgiro 683880\nVerksamhet: Tillverkar tryckkärl,\ntraverser, maskinkonstruktioner,\nbalkkonstruktioner, elevatorer,\nskraptransportörer,\nremtransportörer, plåtfickor, matarvattentankar,\nkondensatorer även i syrafast\nmaterial m m. Plåt- o balkarbeten,\narborrning, svarvning, fräsning,\nborrning o montering.\nLicenssvetsning enl pannsvetsnormerna i\nrostfritt material\nAntal anställda: 80\nÅrsomsättning: 4 500 000\nVerkst dir: Charles Andersson\nKamrer: Töre Nordström\nVerkstadschef: Ingvar Aldvén\nVerkstadsingenjör Per-Gustaf Berg\nEtableringsår. 1955\nOmbildat till KB 1966.\n\nRITPRODUKTER, AB\n\nPnr 171 20\n\nSolna 1, Vretenv 4 A. Fack. Tel\n08-28 1750, 2176 99. Bankgiro\n191-5966. Postgiro 177580-8. Tga\nReprograph\n\nVerksamhet: Säljer ljuskopierings-,\nrit- o mm-rutad polyesterfilm samt\ntryckta ritningsblanketter\nFörsäljningskontor: 11160\nStockholm, Kammakareg 46. Tel\n08-2176 99\n\nStyrelse: Fru Ingrid Wallin (ordf),\ndir Hans B Pettersson, dir Lars B\nPettersson\n\nVerkst dir. Lars B Pettersson\nDisp: Sven Wetterling\nEtableringsår: 1964.\n\nKJELLSTROM &amp; PERSSON, AB\n\nPnr 252 20\n\nHelsingborg, N Storg 8. Tel\n042-110073, 112073. Bankgiro\n863-9585. Postgiro 13330-6\nVerksamhet: Säljer glas o porslin\nAktiekapital: 240 000\nVerkst dir: Ake Jönsson\nEtableringsår: 1871.\n\nTIELMANS PLASTINDUSTRI AB\n\nPnr 582 37\n\nLinköping. Barhällsg 13. Tel\n013-13 23 00, 13 45 23. Bankgiro\n608-0295. Postgiro 263030-9\nVerksamhet: Anslagsramar, pluggar\ntill pappersrullar, rörpluggar,\nam-pullaskar, färgrör o garnspolar för\ntextilindustrin. Legotillverkning\nAntal anställda: 9\nÅrsomsättning: 925 000\nAktiekapital : 20 000\nVerkst dir: stig Tielman\nEtableringsår: 1948\nOmbildat till aktiebolag 1966.\n\nTIELMAN, B\n\nPnr 581 03\n\nLidköping l.Ostgötag 62.Box 350.\nTel 013-12 97 30. Bankgiro60-7976.\nPostgiro 72702. Tga Betielman\nVerksamhet: Tillverkar\nengångsartiklar\n\nVerkst din Bertil Tielman\nEtableringsån 1930.\n\nANDERSSON I KINNA AB, IVAR\n\nPnr 51101\n\nKinna 1, Box 98. Särla. Tel\n0320-106 90. Bankgiro 546-1173.\nPostgiro 34821-9\n\nVerksamhet: Säljer lantbruks-,\nskogs- o industrimaskiner\nAntal anställda: 35\nÅrsomsättning: 11 000 000\nAktiekapital: 400 000\nVerkst dir: Hans Andersson\nEtableringsår: 1920.\n\nANDERSSONS\nMETALLDUKS-FABRIK, J A\n\nPnr 330 20\n\nAnderstorp, Söderg 6-8. Box 31.\nTel 0371-150 34. Bankgiro\n48-8070. Postgiro 24934\nVerksamhet: Tillverkar järn- o\nmetalltrådsdukar\n\nFirmatecknare: Gottfrid Andersson\nEtableringsår: 1892.\n\nLINCO, AB\n\nPnr 102 43\n\nStockholm 5, Linnég 31. Box 5127.\nTel 08-63 06 40. Bankgiro 726-5135.\nPostgiro 253747-0. Tga\nLincoma-rin\n\nVerksamhet: Generalagent för\nEvinrude\n\nAntal anställda: 14\nAktiekapital: 120 000\nVerkst dir: Bengt Nilsson\nEtableringsår: 1946.\n\nGOTEBORGS BANDVÄVERI AB\n\nPnr 400 51\n\nGöteborg 47, Förstamajg 4. Box\n47049. Tel 031-46 00 50. Bankgiro\n446-1034. Postgiro 424950-4. Tga\nNilivar. Telex 20932\nVerksamhet: Tillverkar band\nAntal anställda: 70\nÅrsomsättning: 8 500 000\nAktiekapital: 200 000\nVerkst dir: Nils Ivarsson\nEtableringsår: 1950.\n\nPRECISIONSINSTRUMENT AB\n\nPnr 11341\n\nStockholm, Norrbackag 23. Tel\n08-30 88 42, 30 88 43. Bankgiro\n747-4091. Postgiro 157670-1\nVerksamhet: Tillverkar o säljer\nmanometrar o termometrar. Utför\nrevolver- o automatsvarvning samt\nfinmekaniska arbeten\nAntal anställda: 10\nAktiekapital: 10 000\nVerkst dir Olof Ekström\nEtableringsår: 1947.\n\nANDERBERG AB, CARL\n\nPnr 261 22\n\nLandskrona 1, Box 10. Slottsg 10.\nTel 0418-110 77, 193 77. Bankgiro\n86-8502. Postgiro 291726. Tga\n\nCander\n\nVerksamhet: Tillverkar\nreklamballonger\n\nAntal anställda: 15\nAktiekapital: 50000\nDisp: Christer Anderberg\nEtableringsår: 1946.",
    "structured": {
        "firms": [
            {
                "company_name": "ÖSTLUND, BRÖDERNA",
                "pnr": "68015",
                "address": "Bäckalund, Box 240",
                "phone_number": "0565-200 16",
                "bank_details": {
                    "bankgiro": "11-3855",
                    "postgiro": "285558"
                },
                "activity": "Entreprenadfirma för vatten- o avloppsanläggningar, brobyggnader, brunnsborrning m m",
                "key_personnel": [
                    {
                        "name": "E L Ostlund",
                        "position": ""
                    },
                    {
                        "name": "P A Ostlund",
                        "position": ""
                    },
                    {
                        "name": "N G Ostlund",
                        "position": ""
                    },
                    {
                        "name": "R E Ostlund",
                        "position": ""
                    }
                ],
                "establishment_year": 1944
            },
            {
                "company_name": "UTTERSTRDM MASKIN AB, A",
                "pnr": "12164",
                "address": "Johanneshov, Vättersv 39",
                "phone_number": "08-4806 12, 4806 13",
                "bank_details": {
                    "bankgiro": "295-1416",
                    "postgiro": "550167-1"
                },
                "activity": "Verktygsmaskiner o verktyg till verkstadsindustrin",
                "employees": 10,
                "annual_turnover": 3000000,
                "capital": 100000,
                "key_personnel": [
                    {
                        "name": "Arne Utterström",
                        "position": ""
                    }
                ],
                "establishment_year": 1955
            },
            {
                "company_name": "RISÄNGS TRIKÄVÄVERI",
                "pnr": "51100",
                "address": "Kinna",
                "phone_number": "0320-10133",
                "bank_details": {
                    "bankgiro": "434-7480",
                    "postgiro": "125403-6"
                },
                "activity": "Tillverkar raschel-vävda artiklar",
                "key_personnel": [
                    {
                        "name": "Fabr Einar Rudhner",
                        "position": ""
                    }
                ],
                "establishment_year": 0
            },
            {
                "company_name": "RISÄNGSVERKEN, KB",
                "pnr": "600 06",
                "address": "Norrköping 6, Box 6055",
                "phone_number": "011-100130",
                "bank_details": {
                    "bankgiro": "786-4176",
                    "postgiro": "683880"
                },
                "activity": "Tillverkar tryckkärl, traverser, maskinkonstruktioner, balkkonstruktioner, elevatorer, skraptransportörer, remtransportörer, plåtfickor, matarvattentankar, kondensatorer även i syrafast material m m. Plåt- o balkarbeten, arborrning, svarvning, fräsning, borrning o montering. Licenssvetsning enl pannsvetsnormerna i rostfritt material",
                "employees": 80,
                "annual_turnover": 4500000,
                "key_personnel": [
                    {
                        "name": "Charles Andersson",
                        "position": "Verkst dir"
                    },
                    {
                        "name": "Töre Nordström",
                        "position": "Kamrer"
                    },
                    {
                        "name": "Ingvar Aldvén",
                        "position": "Verkstadschef"
                    },
                    {
                        "name": "Per-Gustaf Berg",
                        "position": "Verkstadsingenjör"
                    }
                ],
                "establishment_year": 1955
            },
            {
                "company_name": "RITPRODUKTER, AB",
                "pnr": "171 20",
                "address": "Solna 1, Vretenv 4 A",
                "phone_number": "08-28 1750, 2176 99",
                "bank_details": {
                    "bankgiro": "191-5966",
                    "postgiro": "177580-8"
                },
                "activity": "Säljer ljuskopierings-, rit- o mm-rutad polyesterfilm samt tryckta ritningsblanketter",
                "establishment_year": 1964
            },
            {
                "company_name": "KJELLSTROM & PERSSON, AB",
                "pnr": "252 20",
                "address": "Helsingborg, N Storg 8",
                "phone_number": "042-110073, 112073",
                "bank_details": {
                    "bankgiro": "863-9585",
                    "postgiro": "13330-6"
                },
                "activity": "Säljer glas o porslin",
                "key_personnel": [
                    {
                        "name": "Ake Jönsson",
                        "position": "Verkst dir"
                    }
                ],
                "establishment_year": 1871
            },
            {
                "company_name": "TIELMANS PLASTINDUSTRI AB",
                "pnr": "582 37",
                "address": "Linköping, Barhällsg 13",
                "phone_number": "013-13 23 00, 13 45 23",
                "bank_details": {
                    "bankgiro": "608-0295",
                    "postgiro": "263030-9"
                },
                "activity": "Anslagsramar, pluggar till pappersrullar, rörpluggar, am-pullaskar, färgrör o garnspolar för textilindustrin. Legotillverkning",
                "employees": 9,
                "annual_turnover": 925000,
                "capital": 20000,
                "key_personnel": [
                    {
                        "name": "stig Tielman",
                        "position": "Verkst dir"
                    }
                ],
                "establishment_year": 1948
            },
            {
                "company_name": "TIELMAN, B",
                "pnr": "581 03",
                "address": "Lidköping l.Ostgötag 62, Box 350",
                "phone_number": "013-12 97 30",
                "bank_details": {
                    "bankgiro": "60-7976",
                    "postgiro": "72702"
                },
                "activity": "Tillverkar engångsartiklar",
                "key_personnel": [
                    {
                        "name": "Bertil Tielman",
                        "position": "Verkst din"
                    }
                ],
                "establishment_year": 1930
            },
            {
                "company_name": "ANDERSSON I KINNA AB, IVAR",
                "pnr": "51101",
                "address": "Kinna 1, Box 98, Särla",
                "phone_number": "0320-106 90",
                "bank_details": {
                    "bankgiro": "546-1173",
                    "postgiro": "34821-9"
                },
                "activity": "Säljer lantbruks-, skogs- o industrimaskiner",
                "employees": 35,
                "annual_turnover": 11000000,
                "capital": 400000,
                "key_personnel": [
                    {
                        "name": "Hans Andersson",
                        "position": "Verkst dir"
                    }
                ],
                "establishment_year": 1920
            },
            {
                "company_name": "ANDERSSONS METALLDUKS-FABRIK, J A",
                "pnr": "330 20",
                "address": "Anderstorp, Söderg 6-8, Box 31",
                "phone_number": "0371-150 34",
                "bank_details": {
                    "bankgiro": "48-8070",
                    "postgiro": "24934"
                },
                "activity": "Tillverkar järn- o metalltrådsdukar",
                "key_personnel": [
                    {
                        "name": "Gottfrid Andersson",
                        "position": ""
                    }
                ],
                "establishment_year": 1892
            },
            {
                "company_name": "LINCO, AB",
                "pnr": "102 43",
                "address": "Stockholm 5, Linnég 31, Box 5127",
                "phone_number": "08-63 06 40",
                "bank_details": {
                    "bankgiro": "726-5135",
                    "postgiro": "253747-0"
                },
                "activity": "Generalagent för Evinrude",
                "employees": 14,
                "capital": 120000,
                "key_personnel": [
                    {
                        "name": "Bengt Nilsson",
                        "position": "Verkst dir"
                    }
                ],
                "establishment_year": 1946
            },
            {
                "company_name": "GOTEBORGS BANDVÄVERI AB",
                "pnr": "400 51",
                "address": "Göteborg 47, Förstamajg 4, Box 47049",
                "phone_number": "031-46 00 50",
                "bank_details": {
                    "bankgiro": "446-1034",
                    "postgiro": "424950-4"
                },
                "activity": "Tillverkar band",
                "employees": 70,
                "annual_turnover": 8500000,
                "capital": 200000,
                "key_personnel": [
                    {
                        "name": "Nils Ivarsson",
                        "position": "Verkst dir"
                    }
                ],
                "establishment_year": 1950
            },
            {
                "company_name": "PRECISIONSINSTRUMENT AB",
                "pnr": "11341",
                "address": "Stockholm, Norrbackag 23",
                "phone_number": "08-30 88 42, 30 88 43",
                "bank_details": {
                    "bankgiro": "747-4091",
                    "postgiro": "157670-1"
                },
                "activity": "Tillverkar o säljer manometrar o termometrar. Utför revolver- o automatsvarvning samt finmekaniska arbeten",
                "employees": 10,
                "capital": 10000,
                "key_personnel": [
                    {
                        "name": "Olof Ekström",
                        "position": "Verkst dir"
                    }
                ],
                "establishment_year": 1947
            },
            {
                "company_name": "ANDERBERG AB, CARL",
                "pnr": "261 22",
                "address": "Landskrona 1, Box 10, Slottsg 10",
                "phone_number": "0418-110 77, 193 77",
                "bank_details": {
                    "bankgiro": "86-8502",
                    "postgiro": "291726"
                },
                "activity": "Tillverkar reklamballonger",
                "employees": 15,
                "capital": 50000,
                "key_personnel": [
                    {
                        "name": "Christer Anderberg",
                        "position": "Disp"
                    }
                ],
                "establishment_year": 1946
            }
        ]
    }
}