{
    "original": "materialhantering ab\n\nPnr 431 22\n\nMölndal 1, Box 103. Agatan 26 B.\nTel 031-27 92 00, 27 92 01.\nBankgiro 420-5597. Postgiro 620600-7\nVerksamhet: Ingenjörsfirma för\ntransportanordningar,\nlagerinredningar, utrustning för industri o\nlager såsom transportvagnar,\nlänkrullar o hjul\n\nVarunamn: Master, Shepheard,\nRhombus\n\nAntal anställda: 4\nÅrsomsättning: 1500 000\nAktiekapital: 100 000\nVeikst dir: ing Per Berghult\nEtableringsår: 1961.\n\nSVÄNGSTA SKORPOR, AB\n\nPnr 294 00\n\nSölvesborg, Box 77. Tel\n0456-125 80. Bankgiro 579-8053.\nPost-giro 285520-3. Tga Svangsta.\nTelex 4482\n\nVerksamhet: Tillverkning o\nförsäljning av skorpor o småbröd\nAntal anställda: 65\nÅrsomsättning: 10 000 000\nAktiekapital: 200 000\nVerkst din Erik Ekegren\nEtableringsår: 1946.\n\nSVÄRD &amp; STRAND MEK\nVERKSTAD, AB\n\nPnr 700 07\n\nÖrebro 7, Slöjdg 37-39. Box 7009.\nTel 019-1135 92, 12 6126\nVerksamhet: Mek verkstad. Utför\nlegoarbeten för verkstadsindustrin\nÅrsomsättning: 2 000 000\nAktiekapital: 50 000\nKontaktman: Gösta Bergdahl\nEtableringsår. 1922.\n\nMELLANDER &amp; ERICSSON AB\n\nPnr 42202\n\nHisings Backa 2, Importg 4. Box\n2019. Tel 031-52 0180. Bankgiro\n42-0126. Postgiro 40433. Telex\n2593 HERCGBG S. Tga Hercmineral\nVerksamhet: Säljer kemikalier\nAntal anställda: 22\nAktiekapital: 600 000\nVerkst dir: Hans Palmgren\nEtableringsår: 1916.\n\nMELLANSVENSKA\nSNICKERI-CENTRALEN EK FUR\n\nPnr 611 01\n\nNyköping 1, Bagarg 11. Box 5. Tel\n0155-855 70. Bankgiro 711-8029.\nPostgiro 333127-9\n\nVerksamhet: Säljer\nbyggnadssnicke-rier o specialinredning\nChef: Ing Kjell Classon\nEtableringsår: 1968.\n\nHALL, AB AUG\n\nPnr 34200\n\nAlvesta. Tel 0472-113 30. Bankgiro\n14-7108. Postgiro 31978. Tga Halls.\nTelex 52060\n\nVerksamhet: Grosshandelsrörelse\nmed järnvaror, hushållsartiklar,\nbyggmaterial\n\nÅrsomsättning: 44000 000\nAktiekapital: 600 000\nStyrelse: Godsägare L Hall (ordf),\ndir K Hall, bankdir B Edwall\nVeikst din Klas A Hall\nEkonomidir: G Hansson\nDisp:r H Olofsson, G Elner\nEtableringsår: 1863.\n\nLINDAHL, STEN\n\nPnr 413 24\n\nGöteborg, Dr Sydows g 3 D. Tel\n031-82 38 33, 82 38 34. Bankgiro\n508-6020. Postgiro 45844-8.\nTga Urbano\n\nVerksamhet: Säljer för utländska\nhuvudmän skinn o läder, gelatin o\nlim, kryddor, kemiska o\nfarmaceu-tiska råvaror samt färger\nÅrsomsättning: 2000 000\nÄgare o chefer: Sten Lindahl,\nBengt Lindahl\nEtableringsår: 1936.\n\nKP-SKYLTFABRIK\n\nPnr 443 01\n\nLerum 1, Göteborgsv. Box 162. Tel\n0302-122 94. Bankgiro 44-4723.\nPostgiro 427295. Telex 20768\nVerksamhet: Fabrikation o\nförsäljning av ljusskyltar av akrylplast\nAntal anställda: 23\nPlatschef: Disp Henry Hansen.\n\nKPV KARLSTADS\nPLÅTVERKSTAD AB\n\nPnr 652 21\n\nKarlstad. Orkang 1. Tel054-18 53 20.\nBankgiro 344-5285. Postgiro\n578839-3\n\nVerksamhet: Utför rostfria\nplåtarbeten o stålkonstruktioner\n.Antal anställda: 70\nÅrsomsättning: 6 0 00 000\nAktiekapital: 100 000\nVerkst dir: Erik Bäckman\nEtableringsår: 1962.\n\nRAD I US, AB\n\nPnr 126 37\n\nHägersten, Tellusborgsv 69. Tel\n08-198410, 181493, 1983 80,\n187171. Bankgiro 74-4307.\nPostgiro 828. Tga Stainless\nVeiksamhet: Specialverkstad för\nrostfria o syrafasta produkter\nAntal anstäUda: 20\nAktiekapital: 1200 000\n\nVeikst din Folke Berg\nVeikmästare: Christian Grawsiö\nEtableringsår: 1913.\n\nEM-VERKEN, AB\n\nPnr 341 00\n\nLjungby. Pabriksg. Tel 0372-112 75,\n10274. Bankgiro 67-5914. Postgiro\n33007\n\nVerksamhet: Tillverkar\nelektro-porslin\n\nAntal anställda: 11\nAktiekapital: 10000\nVerkst dir: Frank Peterson\nEtableringsår: 1947.\n\nERICSSON, AB JOHN H\n\nPnr 721 32\n\nVästerås 1, Box 940. Siöhagsv 6.\nTel 021-13 71 50. Bankgiro\n808-6670. Postgiro 7533-3. Tga\nPappersbolaget\n\nVerksamhet: Pappersgrosshandel,\nciv il tryckeri\nAvdelningskontor\n\nEskilstuna, Mått Johanssons v 20.\nTel 016-1357 50\n\nGävle, Granitv 20. Tel 026-12 07 90\nBorlänge, Industriv 5. Tel\n0243-106 50\n\nÅrsomsättning: 15 000 000\nAktiekapital: 200 000\nVerkst dir: Lennart Nyström\nEtableringsår: 1898\nOmbildat till aktiebolag 1925.\n\nERIKSSONS KNIVFABRIK, K J\n\nPnr 792 00\n\nMora, Box 131. Tel 0250-135 30.\nBankgiro 797-3118. Postgiro\n25653-7. Tga KJknivar\nVerksamhet: Tillverkar o säljer\ntälj- o slidknivar, hushållsknivar,\nslaktknivar, jakt- o sportknivar,\nslöjdknivar, isborrar o isborrskär\nAntal anställda: 35\nÅrsomsättning: 4 000 000\nChef: Einar Eriksson\nEtableringsår: 1912.\n\nARCU ARMATURINDUSTRI AB\n\nPnr 360 75\n\nAls termo, Box 96. Tel 0481-615 00,\n615 22. Bankgiro 147-0715.\nPostgiro 563880-4\n\nVerksamhet: Tillverkar\nradiatorventiler o termostatventiler för\nen-o tvårörssystem\nAktiekapital: 45 000\nStyrelse: Fabr Arne Johansson, ing\nGösta Hammarstedt, ing Curt\nHammarstedt\n\nVerkst dir: Fabr Arne Johansson\nEtableringsår: 1965.",
    "structured": {
        "1": {
            "company_name": "MATERIALHANTERING AB",
            "pnr": "431 22",
            "address": "Mölndal 1, Box 103. Agatan 26 B.",
            "phone_number": "031-27 92 00, 27 92 01",
            "bank_details": {
                "bankgiro": "420-5597",
                "postgiro": "620600-7"
            },
            "activity": "Ingenjörsfirma för transportanordningar, lagerinredningar, utrustning för industri o lager såsom transportvagnar, länkrullar o hjul",
            "employees": 4,
            "annual_turnover": 1500000,
            "capital": 100000,
            "key_personnel": [
                {
                    "name": "Ing Per Berghult",
                    "position": "Veikst dir"
                }
            ],
            "establishment_year": 1961
        },
        "2": {
            "company_name": "SVÄNGSTA SKORPOR, AB",
            "pnr": "294 00",
            "address": "Sölvesborg, Box 77",
            "phone_number": "0456-125 80",
            "bank_details": {
                "bankgiro": "579-8053",
                "postgiro": "285520-3"
            },
            "activity": "Tillverkning o försäljning av skorpor o småbröd",
            "employees": 65,
            "annual_turnover": 10000000,
            "capital": 200000,
            "key_personnel": [
                {
                    "name": "Erik Ekegren",
                    "position": "Verkst din"
                }
            ],
            "establishment_year": 1946
        },
        "3": {
            "company_name": "SVÄRD & STRAND MEK VERKSTAD, AB",
            "pnr": "700 07",
            "address": "Örebro 7, Slöjdg 37-39. Box 7009",
            "phone_number": "019-1135 92, 12 6126",
            "activity": "Mek verkstad. Utför legoarbeten för verkstadsindustrin",
            "annual_turnover": 2000000,
            "capital": 50000,
            "key_personnel": [
                {
                    "name": "Gösta Bergdahl",
                    "position": "Kontaktman"
                }
            ],
            "establishment_year": 1922
        },
        "4": {
            "company_name": "MELLANDER & ERICSSON AB",
            "pnr": "42202",
            "address": "Hisings Backa 2, Importg 4. Box 2019",
            "phone_number": "031-52 0180",
            "bank_details": {
                "bankgiro": "42-0126",
                "postgiro": "40433"
            },
            "activity": "Säljer kemikalier",
            "employees": 22,
            "capital": 600000,
            "key_personnel": [
                {
                    "name": "Hans Palmgren",
                    "position": "Verkst dir"
                }
            ],
            "establishment_year": 1916
        },
        "5": {
            "company_name": "MELLANSVENSKA SNICKERI-CENTRALEN EK FUR",
            "pnr": "611 01",
            "address": "Nyköping 1, Bagarg 11. Box 5",
            "phone_number": "0155-855 70",
            "bank_details": {
                "bankgiro": "711-8029",
                "postgiro": "333127-9"
            },
            "activity": "Säljer byggnadssnicke-rier o specialinredning",
            "employees": "?",
            "establishment_year": 1968
        },
        "6": {
            "company_name": "HALL, AB AUG",
            "pnr": "34200",
            "address": "Alvesta",
            "phone_number": "0472-113 30",
            "bank_details": {
                "bankgiro": "14-7108",
                "postgiro": "31978"
            },
            "activity": "Grosshandelsrörelse med järnvaror, hushållsartiklar, byggmaterial",
            "annual_turnover": 44000000,
            "capital": 600000,
            "key_personnel": [
                {
                    "name": "Klas A Hall",
                    "position": "Veikst din"
                },
                {
                    "name": "G Hansson",
                    "position": "Ekonomidir"
                }
            ],
            "establishment_year": 1863
        },
        "7": {
            "company_name": "LINDAHL, STEN",
            "pnr": "413 24",
            "address": "Göteborg, Dr Sydows g 3 D",
            "phone_number": "031-82 38 33, 82 38 34",
            "bank_details": {
                "bankgiro": "508-6020",
                "postgiro": "45844-8"
            },
            "activity": "Säljer för utländska huvudmän skinn o läder, gelatin o lim, kryddor, kemiska o farmaceutiska råvaror samt färger",
            "annual_turnover": 2000000,
            "key_personnel": [
                {
                    "name": "Sten Lindahl",
                    "position": "Ägare"
                },
                {
                    "name": "Bengt Lindahl",
                    "position": "Chefer"
                }
            ],
            "establishment_year": 1936
        },
        "8": {
            "company_name": "KP-SKYLTFABRIK",
            "pnr": "443 01",
            "address": "Lerum 1, Göteborgsv. Box 162",
            "phone_number": "0302-122 94",
            "bank_details": {
                "bankgiro": "44-4723",
                "postgiro": "427295"
            },
            "activity": "Fabrikation o försäljning av ljusskyltar av akrylplast",
            "employees": 23,
            "key_personnel": [
                {
                    "name": "Henry Hansen",
                    "position": "Platschef"
                }
            ]
        },
        "9": {
            "company_name": "KPV KARLSTADS PLÅTVERKSTAD AB",
            "pnr": "652 21",
            "address": "Karlstad, Orkang 1",
            "phone_number": "054-18 53 20",
            "bank_details": {
                "bankgiro": "344-5285",
                "postgiro": "578839-3"
            },
            "activity": "Utför rostfria plåtarbeten o stålkonstruktioner",
            "employees": 70,
            "annual_turnover": 6000000,
            "capital": 100000,
            "key_personnel": [
                {
                    "name": "Erik Bäckman",
                    "position": "Verkst dir"
                }
            ],
            "establishment_year": 1962
        },
        "10": {
            "company_name": "RAD I US, AB",
            "pnr": "126 37",
            "address": "Hägersten, Tellusborgsv 69",
            "phone_number": "08-198410, 181493, 1983 80, 187171",
            "bank_details": {
                "bankgiro": "74-4307",
                "postgiro": "828"
            },
            "activity": "Specialverkstad för rostfria o syrafasta produkter",
            "employees": 20,
            "capital": 1200000,
            "key_personnel": [
                {
                    "name": "Folke Berg",
                    "position": "Veikst din"
                },
                {
                    "name": "Christian Grawsiö",
                    "position": "Veikmästare"
                }
            ],
            "establishment_year": 1913
        },
        "11": {
            "company_name": "EM-VERKEN, AB",
            "pnr": "341 00",
            "address": "Ljungby, Pabriksg",
            "phone_number": "0372-112 75, 10274",
            "bank_details": {
                "bankgiro": "67-5914",
                "postgiro": "33007"
            },
            "activity": "Tillverkar elektro-porslin",
            "employees": 11,
            "capital": 10000,
            "key_personnel": [
                {
                    "name": "Frank Peterson",
                    "position": "Verkst dir"
                }
            ],
            "establishment_year": 1947
        },
        "12": {
            "company_name": "ERICSSON, AB JOHN H",
            "pnr": "721 32",
            "address": "Västerås 1, Box 940. Siöhagsv 6",
            "phone_number": "021-13 71 50",
            "bank_details": {
                "bankgiro": "808-6670",
                "postgiro": "7533-3"
            },
            "activity": "Pappersgrosshandel, civil tryckeri",
            "annual_turnover": 15000000,
            "capital": 200000,
            "key_personnel": [
                {
                    "name": "Lennart Nyström",
                    "position": "Verkst dir"
                }
            ],
            "establishment_year": 1898
        },
        "13": {
            "company_name": "ERIKSSONS KNIVFABRIK, K J",
            "pnr": "792 00",
            "address": "Mora, Box 131",
            "phone_number": "0250-135 30",
            "bank_details": {
                "bankgiro": "797-3118",
                "postgiro": "25653-7"
            },
            "activity": "Tillverkar o säljer tälj- o slidknivar, hushållsknivar, slaktknivar, jakt- o sportknivar, slöjdknivar, isborrar o isborrskär",
            "employees": 35,
            "annual_turnover": 4000000,
            "key_personnel": [
                {
                    "name": "Einar Eriksson",
                    "position": "Chef"
                }
            ],
            "establishment_year": 1912
        },
        "14": {
            "company_name": "ARCU ARMATURINDUSTRI AB",
            "pnr": "360 75",
            "address": "Alstermo, Box 96",
            "phone_number": "0481-615 00, 615 22",
            "bank_details": {
                "bankgiro": "147-0715",
                "postgiro": "563880-4"
            },
            "activity": "Tillverkar radiatorventiler o termostatventiler för en- o tvårörssystem",
            "capital": 45000,
            "key_personnel": [
                {
                    "name": "Fabr Arne Johansson",
                    "position": "Styrelse"
                },
                {
                    "name": "Ing Gösta Hammarstedt",
                    "position": "Styrelse"
                },
                {
                    "name": "Ing Curt Hammarstedt",
                    "position": "Styrelse"
                }
            ],
            "establishment_year": 1965
        }
    }
}