{
    "original": "FREDRIKSNÄS SÄTERI AB\n\nPnr 615 00\n\nValdemarsvik, Predriksnäs, postl\n700. Tel 0123-22089, 22071.\nBankgiro 674-4726. Postgiro 348480-5.\nTga Fredrikwood\nVerksamhet: Tillverkar o säljer\nplank, battens etc, sågade sparrar,\nlövträ, lådor o pappersved\nAntal anställda: 20\nÅrsomsättning: 1500 000\nAktiekapital: 1400 000\nVeikst dir: Ekon lic Arne Nilsson\nEtableringsår: 1928.\n\nFIB\n\nbord- o rengöringsdukar,\nkorttidsmaterial samt halvfabrikat för olika\ntekniska ändamål\n\nVarunamn: Modelin, Styvlin,\nTrampolin\n\nAntal anställda: 75\n\nAktiekapital: 500000\n\nVerkst dir: Konsul Ake Raihle\n\nDisp: Bengt Svahn\n\nEtableringsår: 1959\n\nFöretaget ingår i Persönerkoncer-\n\nnen.\n\nFIBETEXTIL AB\n\nPnr 430 50\n\nKållered. Box 44. Tel 031-13 48 05.\nBankgiro 84-7889. Postgiro 421408\nVerksamhet: Säljer mattor engros\nAntal anställda: 6\nAktiekapital: 30 000\nVerkst dir: Köpman Berndt Fibert\nEtableringsår: 1946.\n\nFOODIA AB\n\nPnr 245 00\n\nStaffanstorp. Tel 040-14 53 00.\nFrån 1/8 1971 även 040-28 90 00.\nTga Foodia. Telex 32737 FOODIA S\n\nVerksamhet: Tillverkar sylter,\nmarmelader, safter, ättiksinläggningar,\nsoppor, vegetabiliska helkonserver,\nköttkonserver, majonnäs, senap,\ndiupfrysta bär, grönsaker o\nfärdig-lagad mat, salt sill, torkad o lutad\nfisk. sill- o fiskkonserver\nFabriker: 265 01 Åstorp. Tel\n042-51630\n\n453 00 Lysekil. Tel 0523-130 00.\nTelex 42049 FOODIA S\n440 80 Ellös. Tel 0304-502 50\nAntal anställda: 980\nÅrsomsättning: 122 000 000\nVerkst dir: Kjell Nihlberg\nHelägt dotterföretag till\nKooperativa Förbundet.\n\nFORD MOTOR COMPANY AB\n\nPnr 102 50\n\nStockholm 27, Fack. Stockholms\nFrihamn. Tel 08-67 98 00, 67 9820.\nTga Fordmotor. Telex 1451\nVerksamhet: Importerar o säljer\nperson- o lastbilar samt traktorer\nAntal anställda: 420\nÅrsomsättning: 279 000 000\nAktiekapital: 20000000\nVerkst dir. Hans Larsson\nEtableringsår: 1924.\n\nSCANIPS AB\n\nPnr 11242\n\nStockholm, Drottningholmsv 5. Tel\n08-52 04 30. Bankgiro 113-6969.\nPostgiro 51542-9. Tga Svanips.\nTelex 10493 SCANIPS S\nVerksamhet: Agenturverksamhet i\ndatorsystem. Servicebyrå\nAntal anstäUda: 18\nÅrsomsättning: 2 000 000\nAktiekapital: 530 000\nVerkst dir: Bo Malmborg\nEtableringsår: 1966.\n\nARLÖVS INDUSTRIBY AB\n\nPnr 232 00\n\nArlöv, Länsmansg 5-Stortorget 1.\nTel 040-43 05 40. Postgiro 245246-4\nVerksamhet: Modul-byggande.\nFörvaltar industribyggnader\nTeknisk avdelning: Svenska\nIndustribyggen AB. 201 24 Malmö 1,\nBox 445. Tel 040-74040\n\nStyrelse: Textilarb W Törnqvist\n(ordf), kommunaldir A Sjödin, dir\nH Birke, dir F Sundberg, dir A\nGrenner\n\nVerkst dir: Kommunaldir Axel Sjödin\nEtableringsår: 1965.\n\nEtableringsår: 1919\n\nDotterbolag i koncernen: AB\nUpsala Ättiksfabrik, AB Upsala\nSiden-väverier (tillverkar textilier),\nUpsala Foder &amp; Spannmåls AB\n(förädlar jordbruksprodukter).\n\nSLOTTSLISTENS FUR.\nSALJNINGS AB\n\nPnr 416 68\n\nGöteborg O, Anäsv 50. Tel\n031-19 8104,19 8103. Bankgiro 44-4133.\nPostgiro 620301\n\nVerksamhet: Fabrikation o\nmontering av tätningslist\nAntal anställda: 7\nAktiekapital: 20 000\nVerkst dir: Bengt Ytterdahl\nEtableringsår: 1961.\n\nSLOTTSMOLLANS\nTEGEL-BRUK\n\nPnr 30103\n\nHalmstad 1, Box 128. Slottsmöllan.\nTel 035-11 80 50. Bankgiro\n423-6261. Postgiro 14894-0. Tga\nWallbergs. Telex 38019 WAFAB S\nVerksamhet: Tillverkar fasad- o\nmurtegel\n\nFörsäljningskontor: AB\nTegelcentralen i Malmö, Göteborg o\nJönköping. Larsson, Seaton &amp; Co,\nGöteborg\n\nAntal anställda: 35\nÅrsomsättning: 3 000 000\nVerkst dir: Peter Rautenberg\nEtableringsår: Omkring 1800\nDotterbolag till Wallbergs Fabriks\nAB, Halmstad.\n\nSLÄPVAGNSKOPPLINGAR AB\n\nPnr 462 01\n\nVänersborg 1, Box 216. Tel\n0521-180 60. Bankgiro 88-8662. Postgiro\n280801\n\nVerksamhet: Tillverkar\nsläpvagnskopplingar för motorfordon\nVarunamn: VBG-produkter\nAntal anställda: 75\nÅrsomsättning: 8 300000\nAktiekapital: 100 000\nVerkst dir: Herman U Krefting\nEtableringsår: 1950\nOmbildat till aktiebolag 1960.\n\nSLÄTTE MÖBLER, AB\n\nPnr 54 5 00\n\nTöreboda. Tel 0506-116 30.\nBankgiro 217-1748. Postgiro 341776-3.\nTga Swedfurn\n\nVerksamhet: Tillverkar\nstoppmöbler\n\nAntal anställda: 105\nAktiekapital: 200 000\nVerkst dir: Ingvar Skoog\nEtableringsår: 1950.\n\nMOTALA VERKSTAD, AB\n\nPnr 59101\n\nMotala 1, Fack. Tel 0141-160 00.\nPostgiro 73751. Tga Motalaverk.\nTelex 5585\n\nVeiksamhet: Tillverkar hydrauliska\npressar, spånskiveanläggningar,\nmarina produkter, rostfria\ndiskbänkar, sjukhusutrustningar\nAntal anställda: 1 650\nÅrsomsättning: 150 000 000\nAktiekapital: 16 000 000\nStyrelse: Bergsing Axel Ax: son\nJohnson (ordf), dir Bo Ax:son\nJohnson, dir Alvar Lindencrona,\nbruks-disp Wilhelm Haglund, dir Per Adolf\nNorlin, dir Gunnar Westerberg, dir\nHelge Lindberg, dir Anders\nWing-strand\n\nVerkst dir: Anders Wingstrand\nTekn dir: Karl-Ake Jarbelius\nEkonomidir: Knut Claesson\nFörsäljn-dir: Berno Tröst\nInköpschef: Kjell Skog\nEtableringsår. 1822\nÄger Björneborgs Jernverks AB,\nBjörneborg.\n\nMOTESKA, AB\n\nPnr 230 16\n\nJordholmen. Tel 040-14 32 50. Tga\nMoteska\n\nVerksamhet: Lantbrukssprutor o\nhögtryckstvättaggregat\nAntal anställda: 35\nÅrsomsättning: 4 000 000\nEtableringsår: 1947.\n\nTJUSTORPS TEGELBRUKS AB\n\nPnr 233 00\n\nSvedala. Tel 040-44 70 94\nVerksamhet: Tillverkar fasadtegel\nAktiekapital: 2 000 000\nStyrelse: Bruksdisp C G Edstrand\n(ordf), konsul C-G Ljungberg,\nbergsing G Edstrand\nVerkst dir: Klas Ringius\nPlatschef: Disp H Arnstrup\nEtableringsån 1930.\n\nNÄSSJÖ SÅGBLADS.\nFABRIK, AB\n\nPnr 57100\n\nNässjö, Osterlångg 51. Tel\n0380-10102, 10236. Bankgiro 452-7693.\nPostgiro 131339-4. Tga Fribergs\nVerksamhet: Tillverkar\ncirkelsåg-klingor för trä\nAntal anställda: 15\nÅrsomsättning: 2 000 000\nAktiekapital: 20 000\nVerkst dir: Hugo Friberg\nEtableringsår: 1902.\n\nDALSJOFORS MÖBLER, AB\n\nPnr 502 30\n\nBorås, Smedsg 2. Tel 033-1279 60.\nBankgiro 532-1088. Postgiro\n138077-7\n\nVerksamhet: Säljer möbler o mattor\nAntal anställda: 14\nÅrsomsättning: 3 000000\nAktiekapital: 66000\nVerkst dir: Karl Einar Thörner\nEtableringsår: 1935.",
    "structured": {
        "1": {
            "company_name": "FREDRIKSNÄS SÄTERI AB",
            "address": "Valdemarsvik, Predriksnäs, postl 700",
            "phone_number": "0123-22089, 22071",
            "bank_details": {
                "bankgiro": "674-4726",
                "postgiro": "348480-5"
            },
            "activity": "Tillverkar o säljer plank, battens etc, sågade sparrar, lövträ, lådor o pappersved",
            "employees": 20,
            "annual_turnover": 1500000,
            "capital": 1400000,
            "key_personnel": [
                {
                    "name": "Ekon lic Arne Nilsson",
                    "position": "Veikst dir"
                }
            ],
            "establishment_year": 1928
        },
        "2": {
            "company_name": "FIB",
            "activity": "Bord- o rengöringsdukar, korttidsmaterial samt halvfabrikat för olika tekniska ändamål",
            "varunamn": "Modelin, Styvlin, Trampolin",
            "employees": 75,
            "capital": 500000,
            "key_personnel": [
                {
                    "name": "Konsul Ake Raihle",
                    "position": "Verkst dir"
                },
                {
                    "name": "Bengt Svahn",
                    "position": "Disp"
                }
            ],
            "establishment_year": 1959
        },
        "3": {
            "company_name": "FIBETEXTIL AB",
            "address": "Kållered, Box 44",
            "phone_number": "031-13 48 05",
            "bank_details": {
                "bankgiro": "84-7889",
                "postgiro": "421408"
            },
            "activity": "Säljer mattor engros",
            "employees": 6,
            "capital": 30000,
            "key_personnel": [
                {
                    "name": "Köpman Berndt Fibert",
                    "position": "Verkst dir"
                }
            ],
            "establishment_year": 1946
        },
        "4": {
            "company_name": "FOODIA AB",
            "address": "Staffanstorp",
            "phone_number": "040-14 53 00, 040-28 90 00",
            "activity": "Tillverkar sylter, marmelader, safter, ättiksinläggningar, soppor, vegetabiliska helkonserver, köttkonserver, majonnäs, senap, diupfrysta bär, grönsaker o färdig-lagad mat, salt sill, torkad o lutad fisk. sill- o fiskkonserver",
            "employees": 980,
            "annual_turnover": 122000000,
            "key_personnel": [
                {
                    "name": "Kjell Nihlberg",
                    "position": "Verkst dir"
                }
            ]
        },
        "5": {
            "company_name": "FORD MOTOR COMPANY AB",
            "address": "Stockholm 27, Fack. Stockholms Frihamn",
            "phone_number": "08-67 98 00, 67 9820",
            "activity": "Importerar o säljer person- o lastbilar samt traktorer",
            "employees": 420,
            "annual_turnover": 279000000,
            "capital": 20000000,
            "key_personnel": [
                {
                    "name": "Hans Larsson",
                    "position": "Verkst dir"
                }
            ],
            "establishment_year": 1924
        },
        "6": {
            "company_name": "SCANIPS AB",
            "address": "Stockholm, Drottningholmsv 5",
            "phone_number": "08-52 04 30",
            "bank_details": {
                "bankgiro": "113-6969",
                "postgiro": "51542-9"
            },
            "activity": "Agenturverksamhet i datorsystem. Servicebyrå",
            "employees": 18,
            "annual_turnover": 2000000,
            "capital": 530000,
            "key_personnel": [
                {
                    "name": "Bo Malmborg",
                    "position": "Verkst dir"
                }
            ],
            "establishment_year": 1966
        },
        "7": {
            "company_name": "ARLÖVS INDUSTRIBY AB",
            "address": "Arlöv, Länsmansg 5-Stortorget 1",
            "phone_number": "040-43 05 40",
            "activity": "Modul-byggande. Förvaltar industribyggnader",
            "establishment_year": 1965
        },
        "8": {
            "company_name": "SLÄPVAGNSKOPPLINGAR AB",
            "address": "Vänersborg 1, Box 216",
            "phone_number": "0521-180 60",
            "bank_details": {
                "bankgiro": "88-8662",
                "postgiro": "280801"
            },
            "activity": "Tillverkar släpvagnskopplingar för motorfordon",
            "varunamn": "VBG-produkter",
            "employees": 75,
            "annual_turnover": 8300000,
            "capital": 100000,
            "key_personnel": [
                {
                    "name": "Herman U Krefting",
                    "position": "Verkst dir"
                }
            ],
            "establishment_year": 1950
        },
        "9": {
            "company_name": "MOTALA VERKSTAD, AB",
            "address": "Motala 1, Fack",
            "phone_number": "0141-160 00",
            "activity": "Tillverkar hydrauliska pressar, spånskiveanläggningar, marina produkter, rostfria diskbänkar, sjukhusutrustningar",
            "employees": 1650,
            "annual_turnover": 150000000,
            "capital": 16000000,
            "key_personnel": [
                {
                    "name": "Anders Wingstrand",
                    "position": "Verkst dir"
                }
            ],
            "establishment_year": 1822
        },
        "10": {
            "company_name": "TJUSTORPS TEGELBRUKS AB",
            "address": "Svedala",
            "phone_number": "040-44 70 94",
            "activity": "Tillverkar fasadtegel",
            "capital": 2000000,
            "key_personnel": [
                {
                    "name": "Klas Ringius",
                    "position": "Verkst dir"
                }
            ],
            "establishment_year": 1930
        },
        "11": {
            "company_name": "NÄSSJÖ SÅGBLADS. FABRIK, AB",
            "address": "Nässjö, Osterlångg 51",
            "phone_number": "0380-10102, 10236",
            "activity": "Tillverkar cirkelsåg-klingor för trä",
            "employees": 15,
            "annual_turnover": 2000000,
            "capital": 20000,
            "key_personnel": [
                {
                    "name": "Hugo Friberg",
                    "position": "Verkst dir"
                }
            ],
            "establishment_year": 1902
        }
    }
}