{
    "original": "STOCKHOLMS FRIHAMNS AB\n\nPnr 115 28\n\nStockholm, Sandhamnsg 57. Tel\n08-63 55 00. Bankgiro 700-1621.\nPost-giro 508-2. Tga Capitalport\nVerksamhet: Hamn- o\nmagasinsrörelse\n\nAntal anställda: 250\nÅrsomsättning: 16 800 000\nAktiekapital: 500 000\nVerkst dir: A Nordström\nEtableringsår: 1919.\n\nSTOCKHOLMS FÖRENADE\nSTUVERI AB\n\nPnr 104 65\n\nStockholm 15, Box 15055.\nSödermalmstorg 2. Tel 08-44 09 40.\nBankgiro 568-9468. Postgiro 53570-8.\nTga Remember\nVerksamhet: Skeppsstuveri\nAntal anställda: 216\nAktiekapital: 400 000\nVerkst dir: Ivar Söderström.\n\nSTOCKHOLMS FÖRENADE\nSTÄD AB\n\nPnr 112 27\n\nStockholm, Kungsg 84. Tel\n08-54 18 95. Bankgiro 578-0309.\nPostgiro 352838-7\n\nVerksamhet: Städning,\nfönsterputs-ning på entreprenad.\nSpecialstädning, matt- o textilvård\nAntal anställda: 500\nÅrsomsättning: 6 500 000\n\nAktiekapital: 30 000\nStyrelseordf: Dir Rune Wästerlund\nVerkst dir: Erik Källberg\nEtableringsår: 1960.\n\nSTOCKHOLMS GALVA.\nNISERINGSFABRIK AB\n\nPnr 172 39\n\nSundbyberg, Albyg 125. Tel\n08-28 92 35. Postgiro 3703-6. Tga\nGalvanus. Telex 17499\nAktiekapital: 2 400 000\nStyrelse: Bankdir Göte Engfors\n(ordf), fru Siri Collett,fru Ulla\nCol-lett-Larson, dir Ulf Collett, dir\nGustaf Sundberg, adv Bengt Cederquist\nVerkst dir: Ulf Collett\nEtableringsår: 1895\nOmbildat till aktiebolag 1939.\nModerbolag till Gävle\nGalvanise-ringsfabrik AB o Göteborgs\nGal-vaniseringsfabrik AB.\n\nSTOCKHOLMS GRAVYR.\nANSTALT, AB\n\nPnr 11120\n\nStockholm, Gamla Brog 29. Tel\n08-113910, 204269\n\nVeiksamhet: Gravyrarbeten, skyltar,\nstämplar\n\nAktiekapital: 30 000\nVerkst dir: V Mattérn\nEtableringsår: 1940.\n\nSTOCKHOLMS GUMMI.\nINDUSTRI AB\n\nse Ulvex AB.\n\nSTOCKHOLMS INDUSTRI.\nFLÄKT, AB\n\nPnr 13102\n\nNacka 2, Värmdöv 86. Box 237. Tel\n08-405005, 405040. Bankgiro\n173-2114. Postgiro 506372-2\nVerksamhet: Tillverkar ventilar\ntionsmaterial\nAktiekapital: 20000\nVerkst dir: Gunnar Felldin\nEtableringsår: 1953\nOmbildat till aktiebolag 1960.\n\nSTOCKHOLMS JÄRNVARU AB\n\nPnr 113 30\n\nStockholm, Hudiksvallsg 8. Tel\n08-23 42 40. Bankgiro 729-2253.\nPostgiro 56404-7. Tga Essjibe\nVerksamhet: Grosshandel med\njärnmanufaktur, byggnadsvaror,\nhusgeråd o verktyg\nAktiekapital: 360 000\nVerkst dir: Ake Bertilson\nEtableringsår: 1933.\n\nINDUSTRI-REKLAM, AB\n\nPnr 143 01\n\nVårby 1, Box 38. Fittja\nindustriområde. Tel 08-710 01 60. Tga\nReklamir, Stockholm\n\nVerksamhet: Tillverkar,\nimporterar o säljer reklamartiklar\nFabrik: Hägersten, Henriksberg.\nTel 08-4637 93\nAntal anställda: 24\nAktiekapital: 150 000\nStyrelse: Dir Ake Larsson (ordf).\nStig Larsson, Lennart Larsson\nVerkst din Ake Larsson\nEtableringsår: 1937.\n\nGEIGY AKTIEBOLAG\n\nPnr 600 08\n\nNorrköping 8, Box 8007. Tel\n011-11 22 20. Postgiro 177707. Telex\n64055 GEIGY S\n\nVerksamhet: Färgämnen, pigment,\nkemikalier för industrin\nAktiekapital: 2 500 000\nVerkst dir: Ragnar Ödman\nEtableringsår: 1942.\n\nGLA\n\nGLASBETONG, AB\n\nPnr 115 28\n\nStockholm NO, Sandharansg 39.\nTel 08-6354 60. Bankgiro 44-6658.\nPostgiro 190344\n\nVerksamhet: Utför\nglasbetongarbe-ten. Säljer glasblock\nAntal anställda: 22\nAktiekapital: 40 000\nVerkst dir: Karl Åström\nEtableringsår: 1941.\n\nNYME, AB\n\nPnr 150 14\n\nVagnhärad, Box 80. Tel\n0156-102 88. Bankgiro 62-4009. Postgiro\n138477\n\nVerksamhet: Tillverkar mindre\n\nmassartiklar i band o tråd\nAntal anställda: 10\nÅrsomsättning: 750 000\nAktiekapital: 45 000\nVerkst dir Fabr Ernst Sengstmann\nEtableringsår: 1945.\n\nBOJSEN &amp; CO, C V\n\nPnr 200 41\n\nMalmö 8, Box 8045. Ystadv 19.\nTel 040-866 35. Bankgiro 645-2072.\nPostgiro 148545-7. Tga Chemoil.\nTelex 3191 CHEMEX S\nVerksamhet: Import- o export av\nkemikalier, oljor o industriråvaror\nChef: Dir C-E Bojsen\nEtableringsår: 1915.\n\nLEO, AB\n\nPnr 25242\n\nHelsingborg, Hälsov. Tel\n042-1206 00. Bankgiro 863-9619.\nPostgiro 171100-1. Tga Leo\nVerksamhet: Tillverkar läkemedel\nAntal anställda: 550\nÅrsomsättning: 80 000 000\n(koncernen)\n\nAktiekapital: 22500 000\nStyrelse: f Hovrättspresident Joèl\nLaurin (ordf), adv Bertil Peyron,\ngreve Arvid Wachtmeister\nVerkst dir: Alf Eberhard\nV verkst dir: Per-Eric Schyberg\nEtableringsår: 1914\nDotterbolag i Sverige: AB\nLäkeme-dels-Distribution, AB Mekos,\nLejonets Kemiska &amp; Farmacevtiska\nFabriker AB. Samtliga i Helsingborg.\n\nLEO, B A\n\nPnr 730 40\n\nKolbäck. Tel 0220-430 5 5.\nBankgiro 810-9258. Postgiro 165691-7\nVerksamhet: Tillverkar verktyg,\njiggar o fixturer. Utför legoarbeten\nAntal anställda: 6\nÅrsomsättning: 200 000\nChef: Bengt Leo\nEtableringsår: 1954.\n\nB.S.K. MEK VERKSTAD, AB\n\nPnr 692 00\n\nKumla, Box 181. Stenev 29. Tel\n019-701 13, 790 80. Bankgiro\n60-6200. Postgiro 28311. Tga BSK\nVerksamhet: Tillverkar\nplåtrund-ningsmaskiner o bärgningskärror\nAntal anställda: 10\nÅrsomsättning: 600 000\nAktiekapital: 10 000\nVerkst dir: Harry Sandberg\nEtableringsår: 1898.\n\nRÄTTVIKS TEXTIL AB\n\nPnr 795 00\n\nRättvik, Pack 86. Tel 0248-102 50.\n\nBankgiro 79-8067. Postgiro 162778\n\nVerksamhet: Säljer ullgarner o\n\nplastmattor\n\nAntal anställda: 40\n\nÅrsomsättning: 1400000\n\nAktiekapital: 50 000\n\nVerkst dir: Yngve Andersson\n\nEtableringsår 1939.\n\nRDGLE TEGELBRUK\n\nse Olsson &amp; Co, AB P.\n\nRON NAR PS MAKADAM.\nFABRIK, AB\n\nPnr 260 22\n\nTågarp, Box 51. Tel 0418-500 33,\n502 73. Bankgiro 870-3209.\nPostgiro 536653-9\n\nVerksamhet: Tillverkar makadam\nAntal anställda: 13\nÅrsomsättning: 900 000\nAktiekapital: 40 000\nStyrelse: Dir Per Lagerberg (ordf),\ndir Gösta Grundën, civiling\nJan-Magnus Schenström\nVerkst dir Civiling Jan-Magnus\nSchenström (Malmö)\nEtableringsår: 1935.\n\nBRANDFORSÄKRINGSVERKET\n\nPnr 104 40\n\nStockholm 14, Strandv 19. Box\n14061. Tel 08-67 05 30. Bankgiro\n57-2985. Postgiro 4807. Telex 1669\nSTOCKRE S. Tga Brandverket\nVerksamhet: Skadeförsäkring (ej\nsjöförsäkring)\nVerkst dir. Gustaf Mälstad\nEtableringsår: 1782.",
    "structured": {
        "1": {
            "company_name": "STOCKHOLMS FRIHAMNS AB",
            "pnr": "115 28",
            "address": "Stockholm, Sandhamnsg 57",
            "phone_number": "08-63 55 00",
            "bank_details": {
                "bankgiro": "700-1621",
                "postgiro": "508-2"
            },
            "activity": "Hamn- o magasinsrörelse",
            "employees": 250,
            "annual_turnover": 16800000,
            "capital": 500000,
            "key_personnel": [
                {
                    "name": "A Nordström",
                    "position": "Verkst dir"
                }
            ],
            "establishment_year": 1919
        },
        "2": {
            "company_name": "STOCKHOLMS FÖRENADE STUVERI AB",
            "pnr": "104 65",
            "address": "Stockholm 15, Box 15055, Södermalmstorg 2",
            "phone_number": "08-44 09 40",
            "bank_details": {
                "bankgiro": "568-9468",
                "postgiro": "53570-8"
            },
            "activity": "Skeppsstuveri",
            "employees": 216,
            "capital": 400000,
            "key_personnel": [
                {
                    "name": "Ivar Söderström",
                    "position": "Verkst dir"
                }
            ],
            "establishment_year": 1912
        },
        "3": {
            "company_name": "STOCKHOLMS FÖRENADE STÄD AB",
            "pnr": "112 27",
            "address": "Stockholm, Kungsg 84",
            "phone_number": "08-54 18 95",
            "bank_details": {
                "bankgiro": "578-0309",
                "postgiro": "352838-7"
            },
            "activity": "Städning, fönsterputsning på entreprenad. Specialstädning, matt- o textilvård",
            "employees": 500,
            "annual_turnover": 6500000,
            "capital": 30000,
            "key_personnel": [
                {
                    "name": "Rune Wästerlund",
                    "position": "Styrelseordf"
                },
                {
                    "name": "Erik Källberg",
                    "position": "Verkst dir"
                }
            ],
            "establishment_year": 1960
        },
        "4": {
            "company_name": "STOCKHOLMS GALVANISERINGSFABRIK AB",
            "pnr": "172 39",
            "address": "Sundbyberg, Albyg 125",
            "phone_number": "08-28 92 35",
            "postgiro": "3703-6",
            "activity": "Galvanisering",
            "capital": 2400000,
            "key_personnel": [
                {
                    "name": "Göte Engfors",
                    "position": "Styrelseordf"
                },
                {
                    "name": "Siri Collett",
                    "position": "Styrelse"
                },
                {
                    "name": "Ulla Collett-Larson",
                    "position": "Styrelse"
                },
                {
                    "name": "Ulf Collett",
                    "position": "Verkst dir"
                },
                {
                    "name": "Gustaf Sundberg",
                    "position": "Verkst dir"
                },
                {
                    "name": "Bengt Cederquist",
                    "position": "Adv"
                }
            ],
            "establishment_year": 1895
        },
        "5": {
            "company_name": "STOCKHOLMS GRAVYR ANSTALT, AB",
            "pnr": "11120",
            "address": "Stockholm, Gamla Brog 29",
            "phone_number": "08-113910, 204269",
            "activity": "Gravyrarbeten, skyltar, stämplar",
            "capital": 30000,
            "key_personnel": [
                {
                    "name": "V Mattérn",
                    "position": "Verkst dir"
                }
            ],
            "establishment_year": 1940
        },
        "6": {
            "company_name": "STOCKHOLMS GUMMI INDUSTRI AB",
            "description": "se Ulvex AB."
        },
        "7": {
            "company_name": "STOCKHOLMS INDUSTRI FLÄKT AB",
            "pnr": "13102",
            "address": "Nacka 2, Värmdöv 86, Box 237",
            "phone_number": "08-405005, 405040",
            "bank_details": {
                "bankgiro": "173-2114",
                "postgiro": "506372-2"
            },
            "activity": "Tillverkar ventilationsmaterial",
            "capital": 20000,
            "key_personnel": [
                {
                    "name": "Gunnar Felldin",
                    "position": "Verkst dir"
                }
            ],
            "establishment_year": 1953
        },
        "8": {
            "company_name": "STOCKHOLMS JÄRNVARU AB",
            "pnr": "113 30",
            "address": "Stockholm, Hudiksvallsg 8",
            "phone_number": "08-23 42 40",
            "bank_details": {
                "bankgiro": "729-2253",
                "postgiro": "56404-7"
            },
            "activity": "Grosshandel med järnmanufaktur, byggnadsvaror, husgeråd o verktyg",
            "capital": 360000,
            "key_personnel": [
                {
                    "name": "Ake Bertilson",
                    "position": "Verkst dir"
                }
            ],
            "establishment_year": 1933
        },
        "9": {
            "company_name": "INDUSTRI-REKLAM AB",
            "pnr": "143 01",
            "address": "Vårby 1, Box 38, Fittja industriområde",
            "phone_number": "08-710 01 60",
            "activity": "Tillverkar, importerar o säljer reklamartiklar",
            "employees": 24,
            "capital": 150000,
            "key_personnel": [
                {
                    "name": "Ake Larsson",
                    "position": "Styrelseordf"
                },
                {
                    "name": "Stig Larsson",
                    "position": "Styrelse"
                },
                {
                    "name": "Lennart Larsson",
                    "position": "Styrelse"
                },
                {
                    "name": "Ake Larsson",
                    "position": "Verkst dir"
                }
            ],
            "establishment_year": 1937
        },
        "10": {
            "company_name": "GEIGY AKTIEBOLAG",
            "pnr": "600 08",
            "address": "Norrköping 8, Box 8007",
            "phone_number": "011-11 22 20",
            "postgiro": "177707",
            "activity": "Färgämnen, pigment, kemikalier för industrin",
            "capital": 2500000,
            "key_personnel": [
                {
                    "name": "Ragnar Ödman",
                    "position": "Verkst dir"
                }
            ],
            "establishment_year": 1942
        },
        "11": {
            "company_name": "GLASBETONG AB",
            "pnr": "115 28",
            "address": "Stockholm NO, Sandharansg 39",
            "phone_number": "08-6354 60",
            "bankgiro": "44-6658",
            "postgiro": "190344",
            "activity": "Utför glasbetongarbeten. Säljer glasblock",
            "employees": 22,
            "capital": 40000,
            "key_personnel": [
                {
                    "name": "Karl Åström",
                    "position": "Verkst dir"
                }
            ],
            "establishment_year": 1941
        },
        "12": {
            "company_name": "NYME AB",
            "pnr": "150 14",
            "address": "Vagnhärad, Box 80",
            "phone_number": "0156-102 88",
            "bankgiro": "62-4009",
            "postgiro": "138477",
            "activity": "Tillverkar mindre massartiklar i band o tråd",
            "employees": 10,
            "annual_turnover": 750000,
            "capital": 45000,
            "key_personnel": [
                {
                    "name": "Fabr Ernst Sengstmann",
                    "position": "Verkst dir"
                }
            ],
            "establishment_year": 1945
        },
        "13": {
            "company_name": "BOJSEN & CO, C V",
            "pnr": "200 41",
            "address": "Malmö 8, Box 8045, Ystadv 19",
            "phone_number": "040-866 35",
            "bankgiro": "645-2072",
            "postgiro": "148545-7",
            "activity": "Import- o export av kemikalier, oljor o industriråvaror",
            "chief": "Dir C-E Bojsen",
            "establishment_year": 1915
        },
        "14": {
            "company_name": "LEO AB",
            "pnr": "25242",
            "address": "Helsingborg, Hälsov",
            "phone_number": "042-1206 00",
            "bankgiro": "863-9619",
            "postgiro": "171100-1",
            "activity": "Tillverkar läkemedel",
            "employees": 550,
            "annual_turnover": 80000000,
            "capital": 22500000,
            "key_personnel": [
                {
                    "name": "Joèl Laurin",
                    "position": "f Hovrättspresident, Styrelseordf"
                },
                {
                    "name": "Bertil Peyron",
                    "position": "Adv"
                },
                {
                    "name": "Arvid Wachtmeister",
                    "position": "Styrelse"
                },
                {
                    "name": "Alf Eberhard",
                    "position": "Verkst dir"
                },
                {
                    "name": "Per-Eric Schyberg",
                    "position": "V verkst dir"
                }
            ],
            "establishment_year": 1914
        },
        "15": {
            "company_name": "LEO B A",
            "pnr": "730 40",
            "address": "Kolbäck",
            "phone_number": "0220-430 5 5",
            "bankgiro": "810-9258",
            "postgiro": "165691-7",
            "activity": "Tillverkar verktyg, jiggar o fixturer. Utför legoarbeten",
            "employees": 6,
            "annual_turnover": 200000,
            "chief": "Bengt Leo",
            "establishment_year": 1954
        },
        "16": {
            "company_name": "B.S.K. MEK VERKSTAD AB",
            "pnr": "692 00",
            "address": "Kumla, Box 181, Stenev 29",
            "phone_number": "019-701 13, 790 80",
            "bankgiro": "60-6200",
            "postgiro": "28311",
            "activity": "Tillverkar plåtrundningsmaskiner o bärgningskärror",
            "employees": 10,
            "annual_turnover": 600000,
            "capital": 10000,
            "key_personnel": [
                {
                    "name": "Harry Sandberg",
                    "position": "Verkst dir"
                }
            ],
            "establishment_year": 1898
        },
        "17": {
            "company_name": "RÄTTVIKS TEXTIL AB",
            "pnr": "795 00",
            "address": "Rättvik, Pack 86",
            "phone_number": "0248-102 50",
            "bankgiro": "79-8067",
            "postgiro": "162778",
            "activity": "Säljer ullgarner o plastmattor",
            "employees": 40,
            "annual_turnover": 1400000,
            "capital": 50000,
            "key_personnel": [
                {
                    "name": "Yngve Andersson",
                    "position": "Verkst dir"
                }
            ],
            "establishment_year": 1939
        },
        "18": {
            "company_name": "RDGLE TEGELBRUK",
            "description": "se Olsson & Co, AB P."
        },
        "19": {
            "company_name": "RONNARPS MAKADAM FABRIK AB",
            "pnr": "260 22",
            "address": "Tågarp, Box 51",
            "phone_number": "0418-500 33, 502 73",
            "bankgiro": "870-3209",
            "postgiro": "536653-9",
            "activity": "Tillverkar makadam",
            "employees": 13,
            "annual_turnover": 900000,
            "capital": 40000,
            "key_personnel": [
                {
                    "name": "Per Lagerberg",
                    "position": "Styrelseordf"
                },
                {
                    "name": "Gösta Grundën",
                    "position": "Styrelse"
                },
                {
                    "name": "Jan-Magnus Schenström",
                    "position": "Civiling, Styrelse"
                },
                {
                    "name": "Jan-Magnus Schenström",
                    "position": "Verkst dir (Malmö)"
                }
            ],
            "establishment_year": 1935
        },
        "20": {
            "company_name": "BRANDFORSÄKRINGSVERKET",
            "pnr": "104 40",
            "address": "Stockholm 14, Strandv 19, Box 14061",
            "phone_number": "08-67 05 30",
            "bankgiro": "57-2985",
            "postgiro": "4807",
            "activity": "Skadeförsäkring (ej sjöförsäkring)",
            "chief": "Gustaf Mälstad",
            "establishment_year": 1782
        }
    }
}