{
    "original": "YSTADS ALLEHANDA AB\n\nPnr 271 00\n\nYstad, Box 89. Lilla Norreg 9. Tel\n0411-13 6 00\n\nVerksamhet:\nFörmögenhetsförvaltning\n\nAktiekapital: 360 000\nEtableringsår 1873\nOmbildat till aktiebolag 1906.\nSe vidare Bjurström &amp; Co\nBoktryckeri.\n\nYSTADS CENTRAL.\nTRYCKERI, AB\n\nPnr 27100\n\nYstad, Stallg 4-8. Tel 0411-10115,\n10612. Bankgiro 670-2229.\nPostgiro 31139-9\n\nVerksamhet: Broschyrer,\nreklamtryck, blanketter mm i boktryck\no offset\n\nAntal anställda: 25\nAktiekapital: 120 000\nVerkst din Richard Nilstam\nBoktryckare: Knut Nilstam\nEtableringsår: 1925.\n\nYSTADS EXPORT AB\n\nPnr 27100\n\nYstad, Bronsg 8. Box 10. Tel\n0411-170 30. Bankgiro 202-0980. Tga\nPolykemi.\n\nTelex 32299 POLYKEM S\nVerksamhet: Företaget driver\nhandel med plast- o textilavfall.\nSortering o packning vid fabrik i\nTomelilla\n\nFabrik: Tel 0417-126 20\nAntal anställda: 9\nÅrsomsättning: 1000 000\nVerkst dir: Ing Hugo Jönsson\nDir: Karl G Jeppsson (Tomelilla)\nEtableringsår: 1968.\n\nKEREMA-SALÉN AB\n\nPnr 35103\n\nVäxjö 1, Storg 68. Box 56. Tel\n0470-20190. Bankgiro 84-3454.\nPostgiro 263768-4. Tga Kerema\nVerksamhet: Tillverkar klänningar\no dräkter\n\nFörsäljningskonton Stockholm C,\nMäster Samuelsg 42. Box 40027,\nSthlm 40. Tel 08-24 43 35\nVarunamn: Kerema, Salén, Elysée\nAntal anställda: 60\nÅrsomsättning: 5 000 000\nAktiekapital: 225 000\nVerkst dir: Carl W Petri\nEtableringsår: 1943.\n\nKEXMAN\nIMPORTSPECIALISTEN AB\n\nPnr 60103\n\nNorrköping 1, Box 185. Saltängsg\n13. Tel 011-10 70 00. Bankgiro\n125-2782. Postgiro 173201-5\nVerksamhet: Säljer kex i parti\n\nAktiekapital: 5 000\nVerkst dir: Anders Tubbin\nEtableringsår: 1957.\n\nKFAI AB (KOOPERATIVA\nFÖRBUNDET ARKITEKT, och\nINGENJORSKONTORET AB)\n\nPnr 104 65\n\nStockholm 15, Magnus Ladulåsg 11.\nFack. Tel 08-44 90 60. Bankgiro\n56-0244. Postgiro 10. Telex 1490.\nTga Kooperativa\n\nVerksamhet: Projektering av\nbyggnader o installationer,\nbyggadmi-nistration m m\nAntal anställda: 285\nÅrsomsättning: 36 600 000\nStyrelse: Dir Kurt Lindfors (ordf),\ndir Nils Ahlkvist, dir Bertil\nEkberg, prof ark SAR Gunnar\nHenriksson, dir Karl-Erik Persson, dir\nAdolf Lundmark\n\nVerkst dir: Prof ark SAR Gunnar\nHenriksson\n\nÖvriga chefer: Chefsark Gunnar\nSavås (Arkitektbyrå\nA—Detaljhandel), chefsark Valdemar Axelsson,\n(Arkitektbyrå B —Industri o lager),\növering Erik Brunskog\n(Byggadmi-nistrativa byrån), övering Enno\nPenno (Konstruktionsbyrån),\növering Knut Stoltz (Installationsbyrån),\nInformationschef: Vakant\nAdministrations- o ekonomichef:\nCivilekonom Gösta Christensson\nEtableringsår: 1924\nOmbildat till aktiebolag 1965.\n\nKGK MEK VERKSTAD AB\n\nPnr 53200\n\nSkara, Kämpag 5. Box 50. Tel\n0511-10452. Bankgiro 350-4040.\nPostgiro 280901-0\nVerksamhet: Tillverkar\nluftkompressorer, färgsprutor,\nrenblås-ningspistoler, transportblock,\nrördubbar m m\n\nVerkst dir: K Wallentin.\n\nKIENZLE APPARATER I\nGOTEBORG AB\n\nPnr 41108\n\nGöteborg, Trädgårdsg 6. Tel\n031-17 88 55. Bankgiro 89-0309.\nPostgiro 622877\n\nVerksamhet: Försäljning o service\nav färdskrivare, registrerande\nkontrollapparater, diagramblad o\nparkeringsmätare\nVarunamn: Kienzle\nAktiekapital: 30 000\nVerkst dir: Algot Samuelson\nEtableringsår: 1961.\n\nGINBERG AB, J A\n\nPnr 411 13\n\nGöteborg, Smedjeg 5. Tel\n031-10 54 85, 10 54 84. Bankgiro\n506-1639. Postgiro 25564-6\nVerksamhet: Grosshandel i smör,\nost o ägg\nAntal anställda: 4\nÅrsomsättning: 2 000 000\nChef: Lennart Lennestam\nEtableringsår: 1922.\n\nodeshogsverken ab\n\nPnr 599 00\n\nOdeshög, Box 52. Industrig 10.\nTel 0144-107 70, 105 28. Bankgiro\n133-7773. Postgiro 580282-2\nVerksamhet: Transportanordningar.\nMekaniska arbeten m m\nAntal anställda: 20\nÅrsomsättning: 2 000 000\nAktiekapital: 75 000\nVerkst dir: Erie Svensson\nEtableringsår: 1900.\n\nBERGSTRÖM AB, AXEL V\n\nPnr 17121\n\nSolna 1, Box 1037. Pyramidv 7.\nTel 08-82 04 70. Bankgiro 172-8104.\nPostgiro 3092-4.\nTga Fotoaxel, Stockholm.\nTelex 10512 PHOTOAX S\nVerksamhet: Generalagent för\nNIKON fotografiska o optiska artiklar\nVarunamn: Nikon\n.Antal anställda: 24\nÅrsomsättning: 6 000 000\nAktiekapital: 50 000\nVerkst dir: Axel Bergström\nEtableringsår: 1959.\n\nBERGSTRÖMS KEMISKA\nFABRIKER, AB B\n\nPnr 15010\n\nGnesta. Tel 0158-11200. Bankgiro\n700-1100. Postgiro 151635-0. Tga\nBergolin\n\nVerksamhet: Tillverkar\navfettnings-o rengöringsmedel\nVerkst dir: Disp Bonde Bergström\nEtableringsår: 1934.\n\nBERGSTRÖM AB,\nCIVIL-INGENJÖR SVR GUNNAR\n\nPnr 41139\n\nGöteborg, Västgötag 11. Tel\n031-1807 33, 1807 35. Bankgiro\n491-3620. Postgiro 623533-7\nVerksamhet: Byggnadsteknisk\nkonsultation\nAktiekapital: 10 000\nVerkst dir: Gunnar Bergström\nEtableringsår: 1962.\n\nOMEGA.FI LM AB\n\nPnr 11137\n\nStockholm, Apelbergsg 58. Tel\n08-23 7160. Postgiro 500290-2. Tga\nAiromega. Telex 10026\nVerksamhet: Produktion av\nTV-film, långfilm, PR-film\nAktiekapital: 60 000\nVerkst dir: Ing Lennart Berns\nEtableringsår 1958.\n\nGULLHOGENSBRUK, AB\n\nPnr 54101\n\nSkövde 1, Box 33. Tel 0500-106 20.\nTelex 5060. Tga Gullhögen\nVerksamhet: Cementfabrik i\nSkövde. Tillverkar cement o bindemedel\nAntal anställda: 475\nAktiekapital: 40 000 000\nVerkst dir: Bo Rydin\nEtableringsår: 1916.\n\nPERSSON, AB HENNING\n\nPnr 510 35\n\nBoUebygd, Grönkullen. Tel\n033-85210. Bankgiro 420-1489.\nPostgiro 47871-9. Tga Henpers\nVerksamhet: Tillverkar o säljer\nfärger, fernissor, tvål o kern tekn\nartiklar\n\nExportkontor: 403 13 Göteborg 2,\nSurbrunns g 6. Box 2190. Tel\n031-17 2730. Tga Henpers\nAntal anstäUda: 145\nÅrsomsättning: 15 000 000\nAktiekapital: 1700 000\nStyrelse: Adv Stig Wiberg (ordf),\ndisp Roland Arvidsson, dir\nHenning Persson, herr Staffan Persson\nVerkst dir: Henning Persson\nV verkst din Disp Roland\nArvidsson\n\nEtableringsår: 1940.\n\nPERSSONS BYGGNADS AB,\nHENNING\n\nPnr 217 61\n\nMalmö, ABC-husen, John\nEricssons v. Tel 040-764 35. Bankgiro\n873-7163. Postgiro 436508-6\nVerksamhet: Byggnadsentreprenör\nAktiekapital: 250 000\nEtableringsår: 1938.\n\nPERSSONS\nREDSKAPSVERKSTAD, AB HJ\n\nPnr 26201\n\nÄngelholm 1, Box 59. Tel\n042-690 34. Bankgiro 294-2373.\nPostgiro 93648-4\n\nVerksamhet: Tillverkar\njordbearbet-ningsredskap, harvar, hackor,\nlastflak för traktorer samt reservdelar.\nSäljer combivagnar\nAntal anstäUda: 30\nÅrsomsättning: 3 000 000\nAktiekapital: 100000\nVerkst dir: Erie Persson\nEtableringsår: 1914.\n\nEXAKTOR, ELEKTRISKA AB\n\nPnr 33101\n\nVärnamo 1, Malmöv. Pack. Tel\n0370-117 00, 11710. Bankgiro\n291-7086. Postgiro 251698-6. Tga\nExak-torbolag. Telex 70067\nVerksamhet: Elektrisk\nbelysningsarmatur\n\nAntal anställda: 180\nÅrsomsättning: 15 000000\nAktiekapital: 800 000\nVerkst dir: Nils Sigbrandt\nEtableringsår: 1945.\n\nEXCELSIOR AB, KARTONG.\nFABRIKEN\n\nPnr 400 60\n\nGöteborg 6, Box 6061. von Utfallsg.\nTel 031-26 2060. Bankgiro\n410-0764. Postgiro 40085-3\nVerksamhet: Tillverkar kartonger,\nkapslar, runda pappburkar,\nva-cuumformat emballage,\nskin-pack-ning\n\nAntal anställda: 100\nÅrsomsättning: 8 000 000\nAktiekapital: 240 000\nChefer: Disp Tage Jerkander, disp\nStig-Arne Jerkander\nEtableringsår: 1897\nOmbildat till aktiebolag 1912.\n\nEXOVERKEN AB\n\nPnr 381 01\n\nKalmar 1, Pack. Polhemsg 1. Tel\n0480-221 20. Bankgiro 853-6799.\nPostgiro 171322-1. Tga Exo.\nTelex 4865 EXO S\nVerksamhet: Tillverkar\nvärmeledningspannor o elektr\nvarmvattenberedare o gaffelvagnar\nRepresentanter: 12108 Stockholm.\nPack. Johanneshov 8. Tel\n08-8157 62\n\n411 25 Göteborg. Viktoriag 20. Tel\n031-1143 68\n\n56100 Huskvarna, Nyg 2 B. Tel\n036-13 5400\n\n21217 Malmö, Höstg 31. Tel\n040-93 0415\n\n826 00 Söderhamn, Box 57. Tel\n0270-108 00\nVarunamn: Exo\nAntal anställda: 250\nÅrsomsättning: 22 000 000\nAktiekapital: 200 000\nStyrelse: Civiling Harry Hill,\ndir Göran Hill\nVerkst dir: Dir Göran Hill\nEtableringsår: 1939.\n\nSVENSKA THORN AB\n\nPnr 16120\n\nBromma 20, Box 20075. Bällstav\n30-32. Tel 08-98 19 10: Bankgiro\n724-9568. Postgiro 55202-6. Tga\nSwedthorn. Telex 10106\nVerksamhet Marknadsför Atlas\nbelysningsprodukter\nFilialer: Göteborg, Malmö,\nSundavall\n\nAktiekapital: 100000\nVeikst dir: Lars Ljunggren\nEtableringsår: 1945.",
    "structured": {
        "1": {
            "company_name": "YSTADS ALLEHANDA AB",
            "pnr": "271 00",
            "address": "Ystad, Box 89. Lilla Norreg 9.",
            "phone_number": "0411-13 6 00",
            "activity": "Förmögenhetsförvaltning",
            "capital": 360000,
            "establishment_year": 1873
        },
        "2": {
            "company_name": "YSTADS CENTRAL. TRYCKERI, AB",
            "pnr": "27100",
            "address": "Ystad, Stallg 4-8.",
            "phone_number": "0411-10115, 10612",
            "bank_details": {
                "bankgiro": "670-2229",
                "postgiro": "31139-9"
            },
            "activity": "Broschyrer, reklamtryck, blanketter mm i boktryck o offset",
            "employees": 25,
            "capital": 120000,
            "establishment_year": 1925
        },
        "3": {
            "company_name": "YSTADS EXPORT AB",
            "pnr": "27100",
            "address": "Ystad, Bronsg 8. Box 10.",
            "phone_number": "0411-170 30",
            "bank_details": {
                "bankgiro": "202-0980",
                "telex": "32299 POLYKEM S"
            },
            "activity": "Företaget driver handel med plast- o textilavfall. Sortering o packning vid fabrik i Tomelilla",
            "employees": 9,
            "annual_turnover": "1000 000",
            "key_personnel": [
                {
                    "name": "Ing Hugo Jönsson",
                    "position": "Verkst dir"
                },
                {
                    "name": "Karl G Jeppsson",
                    "position": "Dir (Tomelilla)"
                }
            ],
            "establishment_year": 1968
        },
        "4": {
            "company_name": "KEREMA-SALÉN AB",
            "pnr": "35103",
            "address": "Växjö 1, Storg 68. Box 56.",
            "phone_number": "0470-20190",
            "bank_details": {
                "bankgiro": "84-3454",
                "postgiro": "263768-4"
            },
            "activity": "Tillverkar klänningar o dräkter",
            "sales_accounts": "Stockholm C, Mäster Samuelsg 42. Box 40027, Sthlm 40. Tel 08-24 43 35",
            "brands": "Kerema, Salén, Elysée",
            "employees": 60,
            "annual_turnover": "5 000 000",
            "capital": 225000,
            "key_personnel": {
                "name": "Carl W Petri",
                "position": "Verkst dir"
            },
            "establishment_year": 1943
        },
        "5": {
            "company_name": "KEXMAN IMPORTSPECIALISTEN AB",
            "pnr": "60103",
            "address": "Norrköping 1, Box 185. Saltängsg 13.",
            "phone_number": "011-10 70 00",
            "bank_details": {
                "bankgiro": "125-2782",
                "postgiro": "173201-5"
            },
            "activity": "Säljer kex i parti",
            "capital": "5000",
            "key_personnel": {
                "name": "Anders Tubbin",
                "position": "Verkst dir"
            },
            "establishment_year": 1957
        },
        "6": {
            "company_name": "KFAI AB (KOOPERATIVA FÖRBUNDET ARKITEKT, och INGENJORSKONTORET AB)",
            "pnr": "104 65",
            "address": "Stockholm 15, Magnus Ladulåsg 11. Fack.",
            "phone_number": "08-44 90 60",
            "bank_details": {
                "bankgiro": "56-0244",
                "postgiro": "10",
                "telex": "1490 Tga Kooperativa"
            },
            "activity": "Projektering av byggnader o installationer, byggadmi-nistration m m",
            "employees": 285,
            "annual_turnover": "36 600 000",
            "key_personnel": [
                {
                    "name": "Prof ark SAR Gunnar Henriksson",
                    "position": "Verkst dir"
                },
                {
                    "name": "Chefsark Gunnar Savås",
                    "position": "Chefsark (Arkitektbyrå A—Detaljhandel)"
                },
                {
                    "name": "Chefsark Valdemar Axelsson",
                    "position": "Chefsark (Arkitektbyrå B—Industri o lager)"
                },
                {
                    "name": "övering Erik Brunskog",
                    "position": "Byggadmi-nistrativa byrån"
                },
                {
                    "name": "övering Enno Penno",
                    "position": "Konstruktionsbyrån"
                },
                {
                    "name": "övering Knut Stoltz",
                    "position": "Installationsbyrån"
                }
            ],
            "establishment_year": 1924
        },
        "7": {
            "company_name": "KGK MEK VERKSTAD AB",
            "pnr": "53200",
            "address": "Skara, Kämpag 5. Box 50.",
            "phone_number": "0511-10452",
            "bank_details": {
                "bankgiro": "350-4040",
                "postgiro": "280901-0"
            },
            "activity": "Tillverkar luftkompressorer, färgsprutor, renblås-ningspistoler, transportblock, rördubbar m m",
            "key_personnel": {
                "name": "K Wallentin",
                "position": "Verkst dir"
            },
            "establishment_year": 1900
        },
        "8": {
            "company_name": "KIENZLE APPARATER I GOTEBORG AB",
            "pnr": "41108",
            "address": "Göteborg, Trädgårdsg 6.",
            "phone_number": "031-17 88 55",
            "bankgiro": "89-0309",
            "postgiro": "622877",
            "activity": "Försäljning o service av färdskrivare, registrerande kontrollapparater, diagramblad o parkeringsmätare",
            "brands": "Kienzle",
            "capital": 30000,
            "key_personnel": {
                "name": "Algot Samuelson",
                "position": "Verkst dir"
            },
            "establishment_year": 1961
        },
        "9": {
            "company_name": "GINBERG AB, J A",
            "pnr": "411 13",
            "address": "Göteborg, Smedjeg 5.",
            "phone_number": "031-10 54 85, 10 54 84",
            "bank_details": {
                "bankgiro": "506-1639",
                "postgiro": "25564-6"
            },
            "activity": "Grosshandel i smör, ost o ägg",
            "employees": 4,
            "annual_turnover": "2 000 000",
            "key_personnel": {
                "name": "Lennart Lennestam",
                "position": "Chef"
            },
            "establishment_year": 1922
        },
        "10": {
            "company_name": "odeshogsverken ab",
            "pnr": "599 00",
            "address": "Odeshög, Box 52. Industrig 10.",
            "phone_number": "0144-107 70, 105 28",
            "bank_details": {
                "bankgiro": "133-7773",
                "postgiro": "580282-2"
            },
            "activity": "Transportanordningar. Mekaniska arbeten m m",
            "employees": 20,
            "annual_turnover": "2 000 000",
            "capital": 75000,
            "key_personnel": {
                "name": "Erie Svensson",
                "position": "Verkst dir"
            },
            "establishment_year": 1900
        }
    }
}