{
    "original": "APOTEKARNAS KEMISKA\nLABORATORIUM AB (AKLA)\n\nPnr 104 35\n\nStockholm 23, Norrtullsg 41-43. Box\n23146. Tel 08-24 79 30. Bankgiro\n29-5804. Postgiro 1670. Tga\nApotekskemi\n\nVerksamhet: Tillverkar\nförbands-o sjukvårdsartiklar\nAntal anställda: 75\nÅrsomsättning: 7 000 000\nAktiekapital: 100 000\nVerkst dir: Bertil Larsson\nEtableringsår: 1928.\n\nAPOTEKARNES DROGHANDEL\nAB ADA\n\nPnr 401 20\n\nGöteborg 1, Box 49. Importg 16-18.\nTel 031-52 04 00. Bankgiro\n501-1929. Postgiro 5439-5. Tga\nDrogvall. Telex 2255\nVerksamhet: Distribution till\napotek\n\nDistributionscentraler:\n\n20122 Malmö 1, Box 227. Celsiusg\n41. Tel 040-93 43 00. Telex 3156\n102 71 Stockholm 9, Box 9052.\nSjöviksbacken 19. Tel 08-19 00 40.\nTelex 1655\n\n901 04 Umeå 1, Box 306.\nMarie-holmsv 12. Tel 090-13 20 80. Telex\n6713\n\nAktiekapital: 5 000 000\nVerkst dir: Ake Nohrlander\nEtableringsår: 1921.\n\nAPOTEKSVAROR LÄKEKEMI,\nAB\n\nPnr 12609\n\nHägersten 9, Box 902. Jakobsdalsv\n14-16. Tel 08-454020, 45 22 02.\nBankgiro 47-7303. Postgiro\n1932 1 0-2. Tga Apoteksvaror\nVerksamhet: Tillverkar läkemedel,\nkem tekn preparat o\nveterinärmedicin samt näringspreparat\nAktiekapital: 25 000\nÄgare o chef: Ing K G Rosdahl\nEtableringsår: 1954.\n\nAPOTEKSVARUCENTRALEN\nVITRUM APOTEKARE AB\n\nPnr 102 24\n\nStockholm 12, Franzëng 9. Box\n12170. Tel 08-5410 40. Bankgiro\n73-3827. Postgiro 1151.\nTga Vitrum. Telex 10315\nVerksamhet: Engroshandel med\nläkemedel. Läkemedelsfabrik\nAntal anställda: 370\nAktiekapital: 2 268 000\nVerkst dir: Gunnar Källrot\nV verkst dir: Sigvard Lindhagen\nEtableringsår: 1877\nDotterbolag i Danmark, Frankrike,\nItalien.\n\nAPPARATKEMISKA AB AKA\n\nPnr 104 65\n\nStockholm 15, Box 15071. Saltsjö\nJärla Industriområde, Nacka. Tel\n08-716 26 60. Tga Akaval.\nTelex 17049 AKAVAL S\nVerksamhet: Filtrering, dosering,\ninstrumentering o vattenbehandling\nVarunamn: Automatica, Bestå,\nCuno, Dowex, Foxboro, PSI\nAntal anställda: 70\nÅrsomsättning: 25 000 000\nAktiekapital: 100 000\n\nARA\n\nStyrelse: Prof Ingvar Jung (ordf),\ning Lennart Hultkrantz, civiling\nLars Hård, civiling Nils Nilsson,\nciviling Bror Wenke\nVerkst dir: Civiling Nils Nilsson\nEtableringsår: 1951.\n\nAPPELGRENS\nBORSTFABRIK AB\n\nPnr 11621\n\nStockholm, Götg 66. Tel\n08-4153 59\n\nVerksamhet: Tillverkar borstar.\nSpecialitet: industriborstar\nAktiekapital: 15 000\nVerkst dir: Fru I Bang\nEtableringsår: 1959.\n\nSWALANDER &amp; STEN AB\n\nPnr 40011\n\nGöteborg 18, Box 18004. Tel\n031-20 17 40, 18 56 48. Bankgiro\n420-1760. Postgiro 243501-4. Tga\nNordpapp. Telex 21112\nVerksamhet: Export av papper,\npapp, byggnadsplattor m m\nAntal anställda: 15\nAktiekapital: 650 000\nVerkst dir: Bertil Swalander\nEtableringsår: 1947.\n\nLEJE&amp; THURNE AB\n\nPnr 103 22\n\nStockholm 16, Nybrokajen 7. Box\n16063. Tel 08-23 2185. Bankgiro\n33-0185. Postgiro 3445. Telex\n1566. Tga Lethur\n\nVerksamhet: Egna konstruktioner o\nagenturer, maskiner för cellulosa- o\npappersindustrin, kommunal o\nindustriell vattenrening, slambehandling.\nFörsäljning av papper\nFilial: Leje &amp; Thurne AB, LTH\nBüro Dusseldorf,\nLindemann-strasse 23, 4 Dusseldorf\nAntal anställda: 26\nÅrsomsättning: 22 000 000\n(1/1-68-30/6-69)\n\nAktiekapital: 400 000\n\nStyrelse: Dir Börje Gawell (ordf),\nadv Styrbjörn Gärde, dir Rudolf\n\nWoode\n\nVerkst dir: Rudolf Woode\nEtableringsår: 1923\nDotterbolag: Leje &amp; Thurne France\nSA, Rue Tronchet 29, Paris 8.\n\nLEJMARK AB, INGENIORS.\nFIRMA ROBERT\n\nPnr 384 00\n\nBlomstermåla, Timmernabben. Tel\n0499-230 12. Tga Lejmarks\nVerksamhet: Tillverkar Tretong.\nKonsulterande verksamhet\nAntal anställda: 7\nAktiekapital: 100 000\nVerkst dir: Disp Olle Lejmark\nEtableringsår: 1922.\n\nBERO I OREBRO AB\n\nPnr 701 06\n\nÖrebro 1, Nyg 46. Box 439. Tel\n019-12 40 35\n\nVerksamhet: Marknadsför i\nhuvudsak soppor, konserver, sylt o saft\ntill storkök. Generalagent i Sverige\nför Honig Food Ltd, Holland vilka\ntillverkar bl a vakuumtorkade\nsoppor\n\nVarunamn: Bero\nAntal anställda: 11\nÅrsomsättning: 3 000 000\nAktiekapital: 100 000\nVerkst dir: Bertil Roman\nEtableringsår: 1953.\n\nBEROL AB\n\nse MoDoKemi AB.\n\nBERRUM &amp; JORCK, AB\n\nPnr 41116\n\nGöteborg, Korsg 12. Tel\n031-17 15 50. Bankgiro 337-2141.\nPostgiro 46597-1. Tga Olemabe.\nTelex 2522\n\nVerksamhet: Säljer textilvaror o\n\nkonfektionstillbehör\n\nAntal anställda: 4\n\nÅrsomsättning: 6 000 000\n\nAktiekapital: 10 000\n\nVerkst dir: Carl-Eric Andelius\n\nEtableringsår: 1931.\n\nEIR\n\nAntal anställda: 20\nÅrsomsättning: 2 000 000\nAktiekapital: 30000\nVerkst dir: Ing Herbert Einarsson\nEtableringsår: 1966.\n\nWIKLUND AB, GUNNAR\n\nPnr 11135\n\nStockholm, Kungsg 38. Tel\n08-20 62 72. Bankgiro 722-2441.\nPostgiro 195517-8. Tga Gunwik.\nTelex 17159\n\nVerksamhet: Importagenter för\nelektronikmateriel\nAntal anställda: 3\nÅrsomsättning: 1900 000\nAktiekapital: 5 000\nVerkst din Civiling Gunnar\nWiklund\n\nEtableringsår: 1937.\n\nCEVECE MONTAN AB\n\nPnr 402 32\n\nGöteborg 7, Första Långg 21. Box\n7127. Tel 031-24 39 02, 24 39 05.\nTelex 2241\n\nVerksamhet: Import o export av\njärn o stål\nAntal anställda: 8\nÅrsomsättning: 30 000 000\nAktiekapital: 200 000\nVerkst dir: Paul van der Vliet\nEtableringsår: 1962.\n\nFYRIS, MASKINAFFÄREN\n\nPnr 753 21\n\nUppsala, Kungsg 32. Tel\n018-14 90 15. Bankgiro 802-2030.\nPostgiro 135106-3. Tga Fyrismaskin\nVerksamhet: Försäljning o service\nav kontorsmaskiner, kontorsmöbler,\n\nbutiksmaskiner o butiksinredningar\n.Antal anställda: 12\nÅrsomsättning: 1100 000\nChef: Dir Gunnar Hogell\nEtableringsår: 1937.\n\nFAGELFORS TRÄINDUSTRI,\nAB\n\nPnr 570 75\n\nFågelfors. Tel 0491-510 32, 510 35.\nBankgiro 855-3109. Postgiro\n335406-5\n\nVerksamhet: Tillverkar träfönster\nAntal anställda: 25\nÅrsomsättning: 1700 000\nAktiekapital: 30 000\nVerkst dir: Harald Hjelm\nEtableringsår: 1947.\n\nSUNNE CEMENTGJUTERI\n\nPnr 686 00\n\nSunne, Fabriksg 16. Tel\n0565-102 78, 118 05. Bankgiro 444-9377.\nPostgiro 88057-5\nVerksamhet: Tillverkar G-rör,\nF-rör, vägrör o betonghålsten\nAntal anstäUda: 9\nChef: Stig Ekström\nEtableringsår: 1967.\n\nOTKER AB\n\nPnr 17165\n\nSolna, Bagartorpsringen 51. Tel\n08-85 02 80. Bankgiro 620-8276.\nPostgiro 572750-8. Tga\nOetkerbo-laget\n\nVerksamhet: Import o försäljning\nav livsmedel\nAntal anställda: 30\nAktiekapital; 550 000\nVerkst dir. Folke W Nilsson\nEtableringsår: 1961.\n\nOWEDSKLOSTERS\nSTEN-INDUSTRIER, AB\n\nPnr 240 35\n\nHarlösa. Tel 046-630 02, 63016.\nBankgiro 662-7509. Postgiro\n39772-4\n\nVerksamhet: Framställer makadam,\nkrossgrusblandningar, stenmjöl\nAntal anställda: 10\nÅrsomsättning: 800 000\nAktiekapital: 80 000\nStyrelse: Frih Otto Ramel (ordf),\nfrih Hans Ramel\n\nVerkst ledamot: Frih Otto Ramel\nKamrer: Erik R Olsson\nEtableringsår: 1915.",
    "structured": {
        "1": {
            "company_name": "APOTEKARNAS KEMISKA LABORATORIUM AB (AKLA)",
            "pnr": "104 35",
            "address": "Stockholm 23, Norrtullsg 41-43. Box 23146.",
            "phone_number": "08-24 79 30",
            "bank_details": {
                "bankgiro": "29-5804",
                "postgiro": "1670"
            },
            "activity": "Tillverkar förbands-o sjukvårdsartiklar",
            "employees": 75,
            "annual_turnover": 7000000,
            "capital": 100000,
            "key_personnel": [
                {
                    "name": "Bertil Larsson",
                    "position": "Verkst dir"
                }
            ],
            "establishment_year": 1928
        },
        "2": {
            "company_name": "APOTEKARNES DROGHANDEL AB ADA",
            "pnr": "401 20",
            "address": "Göteborg 1, Box 49. Importg 16-18.",
            "phone_number": "031-52 04 00",
            "bank_details": {
                "bankgiro": "501-1929",
                "postgiro": "5439-5"
            },
            "activity": "Distribution till apotek",
            "capital": 5000000,
            "key_personnel": [
                {
                    "name": "Ake Nohrlander",
                    "position": "Verkst dir"
                }
            ],
            "establishment_year": 1921
        },
        "3": {
            "company_name": "APOTEKSVAROR LÄKEKEMI AB",
            "pnr": "12609",
            "address": "Hägersten 9, Box 902. Jakobsdalsv 14-16.",
            "phone_number": "08-454020, 45 22 02",
            "bank_details": {
                "bankgiro": "47-7303",
                "postgiro": "1932 1 0-2"
            },
            "activity": "Tillverkar läkemedel, kem tekn preparat o veterinärmedicin samt näringspreparat",
            "capital": 25000,
            "key_personnel": [
                {
                    "name": "Ing K G Rosdahl",
                    "position": "Ägare o chef"
                }
            ],
            "establishment_year": 1954
        },
        "4": {
            "company_name": "APOTEKSVARUCENTRALEN VITRUM APOTEKARE AB",
            "pnr": "102 24",
            "address": "Stockholm 12, Franzëng 9. Box 12170.",
            "phone_number": "08-5410 40",
            "bank_details": {
                "bankgiro": "73-3827",
                "postgiro": "1151"
            },
            "activity": "Engroshandel med läkemedel. Läkemedelsfabrik",
            "employees": 370,
            "capital": 2268000,
            "key_personnel": [
                {
                    "name": "Gunnar Källrot",
                    "position": "Verkst dir"
                },
                {
                    "name": "Sigvard Lindhagen",
                    "position": "V verkst dir"
                }
            ],
            "establishment_year": 1877
        },
        "5": {
            "company_name": "APPARATKEMISKA AB AKA",
            "pnr": "104 65",
            "address": "Stockholm 15, Box 15071. Saltsjö Järla Industriområde, Nacka.",
            "phone_number": "08-716 26 60",
            "activity": "Filtrering, dosering, instrumentering o vattenbehandling",
            "employees": 70,
            "annual_turnover": 25000000,
            "capital": 100000,
            "key_personnel": [
                {
                    "name": "Ingvar Jung",
                    "position": "Styrelse Ordf"
                },
                {
                    "name": "Lennart Hultkrantz",
                    "position": "Styrelse Medlem"
                },
                {
                    "name": "Lars Hård",
                    "position": "Styrelse Medlem"
                },
                {
                    "name": "Nils Nilsson",
                    "position": "Styrelse Medlem"
                },
                {
                    "name": "Bror Wenke",
                    "position": "Styrelse Medlem"
                },
                {
                    "name": "Civiling Nils Nilsson",
                    "position": "Verkst dir"
                }
            ],
            "establishment_year": 1951
        },
        "6": {
            "company_name": "APPELGRENS BORSTFABRIK AB",
            "pnr": "11621",
            "address": "Stockholm, Götg 66",
            "phone_number": "08-4153 59",
            "activity": "Tillverkar borstar. Specialitet: industriborstar",
            "capital": 15000,
            "key_personnel": [
                {
                    "name": "Fru I Bang",
                    "position": "Verkst dir"
                }
            ],
            "establishment_year": 1959
        },
        "7": {
            "company_name": "SWALANDER & STEN AB",
            "pnr": "40011",
            "address": "Göteborg 18, Box 18004",
            "phone_number": "031-20 17 40, 18 56 48",
            "bank_details": {
                "bankgiro": "420-1760",
                "postgiro": "243501-4"
            },
            "activity": "Export av papper, papp, byggnadsplattor m m",
            "employees": 15,
            "capital": 650000,
            "key_personnel": [
                {
                    "name": "Bertil Swalander",
                    "position": "Verkst dir"
                }
            ],
            "establishment_year": 1947
        },
        "8": {
            "company_name": "LEJE & THURNE AB",
            "pnr": "103 22",
            "address": "Stockholm 16, Nybrokajen 7. Box 16063",
            "phone_number": "08-23 2185",
            "bank_details": {
                "bankgiro": "33-0185",
                "postgiro": "3445"
            },
            "activity": "Egna konstruktioner o agenturer, maskiner för cellulosa- o pappersindustrin, kommunal o industriell vattenrening, slambehandling. Försäljning av papper",
            "employees": 26,
            "annual_turnover": 22000000,
            "capital": 400000,
            "key_personnel": [
                {
                    "name": "Börje Gawell",
                    "position": "Styrelse Ordf"
                },
                {
                    "name": "Styrbjörn Gärde",
                    "position": "Adv"
                },
                {
                    "name": "Rudolf Woode",
                    "position": "Verkst dir"
                }
            ],
            "establishment_year": 1923
        },
        "9": {
            "company_name": "LEJMARK AB, INGENIORS. FIRMA ROBERT",
            "pnr": "384 00",
            "address": "Blomstermåla, Timmernabben",
            "phone_number": "0499-230 12",
            "activity": "Tillverkar Tretong. Konsulterande verksamhet",
            "employees": 7,
            "capital": 100000,
            "key_personnel": [
                {
                    "name": "Disp Olle Lejmark",
                    "position": "Verkst dir"
                }
            ],
            "establishment_year": 1922
        },
        "10": {
            "company_name": "BERO I OREBRO AB",
            "pnr": "701 06",
            "address": "Örebro 1, Nyg 46. Box 439",
            "phone_number": "019-12 40 35",
            "activity": "Marknadsför i huvudsak soppor, konserver, sylt o saft till storkök. Generalagent i Sverige för Honig Food Ltd, Holland vilka tillverkar bl a vakuumtorkade soppor",
            "capital": 100000,
            "key_personnel": [
                {
                    "name": "Bertil Roman",
                    "position": "Verkst dir"
                }
            ],
            "establishment_year": 1953
        },
        "11": {
            "company_name": "BEROL AB",
            "pnr": "N/A",
            "activity": "se MoDoKemi AB."
        },
        "12": {
            "company_name": "BERRUM & JORCK AB",
            "pnr": "41116",
            "address": "Göteborg, Korsg 12",
            "phone_number": "031-17 15 50",
            "bank_details": {
                "bankgiro": "337-2141",
                "postgiro": "46597-1"
            },
            "activity": "Säljer textilvaror o konfektionstillbehör",
            "employees": 4,
            "annual_turnover": 6000000,
            "capital": 10000,
            "key_personnel": [
                {
                    "name": "Carl-Eric Andelius",
                    "position": "Verkst dir"
                }
            ],
            "establishment_year": 1931
        },
        "13": {
            "company_name": "EIR",
            "employees": 20,
            "annual_turnover": 2000000,
            "capital": 30000,
            "key_personnel": [
                {
                    "name": "Ing Herbert Einarsson",
                    "position": "Verkst dir"
                }
            ],
            "establishment_year": 1966
        },
        "14": {
            "company_name": "WIKLUND AB, GUNNAR",
            "pnr": "11135",
            "address": "Stockholm, Kungsg 38",
            "phone_number": "08-20 62 72",
            "bank_details": {
                "bankgiro": "722-2441",
                "postgiro": "195517-8"
            },
            "activity": "Importagenter för elektronikmateriel",
            "employees": 3,
            "annual_turnover": 1900000,
            "capital": 5000,
            "key_personnel": [
                {
                    "name": "Civiling Gunnar Wiklund",
                    "position": "Verkst din"
                }
            ],
            "establishment_year": 1937
        },
        "15": {
            "company_name": "CEVECE MONTAN AB",
            "pnr": "402 32",
            "address": "Göteborg 7, Första Långg 21. Box 7127",
            "phone_number": "031-24 39 02, 24 39 05",
            "activity": "Import o export av järn o stål",
            "employees": 8,
            "annual_turnover": 30000000,
            "capital": 200000,
            "key_personnel": [
                {
                    "name": "Paul van der Vliet",
                    "position": "Verkst dir"
                }
            ],
            "establishment_year": 1962
        },
        "16": {
            "company_name": "FYRIS, MASKINAFFÄREN",
            "pnr": "753 21",
            "address": "Uppsala, Kungsg 32",
            "phone_number": "018-14 90 15",
            "bank_details": {
                "bankgiro": "802-2030",
                "postgiro": "135106-3"
            },
            "activity": "Försäljning o service av kontorsmaskiner, kontorsmöbler, butiksmaskiner o butiksinredningar",
            "employees": 12,
            "annual_turnover": 1100000,
            "key_personnel": [
                {
                    "name": "Gunnar Hogell",
                    "position": "Chef"
                }
            ],
            "establishment_year": 1937
        },
        "17": {
            "company_name": "FAGELFORS TRÄINDUSTRI AB",
            "pnr": "570 75",
            "address": "Fågelfors",
            "phone_number": "0491-510 32, 510 35",
            "bank_details": {
                "bankgiro": "855-3109",
                "postgiro": "335406-5"
            },
            "activity": "Tillverkar träfönster",
            "employees": 25,
            "annual_turnover": 1700000,
            "capital": 30000,
            "key_personnel": [
                {
                    "name": "Harald Hjelm",
                    "position": "Verkst dir"
                }
            ],
            "establishment_year": 1947
        },
        "18": {
            "company_name": "SUNNE CEMENTGJUTERI",
            "pnr": "686 00",
            "address": "Sunne, Fabriksg 16",
            "phone_number": "0565-102 78, 118 05",
            "bank_details": {
                "bankgiro": "444-9377",
                "postgiro": "88057-5"
            },
            "activity": "Tillverkar G-rör, F-rör, vägrör o betonghålsten",
            "employees": 9,
            "key_personnel": [
                {
                    "name": "Stig Ekström",
                    "position": "Chef"
                }
            ],
            "establishment_year": 1967
        },
        "19": {
            "company_name": "OTKER AB",
            "pnr": "17165",
            "address": "Solna, Bagartorpsringen 51",
            "phone_number": "08-85 02 80",
            "bank_details": {
                "bankgiro": "620-8276",
                "postgiro": "572750-8"
            },
            "activity": "Import o försäljning av livsmedel",
            "employees": 30,
            "capital": 550000,
            "key_personnel": [
                {
                    "name": "Folke W Nilsson",
                    "position": "Verkst dir"
                }
            ],
            "establishment_year": 1961
        },
        "20": {
            "company_name": "OWEDSKLOSTERS STEN-INDUSTRIER AB",
            "pnr": "240 35",
            "address": "Harlösa",
            "phone_number": "046-630 02, 63016",
            "bank_details": {
                "bankgiro": "662-7509",
                "postgiro": "39772-4"
            },
            "activity": "Framställer makadam, krossgrusblandningar, stenmjöl",
            "employees": 10,
            "annual_turnover": 800000,
            "capital": 80000,
            "key_personnel": [
                {
                    "name": "Frih Otto Ramel",
                    "position": "Styrelse Ordf"
                },
                {
                    "name": "frih Hans Ramel",
                    "position": "Styrelse Medlem"
                },
                {
                    "name": "Frih Otto Ramel",
                    "position": "Verkst ledamot"
                },
                {
                    "name": "Erik R Olsson",
                    "position": "Kamrer"
                }
            ],
            "establishment_year": 1915
        }
    }
}