{
    "original": "BERGSTRÖM &amp; CO, AB SVEN\n\nPnr 705 90\n\nÖrebro, Gryts Industriområde. Pos ti\n5602. Tel 019-16 00 00. Bankgiro\n614-5585. Postgiro 332269-0\nVerksamhet: Smide, konstruktioner,\nsandblästring o sprutforzinkning\nAntal anställda: 40\nÅrsomsättning: 4 400 000\nAktiekapital: 75000\nVerkst dir: Sven Bergström.\n\nBERGSOE &amp; SON AB, PAUL\n\nPnr 26135\n\nLandskrona, Gasverksg. Tel\n0418-16150. Bankgiro 66-0009. Postgiro\n263489. Tga Bera.\nTelex 72386 BERGSOE S\nVerksamhet: Metallraffinaderi för\ntillverkning av alla slags metaller\no metallegeringar i tackor\nAvdelningskontor: Stockholm.\nLer-krogsv 9-11, Västberga. Tel\n08-45 64 20, 45 64 21. Tga Berafilial.\nTelex 17176 B ER AL S\nVarunamn: Bera\nAntal anställda: 200\nÅrsomsättning: 140 000 000\n.Aktiekapital: 315 000\nVerkst dir: Jens Frijs\nEtableringsår: 1942.\n\nRAMNÄS BRUKS AB\n\nPnr 730 60\nRamnäs\n\nFusioneras under 1971 med\nBulten-Kanthal AB men bedrivertill\ndess verksamheten som juridisk\nperson under ovanstående firmanamn\nSe i övrigt Bulten-Kanthal AB\nRamnäsbrukdivisionen.\n\nRAMSTRÖMS\nGRÄV-MASKINER, AB\n\nPnr 87100\n\nHärnösand, Fiskarg 1. Tel\n0611-146 69, 152 55. Postgiro 29 2537\nVerksamhet: Schaktnings- o\nplaneringsarbeten, maskinuthyrning m m\nAntal anställda: 20\nÅrsomsättning: 1500 000\nAktiekapital: 25 000\nVerkst dir: Rud Ramström\nEtableringsån 1945.\n\nRAMSTRÖMS\nJÄRNHANDEL, AB\n\nPnr 733 00\n\nSala, Rådhusg 3. Tel 0224-132 40.\nBankgiro 23-2015. Postgiro 30950\nVerksamhet: Järnvaror,\nbyggnadsmaterial, verktyg, husgeråd, vapen,\nsport- o fritidsartiklar samt redskap\nför lantbruket\nAntal anställda: 18\nÅrsomsättning: 2900 000\nAktiekapital: 200 000\nVerkst dir: Sten Ramström\nEtableringsår: 1915\nOmbildat till aktiebolag 1944.\n\nRAMSTRÖM, AB FR\n\nPnr 87101\n\nHärnösand 1, Skeppsbron 17-19. Box\n31. Tel 0611-15630. Telex 71020.\nTga Ramström\n\nVerksamhet: Agenturfirma för\nsvenska o utländska tillverkare av:\npumpar, fläktar, kompressorer,\nkolonner, kylmaskiner, värme- o\nkraftteknisk utrustning, torkapparater o\ncentrifuger. Utrustningar för\nvattenberedning o vattenrening.\nLastnings-, transport-, borr- o\nvägmaski-ner. Vibrationsmatare, siktar o\n\ntransportörer.\nTransmissionsmate-riel, rörledningsarmatur,\narbetar-skyddsmateriel. Representerar\nFagersta Bruks AB i Norrland.\nBedriver spedition o skeppsmäkleri\nAvdelningskontor: 951 01 Luleå.\nBox 28. Skomakarg 36. Tel\n0920-149 35\n\n171 24 Solna 1, Box 1241. Västra v\n11 A. Tel 08-730 03 30\n872 00 Kramfors, Järnvägsg 18.\nTel 0612-124 40\n\nVarunamn: Arnold, BaumUller, BSD,\nCeCe, Continental, Dresser,\nHewitt-Robins, ILA, Joy, Kapman,\nKestermann, Link-Belt, Lokomo,\nMobrey, MSA, Permutit, PIV,\nRuck-Zuck, Stafsjö, Sulzer,\nTikamin, Tuflin\nAntal anställda: 80\nAktiekapital: 500 000\nVerkst dir: F Ramström\nEtableringsår: 1876.\n\nRAMSTROMS\nPAPPERSINDUSTRI, RAGNAR\n\nPnr 686 00\n\nSunne, Box 69. Sundg. Tel\n0565-112 90. Bankgiro 131-5639.\nPost-giro 491458-6\n\nVerksamhet: Flexografiskt\nrotationstryck för rullar o ark,\nmönstertryckt omslagspapper,\npåsar, gaveletiketter\nAntal anställda: 36\nÅrsomsättning: 3 300 000\nVerkst dir: Ragnar Ramström\nEtableringsår: 1953.\n\nSUNDBOMS ROR, AB\n\nPnr 95100\n\nLuleå, Stationsg 17. Tel\n0920-128 06, 128 09. Postgiro 481642-1\nVerksamhet: WS-entreprenörer.\nUtför rör-, olje-, ventilations^,\nkyl-o frys- samt\ntryckluftsinstalla-tioner. Säljer alla slags\nhushållsmaskiner\n\nAntal anställda: 15\nÅrsomsättning: 1000 000\nAktiekapital: 60 000\nVerkst dir: Disp Björn Kullberg\nEtableringsår: 1948.\n\nAROS ELECTRONICS AB\n\nPnr 436 00\n\nAskim, Hantverksv 1. Tel\n031-28 03 41, 28 0684. Bankgiro\n200-4034. Postgiro 623941-2\nVerksamhet: Tillverkar o säljer\nmodern kraftelektronik, såsom\nvarvtalsreglering av elektriska motorer,\nbatteriladdare, elvärmeregleringar\nsamt startapparater för 3-fas\nväxelströmsmotorer. Utför\nindustrimontage\n\nFabrik: 724 10 Västerås,\nNaviga-törsg 10. Tel 021-13 40 20\nAntal anställda: 24\nÅrsomsättning: 1500 000\nAktiekapital: 30 000\nVerkst dir: Civiling Nils Paulsson\nEtableringsår: 1970.\n\nEBENFELT, AB BRDDERNA\n\nPnr 502 63\n\nBorås, Getängsv 28-30. Tel\n033-117975. Bankgiro 531-1790.\nPostgiro 34551-2\n\nVerksamhet: Tillverkar\nfritidskläder, skjortor o byxor\nAntal anställda: 150\nAktiekapital: 1000000\nChef: Bengt Ebenfelt\nEtableringsår: 1928\nOmbildat till aktiebolag 1934.\n\nEBER, FABRIKS AB\n\nPnr 211 53\n\nMalmö, Monbijoug 3. Tel\n040-97 94 48, 37721. Bankgiro 87-6114.\nPostgiro 434095. Tga Eber\nVerksamhet: Engrosförsäljning av\nleksaker. Tillverkar skinndjur\nAntal anställda: 10\nÅrsomsättning: 2 700 000\n\nAktiekapital: 25 000\nVerkst dir: Alexander Katina\nEtableringsår: 1961.\n\nEBES MEKANISKA\nERIK BJURK AB\n\nPnr 33100\n\nVärnamo, Gränsg 3. Tel\n0370-12166. Bankgiro 14-1939.\nPostgiro 396751-0\n\nVerksamhet; Tillverkar\ngradnings-maskiner samt specialmaskiner\nÄgare o chef: Erik Björk\nEtableringsår: 1954.\n\nPLA\n\nPICHLER AB, ERIK\n\nPnr 11135\n\nStockholm, Kungsg 48. Tel\n08-24 66 00. Bankgiro 483-5096,\n722-2888. Postgiro 251975-9. Tga\nPich-lerab\n\nVerksamhet: Säljer maskiner o\nmaterial för den grafiska branschen\nÅrsomsättning: 1400 000\nAktiekapital: 30 000\nVerkst dir: Erik Pichler\nEtableringsàr: 1906.\n\nPIGMENTA AB\n\nPnr 17148\n\nSolna, Fabriksv 1. Tel 08-27 27 50.\nBankgiro 56-6077.Postgiro 258598.\nTga Pigmenta.\nTelex 17727 PIGMENT S\nVerksamhet: Tillverkar\nscreenfär-ger av alla slag. Specialitet:\nplastfärger. Säljer duk, filmer,\nschabloner, adhesivmaterial m m\nAntal anställda: 9\nÅrsomsättning: 2 400 000\nAktiekapital: 100 000\nVerkst dir: Nils R:son Hoffman\nFabrikschef: Yngve Prostle\nEtableringsàr: 1946\nSamarbetar med tryckfärgsfabriken\nHoffman &amp; Co AB, Solna.\n\nPIHL, BRUDERNA\n\nPrr 225 90\n\nLund, Stora Uppåkra 2. Tel\n046-119750. Postgiro 25174-4\nVerksamhet: Snittgröntsodling\nAntal anställda: 7\nChefer: Werner Pihl, Hugo Pihl,\nGustaf Pihl\nEtableringsàr: 1929.\n\nPIHL, AB C l\n\nPnr 403 12\n\nGöteborg 2, Kungsg 10. Box 2118.\nTel 031-17 30 50. Bankgiro\n42-0151. Postgiro 240763.\nTga Ferropihl. Telex 2367\nVerksamhet: Export o import av\njärn o stål, verksagenturer\nAvdelningskontor: 852 30\nSundsvall, Storg 16. Tel 060-15 4 2 20.\nTelex 71239. Tga Ferropihl. Chef:\nIng Carl Ivar Sjöholm\nAntal anstäUda: 30\nAktiekapital: 100 000\nStyrelse: Dir Ernst W Larson (ordf),\ndir Rune Flobecker\nVerkst dir: Rune Flobecker\nV verkst dir: Ingemar Ericsson\nEtableringsàr: 1946\nModerbolag för Gustaf Fagerberg AB.\n\nPIHL, HARALD\n\nPnr 11148\n\nStockholm, Nybrokajen 7.\nTel 08-24 43 00. Bankgiro 560-7007.\nPostgiro 502727-1. Tga Hapihl.\nTelex 19999\n\nVerksamhet Säljer metaller,\nkemikalier, plast samt maskiner\nÄgare o chefer:\nCiviling Gunnar H:son Pihl\nCivilekonom Harald H:son Pihl\nEtableringsàr: 1912.\n\nPILEN, AB FABRIKEN\n\nPnr 290 72\n\nAsarum, Box 17. Tel 0454-203 00.\n\nBankgiro 34-3333. Postgiro 383788\nVerksamhet: Tillverkar\nmodelle-ringsmassor\nAntal anstäUda: 7\nAktiekapital: 30 000\nFabrikschef: Fru Birgit Berg\nEtableringsàr 1907\nOmbildat till aktiebolag 1960.\n\nPIHLGREN &amp; KJELLER, AB\n\nPnr 402 71\n\nGöteborg 8,Kalkbruksg 7. Box 8849.\nTel 031-516980, 516981.\nBankgiro 44-2270. Postgiro 41376. Tga\nGrenpihl\n\nVerksamhet: Säljer\nmaskinförnödenheter, byggnadsartiklar,\nisoleringsmaterial, oljor, trassel m m\nAntal anställda: 12\nAktiekapital: 200 000\nVerkst dir: Gustaf Hörberg\nEtableringsàr 1919\nOmbildat till aktiebolag 1965.\n\nPILGRIMSTADS AB\n\nPnr 840 58\n\nPUgrimstad, Box 10. Tel\n0693-31100. Tga Pilgrimboard\nVerksamhet: Tillverkar byggboard\nAntal anställda: 95\nÅrsomsättning: 10 000 000\nAktiekapital: 1500 000\nVerkst dir Folke Lundquist(Ljusne)\nEtableringsàr: 1925.\n\nPILREKLAM\n\nPnr 417 20\n\nGöteborg, Gullrisg 7 E. Tel\n031-23 90 58, 23 01 25. Bankgiro 51-3694.\nPostgiro 425215\n\nVerksamhet: Design, dekor,\nannonser, internationella utställningar o\ninredningar\n\nKontor o studio: 413 10 Göteborg,\nRoseng 2 A. Tel 031-14 06 32\nAntal anstäUda: 8\nKonstnärUg ledare: Jo Erich Kuhn\nTeknisk ledare: Ing Torborg Kuhn\nEtableringsàr 1951.\n\nSVANLUND AB, KARL\n\nPnr 104 62\n\nStockholm 17, Kattgränd 1. Box\n17047. Tel 08-44 02 05. Bankgiro\n44-6995. Postgiro 50313.\nTga Kasva. Telex 1444\nVerksamhet: Agentur o import i\nkaffe, kryddor o artiklar för sötvar\nruindus trin\nAktiekapital: 100 000\nVerkst dir: Sven Fahlberg\nEtableringsår: 1936.\n\nISO-LIN PRODUKTER, AB\n\nPnr 510 20\n\nFritsla, Danska v. Box 51. Tel\n0320-704 68 , 703 69. Bankgiro 54-2329.\nPostgiro 122498\nVerksamhet: Tillverkar\nfönsterbänkar o bänk skivor\nVarunamn: Iso-Lin\nAntal anställda: 6\nAktiekapital: 20000\nFirmatecknare: Enar Nilsson, Sam\nNordling\n\nEtableringsår: 1947.\n\nAPPENDAGE AB\n\nPnr 126 64\n\nHägersten, Jenny Linds g 13. Tel\n08-46 61 50. Bankgiro 570-0463.\nPostgiro 257600-7\nVerksamhet: Tillverkar o säljer\nstädutrustningar, kem-tekn\nstäd-preparat samt städmaskiner. Utför\nstädplanering\nÅrsomsättning: 500 000\nAktiekapital: 30 000\nVerkst dir: Töre Malmquist\nEtableringsår: 1968.\n\nAQUA-SPORT, AB\n\n(Poseidon Industri AB)\n\nPnr 400 60\n\nGöteborg 6, Box 6095. N Gubberog\n30. Tel 031-8015 80. Bankgiro\n50-0635. Postgiro 420502\n\nVerksamhet: Tillverkar o säljer all\nslags dykmateriel,\nandningsapparater för vatten- o rökdykning.\nHögtryckskompressorer 325 atö m m\nVarunamn: Poseidon, Bauer\nAntal anställda: 53\nÅrsomsättning: 4 000 000\nAktiekapital: 100 000\nVerkst dir: Dennis Österlund\nTekn dir: Ingvar Elfström\nEtableringsår: 1957.\n\nBERNOS FÖRSÄLJNINGS AB\n\nPnr 12162\n\nJohanneshov, Hallv 13. Tel 08-\n\n39 03 70. Bankgiro 284-5113.\nPostgiro 56400-5. Tga Bernomek\nVerksamhet: Charkuterimaskiner,\nsvängdörrar o industriportar\nVerkst dir: Berno Hermanson\nEtableringsår: 1950.",
    "structured": {
        "1": {
            "company_name": "BERGSTRÖM & CO",
            "address": "Gryts Industriområde, Örebro",
            "phone_number": "019-16 00 00",
            "bank_details": {
                "bankgiro": "614-5585",
                "postgiro": "332269-0"
            },
            "activity": "Smide, konstruktioner, sandblästring o sprutforzinkning",
            "employees": 40,
            "annual_turnover": 4400000,
            "capital": 75000,
            "key_personnel": [
                {
                    "name": "Sven Bergström",
                    "position": "Verkst dir"
                }
            ],
            "establishment_year": 0
        },
        "2": {
            "company_name": "BERGSOE & SON AB",
            "address": "Gasverksg, Landskrona",
            "phone_number": "0418-16150",
            "bank_details": {
                "bankgiro": "66-0009",
                "postgiro": "263489"
            },
            "activity": "Metallraffinaderi för tillverkning av alla slags metaller o metallegeringar i tackor",
            "employees": 200,
            "annual_turnover": 140000000,
            "capital": 315000,
            "key_personnel": [
                {
                    "name": "Jens Frijs",
                    "position": "Verkst dir"
                }
            ],
            "establishment_year": 1942
        },
        "3": {
            "company_name": "RAMNÄS BRUKS AB",
            "address": "Ramnäs",
            "establishment_year": 1971
        },
        "4": {
            "company_name": "RAMSTRÖMS GRÄV-MASKINER, AB",
            "address": "Fiskarg 1, Härnösand",
            "phone_number": "0611-146 69, 152 55",
            "bank_details": {
                "postgiro": "29 2537"
            },
            "activity": "Schaktnings- o planeringsarbeten, maskinuthyrning m m",
            "employees": 20,
            "annual_turnover": 1500000,
            "capital": 25000,
            "key_personnel": [
                {
                    "name": "Rud Ramström",
                    "position": "Verkst dir"
                }
            ],
            "establishment_year": 1945
        },
        "5": {
            "company_name": "RAMSTRÖMS JÄRNHANDEL, AB",
            "address": "Rådhusg 3, Sala",
            "phone_number": "0224-132 40",
            "bank_details": {
                "bankgiro": "23-2015",
                "postgiro": "30950"
            },
            "activity": "Järnvaror, byggnadsmaterial, verktyg, husgeråd, vapen, sport- o fritidsartiklar samt redskap för lantbruket",
            "employees": 18,
            "annual_turnover": 2900000,
            "capital": 200000,
            "key_personnel": [
                {
                    "name": "Sten Ramström",
                    "position": "Verkst dir"
                }
            ],
            "establishment_year": 1915
        },
        "6": {
            "company_name": "RAMSTRÖM, AB FR",
            "address": "Skeppsbron 17-19, Härnösand",
            "phone_number": "0611-15630",
            "key_personnel": [
                {
                    "name": "F Ramström",
                    "position": "Verkst dir"
                }
            ],
            "establishment_year": 1876
        },
        "7": {
            "company_name": "RAMSTROMS PAPPERSINDUSTRI, RAGNAR",
            "address": "Box 69, Sunne",
            "phone_number": "0565-112 90",
            "bank_details": {
                "bankgiro": "131-5639",
                "postgiro": "491458-6"
            },
            "activity": "Flexografiskt rotationstryck för rullar o ark, mönstertryckt omslagspapper, påsar, gaveletiketter",
            "employees": 36,
            "annual_turnover": 3300000,
            "key_personnel": [
                {
                    "name": "Ragnar Ramström",
                    "position": "Verkst dir"
                }
            ],
            "establishment_year": 1953
        },
        "8": {
            "company_name": "SUNDBOMS ROR, AB",
            "address": "Stationsg 17, Luleå",
            "phone_number": "0920-128 06, 128 09",
            "bank_details": {
                "postgiro": "481642-1"
            },
            "activity": "WS-entreprenörer. Utför rör-, olje-, ventilations-, kyl-o frys- samt tryckluftsinstallationer. Säljer alla slags hushållsmaskiner",
            "employees": 15,
            "annual_turnover": 1000000,
            "capital": 60000,
            "key_personnel": [
                {
                    "name": "Disp Björn Kullberg",
                    "position": "Verkst dir"
                }
            ],
            "establishment_year": 1948
        },
        "9": {
            "company_name": "AROS ELECTRONICS AB",
            "address": "Hantverksv 1, Askim",
            "phone_number": "031-28 03 41, 28 0684",
            "bank_details": {
                "bankgiro": "200-4034",
                "postgiro": "623941-2"
            },
            "activity": "Tillverkar o säljer modern kraftelektronik, såsom varvtalsreglering av elektriska motorer, batteriladdare, elvärmeregleringar samt startapparater för 3-fas växelströmsmotorer. Utför industrimontage",
            "employees": 24,
            "annual_turnover": 1500000,
            "capital": 30000,
            "key_personnel": [
                {
                    "name": "Civiling Nils Paulsson",
                    "position": "Verkst dir"
                }
            ],
            "establishment_year": 1970
        },
        "10": {
            "company_name": "EBENFELT, AB BRDDERNA",
            "address": "Getängsv 28-30, Borås",
            "phone_number": "033-117975",
            "bank_details": {
                "bankgiro": "531-1790",
                "postgiro": "34551-2"
            },
            "activity": "Tillverkar fritidskläder, skjortor o byxor",
            "employees": 150,
            "capital": 1000000,
            "key_personnel": [
                {
                    "name": "Bengt Ebenfelt",
                    "position": "Chef"
                }
            ],
            "establishment_year": 1928
        }
    }
}