{
    "original": "GUFLON AB\n\nPnr 264 00\n\nKlippan. Tel 0435-12190.\nBankgiro 577-9426. Postgiro 703808-6.\nTga Guflon\n\nVerksamhet Tillverkar o säljer\ntekniska plast- o gummiartiklar\nFörsäljningskontor: 126 06\nHägersten 6. Box 666. Tel 08-8 8 4 2 21\nAntal anställda: 10\nAktiekapital: 25 000\nStyrelse: Dir Gunnar Månsson (ordf),\nfru Gunnel Månsson\nVerkst dir: Gunnar Månsson\nEtableringsår: 1941\nOmbildat till aktiebolag 1966.\n\nGUGGENBERGER, ERICH H\n\nPnr 11157\n\nStockholm, Sveav 17. Tel\n08-11 90 00. Postgiro 11900. Telex\n19000. Tga Gugimport\nVerksamhet: Agentur med\ntextilvaror\n\nEtableringsår 1919.\n\nGULDSMEDS AB ELFSTRÖM &amp;\nJOHANSON\n\nPnr 57100\n\nNässjö, Box 195. Storg 24. Tel\n0380-106 96. Bankgiro 452-8063.\nPostgiro 33424-3\nVerksamhet: Säljer ur, guld,\nsilver o presentartiklar\nAntal anställda: 15\nAktiekapital: 350 000\nVerkst dir: Sören Elfström\nEtableringsår: 1920.\n\nGULDSMEDSAKTIEBOLAGET\nG.A.B.\n\nPnr 201 21\n\nMalmö 1, Box 105. Citadellsv 11.\nTel 040-733 30. Bankgiro 283-9306.\nPostgiro 3383-7. Tga GABIS\nVerksamhet: Grossistföretag inom\nguldsmedsbranschen\nAntal anstäUda: 100\nÅrsomsättning: 14 000 000\nAktiekapital: 5 000 000\nVerkst dir: Carl-S Roos\nEtableringsår: 1867.\n\nLUNDH &amp; CO AB, IVAR\n\nPnr 104 40\n\nStockholm 14, Box 14002.\nTor-stenssonsg 3. Tel 08-63 19 20.\nBankgiro 700-2314. Postgiro\n56588-7. Telex 1695\nVerksamhet: Auktoriserad\nskepps-klarering, skeppsmäkleri,\nbefraktning av torrlast, tankfartyg,\nfartygsförsäljning o\nnybyggnadskon-traktering. Agenturverksamhet för\nvarv o fartygsutrustningar.\nFörsäkringsagenter, sjöfartkonsulter\nAvdelningskontor för\nskeppsklare-ring: 15102 Södertälje 2. Tel\n0755-323 10\n\nAntal anställda: 17\nAktiekapital: 50 000\nVerkst dir. Lennart Bengtsson\nEtableringsår. 1922.\n\nADDO, AB\n\nPnr 200 22\n\nMalmö 3, Pack. O Farmv 12. Tel\n040-93 68 00. Bankgiro 999-9004.\nPostgiro 24470-7. Tga Addo.\nTelex 3178\n\n\n\nVerksamhet: Tillverkar räkne- o\nbokföringsmaskiner samt\nutrustning för automatisk\ndatabehandling. Försäljning av\npostbehandlings maskiner\n\nVarunamn: Addo, Addo-X, Adrema,\nPitney-Bowes\nAntal anställda: 2 400\nAktiekapital: 11 250 000\nVerkst dir: Gunnar Agrell\nFTirsäljn-dir: Torsten Odervall\nInköpschef: Börje Winnerstam\nEtableringsår: 1918\nDotterbolag: AB Multo, örkelljunga.\nIngår i Facit-koncernen.\n\nADDRESSOGRAPH\nMULTI-GRAPH AB\n\nPnr 116 65\n\nStockholm, Gotlandsg 43. Tel\n08-44 06 60. Postgiro 1169. Tga\nAdd-mulcor\n\nVerksamhet: Adresseringsmaskiner,\nmaskiner för brevpropaganda o\nkontorstryck, offset- o\nduplice-ringsmaskiner, sättmaskiner,\nfoto-sättningsapparater, rubriksättnings-apparater, kopieringsautomater\nAvdelningskontor: Göteborg C,\nJärntorget 3. Tel 031-24 3312,\n24 3313. Postgiro 1169. Tga\nAdd-mulcor\n\nMalmö C, N Vallg 98. Tel\n040-97 40 15, 97 90 14. Postgiro 1169.\nTga Addmulcor\n\nVarunamn: Addressograph, Bruning,\nFotolist, Headliner, Multigraph,\nMultilith, Vari-Typer\nAktiekapital: 500 000\nVerkst dir: T F E Lane\nEtableringsår: 1922.\n\nWERACO, AB\n\nPnr 11140\n\nStockholm, Roseng 6. Tel\n08-241290. Bankgiro 70-0400.\nPostgiro 1193. Tga Weraco\nVerksamhet: Importerar parfym,\nkosmetik, herrpreparat o\nhårvårds-medel\n\nAntal anställda: 35\nÅrsomsättning: 8 000 000\nAktiekapital: 125 000\nVerkst dir. Jouke Bouius\nEtableringsår: 1947.\n\nNORRLANDS HEMSLÖJD, AB\n\nPnr 112 46\n\nStockholm, Pridhemsg 60. Tel\n08-52 26 46, 53 2636. Bankgiro\n56-7048. Postgiro 270350\nVerksamhet: Engrosförsäljning o\nagenturrörelse med hemslöjd,\npresentartiklar, korgar o textilier\nVerkst dir: Paul Bjuhr\nEtableringsår: 1941.\n\nNORRLANDS SKOGSÄGARES\nCELLULOSA AB\n\nPnr 87200\n\nKramfors. Tel 0612-124 50.\nPostgiro 8540-7. Tga Farmpulp.\nTelex 71240\n\nVerksamhet: Tillverkar\nsulfatmassa (barr- o lövved), sulfitmassa,\nkraftpapper, finpapper, kemiska\nprodukter o sågade trävaror.\nSulfatfab-riker i Dynas, Köpmanholmen o\nVäja, sulfitfabriker i Hörnefors,\nKrokom o Vallvik, pappersbruk i\nVäja o Hörnefors, sågverk i\nKrokom, Köpmanholmen o Väja\nFörsäljning:\n\nMassa, kraftpapper o trävaror;\nKramfors. Ttel 0612-124 50. Telex\n71240. Tga Farmpulp. Chef: Dir\nAlf Lindgren\n\nNcb Papper AB: Stockholm. Tel\n08-23 24 80. Tga Bothnia. Telex 10397.\nChef: Dir Frank Skarborg\nMalmö. Tel 040-18 03 40\nGöteborg. Tel 031-42 00 15\nHörnefors. Tel 0930-209 00\nVarunamn: Dynapak\nAktiekapital: 32 000 000\nStyrelse: Hemmansäg Alfons\nBerglund (ordf), dir Gösta Hallmans,\njur dr Gunnar Hedlund, hemmansäg\nAlf Järmens, hemmansäg Anders\nHedberg, hemmansäg Adil\nJohansson, riksdagsman Axel Wikberg,\nfabriksarb Verner Ågren (repr för\nde anställda)\n\nVerkst dir: Jur dr Gunnar Hedlund\nV verkst dir:r: Berndt Orefors,\nGösta Hallmans, Tage Lundén\nPlatschefer: Dir Tage Lundén,\nKöpmanholmen, övering Folke\nBrunstedt, Hörnefors, dir Evert Nilsson,\nVäja, övering Hans Fastén,\nKrokom. övering Per Svanberg, Vallvik\nEtableringsår: 1959.\n\nNORRLANDS SLIPINDUSTRI,\nAB\n\nPnr 852 43\n\nSundsvall, Ostermov 35. Tel\n060-1104 44. Bankgiro 18-0471.\nPost-giro 70999-8\n\nVerksamhet: Slipning av\neggverktyg för cellulosa- o mekaniska\nindustrin\n\nAntal anställda: 14\nAktiekapital: 20 000\nÄgare o chefer: Alvar Haglund,\nHarry Widmark\nEtableringsår: 1963.\n\nNORRLANDS\nVADD-FABRIK, AB\n\nPnr 81028\n\nJärbo, Norrlandsg 4. Fack 29. Tel\n0290-700 19. Bankgiro 78-7621.\nPostgiro 80088\n\nVerksamhet: Tillverkar sängkläder,\nall slags vadd o tätningslister\nAntal anställda: 10\nÅrsomsättning: 500 000\nAktiekapital: 25 000\nVerkst dir: Rune Berggren\nEtableringsår: 1900.\n\nBERGA SNICKERIFABRIK, AB\n\nPnr 570 71\n\nBerga, Järnvägsg 14. Box 9. Tel\n0491-500 02, 502 22. Bankgiro\n14-9402. Postgiro 23681. Tga\nExport-snickeri, Kalmar\nVerksamhet: Dörrar för export,\nsågade o hyvlade trävaror\nAntal anställda: 60\nÅrsomsättning: 3 400 000\nAktiekapital: 100 000\nVerkst dir: Robert Forsberg\nEtableringsår: 1923.\n\nFIX TRIKAFABRIKER AB\n\nPnr 614 00\n\nSöderköping, Box 16. Tel\n0121-109 80, 10960. Bankgiro 609-8685.\nPostgiro 29402-5\n\nVerksamhet: Ull verkar underkläder,\nfritidsplagg, strumpor o strumpbyxor\nVarunamn: Tussilago, Fix\nAntal anställda: 450\nÅrsomsättning: 24 000 000\nAktiekapital: 600 000\nVerkst dir: Liss Surtevall\nEtableringsår: 1955.\n\nWENNHEDS FABRIKS AB\n\nPnr 330 30\n\nGnosjö, Målskog. Tel 0370-95015,\n95055. Bankgiro 54-2556.\nPostgiro 95042\n\nVerksamhet Tillverkning av spik\no tråddetaljer\n\nAntal anställda: 12\nÅrsomsättning: 1000 000\nAktiekapital: 35 000\nChef: Fabr Adolf Wennhed\nEtableringsår: 1918.\n\nWENNQVISTS\nKONSTRUK-TIONSBYRÄ, K B\n\nPnr 65105\n\nKarlstad l.Herrgårdsg 17.Box 324.\nTel 054-11 53 95. Postgiro 387614\nVeiksamhet: Upprättar\nkonstruktionsritningar för bro-, hus- o\nindustribyggnader. Totalplanerar\nindustribyggnader. Kontroll o\narbetsledning. Ljuskopiering\nAntal anställda: 10\nÅrsomsättning: 450000\nVerkst dir: Civiling Bernt\nWenn-qvist\n\nEtableringsår: 1939.\n\nHYLLINGE PRODUKTER\n\nPnr 260 61\n\nHyllinge, Smedg. Tel 042-25180.\nBankgiro 34-0621. Postgiro 569786\nVerksamhet: Trätoffeltillverkning\nmed inreg varumärke HYLLINGE\nORTOPEDIC. Specialitet:\nträtofflor för industrin med\nhalkskyddan-de sula\n\nChef: Eskil Jacobsson.\n\nHYLLMEKANO, AB\n\nPnr 217 58\n\nMalmö, Tessins v 6. Tel 040-695 43,\n695 44. Bankgiro 641-0690.\nPostgiro 532960-2\n\nVerksamhet: Agentur för AB\nNordverk. Säljer stålinredningar,\nstålhyllor, pallhyllor, container etc\nAntal anställda: 3\nÅrsomsättning: 1500 000\nAktiekapital: 20 000\nVerkst dir: Disp Lennart Ullberg\nEtableringsår: 1960.\n\nGOT A KANAL, REDERI AB\n\nPnr 401 24\n\nGöteborg 1, Hotellplatsen 2. Box\n272. Tel 031-17 76 15. Tga\nCanal-route. Telex 2284\nVerksamhet: Rederi med\npassageraretrafik på \"Sveriges Blå Band\".\nÄven kortare dagsresor\nAvdelningskontor: 11130 Stockholm,\nSkeppsbron 16. Tel 08-10 04 57\nAktiekapital: 100 000\nVerkst dir: Helge Källsson\nEtableringsår: 1869\nOmbildat tül aktiebolag 1957.\n\nGOTA PARTILAGER AB\n\nPnr 417 04\n\nGöteborg H, Kvilleg 9 E. Tel\n031-5117 40, 511741. Bankgiro\n848-3281. Postgiro 45420-7. Tga\nGötalagret\n\nVerksamhet: Leksaker o souvenirer\nen gros\n\nAktiekapital: 50000\nChef: B Bertilsson\nEtableringsår: 1935.",
    "structured": {
        "1": {
            "company_name": "GUFLON AB",
            "address": "Klippan",
            "phone_number": "0435-12190",
            "bank_details": {
                "bankgiro": "577-9426",
                "postgiro": "703808-6"
            },
            "activity": "Tillverkar o säljer tekniska plast- o gummiartiklar",
            "employees": 10,
            "capital": 25000,
            "key_personnel": [
                {
                    "name": "Dir Gunnar Månsson",
                    "position": "ordf"
                },
                {
                    "name": "fru Gunnel Månsson"
                },
                {
                    "name": "Gunnar Månsson",
                    "position": "Verkst dir"
                }
            ],
            "establishment_year": 1941
        },
        "2": {
            "company_name": "GUGGENBERGER, ERICH H",
            "address": "Stockholm, Sveav 17",
            "phone_number": "08-11 90 00",
            "postgiro": "11900",
            "activity": "Agentur med textilvaror",
            "establishment_year": 1919
        },
        "3": {
            "company_name": "GULDSMEDS AB ELFSTRÖM & JOHANSON",
            "address": "Nässjö, Box 195, Storg 24",
            "phone_number": "0380-106 96",
            "bank_details": {
                "bankgiro": "452-8063",
                "postgiro": "33424-3"
            },
            "activity": "Säljer ur, guld, silver o presentartiklar",
            "employees": 15,
            "capital": 350000,
            "key_personnel": {
                "Verkst dir": "Sören Elfström"
            },
            "establishment_year": 1920
        },
        "4": {
            "company_name": "GULDSMEDSAKTIEBOLAGET G.A.B.",
            "address": "Malmö 1, Box 105, Citadellsv 11",
            "phone_number": "040-733 30",
            "bank_details": {
                "bankgiro": "283-9306",
                "postgiro": "3383-7"
            },
            "activity": "Grossistföretag inom guldsmedsbranschen",
            "employees": 100,
            "annual_turnover": 14000000,
            "capital": 5000000,
            "key_personnel": {
                "Verkst dir": "Carl-S Roos"
            },
            "establishment_year": 1867
        },
        "5": {
            "company_name": "LUNDH & CO AB, IVAR",
            "address": "Stockholm 14, Box 14002, Tor-stenssonsg 3",
            "phone_number": "08-63 19 20",
            "bank_details": {
                "bankgiro": "700-2314",
                "postgiro": "56588-7"
            },
            "telex": "1695",
            "activity": "Auktoriserad skepps-klarering, skeppsmäkleri, befraktning av torrlast, tankfartyg, fartygsförsäljning o nybyggnadskon-traktering. Agenturverksamhet för varv o fartygsutrustningar. Försäkringsagenter, sjöfartkonsulter",
            "employees": 17,
            "capital": 50000,
            "key_personnel": {
                "Verkst dir": "Lennart Bengtsson"
            },
            "establishment_year": 1922
        },
        "6": {
            "company_name": "ADDO, AB",
            "address": "Malmö 3, Pack. O Farmv 12",
            "phone_number": "040-93 68 00",
            "bank_details": {
                "bankgiro": "999-9004",
                "postgiro": "24470-7"
            },
            "activity": "Tillverkar räkne- o bokföringsmaskiner samt utrustning för automatisk databehandling. Försäljning av postbehandlings maskiner",
            "employees": 2400,
            "capital": 11250000,
            "key_personnel": [
                {
                    "Verkst dir": "Gunnar Agrell"
                },
                {
                    "Försäljn-dir": "Torsten Odervall"
                },
                {
                    "Inköpschef": "Börje Winnerstam"
                }
            ],
            "establishment_year": 1918,
            "dotterbolag": "AB Multo, örkelljunga. Ingår i Facit-koncernen."
        },
        "7": {
            "company_name": "ADDRESSOGRAPH MULTI-GRAPH AB",
            "address": "Stockholm, Gotlandsg 43",
            "phone_number": "08-44 06 60",
            "postgiro": "1169",
            "activity": "Adresseringsmaskiner, maskiner för brevpropaganda o kontorstryck, offset- o duplice-ringsmaskiner, sättmaskiner, foto-sättningsapparater, rubriksättnings-apparater, kopieringsautomater",
            "branch_offices": [
                {
                    "location": "Göteborg C",
                    "phone_number": "031-24 3312, 24 3313",
                    "postgiro": "1169"
                },
                {
                    "location": "Malmö C, N Vallg 98",
                    "phone_number": "040-97 40 15, 97 90 14",
                    "postgiro": "1169"
                }
            ],
            "varunamn": "Addressograph, Bruning, Fotolist, Headliner, Multigraph, Multilith, Vari-Typer",
            "capital": 500000,
            "key_personnel": {
                "Verkst dir": "T F E Lane"
            },
            "establishment_year": 1922
        },
        "8": {
            "company_name": "WERACO, AB",
            "address": "Stockholm, Roseng 6",
            "phone_number": "08-241290",
            "bank_details": {
                "bankgiro": "70-0400",
                "postgiro": "1193"
            },
            "activity": "Importerar parfym, kosmetik, herrpreparat o hårvårds-medel",
            "employees": 35,
            "annual_turnover": 8000000,
            "capital": 125000,
            "key_personnel": {
                "Verkst dir": "Jouke Bouius"
            },
            "establishment_year": 1947
        },
        "9": {
            "company_name": "NORRLANDS HEMSLÖJD, AB",
            "address": "Stockholm, Pridhemsg 60",
            "phone_number": "08-52 26 46, 53 2636",
            "bankgiro": "56-7048",
            "postgiro": "270350",
            "activity": "Engrosförsäljning o agenturrörelse med hemslöjd, presentartiklar, korgar o textilier",
            "key_personnel": {
                "Verkst dir": "Paul Bjuhr"
            },
            "establishment_year": 1941
        },
        "10": {
            "company_name": "NORRLANDS SKOGSÄGARES CELLULOSA AB",
            "address": "Kramfors",
            "phone_number": "0612-124 50",
            "postgiro": "8540-7",
            "activity": "Tillverkar sulfatmassa (barr- o lövved), sulfitmassa, kraftpapper, finpapper, kemiska produkter o sågade trävaror.",
            "key_personnel": [
                "Chef: Dir Alf Lindgren",
                "Chef: Dir Frank Skarborg",
                "Chef: Dir Tage Lundén, Köpmanholmen",
                "Chef: övering Folke Brunstedt, Hörnefors",
                "Chef: dir Evert Nilsson, Väja",
                "Chef: övering Hans Fastén, Krokom",
                "Chef: övering Per Svanberg, Vallvik"
            ],
            "establishment_year": 1959
        },
        "11": {
            "company_name": "NORRLANDS SLIPINDUSTRI, AB",
            "address": "Sundsvall, Ostermov 35",
            "phone_number": "060-1104 44",
            "bankgiro": "18-0471",
            "postgiro": "70999-8",
            "activity": "Slipning av eggverktyg för cellulosa- o mekaniska industrin",
            "employees": 14,
            "capital": 20000,
            "key_personnel": [
                "Ägare o chefer: Alvar Haglund",
                "Ägare o chefer: Harry Widmark"
            ],
            "establishment_year": 1963
        },
        "12": {
            "company_name": "NORRLANDS VADD-FABRIK, AB",
            "address": "Järbo, Norrlandsg 4, Fack 29",
            "phone_number": "0290-700 19",
            "bankgiro": "78-7621",
            "postgiro": "80088",
            "activity": "Tillverkar sängkläder, all slags vadd o tätningslister",
            "employees": 10,
            "annual_turnover": 500000,
            "capital": 25000,
            "key_personnel": {
                "Verkst dir": "Rune Berggren"
            },
            "establishment_year": 1900
        },
        "13": {
            "company_name": "BERGA SNICKERIFABRIK, AB",
            "address": "Berga, Järnvägsg 14, Box 9",
            "phone_number": "0491-500 02, 502 22",
            "bankgiro": "14-9402",
            "postgiro": "23681",
            "activity": "Dörrar för export, sågade o hyvlade trävaror",
            "employees": 60,
            "annual_turnover": 3400000,
            "capital": 100000,
            "key_personnel": {
                "Verkst dir": "Robert Forsberg"
            },
            "establishment_year": 1923
        },
        "14": {
            "company_name": "FIX TRIKAFABRIKER AB",
            "address": "Söderköping, Box 16",
            "phone_number": "0121-109 80, 10960",
            "bankgiro": "609-8685",
            "postgiro": "29402-5",
            "activity": "Ull verkar underkläder, fritidsplagg, strumpor o strumpbyxor",
            "varunamn": "Tussilago, Fix",
            "employees": 450,
            "annual_turnover": 24000000,
            "capital": 600000,
            "key_personnel": {
                "Verkst dir": "Liss Surtevall"
            },
            "establishment_year": 1955
        },
        "15": {
            "company_name": "WENNHEDS FABRIKS AB",
            "address": "Gnosjö, Målskog",
            "phone_number": "0370-95015, 95055",
            "bankgiro": "54-2556",
            "postgiro": "95042",
            "activity": "Tillverkning av spik o tråddetaljer",
            "employees": 12,
            "annual_turnover": 1000000,
            "capital": 35000,
            "key_personnel": {
                "Chef": "Fabr Adolf Wennhed"
            },
            "establishment_year": 1918
        },
        "16": {
            "company_name": "WENNQVISTS KONSTRUK-TIONSBYRÄ, K B",
            "address": "Karlstad l.Herrgårdsg 17, Box 324",
            "phone_number": "054-11 53 95",
            "postgiro": "387614",
            "activity": "Upprättar konstruktionsritningar för bro-, hus- o industribyggnader. Totalplanerar industribyggnader. Kontroll o arbetsledning. Ljuskopiering",
            "employees": 10,
            "annual_turnover": 450000,
            "key_personnel": {
                "Verkst dir": "Civiling Bernt Wenn-qvist"
            },
            "establishment_year": 1939
        },
        "17": {
            "company_name": "HYLLINGE PRODUKTER",
            "address": "Hyllinge, Smedg",
            "phone_number": "042-25180",
            "bankgiro": "34-0621",
            "postgiro": "569786",
            "activity": "Trätoffeltillverkning med inreg varumärke HYLLINGE ORTOPEDIC. Specialitet: trätofflor för industrin med halkskyddan-de sula",
            "chief": "Eskil Jacobsson"
        },
        "18": {
            "company_name": "HYLLMEKANO, AB",
            "address": "Malmö, Tessins v 6",
            "phone_number": "040-695 43, 695 44",
            "bankgiro": "641-0690",
            "postgiro": "532960-2",
            "activity": "Agentur för AB Nordverk. Säljer stålinredningar, stålhyllor, pallhyllor, container etc",
            "employees": 3,
            "annual_turnover": 1500000,
            "capital": 20000,
            "key_personnel": {
                "Verkst dir": "Disp Lennart Ullberg"
            },
            "establishment_year": 1960
        },
        "19": {
            "company_name": "GOT A KANAL, REDERI AB",
            "address": "Göteborg 1, Hotellplatsen 2",
            "phone_number": "031-17 76 15",
            "activity": "Rederi med passageraretrafik på Sveriges Blå Band. Även kortare dagsresor",
            "branch_offices": {
                "location": "11130 Stockholm, Skeppsbron 16",
                "phone_number": "08-10 04 57"
            },
            "capital": 100000,
            "key_personnel": {
                "Verkst dir": "Helge Källsson"
            },
            "establishment_year": 1869
        },
        "20": {
            "company_name": "GOTA PARTILAGER AB",
            "address": "Göteborg H, Kvilleg 9 E",
            "phone_number": "031-5117 40, 511741",
            "bankgiro": "848-3281",
            "postgiro": "45420-7",
            "activity": "Leksaker o souvenirer en gros",
            "capital": 50000,
            "chief": "B Bertilsson",
            "establishment_year": 1935
        }
    }
}