{
    "original": "SVENSKT KONSTSILKE, AB\n\nPnr 50103\n\nBorås 1, Box 131. Mariestrandsg 1.\nTel 033-12 72 00. Bankgiro\n839-3746. Postgiro 14941-9. Tga\nEskos. Telex 36055\nVerksamhet: Förädling av\nimporterade garner, företrädesvis till\ncordväv för bildäck samt andra\nmaterial för gummiindustrin.\nAgenturverksamhet o\nfastighetsförvaltning\n\nAntal anställda: 90\nÅrsomsättning: 25 000000\nAktiekapital: 6 000000\nVerkst dir: Fredric Suter\nEtableringsàr: 1918.\n\nSVENSKT MJÖLKSOCKER, AB\n\nPnr 595 00\n\nMjölby, Box 184. Magasinsg 25.\nTel 0142-133 20. Bankgiro\n128-2177. Postgiro 75250-1. Tga\nPasteur. Telex 5566 PASTEUR S\nVerksamhet: Tillverkar\nmjölksocker, bageri- o glassaromer,\nbageri-o glasschoklad samt\nanslagspastor m m för bageriindustrin\nAntal anställda: 90\nÅrsomsättning: 14 000 000\nAktiekapital: 300 000\nVerkst dir: Gösta Winberg\nEtableringsàr: 1945.\n\nSVENSKT PAPPER AB\n\nPnr 136 02\n\nHanden 2, Fack. Tel 0750-221 50.\nBankgiro 482-0502. Postgiro\n56060-7. Telex 10977 SWEPAP S\nVerksamhet:\nFinpappersförsäljning. Grossiströrelse i Jordbro\n\nTillverkningsförsäljning:\n\n113 50 Stockholm. Sveav 98. Tel\n08-15 17 10\n\n402 74 Göteborg 8, Box 8945. Tel\n031-23 26 12\n\n21124 Malmö, Bjurög 48. Tel\n0404)3 48 35\nAntal anställda: 70\nÅrsomsättning: 72 000 000\nAktiekapital: 300 000\nVerkst din Lennart Sahlström\nEtableringsàr: 1910\nEtt MoDo-företag.\n\nSVENSKT TENN AB\n\nPnr 114 51\n\nStockholm, Strandv 5 A. Tel\n08-60 0 6 72. Postgiro 51906.\nTga Svente\n\nVerksamhet: Tillverkar o säljer\ntennvaror, möbler, textilier o\nbelysningar\n\nAntal Anställda: 70\nAktiekapital: 100 000\nVeikst din Estrid Ericson\nEtableringsàr: 1924\nOmbildat till aktiebolag 1933.\n\nSVENSON &amp; HAGBERG, AB\n\nPnr 501 02\n\nBorås 1, Box 30. Lilla Brog 9.\nTel 033-1109 29, 111108. Bankgiro\n531-3168. Postgiro 14946-8\nVeiksamhet: Tillverkar\ndamklänningar o klänningsrockar\nAntal anställda: 50\nAktiekapital: 200 000\nVerkst dir: Ulf Nilsson\nEtableringsàr: 1877.\n\nSVENSSONS MEK VERKSTADS\nAB, BRÖDERNA\n\nPnr 69100\n\nKarlskoga, Skråg 11. Tel\n0586-101 94, 101 97. Bankgiro 866-7263.\nPostgiro 335983-2\nVerksamhet: Verktyg, fixturer,\njig-gar, tryckkärl, järnkonstruktioner\nAntal anställda: 80\nÅrsomsättning: 5 000 000\nAktiekapital: 60 000\nVerkst din Torgny Svensson\nEtableringsàr: 1952.\n\nSVENSSONS RÖR AB\n\nPnr 264 00\n\nKlippan, Torggränd 4. Tel\n0435-101 94, 101 97. Bankgiro 86-6726.\nPostgiro 335083\n\nVerksamhet: VVS-, rör-, olje-,\nindustriinstallationer\nAktiekapital: 20 000\nVerkst dir: Bengt Svensson\nEtableringsàr 1946.\n\nSVENGREN &amp; CO AB, 0\n\nPnr 633 40\n\nEskilstuna, Rådhustorget 2. Tel\n016-13 77 50. Bankgiro 601-3908.\nPostgiro 10722-7\n\nVerksamhet: Järn- o leksakshandel\nAntal anställda: 37\nÅrsomsättning: 6 000 000\nAktiekapital: 220 000\nVerkst dir: Hans-Gösta Lindström\nEtableringsår: 1867.\n\nLJUNGDAHLS HANDELS &amp;\nFABRIKS AB, C\n\nPnr 443 00\n\nLerum. Tel 0302-100 31, 109 09\nVerksamhet: Färger, Tremco\nfogmassor, Penetone avfettningsmedel mm\nHuvudkontor: 40272 Göteborg 8,\nBox 8885. Tel 031-51 37 60. Tga\nSpackolin\n\nAntal anställda: 130\nÅrsomsättning: 17 500 000\nAktiekapital: 350 000\nVerkst dir: Jarl Ringström\nEtableringsår: 1902.\n\nARONSSON I LANDSKRONA\nAB, BRÖDERNA\n\nPnr 26122\n\nLandskrona 1, Järnvägsområdet. Box\n163. Tel 0418-163 80. Bankgiro\n86-8525. Postgiro 263360-0.\nTga Metallprodukt\nVerksamhet: Handel med järn- o\nmetallskrot, textilavfall, ull,\ndjurhår m m\n\nDir: Louis Aronsson\nChefsass: Stig Aronsson\nEtableringsår: 1923.\n\nEBBES BRUK AB\n\nPnr 572 00\n\nOskarshamn. Tel 0491-150 20.\nBankgiro 85-6605. Postgiro 577526.\nTga Ebbes Bruk\n\nVerksamhet: Tillverkar\nvarmluftsap-parater, tvättorkar, sanitets-,\nbyggnads- o obeställningsgjutgods.\nSpecialitet: maskinformat gjutgods\ni kvalitet SIS 0115-0120-0125,\ntunnplåtsarbeten\nAntal anställda: 85\nÅrsomsättning: 5 000 000\nAktiekapital: 596 000\nVerkst dir: Ewert Ytterell\nEtableringsår: 1914.\n\nRAH\n\nRAHLËNS GULDSMEDS AB\n\nPnr 502 32\n\nBorås, üsterlångg 44. Tel\n033-1106 31. Bankgiro 83-9356.\nPostgiro 277652\n\nVerksamhet: Säljer guld- o\nsilvervaror en gros. Tillverkar guldringar\nAntal anställda: 10\nAktiekapital: 52 000\nChef: Börje Rahlén\nEtableringsår: 1902\nOmbildat till aktiebolag 1937.\n\nRALTON AB\n\nPnr 25104\n\nHelsingborg 1, Box 258. Sjö g 5.\nTel 042-14 43 50. Bankgiro 65-2852.\nPostgiro 447204-9\nVerksamhet: Importerar o säljer\ni: x, småbröd o bakverk.\nDistribu-&lt;. r reklammaterial o trycksaker\nAntal anställda: 80\nÅrsomsättning: 8 500 000\nAktiekapital: 20 000\nVerkst dir: Hans Raber\nEtableringsår. 1934\nOmbildat till aktiebolag 1954.\n\nRAMEK AB\n\nRationella Mekaniska AB\n\nPnr 59104\n\nMotala 4, Box 450. Kontor o\nverkstäder Borensv 2-4. Tel\n0141-510 88, 106 09. Bankgiro 698-7036.\nPostgiro 715825-6\nVerksamhet:\n\nMEKANISKA SIDAN:\njärnkonstruktioner, pressningsarbeten,\nkantpressning, svarvning, fräsning,\nhyvling, borrning m m.\nSVETSNING: kolstål, rostfritt,\naluminium, punkt- o pressvetsning,\nbetning, industrilackering, montage.\nHDRSIDAN: instrument- o\nprocessledningar i rostfritt, koppar o\nkolstål, industrirörledningar, kolstål,\nrostfritt o montage\nAntal anställda: 45\nÅrsomsättning: 3 000 000\nAktiekapital: 26 000\nStyrelseordf: Dir Rune Persson\nVerkst dir: Rune Persson\nKamrer: Monica Olsson\nMontagechef: Bengt Widing\nVerkstadsing: Birger Sahlström\nVerkmäst: Martin Andersson,\nGunnar Eriksson\nInköp: Gunnar Persson\nChef för ritsidan: Sune Gummesson\nEtableringsår: 1968.\n\nTORKAPPARATER, AB\n\nPnr 11134\n\nStockholm, Sveav 28-30. Tel\n08-104650, 104651. Bankgiro 56-\n\n2985. Postgiro 152688-8.Tga\nTorkapparater\n\nVerksamnet: Konstruerar o låter\nvid olika verkstäder tillverka\nindustriella torkanläggningar, kylare,\nrotérugnar, blandare för\npulverformigt gods, även klibbande,\ndammande o slitande gods samt\ntvätttorn för gaser. Slamtorknings- o\nförbränningsugnar för avloppsslam.\nEgna patenterade konstruktioner\nAntal anställda: 12\nÅrsomsättning: 5 000000\nAktiekapital: 30 000\nVerkst din Civilekonom, ing Gösta\nBojner\n\nEtableringsår: 1937.\n\nGERNER, AB CARL\n\nPnr 21137\n\nMalmö, Stora Nyg 34. Tel 040-\n\n719 00. Bankgiro 34-8321. Postgiro\n14182-0. Tga Gerner\nVerksamhet:\nRörledningsentreprenör, utför värme- o\nsanitetstek-niska installationer\nAntal anställda: 43\nÅrsomsättning: 3600 000\nAktiekapital: 240 000\nChef: Dir Bengt Lindblad\nEtableringsår: 1884.\n\nNÄFVEQVARNS BRUK, AB\n\nPnr 610 54\n\nNävekvarn. Tel 0155-50150. Post.\n\ngiro 26913. Tga Näfveqvarn,\nNyköping\n\nVerksamhet: Lätt- o\ntungmetall-gjuteri, maskinbearbetning\nAntal anställda: 175\nAktiekapital: 3 000 000\nVerkst dir: Lennart Wikblom\nEtableringsår: 1917\nOmbildat till aktiebolag 1923.\n\nNÄVEQVARNSMOTOR AB\nN Q M\n\nPnr 260 35\n\nOdåkra, Fleninge. Tel 042-942 15.\nBankgiro 334-2060. Postgiro\n470934-1. Tga Gardenmachines\nVerksamhet: Tillverkar o säljer\nträdgårdsmaskiner, sopmaskiner,\nuniversaltraktorer\nAntal anställda: 10\nÅrsomsättning: 2 000 000\nAktiekapital: 175 000\nVerkst dir: Lennart Vikstrand\nEtableringsår: 1965.\n\nBOHUSLÄNSKA BETONG AB\n\nPnr 450 53\n\nHällevadsholm, Box 31. Tel\n0524-403 75. Bankgiro 43-9408. Postgiro\n567790\n\nVerksamhet: Tillverkar färdig\nbetong o betongvaror\nAntal anställda: 25\nÅrsomsättning: 2500 000\nAktiekapital: 25 0 000\nVerkst dir: Berndt Davidsson\nEtableringsår: 1946.",
    "structured": {
        "1": {
            "company_name": "SVENSKT KONSTSILKE, AB",
            "pnr": "50103",
            "address": "Borås 1, Box 131. Mariestrandsg 1.",
            "phone_number": "033-12 72 00",
            "bank_details": {
                "bankgiro": "839-3746",
                "postgiro": "14941-9"
            },
            "activity": "Förädling av importerade garner, företrädesvis till cordväv för bildäck samt andra material för gummiindustrin. Agenturverksamhet o fastighetsförvaltning",
            "employees": 90,
            "annual_turnover": 25000000,
            "capital": 6000000,
            "key_personnel": [
                {
                    "name": "Fredric Suter",
                    "position": "Verkst dir"
                }
            ],
            "establishment_year": 1918
        },
        "2": {
            "company_name": "SVENSKT MJÖLKSOCKER, AB",
            "pnr": "595 00",
            "address": "Mjölby, Box 184. Magasinsg 25.",
            "phone_number": "0142-133 20",
            "bank_details": {
                "bankgiro": "128-2177",
                "postgiro": "75250-1"
            },
            "activity": "Tillverkar mjölksocker, bageri- o glassaromer, bageri-o glasschoklad samt anslagspastor m m för bageriindustrin",
            "employees": 90,
            "annual_turnover": 14000000,
            "capital": 300000,
            "key_personnel": [
                {
                    "name": "Gösta Winberg",
                    "position": "Verkst dir"
                }
            ],
            "establishment_year": 1945
        },
        "3": {
            "company_name": "SVENSKT PAPPER AB",
            "pnr": "136 02",
            "address": "Handen 2, Fack.",
            "phone_number": "0750-221 50",
            "bank_details": {
                "bankgiro": "482-0502",
                "postgiro": "56060-7"
            },
            "activity": "Finpappersförsäljning. Grossiströrelse i Jordbro",
            "employees": 70,
            "annual_turnover": 72000000,
            "capital": 300000,
            "key_personnel": [
                {
                    "name": "Lennart Sahlström",
                    "position": "Verkst din"
                }
            ],
            "establishment_year": 1910
        },
        "4": {
            "company_name": "SVENSKT TENN AB",
            "pnr": "114 51",
            "address": "Stockholm, Strandv 5 A.",
            "phone_number": "08-60 0 6 72",
            "postgiro": "51906",
            "activity": "Tillverkar o säljer tennvaror, möbler, textilier o belysningar",
            "employees": 70,
            "capital": 100000,
            "key_personnel": [
                {
                    "name": "Estrid Ericson",
                    "position": "Verkst din"
                }
            ],
            "establishment_year": 1924
        },
        "5": {
            "company_name": "SVENSON & HAGBERG, AB",
            "pnr": "501 02",
            "address": "Borås 1, Box 30. Lilla Brog 9.",
            "phone_number": "033-1109 29, 111108",
            "bank_details": {
                "bankgiro": "531-3168",
                "postgiro": "14946-8"
            },
            "activity": "Tillverkar damklänningar o klänningsrockar",
            "employees": 50,
            "capital": 200000,
            "key_personnel": [
                {
                    "name": "Ulf Nilsson",
                    "position": "Verkst dir"
                }
            ],
            "establishment_year": 1877
        },
        "6": {
            "company_name": "SVENSSONS MEK VERKSTADS AB, BRÖDERNA",
            "pnr": "69100",
            "address": "Karlskoga, Skråg 11",
            "phone_number": "0586-101 94, 101 97",
            "bank_details": {
                "bankgiro": "866-7263",
                "postgiro": "335983-2"
            },
            "activity": "Verktyg, fixturer, jig-gar, tryckkärl, järnkonstruktioner",
            "employees": 80,
            "annual_turnover": 5000000,
            "capital": 60000,
            "key_personnel": [
                {
                    "name": "Torgny Svensson",
                    "position": "Verkst din"
                }
            ],
            "establishment_year": 1952
        },
        "7": {
            "company_name": "SVENSSONS RÖR AB",
            "pnr": "264 00",
            "address": "Klippan, Torggränd 4",
            "phone_number": "0435-101 94, 101 97",
            "bank_details": {
                "bankgiro": "86-6726",
                "postgiro": "335083"
            },
            "activity": "VVS-, rör-, olje-, industriinstallationer",
            "capital": 20000,
            "key_personnel": [
                {
                    "name": "Bengt Svensson",
                    "position": "Verkst dir"
                }
            ],
            "establishment_year": 1946
        },
        "8": {
            "company_name": "SVENGREN & CO AB, 0",
            "pnr": "633 40",
            "address": "Eskilstuna, Rådhustorget 2",
            "phone_number": "016-13 77 50",
            "bank_details": {
                "bankgiro": "601-3908",
                "postgiro": "10722-7"
            },
            "activity": "Järn- o leksakshandel",
            "employees": 37,
            "annual_turnover": 6000000,
            "capital": 220000,
            "key_personnel": [
                {
                    "name": "Hans-Gösta Lindström",
                    "position": "Verkst dir"
                }
            ],
            "establishment_year": 1867
        },
        "9": {
            "company_name": "LJUNGDAHLS HANDELS & FABRIKS AB, C",
            "pnr": "443 00",
            "address": "Lerum",
            "phone_number": "0302-100 31, 109 09",
            "activity": "Färger, Tremco fogmassor, Penetone avfettningsmedel mm",
            "employees": 130,
            "annual_turnover": 17500000,
            "capital": 350000,
            "key_personnel": [
                {
                    "name": "Jarl Ringström",
                    "position": "Verkst dir"
                }
            ],
            "establishment_year": 1902
        },
        "10": {
            "company_name": "ARONSSON I LANDSKRONA AB, BRÖDERNA",
            "pnr": "26122",
            "address": "Landskrona 1, Järnvägsområdet. Box 163",
            "phone_number": "0418-163 80",
            "bank_details": {
                "bankgiro": "86-8525",
                "postgiro": "263360-0"
            },
            "activity": "Handel med järn- o metallskrot, textilavfall, ull, djurhår m m",
            "key_personnel": [
                {
                    "name": "Louis Aronsson",
                    "position": "Dir"
                },
                {
                    "name": "Stig Aronsson",
                    "position": "Chefsass"
                }
            ],
            "establishment_year": 1923
        },
        "11": {
            "company_name": "EBBES BRUK AB",
            "pnr": "572 00",
            "address": "Oskarshamn",
            "phone_number": "0491-150 20",
            "bank_details": {
                "bankgiro": "85-6605",
                "postgiro": "577526"
            },
            "activity": "Tillverkar varmluftsap-parater, tvättorkar, sanitets-, byggnads- o obeställningsgjutgods. Specialitet: maskinformat gjutgods i kvalitet SIS 0115-0120-0125, tunnplåtsarbeten",
            "employees": 85,
            "annual_turnover": 5000000,
            "capital": 596000,
            "key_personnel": [
                {
                    "name": "Ewert Ytterell",
                    "position": "Verkst dir"
                }
            ],
            "establishment_year": 1914
        },
        "12": {
            "company_name": "RAHLËNS GULDSMEDS AB",
            "pnr": "502 32",
            "address": "Borås, üsterlångg 44",
            "phone_number": "033-1106 31",
            "bank_details": {
                "bankgiro": "83-9356",
                "postgiro": "277652"
            },
            "activity": "Säljer guld- o silvervaror en gros. Tillverkar guldringar",
            "employees": 10,
            "capital": 52000,
            "key_personnel": [
                {
                    "name": "Börje Rahlén",
                    "position": "Chef"
                }
            ],
            "establishment_year": 1902
        },
        "13": {
            "company_name": "RALTON AB",
            "pnr": "25104",
            "address": "Helsingborg 1, Box 258. Sjö g 5",
            "phone_number": "042-14 43 50",
            "bank_details": {
                "bankgiro": "65-2852",
                "postgiro": "447204-9"
            },
            "activity": "Importerar o säljer i: x, småbröd o bakverk. Distribu-&lt;. r reklammaterial o trycksaker",
            "employees": 80,
            "annual_turnover": 8500000,
            "capital": 20000,
            "key_personnel": [
                {
                    "name": "Hans Raber",
                    "position": "Verkst dir"
                }
            ],
            "establishment_year": 1934
        },
        "14": {
            "company_name": "RAMEK AB",
            "pnr": "59104",
            "address": "Motala 4, Box 450. Kontor o verkstäder Borensv 2-4",
            "phone_number": "0141-510 88, 106 09",
            "bank_details": {
                "bankgiro": "698-7036",
                "postgiro": "715825-6"
            },
            "activity": "MEKANISKA SIDAN: järnkonstruktioner, pressningsarbeten, kantpressning, svarvning, fräsning, hyvling, borrning m m. SVETSNING: kolstål, rostfritt, aluminium, punkt- o pressvetsning, betning, industrilackering, montage. HDRSIDAN: instrument- o processledningar i rostfritt, koppar o kolstål, industrirörledningar, kolstål, rostfritt o montage",
            "employees": 45,
            "annual_turnover": 3000000,
            "capital": 26000,
            "key_personnel": [
                {
                    "name": "Rune Persson",
                    "position": "Styrelseordf"
                },
                {
                    "name": "Rune Persson",
                    "position": "Verkst dir"
                },
                {
                    "name": "Monica Olsson",
                    "position": "Kamrer"
                },
                {
                    "name": "Birger Sahlström",
                    "position": "Verkmäst"
                }
            ],
            "establishment_year": 1968
        },
        "15": {
            "company_name": "TORKAPPARATER, AB",
            "pnr": "11134",
            "address": "Stockholm, Sveav 28-30",
            "phone_number": "08-104650, 104651",
            "bank_details": {
                "bankgiro": "56-2985",
                "postgiro": "152688-8"
            },
            "activity": "Konstruerar o låter vid olika verkstäder tillverka industriella torkanläggningar, kylare, rotérugnar, blandare för pulverformigt gods, även klibbande, dammande o slitande gods samt tvätttorn för gaser. Slamtorknings- o förbränningsugnar för avloppsslam. Egna patenterade konstruktioner",
            "employees": 12,
            "annual_turnover": 5000000,
            "capital": 30000,
            "key_personnel": [
                {
                    "name": "Gösta Bojner",
                    "position": "Verkst din"
                }
            ],
            "establishment_year": 1937
        },
        "16": {
            "company_name": "GERNER, AB CARL",
            "pnr": "21137",
            "address": "Malmö, Stora Nyg 34",
            "phone_number": "040-719 00",
            "bank_details": {
                "bankgiro": "34-8321",
                "postgiro": "14182-0"
            },
            "activity": "Rörledningsentreprenör, utför värme- o sanitetstekniska installationer",
            "employees": 43,
            "annual_turnover": 3600000,
            "capital": 240000,
            "key_personnel": [
                {
                    "name": "Bengt Lindblad",
                    "position": "Chef"
                }
            ],
            "establishment_year": 1884
        },
        "17": {
            "company_name": "NÄFVEQVARNS BRUK, AB",
            "pnr": "610 54",
            "address": "Nävekvarn",
            "phone_number": "0155-50150",
            "postgiro": "26913",
            "activity": "Lätt- o tungmetall-gjuteri, maskinbearbetning",
            "employees": 175,
            "annual_turnover": 3000000,
            "capital": 3000000,
            "key_personnel": [
                {
                    "name": "Lennart Wikblom",
                    "position": "Verkst dir"
                }
            ],
            "establishment_year": 1917
        },
        "18": {
            "company_name": "NÄVEQVARNSMOTOR AB N Q M",
            "pnr": "260 35",
            "address": "Odåkra, Fleninge",
            "phone_number": "042-942 15",
            "bank_details": {
                "bankgiro": "334-2060",
                "postgiro": "470934-1"
            },
            "activity": "Tillverkar o säljer trädgårdsmaskiner, sopmaskiner, universaltraktorer",
            "employees": 10,
            "annual_turnover": 2000000,
            "capital": 175000,
            "key_personnel": [
                {
                    "name": "Lennart Vikstrand",
                    "position": "Verkst dir"
                }
            ],
            "establishment_year": 1965
        },
        "19": {
            "company_name": "BOHUSLÄNSKA BETONG AB",
            "pnr": "450 53",
            "address": "Hällevadsholm, Box 31",
            "phone_number": "0524-403 75",
            "bank_details": {
                "bankgiro": "43-9408",
                "postgiro": "567790"
            },
            "activity": "Tillverkar färdig betong o betongvaror",
            "employees": 25,
            "annual_turnover": 2500000,
            "capital": 250000,
            "key_personnel": [
                {
                    "name": "Berndt Davidsson",
                    "position": "Verkst dir"
                }
            ],
            "establishment_year": 1946
        }
    }
}