{
    "original": "CASTROL AB\n\nPnr 103 81\n\nStockholm 7, Stureplan 2. Box\n7020. Tel 08-63 18 20. Bankgiro\n56-9327. Postgiro 52564. Telex\n19968 CASTROL S. Tga Castrol\nVerksamhet: Castrol smörj- o\nproduktionsmedel\nAntal anställda: 55\nAktiekapital: 800 000\nVerkst dir: Björn Högberg\nEtableringsår: 1931.\n\nHÄSTVEDA GJUTERI AB\n\nPnr 280 23\n\nHästveda. Tel 0451-303 1 7.\nBankgiro 282-2077. Postgiro 476 588-9\nVerksamhet: Tillverkar\nbeställningsgods\nAntal anställda: 21\nÅrsomsättning: 1300 000\nAktiekapital: 40 000\nVerkst dir: Osten Englund\nEtableringsår: 1954.\n\nHÄSTü BÅTVARV\nBRÖDERNA JOHANSSON &amp; CO\n\nPnr 610 25\n\nArkösund. Tel 0125-200 73, 204 64.\nBankgiro 125-4580. Postgiro\n144436-3\n\nVerksamhet: Vinterförvaring,\nreparationer. Tillverkar ARKÖ\nORIGINAL-Hydrocoptern\nVarunamn: Arkö\nOriginal-Hydro-copter\n\nChefer: Fabr Albin Johansson,\nfabr Börje Johansson, fabr Göran\nJohansson\nEtableringsår 1918.\n\nHÄVEROORTENS\nLASTBIL-CENTRAL FÖRENING UPA\n\nPnr 763 01\n\nHallstavik, Box 37. Uppsalav. Tel\n0175-203 48, 203 80. Bankgiro\n804-8308. Postgiro 14726-4\nVerksamhet: Utför transporter.\nSpeditionsverksamhet i samarbete\nmed Godstrafik &amp; Bilspedition\n\nAntal anställda: 3\nÅrsomsättning: 9 400 000\nFöreståndare o transportchef:\n\nSven Larsson\nEtableringsår. 1943.\n\nSVENSK PLASTIK, AB\n\nPnr 332 00\n\nGislaved, Mårtensg 26. Tel\n0371-103 61. Bankgiro 42-6746. Postgiro\n334239\n\nVerksamhet: Kammar, hushålls- o\nindustriartiklar i förekommande\nplaster\n\nAntal anställda: 20\nAktiekapital: 45 000\nVerkst dir: AV Karlsson\nEtableringsår: 1946.\n\nALFA-LAVAL AB\n\nPnr 14700\n\nTtomba, Fack. Tel 0753-31100.\n\nTga Alfalaval.\nTelex 10260 ALTUMBA S\nVerksamhet: Alfa-Lavalkoncernen\ntillverkar o säljer\nmjölkningsmaskiner, mjölkkylare, separatorer o\nannan utrustning för lantbruket.\nSeparatorer, plattvärmeväxlare,\nkylmaskiner samt övriga maskiner\no utrustningar för mejerier.\nSeparatorer, termiska apparater o\nanläggningar för annan\nlivsmedelsindustri än mejerier, för sjöfarten,\nkraft- o maskinindustrin samt\nkemi- o processindustrierna\nTextilvävstolar, tråddukar för\npappersindustrin\n\nVerkstäder: Eskilstuna.\nPressbolaget Tel 016-13 72 00. Telex 40990\nALTUNA S\n\nLund. Tel 046-14 03 20. Telex\n3145 ALLUND S\nSödertälje. Tel 0755-325 30\nTullinge o Tumba. Tel 0753-311 00.\nTelex 10260, 1253 ALTUMBA S\nVarunamn: Alfa-Laval, De Laval\nAntal anställda: 15 200 (koncernen)\nÅrsomsättning: 1 450 000 000\n(koncernen)\n\nAktiekapital: 213 280 000\nStyrelse: Dir Tryggve Holm (ordf),\ngreve Peder Bonde, agronom Stig\nJanson, dir Karl Nilsson (v ordf),\ndir Hans Ståhle\nVerkst dir: Hans Ståhle\nEtableringsår: 1878\nOmbildat till aktiebolag 1883.\nSvenska dotterbolag: AB\nPump-Separators Gjuterier, Box 18,\nKatrineholm. Tel 0150-133 45.\nAB Rosenblads Patenter. Box 94,\nTumba. Tel 3753-355 00. Telex\n10996 ALROCEL S\nZander &amp; Ingeström AB. Box 12088,\nStockholm 12.Tel 08-224100. Telex\n10074 ZIS S\nMarknadsföringsenheter\nAlfa-Laval Lantbruk Norden AB.\nBox 2058, Södertälje 2. Tel\n0755-325 30. Tga Alfalaval\nVerksamhet: Mjölkningsmaskiner,\nmjölk-kylare samt\ntransportanläggningar o inredningar för ladugårdar\no svingårdar\n\nServa Järnvaru AB, Stockholm\n(se separat notis)\nProf ila AB. Bällstav 6, Bromma.\nTel 08-98 12 60. Telex 17040\nPROFILA S. Säljer\nverktygsmaskiner\n\nEgendom: Hamra Gård, Tumba.\n\nALFA-LAVAL AB,\nPRESSBOLAGET\n\nPnr 631 01\n\nEskilstuna 1, Fack. Tel\n016-258 00. Tga Alfalaval.\nTelex 40990 ALTUNA S\nVerksamhet: Pressnings-,\ntrycknings- o svetsningsarbeten av alla\nslag i järnplåt, aluminium o\nrostfritt\n\nAntal anställda: 400\nÅrsomsättning: 30 000 000\növering: K-E Kinnemar\nKontorschef: S Kördel\nEtableringsår: 1893.\n\nBIL &amp; BUSS I SUNDSVALL AB\n\nPnr 852 34\n\nSundsvall, Pabriksg 20. Tel\n060-15 73 70\n\nVerksamhet: Bilar, reservdelar,\nbilverkstad\nAntal anställda: 109\nÅrsomsättning: 29452 000\nAktiekapital: 2 600 000\nVerkst dir: Gösta Lindqvist\nEtableringsår: 1947.\n\nKORP &amp; SON, INDUSTRI AB\n\nPnr 450 30\n\nBrastad. Tel 0523-404 05. Bankgiro\n535-2636. Postgiro 567133-4\n\nVerksamhet: Tillverkning av\nav-loppsreningsaggregat, slamsug-ningsaggregat, spol- o\nbevattnings-vagnar, container i olika utförande,\navfallskomprimatorer\nAntal anställda: 45\nÅrsomsättning: 5 000 000\n■Aktiekapital: 100 000\nVerkst dir: Rune Korp\nFabrikör: Helge Korp\nEtableringsår: 1961.\n\nCEN\n\nPostgiro 253450-1. Tga\nGustavsbergs. Telex 64107 GEBERGS S\nVerksamhet: Tillverkar\ncentrifugal-gjutna avloppsrör o\nvattenledningsrör, sandgjutna muffrördelar samt\nstränggjutet kvalitetsgjutgods\nFörsäljningskontor: Stockholm K.\nAB Gustavsbergs Fabriker,\nFle-mingg 62. Tel 08-52 08 60\nVarunamn: Gustavsberg\nAntal anställda: 325\nÅrsomsättning: 40 000 000\nAktiekapital: 500 000\nStyrelse: Samma som Kooperativa\nFörbundet\n\nVerkst dir: Tekn dr Bo Broms\n(Gustavsberg)\n\nPlastchef: Overing Alf Öhman\nEtableringsår: 1946\nIngår i AB Gustavsbergs Fabriker.\nDotterbolag till Kooperativa\nFörbundet.\n\nCENTRO-MASKIN t\nGDTEBORG AB\n\nPnr 400 51\n\nGöteborg 47, Fack. Dagjämningsg\n2. Tel 031-46 00 70. Tga\nCentromaskin. Telex 20977\nVerksamhet: Tillverkar o säljer\nämnes- o kapslipmaskiner samt\nsprickindikeringsutrustning för\nstålindustrin\nAktiekapital: 50 000\nVerkst dir: L Söderström\nEtableringsår. 1953\nFöretaget tillhör Sponsor-gruppen.\n\nCENTROTRADE, AB\n\nPnr 113 28\n\nStockholm, Upplandsg 67. Tel\nOS-SI 16 11, 311634. Bankgiro\n576-45 68. Postgiro 151556-8. Tga\nCentrotrade\n\nVerksamhet Tillverkar\ntryckeriprodukter\n\nVerkst dir: Thure Neuberg\nEtableringsår: 1952.\n\nJACOBY, AB G L\n\nPnr 104 35\n\nStockholm 23, Ynglingag 14. Box\n23014. Tel 08-33 6811\nVerksamhet: Kirurgiska instrument,\nfrökontrollapparater o djurburar\nAktiekapital: 60 000\nVerkst dir: G Jacobsson\nEtableringsår: 1860.\n\nJACO-VERKEN ERIC GRANE\nAB\n\nPnr 550 05\n\nJönköping 5, Vasav 5. Box 5033.\nTel 036-1183 80. Tga Jaco\nVerksamhet: Tillverkar alla slags\npressade artiklar av järn eller\nmetall enligt ritning, stansning,\nbock-ning o kantpressning. Utför gas-,\nel- o punktsvetsning,\nmonteringsarbeten. All slags ytbehandling\nombesörjes\nAktiekapital: 350 000\nVerkst dir: Bernt Wållgren\nEtableringsår: 1947\nOmbildat till aktiebolag 1955.\n\nJAEGER PEPS KONFEKTYR\nAB\n\nPnr 52101\n\nFalköping 1, Storg 31. Box 8. Tel\n0515-108 24, 10318. Bankgiro\n21-3876. Postgiro 37092\nVerksamhet: Tillverkar\nkonfekty-rer\n\nAntal anställda: 50\nÅrsomsättning: 8 000 000\nAktiekapital: 640 000\nVerkst dir: Arne Janson\nEtableringsår: 1934.\n\nSYD\n\nSVESA, AB\n\nPnr 211 20\n\nMalmö, Carlsg 42. Tel 040-391 25.\nBankgiro 870-1815. Postgiro\n245232-4. Tga Svesa. Telex 32734\nVerksamhet: Tillverkar o säljer\nsnickerimaskiner o verktyg\nAntal anställda: 20\nAktiekapital: 180 000\nVerkst dir: Erik Grönvall\nEtableringsår: 1945.\n\nSVETONS MEKANISKA\nVERKSTADS AB\n\nPnr 417 05\n\nGöteborg H, Hildebrandsg 3. Tel\n031-22 80 55. Bankgiro 85-1756.\nPostgiro 242378. Tga Svetonab\nVerksamhet: Svetsning o\nmaskinbearbetning av tyngre konstruktioner\nAntal anställda: 40\nÅrsomsättning: 2 100 000\nAktiekapital: 50 000\nVerkst dir: Sven-Olov Wargklev.\n\nSVETS &amp; GROVPLÄT, AB\n\nPnr 19900\n\nEnköping, O Järnvägsg 1. Tel\n0171-31111. Bankgiro 804-2509.\nPostgiro 385172-2\nVerksamhet: Tillverkar o monterar\nalla slags järnkonstruktioner\nAntal anställda: 12\nÅrsomsättning: 850 000\nAktiekapital: 75 000\nVerkst dir: Uno Westerberg\nEtableringsår 1947.\n\nSVETS &amp; MASKIN.\nMONTERING AB\n\nPnr 175 00\n\nJakobsberg, Nettov 3. Box 67. Tel\n0758-36607, 366 08. Bankgiro\n333-2343. Postgiro 399198-1\nVerksamhet: Tillverkar gräv- o\ntraktorskopor. Utför svetsning\nsamt reparationer av\nentreprenadmaskiner\n\nAntal anställda: 25\nAktiekapital: 100000\nVerkst din Helge Andersson\nEtableringsår: 1947.\n\nHAGA, AB MÖBELFABRIKEN\n\nPnr 33100\n\nVärnamo, Hagag 7. Tel\n0370-10312. Bankgiro 141-9316.\nPost-giro 73549-8\n\nVerksamhet: Utför inredningar i\ni ädelträ för apotek, banker m m\nAntal anstäUda: 17\nÅrsomsättning: 1000 000\nAktiekapital: 119 500\nVerkst dir: Helmer Carlsson\nEtableringsår: 1920.",
    "structured": {
        "1": {
            "company_name": "CASTROL AB",
            "pnr": "103 81",
            "address": "Stockholm 7, Stureplan 2. Box 7020",
            "phone_number": "08-63 18 20",
            "bank_details": {
                "bankgiro": "56-9327",
                "postgiro": "52564"
            },
            "activity": "Castrol smörj- o produktionsmedel",
            "employees": 55,
            "capital": 800000,
            "key_personnel": [
                {
                    "name": "Björn Högberg",
                    "position": "Verkst dir"
                }
            ],
            "establishment_year": 1931
        },
        "2": {
            "company_name": "HÄSTVEDA GJUTERI AB",
            "pnr": "280 23",
            "address": "Hästveda",
            "phone_number": "0451-303 1 7",
            "bank_details": {
                "bankgiro": "282-2077",
                "postgiro": "476 588-9"
            },
            "activity": "Tillverkar beställningsgods",
            "employees": 21,
            "annual_turnover": 1300000,
            "capital": 40000,
            "key_personnel": [
                {
                    "name": "Osten Englund",
                    "position": "Verkst dir"
                }
            ],
            "establishment_year": 1954
        },
        "3": {
            "company_name": "HÄSTü BÅTVARV BRÖDERNA JOHANSSON &amp; CO",
            "pnr": "610 25",
            "address": "Arkösund",
            "phone_number": "0125-200 73, 204 64",
            "bank_details": {
                "bankgiro": "125-4580",
                "postgiro": "144436-3"
            },
            "activity": "Vinterförvaring, reparationer. Tillverkar ARKÖ ORIGINAL-Hydrocoptern",
            "key_personnel": [
                {
                    "name": "Fabr Albin Johansson",
                    "position": "Chefer"
                },
                {
                    "name": "Fabr Börje Johansson",
                    "position": "Chefer"
                },
                {
                    "name": "Fabr Göran Johansson",
                    "position": "Chefer"
                }
            ],
            "establishment_year": 1918
        },
        "4": {
            "company_name": "HÄVEROORTENS LASTBIL-CENTRAL FÖRENING UPA",
            "pnr": "763 01",
            "address": "Hallstavik, Box 37. Uppsalav",
            "phone_number": "0175-203 48, 203 80",
            "bank_details": {
                "bankgiro": "804-8308",
                "postgiro": "14726-4"
            },
            "activity": "Utför transporter. Speditionsverksamhet i samarbete med Godstrafik &amp; Bilspedition",
            "employees": 3,
            "annual_turnover": 9400000,
            "key_personnel": [
                {
                    "name": "Sven Larsson",
                    "position": "Föreståndare o transportchef"
                }
            ],
            "establishment_year": 1943
        },
        "5": {
            "company_name": "SVENSK PLASTIK, AB",
            "pnr": "332 00",
            "address": "Gislaved, Mårtensg 26",
            "phone_number": "0371-103 61",
            "bank_details": {
                "bankgiro": "42-6746",
                "postgiro": "334239"
            },
            "activity": "Kammar, hushålls- o industriartiklar i förekommande plaster",
            "employees": 20,
            "capital": 45000,
            "key_personnel": [
                {
                    "name": "AV Karlsson",
                    "position": "Verkst dir"
                }
            ],
            "establishment_year": 1946
        },
        "6": {
            "company_name": "ALFA-LAVAL AB",
            "pnr": "14700",
            "address": "Ttomba, Fack",
            "phone_number": "0753-31100",
            "activity": "Alfa-Lavalkoncernen tillverkar o säljer mjölkningsmaskiner, mjölkkylare, separatorer o annan utrustning för lantbruket.",
            "employees": 15200,
            "annual_turnover": 1450000000,
            "capital": 213280000,
            "key_personnel": [
                {
                    "name": "Hans Ståhle",
                    "position": "Verkst dir"
                }
            ],
            "establishment_year": 1878
        }
    }
}