{
    "original": "TEDDER INDUSTRI AB\n\nPnr 450 40\n\nKungshamn, Svenneby. Tel\n0523-330 62. Bankgiro 54-4223. Postgiro\n115770. Tga Tedder\nVerksamhet: Tillverkar entrémattor\no arbetstrallar av gummi för\nfastigheter o industrier\nVarunamn: Tedder\nAntal anställda: 10\nÅrsomsättning: 500 000\n\nAktiekapital: 5 000\nStyrelseordf: Fabr Bruno Mattsson\nVerkst dir: Bruno Mattsson\nEtableringsår: 1949\nOmbildat till aktiebolag 1960.\n\nTEDDER-KLÄDER AB\n\nPnr 50108\n\nBorås 1, Box 557. Lidaholmsg 3.\nTel 033-12 76 50. Bankgiro\n839-3290. Postgiro 382532-0\nVerksamhet: Tillverkar o säljer\nfritidskläder för herr o junior\nFörsäljningskontor: Stockholm C,\nSveav 25-27. Tel 08-2102 60\nVarunamn: Tedder\nAntal anställda: 150\nÅrsomsättning: 10 000 000\nAktiekapital: 100 000\nÄgare o chefer: Olof Carlesund,\nCarl-Gustaf Gustafson\nEtableringsår: 1947\nOmbildat till aktiebolag 1950.\n\nTEDDINGTON BELLOWS\n(SVENSKA) AB\n\nPnr 124 21\n\nBandhagen 1, Skebokvarnsv 296.\nBox 59. Tel 08-47 27 35. Bankgiro\n173-8475. Postgiro 674295-1.\nTelex 10358\n\nVerksamhet: Säljer kompensatorer,\nbälgrör o slangar\nAktiekapital: 50000\nVerkst dir: Leif Rundgren\nEtableringsår: 1966.\n\nINTER-MEDIA AB\n\nPnr 10122\n\nStockholm 1, Kungsg 72. Box 198.\nTel 08-24 37 90\nAktiekapital: 1850 000\nVerksamhet: Annonsbyrå\nVerkst dir: Lars-Erik Gullberg.\n\nINTERMELT AB\n\nPnr 103 83\n\nStockholm 7, Stureplan 19. Box\n7119. Tel 08-24 34 65. Bankgiro\n569-3619. Postgiro 557560-0. Tga\nIntermelt. Telex 10028\nVerksamhet: Ingeniörer o agenter\nför järnhantering\nAntal anställda: 12\nAktiekapital: 50 000\nVeikst dir: Sture Arvidsson\nEtableringsår: 1957.\n\nBOG\n\nTga Bodenbolag. Telex 17219\nVerksamhet: Läder o skinn\nGarveri: Alingsås. Tel 0322-111 35\nAntal anställda: 40\nÅrsomsättning: 7 000 000\nAktiekapital: 350 000\nStyrelse: Dir Sven Axel Bodén\n(ordf), fra Ebba Bodén, Axel H\nBodén, Sven Fredholm\nVerkst dir: Axel H Bodén\nEtableringsår: 1862\nOmbildat till aktiebolag 1921.\n\nBODENIUS\nPLASTKONFEKTION, AB\n\nPnr 41141\n\nGöteborg, S Kustbaneg 21. Tel\n031-1979 87. Postgiro 420247-9\nVerksamhet: Sömnad av artiklar i\nplastfolie, nylon o vävplast\nAntal anställda: 12\nAktiekapital: 15 000\nVerkst dir: Ernst Bodenius\nFörsäljn-chef: Margret Bodenius\nEtableringsår: 1949.\n\nTHYSELLS INDUSTRI AB\n\nPnr 230 23\n\nAnderslöv. Tel 0410-205 50\nVeiksamhet: Tillverkar rullformade\nprofiler av varm- o kallvalsat\nbandstål, galvaniserat o brännlackerat\nBandskärning\nAntal anställda: 30\nAktiekapital: 300000\nVerkst dir: Börje Thysell\nEtableringsån 1954.\n\nSVENSKA RADIO AB, SRA\n\nPnr 102 20\n\nStockholm 12, Fack. Alströmerg 14.\nTel 08-22 31 40. Bankgiro 729-9407,\n168-1170. Postgiro 2838-1. Tga\n\nSvenskradio. Telex 10094 SRA S\nVerksamhet: Tillverkar o säljer\nkommunikationsradio o radiolänkar.\nInstallation o underhåll av\ntele-materiel\n\nAntal anställda: 1 800\nAktiekapital: 15 780 000\nVerkst din Ivar Ahlgren\nEtableringsår: 1919.\n\nSVENSKA RAKBLADS.\nFABRIKEN AB\n\nPnr 460 50\n\nGrästorp, Gästgivareg. Box 68.\nTel 0514-100 22, 10141. Postgiro\n77430-7. Tga Svenskablad\nVerksamhet: Tillverkar rakblad o\nmaskiner för rakbladstillverkning\nAntal anställda: 20\nÅrsomsättning: 1000000\nAktiekapital: 50 000\nVerkst dir: T Thunberg\nEtableringsår: 1917\nOmbildat till aktiebolag 1941.\n\nSVENSKA RATIONALI.\nSERINGSBYRÄN AB\n\nPnr 413 26\n\nGöteborg SV, Dr Forselius g 52.\nTel 031-1613 00. Bankgiro 36-2187.\nPostgiro 243545\n\nVerksamhet: Konsulterande\ningenjörsbyrå\n\nAntal anställda: 10\nAktiekapital: 5 000\nVerkst din Carl Warfving\nEtableringsår: 1948\nOmbildat till aktiebolag 1960.\n\nSVENSKA RAWLPLUG CO AB\n\nEtt Burmah-företag\n\nPnr 104 62\n\nStockholm 17, Box 17005.\nRosen-lundsg 9. Tel 08-69 03 65.\nBankgiro 446-6421. Postgiro 456515-6.\nTga Rawlplug. Telex 17979\n\n\n\nVerksamhet: Handels-, imports o\nagenturrörelse, företrädesvis med\nmateriel för byggnadsbranschen\nsamt annan förenlig verksamhet\nFilialer:413 20 Göteborg, Lövskogsg\n3. Tel 031-20 83 39, 20 83 69\n21215 Malmö, Nobelv 147. Tel\n040-9303 87, 93 1387\n852 30 Sundsvall, Storg 45. Tel\n060-11 98 18\n\nVarunamn: Kango, Rawlplug,\nVib-roto, Wolf\n\nÅrsomsättning: 6 000 000\nAktiekapital: 25 000\nVerkst dir: Töre Westerlund\nEtableringsår: 1951.\n\nNORDICO\n\nBYGGE-KEMIKALIER, AB\n\nPnr 200 31\n\nMalmö 15, Fack. Botildenborgsv.\nTel 040-21 57 30. Bankgiro\n265-6908. Postgiro 634066-5. Tga\nTwe-deoil\n\nVerksamhet: Tillverkar o säljer\nträimpregneringsmedel, målarfärger,\ndisk- o desinfektionsmedel,\nsmörjmedel samt formolja\nÅrsomsättning: 100 000\nAktiekapital: 5 000\nVerkst dir: Gösta Twede\nEtableringsår: 1963.\n\nAFOSS VERKSTADS AB\n\nPnr 595 00\n\nMjölby, Kyrkog 27. Tel 0142-13175.\nPostgiro 411823. Tga Afoss\nVerksamhet: Kedjehjul-kugghjul o\ngolvslipmaskiner, säljer kedjor,\nutför mekaniska legoarbeten\nVarunamn: APOSS\nAktiekapital: 25 000\nVerkst dir: Gust Stenberg (kontor\nRådhusg 7, 852 31 Sundsvall. Tel\n060-15 9 0 34)\n\nPlatschef: Ing Hans Bäckström\nEtableringsår: 1957.\n\nBERGS SÄNGKLÄDER AB\n\nPnr 340 14\n\nLagan. Tel 0372-303 70. Bankgiro\n147-2489. Postgiro 374461-2. Tga\nPolydun. Telex 4698 BERGS S\nVerksamhet: Tillverkar täcken,\nkuddar o sovsäckar\nVarunamn: Bergs, Polydun\nAntal anställda: 65\nÅrsomsättning: 12 000 000\nAktiekapital: 700 000\nVerkst dir: Thure Berg\nEtableringsår: 1951.\n\nBERGS TINGSLAGS\nELEKTRISKA AB\n\nPnr 84031\n\nÅsarna, Box 11. Tel 0687-300 02.\nBankgiro 78-1217. Postgiro 73125\nVerksamhet: Eldistribution inom\nBergs, Åsarne, Klövsjö,\nVemdalens o Rätans socknar i Jämtlands\nlän samt Haverö socken i\nVästernorrlands län\nAntal anställda: 35\nÅrsomsättning: 2 300 000\nAktiekapital: 675 500\nVerkst dir: sten B Olsson\nEtableringsår: 1914.\n\nT EGES AGENTURER, AB\n\nPnr 700 03\n\nÖrebro 3, Sankt Birgittag 17 A.\nBox 3074. Tel 019-18 5070.\nBankgiro 817-3932. Postgiro 513447-3.\nTga Tegesagent\n\nVerksamhet: Skinn-, sko- o\nväsk-material. Plastfolier\nAntal anställda: 5\nÅrsomsättning: 2 500 000\nAktiekapital: 10 000\nVerkst dir: Per-Göran Andersson\nEtableringsår: 1959.\n\nSBR\n\n5639. Postgiro 670807-7. Tga\nEss-beemteknik\n\nVerksamhet: Projekterar o\ntillverkar sandblästringsmaskiner av\nalla slag. Konstruktions byrå för\nmaskin- o stålkonstruktioner\nAntal anställda: 7\nAktiekapital: 30000\nEtableringsår: 1965.\n\nSBR:s HONUNGSFUR.\nMEDLING AB\n\nPnr 590 20\n\nMantorp, Fallv 9. Box 91. Tel\n0142-20930. Postgiro 475185\nVerksamhet: Förmedling av honung\nfrån medlemmar av SBR till\nåterförsäljare\n\nVerkst dir: Bertil Kristensson\nEtableringsår: 1964.",
    "structured": {
        "1": {
            "company_name": "TEDDER INDUSTRI AB",
            "pnr": "450 40",
            "address": "Kungshamn, Svenneby",
            "phone_number": "0523-330 62",
            "bank_details": {
                "bankgiro": "54-4223",
                "postgiro": "115770"
            },
            "activity": "Tillverkar entrémattor o arbetstrallar av gummi för fastigheter o industrier",
            "employees": 10,
            "annual_turnover": 500000,
            "capital": 5000,
            "key_personnel": [
                {
                    "name": "Fabr Bruno Mattsson",
                    "position": "Styrelseordf"
                },
                {
                    "name": "Bruno Mattsson",
                    "position": "Verkst dir"
                }
            ],
            "establishment_year": 1949
        },
        "2": {
            "company_name": "TEDDER-KLÄDER AB",
            "pnr": "50108",
            "address": "Borås 1, Box 557, Lidaholmsg 3",
            "phone_number": "033-12 76 50",
            "bank_details": {
                "bankgiro": "839-3290",
                "postgiro": "382532-0"
            },
            "activity": "Tillverkar o säljer fritidskläder för herr o junior",
            "employees": 150,
            "annual_turnover": 10000000,
            "capital": 100000,
            "key_personnel": [
                {
                    "name": "Olof Carlesund",
                    "position": "Ägare"
                },
                {
                    "name": "Carl-Gustaf Gustafson",
                    "position": "Ägare"
                }
            ],
            "establishment_year": 1947
        },
        "3": {
            "company_name": "TEDDINGTON BELLOWS (SVENSKA) AB",
            "pnr": "124 21",
            "address": "Bandhagen 1, Skebokvarnsv 296, Box 59",
            "phone_number": "08-47 27 35",
            "bank_details": {
                "bankgiro": "173-8475",
                "postgiro": "674295-1"
            },
            "activity": "Säljer kompensatorer, bälgrör o slangar",
            "capital": 50000,
            "key_personnel": [
                {
                    "name": "Leif Rundgren",
                    "position": "Verkst dir"
                }
            ],
            "establishment_year": 1966
        },
        "4": {
            "company_name": "INTER-MEDIA AB",
            "pnr": "10122",
            "address": "Stockholm 1, Kungsg 72, Box 198",
            "phone_number": "08-24 37 90",
            "activity": "Annonsbyrå",
            "capital": 1850000,
            "key_personnel": [
                {
                    "name": "Lars-Erik Gullberg",
                    "position": "Verkst dir"
                }
            ]
        },
        "5": {
            "company_name": "INTERMELT AB",
            "pnr": "103 83",
            "address": "Stockholm 7, Stureplan 19, Box 7119",
            "phone_number": "08-24 34 65",
            "bank_details": {
                "bankgiro": "569-3619",
                "postgiro": "557560-0"
            },
            "activity": "Ingeniörer o agenter för järnhantering",
            "employees": 12,
            "capital": 50000,
            "key_personnel": [
                {
                    "name": "Sture Arvidsson",
                    "position": "Veikst dir"
                }
            ],
            "establishment_year": 1957
        },
        "6": {
            "company_name": "BOG",
            "activity": "Läder o skinn Garveri",
            "address": "Alingsås",
            "phone_number": "0322-111 35",
            "employees": 40,
            "annual_turnover": 7000000,
            "capital": 350000,
            "key_personnel": [
                {
                    "name": "Sven Axel Bodén",
                    "position": "Styrelse: Dir"
                },
                {
                    "name": "Ebba Bodén",
                    "position": "Styrelse: fra"
                },
                {
                    "name": "Axel H Bodén",
                    "position": "Styrelse"
                },
                {
                    "name": "Sven Fredholm",
                    "position": "Styrelse"
                },
                {
                    "name": "Axel H Bodén",
                    "position": "Verkst dir"
                }
            ],
            "establishment_year": 1862
        },
        "7": {
            "company_name": "BODENIUS PLASTKONFEKTION, AB",
            "pnr": "41141",
            "address": "Göteborg, S Kustbaneg 21",
            "phone_number": "031-1979 87",
            "postgiro": "420247-9",
            "activity": "Sömnad av artiklar i plastfolie, nylon o vävplast",
            "employees": 12,
            "capital": 15000,
            "key_personnel": [
                {
                    "name": "Ernst Bodenius",
                    "position": "Verkst dir"
                },
                {
                    "name": "Margret Bodenius",
                    "position": "För. chef"
                }
            ],
            "establishment_year": 1949
        },
        "8": {
            "company_name": "THYSELLS INDUSTRI AB",
            "pnr": "230 23",
            "address": "Anderslöv",
            "phone_number": "0410-205 50",
            "activity": "Tillverkar rullformade profiler av varm- o kallvalsat bandstål, galvaniserat o brännlackerat",
            "employees": 30,
            "capital": 300000,
            "key_personnel": [
                {
                    "name": "Börje Thysell",
                    "position": "Verkst dir"
                }
            ],
            "establishment_year": 1954
        },
        "9": {
            "company_name": "SVENSKA RADIO AB, SRA",
            "pnr": "102 20",
            "address": "Stockholm 12, Fack. Alströmerg 14",
            "phone_number": "08-22 31 40",
            "bank_details": {
                "bankgiro": "729-9407, 168-1170",
                "postgiro": "2838-1"
            },
            "activity": "Tillverkar o säljer kommunikationsradio o radiolänkar. Installation o underhåll av tele-materiel",
            "employees": 1800,
            "capital": 15780000,
            "key_personnel": [
                {
                    "name": "Ivar Ahlgren",
                    "position": "Verkst din"
                }
            ],
            "establishment_year": 1919
        },
        "10": {
            "company_name": "SVENSKA RAKBLADS. FABRIKEN AB",
            "pnr": "460 50",
            "address": "Grästorp, Gästgivareg. Box 68",
            "phone_number": "0514-100 22",
            "postgiro": "77430-7",
            "activity": "Tillverkar rakblad o maskiner för rakbladstillve",
            "employees": 20,
            "annual_turnover": 1000000,
            "capital": 50000,
            "key_personnel": [
                {
                    "name": "T Thunberg",
                    "position": "Verkst dir"
                }
            ],
            "establishment_year": 1917
        },
        "11": {
            "company_name": "SVENSKA RATIONALISERINGSBYRÄN AB",
            "pnr": "413 26",
            "address": "Göteborg SV, Dr Forselius g 52",
            "phone_number": "031-1613 00",
            "bankgiro": "36-2187",
            "postgiro": "243545",
            "activity": "Konsulterande ingenjörsbyrå",
            "employees": 10,
            "capital": 5000,
            "key_personnel": [
                {
                    "name": "Carl Warfving",
                    "position": "Verkst din"
                }
            ],
            "establishment_year": 1948
        },
        "12": {
            "company_name": "SVENSKA RAWLPLUG CO AB",
            "pnr": "104 62",
            "address": "Stockholm 17, Box 17005, Rosen-lundsg 9",
            "phone_number": "08-69 03 65",
            "bank_details": {
                "bankgiro": "446-6421",
                "postgiro": "456515-6"
            },
            "activity": "Handels-, imports o agenturrörelse, företrädesvis med materiel för byggnadsbranschen samt annan förenlig verksamhet",
            "branches": [
                {
                    "address": "413 20 Göteborg, Lövskogsg 3",
                    "phone_number": "031-20 83 39, 20 83 69"
                },
                {
                    "address": "21215 Malmö, Nobelv 147",
                    "phone_number": "040-9303 87, 93 1387"
                },
                {
                    "address": "852 30 Sundsvall, Storg 45",
                    "phone_number": "060-11 98 18"
                }
            ],
            "brands": [
                "Kango",
                "Rawlplug",
                "Vib-roto",
                "Wolf"
            ],
            "annual_turnover": 6000000,
            "capital": 25000,
            "key_personnel": [
                {
                    "name": "Töre Westerlund",
                    "position": "Verkst dir"
                }
            ],
            "establishment_year": 1951
        },
        "13": {
            "company_name": "NORDICO BYGGE-KEMIKALIER, AB",
            "pnr": "200 31",
            "address": "Malmö 15, Fack. Botildenborgsv",
            "phone_number": "040-21 57 30",
            "bankgiro": "265-6908",
            "postgiro": "634066-5",
            "activity": "Tillverkar o säljer träimpregneringsmedel, målarfärger, disk- o desinfektionsmedel, smörjmedel samt formolja",
            "capital": 5000,
            "key_personnel": [
                {
                    "name": "Gösta Twede",
                    "position": "Verkst dir"
                }
            ],
            "establishment_year": 1963
        },
        "14": {
            "company_name": "AFOSS VERKSTADS AB",
            "pnr": "595 00",
            "address": "Mjölby, Kyrkog 27",
            "phone_number": "0142-13175",
            "postgiro": "411823",
            "activity": "Kedjehjul-kugghjul o golvslipmaskiner, säljer kedjor, utför mekaniska legoarbeten",
            "brands": [
                "APOSS"
            ],
            "capital": 25000,
            "key_personnel": [
                {
                    "name": "Gust Stenberg",
                    "position": "Verkst dir",
                    "branch_address": "Rådhusg 7, 852 31 Sundsvall",
                    "phone_number": "060-15 9 0 34"
                },
                {
                    "name": "Ing Hans Bäckström",
                    "position": "Platschef"
                }
            ],
            "establishment_year": 1957
        },
        "15": {
            "company_name": "BERGS SÄNGKLÄDER AB",
            "pnr": "340 14",
            "address": "Lagan",
            "phone_number": "0372-303 70",
            "bankgiro": "147-2489",
            "postgiro": "374461-2",
            "activity": "Tillverkar täcken, kuddar o sovsäckar",
            "brands": [
                "Bergs",
                "Polydun"
            ],
            "employees": 65,
            "annual_turnover": 12000000,
            "capital": 700000,
            "key_personnel": [
                {
                    "name": "Thure Berg",
                    "position": "Verkst dir"
                }
            ],
            "establishment_year": 1951
        },
        "16": {
            "company_name": "BERGS TINGSLAGS ELEKTRISKA AB",
            "pnr": "84031",
            "address": "Åsarna, Box 11",
            "phone_number": "0687-300 02",
            "bankgiro": "78-1217",
            "postgiro": "73125",
            "activity": "Eldistribution inom Bergs, Åsarne, Klövsjö, Vemdalens o Rätans socknar i Jämtlands län samt Haverö socken i Västernorrlands län",
            "employees": 35,
            "annual_turnover": 2300000,
            "capital": 675500,
            "key_personnel": [
                {
                    "name": "Sten B Olsson",
                    "position": "Verkst dir"
                }
            ],
            "establishment_year": 1914
        },
        "17": {
            "company_name": "TEGES AGENTURER, AB",
            "pnr": "700 03",
            "address": "Örebro 3, Sankt Birgittag 17 A, Box 3074",
            "phone_number": "019-18 5070",
            "bankgiro": "817-3932",
            "postgiro": "513447-3",
            "activity": "Skinn-, sko- o väsk-material. Plastfolier",
            "employees": 5,
            "annual_turnover": 2500000,
            "capital": 10000,
            "key_personnel": [
                {
                    "name": "Per-Göran Andersson",
                    "position": "Verkst dir"
                }
            ],
            "establishment_year": 1959
        },
        "18": {
            "company_name": "SBR",
            "pnr": "5639",
            "activity": "Projekterar o tillverkar sandblästringsmaskiner av alla slag. Konstruktions byrå för maskin- o stålkonstruktioner",
            "employees": 7,
            "capital": 30000,
            "establishment_year": 1965
        },
        "19": {
            "company_name": "SBR:s HONUNGSFÖRMEDLING AB",
            "pnr": "590 20",
            "address": "Mantorp, Fallv 9, Box 91",
            "phone_number": "0142-20930",
            "postgiro": "475185",
            "activity": "Förmedling av honung från medlemmar av SBR till återförsäljare",
            "key_personnel": [
                {
                    "name": "Bertil Kristensson",
                    "position": "Verkst dir"
                }
            ],
            "establishment_year": 1964
        }
    }
}