{
    "original": "A-BYRÄN I DREBRO AB\n\nPnr 701 32\n\nÖrebro 1, Box 960. Västra g 2. Tel\n12 47 40. Bankgiro 482-9057.\nPostgiro 379555-6. Tga Adservice\nVerksamhet: Konsulterande\nannonsbyrå, reklamateljé, AV- o\nfilmsektion. Utför\nmarknadsundersökningar\n\nAntal anställda: 22\nÅrsomsättning: 2100 000\nAktiekapital: 100 000\nVerkst dir: Tom Hultkrantz\nV verkst dir: Sven Söderqvist\nEtableringsår: 1955.\n\nKÄL\n\nVerksamhet: Tillverkar kyl- o\nfrysenheter samt högvakuumpumpar\nAntal anställda: 35\nÅrsomsättning: 3 500 000\nAktiekapital: 50 000\nVerkst dir: Ing Sture Tyllström\nEtableringsår: 1943.\n\nKYMMER AB, INGENJÖRS.\nFIRMAN J\n\nPnr 73100\n\nKöping, Ringv 55. Tel 0221-124 04.\nBankgiro 606-7540. Postgiro\n90404-5\n\nVerksamhet: El-konsult. Delvis\nel affärer\n\nAktiekapital: 5 000\nVerkst dir: Johan Kymmer\nEtableringsår: 1958.\n\nKHYSING &amp; KLEVFORS,\nRORLEDNINGSAKTIEBOLAGET\n\nPnr 774 01\n\nAvesta 1, Box 31. Prästg 40. Tel\n0226-504 49, 505 49. Bankgiro\n794-0307. Postgiro 131139-8\nVerksamhet: Utför värme-,\nsani-tets- o ventilationsentreprenader,\nindustrimontage, oljeservice samt\nreparationsarbeten\nAntal anställda: 32\nÅrsomsättning: 3 000000\nAktiekapital: 20 000\nVerkst din Ing Helmer Khysing\nEtableringsår: 1943.\n\nKABE-MATTAN\nFÖRSÄLJNINGS AB\n\nPnr 114 44\n\nStockholm, Jungfrug 33. Tel\n08-63 54 30. Bankgiro 40 2-6258.\nPostgiro 409500-6. Tga Kabemat\nVeiksamhet: Skrapgaller o\nentrémattor\n\nÅrsomsättning: 2 200 000\nAktiekapital: 300 000\nVerkst dir: Bo Zetterqvist\nEtableringsår: 1950.\n\nLINDBOM AB, J E\n\nPnr 453 00 .\n\nLysekil, N Hamnen. Tel\n0523-118 10. Bankgiro 42-8857.\nPostgiro 72213. Tga Lindbom\nVerksamhet: Försäljning av\nskeppsutrustningar o fiskredskap\nAntal anställda: 11\nAktiekapital: 5 000\nVerkst dir: Bengt Olof Lindbom\nEtableringsår: 1880.\n\nNYKVARNS SKYLT AB\n\nPnr 151 34\n\nSödertälje, Dalg 11. Tel\n0755-60150. Bankgiro 23-2339. Postgiro\n334417\n\nVerksamhet: Ljusreklam, plast\ngraverade o lättmetall\nAntal anställda: 20\nAktiekapital: 30000\nVerkst dir: Bo Waldekrantz\nEtableringsår: 1956.\n\nGÄVLE VERKEN AB\n\nPnr 801 03\n\nGävle 1, Box 217. Tel 026-1150 50.\nBankgiro 783-7131. Postgiro\n9962-2. Tga Gavleverken.\nTelex 81159\n\nVerksamhet: Tillverkar o säljer\nPlagan o Provan byggnadsplåt o\nbyggnadsdetaljer\nVarunamn: Plagan, Provan\nAntal anstäUda: 80\nÅrsomsättning: 28 000 000\nÅrsomsättning: 32 500 000\nAktiekapital: 270 000\nStyrelse: Adv Gustaf Adolf Rising\n(ordf), dir Jan Berglund,dir Gunnar\nEhrlemark, dir Birger Hagström,\nfabr Arne Sjöström\nVerkst dir: Birger Hagström\nEtableringsår: 1847\nNuvarande aktiebolag ombildat\n1953.\n\nGDG BILTRAFIK AB\n\nPnr 442 00\n\nKungälv. Thorilds Gränd 1. Box 34.\nTel 0303-140 90. Bankgiro\n344-4650. Postgiro 48250-5\nVerksamhet: Omnibus- o\nlastbilstrafik, kiosk- o motellrörelse samt\nbilservicerörelse med\ndrivmedels-o gummiringsförsäljning jämte\ngummiverkstäder\nAntal anstäUda: 1500\nÅrsomsättning: 145 000 000\nAktiekapital: 10 000 000\nVerkst dir: Lennart Sandberg\nEtableringsår: 1933.\n\nFOR\n\nAktiekapital: 5 000\nVerkst dir: Lorentz Österlund\nEtableringsår: 1961.\n\nAGRIA UNIVERSAL\nTRAKTORER AB\n\nPnr 19121\n\nSollentuna 1, Box 15.\nKastellgården. Tel 08-96 03 55. Tga\nAgriatrak-tor. Telex 17296 AGRIA S\nVerksamhet: Säljer\n’allround’-maskiner för trädgård, park- o\ngrönområden\nVarunamn: Agria\nAktiekapital: 250 000\nVerkst din Ch Mohrenweizer\nEtableringsår: 1958.\n\nINTERFUTURA AB\n\nPnr 434 00\n\nKungsbacka, Kaprifolv 122. Tel\n0300-138 60. Bankgiro 89-6090.\nPostgiro 683050\n\nVerksamhet: Agenturfirma.\nInternationella kontakter\nAktiekapital: 5 000\nVerkst dir: G Hanssen\nEtableringsår. 1965.\n\nSANDBLOM NEW HAMMER AB\n\nPnr 417 22\n\nGöteborg, Salter ig 20. Tel\n031-5376 43, 53 76 69. Bankgiro\n51-3196. Postgiro 46711. Tga\nSand-bloma\n\nVerksamhet: Tillverkar\nrosthack-ningsmaskiner för el o tryckluft\nVarunamn: Fabi tubrensare,\nSandblom New Hammer\nAktiekapital: 20 000\nÄgare o chefer: Fru Ella Zelander,\nfru A M WUche\nEtableringsår: 1927.\n\nSANDBLOM &amp; STOHNE AB,\nINGENIÖRSFIRMAN\n\nPnr 104 25\n\nStockholm 30, Lindhagensg 122.\nBox 30052. Tel 08-541160.\nBankgiro 733-8213. Postgiro 3268-0.\nTga Elstohne. Telex 1118\nVeiksamhet: Representant för tyska,\nengelska, amerikanska o franska\nfabriker. Säljer elektr\nspecialmotorer, reglerbara transformatorer,\nomformare, mek transmissioner\nsåsom kuggväxelmotorer,\nsnäckväxlar, kopplingar, variatorer mm,\n\nstartapparater av alla slag samt\nautomatikutrustningar,\nkomponenter för kylanläggningar samt\nfläktar\n\nFilialer: Göteborg S, Almedalsv 1.\nTel 031-40 04 65\nJönköping, O Storg 82. Tel\n036-1187 95\n\nMalmö, Nya Agnesfridsv 187. Tel\n040-94 22 00\n\nSundsvall, Packhusg 4. Tel\n060-123120\n\nAntal anstäUda: 112\nÅrsomsättning: 40 000 000\nAktiekapital: 2 000 000\nStyrelse: Adv Kjell Sjö stedt (ordf),\ndir O Bertil Stohne, dir Arvid\nNil-sén, dlr Börje Hedenblad, ing\nHarald Käck, ing Bengt Olsson,\ning Sven Radier\nVeikst dlr: O Bertil Stohne\nV verkst dir: Börje Hedenblad\nEtableringsår: 1926\nOmbildat till aktiebolag 1941\nDotterbolag: AB Stohne-Verken,\nStockholm.\n\nSANDBYMASKINER, AB\n\nPnr 240 17\n\nSödra Sandby. Tel 046-510 01,\n51319. Bankgiro 869-3301.\nPostgiro 36614-6. Tga Sandbymaskiner,\nLund\n\nVerksamhet: Tillverkar\nasfaltblan-dare, betongblandare för\nbyggnads-o cementvaruindustrin, blandare\nför laboratorieändamål o kemiska\nindustrin, torktrummor för torkning\nav grus- o stenmaterial samt\ntransportskruvar för cement, filler,\nkalk mm\n\nVarunamn: Sandby\nAntal anstäUda: 30\nÅrsomsättning: 2 5 00 000\nAktiekapital: 100000\nVeikst dir: Disp Gunnar Wahlbeck\nEtableringsår: 1886\nNuvarande namn o bolag 1946.\n\nSANDBÄCKS GRUS AB\n\nPnr 113 22\n\nStockholm, Odeng 87. Tel\n08-34 37 52, 34 37 53. Postgiro\n289889-8\n\nVeiksamhet: Grus- o\nkroppsprodukter, byggnadssten o fabriksbetong\nAntal anställda: 50\nÅrsomsättning 5 000 000\nAktiekapital: 452 000\nVeikst dir: Ing Per Wretlind\nEtableringsår 1945.\n\nTYPOCHROMA, AB\n\nPnr 116 33\n\nStockholm SO, Bondeg 16-20. Tel\n08-40 30 88, 43 36 82. Bankgiro\n47-6480. Postgiro 1398. Tga\nTypo-chroma\n\nVeiksamhet: Tillverkar\nboktrycks-o offsetfärger\n\nAntal anställda: 20\nÅrsomsättning: 1 800 000\nAktiekapital: 133 400\nVerkst dir: Eli Hanner\nEtableringsår: 1896.",
    "structured": {
        "1": {
            "company_name": "A-BYRÄN I DREBRO AB",
            "pnr": "701 32",
            "address": "Örebro 1, Box 960. Västra g 2",
            "phone_number": "12 47 40",
            "bank_details": {
                "bankgiro": "482-9057",
                "postgiro": "379555-6"
            },
            "activity": "Konsulterande annonsbyrå, reklamateljé, AV- o filmsektion. Utför marknadsundersökningar",
            "employees": 22,
            "annual_turnover": 2100000,
            "capital": 100000,
            "key_personnel": [
                {
                    "name": "Tom Hultkrantz",
                    "position": "Verkst dir"
                },
                {
                    "name": "Sven Söderqvist",
                    "position": "V verkst dir"
                }
            ],
            "establishment_year": 1955
        },
        "2": {
            "company_name": "KÄL",
            "activity": "Tillverkar kyl- o frysenheter samt högvakuumpumpar",
            "employees": 35,
            "annual_turnover": 3500000,
            "capital": 50000,
            "key_personnel": [
                {
                    "name": "Ing Sture Tyllström",
                    "position": "Verkst dir"
                }
            ],
            "establishment_year": 1943
        },
        "3": {
            "company_name": "KYMMER AB, INGENJÖRS. FIRMAN J",
            "pnr": "73100",
            "address": "Köping, Ringv 55",
            "phone_number": "0221-124 04",
            "bank_details": {
                "bankgiro": "606-7540",
                "postgiro": "90404-5"
            },
            "activity": "El-konsult. Delvis el affärer",
            "capital": 5000,
            "key_personnel": [
                {
                    "name": "Johan Kymmer",
                    "position": "Verkst dir"
                }
            ],
            "establishment_year": 1958
        },
        "4": {
            "company_name": "KHYSING & KLEVFORS, RORLEDNINGSAKTIEBOLAGET",
            "pnr": "774 01",
            "address": "Avesta 1, Box 31. Prästg 40",
            "phone_number": "0226-504 49, 505 49",
            "bank_details": {
                "bankgiro": "794-0307",
                "postgiro": "131139-8"
            },
            "activity": "Utför värme-, sani-tets- o ventilationsentreprenader, industrimontage, oljeservice samt reparationsarbeten",
            "employees": 32,
            "annual_turnover": 3000000,
            "capital": 20000,
            "key_personnel": [
                {
                    "name": "Ing Helmer Khysing",
                    "position": "Verkst din"
                }
            ],
            "establishment_year": 1943
        },
        "5": {
            "company_name": "KABE-MATTAN FÖRSÄLJNINGS AB",
            "pnr": "114 44",
            "address": "Stockholm, Jungfrug 33",
            "phone_number": "08-63 54 30",
            "bank_details": {
                "bankgiro": "40 2-6258",
                "postgiro": "409500-6"
            },
            "activity": "Skrapgaller o entrémattor",
            "annual_turnover": 2200000,
            "capital": 300000,
            "key_personnel": [
                {
                    "name": "Bo Zetterqvist",
                    "position": "Verkst dir"
                }
            ],
            "establishment_year": 1950
        },
        "6": {
            "company_name": "LINDBOM AB, J E",
            "pnr": "453 00",
            "address": "Lysekil, N Hamnen",
            "phone_number": "0523-118 10",
            "bank_details": {
                "bankgiro": "42-8857",
                "postgiro": "72213"
            },
            "activity": "Försäljning av skeppsutrustningar o fiskredskap",
            "employees": 11,
            "capital": 5000,
            "key_personnel": [
                {
                    "name": "Bengt Olof Lindbom",
                    "position": "Verkst dir"
                }
            ],
            "establishment_year": 1880
        },
        "7": {
            "company_name": "NYKVARNS SKYLT AB",
            "pnr": "151 34",
            "address": "Södertälje, Dalg 11",
            "phone_number": "0755-60150",
            "bank_details": {
                "bankgiro": "23-2339",
                "postgiro": "334417"
            },
            "activity": "Ljusreklam, plast graverade o lättmetall",
            "employees": 20,
            "capital": 30000,
            "key_personnel": [
                {
                    "name": "Bo Waldekrantz",
                    "position": "Verkst dir"
                }
            ],
            "establishment_year": 1956
        },
        "8": {
            "company_name": "GÄVLE VERKEN AB",
            "pnr": "801 03",
            "address": "Gävle 1, Box 217",
            "phone_number": "026-1150 50",
            "bank_details": {
                "bankgiro": "783-7131",
                "postgiro": "9962-2"
            },
            "activity": "Tillverkar o säljer Plagan o Provan byggnadsplåt o byggnadsdetaljer",
            "varunamn": "Plagan, Provan",
            "employees": 80,
            "annual_turnover": 28500000,
            "capital": 270000,
            "key_personnel": [
                {
                    "name": "Birger Hagström",
                    "position": "Verkst dir"
                }
            ],
            "establishment_year": 1847
        },
        "9": {
            "company_name": "GDG BILTRAFIK AB",
            "pnr": "442 00",
            "address": "Kungälv, Thorilds Gränd 1. Box 34",
            "phone_number": "0303-140 90",
            "bank_details": {
                "bankgiro": "344-4650",
                "postgiro": "48250-5"
            },
            "activity": "Omnibus- o lastbilstrafik, kiosk- o motellrörelse samt bilservicerörelse med drivmedels-o gummiringsförsäljning jämte gummiverkstäder",
            "employees": 1500,
            "annual_turnover": 145000000,
            "capital": 10000000,
            "key_personnel": [
                {
                    "name": "Lennart Sandberg",
                    "position": "Verkst dir"
                }
            ],
            "establishment_year": 1933
        },
        "10": {
            "company_name": "FOR",
            "capital": 5000,
            "key_personnel": [
                {
                    "name": "Lorentz Österlund",
                    "position": "Verkst dir"
                }
            ],
            "establishment_year": 1961
        },
        "11": {
            "company_name": "AGRIA UNIVERSAL TRAKTORER AB",
            "pnr": "19121",
            "address": "Sollentuna 1, Box 15. Kastellgården",
            "phone_number": "08-96 03 55",
            "activity": "Säljer 'allround'-maskiner för trädgård, park- o grönområden",
            "varunamn": "Agria",
            "capital": 250000,
            "key_personnel": [
                {
                    "name": "Ch Mohrenweizer",
                    "position": "Verkst din"
                }
            ],
            "establishment_year": 1958
        },
        "12": {
            "company_name": "INTERFUTURA AB",
            "pnr": "434 00",
            "address": "Kungsbacka, Kaprifolv 122",
            "phone_number": "0300-138 60",
            "bank_details": {
                "bankgiro": "89-6090",
                "postgiro": "683050"
            },
            "activity": "Agenturfirma. Internationella kontakter",
            "capital": 5000,
            "key_personnel": [
                {
                    "name": "G Hanssen",
                    "position": "Verkst dir"
                }
            ],
            "establishment_year": 1965
        },
        "13": {
            "company_name": "SANDBLOM NEW HAMMER AB",
            "pnr": "417 22",
            "address": "Göteborg, Salter ig 20",
            "phone_number": "031-5376 43, 53 76 69",
            "bank_details": {
                "bankgiro": "51-3196",
                "postgiro": "46711"
            },
            "activity": "Tillverkar rosthack-ningsmaskiner för el o tryckluft",
            "varunamn": "Fabi tubrensare, Sandblom New Hammer",
            "capital": 20000,
            "key_personnel": [
                {
                    "name": "Fru Ella Zelander",
                    "position": "Ägare o chef"
                },
                {
                    "name": "fru A M WUche",
                    "position": "Ägare o chef"
                }
            ],
            "establishment_year": 1927
        },
        "14": {
            "company_name": "SANDBLOM & STOHNE AB, INGENIÖRSFIRMAN",
            "pnr": "104 25",
            "address": "Stockholm 30, Lindhagensg 122. Box 30052",
            "phone_number": "08-541160",
            "bank_details": {
                "bankgiro": "733-8213",
                "postgiro": "3268-0"
            },
            "activity": "Representant för tyska, engelska, amerikanska o franska fabriker. Säljer elektr specialmotorer, reglerbara transformatorer, omformare, mek transmissioner såsom kuggväxelmotorer, snäckväxlar, kopplingar, variatorer mm, startapparater av alla slag samt automatikutrustningar, komponenter för kylanläggningar samt fläktar",
            "employees": 112,
            "annual_turnover": 40000000,
            "capital": 2000000,
            "key_personnel": [
                {
                    "name": "O Bertil Stohne",
                    "position": "Veikst dlr"
                },
                {
                    "name": "Börje Hedenblad",
                    "position": "V verkst dir"
                }
            ],
            "establishment_year": 1926
        },
        "15": {
            "company_name": "SANDBYMASKINER, AB",
            "pnr": "240 17",
            "address": "Södra Sandby",
            "phone_number": "046-510 01, 51319",
            "bank_details": {
                "bankgiro": "869-3301",
                "postgiro": "36614-6"
            },
            "activity": "Tillverkar asfaltblan-dare, betongblandare för byggnads-o cementvaruindustrin, blandare för laboratorieändamål o kemiska industrin, torktrummor för torkning av grus- o stenmaterial samt transportskruvar för cement, filler, kalk mm",
            "varunamn": "Sandby",
            "employees": 30,
            "annual_turnover": 2500000,
            "capital": 100000,
            "key_personnel": [
                {
                    "name": "Disp Gunnar Wahlbeck",
                    "position": "Veikst dir"
                }
            ],
            "establishment_year": 1886
        },
        "16": {
            "company_name": "SANDBÄCKS GRUS AB",
            "pnr": "113 22",
            "address": "Stockholm, Odeng 87",
            "phone_number": "08-34 37 52, 34 37 53",
            "postgiro": "289889-8",
            "activity": "Grus- o kroppsprodukter, byggnadssten o fabriksbetong",
            "employees": 50,
            "annual_turnover": 5000000,
            "capital": 452000,
            "key_personnel": [
                {
                    "name": "Ing Per Wretlind",
                    "position": "Veikst dir"
                }
            ],
            "establishment_year": 1945
        },
        "17": {
            "company_name": "TYPOCHROMA, AB",
            "pnr": "116 33",
            "address": "Stockholm SO, Bondeg 16-20",
            "phone_number": "08-40 30 88, 43 36 82",
            "bank_details": {
                "bankgiro": "47-6480",
                "postgiro": "1398"
            },
            "activity": "Tillverkar boktrycks-o offsetfärger",
            "employees": 20,
            "annual_turnover": 1800000,
            "capital": 133400,
            "key_personnel": [
                {
                    "name": "Eli Hanner",
                    "position": "Verkst dir"
                }
            ],
            "establishment_year": 1896
        }
    }
}