{
    "original": "GESTETNER AB\n\nPnr 116 52\n\nStockholm, Maria Skolg 83. Tel\n08-69 08 70. Tga Gestetner\nVerksamhet:\nDupliceringsmaski-ner o tillbehör, elektromaskiner o\ntillbehör, offsetmaskiner o tillbehör\nAvdelningskontor: 413 01 Göteborg,\nGöteborgs Lagerhus. Tel\n031-17 79 30\n\n21122 Malmö, Stortorget 13. Tel\n040-766 20\n\n802 24 Gävle, S Stapeltorgsg 3 A.\nTel 026-18 44 35, 18 44 72\n55255 Jönköping, Smålandsg 6. Tel\n036-164040\n\n652 26 Karlstad, Vikeng 16. Tel\n054-15 95 00\n\n582 63 Linköping, Vistv 34 B. Tel\n\n013-100005, 100069\n\n93100 Skellefteå, Nyg 30 A. Tel\n\n0910-163 50, 166 50\n\n703 61 Örebro, Olaig 7. Tel 019-\n\n14 30 00\n\nAktiekapital: 90 000\nVerkst dir: N E Carlsson\nEtableringsår: 1923.\n\nBOHUSTEGEL AB\n\nPnr 450 50\n\nMunkedal. Tel 0524-210 03.\nBankgiro 366-6245. Postgiro 521400-2\nVerksamhet: Tillverkar röd\nfasadtegel o klosterfasad\nAntal anställda: 28\nÅrsomsättning: 2 500 000\n\nBOILERS\n\nPnr 400 10\n\nGöteborg 3, Bellmansg 11. Box\n3042. Tel 031-1148 76, 11 12 76.\nTelex 21053\n\nVerksamhet: Säljer gavlar, man- o\nhandluckor, ringar av profiljärn,\neldrör, kompensatorer, flänsar o\nplåt ämnen\n\nFörsäljningsorganisation för:\nBoilers Bundepresseri, Ejlstrup\n3200 Helsinge, Danmark\nVerkst dir: Ing Kurt Morén\nEtableringsår: 1969.\n\nLÄR\n\nLARSSONS SKOFABRIK AB,\nTHORSTEN\n\nPnr 302 38\n\nHalmstad, Saltsjöv 5. Tel\n035-1117 46. Bankgiro 42-3578. Postr\ngiro 170249\n\nVerksamhet: Tillverkar damskor\nAntal anställda: 20\nAktiekapital: 80 000\nVerkst dir: Alf Larsson\nEtableringsår: 1934.\n\nVerksamhet; Tillverkar\nmellanglas-persienner, fasadpersienner,\nmarkiser, terrasstak,\nmörkläggningsridåer o filmduk, manuellt o elektr\ndrivna\n\nVarunamn: Compact, Faber,\nRiviera, SM, Sonfy\nAntal anställda: 11\nÅrsomsättning: 750 000\nAktiekapital: 5 000\nVerkst dir: Ing Mats Larsson\nEtableringsår: 1958.\n\nLARSSONS SNICKERIFABRIK,\nAB THURE A\n\nPnr 920 10\n\nVindeln, Brånsv 17. Box 9. Tel\n0933-100 85. Bankgiro 76-5519.\nPostgiro 62492\n\nVerksamhet: Tillverkar o säljer\nkompletta gymnastikutrustningar,\nskolmöbler, slöjdbänkar o\nspecialinredningar\nAntal anställda: 18\nÅrsomsättning: 1 200 000\nAktiekapital: 70 000\nStyrelse: Knut E Hellman (ordf),\nSven N Jonsson, Bengt O Svensson,\nOlof A Viklund\nVerkst din Bengt Svensson\nEtableringsån 1919\nOmbildat till aktiebolag 1939.\n\nLARSSON AB, ÅKE\n\nPnr 212 28\n\nMalmö, Sallerupsv 140 B. Tel\n040-93 61 25. Bankgiro 260-7596.\nPostgiro 436150-7\n\nVerksamhet: Utställningsmaterial,\nfotoförstoringar, specialsnickerier\nAntal anställda: 12\nÅrsomsättning: 800 000\nAktiekapital: 30 000\nVerkst dir: Ake Larsson\nEtableringsår: 1956.\n\nPERMA SYSTEM, AB\n\nPnr 560 41\n\nMullsjö, Box 130. Tel 0392-106 60.\nBankgiro 549-1527. Postgiro\n262927-7. Tga Perma.\nTelex 70169 PERMA S\nVerksamhet: Persiennmaterial\nsåsombeslag, tillbehör, plastdetaljer,\nprofiler, stegband, linor, lameller\nsamt maskinutrustning, lamell\nstansmaskiner, automater, handpressar o\nprofilsaxar. Ridålux\nmörkläggningsgardiner. Fasadpersienner. Markiser\nVarunamn: Perma, Ridålux,\nRidå-nett. Siesta\nAntal anstäUda: 65\nAktiekapital: 200 000\nVeikst dir Låge Persson\nEtableringsàr: 1946.\n\nPERMATS MASKIN\n\nPnr 55276\n\nJönköping, Asaforsv 1. Tel\n036-763 80. Bankgiro 794-5074.\nPostgiro 81968-0\n\nVerksamhet: säljer\nbandslipmaski-ner o polermaskiner, även\nautomatiserade samt fälgputsmaskiner,\nhelautomatiska med\nmagasinladdning\n\nChef: Köpman Ingvar Permats\nEtableringsàr: 1968.\n\nPERMECO AB\n\nPnr 181 02\n\nLidingö 2, Box 229. Kottlav 109.\nTel 08-767 04 40. Bankgiro\n330-4094. Postgiro 572717-7.\nTelex 10015 APRAB S\nVerksamhet Försäljning av\nmaskiner o material för grafisk industri\nAntal anstäUda: 11\nÅrsomsättning: 3 000 000\nAktiekapital: 10000\nVerkst dir: Bror Leuhusen\nEtableringsàr: 1965.\n\nPERMIN AB, CARL\n\nPnr 501 09\n\nBorås 1, Lilla Kyrkog 21. Box 633.\nTel 033-12 77 10. Bankgiro\n839-3530. Postgiro 263123-2\nVerksamhet: Tapisserivaror o\ngarner i parti\nAktiekapital: 200 000\nVerkst dir: Owe Andersson\nEtableringsàr: 1942.\n\nPERMOAB, INDUSTRI FIRMAN\n\nPnr 95060\n\nOverkalix. Tel 0926-107 20\nVerksamhet: Tillverkar\nfotografialbum o gästböcker, pärmar,\nbokbinderi\n\nEtableringsàr: 1932.\n\nPERM.PATENT AB\n\nPnr 60103\n\nNorrköping 1, Stohagsg 14. Box\n176. Tel 011-10 03 20. Bankgiro\n61-0004. Postgiro 372477. Tga\nPermpatent\n\nVeiksamhet: Tillverkar\nhängmap-par m fi kontorsartiklar enligt\negna patent\nAktiekapital: 50 000\nVeikst dir: Axel G Lundgren\nEtableringsàr: 1939.\n\nPERNILLA MODESHOP AB\n\nPnr 40051\n\nGöteborg 47, Box 47011. Kortedala\ntorg 7. Tel 031-464611, 5251 14.\nBankgiro 85-2224. Postgiro\n520688-3\n\nVerksamhet: Damkonfektion\nVeikst dir: Fru Agnes Eriksson\nEtableringsàr: 1955.\n\nPERO-PLAST AB\n\nPnr 63106\n\nEskUstuna 1, Smedjeg 14. Box 539.\nTel 016-11 72 40. Bankgiro\n601-3643. Postgiro 6848-6\nVerksamhet: Tillverkar o säljer\nhembelysning samt formsprutade\nkupor för gatubelysning\nAntal anstäUda: 5\nÅrsomsättning: 1000 000\nAktiekapital: 75 000\nVerkst dir: Per Olsson\nEtableringsàr: 1947.\n\nPERPLEX. AB\n\nPnr 211 32\n\nMalmö, Pors lins g 3-7. Tel\n040-353 02, 353 07. Bankgiro 260-5277.\nPostgiro 39692-9. Tga Perplex\nVerksamhet: Tillverkar kosmetiska\no kem tekn produkter\nAntal anställda: 50\n\nÅrsomsättning: 8 000 000\nAktiekapital: 250 000\nVeikst dir: Bengt Lindgren\nEtableringsàr 1926.\n\nTROEDSSON &amp; NILSSON AB\n\nPnr 280 20\n\nBjärnum. Tel 0451-17146\nVerksamhet: Tunnbinderivaror,\nträ-ullsplattor\n\nFirmatecknare: Ebba Stenmo\nEtableringsår: 1884.\n\nGEIJER &amp; CO AB, HERMAN\n\nPnr 651 03\n\nKarlstad 1, Box 76. Köpmannag 2.\nTel 054-11 53 00. Bankgiro\n535-6506. Postgiro 6289-3. Tga\nGeijer-comp. Telex 66029 GEIJERS S\nVerksamhet: Säljer stål o metaller,\nindustriplast o byggnadsmaterial\nVerkst dir: Berth Wöhrman\nEtableringsår: 1918.\n\nIND\n\nVerksamhet: Tillverkar\nkopplings-sprintar för traktorer\nChefen Harry Elvbro, Torsten\nElvbro\n\nEtableringsår: 1945.\n\nINDUSTRIPRODUKTER\nSUDERBERG &amp; CO AB\n\nPnr 330 33\n\nHillers torp. Tel 0370-222 35\nVerksamhet: Tillverkar bil- o mo\ntortillbehör\nAntal anställda: 30\nAktiekapital: 90 000\nVerkst dir. Fabr A Söderberg\nFabr: G Danielson\nEtableringsår 1952.\n\nAntal anställda: 26\nÅrsomsättning: 1800000\nAktiekapital: 75000\nVerkst dir: Göte Malmgren\nEtableringsår: 1946\nOmbildat till aktiebolag 1961.\n\nINDUSTRISPACKEL\n\nPnr 430 70\n\nSävedalen, Göteborgsv 48. Tel\n031-4670 99. 261271. Bankgiro\n85-2829. Postgiro 620687\nVerksamhet: Tillverkar betong- o\nmetall spackel\nVarunamn: No-Crack\nChef: A Karp\nEtableringsår: 1961.\n\nTORÉNS MEK VERKSTADS AB\n\nPnr 292 00\n\nKarlshamn, Kungsg 72. Tel\n0454-10010, 104 77. Bankgiro 656-6269.\nPostgiro 96990-7\nVerksamhet: Mek verkstad o\nrör-läggeri\n\nAntal anställda: 35\nÅrsomsättning: 2 900 000\nAktiekapital: 65 300\nVerkst din Folke Torén\nEtableringsår. 1901.\n\nSVEBAK, AB\n\nPnr 302 50\n\nHalmstad, Pilefeltsg 58. Tel\n035-10 09 00. Bankgiro 64-0336.\nPostgiro 39274. Tga Svebak\nVerksamhet: Tillverkar o säljer\ntapetklister, kärnbindemedel o\nsvällbakmjöl\n\nVarunamn: Erco, Svebak,\nSvebak-Rogin\n\nAktiekapital: 120 000\nChef: Disp Helge Lindén\nEtableringsår: 1936.\n\nARA GOTEBORG AB\n\nPnr 402 32\n\nGöteborg 7, Första Långg 22. Box\n7097. Tel 031-12 4 7 20. Bankgiro\n67-0063. Postgiro 44807\nVerksamhet: Försäljning av\neldningsolja-, diesel- o smörjoljor\nAntal anställda: 35\nÅrsomsättning: 16 000 000\nAktiekapital: 1000000\nChef: Disp Nils Strömberg\nEtableringsår: 1936.",
    "structured": {
        "1": {
            "company_name": "GESTETNER AB",
            "pnr": "116 52",
            "address": "Stockholm, Maria Skolg 83",
            "phone_number": "08-69 08 70",
            "activity": "Dupliceringsmaskiner o tillbehör, elektromaskiner o tillbehör, offsetmaskiner o tillbehör",
            "establishment_year": 1923,
            "capital": 90000,
            "key_personnel": [
                {
                    "name": "N E Carlsson",
                    "position": "Verkst dir"
                }
            ]
        },
        "2": {
            "company_name": "BOHUSTEGEL AB",
            "pnr": "450 50",
            "address": "Munkedal",
            "phone_number": "0524-210 03",
            "bank_details": {
                "bankgiro": "366-6245",
                "postgiro": "521400-2"
            },
            "activity": "Tillverkar röd fasadtegel o klosterfasad",
            "employees": 28,
            "annual_turnover": 2500000,
            "establishment_year": 1923
        },
        "3": {
            "company_name": "BOILERS",
            "pnr": "400 10",
            "address": "Göteborg 3, Bellmansg 11",
            "phone_number": "031-1148 76, 11 12 76",
            "telex": "21053",
            "activity": "Säljer gavlar, man- o handluckor, ringar av profiljärn, eldrör, kompensatorer, flänsar o plåtämnen",
            "key_personnel": [
                {
                    "name": "Ing Kurt Morén",
                    "position": "Verkst dir"
                }
            ],
            "establishment_year": 1969
        },
        "4": {
            "company_name": "LÄR LARSSONS SKOFABRIK AB, THORSTEN",
            "pnr": "302 38",
            "address": "Halmstad, Saltsjöv 5",
            "phone_number": "035-1117 46",
            "bank_details": {
                "bankgiro": "42-3578",
                "postgiro": "170249"
            },
            "activity": "Tillverkar damskor",
            "employees": 20,
            "capital": 80000,
            "key_personnel": [
                {
                    "name": "Alf Larsson",
                    "position": "Verkst dir"
                }
            ],
            "establishment_year": 1934
        },
        "5": {
            "company_name": "LARSSON SOLSKYDDSFABRIK AB",
            "pnr": "582 63",
            "address": "Linköping, Vistv 34 B",
            "phone_number": "013-100005, 100069",
            "activity": "Tillverkar mellanglas-persienner, fasadpersienner, markiser, terrasstak, mörkläggningsridåer o filmduk, manuellt o elektriskt drivna",
            "employees": 11,
            "annual_turnover": 750000,
            "capital": 5000,
            "key_personnel": [
                {
                    "name": "Ing Mats Larsson",
                    "position": "Verkst dir"
                }
            ],
            "establishment_year": 1958
        },
        "6": {
            "company_name": "LARSSONS SNICKERIFABRIK, AB THURE A",
            "pnr": "920 10",
            "address": "Vindeln, Brånsv 17, Box 9",
            "phone_number": "0933-100 85",
            "bank_details": {
                "bankgiro": "76-5519",
                "postgiro": "62492"
            },
            "activity": "Tillverkar o säljer kompletta gymnastikutrustningar, skolmöbler, slöjdbänkar o specialinredningar",
            "employees": 18,
            "annual_turnover": 1200000,
            "capital": 70000,
            "key_personnel": [
                {
                    "name": "Bengt Svensson",
                    "position": "Verkst dir"
                }
            ],
            "establishment_year": 1919
        },
        "7": {
            "company_name": "LARSSON AB, ÅKE",
            "pnr": "212 28",
            "address": "Malmö, Sallerupsv 140 B",
            "phone_number": "040-93 61 25",
            "bank_details": {
                "bankgiro": "260-7596",
                "postgiro": "436150-7"
            },
            "activity": "Utställningsmaterial, fotoförstoringar, specialsnickerier",
            "employees": 12,
            "annual_turnover": 800000,
            "capital": 30000,
            "key_personnel": [
                {
                    "name": "Ake Larsson",
                    "position": "Verkst dir"
                }
            ],
            "establishment_year": 1956
        },
        "8": {
            "company_name": "PERMA SYSTEM, AB",
            "pnr": "560 41",
            "address": "Mullsjö, Box 130",
            "phone_number": "0392-106 60",
            "bank_details": {
                "bankgiro": "549-1527",
                "postgiro": "262927-7"
            },
            "activity": "Persiennmaterial såsom beslag, tillbehör, plastdetaljer, profiler, stegband, linor, lameller samt maskinutrustning, lamellstansmaskiner, automater, handpressar o profilsaxar. Ridålux mörkläggningsgardiner. Fasadpersienner. Markiser",
            "employees": 65,
            "capital": 200000,
            "key_personnel": [
                {
                    "name": "Låge Persson",
                    "position": "Verkst dir"
                }
            ],
            "establishment_year": 1946
        },
        "9": {
            "company_name": "PERMATS MASKIN",
            "pnr": "55276",
            "address": "Jönköping, Asaforsv 1",
            "phone_number": "036-763 80",
            "bank_details": {
                "bankgiro": "794-5074",
                "postgiro": "81968-0"
            },
            "activity": "Säljer bandslipmaskiner o polermaskiner, även automatiserade samt fälgputsmaskiner, helautomatiska med magasinladdning",
            "key_personnel": [
                {
                    "name": "Köpman Ingvar Permats",
                    "position": "Chef"
                }
            ],
            "establishment_year": 1968
        }
    }
}