{
    "original": "MOBIL OIL AB SWEDEN\n\nPnr 18210\n\nDanderyd 1, Pack. Mörby Centrum.\nTel 08-755 2520. Tga Mobiloil,\nStockholm. Telex 1576\nVerksamhet: Säljer bensin,\nmotor-brännolja o eldningsolja, bil-,\nindustri- o marinsmörjmedel samt\nkemiska produkter\nAntal anställda: 300\nÅrsomsättning: 181110 000\nAktiekapital: 13 000 000\nVerkst dir: Hans Tungården\nEtableringsår: 1900\nHelägda dotterbolag: AB Kol &amp;\nKoks, Stockholm, AB Imperialkoks,\nGöteborg, Bloms Eftr i Kungsbacka\nAB, Kungsbacka, AB Eksjö Kol &amp;\nVed, Eksjö, Västsvenska\nMineral-olje AB, Falköping.\n\nMOBILKRANAR AB\n\nPnr 16170\n\nBromma, Adolfsbergsv 26. Tel\n08-98 09 00. Bankgiro 23-8714.\nPostgiro 607782\n\nVerksamhet: Uthyrning av\nmobilkranar\n\nAntal anställda: 20\nÅrsomsättning: 2 250 000\nAktiekapital: 30 000\nVerkst dir: Göte Hamrin\nEtableringsår: 1960.\n\nLIDBECK &amp; CO, AB ROBERT\n\nPnr 400 79 Gbg 54\nHovgården, östergärde. Box 54010,\nGöteborg 54. Tel 031-92 54 05.\nPostgiro 41322\n\nVerksamhet: Kartongtillverkning,\ntryckeri o pappersförsäljning\nAntal anställda: 15\nÅrsomsättning: 1100 000\nAktiekapital: 130 000\nVerkst dir: Kjell Lidbeck\nEtableringsår: 1902.\n\nLIDBERGS BLANKETT.\nFUR LAG, AB\n\nPnr 274 00\n\nSkurup. Tel 0411-41160\nVerksamhet: Blanketter i\nsnabbiägg o ändlös bana\nAntal anställda: 30\nAktiekapital: 150 000\nVerkst dir: Sven Lidberg\nEtableringsår: 1905.\n\nPLA\n\nVerkst dir: Lars Håkansson\nEtableringsår: 1961.\n\nHEDBERG, FIRMA GOTRIK\n\nPnr 41127\n\nGöteborg, Engelbrektsg 7. Tel\n031-13 71 75, 13 6 7 54. Bankgiro\n84-8485. Postgiro 42507. Tga\nInstrumentalis\n\nVerksamhet: Veterinärinstrument,\nveterinärförnödenheter o\ninstrument för artificiell insemination\nÄgare o chef: Fru Dora Hedberg\nEtableringsår: 1924.\n\nHEDBERG &amp; CO K/B,\nHANS E\n\nPnr 130 11\n\nSaltsjö-Duvnäs. Tel 08-716 27 50.\nBankgiro 19-5927. Postgiro 508725.\nTga Hedbergco, Stockholm\nVerksamhet: Agenturer, läkemedel\no laboratorieartiklar\nChef: Kapten Hans Hedberg\nEtableringsår: 1952.\n\nmaskin-elektro ab\n\nPnr 523 00\n\nUlricehamn, Box 144. Bronäsg 6.\nTel 0321-120 20. Bankgiro\n532-8869. Postgiro 109852-4\nVerksamhet: Tillverkar finstans-,\nplast-, press- o bakelit verktyg\nAntal anstäUda: 68\nÅrsomsättning: 4 500 000\nAktiekapital: 100000\nVerkst dir: Paul Sekely\nEtableringsår: 1960.\n\nmaskingravyr, karlström\n&amp; kjellgren\n\nPnr 112 23\n\nStockholm, Pilg 15. Tel 08-51 48 00.\nPostgiro 256036-5\nVerksamhet: Gravyranstalt\nAntal anställda: 4\nEtableringsår: 1947.\n\nTUL\n\nÅrsomsättning: 1000 000\nAktiekapital: 200 000\nVerkst dir: Evert Andersson\nEtableringsàr. 1898.\n\nTSAPPOS, MICKAEL TH\n\nPnr 11531\n\nStockholm, Strindbergsg 32. Tel\n08-6044 55. Bankgiro 56-4621.\nPostgiro 54464. Tga Tsappakis\nVerksamhet: Säljer naturtvättsvamp,\nsämskskinn, biltillbehör samt\nförmedlar för export begagnade\nbildelar o begagnade\nentreprenadmaskiner\n\nÅrsomsättning: 200 000\nChef: Theophile M Tsappos\nEtableringsàr: 1882.\n\nT-SCHAKT AB\n\nPnr 70102\n\nÖrebro 1, Box 82. Rudbecksg 61.\nTel 019-14 03 00. Bankgiro\n614-7581. Postgiro 114590-3\nVerksamhet: Uthyr\nentreprenadmaskiner\n\nAntal anställda: 6\nÅrsomsättning: 12 000 000\nAktiekapital: 30 000\nVerkst dir: Bertil Liedström\nEtableringsàr: 1965.\n\nTT.LIST, AB\n\nPnr 251 02\n\nHelsingborg 1, Box 36. Tel\n042-614 00. Bankgiro 192-5148.\nPostgiro 71546-6\n\nVerksamhet: Listförsäljning engros\nAktiekapital: 15 000\nVeikst dir Nils Lundgren\nEtableringsàr: 1966.\n\nTUAB\n\nse Teleplan. AB.\n\nTUAVERKEN AB\n\nPnr 543 01\n\nTibro 1, Ställverksg. Box 91. Tel\n0504-125 10. Postgiro 174700-5\nVeiksamhet: Tillverkar\nkontorsmöbler o matrumsstilmöbler\nAntal anställda: 50\nÅrsomsättning: 6 500 000\nAktiekapital: 50 000\nVerkst dir Fabr Thure Andersson\nEtableringsàr. 1951.\n\nTUBA, INDUSTRI AB\n\nPnr 340 22\n\nEneryda. Tel 0476-22200.\nBankgiro 671-7144. Postgiro 44 2653.\nTga Tuba\n\nVerksamhet: Tillverkar\nkontorsstolar, stålrörsmöbler o\nsjukhusinredningar. Utför förnickling o\nför-kromning\n\nAntal anställda: 160\nAktiekapital: 50 000\nVerkst dir. Bertil Jonasson\nEtableringsàr: 1954.\n\nTUBE MASKIN AB\n\nPnr 126 51\n\nHägersten, Sverkersg 6. Tel\n08-45 50 69\n\nVerksamhet: Säljer hela system\nsamt komponenter inom hydraulik\no pneumatiksektorn. Viss egen\n\ntillverkning. Flertal\ngeneralagenturer\n\nFilial: 203 13 Malmö 4, Box 4179.\nTel 040-97 08 04\n\nVerkst dir.n G Bengtsson, L\nTu-nestad\n\nFörsäljn-chef: K Lindfors\nEtableringsàr: 1955.\n\nTuBe PLÅTSLAGERI AB\n\nPnr 585 90\n\nLinköping, Regelg 5. Tel\n013-10 23 35. Bankgiro 120-1961.\nPostgiro 542630-9\n\nTUBE\n\nLINKÖPING\n\nVerksamhet: Utför\nventilationsanläggningar o byggnadsplåtslageri.\nTillverkar spiralfalsade rör,\ninspektionsluckor o andra produkter för\nventilationsbranschen\nAntal anställda: 70\nÅrsomsättning: 5 000 000\nAktiekapital: 100 000\nVeikst dir: Fabr Bertil Andersson\nEtableringsàr: 1945.\n\nTUBFYLLNING\n\nPnr 18132\n\nLidingö, Drottningv 14. Tel\n08-765 32 42\n\nVerksamhet: Utför lönearbeten med\ntub-, fläsk- o burkfyllning\nÄgare: Harry Qwist\nEtableringsàr. 1940.\n\nTUDOR, AB\n\nPnr 105 28\n\nStockholm, Birger Jarlsg 55. Tel\n08-2279 00. Bankgiro 72-7015.\nPostgiro 562-9. Tga Accumulator.\nTelex 10852\n\nVerksamhet: Tillverkar\nblyackumulatorer för stationära o\ntraktio-nära ändamål samt startbatterier,\nackumulatorer för signaländamål,\nutrustning för ackumulatorfabriker,\ntorrelement, tonbatterier for alla\nändamål, likriktare, växelriktare,\nlikspänningsomvandlare,\nregler-transformatorer, transduktorutrust-ningar, elektr motstånd m m samt\nackumulatorsyra o destillerat\nvatten\n\nFilialer: Västra Frölunda, Frökon-\n\ntrollsg 4. Tel 031-4502 70\n\nKarlstad, Lantvärnsg 7. Tel 054-\n\n15 5760, 18 26 97\n\nMalmö S, Norbergsg 3. Tel 040-\n\n800 60\n\nNorrköping, Tullhusg 14. Tel\n011-13 29 09, 12 72 70\n\nSkellefteå, Manhemsg 22. Tel\n0910-373 50\n\nSundsvall, Tövav. Tel 060-1217 80\nUppsala, Kålängsgränd 4. Tel\n018-12 9950, 103900\nVästerås, Stureg 10. Tel\n021-1216 10, 1216 11\n\nÖrebro, N Lillåstrand 7. Tel\n019-18 26 50, 18 26 51\nFabriker Nol o Ängelholm\nVarunamn: Tudor, Bali, Crown,\nEl-tek, Harbeck, Latex, Mipor, Pertrix,\nTor, Tudix, Tupor, Varta, Tufos\nAntal anställda: 1 460\n\nAktiekapital: 10000 000\nStyrelse: Dir Sven Agrup (ordf),\nprof Sune Carlson, dir Carl-Erik\nGranqvist, dir Nils Wahlström\nVerkst dir: Nils Wahlström\nMarknadschef: Dir Gunnar Ekström\nEkonomichef: Dir Börje Dickert\nTekn chef: Disp Erik Sundberg\nPlatschefer Overing Björn Lundin\n(Ängelholm), övering Bo Gartvall\n(Nol)\n\nEtableringsàr: 1914\n\nDotterbolag till AGA AB, Lidingö.\n\nTUFVASSONS\nTRANSFOR-MATORFABRIK AB\n\nPnr 190 30\n\nSigtuna. Tel 0760-50 1 20\nVerksamhet: Tillverkar elektr\ntransformatorer\nAntal anställda: 30\nAktiekapital: 273 600\nVerkst dir: Birger Tufvasson\nEtableringsàr: 1938.\n\nTHUGIS TRÄVARU AB\n\nPnr 570 71\n\nBerga, Box 101. Tel kontor\n0491-504 86, fabrik 50152. Bankgiro\n580-4612. Postgiro 596520-7\nVerksamhet: Tillverkar trappor\nVarunamn: Thugistrappan\nAntal anställda: 20\n\nÅrsomsättning: 1000 000\n\nAktiekapital: 50 000\n\nStyrelse: Sven Gustavsson (ordf),\n\nThure Petersson, Thore Engström,\n\nGeorg Nilsson\n\nVerkst dir. Georg Nilsson\n\nEtableringsàr 1968.\n\nIDE\n\nIBACO AB\n\nPnr 11146\n\nStockholm C, Biblioteksg 11. Tel\n08-1136 55. Postgiro 256353. Tga\nIbacohandel\n\nVerksamhet: Export o import med\nöstländerna, främst Ungern\nAktiekapital: 50 000\nÄgare o chef: Dr Ivan Bakonyi\nEtableringsår: 1955.\n\nI B E INGENJURSFIRMA\nB ERICSON AB\n\nPnr 8 61 00\n\nTimrå, Box 112. Tel 060-733 10.\nBankgiro 18-0154. Postgiro 298814\nVerksamhet: Tillverkar\npunktsvets-aggregat, specialitet: portabla,\nbyggbara\nVarunamn: IBE\n\nÄgare o chef: Ing Birger Ericson\nEtableringsår: 1951.\n\nCLEVES AB, R F\n\nPnr 103 65\n\nStockholm 3, Sveav 31. Box 3269.\nTel 08-23 3155. Bankgiro 16-0446.\nPostgiro 674. Tga Cleveglas\nVerksamhet: Engrosförsäljning o\nbearbetning av planglas o plast\nLager o fabrik: Stockholm 42,\nVre-tenborgsv 21. Tel 08-45 27 55\nAktiekapital: 1200000\nVerkst dir: Bertil Häggmark\nEtableringsår: 1870.\n\nELGASVETS AB\n\nPnr 443 01\n\nLerum, Fack. Tel 0302-116 00.\nBankgiro 440-6039. Postgiro\n44915-7. Tga Elgasvets. Telex 2427\nVerksamhet: Acetylengasverk,\nsvetselektroder, apparater o\ntillbehör för gassvetsning, apparater o\ntillbehör för gasol, elektriska\nsvetsmaskiner o tillbehör, argon,\ngasolgas\n\nAvdelningskontor: Malmö,\nBygg-mästareg 1. Tel 040-342 50\nStockholm. Huvudskärsv 24, pa\nJohanneshov. Tel 08-48 00 40\nSundsvall, Köpmang 1. Tel\n060-15 8100\n\nCfrebro, Slöjdg 1. Tel 019-1217 80\nVarunamn: Elga\nAntal anställda: 130\nÅrsomsättning: 15 000 000\nAktiekapital: 300 000\nVerkst dir: Carl Alfredson\nEtableringsår: 1938.\n\nWINKELCENTRIFUG AB\n\nPnr 102 32\n\nStockholm 6, Norrtullsg 23. Box\n6080. Tel 08-3138 33. Bankgiro\n47-6119. Postgiro 153978. Tga\nWifug\n\nVerksamhet: Tillverkar o säljer\nelektr laboratoriecentrifuger\nAntal anställda: 12\nÅrsomsättning: 750 000\nAktiekapital: 70 000\nVerkst dir: G I Fredholm\nEtableringsår: 1928.\n\nWINQUIST AB, AUTOMOBIL.\nFIRMA C A\n\nPnr 272 01\n\nSimrishamn 1, Fredsdalsg 1. Box\n35. Tel 0414-11770. Bankgiro\n662-2039. Postgiro 34595-9. Tga\nWii&gt;-quist\n\nVerksamhet: Volvoåterförsäljare\no service. Biluthyrning\nAntal anställda: 40\nÅrsomsättning: 10 000 000\nAktiekapital: 250 000\nVerkst din Axel-E Winquist\nEtableringsån 1922.\n\nVINLANDS BYGGMATERIAL\nAB\n\nPnr 43102\n\nMölndal 2. Göteborgsv 119. Box\n2026. Tel 031-16 03 94, 16 03 95\nVerksamhet: Säljer byggmaterial\nÅrsomsättning: 1000 000\nVerkst dir: Folke Wederbrand\nEtableringsår: 1964.",
    "structured": {
        "1": {
            "company_name": "MOBIL OIL AB SWEDEN",
            "activity": "Säljer bensin, motor-brännolja o eldningsolja, bil-, industri- o marinsmörjmedel samt kemiska produkter",
            "employees": 300,
            "annual_turnover": 181110000,
            "capital": 13000000,
            "key_personnel": [
                {
                    "name": "Hans Tungården",
                    "position": "Verkst dir"
                }
            ],
            "establishment_year": 1900
        },
        "2": {
            "company_name": "MOBILKRANAR AB",
            "activity": "Uthyrning av mobilkranar",
            "employees": 20,
            "annual_turnover": 2250000,
            "capital": 30000,
            "key_personnel": [
                {
                    "name": "Göte Hamrin",
                    "position": "Verkst dir"
                }
            ],
            "establishment_year": 1960
        },
        "3": {
            "company_name": "LIDBECK & CO, AB ROBERT",
            "activity": "Kartongtillverkning, tryckeri o pappersförsäljning",
            "employees": 15,
            "annual_turnover": 1100000,
            "capital": 130000,
            "key_personnel": [
                {
                    "name": "Kjell Lidbeck",
                    "position": "Verkst dir"
                }
            ],
            "establishment_year": 1902
        },
        "4": {
            "company_name": "LIDBERGS BLANKETT. FUR LAG, AB",
            "activity": "Blanketter i snabbiägg o ändlös bana",
            "employees": 30,
            "capital": 150000,
            "key_personnel": [
                {
                    "name": "Sven Lidberg",
                    "position": "Verkst dir"
                }
            ],
            "establishment_year": 1905
        },
        "5": {
            "company_name": "maskin-elektro ab",
            "activity": "Tillverkar finstans-, plast-, press- o bakelit verktyg",
            "employees": 68,
            "annual_turnover": 4500000,
            "capital": 100000,
            "key_personnel": [
                {
                    "name": "Paul Sekely",
                    "position": "Verkst dir"
                }
            ],
            "establishment_year": 1960
        },
        "6": {
            "company_name": "maskingravyr, karlström & kjellgren",
            "activity": "Gravyranstalt",
            "employees": 4,
            "establishment_year": 1947
        },
        "7": {
            "company_name": "TUL",
            "annual_turnover": 1000000,
            "capital": 200000,
            "key_personnel": [
                {
                    "name": "Evert Andersson",
                    "position": "Verkst dir"
                }
            ],
            "establishment_year": 1898
        },
        "8": {
            "company_name": "TSAPPOS, MICKAEL TH",
            "activity": "Säljer naturtvättsvamp, sämskskinn, biltillbehör samt förmedlar för export begagnade bildelar o begagnade entreprenadmaskiner",
            "annual_turnover": 200000,
            "key_personnel": [
                {
                    "name": "Theophile M Tsappos",
                    "position": "Chef"
                }
            ],
            "establishment_year": 1882
        },
        "9": {
            "company_name": "T-SCHAKT AB",
            "activity": "Uthyr entreprenadmaskiner",
            "employees": 6,
            "annual_turnover": 12000000,
            "capital": 30000,
            "key_personnel": [
                {
                    "name": "Bertil Liedström",
                    "position": "Verkst dir"
                }
            ],
            "establishment_year": 1965
        },
        "10": {
            "company_name": "TT.LIST, AB",
            "activity": "Listförsäljning engros",
            "capital": 15000,
            "key_personnel": [
                {
                    "name": "Nils Lundgren",
                    "position": "Veikst dir"
                }
            ],
            "establishment_year": 1966
        },
        "11": {
            "company_name": "TUAVERKEN AB",
            "activity": "Tillverkar kontorsmöbler o matrumsstilmöbler",
            "employees": 50,
            "annual_turnover": 6500000,
            "capital": 50000,
            "key_personnel": [
                {
                    "name": "Fabr Thure Andersson",
                    "position": "Verkst dir"
                }
            ],
            "establishment_year": 1951
        },
        "12": {
            "company_name": "TUBA, INDUSTRI AB",
            "activity": "Tillverkar kontorsstolar, stålrörsmöbler o sjukhusinredningar. Utför förnickling o för-kromning",
            "employees": 160,
            "capital": 50000,
            "key_personnel": [
                {
                    "name": "Bertil Jonasson",
                    "position": "Verkst dir"
                }
            ],
            "establishment_year": 1954
        },
        "13": {
            "company_name": "TUBE MASKIN AB",
            "activity": "Säljer hela system samt komponenter inom hydraulik o pneumatiksektorn. Viss egen tillverkning. Flertal generalagenturer",
            "establishment_year": 1955
        },
        "14": {
            "company_name": "TuBe PLÅTSLAGERI AB",
            "activity": "Utför ventilationanläggningar o byggnadsplåtslageri. Tillverkar spiralfalsade rör, inspektionsluckor o andra produkter för ventilationsbranschen",
            "employees": 70,
            "annual_turnover": 5000000,
            "capital": 100000,
            "key_personnel": [
                {
                    "name": "Fabr Bertil Andersson",
                    "position": "Veikst dir"
                }
            ],
            "establishment_year": 1945
        },
        "15": {
            "company_name": "TUBFYLLNING",
            "activity": "Utför lönearbeten med tub-, fläsk- o burkfyllning",
            "establishment_year": 1940
        },
        "16": {
            "company_name": "TUDOR, AB",
            "activity": "Tillverkar blyackumulatorer för stationära o traktio-nära ändamål samt startbatterier, ackumulatorer för signaländamål, utrustning för ackumulatorfabriker, torrelement, tonbatterier for alla ändamål, likriktare, växelriktare, likspänningsomvandlare, regler-transformatorer, transduktorutrust-ningar, elektr motstånd m m samt ackumulatorsyra o destillerat vatten",
            "employees": 1460,
            "annual_turnover": 10000000,
            "capital": 10000000,
            "key_personnel": [
                {
                    "name": "Nils Wahlström",
                    "position": "Verkst dir"
                }
            ],
            "establishment_year": 1914
        },
        "17": {
            "company_name": "TUFVASSONS TRANSFOR-MATORFABRIK AB",
            "activity": "Tillverkar elektr transformatorer",
            "employees": 30,
            "capital": 273600,
            "key_personnel": [
                {
                    "name": "Birger Tufvasson",
                    "position": "Verkst dir"
                }
            ],
            "establishment_year": 1938
        },
        "18": {
            "company_name": "THUGIS TRÄVARU AB",
            "activity": "Tillverkar trappor",
            "employees": 20,
            "annual_turnover": 1000000,
            "capital": 50000,
            "key_personnel": [
                {
                    "name": "Georg Nilsson",
                    "position": "Verkst dir"
                }
            ],
            "establishment_year": 1968
        },
        "19": {
            "company_name": "IBACO AB",
            "activity": "Export o import med östländerna, främst Ungern",
            "capital": 50000,
            "key_personnel": [
                {
                    "name": "Dr Ivan Bakonyi",
                    "position": "Ägare o chef"
                }
            ],
            "establishment_year": 1955
        },
        "20": {
            "company_name": "I B E INGENJURSFIRMA B ERICSON AB",
            "activity": "Tillverkar punktsvets-aggregat, specialitet: portabla, byggbara",
            "key_personnel": [
                {
                    "name": "Ing Birger Ericson",
                    "position": "Ägare o chef"
                }
            ],
            "establishment_year": 1951
        },
        "21": {
            "company_name": "CLEVES AB, R F",
            "activity": "Engrosförsäljning o bearbetning av planglas o plast",
            "annual_turnover": 1200000,
            "capital": 1200000,
            "key_personnel": [
                {
                    "name": "Bertil Häggmark",
                    "position": "Verkst dir"
                }
            ],
            "establishment_year": 1870
        },
        "22": {
            "company_name": "ELGASVETS AB",
            "activity": "Acetylengasverk, svetselektroder, apparater o tillbehör för gassvetsning, apparater o tillbehör för gasol, elektriska svetsmaskiner o tillbehör, argon, gasolgas",
            "employees": 130,
            "annual_turnover": 15000000,
            "capital": 300000,
            "key_personnel": [
                {
                    "name": "Carl Alfredson",
                    "position": "Verkst dir"
                }
            ],
            "establishment_year": 1938
        },
        "23": {
            "company_name": "WINKELCENTRIFUG AB",
            "activity": "Tillverkar o säljer elektr laboratoriecentrifuger",
            "employees": 12,
            "annual_turnover": 750000,
            "capital": 70000,
            "key_personnel": [
                {
                    "name": "G I Fredholm",
                    "position": "Verkst dir"
                }
            ],
            "establishment_year": 1928
        },
        "24": {
            "company_name": "WINQUIST AB, AUTOMOBIL. FIRMA C A",
            "activity": "Volvoåterförsäljare o service. Biluthyrning",
            "employees": 40,
            "annual_turnover": 10000000,
            "capital": 250000,
            "key_personnel": [
                {
                    "name": "Axel-E Winquist",
                    "position": "Verkst dir"
                }
            ],
            "establishment_year": 1922
        },
        "25": {
            "company_name": "VINLANDS BYGGMATERIAL AB",
            "activity": "Säljer byggmaterial",
            "annual_turnover": 1000000,
            "key_personnel": [
                {
                    "name": "Folke Wederbrand",
                    "position": "Verkst dir"
                }
            ],
            "establishment_year": 1964
        }
    }
}