{
    "original": "HÄSTHOLMSVARVET, AB\n\nPnr 115 33\n\nStockholm, Hedinsg 11. Tel\n08-624916. Postgiro 163306\nVerksamhet: Förmedlar o förvaltar\nbåtar\n\nAktiekapital: 300000\nVerkst dir: Ing Knud H Reimers\nEtableringsår: 1915.\n\nRUDA EXPORTTRÄ, AB\n\nPnr 570 71\n\nBerga. Tel 0491-500 10. Telex 4976.\nTga Nilswood, Oskarshamn\nVetksamhet: Såg- o\nimpregne-ringsverk, hyvleri\nAntal anställda: 75\nChef: Disp Göte Åbom\nEtableringsån 1957.\n\nFOTLISA SVENSKA AB\n\nPnr 10061\n\nStockholm 11. Erstag 9. Box 11031.\nTel 08-439632, 438577. Postgiro\n156699\n\nVerksamhet: Formpressning av\n\nfotstöd\n\nVarunamn: Fotlisa\nAktiekapital: 5 000\nVerkst dir: Folke Rudén\nEtableringsår: 1968.\n\nBIL\n\nBIL &amp; BUSS I HUDIKSVALL AB\n\nPnr 824 00\n\nHudiksvall, Södra v 13. Tel\n0650-155 50\n\nVerksamhet: Bilar, reservdelar,\nbilverkstäder, gummi verkstad\nAntal anställda: 132\nÅrsomsättning: 22 669 000\nAktiekapital: 3 900 000\nVerkst dir: Gösta Lindqvist\nEtableringsår: 1933.\n\nALEDALSNYCKELFABRIK\n\nPnr 560 23\n\nBankeryd. Tel 036-720 06.\nBankgiro 836-9167. Postgiro 9359-1\nVerksamhet: Tillverkar färdiga\nnycklar o nyckelämnen, hästbetsel\no excenterspännen samt utför\nklenare o medelgrovt hejarsmide\nAntal anställda: 10\nÄgare o chef: J F Lund\nEtableringsår: 1871.\n\nALLTIMASKIN, MASKINFIRMA\n\nPnr 412 72\n\nGöteborg, Anders Zornsg 21. Tel\n031-40 45 42. Postgiro 427790-1.\nTga Alltimaskin\n\nVerksamhet: Excenterpress 3-2 500\nton, matarverk, alla svarvar, fräs-,\nsick-, kantfals-, stans-,\nrullfals-o Pittsburgmaskiner\nVarunamn: AMP, Muller, Sigl,\nTaratte\n\nChef: Ing Hans Hansson.\n\nALLTI-PÄLS, AB\n\nPnr 57301\n\nTranås 1, Box 239. Vasag 29. Tel\n0140-100 35. Bankgiro 365-6663.\nPostgiro 366255-8\nVerksamhet: Tillverkar pälsar samt\ndammössor i skinn\nAntal anställda: 27\nÅrsomsättning: 2000 000\nAktiekapital: 25 000\nVerkst dir: Disp Erie Bogenius\nEtableringsår: 1947.\n\nALLVÅG MEKANISK\nVERKSTAD\n\nPnr 113 23\n\nStockholm, Hälsingeg 8. Tel\n08-33 96 90. Bankgiro 72-9314.\nPostgiro 252761\n\nVerksamhet: Tillverkar vågar,\ntobak- o varuautomater samt\nbutiksmaskiner\n\nEtableringsår: 1945.\n\nMARKANT, AB\n\nPnr 400 60\n\nGöteborg 6, Räntmästareg 20. Box\n666. Tel 031-15 7101, 15 07 90.\nBankgiro 362-1265. Postgiro\n48655-5. Tga Markant\nVerksamhet: Säljer industrigummi,\nrördetaljer,rörsmide, packningar o\nmaskinförnödenheter\nVarunamn: Gunit-Metall\nÅrsomsättning: 1000 000\nAktiekapital: 30 000\nVerkst dir: Bik Wåhlander\nEtableringsår: 1953.\n\nBERGMAN &amp; SÖNER AB, C\n\nPnr 127 40\n\nSkärholmen, Stångholmsbacken 30.\nTel 08-710 08 20. Bankgiro\n566-0493. Postgiro 193018-9\nVerksamhet: Säljer papper såsom\nemballage, säckar, engångsservis\no hygienpapper en gros\nAntal anställda: 7\nÅrsomsättning: 4 000 000\nAktiekapital: 30 000\nStyrelse: Dir Stig Arvid Bergman\n(crdf), kamrer Knut Ake Bergman,\nköpman Bror Harry Bergman\nVerkst dir: Stig Bergman\nEtableringsår: 1924\nNamnändring 1959 från\nLiljeholmens Påsfabriker AB.\n\nBERGMAN AB, J H\n\nPnr 778 01\n\nNorberg, Box 6. Kvarng 7. Tel\n0223-20950. Bankgiro 811-6105.\nPostgiro 87986-6\n\nVerksamhet: Värme- o sanitära\ninstallationer\nAntal anställda: 26\nÅrsomsättning: 2 000 000\nAktiekapital: 30000\nVerkst dir: Ing Erie E Bergman\nEtableringsår: 1907.\n\nCEDERLOF, AB BRÖDERNA\n\nPnr 800 04\n\nGävle 4, Utmarksv 2. Box 4055.\nTel 026-1156 40. Bankgiro\n193-9123. Postgiro 468424-7.\nTelex 81127\n\nVerksamhet:\nByggmaterialförsälj-ning o plattsättni-ng\nAktiekapital: 60 000\nVerkst dir: Erie E Cederlöf\nEtableringsår: 1953.\n\nCEDERROTHS TEKNISKA\nFABRIK AB\n\nPnr 16210\n\nVällingby 1, Sorterarg 2. Pack. Tel\n08-38 0160. Bankgiro 57-6124.\nPostgiro 644. Telex 10267. Tga\n\nSwedced\n\nVerksamhet: Tillverkar fruktsalt,\nplåster o hygienartiklar\nAntal anställda: 150\nAktiekapital: 1500 000\nVerkst dir: Gunnar O Nittzell\nEtableringsår: 1895.\n\nELVÄRME-VERKEN AB\n\nPnr 421 09\n\nVästra Frölunda 9, Box 9010. Tel\n031-29 20 35. Bankgiro 512-7725.\nPostgiro 49776-8\nVerksamhet: Tillverkar ugnar för\nindustri, slakterier o\nsnickerifabriker, specialtillverkning för\nIndustrin\n\nAntal anställda: 50\nÅrsomsättning: 3 500 000\nAktiekapital: 200 000\nVerkst dir: Patrik Hedendahl\nFabrikschef: Ing Harry Feldt\nEtableringsår: 1946\nDotterbolag: Lecab Rullbanor AB,\nHärryda, Svenska Elektriska\nRegulator AB, Västra Frölunda.\n\nEMBALLAGEINDUSTRI, AB\n\nPnr 531 00\n\nLidköping, Lidbecksg 18. Tel\n0510-203 63. Bankgiro 21-2117. Postgiro\n329431\n\nVerksamhet: Tillverkar trycksaker.\nSpecialitet: fraktsedlar, kartonger\nAntal anstäUda: 10\nAktiekapital: 15 000\nÄgare o chefer: Sam Odkvist,\nAllan Olsson\nEtableringsår: 1960.\n\nEMBALLAGEPROVNINGS.\nLABORATORIET AB\n\nPnr 12122\n\nJohanneshov 1, Box 91. Hammarby\nFabriksv 29-31. Tel 08-44 00 30.\nBankgiro 613-5933. Postgiro\n402850-2\n\nVerksamhet: Serviceorgan knutet\ntill Svenska\nFörpackningsforskningsinstitutet. Företaget svarar\nför serviceverksamheten o utför\nprovning av förpackningar o\nutveckling av systemlösningar där\nprodukt, förpackning o transportled\nanpassas till varandra\nAntal anstäUda: 12\nÅrsomsättning: 710 000\nAktiekapital: 25 000\nVerkst dir. Yngve Dagel\nAvd-chef: Ing Sten Bervel\nEtableringsår. 1954.",
    "structured": {
        "firms": [
            {
                "company_name": "HÄSTHOLMSVARVET, AB",
                "pnr": "115 33",
                "address": "Stockholm, Hedinsg 11",
                "phone_number": "08-624916",
                "postgiro": "163306",
                "activity": "Förmedlar o förvaltar båtar",
                "capital": 300000,
                "key_personnel": [
                    {
                        "name": "Ing Knud H Reimers",
                        "position": "Verkst dir"
                    }
                ],
                "establishment_year": 1915
            },
            {
                "company_name": "RUDA EXPORTTRÄ, AB",
                "pnr": "570 71",
                "address": "Berga",
                "phone_number": "0491-500 10",
                "telex": "4976",
                "activity": "Såg- o impregneringsverk, hyvleri",
                "employees": 75,
                "capital": 0,
                "key_personnel": [
                    {
                        "name": "Disp Göte Åbom",
                        "position": "Chef"
                    }
                ],
                "establishment_year": 1957
            },
            {
                "company_name": "FOTLISA SVENSKA AB",
                "pnr": "10061",
                "address": "Stockholm 11, Erstag 9, Box 11031",
                "phone_number": "08-439632, 438577",
                "postgiro": "156699",
                "activity": "Formpressning av fotstöd",
                "capital": 5000,
                "key_personnel": [
                    {
                        "name": "Folke Rudén",
                        "position": "Verkst dir"
                    }
                ],
                "establishment_year": 1968
            },
            {
                "company_name": "BIL & BUSS I HUDIKSVALL AB",
                "pnr": "824 00",
                "address": "Hudiksvall, Södra v 13",
                "phone_number": "0650-155 50",
                "activity": "Bilar, reservdelar, bilverkstäder, gummi verkstad",
                "employees": 132,
                "annual_turnover": 22669000,
                "capital": 3900000,
                "key_personnel": [
                    {
                        "name": "Gösta Lindqvist",
                        "position": "Verkst dir"
                    }
                ],
                "establishment_year": 1933
            },
            {
                "company_name": "ALEDALSNYCKELFABRIK",
                "pnr": "560 23",
                "address": "Bankeryd",
                "phone_number": "036-720 06",
                "bankgiro": "836-9167",
                "postgiro": "9359-1",
                "activity": "Tillverkar färdiga nycklar o nyckelämnen, hästbetsel o excenterspännen samt utför klenare o medelgrovt hejarsmide",
                "employees": 10,
                "key_personnel": [
                    {
                        "name": "J F Lund",
                        "position": "Ägare o chef"
                    }
                ],
                "establishment_year": 1871
            },
            {
                "company_name": "ALLTIMASKIN, MASKINFIRMA",
                "pnr": "412 72",
                "address": "Göteborg, Anders Zornsg 21",
                "phone_number": "031-40 45 42",
                "postgiro": "427790-1",
                "activity": "Excenterpress 3-2 500 ton, matarverk, alla svarvar, fräs-, sick-, kantfals-, stans-, rullfals-o Pittsburgmaskiner",
                "key_personnel": [
                    {
                        "name": "Ing Hans Hansson",
                        "position": "Chef"
                    }
                ],
                "establishment_year": 0
            },
            {
                "company_name": "ALLTI-PÄLS, AB",
                "pnr": "57301",
                "address": "Tranås 1, Box 239, Vasag 29",
                "phone_number": "0140-100 35",
                "bankgiro": "365-6663",
                "postgiro": "366255-8",
                "activity": "Tillverkar pälsar samt dammössor i skinn",
                "employees": 27,
                "annual_turnover": 2000000,
                "capital": 25000,
                "key_personnel": [
                    {
                        "name": "Disp Erie Bogenius",
                        "position": "Verkst dir"
                    }
                ],
                "establishment_year": 1947
            },
            {
                "company_name": "ALLVÅG MEKANISK VERKSTAD",
                "pnr": "113 23",
                "address": "Stockholm, Hälsingeg 8",
                "phone_number": "08-33 96 90",
                "bankgiro": "72-9314",
                "postgiro": "252761",
                "activity": "Tillverkar vågar, tobak- o varuautomater samt butiksmaskiner",
                "establishment_year": 1945
            },
            {
                "company_name": "MARKANT, AB",
                "pnr": "400 60",
                "address": "Göteborg 6, Räntmästareg 20, Box 666",
                "phone_number": "031-15 7101, 15 07 90",
                "bankgiro": "362-1265",
                "postgiro": "48655-5",
                "activity": "Säljer industrigummi, rördetaljer, rörsmide, packningar o maskinförnödenheter",
                "annual_turnover": 1000000,
                "capital": 30000,
                "key_personnel": [
                    {
                        "name": "Bik Wåhlander",
                        "position": "Verkst dir"
                    }
                ],
                "establishment_year": 1953
            },
            {
                "company_name": "BERGMAN & SÖNER AB, C",
                "pnr": "127 40",
                "address": "Skärholmen, Stångholmsbacken 30",
                "phone_number": "08-710 08 20",
                "bankgiro": "566-0493",
                "postgiro": "193018-9",
                "activity": "Säljer papper såsom emballage, säckar, engångsservis o hygienpapper en gros",
                "employees": 7,
                "annual_turnover": 4000000,
                "capital": 30000,
                "key_personnel": [
                    {
                        "name": "Dir Stig Arvid Bergman (crdf)",
                        "position": "Styrelse"
                    },
                    {
                        "name": "Knut Ake Bergman",
                        "position": "Kamrer"
                    },
                    {
                        "name": "Bror Harry Bergman",
                        "position": "Köpman"
                    },
                    {
                        "name": "Stig Bergman",
                        "position": "Verkst dir"
                    }
                ],
                "establishment_year": 1924
            },
            {
                "company_name": "BERGMAN AB, J H",
                "pnr": "778 01",
                "address": "Norberg, Box 6, Kvarng 7",
                "phone_number": "0223-20950",
                "bankgiro": "811-6105",
                "postgiro": "87986-6",
                "activity": "Värme- o sanitära installationer",
                "employees": 26,
                "annual_turnover": 2000000,
                "capital": 30000,
                "key_personnel": [
                    {
                        "name": "Ing Erie E Bergman",
                        "position": "Verkst dir"
                    }
                ],
                "establishment_year": 1907
            },
            {
                "company_name": "CEDERLOF, AB BRÖDERNA",
                "pnr": "800 04",
                "address": "Gävle 4, Utmarksv 2, Box 4055",
                "phone_number": "026-1156 40",
                "bankgiro": "193-9123",
                "postgiro": "468424-7",
                "telex": "81127",
                "activity": "Byggmaterialförsäljning o plattsättning",
                "capital": 60000,
                "key_personnel": [
                    {
                        "name": "Erie E Cederlöf",
                        "position": "Verkst dir"
                    }
                ],
                "establishment_year": 1953
            },
            {
                "company_name": "CEDERROTHS TEKNISKA FABRIK AB",
                "pnr": "16210",
                "address": "Vällingby 1, Sorterarg 2, Pack",
                "phone_number": "08-38 0160",
                "bankgiro": "57-6124",
                "postgiro": "644",
                "telex": "10267",
                "activity": "Tillverkar fruktsalt, plåster o hygienartiklar",
                "employees": 150,
                "capital": 1500000,
                "key_personnel": [
                    {
                        "name": "Gunnar O Nittzell",
                        "position": "Verkst dir"
                    }
                ],
                "establishment_year": 1895
            },
            {
                "company_name": "ELVÄRME-VERKEN AB",
                "pnr": "421 09",
                "address": "Västra Frölunda 9, Box 9010",
                "phone_number": "031-29 20 35",
                "bankgiro": "512-7725",
                "postgiro": "49776-8",
                "activity": "Tillverkar ugnar för industri, slakterier o snickerifabriker, specialtillverkning för industrin",
                "employees": 50,
                "annual_turnover": 3500000,
                "capital": 200000,
                "key_personnel": [
                    {
                        "name": "Patrik Hedendahl",
                        "position": "Verkst dir"
                    },
                    {
                        "name": "Ing Harry Feldt",
                        "position": "Fabrikschef"
                    }
                ],
                "establishment_year": 1946,
                "subsidiaries": [
                    "Lecab Rullbanor AB, Härryda",
                    "Svenska Elektriska Regulator AB, Västra Frölunda"
                ]
            },
            {
                "company_name": "EMBALLAGEINDUSTRI, AB",
                "pnr": "531 00",
                "address": "Lidköping, Lidbecksg 18",
                "phone_number": "0510-203 63",
                "bankgiro": "21-2117",
                "postgiro": "329431",
                "activity": "Tillverkar trycksaker. Specialitet: fraktsedlar, kartonger",
                "employees": 10,
                "capital": 15000,
                "key_personnel": [
                    {
                        "name": "Sam Odkvist",
                        "position": "Ägare o chefer"
                    },
                    {
                        "name": "Allan Olsson",
                        "position": "Ägare o chefer"
                    }
                ],
                "establishment_year": 1960
            },
            {
                "company_name": "EMBALLAGEPROVNINGS. LABORATORIET AB",
                "pnr": "12122",
                "address": "Johanneshov 1, Box 91, Hammarby Fabriksv 29-31",
                "phone_number": "08-44 00 30",
                "bankgiro": "613-5933",
                "postgiro": "402850-2",
                "activity": "Serviceorgan knutet till Svenska Förpackningsforskningsinstitutet. Företaget svarar för serviceverksamheten o utför provning av förpackningar o utveckling av systemlösningar där produkt, förpackning o transportled anpassas till varandra",
                "employees": 12,
                "annual_turnover": 710000,
                "capital": 25000,
                "key_personnel": [
                    {
                        "name": "Yngve Dagel",
                        "position": "Verkst dir"
                    },
                    {
                        "name": "Ing Sten Bervel",
                        "position": "Avd-chef"
                    }
                ],
                "establishment_year": 1954
            }
        ]
    }
}