{
    "original": "ISABERGS VERKSTADS AB\n\nPnr 330 27\n\nHestra. Tel 0370-352 60.\nTelex 70166\n\nVerksamhet: Tillverkar\nhäftappara-ter, elektr ringklockor o\nringledningstransformatorer\nAntal anstäUda: 190\nAktiekapital: 800 000\nVerkst dir: Simon Brick\nDisp: Olle Westlund\nEtableringsår: 1941.\n\nSVENSK FLOTTESERVICE\n\nPnr 402 71\n\nGöteborg 8, Box 8812. Tel 031-\n\n925478. Godsadress: östergärde\nIndustriområde. Bankgiro 10-7697.\nPostgiro 524471. Tga Flotteservice\nVerksamhet: Utför service å\nuppblåsbara livräddningsflottar,\nrepa-rerar all uppblåsbar\nräddningsma-teriel. Säljer livräddningsflottar o\ngummibåtar för fritidsbruk samt\nflytvästar\n\nVarunamn: Beaufort,\nDeutsche-Schlauchboot, Elliot, Viking-DSL\nÄgare o chef: Ing Torbjörn Flinck\nEtableringsår: 1958.\n\nLINDSTRüM.PLAST AB\n\nPnr 124 21\n\nBandhagen 1, Harpsundsv 164. Box\n53. Tel 08-99 25 10, 99 12 20.\nBankgiro 72-2420. Postgiro 454167.\nTga Lindstromplast\nVerksamhet: Tillverkar plastvaror\nAntal anställda: 8\nÅrsomsättning: 702 000\nÄgare o chef: Ing Alrik Lindström\nEtableringsår: 1950.\n\nBÄTVÅRDSAFFÄREN, AB\n\nPnr 423 00\n\nTorslanda, Hjuvik. Tel 031-9201 21,\n920635. Postgiro 429267-8\nVerksamhet: Handel med båtar,\nmotorer, tillbehör. Bensinstationer\nAntal anställda: 5\nÅrsomsättning: 1500 000\nAktiekapital: 100 000\nVerkst dir: S Hedberg\nEtableringsår: 1957.\n\nmannesmann-sverige ab\n\nPnr 112 65\n\nStockholm, Badstrandsv 28. Tel\n08-1318 40. Postgiro 453575-3.\nTelex 19106 MANNSTH S\nVerksamhet: Representerar\nMannes-mannkoncernens produkter av: stål;\nolegerat, låglegerat, rostfritt,\nnickel o nickellegeringar samt\ntitan o korrosionsbeständiga\ntitan-legeringar. Utförande: rör, plåt\näven prefabricerade o\nmanufakture-rade, smide, band, tråd.\nKomponenter för atom- o konventionella\nvärmekraftverk. Marina\nanläggningar\n\nAvdelningskontor: 411 01 Göteborg,\nFriggag 14. Tel 031-19 3145,\n19 3155\n\nAktiekapital: 100 000\nVerkst dir: Bertil Reichmann\nEtableringsår: 1949\nDotterbolag till Mannesmann-Export\nAG, Dusseldorf.\n\nmanomeco ab\n\nPnr 172 06\n\nSundbyberg 6, Starrbäcksg 24. Box\n645. Tel 08-29 6900. Bankgiro\n23-8745. Postgiro 644670\nVeiksamhet: Underhåll samt\nförsäljning av flyginstrument\nAntal anställda: 4\nÅrsomsättning: 400 000\nAktiekapital: 5 000\nVerkst dir: I Söderstedt\nEtableringsår: 1964.\n\nmantorps säg &amp;\nsnickerifabrik\n\nPnr 590 20\n\nMantorp, Box 36. Tel 0142-200 09,\n201 52. Postgiro 299552\nVeiksamhet: Sågar o förädlar\nvirke, säljer byggnadsmaterial\nAntal anställda: 15\nChef: Arne Ohlsson\nEtableringsår: 1915.\n\nADMI CENTER AB\n\nPnr 41110\n\nGöteborg C, O Hamng 17. Tel\n031-17 65 60. Bankgiro 50-6810.\nPostgiro 523334. Tga Admic\nVerksamhet: Fastighetsförvaltning\no kontorsservice\nAntal anställda: 9\nAktiekapital: 14 000\nVerkst dir: Civilekonom Claes A\nPalmers\n\nEtableringsår: 1964.\n\nADOLFI SNICKERIFABRIK,\nBRUDERNA\n\nPnr 690 50\n\nVretstorp, Box 220. Tel\n0582-60016, 606 80. Bankgiro 604-5702.\nPostgiro 26 93 2 8-1\nVerksamhet: Tillverkar o säljer\nbyggnads- o inredningssnickerier\nAntal anställda: 5\nÅrsomsättning: 450 000\nFirmatecknare: T G Adolfi,\nK L Adolfi.\n\nADOLFSSONS MEKANISKA\nVERKSTAD AB\n\nPnr 630 08\n\nEskilstuna 8, Box 8032.Frituna.\nTel 016-117050. Bankgiro\n601-3023. Postgiro 133727-8\nVerksamhet: Tillverkar\nexcenter-pressar, utför svetsning o\nmekaniska arbeten\nAktiekapital: 50 000\nVerkst dir: Fabr Henry Adolfsson\nEtableringsår: 1947.\n\nALVIKS GUMMI AB\n\nPnr 16146\n\nBromma, Registerv 38. Tel 08-\n\n25 28 40\n\nVerksamhet: Säljer däck o slangar\nm m. Utför regummeringar\nAntal anställda: 22\nÅrsomsättning: 7 000 000\nAktiekapital: 550000\nVerkst dir: Börje Johansson\nEtableringsår: 1929.\n\nJÄGER &amp; SON AB, W\n\nPnr 13104\n\nNacka 4, Vårbäcken 8. Box 4038.\nTel 08-71642 43. Tga Wiljaegers,\nStockholm. Telex 19121\nVerksamhet: Exporterar: skogsbär,\nhudar, trätjära o trämanufaktur\nAktiekapital: 50 000\nVerkst dir: Folke E Jäger\nEtableringsår: 1900.\n\nUPSALA SIDENVAVERIER, AB\n\nPnr 75103\n\nUppsala 1, Kungsg 66. Box 15. Tel\n018-13 97 30. Bankgiro 80-2137.\nPostgiro 23716. Tga Upsalasiden\nVerksamhet: Väveri o trikåindustri\nVarunamn: Gunilla\nAntal anställda: 70\nÅrsomsättning: 8 000 000\nAktiekapital: 1000 000\nVerkst dir: Folke Edlund\nEtableringsår: 1936.\n\nUPPSALA TRÄINDUSTRI\n\nPnr 75103\n\nUppsala 1, Kungsängsesplanaden\n9. Box 7. Tel 018-1203 30.\nBankgiro 23-0368. Postgiro 661954\nVerksamhet: Tillverkar\nmonteringsfärdiga trähus\nChef: Ingvar Pettersson\nEtableringsår: 1957.\n\nSVENSKA FRYSERIERNA, AB\n\nPnr 414 58\n\nGöteborg, Skärgårdsg. Tel\n031-1440 00, 1218 85. Bankgiro\n44-0624. Postgiro 41444. Tga\nFryserierna\n\nVerksamhet: Fryshusrörelse samt\nförsäljning av frysta livsmedel\nFilial: Smögen. Tel 0523-309 05\nAntal anställda: 60\nÅrsomsättning: 4 000 000\nAktiekapital: 1 273 200\nStyrelse: Prof Lennart Rönnmark\n(ordf), dir Ivar Hamdahl, fil dr\nPhilip Lindstedt\n\nVerkst dir: Fil dr Philip Lindstedt\nEtableringsår: 1917.\n\nSVENSKA FORPACKNINGS.\nFORSKNINGSINSTITUTET\n\nPnr 12122\n\nJohanneshov 1, Box 91. Hammarby\nFabriksv 29-31. Tel 08-44 00 30.\nBankgiro 613-5941. Postgiro\n355 660-2\n\nVerksamhet: Halvstatligt\nbransch-forskningsinstitut. Bedriver\nforskning o utbildning inom\nförpacknings- o transportområdet\nAntal anställda: 20\nÅrsomsättning: 1725 000\nVerkst dir: Yngve Dagel\nEtableringsår: 1954.\n\nSVENSKA FÖRVALTNINGS.\nKONTORET, AB\n\nPnr 180 10\n\nEneby berg, Västerängs v 6 B. Box\n4016. Tel 08-758 00 35. Postgiro\n193431\n\nVerksamhet: Bokföring, revision,\nfastighets- o affärsförmedling\nAntal anställda: 2\nÅrsomsättning: 100000\nAktiekapital: 12 000\nVerkst din Sten Rocksberg\nEtableringsår: 1942.\n\nSVENSKA GALANITE\nINDUSTRI AB\n\nPnr 240 21\n\nLöddeköpinge. Tel 046-392 80.\nBankgiro 870-2425. Postgiro\n147752-0\n\nVerksamhet: Tillverkar\nformspru-tade o formblåsta plastartiklar\naèu-som leksaker, artiklar för industrin\nsamt toalettartiklar\nAntal anställda: 100\nÅrsomsättning: 6 000 000\nÄgare o chefen Börje Hansen,\nLudvig Hawaleska\nEtableringsår 1949.\n\nSVENSKA GRANIT.\nINDUSTRI AB\n\nPnr 292 00\n\nKarlshamn, Hamng 12. Box 69. Tel\n0454-142 50. Postgiro 5431.\nTga Granitindustri\nVerksamhet: Tillverkar\nbyggnadssten, gravvårdar m fi arbeten i granit\nFörsäljningskontor: Stockholm.\nTel 08-20 82 40\nAktiekapital: 2 000 000\nVerkst dir: Stig Danielson\nEtableringsår: 1896\nDotterbolag till Investment AB\nSkansen Lejonet.\n\nSVENSKA GRUNDIG AB\n\nPnr 200 41\n\nMalmö 8, Box 8086. Nobelv 23.\nTel 040-92 20 10. Bankgiro\n722-4561. Postgiro 159360-7. Tga\nGrundig. Telex 32559\nVerksamhet: Försäljning o service\nav radio-TV-bandspelare,\nHifi-an-läggningar, dikteringssystem samt\nanaloga o digitala mätinstrument\nAvdelningskontor: Stockholm.\nBällstav 30-32, Box 20017, pa\n16120 Bromma 20. Tel 08-28 27 00\nGöteborg. Fröhusg 3. Box 2002, pa\n42102 Västra Frölunda 2. Tel\n031-45 03 10\n\nVarunamn: Grundig, Stenorette\nAntal anställda: 90\nÅrsomsättning: 38 500 000\nAktiekapital: 10 000 000\nStyrelse: Adv Kaj Sandart (ordf), dr\nEugen Widmaier, adv Erik Linders\nVerkst dir: Erik Tulländer\nV verkst dir. Hans Treder\nEtableringsår: 1962.",
    "structured": {
        "1": {
            "company_name": "ISABERGS VERKSTADS AB",
            "pnr": "330 27",
            "address": "Hestra",
            "phone_number": "0370-352 60",
            "activity": "Tillverkar häftapparater, elektriska ringklockor o ringledningstransformatorer",
            "employees": 190,
            "capital": 800000,
            "key_personnel": [
                {
                    "name": "Simon Brick",
                    "position": "Verkst dir"
                },
                {
                    "name": "Olle Westlund",
                    "position": "Disp"
                }
            ],
            "establishment_year": 1941
        },
        "2": {
            "company_name": "SVENSK FLOTTESERVICE",
            "pnr": "402 71",
            "address": "Göteborg 8, Box 8812, östergärde Industriområde",
            "phone_number": "031-925478",
            "bank_details": {
                "bankgiro": "10-7697",
                "postgiro": "524471"
            },
            "activity": "Utför service å uppblåsbara livräddningsflottar, reparerar all uppblåsbar räddningsmaterial. Säljer livräddningsflottar o gummibåtar för fritidsbruk samt flytvästar",
            "varunamn": "Beaufort, Deutsche-Schlauchboot, Elliot, Viking-DSL",
            "owners_and_directors": "Ing Torbjörn Flinck",
            "establishment_year": 1958
        },
        "3": {
            "company_name": "LINDSTRüM.PLAST AB",
            "pnr": "124 21",
            "address": "Bandhagen 1, Harpsundsv 164, Box 53",
            "phone_number": "08-99 25 10, 99 12 20",
            "bank_details": {
                "bankgiro": "72-2420",
                "postgiro": "454167"
            },
            "activity": "Tillverkar plastvaror",
            "employees": 8,
            "annual_turnover": 702000,
            "owners_and_directors": "Ing Alrik Lindström",
            "establishment_year": 1950
        },
        "4": {
            "company_name": "BÄTVÅRDSAFFÄREN, AB",
            "pnr": "423 00",
            "address": "Torslanda, Hjuvik",
            "phone_number": "031-9201 21, 920635",
            "postgiro": "429267-8",
            "activity": "Handel med båtar, motorer, tillbehör. Bensinstationer",
            "employees": 5,
            "annual_turnover": 1500000,
            "capital": 100000,
            "key_personnel": {
                "name": "S Hedberg",
                "position": "Verkst dir"
            },
            "establishment_year": 1957
        },
        "5": {
            "company_name": "mannesmann-sverige ab",
            "pnr": "112 65",
            "address": "Stockholm, Badstrandsv 28",
            "phone_number": "08-1318 40",
            "postgiro": "453575-3",
            "telex": "19106 MANNSTH S",
            "activity": "Representerar Mannesmannkoncernens produkter av: stål; olegat, låglegerat, rostfritt, nickel o nickellegeringar samt titan o korrosionsbeständiga titanlegeringar. Utförande: rör, plåt även prefabricerade o manufakturerade, smide, band, tråd. Komponenter för atom- o konventionella värmekraftverk. Marina anläggningar",
            "branch_office": {
                "address": "411 01 Göteborg, Friggag 14",
                "phone_number": "031-19 3145, 19 3155"
            },
            "capital": 100000,
            "key_personnel": {
                "name": "Bertil Reichmann",
                "position": "Verkst dir"
            },
            "establishment_year": 1949,
            "sub_company_of": "Mannesmann-Export AG, Dusseldorf"
        },
        "6": {
            "company_name": "manomeco ab",
            "pnr": "172 06",
            "address": "Sundbyberg 6, Starrbäcksg 24, Box 645",
            "phone_number": "08-29 6900",
            "bankgiro": "23-8745",
            "postgiro": "644670",
            "activity": "Underhåll samt försäljning av flyginstrument",
            "employees": 4,
            "annual_turnover": 400000,
            "capital": 5000,
            "key_personnel": {
                "name": "I Söderstedt",
                "position": "Verkst dir"
            },
            "establishment_year": 1964
        },
        "7": {
            "company_name": "mantorps säg & snickerifabrik",
            "pnr": "590 20",
            "address": "Mantorp, Box 36",
            "phone_number": "0142-200 09, 201 52",
            "postgiro": "299552",
            "activity": "Sågar o förädlar virke, säljer byggnadsmaterial",
            "employees": 15,
            "owner": "Arne Ohlsson",
            "establishment_year": 1915
        },
        "8": {
            "company_name": "ADMI CENTER AB",
            "pnr": "41110",
            "address": "Göteborg C, O Hamng 17",
            "phone_number": "031-17 65 60",
            "bankgiro": "50-6810",
            "postgiro": "523334",
            "activity": "Fastighetsförvaltning o kontorsservice",
            "employees": 9,
            "capital": 14000,
            "key_personnel": {
                "name": "Civilekonom Claes A Palmers",
                "position": "Verkst dir"
            },
            "establishment_year": 1964
        },
        "9": {
            "company_name": "ADOLFI SNICKERIFABRIK, BRUDERNA",
            "pnr": "690 50",
            "address": "Vretstorp, Box 220",
            "phone_number": "0582-60016, 606 80",
            "bankgiro": "604-5702",
            "postgiro": "26 93 2 8-1",
            "activity": "Tillverkar o säljer byggnads- o inredningssnickerier",
            "employees": 5,
            "annual_turnover": 450000
        },
        "10": {
            "company_name": "ADOLFSSONS MEKANISKA VERKSTAD AB",
            "pnr": "630 08",
            "address": "Eskilstuna 8, Box 8032, Frituna",
            "phone_number": "016-117050",
            "bankgiro": "601-3023",
            "postgiro": "133727-8",
            "activity": "Tillverkar excenterpressar, utför svetsning o mekaniska arbeten",
            "capital": 50000,
            "key_personnel": {
                "name": "Fabr Henry Adolfsson",
                "position": "Verkst dir"
            },
            "establishment_year": 1947
        },
        "11": {
            "company_name": "ALVIKS GUMMI AB",
            "pnr": "16146",
            "address": "Bromma, Registerv 38",
            "phone_number": "08-25 28 40",
            "activity": "Säljer däck o slangar m m. Utför regummeringar",
            "employees": 22,
            "annual_turnover": 7000000,
            "capital": 550000,
            "key_personnel": {
                "name": "Börje Johansson",
                "position": "Verkst dir"
            },
            "establishment_year": 1929
        },
        "12": {
            "company_name": "JÄGER & SON AB, W",
            "pnr": "13104",
            "address": "Nacka 4, Vårbäcken 8, Box 4038",
            "phone_number": "08-71642 43",
            "telex": "19121",
            "activity": "Exporterar: skogsbär, hudar, trätjära o trämanufaktur",
            "capital": 50000,
            "key_personnel": {
                "name": "Folke E Jäger",
                "position": "Verkst dir"
            },
            "establishment_year": 1900
        },
        "13": {
            "company_name": "UPSALA SIDENVAVERIER, AB",
            "pnr": "75103",
            "address": "Uppsala 1, Kungsg 66, Box 15",
            "phone_number": "018-13 97 30",
            "bankgiro": "80-2137",
            "postgiro": "23716",
            "activity": "Väveri o trikåindustri",
            "varunamn": "Gunilla",
            "employees": 70,
            "annual_turnover": 8000000,
            "capital": 1000000,
            "key_personnel": {
                "name": "Folke Edlund",
                "position": "Verkst dir"
            },
            "establishment_year": 1936
        },
        "14": {
            "company_name": "UPPSALA TRÄINDUSTRI",
            "pnr": "75103",
            "address": "Uppsala 1, Kungsängsesplanaden 9, Box 7",
            "phone_number": "018-1203 30",
            "bankgiro": "23-0368",
            "postgiro": "661954",
            "activity": "Tillverkar monteringsfärdiga trähus",
            "key_personnel": {
                "name": "Ingvar Pettersson",
                "position": "Chef"
            },
            "establishment_year": 1957
        },
        "15": {
            "company_name": "SVENSKA FRYSERIERNA, AB",
            "pnr": "414 58",
            "address": "Göteborg, Skärgårdsg",
            "phone_number": "031-1440 00, 1218 85",
            "bankgiro": "44-0624",
            "postgiro": "41444",
            "activity": "Fryshusrörelse samt försäljning av frysta livsmedel",
            "branch_office": {
                "address": "Smögen",
                "phone_number": "0523-309 05"
            },
            "employees": 60,
            "annual_turnover": 4000000,
            "capital": 1273200,
            "key_personnel": [
                {
                    "name": "Prof Lennart Rönnmark",
                    "position": "ordf"
                },
                {
                    "name": "Ivar Hamdahl",
                    "position": "dir"
                },
                {
                    "name": "Fil dr Philip Lindstedt",
                    "position": "Verkst dir"
                }
            ],
            "establishment_year": 1917
        },
        "16": {
            "company_name": "SVENSKA FORPACKNINGS. FORSKNINGSINSTITUTET",
            "pnr": "12122",
            "address": "Johanneshov 1, Box 91, Hammarby Fabriksv 29-31",
            "phone_number": "08-44 00 30",
            "bankgiro": "613-5941",
            "postgiro": "355 660-2",
            "activity": "Halvstatligt branschforskningsinstitut. Bedriver forskning o utbildning inom förpacknings- o transportområdet",
            "employees": 20,
            "annual_turnover": 1725000,
            "key_personnel": {
                "name": "Yngve Dagel",
                "position": "Verkst dir"
            },
            "establishment_year": 1954
        },
        "17": {
            "company_name": "SVENSKA FÖRVALTNINGS. KONTORET, AB",
            "pnr": "180 10",
            "address": "Eneby berg, Västerängs v 6 B, Box 4016",
            "phone_number": "08-758 00 35",
            "postgiro": "193431",
            "activity": "Bokföring, revision, fastighets- o affärsförmedling",
            "employees": 2,
            "annual_turnover": 100000,
            "capital": 12000,
            "key_personnel": {
                "name": "Sten Rocksberg",
                "position": "Verkst dir"
            },
            "establishment_year": 1942
        },
        "18": {
            "company_name": "SVENSKA GALANITE INDUSTRI AB",
            "pnr": "240 21",
            "address": "Löddeköpinge",
            "phone_number": "046-392 80",
            "bankgiro": "870-2425",
            "postgiro": "147752-0",
            "activity": "Tillverkar formsprutade o formblåsta plastartiklar samt leksaker, artiklar för industrin samt toalettartiklar",
            "employees": 100,
            "annual_turnover": 6000000,
            "owners_and_directors": "Börje Hansen, Ludvig Hawaleska",
            "establishment_year": 1949
        },
        "19": {
            "company_name": "SVENSKA GRANIT. INDUSTRI AB",
            "pnr": "292 00",
            "address": "Karlshamn, Hamng 12, Box 69",
            "phone_number": "0454-142 50",
            "postgiro": "5431",
            "activity": "Tillverkar byggnadssten, gravvårdar m fi arbeten i granit",
            "branch_office": {
                "address": "Stockholm",
                "phone_number": "08-20 82 40"
            },
            "capital": 2000000,
            "key_personnel": {
                "name": "Stig Danielson",
                "position": "Verkst dir"
            },
            "establishment_year": 1896,
            "sub_company_of": "Investment AB Skansen Lejonet"
        },
        "20": {
            "company_name": "SVENSKA GRUNDIG AB",
            "pnr": "200 41",
            "address": "Malmö 8, Box 8086, Nobelv 23",
            "phone_number": "040-92 20 10",
            "bankgiro": "722-4561",
            "postgiro": "159360-7",
            "activity": "Försäljning o service av radio-TV-bandspelare, Hifi-anläggningar, dikteringssystem samt analoga o digitala mätinstrument",
            "branch_offices": [
                {
                    "name": "Stockholm",
                    "address": "Bällstav 30-32, Box 20017, pa 16120 Bromma 20",
                    "phone_number": "08-28 27 00"
                },
                {
                    "name": "Göteborg",
                    "address": "Fröhusg 3, Box 2002, pa 42102 Västra Frölunda 2",
                    "phone_number": "031-45 03 10"
                }
            ],
            "varunamn": "Grundig, Stenorette",
            "employees": 90,
            "annual_turnover": 38500000,
            "capital": 10000000,
            "key_personnel": [
                {
                    "name": "Adv Kaj Sandart",
                    "position": "ordf"
                },
                {
                    "name": "Dr Eugen Widmaier",
                    "position": ""
                },
                {
                    "name": "Adv Erik Linders",
                    "position": ""
                },
                {
                    "name": "Erik Tulländer",
                    "position": "Verkst dir"
                },
                {
                    "name": "Hans Treder",
                    "position": "V verkst dir"
                }
            ],
            "establishment_year": 1962
        }
    }
}