{
    "original": "HJÄ\n\nAktiekapital: 90 000\nVerkst dir: Oscar Gabrielsson\nEtableringsår: 1937.\n\nFRANZÉN &amp; FRIED AB\n\nPnr 111 30\n\nStockholm, Skeppsbron 16. Tel\n08-20 58 92, 20 58 93. Postgiro 3090.\nTga Franzénbolaget, Oleum\nVerksamhet: Säljer kolonialvaror o\nkemikalier en gros\nAktiekapital: 500 000\nVerkst dir: Oscar Fried\nEtableringsår: 1926.\n\nFRANZÉNS\nPUTSSKIVE-FABRIK AB, BERTIL\n\nPnr 597 00\n\nÅtvidaberg, Timmerv 6. Tel\n0120-107 07. Bankgiro 13-2118. Postgiro\n341604\n\nVerksamhet: Tillverkar lappskivor,\nglänsskivor o specialskivor\nAntal anställda: 8\nÅrsomsättning: 250 000\n\nAktiekapital: 20 000\nVerkst dir; Bertil Franzén\nEtableringsår: 1948.\n\nDOVERBY&amp; ROSENBERG AB\n\nPnr 560 23\n\nBankeryd, Box 122. Sjöåkrav. Tel\n036-77180. Bankgiro 140-0175.\nPostgiro 378320-6.\nTelex 70178 DORAB S\nVerksamhet: Säljer\nkontorsmaterial, ritmateriel jämte viss egen\ntillverkning av kontors- o\nritmateriel\n\nKontor: Bankeryd, Sjöåkrav. Tel\n036-77180\n\nLager o expedition: Bankeryd,\nSjöåkrav. Tel 036-771 80\nVarunamn: Dorab\nAntal anställda: 33\nÅrsomsättning: 16 4 00 000\nAktiekapital: 10 000\nVerkst dir: Aston Doverby\nDir: Kurt Österlund\nEtableringsår: 1954.\n\nABECITA AB\n\nPnr 500 07\n\nBorås 7, Herrljungag. Box 1723.\nTel 033-1276 60, 1276 65.\nBankgiro 531-1741. Postgiro 81318-8.\nTga Abecita.\nTelex 36069 ABECITA S\nVerksamhet: Tillverkar o säljer\nkorsetter, gördlar, behå,\nunderkläder o nattdräkter\nVarunamn: Abecita, Peter Pan\nAntal anställda: 280\nÅrsomsättning: 18 000 000\nAktiekapital: 800 000\nVerkst dir: Rune Mattsson\nEkonomichef: Hans Almström\nExportchef: Sten Hellgren\nProd-chef: Stig Bergehall\nInköp: Roland Levinsson\nEtableringsår: 1932.\n\nekenäs glasbruk ab\n\nPnr 574 02\n\nVetlanda 2, Ekenässjön. Box 5.\nTel 0383-30018. Postgiro 231190.\nTga Glasbruket\n\nVerksamhet: Tillverkar servisglas,\nprydnadsglas, slipat o graverat\nAntal anställda: 45\nVerkst dir: Stig Bökmark\nEtableringsår: 1923.\n\nVEGA KONTORSARTIKLAR\n\nPnr 112 37\n\nStockholm, Pontonjärg 23. Tel\n08-514801. Bankgiro 73-3482.\nPostgiro 351463\n\nVerksamhet: Handel med\nkontorsvaror i engros\nChef: Köpman Gunnar Asp\nEtableringsår: 1948.\n\nHÄGGÅSTRANDS VÄVERI AB\n\nPnr 51104\n\nKinna 4, Box 4050. Tel\n0320-115 10. Bankgiro 43-4725.\nPostgiro 143436. Tga Decor\nVerksamhet: Tillverkar gardiner,\nmöbetyger o överkasttyger i\nmetervara samt färdigsydda gardinlufter\no sängöverkast\nAntal anställda: 80\nÅrsomsättning: 8 000 000\nAktiekapital: 125 000\nVerkst dir: Per G V Skoglund\nEtableringsår: 1938.\n\nENE\n\nAktiekapital: 35 000\n\nVerkst dir: Byggn-ing SBR Olof\n\nEmgård\n\nEtableringsår: 1950.\n\nCALVERT &amp; CO, AB\n\nPnr 401 10\n\nGöteborg 1, Fack. O Hamng 19. Tel\n031-172040. Bankgiro 420-0275.\nPostgiro 12074-1. Tga Calvert.\nTelex 20745\n\nCALVERT\n\nVerksamhet: Rör, armatur, sanitet,\nrostfritt, pannor, gallerdurk,\nångledningar, ventilationsanläggningar,\npumpar\n\nAvdelningskontor: Stockholm,\nJuno-hällsv 1. Tel 08-13 12 55. Tga\nCal-verto\n\nKarlstad 5, Box 5032. Tel\n054-1534 08\n\nMalmö. Persborgstorget 2 D. Tel\n040-2125 45\n\nVästerås, Kolv. Tel 021-18 26 40\nVarunamn: Bauer, CeCe, Copperad,\nFarval, Grundfos, Heart, Källan\n\nAntal anställda: 275\nAktiekapital: 1500 000\nStyrelse: Bankdir Arne Nilsson\n(ordf), dir Gustaf Nordén, dir Axel\nWeilenmann, godsägare Percy\nCalvert\n\nVerkst dir. E Abrahamsson\nEtableringsån 1878\nOmbildat till aktiebolag 1910.\n\nCAMECO AB\n\nPnr 180 10\n\nEnebyberg, Täbyv 71. Fack. Tel\n08-758 0180. Bankgiro 62-8707.\nPostgiro 11065. Tga Camedico\nVerksamhet: Sjukvårdsartiklar o\nengångsmaterial för sjukhus\nAntal anställda: 15\nChef: Hugo Castenfors\nEtableringsår: 1962\nOmbildat till aktiebolag 1968.\n\nCAMFIL AB\n\nPnr 150 13\n\nTrosa, Industrig 3. Tel\n0156-12680. Bankgiro 581-2078.\nPostgiro 703390-5.\nTelex 10980 CAMFIL S\nVerksamhet: Tillverkar luftfilter\nAntal anställda: 40\nÅrsomsättning: 8 000 000\nAktiekapital: 500 000\nVerkst dir: Gösta Larson\nEtableringsår: 1963.\n\nSTIGEN FABRIKS AB, FOLKE\n\nPnr 41120\n\nGöteborg, Hvitfeldtsg 14. Tel\n031-1775 75. Bankgiro 337-7371.\nPostgiro 422000-0. Tga Stigenkemi.\nTelex 21107 STIGEN S\nVerksamhet: Tillverkar\nytbehandlingskemikalier för bl a avfettning,\nfosfatering o elektrolytisk\nytbehandling\n\nLicenstillverkning för: M&amp;T\nCHEMICALS INC och PENNWALT CORP,\nUSA samt R. O. Hull &amp; Co, INC,\nUSA\n\nFabrik: Bohus. Tel 031-98 05 45\nAntal anstäUda: 25\nÅrsomsättning: 4 000000\nAktiekapital: 100000\nVerkst dir: Folke Stigen\nEtableringsår: 1915\nf Nordhs Fabriker, Partille.\n\nSTIGTOMTA SMIDES &amp; MEK\nVERKSTAD\n\nPnr 610 55\n\nStigtomta, Box 10. Tel 0155-270 82,\n275 02. Bankgiro 95-1061. Postgiro\n472967\n\nVerksamhet: Tillverkar\njordbruksredskap o snöplogar\nAntal anstäUda: 10\nÅrsomsättning: 600 000\nChef: Carl-Johan Carlsson\nEtableringsår: 1952.",
    "structured": {
        "1": {
            "company_name": "HJÄ",
            "capital": 90000,
            "key_personnel": [
                {
                    "name": "Oscar Gabrielsson",
                    "position": "Verkst dir"
                }
            ],
            "establishment_year": 1937
        },
        "2": {
            "company_name": "FRANZÉN & FRIED AB",
            "pnr": "111 30",
            "address": "Stockholm, Skeppsbron 16",
            "phone_number": "08-20 58 92, 20 58 93",
            "bank_details": {
                "postgiro": "3090"
            },
            "activity": "Säljer kolonialvaror o kemikalier en gros",
            "capital": 500000,
            "key_personnel": [
                {
                    "name": "Oscar Fried",
                    "position": "Verkst dir"
                }
            ],
            "establishment_year": 1926
        },
        "3": {
            "company_name": "FRANZÉNS PUTSSKIVE-FABRIK AB, BERTIL",
            "pnr": "597 00",
            "address": "Åtvidaberg, Timmerv 6",
            "phone_number": "0120-107 07",
            "bank_details": {
                "bankgiro": "13-2118"
            },
            "activity": "Tillverkar lappskivor, glänsskivor o specialskivor",
            "employees": 8,
            "annual_turnover": 250000,
            "capital": 20000,
            "key_personnel": [
                {
                    "name": "Bertil Franzén",
                    "position": "Verkst dir"
                }
            ],
            "establishment_year": 1948
        },
        "4": {
            "company_name": "DOVERBY & ROSENBERG AB",
            "pnr": "560 23",
            "address": "Bankeryd, Box 122, Sjöåkrav",
            "phone_number": "036-77180",
            "bank_details": {
                "bankgiro": "140-0175",
                "postgiro": "378320-6"
            },
            "activity": "Säljer kontorsmaterial, ritmateriel jämte viss egen tillverkning av kontors- o ritmateriel",
            "employees": 33,
            "annual_turnover": 16400000,
            "capital": 10000,
            "key_personnel": [
                {
                    "name": "Aston Doverby",
                    "position": "Verkst dir"
                },
                {
                    "name": "Kurt Österlund",
                    "position": "Dir"
                }
            ],
            "establishment_year": 1954
        },
        "5": {
            "company_name": "ABECITA AB",
            "pnr": "500 07",
            "address": "Borås 7, Herrljungag, Box 1723",
            "phone_number": "033-1276 60, 1276 65",
            "bank_details": {
                "bankgiro": "531-1741",
                "postgiro": "81318-8"
            },
            "activity": "Tillverkar o säljer korsetter, gördlar, behå, underkläder o nattdräkter",
            "employees": 280,
            "annual_turnover": 18000000,
            "capital": 800000,
            "key_personnel": [
                {
                    "name": "Rune Mattsson",
                    "position": "Verkst dir"
                },
                {
                    "name": "Hans Almström",
                    "position": "Ekonomichef"
                },
                {
                    "name": "Sten Hellgren",
                    "position": "Exportchef"
                },
                {
                    "name": "Stig Bergehall",
                    "position": "Prod-chef"
                },
                {
                    "name": "Roland Levinsson",
                    "position": "Inköp"
                }
            ],
            "establishment_year": 1932
        },
        "6": {
            "company_name": "ekenäs glasbruk ab",
            "pnr": "574 02",
            "address": "Vetlanda 2, Ekenässjön, Box 5",
            "phone_number": "0383-30018",
            "bank_details": {
                "postgiro": "231190"
            },
            "activity": "Tillverkar servisglas, prydnadsglas, slipat o graverat",
            "employees": 45,
            "key_personnel": [
                {
                    "name": "Stig Bökmark",
                    "position": "Verkst dir"
                }
            ],
            "establishment_year": 1923
        },
        "7": {
            "company_name": "VEGA KONTORSARTIKLAR",
            "pnr": "112 37",
            "address": "Stockholm, Pontonjärg 23",
            "phone_number": "08-514801",
            "bank_details": {
                "bankgiro": "73-3482",
                "postgiro": "351463"
            },
            "activity": "Handel med kontorsvaror i engros",
            "key_personnel": [
                {
                    "name": "Köpman Gunnar Asp",
                    "position": "Chef"
                }
            ],
            "establishment_year": 1948
        },
        "8": {
            "company_name": "HÄGGÅSTRANDS VÄVERI AB",
            "pnr": "51104",
            "address": "Kinna 4, Box 4050",
            "phone_number": "0320-115 10",
            "bank_details": {
                "bankgiro": "43-4725",
                "postgiro": "143436"
            },
            "activity": "Tillverkar gardiner, möbetyger o överkasttyger i metervara samt färdigsydda gardinlufter o sängöverkast",
            "employees": 80,
            "annual_turnover": 8000000,
            "capital": 125000,
            "key_personnel": [
                {
                    "name": "Per G V Skoglund",
                    "position": "Verkst dir"
                }
            ],
            "establishment_year": 1938
        }
    }
}