{
    "original": "BERGMAN ELKONSULT AB, R\n\nPnr 292 00\n\nKarlshamn, Regerings 56. Tel\n0454-110 97, 110 27. Bankgiro\n862-1765. Postgiro 27321-9\nVerksamhet: Konsulterande\nel-ingenjörer för industrier, kontor mm\n.Antal anställda: 6\nÅrsomsättning: 250 000\nVerkst dir: ing Ragnar Bergman\nEtableringsår: 1934.\n\nBAG\n\nBAGGE AB, PETER\n\nPnr 40121\n\nGöteborg 1, Drottningg 35. Box 105.\nTel 031-11 1935, 11 1937.\nBankgiro 847-7044. Tga Mascot\nVerksamhet: Importagentur,\nkolonialvaror, konserver\nAktiekapital: 10 000\nVerkst dir: Walter Svensson\nEtableringsår: 1895.\n\nCEDINA, AB\n\nPnr 703 54\n\nÖrebro, Malmg 14. Tel 019-111406.\nBankgiro 817-4948. Postgiro\n593620-8\n\nVerksamhet: Tillverkar mjuka dam-\n\no barnskor\n\nAntal anställda: 20\n\nÅrsomsättning: 1 200 000\n\nAktiekapital: 20 000\n\nVerkst dir: Herbert Lang\n\nEtableringsår: 1900.\n\nSCHAKT &amp; SPRÅNGNING, AB\n\nPnr 114 60\n\nStockholm, Linnég 75. Tel\n08-6703 80. Bankgiro 16-0619.\nPostgiro 352953\n\nVerksamhet Utför schaktnings- o\nbergsprängningsarbeten\nAntal anställda: 80\nÅrsomsättning: 12 000 000\nAktiekapital: 100 000\nVeikst dir Hilding Fredin\nEtableringsår: 1947.\n\nSCHAKTMASKINER I\nSTOCKHOLM AB\n\nPnr 172 37\n\nSundbyberg, Solvallav 34. Tel\n08-2902 50. Bankgiro 160-7738.\nPostgiro 26348-3\n\nVaksamhet\nGrävmaskinsuthyrning, entreprenader, sprängning\nAntal anställda: 120\nÅrsomsättning: 10 000000\nAktiekapital: 200000\nVerkst dir Helmer Ohlsson\nEtableringsår: 1945.\n\nOLGÉNS TRYCKERI AB\n\nPnr 172 30\n\nSundbyberg, Råstensg 4. Tel\n08-82 7910,28 06 56. Bankgiro\n237-1433. Postgiro 175275-7\nVerksamhet: Blankettryckeri\nAktiekapital: 5 000\nVeikst dir: Sven Olgén\nEtableringsår: 1957.\n\nMARKNADSPLANERING AB\n\nPnr 101 10\n\nStockholm 1, Fack. Rålambsv 7.\nTel 08-2239 00\n\n402 31 Göteborg, Box 7047. Första\nLångg 16. Tel 031-12 44 80\n203 1 3 Malmö 4, Box 4245. S Tullg\n4 A. Tel 040-714 00\nVerksamhet:\nMarknadsundersökningar, marknadsplanering,\nreklam-prövning\n\nEtableringsår: 1960.\n\ngylner, ab h\n\nPnr 684 01\n\nMunkfors 1, Box 88. Tel\n0563-giro 77017-2\n\n110 60. Bankgiro 108-4060.\nPost-Verksamhet: Bilhandel o\nbilverkstadsrörelse\nAntal anställda: 40\nAktiekapital: 300 000\nVerkst dir: Johan Svensson\nEtableringsår: 1922.\n\ngüntner ingenjorsbyrå\nb e östberg, p m\n\nPnr 112 35\n\nStockholm, Norr Mälarstrand 86.\nTel 08-5114 00, 5114 07. Bankgiro\n477-9336. Postgiro 602044-0\nVerksamhet: Hissar, telfrar o övriga\nlyftanordningar\nAntal anställda: 10\nÅrsomsättning: 500 000\nChef: Ing B E Ostberg\nEtableringsår: 1930.\n\ngyproc, ab\n\nIngår i Cementakoncernen\n\nPnr 201 10\n\nMalmö 1, Stormg 14. Fack. Tel\n040-761 20. Tga Gyproc.\nTelex 32327 GYPROC S\nVerksamhet: Tillverkar gipsskivor\nför invändig beklädnad av väggar\no tak\n\nFörsäljningskontor: 103 63\nStockholm 3. Kungsg 32. Box 3174. Tel\n08-24 33 60. Telex 17217 gyproc s\n411 09 Göteborg, O Hamng 52. Tel\n031-17 75 70. Telex 20855 gyproc s\nFabriker: 190 60 Bålsta. Tel\n0171-50410. Telex 40617 gyproc baalsta\n432 00 Varberg. Tel 0340-163 60.\nTelex 3465 gyproc varberg. Chef:\növering Ake Wiberg\nVarunamn: Gyproc\nAntal anställda: 400\nÅrsomsättning: 63 000 000\nAktiekapital: 18 000 000\nStyrelse: Dir Elam Tunhammar\n(ordf), dir Goofrey Flood, dir\nRichard S Jukes, ambassadör Sten\nLindh, dir Erwin de Shàrengrad,\ndir Sixten Herlin, dir Gunnar\nRosenborg\n\nVerkst dir: Erwin de Shàrengrad\nFörsäljn-chef: Olav Haavimb\nEtableringsår: 1955.\n\nA E SCANDINAVIA AB\n\nPnr 100 31\n\nStockholm 21, Sankt Eriksg 106.\nPack. Tel 08-34 02 30. Bankgiro\n575-7067. Postgiro 254557-2.\nTga Aescandinav. Telex 1829\nAktiekapital: 600 000\nStyrelse: Adv Arthur Boström (ordf),\nadv Ormonde Goldie, dir Ingemar\nJörnberger, mr G A Hepworth,\nmr J T Panks\n\nVerkst dir: Ingemar Jörnberger\nEtableringsår: 1934\n\nSe även Auto-Products AB.\n\nAFFÄRSBALANS EKOJURA AB\n\nPnr 21156\n\nMalmö, Kamrerg 19. Tel\n040-70915. Bankgiro 114-6307.\nPostgiro 638130-6\n\nVerksamhet: Revisions- o juridisk\nbyrå\n\nAntal anställda: 4\n\nAktiekapital: 10 000\nChefer: Revisor Gösta Kinman,\nherr Bo Törnblom\nEtableringsår: 1969.\n\nSCAN COIN AB\n\nPnr 200 13\n\nMalmö 27, Borrg 31. Box 27057.\nTel 040-18 06 45. Bankgiro\n455-5066. Postgiro 634047-5. Tga\nSwedcoin\n\nVerksamhet: Tillverkar o säljer\nmynträknings- o\nförpackningsmaskiner jämte elektroniska\nspecialutrustningar för varierande ändamål\nVarunamn: Scan Coin\nAntal anställda: 25\nÅrsomsättning: 4 000 000\n\nAktiekapital: 100 000\n\nVerkst dir: Civilekonom Knut Ti-\n\ndell\n\nEtableringsår: 1966.\n\nSCANALLOYS\nLEGERINGS-METALLER AB\n\nPnr 271 00\n\nYstad, Stortorget 6. Box 17. Tel\n0411-13 6 60. Bankgiro 411-2181.\nTga AUanbolag. Telex 32299\nVerksamhet: Försäljning av lege.\nringsmetaller för stålverk,\ngjuterier m fi\nAktiekapital: 5 000\nVerkst dir: Allan Nilsson\nEtableringsår: 1969.\n\nEHRNBERG PRODUKTER, AB\n\nPnr 272 01\n\nSimrishamn 1. Box 56. Järnvägsg\n10. Tel 0414-118 10. Tga\nEhrnberg-product. Telex 3355\nVerksamhet: Tillverkar Griffolyn\nvävfolie\n\nVarunamn: Griffolyn\nVerkst din Curt Bergqvist.\n\nEHRNBERG &amp; SONS\nLÄDERFABRIK, AB\n\nPnr 272 01\n\nSimrishamn 1, Box 56. Järnvägsg\n10. Tel 0414-118 10. Tga\nEhmbergs-läder. Telex 3355\n\nVerksamhet: Läder o syntetmaterial\nAntal anställda: 320\nÅrsomsättning: 30 000 000\nAktiekapital: 5 000 000\nVerkst dir: Curt Bergqvist\nEtableringsår: 1808.",
    "structured": {
        "1": {
            "company_name": "BERGMAN ELKONSULT AB",
            "activity": "Konsulterande el-ingenjörer för industrier, kontor mm",
            "establishment_year": 1934,
            "employees": 6,
            "annual_turnover": 250000,
            "key_personnel": [
                {
                    "name": "Ing Ragnar Bergman",
                    "position": "Verkst dir"
                }
            ]
        },
        "2": {
            "company_name": "BAGGE AB, PETER",
            "activity": "Importagentur, kolonialvaror, konserver",
            "establishment_year": 1895,
            "capital": 10000,
            "key_personnel": [
                {
                    "name": "Walter Svensson",
                    "position": "Verkst dir"
                }
            ]
        },
        "3": {
            "company_name": "CEDINA AB",
            "activity": "Tillverkar mjuka dam- o barnskor",
            "establishment_year": 1900,
            "employees": 20,
            "annual_turnover": 1200000,
            "capital": 20000,
            "key_personnel": [
                {
                    "name": "Herbert Lang",
                    "position": "Verkst dir"
                }
            ]
        },
        "4": {
            "company_name": "SCHAKT & SPRÅNGNING AB",
            "activity": "Utför schaktnings- o bergsprängningsarbeten",
            "establishment_year": 1947,
            "employees": 80,
            "annual_turnover": 12000000,
            "capital": 100000,
            "key_personnel": [
                {
                    "name": "Hilding Fredin",
                    "position": "Veikst dir"
                }
            ]
        },
        "5": {
            "company_name": "SCHAKTMASKINER I STOCKHOLM AB",
            "activity": "Grävmaskinsuthyrning, entreprenader, sprängning",
            "establishment_year": 1945,
            "employees": 120,
            "annual_turnover": 10000000,
            "capital": 200000,
            "key_personnel": [
                {
                    "name": "Helmer Ohlsson",
                    "position": "Verkst dir"
                }
            ]
        },
        "6": {
            "company_name": "OLGÉNS TRYCKERI AB",
            "activity": "Blankettryckeri",
            "establishment_year": 1957,
            "capital": 5000,
            "key_personnel": [
                {
                    "name": "Sven Olgén",
                    "position": "Veikst dir"
                }
            ]
        },
        "7": {
            "company_name": "MARKNADSPLANERING AB",
            "activity": "Marknadsundersökningar, marknadsplanering, reklam-prövning",
            "establishment_year": 1960
        },
        "8": {
            "company_name": "GYLNER AB H",
            "activity": "Bilhandel o bilverkstadsrörelse",
            "establishment_year": 1922,
            "employees": 40,
            "capital": 300000,
            "key_personnel": [
                {
                    "name": "Johan Svensson",
                    "position": "Verkst dir"
                }
            ]
        },
        "9": {
            "company_name": "GÜNTNER INGENJORSBYRÅ B E ÖSTBERG PM",
            "activity": "Hissar, telfrar o övriga lyftanordningar",
            "establishment_year": 1930,
            "employees": 10,
            "annual_turnover": 500000
        },
        "10": {
            "company_name": "GYPROC AB",
            "activity": "Tillverkar gipsskivor för invändig beklädnad av väggar o tak",
            "employees": 400,
            "annual_turnover": 63000000,
            "capital": 18000000,
            "key_personnel": [
                {
                    "name": "Erwin de Shàrengrad",
                    "position": "Verkst dir"
                },
                {
                    "name": "Olav Haavimb",
                    "position": "Försäljn-chef"
                }
            ],
            "establishment_year": 1955
        },
        "11": {
            "company_name": "A E SCANDINAVIA AB",
            "establishment_year": 1934,
            "capital": 600000,
            "key_personnel": [
                {
                    "name": "Adv Arthur Boström",
                    "position": "Styrelse ordförande"
                },
                {
                    "name": "Adv Ormonde Goldie",
                    "position": "Styrelse"
                },
                {
                    "name": "Ingemar Jörnberger",
                    "position": "Verkst dir"
                }
            ]
        },
        "12": {
            "company_name": "AFFÄRSBALANS EKOJURA AB",
            "activity": "Revisions- o juridisk byrå",
            "employees": 4,
            "capital": 10000,
            "key_personnel": [
                {
                    "name": "Revisor Gösta Kinman",
                    "position": "Chefer"
                },
                {
                    "name": "Bo Törnblom",
                    "position": "Chefer"
                }
            ],
            "establishment_year": 1969
        },
        "13": {
            "company_name": "SCAN COIN AB",
            "activity": "Tillverkar o säljer mynträknings- o förpackningsmaskiner jämte elektroniska specialutrustningar för varierande ändamål",
            "employees": 25,
            "annual_turnover": 4000000,
            "capital": 100000,
            "key_personnel": [
                {
                    "name": "Civilekonom Knut Tidell",
                    "position": "Verkst dir"
                }
            ],
            "establishment_year": 1966
        },
        "14": {
            "company_name": "SCANALLOYS LEGERINGS-METALLER AB",
            "activity": "Försäljning av legeringsmetaller för stålverk, gjuterier m fi",
            "capital": 5000,
            "key_personnel": [
                {
                    "name": "Allan Nilsson",
                    "position": "Verkst dir"
                }
            ],
            "establishment_year": 1969
        },
        "15": {
            "company_name": "EHRNBERG PRODUKTER AB",
            "activity": "Tillverkar Griffolyn vävfolie",
            "employees": null,
            "capital": null,
            "key_personnel": [
                {
                    "name": "Curt Bergqvist",
                    "position": "Verkst dir"
                }
            ],
            "establishment_year": null
        },
        "16": {
            "company_name": "EHRNBERG & SONS LÄDERFABRIK AB",
            "activity": "Läder o syntetmaterial",
            "employees": 320,
            "annual_turnover": 30000000,
            "capital": 5000000,
            "key_personnel": [
                {
                    "name": "Curt Bergqvist",
                    "position": "Verkst dir"
                }
            ],
            "establishment_year": 1808
        }
    }
}