{
    "original": "CANTEEN AB\n\nPnr 12612\n\nStockholm 42, Box 42016. Elektrav\n49. Tel 08-19 0410. Bankgiro\n744-4078. Postgiro 653630-1. Tga\nCan-teen. Telex 17761\n\nVerksamhet: Varudistribution o\nservering genom automater. Importerar\no säljer automater. Service i 42\nstäder. Se Inköpsregistret under\nförsä 1 j ningsautomat er\nVarunamn: Canteen\nAntal anställda: 55\nÅrsomsättning: 12 000 000\nAktiekapital: 500 000\nVerkst dir: Curt Harald Andréasson\nEtableringsår: 1957.\n\nBLOMQVIST AB, C L\n\nPnr 510 20\n\nFritsla. Tel 0320-705 80, 70043.\nBankgiro 54-2307. Postgiro 81278\nVerksamhet: Handvävnadsgarner\nalla slag\n\nAktiekapital: 100 000\nVerkst dir: Håkan Blomqvist\nEtableringsår: 1911.\n\nBLOMQVIST KONSULTERANDE\nINGENJORSBYRÅAB, EWE\n\nPnr 43133\n\nMölndal, Kråketorpsg 10 C. Tel\n031-871906. Bankgiro 106-0078.\nPostgiro 232476-2\nVerksamhet: Konsulterande\ningenjörsbyrå inom WS-teknik\nAntal anställda: 3\n\nAktiekapital: 5 000\n\nVerkst dir: Ing Ewe Blomqvist\n\nEtableringsår: 1968.\n\nBLOMQVIST\nPROJEKTERINGS-BYRÄ AB, FOLKE\n\nPnr 442 00\n\nKungälv, Gamla Brog 5. Tel\n0303-145 50, 145 51. Bankgiro 152-8702.\nPostgiro 628860-9\nVerksamhet: Projektering av\nbostadshus. Arkitekt- o\nbetongkonstruktioner\nAntal anställda: 4\nÅrsomsättning: 200 000\nAktiekapital: 10 000\nVerkst dir: Ing Folke Blomqvist\nEtableringsår: 1962.\n\nmalotta of sweden ab\n\nPnr 521 02\n\nFalköping 2, Box 225. Nils\nEric-sonsg 16. Tel 0515-134-60.\nBankgiro 547-7476. Postgiro\n642770-2\n\nVerksamhet: Tillverkar klänningar,\nrockar, nattlinnen o barnkläder\nAntal anställda: 150\nAktiekapital: 5 000\nVerkst dir: Stig Hjorth\nEtableringsår: 1965.\n\nKONTAKTOR AB\n\nPnr 17122\n\nSolna 1, Gårdsv 12. Box 1082. Tel\n08-730 03 85. Bankgiro 75-5234.\nPostgiro 369520\n\nVerksamhet: Elektromekanisk\ntillverkning: Manöver- o\nautomatikskåp, ställverk samt\nsvagströms-utrustningar. Mekanisk bearbetning\nsamt lackering. Reparations- o\nservicearbeten\nAntal anställda: 30\nÅrsomsättning: 3 000 000\nAktiekapital: 30 000\nStyrelse: Verkstadschef Lars-Ake\nEricsson (ordf), dir Sonny\nGranholm, servicechef Thor Nyberg\nVerkst dir: Sonny Granholm\nEtableringsår: 1967.\n\nBELLA KONFEKTIONS AB\n\nPnr 20038\n\nMalmö 18, Box 18007. Baskemölleg\n3 E. Tel 040-378 01, 357 68.\nBankgiro 87-5152. Postgiro 245360\nVerksamhet: Tillverkar barnkläder\nAntal anställda: 12\nÅrsomsättning: 550 000\nAktiekapital: 20 000\nVeikst dir: Fru Lorenz Gross\nEtableringsår: 1961.\n\nTRÄEMBALLAGE\n\nPnr 33100\n\nVärnamo, Halmstadsv. Tel\n0370-107 63, 13213. Bankgiro 29-1762.\nPostgiro 387840\n\nVerksamhet: Tillverkar lådämnen\no trälådor, staketribb, lastpallarmm\nÄgare o chef: Fabr Arvid Gisleborn.\n\nTRÄEXPORTEN I NORR.\nKÖPING AB\n\nPnr 60102\n\nNorrköping 1, Trädgårdsg 38. Box\n48. Tel 011-16 68 20, 16 6 8 21.\nBankgiro 61-0048. Postgiro 26000.\nTelex 64037. Tga Neab\nVerksamhet: Trävaruexport\nAktiekapital: 80 000\nVerkst dir: Anders Davidson\nEtableringsån 1957.\n\nTRÄFFS SMIDES- &amp; MEK\nVERKSTAD AB\n\nPnr 662 00\n\nAmål, Karlstadsv 30. Tel\n0532-105 89. Bankgiro 11-6778.\nPost-giro 287479-0\n\nVerksamhet: Flak- o\ntimmerbyggnationer. Lastbankar\n\nAntal anställda: 9\nÅrsomsättning: 500 000\nAktiekapital: 100 000\nVerkst dir: Elis Träff\nEtableringsår: 1917.\n\nL A B SKRIVBYRÅ AB\n\nPnr 111 34\n\nStockholm, Sveav 25-27. Tel\n08-24 57 55, 21 82 30. Bankgiro\n168-7201. Postgiro 58735-2. Tga\nLab-skriv\n\nVerksamhet: Skrivbyrå med\nfullständig kontorsservice\nAntal anställda: 79\nÅrsomsättning: 2 900000\nAktiekapital: 30 000\nVerkst dir: Ebba Giesecke\nEtableringsår: 1954.\n\nBROMAN &amp; CO, AB J R\n\nPnr 104 60\n\nStockholm 20, Fack. Hammarby\nFabriksv 23. Tel 08-440210.\nBankgiro 166-5090. Postgiro 183-4. Tga\nReinholdus\n\nVerksamhet:\nGrosshandelsförsäljning av industriförnödenheter\nVarunamn: Bells, Sia, Teflon\nAktiekapital: 350 000\nVerkst dir: Astor Lindsjöö\nEtableringsår: 1881.\n\nflens byggnads ab\n\nPnr 642 00\n\nFlen, Götg 1. Box 10. Tel\n0157-122 70. Bankgiro 61-5806.\nPostgiro 493499\n\nVerksamhet: Byggnadsrörelse\nAntal anställda: 200\nÅrsomsättning: 15000 000\nAktiekapital: 50 000\nFirmatecknare: Hans Pettersson,\nPaul Israelsson\nEtableringsår: 1955.\n\nMEWA, HANDELSFIRMAN\n\nPnr 413 01\n\nGöteborg, Järntorgsg 12-14. Tel\n031-117680, 11 1246. Bankgiro\n337-4626. Postgiro 44019-8. Tga\nMewa\n\nVerksamhet: Kameyama ljus o\npresentartiklar en gros\nAntal anställda: 6\nÅrsomsättning: 1200 000\nChef: Stig Einar Pettersson\nEtableringsår: 1931.\n\nMEVA\n\nMOTOR ELEKTRISKA\nVERKSTADS AB\n\nPnr 931 01\n\nSkellefteå 1, Box 9. Kustv 21. Tel\n0910-142 00. Bankgiro 764-0600.\nPostgiro 66297-3. Tga Meva\nVerksamhet: Elektromekanisk\nverkstad. Tillverkar bl a kombinerade\nelektr slip- o smärgelmaskiner,\nom-lindningar o reparationer av alla\nslags el-maskiner. Säljer\nel-maski-ner o tillbehör, nytt o begagnat.\nUthyrning av el-maskiner, elverk etc\n\nFilial: Umeå 5, Box 5015. Tel\n090-1114 10\n\nVerkst dir: Arvid Wahlberg\nEtableringsår: 1943.",
    "structured": {
        "1": {
            "company_name": "CANTEEN AB",
            "pnr": "12612",
            "address": "Stockholm 42, Box 42016. Elektrav 49",
            "phone_number": "08-19 0410",
            "bank_details": {
                "bankgiro": "744-4078",
                "postgiro": "653630-1"
            },
            "activity": "Varudistribution o servering genom automater. Importerar o säljer automater. Service i 42 städer. Se Inköpsregistret under försä 1 j ningsautomat er.",
            "employees": 55,
            "annual_turnover": 12000000,
            "capital": 500000,
            "key_personnel": [
                {
                    "name": "Curt Harald Andréasson",
                    "position": "Verkst dir"
                }
            ],
            "establishment_year": 1957
        },
        "2": {
            "company_name": "BLOMQVIST AB, C L",
            "pnr": "510 20",
            "address": "Fritsla",
            "phone_number": "0320-705 80, 70043",
            "bank_details": {
                "bankgiro": "54-2307",
                "postgiro": "81278"
            },
            "activity": "Handvävnadsgarner alla slag",
            "capital": 100000,
            "key_personnel": [
                {
                    "name": "Håkan Blomqvist",
                    "position": "Verkst dir"
                }
            ],
            "establishment_year": 1911
        },
        "3": {
            "company_name": "BLOMQVIST KONSULTERANDE INGENJORSBYRÅAB, EWE",
            "pnr": "43133",
            "address": "Mölndal, Kråketorpsg 10 C",
            "phone_number": "031-871906",
            "bank_details": {
                "bankgiro": "106-0078",
                "postgiro": "232476-2"
            },
            "activity": "Konsulterande ingenjörsbyrå inom WS-teknik",
            "employees": 3,
            "capital": 5000,
            "key_personnel": [
                {
                    "name": "Ing Ewe Blomqvist",
                    "position": "Verkst dir"
                }
            ],
            "establishment_year": 1968
        },
        "4": {
            "company_name": "BLOMQVIST PROJEKTERINGS-BYRÄ AB, FOLKE",
            "pnr": "442 00",
            "address": "Kungälv, Gamla Brog 5",
            "phone_number": "0303-145 50, 145 51",
            "bank_details": {
                "bankgiro": "152-8702",
                "postgiro": "628860-9"
            },
            "activity": "Projektering av bostadshus. Arkitekt- o betongkonstruktioner",
            "employees": 4,
            "annual_turnover": 200000,
            "capital": 10000,
            "key_personnel": [
                {
                    "name": "Ing Folke Blomqvist",
                    "position": "Verkst dir"
                }
            ],
            "establishment_year": 1962
        },
        "5": {
            "company_name": "malotta of sweden ab",
            "pnr": "521 02",
            "address": "Falköping 2, Box 225, Nils Eric-sonsg 16",
            "phone_number": "0515-134-60",
            "bank_details": {
                "bankgiro": "547-7476",
                "postgiro": "642770-2"
            },
            "activity": "Tillverkar klänningar, rockar, nattlinnen o barnkläder",
            "employees": 150,
            "capital": 5000,
            "key_personnel": [
                {
                    "name": "Stig Hjorth",
                    "position": "Verkst dir"
                }
            ],
            "establishment_year": 1965
        },
        "6": {
            "company_name": "KONTAKTOR AB",
            "pnr": "17122",
            "address": "Solna 1, Gårdsv 12, Box 1082",
            "phone_number": "08-730 03 85",
            "bank_details": {
                "bankgiro": "75-5234",
                "postgiro": "369520"
            },
            "activity": "Elektromekanisk tillverkning: Manöver- o automatikskåp, ställverk samt svagströms-utrustningar. Mekanisk bearbetning samt lackering. Reparations- o servicearbeten",
            "employees": 30,
            "annual_turnover": 3000000,
            "capital": 30000,
            "key_personnel": [
                {
                    "name": "Lars-Ake Ericsson",
                    "position": "Verkstadschef (ordf)"
                },
                {
                    "name": "Sonny Granholm",
                    "position": "dir"
                },
                {
                    "name": "Thor Nyberg",
                    "position": "servicechef"
                }
            ],
            "establishment_year": 1967
        },
        "7": {
            "company_name": "BELLA KONFEKTIONS AB",
            "pnr": "20038",
            "address": "Malmö 18, Box 18007, Baskemölleg 3 E",
            "phone_number": "040-378 01, 357 68",
            "bank_details": {
                "bankgiro": "87-5152",
                "postgiro": "245360"
            },
            "activity": "Tillverkar barnkläder",
            "employees": 12,
            "annual_turnover": 550000,
            "capital": 20000,
            "key_personnel": [
                {
                    "name": "Fru Lorenz Gross",
                    "position": "Veikst dir"
                }
            ],
            "establishment_year": 1961
        },
        "8": {
            "company_name": "TRÄEMBALLAGE",
            "pnr": "33100",
            "address": "Värnamo, Halmstadsv",
            "phone_number": "0370-107 63, 13213",
            "bank_details": {
                "bankgiro": "29-1762",
                "postgiro": "387840"
            },
            "activity": "Tillverkar lådämnen o trälådor, staketribb, lastpallarmm",
            "key_personnel": [
                {
                    "name": "Fabr Arvid Gisleborn",
                    "position": "chef"
                }
            ]
        },
        "9": {
            "company_name": "TRÄEXPORTEN I NORR. KÖPING AB",
            "pnr": "60102",
            "address": "Norrköping 1, Trädgårdsg 38, Box 48",
            "phone_number": "011-16 68 20, 16 6 8 21",
            "bank_details": {
                "bankgiro": "61-0048",
                "postgiro": "26000"
            },
            "activity": "Trävaruexport",
            "capital": 80000,
            "key_personnel": [
                {
                    "name": "Anders Davidson",
                    "position": "Verkst dir"
                }
            ],
            "establishment_year": 1957
        },
        "10": {
            "company_name": "TRÄFFS SMIDES- & MEK VERKSTAD AB",
            "pnr": "662 00",
            "address": "Amål, Karlstadsv 30",
            "phone_number": "0532-105 89",
            "bank_details": {
                "bankgiro": "11-6778",
                "postgiro": "287479-0"
            },
            "activity": "Flak- o timmerbyggnationer. Lastbankar",
            "employees": 9,
            "annual_turnover": 500000,
            "capital": 100000,
            "key_personnel": [
                {
                    "name": "Elis Träff",
                    "position": "Verkst dir"
                }
            ],
            "establishment_year": 1917
        },
        "11": {
            "company_name": "L A B SKRIVBYRÅ AB",
            "pnr": "111 34",
            "address": "Stockholm, Sveav 25-27",
            "phone_number": "08-24 57 55, 21 82 30",
            "bank_details": {
                "bankgiro": "168-7201",
                "postgiro": "58735-2"
            },
            "activity": "Skrivbyrå med fullständig kontorsservice",
            "employees": 79,
            "annual_turnover": 2900000,
            "capital": 30000,
            "key_personnel": [
                {
                    "name": "Ebba Giesecke",
                    "position": "Verkst dir"
                }
            ],
            "establishment_year": 1954
        },
        "12": {
            "company_name": "BROMAN & CO, AB J R",
            "pnr": "104 60",
            "address": "Stockholm 20, Fack. Hammarby Fabriksv 23",
            "phone_number": "08-440210",
            "bank_details": {
                "bankgiro": "166-5090",
                "postgiro": "183-4"
            },
            "activity": "Grosshandelsförsäljning av industriförnödenheter",
            "employees": 200,
            "annual_turnover": 15000000,
            "capital": 350000,
            "key_personnel": [
                {
                    "name": "Astor Lindsjöö",
                    "position": "Verkst dir"
                }
            ],
            "establishment_year": 1881
        },
        "13": {
            "company_name": "flens byggnads ab",
            "pnr": "642 00",
            "address": "Flen, Götg 1, Box 10",
            "phone_number": "0157-122 70",
            "bank_details": {
                "bankgiro": "61-5806",
                "postgiro": "493499"
            },
            "activity": "Byggnadsrörelse",
            "employees": 200,
            "annual_turnover": 15000000,
            "capital": 50000,
            "key_personnel": [
                {
                    "name": "Hans Pettersson",
                    "position": "Firmatecknare"
                },
                {
                    "name": "Paul Israelsson",
                    "position": "Firmatecknare"
                }
            ],
            "establishment_year": 1955
        },
        "14": {
            "company_name": "MEWA, HANDELSFIRMAN",
            "pnr": "413 01",
            "address": "Göteborg, Järntorgsg 12-14",
            "phone_number": "031-117680, 11 1246",
            "bank_details": {
                "bankgiro": "337-4626",
                "postgiro": "44019-8"
            },
            "activity": "Kameyama ljus o presentartiklar en gros",
            "employees": 6,
            "annual_turnover": 1200000,
            "key_personnel": [
                {
                    "name": "Stig Einar Pettersson",
                    "position": "Chef"
                }
            ],
            "establishment_year": 1931
        },
        "15": {
            "company_name": "MEVA MOTOR ELEKTRISKA VERKSTADS AB",
            "pnr": "931 01",
            "address": "Skellefteå 1, Box 9, Kustv 21",
            "phone_number": "0910-142 00",
            "bank_details": {
                "bankgiro": "764-0600",
                "postgiro": "66297-3"
            },
            "activity": "Elektromekanisk verkstad. Tillverkar bl a kombinerade elektr slip- o smärgelmaskiner, om-lindningar o reparationer av alla slags el-maskiner. Säljer el-maski-ner o tillbehör, nytt o begagnat. Uthyrning av el-maskiner, elverk etc",
            "branch_office": {
                "location": "Umeå 5, Box 5015",
                "phone_number": "090-1114 10"
            },
            "key_personnel": [
                {
                    "name": "Arvid Wahlberg",
                    "position": "Verkst dir"
                }
            ],
            "establishment_year": 1943
        }
    }
}