{
    "original": "ANTICIMEX AB\n\nPnr 10110\n\nStockholm 1, Vasag 46. Fack. Tel\n08-2315 60. Tga Anticimex\nVerksamhet: Riksorganisation för\nskadedjurs bekämpning\nAntal anställda: 440\nÅrsomsättning: 21000 000\nAktiekapital: 640 000\nVerkst dir: Olof Strid\nEtableringsår: 1934.\n\nANTICIMEX\nHUSBOCKS-FURSÄKRINGS AB\n\nPnr 101 10\n\nStockholm 1, Vasag 46. Fack. Tel\n08-23 15 60\n\nVerksamhet: Husbocksforsäkring\nAntal anställda: 440\nÅrsomsättning: 2 930 000\nAktiekapital: 100 000\nVerkst dir: Olof Strid\nEtableringsår: 1953.\n\nANTONSON-AV E RY AB\n\nPnr 42122\n\nVästra Frölunda 1, Box 126. Tel\n031-45 02 00. Tga Avery. Telex 2287\nVerksamhet: Självhäftande\netiketter, etiketteringsmaskiner o\n-an-läggningar, prismärkningsmaskiner\nFilial: Stockholm SV, Nybohovs\ngränd 46. Tel 08-18 82 20\nAntal anställda: 329\nÅrsomsättning: 35 055 000\nVerkst dir: Magnus Antonson\nEtableringsår: 1894\nOmbildat till aktiebolag 1961.\nDotterbolag till Avery Products\nCorp, USA.\n\nAO.S METALL &amp; MEK\nVERKSTAD AB\n\nPnr 113 53\n\nStockholm, Tuleg 15. Tel 08-\n\n34 24 00. Bankgiro 483-5476.\nPostgiro 253701-7\n\nVerksamhet: Utför\nexperimentarbeten\n\nAktiekapital: 50 000\nFirmatecknare: E Ohlson\nEtableringsår: 1945.\n\nOREBRO METALLFABRIK\n\nPnr 702 15\n\nÖrebro, Pappersbruksallén 3. Tel\n019-1134 79. Postgiro 92876\nVerksamhet: Tillverkar\nmetallrör-delar, sanitetsarmatur, koncentriska\nförbindningar för elektr industrin.\nOriginal Bergs anborrningsapparat\nmed reservdelar\nÄgare o chef: Fabr Lennart\nAndersson\n\nEtableringsår: 1930.\n\nOREBRO\nMURBRUKSFABRIK AB\n\nPnr 702 27\n\nÖrebro, Lundstorpsv 14. Tel\n019-1107 78, 112778. Bankgiro\n463-3640. Postgiro 161003-9\nVerksamhet: Tillverkar murbruk.\nSäljer grus\nAntal anställda: 10\nÅrsomsättning: 1300 000\n\nAktiekapital: 50 000\nDisp: Olle Collgård\nEtableringsår 1955.\n\nOREBRO NYA MÖBEL.\nFABRIK, AB\n\nPnr 70103\n\nÖrebro 1, Slöjdg 29. Box 345. Tel\n019-11 18 67. 1193 80. Postgiro\n30332\n\nVerksamhet: Tillverkar butiks- o\nlagerinredningar\nAntal anställda: 12\nÅrsomsättning: 1300 000\nAktiekapital: 72 000\nEtableringsår: 1919.\n\nMÅL\n\nHärdad o slipad bilbult, axlar o\nliknande, svarvade detaljer,\ninduk-tionshärdning\nBÄCKEFORS BRUKS AB,\n660 06 Bäckefors, Box 51. Tel\n0530-603 60. Tga Jomustad\nStuk- o hejarsmidda artiklar,\nplåt-o svetsningsarbeten\nSELLWING AB, 544 00 Hjo, Box\n100. Tel 0503-11125. Tga\nJomustad\n\nPasta o rörliga exponeringsställ\nför fackhandeln\nMUST AD STALPRESS AB,\n544 00 Hjo, Box 100. Tel\n0503-111 25. Tga Jomustad\nHUSKVARNA STALPRESS AB\n56100 Huskvarna, Box 72. Tel\n036-1327 50\n\nPressnings- o svetsningsarbeten i\nrostfritt o svartplåt,\ntoalettlås-automat\n\nPRIMULATOR AB, Göteborg,\nKro-kegårdsg 5. Box 40, 40120 Gbg 1.\nTel 031-51 36 50. Tga Jomustad\nHandelsautomater, öl- o\nläskedrycksdispenser, automatservering.\n\nMUSTAD &amp; SON, AB O\n\nse Mustad AB, J\n\nMUSTADFORS BRUKS AB\n\nPnr 66010\n\nDals Långed, Box 10. Tel\n0531-410 10. Postgiro 620954-8.\nTga Horsenail, Trollhättan\nVerksamhet: Export o försäljning\nav söm, brodd, båtspik, extra nubb,\nspridningsaggregat för konstgödsel\no vägsalt, maskiner för\npappersindustrin\n\nAntal anställda: 140\nÅrsomsättning: 8 000000\nAktiekapital: 1200 000\nStyrelse: Bankdir Nils Ljungdahl,\ning Krister Mustad, dir Knut\nAars-rud\n\nVerkst din Arne Börjesson\nEtableringsår: 1961.\n\nMUSTANGFABRIKEN AB\nTRELLEBORGS\nVELOCIPED-FABRIK\n\nPnr 23100\n\nTrelleborg,\nJärnvägsg33.Tel0410-154 60. Bankgiro 66-5911. Postgiro\n30468. Tga Mustangfabriken\nVerksamhet: Tillverkar cyklar o\nmopeder\n\nVarunamn: Mustang\nAktiekapital: 125 000\nVerkst dir: Gunnar Liljeberg\nEtableringsår: 1940.\n\nDIEDEN &amp; CO, AB HERBERT\n\nPnr 201 20\n\nMalmö 1, Hamng 4. Box 37. Tel\n040-708 50. Bankgiro 640-0915.\nPostgiro 24580-3. Tga Hedco.\nTelex 32660\n\nVerksamhet: Import av textilier,\nskor, porslin, korta varor m m från\nfjärran östern\n\nAvdelningskontor: 103 85 Stockholm\n7, Mäster Samuelsg 10. Box 7274.\nTel 08-203161\nAntal anställda: 30\nAktiekapital: 600 000\nVerkst dir: Iwe Herlin\nEtableringsår: 1925.\n\nBURE AB\n\nPnr 93015\n\nBureå. Tel 0910-403 50. Bankgiro\n204-0178. Postgiro 61656-5. Tga\nBurebolag, Skellefteå. Telex 6884\nVerksamhet: Tillverkar trävaror,\nblekt o oblekt torr slipmassa\nAntal anställda: 360\nÅrsomsättning: 44 000 000\nAktiekapital: 5 400 000\nVerkst dir: Bengt Lyberg\nPlatschef: Johannes Larson\nEtableringsår: 1796\nÄgare: Mo och Domsjö AB.\n\nBUREAU VERITAS\n\nPnr 41121\n\nGöteborg, Stora Badhusg 20. Tel\n031-1134 44, 13 6878. Bankgiro\n51-1623. Postgiro 422385. Tga Veritas\nVerksamhet: Bureau Veritas, som\nhar sitt huvudkontor i Paris, är ett\ninternationellt\nklassificeringssällskap för klassificering av fartyg o\nflygplan samt utövar kontroll av\nmaterial, maskiner etc\nAvdelningskontor: Stockholm.\nVik-stensg 55, pa 121.56 Johanneshov.\nTel 08-49 47 73\n\n21420 Malmö, S Förstadsg 102. Tel\n040-19 36 60\n\nSverigechef: Civiling Lennart\nNilsson\n\nEtableringsår: 1828.\n\nTHERMIA.ARMATUR, AB\n\nPnr 73101\n\nKöping 1, O Långg 34. Box 98.\nTel 0221-136 30. Tga\nThermiaarma-tur\n\nVerksamhet: Tillverkar\nsanitets-armatur, avstängningsventiler o\nradiatorventiler\n\nFörsäljningskontor: Stockholm 7,\nBirger Jarlsg 15. Tel 08-23 17 20\nVarunamn: Thermiaarmatur\nAntal anställda: 50\nÅrsomsättning: 5 000 000\nAktiekapital: 300 000\nStyrelse: Bruksdisp Lars Degefors\n(ordf), dir Axel Hedberg, dir Lars\nEggert, adv Ola Ellwyn, dir Sven\nWidemar, bankdir Olof Erlandson\nVerkst dir. Axel Hedberg\nEtableringsår: 1920\nOmbildat till aktiebolag 1941.\nFöretaget anslutet till Thermiar\nGruppen.\n\nTHERMIA-VERKEN, AB och\nTHERMIA.VERKENS FOR.\nSÄLJNINGS AB\n\nPnr 671 01\n\nArvika 1, Box 150. Tel 0570-130 50.\nTelex 5753. Tga Thermia\nVerksamhet: Tillverkar o säljer\nvarmvattenberedare,\nelvattenvär-mare, värmetransformatorer,\nvärmeväxlare, elpannor, torkskåp,\nexpansionskärl för slutet system,\nkul-vertisolering. reningsanläggningar\nför bad. Säljer AB Thermia-Armar\nturs tillverkningar av\nKRM-radiator-ventiler. enhandsblandare,\nautomatiska avluftningsventiler m m\nFörsäljningskontor: Stockholm 7,\nBirger Jarlsg 15. Tel 08-23 17 20\nGöteborg C, Lasarettsg 1. Tel\n031-17 10 70\n\nSundsvall 1. Kyrkog 21. Tel\n060-117810\n\nVarunamn: Thermia\nAntal anställda: 400\nÅrsomsättning: 33 000 000\nAktiekapital: 800000 resp 150 000\nStyrelse: Bruksdisp Lars Degefors\n(ordf), dir Axel Hedberg, dir Lars\nEggert, adv Ola Ellwyn, dir Sven\nWidemar, bankdir Olof Erlandson\nVerkst dir. Axel Hedberg\nInköpschef: Rune Johansson\nEtableringsår: 1923\nÄger: AB Thermia-Armatur, Köping.\n\nTERMIT, MASKIN AB\n\nPnr 780 51\n\nDala-Jäma. Tel 0281-205 50.\nBankgiro 46-5808. Postgiro 299650-2\nVerksamhet: Tillverkar\nbetongva-rumaskiner, luftcylindrar o\nlyftverktyg\n\nAntal anställda: 35\nÅrsomsättning: 3 000 000\nAktiekapital: 200000\nVerkst dir: Bengt Henriksson.\n\nTHERMO ROR AB\n\nPnr 35104\n\nVäxjö 1. Box 85. Linnëg 6 A. Tel\n0470-220 30. Bankgiro 146-4015.\nPostgiro 176542-9\nVerksamhet:\nRörledningsentreprenörer\n\nAntal anställda: 35\nÅrsomsättning: 3 500 000\nAktiekapital: 30 000\n\nStyrelse: Ing Låge Hedenfalk,\nfru Gertrud Hedenfalk\nVeikst dir: Låge Hedenfalk\nIngenjör Sven-Olov Olsson\nEtableringsår: 1938.\n\nALBERTS INDUSTRIER AB\n\nPnr 543 01\n\nTibro 1, Box 7. Tel 0504-116 30.\nTga Albertmöbel\n\nVerksamhet: Tillverkar möbler samt\nprodukter i fanerväv\nAntal anställda: 80\nÅrsomsättning: 6 000 000\nAktiekapital: 250 000\nVerkst din Albert Larsson.\n\nALBERTS KONFEKTIONS AB\n\nPnr 500 03\n\nBorås 3, Elinsdalsg 8. Box 1311.\nTel 033-13 2847, 12 08 59. Bankgiro\n531-6054. Postgiro 361312-2\n\nSPEC. BARNKLÄDER\n\nAntal anställda: 60\nAktiekapital: 45 000\nVerkst dir: Lennart Alberts\nEtableringsår: 1962.\n\nSVE\n\nluftfilter, broar, traverser,\njärnkonstruktioner, vibrationsgivare,\n-kon-troll- o -analysutrustningar,\nchock-provningsmaskiner, plastfoliekon-densatorer, elektroniska instrument\nför undervisning o forskning\nVarunamn: MWM\nAktiekapital: 150 000\nVerkst dir: F Grumme\nEtableringsår: 1949.\n\nGLASSAND, AB\n\nPnr 211 20\n\nMalmö, Skeppsbron 5. Tel\n040-12 22 90. Bankgiro 64-0259.\nPostgiro 38697. Tga Glassand\nVerksamhet: Säljer sand till\nglastillverkning o gjuteriändamål\nAntal anstäUda: 3\nÅrsomsättning: 200 000\nAktiekapital: 25 000\nVerkst dir: Kjell Olle Kjellander\nEtableringsår: 1903.\n\nAT i AB\n\nPnr 520 10\n\nGällstad, Box 47. Tel 0321-70121.\nBankgiro 84-0636. Postgiro\n323345-9\n\nVerksamhet: Mode- o sporttrikå i\ndam o herr som tröjor, koftor,\njumpers, skjortor m m samt vävda\ncrimplenetyger\nAntal anställda: 25\nÅrsomsättning: 3 000 000\nAktiekapital: 90 000\nVerkst dir: Arne Andersson\nEtableringsår: 1946.\n\nATLANTIC CONTAINER\nLINE AB\n\nPnr 403 13\n\nGöteborg 2, Box 2158. Postg 2.\nTel 031-17 20 20, 175100. Bankgiro\n553-0431. Postgiro 629922-6\nTga Atconline.\nTelex 20841 ACLLINE S\nVerksamhet: Container m m\ntransporter mellan Norden o USA/Canada\nVerkst dir: Arne GM Koch\nV verkst dir: Buster Hultman\nEtableringsår: 1967.",
    "structured": {
        "1": {
            "company_name": "ANTICIMEX AB",
            "activity": "Riksorganisation för skadedjurs bekämpning",
            "establishment_year": 1934,
            "employees": 440,
            "annual_turnover": 21000000,
            "capital": 640000,
            "key_personnel": [
                {
                    "name": "Olof Strid",
                    "position": "Verkst dir"
                }
            ]
        },
        "2": {
            "company_name": "ANTICIMEX HUSBOCKS-FURSÄKRINGS AB",
            "activity": "Husbocksforsäkring",
            "establishment_year": 1953,
            "employees": 440,
            "annual_turnover": 2930000,
            "capital": 100000,
            "key_personnel": [
                {
                    "name": "Olof Strid",
                    "position": "Verkst dir"
                }
            ]
        },
        "3": {
            "company_name": "ANTONSON-AV E RY AB",
            "activity": "Självhäftande etiketter, etiketteringsmaskiner o anläggningar, prismärkningsmaskiner",
            "establishment_year": 1894,
            "employees": 329,
            "annual_turnover": 35055000,
            "key_personnel": [
                {
                    "name": "Magnus Antonson",
                    "position": "Verkst dir"
                }
            ]
        },
        "4": {
            "company_name": "AO.S METALL & MEK VERKSTAD AB",
            "activity": "Utför experimentarbeten",
            "establishment_year": 1945,
            "capital": 50000,
            "key_personnel": [
                {
                    "name": "E Ohlson",
                    "position": "Firmatecknare"
                }
            ]
        },
        "5": {
            "company_name": "OREBRO METALLFABRIK",
            "establishment_year": 1930
        },
        "6": {
            "company_name": "OREBRO MURBRUKSFABRIK AB",
            "activity": "Tillverkar murbruk. Säljer grus",
            "employees": 10,
            "annual_turnover": 1300000,
            "capital": 50000,
            "key_personnel": [
                {
                    "name": "Olle Collgård",
                    "position": "Disp"
                }
            ],
            "establishment_year": 1955
        },
        "7": {
            "company_name": "OREBRO NYA MÖBEL FABRIK, AB",
            "activity": "Tillverkar butiks- o lagerinredningar",
            "employees": 12,
            "annual_turnover": 1300000,
            "capital": 72000,
            "establishment_year": 1919
        },
        "8": {
            "company_name": "MUSTADFORS BRUKS AB",
            "establishment_year": 1961
        },
        "9": {
            "company_name": "MUSTANGFABRIKEN AB TRELLEBORGS VELOCIPED-FABRIK",
            "activity": "Tillverkar cyklar o mopeder",
            "establishment_year": 1940,
            "capital": 125000,
            "key_personnel": [
                {
                    "name": "Gunnar Liljeberg",
                    "position": "Verkst dir"
                }
            ]
        },
        "10": {
            "company_name": "DIEDEN & CO, AB HERBERT",
            "activity": "Import av textilier, skor, porslin, korta varor m m från fjärran östern",
            "establishment_year": 1925,
            "employees": 30,
            "capital": 600000,
            "key_personnel": [
                {
                    "name": "Iwe Herlin",
                    "position": "Verkst dir"
                }
            ]
        },
        "11": {
            "company_name": "BURE AB",
            "activity": "Tillverkar trävaror, blekt o oblekt torr slipmassa",
            "employees": 360,
            "annual_turnover": 44000000,
            "capital": 5400000,
            "key_personnel": [
                {
                    "name": "Bengt Lyberg",
                    "position": "Verkst dir"
                },
                {
                    "name": "Johannes Larson",
                    "position": "Platschef"
                }
            ],
            "establishment_year": 1796
        },
        "12": {
            "company_name": "THERMIA.ARMATUR, AB",
            "activity": "Tillverkar sanitets-armatur, avstängningsventiler o radiatorventiler",
            "employees": 50,
            "annual_turnover": 5000000,
            "capital": 300000,
            "key_personnel": [
                {
                    "name": "Axel Hedberg",
                    "position": "Verkst dir"
                }
            ],
            "establishment_year": 1920
        },
        "13": {
            "company_name": "THERMIA-VERKEN, AB och THERMIA.VERKENS FOR. SÄLJNINGS AB",
            "activity": "Tillverkar o säljer varmvattenberedare, elvattenvär-mare, värmetransformatorer, värmeväxlare, elpannor, torkskåp, expansionskärl för slutet system, kul-vertisolering, reningsanläggningar för bad.",
            "employees": 400,
            "annual_turnover": 33000000,
            "capital": 800000,
            "establishment_year": 1923
        },
        "14": {
            "company_name": "TERMIT, MASKIN AB",
            "activity": "Tillverkar betongvarumaskiner, luftcylindrar o lyftverktyg",
            "employees": 35,
            "annual_turnover": 3000000,
            "capital": 200000,
            "key_personnel": [
                {
                    "name": "Bengt Henriksson",
                    "position": "Verkst dir"
                }
            ]
        },
        "15": {
            "company_name": "THERMO ROR AB",
            "activity": "Rörledningsentreprenörer",
            "employees": 35,
            "annual_turnover": 3500000,
            "capital": 30000,
            "key_personnel": [
                {
                    "name": "Låge Hedenfalk",
                    "position": "Styrelse"
                },
                {
                    "name": "Gertrud Hedenfalk",
                    "position": "Styrelse"
                },
                {
                    "name": "Låge Hedenfalk",
                    "position": "Verkst dir"
                },
                {
                    "name": "Sven-Olov Olsson",
                    "position": "Ingenjör"
                }
            ],
            "establishment_year": 1938
        },
        "16": {
            "company_name": "ALBERTS INDUSTRIER AB",
            "activity": "Tillverkar möbler samt produkter i fanerväv",
            "employees": 80,
            "annual_turnover": 6000000,
            "capital": 250000,
            "key_personnel": [
                {
                    "name": "Albert Larsson",
                    "position": "Verkst dir"
                }
            ]
        },
        "17": {
            "company_name": "ALBERTS KONFEKTIONS AB",
            "activity": "Spec. BARNKLÄDER",
            "employees": 60,
            "capital": 45000,
            "key_personnel": [
                {
                    "name": "Lennart Alberts",
                    "position": "Verkst dir"
                }
            ],
            "establishment_year": 1962
        },
        "18": {
            "company_name": "AT i AB",
            "activity": "Mode- o sporttrikå i dam o herr som tröjor, koftor, jumpers, skjortor m m samt vävda crimplenetyger",
            "employees": 25,
            "annual_turnover": 3000000,
            "capital": 90000,
            "key_personnel": [
                {
                    "name": "Arne Andersson",
                    "position": "Verkst dir"
                }
            ],
            "establishment_year": 1946
        },
        "19": {
            "company_name": "ATLANTIC CONTAINER LINE AB",
            "activity": "Container m m transporter mellan Norden o USA/Canada",
            "key_personnel": [
                {
                    "name": "Arne GM Koch",
                    "position": "Verkst dir"
                },
                {
                    "name": "Buster Hultman",
                    "position": "V verkst dir"
                }
            ],
            "establishment_year": 1967
        }
    }
}