{
    "original": "WIBRA AB, ATELJÉ\n\nPnr 55102\n\nJönköping 1, Box 442.\nSoldat-torpsg 2. Tel 036-11 14 69, 114469.\nBankgiro 372-6890. Postgiro\n103230-9\n\nVerksamhet: Fotosättning\nStockholmskontor: Tel 08-10 49 99\nVerkst dir: Maud Wiklund\nInköp o Försäljning: Percy N Bratt\nAteljéchef: Lars-Erik Wiik\nEtableringsår: 1969.\n\nmalmbergs iyngsju ab\n\nPnr 290 21\n\nYngsjö, Box 48. Tel 044-23 2180.\nBankgiro 873-6142. Postgiro\n284044-5\n\nVerksamhet: Utför\nbrunnsborrningar, maskinella installationer för\nvatten-o avloppsverk,\nVVS-tek-niska installationer, vatten- o\navloppsanläggningar samt smides- o\nmek arbeten\nAntal anställda: 120\nÅrsomsättning: 12 000 000\nAktiekapital: 360000\nVerkst dir: Fru Sonja Malmberg\nDisp: Folke Hansson\nEtableringsår: 1866.\n\nSAXON &amp; LINDSTRÖMS\nFORLAGS AB\n\nPnr 106 63\n\nStockholm, Sveav 145. Tel\n08-34 03 40. Postgiro 1698.\nTgaMaga-zine press\n\nVerksamhet: Förlags- o\ntryckeri-rörelse\n\nAntal anställda: 315\nAktiekapital: 1125 000\nStyrelse: Dir Bengt Lindström, dir\nHans Lindström, dir Ivar Lindström,\nbokförl Håkan Lindström, dir\nHerbert Ljung\n\nVerkst din Ivar Lindström\nEtableringsår. 1928.\n\nBRASONS KONFEKTIONS AB\n\nPnr 541 00\n\nSkövde, Gustav Adolfsg 36. Tel\n0500-107 40. Bankgiro 532-7929.\nPostgiro 34162\n\nVerksamhet: Tillverkar o säljer\nuddabyxor för herr o junior\nAntal anställda: 150\nÅrsomsättning: 12 000 000\nAktiekapital: 100 000\nVerkst din Allan Andersson\nEtableringsår: 1916.\n\nAMB\n\nAktiekapital: 25 000\nVerkst dir: Sten Strömqvist\nEtableringsår: 1925.\n\nGEFLE RORLÄGGNINGS AB\n\nPnr 80106\n\nGävle 1. Förrådsg 5. Box 507. Tel\n026-18 80 00. Bankgiro 23-7104.\nPostgiro 29989-1. Tga Rörbolaget\nVerksamhet: Värme- o sanitetstekn\nanläggningar. Industrimontage o mek\nverkstad\n\nFilialer: Bollnäs. Tel 0278-11017\nLjusdal. Tel 0651-129 54\nSandviken. Tel 026-25 38 19\nSöderhamn. Tel 0270-110 89\nAktiekapital: 213 000\nVerkst dir: Ing L-G Landström\nEtableringsår: 1900.\n\nPERSSON &amp; CO AB, P\n\nPnr 21124\n\nMalmö, Borrg 1. Tel 040-93 40 70.\nBankgiro 870-4488. Postgiro\n38555-9. Tga Träpersson\nVeiksamhet: Försäljning en gros o\ndistribution av moderbolagets\nprodukter, Ljusne-board,\nLjusne-ply-wood, lamell o trävaror samt\nträvaror från övriga produktioner.\nPartiförsäljning av Panorama-fönster o\nByggeUt/Lockne spånskivor\nAntal anställda: 14\nÅrsomsättning: 13 000 000\nAktiekapital: 500 000\nVeikst dir: Folke Lundquist\n(Ljusne)\n\nPlatschef: Disp Carl-Eric Arwe\nEtableringsår: 1916\nOmbildat till aktiebolag 1947.\n\nPERSSON RÅDGIVANDE\nINGENIURSBYRA AB, P O\n\nPnr 652 24\n\nKarlstad, Kungsg 4. Tel\n054-1800 90. Bankgiro 100-2906.\nPostgiro 590255-6\n\nVerksamhet: Konsultationer för\nindustri- o VVS-anläggningar\nAntal anställda: 13\nÅrsomsättning: 600 000\nAktiekapital: 10 000\nStyrelse: Ing P O Persson (ordf),\nfru Ingalill Persson\nVerkst dir: Ing P O Persson\nIngenjörer: B Andersson, R Ekra, L\nLindegren, H Mårtensson, E\nNilsson, H Nilsson, T Olsson, G\nPersson\n\nEtableringsår: 1961.\n\nWAHLQVIST AB, ERIK\n\nPnr 642 00\n\nFlen, Skebokvarn. Tel 0157-31046,\n310 90. Bankgiro 82-8969. Postgiro\n97114\n\nVerksamhet: Tillverkar o säljer\nalla slag av byggnadssnickerier\n0 byggnadsmaterial\nAntal anställda: 12\nÅrsomsättning: 1200 000\nAktiekapital: 28 000\nVerkst dir: Ernst Carlsson\nKamrer: Olle Lännstig\nEtableringsår: 1933.\n\nMEKANTRANSPORT AB\n\nPnr 41101\n\nGöteborg, Stampg 38. Tel\n031-8009 35. Bankgiro 847-8612.\nPostgiro 529710-6. Tga Närtransport\nVerksamhet: Konstruktion o\ntillverkning av transportanordningar\nAntal anställda: 20\nÅrsomsättning: 6 000 000\nAktiekapital: 10 000\nVerkst dir: Ing L Sundberg\nEtableringsår. 1953.\n\nCLIPPER-VERKEN, AB\n\nPnr 402 22\n\nGöteborg 5, Box 5073. Berzeliig\n23. Tel 031-20 97 66. Tga Clipper-\n\nnet\n\nVerksamhet: Importör o tillverkare\nav syntetiska fiskredskap mm\nÅrsomsättning: 300 000\nAktiekapital: 10 000\nVerkst dir: C G Gregerstam\nEtableringsår: 1957.",
    "structured": {
        "1": {
            "company_name": "WIBRA AB",
            "activity": "Fotosättning",
            "establishment_year": 1969
        },
        "2": {
            "company_name": "Malmbergs Iyngsju AB",
            "activity": "Utför brunnsborrningar, maskinella installationer för vatten-o avloppsverk, VVS-tek-niska installationer, vatten- o avloppsanläggningar samt smides- o mek arbeten",
            "employees": 120,
            "annual_turnover": 12000000,
            "capital": 360000,
            "key_personnel": [
                {
                    "name": "Sonja Malmberg",
                    "position": "Verkst dir"
                },
                {
                    "name": "Folke Hansson",
                    "position": "Disp"
                }
            ],
            "establishment_year": 1866
        },
        "3": {
            "company_name": "Saxon & Lindströms Forlags AB",
            "activity": "Förlags- o tryckeri-rörelse",
            "employees": 315,
            "capital": 1125000,
            "key_personnel": [
                {
                    "name": "Bengt Lindström",
                    "position": "Dir"
                },
                {
                    "name": "Hans Lindström",
                    "position": "Dir"
                },
                {
                    "name": "Ivar Lindström",
                    "position": "Dir"
                },
                {
                    "name": "Håkan Lindström",
                    "position": "Bokförl"
                },
                {
                    "name": "Herbert Ljung",
                    "position": "Dir"
                }
            ],
            "establishment_year": 1928
        },
        "4": {
            "company_name": "Brasons Konfektions AB",
            "activity": "Tillverkar o säljer uddabyxor för herr o junior",
            "employees": 150,
            "annual_turnover": 12000000,
            "capital": 100000,
            "key_personnel": [
                {
                    "name": "Allan Andersson",
                    "position": "Verkst dir"
                }
            ],
            "establishment_year": 1916
        },
        "5": {
            "company_name": "AMB",
            "capital": 25000,
            "key_personnel": [
                {
                    "name": "Sten Strömqvist",
                    "position": "Verkst dir"
                }
            ],
            "establishment_year": 1925
        },
        "6": {
            "company_name": "Gefle Rorläggnings AB",
            "activity": "Värme- o sanitetstekn anläggningar. Industrimontage o mek verkstad",
            "employees": null,
            "capital": 213000,
            "key_personnel": [
                {
                    "name": "Ing L-G Landström",
                    "position": "Verkst dir"
                }
            ],
            "establishment_year": 1900
        },
        "7": {
            "company_name": "Persson & Co AB, P",
            "activity": "Försäljning en gros o distribution av moderbolagets produkter, Ljusne-board, Ljusne-ply-wood, lamell o trävaror samt trävaror från övriga produktioner. Partiförsäljning av Panorama-fönster o ByggeUt/Lockne spånskivor",
            "employees": 14,
            "annual_turnover": 13000000,
            "capital": 500000,
            "key_personnel": [
                {
                    "name": "Folke Lundquist (Ljusne)",
                    "position": "Veikst dir"
                },
                {
                    "name": "Carl-Eric Arwe",
                    "position": "Platschef"
                }
            ],
            "establishment_year": 1947
        },
        "8": {
            "company_name": "Persson Rådgivande Ingeniursbyra AB, P O",
            "activity": "Konsultationer för industri- o VVS-anläggningar",
            "employees": 13,
            "annual_turnover": 600000,
            "capital": 10000,
            "key_personnel": [
                {
                    "name": "P O Persson",
                    "position": "Styrelse"
                },
                {
                    "name": "Ingalill Persson",
                    "position": "Styrelse"
                },
                {
                    "name": "P O Persson",
                    "position": "Verkst dir"
                },
                {
                    "name": "B Andersson",
                    "position": "Ingenjörer"
                },
                {
                    "name": "R Ekra",
                    "position": "Ingenjörer"
                },
                {
                    "name": "L Lindegren",
                    "position": "Ingenjörer"
                },
                {
                    "name": "H Mårtensson",
                    "position": "Ingenjörer"
                },
                {
                    "name": "E Nilsson",
                    "position": "Ingenjörer"
                },
                {
                    "name": "H Nilsson",
                    "position": "Ingenjörer"
                },
                {
                    "name": "T Olsson",
                    "position": "Ingenjörer"
                },
                {
                    "name": "G Persson",
                    "position": "Ingenjörer"
                }
            ],
            "establishment_year": 1961
        },
        "9": {
            "company_name": "Wahlqvist AB, Erik",
            "activity": "Tillverkar o säljer alla slag av byggnadssnickerier 0 byggnadsmaterial",
            "employees": 12,
            "annual_turnover": 1200000,
            "capital": 28000,
            "key_personnel": [
                {
                    "name": "Ernst Carlsson",
                    "position": "Verkst dir"
                },
                {
                    "name": "Olle Lännstig",
                    "position": "Kamrer"
                }
            ],
            "establishment_year": 1933
        },
        "10": {
            "company_name": "Mekantransport AB",
            "activity": "Konstruktion o tillverkning av transportanordningar",
            "employees": 20,
            "annual_turnover": 6000000,
            "capital": 10000,
            "key_personnel": [
                {
                    "name": "Ing L Sundberg",
                    "position": "Verkst dir"
                }
            ],
            "establishment_year": 1953
        },
        "11": {
            "company_name": "Clipper-Verken, AB",
            "activity": "Importör o tillverkare av syntetiska fiskredskap mm",
            "annual_turnover": 300000,
            "capital": 10000,
            "key_personnel": [
                {
                    "name": "C G Gregerstam",
                    "position": "Verkst dir"
                }
            ],
            "establishment_year": 1957
        }
    }
}