{
    "original": "ÄST\n\nASTRA LAKEMEDEL AB\n\nPnr 15185\n\nSödertälje 1, Pack. Tel 0755-329 80.\nBankgiro 170-6167. Postgiro\n9297-3. Tga Astra.\nTelex 1237 ASTRA S\nVerksamhet: Läkemedelsföretag\nVarunamn: Astra\nAktiekapital: 100 000\nStyrelse: Dir Karl Arne Wegerfelt\n(ordf), dir Stig Jakobsson, dir Inge\nEhrlën\n\nVerkst dir: Inge Ehrlën\nEtableringsår: 1969\nDotterbolag till AB Astra,\nSödertälje.\n\nASTRA NUTRITION AB\n\nPnr 43121\n\nMölndal 1, Kråketorpsg 8. Box 75.\nTel 031-87 0140. Bankgiro\n410-0095. Postgiro 5232 27-7.\nTga Astranutri, Göteborg.\nTelex 20046 ASTRA S\nVerksamhet: Näringsforskning\nsamt produktion o försäljning\ninom näringsområdet\nVarunamn: Prot-Animal\nProteinfabrik: Väröbacka. Tel\n0340-612 30\nAktiekapital: 100 000\nStyrelse: Dir Karl Arne Wegerfelt\n(ordf), dir Harry Wendéus, dir Karl\nWärnberg\n\nVerkst dir: Harry Wendéus\nEtableringsår: 1955\n\nDotterbolag till AB Astra,\nSödertälje.\n\nASTRA-DINOL AB\n\nPnr 28101\n\nHässleholm 1, S Industrig. Box 149.\nTel 0451-800 00. Tga Astra-Dinol.\nTelex 4442 TIKAMIN S\nVerksamhet: Utveckling,\ntillverkning o marknadsföring av\nkemisktekniska produkter for industri,\nsjöfart, storkök o bilmarknad.\nMarknadsföring genom dotterbolagen\nAB Alkalion o AB Tikamin. Se\nvidare nämnda bolag\nAktiekapital: 100 000\nStyrelse: Dir Karl Arne Wegerfelt\n(ordf), dir Bill B Ericson, dir Tage\nRanström\n\nVerkst dir: Bill B Ericson\nEtableringsår: 1969\nDotterbolag till AB Astra,\nSödertälje.\n\nASTRA-EWOS AB\n\nPnr 15120\n\nSödertälje 1, Svalängsv 1. Fack.\nTel 0755-340 80. Bankgiro\n170-6183. Postgiro 4773-8. Tga Ewos.\nTelex 10222 EWEX S\nVerksamhet: Tillverkning o\nmarknadsföring av fodersupplement o\nspecialfoder samt\nväxtskydds-preparat\n\nLokalkontor o lager: Malmö. Tel\n040-93 55 60\nVarunamn: Ewos\nAktiekapital: 2 500 000\nStyrelse: Dir Karl Arne Wegerfelt\n(ordf), dir Tage Ranström, dir Sven\nStrand\n\nVerkst dir: Sven Strand\nEtableringsår: 1935\nDotterbolag till AB Astra,\nSödertälje. Se vidare AB Ewos o AB\nPlantex.\n\n46\n\nASTRA-MEDITEC AB\n\nPnr 402 20\n\nGöteborg 5, Fack. Kärrag 5,\nMölndal. Tel 031-87 02 00. Bankgiro\n164-6009. Postgiro 523931-4,\n1386-2. Tga Meditec.\nTelex 20887 MEDITEC S\nVerksamhet: Tillverkning av\nröntgenkontrastmedel, suturmaterial o\nklinisk utrustning för sjukhus,\nelektromedicinska instrument o\napparater. Produktutveckling o\nförsäljning genom dotterbolagen Nukab\nAB o Sjuco AB. Se vidare nämnda\nbolag\n\nLokalkontor: 126 12 Stockholm 42,\nUpplagsv 10. Fack. Tel 08-18 83 60\nVarunamn: Dicodés, Mixobar\nAktiekapital: 180 000\nStyrelse: Dir Karl Arne Wegerfelt\n(ordf), dir Sven Arne Norlindh, dir\nKaj Jacobsson\n\nVerkst dir: Sven Arne Norlindh\nEtableringsår: 1903\nDotterbolag till AB Astra,\nSödertälje.\n\nASTRA-SYNTEX AB\n\nPnr 15185\n\nSödertälje 1, Fack. Tel 0755-329 80.\n\nBankgiro 170-6167. Postgiro\n\n9297-3. Tga Astra.\n\nTelex 1237 ASTRA S\n\nVerksamhet: Agentur: human- o\n\nveterinärläkemedel\n\nVarunamn: AstrarSyntex\n\nAktiekapital: 50 000\n\nStyrelse: Dir Hans Hellström (ordf),\n\ndir Hans-Erik Leufstedt, dir Robert\n\nRademaker\n\nVerkst dir: Erik Hornaess\nEtableringsår: 1969\nDotterbolag till Astra Läkemedel\nAB, Södertälje, Syntex Corporation,\nPanama.\n\nASTRA-WALLCO AB\n\nPnr 12612\n\nStockholm 42, Upplagsv 10. Fack.\nTel 08-18 83 60. Bankgiro 170-6605.\nPostgiro 9919-2. Tga Wallcoab.\nTelex 19056 MED ÄST S\nVerksamhet: Astra-koncernens\nmarknadsföringsbolag på konsuments\nvarumarknaden för kemisk-tekniska\nprodukter (AB Wallco),\nlivsmedelsprodukter (AB Sunco), sport- o\nfritidsartiklar (AB Wallco Sport).\nSe vidare nämnda bolag\nAktiekapital: 1000 000\nStyrelse:Dir Karl Arne Wegerfelt\n(ordf), dir Tage Ranström, dir Sven\nStrand, dir Sven-Olof Nyström\nVerkst dir: Sven-Olof Nyström\nEtableringsår: 1946\nDotterbolag till AB Astra,\nSödertälje.\n\nASTRO AB\n\nPnr 11156\n\nStockholm, Regeringsg 71. Tel\n08-2055 37. Postgiro 56688-5.\nTga Astrobol\n\nVerksamhet: Säljer\nindustritillbehör o halvfabrikat\nAktiekapital: 50 000\nEtableringsår: 1941.\n\nGELO-MASKINER, AB\n\nPnr 442 00\n\nKungälv, Industriv 10. Tel\n0303-109 20. Bankgiro 547-3517.\nPostgiro 713485-1. Tga Gelomaskin.\nTelex 2441 GELO S\nVerksamhet: Tillverkning o export\nav paketeringsmaskiner.\nKrymp-tunnlar\n\nAntal anställda: 34\nÅrsomsättning: 5 000000\nAktiekapital: 50 000\nVerkst dir: Erland Gustavsson\nEtableringsår 1960.\n\nMYRIN AB, ÅKE\n\nPnr 400 43\n\nGöteborg 13, Sävenäs\nIndustriområde. Pack. Tel 031-26 2135.\nBankgiro 50-8107. Postgiro 626316. Tga\nMyrintex\n\nVerksamhet: Sortering, import o\nexport av textila avfallsråvaror\nAvdelningskontor: Borås, pa\nMålsryd. Tel 033-492 80\nAntal anställda: 35\nÅrsomsättning: 5 000 000\nAktiekapital: 300000\nStyrelse: Fru Ingrid Myrin (ordf),\ndir Ake Myrin, P A Lantz\nVerkst dir: Ake Myrin\nEtableringsår: 1964.\n\nBURDE, T R\n\nPnr 351 03\n\nVäxjö 1, Smedjeg 15. Box 31. Tel\n0470-174 40,174 41. Postgiro\n297209. Tga Burde\nVerksamhet: Tillverkar o säljer\nkarnevals- o skämtartiklar av\ngummi, leksaker, jul- o\ndekorationsartiklar, hushålls- o lädervaror,\npap-perskortvaror, souvenirer,\ntobaksutensilier, handverktyg,\nreklamartiklar, Japan- o Hongkongartiklar\nChef: Dir T Burde\nEtableringsår: 1945.\n\nDIAMANTVERKTYG AB\n\nPnr 12171\n\nJohanneshov, Storsjöv 22. Tel\n08-9110 66. Bankgiro 748-0049.\nPostgiro 77779-7. Tga Diamverk\nVerksamhet: Tillverkning av\nelek-trometalliskt bundna verktyg samt\navrivningsverktyg av olika slag.\nSäljer: Diamanter, diamantpulver,\ndiamantpasta, diamantslipskivor,\n\ndiamantbrynen för heningsmaskiner,\ndiamantslipsüft, diamantfilar samt\ndiamantverktyg av olika slag\nVarunamn: Diagrit, Diamverk, X 17\nAktiekapital: 45 000\nChef: Ing Rune Eriksson\nEtableringsår: 1951\nOmbildat till aktiebolag 1961.\n\nDIAMOND SUPERIOR AB\n\nPnr 161 20\n\nBromma 20, Box 20035. Karlsbodav\n39. Tel 08-29 04 40. Bankgiro\n170-9641. Postgiro 296100-1. TgaUtilis.\nTelex 17124\nVerksamhet: Sotblåsare\nÅrsomsättning: 5 000 000\nAntal anställda: 35\nAktiekapital: 100 000\nVerkst dir: Rune Andersson\nEtableringsår: 1918.\n\nTERMANINSTRUMENT\n\nPnr 121 08\n\nJohanneshov 8, Svärdlångsv 56. Box\n803. Tel 08-45 45 55, 45 45 65.\nBankgiro 574-1269. Postgiro 358331-7.\nTga Termanmesser\nVerksamhet: Tillverkar instrument\nför tryck- o temperaturmätning\nAntal anställda: 7\nChefer: Ing Ivar Möllby, fabr\nSigvard Klinta\nEtableringsår 1949.\n\nAL-BE INDUSTRIN\n\nPnr 234 00\n\nLomma, Allég 21. Tel 040-41 21 61.\nPostgiro 439144\n\nVerksamhet: Tillverkar rattmuffar,\ntvätthandskar o polervantar i äkta\nfårskinn\n\nChef: Alf Bergkvist\nEtableringsår: 1955.\n\nSVEAVERKEN AB\n\nPnr 630 09\n\nEskilstuna 9, Box 9026. Tel\n016-25130. Bankgiro 601-3742.\nPostgiro 27791-3. Tga Sveaverken\nVerksamhet: Tillverkar fläktar för\ntorkning o transport av spannmål,\nventilationsfläktar,\ntransportskruvar, sädeskrossar, spannmålssilor\nför torkning o lagring\nVarunamn: Svea\nAntal anställda: 40\nÅrsomsättning: 6 000 000\nAktiekapital: 250 000\nStyrelse: Dir Lars Chr Eriksson\n(ordf), ing Allan Widén, kamrer\nOlof Ståhl\n\nVerkst dir: Ing Allan Widén\nKontorschef: Olof Ståhl\nProd-chef: Jan-Eric Jansson\nEtableringsår: 1911\nOmbildat till aktiebolag 1917.\n\nSVE A WOOD, AB\n\nPnr 41103\n\nGöteborg, Odinsg 20 B. Tel\n031-15 93 55, 15 93 56. Bankgiro\n420-1778. Postgiro 40548-8. Tga\nWood-svea\n\nVerksamhet: Levererar sågade\nträvaror, pålar o övrigt rundvirke på\nsåväl hemmamarknad som för\nexport\n\nAntal anställda: 5\nÅrsomsättning: 3 000 000\nAktiekapital: 100 000\nSgare o chefer: Gösta Karlsson,\nKurt Svanström\nEtableringsår: 1953.\n\nGERMETCO AB\n\nPnr 150 13\n\nTrosa, Box 23. Tel 0156-126 75.\nBankgiro 623-8356. Postgiro\n576665-4. Tga Germetco\nVerksamhet: Tillverkar rostfria\nhushålls- o presentartiklar\nAntal anställda: 37\nÅrsomsättning: 2 200 000\nVerkst dir. Gerhard Gollert\nEtableringsår: 1961.\n\nNODINGE VERKSTÄDER AB\n\nPnr 440 45\n\nNödinge. Tel 0303-29190. Bankgi\nro 89-5636. Postgiro 394280\nVerksamhet: Tillverkar\ntransportredskap för brandfarliga oljor\nAntal anstäUda: 65\nÅrsomsättning: 8 500 000\nAktiekapital: 100 000\nVerkst dir: B Svensson\nEtableringsår: 1950.",
    "structured": {
        "1": {
            "company_name": "ASTRA LAKEMEDEL AB",
            "pnr": "15185",
            "address": "Södertälje 1, Pack",
            "phone_number": "0755-329 80",
            "bank_details": {
                "bankgiro": "170-6167",
                "postgiro": "9297-3"
            },
            "activity": "Läkemedelsföretag",
            "capital": 100000,
            "key_personnel": [
                {
                    "name": "Karl Arne Wegerfelt",
                    "position": "ordf"
                },
                {
                    "name": "Stig Jakobsson",
                    "position": "dir"
                },
                {
                    "name": "Inge Ehrlën",
                    "position": "dir"
                }
            ],
            "establishment_year": 1969
        },
        "2": {
            "company_name": "ASTRA NUTRITION AB",
            "pnr": "43121",
            "address": "Mölndal 1, Kråketorpsg 8, Box 75",
            "phone_number": "031-87 0140",
            "bank_details": {
                "bankgiro": "410-0095",
                "postgiro": "5232 27-7"
            },
            "activity": "Näringsforskning samt produktion o försäljning inom näringsområdet",
            "capital": 100000,
            "key_personnel": [
                {
                    "name": "Karl Arne Wegerfelt",
                    "position": "ordf"
                },
                {
                    "name": "Harry Wendéus",
                    "position": "dir"
                },
                {
                    "name": "Karl Wärnberg",
                    "position": "dir"
                }
            ],
            "establishment_year": 1955
        },
        "3": {
            "company_name": "ASTRA-DINOL AB",
            "pnr": "28101",
            "address": "Hässleholm 1, S Industrig, Box 149",
            "phone_number": "0451-800 00",
            "activity": "Utveckling, tillverkning o marknadsföring av kemisktekniska produkter...",
            "capital": 100000,
            "key_personnel": [
                {
                    "name": "Karl Arne Wegerfelt",
                    "position": "ordf"
                },
                {
                    "name": "Bill B Ericson",
                    "position": "dir"
                },
                {
                    "name": "Tage Ranström",
                    "position": "dir"
                }
            ],
            "establishment_year": 1969
        },
        "4": {
            "company_name": "ASTRA-EWOS AB",
            "pnr": "15120",
            "address": "Södertälje 1, Svalängsv 1, Fack",
            "phone_number": "0755-340 80",
            "bank_details": {
                "bankgiro": "170-6183",
                "postgiro": "4773-8"
            },
            "activity": "Tillverkning o marknadsföring av fodersupplement o specialfoder samt växtskydds-preparat",
            "capital": 2500000,
            "key_personnel": [
                {
                    "name": "Karl Arne Wegerfelt",
                    "position": "ordf"
                },
                {
                    "name": "Tage Ranström",
                    "position": "dir"
                },
                {
                    "name": "Sven Strand",
                    "position": "dir"
                }
            ],
            "establishment_year": 1935
        },
        "5": {
            "company_name": "ASTRA-MEDITEC AB",
            "pnr": "402 20",
            "address": "Göteborg 5, Fack, Kärrag 5, Mölndal",
            "phone_number": "031-87 02 00",
            "bank_details": {
                "bankgiro": "164-6009",
                "postgiro": "523931-4, 1386-2"
            },
            "activity": "Tillverkning av röntgenkontrastmedel, suturmaterial o klinisk utrustning...",
            "capital": 180000,
            "key_personnel": [
                {
                    "name": "Karl Arne Wegerfelt",
                    "position": "ordf"
                },
                {
                    "name": "Sven Arne Norlindh",
                    "position": "dir"
                },
                {
                    "name": "Kaj Jacobsson",
                    "position": "dir"
                }
            ],
            "establishment_year": 1903
        },
        "6": {
            "company_name": "ASTRA-SYNTEX AB",
            "pnr": "15185",
            "address": "Södertälje 1, Fack",
            "phone_number": "0755-329 80",
            "bank_details": {
                "bankgiro": "170-6167",
                "postgiro": "9297-3"
            },
            "activity": "Agentur: human- o veterinärläkemedel",
            "capital": 50000,
            "key_personnel": [
                {
                    "name": "Hans Hellström",
                    "position": "ordf"
                },
                {
                    "name": "Hans-Erik Leufstedt",
                    "position": "dir"
                },
                {
                    "name": "Robert Rademaker",
                    "position": "dir"
                }
            ],
            "establishment_year": 1969
        },
        "7": {
            "company_name": "ASTRA-WALLCO AB",
            "pnr": "12612",
            "address": "Stockholm 42, Upplagsv 10, Fack",
            "phone_number": "08-18 83 60",
            "bank_details": {
                "bankgiro": "170-6605",
                "postgiro": "9919-2"
            },
            "activity": "Astra-koncernens marknadsföringsbolag på konsuments varumarknaden...",
            "capital": 1000000,
            "key_personnel": [
                {
                    "name": "Karl Arne Wegerfelt",
                    "position": "ordf"
                },
                {
                    "name": "Tage Ranström",
                    "position": "dir"
                },
                {
                    "name": "Sven Strand",
                    "position": "dir"
                },
                {
                    "name": "Sven-Olof Nyström",
                    "position": "dir"
                }
            ],
            "establishment_year": 1946
        },
        "8": {
            "company_name": "ASTRO AB",
            "pnr": "11156",
            "address": "Stockholm, Regeringsg 71",
            "phone_number": "08-2055 37",
            "activity": "Säljer industritillbehör o halvfabrikat",
            "capital": 50000,
            "establishment_year": 1941
        },
        "9": {
            "company_name": "GELO-MASKINER, AB",
            "pnr": "442 00",
            "address": "Kungälv, Industriv 10",
            "phone_number": "0303-109 20",
            "bank_details": {
                "bankgiro": "547-3517",
                "postgiro": "713485-1"
            },
            "activity": "Tillverkning o export av paketeringsmaskiner. Krymp-tunnlar",
            "employees": 34,
            "annual_turnover": 5000000,
            "capital": 50000,
            "key_personnel": [
                {
                    "name": "Erland Gustavsson",
                    "position": "Verkst dir"
                }
            ],
            "establishment_year": 1960
        },
        "10": {
            "company_name": "MYRIN AB, ÅKE",
            "pnr": "400 43",
            "address": "Göteborg 13, Sävenäs Industriområde",
            "phone_number": "031-26 2135",
            "bank_details": {
                "bankgiro": "50-8107",
                "postgiro": "626316"
            },
            "activity": "Sortering, import o export av textila avfallsråvaror",
            "employees": 35,
            "annual_turnover": 5000000,
            "capital": 300000,
            "key_personnel": [
                {
                    "name": "Ingrid Myrin",
                    "position": "ordf"
                },
                {
                    "name": "Åke Myrin",
                    "position": "dir"
                },
                {
                    "name": "P A Lantz",
                    "position": "dir"
                }
            ],
            "establishment_year": 1964
        },
        "11": {
            "company_name": "BURDE, T R",
            "pnr": "351 03",
            "address": "Växjö 1, Smedjeg 15, Box 31",
            "phone_number": "0470-174 40,174 41",
            "bank_details": {
                "postgiro": "297209"
            },
            "activity": "Tillverkar o säljer karnevals- o skämtartiklar av gummi...",
            "establishment_year": 1945
        },
        "12": {
            "company_name": "DIAMANTVERKTYG AB",
            "pnr": "12171",
            "address": "Johanneshov, Storsjöv 22",
            "phone_number": "08-9110 66",
            "bank_details": {
                "bankgiro": "748-0049",
                "postgiro": "77779-7"
            },
            "activity": "Tillverkning av elektrometalliskt bundna verktyg samt avrivningsverktyg av olika slag",
            "employees": 7,
            "capital": 45000,
            "key_personnel": [
                {
                    "name": "Rune Eriksson",
                    "position": "Ing"
                }
            ],
            "establishment_year": 1951
        },
        "13": {
            "company_name": "DIAMOND SUPERIOR AB",
            "pnr": "161 20",
            "address": "Bromma 20, Box 20035, Karlsbodav 39",
            "phone_number": "08-29 04 40",
            "bank_details": {
                "bankgiro": "170-9641",
                "postgiro": "296100-1"
            },
            "activity": "Sotblåsare",
            "employees": 35,
            "annual_turnover": 5000000,
            "capital": 100000,
            "key_personnel": [
                {
                    "name": "Rune Andersson",
                    "position": "Verkst dir"
                }
            ],
            "establishment_year": 1918
        },
        "14": {
            "company_name": "TERMANINSTRUMENT",
            "pnr": "121 08",
            "address": "Johanneshov 8, Svärdlångsv 56, Box 803",
            "phone_number": "08-45 45 55, 45 45 65",
            "bank_details": {
                "bankgiro": "574-1269",
                "postgiro": "358331-7"
            },
            "activity": "Tillverkar instrument för tryck- o temperaturmätning",
            "employees": 7,
            "key_personnel": [
                {
                    "name": "Ivar Möllby",
                    "position": "Ing"
                },
                {
                    "name": "Sigvard Klinta",
                    "position": "fabr"
                }
            ],
            "establishment_year": 1949
        },
        "15": {
            "company_name": "AL-BE INDUSTRIN",
            "pnr": "234 00",
            "address": "Lomma, Allég 21",
            "phone_number": "040-41 21 61",
            "postgiro": "439144",
            "activity": "Tillverkar rattmuffar, tvätthandskar o polervantar i äkta fårskinn",
            "establishment_year": 1955
        },
        "16": {
            "company_name": "SVEAVERKEN AB",
            "pnr": "630 09",
            "address": "Eskilstuna 9, Box 9026",
            "phone_number": "016-25130",
            "bank_details": {
                "bankgiro": "601-3742",
                "postgiro": "27791-3"
            },
            "activity": "Tillverkar fläktar för torkning o transport av spannmål...",
            "employees": 40,
            "annual_turnover": 6000000,
            "capital": 250000,
            "key_personnel": [
                {
                    "name": "Lars Chr Eriksson",
                    "position": "ordf"
                },
                {
                    "name": "Allan Widén",
                    "position": "ing"
                },
                {
                    "name": "Olof Ståhl",
                    "position": "kamrer"
                }
            ],
            "establishment_year": 1911
        },
        "17": {
            "company_name": "SVE A WOOD, AB",
            "pnr": "41103",
            "address": "Göteborg, Odinsg 20 B",
            "phone_number": "031-15 93 55, 15 93 56",
            "bank_details": {
                "bankgiro": "420-1778",
                "postgiro": "40548-8"
            },
            "activity": "Levererar sågade trävaror, pålar o övrigt rundvirke på såväl hemmamarknad som för export",
            "employees": 5,
            "annual_turnover": 3000000,
            "capital": 100000,
            "key_personnel": [
                {
                    "name": "Gösta Karlsson",
                    "position": "Sgare o chefer"
                },
                {
                    "name": "Kurt Svanström",
                    "position": "Sgare o chefer"
                }
            ],
            "establishment_year": 1953
        },
        "18": {
            "company_name": "GERMETCO AB",
            "pnr": "150 13",
            "address": "Trosa, Box 23",
            "phone_number": "0156-126 75",
            "bank_details": {
                "bankgiro": "623-8356",
                "postgiro": "576665-4"
            },
            "activity": "Tillverkar rostfria hushålls- o presentartiklar",
            "employees": 37,
            "annual_turnover": 2200000,
            "key_personnel": [
                {
                    "name": "Gerhard Gollert",
                    "position": "Verkst dir"
                }
            ],
            "establishment_year": 1961
        },
        "19": {
            "company_name": "NODINGE VERKSTÄDER AB",
            "pnr": "440 45",
            "address": "Nödinge",
            "phone_number": "0303-29190",
            "bank_details": {
                "bankgiro": "89-5636",
                "postgiro": "394280"
            },
            "activity": "Tillverkar transportredskap för brandfarliga oljor",
            "employees": 65,
            "annual_turnover": 8500000,
            "capital": 100000,
            "key_personnel": [
                {
                    "name": "B Svensson",
                    "position": "Verkst dir"
                }
            ],
            "establishment_year": 1950
        }
    }
}