{
    "original": "SKÅNSK BYGGTJÄNST AB\n\nPnr 21138\n\nMalmö, Studentg 4. Tel 040-709 55.\n\nBankgiro 348-2213. Postgiro\n147566-4\n\nVerksamhet: Permanent byggut-\n\nställning, information\n\nAktiekapital: 65 000\n\nVerkst dir: Civiling Rune Nisses-\n\nGagnér\n\nEtableringsår: 1953.\n\nSKÅNSKA\nANDELSSLAKTERIER EK FÖR SKANEK\n\nPnr 20110\n\nMalmö 1, Rundelen 3. Fack. Tel\n040-743 20. Bankgiro 263-4020,\nPostgiro 38893-4. Tga Skanek.\nTelex 32427 SKANEK S\nVerksamhet: Slakteri med\ntillhörande förädlingsverksamhet\nAntal anställda: 2 200\nÅrsomsättning: 1 000 000 000\nVerkst dir: Lennart Lilliehöök\nEtableringsår: 1934.\n\nAR-VENTILATION AB\n\nPnr 104 60\n\nStockholm 20, Pack. Hammarbyv\n27. Tel 08-22 9 2 40. Tga Ahlsells.\nTelex 1837 ALSEL S\nVerksamhet: Tillverkning av fläktar,\napparater, don o kanaler för\nventilationsanläggningar. Projekterar\no utför\nluftkonditioneringsanlägg-ningar\n\nFörsäljningskontor:\n\nSTOCKHOLM, Hammarbyv 27.\nFack, 104 60 Stockholm 20. Tel\n08-22 92 40\n\nGOTEBORG, Fröfästeg 22 B. Box\n154, 421 22 Västra Frölunda 1. Tel\n031-45 09 40\n\nMALMÖ, Bellevuev 46. Box 67.\n201 20 Malmö 1. Tel 040-1010 30\nNORRKOPING, Fabriksg8. Box\n3066, 600 03 Norrköping 3. Tel\n011-12 95 30\n\nOREBRO, Engelbrektsg 9. Box 141,\n701 03 Örebro 1. Tel 019-13 07 30\nSUNDSVALL. Storg 26, 852 30\nSundsvall. Tel 060-128240\nUMEA, Strömv 8. Box 801, 90110\nUmeå 1. Tel 090-13 50 85\nVerkstäder:\n\nTOMELILLA, Produktverkstaden,\nIndustrig 5. Box 108, 273 00\nTomelilla. Tel 0417-116 00\nTOMELILLA, Kanalverkstaden,\nGustavs torg 2. Box 92, 273 00\nTomelilla. Tel 0417-116 00\nVarunamn: Anemostat, Trane\nAktiekapital: 3 000 000\nStyrelse: Dir Sven Östling (ordf),\ndir Arne Björklund, dir Sven A\nSvennberg\n\nVerkst dir: Sven A Svennberg\nDotterbolag till Ahlsell &amp; Ågren\nAB, Stockholm.\n\nARVIDSJAURS\nLÄDERPRODUKTER\n\n(Ingår i Formelgruppen)\nPnr 930 80\n\nArvidsjaur, Södra g 34. Tel\n0960-103 13. Postgiro 60068\nVerksamhet: Tillverkar skidstavar\nav stål, lättmetall, glasfiber samt\ntonkin för tävling o sport. Snöskor\nmed ram av rotting eller köldhärdig\nplast. Ryggsäckar, damväskor o\nsouvenirer av renhud\nAntal anställda: 35\nÅrsomsättning: 3 000 000\nChef: Gunnar Markström\nEtableringsår: 1955.\n\nARVIDSSONS GLAS &amp; PORSLIN\nAB\n\nPnr 630 04\n\nEskilstuna 4, Box 4026.\nUtter-marksg 31. Tel 016-13 67 30.\nBankgiro 601-4856. Postgiro 290695-6\nVerksamhet: Säljer glas, porslin o\npresentartiklar\nAntal anställda: 12\nÅrsomsättning: 600 000\nAktiekapital: 40 000\nVerkst dir. Engbert Arvidsson\nEtableringsår: 1946.\n\nARVIDSSONS TAPETSERARE.\nVERKSTAD, AB\n\nPnr 51101\n\nKinna 1, Box 43. Söderkulla 6. Tel\n0320-106 35. Bankgiro 546-1397.\nPostgiro 465564-3.\nTelex 36077 ABARVID S\nVerksamhet: Tillverkar gardiner o\nsängöverkast. Importerar textilier\nFabrik: Norge: Halden Heimtextil,\nHalden. Tel 031-844 68\nAntal anställda: 80\nÅrsomsättning: 9400 000\nAktiekapital: 150 000\nVerkst dir: Halvdan Arvidsson\nInköpschef: Allan Arvidsson\nEtableringsår: 1949.\n\nTRANSMARIN, AB\n\nPnr 252 21\n\nHelsingborg, Kungsg 2. Tel\n042-12 75 10. Bankgiro 86-4005.\nPost-giro 14207-5. Tga Transmarin.\nTelex 72215, 72245\nVeiksamhet: Reguljär linjetrafik:\n»Östersjön-Englands västkust\n/Irlands ostkust; Kontinenten/\nLondon-Medelhavet o vice versa\nVerkst dir Mats Olsson\nEtableringsår: 1916.\n\nINTERPLAST AB\n\nPnr 18103\n\nLidingö 3, Box 318. S Kungsv 334.\nTel 08-766 24 68, 766 24 69.\nBankgiro 160-7191. Postgiro 507491-9.\nTga Plastinter\n\nVerksamhet: Skyltfabrik o\nplastindustri\n\nAntal anstäUda: 15\nÅrsomsättning: 2000000\nAktiekapital: 75 000\nVerkst dir: Imre Bolyos\nEtableringsår: 1954.\n\nAMINKEMI AB\n\nPnr 16120\n\nBromma 20, Box 20105. Annedalsv\n39. Tel 08-29 04 20. Bankgiro\n826-3766. Postgiro 359340-7.\nTga Aminkemi\n\nVerksamhet: Tillverkar organiska\nkomplexbildare,\nkorrosionsinhibi-torer, diverse finkemikalier etc\nAntal anställda: 14\nÅrsomsättning: 6 000 000\nAktiekapital: 1000 000\nVerkst dir: Civiling Jurgen Morath\nEtableringsår: 1967.\n\nAMLAB AB\n\nAtlas Marin Laboratorium\n\nPnr 149 01\n\nNynäshamn 1, Box 54. Frejg 23.\nTel 0752-121 70. Bankgiro\n829-9588. Postgiro 555056-1\nVerksamhet: Utvecklar\nultraljuds-o servotekniska utrustningar.\nTillverkar Amdent\ntandsaneringsappa-rat. Service av ekolod,\ngyrokompas-ser, automatstyrsystem m m\nVarunamn: Amdent\nAntal anställda: 95\nÅrsomsättning: 5 000 000\nAktiekapital: 200 000\nVerkst dir: Rune Fahlström\nEtableringsår: 1955.\n\nBRATTS AB, SVEN\n\nPnr 41314\n\nGöteborg, Sveag 7. Tel 031-\n\n14\t18 00. Bankgiro 444-7629.\nPostgiro 40078-8. Tga Svenbratt\nVerksamhet: Säljer\nbyggnadsmaterial\n\nAktiekapital: 20 000\nChef: Försälji&gt;chef Rudolf\nAndersson\n\nEtableringsår: 1897.\n\nSATURN FÄRGER &amp;\nFERNISSOR, AB\n\nPnr 4 02 24\n\nGöteborg 5, Box 5201. Partilie.\nTel 031-44 13 73. Bankgiro\n337-7140. Postgiro 529650-4\nVeiksamhet: Tillverkar o säljer\nfärger o fernissor\nAktiekapital: 25 000\nEtableringsår: 1960.\n\nPETERSEN &amp; CO AB, ALEX\n\nPnr 260 35\n\nOdåkra, Fleninge. Box 100. Tel\n042-551 51, 551 52. Bankgiro\n653-0836, Postgiro 127366-3. Tga Imex\nVerksamhet: Säljer maskiner o\nutrustning till fjäderfäslakterier o\nlivsmedelsindustrin\nAntal anstäUda: 3\nÅrsomsättning: 1500 000\nAktiekapital: 240 000\nVerkst din Sven Alex Petersen\nEtableringsår: 1961.\n\nSVENSKA DUNLOP AB\n\nPnr 60102\n\nNorrköping 1, Box 30. Hagag 4. Tel\n011-12 9215. Bankgiro 609-8040.\nPostgiro 1665-9. Tga Dunlop.\nTelex 64034\n\nVerksamhet: Automobilgummi- o\nkautschukvaror, pressade hjul av\nstålplåt\n\nAktiekapital: 500000\nVerkst dir: R J Shelton\nEtableringsår: 1921.\n\nCORIN &amp; LINDER AB\n\nPnr 41102\n\nGöteborg, Baldersg 10. Tel\n031-19 2610. Bankgiro 50-6587.\nPostgiro 12007. Tga Corilind\nVerksamhet o varunamn: se Svenska\nMaskinaffären AB, Värnamo\nVerkst dir: Anton Johansson\nEtableringsår: 1909\nDotterbolag till Svenska\nMaskinaffären AB, Värnamo.\n\nCORIN &amp; CO AB, FREDR\n\nPnr 40010\n\nGöteborg 3, Box 3017. Viktoriag 3.\nTel 031-13 10 31. Postgiro 424210.\nTga Corin. Telex 2398\nVerksamhet: Bomulls-, textil-,\nfoderkakor o spannmålsagenturer\nAktiekapital: 100 000\nVerkst dir: Lars M Corin\nEtableringsår: 1878.",
    "structured": {
        "1": {
            "company_name": "SKÅNSK BYGGTJÄNST AB",
            "pnr": "21138",
            "address": "Malmö, Studentg 4",
            "phone_number": "040-709 55",
            "bank_details": {
                "bankgiro": "348-2213",
                "postgiro": "147566-4"
            },
            "activity": "Permanent byggutställning, information",
            "capital": 65000,
            "key_personnel": [
                {
                    "name": "Civiling Rune Nisses-Gagnér",
                    "position": "Verkst dir"
                }
            ],
            "establishment_year": 1953
        },
        "2": {
            "company_name": "SKÅNSKA ANDELSSLAKTERIER EK FÖR SKANEK",
            "pnr": "20110",
            "address": "Malmö 1, Rundelen 3",
            "phone_number": "040-743 20",
            "bank_details": {
                "bankgiro": "263-4020",
                "postgiro": "38893-4"
            },
            "activity": "Slakteri med tillhörande förädlingsverksamhet",
            "employees": 2200,
            "annual_turnover": 1000000000,
            "key_personnel": [
                {
                    "name": "Lennart Lilliehöök",
                    "position": "Verkst dir"
                }
            ],
            "establishment_year": 1934
        },
        "3": {
            "company_name": "AR-VENTILATION AB",
            "pnr": "104 60",
            "address": "Stockholm 20, Pack. Hammarbyv 27",
            "phone_number": "08-22 9 2 40",
            "activity": "Tillverkning av fläktar, apparater, don o kanaler för ventilationsanläggningar. Projekterar o utför luftkonditioneringsanläggningar",
            "address_other_locations": [
                "Göteborg, Fröfästeg 22 B, Box 154, 421 22 Västra Frölunda 1, Tel 031-45 09 40",
                "Malmö, Bellevuev 46, Box 67, 201 20 Malmö 1, Tel 040-1010 30",
                "Norrköping, Fabriksg8, Box 3066, 600 03 Norrköping 3, Tel 011-12 95 30",
                "Örebro, Engelbrektsg 9, Box 141, 701 03 Örebro 1, Tel 019-13 07 30",
                "Sundsvall, Storg 26, 852 30 Sundsvall, Tel 060-128240",
                "Umeå, Strömv 8, Box 801, 90110 Umeå 1, Tel 090-13 50 85",
                "Tomelilla, Produktverkstaden, Industrig 5, Box 108, 273 00 Tomelilla, Tel 0417-116 00",
                "Tomelilla, Kanalverkstaden, Gustavs torg 2, Box 92, 273 00 Tomelilla, Tel 0417-116 00"
            ],
            "varunamn": "Anemostat, Trane",
            "capital": 3000000,
            "key_personnel": [
                {
                    "name": "Sven A Svennberg",
                    "position": "Verkst dir"
                }
            ],
            "establishment_year": 9999
        },
        "4": {
            "company_name": "ARVIDSJAURS LÄDERPRODUKTER",
            "pnr": "930 80",
            "address": "Arvidsjaur, Södra g 34",
            "phone_number": "0960-103 13",
            "postgiro": "60068",
            "activity": "Tillverkar skidstavar av stål, lättmetall, glasfiber samt tonkin för tävling o sport. Snöskor med ram av rotting eller köldhärdig plast. Ryggsäckar, damväskor o souvenirer av renhud",
            "employees": 35,
            "annual_turnover": 3000000,
            "key_personnel": [
                {
                    "name": "Gunnar Markström",
                    "position": "Chef"
                }
            ],
            "establishment_year": 1955
        },
        "5": {
            "company_name": "ARVIDSSONS GLAS & PORSLIN AB",
            "pnr": "630 04",
            "address": "Eskilstuna 4, Box 4026, Uttermarksg 31",
            "phone_number": "016-13 67 30",
            "bank_details": {
                "bankgiro": "601-4856",
                "postgiro": "290695-6"
            },
            "activity": "Säljer glas, porslin o presentartiklar",
            "employees": 12,
            "annual_turnover": 600000,
            "capital": 40000,
            "key_personnel": [
                {
                    "name": "Engbert Arvidsson",
                    "position": "Verkst dir"
                }
            ],
            "establishment_year": 1946
        },
        "6": {
            "company_name": "ARVIDSSONS TAPETSERARE. VERKSTAD, AB",
            "pnr": "51101",
            "address": "Kinna 1, Box 43, Söderkulla 6",
            "phone_number": "0320-106 35",
            "bank_details": {
                "bankgiro": "546-1397",
                "postgiro": "465564-3"
            },
            "activity": "Tillverkar gardiner o sängöverkast. Importerar textilier",
            "address_other_locations": [
                "Norge, Halden Heimtextil, Halden, Tel 031-844 68"
            ],
            "employees": 80,
            "annual_turnover": 9400000,
            "capital": 150000,
            "key_personnel": [
                {
                    "name": "Allan Arvidsson",
                    "position": "Inköpschef"
                }
            ],
            "establishment_year": 1949
        },
        "7": {
            "company_name": "TRANSMARIN, AB",
            "pnr": "252 21",
            "address": "Helsingborg, Kungsg 2",
            "phone_number": "042-12 75 10",
            "bank_details": {
                "bankgiro": "86-4005",
                "postgiro": "14207-5"
            },
            "activity": "Reguljär linjetrafik: Östersjön-Englands västkust/Irlands ostkust; Kontinenten/London-Medelhavet o vice versa",
            "capital": 9999,
            "key_personnel": [
                {
                    "name": "Mats Olsson",
                    "position": "Verkst dir"
                }
            ],
            "establishment_year": 1916
        },
        "8": {
            "company_name": "INTERPLAST AB",
            "pnr": "18103",
            "address": "Lidingö 3, Box 318, S Kungsv 334",
            "phone_number": "08-766 24 68, 766 24 69",
            "bank_details": {
                "bankgiro": "160-7191",
                "postgiro": "507491-9"
            },
            "activity": "Skyltfabrik o plastindustri",
            "employees": 15,
            "annual_turnover": 2000000,
            "capital": 75000,
            "key_personnel": [
                {
                    "name": "Imre Bolyos",
                    "position": "Verkst dir"
                }
            ],
            "establishment_year": 1954
        },
        "9": {
            "company_name": "AMINKEMI AB",
            "pnr": "16120",
            "address": "Bromma 20, Box 20105, Annedalsv 39",
            "phone_number": "08-29 04 20",
            "bank_details": {
                "bankgiro": "826-3766",
                "postgiro": "359340-7"
            },
            "activity": "Tillverkar organiska komplexbildare, korrosionsinhibitorer, diverse finkemikalier etc",
            "employees": 14,
            "annual_turnover": 6000000,
            "capital": 1000000,
            "key_personnel": [
                {
                    "name": "Civiling Jurgen Morath",
                    "position": "Verkst dir"
                }
            ],
            "establishment_year": 1967
        },
        "10": {
            "company_name": "AMLAB AB",
            "pnr": "149 01",
            "address": "Nynäshamn 1, Box 54, Frejg 23",
            "phone_number": "0752-121 70",
            "bank_details": {
                "bankgiro": "829-9588",
                "postgiro": "555056-1"
            },
            "activity": "Utvecklar ultraljuds-o servotekniska utrustningar. Tillverkar Amdent tandsaneringsapparat. Service av ekolod, gyrokompasser, automatstyrsystem m m",
            "employees": 95,
            "annual_turnover": 5000000,
            "capital": 200000,
            "key_personnel": [
                {
                    "name": "Rune Fahlström",
                    "position": "Verkst dir"
                }
            ],
            "establishment_year": 1955
        },
        "11": {
            "company_name": "BRATTS AB, SVEN",
            "pnr": "41314",
            "address": "Göteborg, Sveag 7",
            "phone_number": "031-14 18 00",
            "bank_details": {
                "bankgiro": "444-7629",
                "postgiro": "40078-8"
            },
            "activity": "Säljer byggnadsmaterial",
            "capital": 20000,
            "key_personnel": [
                {
                    "name": "Rudolf Andersson",
                    "position": "Försäljningschef"
                }
            ],
            "establishment_year": 1897
        },
        "12": {
            "company_name": "SATURN FÄRGER & FERNISSOR, AB",
            "pnr": "4 02 24",
            "address": "Göteborg 5, Box 5201, Partilie",
            "phone_number": "031-44 13 73",
            "bank_details": {
                "bankgiro": "337-7140",
                "postgiro": "529650-4"
            },
            "activity": "Tillverkar o säljer färger o fernissor",
            "capital": 25000,
            "establishment_year": 1960
        },
        "13": {
            "company_name": "PETERSEN & CO AB, ALEX",
            "pnr": "260 35",
            "address": "Odåkra, Fleninge, Box 100",
            "phone_number": "042-551 51, 551 52",
            "bank_details": {
                "bankgiro": "653-0836",
                "postgiro": "127366-3"
            },
            "activity": "Säljer maskiner o utrustning till fjäderfäslakterier o livsmedelsindustrin",
            "employees": 3,
            "annual_turnover": 1500000,
            "capital": 240000,
            "key_personnel": [
                {
                    "name": "Sven Alex Petersen",
                    "position": "Verkst dir"
                }
            ],
            "establishment_year": 1961
        },
        "14": {
            "company_name": "SVENSKA DUNLOP AB",
            "pnr": "60102",
            "address": "Norrköping 1, Box 30, Hagag 4",
            "phone_number": "011-12 9215",
            "bank_details": {
                "bankgiro": "609-8040",
                "postgiro": "1665-9"
            },
            "activity": "Automobilgummi- o kautschukvaror, pressade hjul av stålplåt",
            "capital": 500000,
            "key_personnel": [
                {
                    "name": "R J Shelton",
                    "position": "Verkst dir"
                }
            ],
            "establishment_year": 1921
        },
        "15": {
            "company_name": "CORIN & LINDER AB",
            "pnr": "41102",
            "address": "Göteborg, Baldersg 10",
            "phone_number": "031-19 2610",
            "bank_details": {
                "bankgiro": "50-6587",
                "postgiro": "12007"
            },
            "activity": "Se Svenska Maskinaffären AB, Värnamo",
            "key_personnel": [
                {
                    "name": "Anton Johansson",
                    "position": "Verkst dir"
                }
            ],
            "establishment_year": 1909,
            "parent_company": "Svenska Maskinaffären AB, Värnamo"
        },
        "16": {
            "company_name": "CORIN & CO AB, FREDR",
            "pnr": "40010",
            "address": "Göteborg 3, Box 3017, Viktoriag 3",
            "phone_number": "031-13 10 31",
            "postgiro": "424210",
            "activity": "Bomulls-, textil-, foderkakor o spannmålsagenturer",
            "capital": 100000,
            "key_personnel": [
                {
                    "name": "Lars M Corin",
                    "position": "Verkst dir"
                }
            ],
            "establishment_year": 1878
        }
    }
}