{
    "original": "NAHRMEKO AB\n\nPnr 57100\n\nNässjö. Box 159. Storg 48. Tel\n0380-103 80, 183 80. Bankgiro\n251-1277. Postgiro 715848-8\nVerksamhet Tillverkar automatiska\npaketeringsmaskiner,\nfiltrerings-utrustningar för öl-, jäst- o annan\nindustri samt legotillverkning\nAntal anställda: 40\nÅrsomsättning: 2 800 000\nAktiekapital: 100 000\nStyrelse: Dir Charles Nahrström,\nfru Gretha Nahrström, civiling Jan\nNarström, fil kand Mats Narström\nVerkst dir: Charles Nahrström\nEtableringsår: 1968.\n\nNORMEK, AB\n\nPnr 117 44\n\nStockholm, Nybohovsbacken 50.\nTel 08-18 6109, 18 6113. Bankgiro\n744-3468. Postgiro 259559-3. Tga\nNormekab. Telex 17836 NORMEK S\nVerksamhet: Säljer\nverktygsmaskiner, diamantverktyg, diamantskivor\no diamantslippasta\nAntal anställda: 8\nAktiekapital: 15 000\nVerkst dir: Ing Ake Lindblom\nEtableringsår: 1956.\n\nNORRA KINDS\nHEM-INDUSTRI, AB\n\nPnr 520 10\n\nGällstad. Tel 0321-70052.\nBankgiro 840-6282. Postgiro 72585\nVerksamhet: Tillverkar sockor,\nstrumpor o vantar\nAktiekapital: 45 000\nVerkst dir: Axel Bolander\nEtableringsår: 1930\nOmbildat till aktiebolag 1935.\n\nNORRA SKÅNE, TIDNINGS AB\n\nPnr 28100\n\nHässleholm, Vattug 14. Tel\n0451-142 00\n\nVerksamhet: Tidnings-, bok- o\nciviltryckeri, bokbinderi. Utger\ntidningen Norra Skåne\nAntal anställda: 126\nAktiekapital: 240 000\nVerkst din Harald Skoglösa\nEtableringsår: 1900.\n\nNORRA VÄSTERBOTTEN\nTIDNINGS-AB\n\nPnr 93101\n\nSkellefteå 1, Kanalg 61. Box 58. Tel\n0910-14000. Bankgiro 764-0345.\nPostgiro 34840-8. Telex 6872\nVerksamhet: Tidningsutgivning.\nUtger tidningen Norra Västerbotten\nAntal anställda: 105\nÅrsomsättning: 8 200 000\nAktiekapital: 900 000\nVerkst dir: Simon Enqvist\nEtableringsår: 1910.\n\nSWANSON AB, ROBERT\n\nPnr 502 34\n\nBorås, Skaraborgs v 30. Tel\n033-112237, 110051. Bankgiro\n839-2748. Postgiro 170631.\nTga Swansons\n\nVerksamhet: Tillverkar\ndamklänningar, klänningsrockar, kjolar,\nnylonrockar\nAntal anställda: 50\nÅrsomsättning: 5 000 000\nAktiekapital: 30 000\nVerkst dir: Robert Swanson\nEtableringsår: 1941.\n\nSVANSTRUM &amp; CO,\nAB ERNST G\n\nPnr 116 25\n\nStockholm, Ostgötag 45. Tel\n08-44 56 55, 44 55 95. Bankgiro\n283-8662. Postgiro 3655-8. Tga\nGes-swan. Telex 1605\nVerksamhet: Agenturer i råkaffe\nAktiekapital: 10 000\nStyrelse: Dir Ove Cargin (ordf),\nfru Inga Wåhlin\nVerkst dir: Fru Inga Wåhlin\nEtableringsår: 1923.\n\nSVANSTROM &amp; CO PAPPERS.\nHANDELS AB, FRANS\n\nPnr 104 60\n\nStockholm, Hammarbyv 76. Tel\n08-2280 60. Bankgiro 560-4590.\nPostgiro 131-3. Tga Svanströms\nVerksamhet: Kontorsmateriel i\ndetalj\n\nAntal anställda: 300\nÅrsomsättning: 36 000 000\nVerkst dir: Bengt Strandberg\nEtableringsår: 1857.\n\nTEKNISKA NEDERLAGET, AB\n\n■ Pnr 104 60\nStockholm. Hammarby Fabriksv\n29-31. Tel 08-44 0515. Bankgiro\n57-1382. Postgiro 3254\nVerksamhet: Grossiströrelse inom\nkem-tekn o kosmetiska branschen\nAntal anställda: 20\nÅrsomsättning: 9 500 000\nAktiekapital: 50 000\nVerkst dir: Lars Josefson\nEtableringsår 1906.\n\nTEKNISKA RÖNTGEN.\nCENTRALEN AB\n\nPnr 104 05\n\nStockholm 50, Björnnäsv 21. Pack.\nTel 08-15 08 80. Bankgiro 728-4581.\nPostgiro 152216-8\nTelex 10349 TRCTEST S. Tga\nNondestructive\n\nVerksamhet Provning, kontroll o\nbesiktning vid byggnad vid\növersyner av produktionsanläggningar\nsamt för kvalitetsövervakning vid\ntillverkning av svetsade produkter\n(se vidare under Inköpsregistrets\nrubriker Konsulterande Ingenjörer\no Materialprovning).\nRegions- o lokalkontor:\nStockholm, Malmö, Göteborg,\nJönköping, Örebro, Sundsvall.\nKarlstad, Västerås, Borlänge, Gävle,\nLuleå\n\nAntal anställda: 270\nÅrsomsättning: 16 000 000\nAktiekapital: 720 000\nVerkst dir. Perenc de Kazinczy\nEtableringsår: 1941.\n\nANDERSSON, AB MARCUS\n\nPnr 702 22\n\nÖrebro, Drottningg 29. Tel\n019-119480. Bankgiro 61-4314.\nPostgiro 28389. Tga Nyshat\nVerksamhet: Lädergrossist\nAktiekapital: 60 000\nVerkst dir: Marcus Andersson\nEtableringsår: 1914.\n\nANDERSSON ARKITEKT- &amp;\nINGENJURSBYRÅ AB,\nMELKER\n\nPnr 58104\n\nLinköping 1, Sankt Larsg 9. Box\n434. Tel 013-11 1080. Bankgiro\n120-2076. Postgiro 263481-4\nVerksamhet: Konsulterande företag\nför husbyggnader, värme-,\nventilations- o sanitetstekniska\nanläggningar samt elektr installationer\nAntal anställda: 30\nAktiekapital: 20000\nStyrelse: Ark SAR Gunnar Måbäck\n(ordf), Ing Melker Måbäck\nVerkst dir: Ing Melker Måbäck\nEtableringsår: 1930.\n\nANDERSSON,\nVERKTYGS-BOLAGET NG\n\nPnr 330 33\n\nHillers torp. Tel 0370-22139,\n\n222 20\n\nVerksamhet: Tillverkar alla slags\nverktyg, specialitet: stans-,\ndrag-o pressgjutningsverktyg,\ngravyr-artjeten. Gnistbearbetning\nÄgare o chef: Pabr N G Andersson\nEtableringsår: 1954.\n\nANDERSSON, GRANIT AB,\nNILS\n\nPnr 453 00\n\nLysekil. Lyse. Tel 0523-610 31,\n600 10. Bankgiro 548-2047.\nPostgiro 168 348-1\n\nVerksamhet: Tillverkar råkantsten,\n\ngatsten\n\nAntal anställda: 42\nÅrsomsättning: 1200 000\nAktiekapital: 10000\nVerkst dir: Pabr Nils Andersson\nEtableringsår: 1920.\n\nANDERSON AB, OLLE\n\nPnr 50108\n\nBorås 1, Skaraborgsv 35. Box 544.\nTel 033-137265. Bankgiro\n839-2268. Postgiro 371936-6\nVerksamhet: Tillverning av\nklänningar, dräkter o dressar, blusar,\nAntal anställda: 60\nÅrsomsättning: 5 000 000\nAktiekapital: 40 000\nFirmatecknare: Olle Anderson,\nLia Anderson\nEtableringsår: 1946.\n\nANDERSON I OREBRO AB,\nPAUL\n\nPnr 703 56\n\nÖrebro, Lövstag 15 D. Tel\n019-1188 25. Bankgiro 815-5814.\nPostgiro 71640-7. Tga Pander\nVerksamhet: Säljer förnödenheter\ntill sko- o lädervarufabrikanter\n\nÅrsomsättning: 1000 000\nAktiekapital: 30 000\nVerkst dir: Göte Anderson\nEtableringsår: 1967.\n\nKAB|, AB\n\nPnr 104 25\n\nStockholm 30, Lindhagensg 133.\nFack. Tel 08-54 0960. Bankgiro\n56-7029. Postgiro 58002. Telex 17065.\nTga Kabiochem\n\nVerksamhet: Tillverkar läkemedel\no läkemedelsråvaror samt kliniska\nreagenser\nVarunamn: Kab i\nAntal anställda: 948\nÅrsomsättning: 117 000 000\nAktiekapital: 32 000 000\nStyrelse: Rikspolischef Carl G\nPersson (ordf), dr Tony Hagström,\ndir Gunnar Svärd, docent Lennart\nSchotte, dir \"Bertil Odelfelt, dir Nils\nHolgerson, dr David Isaksson\nVerkst dir: David Isaksson\nEtableringsår: 1931\nBolaget äges av Statsföretag AB\n(2/3) oPripp-Bryggerierna AB (1/3).\nDotterbolag: Grummebolagen, AB\nRecip, Deutsche Kabi GmbH,\nMUnchen, Tyskland. Kabi\nPhar-maceuticals Ltd, London, England.\nA/S Kabi, Lysaker, Norge. Oy Kabi\n\nAB, Helsingfors, Finland.\nKabi-pharmN.V., Amsterdam, Holland.\n\nKABO PLASTICINDUSTRI, AB\n\nPnr 124 40\n\nBandhagen, Stallarholmsv 48. Tel\n08-8604 10. Bankgiro 33-2075.\nPostgiro 357543\n\nVerksamhet: Tillverkar\nformsprut-gods, 3-dimensionella skyltar\nAntal anställda: 115\nÅrsomsättning: 8 000 000\nAktiekapital: 250 000\nFinnatecknare: A Carlsson, K E\nBlomqvist\n\nEtableringsår: 1947.\n\nIDUS, AB\n\nPnr 191 21\n\nSollentuna 1, Anhaltsv 45. Box 65.\nTel 08-35 42 78, 35 46 78. Bankgiro\n729-2725. Postgiro 28988-4\nVerksamhet: Säljer lönesystem\nAktiekapital: 80 000\nVerkst dir Gösta Ostman\nEtableringsår: 1953.\n\nPROJEKTFINANS AB\n\nPnr 11134\n\nStockholm, Sveav 33. Tel\n08-2170 38. Bankgiro 42-0566.\nPostgiro 605515. Tga Profinans\nVerksamhet: Ekonomisk konsult,\nfinansmäklare, kapitalplacerare\nAntal anställda: 3\nAktiekapital: 5 000\nVerkst dir: Bo Sörman Zandén\nDir: John Magnell\nEtableringsår: 1961.\n\nROSTFRIA INREDNINGAR, AB\n\nPnr 220 04\n\nLund 4, Palkv 14. Pack. Tel\n046-12 78 87, 14 23 80. Bankgiro\n869-4499. Postgiro 538074-6\nVerksamhet: Tillverkar inredningar\no utrustningar för gatukök, barer,\nrestauranger o cafeterior\nVarunamn: Ri\nAktiekapital: 45 000\nChef: Fabr Arne Ljungberg\nEtableringsår: 1962.\n\nBULTEN•KANTHAL AB\n\nPnr 734 01\n\nHallstahammar. Tel 0220-105 00.\nBankgiro 114-4401. Postgiro\n10242-6. Tga Bulten.\nTelex 4714 BULTEN S, 4756\nBULTEN S\nAntal anställda: 4 400\nÅrsomsättning: 350 000 000\nAktiekapital: 40 890 000\nStyrelse: Generalkonsul Ragnar\nSöderberg (ordf), disp Hans v Kant&gt;\nzow, adv Hugo Stenbeck, frih Gösta\nDe Geer, disp Helmer Nathorst,\ndir Bo Ehrner\n\nVerkst dir: Helmer Nathorst\nV verkst dir: Alfred E Rapp\nCentrala staber:\nFinans: Finansdir B Brundin\nEkonomi: Ekonomidir Sture\nEdwardson\n\nProduktion: Produktionsdir Lars\nHolmberg\n\nUtveckling: Utvecklingsdir Erik\nStenfors\n\nPersonal: Personaldir Gösta\nHildingson\n\nMarknadsföring: Marknadsdir Lars\nFjordman\n\nInternationella frågor: Utlandsdir\nLennart Nisser\nEtableringsår: 1873.\n\nBULTENDIVISIONEN\n734 01 Hallstahammar. Tel\n0220-105 00. Telex 4714 BULTEN S,\n4756 BULTEN S. Tga Bulten\nVerksamhet: Tillverkar skruvar,\nmuttrar, nitar, brickor o andra\nbult-artiklar av stål; kallformade,\nvarmsmidda o svarvade detaljer\nVarunamn: Bufo,\nPhillips-Pozi-driv, Insex, Loc-King\nDivisionschef: Mauritz Sahlin\nFörsäljning Sverige: Bruno\nLundberg\n\nFörsäljning Export: Benoit Mordo\nDistriktskontor o lager:\n\nGöteborg, Fröhusg 8. Box 2028,\n421 02 Västra Frölunda 2. Tel\n031-45 08 25. Chef: Folke Jonsson\n211 24 Malmö, Borrg 17. Tel\n040-93 57 30. Chef: Erik Nervall\n100 72 Stockholm 43, Förmansv 26.\nBox 43003. Tel 08-45 25 60. Chef:\nRobert Källgren\n\n852 36 Sundsvall, O Långg 3. Tel\n060-15 05 35. Chef: Bert Brunnzell.\n\nKANTHALDIVISIONEN\n734 01 Hallstahammar. Tel\n0220-116 00. Telex 4744 KANTHAL S,\n40649 KANTHAL S. Tga Kanthal\nVerksamhet: Tillverkar elektr\nmotståndsmaterial, bimetall,\ntermo-elementtråd, eldhärdiga, rostfria o\nsyrafasta rör\n\nVarunamn: Kanthal, Kanthal Super,\nNikrothal\n\nDivisionschef: Björn Edwin\nFörsäljning Skandinavien: Ake\n\nLindblad\n\nFörsäljning Export: Per Kull\nEtableringsår: 1931.\n\nGJUTGODSDI VISIONEN\n(tidigare under AB Kanthal)\n734 01 Hallstahammar. Tel\n0220-116 00. Telex 4744 KANTHAL S,\n40649 KANTHAL S. Tga Kanthal\nVerksamhet: Tillverkar\nprecisions-gjutgods\n\nDivisionschef: Erik Stenfors\nFörsäljning: Iwar Stadier.\n\nRAMNÄS BRUK-DIVISIONEN\n730 60 Ramnäs. Tel 0220-35100.\nTelex 4753 RAMNAES S. Tga\nRamnäsbruk, Västerås\nVerksamhet: Tillverkar\nankarkät-ting, lyftkätting, kätting för\nskogs-o flottningsändamål; diskbänkar,\ntvättbänkar o tvättlådor av\nrostfritt stål; sågade trävaror\nDivisionschef: Berth von Kantzow\nFörsäljn-chef: Axel Norling\nFörsäljning Export: Karl Elworth\nSkogschef: Nils Runnérus\nEtableringsår: 1874.\n\nKEDJEDIVISIONEN\n(tidigare Eskilstuna Fabriks AB)\n631 04 Eskilstuna 1, Kungsg 41. Box\n304. Tel 016-137410. Telex 40983\nCHAIN S. Tga Fabriksbolaget\nVerksamhet: Tillverkar\nprecisions-rullkedjor enl europeisk o\namerikansk standard, fleyer-,\ntransportör- o specialkedjor, kedjehjul.\n\"Fenestra\"-mellanväggar av stål\nVarunamn: FB, Fenestra\nDivisionschef: John H Haglund\nFörsäljning: Reidar Eriksson\nEtableringsår: 1908.\n\nASHAMMAR- DIVISIONEN\n810 25 Ashammar. Tel 0290-502 70.\nTga Ashammars Bultfabrik, Gävle.\nPostgiro 13033\n\nVerksamhet: Tillverkar bultvaror i\nrostfritt o syrafast stål\nDivisionschef: Axel Adolfsson\nEtableringsår: 1899.",
    "structured": {
        "1": {
            "company_name": "NAHRMEKO AB",
            "pnr": "57100",
            "address": "Nässjö. Box 159. Storg 48.",
            "phone_number": "0380-103 80, 183 80",
            "bank_details": {
                "bankgiro": "251-1277",
                "postgiro": "715848-8"
            },
            "activity": "Tillverkar automatiska paketeringsmaskiner, filtrerings-utrustningar för öl-, jäst- o annan industri samt legotillverkning",
            "employees": 40,
            "annual_turnover": 2800000,
            "capital": 100000,
            "key_personnel": [
                {
                    "name": "Dir Charles Nahrström",
                    "position": "Styrelse"
                },
                {
                    "name": "fru Gretha Nahrström",
                    "position": "Styrelse"
                },
                {
                    "name": "civiling Jan Narström",
                    "position": "Styrelse"
                },
                {
                    "name": "fil kand Mats Narström",
                    "position": "Styrelse"
                },
                {
                    "name": "Charles Nahrström",
                    "position": "Verkst dir"
                }
            ],
            "establishment_year": 1968
        },
        "2": {
            "company_name": "NORMEK, AB",
            "pnr": "117 44",
            "address": "Stockholm, Nybohovsbacken 50.",
            "phone_number": "08-18 6109, 18 6113",
            "bank_details": {
                "bankgiro": "744-3468",
                "postgiro": "259559-3"
            },
            "activity": "Säljer verktygsmaskiner, diamantverktyg, diamantskivor o diamantslippasta",
            "employees": 8,
            "capital": 15000,
            "key_personnel": [
                {
                    "name": "Ing Ake Lindblom",
                    "position": "Verkst dir"
                }
            ],
            "establishment_year": 1956
        },
        "3": {
            "company_name": "NORRA KINDS HEM-INDUSTRI, AB",
            "pnr": "520 10",
            "address": "Gällstad.",
            "phone_number": "0321-70052",
            "bank_details": {
                "bankgiro": "840-6282",
                "postgiro": "72585"
            },
            "activity": "Tillverkar sockor, strumpor o vantar",
            "capital": 45000,
            "key_personnel": [
                {
                    "name": "Axel Bolander",
                    "position": "Verkst dir"
                }
            ],
            "establishment_year": 1930
        },
        "4": {
            "company_name": "NORRA SKÅNE, TIDNINGS AB",
            "pnr": "28100",
            "address": "Hässleholm, Vattug 14.",
            "phone_number": "0451-142 00",
            "activity": "Tidnings-, bok- o civiltryckeri, bokbinderi. Utger tidningen Norra Skåne",
            "employees": 126,
            "capital": 240000,
            "key_personnel": [
                {
                    "name": "Harald Skoglösa",
                    "position": "Verkst dir"
                }
            ],
            "establishment_year": 1900
        },
        "5": {
            "company_name": "NORRA VÄSTERBOTTEN TIDNINGS-AB",
            "pnr": "93101",
            "address": "Skellefteå 1, Kanalg 61. Box 58.",
            "phone_number": "0910-14000",
            "bank_details": {
                "bankgiro": "764-0345",
                "postgiro": "34840-8"
            },
            "activity": "Tidningsutgivning. Utger tidningen Norra Västerbotten",
            "employees": 105,
            "annual_turnover": 8200000,
            "capital": 900000,
            "key_personnel": [
                {
                    "name": "Simon Enqvist",
                    "position": "Verkst dir"
                }
            ],
            "establishment_year": 1910
        },
        "6": {
            "company_name": "SWANSON AB, ROBERT",
            "pnr": "502 34",
            "address": "Borås, Skaraborgs v 30.",
            "phone_number": "033-112237, 110051",
            "bank_details": {
                "bankgiro": "839-2748",
                "postgiro": "170631"
            },
            "activity": "Tillverkar damklänningar, klänningsrockar, kjolar, nylonrockar",
            "employees": 50,
            "annual_turnover": 5000000,
            "capital": 30000,
            "key_personnel": [
                {
                    "name": "Robert Swanson",
                    "position": "Verkst dir"
                }
            ],
            "establishment_year": 1941
        },
        "7": {
            "company_name": "SVANSTRUM & CO, AB ERNST G",
            "pnr": "116 25",
            "address": "Stockholm, Ostgötag 45.",
            "phone_number": "08-44 56 55, 44 55 95",
            "bank_details": {
                "bankgiro": "283-8662",
                "postgiro": "3655-8"
            },
            "activity": "Agenturer i råkaffe",
            "capital": 10000,
            "key_personnel": [
                {
                    "name": "Ove Cargin",
                    "position": "Dir"
                },
                {
                    "name": "Inga Wåhlin",
                    "position": "Fru Verkst dir"
                }
            ],
            "establishment_year": 1923
        },
        "8": {
            "company_name": "SVANSTROM & CO PAPPERS. HANDELS AB, FRANS",
            "pnr": "104 60",
            "address": "Stockholm, Hammarbyv 76.",
            "phone_number": "08-2280 60",
            "bank_details": {
                "bankgiro": "560-4590",
                "postgiro": "131-3"
            },
            "activity": "Kontorsmateriel i detalj",
            "employees": 300,
            "annual_turnover": 36000000,
            "key_personnel": [
                {
                    "name": "Bengt Strandberg",
                    "position": "Verkst dir"
                }
            ],
            "establishment_year": 1857
        },
        "9": {
            "company_name": "TEKNISKA NEDERLAGET, AB",
            "pnr": "104 60",
            "address": "Stockholm. Hammarby Fabriksv 29-31.",
            "phone_number": "08-44 0515",
            "bank_details": {
                "bankgiro": "57-1382",
                "postgiro": "3254"
            },
            "activity": "Grossiströrelse inom kem-tekn o kosmetiska branschen",
            "employees": 20,
            "annual_turnover": 9500000,
            "capital": 50000,
            "key_personnel": [
                {
                    "name": "Lars Josefson",
                    "position": "Verkst dir"
                }
            ],
            "establishment_year": 1906
        },
        "10": {
            "company_name": "TEKNISKA RÖNTGEN. CENTRALEN AB",
            "pnr": "104 05",
            "address": "Stockholm 50, Björnnäsv 21. Pack.",
            "phone_number": "08-15 08 80",
            "bank_details": {
                "bankgiro": "728-4581",
                "postgiro": "152216-8"
            },
            "activity": "Provning, kontroll o besiktning vid byggnad vid översyner av produktionsanläggningar samt för kvalitetsövervakning vid tillverkning av svetsade produkter",
            "employees": 270,
            "annual_turnover": 16000000,
            "capital": 720000,
            "key_personnel": [
                {
                    "name": "Perenc de Kazinczy",
                    "position": "Verkst dir"
                }
            ],
            "establishment_year": 1941
        },
        "11": {
            "company_name": "ANDERSSON, AB MARCUS",
            "pnr": "702 22",
            "address": "Örebro, Drottningg 29.",
            "phone_number": "019-119480",
            "bank_details": {
                "bankgiro": "61-4314"
            },
            "activity": "Lädergrossist",
            "capital": 60000,
            "key_personnel": [
                {
                    "name": "Marcus Andersson",
                    "position": "Verkst dir"
                }
            ],
            "establishment_year": 1914
        },
        "12": {
            "company_name": "ANDERSSON ARKITEKT- & INGENJURSBYRÅ AB, MELKER",
            "pnr": "58104",
            "address": "Linköping 1, Sankt Larsg 9. Box 434.",
            "phone_number": "013-11 1080",
            "bank_details": {
                "bankgiro": "120-2076",
                "postgiro": "263481-4"
            },
            "activity": "Konsulterande företag för husbyggnader, värme-, ventilationso sanitetstekniska anläggningar samt elektr installationer",
            "employees": 30,
            "capital": 20000,
            "key_personnel": [
                {
                    "name": "Ark SAR Gunnar Måbäck",
                    "position": "Styrelse ordf"
                },
                {
                    "name": "Ing Melker Måbäck",
                    "position": "Verkst dir"
                }
            ],
            "establishment_year": 1930
        }
    }
}