{
    "original": "NORSTEDTS ELEKTRISKA AB\n\nPnr 58102\n\nLinköping 1, Box 92. Platensg 6.\nTel 013-10 2240. Bankgiro\n607-9370. Postgiro 131643-9\nVerksamhet: Elektr installatör.\nSäl-jerkylskåp, frysboxar, dammsugare\nsamt elektr hushållsmaskiner o\napparater\n\nAktiekapital: 40 000\nVerkst dir: Gösta Norstedt\nEtableringsår 1925\nOmbildat till aktiebolag 1958.\n\nNORSTEDT &amp; SÖNER, AB P A\n\nPnr 10312\n\nStockholm 2, Tryckerig 2. Box\n2052. Tel 08-22 80 40. Bankgiro\n568-9401. Postgiro 93-5. Tga\nNorstedts\n\nVerksamhet: Tryckeri, stilgjuteri,\nbokförlag, skolmateriel\nSkolavdelning: 10430Stockholm45,\nDrottningg 108. Box 45120. Tel\n08-34 9210\n\nAntal anställda: 1700\nÅrsomsättning: 170 000 000\nAktiekapital: 14000000\nVerkst dir: Hovrättsrådet Bengt\nLassen\n\nEtableringsår: 1823.\n\nWIJKST ROM, AB A G\n\nPnr 11122\n\nStockholm C, Kungsg 51. Tel\n08-1093 17, 2178 61. Bankgiro 72-2353.\nPostgiro 351314. Tga Agew\nVerksamhet: Importerar o säljer\näkta stenar o pärlor till juvelerare\nAntal anställda: 3\nAktiekapital: 50 000\nVerkst dir: Gunnar Wijkström\nEtableringsår: 1938.\n\nOREBRO VÄRMEINDUSTRI AB\n\nPnr 705 90\n\nÖrebro, Postl 5692. Tel\n019-16 00 20. Bankgiro 614-5312.\nPostgiro 338500-2\n\nVerksamhet: Tillverkar o säljer\nelvärmepannor o elektr\nvarmvattenberedare\n\nVarunamn: OVI Autoterm\nAntal anställda: 20\nÅrsomsättning: 3 000 000\nAktiekapital: 75 000\nStyrelse: Disp Bengt Ohlsson, dir\nBengt Holmström\nVerkst dir: Ing Bengt Holmström\nEtableringsår: 1954.\n\nOREBRO ÅKERICENTRAL\nEK FOR\n\nPnr 700 02\n\nÖrebro 2, Industrig 10. Box 2057.\nTel 019-13 64 40. Bankgiro\n815-7687. Postgiro 270494-8\nVerksamhet: Lastbilscentral.\nUtför alla slags transporter\nAntal anställda: 13\nÅrsomsättning: 18 000 000\nChef: Disp Bertil Berglöf\nEtableringsår: 1936.\n\nÖREBROELEMENT AB\n\nPnr 70104\n\nÖrebro 1, Olaig 38. Box 290. Tel\n019-13 02 60. Postgiro 666360-3\nVerksamhet: Projekterar, ritar,\ntillverkar o bygger\nmonterings-färdiga butikshus\nÅrsomsättning: 2 000 000\nAktiekapital: 5 000\nStyrelse: Bertil Åhrén (ordf), Olle\nFröberg, Anita Sandën\nVerkst din Olle Fröberg\nEtableringsår: 1964.\n\nÖREBRO-KURIREN,\nTRYCKERI-AB\n\nPnr 70105\n\nÖrebro 1, Olaig 9. Box 327. Tel\n019-1194 40. Bankgiro 35-8887.\nPostgiro 6245-5. Telex 73227\nVerksamhet: Utger även\nKarlskoga-Kuriren\n\nAntal anställda: 116\nÅrsomsättning: 7 200 000\nAktiekapital: 816 325\nVerkst dir: Lennärt Karlsson\nEtableringsår: 1902.\n\nENGELHARDT &amp; CO AB, B\n\nPnr 42121\n\nVästra Frölunda 1, Box 49. Näsetv.\nTel 031-49 02 95. Bankgiro\n506-8234. Postgiro 529785-8.\nTelex 20914 ENGELHA S\nVerksamhet: Importerar, exporterar\no tillverkar hjälpmedel för\nlivsmedelsindustrin\n\nVarunamn: Emulphan, Monobas,\nMonomilk\nAntal anställda: 8\nAktiekapital: 100000\nVerkst dir. Ing Leif Ericson\nEtableringsår. 1962.\n\nELEKTRA I EDSBYN AB\n\nPnr 828 00\n\nEdsbyn. Box 82. Långg 28. Tel\n0271-21230. Bankgiro 786-0265.\nPostgiro 82412-8\n\nVerksamhet: Säljer el artiklar. Utför\nelinstallationer o elreparationer\nAntal anställda: 60\nÅrsomsättning: 4 000 000\nAktiekapital: 50 000\nVerkst din Göran Lindén\nEtableringsår. 1970.\n\nSUNDSVALLSBRYGGERIER AB\n\nPnr 852 34\n\nSundsvaU, Akersviksg 10. Tel\n060-15 74 90. Bankgiro 18-0268.\nPostgiro 125461\n\nVerksamhet: Tillverkar o säljer\nmalt- o läskedrycker\nAntal anställda: 100\nÅrsomsättning: 13 000 000\nAktiekapital: 900 000\nVerkst dir: Gösta Valentin\nEtableringsår: 1897.\n\nKDR\n\nskiner o utensilier för butiker\nAntal anställda: 145\nÅrsomsättning: 44000 000\nAktiekapital: 500 000\nVerkst dir: Ove Anderson\nEtableringsår: 1938\nEtt ICA-företag.\n\nKÖPMANNEN, ORGAN FOR\nSVERIGES KOPMANNAFOR.\nBUND\n\nPnr 105 61\n\nStockholm C, Mäster Samuelsg 22.\n\nTel 08-24 40 40. Bankgiro 72-5003.\nPostgiro 890. Tga\nKöpmannaförbund\n\nVerksamhet: Tidningsutgivning\nAntal anställda: lo\nÅrsomsättning: 2 036 000\nAktiekapital: 17 540\nVerkst dir: Bengt Wahlstedt\nEtableringsår: 1908.\n\nCORONIK, AB\n\nPnr 182 51\n\nDjursholm, Box 12. Bragev 30. Tel\n08-753 04 90. Bankgiro 611-0837.\nPostgiro 355725-3.\nTelex 10956 UCAB S\nVerksamhet: Korrosionsskyddande\nbeläggningar, rör, tankar, fläktar o\nandra utrustningar utförda i\nglas-fiberarmerade härdplaster.\nLuftreningsanläggningar (våtavskiljare)\nVarunamn: Ceilcote\nAntal anställda: 4\nAktiekapital: 30000\nVerkst dir: Börje Skånberg\nEtableringsår: 1970,\n\nNORDBETONG, AB\n\nPnr 891 01\n\nÖrnsköldsvik 1, Strandg 7. Box 165.\nTel 0660-17840. Bankgiro\n771-7093. Postgiro 112449-4.\nTga Nordbetong.\nTelex 6050 HAEGG S\nVerksamhet: Tillverkar\nprefabricerade betongelement\nFabrik: Långviksmon. Tel\n0662-302 50\n\nAntal anställda: 115\nÅrsomsättning: 10000 000\nAktiekapital: 600 000\nVerkst dir: Gösta Hägglund\nFörsäljn-chef: Jan Olov Edblad\nEtableringsår: 1956.\n\nANDERSFORS FABRIK, AB\n\nPnr 330 30\n\nGnosjö. Tel 0370-910 28. Bankgiro\n542-4676. Postgiro 32870-8. Tga\nAndersfors\n\nVerksamhet: Maskinbockade\ntrådartiklar, massartiklar i band o plåt\n.Aktiekapital: 26 000\nVerkst dir: Werner Karlsson\nEtableringsår. 1908.",
    "structured": {
        "1": {
            "company_name": "NORSTEDTS ELEKTRISKA AB",
            "pnr": "58102",
            "address": "Linköping 1, Box 92. Platensg 6.",
            "phone_number": "013-10 2240",
            "bank_details": {
                "bankgiro": "607-9370",
                "postgiro": "131643-9"
            },
            "activity": "Elektr installatör. Säl-jerkylskåp, frysboxar, dammsugare samt elektr hushållsmaskiner o apparater",
            "capital": 40000,
            "key_personnel": [
                {
                    "name": "Gösta Norstedt",
                    "position": "Verkst dir"
                }
            ],
            "establishment_year": 1925
        },
        "2": {
            "company_name": "NORSTEDT & SÖNER, AB P A",
            "pnr": "10312",
            "address": "Stockholm 2, Tryckerig 2. Box 2052.",
            "phone_number": "08-22 80 40",
            "bank_details": {
                "bankgiro": "568-9401",
                "postgiro": "93-5"
            },
            "activity": "Tryckeri, stilgjuteri, bokförlag, skolmateriel",
            "employees": 1700,
            "annual_turnover": 170000000,
            "capital": 14000000,
            "key_personnel": [
                {
                    "name": "Bengt Lassen",
                    "position": "Verkst dir"
                }
            ],
            "establishment_year": 1823
        },
        "3": {
            "company_name": "WIJKST ROM, AB A G",
            "pnr": "11122",
            "address": "Stockholm C, Kungsg 51",
            "phone_number": "08-1093 17, 2178 61",
            "bank_details": {
                "bankgiro": "72-2353",
                "postgiro": "351314"
            },
            "activity": "Importerar o säljer äkta stenar o pärlor till juvelerare",
            "employees": 3,
            "capital": 50000,
            "key_personnel": [
                {
                    "name": "Gunnar Wijkström",
                    "position": "Verkst dir"
                }
            ],
            "establishment_year": 1938
        },
        "4": {
            "company_name": "OREBRO VÄRMEINDUSTRI AB",
            "pnr": "705 90",
            "address": "Örebro, Postl 5692",
            "phone_number": "019-16 00 20",
            "bank_details": {
                "bankgiro": "614-5312",
                "postgiro": "338500-2"
            },
            "activity": "Tillverkar o säljer elvärmepannor o elektr varmvattenberedare",
            "annual_production_value": "OVI Autoterm",
            "employees": 20,
            "annual_turnover": 3000000,
            "capital": 75000,
            "key_personnel": [
                {
                    "name": "Bengt Ohlsson",
                    "position": "Disp"
                },
                {
                    "name": "Bengt Holmström",
                    "position": "dir"
                }
            ],
            "establishment_year": 1954
        },
        "5": {
            "company_name": "ÖREBRO ÅKERICENTRAL EK FOR",
            "pnr": "700 02",
            "address": "Örebro 2, Industrig 10. Box 2057",
            "phone_number": "019-13 64 40",
            "bank_details": {
                "bankgiro": "815-7687",
                "postgiro": "270494-8"
            },
            "activity": "Lastbilscentral. Utför alla slags transporter",
            "employees": 13,
            "annual_turnover": 18000000,
            "key_personnel": [
                {
                    "name": "Bertil Berglöf",
                    "position": "Disp"
                }
            ],
            "establishment_year": 1936
        },
        "6": {
            "company_name": "ÖREBROELEMENT AB",
            "pnr": "70104",
            "address": "Örebro 1, Olaig 38. Box 290",
            "phone_number": "019-13 02 60",
            "postgiro": "666360-3",
            "activity": "Projekterar, ritar, tillverkar o bygger monterings-färdiga butikshus",
            "annual_turnover": "2 000 000",
            "capital": 5000,
            "key_personnel": [
                {
                    "name": "Bertil Åhrén",
                    "position": "ordf"
                },
                {
                    "name": "Olle Fröberg",
                    "position": null
                },
                {
                    "name": "Anita Sandën",
                    "position": null
                }
            ],
            "establishment_year": 1964
        },
        "7": {
            "company_name": "ÖREBRO-KURIREN, TRYCKERI-AB",
            "pnr": "70105",
            "address": "Örebro 1, Olaig 9. Box 327",
            "phone_number": "019-1194 40",
            "bank_details": {
                "bankgiro": "35-8887",
                "postgiro": "6245-5"
            },
            "activity": "Utger även Karlskoga-Kuriren",
            "employees": 116,
            "annual_turnover": 7200000,
            "capital": 816325,
            "key_personnel": [
                {
                    "name": "Lennärt Karlsson",
                    "position": "Verkst dir"
                }
            ],
            "establishment_year": 1902
        },
        "8": {
            "company_name": "ENGELHARDT & CO AB, B",
            "pnr": "42121",
            "address": "Västra Frölunda 1, Box 49. Näsetv",
            "phone_number": "031-49 02 95",
            "bank_details": {
                "bankgiro": "506-8234",
                "postgiro": "529785-8"
            },
            "activity": "Importerar, exporterar o tillverkar hjälpmedel för livsmedelsindustrin",
            "employees": 8,
            "capital": 100000,
            "key_personnel": [
                {
                    "name": "Ing Leif Ericson",
                    "position": "Verkst dir"
                }
            ],
            "establishment_year": 1962
        },
        "9": {
            "company_name": "ELEKTRA I EDSBYN AB",
            "pnr": "828 00",
            "address": "Edsbyn. Box 82. Långg 28",
            "phone_number": "0271-21230",
            "bank_details": {
                "bankgiro": "786-0265",
                "postgiro": "82412-8"
            },
            "activity": "Säljer el artiklar. Utför elinstallationer o elreparationer",
            "employees": 60,
            "annual_turnover": 4000000,
            "capital": 50000,
            "key_personnel": [
                {
                    "name": "Göran Lindén",
                    "position": "Verkst dir"
                }
            ],
            "establishment_year": 1970
        },
        "10": {
            "company_name": "SUNDSVALLSBRYGGERIER AB",
            "pnr": "852 34",
            "address": "SundsvaU, Akersviksg 10",
            "phone_number": "060-15 74 90",
            "bank_details": {
                "bankgiro": "18-0268",
                "postgiro": "125461"
            },
            "activity": "Tillverkar o säljer malt- o läskedrycker",
            "employees": 100,
            "annual_turnover": 13000000,
            "capital": 900000,
            "key_personnel": [
                {
                    "name": "Gösta Valentin",
                    "position": "Verkst dir"
                }
            ],
            "establishment_year": 1897
        },
        "11": {
            "company_name": "KDR",
            "activity": "skiner o utensilier för butiker",
            "employees": 145,
            "annual_turnover": 44000,
            "capital": 500000,
            "key_personnel": [
                {
                    "name": "Ove Anderson",
                    "position": "Verkst dir"
                }
            ],
            "establishment_year": 1938
        },
        "12": {
            "company_name": "KÖPMANNEN, ORGAN FOR SVERIGES KOPMANNAFOR. BUND",
            "pnr": "105 61",
            "address": "Stockholm C, Mäster Samuelsg 22",
            "phone_number": "08-24 40 40",
            "bank_details": {
                "bankgiro": "72-5003",
                "postgiro": "890"
            },
            "activity": "Tidningsutgivning",
            "employees": 10,
            "annual_turnover": 2036000,
            "capital": 17540,
            "key_personnel": [
                {
                    "name": "Bengt Wahlstedt",
                    "position": "Verkst dir"
                }
            ],
            "establishment_year": 1908
        },
        "13": {
            "company_name": "CORONIK, AB",
            "pnr": "182 51",
            "address": "Djursholm, Box 12. Bragev 30",
            "phone_number": "08-753 04 90",
            "bank_details": {
                "bankgiro": "611-0837",
                "postgiro": "355725-3"
            },
            "activity": "Korrosionsskyddande beläggningar, rör, tankar, fläktar o andra utrustningar utförda i glas-fiberarmerade härdplaster. Luftreningsanläggningar (våtavskiljare)",
            "employees": 4,
            "capital": 30000,
            "key_personnel": [
                {
                    "name": "Börje Skånberg",
                    "position": "Verkst dir"
                }
            ],
            "establishment_year": 1970
        },
        "14": {
            "company_name": "NORDBETONG, AB",
            "pnr": "891 01",
            "address": "Örnsköldsvik 1, Strandg 7. Box 165",
            "phone_number": "0660-17840",
            "bank_details": {
                "bankgiro": "771-7093",
                "postgiro": "112449-4"
            },
            "activity": "Tillverkar prefabricerade betongelement",
            "employees": 115,
            "annual_turnover": 10000000,
            "capital": 600000,
            "key_personnel": [
                {
                    "name": "Gösta Hägglund",
                    "position": "Verkst dir"
                }
            ],
            "establishment_year": 1956
        },
        "15": {
            "company_name": "ANDERSFORS FABRIK, AB",
            "pnr": "330 30",
            "address": "Gnosjö",
            "phone_number": "0370-910 28",
            "bank_details": {
                "bankgiro": "542-4676",
                "postgiro": "32870-8"
            },
            "activity": "Maskinbockade trådartiklar, massartiklar i band o plåt",
            "capital": 26000,
            "key_personnel": [
                {
                    "name": "Werner Karlsson",
                    "position": "Verkst dir"
                }
            ],
            "establishment_year": 1908
        }
    }
}