{
    "original": "HEV\n\nAktiekapital: 378 000\nVeikst dir: Nils Aastrup\nEtableringsår: 1881.\n\nIKO KABELFABRIK AB\n\nPnr 510 94\n\nGrimsås. Tel 0325-74 1 00.\nBankgiro 55-3146. Postgiro 160994.\nTelex 36017. Tga Iko\n\nTillverkar plastisolerade\nledningar och kablar för\nsåväl svag- som starkström\n\nAntal anställda: 400\nÅrsomsättning: 120000 000\nAktiekapital: 5 000000\nVerkst dir Vilhelm Tham\nEtableringsår 1947.\n\nBYG\n\nVerksamhet: Utför hus- o\nindustribyggnader, väg- o vattenbyggnader\nAntal anställda: 100\nÅrsomsättning: 8 000 000\nAktiekapital: 100000\nVerkst dir: Byggmäst Stig Carlsson\nEtableringsår: 1957.\n\nUHLÉN &amp; NORD AB\n\nPnr 12173\n\nJohanneshov, Brunnbyv 20. Tel\n08-9104 30. Bankgiro 864-2142.\nPost-giro 1285-6. Tga Uhlennord.\nStockholm\n\nVerksamhet: Import av hästkött o\nrimmad lax\n\nVerkst dir: Allan Uhlén\nEtableringsår 1910\nOmbildat till aktiebolag 1962.\n\nULFERTS FABRIKER AB\n\nPnr 543 01\n\nTibro 1, Box 46. Tel 0504-116 00.\nBankgiro 221-3908. Postgiro\n175110-6. Tga Ulferts\nVerksamhet: Tillverkar skåp, bord,\nstolar, hyllserier,\nkompletteringsmöbler, stoppmöbler, sängar. Plast\nUtställningen i Stockholm:\n\"Möbelcenter\", Storängsv 10, Sthlm NO.\nTel 08-62 02 82\nAntal anställda: 537\nÅrsomsättning: 72 000 000\nAktiekapital: 1000 000\nVerkst dlr: Harald Ulfenborg\nEtableringsår 1942\nOmbildat till aktiebolag 1959.\n\nULLASJO\nPÄLSDJURS-FARM, AB\n\nPnr 510 70\n\nSvensljunga. Kontor: 412 71\nGöteborg, Prästgårdsängen 8. Tel\n031-4099 83\n\nVerksamhet: Uppfödning av mink o\nblåräv\n\nAntal anställda: 45\nÅrsomsättning: 4 000 000\nAktiekapital: 250 000\nVerkst dir. Einar Ullman\nEtableringsår: 1936.\n\nFRODINGE MEJERI AB\n\nPnr 598 00\n\nVimmerby. Tel 0492-402 00\nVerksamhet: Tillverkar o säljer\nFVödinge Ostkaka, vegetabilisk\nost samt livsmedelsaerosoler,\nfärdigvisp, kryddspray o\nbak-formsspray\nAntal anställda: 60\nÅrsomsättning: 16 000 000\nAktiekapital: 100 000\nVerkst dir: Gösta Carlsson\nEtableringsår: 1969.\n\nSVENSK TORVFüRÄDLING, AB\n\nPnr 28010\n\nSösdala, Box 152. Tel 0451-64 0 7 0.\nBankgiro 286-2356. Postgiro\n175708-7. Tga Humus. Telex 4448\n\nVerksamhet: Tillverkar o säljer\ntorv för jordförbättrings ändamål\nVarunamn: Kronmull, Trädgårdstorv\nAntal anställda: 65\nÅrsomsättning: 6 000 000\nAktiekapital: 5 000 000\nVerkst dir. Nils Wahlquist\nEtableringsår: 1939.\n\nSVENSK TRÄBYGGNADS.\nTEKNIK, AB\n\nPnr 112 52\n\nStockholm, Olof Dalins v 14. Tel\n08-5243 26, 5243 28. Bankgiro\n733-8171. Postgiro 55332-1\nVerksamhet: Konstruerar, säljer o\nmonterar limträ, hallbyggnader o\ntakstolar i fribärande utförande\nVarunamn: HB, STT\nAktiekapital: 200 000\nÄgare o chefer: Ing Erik Barkeling,\ning Leif Ek\nEtableringsår: 1957.\n\nKUGELVERKEN AB\n\nPnr 580 06\n\nLinköping 6, Box 6110. Gamla\nTan-neforsv 16-18. Tel 013-10 24 30.\nBankgiro 120-4445. Postgiro\n367870-3. Telex 64923 ABEKO S\nVerksamhet: Tillverkar\ngaffelstap-lare, truckar\nVarunamn: Abeko\nAntal anställda: 25\nÅrsomsättning: 3 000 000\nAktiekapital: 75 000\nVerkst dir: Gösta Kugelberg\nEtableringsår: 1948.\n\nBJELKES, AB\n\nPnr 691 01\n\nKarlskoga 1, Värmlandsv 76. Box\n8. Tel 0586-362 60. Bankgiro\n109-0927. Postgiro 81490-5\nVerksamhet: Tillverkar\nbyggnadssnickerier o emballage. Säljer\nträvaror o alla slag av\nbyggnadsmaterial. Utför tak- o golvläggningar\nAntal anställda: 95\nÅrsomsättning: 12 700 000\nAktiekapital: 143 000\nVerkst dir: Fabr Ragnar Jansson\nEtableringsår: 1935.\n\nSTE\n\nSTENSTORPS\nTRÄ-PRODUKTER AB\n\nPnr 520 50\n\nStenstorp, Box 60. Hantverksg 30.\nTel 0500-504 00. Bankgiro\n530-6246. Postgiro 717131-7\nVeiksamhet: Tillverkar o säljer\nlamellträ i standardformat o\nskärningar, belagt med abaehi, board\neller önskat material. Limfog i\nskärningar, även belagt med önskat\nmaterial\n\nAntal anställda: 40\nÅrsomsättning: 3 000 000\nAktiekapital: 50 000\nVerkst dir: Erik Johansson\nKamrer: M Henriksson\nVerkmäst: A Johnsson\nEtableringsàr: 1928.\n\nSTENSTRÖMS SKJORT.\nFABRIK, AB\n\nPnr 252 57\n\nHelsingborg, Regementsv 1. Tel\n042-180180. Bankgiro 652-8343.\nPostgiro 80080-5. Tga Skjortsten\nVerksamhet: Tillverkar o säljer\nexklusiva skjortor\nAntal anställda: 180\nAktiekapital: 360 000\nVerkst dir Lars Béen\nEtableringsàr: 1899\nDotterbolag: Linköpings\nLinnefabriks AB.\n\nSTEREO-MAT\n\nPnr 114 25\n\nStockholm, Fryxellsg 4. Tel\n08-11 19 80. Kont 6145 47\nVerksamhet: Annonssätteri,\nstereotyper, matriser, plastduplikat,\nfotosättning o tryckeri\nÄgare o chef: H R Krantz\nEtableringsàr: 1953.\n\nSTERN &amp; CO AB, JOHN\n\nPnr 102 43\n\nStockholm 5, Grev Tureg 35. Box\n5099. Tel 08-67 3142. Postgiro\n54777-8. Tga Sternagent\nVerksamhet: Generalrepresentant\nför dörrstängare\nÅrsomsättning: 100 000\nAktiekapital: 15 000\nVerkst dir: Bengt Alrutz\nEtableringsàr: 1953.\n\nSTERNBERG-TEXTIL AB\n\nPnr 111 45\n\nStockholm, Birger Jarlsg 7. Tel\n08-2140 02, 2140 04. Bankgiro\n44-7148. Postgiro 4638. Tga Sterntex\nVerksamhet: Agenturer i\ntextilvaror såsom trikåvaror. Tillverkar\ntvättmedlet Sterlon Tvättcreme\nVarunamn: Sterlon\nÄgare o chefer: Olle Orrskog, Ake\nNaesström\nEtableringsàr: 1950.\n\nSTERNE &amp; SÖNER\n\nPnr 573 00\n\nTranås, Högg 4. Tel 0140-100 30.\n\nTga Borghsterne\n\nVerksamhet: Säljer\ntapetserarmate-rial, möbeltyger, mattor,\nheminredningstextilier o pappersvaror i parti.\n\nSTERNERS SPECIAL.\nFABRIKS AB\n\nPnr 780 51\n\nDala-Järna, Box 28. Tel\n0281-202 69, 202 70. Bankgiro 465-8340.\nPostgiro 322220-5. Tga\nSterner-bolaget\n\nVerksamhet: Tillverkar automater\nför frimärken, biljetter samt\nsjukvårds- o sanitetsartiklar,\nmyntautomater, automatiska\nskoputsnings-maskiner samt sanitetskärl\nAntal anstäUda: 24\nÅrsomsättning: 2 000 000\nAktiekapital: 60 000\nStyrelse: Dir Erie U Sterner (ordf),\nfru Ellen D Sterner, ing Ruben N\nSterner\n\nVerkst dir: Erie U Sterner\nEtableringsàr 1946.\n\nBURMANS MEK VERKSTAD\n\nPnr 571 00\n\nNässjö, Verkstadsg 7. Tel\n0380-118 04\n\nVerksamhet: Tillverkar\nsammansättningsmaskiner för snickerier\nm fi\n\nÄgare o chef: Fabr Torsten\nBurman.\n\nBURNDY SVENSKA AB\n\nPnr 127 04\n\nSkärholmen 4, Box 4012.\nFjärd-holmsgränd 19. Tel 08-710 03 75.\nBankgiro 561-2189. Postgiro\n706380-3. Tga Burswed. Telex\n10982 BURSWED S\nVerksamhet: Tillverkar o\nimporterar elektriska kontaktdon,\nställ-verksklämmor, elektronikdon,\nkontaktpressning\nAntal anställda: 10\nÅrsomsättning: 5 000 000\nAktiekapital: 250 000\nVerkst dir. Sven-Olov Hellström\nEtableringsår: 1964.",
    "structured": {
        "1": {
            "company_name": "IKO KABELFABRIK AB",
            "pnr": "510 94",
            "address": "Grimsås",
            "phone_number": "0325-74 1 00",
            "bank_details": {
                "bankgiro": "55-3146",
                "postgiro": "160994"
            },
            "activity": "Tillverkar plastisolerade ledningar och kablar för svag- som starkström",
            "employees": 400,
            "annual_turnover": 120000000,
            "capital": 5000000,
            "key_personnel": [
                {
                    "name": "Nils Aastrup",
                    "position": "Veikst dir"
                },
                {
                    "name": "Vilhelm Tham",
                    "position": "Verkst dir"
                }
            ],
            "establishment_year": 1947
        },
        "2": {
            "company_name": "BYG",
            "activity": "Utför hus- o industribyggnader, väg- o vattenbyggnader",
            "employees": 100,
            "annual_turnover": 8000000,
            "capital": 100000,
            "key_personnel": [
                {
                    "name": "Stig Carlsson",
                    "position": "Verkst dir"
                }
            ],
            "establishment_year": 1957
        },
        "3": {
            "company_name": "UHLÉN & NORD AB",
            "pnr": "12173",
            "address": "Johanneshov, Brunnbyv 20",
            "phone_number": "08-9104 30",
            "bank_details": {
                "bankgiro": "864-2142",
                "postgiro": "1285-6"
            },
            "activity": "Import av hästkött o rimmad lax",
            "key_personnel": [
                {
                    "name": "Allan Uhlén",
                    "position": "Verkst dir"
                }
            ],
            "establishment_year": 1910
        },
        "4": {
            "company_name": "ULFERTS FABRIKER AB",
            "pnr": "543 01",
            "address": "Tibro 1, Box 46",
            "phone_number": "0504-116 00",
            "bank_details": {
                "bankgiro": "221-3908",
                "postgiro": "175110-6"
            },
            "activity": "Tillverkar skåp, bord, stolar, hyllserier, kompletteringsmöbler, stoppmöbler, sängar. Plast Utställningen i Stockholm: \"Möbelcenter\", Storängsv 10, Sthlm NO. Tel 08-62 02 82",
            "employees": 537,
            "annual_turnover": 72000000,
            "capital": 1000000,
            "key_personnel": [
                {
                    "name": "Harald Ulfenborg",
                    "position": "Verkst dlr"
                }
            ],
            "establishment_year": 1942
        },
        "5": {
            "company_name": "ULLASJO PÄLSDJURS-FARM, AB",
            "pnr": "510 70",
            "address": "Svensljunga",
            "phone_number": "031-4099 83",
            "activity": "Uppfödning av mink o blåräv",
            "employees": 45,
            "annual_turnover": 4000000,
            "capital": 250000,
            "key_personnel": [
                {
                    "name": "Einar Ullman",
                    "position": "Verkst dir"
                }
            ],
            "establishment_year": 1936
        },
        "6": {
            "company_name": "FRODINGE MEJERI AB",
            "pnr": "598 00",
            "address": "Vimmerby",
            "phone_number": "0492-402 00",
            "activity": "Tillverkar o säljer FVödinge Ostkaka, vegetabilisk ost samt livsmedelsaerosoler, färdigvisp, kryddspray o bak-formsspray",
            "employees": 60,
            "annual_turnover": 16000000,
            "capital": 100000,
            "key_personnel": [
                {
                    "name": "Gösta Carlsson",
                    "position": "Verkst dir"
                }
            ],
            "establishment_year": 1969
        },
        "7": {
            "company_name": "SVENSK TORVFüRÄDLING, AB",
            "pnr": "28010",
            "address": "Sösdala, Box 152",
            "phone_number": "0451-64 0 7 0",
            "bank_details": {
                "bankgiro": "286-2356",
                "postgiro": "175708-7"
            },
            "activity": "Tillverkar o säljer torv för jordförbättrings ändamål Varunamn: Kronmull, Trädgårdstorv",
            "employees": 65,
            "annual_turnover": 6000000,
            "capital": 5000000,
            "key_personnel": [
                {
                    "name": "Nils Wahlquist",
                    "position": "Verkst dir"
                }
            ],
            "establishment_year": 1939
        },
        "8": {
            "company_name": "SVENSK TRÄBYGGNADS. TEKNIK, AB",
            "pnr": "112 52",
            "address": "Stockholm, Olof Dalins v 14",
            "phone_number": "08-5243 26, 5243 28",
            "bank_details": {
                "bankgiro": "733-8171",
                "postgiro": "55332-1"
            },
            "activity": "Konstruerar, säljer o monterar limträ, hallbyggnader o takstolar i fribärande utförande Varunamn: HB, STT",
            "capital": 200000,
            "key_personnel": [
                {
                    "name": "Ing Erik Barkeling",
                    "position": ""
                },
                {
                    "name": "ing Leif Ek",
                    "position": ""
                }
            ],
            "establishment_year": 1957
        },
        "9": {
            "company_name": "KUGELVERKEN AB",
            "pnr": "580 06",
            "address": "Linköping 6, Box 6110. Gamla Tanneforsv 16-18",
            "phone_number": "013-10 24 30",
            "bank_details": {
                "bankgiro": "120-4445",
                "postgiro": "367870-3"
            },
            "activity": "Tillverkar gaffelstap-lare, truckar Varunamn: Abeko",
            "employees": 25,
            "annual_turnover": 3000000,
            "capital": 75000,
            "key_personnel": [
                {
                    "name": "Gösta Kugelberg",
                    "position": "Verkst dir"
                }
            ],
            "establishment_year": 1948
        },
        "10": {
            "company_name": "BJELKES, AB",
            "pnr": "691 01",
            "address": "Karlskoga 1, Värmlandsv 76. Box 8",
            "phone_number": "0586-362 60",
            "bank_details": {
                "bankgiro": "109-0927",
                "postgiro": "81490-5"
            },
            "activity": "Tillverkar byggnadssnickerier o emballage. Säljer trävaror o alla slag av byggnadsmaterial. Utför tak- o golvläggningar",
            "employees": 95,
            "annual_turnover": 12700000,
            "capital": 143000,
            "key_personnel": [
                {
                    "name": "Fabr Ragnar Jansson",
                    "position": "Verkst dir"
                }
            ],
            "establishment_year": 1935
        },
        "11": {
            "company_name": "STENSTORPS TRÄ-PRODUKTER AB",
            "pnr": "520 50",
            "address": "Stenstorp, Box 60. Hantverksg 30",
            "phone_number": "0500-504 00",
            "bank_details": {
                "bankgiro": "530-6246",
                "postgiro": "717131-7"
            },
            "activity": "Tillverkar o säljer lamellträ i standardformat o skärningar, belagt med abaehi, board eller önskat material. Limfog i skärningar, även belagt med önskat material",
            "employees": 40,
            "annual_turnover": 3000000,
            "capital": 50000,
            "key_personnel": [
                {
                    "name": "Erik Johansson",
                    "position": "Verkst dir"
                },
                {
                    "name": "M Henriksson",
                    "position": "Kamrer"
                },
                {
                    "name": "A Johnsson",
                    "position": "Verkmäst"
                }
            ],
            "establishment_year": 1928
        }
    }
}