{
    "original": "SANDELL &amp; CO, LAURITZ\n\nPnr 412 63\n\nGöteborg, Almedalsv 1. Tel\n031-403500, 40 35 08. Bankgiro\n506-7020. Postgiro 42303-8\nVerksamhet: Kem tekn tillverkning\no engrosförsäljning av olika typer\nfasta o flytande avfettnings-,\ntvätt-, rengörings- o diskmedel\nRepresentanter: Eslöv. Yngve\nNilsson. Tel 0413-120 26\nStockholm. Hans Westerberg. Tel\n08-110212\n\nTrollhättan. Gösta Hallberg. Tel\n0520-194 5 0\nVaranamn: Elsan\nEtableringsår: 1937.\n\nBJÖRKMAN MEK\nVERKSTAD AB, GUST\n\nPnr 126 09\n\nHägersten 9, Instrumentv 9. Box\n940. Tel 08-45 36 30. Bankgiro\n477-3412. Postgiro 143724-3\nVerksamhet: Mekanisk verkstad\nChef: Ing Kurt Gustavsson\nEtableringsår: 1938.\n\nFAHLSTEDTSMÅLERI AB\n\nPnr 803 55\n\nGävle. Kyrkog 5. Tel 026-115775.\nBankgiro 403-6711. Postgiro\n201460-3\n\nVerksamhet: Måleriarbeten\nAntal anställda: 35\nÅrsomsättning: 2 000 000\nAktiekapital: 10 000\nÄgare o chefer: Sven Fahlstedt,\nGunnar Fahlstedt\nEtableringsår: 1970.\n\nFAHLSTEDTS BYGGNADS.\nFIRMA, AB AN5G\n\nPnr 803 55\n\nGävle, Kyrkog 5. Tel 026-1157 75.\nBankgiro 783-7024. Postgiro\n29075-5\n\nVerksamhet: Byggnadsrörelse.\nNy-o ombyggnader\nAntal anställda: 74\nÅrsomsättning: 9 000 000\nAktiekapital: 150 000\nÄgare o chefer Sven Fahlstedt,\nGunnar Fahlstedt\nEtableringsår: 1913.\n\nPER\n\nTel 019-1137 67, 125155.\nPostgiro 336667\n\nVerksamhet: Helrenovering av alla\nslags motorer\nAntal anställda: 20\nÅrsomsättning: 900 000\nAktiekapital: 100 000\nVerkst dir: Roland Pelgander\nEtableringsår: 1948.\n\nW - DATA AB\n\nPnr 56101\n\nHuskvarna 1, Box 45. Birkag. Tel\n036-13 28 60. Bankgiro 391-2219\nVerksamhet: Fullständig\ndataservice såsom konsultation,\nmetodikutveckling, systemuppläggning,\nprogrammering, dataregistrering,\ndatordrift o datakommunikation\ninom såväl administrativ som\nteknisk databehandling.\nMarknadsföring av systempaket inom metodik\no administrativa tillämpningar\nAntal anställda: 105\nÅrsomsättning: 10 000 000\nAktiekapital: 100 000\nVerkst dir: Agne Näslund\nEtableringsår. 1966\nÄgare: Husqvarna Vapenfabriks\nAB, AB Svenska Fläktfabriken.\n\nWEBES KON FEKT\nYR-INDUSTRI, AB\n\nPnr 56040\n\nHabo, Box 125. Tel 036-403 60,\n403 61. Bankgiro 553-8285.\nPostgiro 96503-8\n\nVerksamhet: Tillverkar o säljer\n\ngeléhallon\n\nAntal anställda: 14\n\nÅrsomsättning: 3800000\n\nAktiekapital: 120000\n\nChef: Folke Wärnbring\n\nEtableringsår: 1953.\n\nLILLIESKOLD AB, CARL A\n\nPnr 11357\n\nStockholm, Rådmansg 50. Tel\n08-15 02 75. Tga Bygglilliesköld\nVerksamhet: Byggnadsentreprenör\no fastighetsförvaltning\nAntal anställda: 15\nÅrsomsättning: 12 000 000\nAktiekapital: 500 000\nVerkst dir: Vakant\nEtableringsår: 1943.\n\nANDERSSON, AB HANS\n\nPnr 274 00\n\nSkurup, Box 53. Kyrkog 25. Tel\n0411-400 06, 40300. Bankgiro\n663-2509. Postgiro 173022-5\nVerksamhet: Säljer spannmål,\nmjöl, trävaror o byggmaterial\nAntal anställda: 25\nÅrsomsättning: 9 700 000\n\nAktiekapital: 100 000\nVerkst din Jerker Nyberg\nEtableringsår: 1850.\n\nGULLVIKS FABRIKS AB\n\nPnr 200 25\n\nMalmö 16, Box 16016.\nJohannes-lustg 9. Tel 040-93 4 1 20. Bankgiro\n15-6471. Postgiro 38136. Tga\nGullvik\n\nVerksamhet: Kemisk fabrik.\nProdukter för lantbruk, skog o industri\nAktiekapital: 2 000 000\nVerkst dir: Philip Sandström\nEtableringsår: 1920.\n\nGULLÄNGETS MEKANISKA,\nAB\n\nPnr 890 28\n\nGuUänget, Box 93. Tel 0660-116 07.\nPostgiro 64787\n\nVerksamhet: Stålkonstruktioner för\nbyggnader, utrustningar till\nkraftverk, reningsverk, järnverk o\ncellu-losafabriker. Utför legoarbeten i\nmek verkstad\nAntal anställda: 20\nÅrsomsättning: 1500 000\nAktiekapital: 30000\nÄgare o chefer: Ing Stig Omnell,\ning Arne Edlund\nEtableringsår: 1947.\n\nKl FA, AB\n\nPnr 171 95\n\nSolna, Banvaktsv 20. Tel\n08-83 40 00. Bankgiro 726-1795.\nPostgiro 2103-0. Tga Kifa.\nTelex 19958 ELEMA S\nVerksamhet: Apparater o\nförnödenheter för sjukhus o sjukvård\nAntal anställda: 131\nAktiekapital: 1500 000\nVerkst dir: Börje Rudewald\nEtableringsår: 1911.\n\nNYLÉN &amp; CO BOKBINDERI AB\n\nPnr 171 52\n\nSolna, Gårdsv 6. Tel 08-82 26 33,\n82 2647. Bankgiro 166-5298.\nPostgiro 251773\n\nVerksamhet: Partibokbinderi,\nförlagsband, pärmtillverkning\nAntal anställda: 39\nÅrsomsättning: 2 000 000\nAktiekapital: 90 000\nVerkst dir: Sture Nylén\nEtableringsår: 1943.\n\nNYLUND &amp; SON PIANO.\nFABRIK KB\n\nPnr 753 23\n\nUppsala, Alsikeg 2. Tel\n018-131519, 13 25 19\nVerksamhet: Tillverkar pianon\nAntal anställda: 30\nÄgare o chef: Dir Martin Nylund\nEtableringsår 1908.\n\nNYMAN 8. SCHULTZ/\nNORDISK RESEBUREAU AB\n\nPnr 103 80\n\nStockholm 7, Fack. Stureplan 6.\nTel 08-24 80 80. Bankgiro 70-0134.\nPostgiro 2115-4. Tga Resebureau.\nTelex 1554\n\nVerksamhet: Resebyrå med samtliga\ni branschen förekommande\nblljetfc-rättigheter. Återförsäljare för till\nSvenska Resebyråföreningen\nanslutna sällskapsresearrangörer.\nArrangerar individuella resor o\nresor i grupp över hela världen, med\nbokning av färdmedel, hotell o\növriga arrangemang\nAntal anställda: 335\nÅrsomsättning: 220 000 000\nAktiekapital: 1000 000\nStyrelse: Bankdir Ando Wikström\n(ordf), envoyé Kurt-Allan Belfrage,\ndir Allan Dessel, dir Sven-Erik\nSvanberg\n\nVerkst dir: Sven Windrup\n\nV verkst dir: Sven Ljunggren\nAdm-chef: Dir Bertil Ödlund\nEtableringsår: 1927.\n\nNYMAN &amp; SCHULTZ\nTRANSPORT AB\n\nPnr 10250\n\nStockholm 27, Fack. S Hamnv 50.\nTel 08-2250 80. Bankgiro 729-5645.\nPostgiro 2857-1. Tga Nymans.\nTelex 17900, 10256 (flygfrakt\nArlanda), 10777 (finska färjetrafiken),\n11137 (passageraravdelningen)\nVerksamhet: Internationella\ntransporter, rederiagenter, lagring,\nterminal, åkeri, bussuthyrning, aukt\nspeditör o skeppsklarerare\nAvdelningskontor:\n402 32 Göteborg 7, Box 7087. Tel\n031-1241 70. Telex 2225, 20764,\n20765 (flygexp Torslanda)\n201 24 Malmö 1, Box 437. Tel\n040-388 10. Telex 32335, 32423, 32409\n(flygexp Bulltofta)\n601 04 Norrköping 1, Box 228. Tel\n011-13 5100. Telex 64176\n231 01 Trelleborg 1, Box 22. Tel\n0410-155 30. Telex 32964\nAntal anställda: 280\nAktiekapital: 1000 000\nVerkst dir Sigurd Eriksson\nEtableringsår. 1861.",
    "structured": {
        "1": {
            "company_name": "SANDELL & CO, LAURITZ",
            "activity": "Kem tekn tillverkning o engrosförsäljning av olika typer fasta o flytande avfettnings-, tvätt-, rengörings- o diskmedel",
            "establishment_year": 1937
        },
        "2": {
            "company_name": "BJÖRKMAN MEK VERKSTAD AB, GUST",
            "activity": "Mekanisk verkstad",
            "establishment_year": 1938
        },
        "3": {
            "company_name": "FAHLSTEDTSMÅLERI AB",
            "activity": "Måleriarbeten",
            "employees": 35,
            "annual_turnover": 2000000,
            "capital": 10000,
            "establishment_year": 1970
        },
        "4": {
            "company_name": "FAHLSTEDTS BYGGNADS. FIRMA, AB AN5G",
            "activity": "Byggnadsrörelse. Ny-o ombyggnader",
            "employees": 74,
            "annual_turnover": 9000000,
            "capital": 150000,
            "establishment_year": 1913
        },
        "5": {
            "company_name": "PER",
            "activity": "Helrenovering av alla slags motorer",
            "employees": 20,
            "annual_turnover": 900000,
            "capital": 100000,
            "establishment_year": 1948
        },
        "6": {
            "company_name": "W - DATA AB",
            "activity": "Fullständig dataservice såsom konsultation, metodikutveckling, systemuppläggning, programmering, dataregistrering, datordrift o datakommunikation inom såväl administrativ som teknisk databehandling. Marknadsföring av systempaket inom metodik o administrativa tillämpningar",
            "employees": 105,
            "annual_turnover": 10000000,
            "capital": 100000,
            "establishment_year": 1966
        },
        "7": {
            "company_name": "WEBES KON FEKT YR-INDUSTRI, AB",
            "activity": "Tillverkar o säljer geléhallon",
            "employees": 14,
            "annual_turnover": 3800000,
            "capital": 120000,
            "establishment_year": 1953
        },
        "8": {
            "company_name": "LILLIESKOLD AB, CARL A",
            "activity": "Byggnadsentreprenör o fastighetsförvaltning",
            "employees": 15,
            "annual_turnover": 12000000,
            "capital": 500000,
            "establishment_year": 1943
        },
        "9": {
            "company_name": "ANDERSSON, AB HANS",
            "activity": "Säljer spannmål, mjöl, trävaror o byggmaterial",
            "employees": 25,
            "annual_turnover": 9700000,
            "capital": 100000,
            "establishment_year": 1850
        },
        "10": {
            "company_name": "GULLVIKS FABRIKS AB",
            "activity": "Kemisk fabrik. Produkter för lantbruk, skog o industri",
            "capital": 2000000,
            "establishment_year": 1920
        },
        "11": {
            "company_name": "GULLÄNGETS MEKANISKA, AB",
            "activity": "Stålkonstruktioner för byggnader, utrustningar till kraftverk, reningsverk, järnverk o cellu-losafabriker. Utför legoarbeten i mek verkstad",
            "employees": 20,
            "annual_turnover": 1500000,
            "capital": 30000,
            "establishment_year": 1947
        },
        "12": {
            "company_name": "KL FA, AB",
            "activity": "Apparater o förnödenheter för sjukhus o sjukvård",
            "employees": 131,
            "capital": 1500000,
            "establishment_year": 1911
        },
        "13": {
            "company_name": "NYLÉN & CO BOKBINDERI AB",
            "activity": "Partibokbinderi, förlagsband, pärmtillverkning",
            "employees": 39,
            "annual_turnover": 2000000,
            "capital": 90000,
            "establishment_year": 1943
        },
        "14": {
            "company_name": "NYLUND & SON PIANO. FABRIK KB",
            "activity": "Tillverkar pianon",
            "employees": 30,
            "establishment_year": 1908
        },
        "15": {
            "company_name": "NYMAN 8. SCHULTZ/NORDISK RESEBUREAU AB",
            "activity": "Resebyrå med samtliga i branschen förekommande blljetfc-rättigheter. Återförsäljare för till Svenska Resebyråföreningen anslutna sällskapsresearrangörer. Arrangerar individuella resor o resor i grupp över hela världen, med bokning av färdmedel, hotell o övriga arrangemang",
            "employees": 335,
            "annual_turnover": 220000000,
            "capital": 1000000,
            "establishment_year": 1927
        },
        "16": {
            "company_name": "NYMAN & SCHULTZ TRANSPORT AB",
            "activity": "Internationella transporter, rederiagenter, lagring, terminal, åkeri, bussuthyrning, aukt speditör o skeppsklarerare",
            "employees": 280,
            "capital": 1000000,
            "establishment_year": 1861
        }
    }
}