{
    "original": "VITTINGE TEGELBRUKS AB\n\nPnr 740 42\n\nVittinge. Tel 0224-612 80.\nBankgiro 81-0727. Postgiro 71855. Tga\nVittingetegel\n\nVerksamhet: Tillverkar o säljer\n1-kupigt o 2-kupigt strängtaktegel\nAntal anställda: 46\nÅrsomsättning: 3 000 000\nAktiekapital: 120 000\nStyrelse: Disp Karl Erik Wall (ordf),\nciviling Bengt Wall. dir Carl Johan\nWall. pol mag Ragnar Wall\nVerkst dir: Dir Carl Johan Wall\nEtableringsår: 1917.\n\nVITTSJü SMIDES &amp;\nMEK VERKSTAD\n\nPnr 280 22\n\nVittsjö, Box 181. Tel 0451-22145.\nBankgiro 280-5265. Postgiro\n131649-6. Tga Vittsjö\nVerksamhet: Tillverkar kugghjul,\nrörflänsar mm\nAntal anställda: 7\nÅrsomsättning: 300 000\nChef: Pabr Sven Hugo Persson\nEtableringsån 1935.\n\nÅSEDA GLASBRUK AB\n\nPnr 360 70\n\nAseda, Box 4. Tel 0474-103 00,\n103 10. Bankgiro 858-5705.\nPostgiro 329389-1. Tga Asedaglas\nVerksamhet: Tillverkar o säljer\nfärgat o klart prydnadsglas\nAntal anställda: 115\nÅrsomsättning: 4 000000\nAktiekapital: 270 000\nVerkst dir o platschef: Kaj\nEngstrand\n\nEtableringsår: 1947.\n\nRATIONELL BELYSNING AB\n\nPnr 113 57\n\nStockholm, Jarlaplan 4. Tel\n08-2013 55. Bankgiro 118-7053.\nPostgiro 609710-9. Tga Luxagent.\nTelex 17358 LUX S\nVerksamhet: Agenturer o grossister\ni belysningsarmatur o tillbehör\nAntal anställda: 3\nÅrsomsättning: 1000 000\nAktiekapital: 5 000\nStyrelseordf: Adv Lars Samzelius\nVerkst dir: Bo G Anneli\nEtableringsår: 1944.\n\nRATIONELL FINANSIERING\nAB\n\nPnr 102 50\n\nStockholm 27, Lidingöv 50. Fack.\nTel 08-63 57 00. Bankgiro 175-7392.\nPostgiro 402950-0\nVerksamhet: Finansrörelse\nAntal anställda: 56\nAktiekapital: 3125 000\nStyrelse: Dir Olle Franzén (ordf),\ndir Bengt Carlman, dir Arne E\nFredén\n\nVerkst dir: Arne E Frodén\nEtableringsår: 1936\nOmbildat 1963 till nuvarande firmar\nnamn.\n\nRATIONELL PRODUKTIVITET\nAB\n\nPnr 21140\n\nMalmö, S Tullg 4 A. Tel\n040-97 95 95, 97 52 51. Bankgiro\n403-4070. Postgiro 539924-1. Tga\nRatio. Telex 3374\nVerksamhet:\nRationaliseringskonsulter inom administration,\nekonomi, produktion, löneteknik o\nutbildningsfrågor\nAntal anstäUda: 8\nStyrelse: Rektor Stig Lundgren\n(ordf), fil mag ing Bo Eriksson\nVeikst dir: Ing Lars Cronehed\nEtableringsår 1959\nOmbildat till aktiebolag 1970.\n\nRATIONELL REDOVISNING,\nAB\n\nPnr 11135\n\nStockholm, Kungsg 14. Tel\n08-23 0415. Bankgiro 569-4047.\nPost-giro 602213-1\n\nVerksamhet: Bokförings- o\nrevisionsbyrå\nAntal anställda: 6\nAktiekapital: 30000\nVerkst dir: Civilekonom Sven E\nRunebou\n\nEtableringsår: 1959.\n\nRATIONELL\nSJUKVÄRDS-ORGANISATION AB(RATSO)\n\nPnr 17136\n\nSolna, Pyramid v 7. Tel 08-82 02 90.\nBankgiro 722-5550. Postgiro\n573658-2\n\nVeiksamhet: Projektering,\nplanering o organisation inom\nsjukvårdssektorn\n\nAvdelningskontor: 222 27 Lund,\nVårvädersg 4 D. Tel 046-1245 30.\nAvd-chef: Wilhelm Engström\nVeikst dir. Ulf Ohlin\nAvd-chef: Bengt Holmberg (Solna)\nEtableringsår 1966.\n\nVISBY BILCITY AB\n\nPnr 621 03\n\nVisby 3, Färjeleden 7. Box 329.\nTel 0498-119 40. Bankgiro\n833-3098. Postgiro 189683. Tga Bilcity\nVerksamhet: Säljer person- o\nlastbilar, reservdelar o tillbehör.\nReparationsverkstad\nAntal anstäUda: 60\nÅrsomsättning: 12500 000\nAktiekapital: 317 500\nVerkst dir: Bengt Ekedahl\nEtableringsår: 1943.\n\nPLÅTBEARBETNING, AB\n\nPnr 72137\n\nVästerås 1, Tunbytorpsg 8. Box\n971. Tel 021-144035. Bankgiro\n232-6171. Postgiro 646650-2\nVeiksamhet: Tillverkar ventils\ntionsanläggningar,\nfasadbeklädnader o byggnadsplåt\nAntal anställda: 38\nÅrsomsättning: 3 000 000\nAktiekapital: 200 000\nVerkst dir: Georg Hammarqvist\nEtableringsår: 1964.\n\nLINDEGREN &amp; RÅE, AB\n\nPnr 11130\n\nStockholm C, Bredgränd 2. Tel\n08-23 87 60. Bankgiro 56-0279.\nPostgiro 2968. Telex 1594. Tga Lindrae\nVerksamhet: Aukt skeppsklarerare,\nlinjeagenter, speditörer\nAktiekapital: 342500\nEtableringsår: 1909.\n\nBEWAG, AB\n\nPnr 21363\n\nMalmö, Ystadv, Hindbygården.\nTel 040-94 50 10. Bankgiro\n876-3179. Postgiro 436912-0. Tga\nBewag. Telex 32280 BEWAG S\nVerksamhet: Säljer väg- o\nbyggnadsmaskiner\nAntal anställda: 24\nÅrsomsättning: 5 500 000\nAktiekapital: 100000\nVerkst dir: C Berlin\nEtableringsår: 1956.\n\nKÄGÉNS INDUSTRIER AB\n\nPnr 57301\n\nTranås 1, Box 2. Huvudkontor o\nverkstäder. Tel 0140-130 00\nVerksamhet: Tillverkar o säljer\nkontorsmöbler o inredningar\n\nFörsäljningskontor: Stockholm,\nGöteborg, Malmö, Örebro,\nSundsvall, Uppsala, Eskilstuna,\nHälsingborg o Tranås\nAntal anställda: 305\nÅrsomsättning: 33000 000\nAktiekapital: 1000 000\nStyrelse: Dir Elis Kågén (ordf),\n-frk Ester Kågén, disp Elis\nCross-ner, frk Barbro Rydén, fru Berit\nKågén, dir Fredrik Petersen,\neko-nomidir Börje Melbäck\nVeikst dir: Fredrik Petersen\nMarknadschef: Bo Rydbeck\nChefarkitekt: Arne Rocén\nProduktionschef: Stig Dackner\nEkonomichef: Lars Sjögren\nEtableringsår: 1907.\n\nVAL\n\nVerkst dir: Vallentin Svensson\nEtableringsår: 1940\nOmbildat till aktiebolag 1960.\n\nWALLGRENS ELEKTRO.\nMEKANISKA VERKSTAD\n\nPnr 852 36\n\nSundsvall, Fredsg 12. Tel\n060-1124 71\n\nVerksamhet: Lindningsarbeten,\nelektr motorreparationer,\nreparationer av hissar, tvättmaskiner m m\nÄgare o chef: Hj Wallgren.\n\nWALLHAMN AB\n\nPnr 444 00\n\nStenungsund, Box 103. Kållekärr.\nTel 0304-602 50. Bankgiro\n535-4444. Postgiro 111855-3. Tga\nWallhamn. Telex 2429 WALLHMN S\nVerksamhet: Hamn, stuveri,\nspedition, skeppsmäkleri,\nfartygskla-rering, magasinering, rederirörelse\n(Roto Line), bilrekonditionering\nAntal anställda: 30\nÅrsomsättning: 15 000 000\nAktiekapital: 1800 000\nVerkst din Lars Gustafsson\nTrafikchef: Bernt Magnusson\nSped-chef: Bo G Nilsson\nHamnkapten: Bengt Evertsson\nKamrer: Per Nilsson\nEtableringsår: 1962\nRepresentant för Wallenius Lines,\nStockholm, Braam &amp; van Veen,\nHolland o Belgien.\n\nWALLINS GRANITINDUSTRIER\nMEK STENHUGGERI,\nBRUDERNA\n\nPnr 343 00\n\nÄlmhult, Box 39. Tel 0476-120 50.\nBankgiro 873-8338. Postgiro\n88508-7. Tga Wallingranit.\nTelex 4662 WALLIN S\nVeiksamhet: Tillverkar o säljer\ngravvårdar. Export av granit\nAntal anställda: 120\nÅrsomsättning: 9 000 000\nChefer: Disp Sture Wallin, ing\nSven Wallin\nEtableringsår: 1904.\n\nA C E JÄRNINDUSTRI\n\nPnr 691 00\n\nKarlskoga, Brickegårdsv 11. Tel\n0586-253 70, 28070. Bankgiro\n60-5358. Postgiro 293920\nVerksamhet: Utför pressarbeten\nupp till 100 tons tryck.\nJärnkonstruktioner, rostfria arbeten\nChef: Pabr G Carlsson\nEtableringsår: 1949.",
    "structured": {
        "firms": [
            {
                "company_name": "VITTINGE TEGELBRUKS AB",
                "pnr": "740 42",
                "address": "Vittinge",
                "phone_number": "0224-612 80",
                "bank_details": {
                    "bankgiro": "81-0727",
                    "postgiro": "71855"
                },
                "activity": "Tillverkar o säljer 1-kupigt o 2-kupigt strängtaktegel",
                "employees": 46,
                "annual_turnover": 3000000,
                "capital": 120000,
                "key_personnel": [
                    {
                        "name": "Disp Karl Erik Wall",
                        "position": "ordf"
                    },
                    {
                        "name": "civiling Bengt Wall",
                        "position": ""
                    },
                    {
                        "name": "dir Carl Johan Wall",
                        "position": ""
                    },
                    {
                        "name": "pol mag Ragnar Wall",
                        "position": ""
                    }
                ],
                "establishment_year": 1917
            },
            {
                "company_name": "VITTSJü SMIDES & MEK VERKSTAD",
                "pnr": "280 22",
                "address": "Vittsjö, Box 181",
                "phone_number": "0451-22145",
                "bank_details": {
                    "bankgiro": "280-5265",
                    "postgiro": "131649-6"
                },
                "activity": "Tillverkar kugghjul, rörflänsar mm",
                "employees": 7,
                "annual_turnover": 300000,
                "key_personnel": [
                    {
                        "name": "Pabr Sven Hugo Persson",
                        "position": ""
                    }
                ],
                "establishment_year": 1935
            },
            {
                "company_name": "ÅSEDA GLASBRUK AB",
                "pnr": "360 70",
                "address": "Aseda, Box 4",
                "phone_number": "0474-103 00, 103 10",
                "bank_details": {
                    "bankgiro": "858-5705",
                    "postgiro": "329389-1"
                },
                "activity": "Tillverkar o säljer färgat o klart prydnadsglas",
                "employees": 115,
                "annual_turnover": 4000000,
                "capital": 270000,
                "key_personnel": [
                    {
                        "name": "Kaj Engstrand",
                        "position": "Verkst dir o platschef"
                    }
                ],
                "establishment_year": 1947
            },
            {
                "company_name": "RATIONELL BELYSNING AB",
                "pnr": "113 57",
                "address": "Stockholm, Jarlaplan 4",
                "phone_number": "08-2013 55",
                "bank_details": {
                    "bankgiro": "118-7053",
                    "postgiro": "609710-9"
                },
                "activity": "Agenturer o grossister i belysningsarmatur o tillbehör",
                "employees": 3,
                "annual_turnover": 1000000,
                "capital": 5000,
                "key_personnel": [
                    {
                        "name": "Adv Lars Samzelius",
                        "position": "Styrelseordf"
                    },
                    {
                        "name": "Bo G Anneli",
                        "position": "Verkst dir"
                    }
                ],
                "establishment_year": 1944
            },
            {
                "company_name": "RATIONELL FINANSIERING AB",
                "pnr": "102 50",
                "address": "Stockholm 27, Lidingöv 50. Fack",
                "phone_number": "08-63 57 00",
                "bank_details": {
                    "bankgiro": "175-7392",
                    "postgiro": "402950-0"
                },
                "activity": "Finansrörelse",
                "employees": 56,
                "capital": 3125000,
                "key_personnel": [
                    {
                        "name": "Dir Olle Franzén",
                        "position": "Styrelse ordf"
                    },
                    {
                        "name": "dir Bengt Carlman",
                        "position": ""
                    },
                    {
                        "name": "dir Arne E Fredén",
                        "position": ""
                    }
                ],
                "establishment_year": 1936
            },
            {
                "company_name": "RATIONELL PRODUKTIVITET AB",
                "pnr": "21140",
                "address": "Malmö, S Tullg 4 A",
                "phone_number": "040-97 95 95, 97 52 51",
                "bank_details": {
                    "bankgiro": "403-4070",
                    "postgiro": "539924-1"
                },
                "activity": "Rationaliseringskonsulter inom administration, ekonomi, produktion, löneteknik o utbildningsfrågor",
                "employees": 8,
                "key_personnel": [
                    {
                        "name": "Rektor Stig Lundgren",
                        "position": "Styrelse ordf"
                    },
                    {
                        "name": "fil mag ing Bo Eriksson",
                        "position": "Veikst dir"
                    }
                ],
                "establishment_year": 1959
            },
            {
                "company_name": "RATIONELL REDOVISNING, AB",
                "pnr": "11135",
                "address": "Stockholm, Kungsg 14",
                "phone_number": "08-23 0415",
                "bank_details": {
                    "bankgiro": "569-4047",
                    "postgiro": "602213-1"
                },
                "activity": "Bokförings- o revisionsbyrå",
                "employees": 6,
                "capital": 30000,
                "key_personnel": [
                    {
                        "name": "Civilekonom Sven E Runebou",
                        "position": "Verkst dir"
                    }
                ],
                "establishment_year": 1959
            },
            {
                "company_name": "RATIONELL SJUKVÄRDS-ORGANISATION AB(RATSO)",
                "pnr": "17136",
                "address": "Solna, Pyramid v 7",
                "phone_number": "08-82 02 90",
                "bank_details": {
                    "bankgiro": "722-5550",
                    "postgiro": "573658-2"
                },
                "activity": "Projektering, planering o organisation inom sjukvårdssektorn",
                "employees": null,
                "key_personnel": [
                    {
                        "name": "Ulf Ohlin",
                        "position": "Veikst dir"
                    },
                    {
                        "name": "Bengt Holmberg",
                        "position": "Avd-chef (Solna)"
                    }
                ],
                "establishment_year": 1966
            },
            {
                "company_name": "VISBY BILCITY AB",
                "pnr": "621 03",
                "address": "Visby 3, Färjeleden 7, Box 329",
                "phone_number": "0498-119 40",
                "bank_details": {
                    "bankgiro": "833-3098",
                    "postgiro": "189683"
                },
                "activity": "Säljer person- o lastbilar, reservdelar o tillbehör. Reparationsverkstad",
                "employees": 60,
                "annual_turnover": 12500000,
                "capital": 317500,
                "key_personnel": [
                    {
                        "name": "Bengt Ekedahl",
                        "position": "Verkst dir"
                    }
                ],
                "establishment_year": 1943
            },
            {
                "company_name": "PLÅTBEARBETNING, AB",
                "pnr": "72137",
                "address": "Västerås 1, Tunbytorpsg 8, Box 971",
                "phone_number": "021-144035",
                "bank_details": {
                    "bankgiro": "232-6171",
                    "postgiro": "646650-2"
                },
                "activity": "Tillverkar ventilationanläggningar, fasadbeklädnader o byggnadsplåt",
                "employees": 38,
                "annual_turnover": 3000000,
                "capital": 200000,
                "key_personnel": [
                    {
                        "name": "Georg Hammarqvist",
                        "position": "Verkst dir"
                    }
                ],
                "establishment_year": 1964
            },
            {
                "company_name": "LINDEGREN & RÅE, AB",
                "pnr": "11130",
                "address": "Stockholm C, Bredgränd 2",
                "phone_number": "08-23 87 60",
                "bank_details": {
                    "bankgiro": "56-0279",
                    "postgiro": "2968"
                },
                "activity": "Aukt skeppsklarerare, linjeagenter, speditörer",
                "capital": 342500,
                "establishment_year": 1909
            },
            {
                "company_name": "BEWAG, AB",
                "pnr": "21363",
                "address": "Malmö, Ystadv, Hindbygården",
                "phone_number": "040-94 50 10",
                "bank_details": {
                    "bankgiro": "876-3179",
                    "postgiro": "436912-0"
                },
                "activity": "Säljer väg- o byggnadsmaskiner",
                "employees": 24,
                "annual_turnover": 5500000,
                "capital": 100000,
                "key_personnel": [
                    {
                        "name": "C Berlin",
                        "position": "Verkst dir"
                    }
                ],
                "establishment_year": 1956
            },
            {
                "company_name": "KÄGÉNS INDUSTRIER AB",
                "pnr": "57301",
                "address": "Tranås 1, Box 2. Huvudkontor o verkstäder",
                "activity": "Tillverkar o säljer kontorsmöbler o inredningar",
                "employees": 305,
                "annual_turnover": 33000000,
                "capital": 1000000,
                "key_personnel": [
                    {
                        "name": "Dir Elis Kågén",
                        "position": "Styrelse ordf"
                    },
                    {
                        "name": "-frk Ester Kågén",
                        "position": ""
                    },
                    {
                        "name": "disp Elis Cross-ner",
                        "position": ""
                    },
                    {
                        "name": "frk Barbro Rydén",
                        "position": ""
                    },
                    {
                        "name": "fru Berit Kågén",
                        "position": ""
                    },
                    {
                        "name": "dir Fredrik Petersen",
                        "position": "Veikst dir"
                    },
                    {
                        "name": "ekonomidir Börje Melbäck",
                        "position": ""
                    }
                ],
                "establishment_year": 1907
            },
            {
                "company_name": "VAL",
                "key_personnel": [
                    {
                        "name": "Vallentin Svensson",
                        "position": "Verkst dir"
                    }
                ],
                "establishment_year": 1940
            },
            {
                "company_name": "WALLGRENS ELEKTRO. MEKANISKA VERKSTAD",
                "pnr": "852 36",
                "address": "Sundsvall, Fredsg 12",
                "phone_number": "060-1124 71",
                "activity": "Lindningsarbeten, elektr motorreparationer, reparationer av hissar, tvättmaskiner m m",
                "key_personnel": [
                    {
                        "name": "Hj Wallgren",
                        "position": "Ägare o chef"
                    }
                ]
            },
            {
                "company_name": "WALLHAMN AB",
                "pnr": "444 00",
                "address": "Stenungsund, Box 103. Kållekärr",
                "phone_number": "0304-602 50",
                "bank_details": {
                    "bankgiro": "535-4444",
                    "postgiro": "111855-3"
                },
                "activity": "Hamn, stuveri, spedition, skeppsmäkleri, fartygskla-rering, magasinering, rederirörelse (Roto Line), bilrekonditionering",
                "employees": 30,
                "annual_turnover": 15000000,
                "capital": 1800000,
                "key_personnel": [
                    {
                        "name": "Lars Gustafsson",
                        "position": "Verkst dir"
                    },
                    {
                        "name": "Bernt Magnusson",
                        "position": "Trafikchef"
                    },
                    {
                        "name": "Bo G Nilsson",
                        "position": "Sped-chef"
                    },
                    {
                        "name": "Bengt Evertsson",
                        "position": "Hamnkapten"
                    },
                    {
                        "name": "Per Nilsson",
                        "position": "Kamrer"
                    }
                ],
                "establishment_year": 1962
            },
            {
                "company_name": "WALLINS GRANITINDUSTRIER MEK STENHUGGERI, BRUDERNA",
                "pnr": "343 00",
                "address": "Älmhult, Box 39",
                "phone_number": "0476-120 50",
                "bank_details": {
                    "bankgiro": "873-8338",
                    "postgiro": "88508-7"
                },
                "activity": "Tillverkar o säljer gravvårdar. Export av granit",
                "employees": 120,
                "annual_turnover": 9000000,
                "key_personnel": [
                    {
                        "name": "Disp Sture Wallin",
                        "position": ""
                    },
                    {
                        "name": "ing Sven Wallin",
                        "position": ""
                    }
                ],
                "establishment_year": 1904
            },
            {
                "company_name": "A C E JÄRNINDUSTRI",
                "pnr": "691 00",
                "address": "Karlskoga, Brickegårdsv 11",
                "phone_number": "0586-253 70, 28070",
                "bank_details": {
                    "bankgiro": "60-5358",
                    "postgiro": "293920"
                },
                "activity": "Utför pressarbeten upp till 100 tons tryck. Järnkonstruktioner, rostfria arbeten",
                "employees": null,
                "key_personnel": [
                    {
                        "name": "Pabr G Carlsson",
                        "position": ""
                    }
                ],
                "establishment_year": 1949
            }
        ]
    }
}