{
    "original": "BERNSTRAND &amp; CO, AB E\n\nPnr 11130\n\nStockholm, Skeppsbron 16. Tel\n08-23 15 55. Bankgiro 72-9569.\nPostgiro 3309. Tga Ebernco\nVerksamhet: Tillverkar\npresenningar, kapell, verktygsväskor o\nindustriförnödenheter\nVerkst dir: Ake Bernstrand\nEtableringsår: 1923.\n\nBERNSTROM &amp; JOHANSSON,\nBYGGNADS AB\n\nPnr 600 03\n\nNorrköping 3, Vatteng 11. Box 3043.\nTel 011-1243 69, 1643 67. Bankgiro\n61-0276. Postgiro 643889\nVerksamhet: Utför ny- o\nombyggna-tion samt reparationer\nAntal anställda: 25\nÅrsomsättning: 2 500 000\nAktiekapital: 5 000\nEtableringsår: 1964.\n\nNACKA BYGGTEKNIK, AB\n\nPnr 13010\n\nEktorp, Klyvarev 34. Tel\n08-7161017, 7169848. Bankgiro\n379-5192. Postgiro 682367-8\nVerksamhet: Konsulterande\ningenjörsfirma. Byggledning,\nbyggnadskontroll, besiktningar,\nbyggnads-beskrivningar, projektering\nAktiekapital: 5 000\nVeikst dir: Byggnadsing SBR Sune\nEnglund\n\nEtableringsår: 1966\nOmbildat till aktiebolag 1968.\n\nNACKA EXPRESS &amp; ÅKERI,\nAB\n\nPnr 13103\n\nNacka 3, Box 340. Värmdöv 106.\nTel 08-716 25 20. Bankgiro\n173-0027. Postgiro 95470-1\nVerksamhet: Akeriverksamhet,\nschakt- o vägarbeten. Uthyrning\nav entreprenadmaskiner\nAntal anställda: 65\nÅrsomsättning: 3 500 000\nAktiekapital: 300 000\nVerkst din Henning R E Nilsson\nEtableringsår: 1922.\n\nNORRAHAMMARS BRUK\n\nPnr 560 20\n\nNorrahammar. Tel 036-606 00.\nPostgiro 5289. Tga Bruket\nVerksamhet: Tillverkar\nbeställ-ningsgjutgods, värmepannor,\nelspisar\n\nDir: Lennart Abjörnsson\n\nÄgare Husqvarna Vapenfabriks AB,\n\nHuskvarna.\n\nNORRBOTTENS\nCEMENT-GJUTERI, AB\n\nPnr 940 20\n\nÖjebyn. Tel 0911-652 50. Bankgiro\n61-1229. Postgiro 67913\nVerksamhet: Betongvaror o\nfabriks-blandad betong\n\nAvdelningskontor: Gällivare. Tel\n0970-113 95\nAntal anställda: 80\nÅrsomsättning: 15 000 000\nAktiekapital: 1500 000\nVerkst dir: J I Hedlund\nEtableringsår: 1918.\n\nNORRBOTTENS ENGROSSIST.\nFÖRENING\n\nPnr 951 01\n\nLuleå 1, V arvs g 39. Box 41. Tel\n0920-12 0 3 0. Bankgiro 752-7278.\nPostgiro 485955-9\nVerksamhet: Konkurs- o\nackordsärenden\n\nStyrelse: Dir Elfrid Oman\nOmbudsman: Disp Curt Pettersson.\n\nNORRBOTTENS\nFISKCENTRUM AB\n\nPnr 95100\n\nLuleå, Banv 19. Tel 0920-28160.\nBankgiro 205-5911. Postgiro\n482020-5. Tga BeDe Fisk\nVerksamhet: säljer norrlandslax,\nlaxöring, löjrom, sikrom mm\nVerkst dir: sten Persson\nEtableringsår: 1935.\n\nATL\n\nVerksamhet: Försäljning o service\nav etikettmaskiner o stansmaskiner\nVarunamn: Wetier, Stenmark,\nMini-Graph\n\nAntal anställda: 14\nÅrsomsättning: 3 000 000\nAktiekapital: 50000\nVerkst dir: Hans Hiller\nEtableringsår: 1962\nDotterbolag: Atlas Marking System\nAS, Danmark.\n\nATLAS,\nÅTERFORSÄKRINGS-AKTIEBOLAGET\n\nPnr 10361\n\nStockholm 3, Box 3071. Sveav 31.\nTel 08-22 35 60. Bankgiro 160^1156.\nPostgiro 258275-7. Tga Reatlas.\nTelex 1832\n\nVerksamhet: Internationell\nåterförsäkring i alla branscher\nAntal anställda: 53\nPremieinkomst: 77 000 000\nAktiekapital: 8 000 000\nVerkst dir: Bengt Kastengren\nEtableringsår: 1907.\n\nSWANSONS VERKSTÄDER AB\n\nPnr 113 60\n\nStockholm, Upplandsg 17. Tel\n08-32 70 50\n\nVerksamhet: Tillverkar bank- o\naffärsinredningar, specialmöbler\nAktiekapital: 40 000\nVerkst dir: Bertel Swanson\nEtableringsår 1933.\n\nTEK\n\nTEKNISKA GUMMIFABRIKEN\nJAKOBSBERG AB\n\nPnr 175 00\n\nJakobsberg, Nettov 11. Box 44.\nTel 0758-310 50. Bankgiro\n239-2348. Postgiro 473626-0\nVerksamhet: Tillverkar\ngummidetaljer för industrin. Specialitet\npre-cisionsgjutna formdetaljer. Egen\ntillverkning av formverktyg\nAntal anställda: 120\nÅrsomsättning: 6 000 000\nAktiekapital: 200 000\nVerkst din Ing Bertil Johnasson\nEtableringsår: 1954.\n\nAND\n\nANDERSSON &amp; CO STENHUG-\n\nGERI, K\n\nPnr 450 73\n\nRabbalshede. Tel 0525-360 87\nVerksamhet: Blågrà o röd granit,\nhalvfabrikat, gravvårdar o\nbyggnadssten\n\nAntal anställda: 25\nÅrsomsättning: 1500 000\nChef: Bertil Andersson\nEtableringsår: 1920.\n\nANDERSSON, BYGGNADS AB\nK I\n\nPnr 502 30\n\nBorås, Lilla Brog 39. Tel\n033-13 73 50. Bankgiro 843-4 1 02.\nPostgiro 145247-3\nVerksamhet: Husbyggnad\nAntal anställda: 80\nÅrsomsättning: 8000 000\nAktiekapital: 100 000\nChef: Byggmäst Bengt Andersson\nEtableringsår: 1937.\n\nANDERSSON &amp; SÖNER\nMÖBELFABRIK, AB KARL\n\nPnr 56101\n\nHuskvarna 1, Box 36. Rosendalag\n6. Tel 036-13 25 30. Bankgiro\n54-4540. Postgiro 77665-6\nVerksamhet: Tillverkar möbler,\nskåp, garderober o köksinredningar\nAntal anställda: 80\nÅrsomsättning: 5 500000\nAktiekapital: 500 000\nVerkst dir: Disp Yngve Malmvall\nEtableringsår: 1898.\n\nANDERSON, FABRIKS AB\nLUDVIG\n\nPnr 511 01\n\nKinna 1, Kasthall. Tel 0320-106 75,\n10678. Postgiro 578745-2. Tga\nMattfabriken\n\nVerksamhet: Tillverkar avpassade\nmattor o heltäckningsmattor\nAktiekapital: 1040 000\nVerkst dir: Stig Lundbeck\nEtableringsår: 1889.\n\nANDERSSONS ISOLERING,\nAB M\n\nPnr 89101\n\nÖrnsköldsvik 1, Box 259. Vikingag\n19. Tel 0660-108 50. Bankgiro\n771-5063. Postgiro 461932-6\nVerksamhet: Utför teknisk\nisolering för ånga, värme o kyla\nFilialer: Stenungsund. Tel\n0303-80135\n\nPiteå. Tel 0911-123 50\nVarunamn: Blixtisolering\nAntal anställda: 150\nÅrsomsättning: 12 000 000\nAktiekapital: 200 000\nVerkst dir: H Andersson\nEtableringsår: 1952.\n\nANDERSSONS ÅKERI AB,\nMALK\n\nPnr 33101\n\nVärnamo 1, Box 67. Jönköpingsv\n105. Tel 0370-11620. Bankgiro\n291-5106. Postgiro 96466-8.\nTelex 70125 ASGVNO S\nVerksamhet: Akerirörelse\nAntal anställda: 92\nÅrsomsättning: 11000 000\n\nAktiekapital: 400000\nVerkst din Bertil Bredgard\nEtableringsår: 1908.\n\nIDH, AB KARL\n\nPnr 57100\n\nNässjö, Handskerydsv 27. Tel\n0380-180 25\n\nVerksamhet: Försäljning för\nUp-sala-Ekeby Kakelplattor, Ifö\ngolvplattor, Ifö o Höganäs golv- o\nväggplattor\nAktiekapital: 10 000\nVerkst dir. Karl Idh.\n\nI DIN, FABRIKS AB LENNART\n\nPnr 33020\n\nAnderstorp, Box 151. Hantverksg\n35. Tel 0371-154 10. Bankgiro\n488-0266. Postgiro 106108-4\nVerksamhet: Bockade o stansade\nartiklar i tråd o band av järn,\nrostfritt, mässing o aluminium.\nOmbesörjer all slags ytbehandling. Egen\nverktygstillverkning\nAntal anstäUda: 10\nAktiekapital: 50 000\nVerkst dir: Lennart Id in\nEtableringsår: 1950.\n\nIDO, VÄRME &amp; SANITETS AB\n\nIngår i Cementakoncernen\nPnr 104 40\n\nStockholm 14. Storg 46. Box 14007.\nTel 08-67 02 60. Postgiro 53717-5.\nTelex 10024. Tga Idobolaget\nVerksamhet: Tillverkar o säljer\nteknisk armatur, sanitetsporslin\no skruv\n\nAntal anstäUda: 61\n\nÅrsomsättning: 26 000 000\n\nAktiekapital: 2 000 000\nVerkst dir: Olle Lindberg\nEtableringsår: 1931.\n\nKADAB ELECTRONICS AB\n\nPnr 100 28\n\nStockholm 49, Igeldammsg 22 B.\nBox 49048. Tel 08-52 05 00.\nBankgiro 62-7463. Postgiro 643000. Tga\nKadabelectronic\n\nVerksamhet: Försäljning o service\nav elektroniska bordsdatamaskiner\nAntal anställda: 4\nÅrsomsättning: 1000 000\nAktiekapital: 50 000\nVeikst dir: Hans Oscar Sandén\nEtableringsår: 1964.\n\nPROJEKTINSTRUMENT AB\n\nPnr 661 00\n\nSäffle, V Storg 20. Box 45. Tel\n0533-150 60. Bankgiro 600-6431.\nPostgiro 712110-6\nVerksamhet: Projektering av\ninstrument o automatikutrustningar.\nSäljer såväl enkla som avancerade\nkomponenter för mät- o\nregler-tekniska applikationer\nFilialer: 400 42 Göteborg 26, Fack.\nTel 031-42 69 25\nAntal anställda: 10\nÅrsomsättning: 2 000 000\nAktiekapital: 20 000\nStyrelse: Ing Bo Jareke (ordf), ing\nAke Bjurteg, ing Kjell Ahrman,\ncivilekonom Lennart Åkerström\nVerkst dir: Civilekonom Lennart\nÅkerström\n\nEtableringsår: 1968.",
    "structured": {
        "firms": [
            {
                "company_name": "BERNSTRAND & CO, AB E",
                "pnr": "11130",
                "address": "Stockholm, Skeppsbron 16",
                "phone_number": "08-23 15 55",
                "bank_details": {
                    "bankgiro": "72-9569",
                    "postgiro": "3309"
                },
                "activity": "Tillverkar presenningar, kapell, verktygsväskor o industriförnödenheter",
                "key_personnel": [
                    {
                        "name": "Ake Bernstrand",
                        "position": "Verkst dir"
                    }
                ],
                "establishment_year": 1923
            },
            {
                "company_name": "BERNSTROM & JOHANSSON, BYGGNADS AB",
                "pnr": "600 03",
                "address": "Norrköping 3, Vatteng 11, Box 3043",
                "phone_number": "011-1243 69, 1643 67",
                "bank_details": {
                    "bankgiro": "61-0276",
                    "postgiro": "643889"
                },
                "activity": "Utför ny- o ombyggnation samt reparationer",
                "employees": 25,
                "annual_turnover": 2500000,
                "capital": 5000,
                "establishment_year": 1964
            },
            {
                "company_name": "NACKA BYGGTEKNIK, AB",
                "pnr": "13010",
                "address": "Ektorp, Klyvarev 34",
                "phone_number": "08-7161017, 7169848",
                "bank_details": {
                    "bankgiro": "379-5192",
                    "postgiro": "682367-8"
                },
                "activity": "Konsulterande ingenjörsfirma. Byggledning, byggnadskontroll, besiktningar, byggnads-beskrivningar, projektering",
                "capital": 5000,
                "key_personnel": [
                    {
                        "name": "Byggnadsing SBR Sune Englund",
                        "position": "Veikst dir"
                    }
                ],
                "establishment_year": 1966
            },
            {
                "company_name": "NACKA EXPRESS & ÅKERI, AB",
                "pnr": "13103",
                "address": "Nacka 3, Box 340, Värmdöv 106",
                "phone_number": "08-716 25 20",
                "bank_details": {
                    "bankgiro": "173-0027",
                    "postgiro": "95470-1"
                },
                "activity": "Akeriverksamhet, schakt- o vägarbeten. Uthyrning av entreprenadmaskiner",
                "employees": 65,
                "annual_turnover": 3500000,
                "capital": 300000,
                "key_personnel": [
                    {
                        "name": "Henning R E Nilsson",
                        "position": "Verkst din"
                    }
                ],
                "establishment_year": 1922
            },
            {
                "company_name": "NORRAHAMMARS BRUK",
                "pnr": "560 20",
                "address": "Norrahammar",
                "phone_number": "036-606 00",
                "postgiro": "5289",
                "activity": "Tillverkar beställ-ningsgjutgods, värmepannor, elspisar",
                "key_personnel": [
                    {
                        "name": "Lennart Abjörnsson",
                        "position": "Dir"
                    }
                ],
                "establishment_year": "N/A"
            }
        ]
    }
}