{
    "original": "daltons roraktiebolag\n\nPnr 360 75\n\nAlstermo, Box 95. Tel\n0481-612 21, 612 22. Postgiro 101811-8\nVerksamhet: Säljer o installerar\nVVS-anläggningar\nAvdelningskontor: Alvesta,\nHagav 3. Tel 0472-101 85, 127 86\nVäxjö, Smedjeg 47. Tel 0470-197 01,\n213 14\n\nBraås. Tel 0474-30240, 305 31\nAntal anställda: 35\nÅrsomsättning: 3 000 000\nAktiekapital: 40 000\nStyrelse: Fabr Arne Johansson\n(ordf), fru Eira Johansson, fru\nMait Jidne, dlr Allan Jonasson\nVerkst din Allan Jonasson\nEtableringsån 1960.\n\nGRANQVIST &amp; CO AB, A\n\nPnr 532 00\n\nSkara, Skoltorget 2, Box 60. Tel\n0511-112 44, 115 44. Bankgiro\n350-4602. Postgiro 7980-6\nVerksamhet: Pappersvaror en gros\no i detalj. Tryckeri\nAntal anställda: 12\nVerkst dir: Anders Granqvist\nEtableringsår: 1875.\n\nBROBERGS INSTRUMENT\n\nPnr 632 20\n\nEskilstuna, Smedjeg 32. Tel\n016-14 03 57. Postgiro 463991-0\nVerksamhet: Kirurgiska instrument,\noperations-, förbands- o\nhushållssaxar samt pincetter\nAntal anställda: 7\nÅrsomsättning: 500 000\nVerkst dir: Lars Broberg\nEtableringsår: 1950.\n\nARTEX-TORGNER AB\n\nPnr 595 00\n\nMjölby, Fabriksg 4. Tel\n0142-133 40. Postgiro 74880-6. Tga\nArtextorgner\n\nVerksamhet: Tillverkar Artex\nbil-klädselöverdrag o bilutrustning\nAktiekapital: 242 000\nVerkst dir: John G Torgner\nEtableringsår: 1931.\n\nCARLSTROM &amp; CO, AB\n\nPnr 280 20\n\nBjämum, Box 46. Tel 0451-20138,\n205 62. Bankgiro 26-5327.\nPostgiro 84662\n\nVerksamhet: Tillverkar möbler\nAntal anställda: 18\nAktiekapital: 100 000\nVerkst dir: Fabr Erik Carlström\nEtableringsår: 1933.\n\nEKSJOVERKEN, AB\n\nPnr 575 00\n\nEksjö, Box 235. Tel 0381-13130.\nBankgiro 266-4613. Postgiro\n142653-5. Tga Eksjoverk\nVerksamhet: Tillverkar kompletta\nspecialmaskiner o\ntransportanordningar, utför maskin- o\nsvetsningsarbeten\n\nAntal anstäUda: 120\nÅrsomsättning: 6 000 000\nAktiekapital: 2 500000\nStyrelse: Birger Strid (ordf),\ngene-raldir Harald Qvistgaard, dir\nGunnar Lindwall, ing Malcom\nTörn-quist, dir Hans Westerlund\nVerkst dir: Hans Westerlund\nDir: Arne Pettersson\nEtableringsår: 1946.\n\nEKSTRANDS GYMNAST\nIK-MATERIEL AB\n\nPnr 126 37\n\nHägersten, Tellusborgsv 96. Tel\n08-45 26 55. Bankgiro 47-7905.\nPostgiro 7560-6\n\nVerksamhet: Tillverkar\ngymnastiksalsinredningar\nAntal anstäUda: 25\nÅrsomsättning: 1 500 000\nAktiekapital: 300 000\nVerkst dir: Per-Erik Ericsson\nEtableringsår: 1872\nOmbildat till aktiebolag 1949.\n\nEKSTRANDS LACK &amp;\nPLÄT AB\n\nPnr 33100\n\nVärnamo, Davelundsg. Tel\n0370-107 80, 127 80\n\nVerksamhet: Fullständig\nkarosseriverkstad, allt i billackering\n\nAktiekapital: 20000\nVerkst dir: Sture Ekstrand\nEtableringsår: 1960.\n\nEKSTRAND AB, PATENT.\nBYRÄN TOR5TEN\n\nPnr 600 02\n\nNorrköping 2, Box 2085. Gamla\nRådstugug 52. Tel 011-1360 20,\n18 8185. Bankgiro 610-0416.\nPost-giro 46 20 34-0. Tga Patex\nVerksamhet: Patentbyrå\n.Antal anstäUda: 5\nAktiekapital: 5 000\nChefer o patentombud: Civiling\nTorsten Ekstrand\nEtableringsår: 1968.\n\nPREMO.MUBLER AB\n\nPnr 57080\n\nVirserum, Box 79. Tel 0495-303 47,\n31215. Bankgiro 857-8486.\nPostgiro 277040-2\n\nVerksamhet: Tillverkar o säljer\nmöbler, tillverkar Premo-hyllan\nVarunamn: Premo\nAntal anställda: 22\nÅrsomsättning: 2500 000\nAktiekapital: 100 000\nVerkst dir: Helge Carmström\nEtableringsår: 1936.\n\nSKO\n\nSKOOGS ELEKTRISKA AB\n\nPnr 20121\n\nMalmö 1, Lundav 142. Box 157.\nTel 040-18 0180. Bankgiro\n641-2886. Postgiro 38909-8. Tga\nSkoog-elektro\n\nVerksamhet: Säljer elektr materiel\nengros\n\nAvdelningskontor: Göteborg, Gamla\nTu ve v 10. Tel 031-23 52 30\nVäxjö, Vildparksg 16. Tel\n0470-220 40\n\nÖrebro, Magasinsg 6, Tel\n019-14 0010\n\nAntal anställda: 90\nAktiekapital: 1500 000\nVetkst dir: Edvin Skoog\nEtableringsån 1934.\n\nSUECIA-FILM, AB\n\nPnr 102 20\n\nStockholm 12, Sysslomansg 8. Fack.\nTel 08-520245. Postgiro\n254607-5. Tga Sueciafilm\nVerksamhet: Kortfilmsinspelning\nAktiekapital: 10 000\nVerkst dir: Kurt Wahlgren\nEtableringsår: 1946\nOmbildat till aktiebolag 1962.\n\nSUEMAX OLJEBRÄNNARE AB\n\nPnr 28601\n\nOrkelljunga 1, Box 26. Tel\n0435-509 05. Bankgiro 67-2734. Postgiro\n581988\n\nVerksamhet: Tillverkar o säljer\noljebrännare samt utrustning för\noljeeldningsanläggningar. Utför\nlegoarbeten för den mekaniska\nverkstadsindustrin\nVarunamn: Suemax\nAntal anstäUda: 18\nÅrsomsättning: 2 000 000\nAktiekapital: 90 000\nVerkst dir: Ing Karl-Gustav\nGustavsson\nEtableringsår: 1959.\n\nINDUSTRICROM AB\n\nPnr 330 20\n\nAnderstorp, Hantverkarg. Box 58.\nTel 0371-16150\n\nindustr|crom\n\nikNeMoj t Anderstorp\n\nVerksamhet: Ytbehandlingsindustri\n\nför metall o plast\n\nAntal anstäUda: 32\n\nÅrsomsättning: 2 500 000\n\nAktiekapital: 25 000\n\nStyrelse: Dir S E Åsberg, fru S E\n\nÅsberg\n\nVerkst dir: S E Åsberg\nEtableringsår: 1957.",
    "structured": {
        "1": {
            "company_name": "daltons roraktiebolag",
            "pnr": "360 75",
            "address": "Alstermo, Box 95",
            "phone_number": "0481-612 21, 612 22",
            "postgiro": "101811-8",
            "activity": "Säljer o installerar VVS-anläggningar",
            "employees": 35,
            "annual_turnover": 3000000,
            "capital": 40000,
            "key_personnel": [
                {
                    "name": "Fabr Arne Johansson",
                    "position": "ordf"
                },
                {
                    "name": "fru Eira Johansson",
                    "position": ""
                },
                {
                    "name": "fru Mait Jidne",
                    "position": ""
                },
                {
                    "name": "dlr Allan Jonasson",
                    "position": ""
                },
                {
                    "name": "Allan Jonasson",
                    "position": "Verkst din"
                }
            ],
            "establishment_year": 1960
        },
        "2": {
            "company_name": "GRANQVIST & CO AB",
            "pnr": "532 00",
            "address": "Skara, Skoltorget 2, Box 60",
            "phone_number": "0511-112 44, 115 44",
            "bankgiro": "350-4602",
            "postgiro": "7980-6",
            "activity": "Pappersvaror en gros o i detalj. Tryckeri",
            "employees": 12,
            "establishment_year": 1875
        },
        "3": {
            "company_name": "BROBERGS INSTRUMENT",
            "pnr": "632 20",
            "address": "Eskilstuna, Smedjeg 32",
            "phone_number": "016-14 03 57",
            "postgiro": "463991-0",
            "activity": "Kirurgiska instrument, operations-, förbands- o hushållssaxar samt pincetter",
            "employees": 7,
            "annual_turnover": 500000,
            "establishment_year": 1950
        },
        "4": {
            "company_name": "ARTEX-TORGNER AB",
            "pnr": "595 00",
            "address": "Mjölby, Fabriksg 4",
            "phone_number": "0142-133 40",
            "postgiro": "74880-6",
            "activity": "Tillverkar Artex bil-klädselöverdrag o bilutrustning",
            "capital": 242000,
            "key_personnel": [
                {
                    "name": "John G Torgner",
                    "position": "Verkst dir"
                }
            ],
            "establishment_year": 1931
        },
        "5": {
            "company_name": "CARLSTROM & CO, AB",
            "pnr": "280 20",
            "address": "Bjämum, Box 46",
            "phone_number": "0451-20138, 205 62",
            "bankgiro": "26-5327",
            "postgiro": "84662",
            "activity": "Tillverkar möbler",
            "employees": 18,
            "capital": 100000,
            "key_personnel": [
                {
                    "name": "Fabr Erik Carlström",
                    "position": "Verkst dir"
                }
            ],
            "establishment_year": 1933
        },
        "6": {
            "company_name": "EKSJOVERKEN, AB",
            "pnr": "575 00",
            "address": "Eksjö, Box 235",
            "phone_number": "0381-13130",
            "bankgiro": "266-4613",
            "postgiro": "142653-5",
            "activity": "Tillverkar kompletta specialmaskiner o transportanordningar, utför maskin- o svetsningsarbeten",
            "employees": 120,
            "annual_turnover": 6000000,
            "capital": 2500000,
            "key_personnel": [
                {
                    "name": "Birger Strid",
                    "position": "ordf"
                },
                {
                    "name": "Harald Qvistgaard",
                    "position": "gene-raldir"
                },
                {
                    "name": "Gunnar Lindwall",
                    "position": "dir"
                },
                {
                    "name": "Malcom Törn-quist",
                    "position": "ing"
                },
                {
                    "name": "Hans Westerlund",
                    "position": "Verkst dir"
                },
                {
                    "name": "Arne Pettersson",
                    "position": "Dir"
                }
            ],
            "establishment_year": 1946
        },
        "7": {
            "company_name": "EKSTRANDS GYMNAST IK-MATERIEL AB",
            "pnr": "126 37",
            "address": "Hägersten, Tellusborgsv 96",
            "phone_number": "08-45 26 55",
            "bankgiro": "47-7905",
            "postgiro": "7560-6",
            "activity": "Tillverkar gymnastiksalsinredningar",
            "employees": 25,
            "capital": 300000,
            "key_personnel": [
                {
                    "name": "Per-Erik Ericsson",
                    "position": "Verkst dir"
                }
            ],
            "establishment_year": 1872
        },
        "8": {
            "company_name": "EKSTRANDS LACK & PLÄT AB",
            "pnr": "33100",
            "address": "Värnamo, Davelundsg",
            "phone_number": "0370-107 80, 127 80",
            "activity": "Fullständig karosseriverkstad, allt i billackering",
            "capital": 20000,
            "key_personnel": [
                {
                    "name": "Sture Ekstrand",
                    "position": "Verkst dir"
                }
            ],
            "establishment_year": 1960
        },
        "9": {
            "company_name": "EKSTRAND AB, PATENT.BYRÄN TORSTEN",
            "pnr": "600 02",
            "address": "Norrköping 2, Box 2085. Gamla Rådstugug 52",
            "phone_number": "011-1360 20, 18 8185",
            "bankgiro": "610-0416",
            "postgiro": "46 20 34-0",
            "activity": "Patentbyrå",
            "employees": 5,
            "capital": 5000,
            "key_personnel": [
                {
                    "name": "Civiling Torsten Ekstrand",
                    "position": "Chefer o patentombud"
                }
            ],
            "establishment_year": 1968
        },
        "10": {
            "company_name": "PREMO.MUBLER AB",
            "pnr": "57080",
            "address": "Virserum, Box 79",
            "phone_number": "0495-303 47, 31215",
            "bankgiro": "857-8486",
            "postgiro": "277040-2",
            "activity": "Tillverkar o säljer möbler, tillverkar Premo-hyllan",
            "employees": 22,
            "capital": 100000,
            "key_personnel": [
                {
                    "name": "Helge Carmström",
                    "position": "Verkst dir"
                }
            ],
            "establishment_year": 1936
        },
        "11": {
            "company_name": "SKOOGS ELEKTRISKA AB",
            "pnr": "20121",
            "address": "Malmö 1, Lundav 142. Box 157",
            "phone_number": "040-18 0180",
            "bankgiro": "641-2886",
            "postgiro": "38909-8",
            "activity": "Säljer elektr materiel engros",
            "employees": 90,
            "capital": 1500000,
            "key_personnel": [
                {
                    "name": "Edvin Skoog",
                    "position": "Vetkst dir"
                }
            ],
            "establishment_year": 1934
        },
        "12": {
            "company_name": "SUECIA-FILM, AB",
            "pnr": "102 20",
            "address": "Stockholm 12, Sysslomansg 8. Fack",
            "phone_number": "08-520245",
            "postgiro": "254607-5",
            "activity": "Kortfilmsinspelning",
            "capital": 10000,
            "key_personnel": [
                {
                    "name": "Kurt Wahlgren",
                    "position": "Verkst dir"
                }
            ],
            "establishment_year": 1946
        },
        "13": {
            "company_name": "SUEMAX OLJEBRÄNNARE AB",
            "pnr": "28601",
            "address": "Orkelljunga 1, Box 26",
            "phone_number": "0435-509 05",
            "bankgiro": "67-2734",
            "postgiro": "581988",
            "activity": "Tillverkar o säljer oljebrännare samt utrustning för oljeeldningsanläggningar. Utför legoarbeten för den mekaniska verkstadsindustrin",
            "employees": 18,
            "annual_turnover": 2000000,
            "capital": 90000,
            "key_personnel": [
                {
                    "name": "Ing Karl-Gustav Gustavsson",
                    "position": "Verkst dir"
                }
            ],
            "establishment_year": 1959
        },
        "14": {
            "company_name": "INDUSTRICROM AB",
            "pnr": "330 20",
            "address": "Anderstorp, Hantverkarg",
            "phone_number": "0371-16150",
            "activity": "Ytbehandlingsindustri för metall o plast",
            "employees": 32,
            "annual_turnover": 2500000,
            "capital": 25000,
            "key_personnel": [
                {
                    "name": "S E Åsberg",
                    "position": "Styrelse, Verkst dir"
                }
            ],
            "establishment_year": 1957
        }
    }
}