{
    "original": "CHI\n\nCEWE MÄTINSTRUMENT AB\n\nPnr 611 01\n\nNyköping 1, Box 294. O Trädgårdsg\n2. Tel 0155-880 80. Bankgiro\n827-2122. Postgiro 390979-3. Tga\nInstrument\n\nVerksamhet: Tillverkar elektr\nmätinstrument m m\nVarunamn: Cewe\nAntal anställda: 100\nÅrsomsättning: 4 500 000\nAktiekapital: 600 000\nStyrelse: Civiling Hans Westerberg\n(ordf), ing Folke Westerberg,\neko-nomidir Lennart Flycht\nVerkst dir: Ing Folke Westerberg\nEtableringsår: 1956.\n\nTOR ANNONSBYRÄ AB\n\nPnr 100 23\n\nStockholm 25, Pack. Adlerbethsg\n17. Tel 08-54 11 05. Bankgiro\n476-8115. Postgiro 601320-5\nVerksamhet: Konsulterande i\nmarknadsförings- o försäljningsfrågor\nAntal anställda: 10\nÅrsomsättning: 4 000 000\nAktiekapital: 200 000\nVerkst dir: Erik Dalgren\nEtableringsår: 1955.\n\nmeba plast, ab\n\nPnr 524 00\n\nHerrljunga, Box 89. Tel 0513-105 02.\nBankgiro 84-1081. Postgiro 287662\nVerksamhet: Industriplast för\nbelysningsändamål\nAntal anställda: 10\nÅrsomsättning: 1500 000\nAktiekapital: 30 000\nVerkst dir: Dennis Svensson\nEtableringsår: 1963.\n\nAPELGRENS REVISIONSBYRÅ\n\nPnr 69101\n\nKarlskoga 1, Katrinedalsg 17. Box\n60. Tel 0586-317 60, 335 60.\nBankgiro 605-5685. Postgiro 163454-2,\n135140-2\n\nVerksamhet: Bokföring o revisioner,\nekonomiska utredningar, bo- o\nfamiljeutrednings ärenden\nÅrsomsättning: 125000\nChef: Revisor Rune Apelgren\nEtableringsår: 1939.\n\nRAMUS AB\n\nPnr 941 00\n\nPiteå, Box 129. Sundsg 35. Tel\n0911-126 60. Bankgiro 28-5384.\nPostgiro 483953-6\nVeiksamhet: Importerar o säljer\nmusikinstrument\nAntal anställda: 22\nÅrsomsättning: 5 800 000\nAktiekapital: 50 000\nVeikst dir: Lars Jonneryd\nEtableringsår 1959.\n\nSUNDBYBERGS GJUTERI\n\nPnr 172 35\n\nSundbyberg, Järnvägsg 9. Tel\n08-280150. Bankgiro 743-5068.\nPostgiro 32160-4\n\nVerksamhet: Tillverkar\nhandels-gjutgods\n\nChef: Erik Ullbors\nEtableringsår: 1921.\n\nSUNDBYBERGS\nILEXPRESS, AB\n\nPnr 172 03\n\nSundbyberg 3, Box 302. Landsv 17.\nTel 08-28 9280. Bankgiro\n743-5126. Postgiro 75239-4\nVerksamhet: utför transporter.\nUthyr presenningar. Bensinstation\nAntal anställda: 140\nÅrsomsättning: 12 000 000\nAktiekapital: 40 000\nVerkst dir: Ake Sjögren\nEtableringsår: 1913.\n\nSUNDBYBERGS MODELL.\nSNICKERI AB\n\nPnr 172 40\n\nSundbyberg, Vackra v 14. Tel\n08-28 0104. Bankgiro 170-9112.\nPostgiro 74806-1\n\nVerksamhet: Modellsnickeri\n.Antal anställda: 5\nÅrsomsättning: 250 000\nAktiekapital: 25 000\nFirmatecknare: Lars Eriksson\nEtableringsår: 1917.\n\nSUNDFRAKT SUNDSVALLS.\nORTENS BILFRAKT EK FOR\n\nPnr 85101\n\nSundsvall 1, Pack. Norra v 30. Tel\n060-1019 00. Bankgiro 180-0507.\nPostgiro 546600-8\nVerksamhet: Transportförsäljning.\n210 medlemmar med 320 lastbilar.\nTransportförmedling för 100-talet\ntraktorer, maskiner av olika slag\nsamt mobilkranar (upp till 70 ton)\nAntal anställda: 25\nÅrsomsättning: 43 000 000\nInsatskapital: 3 700 000\nChef: Disp Viktor Magnusson\nEtableringsår: 1961.\n\nNOR\n\nAntal anställda: 495\nÅrsomsättning: 36000 000\nAktiekapital: 1 000 000\nStyrelse: Adv Sten B: son\nLeijonhufvud (ordf), disp Erik Casserdahl,\ndir Ivar Ryder, dir Robert Tolf\nVerkst dir: Bror Garonius\nFörsäljn-dir:r: Karl-Eric Klingvall,\nNils Kvale\n\nFörsäljn-chef: Björn Zachrisson\nEkonomichef: Carl-Olov Bergqvist\nEtableringsår: 1902\nOmbildat till aktiebolag 1918.\n\nNORMANS BOKBINDERI AB\n\nPnr 11351\n\nStockholm, Luntmakarg 68. Tel\n08-30 0191, 30 0192. Bankgiro\n73-4572. Postgiro 51837\nVerksamhet: Bokbinderi\nAktiekapital: 300 000\nVeikst din Per Ake Julin\nEtableringsår: 1863.\n\nEBÅ LADERVARUFABRIK, AB\n\nPnr 330 20\n\nAnderstorp. Tel 0371-150 05, 15105.\nBankgiro 488-0183. Postgiro\n73743-7. Tga Ebå\nVerksamhet: Tillverkar\nsmåläder-varor o svetsade plastartiklar\nAntal anställda: 25\nVerkst dir: Pontus Asgärde\nEtableringsår: 1936.\n\nCARLSSON &amp; CO AB, S J\n\nPnr 117 43\n\nStockholm 43, Liljeholmsv lo. Box\n43071. Tel 08-451105, 45 4711.\nBankgiro 47-7319. Postgiro 197714\nVerksamhet: Gas-, vatten- o\nvärmeinstallationer\nAntal anställda: 16\nÅrsomsättning: 1 200 000\nAktiekapital: 15 000\nVeikst dir: Sten Carlsson\nEtableringsår: 1915.\n\nCARLSON AB, INGENIORS.\nFIRMA SVEN\n\nPnr 79100\n\nFalun, Timmerv 8. Tel 023-181 80\n\nVerksamhet: Levererar allmänna\ntransportanordningar, skidliftar o\nlinbanor\n\nAktiekapital: 227000\nVerkst dir: Ing Sven Carlson\nEtableringsår: 1909.\n\nl:SON REKLAM, AB\n\nPnr 14121\n\nHuddinge 1, Box 1026. Kvarnbergsv\n35. Tel 08-774 02 20. Bankgiro\n62-6040. Postgiro 267188\nVerksamhet: Silkscreentryckeri.\nTrycker affischer o skyltar\nAntal anställda: 15\nÅrsomsättning: 1700 000\nAktiekapital: 50000\nVerkst dir: Torsten Ingemanson\nEtableringsår 1943.",
    "structured": {
        "1": {
            "company_name": "CEWE MÄTINSTRUMENT AB",
            "pnr": "611 01",
            "address": "Nyköping 1, Box 294. O Trädgårdsg 2",
            "phone_number": "0155-880 80",
            "bank_details": {
                "bankgiro": "827-2122",
                "postgiro": "390979-3"
            },
            "activity": "Tillverkar elektr mätinstrument m m",
            "employees": 100,
            "annual_turnover": 4500000,
            "capital": 600000,
            "key_personnel": [
                {
                    "name": "Civiling Hans Westerberg",
                    "position": "ordf"
                },
                {
                    "name": "ing Folke Westerberg",
                    "position": "eko-nomidir"
                },
                {
                    "name": "Lennart Flycht",
                    "position": "ekonomidir"
                },
                {
                    "name": "Ing Folke Westerberg",
                    "position": "Verkst dir"
                }
            ],
            "establishment_year": 1956
        },
        "2": {
            "company_name": "TOR ANNONSBYRÄ AB",
            "pnr": "100 23",
            "address": "Stockholm 25, Pack. Adlerbethsg 17",
            "phone_number": "08-54 11 05",
            "bank_details": {
                "bankgiro": "476-8115",
                "postgiro": "601320-5"
            },
            "activity": "Konsulterande i marknadsförings- o försäljningsfrågor",
            "employees": 10,
            "annual_turnover": 4000000,
            "capital": 200000,
            "key_personnel": [
                {
                    "name": "Erik Dalgren",
                    "position": "Verkst dir"
                }
            ],
            "establishment_year": 1955
        },
        "3": {
            "company_name": "meba plast, ab",
            "pnr": "524 00",
            "address": "Herrljunga, Box 89",
            "phone_number": "0513-105 02",
            "bank_details": {
                "bankgiro": "84-1081",
                "postgiro": "287662"
            },
            "activity": "Industriplast för belysningsändamål",
            "employees": 10,
            "annual_turnover": 1500000,
            "capital": 30000,
            "key_personnel": [
                {
                    "name": "Dennis Svensson",
                    "position": "Verkst dir"
                }
            ],
            "establishment_year": 1963
        },
        "4": {
            "company_name": "APELGRENS REVISIONSBYRÅ",
            "pnr": "69101",
            "address": "Karlskoga 1, Katrinedalsg 17. Box 60",
            "phone_number": "0586-317 60, 335 60",
            "bank_details": {
                "bankgiro": "605-5685",
                "postgiro": "163454-2, 135140-2"
            },
            "activity": "Bokföring o revisioner, ekonomiska utredningar, bo- o familjeutrednings ärenden",
            "annual_turnover": 125000,
            "key_personnel": [
                {
                    "name": "Revisor Rune Apelgren",
                    "position": "Chef"
                }
            ],
            "establishment_year": 1939
        },
        "5": {
            "company_name": "RAMUS AB",
            "pnr": "941 00",
            "address": "Piteå, Box 129. Sundsg 35",
            "phone_number": "0911-126 60",
            "bank_details": {
                "bankgiro": "28-5384",
                "postgiro": "483953-6"
            },
            "activity": "Importerar o säljer musikinstrument",
            "employees": 22,
            "annual_turnover": 5800000,
            "capital": 50000,
            "key_personnel": [
                {
                    "name": "Lars Jonneryd",
                    "position": "Veikst dir"
                }
            ],
            "establishment_year": 1959
        },
        "6": {
            "company_name": "SUNDBYBERGS ILEXPRESS, AB",
            "pnr": "172 03",
            "address": "Sundbyberg 3, Box 302. Landsv 17",
            "phone_number": "08-28 9280",
            "bank_details": {
                "bankgiro": "743-5126",
                "postgiro": "75239-4"
            },
            "activity": "utför transporter. Uthyr presenningar. Bensinstation",
            "employees": 140,
            "annual_turnover": 12000000,
            "capital": 40000,
            "key_personnel": [
                {
                    "name": "Ake Sjögren",
                    "position": "Verkst dir"
                }
            ],
            "establishment_year": 1913
        },
        "7": {
            "company_name": "SUNDBYBERGS MODELL. SNICKERI AB",
            "pnr": "172 40",
            "address": "Sundbyberg, Vackra v 14",
            "phone_number": "08-28 0104",
            "bank_details": {
                "bankgiro": "170-9112",
                "postgiro": "74806-1"
            },
            "activity": "Modellsnickeri",
            "employees": 5,
            "annual_turnover": 250000,
            "capital": 25000,
            "key_personnel": [
                {
                    "name": "Lars Eriksson",
                    "position": "Firmatecknare"
                }
            ],
            "establishment_year": 1917
        },
        "8": {
            "company_name": "NOR",
            "employees": 495,
            "annual_turnover": 36000000,
            "capital": 1000000,
            "key_personnel": [
                {
                    "name": "Adv Sten B: son Leijonhufvud",
                    "position": "ordf"
                },
                {
                    "name": "disp Erik Casserdahl",
                    "position": "disp"
                },
                {
                    "name": "dir Ivar Ryder",
                    "position": "dir"
                },
                {
                    "name": "dir Robert Tolf",
                    "position": "dir"
                },
                {
                    "name": "Bror Garonius",
                    "position": "Verkst dir"
                },
                {
                    "name": "Karl-Eric Klingvall",
                    "position": "Försäljn-dir"
                },
                {
                    "name": "Nils Kvale",
                    "position": "Försäljn-chef"
                },
                {
                    "name": "Carl-Olov Bergqvist",
                    "position": "Ekonomichef"
                }
            ],
            "establishment_year": 1902
        },
        "9": {
            "company_name": "NORMANS BOKBINDERI AB",
            "pnr": "11351",
            "address": "Stockholm, Luntmakarg 68",
            "phone_number": "08-30 0191, 30 0192",
            "bank_details": {
                "bankgiro": "73-4572",
                "postgiro": "51837"
            },
            "activity": "Bokbinderi",
            "capital": 300000,
            "key_personnel": [
                {
                    "name": "Per Ake Julin",
                    "position": "Veikst din"
                }
            ],
            "establishment_year": 1863
        },
        "10": {
            "company_name": "EBÅ LADERVARUFABRIK, AB",
            "pnr": "330 20",
            "address": "Anderstorp",
            "phone_number": "0371-150 05, 15105",
            "bank_details": {
                "bankgiro": "488-0183",
                "postgiro": "73743-7"
            },
            "activity": "Tillverkar småläder-varor o svetsade plastartiklar",
            "employees": 25,
            "key_personnel": [
                {
                    "name": "Pontus Asgärde",
                    "position": "Verkst dir"
                }
            ],
            "establishment_year": 1936
        },
        "11": {
            "company_name": "CARLSSON & CO AB, S J",
            "pnr": "117 43",
            "address": "Stockholm 43, Liljeholmsv lo. Box 43071",
            "phone_number": "08-451105, 45 4711",
            "bank_details": {
                "bankgiro": "47-7319",
                "postgiro": "197714"
            },
            "activity": "Gas-, vatten- o värmeinstallationer",
            "employees": 16,
            "annual_turnover": 1200000,
            "capital": 15000,
            "key_personnel": [
                {
                    "name": "Sten Carlsson",
                    "position": "Veikst dir"
                }
            ],
            "establishment_year": 1915
        },
        "12": {
            "company_name": "CARLSON AB, INGENIORS. FIRMA SVEN",
            "pnr": "79100",
            "address": "Falun, Timmerv 8",
            "phone_number": "023-181 80",
            "activity": "Levererar allmänna transportanordningar, skidliftar o linbanor",
            "capital": 227000,
            "key_personnel": [
                {
                    "name": "Ing Sven Carlson",
                    "position": "Verkst dir"
                }
            ],
            "establishment_year": 1909
        },
        "13": {
            "company_name": "l:SON REKLAM, AB",
            "pnr": "14121",
            "address": "Huddinge 1, Box 1026. Kvarnbergsv 35",
            "phone_number": "08-774 02 20",
            "bank_details": {
                "bankgiro": "62-6040",
                "postgiro": "267188"
            },
            "activity": "Silkscreentryckeri. Trycker affischer o skyltar",
            "employees": 15,
            "annual_turnover": 1700000,
            "capital": 50000,
            "key_personnel": [
                {
                    "name": "Torsten Ingemanson",
                    "position": "Verkst dir"
                }
            ],
            "establishment_year": 1943
        }
    }
}