{
    "original": "NOT\n\nstamsatser, kedjeblanketter,\nOCR-blanketter, fraktsedlar\nAntal anstäUda: 125\nAktiekapital: 250 000\nStyrelse: Lennart Porsmark (ordf).\nStig Porsmark, Olof Porsmark\nVerkst dir: Boktr Olof Porsmark\nEtableringsår. 1923.\n\nKUMLA HYTTFABRIK, AB\n\nPnr 692 00\n\nKumla, Industrig. Box 44. Tel\n019-792 10. Bankgiro 82-0824. Postgiro\n65982\n\nVerksamhet: Tillverkar\ntraktorhytter, hydraulkolvar o ventiler\nVarunamn: Kumlahytten\nAntal anställda: 65\nÅrsomsättning: 3 000 000\nAktiekapital: 100 000\nStyrelse: Disp Artur Lundgren\n(ordf), ing Torsten Nyström\nVerkst dir: Disp Artur Lundgren\nEtableringsår: 1950.\n\nTOLLS BYGGNADS AB\n\nPnr 103 42\n\nStockholm 40, Kungsg 36. Box\n40083. Tel 08-22 64 60\nVerksamhet:\nByggnadsentreprenörer.\n\nTOLLARPS SNICKERI.\nFABRIK, AB\n\nPnr 290 10\n\nTollarp, Marieholmsv. Box 58. Tel\n0450-102 56. Bankgiro 867-6033.\nPostgiro 341185-7\nVerksamhet: Tillverkar skol- o\nsjukhusinredningar. Specialitet:\nskolinredningar o\nspecialinredningar\n\nAntal anställda: 15\nVerkst dir: Fru Inga Olsson\nEtableringsår: 1949.\n\nSUNDSTRÖM AB, LARS\n\nPnr 790 25\n\nLinghed, Postl 197 A. Tel\n0246-220 00. Bankgiro 466-1096.\nPostgiro 331641-1\n\nVerksamhet: Rörledningsfirma.\nWS-installationer\nAntal anställda: 24\nÅrsomsättning: 2 600 000\nAktiekapital: 25 000\nVerkst dir: Lars Sundström\nEtableringsår: 1953.\n\nSVENSK BOKSERVICE SRA, AB\n\nPnr 162 10\n\nVällingby 1, Pack. Sorterarg 23.\nTel 08-89 0200. Bankgiro 331-7294.\nPostgiro 4940-3\n\nVerksamhet: Bokförlag o\nbokförsäljning\n\nVerkst dir: Lars Ahstrand.\n\nSVENSK BYGGNADSTEKNIK,\nBJERNEFORS &amp; CO, AB\n\nPnr 41137\n\nGöteborg, Vasag 58. Tel\n031-1117 82, 133882. Bankgiro\n491-2416. Postgiro 240933\nVerksamhet: Byggnadsrörelse\nAntal anställda: 59\nÅrsomsättning: 4 500 000\nAktiekapital: 100 000\nVerkst dir : Byggn-ing Hans\nBjerne-fors\n\nEtableringsår: 1946.\n\nVARIA, HANDELSFIRMAN\n\nPnr 30102\n\nHalmstad 1, Box 42. Tel 035-\n\n10 20 77, 12 42 57\n\nVerksamhet Export o import av\n\nläder- o plastvaror\n\nÄgare o chef: Dir Gustaf Salsgård.\n\nVARIA INDUSTRI AB\n\nPnr 642 00\n\nFlen, Box 55. Tel 0157-122 15.\nBankgiro 281-8136. Postgiro\n682050-0. Tga Varia\nVerksamhet: Tillverkar hemmöbler.\nHandelsbrädgård\nAntal anställda: 50\nÅrsomsättning: 3 000 000\nAktiekapital: 200 000\nVerkst dir: Gunnar Johannesson\nEtableringsår: 1966.\n\nHERMELINS HANDELS AB\n\nPnr 11230\n\nStockholm, Polhemsg 19. Tel\n08-54 11 10. Telex 17344. Tga\nHermelintrade\n\nVerksamhet:\nGeneralagentförDura-lex härdglas o restaurangmaskiner\nAntal anställda: 15\nAktiekapital: 100 000\nVerkst dir: Curt Hermelin.\n\nHERMES, AB MÖBEL.\nFABRIKEN\n\nPnr 56012\n\nVaggeryd, Box 154. Tel\n0393-10072,10972. Bankgiro29-9237.\nPostgiro 266454. Tga Hermes\nVerksamhet:\nKompletteringsmöbler i olika stilar o modeller\nAntal anställda: 30\nÅrsomsättning: 2 700 000\nAktiekapital: 52 000\nVerkst dir: Disp Bertil\nTallehammar\n\nEtableringsår: 1942.\n\nHERMODS KORRESPONDENS.\nINSTITUTS STIFTELSE\n\nPnr 205 10\n\nMalmö, Slottsg 24. Tel 040-769 00.\nBankgiro 64-0038. Postgiro 24462\nVerksamhet: Meddelar\nundervisning per korrespondens. Framställer\nläromedel, särskilt självinstruerande\n\nmaterial. Planlägger o genomför\npersonalutbildning. Utger\nelevtidningen Korrespondens\nAvdelningskontor: 103 40\nStockholm 40, HERMODS, Sergelg 19.\nFack. Tel 08-23 46 70\nAntal anstäUda: 350\nStyrelse: Dir Holger Crafoord(ordf),\ndir J P Bager, rektor Birger Bjerre,\ndir Gunnar Gaddën, fil dr Börje\nHolmberg, dir Nils Linander, rektor\nBertil Sjöberg, dir Ake Ståhlbrandt\nVerkst din Pil dr Börje Holmberg\nEtableringsår: 1898.\n\nHERNEK-LINDSTEN-MOHLIN\nKONSULTERANDE\nARKITEKTER och INGENJÖRER ab\n\nPnr 45100\n\nUddevalla, Nonnens v 9. Tel\n0522-124 20, 124 23. Bankgiro 428-0756.\nPostgiro 476963-4\nAntal anstäUda: 15\nAktiekapital: 5 000\nÄgare: C A Hernek SAR, H\nLindsten SAR\n\nEtableringsår: 1951.\n\nIKO AB, KONSULTBYRÄN\n\nPnr 147 00\n\nTumba, Köpmanplan 3. Box 122.\nTel 0753-31135. Bankgiro\n624-1681. Postgiro 670755-8\nVerksamhet: Rationalisering inom\nteknik o administration\nAntal anställda: 28\nAktiekapital: 10 000\nVerkst dir Civiling Olav Imshaug\nEtableringsår: 1965.\n\nBYGGING, AB\n\nPnr 100 73\n\nStockholm 44, Box 44030.\nLjus-stöparbacken 20, Gröndal. Tel\n08-190210. Bankgiro 566-0162.\nPostgiro 53707-6. Tga Bygging.\nTelex 10329\n\nVerksamhet: Tillverkning,\nförsäljning o uthyrning av hydraulisk\nutrustning för glidformar samt\nhydrauliska domkrafter för lyftning\no sänkning av tunga laster\nAntal anställda: 40\nÅrsomsättning: 7 500000\nAktiekapital: 1000 000\nStyrelse: Adv Sigurd Waldenström\n(ordf), dir Berge M Heede Jr,\ndu-Erik H Lindström\nVerkst dir: Erik H Lindström\nEtableringsår: 1942.\n\nULAX, AB\n\nPnr 59100\n\nMotala, Ekon. Tel 0141-10165,\n14130. Bankgiro 13-4288. Postgiro\n11377. Tga Ulax\n\nVerksamhet: Tillverkar mjölkfilter\nav kem renad bomull, bomullsfilter\nför andningsskydd m m.\nFörbandsbomull samt varor av kem renad\nbomull för diverse ändamål.\nBlekning o kem rening av bomull\nVarunamn: Ulax\nAntal anställda: 36\nÅrsomsättning: 1800 000\nAktiekapital: 300000\nVerkst dir: Disp Wilhelm Ulander\nEtableringsår: 1902.",
    "structured": {
        "1": {
            "company_name": "KUMLA HYTTFABRIK AB",
            "address": "Kumla, Industrig. Box 44",
            "phone_number": "019-792 10",
            "bank_details": {
                "bankgiro": "82-0824",
                "postgiro": "65982"
            },
            "activity": "Tillverkar traktorhytter, hydraulkolvar o ventiler",
            "employees": 65,
            "annual_turnover": 3000000,
            "capital": 100000,
            "key_personnel": [
                {
                    "name": "Disp Artur Lundgren",
                    "position": "ordf"
                },
                {
                    "name": "ing Torsten Nyström",
                    "position": "undefined"
                }
            ],
            "establishment_year": 1950
        },
        "2": {
            "company_name": "TOLLS BYGGNADS AB",
            "address": "Stockholm 40, Kungsg 36. Box 40083",
            "phone_number": "08-22 64 60",
            "activity": "Byggnadsentreprenörer",
            "establishment_year": 0
        },
        "3": {
            "company_name": "TOLLARPS SNICKERI.FABRIK AB",
            "address": "Tollarp, Marieholmsv. Box 58",
            "phone_number": "0450-102 56",
            "bank_details": {
                "bankgiro": "867-6033",
                "postgiro": "341185-7"
            },
            "activity": "Tillverkar skol- o sjukhusinredningar. Specialitet: skolinredningar o specialinredningar",
            "employees": 15,
            "key_personnel": [
                {
                    "name": "Fru Inga Olsson",
                    "position": "Verkst dir"
                }
            ],
            "establishment_year": 1949
        },
        "4": {
            "company_name": "SUNDSTRÖM AB, LARS",
            "address": "Linghed, Postl 197 A",
            "phone_number": "0246-220 00",
            "bank_details": {
                "bankgiro": "466-1096",
                "postgiro": "331641-1"
            },
            "activity": "Rörledningsfirma. WS-installationer",
            "employees": 24,
            "annual_turnover": 2600000,
            "capital": 25000,
            "key_personnel": [
                {
                    "name": "Lars Sundström",
                    "position": "Verkst dir"
                }
            ],
            "establishment_year": 1953
        },
        "5": {
            "company_name": "SVENSK BOKSERVICE SRA AB",
            "address": "Vällingby 1, Pack. Sorterarg 23",
            "phone_number": "08-89 0200",
            "bank_details": {
                "bankgiro": "331-7294",
                "postgiro": "4940-3"
            },
            "activity": "Bokförlag o bokförsäljning",
            "key_personnel": [
                {
                    "name": "Lars Ahstrand",
                    "position": "Verkst dir"
                }
            ],
            "establishment_year": 0
        },
        "6": {
            "company_name": "SVENSK BYGGNADSTEKNIK, BJERNEFORS & CO AB",
            "address": "Göteborg, Vasag 58",
            "phone_number": "031-1117 82, 133882",
            "bank_details": {
                "bankgiro": "491-2416",
                "postgiro": "240933"
            },
            "activity": "Byggnadsrörelse",
            "employees": 59,
            "annual_turnover": 4500000,
            "capital": 100000,
            "key_personnel": [
                {
                    "name": "Byggn-ing Hans Bjerne-fors",
                    "position": "Verkst dir"
                }
            ],
            "establishment_year": 1946
        },
        "7": {
            "company_name": "VARIA, HANDELSFIRMAN",
            "address": "Halmstad 1, Box 42",
            "phone_number": "035-10 20 77, 12 42 57",
            "activity": "Export o import av läder- o plastvaror",
            "establishment_year": 0
        },
        "8": {
            "company_name": "VARIA INDUSTRI AB",
            "address": "Flen, Box 55",
            "phone_number": "0157-122 15",
            "bank_details": {
                "bankgiro": "281-8136",
                "postgiro": "682050-0"
            },
            "activity": "Tillverkar hemmöbler. Handelsbrädgård",
            "employees": 50,
            "annual_turnover": 3000000,
            "capital": 200000,
            "key_personnel": [
                {
                    "name": "Gunnar Johannesson",
                    "position": "Verkst dir"
                }
            ],
            "establishment_year": 1966
        },
        "9": {
            "company_name": "HERMELINS HANDELS AB",
            "address": "Stockholm, Polhemsg 19",
            "phone_number": "08-54 11 10",
            "activity": "GeneralagentförDura-lex härdglas o restaurangmaskiner",
            "employees": 15,
            "capital": 100000,
            "key_personnel": [
                {
                    "name": "Curt Hermelin",
                    "position": "Verkst dir"
                }
            ],
            "establishment_year": 0
        },
        "10": {
            "company_name": "HERMES AB MÖBEL.FABRIKEN",
            "address": "Vaggeryd, Box 154",
            "phone_number": "0393-10072,10972",
            "bank_details": {
                "bankgiro": "29-9237",
                "postgiro": "266454"
            },
            "activity": "Kompletteringsmöbler i olika stilar o modeller",
            "employees": 30,
            "annual_turnover": 2700000,
            "capital": 52000,
            "key_personnel": [
                {
                    "name": "Disp Bertil Tallehammar",
                    "position": "undefined"
                }
            ],
            "establishment_year": 1942
        },
        "11": {
            "company_name": "HERMODS KORRESPONDENS. INSTITUTS STIFTELSE",
            "address": "Malmö, Slottsg 24",
            "phone_number": "040-769 00",
            "bank_details": {
                "bankgiro": "64-0038",
                "postgiro": "24462"
            },
            "activity": "Meddelar undervisning per korrespondens. Framställer läromedel, särskilt självinstruerande material. Planlägger o genomför personalutbildning. Utger elevtidningen Korrespondens",
            "employees": 350,
            "key_personnel": [
                {
                    "name": "Pil dr Börje Holmberg",
                    "position": "Verkst din"
                }
            ],
            "establishment_year": 1898
        },
        "12": {
            "company_name": "HERNEK-LINDSTEN-MOHLIN KONSULTERANDE ARKITEKTER och INGENJÖRER ab",
            "address": "Uddevalla, Nonnens v 9",
            "phone_number": "0522-124 20, 124 23",
            "bank_details": {
                "bankgiro": "428-0756",
                "postgiro": "476963-4"
            },
            "employees": 15,
            "capital": 5000,
            "key_personnel": [
                {
                    "name": "C A Hernek SAR",
                    "position": "undefined"
                },
                {
                    "name": "H Lindsten SAR",
                    "position": "undefined"
                }
            ],
            "establishment_year": 1951
        },
        "13": {
            "company_name": "IKO AB, KONSULTBYRÄN",
            "address": "Tumba, Köpmanplan 3. Box 122",
            "phone_number": "0753-31135",
            "bank_details": {
                "bankgiro": "624-1681",
                "postgiro": "670755-8"
            },
            "activity": "Rationalisering inom teknik o administration",
            "employees": 28,
            "capital": 10000,
            "key_personnel": [
                {
                    "name": "Civiling Olav Imshaug",
                    "position": "Verkst dir"
                }
            ],
            "establishment_year": 1965
        },
        "14": {
            "company_name": "BYGGING AB",
            "address": "Stockholm 44, Box 44030. Ljus-stöparbacken 20, Gröndal",
            "phone_number": "08-190210",
            "bank_details": {
                "bankgiro": "566-0162",
                "postgiro": "53707-6"
            },
            "activity": "Tillverkning, försäljning o uthyrning av hydraulisk utrustning för glidformar samt hydrauliska domkrafter för lyftning o sänkning av tunga laster",
            "employees": 40,
            "annual_turnover": 7500000,
            "capital": 1000000,
            "key_personnel": [
                {
                    "name": "Erik H Lindström",
                    "position": "Verkst dir"
                }
            ],
            "establishment_year": 1942
        },
        "15": {
            "company_name": "ULAX AB",
            "address": "Motala, Ekon",
            "phone_number": "0141-10165, 14130",
            "bank_details": {
                "bankgiro": "13-4288",
                "postgiro": "11377"
            },
            "activity": "Tillverkar mjölkfilter av kem renad bomull, bomullsfilter för andningsskydd m m. Förbandsbomull samt varor av kem renad bomull för diverse ändamål. Blekning o kem rening av bomull",
            "employees": 36,
            "annual_turnover": 1800000,
            "capital": 300000,
            "key_personnel": [
                {
                    "name": "Disp Wilhelm Ulander",
                    "position": "Verkst dir"
                }
            ],
            "establishment_year": 1902
        }
    }
}