{
    "original": "VÄRMEKONSULTBYRÄN AB\n\nPnr 11122\n\nStockholm C, Kungsg 66. Tel\n08-11 99 95, 21 97 95. Postgiro 351930\nVerksamhet: Konsulterande inom\nångteknik o VVS\nAntal anställda: 5\nAktiekapital: 5 000\nVerkst dir Ing Yngve Gustavsson\nEtableringsår 1954.\n\nHJÄ\n\nVeiksamhet: Tillverkning av Denco\nPloor dubbelgolv speciellt avsett\nför datacentraler\n\nGeneralagenter i Sverige, Danmark,\nNorge o Finland för Denco Miller\nLimited, Hereford, England:\nKyl-torkar för tryckluft o andra gaser.\nLuftkonditioneringssystemet\nCom-putaire för datacentraler.\nHiross Denco S.p.a., S. Angelo di\nPiove (Padova), Italien:\nTryckluft-filter, automatiska\nkondensvatten-avledare, efterkylare för tryckluft\nAktiekapital: 50 000\nStyrelse: Ing Erie Wrethagen (ordf),\ndott Claudio Rossi, ing Stig Odén\nVeikst dir: Ing Stig Odén\nEtableringsår: 1967.\n\nHIRSCHS KEMIKALIE.\nIMPORT, AB\n\nPnr 11140\n\nStockholm. Tegnérg 1. Tel 08-\n\n20 0 8 77,20 08 78. Bankgiro\n56-9308. Postgiro 250701-0\nVerksamhet: Importerar alla slags\nkemikalier o råvaror samt\nlivsmedel\n\nAntal anställda: 5\nAktiekapital: 30 000\nVeikst dir: G Hirsch\nEtableringsår: 1945.\n\nHIRSCHS METALL AB\n\nPrr 12612\n\nStockholm 42, Box 42028.\nLerkrogs-v 9-11, Västberga Industriområde,\nHägersten. Tel 08-45 2950.\nBankgiro 56-9512. Postgiro 53451. Tga\nMe ta 11 hirsch. Telex 17176\nVeiksamhet:\nMetallraffinerings-verk\n\nAktiekapital: 200000\nVeikst dir: Sune Mö me\nDisp: Björn Strauss\nEtableringsår: 1907\n\nDotterbolag till Paul Bergsöe &amp;\nSon, Landskrona.\n\nHISINGEPLAST, AB\n\nPnr 403 11\n\nGöteborg 2, Lillhagsv. Box 2043.\nTel 031-170220, 2260 00.\nBankgiro 852-6501. Postgiro 622480-2.\nTga Trepebol\n\nVeiksamhet: Kem tekn fabrik.\nSpecialitet: Tillverkar Plastic-Padding\nAktiekapital: 50 000\nVeikst dir: Gösta Ericson\nEtableringsår: 1959.\n\nFOTO TRÅLBINDERI\n\nPnr 430 92\n\nFotö. Tel 031-78 0049, 78 16 28.\nBankgiro 55-4133. Postgiro 42670\nVerksamhet: Tillverkar fiskredskap\nAntal anställda: 18\nÅrsomsättning: 1500 000\nChef: David Gustavsson.\n\nFOUNDRYCONSULT\nCOMPANY AB\n\nPnr 611 00\n\nNyköping, Ringv 33. Tel\n0155-14154. Postgiro 110519-6. Tga\nFoundryconsult\n\nVerksamhet: Konsulterande inom\n\ngjuteriområdet\n\nAktiekapital: 6 000\n\nVerkst dir: Civiling J Drachmann\n\nEtableringsår: 1956.\n\nALBY KLORAT\n\nPnr 774 00\n\nAvesta, Månsbo. Tel 0226-504 80.\nPostgiro 98204. Tga Chlorate.\nTelex 7540 KLORAT S\nVerksamhet: Kemisk fabrik i Alby.\nKemisk fabrik o kraftstation i\nAvesta. Tillverkar kalium- o\nnatri-umklorat, fosfor o fosforprodukter,\nmagnetitelektroder samt producerar\nelektr energi\nAntal anställda: 250\nÅrsomsättning: 27 000000\nVerkst ledning: Dir Nils\nNordenborg, dir Gunnar Norlander\nFabriksing:r: Diploming Valdemar\nSimons (Månsbo), disp Gustav\nWallin (Alby)\n\nÄges av Svenska Tandsticks AB\nJönköping genom Svenska\nStabindustrier AB, Jönköping.\n\nALCAMO, AB\n\nPnr 200 62\n\nMalmö 9, Fack. Regementsg 16.\nTel 040-97 14 27, 12 71 89.\nBankgiro 348-2130. Postgiro 37698-8\nVerksamhet: Reservdelar m m för\nkontorsmaskiner\nAktiekapital: 20 000\nVerkst dir: Henry Persson\nEtableringsår: 1955.\n\nSKO\n\nSKÖVDE GRÄV &amp; SCHAKT\n\nPnr 54100\n\nSkövde, Richertsg 2. Tel\n0500-15972, 192 52. Bankgiro 21-0109.\nPostgiro 495048-1\nVerksamhet: Utför schaktning,\nplanerar, transporter\nAntal anställda: 29\nÄgare o chef: Sven Magnusson.\n\nSKÖVDE KONTROLL.\nSLAKTERI, AB\n\nPnr 541 00\n\nSkövde, Aspelundsv. Tel\n0500-18190. Postgiro 270751-1\nVerksamhet: Slakteri o partihandel\nmed hela fall av kött o fläsk\nAntal anställda: 70\nÅrsomsättning: 49 000 000\nAktiekapital: 450 000\nVerkst dir: Sven Sköld\nEtableringsàr: 1943.\n\nSKÖVDE OFFSETTRYCK AB\n\nSkövde 1, Box 246. Kvarnv,\nSkul-torp. Tel 0500-34015. Bankgiro\n210-2721. Postgiro 541140-0\nVerksamhet: Tryckning av offset\n.Antal anställda: 27\nÅrsomsättning: 3 500 000\nAktiekapital: 60 000\nStyrelse: Dir Lars-Erik Meijer,\nBo-Göran Meijer\nChef: Dir Lars-Erik Meijer\nEtableringsàr: 1962.\n\nSKÖVDE-HJO SPARBANK\n\nPnr 54101\n\nSkövde 1, Box 123. Rådhusg 20.\nTel 0500-18100. Bankgiro 981-2991.\nPostgiro 6320-6\nVerksamhet: Fullständig\nbankservice\n\n.Antal anställda: 70\nÅrsomsättning: 266 307 000\nVerkst dir: Bengt Skoglund\nEtableringsàr: 1861.\n\nSLANGSPECIALISTEN\nAB TEXAN\n\nPnr 216 14\n\nMalmö, Getg 23. Tel 040-16 20 40.\nBankgiro 870-2094. Postgiro\n431391-2. Tga Texanimport\nVerksamhet: Metall-, gummi-,\nplast-o teflonslang, slangarmatur\nVarunamn: Texan\nAktiekapital: 100 000\nVerkst dir Knut Hedberg\nEtableringsàr: 1956.\n\nSLERTMANS\nSMIDES-VERKSTAD\n\nPnr 67100\n\nArvika, Fallebergsv. Tel\n0570-104 96, 116 00. Postgiro 324732-7\nVerksamhet: Tillverkar travsulkies\no trav-, galopp- o ponnieskor\nChef: Folke Slertman\nEtableringsàr: 1942.\n\nSL-FÄRJORNA AB\n\nPnr 261 22\n\nLandskrona 1, Box 104. S Långg.\nFärjestationen. Tel 0418-164 50.\nBankgiro 868-6461. Postgiro\n654400-1. Tga Scarlett.\nTelex 72288 SLFERRY S\n\nVerksamhet: Färjetrafik mellan\nLandskrona o Köpenhamn\nDotterbolag till Linjebuss\nInternational AB\nSe detta bolag.\n\nSLIMA.VERKEN\n\nPnr 343 00\n\nÄlmhult, Skånev. Tel 0476-122 30.\n\nBankgiro 873-8650. Postgiro\n269998-1. Tga Slima\nVerksamhet: Tillverkar\nbakelitbundna navrondeller, kapskivor,\nslipskivor, stensågklingor m m\nAntal anställda: 20\nÅrsomsättning: 1 000 000\nChef: Sven Wallin\nEtableringsàr: 1944.\n\nS LIP-BRANZA, AB\n\nPnr 65107\n\nKarlstad 1, Box 468. Lantvärnsg 8.\nTel 054-1157 60. Bankgiro\n344-5277. Postgiro 32506-8.Tga Branza\nVerksamhet: Tillverkar slipmaterial\nAktiekapital: 50 000\nVerkst dir. Börje Pettersson\nEtableringsàr: 1961.\n\nSLIPINDUSTRI, AB\n\nPnr 632 21\n\nEskilstuna, Kungsg 74. Tel\n016-13 90 19. Bankgiro 601-5358.\nPostgiro 336989-9\n\nVerksamhet: Tillverkar pinnfräsar,\nändplanfräsar o kilspårsfräsar\nAntal anställda: 17\nÅrsomsättning: 1 200 000\nAktiekapital: 60 000\nVerkst dir: Lars Degefors\nEtableringsàr: 1947.\n\nSLIPMATERIAL DILOX AB\n\nPnr 54101\n\nSkövde 1, Box 23. Tel 0500-81080.\nBankgiro 364-9688. Postgiro\n336278-7. Tga Dilox\nVerksamhet: Tillverkning o\nförsäljning av slipmateriel\nVarunamn: Dilox\nAktiekapital: 100 000\nDisp: H Wahlström\nEtableringsàr: 1949.\n\nSLIPMATERIALAFFÄREN\n\nPnr 200 13\n\nMalmö 27, Hanög 2 A. Fack. Tel\n040-18 09 20. Bankgiro 64-0159.\nPostgiro 38069. Tga Slipaffären\nVerksamhet: Säljer Carborundum\no Aloxite slipskivor, Carborundum\nslipduk, slippapper o\ntejp-produkter, Greif, SMA m fi slipmaskiner\nServicekontor: Göteborg H,\nEke-träg 2 A. Box 21039, Gbg 21. Tel\n031-22 44 59\n\nÖrebro, Hjalmar Bergmans v 36.\nBox 7005. Tel 019-1303 70\nVarunamn: Aloxite, Carborundum,\nGreif, SMA\n\nChef: Disp Owe Nilsson\nFörsäljn-chef: Knut Nilsson\nEtableringsàr: 1907.\n\nSLIPMATERIAL-NAXOS, AB\n\nPnr 593 01\n\nVästervik 1, Folkparksv 31. Fack.\nTel 04 90-130 00. Bankgiro\n667-0574. Postgiro 14818-9.\n\nTga Slipmaterial. Telex 3917\nVerksamhet: Tillverkar keramiska-,\nfenoplastbundna-, diamant- o\nbor-nitridslipskivor, kapskivor,\nnavrondeller, polerslipskivor ,\nslipsegment, slipstift, brynen,\nstensågklingor, slipmaskiner, verktyg för\nrivning av slipskivor, slippapper o\nslipduk. Undervisning i slipteknik\nAvdelningskontor: Boliden, Storg\n39. Tel 0910-610 59\nBollstabruk, Källåkersv 8. Tel\n0612-210 32\n\nEskilstuna, Rademacherg 19. Tel\n016-14 57 20\n\nFalun, Gruvg 16-18. Tel 023-197 98\nGöteborg C, Skeppsbroplatsen 1.\nTel 031-171135\nMalmö O, Kruse g 48. Tel\n040-93 42 35\n\nStockholm K, John Ericssonsg 9.\nTel 08-52 09 90\n\nVarunamn: Alumo, Krokodil,\nRoto-flex, Sicto, Stenalon, Veralon,\nPolybond\n\nAntal anställda: 600\nAktiekapital: 9000 000\nStyrelse: Dir Olov Herneryd(ordf),\ndir Olof Rinné, dir N Malte Nilsson,\nförsäljn-chef Yngve Carlén\nVerkst dir: N Malte Nilsson\nFörsäljn-chef: Rune Cederlund\nIntendent: Hans Holmgren\nEtableringsàr: 1895\nBolaget bildades 1942 genom\nsammanslagning av AB Slipmaterial,\nVästervik, grundat 1913 o AB\nSvenska Naxos, Lomma, grundat 1895.\nÄgare: Höganäs AB.\n\nSLIPSTENAR, AB\n\nPnr 802 33\n\nGävle, S Skeppsbron 20. Tel\n026-12 2022. Postgiro 34209-7\nVerksamhet: Säljer slipstenar o\npluggmassa\nAktiekapital: 10 000\nVerkst dir: Carl Rahm\nEtableringsàr 1911.\n\nWENNARDT AB, NILS\n\nPnr 403 11\n\nGöteborg 2, Kungsg 15. Box 2031.\nTel 031-1109 21. Bankgiro 84-8315.\nPostgiro 427940. Tga Niwab\nVerksamhet: Export av\nverkstadsindustriprodukter o import av\nindustriråvaror\nAktiekapital: 100 000\nVerkst dir: Nils Wennardt\nEtableringsår: 1954.\n\nMARINKONSTRUKTIONER\n\nPnr 402 21\n\nGöteborg 5, Lundbyhamnen 122.\nBox 5009. Tel 031-22 85 44, 22 76 55.\nBankgiro 500-6846. Postgiro\n241282. Tga Marinko. Telex 20997\nVerksamhet: Effektiv lasthantering\nHalléns patent: Bipodmaster,\nuniversal o containerbommar,\nfallrepstrappor, landgångar m m\nÄgare o chef: Civiling Eskil\nHallén\n\nEtableringsår: 1946.\n\nMARIN-MONTAGE AB,\nINGE NIORSFIRMA\n\nPnr 12143\n\nJohanneshov, Huddingev 113.\nTel 08-4928 30. Postgiro 253517.\nTelex 10376 marinmontage\nVerksamhet: Marinelektrisk\nutrustning o instrument\nAntal anställda: 75\nÅrsomsättning: 6 000 000\nAktiekapital: 125 000\nVerkst dir: Arne Larsson\nEtableringsår: 1946.\n\nMARINPRODUKTER\n\nPnr 400 43\n\nGöteborg 30, Box 30058.\nPennygången 78. Tel 031-41 64 35,\n82 29 00. Bankgiro 439-9655.\nPostgiro 41560-4.\nTelex 21090 BEJOHAB S\nVerksamhet: Säljer armatur för gas,\nvatten o ånga, elektr motorer o\nstartapparater, pumpar,\nnivåmätning. Representant för Norsk\nHydro Verksteder AS o\nNoratom-Norcontrol AS\n\nVarunamn: DRAMMEN,\nHidrover-tapumpar\n\nChef: Ing Bertil Johnsson\nEtableringsår: 1962.\n\nNILSSON AB, RICHARD\n\nPnr 131 00\n\nNacka, Becksjudarv 35. Tel\n08-7162645. Postgiro 153192-0. Tga\nSteelman. Telex 1634 STEEL S\nVerksamhet: Maskiner,\ndestruk-tionsanläggningar, valsar, malm,\nrör samt eldfast materiel\nAntal anställda: 14\nAktiekapital: 315 000\nStyrelse: Dir Per Nilson, dir Olof\nRastad\n\nVerkst dir: Olof Rastad\nEtableringsår: 1936\nOmbildat till aktiebolag 1946.\n\nNILSSON AB, ROLF\n\nPnr 430 21\n\nAskloster, Box 51. Tel\n0340-26200. Bankgiro 425-1674.\nPostgiro 474335-7.\nTelex 3473 NILSSON S\nVerksamhet: Säljer skor m m\nengros\n\nFörsäljningskontor 115 27\nStockholm, Wittstocksg 40. Tel\n08-67 2168\n\nAntal anställda: 35\nÅrsomsättning: 30 000 000\nAktiekapital: 100 000\nVerkst dir: Rolf Nilsson\nFörsäljn-chef: Henry Eliasson\nInköpschef: Börje Kling\nEkonomichef: Christer Larsson\nEtableringsår: 1954.\n\nLAN\n\nAktiekapital: 60 000\nVerkst dir: Disp Carsten Lange\nEtableringsår: 1926\nOmbildat till aktiebolag 1941.\n\nLANGES MEK VERKSTAD\nAB, E\n\nPnr 68100\n\nKristinehamn, Hamnbrog 4. Tel\n0550-115 22. Postgiro 24358-4\nVerksamhet: Tillverkar verktyg\nför bil- o gummiverkstäder\nAntal anställda: 5\nÅrsomsättning: 300 000\nAktiekapital: 20 000\nVerkst dir: Ing Emil Lange\nEtableringsår: 1925.\n\nJIN\n\nÅrsomsättning: 1500000\nAktiekapital: 10000\nVerkst dir: Lars Ingvar Nordström\nEtableringsår. 1879.",
    "structured": {
        "1": {
            "company_name": "VÄRMEKONSULTBYRÄN AB",
            "pnr": "11122",
            "address": "Stockholm C, Kungsg 66.",
            "phone_number": "08-11 99 95, 21 97 95.",
            "bank_details": {
                "postgiro": "351930"
            },
            "activity": "Konsulterande inom ångteknik o VVS",
            "employees": 5,
            "capital": 5000,
            "key_personnel": [
                {
                    "name": "Ing Yngve Gustavsson",
                    "position": "Verkst dir"
                }
            ],
            "establishment_year": 1954
        },
        "2": {
            "company_name": "HJÄ",
            "activity": "Tillverkning av Denco Ploor dubbelgolv speciellt avsett för datacentraler",
            "capital": 50000,
            "key_personnel": [
                {
                    "name": "Ing Erie Wrethagen",
                    "position": "Styrelseordförande"
                },
                {
                    "name": "dott Claudio Rossi",
                    "position": "Styrelsedirektör"
                },
                {
                    "name": "ing Stig Odén",
                    "position": "Verkställande direktör"
                }
            ],
            "establishment_year": 1967
        },
        "3": {
            "company_name": "HIRSCHS KEMIKALIE. IMPORT, AB",
            "pnr": "11140",
            "address": "Stockholm. Tegnérg 1.",
            "phone_number": "08-20 0 8 77,20 08 78.",
            "bank_details": {
                "bankgiro": "56-9308",
                "postgiro": "250701-0"
            },
            "activity": "Importerar alla slags kemikalier o råvaror samt livsmedel",
            "employees": 5,
            "capital": 30000,
            "key_personnel": [
                {
                    "name": "G Hirsch",
                    "position": "Verkst dir"
                }
            ],
            "establishment_year": 1945
        },
        "4": {
            "company_name": "HIRSCHS METALL AB",
            "prr": "12612",
            "address": "Stockholm 42, Box 42028. Lerkrogs-v 9-11, Västberga Industriområde, Hägersten.",
            "phone_number": "08-45 2950.",
            "bank_details": {
                "bankgiro": "56-9512",
                "postgiro": "53451"
            },
            "activity": "Metallraffinerings-verk",
            "capital": 200000,
            "key_personnel": [
                {
                    "name": "Sune Mö me",
                    "position": "Verkst dir"
                },
                {
                    "name": "Björn Strauss",
                    "position": "Disp"
                }
            ],
            "establishment_year": 1907
        },
        "5": {
            "company_name": "HISINGEPLAST, AB",
            "pnr": "403 11",
            "address": "Göteborg 2, Lillhagsv. Box 2043.",
            "phone_number": "031-170220, 2260 00.",
            "bank_details": {
                "bankgiro": "852-6501",
                "postgiro": "622480-2"
            },
            "activity": "Kem tekn fabrik. Specialitet: Tillverkar Plastic-Padding",
            "employees": 0,
            "capital": 50000,
            "key_personnel": [
                {
                    "name": "Gösta Ericson",
                    "position": "Verkst dir"
                }
            ],
            "establishment_year": 1959
        },
        "6": {
            "company_name": "FOTO TRÅLBINDERI",
            "pnr": "430 92",
            "activity": "Tillverkar fiskredskap",
            "employees": 18,
            "annual_turnover": 1500000,
            "key_personnel": [
                {
                    "name": "David Gustavsson",
                    "position": "Chef"
                }
            ]
        },
        "7": {
            "company_name": "FOUNDRYCONSULT COMPANY AB",
            "pnr": "611 00",
            "address": "Nyköping, Ringv 33.",
            "phone_number": "0155-14154.",
            "bank_details": {
                "postgiro": "110519-6"
            },
            "activity": "Konsulterande inom gjuteriområdet",
            "capital": 6000,
            "key_personnel": [
                {
                    "name": "Civiling J Drachmann",
                    "position": "Verkst dir"
                }
            ],
            "establishment_year": 1956
        },
        "8": {
            "company_name": "ALBY KLORAT",
            "pnr": "774 00",
            "address": "Avesta, Månsbo. Tel 0226-504 80.",
            "postgiro": "98204",
            "activity": "Kemisk fabrik i Alby. Kemisk fabrik o kraftstation i Avesta. Tillverkar kalium- o natri-umklorat, fosfor o fosforprodukter, magnetitelektroder samt producerar elektr energi",
            "employees": 250,
            "annual_turnover": 27000000
        },
        "9": {
            "company_name": "ALCAMO, AB",
            "pnr": "200 62",
            "address": "Malmö 9, Fack. Regementsg 16.",
            "phone_number": "040-97 14 27, 12 71 89.",
            "bank_details": {
                "bankgiro": "348-2130",
                "postgiro": "37698-8"
            },
            "activity": "Reservdelar m m för kontorsmaskiner",
            "capital": 20000,
            "key_personnel": [
                {
                    "name": "Henry Persson",
                    "position": "Verkst dir"
                }
            ],
            "establishment_year": 1955
        },
        "10": {
            "company_name": "SKÖVDE GRÄV & SCHAKT",
            "pnr": "54100",
            "address": "Skövde, Richertsg 2.",
            "phone_number": "0500-15972, 192 52.",
            "bank_details": {
                "bankgiro": "21-0109",
                "postgiro": "495048-1"
            },
            "activity": "Utför schaktning, planerar, transporter",
            "employees": 29,
            "key_personnel": [
                {
                    "name": "Sven Magnusson",
                    "position": "Ägare o chef"
                }
            ]
        }
    }
}