{
    "original": "NEGLINGEVARVET, AB\n\nPnr 133 00\n\nSaltsjöbaden, Vikingav 17. Tel\n08-71712 37. 7171253. Bankgiro\n165-2072. Postgiro 29044-5. Tga Plyms\nVerksamhet: Nybyggnad o reparar\ntion av segel- o motoryachter\nAntal anställda: 21\nEtableringsår: 1893.\n\nMOTALA GLASMÄSTERI AB\n\nPnr 591 01\n\nMotala 1, Box 93. Pabriksg 4. Tel\n0141-105 29, 112 57. Bankgiro\n822-0196. Postgiro 92700-4\nVerksamhet: Glasmästeri\nAntal anställda: 5\nÅrsomsättning: 4 500 000\nAktiekapital: 10 000\nVeikst dir: Pähr Johansson\nEtableringsår: 1942.\n\nSCANGOTHIA AB\n\nPnr 402 31\n\nGöteborg 7, Haga österg 14. Box\n7032. Tel 031-13 86 63, 138643.\nBankgiro 847-9552. Postgiro\n240568-6. Tga Scangot.\nTelex 21181\n\nVerksamhet: Importagenturer inom\nartiklar för hem, hushåll o sport\nChef: G Olsson\nEtableringsår: 1945.\n\nGRA\n\n19046. Tel 08-34 04 70. Bankgiro\n73-1283. Postgiro 559446\nVerksamhet: Boktryck-offset,\ntidskrifter, böcker, kommersiellt tryck\nAntal anstäUda: 20\nÅrsomsättning: 2 000 000\nAktiekapital: 220 000\nVerkst dir: Gösta Lindstrand\nEtableringsår: 1949.\n\n08-51 34 40, 5145 55. Bankgiro\n73-1309. Postgiro 44783-9\nVerksamhet: Framställning av\nklichéer o offsetplåtar\nAntal anställda: 15\nÅrsomsättning: 800 000\nAktiekapital: 70 000\nVerkst dir: Ake Rolf\nEtableringsår: 1948.\n\nHAMMARSTRÖM AB, IVAR\n\nPnr 85102\n\nSundsvaU 1, Storg 10. Box 56. Tel\n060-15 08 20. Bankgiro 774-4972.\nPostgiro 476280-3. Telex 71217\nVerksamhet: Säljer\nindustriförnödenheter. Representant i Norrland\nför AB Electrolux (stålinredningar),\nHvilans Mek Verkstads AB, Häfla\nBruks AB, AB Iggesunds Bruk,\nJohnson Metall AB\nAktiekapital: 60 000\nVerkst dir: Ing Ivar Hammarström\nEtableringsår: 1959.\n\nENVALL, AB BRÖDERNA\n\nPnr 710 41\n\nFellingsbro, Box 81. Tel\n0589-20525. Bankgiro 81-8507. Postgiro\n23136. Tga Envallbröderna\nVerksamhet: Projektering, leverans\no montage av transport-, kross- o\nsorteringsanläggningar för gruvor,\n\njärnbruk, kem tekn industri etc\nAvdelningskontor för transport-,\nkross- o sorteringsanläggningar:\n\n70112 Cfrebro, Oskarsparken 1. Tel\n\n019-124970\n\nAntal anställda: 110\n\nÅrsomsättning: 10 000 000\n\nAktiekapital: 300 000\n\nStyrelse: Ing Bengt Envall (ordf),\n\ndisp Karl Axel Envall, dir-ass L M\n\nEnvall\n\nVerkst dir: Karl Axel Envall\nEtableringsår: 1907.\n\nGAR\n\nGARNIMPORT, AB\n\nPnr 431 21\n\nMölndal 1. Delbancog 11. Box 57.\nTel 031-27 98 05, 27 98 06. Bankgiro\n509-7613. Postgiro 240209-7.\nTga Garnimport.\nTelex 21142 GARNIMP S\nVerksamhet: Säljer garner,\nfärdigsydda lakan, påslakan o örngott\nAktiekapital: 10 000\nVerkst dir: Ing Rune Ström\nEtableringsår: 1963.\n\nPERFORERAD PLÄT, AB\n\nPnr 81200\n\nStorvik, Box 33. Tel 0290-111 90.\nBankgiro 789-4116. Postgiro\n80437-7. Tga Perforeradplåt\nVerksamhet: Perforerad plåt,\nkall-formade profiler o diverse\nplåtkonstruktioner i tunnplåt\nAnstal anställda: 65\nÅrsomsättning: 8 000 000\nAktiekapital: 480 000\nStyrelse: Tjänsteman T Isberg\n(ordf), tjänsteman E Westlund,\ntjänsteman L-E Westlund, G Jirving,\nI Johansson, ing M Isberg\nVeikst dir: Börje Holm\nEtableringsår: 1932.\n\nPOOLSPECIALISTEN AB\n\nPnr 146 00\n\nTullinge, Falkbergsv 7-9. Tel\n08-7780180. Bankgiro 301-4735.\nPostgiro 408582-5\n\nVerksamhet: Tillverkar o säljer\nvillapooler o simbassänger\nAntal anställda: 11\nÅrsomsättning: 2 000 000\nAktiekapital: 10000\nVerkst dir: Civiling Per Wilmenius\nEtableringsår: 1963.\n\nAC-MEKAN, FÖRSÄLJNINGS AB\n\nPnr 93101\n\nSkellefteå 1, Kanalg 73. Box 15.\nTel 0910-77200. Bankgiro 20^1060.\nPostgiro 66085\n\nVerksamhet: Samägt\nförsäljnings-o utvecklingsaktiebolag för\nmekanisk industri\n\nTunnplåtearbeten: Pressning,\ndjup-dragning, trycksvarvning,\nsvetsning, montage, målning\n\nGrovplåtsarbeten: Plåt- o\nbalkkonstruktioner, formning, svetsning\n(även licenssvetsning), montage,\nmålning\n\nRörkonstruktioner: Formning,\nsvetsning, bockning, montage, målning\nSkärande bearbetning\nSänksmide: Största styckevikt 1 kg\nGjutgods\n\nKompletta anläggningar:\nTransportanläggningar, processanläggningar\nAntal anställda: 5\nAktiekapital: 145 000\nStyrelse: Dir Lars Anton Lindqvist\n(ordf), dir Olle Landseli, dir Sam\nÖgren, ing Dan Eriksson, prod-chef\nThore Bäcklund\nVerkst dir: Olle Landseli\nEtableringsår: 1965.",
    "structured": {
        "1": {
            "company_name": "NEGLINGEVARVET, AB",
            "pnr": "133 00",
            "address": "Saltsjöbaden, Vikingav 17",
            "phone_number": "08-71712 37, 7171253",
            "bank_details": {
                "bankgiro": "165-2072",
                "postgiro": "29044-5"
            },
            "activity": "Nybyggnad o reparar tion av segel- o motoryachter",
            "employees": 21,
            "establishment_year": 1893
        },
        "2": {
            "company_name": "MOTALA GLASMÄSTERI AB",
            "pnr": "591 01",
            "address": "Motala 1, Box 93, Pabriksg 4",
            "phone_number": "0141-105 29, 112 57",
            "bank_details": {
                "bankgiro": "822-0196",
                "postgiro": "92700-4"
            },
            "activity": "Glasmästeri",
            "employees": 5,
            "annual_turnover": 4500000,
            "capital": 10000,
            "key_personnel": {
                "Veikst dir": "Pähr Johansson"
            },
            "establishment_year": 1942
        },
        "3": {
            "company_name": "SCANGOTHIA AB",
            "pnr": "402 31",
            "address": "Göteborg 7, Haga österg 14, Box 7032",
            "phone_number": "031-13 86 63, 138643",
            "bank_details": {
                "bankgiro": "847-9552",
                "postgiro": "240568-6"
            },
            "activity": "Importagenturer inom artiklar för hem, hushåll o sport",
            "key_personnel": {
                "Chef": "G Olsson"
            },
            "establishment_year": 1945
        },
        "4": {
            "company_name": "GRA",
            "address": "19046",
            "phone_number": "08-34 04 70",
            "bank_details": {
                "bankgiro": "73-1283",
                "postgiro": "559446"
            },
            "activity": "Boktryck-offset, tidskrifter, böcker, kommersiellt tryck",
            "employees": 20,
            "annual_turnover": 2000000,
            "capital": 220000,
            "key_personnel": {
                "Verkst dir": "Gösta Lindstrand"
            },
            "establishment_year": 1949
        },
        "5": {
            "company_name": "08-51 34 40, 5145 55",
            "bank_details": {
                "bankgiro": "73-1309",
                "postgiro": "44783-9"
            },
            "activity": "Framställning av klichéer o offsetplåtar",
            "employees": 15,
            "annual_turnover": 800000,
            "capital": 70000,
            "key_personnel": {
                "Verkst dir": "Ake Rolf"
            },
            "establishment_year": 1948
        },
        "6": {
            "company_name": "HAMMARSTRÖM AB, IVAR",
            "pnr": "85102",
            "address": "SundsvaU 1, Storg 10, Box 56",
            "phone_number": "060-15 08 20",
            "bank_details": {
                "bankgiro": "774-4972",
                "postgiro": "476280-3"
            },
            "activity": "Säljer industri förnödenheter",
            "representant": "AB Electrolux (stålinredningar), Hvilans Mek Verkstads AB, Häfla Bruks AB, AB Iggesunds Bruk, Johnson Metall AB ",
            "capital": 60000,
            "key_personnel": {
                "Verkst dir": "Ing Ivar Hammarström"
            },
            "establishment_year": 1959
        },
        "7": {
            "company_name": "ENVALL, AB BRÖDERNA",
            "pnr": "710 41",
            "address": "Fellingsbro, Box 81",
            "phone_number": "0589-20525",
            "bank_details": {
                "bankgiro": "81-8507",
                "postgiro": "23136"
            },
            "activity": "Projektering, leverans o montage av transport-, kross- o sorteringsanläggningar för gruvor, järnbruk, kem tekn industri etc",
            "division_office": "70112 Cfrebro, Oskarsparken 1",
            "division_phone_number": "019-124970",
            "employees": 110,
            "annual_turnover": 10000000,
            "capital": 300000,
            "key_personnel": {
                "Styrelse": "Ing Bengt Envall (ordf), disp Karl Axel Envall, dir-ass L M Envall",
                "Verkst dir": "Karl Axel Envall"
            },
            "establishment_year": 1907
        },
        "8": {
            "company_name": "GARNIMPORT, AB",
            "pnr": "431 21",
            "address": "Mölndal 1, Delbancog 11, Box 57",
            "phone_number": "031-27 98 05, 27 98 06",
            "bank_details": {
                "bankgiro": "509-7613",
                "postgiro": "240209-7"
            },
            "activity": "Säljer garner, färdigsydda lakan, påslakan o örngott",
            "capital": 10000,
            "key_personnel": {
                "Verkst dir": "Ing Rune Ström"
            },
            "establishment_year": 1963
        },
        "9": {
            "company_name": "PERFORERAD PLÄT, AB",
            "pnr": "81200",
            "address": "Storvik, Box 33",
            "phone_number": "0290-111 90",
            "bank_details": {
                "bankgiro": "789-4116",
                "postgiro": "80437-7"
            },
            "activity": "Perforerad plåt, kall-formade profiler o diverse plåtkonstruktioner i tunnplåt",
            "employees": 65,
            "annual_turnover": 8000000,
            "capital": 480000,
            "key_personnel": {
                "Styrelse": "Tjänsteman T Isberg (ordf), tjänsteman E Westlund, tjänsteman L-E Westlund, G Jirving, I Johansson, ing M Isberg",
                "Veikst dir": "Börje Holm"
            },
            "establishment_year": 1932
        },
        "10": {
            "company_name": "POOLSPECIALISTEN AB",
            "pnr": "146 00",
            "address": "Tullinge, Falkbergsv 7-9",
            "phone_number": "08-7780180",
            "bank_details": {
                "bankgiro": "301-4735",
                "postgiro": "408582-5"
            },
            "activity": "Tillverkar o säljer villapooler o simbassänger",
            "employees": 11,
            "annual_turnover": 2000000,
            "capital": 10000,
            "key_personnel": {
                "Verkst dir": "Civiling Per Wilmenius"
            },
            "establishment_year": 1963
        },
        "11": {
            "company_name": "AC-MEKAN, FÖRSÄLJNINGS AB",
            "pnr": "93101",
            "address": "Skellefteå 1, Kanalg 73, Box 15",
            "phone_number": "0910-77200",
            "bank_details": {
                "bankgiro": "20^1060",
                "postgiro": "66085"
            },
            "activity": "Samägt försäljnings-o utvecklingsaktiebolag för mekanisk industri",
            "capabilities": "Tunnplåtearbeten: Pressning, djup-dragning, tryck svarvning, svetsning, montage, målning. Grovplåtsarbeten: Plåt- o balkkonstruktioner, formning, svetsning (även licenssvetsning), montage, målning. Rörkonstruktioner: Formning, svetsning, bockning, montage, målning. Skärande bearbetning. Sänksmide: Största styckevikt 1 kg. Gjutgods. Kompletta anläggningar: Transportanläggningar, processanläggningar",
            "employees": 5,
            "capital": 145000,
            "key_personnel": {
                "Styrelse": "Dir Lars Anton Lindqvist (ordf), dir Olle Landseli, dir Sam Ögren, ing Dan Eriksson, prod-chef Thore Bäcklund",
                "Verkst dir": "Olle Landseli"
            },
            "establishment_year": 1965
        }
    }
}