{
    "original": "TRANSCHARTER, AB\n\nPnr 41113\n\nGöteborg, Packhusplatsen 2. Tel\n031-116132, 1138 20. Tga\nIngjan-ship. Telex 2373 CHARLES S\nVerksamhet: Befraktning o\nspecialtransporter över hela världen.\nAgent för Independent Shipping\nAgency SA, Genève\nAktiekapital: 10 000\nStyrelseordf: Dir Ingemar Jonsson\nVerkst dir: Ralf E Hart\nEtableringsår: 1969\nDotterbolag till Charles Thorburn\nGöteborg AB.\n\nTRANS-EX, REDERI AB\n\nPnr 403 10\n\nGöteborg 2, Pack. Packhusplatsen\n3. Tel 031-17 67 00. Bankgiro\n500-5715. Postgiro 12107. Tga Nike.\nTelex 2300\n\nVerksamhet: Rederirörelse\nAktiekapital: 3 000 000\nVerkst dir. Rolf Carlsson\nEtableringsår: 1940.\n\nGRÖNLUNDS FISKE, AB\n\nPnr 912 00\n\nVilhelmina, Box 101. Tel\n0940-106 46. Bankgiro 765-2357.\nPost-giro 173581-0\n\nVerksamhet: Tillverkar\nsportfiskredskap, såsom flugor alla typer,\ndrag, spinnare, håvar o d\nVarunamn: RGV\nAntal anställda: 15\nÅrsomsättning: 800 000\nVerkst din Karl Grönlund.\n\nGRÖNLUNDS ORGELBYGGERI\n\nPnr 950 10\n\nGammelstad, Hantverksv 22. Tel\n0920-541 65, 532 30. Bankgiro\n75-2481. Postgiro 67544\nVerksamhet: Tillverkar piporglar\ni alla storlekar. Specialitet:\nhelmekaniska orglar. Eget plpmakeri\nAntal anställda: 36\nÅrsomsättning: 2 000 000\nVerkst dir: J Gustaf Grönlund\nInnehavare: Ruth Grönlund\nIntonatörer: Jan-Olof Grönlund,\nAnders Grönlund\nEtableringsår: 1930.\n\nPETERSSON, AB BRUNO\n\nPnr 534 00\n\nVara. Tel 0512-113 00, 113 21\nVerksamhet: Tillverkar\nlantbruksmaskiner o hammarkvarnar\nAntal anställda: 25\nÅrsomsättning: 2 000000\nChef: Fabr Bruno Petersson\nEtableringsår: 1952.\n\nLEO\n\nStyrelse: Dir L Bylund, dir G\nMan-kert\n\nVerkst dir: L Andersson\nEtableringsår: 1954.\n\nLUFBERGS AB, BRÖDERNA\n\nPnr 652 26\n\nKarlstad,Älvg 17.Tel 054-11 1742.\nBankgiro 100-0645. Postgiro\n8427-7. Tga Löfbergs\nAktiekapital: 300 000\nVerkst dir: Konsul Henning\nJohnson\n\nEtableringsår: 1906\nOmbildat till aktiebolag 1916.\n\nLOFBERG, AB ANDERS\n\nPnr 65106\n\nKarlstad 1, Box 368. Tolagsg 1.\nTel 054-15 00 80. Bankgiro\n881-3206, Postgiro 13154-0. Tga\nAbai. Telex 66035\nVerksamhet: Kaffeimport o rosteri\nVarunamn: Löfbergs Lila\nAktiekapital: 2 000 000\nVerkst dir: Ake Löfberg\nEtableringsår: 1906\nOmbildat till aktiebolag 1927.\nÄger AB Löf-Eda Verken,\nKarlstad (se detta bolag).\n\nLOFBERG, AB HARALD\n\nPnr 101 10\n\nStockholm 1, Kungsg 66. Fack. Tel\n08-22 66 00. Bankgiro 56-3513.\n\nPostgiro 884. Tga Sextiosex\nVerksamhet: Hemtextil, sängar,\nmodetyger, leverans- o\ninredningsavdelning\n\nFilial: Sundbyberg, Landsv 65. Tel\n08-28 92 50. Stormarknad för\nheltäckningsmattor, linoleum o hemtextil\nAktiekapital: 800 000\nVerkst dir: Carl E Carlson\nEtableringsår: 1900.\n\nLOF DAHL ANNONSBYRÅ AB,\nKURT\n\nPnr 10110\n\nStockholm 1, Kungsg 55. Fack.\nTel 08-24 51 20. Bankgiro 564-6849.\nPostgiro 150379-6\nVeiksamhet: Auktoriserad\nannonsbyrå\n\nAntal anställda: 14\nÅrsomsättning: 5 000000\nAktiekapital: 125 000\nVerkst dir: Kurt Löfdahl\nEtableringsår: 1957.\n\nINVESTMENT AB PROMOTION\n\nPnr 11436\n\nStockholm, Stureg 38’. Tel\n08-67 04 55. Bankgiro 700-5820.\nPostgiro 709167-1. Tga Promotion\nVerksamhet: Pörvaltningsrörelse\nAntal anstäUda: 8\nAktiekapital: 50 322 200\nVerkst dir: Nils Edholm.\n\nINVESTOR, AB\n\nPnr 103 24\n\nStockholm 16, Wahrendorffsg 1. Box\n16174. Tel 08-23 37 90. Bankgiro\n16-0103. Tga Investor\nVerksamhet: Förvaltningsbolag\nAktiekapital: 60 000 000\nVeikst dir: Carl de Geer\nEtableringsår: 1916.\n\nDIE\n\nVarunamn: Acordial, Divinycell,\nNeway, P C Henderson, Lignacord,\nPlanacord, Sigerist\nAntal anställda: 62\nÅrsomsättning: 8 000 000\nAktiekapital: 1000 000\nStyrelseordf: Dir Bertil Diedrichs\nVerkst dir: Göran Diedrichs\nEtableringsår: 1909\nOmbildat 1968.\n\nTidigare namn: Bertildi AB,\nDiedrichs AB, Holmquist &amp; Co AB,\nTeknab.\n\nDIESELGENERATORER AB\n\nPnr 42241\n\nHisings Backa, Klassikerg 17.\nTel 031-518000. Bankgiro 20-1935.\nPostgiro 721483. Tga Dieselgen.\nTelex 21174 DISEL S\n\nVerksamhet: Säljer dieselmotorer,\ndieselgenerator-, pump- o\nkompressoraggregat. Agent för\nScandina-vian Engeneering Ltd A/S,\nKöpenhamn. Ensamförsäljare för\nMercedes-Benz o KVD dieselmotorer\nVarunamn: Mercedes-Benz, Ford,\nKVD\n\nAntal anställda: 4\nÅrsomsättning: 2 500 000\nAktiekapital: 10 000\nVerkst dir: Rolf Elf stedt\nEtableringsår: 1969.\n\nHEBE, METALLINDUSTRIEN\n\nPnr 330 33\n\nHillerstorp.Tel 0370-220 69,223 69.\nBankgiro 54-3212. Postgiro 27 65 24\nVerksamhet: Pressade\nmassartiklar. Specialitet: möbelbeslag\nChef: Fabr Sture Svensson\nEtableringsår: 1944.\n\nSECURITAS ALARM, AB\n\nPnr 104 60\n\nStockholm 20. Pack. Heliosv 12.\nTel 08-44 90 90. Bankgiro 730-7267.\nPostgiro 149090-3. Tga Securilarm\n\nsecuntas\n\nVerksamhet: Tillverkar o\ninstallerar automatiska inbrotts- o\növerfallslarmsystem, brandlarm,\nautomatiska identitetskontrollsystem,\nrobottelefoner,\nvisiteringskontroll-utrustnlngar, fjärrövervaknings-centraler, special-TV-anläggningar,\nfotokamerasystem för övervakning\nAvdelningskontor: 104 60\nStockholm 20, Pack. Heliosv 12. Tel\n08-44 90 90\n\n40232 Göteborg 7, Box 7105.\nPusterviksg 13. Tel 031-17 41 90\n20110 Malmö 1, Fack. Västerg 21.\nTel 040-745 00\n\n60002 Norrköping 2, Box 2114.\nReps lagarg 15. Tel 011-134115\n70008 Örebro 8, Box 8105.\nKöpmang 62-68. Tel 019-119140\n80222 Gävle, S Kungsg 10. Tel\n026-18 0070\n\n85230 Sundsvall, Storg 1. Tel\n060-1104 00\n\nVarunamn: Securicoll, Securilarm,\nSecurisense, Securitell,\nSecuri-space, Secvriguard, Securibeam,\nSecurismoke, Securiterm, Securifon,\nSecuriflam\nAntal anställda: 320\nÅrsomsättning: 20000 000\nAktiekapital: 500000\nStyrelse: Dir Axel Iveroth (ordf),\ngeneralkonsul Erik\nPhilip-Sörensen, bankdir Bengt Lindgren\nVerkst dir Olaf Holst\nEtableringsår 1948.\n\nLKB MEDICAL AB\n\nPnr 16111\n\nBromma, Ranhammarsv 21. Tel\n08-80 27 40. Bankgiro 16-0521.\nPostgiro 476028. Tga Medicalab\nVerksamhet: Tillverkar o säljer\nmedicinska apparater\nAntal anstäUda: 40\nÅrsomsättning: 6 500 000\nAktiekapital: 100 000\nVerkst din C-O Henrikson\nEtableringsår: 1959.",
    "structured": {
        "1": {
            "company_name": "TRANSCHARTER, AB",
            "pnr": "41113",
            "address": "Göteborg, Packhusplatsen 2",
            "phone_number": "031-116132",
            "bank_details": {
                "bankgiro": "",
                "postgiro": ""
            },
            "activity": "Befraktning o specialtransporter över hela världen. Agent för Independent Shipping Agency SA, Genève",
            "establishment_year": 1969
        },
        "2": {
            "company_name": "TRANS-EX, REDERI AB",
            "pnr": "403 10",
            "address": "Göteborg 2, Pack. Packhusplatsen 3",
            "phone_number": "031-17 67 00",
            "bank_details": {
                "bankgiro": "500-5715",
                "postgiro": "12107"
            },
            "activity": "Rederirörelse",
            "establishment_year": 1940
        },
        "3": {
            "company_name": "GRÖNLUNDS FISKE, AB",
            "pnr": "912 00",
            "address": "Vilhelmina, Box 101",
            "phone_number": "0940-106 46",
            "bank_details": {
                "bankgiro": "765-2357",
                "postgiro": "173581-0"
            },
            "activity": "Tillverkar sportfiskredskap, såsom flugor alla typer, drag, spinnare, håvar o d",
            "employees": 15,
            "annual_turnover": 800000,
            "capital": 0,
            "establishment_year": null
        },
        "4": {
            "company_name": "GRÖNLUNDS ORGELBYGGERI",
            "pnr": "950 10",
            "address": "Gammelstad, Hantverksv 22",
            "phone_number": "0920-541 65, 532 30",
            "bank_details": {
                "bankgiro": "75-2481",
                "postgiro": "67544"
            },
            "activity": "Tillverkar piporglar i alla storlekar. Specialitet: helmekaniska orglar. Eget plpmakeri",
            "employees": 36,
            "annual_turnover": 2000000,
            "key_personnel": [
                {
                    "name": "J Gustaf Grönlund",
                    "position": "Verkst dir"
                },
                {
                    "name": "Ruth Grönlund",
                    "position": "Innehavare"
                },
                {
                    "name": "Jan-Olof Grönlund",
                    "position": "Intonatörer"
                },
                {
                    "name": "Anders Grönlund",
                    "position": "Intonatörer"
                }
            ],
            "establishment_year": 1930
        },
        "5": {
            "company_name": "PETERSSON, AB BRUNO",
            "pnr": "534 00",
            "address": "Vara",
            "phone_number": "0512-113 00, 113 21",
            "activity": "Tillverkar lantbruksmaskiner o hammarkvarnar",
            "employees": 25,
            "annual_turnover": 2000000,
            "capital": 0,
            "establishment_year": 1952
        },
        "6": {
            "company_name": "LEO",
            "key_personnel": [
                {
                    "name": "L Andersson",
                    "position": "Verkst dir"
                }
            ],
            "establishment_year": 1954
        },
        "7": {
            "company_name": "LUFBERGS AB, BRÖDERNA",
            "pnr": "652 26",
            "address": "Karlstad, Älvg 17",
            "phone_number": "054-11 1742",
            "bank_details": {
                "bankgiro": "100-0645",
                "postgiro": "8427-7"
            },
            "activity": "Importera o rosteri",
            "employees": 0,
            "annual_turnover": 0,
            "capital": 300000,
            "establishment_year": 1906
        },
        "8": {
            "company_name": "LOFBERG, AB ANDERS",
            "pnr": "65106",
            "address": "Karlstad 1, Box 368, Tolagsg 1",
            "phone_number": "054-15 00 80",
            "bank_details": {
                "bankgiro": "881-3206",
                "postgiro": "13154-0"
            },
            "activity": "Kaffeimport o rosteri",
            "employees": 0,
            "annual_turnover": 0,
            "capital": 2000000,
            "establishment_year": 1906
        },
        "9": {
            "company_name": "LOFBERG, AB HARALD",
            "pnr": "101 10",
            "address": "Stockholm 1, Kungsg 66. Fack",
            "phone_number": "08-22 66 00",
            "bank_details": {
                "bankgiro": "56-3513",
                "postgiro": "884"
            },
            "activity": "Hemtextil, sängar, modetyger, leverans- o inredningsavdelning",
            "establishment_year": 1900
        },
        "10": {
            "company_name": "LOF DAHL ANNONSBYRÅ AB, KURT",
            "pnr": "10110",
            "address": "Stockholm 1, Kungsg 55. Fack",
            "phone_number": "08-24 51 20",
            "bank_details": {
                "bankgiro": "564-6849",
                "postgiro": "150379-6"
            },
            "activity": "Auktoriserad annonsbyrå",
            "employees": 14,
            "annual_turnover": 5000000,
            "capital": 125000,
            "establishment_year": 1957
        }
    }
}