{
    "original": "LDV\n\nVerksamhet: Säljer båtmotorer,\nbåtar o tillbehör\nChef: K W Löfgren\nEtableringsår: 1930.\n\nLüWGRENS\nELEKTRO-DIESEL AB, N\n\nPnr 70102\n\nÖrebro 1, Box 11. Fredsg 3. Tel\n019-119815. Bankgiro 642-1275.\nPostgiro 716100-3\nVerksamhet: Utför bilelektr\nreparationer o dieselreparationer.\nSäljer bilelektr artiklar i detalj o\nengros\n\nAntal anställda: 15\nÅrsomsättning: 1700 000\nAktiekapital: 10 000\nStyrelse: Dir Lars-Erik Bergstrand,\ndir Nils Löwgren\nVerkst dir: Nils Löwgren\nVerkmäst: Lars Wren\nLagerchef: Kenneth Englund\nKamrer: Lise-Lotte Molin\nFörsäljare: Gösta Stridh\nEtableringsår: 1968.\n\nLDFKVIST, LDFQUIST,\nLÖFQVIST\n\nLDFKVIST AB, BYGGNADS.\nFIRMA ARNE\n\nPnr 38100\n\nKalmar, Unionsg 21. Tel\n0480-109 00. Postgiro 163626-5\nVerksamhet: Utför\nhusbyggnadsarbeten, tekn utredningar,\nbyggnadskontroll o värderingar\nAntal anställda: 30\nAktiekapital: 20 000\nVerkst dir: Arne Löfkvist\nEtableringsår: 1952.\n\nLüFQUISTS ELEKTRISKA AB,\nHJALMAR\n\nPnr 103 81\n\nStockholm 7, Birger Jarlsg 23.\nBox 7022. Tel 08-23 20 00.\nBankgiro 238-6795. Postgiro 4750-6.\nTga Elektrolöfquist\nVerksamhet: Utför elektr\ninstallationer för ljus, kraft, värme o\ntele-signal. Säljer belysningsarmatur,\nelektr hushållsapparater o kylskåp\nAntal anställda: 90\nÅrsomsättning: 6 000 000\nAktiekapital: 170 000\nStyrelse: Adv Rolf Jörgensen (ordf),\nbankdir Alf Ericsson, dir Jan-Ake\nHedin\n\nVerkst dir: Jan-Ake Hedin\nEtableringsår: 1891\nOmbildat till aktiebolag 1920.\n\nLOKERYDS TRÄINDUSTRI\n\nPnr 56013\n\nHok. Tel 0393-200 07. Bankgiro\n146-4213. Postgiro 642001-2\nVerksamhet: Tillverkar o säljer\nlastpallar o pallramar\nAntal anställda: 8\nÅrsomsättning: 900 000\nChef: Fabr Janne Nordqvist\nVerkmäst: Jan-Ake Nordquist\nEtableringsår: 1963.\n\nTENSON.PRODUKTER AB\n\nPnr 432 00\n\nVarberg, Lassabacka. Tel\n0340-164 70. Bankgiro 106-3940.\nPostgiro 23154-8. Tga Tenson.\nTelex 3483\n\nVerksamhet: Tillverkar \"Tenson\"\nbad-, skid- o sportartiklar\nAntal anställda: 100\nÅrsomsättning: 10 000 000\nAktiekapital: 250 000\nVerkst dir: Paul Rydholm\nEtableringsår 1951.\n\nAK OPTIK INSTRUMENT AB\n\nPnr 104 60\n\nStockholm 20, Fack. Huddingev\n103 B, Johanneshov. Tel\n08-39 0100. Bankgiro 16-0644.\nPostgiro 56967. Tga Remind. Telex\n1562\n\nVerksamhet: Importerar o säljer\noptiska, vetenskapliga m fi\ninstrument. Generalagent för\nVEB Carl Zeiss JENA\n\nAktiekapital: 65 000\nVerkst dir: Stig Lundmark\nEtableringsår: 1949.\n\nKIHLSHIP AB\n\nPnr 41121\n\nGöteborg, skeppsbron 4. Tel\n031-17 62 90. Bankgiro 420-2263.\nPostgiro 425608-7. Tga Kihlship.\nTelex 2274\n\nVerksamhet: Rederirörelse, köp o\nförsäljning av fartyg\nAntal anställda: 19\nAktiekapital: 325 000\nVerkst dir: Lennart Kihlberg\nEtableringsår: 1952.\n\nKIHLSTROMS MANOMETER.\nFABRIK, AB\n\nPnr 11638\n\nStockholm, Malmgårdsv 63. Tel\n08-23 22 05. Bankgiro 73-2374.\nPostgiro 156040. Tga Termomano.\nTelex 17508 AKM S\nVerksamhet: Tillverkar\ntemperaturmätare o tryckmätare m m\nVarunamn: AKM\nAntal anställda: 70\nÅrsomsättning: 4 500 000\nAktiekapital: 50 000\nVerkst dir: Ing Gösta Eriksson\nEtableringsår: 1876.\n\nHENRIKSSON &amp; CO, AB J A\n\nPnr 901 02\n\nUmeå 1, Sp år v 26 B. Box 83. Tel\n090-13 2470. Tga Henriksoncomp.\nTelex 54038\n\nUmeå Uthamn. Tel 090-409 20\nVerksamhet: Auktoriserade\nskeppsklarerare, auktoriserade speditörer,\nlinjeagenter. Åkeri.\nPresenningsuthyrning. Kol, koks o olja\nAvdelningskontor: Holmsund. Se\nUmeå uthamn\nAntal anstäUda: 30\nAktiekapital: 70 000\nStyrelse: Per Henriksson, T\nAndersson, I Pontusson\nChef: Dir Per Henriksson\nEtableringsår: 1899.\n\nHENRIKSSON\nINGENJÖRSBYRÅ AB, KURT\n\nPnr 112 21\n\nStockholm, Kungsholmstorg 10. Tel\n08-24 64 90. Postgiro 603975\nVerksamhet: Konsulterande inom\nbyggnadsbranschen\nAntal anstäUda: 13\nVerkst din Kurt Henriksson\nEtableringsår: 1959.\n\nHERA ANNONSBYRÅ AB\n\nPnr 11187\n\nStockholm 1, Hovslagarg 2, Box\n1711. Tel 08-23 03 20. Bankgiro\n724-9394. Postgiro 151471-0. Tga\n\nRecolt\n\nVerksamhet: Auktoriserad o\nnominerad annonsbyrå\nAktiekapital: 250000\nVerkst dir: Per Henricson\nEtableringsår: 1943.\n\nHERA NORRLAND\nANNONSBYRÅ AB\n\nPnr 852 30\n\nSundsvaU, Storg 12. Tel\n060-1259 40. Bankgiro 401-8073.\nPostgiro 299885-4\nVerksamhet: Reklambyrå\nAktiekapital: 60 000\nVerkst dir: Anders Lindström\nEtableringsår: 1969.\n\nSVECIA TRÄINDUSTRI, AB\n\nPnr 330 23\n\nSmålandsstenar, Dalsg 19. Box 47.\nTel 0371-31010. Bankgiro\n427-6317. Postgiro 281009-1\nVerksamhet: Tillverkar sängar o\nbarn-toil ettstolar\nAntal anställda: 45\nÅrsomsättning: 3 800 000\nAktiekapital: 100 000\nVeikst dir: Harry Lundén\nEtableringsår: 1944.\n\nINDRA FOOD, AB\n\nPnr 252 28\n\nHelsingborg, Zenitg 1. Tel\n042-180410. Bankgiro 761-6576.\nPostgiro 438130-7. Tga Indra.\nTelex 7249 ZEN1TH S\nVeiksamhet: Tillverkar o säljer\nfärdiglagad djupfryst mat,\ncharku-terivaror samt kött o fläsk\nAntal anställda: 520\nÅrsomsättning: 110000000\nVeikst dir: Börje Lindgren\nEtableringsår: 1967\nDotterbolag till AB Aritmos.\n\nINDUKTIONSVÄRME, AB\n\nPnr 12154\n\nJohanneshov, Söderarmsv 11. Tel\n08-599827,599828. Bankgiro\n47-8629. Postgiro 458385-2\nVerksamhet: Utför\ninduktionshärd-ning o induktions lödning\nAntal anstäUda: 7\nÅrsomsättning: 500 000\nAktiekapital: 15 000\nVerkst dir: Bengt Kullman\nEtableringsår: 1952.\n\nHUS\n\nChef kamerala avdelningen:\nKamrer Stig Håkansson\nEtableringsår: 1912\nOmbildat till aktiebolag 1923.\n\nHUSQVARNA BORSTFABRIK,\nAB\n\nPnr 56101\n\nHuskvarna 1, Pack. Tel036-132600.\nBankgiro 544-5515. Postgiro\n5419-7. Tga Borstfabriken.\nTelex 70006 HUSBOR S\nVerksamhet: Tillverkning av\nborstar o plastartiklar inom\nvaruområdena personvård, hem, hushåll,\nbilvård o fritid samt tillverkning\nav roterande borstar o maskiner\nför ytbehandling o plastartiklar för\nindustri o materialhantering\nFörsäljningskontor: Stockholm,\nKungsg 3. Tel 08-14 07 80\nGöteborg, Chalmersg 11. Tel\n031-13 30 38\n\nMalmö, S Tullg 4 A. Tel\n040-97 55 35\n\nVarunamn: Kontur, Kungs,\nSignatur, Siluett m fi\nAntal anställda: 330\nÅrsomsättning: 30000000\nAktiekapital: 4 500 000\nStyrelse: Disp Franz Hartmann\n(ordf), dir Sigurd Ljungcrantz,\nbruks-disp Bo Risberg, dir Gunnar Olsson\nVerkst dir: Gunnar Olsson\nEkonomiavdelning:\nEkonomichef: Olle Odenströmer\nInköpschef: Bertil Dahlberg\nPersonalchef: Gunnar Jonsson\nSektor plast:\n\nOvering: Sven Samuelsson\nMarknadschef: Sven Johnsson\nFörsäljn-chef: Göran Freed\nProd-ing: Birger Bentsen\nInköpschef: Sune Rapp\nSektor ytbehandling:\nOvering: Hans Drabe\nFörsäljn-chef: Ulf Nordmalm\nInköpschef: Carl-Erik Gustafsson\nAnläggningsavdelning:\nIng: Ingemar Holmqvist\nEtableringsån 1896\nOmbildat till aktiebolag 1911.\n\nHUSKVARNA\nBYGGMATERIAL, AB\n\nPnr 56100\n\nHuskvarna, Järnvägsg 18. Tel\n036-13 26 10. Bankgiro 544-5135.\nPostgiro 367470-2\n\nVerksamhet: Säljer allt i\nbyggnadsbranschen\nAktiekapital: 80 000\nVerkst dir: Köpman P L Rydell\nEtableringsår 1948.\n\nHUSKVARNA\nCEMENT-GJUTERI AB\n\nPnr 56100\n\nHuskvarna, Rosendalag 4. Tel\n036-13 27 70\n\nVerksamhet: Tillverkar betongrör\nav alla slag, trädgårdsplattor m m.\nMedlem av kontrollrådet för\nbetongrör\n\nAktiekapital: 25 000\nFirmatecknare: C G Petersson\nHelägt dotterbolag: Segafabriken i\nTenhult AB.\n\nHUSKVARNA STÅLPRESS AB\n\nse Mustad AB, J.\n\nHUSQVARNA\nVAPEN-FABRIKS AB\n\nPnr 56101\n\nHuskvarna 1, Fack. Tel 036-13 25 00.\nPostgiro 8474-9. Tga\nVapenfabriken. Telex 70048\nVerksamhet: Gjuteri o mek\nverkstad. Tillverkar symaskiner,\nelspisar, electronicugnar, kaminer,\nvärmepannor, gräsklippare, tvätt- o\ndiskmaskiner, hushållsartiklar,\nkyl-o frysskåp, motorcyklar, motorsågar,\nmotordetaljer\n\nFörsäljningskontor: Göteborg C,\nKungsportsavenyen 3. Tel\n031-170580\n\nJönköping, S Strandg 7. Tel\n036-1194 90\n\nMalmö C, Söderg 13. Tel\n040-703 80\n\nStockholm C, Brunnsg 6-8. Tel\n08-22 32 20\n\nSundsvall, Packhusg 6. Tel\n060-155940\n\nNorrköping, Drottningg 38. Tel\n011-13 40 95\n\nKarlstad, Drottningg 18. Tel 054-\n\n1502 25\n\nGävle, N Skeppsbron 1. Tel\n026-12 95 90\n\nSkellefteå, S Järnvägsg 50. Tel\n0910-17150\nAntal anställda: 4 600\nÅrsomsättning: 440 000 000\n.Aktiekapital: 40 000 000\nStyrelse: Adv Sten S:son\nAnkarcrona (ordf), dir Bo Ehrner, dir\nGunnar Ericsson, dir Nils\nHolgersson, dir Gösta Lewenhaupt, dir\nJohan Nordenfalk, dir Gösta\nRehn-qvist\n\nVerkst dir: Gösta Rehnqvist\nFörsäljn-dir Evald Liljegren\nTekn dir: Gunnar Brynge\nEkonomidir: Stig Guida\nInköpschef: Evert Seiving\nEtableringsår: 1689\nOmbildat till aktiebolag 1867.\nÄger Norrahammars Bruk,\nNorrahammar, AB Ero-Frys, Arvika, AB\nHöörs Plåt, Höör, Tandsbyns Mek\nVerkstad, Tandsbyn.\n\nHUSTEKNIK, AB\n\nPnr 11136\n\nStockholm, Drottningg 71 D. Tel\n08-2178 93,217944. Postgiro\n602954-0\n\nVerksamhet: Konsulterande\ningenjörsbyrå\nAntal anställda: 10\nAktiekapital: 30 000\nVerkst dir: Ing Arne Larsson\nEtableringsår: 1953.\n\nCOSTER &amp; CO, AB FREDRIK\n\nPnr 411 15\n\nGöteborg, Kyrkog 4. Tel\n031-17 59 60. Bankgiro 50-0739.\nPostgiro 44897. Tga Costerco.\nTelex 20056 COSTERS S\nVerksamhet: Export av sågade o\nhyvlade trävaror\n\nAntal anställda: 5\nÅrsomsättning: 15 000 000\nAktiekapital: 50 000\nStyrelse: Dir O Sörmon (ordf),\nfru Elsie Sörmon\nVerkst dir: Oskar Sörmon\nEtableringsår: 1868.\n\nRYDELL &amp; ENGDAHL AB\n\nPnr 234 00\n\nLomma, Klockarev 8. Box 98. Tel\n040-4135 85, 463949. Bankgiro\n134-5008. Postgiro 430375-6\nVerksamhet: Industriplast,\nplast-beläggningar, reparationer,\nplastentreprenader, plastråvaror\nAntal anstäUda: 17\nÅrsomsättning: 1500 000\nAktiekapital: 90 000\nChefer: Ing Egon Rydell, ing Karl\nEngdahl\n\nEtableringsår: 1965.",
    "structured": {
        "0": {
            "company_name": "LDV",
            "activity": "Säljer båtmotorer, båtar o tillbehör",
            "establishment_year": 1930
        },
        "1": {
            "company_name": "LüWGRENS ELEKTRO-DIESEL AB, N",
            "pnr": "70102",
            "address": "Örebro 1, Box 11. Fredsg 3",
            "phone_number": "019-119815",
            "bank_details": {
                "bankgiro": "642-1275",
                "postgiro": "716100-3"
            },
            "activity": "Utför bilelektr reparationer o dieselreparationer. Säljer bilelektr artiklar i detalj o engros",
            "employees": 15,
            "annual_turnover": 1700000,
            "capital": 10000,
            "key_personnel": [
                {
                    "name": "Dir Lars-Erik Bergstrand",
                    "position": "dir"
                },
                {
                    "name": "dir Nils Löwgren",
                    "position": "dir"
                },
                {
                    "name": "Nils Löwgren",
                    "position": "Verkst dir"
                },
                {
                    "name": "Lars Wren",
                    "position": "Verkmäst"
                },
                {
                    "name": "Kenneth Englund",
                    "position": "Lagerchef"
                },
                {
                    "name": "Lise-Lotte Molin",
                    "position": "Kamrer"
                },
                {
                    "name": "Gösta Stridh",
                    "position": "Försäljare"
                }
            ],
            "establishment_year": 1968
        },
        "2": {
            "company_name": "LDFKVIST AB, BYGGNADS. FIRMA ARNE",
            "pnr": "38100",
            "address": "Kalmar, Unionsg 21",
            "phone_number": "0480-109 00",
            "postgiro": "163626-5",
            "activity": "Utför husbyggnadsarbeten, tekn utredningar, byggnadskontroll o värderingar",
            "employees": 30,
            "capital": 20000,
            "key_personnel": {
                "name": "Arne Löfkvist",
                "position": "Verkst dir"
            },
            "establishment_year": 1952
        },
        "3": {
            "company_name": "LüFQUISTS ELEKTRISKA AB, HJALMAR",
            "pnr": "103 81",
            "address": "Stockholm 7, Birger Jarlsg 23. Box 7022",
            "phone_number": "08-23 20 00",
            "bank_details": {
                "bankgiro": "238-6795",
                "postgiro": "4750-6"
            },
            "activity": "Utför elektr installationer för ljus, kraft, värme o tele-signal. Säljer belysningsarmatur, elektr hushållsapparater o kylskåp",
            "employees": 90,
            "annual_turnover": 6000000,
            "capital": 170000,
            "key_personnel": [
                {
                    "name": "Adv Rolf Jörgensen",
                    "position": "ordf"
                },
                {
                    "name": "bankdir Alf Ericsson",
                    "position": "dir"
                },
                {
                    "name": "dir Jan-Ake Hedin",
                    "position": "dir"
                },
                {
                    "name": "Jan-Ake Hedin",
                    "position": "Verkst dir"
                }
            ],
            "establishment_year": 1891
        },
        "4": {
            "company_name": "LOKERYDS TRÄINDUSTRI",
            "pnr": "56013",
            "address": "Hok",
            "phone_number": "0393-200 07",
            "bankgiro": "146-4213",
            "postgiro": "642001-2",
            "activity": "Tillverkar o säljer lastpallar o pallramar",
            "employees": 8,
            "annual_turnover": 900000,
            "key_personnel": [
                {
                    "name": "Fabr Janne Nordqvist",
                    "position": "Chef"
                },
                {
                    "name": "Jan-Ake Nordquist",
                    "position": "Verkmäst"
                }
            ],
            "establishment_year": 1963
        },
        "5": {
            "company_name": "TENSON.PRODUKTER AB",
            "pnr": "432 00",
            "address": "Varberg, Lassabacka",
            "phone_number": "0340-164 70",
            "bankgiro": "106-3940",
            "postgiro": "23154-8",
            "activity": "Tillverkar 'Tenson' bad-, skid- o sportartiklar",
            "employees": 100,
            "annual_turnover": 10000000,
            "capital": 250000,
            "key_personnel": {
                "name": "Paul Rydholm",
                "position": "Verkst dir"
            },
            "establishment_year": 1951
        },
        "6": {
            "company_name": "AK OPTIK INSTRUMENT AB",
            "pnr": "104 60",
            "address": "Stockholm 20, Fack. Huddingev 103 B, Johanneshov",
            "phone_number": "08-39 0100",
            "bankgiro": "16-0644",
            "postgiro": "56967",
            "activity": "Importerar o säljer optiska, vetenskapliga m fi instrument. Generalagent för VEB Carl Zeiss JENA",
            "capital": 65000,
            "key_personnel": {
                "name": "Stig Lundmark",
                "position": "Verkst dir"
            },
            "establishment_year": 1949
        }
    }
}