{
    "original": "ÅKERSON &amp; CO AB\n\nPnr 803 52\n\nGävle, N Rådmansg 8 B. Tel\n026-12 00 15, 12 1115. Bankgiro\n237-1375. Postgiro 71002-0. Tga Aker-\n\nsons\n\nVerksamhet: Säljer fossila bränslen\nAntal anställda: 7\nAktiekapital: 200000\nChef: S Eklund\nEtableringsår: 1762.\n\nÅKERSTRÖMS ELEKTRISKA\nAB\n\nPnr 79101\n\nFalun 1, Trotzg 109. Box 2. Tel\n023-104 08. 104 58. Bankgiro\n464-2088. Postgiro 11081-7. Tga\nElmotor\n\nVerksamhet: Tillverkar o säljer\nenfas o 3-fas motorer\nAntal anställda: 45\nAktiekapital: 100 000\nVerkst din Sigge Andersson\nEtableringsån 1923.\n\nSVEAFODER, AB\n\nPnr 700 02\n\nÖrebro 2, Box 2022. Grev Roseng 1.\nTel 019-12 45 25. Bankgiro\n855-6201. Postgiro 26464-8\nChef: Disp Torsten Persson\nVerksamhet: Hönsfoder,\nkalkonfoder, svinfoder o nötfoder i parti.\nVärpbursystem o redskap\nAntal anställda: 33\nÅrsomsättning: 11000 000\nAktiekapital: 200 000\nVerkst dir: H Melin\nEtableringsår: 1928.\n\nGLASSERVICE, AB\n\nPnr 21214\n\nMalmö, Industrig 12. Tel\n040-347 53. Postgiro 435676-2\nVerksamhet: Glasmästeri\nAktiekapital: 5 000\nVerkst dir: Uno Borgstrand\nEtableringsår: 1953.\n\nGLEERUP BOKFORLAG,\nAB C W K\n\nPnr 22105\n\nLund 1, Oesundsv 1. Box 1205.\n\nTel 046-1175 00. Bankgiro\n660-6487. Postgiro 30843-7. Tga\nGleerups\n\nVerksamhet: Bokförlag, bokbinderi\no pappershandel\nAntal anstäUda: 90\nAktiekapital: 800 000\nVerkst dir: Walter Ekstrand\nEtableringsår: 1826.\n\nGLEMBRING AB,\nINGENJURSFIRMAN\n\nPnr 41123\n\nGöteborg, Sprängkullsg 10 B. Tel\n031-1162 63, 11 78 69. Bankgiro\n337-2430. Postgiro 49261-1. Tga\nMaskinglembring\n\nVerksamhet: Fyllnings- o\nförpackningsmaskiner, automatvågar,\ngängstång, pinn- o specialbult\nAntal anstäUda: 5\nÅrsomsättning: 400 000\nAktiekapital: 30000\nVerkst dir. Ing Allan Glembring\nEtableringsår: 1949.\n\nATEX, TEXTIL AB\n\nPnr 43135 Gbg 14\nMölndal, Agatan. Box 14038, Gbg\n14. Tel 031-2717 00. Bankgiro\n84-8026. Postgiro 12363. Tga Atex\nVerksamhet: Tillverkar\ndamklänningar\n\nAntal anställda: 30\nAktiekapital: 45 000\nVerkst dir: Gunnar Kaplan\nEtableringsår: 1940.\n\nFORSBERGS BYGGNADS AB, G\n\nPnr 702 17\n\nÖrebro, Gärdesg 7. Tel\n019-11 17 37. 1282 09. Bankgiro\n815-5533. Postgiro 113142-4\nVerksamhet: Uppför\nindustribyggnader. Utför ombyggnadsarbeten\nAntal anstäUda: 50\nÅrsomsättning: 4 000000\nAktiekapital: 50 000\nVerkst dir: Gustaf Forsberg\nEtableringsår: 1946.\n\nFORSBERGS INDUSTRI AB,\nIVAR\n\nPnr 830 40\n\nKrokom. Tel 0640-104 30. Bankgiro\n779-8077. Postgiro 337258-8\nVerksamhet Tillverkar ytter- o\ninnerdörrar med massiv trästomme.\nGlasmästeri för bil- o\nbyggnadsglas\n\nFilial: 83100 Östersund,\nOden-skogsv 35. Tel 063-233 50\nAntal anställda: 40\nÅrsomsättning: 4 500 000\nAktiekapital: 400 000\nVerkst dir: Ivar Forsberg\nEtableringsår: 1946.\n\nFORSBERG &amp; CO KB,\nBYGGNADSFIRMAN OLAUS\n\nPnr 902 45\n\nUmeå, Kungsg 43. Tel 090-12 22 60.\nBankgiro 759-8303. Postgiro\n63850-2\n\nVerksamhet: Uppför bostadshus o\nindustribyggnader\nAntal anstäUda: 450\nÅrsomsättning: 45 000 000\nChef: Byggmäst Olaus Forsberg\nEtableringsår: 1937.\n\nINDUSTRI.TRYCKERIET AB\n\nPnr 703 54\n\nÖrebro, Malmg 5. Tel 019-1175 08.\nBankgiro 61-4413. Postgiro 98163\nVerksamhet: Boktryckeri med\nfler-färgsarbeten som specialitet\nAntal anställda: 7\nÅrsomsättning: 700 000\nAktiekapital: 10 000\nVerkst dir: Rolf Wong\nEtableringsår: 1935.\n\nflinck, ingenjörsfirma t\n\nPnr 402 71\n\nGöteborg 8, Box 8812. Godsadress:\nOstergärde Industriområde. Tel\n031-925478. Postgiro 424177. Tga\nFlotteservice\n\nVerksamhet: Säljer\nindustristav-lampor\n\nVarunamn: Bright Star\n\nÄgare o chef: Ing Thorbjörn Flinck\n\nEtableringsår: 1952.\n\nflinckman konsultbyrå\nab\n\nPnr 100 64\n\nStockholm 38, Tideliusg 61. Fack.\nTel 08-84 02 50. Bankgiro 56-9805.\nPostgiro 402848. Tga\nFlinckman-konsult\n\nVerksamhet: Reklambyrå\nAntal anställda: 10\nÅrsomsättning: 1500 000\nAktiekapital: 25 000\nVerkst dir: Ulf B Flinckman\nEtableringsår: 1965.\n\nfloby gjuteri ab\n\nPnr 52040\n\nFloby. Tel 0515-40225. Postgiro\n361 398-0\n\nVerksamhet: Tillverkar gjutgods\nför båtar samt maskingjutgods\nAntal anställda: 10\nAktiekapital: 58 000\nVerkst dir: K E Lilja\nEtableringsår: 1947.\n\nESSELS AGENTURER, AB\n\nPnr 50243\n\nBorås, Björkängsg 21. Tel\n033-11 18 85, 11 10 33. Postgiro 263556\nVerksamhet: Specialitet modetrikå\no nylonunderkläder\nAntal anställda: 4\nÅrsomsättning: 3 500 000\nAktiekapital: 25 000\nVerkst dir: Sture Larsson\nEtableringsår: 1949.\n\nBROKINDS SNICKERI AB\n\nPnr 590 41\n\nRimforsa. Tel 013-412 10.\nBankgiro 120-1375. Postgiro 1462-2\nVerksamhet: Tillverkar o säljer\nspecialinredningar till byggnader\nför offentlig miljö\nAntal anställda: 30\nÅrsomsättning: 2 000 000\nAktiekapital: 80 000\nStyrelse: Fabr Ake Östergren\n(ordf), fabr Sigvard Johansson,\nfabr Ingemar Levin\nVerkst din Ingemar Levin\nKamrer: Inga Strömberg\nEtableringsår: 1941.\n\nMEVABO AB\n\nPnr 330 10\n\nBredaryd. Tel 0370-803 50.\nBankgiro 54-2560. Postgiro 126976\nVerksamhet: Tillverkar snäck- o\nkuggväxlar\nAntal anställda: 50\nÅrsomsättning: 3 000 000\nAktiekapital: 150 000\nVeikst dir: Bengt Benzler\nEtableringsår: 1955.",
    "structured": {
        "1": {
            "company_name": "ÅkerSon & Co AB",
            "pnr": "803 52",
            "address": "Gävle, N Rådmansg 8 B",
            "phone_number": "026-12 00 15, 12 1115",
            "bank_details": {
                "bankgiro": "237-1375",
                "postgiro": "71002-0"
            },
            "activity": "Säljer fossila bränslen",
            "employees": 7,
            "capital": 200000,
            "key_personnel": [
                {
                    "name": "S Eklund",
                    "position": "Chef"
                }
            ],
            "establishment_year": 1762
        },
        "2": {
            "company_name": "ÅkerStröms Elektriska AB",
            "pnr": "79101",
            "address": "Falun 1, Trotzg 109, Box 2",
            "phone_number": "023-104 08, 104 58",
            "bank_details": {
                "bankgiro": "464-2088",
                "postgiro": "11081-7"
            },
            "activity": "Tillverkar o säljer enfas o 3-fas motorer",
            "employees": 45,
            "capital": 100000,
            "key_personnel": [
                {
                    "name": "Verkst din Sigge Andersson",
                    "position": "Verkställande direktör"
                }
            ],
            "establishment_year": 1923
        },
        "3": {
            "company_name": "SveaFoder AB",
            "pnr": "700 02",
            "address": "Örebro 2, Box 2022, Grev Roseng 1",
            "phone_number": "019-12 45 25",
            "bank_details": {
                "bankgiro": "855-6201",
                "postgiro": "26464-8"
            },
            "activity": "Hönsfoder, kalkonfoder, svinfoder o nötfoder i parti. Värpbursystem o redskap",
            "employees": 33,
            "annual_turnover": 11000000,
            "capital": 200000,
            "key_personnel": [
                {
                    "name": "Disp Torsten Persson",
                    "position": "Chef"
                },
                {
                    "name": "H Melin",
                    "position": "Verkställande direktör"
                }
            ],
            "establishment_year": 1928
        },
        "4": {
            "company_name": "Glasservice AB",
            "pnr": "21214",
            "address": "Malmö, Industrig 12",
            "phone_number": "040-347 53",
            "postgiro": "435676-2",
            "activity": "Glasmästeri",
            "capital": 5000,
            "key_personnel": [
                {
                    "name": "Uno Borgstrand",
                    "position": "Verkställande direktör"
                }
            ],
            "establishment_year": 1953
        },
        "5": {
            "company_name": "Gleerup Bokförlag AB C W K",
            "pnr": "22105",
            "address": "Lund 1, Oesundsv 1, Box 1205",
            "phone_number": "046-1175 00",
            "bank_details": {
                "bankgiro": "660-6487",
                "postgiro": "30843-7"
            },
            "activity": "Bokförlag, bokbinderi o pappershandel",
            "employees": 90,
            "capital": 800000,
            "key_personnel": [
                {
                    "name": "Walter Ekstrand",
                    "position": "Verkställande direktör"
                }
            ],
            "establishment_year": 1826
        },
        "6": {
            "company_name": "Glembring AB, Ingenjursfirman",
            "pnr": "41123",
            "address": "Göteborg, Sprängkullsg 10 B",
            "phone_number": "031-1162 63, 11 78 69",
            "bank_details": {
                "bankgiro": "337-2430",
                "postgiro": "49261-1"
            },
            "activity": "Fyllnings- o förpackningsmaskiner, automatvågar, gängstång, pinn- o specialbult",
            "employees": 5,
            "annual_turnover": 400000,
            "capital": 30000,
            "key_personnel": [
                {
                    "name": "Ing Allan Glembring",
                    "position": "Verkställande direktör"
                }
            ],
            "establishment_year": 1949
        },
        "7": {
            "company_name": "Atex, Textil AB",
            "pnr": "43135 Gbg 14",
            "address": "Mölndal, Agatan, Box 14038, Gbg 14",
            "phone_number": "031-2717 00",
            "bankgiro": "84-8026",
            "postgiro": "12363",
            "activity": "Tillverkar damklänningar",
            "employees": 30,
            "capital": 45000,
            "key_personnel": [
                {
                    "name": "Gunnar Kaplan",
                    "position": "Verkställande direktör"
                }
            ],
            "establishment_year": 1940
        },
        "8": {
            "company_name": "Forsbergs Byggnads AB, G",
            "pnr": "702 17",
            "address": "Örebro, Gärdesg 7",
            "phone_number": "019-11 17 37, 1282 09",
            "bank_details": {
                "bankgiro": "815-5533",
                "postgiro": "113142-4"
            },
            "activity": "Uppför industribyggnader. Utför ombyggnadsarbeten",
            "employees": 50,
            "annual_turnover": 4000000,
            "capital": 50000,
            "key_personnel": [
                {
                    "name": "Gustaf Forsberg",
                    "position": "Verkställande direktör"
                }
            ],
            "establishment_year": 1946
        },
        "9": {
            "company_name": "Forsbergs Industri AB, Ivar",
            "pnr": "830 40",
            "phone_number": "0640-104 30",
            "bankgiro": "779-8077",
            "postgiro": "337258-8",
            "activity": "Tillverkar ytter- o innerdörrar med massiv trästomme. Glasmästeri för bil- o byggnadsglas",
            "employees": 40,
            "annual_turnover": 4500000,
            "capital": 400000,
            "key_personnel": [
                {
                    "name": "Ivar Forsberg",
                    "position": "Verkställande direktör"
                }
            ],
            "establishment_year": 1946
        },
        "10": {
            "company_name": "Forsberg & Co KB, Byggnadsfirman Olaus",
            "pnr": "902 45",
            "address": "Umeå, Kungsg 43",
            "phone_number": "090-12 22 60",
            "bankgiro": "759-8303",
            "postgiro": "63850-2",
            "activity": "Uppför bostadshus o industribyggnader",
            "employees": 450,
            "annual_turnover": 45000000,
            "key_personnel": [
                {
                    "name": "Byggmäst Olaus Forsberg",
                    "position": "Chef"
                }
            ],
            "establishment_year": 1937
        },
        "11": {
            "company_name": "Industri.Tryckeriet AB",
            "pnr": "703 54",
            "address": "Örebro, Malmg 5",
            "phone_number": "019-1175 08",
            "bankgiro": "61-4413",
            "postgiro": "98163",
            "activity": "Boktryckeri med fler-färgsarbeten som specialitet",
            "employees": 7,
            "annual_turnover": 700000,
            "capital": 10000,
            "key_personnel": [
                {
                    "name": "Rolf Wong",
                    "position": "Verkställande direktör"
                }
            ],
            "establishment_year": 1935
        },
        "12": {
            "company_name": "Flinck, Ingenjörsfirma T",
            "pnr": "402 71",
            "address": "Göteborg 8, Box 8812, Ostergärde Industriområde",
            "phone_number": "031-925478",
            "postgiro": "424177",
            "activity": "Säljer industristav-lampor",
            "owner": "Ing Thorbjörn Flinck",
            "establishment_year": 1952
        },
        "13": {
            "company_name": "Flinckman Konsultbyrå AB",
            "pnr": "100 64",
            "address": "Stockholm 38, Tideliusg 61",
            "phone_number": "08-84 02 50",
            "bankgiro": "56-9805",
            "postgiro": "402848",
            "activity": "Reklambyrå",
            "employees": 10,
            "annual_turnover": 1500000,
            "capital": 25000,
            "key_personnel": [
                {
                    "name": "Ulf B Flinckman",
                    "position": "Verkställande direktör"
                }
            ],
            "establishment_year": 1965
        },
        "14": {
            "company_name": "Floby Gjuteri AB",
            "pnr": "52040",
            "address": "Floby",
            "phone_number": "0515-40225",
            "postgiro": "361 398-0",
            "activity": "Tillverkar gjutgods för båtar samt maskingjutgods",
            "employees": 10,
            "capital": 58000,
            "key_personnel": [
                {
                    "name": "K E Lilja",
                    "position": "Verkställande direktör"
                }
            ],
            "establishment_year": 1947
        },
        "15": {
            "company_name": "Essels Agenturer AB",
            "pnr": "50243",
            "address": "Borås, Björkängsg 21",
            "phone_number": "033-11 18 85, 11 10 33",
            "postgiro": "263556",
            "activity": "Specialitet modetrikå o nylonunderkläder",
            "employees": 4,
            "annual_turnover": 3500000,
            "capital": 25000,
            "key_personnel": [
                {
                    "name": "Sture Larsson",
                    "position": "Verkställande direktör"
                }
            ],
            "establishment_year": 1949
        },
        "16": {
            "company_name": "Brokinds Snickeri AB",
            "pnr": "590 41",
            "address": "Rimforsa",
            "phone_number": "013-412 10",
            "bankgiro": "120-1375",
            "postgiro": "1462-2",
            "activity": "Tillverkar o säljer specialinredningar till byggnader för offentlig miljö",
            "employees": 30,
            "annual_turnover": 2000000,
            "capital": 80000,
            "elders": {
                "chairman": "Fabr Ake Östergren",
                "vice_chairman": "Fabr Sigvard Johansson",
                "fabr_ingemar_levin": "Fabr Ingemar Levin",
                "cashier": "Inga Strömberg"
            },
            "establishment_year": 1941
        },
        "17": {
            "company_name": "Mevabo AB",
            "pnr": "330 10",
            "address": "Bredaryd",
            "phone_number": "0370-803 50",
            "bankgiro": "54-2560",
            "postgiro": "126976",
            "activity": "Tillverkar snäck- o kuggväxlar",
            "employees": 50,
            "annual_turnover": 3000000,
            "capital": 150000,
            "key_personnel": [
                {
                    "name": "Bengt Benzler",
                    "position": "Verkställande direktör"
                }
            ],
            "establishment_year": 1955
        }
    }
}