{
    "original": "PROLS FABRIK, AB\n\nPnr 124 21\n\nBandhagen 1, Harpsundsv 158-160.\nBox 1. Tel 08-86 02 40\nVerksamhet: Tillverkar\nrengöringsmedel, bonvax o polish\nVarunamn: Prol, Tindra\nAntal anställda: 16\nÅrsomsättning: 2 800 000\nAktiekapital: 100 000\nÄgare o chef: Disp Hans Edvard\nLagerstam\nEtableringsår: 1909.\n\nNC\n\nN\n\nNACKA BIL AB\n\nPnr 131 01\n\nNacka 1, Värmdöv 260. Box 26.\nTel 08-716 28 20. Postgiro 444669\nVerksamhet: Bilförsäljning,\nbilreparationer o bensinstationer\nAntal anställda: 70\nÅrsomsättning: 25 000 000\nAktiekapital: 200 000\nVerkst dir: Fredrik Eneqvist\nEtableringsår: 1954.\n\nFRANZÉN AB, HANNS -OTTO\n\nPnr 114 60\n\nStockholm. Styrmansg 50. Tel\n08-62 95 96, 60 72 64. Bankgiro 47-7613,\nPostgiro 190677. Tga Hanns-Otto\nVerksamhet: Säljer\nlivsmedelsmaskiner. Specialitet: Scotsman\nismaskiner\n\nVarunamn: Alexanderwerk,\nScotsman\n\nÄgare o chef: Hanns-Otto Franzén\nEtableringsår: 1942.\n\nFRANZÉN,\nINGENJÖRS-FIRMAN KAJ\n\nPnr 400 30\n\nGöteborg 11, Nordostpassagen 33.\nBox 11068. Tel 031-42 45 25,\n42 45 26. Telex 20825. Tga\nKaj-franz\n\nVerksamhet: Säljer maskiner o\noljeadditiv, båtar\nAntal anställda: 4\nÅrsomsättning: 8 000 000\nChef: Civiling Kaj Franzén\nEtableringsår: 1953.\n\nNORMAN, ARNE\n\nPnr 79020\n\nGrycksbo. Tel 023-407 90. Bankgiro\n464-4167. Postgiro 79355-4\nVerksamhet: Bandväveri. Tillverkar\ns k svenskremmar\nVarunamn: Arnö\nChef: Arne Norman\nEtableringsår: 1963.\n\nAXELSON, CARL J R\n\nPnr 115 33\n\nStockholm, Hedinsg 3. Tel\n08-62 97 89. Postgiro 191643-6. Tga\nCarlaxtrade\n\nVerksamhet: Agenturer för\nmarkis-väv, kapellduk, presenningsduk\nÄgare o chef: Carl Axelson\nEtableringsår: 1948.\n\nATLET AB\n\nPnr 430 50\n\nKållered. Tel 031-75 04 90.\nBankgiro 501-0657. Postgiro 422723-7.\nTga Atlettruck.\nTelex 2452 ATLET S\nVerksamhet: Tillverkar o säljer\neltruckar för intern\nmaterialhantering\n\nVarunamn: Atlet\nAntal anställda: 80\nÅrsomsättning: 13 000 000\nAktiekapital: 300 000\nVerkst dir: K Jacobsson\nEtableringsår: 1952\nOmbildat till aktiebolag 1962.\n\nATLINGS MASKINFABRIK AB\n\nPnr 816 00\n\nOckelbo, Kråkstigen 3, Tel\n0297-404 50, 404 51. Bankgiro 237-9121.\nPostgiro 280046-4. Tga\nAtling-maskin\n\nVerksamhet: Tillverkar o säljer\nstationära nitningsmaskiner,\nexpanderande hylsdornar,\ngängtappschuc-kar, stålfästeskruv, spånkrokar,\nlegoarbeten\n\nVarunamn: Atlings, Nita, Kultopp,\nDosking\n\nAntal anställda: 40\nÅrsomsättning: 2 000 000\nAktiekapital: 30 000\nVerkst dir: Gunnar Atling\nEtableringsår: 1946.\n\nTEKNO.EFFEKT, AB\n\nPnr 11653\n\nStockholm, Rosenlundsg 50-52.\nTel 08-84 04 40, verkstad 84 82 0 6.\nBankgiro 160-1764. Postgiro\n195177-1\n\nVerksamhet: Alla slags mekaniska\no finmekaniska arbeten.\nSpecialitet: styck- o serietillverkning av\nspecialmaskiner, apparater o\nfix-turer samt jiggborrning o noggranna\nplåtarbeten\n\nAntal anställda: 40\nÅrsomsättning: 2 400 000\nAktiekapital: 25 000\nVerkst dir: Dr-ing Felix Nieburg\nEtableringsår: 1943.\n\nSVARTHÅLSFORSEN, AB\n\nPnr 104 32\n\nStockholm 19, Tuleg 13. Fack. Tel\n23 65 40, riks 08-23 56 40\nVerksamhet: Kraftverksrörelse\nAntal anställda: 49\nÅrsomsättning: 36 600 000\nAktiekapital: 40 000 000\nVerkst dir: Jan-Erik Ryman\nEtableringsår: 1919\nÄger Järpströmmens Kraftverk,\nJärpen samt Svarthålsforsens\nKraftverk, Bispgården.\nAnläggningar i Stockholm.\n\nSVARVERI &amp; LEKSAKS.\nFABRIKEN\n\nPnr 574 00\n\nVetlanda, Brogårdsg. Tel 0383-\n\n109 64, 108 41. Bankgiro 144-9446.\n\nPostgiro 292418-1\n\nVerksamhet: Tillverkar mindre\n\nsnickerier o schatuller. Utför ko-\n\npiers värvning\n\nAntal anställda: 7\n\nÄgare o chef: Nils Henriksson\n\nEtableringsår: 1946.\n\nSPORT &amp; RESEFFEKTER AB\n\nPnr 125 05\n\nÄlvsjö 5, Stamg 23-25. Fack. Tel\n08-91 64 50, 9164 60. Bankgiro\n731-0345. Postgiro 352276-0. Tga\nLe-derc ahlman.\n\nTelex 17249 CAHLMAN S\nVerksamhet: Handväskor o\nlädervaror. Specialitet: krokodilvaror o\nportföljer\nAntal anställda: 8\nÅrsomsättning: 4 500000\nAktiekapital: 40 000\nVerkst dir: Sven-Erie Cahlman\nEtableringsår: 1948.\n\nMOD\n\nMODOKEMI AB\n\nPnr 444 00\n\nStenungsund. Tel 0303-706 20.\nBankgiro 771-8133. Postgiro\n414259-2. Tga Modokemi.\nTelex 21222 MODOKEM S\n114 84 Stockholm, Box 5407. Tel\n08-67 00 40. Tga Modokemi.\nTelex 19920 MODOKEM S\n43121 Mölndal, Pack. Krokslätt.\nTel 031-27 20 00. Tga Modokemi.\nTelex 2336 MODOKEM S\nVerksamhet: Tillverkar o\nmarknadsför tensider, polyoler,\nglyko-ler, lösningsmedel, mjukningsmedel,\npiaster för färg- o lackindustrin,\nomättade polyestrar, vattenlösliga\ncellulosaetrar\nAntal anställda: 1000\nÅrsomsättning: 200 000 000\nVerkst dir: Gunnar Agfors\nÄgare: Mo och Domsjö AB.\n\n[-MODULENT-KONSTRUK-TIONER,-]\n\n{+MODULENT-KONSTRUK-\nTIONER,+} AB\n\nPnr 281 01\n\nHässleholm 1, N Industrig 12.\nFack. Tel 0451-800 45\nVerksamhet: Tillverkar\nmanskapsbodar, servicebyggnader o villor\nAntal anställda: 120\nAktiekapital: 100 000\nVerkst dir: Gerhard Hobohm\nEtableringsàr: 1964.\n\nMODULFONSTER AB\n\nPnr 23101\n\nTrelleborg 1, Industrig. Box 9. Tel\n0410-190 60. Bankgiro 223-4243.\nPostgiro 637050-6\nVerksamhet: Tillverkning o\nförsäljning av pivå- o slagfönster av trä o\naluminium, fasadelement,\nfasadbeklädnader. Målning, glasning,\nmontage\n\nVarunamn: Modulfönster\nAktiekapital: 75 000\nVerkst dir: Civiling Per Wegefelt\nFörsäljningschef: Arne Trelling\nEtableringsàr: 1968.\n\nMOELLER&amp; NEUMANN\n(SKANDINAVISKA) AB\n\nPnr 19402\n\nUpplands Väsby 2, Ingeborgs v 4.\nBox 257. Tel 0760-34 1 22.\nTga Moeneu. Telex 1262\nVerksamhet: Säljer\nvalsverksanläggningar o hydrauliska pressar\nAktiekapital: 65 000\nVerkst dir: H J Schuermann\nEtableringsàr: 1967.\n\nMOFALLA\nBETONG-INDUSTRI, AB\n\nPnr 544 00\n\nHjo, Box 3313. Tel 0503-150 70,\n15120. Bankgiro 216-3921.\nPostgiro 24833-6\n\nVerksamhet: Tillverkar cementrör,\nhålsten o gångplattor\nAntal anstäUda: u\nÅrsomsättning: 662 000\nAktiekapital: 125 000\nVerkst dir: Gunnar Bergman\nEtableringsàr: 1956.\n\nMOHAB.FABRIKERNA AB\n\nPnr 200 12\n\nMalmö 2, Nobelv 129. Box 2075.\nTel 040-93 46 10. Bankgiro\n87-0198. Postgiro 38 299. Telex 32463.\nTga Mohab\n\nVerksamhet: Byggnadstekniska o\nkem tekn produkter\nAktiekapital: 1502 500\nVerkst dir: Håkan Nyman\nEtableringsàr: 1905.\n\nMOHAG, AB\n\nPnr 71100\n\nLindesberg, Kristinav 7. Tel\n0581-10146. Bankgiro 462-0498.\nPostgiro 372660-1. Tga Mosesson\nVerksamhet: Säljer trävaror o\nwallboard\n\nAntal anstäUda: 3\nÅrsomsättning: 1 000 000\nAkUekapital: 10 000\nVerkst dir: Stig Mosesson\nEtableringsàr: 1946.\n\nMOHOGS MEK VERKSTAD, AB\n\nPnr 851 01\n\nSundsvaU 1, Fack. Tel 060-642 00.\nPostgiro 178757. Tga Mohög\nVerksamhet: Mekanisk verkstad med\ngrovplåtslageri. Tillverkar\nstålkonstruktioner för industri- o\naffärsbyggnader, broar o kraftverk.\nOlj e lagringsc ist er ner, g as kloc kor,\ntryckkärl, ångackumulator m m.\nFormatsågar, sorterings- o\nstap-lingsanordningar för board-,\nplywood., spånskiveindustrin etc.\nStrömbildare för isfritt vatten,\nsnösmältning, muddring o\nvattencirkulation\n\nFilial: Härnösand, pa Ramvik.\nGustafsviks Torrdocka.\nDimensioner: Längd 165 m, bredd i\nportöppningen 21 m, djup på\ndocktröskeln 8 m\n\nFartygsnybyggnader o reparationer.\nStålkonstruktioner, strömbildare\nVarunamn: Mohög\nAntal anstäUda: 250\nÅrsomsättning: 21000 000\nAktiekapital: 275 300\nStyrelse: Adv Birger Kjell son\n(ordf), dir Hans Bäuml, adv Gunnar\nAbersten\n\nVerkst dir: Hans Bäuml\nEtableringsàr: 1857\nOmbildat till aktiebolag 1911.\n\nMOKO NORRLÄNDSKA\nMOTORKOMPANIET I LULEÅ\nAB\n\nPnr 95100\n\nLuleå, Robertsviksg 3. Tel\n0920-101 60. Bankgiro 752-4507.\nPostgiro 60176-5\n\nVerksamhet: Bilgummi, batterier,\nbiltillbehör, regummerings- o\nvul-kaniseringsverkstad, batteriverkstad, broms- o framvagnsservice.\nPartiförsäljning av biltillbehör på\nNorrbottens län\nAntal anstäUda: 30\nÅrsomsättning: 4 70 0 000\nAktiekapital: 150 000\nVerkst dir: Levi Bjurström\nEtableringsàr: 1921.\n\nMOLANDER &amp; SON AB\n\nPnr 104 62\n\nStockholm 17, Box 17076.\nBränn-kyrkag 64-74. Tel 08-690100.\nBankgiro 724-5228. Postgiro\n3164-1. Tga Molanderson\nVerksamhet: Fotografiska artiklar\nför amatör- o yrkesbruk\nAntal anställda: 135\nÅrsomsättning: 22 800 000\nAktiekapital: 500 000\nVerkst dir: Olle Molander jr\nEtableringsàr 1921.",
    "structured": {
        "1": {
            "company_name": "PROLS FABRIK, AB",
            "pnr": "124 21",
            "address": "Bandhagen 1, Harpsundsv 158-160. Box 1",
            "phone_number": "08-86 02 40",
            "activity": "Tillverkar rengöringsmedel, bonvax o polish",
            "employees": 16,
            "annual_turnover": 2800000,
            "capital": 100000,
            "key_personnel": [
                {
                    "name": "Disp Hans Edvard Lagerstam",
                    "position": "Ägare o chef"
                }
            ],
            "establishment_year": 1909
        },
        "2": {
            "company_name": "NACKA BIL AB",
            "pnr": "131 01",
            "address": "Nacka 1, Värmdöv 260. Box 26",
            "phone_number": "08-716 28 20",
            "bank_details": {
                "postgiro": "444669"
            },
            "activity": "Bilförsäljning, bilreparationer o bensinstationer",
            "employees": 70,
            "annual_turnover": 25000000,
            "capital": 200000,
            "key_personnel": [
                {
                    "name": "Fredrik Eneqvist",
                    "position": "Verkst dir"
                }
            ],
            "establishment_year": 1954
        },
        "3": {
            "company_name": "FRANZÉN AB, HANNS -OTTO",
            "pnr": "114 60",
            "address": "Stockholm. Styrmansg 50",
            "phone_number": "08-62 95 96",
            "bank_details": {
                "bankgiro": "47-7613",
                "postgiro": "190677"
            },
            "activity": "Säljer livsmedelsmaskiner",
            "key_personnel": [
                {
                    "name": "Hanns-Otto Franzén",
                    "position": "Ägare o chef"
                }
            ],
            "establishment_year": 1942
        },
        "4": {
            "company_name": "FRANZÉN, INGENJÖRS-FIRMAN KAJ",
            "pnr": "400 30",
            "address": "Göteborg 11, Nordostpassagen 33. Box 11068",
            "phone_number": "031-42 45 25, 42 45 26",
            "telex": "20825",
            "activity": "Säljer maskiner o oljeadditiv, båtar",
            "employees": 4,
            "annual_turnover": 8000000,
            "key_personnel": [
                {
                    "name": "Civiling Kaj Franzén",
                    "position": "Chef"
                }
            ],
            "establishment_year": 1953
        },
        "5": {
            "company_name": "NORMAN, ARNE",
            "pnr": "79020",
            "address": "Grycksbo",
            "phone_number": "023-407 90",
            "bank_details": {
                "bankgiro": "464-4167",
                "postgiro": "79355-4"
            },
            "activity": "Bandväveri. Tillverkar s k svenskremmar",
            "key_personnel": [
                {
                    "name": "Arne Norman",
                    "position": "Chef"
                }
            ],
            "establishment_year": 1963
        },
        "6": {
            "company_name": "AXELSON, CARL J R",
            "pnr": "115 33",
            "address": "Stockholm, Hedinsg 3",
            "phone_number": "08-62 97 89",
            "postgiro": "191643-6",
            "activity": "Agenturer för markis-väv, kapellduk, presenningsduk",
            "key_personnel": [
                {
                    "name": "Carl Axelson",
                    "position": "Ägare o chef"
                }
            ],
            "establishment_year": 1948
        },
        "7": {
            "company_name": "ATLET AB",
            "pnr": "430 50",
            "address": "Kållered",
            "phone_number": "031-75 04 90",
            "bank_details": {
                "bankgiro": "501-0657",
                "postgiro": "422723-7"
            },
            "telex": "2452",
            "activity": "Tillverkar o säljer eltruckar för intern materialhantering",
            "employees": 80,
            "annual_turnover": 13000000,
            "capital": 300000,
            "key_personnel": [
                {
                    "name": "K Jacobsson",
                    "position": "Verkst dir"
                }
            ],
            "establishment_year": 1952
        },
        "8": {
            "company_name": "ATLINGS MASKINFABRIK AB",
            "pnr": "816 00",
            "address": "Ockelbo, Kråkstigen 3",
            "phone_number": "0297-404 50, 404 51",
            "bank_details": {
                "bankgiro": "237-9121",
                "postgiro": "280046-4"
            },
            "activity": "Tillverkar o säljer stationära nitningsmaskiner, expanderande hylsdornar",
            "employees": 40,
            "annual_turnover": 2000000,
            "capital": 30000,
            "key_personnel": [
                {
                    "name": "Gunnar Atling",
                    "position": "Verkst dir"
                }
            ],
            "establishment_year": 1946
        },
        "9": {
            "company_name": "TEKNO.EFFEKT, AB",
            "pnr": "11653",
            "address": "Stockholm, Rosenlundsg 50-52",
            "phone_number": "08-84 04 40",
            "bank_details": {
                "bankgiro": "160-1764",
                "postgiro": "195177-1"
            },
            "activity": "Alla slags mekaniska o finmekaniska arbeten",
            "employees": 40,
            "annual_turnover": 2400000,
            "capital": 25000,
            "key_personnel": [
                {
                    "name": "Dr-ing Felix Nieburg",
                    "position": "Verkst dir"
                }
            ],
            "establishment_year": 1943
        },
        "10": {
            "company_name": "SVARTHÅLSFORSEN, AB",
            "pnr": "104 32",
            "address": "Stockholm 19, Tuleg 13",
            "phone_number": "23 65 40, riks 08-23 56 40",
            "activity": "Kraftverksrörelse",
            "employees": 49,
            "annual_turnover": 36600000,
            "capital": 40000000,
            "key_personnel": [
                {
                    "name": "Jan-Erik Ryman",
                    "position": "Verkst dir"
                }
            ],
            "establishment_year": 1919
        },
        "11": {
            "company_name": "SVARVERI & LEKSAKS. FABRIKEN",
            "pnr": "574 00",
            "address": "Vetlanda, Brogårdsg.",
            "phone_number": "0383-109 64, 108 41",
            "bank_details": {
                "bankgiro": "144-9446",
                "postgiro": "292418-1"
            },
            "activity": "Tillverkar mindre snickerier o schatuller",
            "employees": 7,
            "key_personnel": [
                {
                    "name": "Nils Henriksson",
                    "position": "Ägare o chef"
                }
            ],
            "establishment_year": 1946
        },
        "12": {
            "company_name": "SPORT & RESEFFEKTER AB",
            "pnr": "125 05",
            "address": "Älvsjö 5, Stamg 23-25",
            "phone_number": "08-91 64 50, 9164 60",
            "bank_details": {
                "bankgiro": "731-0345",
                "postgiro": "352276-0"
            },
            "telex": "17249",
            "activity": "Handväskor o lädervaror",
            "employees": 8,
            "annual_turnover": 4500000,
            "capital": 40000,
            "key_personnel": [
                {
                    "name": "Sven-Erie Cahlman",
                    "position": "Verkst dir"
                }
            ],
            "establishment_year": 1948
        },
        "13": {
            "company_name": "MODOKEMI AB",
            "pnr": "444 00",
            "address": "Stenungsund",
            "phone_number": "0303-706 20",
            "bank_details": {
                "bankgiro": "771-8133",
                "postgiro": "414259-2"
            },
            "telex": "21222",
            "activity": "Tillverkar o marknadsför tensider, polyoler, glykoler",
            "employees": 1000,
            "annual_turnover": 200000000,
            "key_personnel": [
                {
                    "name": "Gunnar Agfors",
                    "position": "Verkst dir"
                }
            ],
            "establishment_year": null
        },
        "14": {
            "company_name": "MODULENT-KONSTRUKTIONER, AB",
            "pnr": "281 01",
            "address": "Hässleholm 1, N Industrig 12",
            "phone_number": "0451-800 45",
            "activity": "Tillverkar manskapsbodar, servicebyggnader o villor",
            "employees": 120,
            "capital": 100000,
            "key_personnel": [
                {
                    "name": "Gerhard Hobohm",
                    "position": "Verkst dir"
                }
            ],
            "establishment_year": 1964
        },
        "15": {
            "company_name": "MODULFONSTER AB",
            "pnr": "23101",
            "address": "Trelleborg 1, Industrig. Box 9",
            "phone_number": "0410-190 60",
            "bank_details": {
                "bankgiro": "223-4243",
                "postgiro": "637050-6"
            },
            "activity": "Tillverkning o försäljning av pivå- o slagfönster av trä o aluminium",
            "employees": null,
            "capital": 75000,
            "key_personnel": [
                {
                    "name": "Civiling Per Wegefelt",
                    "position": "Verkst dir"
                },
                {
                    "name": "Arne Trelling",
                    "position": "Försäljningschef"
                }
            ],
            "establishment_year": 1968
        },
        "16": {
            "company_name": "MOELLER & NEUMANN (SKANDINAVISKA) AB",
            "pnr": "19402",
            "address": "Upplands Väsby 2, Ingeborgs v 4. Box 257",
            "phone_number": "0760-34 1 22",
            "telex": "1262",
            "activity": "Säljer valsverksanläggningar o hydrauliska pressar",
            "capital": 65000,
            "key_personnel": [
                {
                    "name": "H J Schuermann",
                    "position": "Verkst dir"
                }
            ],
            "establishment_year": 1967
        },
        "17": {
            "company_name": "MOFALLA BETONG-INDUSTRI, AB",
            "pnr": "544 00",
            "address": "Hjo, Box 3313",
            "phone_number": "0503-150 70, 15120",
            "bank_details": {
                "bankgiro": "216-3921",
                "postgiro": "24833-6"
            },
            "activity": "Tillverkar cementrör, hålsten o gångplattor",
            "employees": 0,
            "annual_turnover": 662000,
            "capital": 125000,
            "key_personnel": [
                {
                    "name": "Gunnar Bergman",
                    "position": "Verkst dir"
                }
            ],
            "establishment_year": 1956
        },
        "18": {
            "company_name": "MOHAB.FABRIKERNA AB",
            "pnr": "200 12",
            "address": "Malmö 2, Nobelv 129. Box 2075",
            "phone_number": "040-93 46 10",
            "bank_details": {
                "bankgiro": "87-0198",
                "postgiro": "38 299"
            },
            "telex": "32463",
            "activity": "Byggnadstekniska o kem tekn produkter",
            "capital": 1502500,
            "key_personnel": [
                {
                    "name": "Håkan Nyman",
                    "position": "Verkst dir"
                }
            ],
            "establishment_year": 1905
        },
        "19": {
            "company_name": "MOHAG, AB",
            "pnr": "71100",
            "address": "Lindesberg, Kristinav 7",
            "phone_number": "0581-10146",
            "bank_details": {
                "bankgiro": "462-0498",
                "postgiro": "372660-1"
            },
            "activity": "Säljer trävaror o wallboard",
            "employees": 3,
            "annual_turnover": 1000000,
            "capital": 10000,
            "key_personnel": [
                {
                    "name": "Stig Mosesson",
                    "position": "Verkst dir"
                }
            ],
            "establishment_year": 1946
        },
        "20": {
            "company_name": "MOHOGS MEK VERKSTAD, AB",
            "pnr": "851 01",
            "address": "SundsvaU 1",
            "phone_number": "060-642 00",
            "postgiro": "178757",
            "activity": "Mekanisk verkstad med grovplåtslageri",
            "employees": 250,
            "annual_turnover": 21000000,
            "capital": 275300,
            "key_personnel": [
                {
                    "name": "Hans Bäuml",
                    "position": "Verkst dir"
                }
            ],
            "establishment_year": 1857
        },
        "21": {
            "company_name": "MOKO NORRLÄNDSKA MOTORKOMPANIET I LULEÅ AB",
            "pnr": "95100",
            "address": "Luleå, Robertsviksg 3",
            "phone_number": "0920-101 60",
            "bank_details": {
                "bankgiro": "752-4507",
                "postgiro": "60176-5"
            },
            "activity": "Bilgummi, batterier, biltillbehör",
            "employees": 30,
            "annual_turnover": 4700000,
            "capital": 150000,
            "key_personnel": [
                {
                    "name": "Levi Bjurström",
                    "position": "Verkst dir"
                }
            ],
            "establishment_year": 1921
        },
        "22": {
            "company_name": "MOLANDER & SON AB",
            "pnr": "104 62",
            "address": "Stockholm 17, Box 17076. Bränn-kyrkag 64-74",
            "phone_number": "08-690100",
            "bank_details": {
                "bankgiro": "724-5228",
                "postgiro": "3164-1"
            },
            "activity": "Fotografiska artiklar för amatör- o yrkesbruk",
            "employees": 135,
            "annual_turnover": 22800000,
            "capital": 500000,
            "key_personnel": [
                {
                    "name": "Olle Molander jr",
                    "position": "Verkst dir"
                }
            ],
            "establishment_year": 1921
        }
    }
}