{
    "original": "FRANG AB, VERNER\n\nPnr 501 06\n\nBorås 1, Arlag 7. Box 313. Tel\n033-12 78 00. Bankgiro 531-2996.\nPostgiro 171314-8. Tga Prång.\nTelex 36053 PRÅNG S\nVerksamhet: Importagentur. Garner\nalla slag\n\nEtableringsår: 1954.\n\nAXENTA INDUSTRI AB\n\nPnr 36010\n\nRyd, österg 16. Tel 0459-808 30,\n808 31. Bankgiro 632-7050.\nPostgiro 677533-2\n\nVerksamhet: Tillverkar\nstålinredningar o ventilationer för\nvilla-Antal anställda: 26\nÅrsomsättning: 2 200 000\nAktiekapital: 250 000\nVerkst dir: Stellan Åström\nEtableringsår: 1964.\n\nDEUTGEN &amp; CO AB, F\n\nPnr 11143\n\nStockholm, Norrlandsg 31-33. Tel\n\n08-21 85 05 , 2185 06\n\nVerksamhet: Säljer trafikspeglar o\n\ninstrument för byggkontroll\n\nAktiekapital: 50 000\n\nVerkst dir: Överstelöjtnant Sten D\n\nEkelund\n\nEtableringsår: 1862.\n\nZANBERTSLÄTTMETALL AB\n\nPnr 560 12\n\nVaggeryd. Tel 0393-22051. 22081.\nBankgiro 289-2263. Postgiro\n380920-9\n\nVerksamhet: Tillverkar\nkilremsski-v or enl svensk standard.\nLättme-tallgjutningar i förekommande\nlegeringar. Egen modelltillverkning.\nMaskinbearbetning\nAntal anställda: 30\nÅrsomsättning: 2000 000\nAktiekapital: 100000\nVerkst dir. BAG Bokinge\nEtableringsår 1947.\n\nGETINGE SNICKERIFABRIK\n\nPnr 310 44\n\nGetinge. Tel 035-540 80. Bankgiro\n43-1464. Postgiro 145560\nVerksamhet: Tllverkar all slags\nbyggnadssnickerier\n\nAntal anställda: 7\n\nChef: Pabr Bo Gillberg\nEtableringsår: 1965.\n\nGETTERÄNS SNICKERI.\nFABRIK\n\nPnr 840 13\n\nTorpshammar. Tel 0691-203 89.\nBankgiro 18-2506. Postgiro 390690\nVerksamhet: Tillverkar pivåhängda\nfönster o slagfönster\nAntal anställda: 10\nÅrsomsättning: 400 000\nChef: Stig Skerved\nEtableringsår: 1918.\n\nGEVALIAROSTERIET VICTTH\nENGWALL &amp; CO AB\n\nPnr 170 23\n\nBarkarby, Pack. Tel 08-36 28 90\nVerksamhet: Distribution av kaffe\no kryddor\n\nAvdelningskontor: Västra Frölunda,\nBox 2010. Tel 031-45 04 40\nArlöv, Företags v 16. Tel\n040-43 20 60\n\nAntal anställda: 95\nAktiekapital: 300 000\nVerkst dir: Jacob Engwall\nDotterbolag till Vict Th Engwall &amp;\nCo KB, Gävle.\n\nGEVEA, AB\n\nPnr 600 05\n\nNorrköping 5, Vagng 9. Box 5017.\nTel 011-1848 00. Bankgiro\n125-1636. Postgiro 74683-4\nVerksamhet: Tillverkar\nhögspänningsapparater\nVarunamn: Gevea, Zentus\nAktiekapital: 50 000\nVerkst dir: Bengt Andersén\nEtableringsår: 1919.\n\nTER\n\nsin o olja, slangklämmor,\nfatpumpar o elpumpar\nAktiekapital: 30 000\nVeikst dir: Törd Gibel\nEtableringsår 1951.\n\nALBACKENS SKINNVARU AB\n\nPnr 782 00\n\nMalung. Box 65. Tel 0280-118 30.\nBankgiro 46-8453. Postgiro\n118173\n\nVerksamhet: Tillverkar\nskinnkläder för dam o herr\nAntal anställda: 55\nÅrsomsättning: 4 000 000\nAktiekapital: 100 000\nVerkst dir: Carl Olof Nilsson\nEtableringsår: 1916.\n\nSVANEHOLMS AB\n\nPnr 660 31\n\nSvanskog. Tel 0532-30100.\nPostgiro 99439. Tga Svaneholm, Amål.\nTelex 5317\n\nVerksamhet: Papp, kartong o\nwallboardfabrik\nAntal anställda: 360\nÅrsomsättning: 30 000 000\nAktiekapital: 1100 000\nStyrelse: Disp Leif Brynteson, fru\nMargit Brynteson, adv Kjell\nHolmqvist\n\nVerkst dir: Disp Leif Brynteson\nEtableringsår: 1910.\n\nGEMA KEMISKA FABRIK AB\n\nPnr 79101\n\nFalun 1, N Järnvägsg 5-7. Box\n209. Tel 023-192 30. Bankgiro\n792-5860. Postgiro 160497-4.\nTga Aherdin. Telex 7619\nVerksamhet: Tillverkar\nhårvårds-medel, hårfärger, handcréme,\nbad-artiklar, myggpreparat,\nbilvårdsartiklar m m\n\nAvdelningskontor: Stockholm SO,\nErstag 29. Tel 08-42 58 55, 42 58 56\nKållered, Box 130. Tel 031-75 14 41\n\nMalmö C, O Promenaden 1. Tel\n040-1287 52, 12 87 34\nAntal anställda: 135\nÅrsomsättning: 32 000 000\nStyrelse: Adv Robert Melin (ordf),\ndisp Anders Herdin, ing Nils Herdin,\nboktr Sven Strålin\nVerkst dir: Disp Anders Herdin\nEtableringsår: 1939.\n\nWITTE.INDUSTRIER, AB\n\nPnr 53100\n\nLidköping. De la Gardiev 8. Tel\n0510-209 08. Bankgiro 212-1499.\nPostgiro 269952-8\nVerksamhet: Tillverkar\nreglermoto-rer för värme o ventilation,\nventiler för värmeanläggningar,\nlegotillverkning av gängse verkstads\nprodukter (mindre o medelstora\ndetaljer). Specialitet:\nautomatsvarv-ning, kuggbearbetning\n\nAntal anställda: 50\nÅrsomsättning: 4 000 000\nAktiekapital: 135 000\nVerkst din Rolf Lööf\nVerkmästare: Sten Svensson\nEtableringsår: 1960.",
    "structured": {
        "1": {
            "company_name": "FRANG AB",
            "pnr": "501 06",
            "address": "Borås 1, Arlag 7, Box 313",
            "phone_number": "033-12 78 00",
            "bank_details": {
                "bankgiro": "531-2996",
                "postgiro": "171314-8"
            },
            "activity": "Importagentur. Garner alla slag",
            "establishment_year": 1954
        },
        "2": {
            "company_name": "AXENTA INDUSTRI AB",
            "pnr": "36010",
            "address": "Ryd, österg 16",
            "phone_number": "0459-808 30, 808 31",
            "bank_details": {
                "bankgiro": "632-7050",
                "postgiro": "677533-2"
            },
            "activity": "Tillverkar stålinredningar o ventilationer för villa",
            "employees": 26,
            "annual_turnover": 2200000,
            "capital": 250000,
            "key_personnel": [
                {
                    "name": "Stellan Åström",
                    "position": "Verkst dir"
                }
            ],
            "establishment_year": 1964
        },
        "3": {
            "company_name": "DEUTGEN & CO AB",
            "pnr": "11143",
            "address": "Stockholm, Norrlandsg 31-33",
            "phone_number": "08-21 85 05 , 2185 06",
            "activity": "Säljer trafikspeglar o instrument för byggkontroll",
            "capital": 50000,
            "key_personnel": [
                {
                    "name": "Överstelöjtnant Sten D Ekelund",
                    "position": "Verkst dir"
                }
            ],
            "establishment_year": 1862
        },
        "4": {
            "company_name": "ZANBERTSLÄTTMETALL AB",
            "pnr": "560 12",
            "address": "Vaggeryd",
            "phone_number": "0393-22051, 22081",
            "bank_details": {
                "bankgiro": "289-2263",
                "postgiro": "380920-9"
            },
            "activity": "Tillverkar kilremsski-v or enl svensk standard",
            "employees": 30,
            "annual_turnover": 2000000,
            "capital": 100000,
            "key_personnel": [
                {
                    "name": "BAG Bokinge",
                    "position": "Verkst dir"
                }
            ],
            "establishment_year": 1947
        },
        "5": {
            "company_name": "GETINGE SNICKERIFABRIK",
            "pnr": "310 44",
            "address": "Getinge",
            "phone_number": "035-540 80",
            "bank_details": {
                "bankgiro": "43-1464",
                "postgiro": "145560"
            },
            "activity": "Tllverkar all slags byggnadssnickerier",
            "employees": 7,
            "key_personnel": [
                {
                    "name": "Pabr Bo Gillberg",
                    "position": "Chef"
                }
            ],
            "establishment_year": 1965
        },
        "6": {
            "company_name": "GETTERÄNS SNICKERI FABRIK",
            "pnr": "840 13",
            "address": "Torpshammar",
            "phone_number": "0691-203 89",
            "bank_details": {
                "bankgiro": "18-2506",
                "postgiro": "390690"
            },
            "activity": "Tillverkar pivåhängda fönster o slagfönster",
            "employees": 10,
            "annual_turnover": 400000,
            "key_personnel": [
                {
                    "name": "Stig Skerved",
                    "position": "Chef"
                }
            ],
            "establishment_year": 1918
        },
        "7": {
            "company_name": "GEVALIAROSTERIET VICTTH ENGWALL & CO AB",
            "pnr": "170 23",
            "address": "Barkarby, Pack",
            "phone_number": "08-36 28 90",
            "activity": "Distribution av kaffe o kryddor",
            "employees": 95,
            "capital": 300000,
            "key_personnel": [
                {
                    "name": "Jacob Engwall",
                    "position": "Verkst dir"
                }
            ],
            "establishment_year": null
        },
        "8": {
            "company_name": "GEVEA, AB",
            "pnr": "600 05",
            "address": "Norrköping 5, Vagng 9, Box 5017",
            "phone_number": "011-1848 00",
            "bank_details": {
                "bankgiro": "125-1636",
                "postgiro": "74683-4"
            },
            "activity": "Tillverkar högspänningsapparater",
            "varunamn": "Gevea, Zentus",
            "capital": 50000,
            "key_personnel": [
                {
                    "name": "Bengt Andersén",
                    "position": "Verkst dir"
                }
            ],
            "establishment_year": 1919
        },
        "9": {
            "company_name": "TER",
            "activity": "Tillverkar tändstift, glödstift, allmogepetin o olja, slangklämmor, fatpumpar o elpumpar",
            "employees": null,
            "capital": 30000,
            "key_personnel": [
                {
                    "name": "Törd Gibel",
                    "position": "Veikst dir"
                }
            ],
            "establishment_year": 1951
        },
        "10": {
            "company_name": "ALBACKENS SKINNVARU AB",
            "pnr": "782 00",
            "address": "Malung, Box 65",
            "phone_number": "0280-118 30",
            "bank_details": {
                "bankgiro": "46-8453",
                "postgiro": "118173"
            },
            "activity": "Tillverkar skinnkläder för dam o herr",
            "employees": 55,
            "annual_turnover": 4000000,
            "capital": 100000,
            "key_personnel": [
                {
                    "name": "Carl Olof Nilsson",
                    "position": "Verkst dir"
                }
            ],
            "establishment_year": 1916
        },
        "11": {
            "company_name": "SVANEHOLMS AB",
            "pnr": "660 31",
            "address": "Svanskog",
            "phone_number": "0532-30100",
            "postgiro": "99439",
            "activity": "Papp, kartong o wallboardfabrik",
            "employees": 360,
            "annual_turnover": 30000000,
            "capital": 1100000,
            "key_personnel": [
                {
                    "name": "Disp Leif Brynteson",
                    "position": "Styrelse"
                },
                {
                    "name": "fru Margit Brynteson",
                    "position": "Styrelse"
                },
                {
                    "name": "adv Kjell Holmqvist",
                    "position": "Styrelse"
                },
                {
                    "name": "Disp Leif Brynteson",
                    "position": "Verkst dir"
                }
            ],
            "establishment_year": 1910
        },
        "12": {
            "company_name": "GEMA KEMISKA FABRIK AB",
            "pnr": "79101",
            "address": "Falun 1, N Järnvägsg 5-7, Box 209",
            "phone_number": "023-192 30",
            "bank_details": {
                "bankgiro": "792-5860",
                "postgiro": "160497-4"
            },
            "activity": "Tillverkar hårvårds-medel, hårfärger, handcréme, bad-artiklar, myggpreparat, bilvårdsartiklar m m",
            "employees": 135,
            "annual_turnover": 32000000,
            "key_personnel": [
                {
                    "name": "Adv Robert Melin",
                    "position": "Styrelse (ordf)"
                },
                {
                    "name": "disp Anders Herdin",
                    "position": "Styrelse"
                },
                {
                    "name": "ing Nils Herdin",
                    "position": "Styrelse"
                },
                {
                    "name": "boktr Sven Strålin",
                    "position": "Styrelse"
                },
                {
                    "name": "Disp Anders Herdin",
                    "position": "Verkst dir"
                }
            ],
            "establishment_year": 1939
        },
        "13": {
            "company_name": "WITTE.INDUSTRIER, AB",
            "pnr": "53100",
            "address": "Lidköping, De la Gardiev 8",
            "phone_number": "0510-209 08",
            "bank_details": {
                "bankgiro": "212-1499",
                "postgiro": "269952-8"
            },
            "activity": "Tillverkar reglermoto-rer för värme o ventilation, ventiler för värmeanläggningar, legotillverkning av gängse verkstads produkter (mindre o medelstora detaljer). Specialitet: automatsvarv-ning, kuggbearbetning",
            "employees": 50,
            "annual_turnover": 4000000,
            "capital": 135000,
            "key_personnel": [
                {
                    "name": "Rolf Lööf",
                    "position": "Verkst din"
                },
                {
                    "name": "Sten Svensson",
                    "position": "Verkmästare"
                }
            ],
            "establishment_year": 1960
        }
    }
}