{
    "original": "CLARHOLM&amp; BERGMAN AB\n\nPnr 43122\n\nMölndal 1, Box 168. Wolffsg 2. Tel\n031-27 50 80. Postgiro 40515. Tga\nClarholms\n\nVerksamhet: Partihandel i\nkolonialvaror m m\n\nAntal anställda: 332 (koncernen)\nÅrsomsättning: 225 000 000\n(koncernen 1970)\n\nAktiekapital: 1330100 (koncernen)\nVerkst dir: E K Österdahl\nEtableringsår: 1846.\n\nFILADELFIA AB, FÖRLAGET\n\nPnr 16182\n\nBromma, vultejusv 61. Tel\n08-87 93 80. Bankgiro 476-1086.\nPostgiro 1375-5\n\nVerksamhet: Bok- o musikförlag\n.Antal anstäUda: 42\nÅrsomsättning: 5 900000\nAktiekapital: 300 000\nEtableringsår 1913.\n\nPERFECTA.SILENTA, AB\n\nPnr 350 03\n\nVäxjö 3. Box 3018. Smedjeg 20. Tel\n0470-104 75. Bankgiro 821-5659.\nPostgiro 120450-2. Tga Silenta.\nTelex 4686\n\nVerksamhet: Tillverkar\noljebrännare för lätta eldningsoljor från\n1,6 kg/tim upp till 350 kg/tim,\nvärmeledningspumpar upp till 8 000\n1/min, servis varmvattenpumpar upp\ntill 400 1/tim samt specialpumpar\nAntal anställda: 90\nÅrsomsättning: 23 000 000\nAktiekapital: 250000\n\nStyrelse: Dr Hjalmar Olson (ordf),\ndir Gunnar Ekman, disp Franz\nHartmann, dir Sigurd Ljungcrantz\nVerkst dir: Sigurd Ljungcrantz\nPlatschef: Ing Bertil Sandberg\nEtableringsår: 1956\nNuvarande namn 1966.\n\nPERFEKTA, GJUTERI.\nAKTIEBOLAGET\n\nPnr 67103\n\nArvika 3, Rosendal. Box 3017. Tel\n0570-128 05,128 80. Postgiro445899\nVerksamhet: Beställningsgjutgods\nAntal anställda: 150\nAktiekapital: 5 000\nVerkst dir: Disp Ake Fredricksson\nEtableringsår: 1955.\n\nPON\n\nsimdynor o plastsvetsmaskiner.\nUtför plastsvetsning\nAktiekapital: 5 000\nVerkst dir: P E Jon-And\nEtableringsår: 1956.\n\nBORÅS STÄMPELFABRIK AB\n\nPnr 501 02\n\nBorås 1, Box 17. Tel 033-127915.\nBankgiro 839-3167. Postgiro\n132600-8\n\nVerksamhet: Stämpelfabrik,\netikettfabrik, gravyranstalt\nAntal anställda: 82\nÅrsomsättning: 7 000 000\nAktiekapital: 350 000\nVerkst dir: Algot Bengtsson\nEtableringsår: 1934.\n\nBETON AB VESTRA SVERIGE\n\nPnr 42102\n\nVästra Frölunda 2, Box 2047.\nFrö-husg 6. Tel 031-45 01 40\nVerksamhet: Byggnadsrörelse med\nindustribyggnader som specialitet\nAntal anställda: 105\nÅrsomsättning: 12 000 000\nAktiekapital: 450000\nVerkst dir: Ake Liljeblad\nEtableringsår: 1909.\n\nSÖRMLANDS SMÅHUS, AB\n\nPnr 633 44\n\nEskilstuna, Heljestrandsg 1 A. Tel\n016-1173 40. Bankgiro 601-8659.\nPostgiro 619390-8\nVerksamhet: Byggnadsrörelse.\nHuvudsakligen småhus\nAntal anställda: 100\nÅrsomsättning: 15 000 000\nAktiekapital: 20 000\nVerkst dir: Civiling Nils Arne\nSävstam\n\nEtableringsår. 1962.\n\nBERAB, AB\n\nPnr 11357\n\nStockholm C, Kungsg 29. Tel\n08-2142 39. Tga Berimpex\nVerksamhet: Import, export o\nskumplast konfektionering\nAktiekapitel: 250 000\nVerkst dir: Ulf J Kronberg\nEtableringsår: 1950.\n\nHARDMETALLVERKTYG, AB\n\nPnr 81600\n\nOckelbo, Box 8. Tel 0297-403 80,\n412 80. Bankgiro 237-9105.\nPostgiro 293716-7. Tga Rebit\nVerksamhet: Tillverkar bergborrar\nmed hårdmetallskär,\nhårdmetallverktyg för sten, stålverktyg för\npneumatiska maskiner,\nbetongmejslar, tjälmejslar, asfaltmejslar,\nbil-ningsmejslar, spadar, spår- o\nskarpmejslar etc\nVarunamn: Rebit\nAntal anställda: 20\nÅrsomsättning: 2 600 000\nAktiekapital: 60 000\nVerkst dir: Erie Wall\nEtableringsår: 1945\nDotterbolag: AB Sandvikens\nTryckluftverktyg, Ockelbo.\n\nH-A-S BOKFORINGS- &amp;\nREVISIONSBYRÅ\n\nPnr 11669\n\nStockholm, Ringv 64. Tel\n08-6927 27, 69 27 79. Postgiro\n407575-0, 687978-2\nVerksamhet: Bokföring, revision,\nbokslut, siffergranskning,\nfaktureringar, bouppteckningar,\narvsskiften, firmaregistreringar, även\nAB, upprättande av olika\nköpeavtal m m\n\nChef: Revisor H-A Sundström\nEtableringsår: 1960.\n\nSTA\n\nAktiekapital: 5 000\nVerkst dir: Tryggve Norin\nEtableringsår: 1967.\n\nSTAR, AB KARTONG.\nFABRIKEN\n\nPnr 56040\n\nHabo. Tel 036-400 60, 401 46.\nBankgiro 553-8210. Postgiro 144760-6\nVerksamhet: Stansade o klädda\nkartonger samt stansade o pressade\npappdetaljer för isoleringsändamål\nAktiekapital: 50 000\nVerkst dir: Disp Stig-Erland\nDagman\n\nEtableringsår: 1931\nOmbildat till aktiebolag 1946.\n\nSTARFILM, AB\n\nPnr 113 23\n\nStockholm, Hälsingeg 7. Tel\n08-34 08 90. Postgiro 250819-0. Tga\nStarmovies\n\nVerksamhet: Filminspelning,\nfilmuthyrning o reklamfilmsvisning\nAntal anställda: 10\nÅrsomsättning: 800 000\nAktiekapital: 50 000\nStyrelseordf: Dir Hugo Willbjer\nVerkst dir: Hugo Willbjer\nEtableringsår: 1945.",
    "structured": {
        "1": {
            "company_name": "CLARHOLM& BERGMAN AB",
            "pnr": "43122",
            "address": "Mölndal 1, Box 168. Wolffsg 2",
            "phone_number": "031-27 50 80",
            "bank_details": {
                "postgiro": "40515"
            },
            "activity": "Partihandel i kolonialvaror m m",
            "employees": 332,
            "annual_turnover": 225000000,
            "capital": 1330100,
            "key_personnel": [
                {
                    "name": "E K Österdahl",
                    "position": "Verkst dir"
                }
            ],
            "establishment_year": 1846
        },
        "2": {
            "company_name": "FILADELFIA AB, FÖRLAGET",
            "pnr": "16182",
            "address": "Bromma, vultejusv 61",
            "phone_number": "08-87 93 80",
            "bank_details": {
                "bankgiro": "476-1086",
                "postgiro": "1375-5"
            },
            "activity": "Bok- o musikförlag",
            "employees": 42,
            "annual_turnover": 5900000,
            "capital": 300000,
            "establishment_year": 1913
        },
        "3": {
            "company_name": "PERFECTA.SILENTA, AB",
            "pnr": "350 03",
            "address": "Växjö 3, Box 3018. Smedjeg 20",
            "phone_number": "0470-104 75",
            "bank_details": {
                "bankgiro": "821-5659",
                "postgiro": "120450-2"
            },
            "activity": "Tillverkar oljebrännare för lätta eldningsoljor",
            "employees": 90,
            "annual_turnover": 23000000,
            "capital": 250000,
            "key_personnel": [
                {
                    "name": "Dr Hjalmar Olson",
                    "position": "Styrelseordf"
                },
                {
                    "name": "Gunnar Ekman",
                    "position": "dir"
                },
                {
                    "name": "Franz Hartmann",
                    "position": "disp"
                }
            ],
            "establishment_year": 1956
        },
        "4": {
            "company_name": "PERFEKTA, GJUTERI. AKTIEBOLAGET",
            "pnr": "67103",
            "address": "Arvika 3, Rosendal. Box 3017",
            "phone_number": "0570-128 05",
            "bank_details": {
                "postgiro": "445899"
            },
            "activity": "Beställningsgjutgods",
            "employees": 150,
            "capital": 5000,
            "key_personnel": [
                {
                    "name": "Disp Ake Fredricksson",
                    "position": "Verkst dir"
                }
            ],
            "establishment_year": 1955
        },
        "5": {
            "company_name": "PON",
            "activity": "Simdynor o plastsvetsmaskiner. Utför plastsvetsning",
            "capital": 5000,
            "key_personnel": [
                {
                    "name": "P E Jon-And",
                    "position": "Verkst dir"
                }
            ],
            "establishment_year": 1956
        },
        "6": {
            "company_name": "BORÅS STÄMPELFABRIK AB",
            "pnr": "501 02",
            "address": "Borås 1, Box 17",
            "phone_number": "033-127915",
            "bank_details": {
                "bankgiro": "839-3167",
                "postgiro": "132600-8"
            },
            "activity": "Stämpelfabrik, etikettfabrik, gravyranstalt",
            "employees": 82,
            "annual_turnover": 7000000,
            "capital": 350000,
            "key_personnel": [
                {
                    "name": "Algot Bengtsson",
                    "position": "Verkst dir"
                }
            ],
            "establishment_year": 1934
        },
        "7": {
            "company_name": "BETON AB VESTRA SVERIGE",
            "pnr": "42102",
            "address": "Västra Frölunda 2, Box 2047. Frö-husg 6",
            "phone_number": "031-45 01 40",
            "activity": "Byggnadsrörelse med industribyggnader som specialitet",
            "employees": 105,
            "annual_turnover": 12000000,
            "capital": 450000,
            "key_personnel": [
                {
                    "name": "Ake Liljeblad",
                    "position": "Verkst dir"
                }
            ],
            "establishment_year": 1909
        },
        "8": {
            "company_name": "SÖRMLANDS SMÅHUS, AB",
            "pnr": "633 44",
            "address": "Eskilstuna, Heljestrandsg 1 A",
            "phone_number": "016-1173 40",
            "bank_details": {
                "bankgiro": "601-8659",
                "postgiro": "619390-8"
            },
            "activity": "Byggnadsrörelse. Huvudsakligen småhus",
            "employees": 100,
            "annual_turnover": 15000000,
            "capital": 20000,
            "key_personnel": [
                {
                    "name": "Civiling Nils Arne Sävstam",
                    "position": "Verkst dir"
                }
            ],
            "establishment_year": 1962
        },
        "9": {
            "company_name": "BERAB, AB",
            "pnr": "11357",
            "address": "Stockholm C, Kungsg 29",
            "phone_number": "08-2142 39",
            "activity": "Import, export o skumplast konfektionering",
            "capital": 250000,
            "key_personnel": [
                {
                    "name": "Ulf J Kronberg",
                    "position": "Verkst dir"
                }
            ],
            "establishment_year": 1950
        },
        "10": {
            "company_name": "HARDMETALLVERKTYG, AB",
            "pnr": "81600",
            "address": "Ockelbo, Box 8",
            "phone_number": "0297-403 80, 412 80",
            "bank_details": {
                "bankgiro": "237-9105",
                "postgiro": "293716-7"
            },
            "activity": "Tillverkar bergborrar med hårdmetallskär, hårdmetallverktyg för sten, stålverktyg för pneumatiska maskiner",
            "employees": 20,
            "annual_turnover": 2600000,
            "capital": 60000,
            "key_personnel": [
                {
                    "name": "Erie Wall",
                    "position": "Verkst dir"
                }
            ],
            "establishment_year": 1945
        },
        "11": {
            "company_name": "H-A-S BOKFORINGS- & REVISIONSBYRÅ",
            "pnr": "11669",
            "address": "Stockholm, Ringv 64",
            "phone_number": "08-6927 27, 69 27 79",
            "bank_details": {
                "postgiro": "407575-0, 687978-2"
            },
            "activity": "Bokföring, revision, bokslut, siffergranskning",
            "key_personnel": [
                {
                    "name": "Revisor H-A Sundström",
                    "position": "Chef"
                }
            ],
            "establishment_year": 1960
        },
        "12": {
            "company_name": "STA",
            "capital": 5000,
            "key_personnel": [
                {
                    "name": "Tryggve Norin",
                    "position": "Verkst dir"
                }
            ],
            "establishment_year": 1967
        },
        "13": {
            "company_name": "STAR, AB KARTONG. FABRIKEN",
            "pnr": "56040",
            "address": "Habo",
            "phone_number": "036-400 60, 401 46",
            "bank_details": {
                "bankgiro": "553-8210",
                "postgiro": "144760-6"
            },
            "activity": "Stansade o klädda kartonger samt stansade o pressade pappdetaljer för isoleringsändamål",
            "capital": 50000,
            "key_personnel": [
                {
                    "name": "Disp Stig-Erland Dagman",
                    "position": "Verkst dir"
                }
            ],
            "establishment_year": 1931
        },
        "14": {
            "company_name": "STARFILM, AB",
            "pnr": "113 23",
            "address": "Stockholm, Hälsingeg 7",
            "phone_number": "08-34 08 90",
            "bank_details": {
                "postgiro": "250819-0"
            },
            "activity": "Filminspelning, filmuthyrning o reklamfilmsvisning",
            "employees": 10,
            "annual_turnover": 800000,
            "capital": 50000,
            "key_personnel": [
                {
                    "name": "Hugo Willbjer",
                    "position": "Styrelseordf"
                }
            ],
            "establishment_year": 1945
        }
    }
}