{
    "original": "ASTA AB, PARFYMERI\n\nPnr 172 23\n\nSundbyberg, Hamng 33. Tel 08-\n\n28 25 80\n\nVerksamhet: Damfrisör- o\nparfymeriartiklar m m en gros\n\nAktiekapital: 150 000\nVerkst dir: Arne Österberg\nEtableringsår: 1943.\n\nASTBORGS SKYLTAR\nSTÄMPLAR GRAVYR\n\nPnr 252 20\n\nHelsingborg, Fågelsångsg 29. Tel\n\n042-11 8017, 12 38 32. Bankgiro\n\n653-2592. Postgiro 464181-7\n\nVerksamhet: Tillverkar skyltar o\n\ngummistämplar\n\nÄgare o chef: Sven Astborg\n\nEtableringsår: 1943.\n\nASTO AB\n\nPnr 114 26\n\nStockholm, Bragev 15. Tel\n08-215488. Postgiro 257745. Tga\nAstoab. Telex 10490\nVerksamhet: Representerar tyska\no schweiziska finmekaniska,\nmekaniska o elektrotekniska\nlegotill-verkare\n\nAktiekapital: 5 000\n\nVerkst dir: Civiling Lars-Erik\n\nHolmer\n\nEtableringsår: 1946.\n\nVerksamhet: Konsulterande\ningenjörsbyrå: transport-materialhantering, fysisk distribution,\norganisation. Modellverkstad: skalamodeller\nför utställningar, marknadsföring,\nexperiment, industri, maskin,\nundervisningsmodeller mm.\nFörsäljning av\nFAC-konstruktions-system\n\nVarunamn: FAC\n\nAgenter för\nFAC-konstruktions-sy stern i: Finland, Norge, Danmark,\nBenelux, England, Frankrike,\nÖsterrike, Australien, Israel,\nPersien m fi.\n\nVissa av dessa representerar oss\näven för modeller\nAntal anställda: 16\nÅrsomsättning: 100 0 000\nAktiekapital: 30 000\nStyrelse: Leg läk Helena von\nKle-wesal-Palm. övering Carl Filip\nPalm, dir Lennart Palm\nVerkst dir: Ing Lennart Palm\nIngenjörsbyrån: ing Lennart Palm\nModellverkstaden: Modelltekniker\nBengt Andersson\nFAC-konstruktionssystem:\nFAC-tekniker Sven-Olof Forsling\nEkonomiavd: Kamrer Alf Roseli\nEtableringsår: 1960.\n\nSKYDDSKLÄDER, AB\n\nPnr 510 47\n\nFristad, Stora v 31. Box 70. Tel\n033-602 20, order 61060. Bankgiro\n84-4830. Postgiro 720. Tga\nSkyddskläder\n\nVerksamhet: Tillverkar arbets- o\nskyddskläder, byxor, regnkläder,\narbetsskjortor m m\nVarunamn: Fristads\nAntal anställda: 400\nÅrsomsättning: 25 000 000\nAktiekapital: 500 000\nStyrelse: Dir John Magnuson (ordf),\ndir Bertil Magnuson, ing Birger\nMagnuson (suppl), kamrer Knut\nSöderberg\n\nVerkst dir: Bertil Magnuson\nV verkst dir: Birger Magnuson\nEtableringsår: 1925.\n\nBREMELL &amp; CO AB\n\nPnr 402 23\n\nGöteborg 5, Box 5152. Tel\n031-27 5170. Tga Bremellco\nVerksamhet: Leksaker,\npresentartiklar o souvenirer\nAktiekapital: 50 000\nVerkst dir: David Bremell\nEtableringsår 1947.\n\nROLLAB, AB\n\nPnr 17107\n\nSolna 7, Järvstigen 5. Box 773. Tel\n08-85 65 65, 85 13 16. Bankgiro\n572-3879. Postgiro 196072-3. Telex\n10598. Tga Rollabor\nVerksamhet: Konsult inom flyg- o\nmaskinteknik\nAntal anställda: 15\nÅrsomsättning: 1000 000\nAktiekapital: 100 000\nVerkst dir: Civiling John Rosén\nEtableringsår: 1963.\n\nOSB-INDUSTRIER, AB\n\nPnr 693 01\n\nDegerfors 1, Box 61. Tel\n0586-42120. Bankgiro 614-4869.\nPostgiro 20742-3\n\nVerksamhet: Konfektionsindustri\nVarunamn: Norsel\nAntal anställda: 75\nÅrsomsättning: 15 000 000\n\nStyrelse: Dir Olof Sjöberg (ordf),\ndisp Knut Lundqvist\nEtableringsàr: 1957.\n\nOSTANÅSÅGEN AB\n\nPnr 828 00\n\nEdsbyn. Tel 027.1-21107, 21950.\nBankgiro 786-0216. Postgiro\n277190-5. Tga Ovanåkersvirke\nVerksamhet: Tillverkar sågade o\nhyvlade trävaror\nAntal anställda: 35\nÅrsomsättning: 4 000 000\nAktiekapital: 155 000\nVerkst dir: Byggmäst H Andersson\nEtableringsàr: 1892.\n\nOSTBERG &amp; DIEDRICHS AB\n\nPrr 11151\n\nStockholm, Drottningg 14. Tel\n08-23 02 90. Tga Woodpulp.\nTelex 10758 WOODTEX S\nVerksamhet: Export av cellulosa,\nimport av svavel, kaolin o textilvaror\nAktiekapital: 300 000\nVerkst dir. Bengt Diedrichs\nEtableringsàr: 1910.\n\nOSTBERGS FABRIKS AB\n\nPnr 822 00\n\nAlfta, Box 1200. Tel 0271-104 75.\nBankgiro 784-7551. Postgiro\n267041-2. Tga ÖSA, Bollnäs.\nTelex 81022\n\nVerksamhet: Maskiner o utrustning\nför helmekaniserat skogsbruk\nVarunamn: OSA\nAntal anställda: 450\nAktiekapital: 500 000\nVerkst dir: Martin Ostberg\nEtableringsån 1918.\n\nGACO VARMEINDUSTRI AB\n\nPnr 830 44\n\nNälden, Box 59. Tel 0640-200 25.\nBankgiro 198-9151. Postgiro\n87585-6\n\nVerksamhet: Tillverkar\nvarmvattenberedare, cisterner o\nelvärmeapparater. Utför legoarbeten\nVarunamn: Gaco\nAntal anställda: 17\nÅrsomsättning: 800000\nAktiekapital: 60000\nVerkst dir: Gösta Arnung\nFabr: Martin Westlund\nEtableringsår: 1888.\n\nHANÖ TRAC AB\n\nPnr 570 40\n\nAneby. Tel 0380-404 40. Bankgiro\n295-8890. Postgiro 690810-7\nVeiksamhet: Generalagent för\nHanomag bandtraktorer o hjullastare\nVaiunamn: Hanomag.\n\nHANSA, HANDELS AB\n\nPnr 212 28\n\nMalmö, Sallerupsv 90. Tel\n040-93 69 50. Bankgiro 875-5050.\nPost-giro 14032-7\n\nVeiksamhet: Export o import.\nTillverkar pappersvaror, papperspåsar,\npappersservetter, pappersborddukar,\nhushållsfolie o emballage för\nbagerier o charkuterier, aluminiumformar,\nfrysemballage o cobbelrör. Säljer\nallt i pappersbranschen samt\nbindgarn, kartonger, emballageartiklar\no binderiartiklar för blommor.\nGeneralagentur för Sverige för\nPapier-fabrik Halstrick, Stotzheim über\nEuskirchen, Västtyskland samt\nBäckelunds Papirverk, Viborg,\nDanmark\n\nVarunamn: Alltifoil, Festival,\nHansa\n\nAntal anställda: 42\nÅrsomsättning: 9 300 000\nAktiekapital: 15 000\n\nStyrelse: Dir Iwe Andersson (ordf),\nfru Alva Andersson, disp Tommy\nAndersson\n\nVeikst dir: Iwe Andersson\nDisp:r Tommy Andersson, Ake\nNilsson\n\nFabrikschef: Göte Davidsson\nInköpschef: Stig Jönsson\nEtableringsår: 1916.\n\nMMT TRICOT AB\n\nPnr 200 70\n\nMalmö 5, Fack. Ronneholmsv 38.\nTel 040-714 30. Bankgiro 641-3348.\nPostgiro 38372-9. Tga\nTricotfab-riken\n\nVerksamhet Tillverkar o säljer\njerseykonfektion, design Katja of\nSweden o Elisabeth, för damer,\nflickor o bam samt högklassiga\nherrunderkläder o herrstrumpor\nFörsäljningskontor: Göteborg C,\nCentrumhuset. Tel 031-11 10 36\nStockholm C, Sveav 17. Tel\n08-1002 30, 10 03 30, 10 04 30\nAntal anställda: 300\n\nMO INDUSTRI AB\n\nPnr 560 25\n\nBottnaryd. Tel 036-20130.\nBankgiro 549-1717. Postgiro 84633-7.\nTga Miab\n\nVerksamhet: Tillverkar polyeten-\n\nemballage\n\nAntal anställda: 20\n\nÅrsomsättning: 2 500 000\n\nAktiekapital: 50 000\n\nÄgare o chefer: Bertil Hermansson,\n\nThore Gustavsson\n\nEtableringsår: 1957.\n\nARNHEIM, AB ADOLF M\n\nPnr 12612\n\nStockholm 42, Box 42002.\nKaru-sellplan 7-13. Tel 08-19 58 02,\n19 58 03. Bankgiro 29-5002.\nPostgiro 57088-7. Tga Amavapen\nVerksamhet: Jaktvapen, pistoler,\nammunition o sportartiklar i parti\nAntal anställda: 14\nÅrsomsättning: 2 600 000\n\nAktiekapital: 537 500\nVerkst dir: Peter Odelfelt\nEtableringsår: 1919.",
    "structured": {
        "Firm1": {
            "company_name": "ASTA AB",
            "pnr": "172 23",
            "address": "Sundbyberg, Hamng 33",
            "phone_number": "08-28 25 80",
            "activity": "Damfrisör- o parfymeriartiklar m m en gros",
            "capital": 150000,
            "key_personnel": [
                {
                    "name": "Arne Österberg",
                    "position": "Verkst dir"
                }
            ],
            "establishment_year": 1943
        },
        "Firm2": {
            "company_name": "ASTBORGS SKYLTAR STÄMPLAR GRAVYR",
            "pnr": "252 20",
            "address": "Helsingborg, Fågelsångsg 29",
            "phone_number": "042-11 8017, 12 38 32",
            "bank_details": {
                "bankgiro": "653-2592",
                "postgiro": "464181-7"
            },
            "activity": "Tillverkar skyltar o gummistämplar",
            "employees": null,
            "annual_turnover": null,
            "annual_production_value": null,
            "capital": null,
            "key_personnel": [
                {
                    "name": "Sven Astborg",
                    "position": "Ägare o chef"
                }
            ],
            "establishment_year": 1943
        },
        "Firm3": {
            "company_name": "ASTO AB",
            "pnr": "114 26",
            "address": "Stockholm, Bragev 15",
            "phone_number": "08-215488",
            "postgiro": "257745",
            "activity": "Representerar tyska o schweiziska finmekaniska, mekaniska o elektrotekniska legotill-verkare",
            "capital": 5000,
            "key_personnel": [
                {
                    "name": "Civiling Lars-Erik Holmer",
                    "position": "Verkst dir"
                }
            ],
            "establishment_year": 1946
        },
        "Firm4": {
            "company_name": "FAC AB",
            "activity": "Konsulterande ingenjörsbyrå: transport-materialhantering, fysisk distribution, organisation",
            "employees": 16,
            "annual_turnover": 1000000,
            "capital": 30000,
            "key_personnel": [
                {
                    "name": "Leg läk Helena von Kle-wesal-Palm",
                    "position": "Styrelse"
                },
                {
                    "name": "övering Carl Filip Palm",
                    "position": "Styrelse"
                },
                {
                    "name": "dir Lennart Palm",
                    "position": "Styrelse"
                }
            ],
            "establishment_year": 1960
        },
        "Firm5": {
            "company_name": "SKYDDSKLÄDER AB",
            "pnr": "510 47",
            "address": "Fristad, Stora v 31, Box 70",
            "phone_number": "033-602 20, order 61060",
            "bankgiro": "84-4830",
            "postgiro": "720",
            "activity": "Tillverkar arbets- o skyddskläder, byxor, regnkläder, arbetsskjortor m m",
            "varunamn": "Fristads",
            "employees": 400,
            "annual_turnover": 25000000,
            "capital": 500000,
            "key_personnel": [
                {
                    "name": "Dir John Magnuson (ordf)",
                    "position": "Styrelse"
                },
                {
                    "name": "dir Bertil Magnuson",
                    "position": "Styrelse"
                },
                {
                    "name": "ing Birger Magnuson (suppl)",
                    "position": "Styrelse"
                },
                {
                    "name": "kamrer Knut Söderberg",
                    "position": "Styrelse"
                },
                {
                    "name": "Verkst dir Bertil Magnuson"
                },
                {
                    "name": "V verkst dir Birger Magnuson"
                }
            ],
            "establishment_year": 1925
        },
        "Firm6": {
            "company_name": "BREMELL & CO AB",
            "pnr": "402 23",
            "address": "Göteborg 5, Box 5152",
            "phone_number": "031-27 5170",
            "activity": "Leksaker, presentartiklar o souvenirer",
            "capital": 50000,
            "key_personnel": [
                {
                    "name": "David Bremell",
                    "position": "Verkst dir"
                }
            ],
            "establishment_year": 1947
        },
        "Firm7": {
            "company_name": "ROLLAB AB",
            "pnr": "17107",
            "address": "Solna 7, Järvstigen 5, Box 773",
            "phone_number": "08-85 65 65, 85 13 16",
            "bankgiro": "572-3879",
            "postgiro": "196072-3",
            "activity": "Konsult inom flyg- o maskinteknik",
            "employees": 15,
            "annual_turnover": 1000000,
            "capital": 100000,
            "key_personnel": [
                {
                    "name": "Civiling John Rosén",
                    "position": "Verkst dir"
                }
            ],
            "establishment_year": 1963
        },
        "Firm8": {
            "company_name": "OSB-INDUSTRIER AB",
            "pnr": "693 01",
            "address": "Degerfors 1, Box 61",
            "phone_number": "0586-42120",
            "bankgiro": "614-4869",
            "postgiro": "20742-3",
            "activity": "Konfektionsindustri",
            "varunamn": "Norsel",
            "employees": 75,
            "annual_turnover": 15000000,
            "key_personnel": [
                {
                    "name": "Dir Olof Sjöberg (ordf)",
                    "position": "Styrelse"
                },
                {
                    "name": "disp Knut Lundqvist",
                    "position": "Styrelse"
                }
            ],
            "establishment_year": 1957
        },
        "Firm9": {
            "company_name": "OSTANÅSÅGEN AB",
            "pnr": "828 00",
            "address": "Edsbyn",
            "phone_number": "027.1-21107, 21950",
            "bankgiro": "786-0216",
            "postgiro": "277190-5",
            "activity": "Tillverkar sågade o hyvlade trävaror",
            "employees": 35,
            "annual_turnover": 4000000,
            "capital": 155000,
            "key_personnel": [
                {
                    "name": "Byggmäst H Andersson",
                    "position": "Verkst dir"
                }
            ],
            "establishment_year": 1892
        },
        "Firm10": {
            "company_name": "OSTBERG & DIEDRICHS AB",
            "prr": "11151",
            "address": "Stockholm, Drottningg 14",
            "phone_number": "08-23 02 90",
            "activity": "Export av cellulosa, import av svavel, kaolin o textilvaror",
            "capital": 300000,
            "key_personnel": [
                {
                    "name": "Bengt Diedrichs",
                    "position": "Verkst dir"
                }
            ],
            "establishment_year": 1910
        },
        "Firm11": {
            "company_name": "OSTBERGS FABRIKS AB",
            "pnr": "822 00",
            "address": "Alfta, Box 1200",
            "phone_number": "0271-104 75",
            "bankgiro": "784-7551",
            "postgiro": "267041-2",
            "activity": "Maskiner o utrustning för helmekaniserat skogsbruk",
            "varunamn": "OSA",
            "employees": 450,
            "capital": 500000,
            "key_personnel": [
                {
                    "name": "Martin Ostberg",
                    "position": "Verkst dir"
                }
            ],
            "establishment_year": 1918
        },
        "Firm12": {
            "company_name": "GACO VARMEINDUSTRI AB",
            "pnr": "830 44",
            "address": "Nälden, Box 59",
            "phone_number": "0640-200 25",
            "bankgiro": "198-9151",
            "postgiro": "87585-6",
            "activity": "Tillverkar varmvattenberedare, cisterner o elvärmeapparater",
            "employees": 17,
            "annual_turnover": 800000,
            "capital": 60000,
            "key_personnel": [
                {
                    "name": "Gösta Arnung",
                    "position": "Verkst dir"
                },
                {
                    "name": "Martin Westlund",
                    "position": "Fabr"
                }
            ],
            "establishment_year": 1888
        },
        "Firm13": {
            "company_name": "HANÖ TRAC AB",
            "pnr": "570 40",
            "address": "Aneby",
            "phone_number": "0380-404 40",
            "bankgiro": "295-8890",
            "postgiro": "690810-7",
            "activity": "Generalagent för Hanomag bandtraktorer o hjullastare",
            "varunamn": "Hanomag"
        },
        "Firm14": {
            "company_name": "HANSA, HANDELS AB",
            "pnr": "212 28",
            "address": "Malmö, Sallerupsv 90",
            "phone_number": "040-93 69 50",
            "bankgiro": "875-5050",
            "postgiro": "14032-7",
            "activity": "Export o import",
            "employees": 42,
            "annual_turnover": 9300000,
            "capital": 15000,
            "key_personnel": [
                {
                    "name": "Dir Iwe Andersson (ordf)",
                    "position": "Styrelse"
                },
                {
                    "name": "fru Alva Andersson",
                    "position": "Styrelse"
                },
                {
                    "name": "disp Tommy Andersson",
                    "position": "Disp:r"
                },
                {
                    "name": "Ake Nilsson",
                    "position": "Disp:r"
                },
                {
                    "name": "Göte Davidsson",
                    "position": "Fabrikschef"
                },
                {
                    "name": "Stig Jönsson",
                    "position": "Inköpschef"
                }
            ],
            "establishment_year": 1916
        },
        "Firm15": {
            "company_name": "MMT TRICOT AB",
            "pnr": "200 70",
            "address": "Malmö 5, Fack. Ronneholmsv 38",
            "phone_number": "040-714 30",
            "bankgiro": "641-3348",
            "postgiro": "38372-9",
            "activity": "Tillverkar o säljer jerseykonfektion",
            "employees": 300
        },
        "Firm16": {
            "company_name": "MO INDUSTRI AB",
            "pnr": "560 25",
            "address": "Bottnaryd",
            "phone_number": "036-20130",
            "bankgiro": "549-1717",
            "postgiro": "84633-7",
            "activity": "Tillverkar polyeten-emballage",
            "employees": 20,
            "annual_turnover": 2500000,
            "capital": 50000,
            "key_personnel": [
                {
                    "name": "Bertil Hermansson"
                },
                {
                    "name": "Thore Gustavsson"
                }
            ],
            "establishment_year": 1957
        },
        "Firm17": {
            "company_name": "ARNHEIM, AB ADOLF M",
            "pnr": "12612",
            "address": "Stockholm 42, Box 42002, Karussellplan 7-13",
            "phone_number": "08-19 58 02, 19 58 03",
            "bankgiro": "29-5002",
            "postgiro": "57088-7",
            "activity": "Jaktvapen, pistoler, ammunition o sportartiklar i parti",
            "employees": 14,
            "annual_turnover": 2600000,
            "capital": 537500,
            "key_personnel": [
                {
                    "name": "Peter Odelfelt",
                    "position": "Verkst dir"
                }
            ],
            "establishment_year": 1919
        }
    }
}