{
    "original": "BLOMGREN, AB B\n\nPnr 11129\n\nStockholm, Svartmang 6. Tel\n08-2130 88. Postgiro 250239-1\n\nVerksamhet: Entreprenadfirma för\nbroar, vattenbyggnader o vägar\nAntal anställda: 15\nÅrsomsättning: 1500 000\nAktiekapital: 48 000\nVerkst dir: Civiling Bo Blomgren\nEtableringsår: 1952.\n\nBLOMKVIST, BLOMQUIST,\nBLOMQVIST\n\nBLOMQVIST ELEMENT.\nBYGGEN AB\n\nPnr 442 00\n\nKungälv, Gamla Brog 5. Tel\n0303-145 50, 145 51. Bankgiro 513-3293.\nPostgiro 528320-5\nVerksamhet: Utför\nelementbyggnation med egen elementtillverkning\nAntal anställda: 29\nÅrsomsättning: 5 000 000\nAktiekapital: 15 000\nStyrelseordf: Ing Folke Blomqvist\nVerkst dir: Ing Folke Blomqvist\nEtableringsår: 1959\nNamnändring 1968.\n\nBLOMQVISTS VERKSTADS AB\n\nPnr 15102\n\nSödertälje 2, Skepparev. Box 2036.\nTel 0755-32970. Bankgiro\n622-5585. Postgiro 161780-2. Tga Beve\nVerksamhet: Tillverkar o säljer\nbänksvarvar samt glasfibertankar\nför oljor, avlopp o vatten\nVarunamn: Blomqvist\nAktiekapital: 50000\nEtableringsår: 1896.\n\nBLOMKVIST METALLFABRIK,\nARTUR\n\nPnr 632 26\n\nEskilstuna, Bergsg 34. Tel\n016-1315 49. Postgiro 72331-2\nChef: Artur Blomkvist\nEtableringsår: 1921.\n\nmalå säg &amp; hyvleri, ab\n\nPnr 930 70\n\nMalå. Storg. Tel 0953-107 70.\nBankgiro 76-6218. Postgiro 326296-1\nVerksamhet: Sågade o hyvlade\nträvaror. Tillverkar färdigkapat virke\nför hustillverkning, behandlad list\no panel ’Malåpanelen’\nVarunamn: Malåpanel\nAntal anställda: 45\nÅrsomsättning: 5 500 000\nAktiekapital: 50 000\nVerkst dir: Evald Eriksson\nFörsäljn-chef: Disp Allan Eriksson\nEtableringsår: 1946.\n\nI TO EXPORT &amp; IMPORT AB\n\nPnr 41110\n\nGöteborg 11, Box 11032. O Hamng\n19 A. Tel 031-17 48 40. Bankgiro\n508-8398. Postgiro 526257-1. Tga\nItoexport. Telex 21197\nVerksamhet: Säljer radio, TV,\nbandspelare, stereo o elektroniska\nartiklar. Generalagent för Sanyo\nElectric Co, Osaka, Japan\nFilial: 112 54 Stockholm, Birger\nSjöbergs v 1. Tel 08-53 43 78\nVarunamn: Sanyo\nAntal anställda: 8\nÅrsomsättning: 8400 000\nAktiekapital: 50 000\nVerkst din Erwin SUssman\nFörsäljn-dir. Selfrid Ohlund\nEtableringsår 1960.\n\nWEDDE &amp; CO AB\n\nPnr 790 80\n\nÄlvdalen. Tel 0251-520 13, 520 14.\nBankgiro 472-0363. Postgiro\n342400-9\n\nVerksamhet: Tillverkar sågade o\nhyvlade trävaror\nAntal anställda: 25\nÅrsomsättning: 5 000 000\nAktiekapital: 40 000\nVerkst dir: P J Wedde\nEtableringsår: 1949.\n\nekholms byggnadsvaror\n\nPnr 70212\n\nÖrebro, Trädgårdsg 15. Tel\n019-119155. Bankgiro 815-4312.\nPostgiro 76473-8\n\nVerksamhet: Säljer byggnadsvaror\nsamt uthyr presenningar\nChef: G Ekholm\nEtableringsår: 1930.\n\nSVENSK FILMINDUSTRI, AB\n\nPnr 10110\n\nStockholm 1, Kungsg 36. Pack. Tel\n08-22 14 00. Bankgiro 562-9670.\nPostgiro 630-4. Tga Filmindustri\nVerksamhet: Producerar film på\n’Filmstaden* i Solna\nAntal anställda: 725\nÅrsomsättning: 49 000 000\nAktiekapital: 12 000 000\nVerkst dir: C H Fant\nEtableringsår: 1919.\n\nTRO\n\nVerksamhet: Utför entreprenader i\nvägbyggnader o schaktbranschen\nAntal anställda: 35\nÅrsomsättning: 5 000 000\nAktiekapital: 25000\nStyrelse: Dir Rune Haake (ordf),\ndir Karl-Erik Andersson\nVerkst dir: Rune Haake\nEtableringsår: 1968.\n\nTROLLHÄTTANS TRYCKERI\nAB\n\nPnr 461 00\n\nTrollhättan, Staveredsg 18. Tel\n0520-126 70. Bankgiro 89-2449.\nPostgiro 87310\nAntal anställda: 50\nAktiekapital: 120 000\nVerkst dir: Lars Ström\nEtableringsår. 1934.\n\nBORÉNSAB\n\nPnr 500 04\n\nBorås 4, Box 44093. Barnhemsg 15\nTel 033-1179 00. Bankgiro 53-1106\nPostgiro 34110-7\n\nVerksamhet: Tillverkar\nbelysningsarmatur\n\nAntal anställda: 50\nAktiekapital: 100 000\nVerkst dir: Karl Borén\nEtableringsår: 1924.\n\nFOLKES BILVERKSTÄDER AB\n\nPnr 372 00\n\nRonneby, Karlshamnsv. Tel\n0457-12940. Bankgiro 349-6155.\nPostgiro 289085-3\n\nVerksamhet: Auktoriserad\nåterförsäljare för General Motors samt\nservice. Billackering. Biluthyrning\nFilial: 360 20 Tingsryd. Tel\n0477-105 60\n\nAntal anställda: 30\nÅrsomsättning: 5 000 000\nStyrelse: Jägmäst Erie Cassel,\nfru Siv Cassel, dir Folke Svensson\nVerkst dir: Folke Svensson\nFörsäljn-chef: Gunnar Knutsson\nVerkmästare: Sten Berndtsson\nEtableringsår 1945.\n\nGRUN &amp; CO, AB HUGO\n\nPnr 11143\n\nStockholm, Norrlandsg 18. Tel\n08-2107 17, 10 52 70. Bankgiro\n560-1588. Postgiro 52482-7. Tga\nPerl-grün\n\nVerksamhet Säljer guld, silver,\njuveler engros\nAntal anställda: 9\nÅrsomsättning: 1700000\nAktiekapital: 50 000\nVerkst dir: Ellen Wikström\nEtableringsår: 1920.",
    "structured": {
        "1": {
            "company_name": "BLOMGREN, AB B",
            "address": "Stockholm, Svartmang 6.",
            "phone_number": "08-2130 88",
            "bank_details": {
                "postgiro": "250239-1"
            },
            "activity": "Entreprenadfirma för broar, vattenbyggnader o vägar",
            "employees": 15,
            "annual_turnover": 1500000,
            "capital": 48000,
            "key_personnel": [
                {
                    "name": "Civiling Bo Blomgren",
                    "position": "Verkst dir"
                }
            ],
            "establishment_year": 1952
        },
        "2": {
            "company_name": "BLOMQVIST ELEMENT. BYGGEN AB",
            "address": "Kungälv, Gamla Brog 5.",
            "phone_number": "0303-145 50",
            "bank_details": {
                "bankgiro": "513-3293",
                "postgiro": "528320-5"
            },
            "activity": "Utför elementbyggnation med egen elementtillverkning",
            "employees": 29,
            "annual_turnover": 5000000,
            "capital": 15000,
            "key_personnel": [
                {
                    "name": "Ing Folke Blomqvist",
                    "position": "Styrelseordf"
                },
                {
                    "name": "Ing Folke Blomqvist",
                    "position": "Verkst dir"
                }
            ],
            "establishment_year": 1959,
            "namnändring": 1968
        },
        "3": {
            "company_name": "BLOMQVISTS VERKSTADS AB",
            "address": "Södertälje 2, Skepparev. Box 2036.",
            "phone_number": "0755-32970",
            "bank_details": {
                "bankgiro": "622-5585",
                "postgiro": "161780-2"
            },
            "activity": "Tillverkar o säljer bänksvarvar samt glasfibertankar för oljor, avlopp o vatten",
            "annual_production_value": "Varunamn: Blomqvist",
            "capital": 50000,
            "establishment_year": 1896
        },
        "4": {
            "company_name": "BLOMKVIST METALLFABRIK, ARTUR",
            "address": "Eskilstuna, Bergsg 34.",
            "phone_number": "016-1315 49",
            "bank_details": {
                "postgiro": "72331-2"
            },
            "key_personnel": [
                {
                    "name": "Artur Blomkvist",
                    "position": "Chef"
                }
            ],
            "establishment_year": 1921
        },
        "5": {
            "company_name": "malå säg & hyvleri, ab",
            "address": "Malå. Storg.",
            "phone_number": "0953-107 70",
            "bank_details": {
                "bankgiro": "76-6218",
                "postgiro": "326296-1"
            },
            "activity": "Sågade o hyvlade trävaror. Tillverkar färdigkapat virke för hustillverkning, behandlad list o panel 'Malåpanelen'",
            "employees": 45,
            "annual_turnover": 5500000,
            "capital": 50000,
            "key_personnel": [
                {
                    "name": "Evald Eriksson",
                    "position": "Verkst dir"
                },
                {
                    "name": "Disp Allan Eriksson",
                    "position": "Försäljn-chef"
                }
            ],
            "establishment_year": 1946
        },
        "6": {
            "company_name": "I TO EXPORT & IMPORT AB",
            "address": "Göteborg 11, Box 11032. O Hamng 19 A.",
            "phone_number": "031-17 48 40",
            "bank_details": {
                "bankgiro": "508-8398",
                "postgiro": "526257-1"
            },
            "activity": "Säljer radio, TV, bandspelare, stereo o elektroniska artiklar. Generalagent för Sanyo Electric Co, Osaka, Japan",
            "employees": 8,
            "annual_turnover": 8400000,
            "capital": 50000,
            "key_personnel": [
                {
                    "name": "Erwin SUssman",
                    "position": "Verkst din"
                },
                {
                    "name": "Selfrid Ohlund",
                    "position": "Försäljn-dir"
                }
            ],
            "establishment_year": 1960
        },
        "7": {
            "company_name": "WEDDE & CO AB",
            "address": "Älvdalen.",
            "phone_number": "0251-520 13",
            "bank_details": {
                "bankgiro": "472-0363",
                "postgiro": "342400-9"
            },
            "activity": "Tillverkar sågade o hyvlade trävaror",
            "employees": 25,
            "annual_turnover": 5000000,
            "capital": 40000,
            "key_personnel": [
                {
                    "name": "P J Wedde",
                    "position": "Verkst dir"
                }
            ],
            "establishment_year": 1949
        },
        "8": {
            "company_name": "ekholms byggnadsvaror",
            "address": "Örebro, Trädgårdsg 15.",
            "phone_number": "019-119155",
            "bank_details": {
                "bankgiro": "815-4312",
                "postgiro": "76473-8"
            },
            "activity": "Säljer byggnadsvaror samt uthyr presenningar",
            "key_personnel": [
                {
                    "name": "G Ekholm",
                    "position": "Chef"
                }
            ],
            "establishment_year": 1930
        },
        "9": {
            "company_name": "SVENSK FILMINDUSTRI, AB",
            "address": "Stockholm 1, Kungsg 36. Pack.",
            "phone_number": "08-22 14 00",
            "bank_details": {
                "bankgiro": "562-9670",
                "postgiro": "630-4"
            },
            "activity": "Producerar film på 'Filmstaden' i Solna",
            "employees": 725,
            "annual_turnover": 49000000,
            "capital": 12000000,
            "key_personnel": [
                {
                    "name": "C H Fant",
                    "position": "Verkst dir"
                }
            ],
            "establishment_year": 1919
        }
    }
}