{
    "original": "SMITH AB, AND\n\nPnr 103 82\n\nStockholm 7, Strandv 5 B. Box\n7093. Tel 08-67 92 70. Bankgiro\n732-0450. Postgiro 255035-8. Tga\nCoalsmith, Oilsmith. Telex 19396\nVerksamhet: Importerar o säljer\neldningsoljor, kol o koks en gros\nAntal anstäUda: 5\nAktiekapital: 100 000\nVerkst dir: Anders Smith\nEtableringsår: 1908.\n\nSMITH STENUNGSUND\nAB, AND\n\nPnr 444 00\n\nStenungsund, Box 75. Tel\n0303-709 78. Postgiro 414600-7\nVerksamhet: Säljer\npetroleumprodukter\n\nÅrsomsättning: 230 000\nAktiekapital: 5 000\nStyrelseordf: Dir Bertil Johannisson\nPlatschef: Rolf Andersson\nEtableringsår: 1961\nDotterbolag till And Smith\nUddevalla AB, Uddevalla.\n\nSMITH UDDEVALLA AB, AND\n\nPnr 45101\n\nUddevalla 1, Kungsg 15. Box 13.\nTel 0522-143 10. Bankgiro\n428-0368. Postgiro 99999-5. Tga Smith\nVerksamhet: Import av stenkol,\nkoks o petroleumprodukter\nAntal anställda: 44\nÅrsomsättning: 17 500 000\nAktiekapital: 375 000\nVerkst dir: Bertil Johannisson\nEtableringsår: 1908\nOmbildat till aktiebolag 1938.\nDotterbolag: Sjöström &amp; Co\nVänersborg AB, Vänersborg, And Smith\nStenungsund AB, Stenungsund.\n\nSMITH, AB OLOF\n\nPnr 402 71\n\nGöteborg 8, Rundbäcksg 2. Box\n8839. Tel 031-51 87 58, 51 87 56.\nBankgiro 84-8323. Postgiro 240673.\nTga Abosmith.\nTelex 20951 SMITH S\nVerksamhet: Maskiner för\nbleckem-ballagetill verkning\nAntal anställda: 20\nAktiekapital: 450 000\nVerkst dir: Fru Margareta Smith\nEtableringsår: 1945.\n\nTILLING AB, BRÖDERNA\n\nPnr 11136\n\nStockholm, Holländarg 11. Tel\n08-1100 00\n\nVerksamhet: Gummimattor o-slang,\ntekn gummiartiklar m m i parti\nAktiekapital: 75 000\nVerkst dir. L O Tilling\nEtableringsår 1946\nOmbildat till aktiebolag 1951.\n\nTILLQUIST, INGENIORS.\nFIRMA HUGO\n\nPnr 17103\n\nSolna 3. S Lår«g 21. Box 303. Tel\n08-83 0100. Telex 10138. Tga\nConduit\n\nVerksamhet: Instrument o\napparatur för vetenskap o industri\nAntal anställda: 150\nÅrsomsättning: 30 000 000\nVerkst dir Gunnar Linde-Olsson\nEtableringsår 1895.\n\nBYGGLEDNING\n\nPnr 65220\n\nKarlstad, Attkantsg 11. Tel\n054-18 16 60, 18 18 60. Bankgiro\n603-8830. Postgiro 444611-8\nVerksamhet: Allmän\nbyggnadsteknisk konsultverksamhet såsom\nbyggbesiktningar, byggledning,\nbyggkontroll, utredningar o\nvärderingar av byggnadsskador,\nutredningar o lösningar av tvister.\nSpecialitet: för- o\nefterbesikt-rungar av fastigheter vid\nmarkstörande arbeten samt i samband\nhärmed skadevärdering o\nskaderegle-ring\n\nAntal anställda: 6\nÅrsomsättning: 500 000\nChef: Civiling SVR Lars Zachrison\nBy ggn-kontrollanter: Ing Bertil\nGrahn, ing Axel Lundberg, ing\nIwan Olsson\nEtableringsår: 1959.\n\nBYGGMAN,\nMASKINAKTIEBOLAGET\n\nPnr 161 26\n\nBromma 1, Box 116. Bällstav 161.\nTel 08-87 04 70. Bankgiro 743-5449.\nPostgiro 58 765-9\n\nVerksamhet: Tillverkar\nstålkonstruktioner, formar för\nbetongelement-tillverkning, lyft- o\ntransportutrustning mm samt inredningssnickerier\nför kontor, butiker, banker o labo\nratorier. Säljer, uthyr, monterar o\nreparerar byggnadsmaskiner\nFilial: Södertälje. Tel 0755-13 001\nSnickeriverkstad: Bromma,\nMarie-häll. Tel 08-87 04 70, 29 63 24\nÅrsomsättning: 9 000 000\nAktiekapital: 350 000\nVerkst dir: Civiling Lennart Montén\nEtableringsår 1953.\n\nBYGGMATERIAL I\nKARLSTAD AB\n\nPnr 65104\n\nKarlstad 1, Box 142. Tel\n054-1190 60, 1190 61. Bankgiro\n881-3461. Postgiro 130974-9\nVerksamhet: Säljer fönster-,\ndörr-o kökssnickerier\n\nÅrsomsättning: 2 200 000\nAktiekapital: 50000\nVerkst dir. Lars Adelson\nEtableringsår: 1937.\n\nULVANDER, GUNNAR\n\nPnr 18104\n\nLidingö 4, Oskarsv 64. Fack. Tel\n08-76583 17. Bankgiro 74-3154.\nPostgiro 154535. Tga Ulvur\nVerksamhet: Engrosförsäljning av ur\nÅrsomsättning: 300 000\nÄgare o chef: Gunnar Ulvander\nEtableringsår: 1938.\n\nSTÅ\n\nExportchef: David Isakson\nEtableringsår: 1876\nOmbildat till aktiebolag 1923.\n\nSTÅHLS\nMÖBELFABRIKS AB, AXEL\n\nPnr 598 00\n\nVimmerby. Tel 0492-126 20\nVerksamhet: Tillverkar byggbara\nbokhyllor \"Polyform\"\nAntal anställda: 25\nÅrsomsättning: 2 500 000\nAktiekapital: 103 400\nVerkst dir: Nils Ståhl\nEtableringsår: 1902.\n\nSTÅHL, BYGGNADS AB\nHENRY\n\nPnr 60102\n\nNorrköping 1, Box 31. Tel\n011-1309 15, 133085\nVerksamhet: Uppför bostads-,\naffärs- o industribyggnader\nÅrsomsättning: 40 000 000\nAktiekapital: 75 000\nVerkst din Henry Ståhl\nEtableringsår. 1942.\n\nLUNDBERGS PLÅT AB\n\nPnr 55102\n\nJönköping 1, Fridhemsv 29. Box\n162. Tel 036-119 3 30. Bankgiro\n835-7832. Postgiro 140572-9\nVerksamhet: Tillverkar\ntunnplåtsarbeten i rostfritt o järn, rostfria\nspecialarbeten, imkåpor, grytdiskar,\nservisgodsvagnar,\nstorköksinredningar o reparationer\nAntal anställda: 28\nÅrsomsättning: 2 500 000\nAktiekapital: 300 000\nVerkst dir: Fabr Nils Erie\nLundberg\n\nEtableringsår: 1869.\n\nLUNDBERGS REVISIONS.\nBYRÄ AB, ERIK\n\nPnr 400 24\n\nGöteborg 35, Prästgårdsängen 13.\nBox 35030. Tel 031-40 49 75,\n4049 85. Bankgiro 420-5407.\nPostgiro 47268-8\n\nVerksamhet: Revisionsbyrå\nAntal anställda: 5\nAktiekapital: 35 000\nChef: Aukt revisor ETik Lundberg\nEtableringsår: 1912.\n\nEDM\n\nEDMÅ, METALLFABRIKEN\n\nPnr 33100\n\nVärnamo, Jönköpingsv. Tel\n0370-102 85\n\nVerksamhet: utför pressning o\npunktsvetsning av massartiklar i\ntråd o band. Prydnadsartiklar i\nsmide. Utför legoarbeten samt\nrull-gängning\n\nÄgare o chefer: K E P Mårtensson,\nG A E Nilsson\nEtableringsår: 1941.\n\nde JONG, AB A M\n\nPnr 162 10\n\nVällingby 1, Krossg 22. Fack. Tel\n08-38 02 65. Tga Dejong\nVerksamhet: Byggnadsbeslag i parti\nAntal anställda: 24\nAktiekapital: 350 000\nVerkst dir: A M de Jong\nEtableringsår: 1924.\n\nJONO AB SVETS &amp;\nPLÅTSLAGERI\n\nPnr 86035\n\nSötåker. Tel 060-40688, 41088.\nBankgiro 184-2202. Postgiro\n590897-5\n\nVerksamhet: Utför\njärnkonstruktioner, grovplåtslageriarbeten,\nmaskinarbeten, rostfria arbeten,\nirdustrimonteringar, syrafast\nrör-montering samt licenssvetsning\n(2343 o 1330) omfattande\nkonstruktions- o tryckkärlsstål samt\nrostfritt\n\nAntal anställda: 45\nVerkst dir: Alf Johansson\nÖvrig chef: Fabr Birger Norberg\nEtableringsår: 1961.\n\nJOHNSEN, AB VILHELM\n\nPnr 103 62\n\nStockholm 3, Tunnelg 14. Box 3131.\nTel 08-23 73 90. Bankgiro 722-1534.\nPostgiro 2320-8. Tga Gerty.\nTelex 1423\n\nVerksamhet: Säljer maskiner,\nutensilier o förbrukningsartiklar till\nden grafiska industrin\nAvdelningskontor: Göteborg V,\nBetzensg 4. Tel 031-42 01 20\nMalmö V, Tessins v 2. Tel\n040-745 10\n\nAntal anställda: 83\nÅrsomsättning: 26 000 000\nAktiekapital: 1400 000\nStyrelse: Adv Gösta Åkerlund\n(ordf), dir Peter Johnsen, disp\nHarry Widestam, kamrer Bertil\nösterlind\n\nVerkst dir: Peter Johnsen\nEtableringsår: 1894\nOmbildat till aktiebolag 1929.\n\nJONSEREDS FABRIKERS AB\n\nPnr 430 71\n\nJonsered. Tel 031-72 03 00.\nBankgiro 500-1649. Postgiro 10300-2.\nTga Jonsereds, Göteborg.\nTelex 2425, 21212\nVerksamhet: Tillverkar linne- o\nbomullsvaror, träbearbetningsma^\nskiner, motorsågar, kranar,\nlagerhallar o kapell\n\nGjuteriet: Falkenberg, Hamnv 15.\nTel 0346-100 29\n\nMotorsågsfabriken: Brastad. Tel\n0523-404 60\n\nPresenningsfabriken: Brastad. Tel\n0523-401 21, 409 00\n\nDistriktskontor: 41707 Göteborg.\nJonsereds Presenningsuthyrning.\nTackjärnsg 2. Tel 031-23 51 25.\nPostgiro 42456-4. Tga Godsskydd.\nAvdelningschef: Thure Gillgren\n211 24 Malmö. Jonsereds\nPresenningsuthyrning, Blidög 28. Tel\n040-93 43 60. Postgiro 147524-3. Tga\nGodsskydd. Avdelningschef: Erik\nBennrup\n\n602 23 Norrköping. Jonsereds\nPresenningsuthyrning, Linnég 21. Tel\n011-16 23 00. Postgiro 176364-8.\nTga Godsskydd. Avdelningschef:\nLars Cronehall\n\n161 07 Stockholm. Jonsereds\nPresenningsuthyrning, Tornväktargränd\n1 (vid Bällstavägen), Bromma. Tel\n08-87 0140. Postgiro 58222-1. Tga\nGodsskydd. Avdelningschef: N G\nKristiansson\n\n852 43 Sundsvall. Jonsereds\nPresenningsuthyrning, Hovg 1. Tel\n060-15 42 50. Postgiro 137593-0.\nTga Godsskydd. Avdelningschef:\nKjell Englén\n\n660 52 Edsvalla, Edsvalla Bruk.\nTel 054-441 61\n\nVarunamn: Jonsereds, Raket\nAntal anställda: 1200\nÅrsomsättning: 125 000 000\nAktiekapital: 24 000 000\nStyrelse: Dir Folke Lindskog (ordf),\ndisp Erie Brodén, dir Gunnar\nGibson, dir Ivar Lindquist, bergsing\nL Nordenfelt\n\nVerkst dir: Disp Erie Brodén\nEtableringsår: 1833.\n\nJONSSON, JONSON, JOHNSON,\nJOHNSSON\n\nJOHNSON CONSTRUCTION\nCOMPANY AB\n\nPnr 100 72\n\nStockholm 43, Liljeholmsv 32. Box\n43051. Tel 08-68 01 90. Bankgiro\n168-9041. Postgiro 657279-6.\nTga Johnsonstruct. Telex 17689\nVerksamhet: B ygg nadse ntreprenåder\nför husbyggnads-, väg- o\nvattenbyggnadsarbeten i utlandet.\nLeverans av kompletta\nindustrianläggningar, avloppsreningsverk o\nsopförbränningsanläggningar i såväl\nSverige som utlandet\nProjektstudier, mekaniska o\nbyggnadstekniska konstruktionsarbeten,\nupphandling, platsledning, kontroll,\nprojektledning o planering\nProjekterar o levererar utrustningar\nför behandling av renvatten o\navloppsvatten, värmeväxlare o\nvärme-återvinningsapparater samt luft- o\ngasförvärmare\n\nVarunamn: Inka, Herkulespålar\nAntal anställda: 100\nAktiekapital: 1500 000\nStyrelse: Dir Sture Westby (ordf),\ndir Curt Nilsson, dir Ake Hallgren\nVerkst dir: Ake Hallgren\nEtableringsår: 1962.\n\nJOHNSSONS KORKFABRIK, AB\n\nPnr 245 00\n\nStaffanstorp, Djurslöv 308. Tel\n040-44 5290, 44 5096. Bankgiro\n264-2270. Postgiro 14135\nVerksamhet: Tillverkar allt inom\nbranschen såsom buteljkork,\naluminiumkapsyler, korksmul etc.\nSäljer korkisolering, korkparkett,\nkorkgummi o presskork\nAktiekapital: 140 000\nStyrelse: Disp Sven J Malmström\n(ordf), disp Bengt Malmström,\nkamrer Hans Malmström, fru\nGertrud Malmström, disp Olof\nMalmström, fru Hanna Sölberg, ing Knut\nÖsterberg ’\n\nVerkst dir. Disp Bengt Malmström\nEtableringsår: 1879\nOmbildat till aktiebolag 1936.\n\nJONSSONS\nLEDSTÅNGSFABRIK AB\n\nPnr 574 01\n\nVetlanda 1, Industrig 30. Box 24.\nTel 0383-101 24\n\nVerksamhet: Tillverkar ledstänger\no öv er liggare av trä o plast\nAktiekapital: 25 000\nVerkst dir: Bertil Petersson\nEtableringsår: 1963.\n\nEKONOMISYSTEM\n\nPnr 70106\n\nÖrebro 1, Bromsg 8. Box 491. Tel\n019-1236 77. Bankgiro 815-7091.\nPostgiro 367317-5\nVeiksamhet: Blankettförlag.\nUtarbetar o säljer systemblanketter\nChef: John Hedblom\nEtableringsår: 1947.",
    "structured": {
        "firms": [
            {
                "company_name": "SMITH AB",
                "activity": "Importerar o säljer eldningsoljor, kol o koks en gros",
                "establishment_year": 1908,
                "employees": 5,
                "capital": 100000,
                "key_personnel": [
                    {
                        "name": "Anders Smith",
                        "position": "Verkst dir"
                    }
                ]
            },
            {
                "company_name": "SMITH STENUNGSUND AB",
                "activity": "Säljer petroleumprodukter",
                "establishment_year": 1961,
                "annual_turnover": 230000,
                "capital": 5000,
                "key_personnel": [
                    {
                        "name": "Bertil Johannisson",
                        "position": "Styrelseordf"
                    },
                    {
                        "name": "Rolf Andersson",
                        "position": "Platschef"
                    }
                ]
            },
            {
                "company_name": "SMITH UDDEVALLA AB",
                "activity": "Import av stenkol, koks o petroleumprodukter",
                "establishment_year": 1908,
                "annual_turnover": 17500000,
                "capital": 375000,
                "key_personnel": [
                    {
                        "name": "Bertil Johannisson",
                        "position": "Verkst dir"
                    }
                ]
            },
            {
                "company_name": "SMITH, AB OLOF",
                "activity": "Maskiner för bleckem-ballagetill verkning",
                "establishment_year": 1945,
                "employees": 20,
                "capital": 450000,
                "key_personnel": [
                    {
                        "name": "Fru Margareta Smith",
                        "position": "Verkst dir"
                    }
                ]
            },
            {
                "company_name": "TILLING AB, BRÖDERNA",
                "activity": "Gummimattor o-slang, tekn gummiartiklar m m i parti",
                "establishment_year": 1946,
                "capital": 75000,
                "key_personnel": [
                    {
                        "name": "L O Tilling",
                        "position": "Verkst dir"
                    }
                ]
            },
            {
                "company_name": "TILLQUIST, INGENIORS. FIRMA HUGO",
                "activity": "Instrument o apparatur för vetenskap o industri",
                "establishment_year": 1895,
                "employees": 150,
                "annual_turnover": 30000000,
                "key_personnel": [
                    {
                        "name": "Gunnar Linde-Olsson",
                        "position": "Verkst dir"
                    }
                ]
            },
            {
                "company_name": "BYGGLEDNING",
                "activity": "Allmän byggnadsteknisk konsultverksamhet såsom byggbesiktningar, byggledning, byggkontroll, utredningar o värderingar av byggnadsskador, utredningar o lösningar av tvister. Specialitet: för- o efterbesikt-rungar av fastigheter vid markstörande arbeten samt i samband härmed skadevärdering o skaderegle-ring",
                "establishment_year": 1959,
                "employees": 6,
                "annual_turnover": 500000,
                "key_personnel": [
                    {
                        "name": "Civiling SVR Lars Zachrison",
                        "position": "Chef"
                    }
                ]
            },
            {
                "company_name": "BYGGMAN, MASKINAKTIEBOLAGET",
                "activity": "Tillverkar stålkonstruktioner, formar för betongelement-tillverkning, lyft- o transportutrustning mm samt inredningssnickerier för kontor, butiker, banker o labo ratorier. Säljer, uthyr, monterar o repararerar byggnadsmaskiner",
                "establishment_year": 1953,
                "annual_turnover": 9000000,
                "capital": 350000,
                "key_personnel": [
                    {
                        "name": "Civiling Lennart Montén",
                        "position": "Verkst dir"
                    }
                ]
            },
            {
                "company_name": "BYGGMATERIAL I KARLSTAD AB",
                "activity": "Säljer fönster-, dörr-o kökssnickerier",
                "establishment_year": 1937,
                "annual_turnover": 2200000,
                "capital": 50000,
                "key_personnel": [
                    {
                        "name": "Lars Adelson",
                        "position": "Verkst dir"
                    }
                ]
            },
            {
                "company_name": "ULVANDER, GUNNAR",
                "activity": "Engrosförsäljning av ur",
                "establishment_year": 1938,
                "annual_turnover": 300000,
                "key_personnel": [
                    {
                        "name": "Gunnar Ulvander",
                        "position": "Ägare o chef"
                    }
                ]
            }
        ]
    }
}