{
    "original": "TIBRO STOLFABRIK, AB\n\nPnr 543 01\n\nTibro 1, Grönhultsv. Box 194. Tel\n0504-114 8 5. Bankgiro 22-1310.\nPostgiro 519207\n\nVerksamhet: Tillverkar stilstolar\nAntal anställda: 18\nÅrsomsättning: 1 100 000\nAktiekapital: 100 000\nÄgare: Fabr Egron Hugosson, fabr\nSixten Johansson\nEtableringsår: 1959.\n\nKOL\n\nIntendent: Erik Berg\nEtableringsår: 1851\nBolag: 1875.\n\nKOCKUMS MEKANISKA\nVERKSTADS AB\n\nPnr 20110\n\nMalmö l, Stora Varvsg. Pack. Tel\n040-744 20, 744 00. Bankgiro\n640-1061. Postgiro 38200-2. Tga\nKockumverkstad.\nTelex 3189 KOCKUM S\nVerksamhet: Moderbolag i\nKockumgruppen, vilken bedriver mekanisk\ntillverkning på fyra huvudlinjer:\nSkeppsbyggeri, fartygsreparationer\no fartygstillbehör (Malmö o\nHälsingborg), jordförflyttningsmaskiner\n(Landskrona), transportutrustningar\no containers (Falkenberg), maskiner\no fordon för skogsindustrin\n(Söderhamn o Filipstad)\nProdukter: (moderbolag) Fartyg\nupp till 700 000 tons dw\ndieselmotorer o turbinanläggningar för\nfartyg, akustiska signalapparater,\nelektroniska o optiska\nlastfördel-ningsinstrument, elektroniska\nförbränningskontroller etc\nVarunamn: Electro-Tyfon,\nLoadmas-ter Computer, Optical Trim\nLoa-der, Supertyfon, Tyfon\nAntal anställda: 5 000\nÅrsomsättning: 850 000 000\n(koncernen)\n\nAktiekapital: 100 000 000\nStyrelse: Bankir L-E Thunholm\n(ordf), greve lan Hamilton, dir\nEinar Hansen, disp Jan Herslow,\ndir Thorolf Hjort, dir Nils\nHolmström (v ordf), dir Bernt-Erik\nKockum, dir Gunnar Kockum, dir\nElam Tunhammar, dir Anders Wall\nVerkst dir: Nils-Hugo Hallenborg\nV verkst dir:r: Olafur Sigurdsson,\nHans-Erik Ovin, Gunnar Kockum\nTekn dir: Olafur Sigurdsson\nÖvriga chefer: Försäljning\n(fartyg) dir K G Råwall, inköp S\nEricsson, konstruktion (fartyg) dir S\nBergman, administration dir Fred\nGärdsmo, ekonomidir Chr\nChristiansson\n\nEtableringsår: 1840\nProducerande dotterbolag i Sverige:\nAB Kockum Landsverk,\nLandskrona, Kockum Interconsult AB,\nFalkenberg, Kockum Söderhamn AB,\nSöderhamn, Kockums Filipstad AB,\nFilipstad, Helsingborgs Varfs AB,\nHälsingborg, Kockum Rosengren\nAB, Malmö.\n\nKOCKUM ROSENGREN AB\n\nPnr 20110\n\nMalmö 1, Fack. Stora Varvsg. Tel\n040-702 80. Kockumsverkstad.\nTelex 3189 KOCKUM S\nVerksamhet: Tillverkar o monterar\nprefabricerade småhusskorstenar i\nplåt, mekaniska frånluftsystem,\nöppna spisar\nAntal anställda: 75\nÅrsomsättning: 10 000 000\nAktiekapital: 50 000\nVerkst dir: Jan Rosenberg\nEtableringsår: 1908\nOmbildat till aktiebolag 1963.\nNamnändring 1969.\n\nKOCKUM SÖDERHAMN AB\n\nPnr 82601\n\nSöderhamn 1, Fack. Tel\n0270-100 10. Bankgiro 61-2686. Postgiro\n174200. Tga Sverk. Telex 81025\nVeiksamhet: Sågverksutrustningar,\nbarkningsmaskiner, skogstraktorer\nFörsäljningskontor: 652 21 Karlstad,\nSågverksg 12. Tel 054-18 02 40\n852 53 Sundsvall. AB Kockum\nLandsverk, Ortviksv 1. Tel 060-15 00 80\n421 31 Västra Frölunda. AB Kockum\nLands verk, Frökotteg 11. Tel\n031-49 00 50\n\n352 36 Växiö. AB Kockum\nLandsverk, Industrig 2. Tel 0470-260 70\n891 01 Örnsköldsvik 1, Box 2. Tel\n0660-103 80\nAntal anställda: 450\nÅrsomsättning: 105 000 000\nAktiekapital: 5 000 000\nStyrelse: Dir Nils-Hugo Hallenborg\n(ordf), dir Gunnar Kockum, dir Kjell\nHåkansson\n\nVerkst dir: Kjell Håkansson\nFörsäljn-chef: Floyd Werner\nEkonomichef: Bengt Olofsson\nAdministrativ chef: Nils Lood\nKonstr-chef: Heimer Eriksson’\nProd-chef: Thure Sundberg\nEtableringsår: 1864\nIngår i Kockum-gruppen.\n\nKOCKUM-LANDSVERK, AB\n\nPnr 261 20\n\nLandskrona 1, Industrig. Fack. Tel\n0418-770 00. Bankgiro 660-0621.\nPostgiro 23222-3. Tga Landsverk.\nTelex 72285\n\nVerksamhet: Mekanisk verkstad.\nTillverkar entreprenadmaskiner\nFörsäljningskontor: Växjö. Tel\n0470-260 70\n\nGöteborg. Tel 031-49 00 50\nJakobsberg. Tel 0758-103 00\nSundsvall. Tel 060-15 00 80\nAntal anställda: 900\nÅrsomsättning: 140 000 000\nAktiekapital: 23 000 000\nStyrelse: Dir Nils-Hugo Hallenborg\n(ordf), dir Gunnar Kockum, dir\nCarl-Erik Andersson\nVerkst dir: Carl-Erik Andersson\nEtableringsår: 1873\nFöretaget ägs av Kockums\nMekaniska Verkstads AB.\n\nKOCOVERK, KNUT OLSSON &amp;\nCO VERKSTADER AB\n\nPnr 19121\n\nSollentuna, Engelbrektsv 3. Tel\n08-35 40 00, 35 26 60. Tga Knutolsco\nVerksamhet: Tillverkar\nbyggnadsmaskiner o varmluftsapparater samt\nutför metallfasader o\nbyggnads-plåtslageriarbeten\nÅrsomsättning: 10 000 000\nAktiekapital: 200 000\nVerkst dir: Knut Olsson\nEtableringsår: 1920.\n\nFREJ, HANDELS AB\n\nPnr 114 51\n\nStockholm, Artillerig 22. Tel\n08-60 22 13, 67 78 13. Bankgiro\n26-9140. Postgiro 52449\nVerksamhet: Innehav o förvaltning\nav fastigheter\nAktiekapital: 150 000\nVerkst dir: Valdemar Dyme\nEtableringsår: 1953.\n\nPERFOVERKEN, AB\n\nPnr 542 01\n\nMariestad 1, Box 74. Hantverkareg\n7. Tel 0501-165 70. Bankgiro\n819-0050. Postgiro 20858-7\nVerksamhet: Perforering av plåt\nsamt tillverkning av profiler\nAntal anställda: 50\nÅrsomsättning: 5 000 000\nAktiekapital: 25 000\nVerkst dir: Uno Widström\nEtableringsår: 1961.\n\nPOSTO, AB\n\nPnr 28603\n\nOrkelljunga 3, Eket. Box 3042. Tel\n0435-533 75. Bankgiro 672-6053.\nPostgiro 390973-6. Tga Posto, Eket\nVerksamhet: Utför\nautomatsvarv-ning med upp till 48 mm 0\nmaterialgenomgång, revolversvarvning,\ncen-terlesslipning o borrarbeten,\ntillverkar manuella o elektriska\nbrevöppnare\n\nAntal anställda: 70\n\nÅrsomsättning: 4 500 000\n\nAktiekapital: 50 000\n\nStyrelse: Ing Gunnar Agrell (ordf),\n\ning Göran Sandberg\n\nVerkst dir. Ing Göran Sandberg\n\nEtableringsår 1949.\n\nWALLNAS AB\n\nPnr 570 31\n\nIngatorp. Tel 0496-500 11, 500 28.\nBankgiro 45-0908. Postgiro 6339.\nTga Wallnäsbolaget\nVerksamhet: Tillverkar sågade o\nhyvlade trävaror, stolpar o massa ved\nAntal anställda: 58\nÅrsomsättning: 5 500 000\n\nAktiekapital: 1800 000\nVerkst dir. Sven Fagerholm\nEtableringsår: 1896.\n\nWALLÄKRA STEN KARLS.\nFABRIK\n\nPnr 260 30\n\nVallåkra. Tel 042-990 31. Tga\nWallåkra\n\nVerksamhet: Tillverkar unika\nvaser o urnor i stengods, från\nminiatyrvaser upp till golvvaser\nVarunamn: Wallåkra\nAntal anställda: 4\nÄgare o chefer: Stig B Andersson,\nArthur W Andersson\nEtableringsår: 1864.\n\nOLSSONS BIL AB, BRÖDERNA\n\nPnr 285 01\n\nMarkaryd 1, Västerg 11. Box 45.\nTel0433-112 40. Bankgiro 279-5409.\nPostgiro 137423-0\nVerksamhet: G M återförsäljare o\nservice. Biluthyrning\nAntal anställda: 29\nÅrsomsättning: 6 000 000\n\nAktiekapital: 65 000\nVeikst dir: Erik Olsson\nDisp: Kjell Olsson\nEtableringsår: 1906.\n\nESKILSTUNA GALVAN AB\n\nPnr 630 05\n\nEskilstuna 5, Box 5052. Fräsarg 5.\nTel 016-13 75 20. Bankgiro\n601-5747. Postgiro 448760-9\nVerksamhet: utför varmförzlnkning,\nel-förzinkning. sprutförzinkning,\nrostskyddsmålning o sandblästring\nDotterbolag: Motala. Motala\nGalvan, Smedsby. Tel 0141-148 92\nEskilstuna. Industri-Crom, Fräsarg\n5. Tel 016-13 75 20\nAntal anstäUda: 25\nAktiekapital: 100 000\nStyrelse: Dir Gustaf Johansson\n(ordf), dir Arne Johansson, fabr\nLars Johansson\nVerkst dir: Arne Johansson\nEtableringsår: 1954\nOmbildat tül aktiebolag 1964.\n\nESKILSTUNA GJUTERI AB\n\nPnr 632 21\n\nEskilstuna, Björksg 4. Tel\n016-13 1049, 13 84 49. Bankgiro\n60-1441. Postgiro 10792-0\nVerksamhet: Tillverkar handformat\ngjutgods upp till 5 tons styckevikt\nsamt maskinformat smågods\nAktiekapital: 150 000\nVerkst dir: Hugo Andersson\nEtableringsår. 1911.\n\nROS\n\nFilialfabrik: Kristianstad. Tel\n044-12 32 70. Telex 4437. Tillverkar\nblankettkarbon o telexrullar.\nPlatschef: disp Bo Malmquist\nAktiekapital: 425 000\nStyrelse: Dir: Stig Allsing, dir Olof\nOgren, disp Per Wenander, Mr\nKenneth Goldie, disp Lars de Geer,\ndir Rune Nilsson\nVerkst din Disp Per Wenander\nEtableringsàr: 1855\nOmbildat till aktiebolag 1930.\n\nROSENDALS\nKONFEKTIONS AB\n\nPnr 510 90\n\nLimmared. Tel 0325-713 00.\nBankgiro 55-3121. Postgiro 269661\nVerksamhet: Tillverkar barnkläder\nAntal anställda: 100\nÅrsomsättning: 5 000 000\nAktiekapital: 150 000\nVeikst din Torsten Ombert\nEtableringsàr: 1944.\n\nROSENDALS MÖBELFABRIK\nAB\n\nPnr 360 40\n\nRottne, Löpanäsv 19. Tel\n0470-910 26, 913 26. Bankgiro 66-8284.\nPostgiro 224342\n\nVerksamhet: Tillverkar bord o\nbokhyllor\n\nAntal anställda: 22\nÅrsomsättning: 1200 000\nAktiekapital: 25 000\nVerkst dir: Kjell Johansson\nEtableringsàr: 1959.\n\nROSENFORS BRUK, AB\n\nPnr 570 82\n\nMålilla. Tel 0495-208 20.\nPostgiro 8992. Tga Toolbruk.\nTelex 3931\n\n\n\nVerksamhet: Mek verkstad i\nRosen-fors (Kalmar’). Tillverkar\nverktygsmaskiner såsom fräsmaskiner jämte\ntillbehör samt vävmaskiner för\nwiror, ylle, bomulls- o plastfilt\nVarunamn: Rosenfors\nAntal anställda: 110\nÅrsomsättning: 6 200 000\nAktiekapital: 100 000\nStyrelse: Konsul Tryggve Holm\n(ordf), adv Sten Lindskog, bankdir\nSigvard Nylén, dir Gösta Rehnquist\nVerkst din Bruksdisp Lennart\nTorstenson\n\nTekn dir: Nils Olov Engström\nPlatschef: Overing Fritz Svensson\nKamrer: Hans Löthstam\nBruket äges av Gusums Bruk AB,\nGusum.\n\nROSENGRENS\nBLECK-SLAGERI AB\n\nPnr 200 32\n\nMalmö 18, Volframg 3. Box 18028.\nTel 040-94 65 80. Postgiro\n432364-8\n\nVerksamhet: Byggnadsplåtslageri,\nventilationsarbeten samt\nbeställningsarbeten i rostfritt\n\nAntal anställda: 70\nVerkst dir: Stig Lundin\nEtableringsàr: 1908.\n\nROSENGRENS SYFABRIK\n\nPnr 50108\n\nBorås 1, Box 522. Lidaholmsg 3.\nTel 033-12 78 25. Bankgiro\n839-2599. Postgiro 24894-8\nVerksamhet: Tillverkar o säljer\nherrskjortor, damskjortblusar,\nskjortblusklänningar, lättare\nkavajer, herr- o dambyxor samt\nspeciella plagg för yrkeskategorier\nAntal anställda: 80\nÅrsomsättning: 3 500 000\nÄgare o chef: Fabr Erie Rosengren\nFörsäljning: Disp Lennart\nRosengren\n\nProduktion: Fabrikschef Sven\n\nRosengren\n\nEtableringsàr: 1947.\n\nROSENGRENS AB, EA\n\nPnr 59101\n\nHuvudkonton Motala 1, Box 66. Tel\n0141-163 60. Tga Earosengrens.\nTelex 5580 EARMTLA S\nVerksamhet: Specialitet: möbler\nför kontor o offentlig miljö,\nbankirredningar, värde valvdörrar,\nvärdeskåp, dokumentskåp\nFabrik för tillverkning av\nkontorsmöbler i Motala. Motalaverken. Tel\n0141-163 60. Tga Earosengrens\nFabrik för bankartiklar, dokument-,\nvärdeskåp etc i Malung.\nMalungverken. Fack 116. Tel 0280-118 50.\nTga Norema. Telex7732 EARMLG S\nFörsäljningskontor: 591 01 Motala 1,\nBox 66. Tel 0141-163 60\n11140 Stockholm, Döbelnsg 21. Tel\n290280\n\nSundbyberg. Karlsbodav 25, pa\n16170 Bromma. Tel 08-29 02 80.\nTelex 1896 EARSTH S\n\n402 70 Göteborg 8, Fack. Tel\n031-52 02 20\n\n21225 Malmö, Krusegränd 42 E.\nTel 040-18 10 50\n\n852 44 Sundsvall, Kyrkog 4. Tel\n060-15 41 40\n\nDotterbolag: E A Rosengrens A/S,\nLerstf Parkallé 112, Köpenhamn.\nTel 0012-29 65 00\nE A Rosengrens A/S, Økernv 9,\nOslo. Tel 02-67 35 92\nE A Rosengrens GmbH, Parkstrasse\n46, 6232 Bad Soden. Tel\n06196-269 06\n\nAntal anställda: 750\nÅrsomsättning: 60 000 000\nAktiekapital: 8 5 00 000\nStyrelse: Disp F Hartmann (ordf),\ndisp Bo Risberg, dlr Lars\nHill-Lindquist, dir Sigurd Ljungcrantz,\ndir Gunnar Olsson\nVerkst din Gunnar Olsson\nEtableringsån 1886\nOmbildat till aktiebolag 1910.\nDotterbolag: Göteborgs\nKassaskåpsfabriks AB, Göteborg, AB\nHedal-verken, Kungsbacka, AB Norema\nIndustrier, Malung, Verkstads AB\nLindqvist, Motala.\n\nROSENGRENS METALL.\nGJUTERI AB, J N\n\nPnr 200 61\n\nMalmö 30, Barlastg. Box 30023.\nTel 040-15 30 00, 15 30 01. Bankgiro\n869-0182. Postgiro 30685-2. Tga\n\nMetallgjuteriet\n\nVerksamhet: Tillverkar gjutgods,\nmetallgjutgods o lättmetallegeringar\nsamt utför konstgjutningar o\ncen-trifugalgjutningar\nAntal anställda: 35\nÅrsomsättning: 3 000 000\nAktiekapital: 132000\nStyrelse: Jur dr Erik Danielsson\n(ordf), gjuteriing Bertil Ekeblom,\nkamrer Erik Larsson, ing Arne\nRosengren, ing Bengt Rosengren\nVerkst dir. Ing Bengt Rosengren\nEtableringsàr: 1930.\n\nROSENQUIST, AB NILS\n\nPnr 27201\n\nSimrishamn 1, Kristianstadsv 1. Box\n38. Tel 0414-118 40. Bankgiro\n66-2234. Postgiro 91216-2\nVerksamhet: Säljer trävaror,\nbyggnadsmaterial, golv, eldningsolja,\nkol o koks\n\nÅrsomsättning: 4 600 000\nAktiekapital: 100 000\nVerkst dir. Stig Björnsson\nEtableringsån 1915.\n\nROSENLEWS AB\nHUSHÅLLSMASKINER\n\nPnr 172 03\n\nSundbyberg 3, Högklintav 9. Box\n325. Tel 08-98 08 30. Bankgiro\n74-3641. Postgiro 671669. Tga\nRosen-lewab. Telex 10325 ROLEWAB S\nVerksamhet: Grossistförsäljning av\nhushållskapitalvaror\nVarunamn: Rosenlew\nAntal anställda: 13\nÅrsomsättning: 7 000 000\nAktiekapital: 200 000\nVerkst dir: Torsten Elmström\nEtableringsàr: 1965.\n\nROSENLIND, ÅKE\n\nPnr 43136\n\nMölndal, Höjdg 14. Tel031-27 14 24.\nPostgiro 426253\n\nVerksamhet: Papper o påsar i parti\nÄgare o chef: Ake Rosenlind\nEtableringsån 1953.\n\nPLYFA, AB\n\nPnr 20110\n\nMalmö 1, Industrig 15. Fack. Tel\n040-93 4 7 4 0. Bankgiro 640-1491.\nPostgiro 38945-2. Tga Plyfa.\nTelex 3179\n\nVerksamhet: Plywood, lamellträ,\nformsättningsplattor, profilplywood,\nspånplattor, tunnor o lådor av\nplywood samt pallboxar\nFabrik: Hassela. Tel 0652-403 00\nVarunamn: Plyfa\nAntal anstäUda: 300\nÅrsomsättning: 30 000 000\nAktiekapital: 2 500 000\nStyrelse: Bankdir Claes Lindskog\n(ordf), disp Carl Rasmusson,\ndir Kristian Staerk, fabrikschef\nLars Hjertberg\n\nVerkst dir: Disp Carl Rasmusson\nEtableringsår: 1933.\n\nPLYMOTH GARAGE.\nPLATTOR AB\n\nPnr 21618\n\nMalmö, Ostanv 36. Tel\n040-15 33 00, 15 87 79\nVerksamhet: Tillverkar o säljer\nPlymoth garageplattor för\nparkeringsgarage\nVarunamn: Plymoth\nFörsäljningskontor i: USA, Canada,\nDanmark, England, Finland,\nFrankrike, Västtyskland\nAntal anstäUda: 10\nÅrsomsättning: 1500 000\nAktiekapital: 50 000\nVerkst dir: Inge Plymoth\n\nFörsäljn-chef: Ing Carl-Henrik\nRamel\n\nEtableringsår: 1964.",
    "structured": {
        "1": {
            "company_name": "TIBRO STOLFABRIK, AB",
            "pnr": "543 01",
            "address": "Tibro 1, Grönhultsv. Box 194",
            "phone_number": "0504-114 8 5",
            "bank_details": {
                "bankgiro": "22-1310",
                "postgiro": "519207"
            },
            "activity": "Tillverkar stilstolar",
            "employees": 18,
            "annual_turnover": 1100000,
            "capital": 100000,
            "key_personnel": [
                {
                    "name": "Fabr Egron Hugosson",
                    "position": "fabr"
                },
                {
                    "name": "Sixten Johansson",
                    "position": "Unknown"
                }
            ],
            "establishment_year": 1959
        },
        "2": {
            "company_name": "KOCKUMS MEKANISKA VERKSTADS AB",
            "pnr": "20110",
            "address": "Malmö l, Stora Varvsg",
            "phone_number": "040-744 20, 744 00",
            "bank_details": {
                "bankgiro": "640-1061",
                "postgiro": "38200-2"
            },
            "activity": "Moderbolag i Kockumgruppen",
            "employees": 5000,
            "annual_turnover": 850000000,
            "capital": 100000000,
            "key_personnel": [
                {
                    "name": "Bankir L-E Thunholm",
                    "position": "ordf"
                }
            ],
            "establishment_year": 1840
        },
        "3": {
            "company_name": "KOCKUM ROSENGREN AB",
            "pnr": "20110",
            "address": "Malmö 1, Fack",
            "phone_number": "040-702 80",
            "activity": "Tillverkar o monterar prefabricerade småhusskorstenar i plåt, mekaniska frånluftsystem, öppna spisar",
            "employees": 75,
            "annual_turnover": 10000000,
            "capital": 50000,
            "key_personnel": [
                {
                    "name": "Jan Rosenberg",
                    "position": "Verkst dir"
                }
            ],
            "establishment_year": 1908
        },
        "4": {
            "company_name": "KOCKUMS SÖDERHAMN AB",
            "pnr": "82601",
            "address": "Söderhamn 1, Fack",
            "phone_number": "0270-100 10",
            "bank_details": {
                "bankgiro": "61-2686",
                "postgiro": "174200"
            },
            "activity": "Sågverksutrustningar, barkningsmaskiner, skogstraktorer",
            "employees": 450,
            "annual_turnover": 105000000,
            "capital": 5000000,
            "key_personnel": [
                {
                    "name": "Nils-Hugo Hallenborg",
                    "position": "ordf"
                }
            ],
            "establishment_year": 1864
        }
    }
}