{
    "original": "AXELSON AB, STIG\n\nPnr 41119\n\nGöteborg, Ingenjörsg 1 B. Tel\n031-1153 62, 1153 64. Postgiro\n426410. Tga Exportax.\nTelex 20721 AXELSON S\nVerksamhet: Exporterar papper o\npapp o tillverkningar därav,\nträfiberskivor, plastfilm, aluminiumfolie\nm m\n\nAntal anställda: 5\nÅrsomsättning: 10 000 000\nVerkst dir: Stig Axelson\nEtableringsår: 1964.\n\nSVEA CHOKLAD, AB\n\nPnr 60103\n\nNorrköping l.Tullhusg 13. Box 115.\nTel 011-10 03 10. Bankgiro 82-4302.\nPostgiro 28260. Tga Svea\nVerksamhet: Tillverkar choklad,\nkarameller, köla, marmelad mm\nAntal anställda: 112\nÅrsomsättning: 16 600 000\nAktiekapital: 1200 000\nVerkst dir: Alvar Kempel\nEtableringsår: 1887.\n\nSVEA INKASSO. &amp;\nJURIDISKA BYRÄ\n\nPnr 11353\n\nStockholm, Tuleg 53. Tel\n08-340950. Postgiro 355548-9\n\nINKASSO &amp;\njuridiska\nBYRÅ-\n\nVerksamhet: Inkasso- o juridisk\nrörelse\n\nAntal anställda: 20\nÄgare o chef: Dir Stig Bäckström\nJur chef: Jur kand Gunhild Lenas\nInkassochef: Urban Henriksson\nEtableringsår: 1957.\n\nTEKNOSAN, AB\n\nPnr 201 10\n\nMalmö 1, Stora Nyg 18. Fack. Tel\n040-93 66 00. Tga Teknosan.\nTelex 3101 FERROCO S\nVerksamhet: Säljer\nbekämpningsmedel, desinfektionsmedel o\nfoderpreparat, vitaminpreparat o\nväxt-skyddsmedel\nAktiekapital: 100 000\nChef: Dir Sven Carlsten\nEtableringsår: 1958\nDotterbolag till AB Ferrosan,\nMalmö.\n\nTEKO AB, INGENIÖRSFIRMAN\n\nse Culligan Teko AB.\n\nTEKÅ REKLAM AB\n\nPnr 573 01\n\nTranås 1. Box 23. Stigbergsg 3.\nTel 0140-100 15\n\nVerksamhet: Reklambyrå,\nannonsbyrå\n\nVerkst dir: Olle Svenler.\n\nTEL INTER AB\n\nPnr 123 21\n\nFarsta 1, Filipstadsbacken 26. Box\n59. Tel 08-64 18 00, 64 3300.\nPost-giro 359505.Telex 10008.Tga\nTel-interab, Stockholm\nVerksamhet: Importerar o säljer\nelektronikutrustning\nÅrsomsättning: 2 000 000\nAktiekapital: 50 000\nDir Hans Thärn\nEtableringsår: 1962.\n\nSVENSSON &amp; CO» OSCAR E\n\nPnr 112 22\n\nStockholm, John Ericssonsg\n12-14. Tel 08-52 03 35. Bankgiro\n332-0314- Postgiro 253683-7. Tga\nSvenssonpapmet. Telex 1835\nVerksamhet: Generalagentur för\nfin-o grovpapper samt kartong,\nnonferrometaller, förpackningsfolier o\n-filmer av olika slag samt\ntermoplaster\n\nAntal anställda: 12\nÅrsomsättning: 30 500 000\nÄgare o chef: Anders Lindquist\nEtableringsår 1903.\n\nSVENSSON &amp; CO METALL.\nFABRIK, OSKAR\n\nPnr 33033\n\nHill ers toip, Tyngel. Tel\n0370-821 03, 821 04. Bankgiro 54-3251.\nPostgiro 364988\n\nVeiksamhet: Tillverkar o\nexporterar oljekannor (pumpsmörjkannor)\nmed plast- eller metallbehållare,\nbiltillbehör såsom\nskattekvitto-hållare, radio- o TV-materiel\nAntal anställda: 4\nChefer: Oskar Svensson, Lennart\nSvensson\n\nEtableringsår 1949.\n\nSWENSONS SNICKERI &amp;\nTRAVARU AB, OTTO\n\nPnr 372 00\n\nRonneby, Fridhemsv 7. Box 74. Tel\n0457-129 90. Bankgiro 862-4652.\nPostgiro 98457-5. Tga Ariträ\nVerksamhet: Säljer trävaror o\nbyggnadsmaterial\nAntal anställda: 42\nÅrsomsättning: 7 200 000\nAktiekapital: 300 000\n\nStyrelse: Disp Olle Borenberg\nVerkst dir: Olle Borenberg\nEtableringsår: 1942.\n\nSVENSSONS MEK VERKSTAD\nAB, P J\n\nPnr 300 03\n\nHalmstad 3, Box 3034. FlygareglO.\nTel 035-10 01 70. Bankgiro\n423-6170. Postgiro 137570-8\nVerksamhet: Tillverkar\nspecialmaskiner för industrin\nAntal anställda: 70\nÅrsomsättning: 4 200 000\nAktiekapital: 300000\nVerkst dir Lennart Johansson\nEtableringsår: 1879.\n\nAUTOCALOR,AB\n\nPnr 41102\n\nGöteborg, Polhemsplatsen 7. Tel\n031-19 2150. Bankgiro 50-9602.\nPostgiro 43620. Tga Autocalor.\nTelex 2594 ACALGOT S\nVerksamhet: Tillverkar\nautomatiska värmeanläggningar\nAntal anställda: 23\nÅrsomsättning: 1 600 000\nAktiekapital: 100 000\nVerkst dir: Ernst Haglund\nEtableringsår: 1928.\n\nINR\n\nVerksamhet: Företagsstyrning,\nproduktionsstyrning, datateknik\nAvdelning skontor:\n212 14 Malmö, Industrig 13. Tel\n040-18 03 45\n\n41110 Göteborg, O Hamng 17. Tel\n031-17 65 60\n\nDanmark: Köpenhamn F, Finsensv\n15. Tel (1) 10 8211\nNcrge: Oslo 6, Grensev 99,\nEtterstad. Tel (2) 67 31 94\nFinland: Helsingfors, Nylandsg 17.\nTel (0) 13142\nAntal anställda: 25\nÅrsomsättning: 4 000 000\nAktiekapital: 24 000\nVerkst dir: Civilekonom Bengt Öhrn\nEtableringsår: 1964.\n\nANDERSSONS SÖNER AB, J G\n\nPnr 360 24\n\nLinneryd. Tel 0470-343 40.\nBankgiro 293-5021. Postgiro 385220-9.\nTga Bomanwood, Växjö\nVerksamhet: Säljer sågade o\nhyvlade trävaro inom o utom landet\nAntal anställda: 72\nÅrsomsättning: 8 800 000\nAktiekapital: 200 000\nVerkst dir: Disp Erland Andersson\nEtableringsår 1928.\n\nLINATEX AB\n\nPnr 60102\n\nNorrköping 1, Skeppareg 6. Box 39.\nTel 011-18 03 25. Bankgiro\n125-1040. Postgiro 282574-3.\nTga Linatex\n\nVerksamhet: Utför industriella\nbeläggningar o konstruktioner i\nLina-tex 95 % naturgummi mot slitage\no korrosion\nVarunamn: Linatex\nAktiekapital: 60 000\nVerkst dir: Ing Max Siemsen\nEtableringsår: 1952.\n\nOLS\n\nAktiekapital: 100000\nStyrelse: Dir Birger Löwhagen\n(ordf), dir Lennart Larsson (Växjö),\ndir Börje Berendahl (Åstorp)\nVerkst dir: Yngve Klint\nEtableringsår: 1960.\n\nOLOVSON BYGGNADSFIRMA,\nRUNE\n\nPnr 41455\n\nGöteborg, Karl Johansg 76. Tel\n031-12 20 22. Postgiro 523785\nVerksamhet: Husbyggnader,\nreparationer, ändringar o värderingar\nÄgare o chef: Rune Olovson\nEtableringsår: 1959.\n\nOLOF ST ROMS\nBOKTRYCKERI AB\n\nPnr 293 00\n\nOlofström, Box 104. Nya\nIndustri-onrådet. Tel 0454-413 75.\nBankgiro 151-7085. Postgiro 383930-5\nVeiksamhet: Specialtryckeri för\nstamsatser, stamsatsblock o\ndatablanketter\n\nFörsäljningskontor: 100 72\nStockholm 43, Box 43042.\nLiljeholms-torg 1. Tel 08-45 48 80\nVarunamn: OB\nAntal anställda: 37\nÅrsomsättning: 3 000 000\nAktiekapital: 15 000\nStyrelse: Boktr Kurt Adohlfson,\nadv Fritz Fieber, adv Lars\nManner-hult, boktr Tage Tingstedt\nVerkst dir: Tage Tingstedt\nBoktr: Kurt Adohlfson\nKamrer: Bo Johansson\nEtableringsår: 1953.\n\nOLOF ST ROMS HÄNDELS. &amp;\nINDUSTRI AB\n\nPnr 293 00\n\nOlofström, Vilshultsv 95. Box 68.\nTel 0454-401 45. Bankgiro 15-1648.\nPostgiro 380025. Tga Ohia\nVerksamhet: Tillverkar rostfria\nhusgeråd, kastruller mm\nÅrsomsättning: 150 000\nAktiekapital: 10 200\nVerkst dir: Carl Johansson\nEtableringsår: 1947.\n\nPOULSEN &amp; RAGOCZY, AB\n\nPnr 70104\n\nÖrebro 1, Frykstensg 6. Box 258.\nTel 019-1192 50. Bankgiro\n614-4562. Postgiro 52463-7. Tga\nLäderagent. Telex 73234\n\nVerksamhet: Import o export av\nläder o plast\nAktiekapital: 200 000\nVerkst dir: Sven Oscarson\nEtableringsår 1909.",
    "structured": {
        "1": {
            "company_name": "AXELSON AB, STIG",
            "address": "Göteborg, Ingenjörsg 1 B",
            "phone_number": "031-1153 62, 1153 64",
            "postgiro": "426410",
            "activity": "Exporterar papper och papp o tillverkningar därav, träfiberskivor, plastfilm, aluminiumfolie m m",
            "employees": 5,
            "annual_turnover": 10000000,
            "key_personnel": [
                {
                    "name": "Stig Axelson",
                    "position": "Verkst dir"
                }
            ],
            "establishment_year": 1964
        },
        "2": {
            "company_name": "SVEA CHOKLAD, AB",
            "address": "Norrköping l.Tullhusg 13",
            "phone_number": "011-10 03 10",
            "bankgiro": "82-4302",
            "postgiro": "28260",
            "activity": "Tillverkar choklad, karameller, köla, marmelad mm",
            "employees": 112,
            "annual_turnover": 16600000,
            "capital": 1200000,
            "key_personnel": [
                {
                    "name": "Alvar Kempel",
                    "position": "Verkst dir"
                }
            ],
            "establishment_year": 1887
        },
        "3": {
            "company_name": "SVEA INKASSO & JURIDISKA BYRÄ",
            "address": "Stockholm, Tuleg 53",
            "phone_number": "08-340950",
            "postgiro": "355548-9",
            "activity": "Inkasso- o juridisk rörelse",
            "employees": 20,
            "key_personnel": [
                {
                    "name": "Dir Stig Bäckström",
                    "position": "Ägare o chef"
                },
                {
                    "name": "Jur kand Gunhild Lenas",
                    "position": "Jur chef"
                },
                {
                    "name": "Urban Henriksson",
                    "position": "Inkassochef"
                }
            ],
            "establishment_year": 1957
        },
        "4": {
            "company_name": "TEKNOSAN, AB",
            "address": "Malmö 1, Stora Nyg 18",
            "phone_number": "040-93 66 00",
            "activity": "Säljer bekämpningsmedel, desinfektionsmedel o foderpreparat, vitaminpreparat o växt-skyddsmedel",
            "capital": 100000,
            "key_personnel": [
                {
                    "name": "Dir Sven Carlsten",
                    "position": "Chef"
                }
            ],
            "establishment_year": 1958,
            "parent_company": "AB Ferrosan, Malmö"
        },
        "5": {
            "company_name": "TEKO AB, INGENIÖRSFIRMAN",
            "alternative_name": "Culligan Teko AB"
        },
        "6": {
            "company_name": "TEKÅ REKLAM AB",
            "address": "Tranås 1, Box 23, Stigbergsg 3",
            "phone_number": "0140-100 15",
            "activity": "Reklambyrå, annonsbyrå",
            "key_personnel": [
                {
                    "name": "Olle Svenler",
                    "position": "Verkst dir"
                }
            ]
        },
        "7": {
            "company_name": "TEL INTER AB",
            "address": "Farsta 1, Filipstadsbacken 26",
            "phone_number": "08-64 18 00, 64 3300",
            "bankgiro": "50-9602",
            "postgiro": "359505",
            "activity": "Importerar o säljer elektronikutrustning",
            "annual_turnover": 2000000,
            "capital": 50000,
            "key_personnel": [
                {
                    "name": "Hans Thärn",
                    "position": "Dir"
                }
            ],
            "establishment_year": 1962
        },
        "8": {
            "company_name": "SVENSSON & CO» OSCAR E",
            "address": "Stockholm, John Ericssonsg 12-14",
            "phone_number": "08-52 03 35",
            "bankgiro": "332-0314",
            "postgiro": "253683-7",
            "activity": "Generalagentur för fin- och grovpapper samt kartong, nonferrometaller, förpackningsfolier o filmer av olika slag samt termoplaster",
            "employees": 12,
            "annual_turnover": 30500000,
            "key_personnel": [
                {
                    "name": "Anders Lindquist",
                    "position": "Ägare o chef"
                }
            ],
            "establishment_year": 1903
        },
        "9": {
            "company_name": "SVENSSON & CO METALL. FABRIK, OSKAR",
            "address": "Hillersjoip, Tyngel",
            "phone_number": "0370-821 03, 821 04",
            "bankgiro": "54-3251",
            "postgiro": "364988",
            "activity": "Tillverkar o exporterar oljekannor (pumpsmörjkannor) med plast- eller metallbehållare, biltillbehör såsom skattekvitto-hållare, radio- o TV-materiel",
            "employees": 4,
            "key_personnel": [
                {
                    "name": "Oskar Svensson",
                    "position": "Chef"
                },
                {
                    "name": "Lennart Svensson",
                    "position": "Chefer"
                }
            ],
            "establishment_year": 1949
        },
        "10": {
            "company_name": "SWENSONS SNICKERI & TRAVARU AB, OTTO",
            "address": "Ronneby, Fridhemsv 7",
            "phone_number": "0457-129 90",
            "bankgiro": "862-4652",
            "postgiro": "98457-5",
            "activity": "Säljer trävaror o byggnadsmaterial",
            "employees": 42,
            "annual_turnover": 7200000,
            "capital": 300000,
            "key_personnel": [
                {
                    "name": "Disp Olle Borenberg",
                    "position": "Styrelse"
                },
                {
                    "name": "Olle Borenberg",
                    "position": "Verkst dir"
                }
            ],
            "establishment_year": 1942
        },
        "11": {
            "company_name": "SVENSSONS MEK VERKSTAD AB, P J",
            "address": "Halmstad 3, Box 3034, FlygareglO",
            "phone_number": "035-10 01 70",
            "bankgiro": "423-6170",
            "postgiro": "137570-8",
            "activity": "Tillverkar specialmaskiner för industrin",
            "employees": 70,
            "annual_turnover": 4200000,
            "capital": 300000,
            "key_personnel": [
                {
                    "name": "Lennart Johansson",
                    "position": "Verkst dir"
                }
            ],
            "establishment_year": 1879
        },
        "12": {
            "company_name": "AUTOCALOR,AB",
            "address": "Göteborg, Polhemsplatsen 7",
            "phone_number": "031-19 2150",
            "bankgiro": "50-9602",
            "postgiro": "43620",
            "activity": "Tillverkar automatiska värmeanläggningar",
            "employees": 23,
            "annual_turnover": 1600000,
            "capital": 100000,
            "key_personnel": [
                {
                    "name": "Ernst Haglund",
                    "position": "Verkst dir"
                }
            ],
            "establishment_year": 1928
        },
        "13": {
            "company_name": "INR",
            "address": "212 14 Malmö, Industrig 13",
            "phone_number": "040-18 03 45, 41110 Göteborg, O Hamng 17, Tel 031-17 65 60, Danmark: Köpenhamn F, Finsensv 15, Tel (1) 10 8211, Norge: Oslo 6, Grensev 99, Etterstad, Tel (2) 67 31 94, Finland: Helsingfors, Nylandsg 17, Tel (0) 13142",
            "employees": 25,
            "annual_turnover": 4000000,
            "capital": 24000,
            "key_personnel": [
                {
                    "name": "Civilekonom Bengt Öhrn",
                    "position": "Verkst dir"
                }
            ],
            "establishment_year": 1964
        },
        "14": {
            "company_name": "ANDERSSONS SÖNER AB, J G",
            "address": "Linneryd",
            "phone_number": "0470-343 40",
            "bankgiro": "293-5021",
            "postgiro": "385220-9",
            "activity": "Säljer sågade o hyvlade trävaro inom o utom landet",
            "employees": 72,
            "annual_turnover": 8800000,
            "capital": 200000,
            "key_personnel": [
                {
                    "name": "Disp Erland Andersson",
                    "position": "Verkst dir"
                }
            ],
            "establishment_year": 1928
        },
        "15": {
            "company_name": "LINATEX AB",
            "address": "Norrköping 1, Skeppareg 6, Box 39",
            "phone_number": "011-18 03 25",
            "bankgiro": "125-1040",
            "postgiro": "282574-3",
            "activity": "Utför industriella beläggningar o konstruktioner i Lina-tex 95 % naturgummi mot slitage o korrosion",
            "capital": 60000,
            "key_personnel": [
                {
                    "name": "Ing Max Siemsen",
                    "position": "Verkst dir"
                }
            ],
            "establishment_year": 1952
        },
        "16": {
            "company_name": "OLS",
            "address": "Stockholm 43, Box 43042, Liljeholms-torg 1, Tel 08-45 48 80",
            "capital": 100000,
            "key_personnel": [
                {
                    "name": "Dir Birger Löwhagen",
                    "position": "Styrelse"
                },
                {
                    "name": "Yngve Klint",
                    "position": "Verkst dir"
                }
            ],
            "establishment_year": 1960
        },
        "17": {
            "company_name": "OLOVSON BYGGNADSFIRMA, RUNE",
            "address": "Göteborg, Karl Johansg 76",
            "phone_number": "031-12 20 22",
            "postgiro": "523785",
            "activity": "Husbyggnader, reparationer, ändringar o värderingar",
            "key_personnel": [
                {
                    "name": "Rune Olovson",
                    "position": "Ägare o chef"
                }
            ],
            "establishment_year": 1959
        },
        "18": {
            "company_name": "OLOF ST ROMS BOKTRYCKERI AB",
            "address": "Olofström, Box 104, Nya Industri-onrådet",
            "phone_number": "0454-413 75",
            "bankgiro": "151-7085",
            "postgiro": "383930-5",
            "activity": "Specialtryckeri för stamsatser, stamsatsblock o datablanketter",
            "employees": 37,
            "annual_turnover": 3000000,
            "capital": 15000,
            "key_personnel": [
                {
                    "name": "Tage Tingstedt",
                    "position": "Verkst dir"
                },
                {
                    "name": "Kurt Adohlfson",
                    "position": "Boktr"
                }
            ],
            "establishment_year": 1953
        },
        "19": {
            "company_name": "OLOF ST ROMS HÄNDELS. & INDUSTRI AB",
            "address": "Olofström, Vilshultsv 95, Box 68",
            "phone_number": "0454-401 45",
            "bankgiro": "15-1648",
            "postgiro": "380025",
            "activity": "Tillverkar rostfria husgeråd, kastruller mm",
            "annual_turnover": 150000,
            "capital": 10200,
            "key_personnel": [
                {
                    "name": "Carl Johansson",
                    "position": "Verkst dir"
                }
            ],
            "establishment_year": 1947
        },
        "20": {
            "company_name": "POULSEN & RAGOCZY, AB",
            "address": "Örebro 1, Frykstensg 6, Box 258",
            "phone_number": "019-1192 50",
            "bankgiro": "614-4562",
            "postgiro": "52463-7",
            "activity": "Import o export av läder o plast",
            "capital": 200000,
            "key_personnel": [
                {
                    "name": "Sven Oscarson",
                    "position": "Verkst dir"
                }
            ],
            "establishment_year": 1909
        }
    }
}