{
    "original": "JACOBSEN AB, WILH CARL\n\nPnr 101 21\n\nStockholm 1, Kungsg 48. Box 140.\nTel 08-23 18 75. Bankgiro 72-2360.\nPostgiro 1840. Tga Confident.\nTelex 17954 CONFIDE S\nVerksamhet: Handelsagenturer med\nelmateriel o elektronik-komponenter\nAntal anställda: 4\nAktiekapital: 24 000\nVerkst dir: Rolf Jacobsen\nEtableringsår: 1906.\n\nJACOBSSON, JACOBSON,\nJAKOBSSON\n\nJACOBSSONS BIL AB\n\nPnr 780 20\n\nStora Tuna. Tel 0243-33390.\nBankgiro 79-45 25. Postgiro 376337\nVeiksamhet: Säljer Volvobilar.\nService, motell\n\nFilial: Insjön. Tel 0247-40630\nAntal anställda: 85\nÅrsomsättning: 19 000 000\nAktiekapital: 500 000\nVerkst dir: Gustaf Jacobsson\nEtableringsår: 1952.\n\nBJURHAGENS FABRIKERS AB\n\nPnr 200 12\n\nMalmö 2, Fack. Agneslundsv 14.\nTel 040-93 47 70. Bankgiro\n643-0151. Postgiro 39069-0. Tga\nKabelfabriken. Telex 3123\n\n\n\t©b\t\n\tBJURHAGEN\t\n\n\nVerksamhet: Lednings- o\nkabeltillverkning\nSälj- o lagerkontor:\n\n211 24 Malmö, Borrg 6. Tel\n040-93 60 50\n\nFabrik: 271 00 Ystad, Dragong 15.\nTel 0411-160 00\nVarunamn: BE-PAC system\nAntal anställda: 180\nAktiekapital: 10 000 000\nVerkst dir: Hans Pettersson\n\nInköpschef: B Gyllander\nSäljledare: V Lydov\nExportchef: L Groth\nFkonomichef: I Jansson\nProd-chef i Malmö: Ing M Karlsson\nProd-chef i Ystad: Ing Nils Ring\nEtableringsår: 1924.\n\nSKOHGS VERKSTÄDER, S J\n\nPnr 690 30\n\nFinnerödja, Box 103. Industrig 1.\nTel 0584-20252, 200 80. Bankgiro\n815-7554. Postgiro 28211-1. Tga\nKopparskohg\n\nVerksamhet: Tillverkar villapannor,\nelvarmvattenberedare,\nelvärmepannor, elvarmvattenberedarecentraler,\nvarmvattenbatterier, värmeväxlare o\nsvetsade plåtarbeten samt\ntryckkärl\n\nVarunamn: EL-SV, SV\nDisp: Rune Skohg\nDisp: Sven Skohg\nEtableringsår: 1874.\n\nBRÄNNANS SMIDE AB\n\nPnr 93102\n\nSkellefteå 2, Brog. Box 956. Tel\n0910-773 90. Bankgiro 61-1699.\nPostgiro 386997\n\nVerksamhet Tillverkar\npersonbilssläpvagnar o draganordningar för\npersonbilar samt bromspaket för\nombyggnad\nAntal anstäUda: 15\nÄgare o chef: André Lundmark.\n\nBRÄNNEHEDS SMIDES- &amp;\nMEK VERKSTAD AB\n\nPnr 533 00\n\nGötene, Kinneg4. Tel 0511-500 66.\nBankgiro 543-8080. Postgiro\n292669-9\n\nVerksamhet: Tillverkar\nbyggnads-smide o verkstadspressar.\n\nBRÄNNEHYLTE\nMEK VERKSTAD, AB\n\nPnr 330 33\n\nHiUerstorp. Tel 0370-222 30. Tga\nBrännemek. Telex 70161\nVerksamhet: Tillverkar\nbyggnadsbeslag, pallramsbeslag,\nhusgerådsartiklar, trädgårdsredskap,\nvalv-stämp, upphängningsjärn för VVS\ninstallationer. Specialitet: arbeten\ni plåt\n\nAntal anstäUda: 35\nÅrsomsättning: 3 000 000\nAktiekapital: 160 000\nVerkst dir: Bengt Erlandsson\nEtableringsår: 1946\nOmbildat till aktiebolag 1949.\n\nBRÄNN LANDS NYA\nT RA FÖRÄDLINGS AB\n\nPnr 905 90\n\nUmeå, Obacka. Tel 090-1108 07,\n14910. Postgiro 624 50\nVerksamhet: Sågade o hyvlade\nträvaror i parti o minut. Arsenik- o\nkreosotimpregnerade trävaror\nAntal anstäUda: 59\nAktiekapital: 110 000\nVerkst dir: Abel Olsson\nEtableringsår: 1923.\n\nINDUSTRIDATA AB\n\nPnr 17120\n\nSolna 1, Albyg 102. Fack. Tel\n08-9303 50. Bankgiro 620-9043.\nPost-giro 447696-6.\nTelex 19035 IDATA S\nVerksamhet: Datacentraler o\nkonsulter inom administrativ o teknisk\ndatabehandling\n\nDistriktskontor: Solna 1, Albyg 102.\n\nPack. Tel 08-9 8 03 50. Chef: Per-\n\nAxel Liljequist\n\nGöteborg 13, Industriv 11. Box\n\n13072. Tel 031-26 2 1 90. Chef:\n\nPer-Erik Mellbin\n\nMalmö 1, Citadell sv 9. Box 474.\n\nTel 040-771 80. Chef: Lars-Olof\n\nBjörkskär\n\nLinköping 1, Klosterg 5. Box 338.\nTel 013-1113 20. Chef: Viktor\nJohanson\n\nVästerås, Ostermalmsg 15. Tel\n021-12 04 3 0. Chef: Stig Engstrand\nAntal anstäUda: 170\nÅrsomsättning: 13 000 000\nAktiekapital: 400 000\nVerkst dir: Bertil Brynander\nEtableringsår 1964\nFöretaget har bildats på initiativ av\nAsea, Facit, Saab o Skandinaviska\nElverk.\n\nINDUSTRIDESTILLATION, AB\n\nPnr 16211\n\nVällingby 1. Box 69. Tel\n08-8904 50. Bankgiro 33-3205.\nPostgiro 459080-8\n\nVerksamhet: Mottager olje- o\nkemikalieavfall för upparbetning eller\ndestruktion\n\nFUial: Malmö, Malmö Frihamn. Tel\n\n040-127295\n\nAntal anställda: 34\n\nÅrsomsättning: 5 000 000\n\nAktiekapital: 200 000\n\nStyrelse: Dir Björn Wallander (ordf),\n\ndir Allan Grämer, ing Tage Sundh,\n\ndir Torbjörn Winberg\n\nVeikst dir: Allan Grämer\n\nEtableringsår: 1951\n\nDotterbolag till SAKAB (Svensk\n\nAvfallskonvertering AB).\n\nINDUSTRIDIAMANTER, AB\n\nPnr 76100\n\nNorrtälje. Baldersg 19. Box 125.\nTel 0176-128 60. Bankgiro\n744-4336. Postgiro 55405-5. Tga\nIndi-mant. Telex 10208\nVerksamhet: Tillverkar\ndiamant-verktyg\n\nVarunamn: Indimant\nAntal anstäUda: 50\n\nAktiekapital: 500 000\nVerkst dir. Erik Wickberg\nEtableringsår 1925.\n\nINDUSTRIELL\nDATAKONSULT AB\n\nPnr 416 60\n\nGöteborg. Scheleg 6. Tel\n031-80 23 67\n\nVerksamhet: Systemutveckling o\nprogrammering\n\nFUial: 46104 Trollhättan 4,\nGök-ottev 5. Box 4003. Tel 0520-166 26,\n31125\n\nAntal anstäUda: 9\n\nAktiekapital: 6 000\nVerkst dir: B Ramström\nEtableringsår: 1966.\n\nFörsäljningskontor: Stockholm.\nKrossg 32, pa 16211 Vällingby. Tel\n08-89 04 60\n\n400 25 Göteborg, Almedalsv 1. Tel\n031-40 9185\n\n203 11 Malmö, Stora Nyg 59. Tel\n040-705 00\n\n724 66 Västerås, Jonas Wenströms g\n11. Tel 021-12 0005\n550 04 Jönköping, Jutev 16-20. Tel\n036-16 5125\n\n651 08 Karlstad, Fredsg 1 B. Tel\n054-18 03 45\n\n90243 Umeå, Kungsg 97. Tel\n090-129130\n\nAntal anställda: 260\nÅrsomsättning: 32 000 000\nAktiekapital: 2 650000\nStyrelse: Adv Sven Munck af\nRo-senschöld (ordf), dir Göte\nJohansson, dir Bertil Stigen, civiling Rolf\nStigen, mr Jesse M Shaver, mr\nNobert O Grohman\nVerkst dir. Ing Bengt Hjort\nEtableringsår: 1941.\n\nINDUSTRIFJÄDRAR, AB\n\nse Stece.\n\nINDUSTRIFÄRGER, AB\n\nPnr 18102\n\nLidingö 2, Kottlav 72. Fack. Tel\n08-766 00 80. Bankgiro 627-4260.\nPostgiro 6622-5. Tga Industrifärger\nVerksamhet: Tillverkar färger o\nfernissor för industriändamål\nAntal anstäUda: 50\nAktiekapital: 300000\nEtableringsår: 1931.\n\nINDUSTRI - FORPACKNINGAR\n(INDUSTRI-PAC) AB\n\nPtr 261 90\n\nLandskrona, Saxtorp. Tel\n0418-305 00. Postgiro 57013\nVerksamhet: Sälja- cellofan- o\nplastprodukter\nVeikst dir: Bo Lindahl\nEtableringsår: 1953.\n\nRUNÄ VERKTYGS AB\n\nPnr 330 30\n\nGnosjö, Ågatan 19. Tel 0370-910 08,\n917 69. Bankgiro54-2536. Postgiro\n335856-1\n\nVerksamhet: Konstruerar o\ntillverkar pressverktyg\nAntal anställda: 7\nChef: Rune Johansson\nEtableringsår: 1948.\n\nNORDWALL AB, STEN\n\nPnr 104 60\n\nStockholm, Hammarbyv 66-68. Tel\n08-23 86 00. Bankgiro 733-2257.\nPostgiro 4857-9. Tga Steno.\nTelex 10739\n\nVerksamhet: Försäljning engros\nav byggnads- o industrimaterial\nVarunamn: Steno, Söderhamns kåpan\nAntal anstäUda: 19\nÅrsomsättning: 4 400 000\nAktiekapital: 150000\nDisp: C G Berg\nEtableringsår: 1936\nOmbildat till aktiebolag 1946.\n\nNORDVALL &amp; CO, AB W H\n\nPnr 275 00\n\nSjöbo, Planteringsg 46. Box 14. Tel\n0416-108 50. Bankgiro 282-7475.\nPostgiro 6623-3. Tga Nordvall\nVerksamhet: Tryckeri för\nsjälvhäf-tande o gummerade etiketter, tejp,\nsnabbset, blanketter o övriga\ntrycksaker. Papper en gros\nAntal anställda: 37\nÅrsomsättning: 5 000 000\nAktiekapital: 150 000\nStyrelse: Fru Ruth Johansson\n(ordf), dir Gustav Dahl, inköpschef\nJohan Jönsson\nVerkst dir Gustav Dahl\nEtableringsår. 1907.\n\nPETERSON &amp; CO, AB J A\n\nPnr 510 52\n\nMålsryd. Tel 033-490 80. Bankgiro\n83-9355. Postgiro 72167. Tga\nJa-peters\n\nVerksamhet: Fastighetsförvaltning,\neldistribution o beklädnadshandel\nAntal anställda: 15\nÅrsomsättning: 2 700 000\nAktiekapital: 1700000\nVerkst dir: Ulf Synnerstad\nEtableringsår: 1863.\n\nPETTERSSONS SNICKERI AB,\nJ M\n\nPnr 352 31\n\nVäxjö, Bäckg 22. Tel 0470-12247.\nBankgiro 292-6483. Postgiro\n92874-7\n\nVerksamhet: Tillverkar\nbyggnadssnickerier, specialitet entrépartier\no glaspartier samt\nspecialinredningar för skolor, sjukhus o\noffentliga byggnader\nAntal anställda: 12\nÅrsomsättning: 800 000\nAktiekapital: 50000\nVeikst dir: Major Arne Parck\nEtableringsår: 1888.\n\nPETERSON INDUSTRI AB,\nLEVI\n\nPnr 330 20\n\nAnderstorp, Agatan 48. Box 81. Tel\n0371-161 90. Bankgiro 488-0522.\nPostgiro 22575-5. Tga Levier\nVerksamhet: Tillverkar nitar o\nnit-ningsmaskiner för dubbelnit, beslag\no artiklar för läder- o\nreseffektin-dustrin, dragna o pressade\nmetallartiklar, mandelkvarnar o\npuré-pressar\n\nAntal anställda: 50\nÅrsomsättning: 3 200 000\nAktiekapital: 150 600\nVerkst dir: Kurt Idin\nKamrer. Hartvig Idin\nEtableringsår: 1914.\n\nPETTERSSON\nKONSUL-TERANDE INGENIORSBYRÄ\nAB, MARTIN\n\nPnr 502 32\n\nBorås, Allég 60. Tel 033-13 63 65.\nBankgiro 98-4306. Postgiro\n567036-9\n\nVerksamhet: Teknisk\nkonsultverksamhet inom VVS-branschen\nAntal anställda: 13\nÅrsomsättning: 550 000\nAktiekapital: 15 000\nStyrelse: Ing Martin Pettersson\n(crdf), fru Mirjam Pettersson\nVerkst dir: Martin Pettersson\nEtableringsår: 1965.\n\nALMEX, AB\n\nPnr 11251\n\nStockholm. Sankt Göransg 160 B.\nTel 08-54 14 80. Bankgiro 167-8077.\nPostgiro 255254-5. Tga Mexal\nVerksamhet: Tillverkar\nbiljettmaskiner o elektronikprodukter\nAntal anställda: 140\nAktiekapital: 2100 000\nVerkst dir: Nils Ståhl\nEtableringsår 1946.\n\nGRANDIN AB, HARRY\n\nPnr 50105\n\nBorås 1, Box 300. Stureg 7. Tel\n033-10 26 00\n\nVerksamhet: Textilagenturer\nAktiekapital: 40 000\nVerkst dir: Harry Grandin\nEtableringsår: 1934.\n\nGRANHAGA METALLINDUSTRI\nAB\n\nPnr 54500\n\nTöreboda, Box 51. Tel 0506-11670.\nBankgiro 217-1700. Postgiro\n360268-7\n\nVerksamhet: Tillverkar modern\nhembelysning i plåt\nAntal anstäUda: 50\nÅrsomsättning: 3 500 000\nAktiekapital: 150 000\nVerkst dir. Sven Persson\nEtableringsår: 1947.\n\nGRANHAGE AB,\nENTREPRE-NADFIRMA GUNNAR\n\nPnr 412 52\n\nGöteborg, Sten Stureg 40. Tel\n031-18 70 25. Bankgiro 50-6616.\nPostgiro 420387\n\nVerksamhet: Spränger o schaktar\ngrunder till hus, makadamfabrik\nAntal anställda: 70\nÅrsomsättning: 8 000 000\nAktiekapital: 50 000\nVerkst dirr: Byggmäst Gunnar\nGranhage, byggmäst Holger Granhage\nEtableringsår: 1953.",
    "structured": {
        "1": {
            "company_name": "JACOBSEN AB, WILH CARL",
            "pnr": "101 21",
            "address": "Stockholm 1, Kungsg 48. Box 140.",
            "phone_number": "08-23 18 75",
            "bank_details": {
                "bankgiro": "72-2360",
                "postgiro": "1840"
            },
            "activity": "Handelsagenturer med elmateriel o elektronik-komponenter",
            "employees": 4,
            "capital": 24000,
            "key_personnel": [
                {
                    "name": "Rolf Jacobsen",
                    "position": "Verkst dir"
                }
            ],
            "establishment_year": 1906
        },
        "2": {
            "company_name": "JACOBSSONS BIL AB",
            "pnr": "780 20",
            "address": "Stora Tuna",
            "phone_number": "0243-33390",
            "bank_details": {
                "bankgiro": "79-45 25",
                "postgiro": "376337"
            },
            "activity": "Säljer Volvobilar. Service, motell",
            "employees": 85,
            "annual_turnover": 19000000,
            "capital": 500000,
            "key_personnel": [
                {
                    "name": "Gustaf Jacobsson",
                    "position": "Verkst dir"
                }
            ],
            "establishment_year": 1952
        },
        "3": {
            "company_name": "BJURHAGENS FABRIKERS AB",
            "pnr": "200 12",
            "address": "Malmö 2, Fack. Agneslundsv 14.",
            "phone_number": "040-93 47 70",
            "bank_details": {
                "bankgiro": "643-0151",
                "postgiro": "39069-0"
            },
            "activity": "Lednings- o kabeltillverkning",
            "employees": 180,
            "capital": 10000000,
            "key_personnel": [
                {
                    "name": "Hans Pettersson",
                    "position": "Verkst dir"
                },
                {
                    "name": "B Gyllander",
                    "position": "Inköpschef"
                },
                {
                    "name": "V Lydov",
                    "position": "Säljledare"
                },
                {
                    "name": "L Groth",
                    "position": "Exportchef"
                },
                {
                    "name": "I Jansson",
                    "position": "Fkonomichef"
                },
                {
                    "name": "Ing M Karlsson",
                    "position": "Prod-chef i Malmö"
                },
                {
                    "name": "Ing Nils Ring",
                    "position": "Prod-chef i Ystad"
                }
            ],
            "establishment_year": 1924
        },
        "4": {
            "company_name": "SKOHGS VERKSTÄDER, S J",
            "pnr": "690 30",
            "address": "Finnerödja, Box 103. Industrig 1.",
            "phone_number": "0584-20252, 200 80",
            "bank_details": {
                "bankgiro": "815-7554",
                "postgiro": "28211-1"
            },
            "activity": "Tillverkar villapannor, elvarmvattenberedare, elvärmepannor, elvarmvattenberedarecentraler, varmvattenbatterier, värmeväxlare o svetsade plåtarbeten samt tryckkärl",
            "key_personnel": [
                {
                    "name": "Rune Skohg",
                    "position": "Disp"
                },
                {
                    "name": "Sven Skohg",
                    "position": "Disp"
                }
            ],
            "establishment_year": 1874
        },
        "5": {
            "company_name": "BRÄNNANS SMIDE AB",
            "pnr": "93102",
            "address": "Skellefteå 2, Brog. Box 956.",
            "phone_number": "0910-773 90",
            "bank_details": {
                "bankgiro": "61-1699",
                "postgiro": "386997"
            },
            "activity": "Tillverkar personbilssläpvagnar o draganordningar för personbilar samt bromspaket för ombyggnad",
            "employees": 15,
            "owner": "André Lundmark"
        },
        "6": {
            "company_name": "BRÄNNEHEDS SMIDES- & MEK VERKSTAD AB",
            "pnr": "533 00",
            "address": "Götene, Kinneg4",
            "phone_number": "0511-500 66",
            "bank_details": {
                "bankgiro": "543-8080",
                "postgiro": "292669-9"
            },
            "activity": "Tillverkar byggnads-smide o verkstadspressar"
        },
        "7": {
            "company_name": "BRÄNNEHYLTE MEK VERKSTAD, AB",
            "pnr": "330 33",
            "address": "HiUerstorp",
            "phone_number": "0370-222 30",
            "bank_details": {
                "bankgiro": "Not Available",
                "postgiro": "Not Available"
            },
            "activity": "Tillverkar byggnadsbeslag, pallramsbeslag, husgerådsartiklar, trädgårdsredskap, valv-stämp, upphängningsjärn för VVS installationer"
        },
        "8": {
            "company_name": "BRÄNN LANDS NYA TRA FÖRÄDLINGS AB",
            "pnr": "905 90",
            "address": "Umeå, Obacka",
            "phone_number": "090-1108 07, 14910",
            "bank_details": {
                "bankgiro": "Not Available",
                "postgiro": "624 50"
            },
            "activity": "Sågade o hyvlade trävaror i parti o minut. Arsenik- o kreosotimpregnerade trävaror"
        },
        "9": {
            "company_name": "INDUSTRIDATA AB",
            "pnr": "17120",
            "address": "Solna 1, Albyg 102",
            "phone_number": "08-9303 50",
            "bank_details": {
                "bankgiro": "620-9043",
                "postgiro": "447696-6"
            },
            "activity": "Datacentraler o konsulter inom administrativ o teknisk databehandling",
            "employees": 170,
            "annual_turnover": 13000000,
            "capital": 400000,
            "key_personnel": [
                {
                    "name": "Bertil Brynander",
                    "position": "Verkst dir"
                }
            ],
            "establishment_year": 1964
        }
    }
}