{
    "original": "OSMUND FABRIKS AB\n\nPnr 75105\n\nUppsala 1, Såg arg 9-11. Box 287.\nTel 018-13 95 55. Bankgiro 80-2131.\nPostgiro 26688. Tfea Osmund\n\nVerksamhet: Elektriska, oljeeldade\no gaseldade industriugnar,\noljebrännare, regulatorer,\nhögtrycksfläktar, tegelsågar mm. Mekanisk\nverkstad for legoarbeten\nVarunamn: Osmund\nAntal anstäUda: 80\nÅrsomsättning: 6000 000\nAktiekapital: 515 000\nVeikst dir: Karl-Einar Lundberg.\n\nOSRAM-ELEKTRAVERKEN, AB\n\nPnr 104 60\n\nStockholm 20, Box 20050. Virkesv\n21. Tel 08-44 94 40. Postgiro\n727-8. Tga Osram\nVerksamhet: Tillverkar o försäljer\nglödlampor av märket \"Osram\"\nAntal anstäUda: 300\nAktiekapital: 2750 000\nVeikst dir: Gösta Ginner\nEtableringsår: 1906.\n\nVÄSTKUSTREKLAM, AB\n\nPnr 417 04\n\nGöteborg, Kvilleg 9. Tel\n031-23 43 66, 2238 64. Postgiro 420821\nVerksamhet: Märkesvaruskyltningar\nAntal anställda: 15\nÅrsomsättning: 400 000\n\nAktiekapital: 30000\nVerkst din Ove Håkansson\nEtableringsår. 1960-\n\nFORSSJO NYA TRÄVARU AB\n\nPnr 64100\n\nKatrineholm, Fredsg 63. Tel\n0150-13160. Postgiro87975. TgaForssjö\nVerksamhet: Tillverkar lådor o\nlåd-ämnen\n\nAktiekapital: 320 000\n\nVerkst dir: Karl August Malmnäs\n\nEtableringsår: 1934.\n\nSCANDIA PLYWOOD AB\n\nPnr 660 56\n\nSkattkärr, Box 42. Tel 054-60180.\nBankgiro 438-8724. Postgiro\n\n94374-6. Tga Scandiaply\nVerksamhet: Tillverkar plywood\nför inomhus- o utomhusbruk,\nform-plywood för betonggjutning samt\nlamellträ\n\nAntal anställda: 90\nÅrsomsättning: 7 000 000\nAktiekapital: 360 000\nStyrelse: Civiling Erik Wästlund\n(ordf), bankdir Nils Allström,\nnämndeman Karl Danielsson, fil lic Ake\nRehnberg, disp Bengt Wästlund\nVerkst dlr: Disp Bengt Wästlund\nProd-chef: Civiling Sven Jönsson\nEtableringsår: 1935.\n\nSCANDIA PRESENT AB\n\n(f d Mitab AB o AB Ystad-Metall)\n\nPnr 292 00\n\nKarlshamn, Box 60. Tel\n0454-144 90. Bankgiro 670-3 1 93.\nPostgiro 532366-2. Tga Scandiapresent\nVerksamhet: Tillverkar o säljer\npresentartiklar i metall\nAntal anställda: 70\nÅrsomsättning: 5 000 000\nAktiekapital: 1000 000\nVerkst dir: Töre Berg\nDisp: Inge Gärsgård\nEtableringsår: 1970.\n\nB ELMA, AB\n\nPnr 78101\n\nBorlänge 1, Box 14. Tel\n0243-260 60. Bankgiro 794-5272.\nPostgiro 462568-7. Tga Belma\nVerksamhet: Säljer biltillbehör i\nparti. Import o export\nAntal anställda: 9\nÅrsomsättning: 2 500 000\nAktiekapital: 32 000\nVerkst dir: Kurt Astor\nEtableringsår: 1950.\n\nfliesberg ab, gunnar\n\nPnr 16116\n\nBromma 16, Fack 2.\nSmedslätts-torget 49. Tel 08-26 99 24, 269925.\nBankgiro 33-1097. Postgiro\n602235-4. Tga Gunnarius.\nTelex 10629 GUNNARI S\nVerksamhet: Björk- o\nflygplansply-wood, lamellträ, spånskivor, laminat\nÄgare o chef: Gunnar Fliesberg\nEtableringsår: 1959.\n\nBRODIN &amp; SON, AB\n\nPnr 73101\n\nKöping 1, Industrig. Box 137.Tel\n0221-10172. Bankgiro 81-1306.\nPostgiro 296302-3\nVerksamhet: Tillverkar svetsade\njärn- o stålkonstruktioner\nAntal anställda: 30\nÅrsomsättning: 1000 000\nAktiekapital: 30 000\nVerkst dir: Gösta Brodin\nEtableringsår: 1920.\n\nFALLENIUS &amp; LEFFLERS AB\n\nPnr 403 10\n\nGöteborg 2, Fack. Packhusplatsen\n2. Tel 031-17 39 00. Tga Fallenius.\nTelex 2511\n\nVerksamhet: Nationella o\ninternationella transporter per båt,\njärnväg, lastbil o flyg, samlastning,\nspedition, skeppsmäkleri, klare-\n\nring, lagring, transportrådgivning,\nresebyrå\n\nAktiekapital: 4 200 000\nVerkst dir: S Johansson\nEtableringsår 1891.\n\nMEYER AB, CARL\n\nPnr 41109\n\nGöteborg, O Hamng 46. Tel\n031-1056 32, 105633. Postgiro\n404 1 9-4. Tga Carlmeyer\nVeiksamhet: Försäkringar\nAntal anställda: 5\nAktiekapital: 15 000\nVerkst dir Lennart Dahlöf\nEtableringsår: 1855.\n\nM F R MELLANSVENSK\nFORE-TAGSRATIONALISERING AB\n\nPnr 724 66\n\nVästerås, Jonas Wenströms g 13.\nTel 021-12 02 25. Bankgiro\n367-5790. Postgiro 688140-3\nVerksamhet: Administrativ o\nteknisk rationalisering. Utbildning.\nBokföring. Konstruktion\nFilialer: 252 24 Helsingborg,\nTräd-gårdsg 7. Tel 042-14 77 5 0.\nChef: Overing Bernt Orest\n552 40 Jönköping, Bokbindarg 12.\nTel 036-16 89 60.\nChef: Overing Akke Svahnberg\nAntal anställda: 40\nÅrsomsättning: 3 000000\nAktiekapital: 50 000\nStyrelse: Overing Bertil Ohlsson\n(ordf), övering Akke Svahnberg,\növering Gösta Nilsson,\nföretagsekonom Bernt Orest, övering Börje\nOrest\n\nVerkst dir: Börje Orest\nÖvriga chefer: Overing Bertil\nOhlsson, övering Gösta Nilsson,\növering Nils Möller\nEtableringsår: 1966.\n\nSYDSVENSKA SMÅHUS AB\n\nPnr 21120\n\nMalmö, Skeppsbron 3. Tel\n040-733 65. Bankgiro 640-6755.\nPostgiro 632920-5\n\nVerksamhet: Projekterar villor.\nSäljer byggsatser i lättbetong o\nsten\n\nAntal anställda: 20\nÅrsomsättning: 12 000 000\nAktiekapital: 450 000\nVerkst dir Leo Kramår\nEtableringsår: 1962.",
    "structured": {
        "1": {
            "company_name": "OSMUND FABRIKS AB",
            "pnr": "75105",
            "address": "Uppsala 1, Såg arg 9-11. Box 287.",
            "phone_number": "018-13 95 55",
            "bank_details": {
                "bankgiro": "80-2131",
                "postgiro": "26688"
            },
            "activity": "Elektriska, oljeeldade o gaseldade industriugnar, oljebrännare, regulatorer, högtrycksfläktar, tegelsågar mm. Mekanisk verkstad for legoarbeten",
            "employees": 80,
            "annual_turnover": 6000000,
            "capital": 515000,
            "key_personnel": [
                {
                    "name": "Karl-Einar Lundberg",
                    "position": "Veikst dir"
                }
            ],
            "establishment_year": 0
        },
        "2": {
            "company_name": "OSRAM-ELEKTRAVERKEN, AB",
            "pnr": "104 60",
            "address": "Stockholm 20, Box 20050. Virkesv 21.",
            "phone_number": "08-44 94 40",
            "postgiro": "727-8",
            "activity": "Tillverkar o försäljer glödlampor av märket 'Osram'",
            "employees": 300,
            "capital": 2750000,
            "key_personnel": [
                {
                    "name": "Gösta Ginner",
                    "position": "Veikst dir"
                }
            ],
            "establishment_year": 1906
        },
        "3": {
            "company_name": "VÄSTKUSTREKLAM, AB",
            "pnr": "417 04",
            "address": "Göteborg, Kvilleg 9.",
            "phone_number": "031-23 43 66, 2238 64",
            "postgiro": "420821",
            "activity": "Märkesvaruskyltningar",
            "employees": 15,
            "annual_turnover": 400000,
            "capital": 30000,
            "key_personnel": [
                {
                    "name": "Ove Håkansson",
                    "position": "Verkst din"
                }
            ],
            "establishment_year": 1960
        },
        "4": {
            "company_name": "FORSSJO NYA TRÄVARU AB",
            "pnr": "64100",
            "address": "Katrineholm, Fredsg 63.",
            "phone_number": "0150-13160",
            "postgiro": "87975",
            "activity": "Tillverkar lådor o låd-ämnen",
            "capital": 320000,
            "key_personnel": [
                {
                    "name": "Karl August Malmnäs",
                    "position": "Verkst dir"
                }
            ],
            "establishment_year": 1934
        },
        "5": {
            "company_name": "SCANDIA PLYWOOD AB",
            "pnr": "660 56",
            "address": "Skattkärr, Box 42.",
            "phone_number": "054-60180",
            "bank_details": {
                "bankgiro": "438-8724",
                "postgiro": "94374-6"
            },
            "activity": "Tillverkar plywood för inomhus- o utomhusbruk, form-plywood för betonggjutning samt lamellträ",
            "employees": 90,
            "annual_turnover": 7000000,
            "capital": 360000,
            "key_personnel": [
                {
                    "name": "Civiling Erik Wästlund",
                    "position": "Styrelse"
                },
                {
                    "name": "Nils Allström",
                    "position": "bankdir"
                },
                {
                    "name": "Karl Danielsson",
                    "position": "nämndeman"
                },
                {
                    "name": "Ake Rehnberg",
                    "position": "fil lic"
                },
                {
                    "name": "Bengt Wästlund",
                    "position": "disp"
                }
            ],
            "establishment_year": 1935
        },
        "6": {
            "company_name": "SCANDIA PRESENT AB (f d Mitab AB o AB Ystad-Metall)",
            "pnr": "292 00",
            "address": "Karlshamn, Box 60.",
            "phone_number": "0454-144 90",
            "bank_details": {
                "bankgiro": "670-3 1 93",
                "postgiro": "532366-2"
            },
            "activity": "Tillverkar o säljer presentartiklar i metall",
            "employees": 70,
            "annual_turnover": 5000000,
            "capital": 1000000,
            "key_personnel": [
                {
                    "name": "Töre Berg",
                    "position": "Verkst dir"
                },
                {
                    "name": "Inge Gärsgård",
                    "position": "Disp"
                }
            ],
            "establishment_year": 1970
        },
        "7": {
            "company_name": "B ELMA, AB",
            "pnr": "78101",
            "address": "Borlänge 1, Box 14.",
            "phone_number": "0243-260 60",
            "bank_details": {
                "bankgiro": "794-5272",
                "postgiro": "462568-7"
            },
            "activity": "Säljer biltillbehör i parti. Import o export",
            "employees": 9,
            "annual_turnover": 2500000,
            "capital": 32000,
            "key_personnel": [
                {
                    "name": "Kurt Astor",
                    "position": "Verkst dir"
                }
            ],
            "establishment_year": 1950
        },
        "8": {
            "company_name": "fliesberg ab, gunnar",
            "pnr": "16116",
            "address": "Bromma 16, Fack 2. Smedslätts-torget 49.",
            "phone_number": "08-26 99 24, 269925",
            "bank_details": {
                "bankgiro": "33-1097",
                "postgiro": "602235-4"
            },
            "activity": "Björk- o flygplansply-wood, lamellträ, spånskivor, laminat",
            "key_personnel": [
                {
                    "name": "Gunnar Fliesberg",
                    "position": "Ägare o chef"
                }
            ],
            "establishment_year": 1959
        },
        "9": {
            "company_name": "BRODIN & SON, AB",
            "pnr": "73101",
            "address": "Köping 1, Industrig. Box 137.",
            "phone_number": "0221-10172",
            "bank_details": {
                "bankgiro": "81-1306",
                "postgiro": "296302-3"
            },
            "activity": "Tillverkar svetsade järn- o stålkonstruktioner",
            "employees": 30,
            "annual_turnover": 1000000,
            "capital": 30000,
            "key_personnel": [
                {
                    "name": "Gösta Brodin",
                    "position": "Verkst dir"
                }
            ],
            "establishment_year": 1920
        },
        "10": {
            "company_name": "FALLENIUS & LEFFLERS AB",
            "pnr": "403 10",
            "address": "Göteborg 2, Fack. Packhusplatsen 2.",
            "phone_number": "031-17 39 00",
            "activity": "Nationella o internationella transporter per båt, järnväg, lastbil o flyg, samlastning, spedition, skeppsmäkleri, klare-ring, lagring, transportrådgivning, resebyrå",
            "capital": 4200000,
            "key_personnel": [
                {
                    "name": "S Johansson",
                    "position": "Verkst dir"
                }
            ],
            "establishment_year": 1891
        },
        "11": {
            "company_name": "MEYER AB, CARL",
            "pnr": "41109",
            "address": "Göteborg, O Hamng 46.",
            "phone_number": "031-1056 32, 105633",
            "postgiro": "404 1 9-4",
            "activity": "Försäkringar",
            "employees": 5,
            "capital": 15000,
            "key_personnel": [
                {
                    "name": "Lennart Dahlöf",
                    "position": "Verkst dir"
                }
            ],
            "establishment_year": 1855
        },
        "12": {
            "company_name": "M F R MELLANSVENSK FORE-TAGSRATIONALISERING AB",
            "pnr": "724 66",
            "address": "Västerås, Jonas Wenströms g 13.",
            "phone_number": "021-12 02 25",
            "bank_details": {
                "bankgiro": "367-5790",
                "postgiro": "688140-3"
            },
            "activity": "Administrativ o teknisk rationalisering. Utbildning. Bokföring. Konstruktion",
            "employees": 40,
            "annual_turnover": 3000000,
            "capital": 50000,
            "key_personnel": [
                {
                    "name": "Bertil Ohlsson",
                    "position": "Styrelse"
                },
                {
                    "name": "Akke Svahnberg",
                    "position": "övering chefer"
                },
                {
                    "name": "Gösta Nilsson",
                    "position": "övering chefer"
                },
                {
                    "name": "Nils Möller",
                    "position": "övering chefer"
                }
            ],
            "establishment_year": 1966
        },
        "13": {
            "company_name": "SYDSVENSKA SMÅHUS AB",
            "pnr": "21120",
            "address": "Malmö, Skeppsbron 3.",
            "phone_number": "040-733 65",
            "bank_details": {
                "bankgiro": "640-6755",
                "postgiro": "632920-5"
            },
            "activity": "Projekterar villor. Säljer byggsatser i lättbetong o sten",
            "employees": 20,
            "annual_turnover": 12000000,
            "capital": 450000,
            "key_personnel": [
                {
                    "name": "Leo Kramår",
                    "position": "Verkst dir"
                }
            ],
            "establishment_year": 1962
        }
    }
}