{
    "original": "ANDERSSON, AB HERBERT\n\nPnr 270 53\n\nGärsnäs. Tel 0414-503 00.\nBankgiro 662-5024. Postgiro 146863-6\nVerksamhet: Tillverkar bord, stolar,\nskåp, soffor, fåtöljer o inredningar\nAntal anställda: 70\nÅrsomsättning: 4 000 000\n.Aktiekapital: 200 000\nVerkst dir: Inredn-ark Elias Barup\nEtableringsår: 1893.\n\nBESKOW, H\n\nPnr 11523\n\nStockholm, Lützeng 3. Tel\n08-618314, 62 09 31. Postgiro 190100.\nTga Bestwood\n\nVerksamhet: Agentur i utländska\nträvaror\n\nÄgare o chef: Dir Helge Beskow\nEtableringsår: 1933.\n\nBORÅS TAPETFABRIKS AB\n\nPnr 50102\n\nBorås 1, Box 1. Surbrunnsg 10. Tel\n033-1273 20. Bankgiro 839-1443.\nPostgiro 15185-2. TgaTapetfabriken\nVerksamhet: Tillverkar o säljer\ntapeter\n\nVarunamn: Borosan, Boroton, Wymura\nAntal anställda: 55\nÅrsomsättning: 12 000 000\nAktiekapital: 983000\nStyrelse: Dir Harry Follinge (ordf),\ndir Karl-Axel Nyberg, dir Sven\nStenlund, dir Ake Stenlund\nVerkst dir: Harald Bodin\nJourh styr ledamot: Dir Ake\nStenlund\n\nEtableringsår: 1905.\n\nVATTENANALYS AB\n\nPnr 602 22\n\nNorrköping, Slottsg 116. Tel\n011-18 67 20. Postgiro 669090\nVerksamhet: Laboratorium för\nfysi-kalisk-kemiska o bakteriologiska\nundersökningar\nAntal anställda: 4\nÅrsomsättning: 150 000\nAktiekapital: 5 000\nVerkst dir: Ing John A Sandlund\nEtableringsår: 1965.\n\nVATTENBYGGNADSBYRÅN\n(VBB), AB\n\nPnr 102 41\n\nStockholm 5, Linnég 2. Box 5038.\nTel 08-22 85 80. Postgiro 53670-6.\nTga Vatten.\n\nTelex 10477 VATTEN S\nVerksamhet: Konsulterande\ningenjörs- o arkitektverksamhet i in- o\nutlandet för vattenkraft,\ndammbyggnad, hamnbyggnad o farleder,\nbrobyggnad, bergmekanik o geoteknik,\nvattenförsörjning o vattenrening,\navloppsrening, ledningsarbeten,\nsopbehandling, vattenkemi,\nsamhällsplanering, arkitektur,\ntrafikteknik, väg- o gatubyggnad, fri-\n\ntidsanläggningar, fotogrammetri,\nindustrilokalisering,\nindustriplanering, industriprojektering,\nhusbyggnad, byggledning, hiss- o\ntransportteknik, maskinteknik,\nstålkonstruktioner, turbiner o pumpar\nDistriktkontor: Falun, Slagg 7.\nTel 023-230 70\n\nGävle, Staketg 10. Tel 026-18 32 10,\n184710\n\nGöteborg C, Lilla Badhusg 2. Box\n2203, Gbg 2. Tel 031-17 83 00\nKarlstad. Kungsg 12. Tel\n054-1153 40\n\nKramfors, Limstag 17. Tel\n0612-123 95\n\nLinköping, Storg 28. Tel\n013-1112 40\n\nLuleå, Ràdhustorget 2. Tel\n0920-263 00, 236 01\n\nMalmö SV, Geijersg 8. Tel\n040-15 9000\n\nSkellefteå, Strandg 26 ö g. Tel\n0910-763 74\n\nSundsvall, Torgg 8. Box 259. Tel\n060-15 09 00\n\nUmeå, Rådhusesplanaden 17 C. Tel\n090-114940, 114941\nÖrebro, Engelbrektsg 6. Tel\n019-12 49 90\n\nAntal anställda: 1050\nÅrsomsättning: 86 300 000\nAktiekapital: 5 500 000\nStyrelse: Ambassadör Sven\nDahlman (ordf), civiling Nils Berg,\nciviling H Kristensen, civiling\nErik Isgård, prof Gunnar Lindman,\nciviling Bengt Gustafsson,\nciviling Sven Rydman, prof Stig\nNordqvist\n\nVerkst dir: Civiling Nils Berg\nEtableringsår: 1897\nOmbildat 1902.\n\nVATTENTEKNIK AB,\nINGENIÖRSFIRMAN\n\nPnr 21142\n\nMalmö, Regementsg 18. Tel\n040-388 00. Telex 32444. Tga\nVattenteknik\n\nVerksamhet: Anläggningar o filter\nför rening av fabrikations- o\nhushållsvatten, matarvattenrening,\npartiell- o total avsaltning, simbad o\nswimmingpools, vattenverk,\navloppsvattenrening etc\nAvdelningskontor: 18132 Lidingö,\nSturev 68. Tel 08-765 2810. Telex\n1432\n\n417 05 Göteborg, Angpanneg 4. Tel\n031-5130 60. Telex 2247\nVarunamn: Magno\nAntal anställda: 60\nAktiekapital: 100000\nVerkst dir: E Eklund\nEtableringsår: 1940.\n\nBE-PEPLÅT&amp;MEKANISKAAB\n\nPnr 59100\n\nMotala, Myntg 4. Tel 0141-52111.\nBankgiro 67-0912. Postgiro\n712190-8\n\nVerksamhet: Utför legoarbeten,\nsvarvning, fräsning, svetsning\nsamt pressningsarbeten,\nexcenter-o kantpressning\nAntal anställda: 6\nÅrsomsättning: 450 000\nAktiekapital: 5 000\nVerkst dir: Ing Bernt Pettersson\nEtableringsår: 1968.\n\nSERVEX, AB\n\nPnr 102 50\n\nStockholm 27, Tegeluddsv 3. Fack.\nTel 08-63 55 20. Bankgiro 168-1477.\nPostgiro 506630-3\nVerksamhet: Försäljning av\nTV-antenner, tonband, tillbehör till\nradio, TV, bandspelare samt\nelektronikkomponenter såsom\nmottagarrör, halvledare, motstånd,\nkondensatorer, högtalare etc. Service för\nradio, TV, grammofoner,\nbandspelare, hem- o hushållsapparater av\nmärkena Philips, Dux, AGA, Coi&gt;\nserton, Radiola\n\nStyrelse: Dir Olle Franzén (ordf),\ndir Gunnar Nyberg, dir Hans Jacob\nWaern, dir Curt Rödöö, dir Carl\nJohan Tjeder\n\nVerkst dir: Gunnar Nyberg\nEtableringsàr: 1954.\n\nSERV.O.MATIC, AB\n\nPnr 17122\n\nSolna 1. Box 1136. Gustafsv 10.\nTel 08-730 01 95. Bankgiro\n620-7674. Postgiro 440780-5. Tga\nServomatic\n\nVerksamhet: Säljer varu-,\nmusik-o spelautomater\nAntal anställda: 12\nÅrsomsättning: 10 000 000\n\nAktiekapital: 180 000\nVerkst dir: Lars Ek\nEtableringsån 1954.\n\nLAMMPÄLS, AB\n\nPnr 62101\n\nVisby 1, Box 195. Kung Magnusv\n16. Tel 0498-15250. Bankgiro\n833-4039. Postgiro 188 421-2\nVerksamhet: Säljer dampälsar,\njackor, mössor m m\nAntal anställda: 20\nÅrsomsättning: 1000 000\nAktiekapital: 100 000\nVerkst dir. Erie Jolby\nEtableringsår: 1946.\n\nLANA POSTORDER\nBERTIL LARSSON AB\n\nPnr 50010\n\nBorås 10. Tingsg 47. BoX 10025.\nTel 033-12 63 90, 10 19 90.\nBankgiro 19-3013. Postgiro 166620-5\nVerksamhet Postorderförsäljning\ni konfektion\n\nVerkst dir: Bertil Larsson\nEtableringsår: 1961.\n\nLAND och SJÖ, ÖMSESIDIGA\n\nOLYCKSFALLSFÖRSÄKRINGS.\n\nBOLAGET\n\nPnr 103 62\n\nStockholm 3, Sveav 39. Box 3128.\nTel 08-22 49 50. Bankgiro 73-0414.\nPostgiro 521. Tga Landochsjö\nVerksamhet: Försäkring jämlikt\nlagen den 14 maj 1954 om\nyrkesskadeförsäkring\nAntal anställda: 20\nPremieinkomst: 366 000\nFonder: 190000 000\nStyrelse: Justitieråd Nils Regner\n(ordf), civiling Gunnar Berg(vordf),\nförsäkrings dir Otto Fröman, disp\nPer Olof Hedberg, bank’dir Bertil\nHedensjö, konsul Carl-Otto\nHillerström, försäkringsdir Trygve\nLovén, dir J O Nauclér, dir Tage\nOlby, ing Henrik Ofvergård\nVerkst dir: Otto Fröman\nV verkst dir: Anders Ekman\nÖverläkare: Bertil Blomstedt\nAktuarie: Walter Andersson\nRäkenskapsavd: Kamrer Ulla\nIvarson\n\nEtableringsår: 1917.\n\nCLARKSON LTD AB\n\nPnr 400 20\n\nGöteborg 14, Box 14064. Kulleg 10.\nTel 031-20 2644, 2026 45.\nBankgiro 848-2309. Postgiro 622560-1.\nTelex 20926 CLARKSN S\nVerksamhet: Säljer Clarkson\nverktyg såsom fräsverktyg, chuckar,\ngängverktyg, borrar brotchar samt\nverktygsslipmaskiner\nVarunamn: Clarkson\nAntal anställda: 5\nÅrsomsättning: 1500 000\nAktiekapital: 25 000\nStyrelse: Dir Jan Bengtsson (ordf),\nadv Jan Melin\nVerkst dir: Jan Bengtsson\nEtableringsår: 1961.\n\nELIASSON AB, AXEL\n\nPnr 126 12 Sthlm 42\nHägersten, Vretensborgsv 5. Box\n42106, Sthlm 42. Tel 08-19 0 2 20.\nBankgiro 477-9351. Postgiro\n1365-6. Tga Ljustryck\nVerksamhet: Konstförlag.\nTillverkar vy- o brevkort\nAntal anställda: 40\nÅrsomsättning: 5 500 000\nAktiekapital: 150 000\nStyrelse: Dir Folke Lindberg (ordf),\ndir Stig Hedlund, dir Torsten\nPehrsson\n\nVerkst dir: Torsten Pehrsson\nEtableringsår: 1890.\n\nWINGSTEDT AB. KURT\n\nPnr 111 24\n\nStockholm. Walling 37. Tel\n08-14 04 40. Bankgiro 728-7659.\nPostgiro 536220-2\n\nVerksamhet: Reklam o information.\nAnnonser, trycksaker, stillfilm m m\nAntal anställda: 16\nÅrsomsättning: 5 000000\nAktiekapital: 50 000\nVerkst dir: Kurt Wingstedt\nEtableringsår: 1963.",
    "structured": {
        "1": {
            "company_name": "ANDERSSON, AB HERBERT",
            "address": "Gärsnäs",
            "phone_number": "0414-503 00",
            "bank_details": {
                "bankgiro": "662-5024",
                "postgiro": "146863-6"
            },
            "activity": "Tillverkar bord, stolar, skåp, soffor, fåtöljer o inredningar",
            "employees": 70,
            "annual_turnover": 4000000,
            "capital": 200000,
            "key_personnel": [
                {
                    "name": "Inredn-ark Elias Barup",
                    "position": "Verkst dir"
                }
            ],
            "establishment_year": 1893
        },
        "2": {
            "company_name": "BESKOW, H",
            "address": "Stockholm, Lützeng 3",
            "phone_number": "08-618314, 62 09 31",
            "bank_details": {
                "postgiro": "190100"
            },
            "activity": "Agentur i utländska trävaror",
            "key_personnel": [
                {
                    "name": "Dir Helge Beskow",
                    "position": "Ägare o chef"
                }
            ],
            "establishment_year": 1933
        },
        "3": {
            "company_name": "BORÅS TAPETFABRIKS AB",
            "address": "Borås 1, Box 1, Surbrunnsg 10",
            "phone_number": "033-1273 20",
            "bank_details": {
                "bankgiro": "839-1443",
                "postgiro": "15185-2"
            },
            "activity": "Tillverkar o säljer tapeter",
            "employees": 55,
            "annual_turnover": 12000000,
            "capital": 983000,
            "key_personnel": [
                {
                    "name": "Dir Harry Follinge (ordf)",
                    "position": "Styrelse"
                },
                {
                    "name": "Dir Karl-Axel Nyberg",
                    "position": "Styrelse"
                },
                {
                    "name": "Dir Sven Stenlund",
                    "position": "Styrelse"
                },
                {
                    "name": "Dir Ake Stenlund",
                    "position": "Styrelse"
                },
                {
                    "name": "Harald Bodin",
                    "position": "Verkst dir"
                }
            ],
            "establishment_year": 1905
        },
        "4": {
            "company_name": "VATTENANALYS AB",
            "address": "Norrköping, Slottsg 116",
            "phone_number": "011-18 67 20",
            "bank_details": {
                "postgiro": "669090"
            },
            "activity": "Laboratorium för fysi-kalisk-kemiska o bakteriologiska undersökningar",
            "employees": 4,
            "annual_turnover": 150000,
            "capital": 5000,
            "key_personnel": [
                {
                    "name": "Ing John A Sandlund",
                    "position": "Verkst dir"
                }
            ],
            "establishment_year": 1965
        },
        "5": {
            "company_name": "VATTENBYGGNADSBYRÅN (VBB), AB",
            "address": "Stockholm 5, Linnég 2, Box 5038",
            "phone_number": "08-22 85 80",
            "bank_details": {
                "postgiro": "53670-6"
            },
            "activity": "Konsulterande ingenjörs- o arkitektverksamhet i in- o utlandet för vattenkraft, dammbyggnad, hamnbyggnad o farleder...",
            "employees": 1050,
            "annual_turnover": 86300000,
            "capital": 5500000,
            "key_personnel": [
                {
                    "name": "Ambassadör Sven Dahlman (ordf)",
                    "position": "Styrelse"
                },
                {
                    "name": "Civiling Nils Berg",
                    "position": "Verkst dir"
                }
            ],
            "establishment_year": 1897
        },
        "6": {
            "company_name": "VATTENTEKNIK AB, INGENIÖRSFIRMAN",
            "address": "Malmö, Regementsg 18",
            "phone_number": "040-388 00",
            "telex": "32444",
            "activity": "Anläggningar o filter för rening av fabrikations- o hushållsvatten, matarvattenrening, partiell- o total avsaltning, simbad o swimmingpools...",
            "sub_offices": [
                "18132 Lidingö, Sturev 68",
                "417 05 Göteborg, Angpanneg 4"
            ],
            "employees": 60,
            "capital": 100000,
            "key_personnel": {
                "name": "E Eklund",
                "position": "Verkst dir"
            },
            "establishment_year": 1940
        },
        "7": {
            "company_name": "BE-PEPLÅT&M...",
            "address": "Motala, Myntg 4",
            "phone_number": "0141-52111",
            "bank_details": {
                "bankgiro": "67-0912",
                "postgiro": "712190-8"
            },
            "activity": "Utför legoarbeten, svarvning, fräsning, svetsning samt pressningsarbeten, excenter-o kantpressning",
            "employees": 6,
            "annual_turnover": 450000,
            "capital": 5000,
            "key_personnel": {
                "name": "Ing Bernt Pettersson",
                "position": "Verkst dir"
            },
            "establishment_year": 1968
        },
        "8": {
            "company_name": "SERVEX, AB",
            "address": "Stockholm 27, Tegeluddsv 3",
            "phone_number": "08-63 55 20",
            "bank_details": {
                "bankgiro": "168-1477",
                "postgiro": "506630-3"
            },
            "activity": "Försäljning av TV-antenner, tonband, tillbehör till radio, TV, bandspelare samt elektronikkomponenter...",
            "key_personnel": [
                {
                    "name": "Dir Olle Franzén (ordf)",
                    "position": "Styrelse"
                },
                {
                    "name": "Dir Gunnar Nyberg",
                    "position": "Verkst dir"
                }
            ],
            "establishment_year": 1954
        },
        "9": {
            "company_name": "SERV.O.MATIC, AB",
            "address": "Solna 1, Box 1136, Gustafsv 10",
            "phone_number": "08-730 01 95",
            "bank_details": {
                "bankgiro": "620-7674",
                "postgiro": "440780-5"
            },
            "activity": "Säljer varu-, musik-o spelautomater",
            "employees": 12,
            "annual_turnover": 10000000,
            "capital": 180000,
            "key_personnel": {
                "name": "Lars Ek",
                "position": "Verkst dir"
            },
            "establishment_year": 1954
        },
        "10": {
            "company_name": "LAMMPÄLS, AB",
            "address": "Visby 1, Box 195, Kung Magnusv 16",
            "phone_number": "0498-15250",
            "bank_details": {
                "bankgiro": "833-4039",
                "postgiro": "188 421-2"
            },
            "activity": "Säljer dampälsar, jackor, mössor m m",
            "employees": 20,
            "annual_turnover": 1000000,
            "capital": 100000,
            "key_personnel": {
                "name": "Erie Jolby",
                "position": "Verkst dir"
            },
            "establishment_year": 1946
        },
        "11": {
            "company_name": "LANA POSTORDER BERTIL LARSSON AB",
            "address": "Borås 10, Tingsg 47, BoX 10025",
            "phone_number": "033-12 63 90, 10 19 90",
            "bank_details": {
                "bankgiro": "19-3013",
                "postgiro": "166620-5"
            },
            "activity": "Postorderförsäljning i konfektion",
            "key_personnel": {
                "name": "Bertil Larsson",
                "position": "Verkst dir"
            },
            "establishment_year": 1961
        },
        "12": {
            "company_name": "LAND och SJÖ, ÖMSESIDIGA OLYCKSFALLSFÖRSÄKRINGS.BOLAGET",
            "address": "Stockholm 3, Sveav 39, Box 3128",
            "phone_number": "08-22 49 50",
            "bank_details": {
                "bankgiro": "73-0414",
                "postgiro": "521"
            },
            "activity": "Försäkring jämlikt lagen den 14 maj 1954 om yrkesskadeförsäkring",
            "employees": 20,
            "premium_income": 366000,
            "funds": 190000000,
            "key_personnel": [
                {
                    "name": "Justitieråd Nils Regner",
                    "position": "Styrelse"
                },
                {
                    "name": "Civiling Gunnar Berg",
                    "position": "Styrelse"
                },
                {
                    "name": "Försäkrings dir Otto Fröman",
                    "position": "Styrelse"
                },
                {
                    "name": "Disp Per Olof Hedberg",
                    "position": "Styrelse"
                },
                {
                    "name": "Bank’dir Bertil Hedensjö",
                    "position": "Styrelse"
                },
                {
                    "name": "Konsul Carl-Otto Hillerström",
                    "position": "Styrelse"
                },
                {
                    "name": "Försäkringsdir Trygve Lovén",
                    "position": "Styrelse"
                },
                {
                    "name": "Dir J O Nauclér",
                    "position": "Styrelse"
                },
                {
                    "name": "Dir Tage Olby",
                    "position": "Styrelse"
                },
                {
                    "name": "Ing Henrik Ofvergård",
                    "position": "Styrelse"
                },
                {
                    "name": "Otto Fröman",
                    "position": "Verkst dir"
                }
            ],
            "establishment_year": 1917
        },
        "13": {
            "company_name": "CLARKSON LTD AB",
            "address": "Göteborg 14, Box 14064, Kulleg 10",
            "phone_number": "031-20 2644, 2026 45",
            "bank_details": {
                "bankgiro": "848-2309",
                "postgiro": "622560-1"
            },
            "telex": "20926 CLARKSN S",
            "activity": "Säljer Clarkson verktyg såsom fräsverktyg, chuckar, gängverktyg, borrar brotchar samt verktygsslipmaskiner",
            "employees": 5,
            "annual_turnover": 1500000,
            "capital": 25000,
            "key_personnel": [
                {
                    "name": "Dir Jan Bengtsson (ordf)",
                    "position": "Styrelse"
                },
                {
                    "name": "Adv Jan Melin",
                    "position": "Styrelse"
                },
                {
                    "name": "Jan Bengtsson",
                    "position": "Verkst dir"
                }
            ],
            "establishment_year": 1961
        },
        "14": {
            "company_name": "ELIASSON AB, AXEL",
            "address": "Hägersten, Vretensborgsv 5, Box 42106, Sthlm 42",
            "phone_number": "08-19 0 2 20",
            "bank_details": {
                "bankgiro": "477-9351",
                "postgiro": "1365-6"
            },
            "activity": "Konstförlag. Tillverkar vy- o brevkort",
            "employees": 40,
            "annual_turnover": 5500000,
            "capital": 150000,
            "key_personnel": [
                {
                    "name": "Dir Folke Lindberg (ordf)",
                    "position": "Styrelse"
                },
                {
                    "name": "Dir Stig Hedlund",
                    "position": "Styrelse"
                },
                {
                    "name": "Dir Torsten Pehrsson",
                    "position": "Styrelse"
                },
                {
                    "name": "Torsten Pehrsson",
                    "position": "Verkst dir"
                }
            ],
            "establishment_year": 1890
        },
        "15": {
            "company_name": "WINGSTEDT AB. KURT",
            "address": "Stockholm, Walling 37",
            "phone_number": "08-14 04 40",
            "bank_details": {
                "bankgiro": "728-7659",
                "postgiro": "536220-2"
            },
            "activity": "Reklam o information. Annonser, trycksaker, stillfilm m m",
            "employees": 16,
            "annual_turnover": 5000000,
            "capital": 50000,
            "key_personnel": {
                "name": "Kurt Wingstedt",
                "position": "Verkst dir"
            },
            "establishment_year": 1963
        }
    }
}