{
    "original": "fahlen, ab j\n\nPnr 83101\n\nÖstersund 1, Box 539. Prästg 27.\nTel 063-172 80. Postgiro 94004-9\nVerksamhet: Säljer barn- o\ntonårskläder\n\nAntal anställda: 24\nAktiekapital: 55 000\nVeikst dir: Hans Asgårdh\nEtableringsår. 1885.\n\nELEKTRONIKKONTROLL\n\nPnr 161 45\n\nBromma, Arkitektv 52. Tel\n08-26 22 24, 26 7710. Bankgiro\n744-0738. Postgiro 358604-7\nVerksamhet: Konsulterande\ningenjörsbyrå inom elektronik\nChef: Ing Gunnar Högberg\nEtableringsår: 1950.\n\nVVS\n\nAktiekapital: 500 000’\nVerkst dir: Carl-Eric Bojsen\nDisponent: Leif Persson\nEtableringsår: 1960.\n\nETE.TRYCKERIET\n\nPnr 602 27\n\nNorrköping, Hospitalsg 1 A. Tel\n011-13 20 01. Bankgiro 34-9284.\nPostgiro 103885\nVerksamhet; Tryckeri\nChef: Boktr Evert Edlund\nEtableringsår: 1951.\n\nNORRLJUS, AB\n\nPnr 820 60\n\nDelsbo, Fredriksfors. Tel\n0653-230 33, 23055. Bankgiro 785-9085.\nPostgiro 580570-0. Tga Norrljus\nVerksamhet: Tillverkar o säljer ljus\nav alla slag\nVarunamn: Norrljus\nAntal anställda: 100\nÅrsomsättning: 9 000 000\nAktiekapital: 5 000\nStyrelse: Dir Ebbe Christensson,\ndir Dick Reuterskiöld\nChef: Disp Bertil Swenson\nEtableringsår: 1955.\n\nNORRLÄNDSKA BETONG- och\nSTENINDUSTRI AB\n\nPnr 840 76\n\nStugun. Tel 0695-10035, 10065.\nBankgiro 37-0435. Postgiro 95380\nVerksamhet: Levererar betong- o\nvägbeläggningsmaterial\nAktiekapital: 500 000\nVerkst din Sven Jansson\nEtableringsår: 1946.\n\nNORRLÄNDSKA REPRODUK.\nTIONSANSTALTEN, AB\n\nPnr 90103\n\nUmeå 1, Storg 18. Box 150. Tel\n090-1169 95. Bankgiro 461540\nVerksamhet: Utför ljuskopiering,\nkontaktkopiering, skaländringar,\ncronaflexkopior, teknokopior,\narkiv-o mikrofotografering, bildkort,\nfotostat-o el-statkopior,\nelektrostencil-er, duplicering, kontors- o\nsnabboffset, boktryck, folieprägling\nAvdelningskontor: Umeå, Kungsg\n119. Tel 090-1159 95\nAntal anställda: 13\nVerkst din David Andersson\nEtableringsår: 1950.\n\nNORRLÄNDSKA SOCIALDEMO.\nKRATEN, TRYCKERI-AB\n\nPnr 961 01\n\nBoden 1, Fabriks g 6. Box 182. Tel\n0921-136 20. Bankgiro 600-7934.\nPostgiro 60093-2.\nTga Norrländskan. Telex 8301\nVerksamhet: Tidningsutgivning\nAntal anställda: 178\nÅrsomsättning: 15 000 000\nAktiekapital: 600 000\nVerkst dir: Harald Johansson\nChefred: Lars Fagerström\nEtableringsår: 1918.\n\nNORRLÄNDSKA VERKTYGS.\nFABRIKEN\n\nPnr 830 70\n\nHammerdal. Tel 0644-105 45.\nBankgiro 77-9348. Postgiro 160430\nVerksamhet:Tillverkar NOVA elektr\nsvetsaggregat o svetsutrustningar\nÄgare o chef: Lars Erie Nilsson\nEtableringsån 1956.\n\nNORRMALMS GJUTERI &amp; MEK\nVERKSTAD, AB\n\nPnr 502 39\n\nBorås, Stenbocksg 18. Tel\n033-11 17 75. Bankgiro 531-2725.\nPostgiro 28577-3\n\nVerksamhet: Sprutverktyg för plast.\nValsar. Kugghjul\nAntal anställda: 15\nÅrsomsättning: 700 000\nVerkst dir: L O Larson\nEtableringsån 1901.\n\nSAL\n\nVerksamhet: Generalrepresentant\nför utländska tillverkare av\nelektroniska komponenter\nAktiekapital: 20 000\nVerkst dir: Ing N T Håkansson\nEtableringsår 1899.\n\nCEN\n\n254156-3. Tga Ceholmab\nVerksamhet: Rådgivande ingenjörer\nför hus-, väg- o\nvattenbyggnadskonstruktioner\n\nAvdelningskontor: 211 20 Malmö,\nCitadellsv 17. Tel 040-706 80\n352 34 Växjö, S Järnvägsg 4. Tel\n0470-104 35\nAntal anställda: 60\nÅrsomsättning: 4 05 0 000\nAktiekapital: 480 000\nStyrelse: Bankdir Anders Winblad\n(ordf), tekn dr Ake Holmberg,\nkamrer Göte Ekberg, tekn lic Erik\nPlem, civiling Nils Dahlqvist, ing\nLennart Klarin, civiling Sten\nLindgren, civiling Karl-Gustaf Lye,\nciviling Ingvar Wiking\nVerkst dir: Ake Holmberg\nEtableringsår: 1954.\n\nCENTERLOF AB,\nINGENJÖRS-BYRÅN NILS\n\nPnr 213 64\n\nMalmö. Emilstorps g 29. Tel\n040-94 22 80. Bankgiro 870-4199.\nPostgiro 539332-7. Tga Ceab\nVerksamhet: Konsulterande\ningenjörer för hus-, väg- o\nvattenbyggnadskonstruktioner. Industriprojektering\n\nAntal anställda: 30\n\nÅrsomsättning: 2 000 000\n\nAktiekapital: 150 000\n\nVerkst dir: Civiling Nils Centerlöf\n\nIndustriprojektering: övering Erie\n\nHellström\n\nEtableringsår: 1963\n\nHelägt dotterföretag till Kjessler\n\n&amp; Mannerstråle AB, Stockholm.\n\nCENTRAL ELECTRIC\n\nPnr 200 40\n\nMalmö 8, Box 8078. Pinlandsg 6.\nTel 040-96 02 90. Bankgiro\n260-5533. Postgiro 245748-9\nVerksamhet: Säljer svagströms- o\ntidkontrollanläggningar, elektriska\nur, tornur o tidur. Utför service o\nreparationsarbeten. Representanter\nför Westerstrand &amp; Söner Urfabrik,\nTöreboda\n\nChef: Gösta Fransson\nEtableringsår: 1946.\n\nTRANG IA AB\n\nPnr 830 47\n\nTrångsviken, Box 5. Tel\n0640-400 17. Bankgiro 19-8938. Postgiro\n12779-5. Tga Trangia\nVerksamhet: Tillverkar kokkärl för\nfriluftsbruk. Utför legoarbeten\nVarunamn: Trangia\nAntal anställda: 12\nÅrsomsättning: 800 000\nAktiekapital: 100000\nVerkst dir: John E Jonsson\nEtableringsår 1925.\n\nRIMA AB\n\nPnr 102 42\n\nStockholm 5, Grev Tureg 15. Box\n5077. Tel 08-67 90 15. Bankgiro\n13-6700. Postgiro 156700. Telex 17153.\nTga Rimabolagen\nVerksamhet: Säljer pumpar o\ntillbehör, rör-, värme- o\nsanitetsarma-tur, rörverktyg, Heinrich Singer\nrördelar, Schönebecker\nsilrörsbrun-nar, Cewe elektr apparater, OBO\nFestholz\n\nAntal anstäUda: 20\nÅrsomsättning: 4 000 000\nAktiekapital: 150 000\nStyrelse: Dir Ake Dunér\nVerkst dir: Ake Dunér\nFörsäljn-chef: Folke Attoff\nKamrer: Bengt Edenring\nEtableringsår: 1927\nDotterbolag: Martin Rind AB,\nHändels &amp; Industri AB ÄRO, båda i\nStockholm.\n\nRINALDO &amp; JOHANSSON AB\n\nPnr 692 00\n\nKumla, V Bang 50. Box 104. Tel\n019-709 70. Bankgiro 606-1097.\nPostgiro 30347-9. Tga Rijokartong.\nTelex 73322\n\nVerksamhet: Förpackningsindustri\nmed modernt offsettryckeri\nAntal anställda: 130\nVerkst dir Sune Johansson\nEtableringsår: 1922.\n\nLUGNVIKS BILDEMONTERING\n\nPnr 83105\n\nÖstersund 5, Box 5025. Trådv 13.\nTel 063-133 87. Bankgiro 777-8590.\nPostgiro 446910-2\nVerksamhet: Köper o säljer\nbegagnade bilar o bildelar\nAntal anställda: 5\nÅrsomsättning: 500000\nChef: Sten Edström\nEtableringsår: 1953.\n\nLULEÅ BRYGGERI\nNYCKELBRYGGERIER, AB\n\nPnr 951 01\n\nLuleå 1, Varvsg 1-7. Box 56. Tel\n0920-104 40. Postgiro 23265-2.\nTga Bryggeribolaget\nVerksamhet: Tillverkar o säljer\nmalt- o läskedrycker\nAntal anställda: 145\nÅrsomsättning: 25 000 000\nAktiekapital: 900 000\nStyrelse: Dir Olof Wirström,\ntand-läk Hugo Burström, disp Kjell\nWirström, disp Folke Burström\nVerkst dir: Disp Folke Burström\nV verkst dir: Gustaf Burström\nBrygging: G Sandgren\nEtableringsår: 1908.\n\nLULEÅ KOMMUNALA\nRENHÅLLNINGS-AB\n\nPnr95101\n\nLuleå 1, Box 113. Logementsg 3.\nTel 0920-16230. Bankgiro 65248-7.\nPostgiro 3696556\nVerksamhet: Renhållningsverk o\nåkeri\n\nAntal anställda: 45\nÅrsomsättning: 3 120000\nAktiekapital: 25 150\nVerkst din Gustav Lindgren\nEtableringsår: 1919.\n\nLULEÅ LASTBILCENTRAL\nEK FÖRENING\n\nPnr 95100\n\nLuleå, Sandviksg 11. Tel\n0920-10120. Bankgiro 75-8322.\nPostgiro 65610-8\n\nVerksamhet Transportförmedling\nAntal anställda: 20\nÅrsomsättning: 10 000 000\nVerkst dir. Gunnar Stoltz\nEtableringsår: 1902.",
    "structured": {
        "1": {
            "company_name": "FAHLEN, AB J",
            "pnr": "83101",
            "address": "Östersund 1, Box 539. Prästg 27.",
            "phone_number": "063-172 80",
            "bank_details": {
                "postgiro": "94004-9"
            },
            "activity": "Säljer barn- o tonårskläder",
            "employees": 24,
            "capital": 55000,
            "key_personnel": [
                {
                    "name": "Hans Asgårdh",
                    "position": "Veikst dir"
                }
            ],
            "establishment_year": 1885
        },
        "2": {
            "pnr": "161 45",
            "address": "Bromma, Arkitektv 52.",
            "phone_number": "08-26 22 24, 26 7710",
            "bank_details": {
                "bankgiro": "744-0738",
                "postgiro": "358604-7"
            },
            "activity": "Konsulterande ingenjörsbyrå inom elektronik",
            "key_personnel": [
                {
                    "name": "Ing Gunnar Högberg",
                    "position": "Chef"
                }
            ],
            "establishment_year": 1950
        },
        "3": {
            "activity": "VVS",
            "capital": 500000,
            "key_personnel": [
                {
                    "name": "Carl-Eric Bojsen",
                    "position": "Verkst dir"
                },
                {
                    "name": "Leif Persson",
                    "position": "Disponent"
                }
            ],
            "establishment_year": 1960
        },
        "4": {
            "pnr": "602 27",
            "address": "Norrköping, Hospitalsg 1 A.",
            "phone_number": "011-13 20 01",
            "bank_details": {
                "bankgiro": "34-9284",
                "postgiro": "103885"
            },
            "activity": "Tryckeri",
            "key_personnel": [
                {
                    "name": "Boktr Evert Edlund",
                    "position": "Chef"
                }
            ],
            "establishment_year": 1951
        },
        "5": {
            "company_name": "NORRLJUS, AB",
            "pnr": "820 60",
            "address": "Delsbo, Fredriksfors.",
            "phone_number": "0653-230 33, 23055",
            "bank_details": {
                "bankgiro": "785-9085",
                "postgiro": "580570-0"
            },
            "activity": "Tillverkar o säljer ljus av alla slag",
            "employees": 100,
            "annual_turnover": 9000000,
            "capital": 5000,
            "key_personnel": [
                {
                    "name": "Dir Ebbe Christensson",
                    "position": "Styrelse"
                },
                {
                    "name": "Dir Dick Reuterskiöld",
                    "position": "Styrelse"
                },
                {
                    "name": "Disp Bertil Swenson",
                    "position": "Chef"
                }
            ],
            "establishment_year": 1955
        },
        "6": {
            "company_name": "NORRLÄNDSKA BETONG- och STENINDUSTRI AB",
            "pnr": "840 76",
            "address": "Stugun.",
            "phone_number": "0695-10035, 10065",
            "bank_details": {
                "bankgiro": "37-0435",
                "postgiro": "95380"
            },
            "activity": "Levererar betong- o vägbeläggningsmaterial",
            "capital": 500000,
            "key_personnel": [
                {
                    "name": "Sven Jansson",
                    "position": "Verkst din"
                }
            ],
            "establishment_year": 1946
        },
        "7": {
            "company_name": "NORRLÄNDSKA REPRODUKTIONSANSTALTEN, AB",
            "pnr": "90103",
            "address": "Umeå 1, Storg 18. Box 150",
            "phone_number": "090-1169 95",
            "bank_details": {
                "bankgiro": "461540"
            },
            "activity": "Utför ljuskopiering, kontaktkopiering, skaländringar, etc.",
            "employees": 13,
            "key_personnel": [
                {
                    "name": "David Andersson",
                    "position": "Verkst din"
                }
            ],
            "establishment_year": 1950
        },
        "8": {
            "company_name": "NORRLÄNDSKA SOCIALDEMOKRATEN, TRYCKERI-AB",
            "pnr": "961 01",
            "address": "Boden 1, Fabriks g 6. Box 182",
            "phone_number": "0921-136 20",
            "bank_details": {
                "bankgiro": "600-7934",
                "postgiro": "60093-2"
            },
            "activity": "Tidningsutgivning",
            "employees": 178,
            "annual_turnover": 15000000,
            "capital": 600000,
            "key_personnel": [
                {
                    "name": "Harald Johansson",
                    "position": "Verkst dir"
                },
                {
                    "name": "Lars Fagerström",
                    "position": "Chef"
                }
            ],
            "establishment_year": 1918
        },
        "9": {
            "company_name": "NORRLÄNDSKA VERKTYGSFABRIKEN",
            "pnr": "830 70",
            "address": "Hammerdal",
            "phone_number": "0644-105 45",
            "bank_details": {
                "bankgiro": "77-9348",
                "postgiro": "160430"
            },
            "activity": "Tillverkar NOVA elektr svetsaggregat o svetsutrustningar",
            "key_personnel": [
                {
                    "name": "Lars Erie Nilsson",
                    "position": "Ägare o chef"
                }
            ],
            "establishment_year": 1956
        },
        "10": {
            "company_name": "NORRMALMS GJUTERI & MEK VERKSTAD, AB",
            "pnr": "502 39",
            "address": "Borås, Stenbocksg 18",
            "phone_number": "033-11 17 75",
            "bank_details": {
                "bankgiro": "531-2725",
                "postgiro": "28577-3"
            },
            "activity": "Sprutverktyg för plast. Valsar. Kugghjul",
            "employees": 15,
            "annual_turnover": 700000,
            "key_personnel": [
                {
                    "name": "L O Larson",
                    "position": "Verkst dir"
                }
            ],
            "establishment_year": 1901
        }
    }
}