{
    "original": "LUMALAMPAN AB\n\nPnr 104 60\n\nStockholm, Lumav 6. Tel 44 9100,\nriks 08-44 91 60. Postgiro 156690.\nTga Lumalampan.\nTelex 17431 LUMA S\nVerksamhet: Elektr glödlampor\nÅrsomsättning: 100 000 000\nAktiekapital: 6 000 000\nVerkst dir: Sten Sjöberg\nEtableringsår: 1930.\n\ngerber &amp; hesslow, ab\n\nPnr 103 41\n\nStockholm 40, Box 40017. Sveav\n13-15. Tel 08-24 2040. Bankgiro\n72-2185. Postgiro 53683. Tga\nWolreg. Telex 1538\nVerksamhet: Industriråvaror,\nkonstruktionsmaterial för\nmaskinindustri, maskiner för kemisk\nindustri, import o export\nVarunamn: Aerox, Alcoa, Allgaier,\nAlpine, Frialit, Fryma, Galileo,\nGelsenguss, Krauss-Maffei, Nalco,\nNautamix, Nauta^Vometec,\nPoly-penco, Westfalia\nAntal anställda: 24\nÅrsomsättning: 34 000 000\nAktiekapital: 150 000\nStyrelse: Dir Carl Larsson (ordf),\ndir Sven G Hesslow, adv Rolf\nWidstrand\n\nVerkst dir: Sven G Hesslow\nEtableringsår: 1920.\n\nGRÖNLUND AB, A E\n\nPnr 803 50\n\nGävle, Hamntorget 4. Tel\n026-112957, 112980. Bankgiro\n336-7794. Postgiro 25901-0\nVerksamhet: Tillverkar sjöfärdiga\nfisknät m m. Säljer i parti o minut\nfiskredskap, båtmotorer, båtar,\nbåt-utrustningar, regnkläder m m\nAntal anställda: 5\nAktiekapital: 51000\nVerkst dir: B Einar Grönlund\nEtableringsår: 1904.\n\nLENA.MODELLER, AB\n\nPnr 412 54\n\nGöteborg, södra v 20. Tel\n031-18 79 63. Bankgiro 500-1482.\nPostgiro 49660-4. Tga Lenamode\nVerksamhet: Damkonfektion\nAntal anställda: 8\nAktiekapital: 25 000\nEirmatecknare: AnnarLisa Eklund.\nStig Eklund.\n\nLÉNBERG AB, BRÖDERNA\n\nPnr50103\n\nBorås 1, Box 152. Bryggareg 14.\nTel 033-114119, 132180.\nBankgiro 839-3415. Postgiro 171133-2\nVerksamhet: Tillverkar herr- o\ngosskjortor samt -pyjamas\nVarunamn: Lénbergs\nVerkst dir. Gunnar Lënberg\nEtableringsår: 1939\nOmbildat till aktiebolag 1970.\n\nLENBRO AB\n\nPnr 41110\n\nGöteborg C, O Hamng 15. Tel\n031-17 54 20. Bankgiro 848-1400.\nPostgiro 422175. Tga Lenbro.\nTelex 20877\n\nVerksamhet: Importagenturer i\nråvaror o maskiner för färg-,\npappers*, gummi- o plastindustrin m m\nAktiekapital: 50000\nVerkst dir: Elis Tornberg\nEtableringsår: 1927.\n\nLENHOVDA RADIATOR.\nFABRIKS AB\n\nPnr 360 73\n\nLenhovda. Tel 0474-200 88,20 3 88.\nBankgiro 66-9532.Postgiro 131650.\nTga Radiatorer, Växjö\nVerksamhet: Tillverkar\nplåtradiatorer\n\nAktiekapital: 120 000\nVerkst dir: Yngve Johansson\nEtableringsår: 1936.\n\nLENHOVDA SNICKERI.\nFABRIK, AB\n\nPnr 360 73\n\nLenhovda. Tel 0474-205 20\nVerksamhet: Tillverkar\nbyggnadssnickerier m m, specialitet:\nfönstersnickerier\n\nAntal anställda: 200\nÅrsomsättning: 16 000 000\nAktiekapital: 90 300\nVerkst dir. Harry Magnusson\nEtableringsår: 1922.\n\nPETTERSSON &amp; HELLBERG\n\nPnr 644 00\n\nTorshälla, Järnvägsg 9. Tel\n016-55032. Bankgiro 623-5378.\nPostgiro 27786-3. Tga Saxsprint\nVerksamhet: Tillverkar saxsprintar\n(saxpinnar), rem- o\nelevatorskop-skruv\n\nChef: Ing Gösta Hellberg\nEtableringsår: 1888.\n\nPETTERSSONS JÄRN.\nFORÄDLING, AB\n\nPnr 33033\n\nHillerstorp. Tel 0370-222 05.\nBankgiro 543-2208. Postgiro 37375-3.\nTga Järnförädling\n\nVerksamhet: Tillverkar skruvkrok o\nfiberplattspik\nAntal anställda: 25\nÅrsomsättning: 4 500 000\nAktiekapital: 133 000\nVerkst dir: Erland Törefors\nEtableringsår: 1921.\n\nVEN\n\nAktiekapital: 25 000\nVerkst dir: Lennart Wenström\nEtableringsår: 1914.\n\nOLSSON &amp; CO, AB L\n\nPnr 430 60\n\nLandvetter, Box 33. Tel\n031-7113 06, 7113 80. Bankgiro\n44-4256. Postgiro 243185-6. Tga\nHandleco. Telex 2454\nVerksamhet: Agenturrörelse.\nGeneralagent for ljus från Kameyama\nCandle Co, Ltd samt Famulus\ndammsugare o rakapparater\nVerkst dir: Lennart Olsson\nEtableringsår: 1948\nOmbildat till aktiebolag 1960.\n\nOLSSONS MEK VERKSTAD AB,\nLARS E\n\nPnr 723 35\n\nVästerås, Stockholmsv 11. Tel\n021-13 35 27. Bankgiro 80-8787.\nPostgiro 141487\n\nVerksamhet: Mek verkstad.\nSpecialitet: kuggstångsfräsning\nAktiekapital: 15 000\nChef: Lars Erik Olsson\nEtableringsår: 1935.\n\nOHLSSON &amp; CO MEK\nVERKSTAD, AB M\n\nPnr 213 63\n\nMalmö, Silverviksg 5. Tel\n040-94 34 00. Postgiro 39390-0\nVerksamhet: Tillverkar\nspecialmaskiner för textilindustrin\nAntal anställda: 5\nÅrsomsättning: 375 000\nAktiekapital: 100 000\nVerkst dir: Pabr Manfred Ohlsson\nEtableringsår: 1932.\n\nfalerums snickerifabrik\n\nPnr 590 70\n\nFalerum, Box 148. Tel 0120-200 52.\nBankgiro 652-7121. Postgiro 138396-7\nVerksamhet: Tillverkar o säljer\nköksinredningar o trappor. Säljer\nfönster o dörrar\nAntal anstäUda: 6\nÅrsomsättning: 400 000\nÄgare o chef: Gunno Meidler\nEtableringsår: 1926.\n\nNILSSON &amp; CO, AB C 0\n\nPnr 68100\n\nKristinehamn, Hantverkarg 14. Tel\n0550-153 06, 15307. Postgiro 28623\nVerksamhet: Elektriska\ninstallationer m m o maskiner\nFUial: Karlskoga, Grönfeltsg 3. Tel\n0586-307 45. Förest: K Daun\nAntal anstäUda: 65\nÅrsomsättning: 5 000 000\nAktiekapital: 75 000\nVerkst dir: I Nygren\nEtableringsår: 1916\nOmbüdat till aktiebolag 1933.\n\nNILSSONS ELEKTR RE PARA.\nTIONSVERKSTAD, AB CARL A\n\nPnr 252 27\n\nHälsingborg, Cindersg 11. Tel\n042-113402. Bankgiro 44-5378.\nPostgiro 263961\n\nVerksamhet: Elektrisk o mekanisk\n\nreparationsverkstad\n\nAntal anstäUda: 15\n\nÅrsomsättning: 930 000\n\nAktiekapital: 15 000\n\nVerkst dir: Ing Bertil Stigemar\n\nEtableringsår: 1918.\n\nDUNKEVERKEN, AB\n\nPnr 56023\n\nBankeryd, Box 1. Tallv 5. Tel\n036-771 95. Bankgiro 140-1876.\nPostgiro 369471-8\n\nVerksamhet: Tillverkar\nflaggstänger, antennmaster o gardinbeslag\nAntal anställda: 15\nAktiekapital: 20000\nVerkst dir: Ebbe Andersson\nEtableringsår: 1944\nOmbildat till aktiebolag 1968.\n\nDURIBOLAGET IMPORT &amp;\nEXPORT AB\n\nPnr 12612\n\nStockholm 42. Box 42029.\nVretens-bcrgsv 42, Hägersten. Tel\n08-18 64 36, 18 64 37. Bankgiro\n400-2499. Postgiro 2291-3. Tga Aduri\nVerksamhet: Importerar o säljer\ngolvmaterial samt tillbehör\nAntal anställda: 12\nÅrsomsättning: 2 000 000\nAktiekapital: 5 000\nVerkst dir: Erling Oddestad\nEtableringsår: 1932.\n\nDURO I OREBRO AB,\nINGENJÖRSFIRMAN\n\nPnr 701 05\n\nÖrebro 1, Hertig Karls Allé 8. Box\n333. Tel 019-12 36 02. Telex 73332.\nTga Duro\n\nVerksamhet: Tryckerimaskiner o\ngrafiska artiklar\nAktiekapital: 25 000\nVerkst dir: Thorwald Wisstoff\nEtableringsår: 1946.",
    "structured": {
        "1": {
            "company_name": "LUMALAMPAN AB",
            "pnr": "104 60",
            "address": "Stockholm, Lumav 6",
            "phone_number": "44 9100, riks 08-44 91 60",
            "postgiro": "156690",
            "activity": "Elektr glödlampor",
            "annual_turnover": 100000000,
            "capital": 6000000,
            "key_personnel": [
                {
                    "name": "Sten Sjöberg",
                    "position": "Verkst dir"
                }
            ],
            "establishment_year": 1930
        },
        "2": {
            "company_name": "gerber & hesslow, ab",
            "pnr": "103 41",
            "address": "Stockholm 40, Box 40017, Sveav 13-15",
            "phone_number": "08-24 2040",
            "postgiro": "53683",
            "bank_details": {
                "bankgiro": "72-2185"
            },
            "activity": "Industriråvaror, konstruktionsmaterial för maskinindustri, maskiner för kemisk industri, import o export",
            "employees": 24,
            "annual_turnover": 34000000,
            "capital": 150000,
            "key_personnel": [
                {
                    "name": "Carl Larsson",
                    "position": "Styrelse Dir"
                },
                {
                    "name": "Sven G Hesslow",
                    "position": "Dir"
                },
                {
                    "name": "Rolf Widstrand",
                    "position": "adv"
                }
            ],
            "establishment_year": 1920
        },
        "3": {
            "company_name": "GRÖNLUND AB, A E",
            "pnr": "803 50",
            "address": "Gävle, Hamntorget 4",
            "phone_number": "026-112957, 112980",
            "postgiro": "25901-0",
            "activity": "Tillverkar sjöfärdiga fisknät m m. Säljer i parti o minut fiskredskap, båtmotorer, båtar, båt-utrustningar, regnkläder m m",
            "employees": 5,
            "capital": 51000,
            "key_personnel": [
                {
                    "name": "B Einar Grönlund",
                    "position": "Verkst dir"
                }
            ],
            "establishment_year": 1904
        },
        "4": {
            "company_name": "LENA.MODELLER, AB",
            "pnr": "412 54",
            "address": "Göteborg, södra v 20",
            "phone_number": "031-18 79 63",
            "bank_details": {
                "bankgiro": "500-1482"
            },
            "postgiro": "49660-4",
            "activity": "Damkonfektion",
            "employees": 8,
            "capital": 25000,
            "key_personnel": [
                {
                    "name": "AnnarLisa Eklund.",
                    "position": "Eirmatecknare"
                },
                {
                    "name": "Stig Eklund",
                    "position": ""
                }
            ],
            "establishment_year": ""
        },
        "5": {
            "company_name": "LÉNBERG AB, BRÖDERNA",
            "pnr": "50103",
            "address": "Borås 1, Box 152, Bryggareg 14",
            "phone_number": "033-114119, 132180",
            "bank_details": {
                "bankgiro": "839-3415"
            },
            "postgiro": "171133-2",
            "activity": "Tillverkar herr- o gosskjortor samt -pyjamas",
            "employees": "",
            "capital": "",
            "key_personnel": [
                {
                    "name": "Gunnar Lënberg",
                    "position": "Verkst dir"
                }
            ],
            "establishment_year": 1939
        },
        "6": {
            "company_name": "LENBRO AB",
            "pnr": "41110",
            "address": "Göteborg C, O Hamng 15",
            "phone_number": "031-17 54 20",
            "bank_details": {
                "bankgiro": "848-1400"
            },
            "postgiro": "422175",
            "activity": "Importagenturer i råvaror o maskiner för färg-, pappers-, gummi- o plastindustrin m m",
            "employees": "",
            "capital": 50000,
            "key_personnel": [
                {
                    "name": "Elis Tornberg",
                    "position": "Verkst dir"
                }
            ],
            "establishment_year": 1927
        },
        "7": {
            "company_name": "LENHOVDA RADIATOR. FABRIKS AB",
            "pnr": "360 73",
            "address": "Lenhovda",
            "phone_number": "0474-200 88,20 3 88",
            "bank_details": {
                "bankgiro": "66-9532"
            },
            "postgiro": "131650",
            "activity": "Tillverkar plåtradiatorer",
            "employees": "",
            "capital": 120000,
            "key_personnel": [
                {
                    "name": "Yngve Johansson",
                    "position": "Verkst dir"
                }
            ],
            "establishment_year": 1936
        },
        "8": {
            "company_name": "LENHOVDA SNICKERI. FABRIK, AB",
            "pnr": "360 73",
            "address": "Lenhovda",
            "phone_number": "0474-205 20",
            "activity": "Tillverkar byggnadssnickerier m m, specialitet: fönstersnickerier",
            "employees": 200,
            "annual_turnover": 16000000,
            "capital": 90300,
            "key_personnel": [
                {
                    "name": "Harry Magnusson",
                    "position": "Verkst dir"
                }
            ],
            "establishment_year": 1922
        },
        "9": {
            "company_name": "PETTERSSON & HELLBERG",
            "pnr": "644 00",
            "address": "Torshälla, Järnvägsg 9",
            "phone_number": "016-55032",
            "bank_details": {
                "bankgiro": "623-5378"
            },
            "postgiro": "27786-3",
            "activity": "Tillverkar saxsprintar (saxpinnar), rem- o elevatorskop-skruv",
            "key_personnel": [
                {
                    "name": "Ing Gösta Hellberg",
                    "position": "Chef"
                }
            ],
            "establishment_year": 1888
        },
        "10": {
            "company_name": "PETTERSSONS JÄRN. FORÄDLING, AB",
            "pnr": "33033",
            "address": "Hillerstorp",
            "phone_number": "0370-222 05",
            "bank_details": {
                "bankgiro": "543-2208"
            },
            "postgiro": "37375-3",
            "activity": "Tillverkar skruvkrok o fiberplattspik",
            "employees": 25,
            "annual_turnover": 4500000,
            "capital": 133000,
            "key_personnel": [
                {
                    "name": "Erland Törefors",
                    "position": "Verkst dir"
                }
            ],
            "establishment_year": 1921
        },
        "11": {
            "company_name": "VEN",
            "capital": 25000,
            "key_personnel": [
                {
                    "name": "Lennart Wenström",
                    "position": "Verkst dir"
                }
            ],
            "establishment_year": 1914
        },
        "12": {
            "company_name": "OLSSON & CO, AB L",
            "pnr": "430 60",
            "address": "Landvetter, Box 33",
            "phone_number": "031-7113 06, 7113 80",
            "bank_details": {
                "bankgiro": "44-4256"
            },
            "postgiro": "243185-6",
            "activity": "Agenturrörelse. Generalagent for ljus från Kameyama Candle Co, Ltd samt Famulus dammsugare o rakapparater",
            "key_personnel": [
                {
                    "name": "Lennart Olsson",
                    "position": "Verkst dir"
                }
            ],
            "establishment_year": 1948
        },
        "13": {
            "company_name": "OLSSONS MEK VERKSTAD AB, LARS E",
            "pnr": "723 35",
            "address": "Västerås, Stockholmsv 11",
            "phone_number": "021-13 35 27",
            "bank_details": {
                "bankgiro": "80-8787"
            },
            "postgiro": "141487",
            "activity": "Mek verkstad. Specialitet: kuggstångsfräsning",
            "capital": 15000,
            "key_personnel": [
                {
                    "name": "Lars Erik Olsson",
                    "position": "Chef"
                }
            ],
            "establishment_year": 1935
        },
        "14": {
            "company_name": "OHLSSON & CO MEK VERKSTAD, AB M",
            "pnr": "213 63",
            "address": "Malmö, Silverviksg 5",
            "phone_number": "040-94 34 00",
            "postgiro": "39390-0",
            "activity": "Tillverkar specialmaskiner för textilindustrin",
            "employees": 5,
            "annual_turnover": 375000,
            "capital": 100000,
            "key_personnel": [
                {
                    "name": "Pabr Manfred Ohlsson",
                    "position": "Verkst dir"
                }
            ],
            "establishment_year": 1932
        },
        "15": {
            "company_name": "falerums snickerifabrik",
            "pnr": "590 70",
            "address": "Falerum, Box 148",
            "phone_number": "0120-200 52",
            "bank_details": {
                "bankgiro": "652-7121"
            },
            "postgiro": "138396-7",
            "activity": "Tillverkar o säljer köksinredningar o trappor. Säljer fönster o dörrar",
            "employees": 6,
            "annual_turnover": 400000,
            "key_personnel": [
                {
                    "name": "Gunno Meidler",
                    "position": "Ägare o chef"
                }
            ],
            "establishment_year": 1926
        },
        "16": {
            "company_name": "NILSSON & CO, AB C 0",
            "pnr": "68100",
            "address": "Kristinehamn, Hantverkarg 14",
            "phone_number": "0550-153 06, 15307",
            "postgiro": "28623",
            "activity": "Elektriska installationer m m o maskiner",
            "employees": 65,
            "annual_turnover": 5000000,
            "capital": 75000,
            "key_personnel": [
                {
                    "name": "I Nygren",
                    "position": "Verkst dir"
                }
            ],
            "establishment_year": 1916
        },
        "17": {
            "company_name": "NILSSONS ELEKTR RE PARA. TIONSVERKSTAD, AB CARL A",
            "pnr": "252 27",
            "address": "Hälsingborg, Cindersg 11",
            "phone_number": "042-113402",
            "bank_details": {
                "bankgiro": "44-5378"
            },
            "postgiro": "263961",
            "activity": "Elektrisk o mekanisk reparationsverkstad",
            "employees": 15,
            "annual_turnover": 930000,
            "capital": 15000,
            "key_personnel": [
                {
                    "name": "Ing Bertil Stigemar",
                    "position": "Verkst dir"
                }
            ],
            "establishment_year": 1918
        },
        "18": {
            "company_name": "DUNKEVERKEN, AB",
            "pnr": "56023",
            "address": "Bankeryd, Box 1, Tallv 5",
            "phone_number": "036-771 95",
            "bank_details": {
                "bankgiro": "140-1876"
            },
            "postgiro": "369471-8",
            "activity": "Tillverkar flaggstänger, antennmaster o gardinbeslag",
            "employees": 15,
            "capital": 20000,
            "key_personnel": [
                {
                    "name": "Ebbe Andersson",
                    "position": "Verkst dir"
                }
            ],
            "establishment_year": 1944
        },
        "19": {
            "company_name": "DURIBOLAGET IMPORT & EXPORT AB",
            "pnr": "12612",
            "address": "Stockholm 42, Box 42029, Vretens-bcrgsv 42, Hägersten",
            "phone_number": "08-18 64 36, 18 64 37",
            "bank_details": {
                "bankgiro": "400-2499"
            },
            "postgiro": "2291-3",
            "activity": "Importerar o säljer golvmaterial samt tillbehör",
            "employees": 12,
            "annual_turnover": 2000000,
            "capital": 5000,
            "key_personnel": [
                {
                    "name": "Erling Oddestad",
                    "position": "Verkst dir"
                }
            ],
            "establishment_year": 1932
        },
        "20": {
            "company_name": "DURO I OREBRO AB, INGENJÖRSFIRMAN",
            "pnr": "701 05",
            "address": "Örebro 1, Hertig Karls Allé 8, Box 333",
            "phone_number": "019-12 36 02",
            "bank_details": {
                "bankgiro": "25-000"
            },
            "activity": "Tryckerimaskiner o grafiska artiklar",
            "capital": 25000,
            "key_personnel": [
                {
                    "name": "Thorwald Wisstoff",
                    "position": "Verkst dir"
                }
            ],
            "establishment_year": 1946
        }
    }
}