{
    "original": "SALÉN &amp; WICANDER AB\n\nPnr 172 03\n\nSuufcyberg 3, Pack. Vretenv 4,\nSolna. Tel 08-98 06 80. Tga\nSal-wico. Telex 19054\nAvdelningskontor 403 14 Göteborg\n2, Skeppsbroplatsen 1. Box 2253.\nTelex 20660. Tel 031-17 6205\nVarunamn: Bosch, Fenwal, Flight\nRefuelling, Graviner, Gunclean,\nHudson Eng Co, Penco Div, Plalh,\nPut, Rolls-Royce, Rover, Rubery\nOwen, Salwico, Toyota, VDN,\nVer-tol, Wharton, Vogel\nAntal anstäUda: 101\nÅrsomsättning: 35 140 000\nAktiekapital: 600 000\nStyrelse: Civiling Oscar Göran\nAxell, dir Nils Jannerfeldt, dir\nChrister Salén, dir Ake Lindbäck,\ndir Sven Hampus Salén, dir Sture\nödner\n\nVerkst dir. Civiling Oscar Göran\nAxell\n\nEtableringsår. 1945.\n\nCENTRALFILM, AB\n\nPnr 115 27\n\nStockholm, Kaknäs. Tel\n08-63 14 30. Tga Centralfilm.\nTelex 19068\n\nVerksamhet: Producerar film o\nstillfilm för reklam, information,\nundervisning etc\nAntal anställda: 9\nÅrsomsättning: 1000 000\nAktiekapital: 25 000\nStyrelse: Åke Bengtsson (ordf).\nKay Pergament\nVerkst dir: Ake Bengtsson\nEtableringsår: 1945.\n\nCENTRALGARAGET I\nY5TAD AB\n\nPnr 271 00\n\nYstad, Fack. Stcra Västerg 14.\nTel 0411-137 50. Bankgiro\n873-1689. Postgiro 143318-4\nVerksamhet: Auktoriserad\nVolvoåterförsäljare samt service.\nBiluthyrning\nAntal anställda: 36\nÅrsomsättning: 9 000 000\nAktiekapital: 125 000\nStyrelse: Dir Carl Persson (ordf),\nfru Lena Mangbo, fru Eva Persson,\nekonomichef Wilhelm Mellwing\nVerkst dir: Carl Persson\nEkonomichef: Jan Borgström\nFörsäljn-chef: Esthen Ohlsson\nVerkstadschef: Berner Holmgren\nEtableringsår: 1958.\n\nLUNDH AB, HJALMAR\n\nPnr 632 21\n\nEskilstuna, Libergsg 2. Tel\n016-13 1164. Bankgiro 60-1344.\nPostgiro 140297\n\nVerksamhet: Utför förnickling o\nförkromning\nAktiekapital: 60 000\nVerkst dir: Fabr C O Lundh\nEtableringsår: 1911.\n\nESK\n\nESANCO IMPORT AB\n\nPnr 112 29\n\nStockholm. Hjärneg 10. Tel\n08-54 80 88 , 54 80 93,54 7 8 55.\nBankgiro 73-2074. Postgiro 254070. Tga\nMonescostock\n\nVerksamhet: Plastråvaror,\nhalvfabrikat, kemikalier\nVarunamn: Moly-Paul, PBC\nÅrsomsättning: 3 500 000\nAktiekapital: 25 000\nStyrelse: Dir Sten Blomqvist (ordf),\ndir Birger Dahl\nVerkst dir: Birger Dahl\nEtableringsår: 1953.\n\nADB-SYSTEM AB\n\nPnr 400 10\n\nGöteborg 3, Erik Dahlbergsg 4.\nBox 3033. Tel 031-17 78 95.\nBankgiro 509-6995. Postgiro 623392-8\nVerksamhet: Konsult- o\nservicebyrå för kommersiell databehandling\nFilial: Borås, Box 354. Tel\n033-13 84 88\n\nAntal anställda: 17\nÅrsomsättning: 2 000 000\nAktiekapital: 5 000\nChefer Bertil Skoog, Olle Johanson\nEtableringsår: 1962.\n\nWENTZELSHOBBY AB\n\nPnr 10131\n\nStockholm 1, Mäster Samuelsg 65.\nBox 801. Tel 08-24 53 95\nVerksamhet: Tillverkar o säljer\nhobbyartiklar o tillbehör i parti o\nminut\n\nAktiekapital: 60 000\n\nVerkst dir: Sven-Gunnar Wentzel\n\nEtableringsår: 1934.\n\nNORRLANDSBILD AB\n\nPnr 85106\n\nSundsvall 1, Köpmang 16. Box 404.\nTel 060-15 05 05. Bankgiro 18-0210.\nPostgiro 165202\n\nVerksamhet: Reportage o\nindustrifoto, ljus- o fotokopieringar.\nMeterförstoringar, arkivfoto, offsettryck\nAntal anställda: 10\nÅrsomsättning: 650 000\nAktiekapital: 15 000\nVerkst dir: T Persson.\n\nNORRLANDSHUS, AB\n\nPnr 840 60\n\nBräcke. Tel 0693-105 40. Bankgiro\n778-9092. Postgiro 287656-3\nVerksamhet: Monteringsfärdiga\nsegmenthus\n\nÅrsomsättning: 17 000 000\nAktiekapital: 105 000\nVerkst dir: Rudolf Strand\nEtableringsår: 1939.\n\nodmankonfektion ab\n\nPnr 400 22\n\nGöteborg 24, Kristinehöjdsg 8.\nBox 24072. Tel 031-2014 67.\nBankgiro 44-3141. Postgiro 420126\nVerksamhet: Tillverkar barnblusar\nAntal anställda: 4\nÅrsomsättning: 100 000\nAktiekapital: 10 000\nVeikst dir: Torsten ödman\nEtableringsår: 1954.\n\nogren, ab magnus\n\nPnr 500 05\n\nBorås 5, Fjärde Villag 11. Box\n\n55070. Tel 033-12 30 32, 1312 99.\n\nBankgiro 83-9380. Postgiro 348307.\n\nTelex 36015. Tga Magent\n\nVerksamhet: Agenturverksamhet i\n\nelastiska vävnader, bomulls- o\n\nyllevävnader\n\nAktiekapital: 5 000\n\nÄgare o chef: Magnus W ögren\n\nEtableringsån 1951.\n\nLOFAB, AB\n\nPnr 200 25\n\nMalmö 16, Emilstorpsg 24. Box\n16034. Tel 040-94 53 20. Bankgiro\n875-3568. Postgiro 246800-7. Tga\nLofab. Telex 32580\nVerksamhet: Tillverkar fräsar,\nfräsdornar, fräsdornsringar,\nfräs-chuckar o arborrverktyg\nVarunamn: Lofab\nAntal anstäUda: 30\nÅrsomsättning: 2 500 000\nAktiekapital: 100 000\nVerkst dir: Lennart Ohlsson\nEtableringsår: 1948,\n\nLOFTAHAMMARS CEMENT.\nVARUFABRIK, AB\n\nPnr 593 00\n\nVästervik. Tel 0490-115 17.\nBankgiro 368-2416. Postgiro 72931-9\nVerksamhet: Tillverkar o säljer\nbetong o betongvaror\nAktiekapital: 48 000\nVerkst dir: Anders Bäcklund\nEtableringsår: 1929\nOmbildat till aktiebolag 1953.\n\nLOHA, AB\n\nPnr 124 21\n\nBandhagen 1, Rågsveds Centrum.\nBox 26. Tel 08-86 04 60. Bankgiro\n33-1427. Postgiro 4059.\nTga Abloha, Stockholm.\nTelex 10583\n\nVerksamhet: Säljer strumpor o\nstrumpbyxor en gros\nVarunamn: Loha\nAntal anställda: 45\nÅrsomsättning: 17 000 000\nAktiekapital: 700 000\nVerkst dir: Bertil Morin\nEtableringsår: 1933.\n\nBER\n\ngiro 626825-4. Tga Bergberg\nVerksamhet: Kallvalsad plåt,\nfor-matklippt enligt kundens\ntoleransfordringar\nAntal anställda: 6\nÅrsomsättning: 2 500 000\nAktiekapital: 10 000\nVerkst dir: Ing Gunnar Bergsten\nEtableringsår: 1964.",
    "structured": {
        "1": {
            "company_name": "SALÉN & WICANDER AB",
            "pnr": "172 03",
            "address": "Suufcyberg 3, Pack. Vretenv 4, Solna",
            "phone_number": "08-98 06 80",
            "bank_details": {
                "bankgiro": "Not available",
                "postgiro": "Not available"
            },
            "activity": "Varunamn: Bosch, Fenwal, Flight Refuelling, Graviner, Gunclean, Hudson Eng Co, Penco Div, Plalh, Put, Rolls-Royce, Rover, Rubery Owen, Salwico, Toyota, VDN, Ver-tol, Wharton, Vogel",
            "employees": 101,
            "annual_turnover": 35140000,
            "capital": 600000,
            "key_personnel": [
                {
                    "name": "Civiling Oscar Göran Axell",
                    "position": "Verkst dir"
                },
                {
                    "name": "Nils Jannerfeldt",
                    "position": "dir"
                },
                {
                    "name": "Christer Salén",
                    "position": "dir"
                },
                {
                    "name": "Ake Lindbäck",
                    "position": "dir"
                },
                {
                    "name": "Sven Hampus Salén",
                    "position": "dir"
                },
                {
                    "name": "Sture ödner",
                    "position": "dir"
                }
            ],
            "establishment_year": 1945
        },
        "2": {
            "company_name": "CENTRALFILM, AB",
            "pnr": "115 27",
            "address": "Stockholm, Kaknäs",
            "phone_number": "08-63 14 30",
            "bank_details": {
                "bankgiro": "Not available",
                "postgiro": "Not available"
            },
            "activity": "Verksamhet: Producerar film o stillfilm för reklam, information, undervisning etc",
            "employees": 9,
            "annual_turnover": 1000000,
            "capital": 25000,
            "key_personnel": [
                {
                    "name": "Åke Bengtsson",
                    "position": "Verkst dir"
                }
            ],
            "establishment_year": 1945
        },
        "3": {
            "company_name": "CENTRALGARAGET I Y5TAD AB",
            "pnr": "271 00",
            "address": "Ystad, Fack. Stcra Västerg 14",
            "phone_number": "0411-137 50",
            "bank_details": {
                "bankgiro": "873-1689",
                "postgiro": "143318-4"
            },
            "activity": "Verksamhet: Auktoriserad Volvoåterförsäljare samt service. Biluthyrning",
            "employees": 36,
            "annual_turnover": 9000000,
            "capital": 125000,
            "key_personnel": [
                {
                    "name": "Carl Persson",
                    "position": "Verkst dir"
                }
            ],
            "establishment_year": 1958
        },
        "4": {
            "company_name": "LUNDH AB, HJALMAR",
            "pnr": "632 21",
            "address": "Eskilstuna, Libergsg 2",
            "phone_number": "016-13 1164",
            "bank_details": {
                "bankgiro": "60-1344",
                "postgiro": "140297"
            },
            "activity": "Verksamhet: Utför förnickling o förkromning",
            "capital": 60000,
            "key_personnel": [
                {
                    "name": "Fabr C O Lundh",
                    "position": "Verkst dir"
                }
            ],
            "establishment_year": 1911
        },
        "5": {
            "company_name": "ESANCO IMPORT AB",
            "pnr": "112 29",
            "address": "Stockholm, Hjärneg 10",
            "phone_number": "08-54 80 88",
            "bank_details": {
                "bankgiro": "73-2074",
                "postgiro": "254070"
            },
            "activity": "Verksamhet: Plastråvaror, halvfabrikat, kemikalier. Varunamn: Moly-Paul, PBC",
            "employees": 0,
            "annual_turnover": 3500000,
            "capital": 25000,
            "key_personnel": [
                {
                    "name": "Birger Dahl",
                    "position": "Verkst dir"
                }
            ],
            "establishment_year": 1953
        },
        "6": {
            "company_name": "ADB-SYSTEM AB",
            "pnr": "400 10",
            "address": "Göteborg 3, Erik Dahlbergsg 4, Box 3033",
            "phone_number": "031-17 78 95",
            "bank_details": {
                "bankgiro": "509-6995",
                "postgiro": "623392-8"
            },
            "activity": "Verksamhet: Konsult- o servicebyrå för kommersiell databehandling",
            "employees": 17,
            "annual_turnover": 2000000,
            "capital": 5000,
            "key_personnel": [
                {
                    "name": "Bertil Skoog",
                    "position": "chef"
                },
                {
                    "name": "Olle Johanson",
                    "position": "chef"
                }
            ],
            "establishment_year": 1962
        },
        "7": {
            "company_name": "WENTZELSHOBBY AB",
            "pnr": "10131",
            "address": "Stockholm 1, Mäster Samuelsg 65, Box 801",
            "phone_number": "08-24 53 95",
            "activity": "Verksamhet: Tillverkar o säljer hobbyartiklar o tillbehör i parti o minut",
            "capital": 60000,
            "key_personnel": [
                {
                    "name": "Sven-Gunnar Wentzel",
                    "position": "Verkst dir"
                }
            ],
            "establishment_year": 1934
        },
        "8": {
            "company_name": "NORRLANDSBILD AB",
            "pnr": "85106",
            "address": "Sundsvall 1, Köpmang 16, Box 404",
            "phone_number": "060-15 05 05",
            "bank_details": {
                "bankgiro": "18-0210",
                "postgiro": "165202"
            },
            "activity": "Verksamhet: Reportage o industrifoto, ljus- o fotokopieringar. Meterförstor"
        },
        "employees": 10,
        "annual_turnover": 650000,
        "capital": 15000,
        "key_personnel": [
            {
                "name": "T Persson",
                "position": "Verkst dir"
            }
        ],
        "establishment_year": "Not available"
    }
}