{
    "original": "SORIGONA, AB\n\nPnr 232 00\n\nArlöv, Bruksg. Box 83. Tel 040-\n\n43 36 40\n\nVerksamhet: Tillverkar\nhögmolekylärt dextran\nAntal anställda: 25\nÅrsomsättning: 4 000 000\nAktiekapital: 300 000\nVerkst dir: Allan Bäckman\nEtableringsår: 1945\nOmbildat till aktiebolag 1968.\nDotterbolag till AB Cardo.\n\nSOUND RADIO AB\n\nPnr 13100\n\nNacka, Furuv 11. Tel 08-716 78 00,\n716 79 00. Bankgiro 577-4575.\nPostgiro 258927-3. Tga Soundradio\nVerksamhet: Engrosrörelse med\nspecialartiklar i radiobranschen\nAktiekapital: 100 000\nFirmatecknare: Disp Hessel\nGlück-man\n\nEtableringsår: 1947.\n\nSOUTH-VENERN SAWMILLS,\nAB\n\nPnr 400 10\n\nGöteborg 3, Box 3075. Tel\n031-13 06 26. Tga Southvenern\nVerksamhet: Exportförsäljning av\nsågat o hyvlat virke\nFörsäljningskonton Göteborg 3.\nTrävaru AB Allen, Box 3075. Tel\n031-13 32 66. Telex 20789\nVerkst dir: Sten-Ake Johnsson\nEtableringsån 1957.\n\nTRÄ\n\nTRÄ &amp; FANER, AB\n\nPnr 601 03\n\nNorrköping 1, Slottsg 52. Box 170.\nTel 011-12 5488,1283 88. Bankgiro\n12-5024. Postgiro 24963\nVerksamhet: Säljer trävaror o\nfanér\n\nAktiekapital: 50 000\nStyrelseordf: Ulf Beskow\nEtableringsår: 1929.\n\nSELLNER &amp;CO K/B\n\nPnr 590 50\n\nVikingstad, Sjögestad. Tel\n013-820 03. Bankgiro 60-7854.\nPost-gi ro 576344\n\nVerksamhet Säljer fodervaror o\nförnödenheter för pälsdjursgårdar\nÅrsomsättning: 1 000 000\nInsatskapital: 10 000\nChef: T Bellner\nEtableringsår: 1962.\n\nSCANDIACONSULT\nINTERNATIONAL AB\n\nPnr 102 60\n\nStockholm 4, Kapellgränd 7. Fack.\nTel 08-23 74 30. Tga\nScandiaCon-sult\n\nVerksamhet: Totalprojektering\ninom områden som täcks av\nmoderbolaget Orrje &amp; Co AB\nÅrsomsättning: 7 600 000\nAktiekapital: 150 000\nVerkst dir: Rune Lundström\nEtableringsår: 1952.\n\nfleron, ab e\n\nPnr 201 21\n\nMalmö 1, Box 186. Limhamnsv\nlll-ll 3. Tel 040-1600 00, 16 00 90.\nBankgiro 870-1195. Postgiro\n37843-0. Tga Flerona.\nTelex 3112 FLERONA S\nVerksamhet: Säljer\nindustriförnödenheter, bildelar, motorcyklar,\nmotorgräsklippare, universaltraktorer,\nmotorredskap o kugghjul\nAntal anställda: 76\nÅrsomsättning: 12 400 000\nAktiekapital: 1000 000\nStyrelse: Dir Holger Bergërus, fru\nKristina Bergström, dir Bo\nDahlgren, dir Björn Lindhe, dir Axel\nLöfström\n\nVerkst dir: Axel Löfström\nV verkst dir: Björn Lindhe\nFörsäljn-avd: Dir Sten Mellgren,\nR Carlsson, A Känne\nEtableringsår: 1904\nI Flerongruppen ingående bolag:\nSkandinaviska Kugghjuls AB\nAB Motorslip\n\nFastighets AB Leo i Malmö\nMotor-Fleron i Malmö AB\nMotor-Fleron i Stockholm AB\nMotor-Fleron i Göteborg AB\nMotor-Fleron i Sundsvall AB.\n\nflexibox ab\n\nPnr 18107\n\nLidingö 7, Box 724. Bodalsv 2 A.\nTel 08-765 25 55. Bankgiro 74-6557.\nPostgiro 669040. Telex 17421\nVerksamhet: Säljer mekaniska\nplan-tätningar o flexibla axelkopplingar\nAntal anställda: 10\nAktiekapital: 50 000\nFörsäljn-chef: Owe Bergius\nEkonomichef: Stig Hoffner\nEtableringsår: 1965.\n\nfliesberg ab, ingeniors.\nFIRMAN\n\n(Ingår i Hartig Fliesberg\nFöretagen AB)\nPnr 103 81\n\nStockholm 7, Box 7044. Nybrog 3.\nTel 08-23 53 75. Tga Fliesberco.\nTelex 19102 HARTIG S\nVerksamhet: Mekanisk verkstad.\nTillverkar o säljer\nkondensvatten-avledare, nålventiler, silar,\nregulatorer, instrument o\nsäkerhetsventiler samt för cellulosa- o\npappersindustrien: fiberåtervinningsan-läggningar, vakuumregulatorer,\nsuglådor o spritsrör\nVerkstad o lager: Solna,Englundav\n7. Tel 08-98 0240\nVarunamn: Serck Glocon, Crosby,\nD-18, Negretti &amp; Zambra, PVRT,\nPVRK, Sarco, Spirax,\nSven-Peder-sen, Vee-Reg\nEtableringsår: 1931.\n\nfliesbergs sport &amp;\nfritidslagret, ab\n\nPnr 88101\n\nSollefteå, Box 263. Tel\n0620-136 50. Postgiro 543540-9\nVerksamhet: Säljer sport- o fri-\n\ntidsartiklar per postorder o i detalj\nAntal anställda: 19\nÅrsomsättning: 5 200 000\nVerkst din Fredrik Fliesberg\nEtableringsår: 1940.\n\nFALLENIUS RESEBYRÅ AB\n\nPnr 403 17\n\nGöteborg 2, Box 2505. V Hamng 5.\n\nTel 031-17 82 30. Tga Fallenius\nTravel. Telex 21121\nAvdelningskontor. 11187\nStockholm, Box 17076. Tel 08-23 53 30\n200 10 Malmö 17, Box 17076. Tel\n040-774 55\nAntal anställda: 31\nAktiekapital: 50 000\nVerkst dir Tom Fallenius\nEtableringsår: 1954.\n\nBRODIN AB, OLOF\n\nPnr 103 27\n\nStockholm 16, Box 16405.\nRege-ringsg 45. Tel 08-23 53 90.\nBankgiro 724-7364. Postgiro 457743-3.\nTga Brodintime, Brodinsale.\nTelex 1476, 10500\nVerksamhet: Skeppsmäkleri med\nbefraktning, köp o försäljning\nAntal anställda: 11\nAktiekapital: 80 000\nVerkst dir: Ryttmäst Olof Brodin\nEtableringsår: 1923.\n\nBROGÅRDS KVARN &amp;\nTRÄVARU AB\n\nPnr 380 30\n\nRockneby, Box 6. Tel 0480-661 58,\n660 76. Bankgiro 853-6583.\nPostgiro 31992-1. Tga Bromill.\nTelex 43032 BROMILL S\nVerksamhet: Kvarnrörelse,\nspannmålshandel, fodertillverkning,\nsågverksrörelse samt lantbruk\nAntal anställda: 70\nÅrsomsättning: 7 800 000\nAktiekapital: 150 000\nVerkst dir: Torsten Johansson\nEtableringsår: 1940.\n\nCAS\n\nCASLON PRESS\nBOKTRYCKERI AB\n\nPnr 113 59\n\nStockholm, Sveav 90. Tel\n08-15 13 15. Bankgiro 73-4556.\nPostgiro 59420-0\n\nVerksamhet: Tidskrifter o\nreklamtrycksaker\nAntal anställda: 30\nAktiekapital: 5 000\nVerkst dir: Bengt Lagerström\nEtableringsår: 1924.\n\nIWEMA, AB\n\nPnr 414 54\n\nGöteborg V, Chapmansg 4. Tel\n031-124785. Bankgiro 514-8028.\nPostgiro 521657-7. Tga Iwema.\nTelex 20725\n\nVerksamhet: Säljer\nproduktionsmaskiner av olika slag,\nfyllningsmaskiner, förpackningsmaskiner,\nrökanläggningar o utrustningar för\nkonservfabriker, storkök,\ncharkute-rifabriker samt pallastningsmaskin\nför säckar eller kartonger\nAntal anställda: 20\nÅrsomsättning: 9 000 000\nAktiekapital: 100 000\nVerkst dir: Ingvar Weiner\nEtableringsår 1959.\n\nSTOREBRO BRUKS AB\n\nPnr 59083\n\nStorebro. Tel 0492-301 60. Tga\nStorebrobruk\n\nVerksamhet: Snabbsvarvar,\nsegel-o motorbåtar\nAntal anställda: 450\nÅrsomsättning: 27 000 000\nAktiekapital: 1000 000\nVerkst dir: Ivar Gustafsson\nEtableringsår: 1728.",
    "structured": {
        "1": {
            "company_name": "SORIGONA, AB",
            "pnr": "232 00",
            "address": "Arlöv, Bruksg. Box 83",
            "phone_number": "040-43 36 40",
            "activity": "Tillverkar högmolekylärt dextran",
            "employees": 25,
            "annual_turnover": 4000000,
            "capital": 300000,
            "key_personnel": [
                {
                    "name": "Allan Bäckman",
                    "position": "Verkst dir"
                }
            ],
            "establishment_year": 1945
        },
        "2": {
            "company_name": "SOUND RADIO AB",
            "pnr": "13100",
            "address": "Nacka, Furuv 11",
            "phone_number": "08-716 78 00, 716 79 00",
            "bank_details": {
                "bankgiro": "577-4575",
                "postgiro": "258927-3"
            },
            "activity": "Engrosrörelse med specialartiklar i radiobranschen",
            "capital": 100000,
            "key_personnel": [
                {
                    "name": "Disp Hessel Glück-man",
                    "position": "Firmatecknare"
                }
            ],
            "establishment_year": 1947
        },
        "3": {
            "company_name": "SOUTH-VENERN SAWMILLS, AB",
            "pnr": "400 10",
            "address": "Göteborg 3, Box 3075",
            "phone_number": "031-13 06 26",
            "activity": "Exportförsäljning av sågat o hyvlat virke",
            "establishment_year": 1957
        },
        "4": {
            "company_name": "TRÄ TRÄ & FANER, AB",
            "pnr": "601 03",
            "address": "Norrköping 1, Slottsg 52. Box 170",
            "phone_number": "011-12 5488, 1283 88",
            "bank_details": {
                "bankgiro": "12-5024",
                "postgiro": "24963"
            },
            "activity": "Säljer trävaror o fanér",
            "capital": 50000,
            "key_personnel": [
                {
                    "name": "Ulf Beskow",
                    "position": "Styrelseordf"
                }
            ],
            "establishment_year": 1929
        },
        "5": {
            "company_name": "SELLNER & CO K/B",
            "pnr": "590 50",
            "address": "Vikingstad, Sjögestad",
            "phone_number": "013-820 03",
            "bank_details": {
                "bankgiro": "60-7854",
                "postgiro": "576344"
            },
            "activity": "Säljer fodervaror o förnödenheter för pälsdjursgårdar",
            "annual_turnover": 1000000,
            "capital": 10000,
            "key_personnel": [
                {
                    "name": "T Bellner",
                    "position": "Chef"
                }
            ],
            "establishment_year": 1962
        },
        "6": {
            "company_name": "SCANDIACONSULT INTERNATIONAL AB",
            "pnr": "102 60",
            "address": "Stockholm 4, Kapellgränd 7",
            "phone_number": "08-23 74 30",
            "activity": "Totalprojektering inom områden som täcks av moderbolaget Orrje & Co AB",
            "annual_turnover": 7600000,
            "capital": 150000,
            "key_personnel": [
                {
                    "name": "Rune Lundström",
                    "position": "Verkst dir"
                }
            ],
            "establishment_year": 1952
        },
        "7": {
            "company_name": "fleron, ab e",
            "pnr": "201 21",
            "address": "Malmö 1, Box 186, Limhamnsv 111-113",
            "phone_number": "040-1600 00, 16 00 90",
            "bank_details": {
                "bankgiro": "870-1195",
                "postgiro": "37843-0"
            },
            "activity": "Säljer industriförnödenheter, bildelar, motorcyklar, motorgräsklippare, universaltraktorer, motorredskap o kugghjul",
            "employees": 76,
            "annual_turnover": 12400000,
            "capital": 1000000,
            "key_personnel": [
                {
                    "name": "Holger Bergërus",
                    "position": "Verkst dir"
                },
                {
                    "name": "Kristina Bergström",
                    "position": "Styrelse"
                },
                {
                    "name": "Bo Dahlgren",
                    "position": "Styrelse"
                },
                {
                    "name": "Björn Lindhe",
                    "position": "Styrelse"
                },
                {
                    "name": "Axel Löfström",
                    "position": "V verkst dir"
                }
            ],
            "establishment_year": 1904
        },
        "8": {
            "company_name": "flexibox ab",
            "pnr": "18107",
            "address": "Lidingö 7, Box 724, Bodalsv 2 A",
            "phone_number": "08-765 25 55",
            "bank_details": {
                "bankgiro": "74-6557",
                "postgiro": "669040"
            },
            "activity": "Säljer mekaniska plan-tätningar o flexibla axelkopplingar",
            "employees": 10,
            "capital": 50000,
            "key_personnel": [
                {
                    "name": "Owe Bergius",
                    "position": "Försäljn-chef"
                },
                {
                    "name": "Stig Hoffner",
                    "position": "Ekonomichef"
                }
            ],
            "establishment_year": 1965
        },
        "9": {
            "company_name": "fliesberg ab, ingeniors. FIRMAN",
            "pnr": "103 81",
            "address": "Stockholm 7, Box 7044, Nybrog 3",
            "phone_number": "08-23 53 75",
            "activity": "Mekanisk verkstad. Tillverkar o säljer kondensvatten-avledare, nålventiler, silar, regulatorer, instrument o säkerhetsventiler samt för cellulosa- o pappersindustrien: fiberåtervinningsan-läggningar, vakuumregulatorer, suglådor o spritsrör",
            "establishment_year": 1931
        },
        "10": {
            "company_name": "fliesbergs sport & fritidslagret, ab",
            "pnr": "88101",
            "address": "Sollefteå, Box 263",
            "phone_number": "0620-136 50",
            "activity": "Säljer sport- o fritidsartiklar per postorder o i detalj",
            "employees": 19,
            "annual_turnover": 5200000,
            "key_personnel": [
                {
                    "name": "Fredrik Fliesberg",
                    "position": "Verkst din"
                }
            ],
            "establishment_year": 1940
        },
        "11": {
            "company_name": "FALLENIUS RESEBYRÅ AB",
            "pnr": "403 17",
            "address": "Göteborg 2, Box 2505, V Hamng 5",
            "phone_number": "031-17 82 30",
            "activity": "Travel",
            "employees": 31,
            "capital": 50000,
            "key_personnel": [
                {
                    "name": "Tom Fallenius",
                    "position": "Verkst dir"
                }
            ],
            "establishment_year": 1954
        },
        "12": {
            "company_name": "BRODIN AB, OLOF",
            "pnr": "103 27",
            "address": "Stockholm 16, Box 16405, Rege-ringsg 45",
            "phone_number": "08-23 53 90",
            "bank_details": {
                "bankgiro": "724-7364",
                "postgiro": "457743-3"
            },
            "activity": "Skeppsmäkleri med befraktning, köp o försäljning",
            "employees": 11,
            "capital": 80000,
            "key_personnel": [
                {
                    "name": "Ryttmäst Olof Brodin",
                    "position": "Verkst dir"
                }
            ],
            "establishment_year": 1923
        },
        "13": {
            "company_name": "BROGÅRDS KVARN & TRÄVARU AB",
            "pnr": "380 30",
            "address": "Rockneby, Box 6",
            "phone_number": "0480-661 58, 660 76",
            "bank_details": {
                "bankgiro": "853-6583",
                "postgiro": "31992-1"
            },
            "activity": "Kvarnrörelse, spannmålshandel, fodertillverkning, sågverksrörelse samt lantbruk",
            "employees": 70,
            "annual_turnover": 7800000,
            "capital": 150000,
            "key_personnel": [
                {
                    "name": "Torsten Johansson",
                    "position": "Verkst dir"
                }
            ],
            "establishment_year": 1940
        },
        "14": {
            "company_name": "CAS CASLON PRESS BOKTRYCKERI AB",
            "pnr": "113 59",
            "address": "Stockholm, Sveav 90",
            "phone_number": "08-15 13 15",
            "bank_details": {
                "bankgiro": "73-4556",
                "postgiro": "59420-0"
            },
            "activity": "Tidskrifter o reklamtrycksaker",
            "employees": 30,
            "capital": 5000,
            "key_personnel": [
                {
                    "name": "Bengt Lagerström",
                    "position": "Verkst dir"
                }
            ],
            "establishment_year": 1924
        },
        "15": {
            "company_name": "IWEMA, AB",
            "pnr": "414 54",
            "address": "Göteborg V, Chapmansg 4",
            "phone_number": "031-124785",
            "bank_details": {
                "bankgiro": "514-8028",
                "postgiro": "521657-7"
            },
            "activity": "Säljer produktionsmaskiner av olika slag, fyllningsmaskiner, förpackningsmaskiner, rökanläggningar o utrustningar för konservfabriker, storkök, charkute-rifabriker samt pallastningsmaskin för säckar eller kartonger",
            "employees": 20,
            "annual_turnover": 9000000,
            "capital": 100000,
            "key_personnel": [
                {
                    "name": "Ingvar Weiner",
                    "position": "Verkst dir"
                }
            ],
            "establishment_year": 1959
        },
        "16": {
            "company_name": "STOREBRO BRUKS AB",
            "pnr": "59083",
            "address": "Storebro",
            "phone_number": "0492-301 60",
            "activity": "Snabbsvarvar, segel-o motorbåtar",
            "employees": 450,
            "annual_turnover": 27000000,
            "capital": 1000000,
            "key_personnel": [
                {
                    "name": "Ivar Gustafsson",
                    "position": "Verkst dir"
                }
            ],
            "establishment_year": 1728
        }
    }
}