{
    "original": "LÄT\n\nAktiekapital: 6 300 000\nStyrelse: Bokförl Gerard Bonnier\nf hovrättsrådet Bengt Lassen,\ndu-Birger Beckman\nVeikst dir: Birger Beckman\nEkonomichef: Olle Kindhammar\nEtableringsår: 1911\nOmbildat till aktiebolag 1928.\nDotterbolag: Akademiförlaget i Gbg\nAB, AB Magn Bergvall, Sthlm, A V\nCarlsons Bokförlags AB, Sthlm,\nScandinavian University Books AB,\nSthlm, AB\nSkolbokcentralen/Uni-versity Book Center, Sthlm,\nFörlags AB Saga/Svensk\nLäraretidning, Sthlm, Uniskol, Bokförlaget\nUniversitet o Skola AB, Lund, AB\nSvenska Bokförlaget, Sthlm,\nFörlags AB Teknik o Ekonomi, Sthlm,\nAB Språkförlag et/Svenska\nBokförlaget, Sthlm.\n\nLÄTT METALL PRODUKTER\n\nPnr 462 00\n\nVänersborg, Gjuterig 3. Tel\n0521-156 51. Bankgiro 888-8216.\nPostgiro 444429-5\n\nVeiksamhet: Tillverkar\nmonteringsfärdiga lastflak o karosserier i\nlättmetall\n\nÄgare o chef: Nils Mårdfelt\nEtableringsår: 1955.\n\nKIL\n\njärn, garagegångjärn o sågspindlar,\nbil- o vagnsfjädrar av oljehärdat\nspecialstål, bilflakbeslag, diverse\nhand- o maskinformat gjutgods.\nEn-groshandel med häftmaskiner\nAntal anställda: 180\nÅrsomsättning: 16 000 000\nChef: Bertil Morsing\nEtableringsår: 1860\nÄger Josef Kihlberg AB, Hjo.\n\nKILDEN &amp; CO, HELGE\n\nPnr 40124\n\nGöteborg 1, Drottningg 15. Box\n246. Tel 031-115081, 115082.\nBankgiro 847-8489. Postgiro\n40241-2\n\nVerksamhet: Säljer färger, penslar,\nkemikalier o fernissor i parti\nÄgare o chefer: Hut Swedberg,\nAke Kildén\nEtableringsår: 1929.\n\nEKOPÉ, AB\n\nPnr 30104\n\nHalmstad 1, Brog 30. Box 215. Tel\n035-119175. Bankgiro 530-3052.\nPostgiro 442878-5\nVerksamhet: Säljer Dermetics\nkosmetiska preparat\nFabrik: Simlångsdalen. Tel\n035-70270\n\nFörsäljningskontor Stocksund,\nVillav 12. Tel 08-85 9111\nAntal anställda: 20\nÅrsomsättning: 2 000 000\nAktiekapital: 350 000\nVerkst dir: Curt Persson\nEtableringsår: 1953.\n\nBOSTROM AB, BERTIL\n\nPnr 522 00\n\nTidaholm, Hägnev 2. Tel\n0502-113 50\n\nVerksamhet: Byggnadsmaterial i\nparti o minut, sågverk o hyvleri\nAvdelningskontor: Norrköping,\nFabriksg 10. Tel 011-1003 00\nÖrebro, Törng 2. Tel 019-13 62 10\nAntal anställda: 85\nÅrsomsättning: 35 000 000\nAktiekapital: 1000 000\nVerkst dir: Bertil Boström\nEtableringsår 1942.\n\nBARNÄNGEN AB\n\nPnr 102 22\n\nStockholm 12, Box 12080.\nGustavs-lundsv 145. Tel 08-25 25 80.\nBankgiro 48-3109. Postgiro 878-9.\nTga Barnängens.\nTelex 10628 VADCUM S\nVerksamhet: Tillverkar o säljer\nkem tekn artiklar o kosmetika\nAntal anställda: 312\n\nÅrsomsättning: 38 000 (koncernen\n111 000 000)\nAktiekapital: 11000 000\nVerkst dir: Jörgen M Blegvad\nEtableringsår 1868.\n\nBAROMETERNS AB,\nTIDNINGEN\n\nPnr 38101\n\nKalmar 1, S Långg 31. Box 246.\nTel 0480-152 00. Bankgiro\n655-7664. Postgiro 12759-7.\nTelex 4851\n\nVerksamhet: Utgivare av\ntidningarna Barometern o\nOskarshamns-Tidningen, bok-, reklam- o\naffärs-tryck. KlichSanstalt\nAntal anställda: 262\nÅrsomsättning: 16 960 000\nAktiekapital: 240 000\nVerkst dir: Chefred Tage Forsberg\nEtableringsår: 1841\nDotterbolag: AB\nOskarshamns-Tidningen.\n\nBARRACUDATAK AB\n\nPnr 116 21\n\nStockholm, Götg 66. Tel 08-44 99 45\nVerksamhet: Säljer o monterar\nBar-racuda plasttak\nVarunamn: Barracuda Plasttak\n.Antal anställda: 24\nÅrsomsättning: 6 000 000\nAktiekapital: 100 000\nVerkst dir: Sven Agnefors\nEtableringsår: 1965.\n\nBROBY MÖBEL AB\n\nPnr 686 00\n\nSunne, Box 239. Tel 05 65-10 1 63.\nBankgiro 113-8783. Postgiro\n269 202-8\n\nVerksamhet: Tillverkar stoppmöbler\nAntal anställda: 25\nÅrsomsättning: 1650 000\nAktiekapital: 50 000\nVerkst din Paul Iverlund\nEtableringsår: 1946.\n\nTESAteipab\n\nse Beiersdorf AB.\n\nTHESAM AB\n\nPnr 20013\n\nMalmö 27, Koksg 14. Box 27038.\nTel 040-18 68 00. Bankgiro 26-3468.\nPostgiro 437140. Telex 3152. Tga\nThesam\n\nVerksamhet: Värmeledningspannor,\nmaskiner o oljebrännare\nAktiekapital: 27 000\nVerkst dir C Eckersten\nEtableringsår: 1941.\n\nekman ab, eric s\n\nPnr 112 66\n\nStockholm, Essingestråket 37. Tel\n08-56 44 54, 56 44 55. Bankgiro\n730-2367. Postgiro 255087-9\nVerksamhet: Säljer Alofan,\nAlo-film, Diofan o Polyten i ark o\nrullar, fodral o påsar\nAktiekapital: 30000\nVerkst dir: Erie S Ekman\nEtableringsår: 1953.\n\nekman agenturaffär,\nnils\n\nPnr 41141\n\nGöteborg, Gårdav 5. Tel\n031-15 63 06, 15 63 07. Bankgiro\n50-7945. Postgiro 40729\nVerksamhet: Säljer parkett,\nlamellträ, plywood, plastgolvplattor,\nträfiberplattor m m\nAntal anställda: 6\nÄgare o chef: Nils Ekman\nEtableringsår: 1918.\n\nBYGGPROJEKTERING ARB\n\nPnr 113 54\n\nStockholm, Ingemarsg 2. Tel\n08-15 06 35. Bankgiro 805-8745.\nPostgiro 73143-0\n\nVerksamhet; Utreder\netablerings-o exploateringsprojekt\nAntal anställda: 30\nÅrsomsättning: 2 000 000\nAktiekapital: 5 000\nVerkst dir. Bengt Lindgren\nEtableringsår 1965.\n\nMOTORKRAFT, AB\n\nPnr 112 51\n\nStockholm, Warfvinges v 30. Tel\n08-13 08 80. Bankgiro 482-4033.\nPostgiro 56090-4\n\nVerksamhet: Import- o\ngrossistförsäljning av motorcyklar, mopeder\nAntal anställda: 40\nÅrsomsättning: 14 400 000\nAktiekapital: 150 000\nVerkst dir: Bengt Furugård\nEtableringsår: 1933.",
    "structured": {
        "1": {
            "company_name": "LÄTT METALL PRODUKTER",
            "activity": "Tillverkar monteringsfärdiga lastflak o karosserier i lättmetall",
            "establishment_year": 1955
        },
        "2": {
            "company_name": "KIL",
            "employees": 180,
            "annual_turnover": 16000000,
            "establishment_year": 1860
        },
        "3": {
            "company_name": "KILDEN & CO, HELGE",
            "activity": "Säljer färger, penslar, kemikalier o fernissor i parti",
            "establishment_year": 1929
        },
        "4": {
            "company_name": "EKOPÉ, AB",
            "activity": "Säljer Dermetics kosmetiska preparat",
            "employees": 20,
            "annual_turnover": 2000000,
            "capital": 350000,
            "establishment_year": 1953
        },
        "5": {
            "company_name": "BOSTROM AB, BERTIL",
            "activity": "Byggnadsmaterial i parti o minut, sågverk o hyvleri",
            "employees": 85,
            "annual_turnover": 35000000,
            "capital": 1000000,
            "establishment_year": 1942
        },
        "6": {
            "company_name": "BARNÄNGEN AB",
            "activity": "Tillverkar o säljer kem tekn artiklar o kosmetika",
            "employees": 312,
            "annual_turnover": 38000,
            "capital": 11000000,
            "establishment_year": 1868
        },
        "7": {
            "company_name": "BAROMETERNS AB, TIDNINGEN",
            "activity": "Utgivare av tidningarna Barometern o Oskarshamns-Tidningen, bok-, reklam- o affärs-tryck. KlichSanstalt",
            "employees": 262,
            "annual_turnover": 16960000,
            "capital": 240000,
            "establishment_year": 1841
        },
        "8": {
            "company_name": "BARRACUDATAK AB",
            "activity": "Säljer o monterar Barracuda plasttak",
            "employees": 24,
            "annual_turnover": 6000000,
            "capital": 100000,
            "establishment_year": 1965
        },
        "9": {
            "company_name": "BROBY MÖBEL AB",
            "activity": "Tillverkar stoppmöbler",
            "employees": 25,
            "annual_turnover": 1650000,
            "capital": 50000,
            "establishment_year": 1946
        },
        "10": {
            "company_name": "THESAM AB",
            "activity": "Värmeledningspannor, maskiner o oljebrännare",
            "capital": 27000,
            "establishment_year": 1941
        },
        "11": {
            "company_name": "ekman ab, eric s",
            "activity": "Säljer Alofan, Alo-film, Diofan o Polyten i ark o rullar, fodral o påsar",
            "capital": 30000,
            "establishment_year": 1953
        },
        "12": {
            "company_name": "ekman agenturaffär, nils",
            "activity": "Säljer parkett, lamellträ, plywood, plastgolvplattor, träfiberplattor m m",
            "employees": 6,
            "establishment_year": 1918
        },
        "13": {
            "company_name": "BYGGPROJEKTERING ARB",
            "activity": "Utreder etablerings-o exploateringsprojekt",
            "employees": 30,
            "annual_turnover": 2000000,
            "capital": 5000,
            "establishment_year": 1965
        },
        "14": {
            "company_name": "MOTORKRAFT, AB",
            "activity": "Import- o grossistförsäljning av motorcyklar, mopeder",
            "employees": 40,
            "annual_turnover": 14400000,
            "capital": 150000,
            "establishment_year": 1933
        }
    }
}