{
    "original": "OLMÉUS, AB ERIK\n\nPnr 502 33\n\nBorås, Nyg 5. Tel 033-11 86 02,\n1186 32. Bankgiro 360-8429.\nPostgiro 25310-4\n\nVerksamhet: Textilagentur\nAktiekapital: 10 000\nVerkst dir: Erik Olméus\nEtableringsår: 1949.\n\nOLOFSHUS KEMISKA\nINDUSTRI\n\nPnr 330 20\n\nAnderstorp. Tel 0371-150 03.\nBankgiro 48-8146. Postgiro 123323-8\nVeiksamhet: Tillverkar sårsalvan\nVätterin\n\nÄgare: Olof Lindén\nEtableringsår: 1957.\n\nHÄLLDE-MASKINER, AB\n\nPnr 102 31\n\nStockholm 6, Gästrikeg 1. Box\n6035. Tel 08-23 74 00. Bankgiro\n72-6113. Postgiro 192936. Tga\nHällde\n\nVerksamhet: Maskiner för storkök,\nrestauranger, konservindustri etc.\nTillverkar\ngrönsaksskärningsmaski-ner, smörportionerare, brödskärare\nAntal anställda: 26\nÅrsomsättning: 3800000\nAktiekapital: 300 000\nVerkst dir: Bo Dahlquist\nEtableringsår: 1941.\n\nCALUX, AB\n\nPnr 103 64\n\nStockholm 3, Apelbergsg 58. Box\n3211. Tel 08-23 4875. Postgiro\n198970. Telex 1447. Tga Calux\nVerksamhet: Tillverkar elektr\nma-materiel, apparatskåp, stativ etc\nAntal anställda: 70\nAktiekapital: 250 000\nVerkst din Lennart Carp\nEtableringsår: 1945.\n\nTUOLLUVAARA GRUV AB\n\nPnr 98104\n\nKiruna 4, Fack. Tel 0980-120 90.\nBankgiro 75-5747. Postgiro 65512.\nTga Tuollubolag, Kiruna.\nTelex 8745\n\nVerksamhet: Bryter järnmalm,\nstyckemalm o slig\nAntal anställda: 290\nÅrsomsättning: 35000000\nAktiekapital: 9000000\nVerkst dir: Disp P Vilhelm Villner\nEtableringsår: 1900.\n\nROSBERG &amp; WIDENOR AB\n\nPnr 112 22\n\nStockholm, John Ericssonsg 12.\nTel 08-5102 23\n\nVeiksamhet: Bil- o motorverktyg\nAktiekapital: 100000\nVerkst dir: C E Johansson\nEtableringsàr: 1945.\n\nROSDALA GLASBRUK, AB\n\nPnr 360 71\n\nNonhult. Tel 0474-400 02, 403 07.\nBankgiro 29-3611. Postgiro 36521.\nTga Rosdalaglas, Växjö\nVeiksamhet: Tillverkar\nbelysningsglas\n\nAntal anstäUda: 90\nÅrsomsättning: 3 500 000\nAktiekapital: 400 000\nVeikst dir: Frk Brita Nyrén\nDisp: Adolf Kroon\nEtableringsàr: 1900.\n\nROSELLPLAST AB\n\nPnr 552 67\n\nJönköping, Solåsv 20. Tel\n036-1660 90. Bankgiro 835-8442.\nPostgiro 105935-1\n\nVeiksamhet: Formsprutade\nplast-artiklar i alla förekommande\nthermo-plaster för industrin.\nEgen konstruktion o\nverktygstillverkning\n\nAktiekapital: 25 000\nVerkst dir: Stig Rosell\nEtableringsàr 1950.\n\nEMTIVERKEN, AB\n\nPnr 630 03\n\nEskilstuna 3, Box 3037. S Bangårdsg\n16. Tel 016-13 23 40,13 23 45.\nBankgiro 684-7669\n\nVerksamhet: Tillverkar rullstolar,\npress- o stansverktyg\nAntal anställda: 15\nÅrsomsättning: 800 000\nAktiekapital: 25 000\nVerkst dir: Sven Ström\nEtableringsår: 1925.\n\nBOHLMARK-PUKEBERG AB\n\nPnr 382 00\n\nNybro. Huvudkontor. Tel\n0481-137 20. Tga Böhlmarks, Kalmar\nVerksamhet: Tillverkar elektrisk\nbelysningsarmatur, belysningsglas,\nhushålls- o prydnadsglas\nDetaljförsä]jning: Stockholm C,\nNorrmalmstorg 4. Tel 08-10 26 89,\n20 76 40\n\nIndustrianläggning: Nybro.\nPukebergs Glasbruk. Tel 0481-137 20\nAntal anställda: 175\nÅrsomsättning: 7 000 000\nAktiekapital: 1200 000\nStyrelse: Dir Lars Edlund (ordf),\ning Gunnar Kempe, hovoptiker\nKlas Ostlund\n\nVerkst dir: Civiling Bo Bengtson\nEtableringsår: 1872.\n\nBÖNHAMNS BLECK\nEMBALLAGEFABRIK, AB\n\nPnr 870 30\n\nNordingrå, Box 3450. Tel\n0613-230 02. Bankgiro 77-0110.\nPostgiro 282720\n\nVerksamhet: Tillverkar\npatentburkar for färger o fernissor, emballage\nför fiskkonserver, samt\nmarschall-burkar\n\nAntal anställda: 14\nÅrsomsättning: 1800 000\nAktiekapital: 75 000\nVerkst dir: Fabr Edvin Näslund\nEtableringsår 1925\nOmbildat till aktiebolag 1960.\n\nBONNELYCHE &amp; THUROE AB\n\nPnr 200 60\n\nMalmö 30, Fack. Oväg, Limhamn.\nTel huvudkontor 040-16 20 20.\nBankgiro 640-1343. Postgiro 38538-5.\nTga Bönnelyche\n\nVerksamhet: Tillverkar\nasfaltprodukter, träskyddsmedel, färger o\nogräsbekämpningsmedel.\nByggnadsglas o plastprodukter engros.\nFörsäljning: Växtskyddsprodukter,\nglas, entreprenader, metallverkstad,\n\nBORIS, BYGGNADS AB\n\nPnr 577 00\n\nHultsfred. Box 35. V Långg 55.\nTel 0495-10170, 113 70. Bankgiro\n268-5675. Postgiro 288561-4\nVerksamhet: Bygger, bostäder,\nskolo-, sjukhus, förvaltningsbyggnader\nAntal anställda: 100\nÅrsomsättning: 7 000 000\nAktiekapital: 10000\nVerkst din Ing SBR Nils Böris\nEtableringsår. 1961.\n\nSIEVERTS KABELVERK AB\n\nPnr 172 87\n\nSundbyberg, Landsv 66. Tel\n28 28 60, riks 08-28 27 20.\nBankgiro 743-5258. Postgiro 24000-2.\nTga Sievertsfabrik.\nTelex 1676 SIEVKAB S\nVerksamhet: Tillverkar\nstarkströmskabel, ledning, kabelskåp mm\nAntal anställda: 1129\nÅrsomsättning: 210 000 000\nAktiekapital: 90 000 000\nVerkst din Nils Y Åkesson\nEtableringsår. 1888.\n\nABE\n\nA\n\nABACUS, BYGGNADS AB\n\nPnr 102 45\n\nStockholm 5, Östermalmstorg 5. Box\n5224. Tel 08-63 07 25. Bankgiro\n73-0732. Postgiro 192745-8\nVerksamhet: Utför nybyggnader,\nombyggnader o reparationer\nAntal anställda: 130\nÅrsomsättning: 20 000 000\nAktiekapital: 100 000\nVerkst dir: Ing S A H Ädling\nArbetschef: Ing Folke Magnusson\nEtableringsår: 1941.\n\nDONNÉR AB, HERM\n\nPnr 290 20\n\nÅhus, Box 72. Tel 044-24 00 29,\n24 0 0 33. Bankgiro 87-3606.\nPost-giro 225519. Telex 4470. Tga\nDonner\n\nVerksamhet: Skeppsmäkleri,\nbefraktning, spedition\nAntal anställda: 6\nAktiekapital: 20 000\nDir: John Donnér\nEtableringsår: 1897.\n\nDONSO FISKEREDSKAP\nNILSSON &amp; FHAGER\n\nPnr 430 82\n\nDonsö. Tel 031-77 07 70. Postgiro\n347041\n\nVerksamhet: Säljer\nskeppsförnödenheter o fiskredskap\nÄgare o chefer: Svante Nilsson,\nBertil Phager\nEtableringsår: 1950.",
    "structured": {
        "firms": [
            {
                "company_name": "OLMÉUS, AB ERIK",
                "pnr": "502 33",
                "address": "Borås, Nyg 5. 1186 32",
                "phone_number": "033-11 86 02",
                "bank_details": {
                    "bankgiro": "360-8429",
                    "postgiro": "25310-4"
                },
                "activity": "Textilagentur",
                "capital": 10000,
                "key_personnel": [
                    {
                        "name": "Erik Olméus",
                        "position": "Verkst dir"
                    }
                ],
                "establishment_year": 1949
            },
            {
                "company_name": "OLOFSHUS KEMISKA INDUSTRI",
                "pnr": "330 20",
                "address": "Anderstorp",
                "phone_number": "0371-150 03",
                "bank_details": {
                    "bankgiro": "48-8146",
                    "postgiro": "123323-8"
                },
                "activity": "Tillverkar sårsalvan",
                "establishment_year": 1957,
                "key_personnel": [
                    {
                        "name": "Olof Lindén",
                        "position": "Ägare"
                    }
                ]
            },
            {
                "company_name": "HÄLLDE-MASKINER, AB",
                "pnr": "102 31",
                "address": "Stockholm 6, Gästrikeg 1. Box 6035.",
                "phone_number": "08-23 74 00",
                "bank_details": {
                    "bankgiro": "72-6113",
                    "postgiro": "192936"
                },
                "activity": "Maskiner för storkök, restauranger, konservindustri etc.",
                "employees": 26,
                "annual_turnover": 3800000,
                "capital": 300000,
                "key_personnel": [
                    {
                        "name": "Bo Dahlquist",
                        "position": "Verkst dir"
                    }
                ],
                "establishment_year": 1941
            },
            {
                "company_name": "CALUX, AB",
                "pnr": "103 64",
                "address": "Stockholm 3, Apelbergsg 58. Box 3211.",
                "phone_number": "08-23 4875",
                "bank_details": {
                    "postgiro": "198970"
                },
                "activity": "Tillverkar elektr ma-materiel, apparatskåp, stativ etc",
                "employees": 70,
                "capital": 250000,
                "key_personnel": [
                    {
                        "name": "Lennart Carp",
                        "position": "Verkst din"
                    }
                ],
                "establishment_year": 1945
            },
            {
                "company_name": "TUOLLUVAARA GRUV AB",
                "pnr": "98104",
                "address": "Kiruna 4, Fack.",
                "phone_number": "0980-120 90",
                "bank_details": {
                    "bankgiro": "75-5747",
                    "postgiro": "65512"
                },
                "activity": "Bryter järnmalm, styckemalm o slig",
                "employees": 290,
                "annual_turnover": 35000000,
                "capital": 9000000,
                "key_personnel": [
                    {
                        "name": "Disp P Vilhelm Villner",
                        "position": "Verkst dir"
                    }
                ],
                "establishment_year": 1900
            },
            {
                "company_name": "ROSBERG & WIDENOR AB",
                "pnr": "112 22",
                "address": "Stockholm, John Ericssonsg 12.",
                "phone_number": "08-5102 23",
                "activity": "Bil- o motorverktyg",
                "capital": 100000,
                "key_personnel": [
                    {
                        "name": "C E Johansson",
                        "position": "Verkst dir"
                    }
                ],
                "establishment_year": 1945
            },
            {
                "company_name": "ROSDALA GLASBRUK, AB",
                "pnr": "360 71",
                "address": "Nonhult",
                "phone_number": "0474-400 02, 403 07",
                "bank_details": {
                    "bankgiro": "29-3611",
                    "postgiro": "36521"
                },
                "activity": "Tillverkar belysningsglas",
                "employees": 90,
                "annual_turnover": 3500000,
                "capital": 400000,
                "key_personnel": [
                    {
                        "name": "Frk Brita Nyrén",
                        "position": "Veikst dir"
                    },
                    {
                        "name": "Adolf Kroon",
                        "position": "Disp"
                    }
                ],
                "establishment_year": 1900
            },
            {
                "company_name": "ROSELLPLAST AB",
                "pnr": "552 67",
                "address": "Jönköping, Solåsv 20.",
                "phone_number": "036-1660 90",
                "bank_details": {
                    "bankgiro": "835-8442",
                    "postgiro": "105935-1"
                },
                "activity": "Formsprutade plast-artiklar i alla förekommande thermo-plaster för industrin. Egen konstruktion o verktygstillverkning",
                "capital": 25000,
                "key_personnel": [
                    {
                        "name": "Stig Rosell",
                        "position": "Verkst dir"
                    }
                ],
                "establishment_year": 1950
            },
            {
                "company_name": "EMTIVERKEN, AB",
                "pnr": "630 03",
                "address": "Eskilstuna 3, Box 3037. S Bangårdsg 16.",
                "phone_number": "016-13 23 40,13 23 45",
                "bank_details": {
                    "bankgiro": "684-7669"
                },
                "activity": "Tillverkar rullstolar, press- o stansverktyg",
                "employees": 15,
                "annual_turnover": 800000,
                "capital": 25000,
                "key_personnel": [
                    {
                        "name": "Sven Ström",
                        "position": "Verkst dir"
                    }
                ],
                "establishment_year": 1925
            },
            {
                "company_name": "BOHLMARK-PUKEBERG AB",
                "pnr": "382 00",
                "address": "Nybro. Huvudkontor.",
                "phone_number": "0481-137 20",
                "activity": "Tillverkar elektrisk belysningsarmatur, belysningsglas, hushålls- o prydnadsglas",
                "employees": 175,
                "annual_turnover": 7000000,
                "capital": 1200000,
                "key_personnel": [
                    {
                        "name": "Civiling Bo Bengtson",
                        "position": "Verkst dir"
                    }
                ],
                "establishment_year": 1872
            },
            {
                "company_name": "BÖNHAMNS BLECK EMBALLAGEFABRIK, AB",
                "pnr": "870 30",
                "address": "Nordingrå, Box 3450",
                "phone_number": "0613-230 02",
                "bank_details": {
                    "bankgiro": "77-0110",
                    "postgiro": "282720"
                },
                "activity": "Tillverkar patentburkar for färger o fernissor, emballage för fiskkonserver, samt marschall-burkar",
                "employees": 14,
                "annual_turnover": 1800000,
                "capital": 75000,
                "key_personnel": [
                    {
                        "name": "Fabr Edvin Näslund",
                        "position": "Verkst dir"
                    }
                ],
                "establishment_year": 1960
            },
            {
                "company_name": "BONNELYCHE & THUROE AB",
                "pnr": "200 60",
                "address": "Malmö 30, Fack. Oväg, Limhamn",
                "phone_number": "040-16 20 20",
                "bank_details": {
                    "bankgiro": "640-1343",
                    "postgiro": "38538-5"
                },
                "activity": "Tillverkar asfaltprodukter, träskyddsmedel, färger o ogräsbekämpningsmedel",
                "establishment_year": 1950,
                "key_personnel": [
                    {
                        "name": "",
                        "position": ""
                    }
                ]
            },
            {
                "company_name": "BORIS, BYGGNADS AB",
                "pnr": "577 00",
                "address": "Hultsfred. Box 35. V Långg 55",
                "phone_number": "0495-10170, 113 70",
                "bank_details": {
                    "bankgiro": "268-5675",
                    "postgiro": "288561-4"
                },
                "activity": "Bygger, bostäder, skolo-, sjukhus, förvaltningsbyggnader",
                "employees": 100,
                "annual_turnover": 7000000,
                "capital": 10000,
                "key_personnel": [
                    {
                        "name": "Ing SBR Nils Böris",
                        "position": "Verkst din"
                    }
                ],
                "establishment_year": 1961
            },
            {
                "company_name": "SIEVERTS KABELVERK AB",
                "pnr": "172 87",
                "address": "Sundbyberg, Landsv 66",
                "phone_number": "08-28 28 60, riks 08-28 27 20",
                "bank_details": {
                    "bankgiro": "743-5258",
                    "postgiro": "24000-2"
                },
                "activity": "Tillverkar starkströmskabel, ledning, kabelskåp mm",
                "employees": 1129,
                "annual_turnover": 210000000,
                "capital": 90000000,
                "key_personnel": [
                    {
                        "name": "Nils Y Åkesson",
                        "position": "Verkst din"
                    }
                ],
                "establishment_year": 1888
            },
            {
                "company_name": "ABE A ABACUS, BYGGNADS AB",
                "pnr": "102 45",
                "address": "Stockholm 5, Östermalmstorg 5. Box 5224",
                "phone_number": "08-63 07 25",
                "bank_details": {
                    "bankgiro": "73-0732",
                    "postgiro": "192745-8"
                },
                "activity": "Utför nybyggnader, ombyggnader o reparationer",
                "employees": 130,
                "annual_turnover": 20000000,
                "capital": 100000,
                "key_personnel": [
                    {
                        "name": "Ing S A H Ädling",
                        "position": "Verkst dir"
                    },
                    {
                        "name": "Ing Folke Magnusson",
                        "position": "Arbetschef"
                    }
                ],
                "establishment_year": 1941
            },
            {
                "company_name": "DONNÉR AB, HERM",
                "pnr": "290 20",
                "address": "Åhus",
                "phone_number": "044-24 00 29, 24 0 0 33",
                "bank_details": {
                    "bankgiro": "87-3606",
                    "postgiro": "225519"
                },
                "activity": "Skeppsmäkleri, befraktning, spedition",
                "employees": 6,
                "capital": 20000,
                "key_personnel": [
                    {
                        "name": "John Donnér",
                        "position": "Dir"
                    }
                ],
                "establishment_year": 1897
            },
            {
                "company_name": "DONSO FISKEREDSKAP NILSSON & FHAGER",
                "pnr": "430 82",
                "address": "Donsö",
                "phone_number": "031-77 07 70",
                "bank_details": {
                    "postgiro": "347041"
                },
                "activity": "Säljer skeppsförnödenheter o fiskredskap",
                "key_personnel": [
                    {
                        "name": "Svante Nilsson",
                        "position": "Ägare o chef"
                    },
                    {
                        "name": "Bertil Phager",
                        "position": "Ägare o chef"
                    }
                ],
                "establishment_year": 1950
            }
        ]
    }
}