{
    "original": "SVENSKA KRAUTOXIN AB\n\nPnr 21121\n\nMalmö. Västerg 20. Tel 040-377 53.\nBankgiro 761-3698. Postgiro\n435670-5\n\nVerksamhet; Importerar\nkonsthart-ser såsom epoxi o silikon\nAktiekapital: 5 000\nVerkst dir. Ing Günther Schaedel\nEtableringsår: 1967.\n\nSVENSKA KREDIT\nFÖRSÄKRINGS AB\n\nPnr 103 82\n\nStockholm 7, Box 7073.\nNorrmalms-torg 14. Tel 08-22 10 60. Bankgiro\n700-1795. Postgiro 3020-5. Tga\nSvenskakredit.\nTelex 10124 SVENSKA S\nVerksamhet: Kreditförsäkring\nAntal anställda: 37\nAktiekapital: 2 000 000\nStyrelse: Dir R Sundén (ordf),\nbruks-disp A Pihlgren, civiling E\nByström, dir E Engel, dir A\nLundeborg, dir O Karleby, dir O\nAppel-tofft, adv H Stenbeck jr, adv B\nWesterling, dir A Zander, dir\nS A vall\n\nVerkst dir: E Engel\nEtableringsår: 1928.\n\nSVENSKA KRUTFAK.\nTORIERNA, AB\n\nPnr 240 23\n\nDösjebro, Box 18. Tel 046-713 00.\nBankgiro 372-5082. Postgiro\n9480-5. Tga Normal\nVerksamhet: Tillverkar\njaktammunition o lerduvor.\nPostorderförsäljning av färger\nAntal anställda: 10\nÅrsomsättning: 650000\nAktiekapital: 350 000\nVerkst dir: Yngve Wiberg\nEtableringsår: 1897.\n\nSVENSKA KULLAGER.\nFABRIKEN, AB\n\nPnr 415 50\n\nGöteborg, Hornsg 1, Tel\n031-84 00 00. Bankgiro 160-0634,\n500-5509. Postgiro 9000-1.\nTga Kullager. Telex 2350\nVarunamn: SKF, SKEF-TOOL,\nKoppers\n\nMODERBOLAGET\nAntal anställda: 12*450\nÅrsomsättning: 880 900 000\nAktiekapital: 450000000\nStyrelse: Bankdir Jacob Wallenberg\n(ordf), disp Sverre R:son Sohlman,\nhandl Peter K:son Mark, dir Bertil\nCarlander, dir Sven T Åberg, adv\nGiovanni Agnelli, disp Wilhelm\nHaglund, dir Folke Lindskog\nVerkst dir: Folke Lindskog\n\nV\tverkst dir: Isak Forslund\n\nV\tverkst dir: Lennart Johansson\n\nV\tverkst dir: Bengt Kihlberg\nDir: Gunnar L Arvidsson\nEtableringsår: 1907\n\nGOTEBORGSDIVISIONEN\nChef: Dir Torsten Grufman\nVerksamhet: Tillverkning o\nförsäljning av rullningslager, ledlager,\nlagerhus, transportvagnshjul o\n-rullar, svarvdubbar,\naxelkopplingar, kugghjul, mätdon, gjutgods i\nnormaljärn, högvärdigt gjutjärn o\nsegjärn med hand-, maskin- o\nskalformning\n\nGöteborgsverken: 415 50 Göteborg,\nHornsg 1. Tel 031-8400 00. Tga\nKullager. Telex 2350\nKatrineholmsverken: 64100\nKatrineholm, Box 89. Tel 0150-13130.\nTga Kullager. Telex 64005. Gjuteri\no mekanisk verkstad\nPlatschef: Dir Curt Westerfors\nFörsäljningskontor:\nGöteborg: N Agatan 10,\n416 64 Göteborg. Tel 031-8018 80\nJönköping: österängsv 2. Box 6042,\n550 06 Jönköping 6. Tel\n036-1197 30. Telex 70013\nLudvika: Storg 35. Box 142,\n77101 Ludvika 1. Tel 0240-136 00.\nTelex 73382\n\nMalmö: Rundelsg 16 A. Box 374,\n20123 Malmö 1. Tel 040-710 20.\n\nTelex 3198\n\nStockholm: Landsv 60. Box 136,\n172 24 Sundbyberg 1. Tel\n08-9817 20. Telex 1456\nSundsvall: Trädgårdsg 3. Box 84,\n851 02 Sundsvall 1. Tel\n060-15 78 40. Telex 71040.\n\nSVENSKA KULLAGER.\nFABRIKEN STÄLDIVISIONEN\nSKF STÅL\n\nPnr 813 01\n\nHofors. Tel 0290-21800. Tga\nSkef-steel, Hofors. Telex 81005\nChef: Dir Bengt Kihlberg\nMarknadsföring chef: Dir Per\nGrufman\n\nInköpschef: Herr Bert Granat\nTillverkningschef: Dir Olle Testad\nAktiekapital: Se AB Svenska\nKullagerfabriken, Göteborg\nStyrelse o verkst dir: Se AB\nSvenska Kullagerfabriken, Göteborg\n\nVerk\nHofors\n\nPost, tel, telegram, telex, som ovan\nAntal anställda: 4 000\n\nHällefors\n\nPnr 712 00. Tel 0591-600 00. Tga\nSkefsteel, Hällefors. Telex 5648\nAntal anställda: 1700\n\nBångbro\n\nPnr 710 70. Tel 0580-114 10\nAntal anställda: 400\n\nVerksamhet: Tillverkar legerade\no olegerade kvalitetsstål i form\nav tjockväggiga tör, valsad o\nsmidd ring, valstråd, varmvalsad\no skals varvad stång, varm- o\nkallvalsade band. Kallformade o\nfin-klippta detaljer. Sågverksprodukter\nFörsäljn-kontor med lager:\nEskilstuna, Pressarg 14-16. Tel\n016-1470 90. Telex 40988\nGöteborg 13, von Utfallsg 1 o 9.\nTel 031-26 22 00. Telex 20705\nMalmö, Stålkuleg 5. Tel\n040-93 68 20. Telex 3174\nStockholm, Björnnäs v 2. Tel\n08-150455. Telex 1846\nSundsvall. C G Sandström AB,\nFörràdsg 5, Box 31. Tel\n060-150560. Telex 71202\nSamtliga kontor säljer o lagerför\nrör, stång, tråd, band o ring.\n\nSVENSKA KOTTIMPORTEN, AB\n\nPnr 100 56\n\nStockholm, Frihamnen. Tel\n08-67 9190\n\nVerksamhet: Importerar nötkött,\nfläskdetaljer, organvaror o vilt\nAntal anställda: 21\nÅrsomsättning: 75 000 000\nAktiekapital: 100 000\nVerkst din Lars Flodin\nEtableringsår 1960.\n\nfalk tryckeri ab, bengt\n\nPnr 172 06\n\nSundbyberg 6, Box 638. Humbleg\n638. Tel 08-29 28 29, 29 92 29.\nBankgiro 43-1475. Postgiro 81170\nVeiksamhet: Tillverkar o säljer\nkortsystem o planeringstavlor\nAktiekapital: 5 000\nVerkst dir: Bengt Falk\nEtableringsår: 1967.\n\nNILSSON &amp; SÖNER GRANIT AB\n\nPnr 593 02\n\nVästervik 2, Box 2005. Sankta\nGertruds v 66. Tel 0490-13110.\nBankgiro 667-0368. Postgiro\n33584-4. Tga Nilsten\nVerksamhet: Tillverkar\ngravvårdar, skulptur, byggnadssten; granit\nfrån egna brott. Export; marmor o\nkalksten från egna verk\nKontor o utställning: Enskede,\nSandsborgsv 39. Tel 08-49 57 66\nAntal anstäUda: 75\nÅrsomsättning: 4 5 00 000\nVerkst dir: Gunnar Nilsson\nEtableringsår: 1921.\n\nNILSSONS TRIKÄFABRIK, AB\n\nPnr 510 21\n\nSätüa. Tel 0301-420 23\nVerksamhet: Tillverkar scarves\no stickade mössor\nÅrsomsättning: 1800000\nAktiekapital: 30 000\nVerkst dir: Kjell Grebeüus\nEtableringsår: 1962.\n\nELEKTROSKYLT AB\n\nPnr 817 00\n\nNorrsundet, Box 1. Tel\n0297-300 10 , 300 01. Bankgiro 785-2114.\nPostgiro 173776-6. Tga\nElektro-skylt, Gävle\n\nVerksamhet: Tillverkar skyltar av\nalla slag, tryckta etiketter på plast\no metallfolier, bokstäver,\nreflexmaterial m m\nAntal anställda: 5\nAktiekapital: 30 000\nVerkst dir: Sören Engman\nVerkmäst: Dan Engman\nEtableringsår: 1947.\n\nW-W STAL AB\n\nPnr 41137\n\nGöteborg, vasag 58. Tel\n031-17 0110. Bankgiro 108-0118.\nPostgiro 527790-0. Tga Wewestal. Telex\n2357\n\nVerksamhet: Utländska agenturer i\njärn- o stålbranschen\nÅrsomsättning: 7 000 000\nAktiekapital: 150 000\nChefer: Dir C W Werner ,■ ing\nChrister Wigelius\nEtableringsår: 1959.\n\nESSMAN LIVSMEDELS AB\n\nPnr 58104\n\nLinköping 1, Box 406. Platensg 33.\nTel 013-12 96 40. Bankgiro\n346-9459. Postgiro 71958-3\nVerksamhet: Tillverkar o säljer\ncharkuterivaror o konserver.\nStyckning av kött o fläsk\nFilialfabriker: 59100 Motala,\nKyrkog 18. Tel 0141-174 70\n602 34 Norrköping, Bryggareg 6.\nTel 011-16 18 55\nVarunamn: Essman\nAntal anställda: 400\nÅrsomsättning: 110 000 000\nAktiekapital: 500000\nStyrelse: Fru Catarina Ström (ordf),\ndir Harry Ekenger, disp Henric\nEkenger, disp Kenne Hägersten\nVerkst dir: Harry Ekenger\nV verkst dir: Henric Ekenger\nAdm-chef: Disp Kenne Hägersten\nFörsäljn-chef: Disp Sigvard\nClaesson\n\nEtableringsår: 1915\nOmbildat till aktiebolaget 1946.\nNamnändrat till Essman\nLivsmedels AB 1968.\n\nDotterbolag: Essfod AB, Linköping.\n\nESSO CHEMICAL AB\n\nPnr 171 54\n\nSolna, Vretenv 10. Tel 08-98 08 90.\nBankgiro 27-8361. Postgiro 837200.\nTga Essochem.\nTelex 10815 ESSOCHM S\nVerksamhet: Tillverkar eten,\npro-pen samt harts (Escopol) i Stenung-\n\nsund. Säljer importerade kemikalier\nsåsom lösningsmedel,\nindustrikemikalier, hartser, elastomerer, plaster\no tillsatsmedel till smörjoljor o\nbränslen\n\nFabrik: 444 00 Stenungsund, Fack.\nTel 0303-706 60. Chef: JohanKBöe\nDistriktskontor: 40313 Göteborg 2,\nBox 2186. Tel 031-20 07 00\n201 23 Malmö 1, Box 386. Tel\n040-706 60\n\nVarunamn: Escopol\nAntal anställda: 250\nÅrsomsättning: 143 000 000\nAktiekapital: 2 000 000\nStyrelse: Tekn dr Töre Browaldh\n(ordf), dir Bengt I:son Sjöberg, dir\nLewis A Winkler\nVerkst dir: Lewis A Winkler\nMarknadschef: Töre Hallén\nFörsäljn-chef: Hillar Tuiskvere\nEtableringsår: 1932\nNamnändring 1966.\n\nESSO MOTOR HOTEL AB\n\nPnr 10240\n\nStockholm 5, Fack. Grevtureg 19.\nTel 08-67 98 40. Bankgiro 700-5010.\nPostgiro 891-2. Tga Essotel.\nTelex 17995\n\nVerksamhet: Hotellrörelse med\nrestauranger o tavernor över hela\nlandet. Konferensförsäljning\nAntal anställda: 890\nÅrsomsättning: 77 000 000\nAktiekapital: 200000\nStyrelse: Dir Bengt I:son Sjögren,\ndir Torsten Andersson, Jack\nRellly jr\n\nVerkst dir: Arne Gustafsson\nEtableringsår: 1968.\n\nSTO\n\nförvaringsetuier o skyltställ\nVarunamn: Design Philipp\nChef: Ernst Wolf\nEtableringsår: 1936.\n\nSTOCKHOLMS FARTYGS.\nSERVICE, AB\n\nPnr 100 56\n\nStockholm, Stockholms Frihamn.\nTel 08-67 36 16. Bankgiro 72-8053.\nPostgiro 556573. Tga Stofartserv\nVerksamhet: Underhålls- samt\ndiverse arbeten å fartyg. Oljeservice,\nslammsugnihg, tankrengöring\nAntal anställda: 40\nAktiekapital: 30 000\nVerkst dir: Sven O Andersson\nEtableringsår: 1947\nOmbildat till aktiebolag 1957.\n\nSTOCKHOLMS FJÄDER.\nFABRIK, KB\n\nPnr 113 53\n\nStockholm, Tuleg 15. Tel\n08-32 48 50. Bankgiro 670-0256.\nPostgiro 52809-1. Tga Fjäderwal\nVerksamhet: Tillverkar\nspiralfjädrar o plattfjädrar\nChef: Fabr Göran Andersen\nEtableringsår: 1915.\n\nSTOCKHOLMS\nFLAGG-FABRIK AB\n\nPnr 11438\n\nStockholm, Grev Tureg 35. Tel\n08-23 27 25. Bankgiro 726-5853.\nPostgiro 50620-4\n\nVerksamhet: Tillverkar o säljer\nflaggor, fanor med tillbehör\nAktiekapital: 15 000\nVerkst dir: Ch Lagerfeldt\nEtableringsår: 1882.\n\nEXPLOATOR PLAST AB\n\nPnr 800 06\n\nGävle 6, Box 6097. Akarg 43. Tel\n026-18 82 30. Bankgiro 633-6200.\nPostgiro 343310-9. Tga Exploator\nVerksamhet: Tillverkar o försäljer\nextruderande plastprofiler\nPlastfabrik: 730 73 Ransta. Tel\n0224-203 20\n\nÅrsomsättning: 2 000 000\nAktiekapital: 30 000\nStyrelse: Olle Skanhed. Carl\nThorn-berg\n\nFabrikschef: Roland Andersson\nEtableringsår. 1968.\n\nPERSSONSÅKERI, AB GUSTAV\n\nPnr 211 24\n\nMalmö, Vädersg 8-10. Tel\n040-93 5180\n\nVerksamhet: utför tunga som lätta\ntransporter, trailer- o\nmöbelstran-sport. Bilar med tipp o krän\nAntal anställda: 90\nÅrsomsättning: 8 000 000\nAktiekapital: 150 000\nVerkst dir: Gustav Persson\nEtableringsår: 1929.\n\nPERSSON &amp; CO AB,\nHANDELSFIRMA H\n\nPnr 722 31\n\nVästerås, Hökåsen. Tel 021-242 00,\n24210. Bankgiro 86-0602.\nPostgiro 329957\n\nVerksamhet: Tillverkar svetsade\nTIR- o inrikes lastbilskapell\nAntal anställda: 4\nÅrsomsättning: 500 000\nAktiekapital: 105 000\nVerkst dir: Helmer Persson\nEtableringsår: 1952.\n\nANDERSSONS MEK VERKSTAD\n\nPnr 64100\n\nKatrineholm, Trädgårdsg 1. Tel\n0150-122 90. Postgiro 205520-0\n\nVerksamhet: Beställningsarbeten i\nsvarvning, fräsning, hyvling o\nsvetsning. Tillverkar o reparerar\nmaskiner o maskindelar\nÄgare o chef: Erie H Andersson\nEtableringsår: 1949.\n\nANDERSSONS\nMETALLDUKS-FABRIK, BRÖDERNA\n\nPnr 330 20\n\nAnders torp, Dalg 8. Box 83. Tel\n0371-153 29\n\nVerksamhet: Tillverkar metallduk\no ståltrådsduk\n\nÄgare o chef: Fabr Gottfrid\nAndersson.\n\nANDERSSON &amp; NILSSON\n\nPnr 852 37\n\nSundsvall, N Järnvägsg 52. Tel\n060-1147 57. Bankgiro 35-0707.\nPostgiro 297331\n\nVerksamhet: Byggnadssmide, stål\no järnkonstruktioner,\nsläpvagnskopplingar, mek arbeten m m\nVarunamn: Simson\nVerkst dir: D G A N Andersson\nEtableringsår: 1930.\n\nANDERSSON &amp; PETTERSSON\nAB, PLÄTSLAGERIFIRMAN\n\nPnr 502 64\n\nBorås, Kilsundsg 10. Tel\n033-11 19 76, 11 67 20. Bankgiro\n84-6461. Postgiro 291047\nVerksamhet: Plåtslageri\nAktiekapital: 15 000\nVerkst dir: Gösta Pettersson\nEtableringsår: 1944.",
    "structured": {
        "1": {
            "company_name": "SVENSKA KRAUTOXIN AB",
            "pnr": "21121",
            "address": "Malmö. Västerg 20",
            "phone_number": "040-377 53",
            "bank_details": {
                "bankgiro": "761-3698",
                "postgiro": "435670-5"
            },
            "activity": "Importerar konsthart-ser såsom epoxi o silikon",
            "capital": 5000,
            "key_personnel": [
                {
                    "name": "Ing Günther Schaedel",
                    "position": "Verkst dir"
                }
            ],
            "establishment_year": 1967
        },
        "2": {
            "company_name": "SVENSKA KREDIT FÖRSÄKRINGS AB",
            "pnr": "103 82",
            "address": "Stockholm 7, Box 7073. Norrmalms-torg 14",
            "phone_number": "08-22 10 60",
            "bank_details": {
                "bankgiro": "700-1795",
                "postgiro": "3020-5"
            },
            "activity": "Kreditförsäkring",
            "employees": 37,
            "capital": 2000000,
            "key_personnel": [
                {
                    "name": "Dir R Sundén",
                    "position": "ordf"
                },
                {
                    "name": "bruks-disp A Pihlgren",
                    "position": "disp"
                },
                {
                    "name": "civiling E Byström",
                    "position": "dir"
                },
                {
                    "name": "dir E Engel",
                    "position": null
                },
                {
                    "name": "dir A Lundeborg",
                    "position": null
                },
                {
                    "name": "dir O Karleby",
                    "position": null
                },
                {
                    "name": "dir O Appel-tofft",
                    "position": null
                },
                {
                    "name": "adv H Stenbeck jr",
                    "position": "adv"
                },
                {
                    "name": "adv B Westerling",
                    "position": "adv"
                },
                {
                    "name": "dir A Zander",
                    "position": null
                },
                {
                    "name": "dir S A vall",
                    "position": null
                }
            ],
            "establishment_year": 1928
        },
        "3": {
            "company_name": "SVENSKA KRUTFAKTORIERNA, AB",
            "pnr": "240 23",
            "address": "Dösjebro, Box 18",
            "phone_number": "046-713 00",
            "bank_details": {
                "bankgiro": "372-5082",
                "postgiro": "9480-5"
            },
            "activity": "Tillverkar jaktammunition o lerduvor. Postorderförsäljning av färger",
            "employees": 10,
            "annual_turnover": 650000,
            "capital": 350000,
            "key_personnel": [
                {
                    "name": "Yngve Wiberg",
                    "position": "Verkst dir"
                }
            ],
            "establishment_year": 1897
        },
        "4": {
            "company_name": "SVENSKA KULLAGER FABRIKEN, AB",
            "pnr": "415 50",
            "address": "Göteborg, Hornsg 1",
            "phone_number": "031-84 00 00",
            "bank_details": {
                "bankgiro": "160-0634",
                "postgiro": "9000-1"
            },
            "varunamn": "SKF, SKEF-TOOL, Koppers",
            "employees": 12,
            "annual_turnover": 880900000,
            "capital": 450000000,
            "key_personnel": [
                {
                    "name": "Bankdir Jacob Wallenberg",
                    "position": "ordf"
                }
            ],
            "establishment_year": 1907
        },
        "5": {
            "company_name": "SVENSKA KULLAGER FABRIKEN STÄLDIVISIONEN SKF STÅL",
            "pnr": "813 01",
            "address": "Hofors",
            "phone_number": "0290-21800",
            "varunamn": "SKF STÅL",
            "employees": 4000,
            "establishment_year": null
        },
        "6": {
            "company_name": "SVENSKA KOTTIMPORTEN, AB",
            "pnr": "100 56",
            "address": "Stockholm, Frihamnen",
            "phone_number": "08-67 9190",
            "activity": "Importerar nötkött, fläskdetaljer, organvaror o vilt",
            "employees": 21,
            "annual_turnover": 75000000,
            "capital": 100000,
            "key_personnel": [
                {
                    "name": "Lars Flodin",
                    "position": "Verkst dir"
                }
            ],
            "establishment_year": 1960
        },
        "7": {
            "company_name": "FALK TRYCKERI AB, BENGT",
            "pnr": "172 06",
            "address": "Sundbyberg 6, Box 638. Humbleg 638",
            "phone_number": "08-29 28 29, 29 92 29",
            "bank_details": {
                "bankgiro": "43-1475",
                "postgiro": "81170"
            },
            "activity": "Tillverkar o säljer kortsystem o planeringstavlor",
            "capital": 5000,
            "key_personnel": [
                {
                    "name": "Bengt Falk",
                    "position": "Verkst dir"
                }
            ],
            "establishment_year": 1967
        },
        "8": {
            "company_name": "NILSSON & SÖNER GRANIT AB",
            "pnr": "593 02",
            "address": "Västervik 2, Box 2005. Sankta Gertruds v 66",
            "phone_number": "0490-13110",
            "bank_details": {
                "bankgiro": "667-0368",
                "postgiro": "33584-4"
            },
            "activity": "Tillverkar gravvårdar, skulptur, byggnadssten; granit från egna brott. Export; marmor o kalksten från egna verk",
            "employees": 75,
            "annual_turnover": 4500000,
            "key_personnel": [
                {
                    "name": "Gunnar Nilsson",
                    "position": "Verkst dir"
                }
            ],
            "establishment_year": 1921
        },
        "9": {
            "company_name": "NILSSONS TRIKÄFABRIK, AB",
            "pnr": "510 21",
            "address": "Sätüa",
            "phone_number": "0301-420 23",
            "activity": "Tillverkar scarves o stickade mössor",
            "annual_turnover": 1800000,
            "capital": 30000,
            "key_personnel": [
                {
                    "name": "Kjell Grebeüus",
                    "position": "Verkst dir"
                }
            ],
            "establishment_year": 1962
        },
        "10": {
            "company_name": "ELEKTROSKYLT AB",
            "pnr": "817 00",
            "address": "Norrsundet, Box 1",
            "phone_number": "0297-300 10 , 300 01",
            "bank_details": {
                "bankgiro": "785-2114",
                "postgiro": "173776-6"
            },
            "activity": "Tillverkar skyltar av alla slag, tryckta etiketter på plast o metallfolier, bokstäver, reflexmaterial m m",
            "employees": 5,
            "capital": 30000,
            "key_personnel": [
                {
                    "name": "Sören Engman",
                    "position": "Verkst dir"
                },
                {
                    "name": "Dan Engman",
                    "position": "Verkmäst"
                }
            ],
            "establishment_year": 1947
        }
    }
}