{
    "original": "WIKSTRÖM J:or, P\n\nPnr 10245\n\nStockholm 5, Stureg 46. Box 5251.\nTel 08-67 01 20. Bankgiro 16-0235.\nPostgiro 3415. Telex 1668. Tga\nWikströms\n\nVerksamhet: Säljer sågade trävaror,\nträfiberskivor, plywood m m\nAntal anställda: 25\nÅrsomsättning: 60 000 000\nÄgare o chef: Grossh Per Wikström\nEtableringsår: 18 36.\n\nWIKSTRÖM INGENJORSBYRÅ\nAB. SUNE\n\nPnr 400 24\n\nGöteborg 35, Brödrag 6. Box 35042.\nTel 031-400180. Bankgiro\n510-3213. Postgiro 241855-6\nVerksamhet: Konsulterande\ningenjörsbyrå. inom VVS\nAntal anställda: 25\nÅrsomsättning: 1500 000\nAktiekapital: 5 000\nVerkst dir: Sune Wikström\nEtableringsår: 1955.\n\nWKTRO FÄRG- &amp;\nFERNISS-FABRIK\n\nPnr 41110\n\nGöteborg. O Hamng 19 A. Tel\n031-17 3170. Bankgiro 153-0583.\nPostgiro 43672\n\nVerksamhet: Tillverkar Wicote\n\ntakmassa\n\nAntal anställda: 4\n\nÅrsomsättning: 500 000\n\nVerkst dir. Carl-Gustav Wiktorsson\n\nEtableringsår: 1947.\n\nWIHLBORG, BYGGNADS AB\nARNE\n\nPnr 23100\n\nTrelleborg, Corfitz Beck-Frlisg 1.\nTel 0410-154 40. Postgiro 536273\nVerksamhet: Byggnadsrörelse\nAntal anställda: 50\nÅrsomsättning: 3 000 000\nAktiekapital: 30 000\nVerkst dir: Byggmäst Arne\nWihlborg\n\nEtableringsår: 1959.\n\nTRI-FOL GLAS AB\n\nPnr 332 00\n\nGislaved, Màrtensg 14. Tel\n0371-12600. Bankgiro 617-8032.\nPostgiro 22081-4\n\nVerksamhet: Tillverkar laminerat\nbilglas\n\nAktiekapital: 100 000\nVerkst dir: Ing Yngve Gruvfält\nEtableringsår: 1970.\n\nENGELBREKT MASKIN AB\n\nPnr 112 33\n\nStockholm, Kronobergsg 21. Tel\n08-54 07 25. Bankgiro 11-4479.\nPostgiro 553580. Tga Engelbrekt.\nTelex 17305 NORDCO S\nVerksamhet: Säljer\nATMO-kompres-sorer samt\nBÖHLER-bergborr-maskiner\n\nAntal anställda: 10\nAktiekapital: 15 000\nStyrelse: Dir Björn Scherrer\nVerkst dir: Björn Scherrer\nKontorschef: Torbjörn Steiner\nEtableringsår: 1966\nDotterbolag till AB Marindiesel.\n\nENGELBREKTSON &amp; CO AB\n\nPnr 41117\n\nGöteborg, V Hamng 23. Tel\n031-13 2350, 13 23 52. Bankgiro\n42-0280. Postgiro 12136. Tga\nEngelbrekt\n\nVerksamhet: Grosshandel med järn\no metaller, halvfabrikat samt\ndiverse smiden o tillbehör\nAntal anställda: 6\nAktiekapital: 100000\nVerkst dir: Gustaf Engelbrektson\nEtableringsår: 1926.\n\nWALEIJ &amp; SÖNER, AB\n\nPnr 910 70\n\nDorotea, Box 31. Smedsv. Tel\n0942-100 27. 100 95. Bankgiro\n762-0719. Postgiro 80237-1\nVerksamhet: Tillverkar AWS\nskogsvagnar 8-15 ton med eller utan\nhydraulisk drift samt järn- o\nstålkonstruktioner. Legoarbeten\nVarunamn: AWS\nAntal anstäUda: 5\nÅrsomsättning: 500 000\nVerkst dir: O Waleij\nEtableringsår: 1892.\n\nFARMA TEXTILTRYCK AB\n\nPnr 51104\n\nKinna4, Fack. Tel 0320-110 9 3,\n108 42. Bankgiro 43-4797. Postgiro\n49988. Tga Farmatex\nVerksamhet: Tryckta o vävda\nhemtextilier\n\nAntal anställda: 13\nÅrsomsättning: 6 500 000\nAktiekapital: 60 000\nStyrelse: Disp Lennart Svefors,\ntextilkonstn:a Brita Svefors\nVerkst dir: Lennart Svefors\nEtableringsår: 1962.\n\nAUTOMAGNET, AB\n\nPnr 411 03\n\nGöteborg, Odinsg 20. Tel\n031-15 24 08, 15 24 09. Bankgiro 50-8088.\nPostgiro 40945\n\nVerksamhet: Bilelektrisk verkstad\nAntal anställda: 8\nÅrsomsättning: 680 000\nAktiekapital: 30 000\nVerkst dir: Holger Lindgren\nEtableringsår: 1922\nOmbildat till aktiebolag 1938.\n\nAUTOMAT,\nMETALLFABRIKEN\n\nPnr 33020\n\nAnderstorp, Box 2. Tel 0371-15910.\nBankgiro 488-0621. Postgiro\n2229 25-0\n\nVerksamhet: Tillverkar\nmaskin-formade tråddetaljer\nÄgare: Gunnar Svensson\nEtableringsår: 1944.\n\nAUTOMATDETALJER\nEBERSTEIN &amp; CO AB\n\nPnr 332 00\n\nGislaved, Karl Johansg 19. Box\n27. Tel 0371-102 17. Bankgiro\n426-7092. Postgiro 368458-6\nVerksamhet: Automatsvarvning\nAntal anställda: 3\nVerkst dir: B Eberstein\nEtableringsår: 1948.\n\nwagner, ab fredr\n\nPnr 101 10\n\nStockholm 1, Vasag 48. Pack. Tel\n08-22 99 00. Bankgiro 56-3604.\n\nPostgiro 912. Telex 19902. Tga\nFredwagner\n\nVerksamhet: Säljer tryckeri- o\nbok-binderimaskiner\nAntal anställda: 125\nAktiekapital: 1200 000\nVerkst dir: Arne Frögelius\nEtableringsån 1895.\n\nFIXFABRIKEN, AB\n\nPnr 414 51\n\nGöteborg. Bruksg 17. Tel 031-\n\n1241 20. Bankgiro 51-2720.\nPostgiro 40166. Tga Fixfabriken\nVerksamhet: Tillverkar o säljer\nbyggnadsbeslag, körvisare mm\nVarunamn: Fix, Fixlight, Fixlock,\nSurfing, Therglas\nAntal anställda: 250\nÅrsomsättning: 15 000 000\nAktiekapital: 600000\nVerkst dir: Walter Bengtsson\nEtableringsår: 1925.\n\nSVENSSON, AB LUDVIG\n\nPnr 51101\n\nKinna 1, Fack. Tel 0320-115 80.\nBankgiro 546-1157. Postgiro\n8747-8. Tga Ludvig. Telex 36014\nVerksamhet: Tillverkar\nhemtextilprodukter såsom gardiner,\ngardinlufter, duktyger, överkast (chenille).\nFärgeri o appreteringsverk\nAktiekapital: 800 000\nVeikst din Ivan L Ludvigson\nDisp: Sven Kylberg\nDriftsing: Sten Ludvigson\nKamrer: Ingemar Ericsson\nFörsäljn-chef: Stig Johansson\nProd-chef: Arne Wegsjö\nEtableringsår: 1928.\n\nSVENSSON &amp; CO\nSKEPPS-MÄKLERI AB, LUDVIG\n\nPnr 211 20\n\nMalmö C, Skeppsbron 5. Tel\n040-101310. Bankgiro 263-4152.\nPostgiro 435080-7. Tga Svensson.\nTelex 3154\n\nVerksamhet: Skeppsmäkleri,\nbefraktning o spedition\nAntal anställda: 9\nAktiekapital: 50 000\nVerkst dir: Skeppsmäkl K Sjögren\nEtableringsår. 1910.\n\nNOR\n\nAktiekapital: 100 000\nÄgare o chef: Bror Eliasson\nEtableringsår: 1952.\n\nNORDENDAG &amp; SÄF ST ROM,\n5MI DESFIRMAN\n\nPnr 753 23\n\nUppsala, Bergsbrunnag 10. Tel 018-\n\n14 6645, 1304 98. Bankgiro 35-\n\n3351. Postgiro 177350\n\nVerksamhet: Järnkonstruktioner o\n\nbyggnadssmlde\n\nAntal anställda: 25\n\nÄgare o chefer: G Nordendag,\n\nB Säf ström\n\nEtableringsår: 1941.",
    "structured": {
        "1": {
            "company_name": "WIKSTRÖM J:or, P",
            "pnr": 10245,
            "address": "Stockholm 5, Stureg 46. Box 5251.",
            "phone_number": "08-67 01 20",
            "bank_details": {
                "bankgiro": "16-0235",
                "postgiro": "3415"
            },
            "activity": "Säljer sågade trävaror, träfiberskivor, plywood m m",
            "employees": 25,
            "annual_turnover": 60000000,
            "key_personnel": [
                {
                    "name": "Grossh Per Wikström",
                    "position": "Ägare o chef"
                }
            ],
            "establishment_year": 1836
        },
        "2": {
            "company_name": "WIKSTRÖM INGENJORSBYRÅ AB. SUNE",
            "pnr": 40024,
            "address": "Göteborg 35, Brödrag 6. Box 35042.",
            "phone_number": "031-400180",
            "bank_details": {
                "bankgiro": "510-3213",
                "postgiro": "241855-6"
            },
            "activity": "Konsulterande ingenjörsbyrå. inom VVS",
            "employees": 25,
            "annual_turnover": 1500000,
            "capital": 5000,
            "key_personnel": [
                {
                    "name": "Sune Wikström",
                    "position": "Verkst dir"
                }
            ],
            "establishment_year": 1955
        },
        "3": {
            "company_name": "WKTRO FÄRG- & FERNISS-FABRIK",
            "pnr": 41110,
            "address": "Göteborg. O Hamng 19 A",
            "phone_number": "031-17 3170",
            "bank_details": {
                "bankgiro": "153-0583",
                "postgiro": "43672"
            },
            "activity": "Tillverkar Wicote takmassa",
            "employees": 4,
            "annual_turnover": 500000,
            "key_personnel": [
                {
                    "name": "Carl-Gustav Wiktorsson",
                    "position": "Verkst dir"
                }
            ],
            "establishment_year": 1947
        },
        "4": {
            "company_name": "WIHLBORG, BYGGNADS AB ARNE",
            "pnr": 23100,
            "address": "Trelleborg, Corfitz Beck-Frlisg 1",
            "phone_number": "0410-154 40",
            "postgiro": "536273",
            "activity": "Byggnadsrörelse",
            "employees": 50,
            "annual_turnover": 3000000,
            "capital": 30000,
            "key_personnel": [
                {
                    "name": "Byggmäst Arne Wihlborg",
                    "position": "Verkst dir"
                }
            ],
            "establishment_year": 1959
        },
        "5": {
            "company_name": "TRI-FOL GLAS AB",
            "pnr": 33200,
            "address": "Gislaved, Màrtensg 14",
            "phone_number": "0371-12600",
            "bank_details": {
                "bankgiro": "617-8032",
                "postgiro": "22081-4"
            },
            "activity": "Tillverkar laminerat bilglas",
            "capital": 100000,
            "key_personnel": [
                {
                    "name": "Ing Yngve Gruvfält",
                    "position": "Verkst dir"
                }
            ],
            "establishment_year": 1970
        },
        "6": {
            "company_name": "ENGELBREKT MASKIN AB",
            "pnr": 11233,
            "address": "Stockholm, Kronobergsg 21",
            "phone_number": "08-54 07 25",
            "bank_details": {
                "bankgiro": "11-4479",
                "postgiro": "553580"
            },
            "activity": "Säljer ATMO-kompres-sorer samt BÖHLER-bergborr-maskiner",
            "employees": 10,
            "capital": 15000,
            "key_personnel": [
                {
                    "name": "Björn Scherrer",
                    "position": "Styrelse, Verkst dir"
                },
                {
                    "name": "Torbjörn Steiner",
                    "position": "Kontorschef"
                }
            ],
            "establishment_year": 1966
        },
        "7": {
            "company_name": "ENGELBREKTSON & CO AB",
            "pnr": 41117,
            "address": "Göteborg, V Hamng 23",
            "phone_number": "031-13 2350, 13 23 52",
            "bank_details": {
                "bankgiro": "42-0280",
                "postgiro": "12136"
            },
            "activity": "Grosshandel med järn o metaller, halvfabrikat samt diverse smiden o tillbehör",
            "employees": 6,
            "capital": 100000,
            "key_personnel": [
                {
                    "name": "Gustaf Engelbrektson",
                    "position": "Verkst dir"
                }
            ],
            "establishment_year": 1926
        },
        "8": {
            "company_name": "WALEIJ & SÖNER, AB",
            "pnr": 91070,
            "address": "Dorotea, Box 31. Smedsv.",
            "phone_number": "0942-100 27, 100 95",
            "bank_details": {
                "bankgiro": "762-0719",
                "postgiro": "80237-1"
            },
            "activity": "Tillverkar AWS skogsvagnar 8-15 ton med eller utan hydraulisk drift samt järn- o stålkonstruktioner. Legoarbeten",
            "employees": 5,
            "annual_turnover": 500000,
            "key_personnel": [
                {
                    "name": "O Waleij",
                    "position": "Verkst dir"
                }
            ],
            "establishment_year": 1892
        },
        "9": {
            "company_name": "FARMA TEXTILTRYCK AB",
            "pnr": 51104,
            "address": "Kinna4, Fack.",
            "phone_number": "0320-110 9 3, 108 42",
            "bank_details": {
                "bankgiro": "43-4797",
                "postgiro": "49988"
            },
            "activity": "Tryckta o vävda hemtextilier",
            "employees": 13,
            "annual_turnover": 6500000,
            "capital": 60000,
            "key_personnel": [
                {
                    "name": "Disp Lennart Svefors",
                    "position": "Styrelse"
                },
                {
                    "name": "Arne Frögelius",
                    "position": "Verkst dir"
                }
            ],
            "establishment_year": 1962
        },
        "10": {
            "company_name": "AUTOMAGNET, AB",
            "pnr": 41103,
            "address": "Göteborg, Odinsg 20",
            "phone_number": "031-15 24 08, 15 24 09",
            "bank_details": {
                "bankgiro": "50-8088",
                "postgiro": "40945"
            },
            "activity": "Bilelektrisk verkstad",
            "employees": 8,
            "annual_turnover": 680000,
            "capital": 30000,
            "key_personnel": [
                {
                    "name": "Holger Lindgren",
                    "position": "Verkst dir"
                }
            ],
            "establishment_year": 1922
        },
        "11": {
            "company_name": "AUTOMAT, METALLFABRIKEN",
            "pnr": 33020,
            "address": "Anderstorp, Box 2",
            "phone_number": "0371-15910",
            "bank_details": {
                "bankgiro": "488-0621",
                "postgiro": "2229 25-0"
            },
            "activity": "Tillverkar maskin-formade tråddetaljer",
            "owner": "Gunnar Svensson",
            "establishment_year": 1944
        },
        "12": {
            "company_name": "AUTOMATDETALJER EBERSTEIN & CO AB",
            "pnr": 33200,
            "address": "Gislaved, Karl Johansg 19. Box 27",
            "phone_number": "0371-102 17",
            "bank_details": {
                "bankgiro": "426-7092",
                "postgiro": "368458-6"
            },
            "activity": "Automatsvarvning",
            "employees": 3,
            "key_personnel": [
                {
                    "name": "B Eberstein",
                    "position": "Verkst dir"
                }
            ],
            "establishment_year": 1948
        },
        "13": {
            "company_name": "wagner, ab fredr",
            "pnr": 10110,
            "address": "Stockholm 1, Vasag 48. Pack",
            "phone_number": "08-22 99 00",
            "bank_details": {
                "bankgiro": "56-3604",
                "postgiro": "912"
            },
            "activity": "Säljer tryckeri- o bok-binderimaskiner",
            "employees": 125,
            "capital": 1200000,
            "key_personnel": [
                {
                    "name": "Arne Frögelius",
                    "position": "Verkst dir"
                }
            ],
            "establishment_year": 1895
        },
        "14": {
            "company_name": "FIXFABRIKEN, AB",
            "pnr": 41451,
            "address": "Göteborg. Bruksg 17",
            "phone_number": "031-124120",
            "bank_details": {
                "bankgiro": "51-2720",
                "postgiro": "40166"
            },
            "activity": "Tillverkar o säljer byggnadsbeslag, körvisare mm",
            "varunamn": "Fix, Fixlight, Fixlock, Surfing, Therglas",
            "employees": 250,
            "annual_turnover": 15000000,
            "capital": 600000,
            "key_personnel": [
                {
                    "name": "Walter Bengtsson",
                    "position": "Verkst dir"
                }
            ],
            "establishment_year": 1925
        },
        "15": {
            "company_name": "SVENSSON, AB LUDVIG",
            "pnr": 51101,
            "address": "Kinna 1, Fack",
            "phone_number": "0320-115 80",
            "bank_details": {
                "bankgiro": "546-1157",
                "postgiro": "8747-8"
            },
            "activity": "Tillverkar hemtextilprodukter såsom gardiner, gardinlufter, duktyger, överkast (chenille). Färgeri o appreteringsverk",
            "capital": 800000,
            "key_personnel": [
                {
                    "name": "Ivan L Ludvigson",
                    "position": "Verkst dir"
                },
                {
                    "name": "Sten Ludvigson",
                    "position": "Driftsing"
                }
            ],
            "establishment_year": 1928
        },
        "16": {
            "company_name": "SVENSSON & CO SKEPPS-MÄKLERI AB, LUDVIG",
            "pnr": 21120,
            "address": "Malmö C, Skeppsbron 5",
            "phone_number": "040-101310",
            "bank_details": {
                "bankgiro": "263-4152",
                "postgiro": "435080-7"
            },
            "activity": "Skeppsmäkleri, befraktning o spedition",
            "employees": 9,
            "capital": 50000,
            "key_personnel": [
                {
                    "name": "Skeppsmäkl K Sjögren",
                    "position": "Verkst dir"
                }
            ],
            "establishment_year": 1910
        },
        "17": {
            "company_name": "NOR",
            "capital": 100000,
            "key_personnel": [
                {
                    "name": "Bror Eliasson",
                    "position": "Ägare o chef"
                }
            ],
            "establishment_year": 1952
        },
        "18": {
            "company_name": "NORDENDAG & SÄF ST ROM, 5MI DESFIRMAN",
            "pnr": 75323,
            "address": "Uppsala, Bergsbrunnag 10",
            "phone_number": "018-14 6645, 1304 98",
            "bank_details": {
                "bankgiro": "35-3351",
                "postgiro": "177350"
            },
            "activity": "Järnkonstruktioner o byggnadssmlde",
            "employees": 25,
            "key_personnel": [
                {
                    "name": "G Nordendag",
                    "position": "Ägare o chef"
                },
                {
                    "name": "B Säf ström",
                    "position": "Ägare o chef"
                }
            ],
            "establishment_year": 1941
        }
    }
}