{
    "original": "JULARBO PLASTIC, AB\n\nPnr 775 01\n\nKrylbo 1, Box 8. Tel 0226-660 59.\nTga Avawood\n\nVerksamhet: Tvättklämmor i plast\nÅrsomsättning: 250 000\nAktiekapital: 5 000\nEtableringsår: 1964.\n\nWEIBULL. GARVAMNES AB\n\nPnr 261 53\n\nLandskrona, Ringv 163. Tel\n0418-163 60. Tga Weibulltan\nVerksamhet: Framställer kemiska\nprodukter\n\nAntal anställda: 52\nÅrsomsättning: 7 000 000\nAktiekapital: 1800 000\nVerkst dir: Sture Holmberg\növering: Stig Nilsson\nEtableringsår: 1917\nDotterföretag till Bergviks\nHartsprodukter AB, Söderhamn.\n\nWEIBULL AB, INGENIURS.\nFIRMAN NILS\n\nPnr 201 21\n\nMalmö 1, Box 184. Tel 040-15 8142.\nHässleholm. Tel 0451-141 15.\nPostgiro 39546-7. Tga Nilswei.\nTelex 32226 NILSWEI S,\n4486 NILSWEI S\n\nVerksamhet: Konstruktionskontor o\nmekaniska verkstäder. Projekterar\no tillverkar siloanläggningar,\ntransportanläggningar o\nförpackningsmaskiner. Tillverkar maskiner o\napparater efter egna o kunders\nkonstruktioner o ritningar\nAntal anställda: 300 (inkl\ndotterföretag)\n\nÅrsomsättning: 14 000 000 (inkl\n\ndotterföretag)\n\nAktiekapital: 303 300 (inkl\ndotterföretag)\n\nStyrelse: Civiling Erik Lindeblad\n(ordf), civiling Claes Weibull,\nadv Denver Weibull\nVerkst dir: Civiling Claes Weibull\nVerkstadschef: Börje Persson\nEtableringsår: 1921\nOmbildat till aktiebolag 1954.\nDotterbolag: AB Hässleholms\nVerkstäder, Hässleholm.\n\nWEIBULL AB, W\n\nPnr 261 20\n\nLandskrona 1, Fack. Tel\n0418-780 00. Bankgiro 660-1074.\nPostgiro 6760-3. Tga Weibull.\nTelex 72388\n\nVerksamhet: Växtförädling.\nUtsädeshandel, originalutsäden för\nlantbruk o trädgård\nAntal anställda: 800\nÅrsomsättning: 125 000 000\nAktiekapital: 6 000 000\nVerkst dir: Widar Weibull\nV verkst dirr: Fritz Nordén, Gösta\nGranström\n\nEtableringsår: 1870.\n\nHURLE BRUK, AB\n\nPnr 33100\n\nVärnamo. Tel 0370-200 20 , 20040.\nTga Brukethörle\n\nVerksamhet: Tillverkar sågade o\nhyvlade trävaror\nAntal anställda: 39\nÅrsomsättning: 2 999 000\nAktiekapital: 900 000\nVerkst dir: Rolf Böhn.\n\nHOR LE TRÅD, AB\n\nPnr 33100\n\nVärnamo, Hörle. Tel 03 70-200 00.\nBankgiro 260-47 75. Postgiro\n532311-8. Tga HT WIRE.\nTelex 70177 HTWIRE S\nVerksamhet: Tillverkar tråd i ring\ninom dimensionsområdet 0,5-20 mm,\ntråd i riktade längder\ndimensionsområdet 0,6-14 mm, plattvalsadtråd,\narmeringsnät, armeringsstål\n(Bi-stål), kallbearbetade profiler,\n\nemballagetråd, även öglad\nFilialer: Rydaholm o Värnamo\nAntal anställda: 100\nÅrsomsättning: 20 000 000\nAktiekapital: 750 000\nStyrelse: Dir Per Hjalmar\nFagerholm (ordf), dlr Sven Broman, dir\nDick Gelbjerg-Hansen\nVerkst dir: Sven Broman\nPlatschef: Ing Ake Carlsson\nÄgare: Edw H Thomée AB, Malmö.\n\nHÖRNELL, JOHN A\n\nPnr 890 27\n\nOverhömäs, Box 1220. Tel\n0660-70 1 60 , 700 61. Bankgiro 771-5501.\nPostgiro 64000-3\nVerksamhet: Tillverkar o säljer\nsport- o arbetshandskar, vantar,\ntofflor, mössor o bilsitsar\nChef: Fabr John A Hörnell\nEtableringsån 1936.\n\nNÄSSJÖ GLASMÄSTERI AB\n\nPnr 57100\n\nNässjö, Storg 13. Tel 0380-12110,\n19000. Bankgiro 985-5024.\nPostgiro 387902-0\n\nVerksamhet: Säljer byggnads-,\ninrednings-, plast- o spegelglas,\nbilrutor, samt har sliperi o\ntillverkning av blyfönster, speglar o\nbordsskivor i glas\nAktiekapital: 20 000\nVerkst dir: Gunnar Winkvist\nEtableringsår: 1948.\n\nRUBE, AB\n\nPnr 330 31\n\nKulltorp. Tel 0370-82270.\nBankgiro 542-6176. Postgiro 577388-2.\nTga Rube\n\nVerksamhet: Tillverkar\npressgjutgods, verktyg, stålrör, kontorsstolar.\nUtför svarvningsarbeten i järn o\nmetall\n\nAntal anställda: 40\n\nÅrsomsättning: 6 000 000\n\nAktiekapital: 60 000\n\nStyrelse: Ing Rune Karlsson (ordf),\n\ndir Bengt Erlandsson, ing Rune\n\nLidén\n\nVerkst din Ing Rune Karlsson\nEtableringsàr: 1960.\n\nRUBERGS FABRIKS AB, WILH\n\nPnr 29105\n\nKristianstad 5, Långebrog 22. Box\n5105. Tel 044-11 01 74, 11 01 78.\nBankgiro 657-9296. Postgiro\n288384-1\n\nVerksamhet: Tillverkar pumpar,\nmotorsprutor o brandmaterial,\nsyrgas o dissousgas\nAntal anställda: 50\nÅrsomsättning: 2000 000\nAktiekapital: 30 000\nVerkst din Ing Wilh Ruberg\nEtableringsàr: 1923\nOmbildat till aktiebolag 1942.\n\nRUBIN ARKITEKT- &amp;\nINGENIORSBYRA AB, OWE\n\nPnr 29100\n\nKristianstad, Magasinsg 2. Tel\n044-12 32 45. Bankgiro 658-0187.\nPostgiro 585754-5\nVerksamhet; Arkitekt- o\ningeniörs-byrå. Totalprojektering med\ntonvikt på industrin.\nByggnadskontroll. Besiktningar\nAvdelningskontor: 283 00 Osby,\nPostg 4 B. Tel 0479-133 00\nAntal anställda: 20\nÅrsomsättning: 1500 000\nAktiekapital: 50 000\nStyrelse: Ing Owe Rubin, fru\nGunny Elsebet Rubin, ing Sven\nErik Hallberg\nVerkst din Ing Owe Rubin\nEtableringsàr 1961.\n\nALESON &amp; CO, P\n\nPnr 116 47\n\nStockholm, Sankt Paulsg 11. Tel\n08-40 75 25, 4139 33. Bankgiro\n70-0322. Postgiro 500395-9. Tga\nPalesonco. Telex 1575\nVerksamhet: Importagenturer i\nRå-kaffe\n\nÄgare: Per Aleson, Nilserik Ekborg\nEtableringsår: 1950.\n\nALLSVETS I OREBRO AB\n\nPnr 703 58\n\nÖrebro, Bessemerv 10. Tel\n019-12 47 8 5. Bankgiro 815-5616.\nPostgiro 368530-2\n\nVerksamhet: Tillverkar på\nbeställning maskiner o maskindetaljer,\ntryckkärl, cisterner, pålsmide o\narbeten av rostfritt material. Utför\nmontagearbeten, svetsning, mek o\nreparationsarbeten\nAntal anställda: 75\nÅrsomsättning: 6000 000\nAktiekapital: 150 000\nVerkst dir: Fabr Gösta Klingberg\nVerkstadschef: Ing Ingemar Björk\nEtableringsår: 1954.\n\nALLT FOR\nBYGGNADSFACKET AB\n\nPnr 100 21\n\nStockholm 18, Pack. Tel\n08-54 05 40. Bankgiro 44-7218.\nPostgiro 151470. Tga Håessbe\nVerksamhet: Byggnadsmaterial,\nprodukter från HSB:s industrier\nChef: Dir Rolf Persson.\n\nALLT I PLÅT, AB\n\nPnr 360 70\n\nAseda, Box 124. Tel 0474-108 50.\nBankgiro 8 58-50 28. Postgiro\n291995-9\n\nVerksamhet: Tillverkar\nvattenvär-mare, förbränningsugnar, bastuugnar\nAntal anställda: 30\nAktiekapital: 75 000\nVerkst dir: Ragnar Persson\nEtableringsår: 1945.\n\nHARBIG, AB ERNST\n\nPnr 111 21\n\nStockholm, Drottningg 70. Tel\n08-10 63 69, 115169. Bankgiro\n13-6132. Postgiro 3257. Telex 10316.\nTga Ernstharbig\n\nVerksamhet: Säljer grafiska\nmaskiner, vakuumpumpar o\nkompressorer\n\nVarunamn: Gebr Becker, Vickers\n(Engineers) Ltd\nAktiekapital: 50 000\nVerkst dir: Lennart Harbig\nEtableringsår: 1922.\n\nVOL\n\nWOCOTEX AB\n\nPnr 116 25\n\nStockholm, üstgötag 45. Tel\n08-44 55 95, 44 56 55. Bankgiro\n284-0379. Postgiro 556620-3. Tga\nWocotex. Telex 1605\nVerksamhet: Generalagenturer 1\nmyntstyrda bil- o tvättautomater,\ntvätt- o oljemedel etc\nUtställning: Stockholm SU, Asög\n128. Tel 08-40 0136\nVarunamn: Woco\nAktiekapital: 10 000\nStyrelse: Fru Inga Wåhlin (ordf),\ndir Ove Cargin\nVerkst dir: Ove Cargin\nEtableringsår: 1962.\n\nCERES, INDUSTRI AB\n\nPnr 211 20\n\nMalmö, Citadellsv 17. Tel\n040-1213 47. Bankgiro 260-0336.\nPostgiro 14093-8. Tga Oljeceres\nVerksamhet: Säljer kitt,\nrostskyddsolja o kem-tekn artiklar\nAntal anställda: 4\nÅrsomsättning: 500 000\n.Aktiekapital: 450 000\nVerkst dir: H Nilsson\nEtableringsår: 1902.",
    "structured": {
        "1": {
            "company_name": "JULARBO PLASTIC, AB",
            "pnr": "775 01",
            "address": "Krylbo 1, Box 8",
            "phone_number": "0226-660 59",
            "activity": "Tvättklämmor i plast",
            "annual_turnover": 250000,
            "capital": 5000,
            "establishment_year": 1964
        },
        "2": {
            "company_name": "WEIBULL. GARVAMNES AB",
            "pnr": "261 53",
            "address": "Landskrona, Ringv 163",
            "phone_number": "0418-163 60",
            "activity": "Framställer kemiska produkter",
            "employees": 52,
            "annual_turnover": 7000000,
            "capital": 1800000,
            "establishment_year": 1917
        },
        "3": {
            "company_name": "WEIBULL AB, INGENIURS. FIRMAN NILS",
            "pnr": "201 21",
            "address": "Malmö 1, Box 184",
            "phone_number": "040-15 8142",
            "employees": 300,
            "annual_turnover": 14000000,
            "capital": 303300,
            "establishment_year": 1921
        },
        "4": {
            "company_name": "WEIBULL AB, W",
            "pnr": "261 20",
            "address": "Landskrona 1, Fack",
            "phone_number": "0418-780 00",
            "activity": "Växtförädling",
            "employees": 800,
            "annual_turnover": 125000000,
            "capital": 6000000,
            "establishment_year": 1870
        },
        "5": {
            "company_name": "HURLE BRUK, AB",
            "pnr": "33100",
            "address": "Värnamo",
            "phone_number": "0370-200 20 , 20040",
            "activity": "Tillverkar sågade o hyvlade trävaror",
            "employees": 39,
            "annual_turnover": 2999000,
            "capital": 900000,
            "establishment_year": null
        },
        "6": {
            "company_name": "HOR LE TRÅD, AB",
            "pnr": "33100",
            "address": "Värnamo, Hörle",
            "phone_number": "03 70-200 00",
            "activity": "Tillverkar tråd i ring inom dimensionsområdet 0,5-20 mm",
            "employees": 100,
            "annual_turnover": 20000000,
            "capital": 750000,
            "establishment_year": null
        },
        "7": {
            "company_name": "HÖRNELL, JOHN A",
            "pnr": "890 27",
            "address": "Overhömäs, Box 1220",
            "phone_number": "0660-70 1 60 , 700 61",
            "activity": "Tillverkar o säljer sport- o arbetshandskar, vantar, tofflor, mössor o bilsitsar",
            "establishment_year": 1936
        },
        "8": {
            "company_name": "NÄSSJÖ GLASMÄSTERI AB",
            "pnr": "57100",
            "address": "Nässjö, Storg 13",
            "phone_number": "0380-12110, 19000",
            "activity": "Säljer byggnads-, inrednings-, plast- o spegelglas",
            "owners": "Not specified",
            "establishment_year": 1948
        },
        "9": {
            "company_name": "RUBE, AB",
            "pnr": "330 31",
            "address": "Kulltorp",
            "phone_number": "0370-82270",
            "activity": "Tillverkar pressgjutgods, verktyg, stålrör, kontorsstolar",
            "employees": 40,
            "annual_turnover": 6000000,
            "capital": 60000,
            "establishment_year": 1960
        },
        "10": {
            "company_name": "RUBERGS FABRIKS AB, WILH",
            "pnr": "29105",
            "address": "Kristianstad 5, Långebrog 22, Box 5105",
            "phone_number": "044-11 01 74, 11 01 78",
            "activity": "Tillverkar pumpar, motorsprutor o brandmaterial, syrgas o dissousgas",
            "employees": 50,
            "annual_turnover": 2000000,
            "capital": 30000,
            "establishment_year": 1923
        },
        "11": {
            "company_name": "RUBIN ARKITEKT- & INGENIORSBYRA AB, OWE",
            "pnr": "29100",
            "address": "Kristianstad, Magasinsg 2",
            "phone_number": "044-12 32 45",
            "activity": "Arkitekt- o ingenjörs-byrå. Totalprojektering med tonvikt på industrin",
            "employees": 20,
            "annual_turnover": 1500000,
            "capital": 50000,
            "establishment_year": 1961
        },
        "12": {
            "company_name": "ALESON & CO, P",
            "pnr": "116 47",
            "address": "Stockholm, Sankt Paulsg 11",
            "phone_number": "08-40 75 25, 4139 33",
            "activity": "Importagenturer i Rå-kaffe",
            "owners": "Per Aleson, Nilserik Ekborg",
            "establishment_year": 1950
        },
        "13": {
            "company_name": "ALLSVETS I OREBRO AB",
            "pnr": "703 58",
            "address": "Örebro, Bessemerv 10",
            "phone_number": "019-12 47 8 5",
            "activity": "Tillverkar på beställning maskiner o maskindetaljer, tryckkärl, cisterner, pålsmide o arbeten av rostfritt material"
        },
        "14": {
            "company_name": "ALLT FOR BYGGNADSFACKET AB",
            "pnr": "100 21",
            "address": "Stockholm 18, Pack",
            "phone_number": "08-54 05 40",
            "activity": "Byggnadsmaterial, produkter från HSB:s industrier"
        },
        "15": {
            "company_name": "ALLT I PLÅT, AB",
            "pnr": "360 70",
            "address": "Aseda, Box 124",
            "phone_number": "0474-108 50",
            "activity": "Tillverkar vattenvärmare, förbränningsugnar, bastuugnar",
            "employees": 30,
            "capital": 75000,
            "establishment_year": 1945
        },
        "16": {
            "company_name": "HARBIG, AB ERNST",
            "pnr": "111 21",
            "address": "Stockholm, Drottningg 70",
            "phone_number": "08-10 63 69, 115169",
            "activity": "Säljer grafiska maskiner, vakuumpumpar o kompressorer",
            "capital": 50000,
            "establishment_year": 1922
        },
        "17": {
            "company_name": "VOL WOCOTEX AB",
            "pnr": "116 25",
            "address": "Stockholm, üstgötag 45",
            "phone_number": "08-44 55 95, 44 56 55",
            "activity": "Generalagenturer 1 myntstyrda bil- o tvättautomater, tvätt- o oljemedel etc",
            "capital": 10000,
            "establishment_year": 1962
        },
        "18": {
            "company_name": "CERES, INDUSTRI AB",
            "pnr": "211 20",
            "address": "Malmö, Citadellsv 17",
            "phone_number": "040-1213 47",
            "activity": "Säljer kitt, rostskyddsolja o kem-tekn artiklar",
            "employees": 4,
            "annual_turnover": 500000,
            "capital": 450000,
            "establishment_year": 1902
        }
    }
}