{
    "original": "SKD\n\nSKÅNSKA GUMMI AB\n\nPnr 235 00\n\nVellinge, Malmöv. Pack. Tel\n040-4207 70. Bankgiro 666-2365.\nPostgiro 431030-6, Tga Scaniarubber\nVerksamhet: Tillverkar o säljer\nsittmöbler, sängar, industridetaljer\ni formpressad kallskum. Madrasser,\nplymåer i polyeter\nAntal anställda: 50\nÅrsomsättning: 5 000 000\nAktiekapital: 200 000\nVerkst dir: Henry Persson\nEtableringsàr: 1952.\n\nSKÅNSKA LANTMÄNNENS\nCENTRALFURENING U P A\n\nPnr 201 24\n\nMalmö 1, Box 485. Tel 040-738 20.\nBankgiro 34-8354. Postgiro 14174.\nTga Centralförening\nVerksamhet: Fodermedel,\ngödselmedel, spannmål, utsäde, potatis,\neldningsoljor, driv- o smörjmedel,\nbyggnadsmaterial, trä- o järnvaror,\nkemiska preparat m m\nAntal anstäUda: 940\nÅrsomsättning: 513 308 000\nVerkst dir: Birger Håstadius\nEtableringsàr: 1904.\n\nSKÅNSKA MAKADAM.\nFABRIKEN, AB\n\nPnr 265 01\n\nÅstorp 1, Box 104. Tel 042-509 75.\nBankgiro 67-1305. Postgiro 84050.\nTga Skamack\n\nVerksamhet: Tillverkar makadam\no betong\n\nAntal anställda: 93\nÅrsomsättning: 11000 000\nAktiekapital: 1800 000\nVerkst dir: Börje Berendahl\nEtableringsàr: 1903.\n\nSKÅNSKA\nPAPPERS-CENTRALEN AB\n\nPnr 212 28\n\nMalmö, Sallerupsv 90. Tel\n040-93 54 30. Bankgiro 641-3439.\nPost-giro 39247-2\n\nVerksamhet: Allt i pappersvaror o\nemballageartiklar. Egna\ntillverkningar\n\nAntal anställda: 39\nÅrsomsättning: 3 200 000\nAktiekapital: 30 000\nVerkst dir: Iwe Andersson\nEtableringsàr: 1935.\n\nSKÅNSKA SKRUV.\nFABRIKEN, AB\n\nPnr 272 00\n\nSimrishamn, Fabriken 1. Tel\n0414-10208. Bankgiro 662-2668.\nPostgiro 284000-0\n\nVerksamhet: Automatsvarvade\nartiklar upp till 60 mm diameter\nAntal anstäUda: 21\nÅrsomsättning: 800 000\nAktiekapital: 50 000\nVerkst dir: Birger Johnsson\nEtableringsàr 1951.\n\nJON\n\nJONSSON &amp; HALLSJU AB\n\nPnr 782 00\n\nMalung. Tel 0280-100 50, 105 50.\nBankgiro 79-7035. Postgiro 30182\nVerksamhet: Tillverkar o säljer\nskinnkläder i parti\nAntal anställda: 30\nÅrsomsättning: 1 200 000\nAktiekapital: 75 000\nVerkst dir: Ingvar Hallsjö\nEtableringsår: 1915\nOmbildat till aktiebolag 1954.\n\nJOHNSON HILL AB\n\nPnr 700 02\n\nÖrebro 2, Bettorpsg 8. Box 2103.\nTel 019-14 01 50. Tga Johnsonhill\nVerksamhet: Offsettryckeri\nAntal anställda: 80\nAktiekapital: 1 750 000\nVerkst dir: Sune Johansson\nEtableringsår 1900.\n\nHALLQVIST LÄDER AB,\nOSCAR\n\nPnr 21134\n\nMalmö, Skomakareg 12. Tel\n040-72175. Bankgiro 640-1376.\nPostgiro 24592-8\n\nVerksamhet: Tillverkar skärp o\n\nHALLSTA INDUSTRI.\nTJÄNST AB\n\nPnr 734 00\n\nHallstahammar, Videv 6 C. Tel\n0220-134 32. Postgiro 612234-5\nVerksamhet: Grovplåtslageri samt\nsvetsningsverkstad\nVerkstad: Hallstahammar,\nSmåindustriområde. Tel 0220-110 03\nAntal anställda: 35\nÅrsomsättning: 2 600 000\nAktiekapital: 10 000\nChefer: Thure Koorp, Karl Hjärpe\nEtableringsår: 1963.\n\nHALLSTABERGS MEK VERK.\nSTAD\n\nPnr 725 90\n\nVästerås, Björksta. Tel\n0171-431 23. Postgiro 285471\nVerksamhet: Tillverkar\nbetongvältar för lantbruk\nÅrsomsättning: 25 000\nChef: Agne Kihlin\nEtableringsår: 1945.\n\nJUBELS AB\n\nPnr 53101\n\nLidköping 1, Läckög 11. Box 79.\nTel 0510-27120. Bankgiro\n841-3767. Postgiro 14924-5\nVerksamhet: Dörrfabrik o sågverk.\nSäljer byggvaror o småhus i\nLidköping. Skara o Mariestad\nAntal anställda: 200\nÅrsomsättning: 25 000000\nAktiekapital: 1500 000\nVerkst dir: Lars Svensson\nEtableringsår: 1870\nDotterbolag: Lovene Dörrfabriks AB,\nLidköping, Skara Trä\nKämpagår-den AB, Skara, Timanders\nByggmaterial AB, Timmersdala.\n\nJUDELLS RDR AB\n\nPnr 199 00\n\nEnköping, Stureplan. Tel\n0171-332 40. Postgiro 33542-2\nVerksamhet: Värme, sanitet o olja\nFilialer. Bälsta. Tel 0171-506 50\nSala, Freds g 19. Tel 0224-13105\nSträngnäs, Nikanderg 5. Tel\n0152-109 82, 122 08\nAntal anställda: 90\nÅrsomsättning: 8 000 000\nAktiekapital: 50 000\nFirmatecknare: E E Judell, R H\nJude 11\n\nEtableringsår: 1954.\n\nSNICKERI &amp; LACKERING AB\n\nPnr 422 46\n\nHisings Backa, Backadalsmotet.\nTel 031-521944, 5219 43\nVerksamhet: Tillverkar lastpallar,\npallkragar, emballage\nAntal anstäUda: 12\nAktiekapital: 50 000\nVerkst dir: Rune Johansson\nEtableringsår: 1950.\n\nBOHLIN &amp; CO AB, ALB\n\nPnr 41101\n\nGöteborg, Stampg 60. Tel\n031-15 11 06, 15 11 33. Bankgiro\n50-0219. Postgiro 40710. Tga\nBoh-linco\n\nVerksamhet: Tillverkar herrhattar\no mössor av tyg\nAntal anställda: 50\nÅrsomsättning: 2 500 000\nAktiekapital: 100 000\nEtableringsår: 1894.\n\nWELANDER &amp; JOSEPHSON, AB\n\nPnr 172 24\n\nSundbyberg 1, Box 132.\nPräst-gårdsg 8-10. Tel 08-98 14 65,\n98 34 11. Bankgiro 724-5160.\nPostgiro 455501-7. Tga Wejomotor.\nTelex 10459\n\nVerksamhet: Grossistförsäljning\nav sport- o fritidsartiklar\nAntal anstäUda: 23\nÅrsomsättning: 9 000 000\nAktiekapital: 50 000\nVerkst din Jan Erik Josephson\nEtableringsår: 1952.\n\nCALCOTRADING AB\n\nPnr 211 34\n\nMalmö, Söderg 12. Tel 040-775 60.\n\nBankgiro 26-1105. Postgiro 632927.\n\nTga Calco. Telex 32583 CALOS S\n\nVerksamhet: Import o agentur med\n\nkemikalier\n\nAntal anställda: 5\n\nÅrsomsättning: 5 000 000\n\nAktiekapital: 15 000\n\nÄgare o chefer: Bertil Thilly, Sven\n\nEriksson\n\nEtableringsår: 1965.\n\nGAMEO, AB\n\nPnr 41115\n\nGöteborg, Kyrkog 4. Tel\n031-1179 73, 1183 76. Bankgiro\n33-7386. Postgiro 420575. Tga Gameo\nVerksamhet: Agentur elektr\nhushållsmaskiner såsom tvättmaskiner\nAntal anställda: 3\nAktiekapital: 25 000\nVerkst dir: Göran Ohlsson\nEtableringsår: 1930.\n\nLAHOLMS KERAMIK\n\nPnr 312 00\n\nLaholm, Repslagareg 12. Box 70.\nTel 0430-104 81. Bankgiro\n659-1457. Postgiro 321759-3\nVerksamhet: Tillverkar\nprydnadskeramik\n\nAntal anställda: 17\nÅrsomsättning: 700 000\nChef: Fabr Olof Larson.\n\nLAHOLM STAL AB\n\nPnr 312 00\n\nLaholm, Repslagareg 1. Tel\n0430-114 91, 12193. Bankgiro 296-6075.\nPostgiro 74933-3. Tga Laholmstål\nVerksamhet: Centrifugalgjutning\nav rostfria ämnesrör. Mek verkstad\nAntal anställda: 14\nAktiekapital: 300 000\nStyrelse: Adv Bror-Emil Jeppsson\n(ordf), ing Nils Jensen, dir Villy\nJensen\n\nVerkst dir: Ing Nils Jensen\nEtableringsår: 1962.\n\nLAHOLMS TIDNING\nFÖRENING UPA\n\nPnr 31201\n\nLaholm 1. Smedjeg 2. Box 78. Tel\n0430-116 50, 103 00. Bankgiro\n659-1176. Postgiro 175758-2, 179080-7\nVerksamhet: Tidningstryckeri\nAntal anställda: 18\nÅrsomsättning: 800 000\nVerkst dir o ansvarig utgivare:\nRichard Bengtsson\nChefred: Låge Bengtsson\nEtableringsår: 1931.\n\nLAHOLMSORTENS\nLANTMANNAFORENING UPA\n\nPnr 312 00\n\nLaholm, Lantmannag. Tel\n0430-122 50. Postgiro 146959-2\nVerksamhet: Handel med\nlantbruksförnödenheter o byggnadsmaterial\nAntal anställda: 19\nÅrsomsättning: 19100 000\nInsatskapital: 2 200 000\nChef: Disp Georg Andersson\nEtableringsår: 1913.\n\nLAIBLE-ALBERTS,\nINGEN-JORSFIRMA W\n\nPnr 59100\n\nMotala, Utsiktsv 22 B. Tel\n0141-117 19. Bankgiro 822-0238.\nPostgiro 464421-7. Tga Laible.\nTelex 5599 LAIBLE S\nVerksamhet: Vapen för militärt o\ncivilt bruk. Hel- o halvfabrikat\nfor den mek industrin.\nSymaskinsdelar, verktyg, fixturer,\nspecial-mätdon, automatiska fräsmaskiner\nChef: Ing Walter Laible\nEtableringsår: 1950.",
    "structured": {
        "firms": [
            {
                "company_name": "SKÅNSKA GUMMI AB",
                "pnr": "235 00",
                "address": "Vellinge, Malmöv. Pack.",
                "phone_number": "040-4207 70",
                "bank_details": {
                    "bankgiro": "666-2365",
                    "postgiro": "431030-6"
                },
                "activity": "Tillverkar o säljer sittmöbler, sängar, industridetaljer i formpressad kallskum. Madrasser, plymåer i polyeter",
                "employees": 50,
                "annual_turnover": 5000000,
                "capital": 200000,
                "key_personnel": [
                    {
                        "name": "Henry Persson",
                        "position": "Verkst dir"
                    }
                ],
                "establishment_year": 1952
            },
            {
                "company_name": "SKÅNSKA LANTMÄNNENS CENTRALFURENING U P A",
                "pnr": "201 24",
                "address": "Malmö 1, Box 485",
                "phone_number": "040-738 20",
                "bank_details": {
                    "bankgiro": "34-8354",
                    "postgiro": "14174"
                },
                "activity": "Fodermedel, gödselmedel, spannmål, utsäde, potatis, eldningsoljor, driv- o smörjmedel, byggnadsmaterial, trä- o järnvaror, kemiska preparat m m",
                "employees": 940,
                "annual_turnover": 513308000,
                "key_personnel": [
                    {
                        "name": "Birger Håstadius",
                        "position": "Verkst dir"
                    }
                ],
                "establishment_year": 1904
            },
            {
                "company_name": "SKÅNSKA MAKADAM. FABRIKEN, AB",
                "pnr": "265 01",
                "address": "Åstorp 1, Box 104",
                "phone_number": "042-509 75",
                "bank_details": {
                    "bankgiro": "67-1305",
                    "postgiro": "84050"
                },
                "activity": "Tillverkar makadam o betong",
                "employees": 93,
                "annual_turnover": 11000000,
                "capital": 1800000,
                "key_personnel": [
                    {
                        "name": "Börje Berendahl",
                        "position": "Verkst dir"
                    }
                ],
                "establishment_year": 1903
            },
            {
                "company_name": "SKÅNSKA PAPPERS-CENTRALEN AB",
                "pnr": "212 28",
                "address": "Malmö, Sallerupsv 90",
                "phone_number": "040-93 54 30",
                "bank_details": {
                    "bankgiro": "641-3439",
                    "postgiro": "39247-2"
                },
                "activity": "Allt i pappersvaror o emballageartiklar. Egna tillverkningar",
                "employees": 39,
                "annual_turnover": 3200000,
                "capital": 30000,
                "key_personnel": [
                    {
                        "name": "Iwe Andersson",
                        "position": "Verkst dir"
                    }
                ],
                "establishment_year": 1935
            },
            {
                "company_name": "SKÅNSKA SKRUV. FABRIKEN, AB",
                "pnr": "272 00",
                "address": "Simrishamn, Fabriken 1",
                "phone_number": "0414-10208",
                "bank_details": {
                    "bankgiro": "662-2668",
                    "postgiro": "284000-0"
                },
                "activity": "Automatsvarvade artiklar upp till 60 mm diameter",
                "employees": 21,
                "annual_turnover": 800000,
                "capital": 50000,
                "key_personnel": [
                    {
                        "name": "Birger Johnsson",
                        "position": "Verkst dir"
                    }
                ],
                "establishment_year": 1951
            },
            {
                "company_name": "JONSSON & HALLSJU AB",
                "pnr": "782 00",
                "address": "Malung",
                "phone_number": "0280-100 50, 105 50",
                "bank_details": {
                    "bankgiro": "79-7035",
                    "postgiro": "30182"
                },
                "activity": "Tillverkar o säljer skinnkläder i parti",
                "employees": 30,
                "annual_turnover": 1200000,
                "capital": 75000,
                "key_personnel": [
                    {
                        "name": "Ingvar Hallsjö",
                        "position": "Verkst dir"
                    }
                ],
                "establishment_year": 1915
            },
            {
                "company_name": "JOHNSON HILL AB",
                "pnr": "700 02",
                "address": "Örebro 2, Bettorpsg 8, Box 2103",
                "phone_number": "019-14 01 50",
                "activity": "Offsettryckeri",
                "employees": 80,
                "capital": 1750000,
                "key_personnel": [
                    {
                        "name": "Sune Johansson",
                        "position": "Verkst dir"
                    }
                ],
                "establishment_year": 1900
            },
            {
                "company_name": "HALLSTABERGS MEK VERKSTAD",
                "pnr": "734 00",
                "address": "Hallstahammar, Videv 6 C, Småindustriområde",
                "phone_number": "0220-134 32, 0220-110 03",
                "activity": "Grovplåtslageri samt svetsningsverkstad",
                "employees": 35,
                "annual_turnover": 2600000,
                "capital": 10000,
                "key_personnel": [
                    {
                        "name": "Thure Koorp",
                        "position": "Chef"
                    },
                    {
                        "name": "Karl Hjärpe",
                        "position": "Chef"
                    }
                ],
                "establishment_year": 1963
            },
            {
                "company_name": "HALLSTABERGS MEK VERKSTAD",
                "pnr": "734 00",
                "address": "Hallstahammar, Videv 6 C",
                "phone_number": "0220-134 32, 0220-110 03",
                "activity": "Grovplåtslageri samt svetsningsverkstad",
                "employees": 35,
                "annual_turnover": 2600000,
                "capital": 10000,
                "key_personnel": [
                    {
                        "name": "Thure Koorp",
                        "position": "Chef"
                    },
                    {
                        "name": "Karl Hjärpe",
                        "position": "Chef"
                    }
                ],
                "establishment_year": 1963
            },
            {
                "company_name": "HALLSTABERGS MEK VERKSTAD",
                "pnr": "734 00",
                "address": "Hallstahammar, Videv 6 C",
                "phone_number": "0220-134 32, 0220-110 03",
                "activity": "Grovplåtslageri samt svetsningsverkstad",
                "employees": 35,
                "annual_turnover": 2600000,
                "capital": 10000,
                "key_personnel": [
                    {
                        "name": "Thure Koorp",
                        "position": "Chef"
                    },
                    {
                        "name": "Karl Hjärpe",
                        "position": "Chef"
                    }
                ],
                "establishment_year": 1963
            },
            {
                "company_name": "HALLSTABERGS MEK VERKSTAD",
                "pnr": "734 00",
                "address": "Hallstahammar, Videv 6 C",
                "phone_number": "0220-134 32, 0220-110 03",
                "activity": "Grovplåtslageri samt svetsningsverkstad",
                "employees": 35,
                "annual_turnover": 2600000,
                "capital": 10000,
                "key_personnel": [
                    {
                        "name": "Thure Koorp",
                        "position": "Chef"
                    },
                    {
                        "name": "Karl Hjärpe",
                        "position": "Chef"
                    }
                ],
                "establishment_year": 1963
            }
        ]
    }
}