{
    "original": "BELLINGA STENINDUSTRI, AB\n\nPnr 270 12\n\nRydsgård. Tel 0411-47168, 47167.\nBankgiro 670-2138. Postgiro\n145499-0\n\nVerksamhet: Makadamtillverkning\nm m samt försäljning av grus\nFilialer: Degeberga. Stenkrossen\nDegeberga. Tel 0450-513 83\nGnnestad. Dnnestads\nMakadamfabrik. Tel 044-702 14\nAntal anställda: 35\nÅrsomsättning: 4 500 000\nAktiekapital: 770 000\nVerkst dir: Ing Hans Hansson\nEtableringsår: 1937.\n\nTRÄ &amp; METALL\n\nPnr 68101\n\nKristinehamn 1, Box 181.\nBro-ängsg 10. Tel 0550-125 69.\nBankgiro 11-0057. Postgiro 328528-5\nVerksamhet: Tillverkar \"Snabb\"\nlyftverktyg för plåt, balk o räls\nVarunamn: Snabb\nChef: S A Woolke\nEtableringsår: 1946.\n\nBERNERS AB\n\nPnr 50107\n\nBorås 1, Göteborgsv. Box 420.\nTel 033-111240. 1115 79.\nBankgiro 83-9124. Postgiro 20601\nVerksamhet: Tillverkar bomull- o\nrayonfoder, domestiker\nAntal anställda: 33\nÅrsomsättning: 6 200 000\nAktiekapital: 1201200\nVerkst dir: Berit Berner\nEtableringsår: 1916.\n\nMYRENS MEK VERKSTADS AB\n\nPnr 452 00\n\nStrömstad, Box 45. Tel 0526-10047,\n102 75. Bankgiro 551-3569. Postr\ngiro 173320-3\n\nVerksamhet: Fullständig\nvarvsrörelse\n\nAntal anstäUda: 9\nAktiekapital: 35 000\nVerkst dir: Allan Ljungqvist\nEtableringsår: 1915.\n\nLEKSANDS VÄVERI AB\n\nPnr 793 00\n\nLeksand, Box 17. Norsg. Tel\n0247-112 69, 117 69. Bankgiro\n46-7214. Postgiro 36 2794\nVerksamhet: Tillverkar dukar,\nduktyg o servetter av bomull o linne\nAntal anställda: 15\nÅrsomsättning: 2 000 000\nAktiekapital: 100 000\nVerkst dir: Ing Rune Håkansson\nEtableringsår: 1947.\n\nDALA-GRUS, AB\n\nPnr 580 03\n\nLinköping 3, Box 3068. Tel\n013-13 02 20\n\nVerksamhet: Grusverksrörelse\nAntal anställda: 8\nÅrsomsättning: 3 000 000\nAktiekapital: 100000\nVerkst dir: Sture Ernskog.\n\nDALA-JÄRNA SÅGVERKS AB\n\nPnr 780 51\n\nDala Järna, Fack 19. Tel 0281-\n\n200 98, 201 37. Bankgiro 46-5820.\nPostgiro 74682\n\nVerksamhet: Tillverkar sågade o\nhyvlade trävaror\nAntal anställda: 25\nÅrsomsättning: 1800 000\n.Aktiekapital: 177 000\nVerkst dir: A Söder\nEtableringsår: 1918.\n\nALBIHNS PATENTBYRÄ AB, H\n\nPnr 103 81\n\nStockholm 7, Kungsg 6. Box 7045.\n■ Tel 08-2293 30. Bankgiro 170-1598.\nPostgiro 3524-6. Tga Albihnpatent\nVerksamhet: Hjälper genom\ntekniska experter enskilda o foretag\natt söka patentskydd, mönster- o\nvarumärkesregistreringar i Sverige\no utlandet, licensavtal\nAntal anställda: 85\nÅrsomsättning: 13000000\nAktiekapital: 200 000\nStyrelse: Adv Lars Samzelius\n(ordf), civillng Göte Ernerot, fil\nlic fru Marianne Fridberg, dir\nPer-Urban Hjärne, ing Kuno\nChristens-son\n\nVerkst dir: Per-Urban Hjärne\nEtableringsår: 1891.\n\nFORSBLAD AB, ANDERS\n\nPnr 40231\n\nGöteborg 7, Box 7013.\nNordostpassagen 29. Tel 031-1244 50.\nBankgiro 848-3117. Postgiro\n45156-7. Tga Glimt. Telex 20794\nVerksamhet: In- o utländska\nagen-turer i slakteri varor, kryddor, fröer,\nkonserver, div kolonialvaror\nAktiekapital: 5 000\nVerkst din Lars Axelsson\nEtableringsår: 1938\nOmbildat till aktiebolag 1966.\n\nFORSBRO YLLEFABRIK, AB\n\nPnr 82010\n\nArbrå. Tel 0278-400 32. Postgiro\n173418\n\nVerksamhet: Tillverkar sängfiltar\nav ylle resp bomull för statliga\ninrättningar o enskilt bruk\nAntal anstäUda: 50\nStyrelse: Dir Gunnar Rydahl (ordf),\nherr Rune Rydahl\nVerkst dir: Gunnar Rydahl\nEtableringsår: 1879.\n\nG. G.-ARECOS AB\n\nPnr 117 43\n\nStockholm, Ingenjörsv 2. Tel\n08-69 09 20. Bankgiro 56-9535.\nPostgiro 53216\n\nVerksamhet: Grossistfirma i\nvärme-, vatten- o sanitetsbranschen\nAntal anställda: 78\nÅrsomsättning: 40 000 000\nAktiekapital: 830 000\nStyrelse: Dir Gunnar Ekman, dir\nHarry Hjalmarson, dir John Axel\nSallborg, dir Bertil Tronët, fil lic\nMauritz Bonow\nVerkst dir: Ake Wissén\nKamrer: Nils Karlsson\nEtableringsår: 1923\nDotterbolag till Kooperativa\nFörbundet, Stockholm.\n\nG G C GJUTERI AB\n\nPnr 63102\n\nEskilstuna, Najaden 1. Tel\n016-1319 53, 13 96 04. Bankgiro\n828-1339. Postgiro 85122-0\nVerksamhet: Tillverkar kokill- o\nsandgjutgods, vattenpass, hyvlar,\nplattskärningsmaskiner samt\nchar-kuteriformar\nAktiekapital: 120000\nVerkst dir: M Larsson\nEtableringsår: 1921\nOmbildat till aktiebolag 1955.\n\nGH-PLAST\n\nPnr 760 45\n\nGrisslehamn, Postl 479. Tel\n0175-303 63, 302 62. Postgiro 693985\n\nVerksamhet Formsprutning av\nplastartiklar bl a\nförpackningsartiklar, klädnypor, kapsyler o\npappersplugg\n\nÅrsomsättning: 200 000\nChef: Heino Tamp\nEtableringsår: 1967.\n\nELLO-LIVS, AB\n\nPnr 360 30\n\nLammhult, Box 86. Tel 0472-607 10\nVerksamhet: Slakterirörelse.\nTillverkar charkuterivaror\nAntal anställda: 40\nÅrsomsättning: 12 000 000\nAktiekapital: 100000\nVerkst dir. Lars-Olof Andersson\nEtableringsår: 1947.",
    "structured": {
        "1": {
            "company_name": "BELLINGA STENINDUSTRI, AB",
            "pnr": "270 12",
            "address": "Rydsgård",
            "phone_number": "0411-47168, 47167",
            "bank_details": {
                "bankgiro": "670-2138",
                "postgiro": "145499-0"
            },
            "activity": "Makadamtillverkning m m samt försäljning av grus",
            "employees": 35,
            "annual_turnover": 4500000,
            "capital": 770000,
            "key_personnel": [
                {
                    "name": "Ing Hans Hansson",
                    "position": "Verkst dir"
                }
            ],
            "establishment_year": 1937
        },
        "2": {
            "company_name": "TRÄ & METALL",
            "pnr": "68101",
            "address": "Kristinehamn 1, Box 181, Bro-ängsg 10",
            "phone_number": "0550-125 69",
            "bank_details": {
                "bankgiro": "11-0057",
                "postgiro": "328528-5"
            },
            "activity": "Tillverkar 'Snabb' lyftverktyg för plåt, balk o räls",
            "key_personnel": [
                {
                    "name": "S A Woolke",
                    "position": "Chef"
                }
            ],
            "establishment_year": 1946
        },
        "3": {
            "company_name": "BERNERS AB",
            "pnr": "50107",
            "address": "Borås 1, Göteborgsv. Box 420",
            "phone_number": "033-111240, 1115 79",
            "bank_details": {
                "bankgiro": "83-9124",
                "postgiro": "20601"
            },
            "activity": "Tillverkar bomull- o rayonfoder, domestiker",
            "employees": 33,
            "annual_turnover": 6200000,
            "capital": 1201200,
            "key_personnel": [
                {
                    "name": "Berit Berner",
                    "position": "Verkst dir"
                }
            ],
            "establishment_year": 1916
        },
        "4": {
            "company_name": "MYRENS MEK VERKSTADS AB",
            "pnr": "452 00",
            "address": "Strömstad, Box 45",
            "phone_number": "0526-10047, 102 75",
            "bank_details": {
                "bankgiro": "551-3569",
                "postgiro": "173320-3"
            },
            "activity": "Fullständig varvsrörelse",
            "employees": 9,
            "capital": 35000,
            "key_personnel": [
                {
                    "name": "Allan Ljungqvist",
                    "position": "Verkst dir"
                }
            ],
            "establishment_year": 1915
        },
        "5": {
            "company_name": "LEKSANDS VÄVERI AB",
            "pnr": "793 00",
            "address": "Leksand, Box 17, Norsg",
            "phone_number": "0247-112 69, 117 69",
            "bank_details": {
                "bankgiro": "46-7214",
                "postgiro": "36 2794"
            },
            "activity": "Tillverkar dukar, duktyg o servetter av bomull o linne",
            "employees": 15,
            "annual_turnover": 2000000,
            "capital": 100000,
            "key_personnel": [
                {
                    "name": "Ing Rune Håkansson",
                    "position": "Verkst dir"
                }
            ],
            "establishment_year": 1947
        }
    }
}