{
    "original": "ATLANTTRAFIK, AB\n\nPnr 40317\n\nGöteborg 2, Box 2522.\nPackhusplatsen 6. Tel 17 20 20, riks\n031-17 5100. Bankgiro 50-0866.\nPostgiro 241600. Tga Oceanship.\nTelex 2239 ESOEL S\nVerksamhet: Rederirörelse\nAktiekapital: 50 000\nVerkst dir: Thomas Belfrage\nEtableringsår: 1946.\n\nNORDENSON AB, H\n\nPnr 113 58\n\nStockholm, DÖbelnsg 16 B. Tel\n08-15 98 50. Tga Nordswed.\nTelex 10386\n\nVerksamhet: Importagent i husgeråd\no handverktyg\nAntal anställda: 4\nÅrsomsättning: 2 000 000\nAktiekapital: 200 000\nVerkst dir: H Nordenson\nEtableringsår: 1933.\n\nARMÉ-, MARIN- 0 FLYGFILM,\nFÖRENINGEN\n\nPnr 114 57\n\nStockholm, Riddarg 23 B. Tel\n08-67 09 40. Bankgiro 732-0054.\nPostgiro 151047-8. Tga Militärfilm\nVerksamhet: Filmdistribution.\nUndervisnings- o upplysningsfilm.\nBildband. Utbildar personal för\nhandhavande av projektorer\nAntal anställda: 12\nVerkst ledamot: Kapten Bo\nSylvan-der\n\nEtableringsår: 1920.\n\nFOSFOROS, AB\n\nPnr 141 22\n\nHuddinge 1, Dalhemsv 45.Box 1059.\nTel 08-757 27 70. Bankgiro 74-6128.\nPostgiro 195270. Tga Fosforos\nVerksamhet: Säljer byggnadsvaror\no industriförnödenheter\nAntal anställda: 9\nAktiekapital: 25 000\nStyrelse: Dir Hans Kraijn\nVerkst dir: Dir Hans Kraijn\nEtableringsår: 1943\nDotterbolag: Fosforos Magasins AB,\nHuddinge, AB Gullmarshus,\nHuddinge.\n\nFORSVIKS SKOGAR AB\n\nPnr 540 42\n\nForsvik. Tel 0505-410 00. Bankgiro\n84-8038. Postgiro 28200. Tga\nForsskogar. Telex 5974 FSKOGAB S\nVerksamhet: Tillverkar sågade o\nhyvlade trävaror, lastpallar o\nträemballage. Utför träimpregnering\nAntal anstäUda: 220\nDisp: Thorvald Svensson\nEtableringsår: 1936.\n\nBAYER KEMI AB\n\nPnr 400 15\n\nGöteborg 53, Box 53193.\nKungs-portsavenyn 31-35. Tel 031-20 0 9 80.\nTga Bayerkemi. Telex 2383\nVerksamhet: Repr för\nFarbenfabri-kenBayer AG, Leverkusen, i\nanilinfärger, syntetfibrer o kemikalier.\nAvdelningskontor: 502 30 Borås,\nPostg 5. Tel 033-124370, 124371\n20311 Malmö, Stora Nyg 31. Tel\n040-708 40. Telex 3173\n60225 Norrköping, Repslagareg 15.\nTel 011-100250\n\n10243 Stockholm, Nybrog 39. Tel\n08-23 89 20. Telex 19029\nAntal anställda: 80\nAktiekapital: 500 000\nVeikst dir: Börje A Thulin\nEtableringsår: 1950.\n\nSON\n\nVerksamhet: Tillverkning o\nförsäljning av hemelektronik o\nindustrielektronik, på det senare området\nmed speciell inriktning på\nkommunikationssystem\n\nAntal anställda: 125 (inom\nSonab-gruppen)\n\nÅrsomsättning: 10 000 000\nStyrelse: Dir Gunnar Wannberger\n(ordf), övering Gösta Knall, tekn\ndir Carl-Gösta Asdal, generaldir\nErie Malmberg, dir Hans Wagner\nVerkst dir: Hans Wagner (Stockholm)\nProduktutvecklingschef: Civiling\nNils Mårtensson\nEtableringsår: 1966.\n\nTRÄFRAKTKONTORET\n\nPnr 411 21\n\nGöteborg, Skeppsbron 4. Tel\n031-119001, 1190 02. Bankgiro\n511-6017. Postgiro 40056-4. Tga\nWood-chart. Telex 20615\nVerksamhet: Skeppsmäkleri,\nbe-fraktningsrörelse o spedition.\nAgentur\n\nAntal anställda: 5\n\nÄgare o chef: Skeppsmäkl Sture\n\nGustafson\n\nEtableringsår: 1928.\n\nBODENS LJUS &amp; KRAFT AB\n\nPnr 961 00\n\nBoden, Drottningg 6. Tel\n0921-16000. Bankgiro 753-3375.\nPostgiro 65887-2\n\nVerksamhet: Elektr installationer.\nSäljer hushållsmaskiner, radio o\nTV samt övriga elektr artiklar\nAntal anställda: 50\nÅrsomsättning: 5 000 000\nAktiekapital: 100 000\nVerkst dir: Ing Yngve Wennskog\nEtableringsår: 1942.\n\nNORDISKA FLUIDIK AB\n\nPnr 13102\n\nNacka 2, Box 261. Planiav 13. Tel\n08-716 53 04. 716 53 05. Bankgiro\n101-2889. Postgiro 688290-6. Tga\nFluidik. Telex 10839 ESPEVE S\nVerksamhet: Säljer hydrauliska\nkomponenter o system\nAktiekapital: 6 000\nVerkst dir: Harry Aredal\nEtableringsår: 1966.\n\nSCHARIN &amp; CO KB\n\nPnr 90104\n\nUmeå 1, V Kyrkog 1. Box 286. Tel\n090-13 23 40. Bankgiro 75-9950.\nPostgiro 62206. Tga Scharinwood\nVeiksamhet: TYävarugrossist.\nFörsäljning o export av sågade o\nhyvlade trävaror\nAntal anställda: 5\nÅrsomsättning: 8 000 000\nChef: Konsul Jan Unander-Scharin\nEtableringsår 1951.",
    "structured": {
        "1": {
            "company_name": "ATLANTTRAFIK, AB",
            "address": "Göteborg 2, Box 2522. Packhusplatsen 6",
            "phone_number": "031-17 5100",
            "bank_details": {
                "bankgiro": "50-0866",
                "postgiro": "241600"
            },
            "activity": "Rederirörelse",
            "capital": 50000,
            "key_personnel": [
                {
                    "name": "Thomas Belfrage",
                    "position": "Verkst dir"
                }
            ],
            "establishment_year": 1946
        },
        "2": {
            "company_name": "NORDENSON AB, H",
            "address": "Stockholm, DÖbelnsg 16 B",
            "phone_number": "08-15 98 50",
            "activity": "Importagent i husgeråd o handverktyg",
            "employees": 4,
            "annual_turnover": 2000000,
            "capital": 200000,
            "key_personnel": [
                {
                    "name": "H Nordenson",
                    "position": "Verkst dir"
                }
            ],
            "establishment_year": 1933
        },
        "3": {
            "company_name": "FOSFOROS, AB",
            "address": "Huddinge 1, Dalhemsv 45.Box 1059",
            "phone_number": "08-757 27 70",
            "bank_details": {
                "bankgiro": "74-6128",
                "postgiro": "195270"
            },
            "activity": "Säljer byggnadsvaror o industriförnödenheter",
            "employees": 9,
            "capital": 25000,
            "key_personnel": [
                {
                    "name": "Hans Kraijn",
                    "position": "Verkst dir"
                }
            ],
            "establishment_year": 1943
        },
        "4": {
            "company_name": "FORSVIKS SKOGAR AB",
            "address": "Forsvik",
            "phone_number": "0505-410 00",
            "bank_details": {
                "bankgiro": "84-8038",
                "postgiro": "28200"
            },
            "activity": "Tillverkar sågade o hyvlade trävaror, lastpallar o träemballage. Utför träimpregnering",
            "employees": 220,
            "key_personnel": [
                {
                    "name": "Thorvald Svensson",
                    "position": "Disp"
                }
            ],
            "establishment_year": 1936
        },
        "5": {
            "company_name": "BAYER KEMI AB",
            "address": "Göteborg 53, Box 53193. Kungs-portsavenyn 31-35",
            "phone_number": "031-20 0 9 80",
            "bank_details": {
                "bankgiro": "Not available"
            },
            "activity": "Repr för Farbenfabri-kenBayer AG, Leverkusen, i anilinfärger, syntetfibrer o kemikalier",
            "employees": 80,
            "capital": 500000,
            "key_personnel": [
                {
                    "name": "Börje A Thulin",
                    "position": "Veikst dir"
                }
            ],
            "establishment_year": 1950
        },
        "6": {
            "company_name": "SON",
            "activity": "Tillverkning o försäljning av hemelektronik o industrielektronik, på det senare området med speciell inriktning på kommunikationssystem",
            "employees": 125,
            "annual_turnover": 10000000,
            "key_personnel": [
                {
                    "name": "Gunnar Wannberger",
                    "position": "ordf"
                },
                {
                    "name": "Gösta Knall",
                    "position": "övering"
                },
                {
                    "name": "Carl-Gösta Asdal",
                    "position": "tekn dir"
                },
                {
                    "name": "Erie Malmberg",
                    "position": "generaldir"
                }
            ],
            "establishment_year": 1966
        },
        "7": {
            "company_name": "TRÄFRAKTKONTORET",
            "address": "Göteborg, Skeppsbron 4",
            "phone_number": "031-119001, 1190 02",
            "bank_details": {
                "bankgiro": "511-6017",
                "postgiro": "40056-4"
            },
            "activity": "Skeppsmäkleri, be-fraktningsrörelse o spedition. Agentur",
            "employees": 5,
            "key_personnel": [
                {
                    "name": "Skeppsmäkl Sture Gustafson",
                    "position": "Ägare o chef"
                }
            ],
            "establishment_year": 1928
        },
        "8": {
            "company_name": "BODENS LJUS & KRAFT AB",
            "address": "Boden, Drottningg 6",
            "phone_number": "0921-16000",
            "bank_details": {
                "bankgiro": "753-3375"
            },
            "activity": "Elektr installationer. Säljer hushållsmaskiner, radio o TV samt övriga elektr artiklar",
            "employees": 50,
            "annual_turnover": 5000000,
            "capital": 100000,
            "key_personnel": [
                {
                    "name": "Ing Yngve Wennskog",
                    "position": "Verkst dir"
                }
            ],
            "establishment_year": 1942
        },
        "9": {
            "company_name": "NORDISKA FLUIDIK AB",
            "address": "Nacka 2, Box 261. Planiav 13",
            "phone_number": "08-716 53 04, 716 53 05",
            "bank_details": {
                "bankgiro": "101-2889",
                "postgiro": "688290-6"
            },
            "activity": "Säljer hydrauliska komponenter o system",
            "capital": 6000,
            "key_personnel": [
                {
                    "name": "Harry Aredal",
                    "position": "Verkst dir"
                }
            ],
            "establishment_year": 1966
        },
        "10": {
            "company_name": "SCHARIN & CO KB",
            "address": "Umeå 1, V Kyrkog 1. Box 286",
            "phone_number": "090-13 23 40",
            "bank_details": {
                "bankgiro": "75-9950",
                "postgiro": "62206"
            },
            "activity": "TYävarugrossist. Försäljning o export av sågade o hyvlade trävaror",
            "employees": 5,
            "annual_turnover": 8000000,
            "key_personnel": [
                {
                    "name": "Konsul Jan Unander-Scharin",
                    "position": "Chef"
                }
            ],
            "establishment_year": 1951
        }
    }
}