{
    "original": "AUTOMATIC AB\n\nPnr 11122\n\nStockholm, Kungsg 74. Tel\n08-23 27 30. Postgiro 51569-2.\nTga Betterway\n\nVerksamhet: Produktionsbolag för\nmodern butiksreklam,\nbutiksinredningar, present- o fritidsartiklar,\ngjuten skylt av aluminium.\nLegotillverkningar i rör, tråd, plåt, trä o plast.\nGjutning i aluminium. 2 500 m2\nverkstad färdigställd 1965-70\nFabrik: 330 30 Gnosjö, Västerg 14.\nTel 0370-914 05\n\nAvdelningskontor: 41118 Göteborg,\nKaserntorget 6. Tel 031-13 36 63\n21145 Malmö, Davidshallsg 42.\nTel 040-37970\nAntal anställda: 50\nAktiekapital: 150000\nDir: Arne Sönnergaard\nEtableringsår: 1921.\n\nAUTOMATIN\n\nAUTOMAT FIRMA B-E\nEK-STRÖM KOMMANDITBOLAG\n\nPnr 11459\n\nStockholm, Karlav 70. Tel\n08-67 66 81. Bankgiro 56-7504.\nPostgiro 458270\n\nVerksamhet: Säljer o uppställer\nkaffe-, läskedrycks- o varuautomater\nÄgare o chefer: Bengt Ekström,\nfru Mary-Anne Ekström\nEtableringsår: 1951.\n\nAUTOMATINDUSTRIER\nI GÄVLE AB\n\nPnr 80012\n\nGävle 12, Fack. Tel 026-67050.\nBankgiro 23-7155. Postgiro 94134\nVerksamhet:\nAutomatsvarvnings-arbeten\n\nAntal anställda: 55\nÅrsomsättning: 4500 000\nAktiekapital: 250 000\nStyrelse: Dir Erie Boberg (ordf),\nfabr Conrad Andersson, fabr Osten\nAndersson, ing Gunnar Dahlin\nVerkst dir: Erie Boberg\nEtableringsår: 1955\nOmbildat till aktiebolag 1960.\n\nAUTOMATIONSKONSULT, AB\n\nPnr 19107\n\nSollentuna 7, Box 7060. Tel\n08-754 31 00. Bankgiro 655-6146.\nPostgiro 58290-8.\n\nTelex 10936 SCANTEC S\nVerksamhet: Konsultföretag inom\nautomationssektorn företrädesvis\nför massa- o pappersindustrin,\nkemisk industri, processindustri o\nmiljövård. Företaget projekterar\nkonventionell automatik o\nreglerut-rustningar liksom digital\nmätvärdesinsamling med eller utan\ndatorstyrning. Verksamheten omfattar delar\nav projekt eller komplett\n’nyckelfärdiga’ automatikanläggningar\ninkl igångkörning\nAntal anställda: 4\nAktiekapital: 5 000\nStyrelse: Dir Bo Westerberg, dir\nIvar Bull-Simonsen, dir Magnus\nLettius, dir Olle Grundh (suppl),\ndir Sven Wejdling (suppl)\nVerkst dir: Magnus Lettius\nEtableringsår: 1969\nIngår i Fannyudde-koncernen.\n\nAUTOMATKOMPANIET AB\n\nPnr 12612\n\nStockholm 42, Box 42016. Elektrav\n49. Tel 08-19 04 10\nVerksamhet: Importerar o säljer\nautomater för kaffe, läskedrycker\nAntal anställda: 5\nÅrsomsättning: 1000 000\nAktiekapital: 5 000\nStyrelseordf: Dir Curt H Andréasson\nVerkst dir: Curt H Andréasson\nEtableringsår: 1965.\n\nWÄRNÄS ARMATUR, AB\n\nPnr 33100\n\nVärnamo, Malmöv 2. Tel\n0370-104 59, 114 59\n\nVerksamhet: Tillverkar\nbelysningsarmatur\n\nAntal anställda: 25\nÅrsomsättning: 800 000\nAktiekapital: 20000\nVerkst din Pabr Axel Wärnå\nEtableringsår. 1932.\n\nFERGAS AB\n\nPnr 582 21\n\nLinköping, Oskarsg 10. Tel\n013-14 6175. Bankgiro 120-0385.\nPostgiro 338632-3\n\nVerksamhet: Tillverkar fläkthjul,\nverktyg samt utför\npressningsarbeten upp till 250 ton\nAntal anställda: 50\nAktiekapital: 30 000\nÅrsomsättning: 4 200 000\nVerkst dir: Lennart Wallman\nEtableringsår: 1949.\n\nFERGIN AB, INGENIORS.\nFIRMA STIG\n\nPnr 591 03\n\nMotala 3, Box 305. Drakv 3. Tel\n0141-500 25. Bankgiro 700-1803.\nPostgiro 379311-4. Tgalngfergin\nVerksamhet: Tillverkar kapslad\nlysrörsarmatur i plast, varor o skyltar\ni akrylplast\n\nVarunamn: Flexiplast, Norka\nAntal anställda: 14\nAktiekapital: 100 000\nVerkst dir: Ing Stig Fergin.\n\nFERIEPRODUKTER AB\n\nPnr 283 00\n\nOsby. V Järnvägsg. Tel\n0479-119 00, 119 30. Bankgiro 28-1714.\nPostgiro 98485. Telex 4684\nVerksamhet: Tillverkar\nträdgårdsmöbler o parasoller\nChef: Disp Nils Erik Lindroth.\n\nFERLIN &amp; CO AB, OSCAR\n\nPnr 111 56\n\nStockholm, Regeringsg 56. Tel\n08-1147 00,10 03 73. Bankgiro\n72-4750. Postgiro 2373. Tga Ferlins.\nTelex 17028\n\nVerksamhet: Assuransfirma\n\nAntal anställda: 6\n\nAktiekapital: 5 000\n\nStyrelse: Ing Pär J Wiksten (ordf),\n\ndir Wald Odenrick\n\nVerkst dir: Ing Pär J Wiksten\n\nEtableringsår: 1876\n\nOmbildat till aktiebolag 1962.\n\nFERM &amp; OLSSON AB\n\nPnr 453 00\n\nLysekil, Box 3. Gullmarskajen. Tel\n0523-100 07. 103 72. Bankgiro\n548-3540. Postgiro 333166-7. Tga\nFerm-son. Telex 42080 FERM S\nVerksamhet: Befraktning, klarering,\nspedition o bunkeroljor\nAntal anställda: 11\nVerkst dir: Hedly Ferm\nEtableringsår: 1924.\n\nUNA\n\n44 70 34. Bankgiro 72-8419.\nPost-giro 2502. Tga Unagum\nVerksamhet: Tillverkar\nindustriportar o utför smidesarbeten\nVarunamn: Overhead Door\nAktiekapital: 100 000\nVerkst dir: Stig Claesson\nEtableringsår: 1931.\n\nUNAX BOLAGET,\nS BENGTSON &amp; CO\n\nPnr 217 58\n\nMalmö, Tessins väg 2. Tel\n040-600 27. Bankgiro 264-2312.\nPostgiro 246930-2\n\nVerksamhet: Agenturer i\nkontorsmaskinbranschen\n\nÄgare o chef: Disp Bertil Bengtson\nEtableringsår: 1949.\n\nUNDERSÅKERS ELEKTRISKA\nKRAFT AB\n\nPnr 830 05\n\nJärpen, Aüantv 5. Tel 0647-103 78.\nPostgiro 130813-9\nVerksamhet: Eldistribution\nAktiekapital: 258 800\nVerkst dir: Gustav Nilsson\nFirmatecknare: Gustav Nilsson,\nOlov Sundström\nEtableringsår: 1922.\n\nRES\n\nREM A ELECTRONIC AB\n\nPnr 722 33\n\nVästerås, Bygelv 20. Tel\n021-60610. Bankgiro 982-4 665.\nPostgiro 473920-7\n\nVerksamhet: Tillverkar elektroniska\nmät- o styrutrustningar, fotocelldon\no transformatorer\nAntal anstäUda: 40\nAktiekapital: 10000\nVerkst dir. Ing Carl Petterson\nEtableringsår 1954.\n\nELEKTRONLUNO AB\n\nPnr 20110\n\nMalmö 1, Borrg 4. Fack. Tel\n040-93 48 20. Bankgiro 36-0990. Postgiro\n530220. Tga Elektronlund.\nTelex 3105 LUNDBOL S\nVerksamhet: Tillverkning av\nin-dustrielektronisk utrustning för\nsortering, räkning, mätning mm. Import\no försäljning av Imhof\ninstrumentlådor, rackar samt byggsystem.\nCer-berus glimlampor o kallkatodrör\nVarunamn: Cerberus, Imhof\nAntal anställda: 45\nÅrsomsättning: 3 500 000\nAktiekapital: 500 000\nVerkst dir: Ingmar Norlindh\nEtableringsår: 1958\nOmbildat till aktiebolag 1967.\n\nELEKTRONOM, AB\n\nPnr 17104\n\nSolna 4, Box 457. Ankdammsg 11.\nTel 08-82 03 30. Bankgiro 13-6233.\nPostgiro 555151. Tga Elektronomi.\nTelex 1561 ELECTRA S\nVerksamhet: Agenturer i elektr\nbranschen omfattande: kablar,\nlin-jeklämmor, strålkastare, hög- o\nlågspänningsmateriel,\nströmavtaga-re, telemateriel, normal- o\nkvicksilverlampor, kabelrännor\nFilial: 41110 Göteborg, O Hamng\n17. Tel 031-17 65 60\nVarunamn: Arcus, Beseg,\nDries-cher, Hupperich, Krone, Radium,\nKabelwerk Rheydt, Schmidt-Strahl,\nSchlemmer, Tehalit, Benjamin\nElectric, Simplex Circulume, Priess\nAntal anställda: 25\nÅrsomsättning: 8 000 000\nAktiekapital: 100000\nVerkst dir: Edward Albert Bolie\nFörsäljn-chef för hög- o\nlågspänningsmateriel: Ing Lars Björck\nFörsäljn-chef för belysning: Ing\nGunnar Timmerman\nTehalitsystem: Herr Edgar Sjöström\nDistr-chef för Västra Sverige: Herr\nEinar Lagerqvist\nEtableringsår: 1957.\n\nNILSSONS VERKSTADS- &amp;\nFABRIKS AB, A\n\nPnr 113 41\n\nStockholm, Norrbackag 23. Tel\n08-23 44 90. Bankgiro 722-4769.\nPostgiro 51752-4\n\nVerksamhet: Montering,\nreparationer o flyttningar\nAntal anstäUda: 21\nÅrsomsättning: 950 000\nAktiekapital: 100000\nVerkst dir: Henry Persson\nEtableringsår: 1899.\n\nfalken,sko ab\n\nPnr 311 00\n\nFalkenberg, Igeldammsv 7. Tel\n0346-124 70\n\nVerksamhet: Skotillverkning\nAntal anstäUda: 30\nAktiekapital: 50 000\nVerkst dir: Gottfrid Rangert\nEtableringsår: 1953.\n\nfalkenbergs belys.\nning. ab\n\nPnr 311 00\n\nFalkenberg, Schubergsv 20. Tel\n0346-14240. Bankgiro 42-5710.\nPostgiro 114516. Tga Fabe\n\nVerksamhet: Tillverkar elektr\nbelysningsarmatur\nAntal anställda: 40\nAktiekapital: 100 000\nVerkst dir: Gert Andersson\nDisp: Knut Andersson\nEtableringsår: 1951.\n\nfalkenbergs betong.\nindustri ab\n\nPnr 31100\n\nFalkenberg. Tel 0346-192 80.\nBankgiro 425-8257. Postgiro 515889-4\nVerksamhet: Tillverkar\nväggelement, trappor, plattor,\nfabriksbetong, rör o rördelar mm\nAntal anstäUda: 95\nÅrsomsättning: 11000 000\nAktiekapital: 300 000\nStyrelse: Jan Paulson, Sven-Erik\nPaulson, Gert Sevholt\nEtableringsår: 1959.\n\nfalkenbergs\nbiltransport gert olsson ab\n\nPnr 31100\n\nFalkenberg, Box 157. Valenciav 18.\nTel 0346-160 40. Bankgiro\n985-0421. Postgiro 494009-4.\nTelex 38024 OLTRANS S\nVerksamhet: Internationella\ntransporter\n\nAntal anstäUda: 45\nÅrsomsättning: 7 000 000\nAktiekapital: 40 000\nStyrelse: Akeriägare Gert Olsson,\nfru Elsie Olsson\nVerkst dir Gert Olsson\nEtableringsår: 1962.\n\nfalkenbergs bok.\ntryckeri ab\n\nPnr 31100\n\nFalkenberg, Storg 45. Box 11. Tel\n\n0346-140 75. Bankgiro 425-7754.\n\nPostgiro 164846-8\n\nVerksamhet: Tryckerirörelse med\n\nbokbinderi\n\nAntal anstäUda: 40\n\nÅrsomsättning: 3 000 000\n\nAktiekapital: 100 000\n\nVerkst dir: Hubert Carlson\n\nEtableringsår: 1946.\n\nOLSSONS BYGGMATERIAL\nAB, P\n\nPnr 25101\n\nHelsingborg 1, Fack. Angelholmsv.\nTel 042-18 03 60. Bankgiro\n652-8103. Postgiro 30398-2\nVerksamhet: Försäljning o\nentreprenadverksamhet med\nbyggnadsma&gt;-terial, trävaror, golvbeläggningar,\nplattsättningar, taktäckningar mm\nAntal anställda: 150\nÅrsomsättning: 21000 000\nAktiekapital: 200 000\nStyrelse: Dir Otto P Olsson (ordf),\nciviling Sven Weiner, dir Göran\nOlsson\n\nVerkst dir: Göran Olsson\nEtableringsår: 1905.\n\nHEFA AB\n\nPnr 440 32\n\nYtterby, Marstrandsv. Tel\n0303-92210. Bankgiro 443-6150.\nPostgiro 529050-7. Tga Hefaprod,\nGöteborg. Telex 2422\nVeiksamhet: Import från Rumänien\nav skor, textilier, bildäck m m.\nSp ort grossist\n\nElUal: Bukarest. Telex 297\nAntal anställda: 18\nÅrsomsättning: 10 000 000\n\nAktiekapital: 100 000\nVerkst dir: Folke Alfredsson\nEtableringsår: 1958.\n\nHEIJEL PLASTVARU AB,\nARTUR\n\nPnr 330 20\n\nAnders torp, Agatan 25. Tel\n0371-151 32, 155 61. Bankgiro 48-8027.\nPostgiro 71436-0\n\nVeiksamhet: Tillverkar bilplädar o\nvärmesitsar, portfölj sitsen Tropik\no El-Tropik, rattskydd, bilkuddar,\nröck-, sadel- o ansiktsskydd\nAntal anställda: 12\nAktiekapital: 40000\nChef: Lennart Heijel\nEtableringsår: 1940\nOmbildat till aktiebolag 1962.\n\nHEILBRONN GLAS- AGENTUR.\n&amp; HANDELSFIRMA, PHILIPP\n\nPnr 11160\n\nStockholm, Kammakarg 19. Tel\n08-2089 21. Postgiro 192391.\nTga Heilbronnglas\nVeiksamhet: Generalagent för S A\ndes Miroiteries de Charleroi,\nCri-stalleries du Val-St-Lambert\nVarunamn: Mirox\nChef: Else Heilbronn\nFtableringsär: 1939.\n\nHEIMDAL, AB CURT\n\nPnr 11353\n\nStockholm, Tuleg 39. Tel\n08-240 1 70. Bankgiro 33-2064.\nPostgiro 355634. Telex 10198. Tga\nCastell\n\nVerksamhet: Skriv- o ritmateriel:\nImporterar som generalagent för\nnedanstående firmor olika slag av\nkontorsartiklar/skolartiklar. Firma\nA W Faber-Castell, Stein bei\nNürnberg, A W Faber-Castell\nFüll-halterfabrik GmbH, Heidelberg,\nA W Faber-Castell Pen Co,Newark/\nN J, USA, Sanford Ink Company,\nChicago, USA, Isoklepa-Fabrik,\nStuttgart, Clemens Riefler,\nNessel-wang Daniel Peres, Solingen\nVamnamn: Faber-Castell\nAntal anstäUda: 16\nVeikst dir: Curt Heimdal\nEtableringsår: 1948.",
    "structured": {
        "1": {
            "company_name": "AUTOMATIC AB",
            "pnr": "11122",
            "address": "Stockholm, Kungsg 74",
            "phone_number": "08-23 27 30",
            "bank_details": {
                "postgiro": "51569-2"
            },
            "activity": "Produktionsbolag för modern butiksreklam, butiksinredningar, present- o fritidsartiklar, gjuten skylt av aluminium. Legotillverkningar i rör, tråd, plåt, trä o plast. Gjutning i aluminium.",
            "employees": 50,
            "capital": 150000,
            "key_personnel": [
                {
                    "name": "Arne Sönnergaard",
                    "position": "Director"
                }
            ],
            "establishment_year": 1921
        },
        "2": {
            "company_name": "AUTOMATIN"
        },
        "3": {
            "company_name": "AUTOMAT FIRMA B-E EK-STRÖM KOMMANDITBOLAG",
            "pnr": "11459",
            "address": "Stockholm, Karlav 70",
            "phone_number": "08-67 66 81",
            "bank_details": {
                "bankgiro": "56-7504",
                "postgiro": "458270"
            },
            "activity": "Säljer o uppställer kaffe-, läskedrycks- o varuautomater",
            "establishment_year": 1951
        },
        "4": {
            "company_name": "AUTOMATINDUSTRIER I GÄVLE AB",
            "pnr": "80012",
            "address": "Gävle 12, Fack",
            "phone_number": "026-67050",
            "bank_details": {
                "bankgiro": "23-7155",
                "postgiro": "94134"
            },
            "activity": "Automatsvarvnings-arbeten",
            "employees": 55,
            "annual_turnover": 4500000,
            "capital": 250000,
            "key_personnel": [
                {
                    "name": "Erie Boberg",
                    "position": "Chairman"
                },
                {
                    "name": "Conrad Andersson",
                    "position": "Factory Manager"
                },
                {
                    "name": "Osten Andersson",
                    "position": "Factory Manager"
                },
                {
                    "name": "Gunnar Dahlin",
                    "position": "Engineer"
                }
            ],
            "establishment_year": 1955
        },
        "5": {
            "company_name": "AUTOMATIONSKONSULT, AB",
            "pnr": "19107",
            "address": "Sollentuna 7, Box 7060",
            "phone_number": "08-754 31 00",
            "bank_details": {
                "bankgiro": "655-6146",
                "postgiro": "58290-8"
            },
            "activity": "Konsultföretag inom automationssektorn företrädesvis för massa- o pappersindustrin, kemisk industri, processindustri o miljövård.",
            "employees": 4,
            "capital": 5000,
            "key_personnel": [
                {
                    "name": "Bo Westerberg",
                    "position": "Director"
                },
                {
                    "name": "Ivar Bull-Simonsen",
                    "position": "Director"
                },
                {
                    "name": "Magnus Lettius",
                    "position": "Director"
                }
            ],
            "establishment_year": 1969
        },
        "6": {
            "company_name": "AUTOMATKOMPANIET AB",
            "pnr": "12612",
            "address": "Stockholm 42, Box 42016. Elektrav 49",
            "phone_number": "08-19 04 10",
            "activity": "Importerar o säljer automater för kaffe, läskedrycker",
            "employees": 5,
            "annual_turnover": 1000000,
            "capital": 5000,
            "key_personnel": [
                {
                    "name": "Curt H Andréasson",
                    "position": "Chairman"
                }
            ],
            "establishment_year": 1965
        },
        "7": {
            "company_name": "WÄRNÄS ARMATUR, AB",
            "pnr": "33100",
            "address": "Värnamo, Malmöv 2",
            "phone_number": "0370-104 59, 114 59",
            "activity": "Tillverkar belysningsarmatur",
            "employees": 25,
            "annual_turnover": 800000,
            "capital": 20000,
            "key_personnel": [
                {
                    "name": "Pabr Axel Wärnå",
                    "position": "Factory Director"
                }
            ],
            "establishment_year": 1932
        },
        "8": {
            "company_name": "FERGAS AB",
            "pnr": "582 21",
            "address": "Linköping, Oskarsg 10",
            "phone_number": "013-14 6175",
            "bank_details": {
                "bankgiro": "120-0385",
                "postgiro": "338632-3"
            },
            "activity": "Tillverkar fläkthjul, verktyg samt utför pressningsarbeten upp till 250 ton",
            "employees": 50,
            "annual_turnover": 4200000,
            "capital": 30000,
            "key_personnel": [
                {
                    "name": "Lennart Wallman",
                    "position": "Factory Director"
                }
            ],
            "establishment_year": 1949
        },
        "9": {
            "company_name": "FERGIN AB, INGENIORS. FIRMA STIG",
            "pnr": "591 03",
            "address": "Motala 3, Box 305. Drakv 3",
            "phone_number": "0141-500 25",
            "bank_details": {
                "bankgiro": "700-1803",
                "postgiro": "379311-4"
            },
            "activity": "Tillverkar kapslad lysrörsarmatur i plast, varor o skyltar i akrylplast",
            "employees": 14,
            "capital": 100000,
            "key_personnel": [
                {
                    "name": "Ing Stig Fergin",
                    "position": "Factory Director"
                }
            ],
            "establishment_year": null
        },
        "10": {
            "company_name": "FERIEPRODUKTER AB",
            "pnr": "283 00",
            "address": "Osby. V Järnvägsg",
            "phone_number": "0479-119 00, 119 30",
            "bank_details": {
                "bankgiro": "28-1714",
                "postgiro": "98485"
            },
            "activity": "Tillverkar trädgårdsmöbler o parasoller",
            "key_personnel": [
                {
                    "name": "Disp Nils Erik Lindroth",
                    "position": "Chief"
                }
            ],
            "establishment_year": null
        },
        "11": {
            "company_name": "FERLIN & CO AB, OSCAR",
            "pnr": "111 56",
            "address": "Stockholm, Regeringsg 56",
            "phone_number": "08-1147 00,10 03 73",
            "bank_details": {
                "bankgiro": "72-4750",
                "postgiro": "2373"
            },
            "activity": "Assuransfirma",
            "employees": 6,
            "capital": 5000,
            "key_personnel": [
                {
                    "name": "Ing Pär J Wiksten",
                    "position": "Chairman"
                },
                {
                    "name": "Wald Odenrick",
                    "position": "Director"
                }
            ],
            "establishment_year": 1876
        },
        "12": {
            "company_name": "FERM & OLSSON AB",
            "pnr": "453 00",
            "address": "Lysekil, Box 3, Gullmarskajen",
            "phone_number": "0523-100 07, 103 72",
            "bank_details": {
                "bankgiro": "548-3540",
                "postgiro": "333166-7"
            },
            "activity": "Befraktning, klarering, spedition o bunkeroljor",
            "employees": 11,
            "key_personnel": [
                {
                    "name": "Hedly Ferm",
                    "position": "Factory Director"
                }
            ],
            "establishment_year": 1924
        }
    }
}