{
    "original": "TEGMA, AB\n\nPnr 214 44\n\nMalmö, Kopparbergsg 29. Tel\n040-92 2170. Bankgiro 87-4836.\nPostgiro 38583. Telex 32543\nVerksamhet: Säljer o tillverkar\narbetarskyddsmaterial av alla slag\nAvdelningskontor: 416 56 Göteborg,\nBirkag 39. Tel 031-21 14 25, 21 14 35\nOrderkontor: 162 36 Vällingby,\nAprikos g 30. Tel 08-38 17 00\nVarunamn: Auer, Clora\nAntal anställda: 65\nÅrsomsättning: 10000 000\nAktiekapital: 50 000\nÄgare o chefer: Dir Nils Ersin, dir\nAke Tegman\n\nTeknisk chef: Skyddsing Gunnar\nBergqvist\n\nEtableringsår: 1946\nOmbildat till aktiebolag 1957.\n\nTEGNËR AB, C A\n\nPnr 11447\n\nStockholm. Majorsg 17. Tel\n08-62 4000, 67 80 85. Bankgiro\n726-8881. Postgiro 150907-4. Tga\nCategner\n\nVerksamhet: Tillverkar o säljer\nelektr hörselmätningsapparatur sk\naudiometrar samt tysta rum\nAntal anställda: 20\nAktiekapital: 100000\nStyrelse: Dir Carl-Axel Tegnér\n(ordf), fru Inger Tegnér\nVerkst dir: C A Tegnér\nEtableringsår: 1934.\n\nTEGNER EMBALLAGE\nAGENTURER, AB ERIK\n\nPnr 211 25\n\nMalmö, Osterg 27. Tel 040-735 1 0.\nPostgiro 247273\nVerksamhet: Säljer emballage,\ni huvudsak wellpappemballage\nAntal anställda: 4\nÅrsomsättning: 15 000 000\nAktiekapital: 15 000\nVerkst dir: Erik Tegnér\nEtableringsår: 1947.\n\nTE.HÅ AB MEK VERKSTAD\no VERKTYGSFABRIK\n\nPnr 520 13\n\nTvärred. Tel 0321-50250, 503 50.\nBankgiro 53-287 2. Postgiro 418680\nVerksamhet: Formverktyg för\nplastindustrin\nAntal anställda: 10\nAktiekapital: 46000\nVeikst dir. Gösta Gustafsson\nEtableringsår: 1957.\n\nmaskinlagret i svedala\nab\n\nPnr 233 00\n\nSvedala, Box 53, Börringev 3. Tel\n040-40 20 20. Bankgiro 196-1713.\nPostgiro 519370-1. Tga\nMachine-stock. Telex 32215 FYRA S\nVerksamhet: Säljer o köper nya o\nbegagnade verkstadsmaskiner\nAntal anställda: 7\nÅrsomsättning: 4 000 000\nAktiekapital: 60 000 000\nVeikst din Lennart Cedero\nEtableringsår 1960.\n\nPLANO AB\n\nPnr 18141\n\nLidingö, Vasav 82. Tel08-765 32 00,\n765 3 2 12. Bankgiro 627-4104.\nPostgiro 157520-8\n\nVerksamhet: Tryckeri o\nspiralblocksfabrik\nAktiekapital: 30 000\nVerkst dir: Bengt Söderström\nEtableringsår: 1932.\n\nNYQVIST &amp; BERGH AB\n\nPnr 40121\n\nGöteborg 1, N Hamng 36. Box 72.\nTel 031-1130 9 2, 13 37 27.\nBank-giro 33-7715. Postgiro 6 22820. Tga\nNybesteel\n\nVeiksamhet: Grossisthandel,\nförsäljning av järn- o stålvaror\nAntal anställda: 3\nÅrsomsättning: 1 500 000\nAktiekapital: 50 000\nVerkst dir: A R Nyqvist\nEtableringsår: 1962.\n\nAGRAFO I SKÖVDE AB\n\nPnr 541 01\n\nSkövde 1, Box 170. Barrstigen 2.\nTel 0500-14 9 20. Bankgiro\n413-9572. Postgiro 173880-6\nAntal anställda: 5\nAktiekapital: 25 000\nPlatschef: Berndt Jivesten\nEtableringsår 1970.\n\nFORSLUNDS MASKIN AB, H\n\nPnr 582 20\n\nLinköping, Platensg 28 o 29. Tel\n013-13 02 70. Bankgiro 120-4247.\nPostgiro 582939-5\nVerksamhet: Försäljning av\nlantbruksmaskiner o traktorer\nAktiekapital: 50000\nVerkst dir: Ing Helge Forslund\nEtableringsår: 1961.\n\nhäl\n\nVerksamhet: Konditori-,\nrestaurang- o storköksutrustningar\nFilial: 41125 Göteborg, Viktoriag\n6. Tel 031-13 85 75\nVarunamn: Hyma\nAktiekapital: 500 000\nVeikst dir: Egil Hylén\nDivass: Tege Hylén\nEtableringsår 1936.\n\nhyssna bobinfabrik\n\nPiir 510 22\n\nHyssna, Box 6. Tel 0320-390 05,\n39131. Bankgiro 54-6106. Postgiro\n146410\n\nVerksamhet: Tillverkar bobiner,\nvävbommar m m för textilindustrin\nAntal anställda: 13\nÅrsomsättning: 400 000\nChefer: Johan Askerdal, Erik\nAskerdal\n\nEtableringsår 1886.\n\nESS\n\nVerksamhet: Tillverkar\nkontorsvaror o spelkort. Grossiströrelse i\npappershandelsvaror\nFabrik: 632 33 Eskilstuna, Sättargl\nAntal anställda: 900\nVerkst dir; Bengt Strandberg\nEtableringsår: 1845.\n\nEST I, AB\n\nPnr 574 00\n\nVetlanda, Ekenässjön. Tel\n0383-300 38\n\nVerksamhet: Tillverkar\nrörledningsarmatur o säkerhetsventiler,\nsvarvningsarbeten av alla slag\nAktiekapital: 40 000\nVerkst dir: Sixten Carlström\nEtableringsår: 1942.\n\nAND\n\nVerksamhet: Idrottsdräkter,\nklubbmärken, reklam\nAntal anställda: 17\nÅrsomsättning: 900 000\nAktiekapital: 50 000\nVeikst dir: Sven Anagrius\nEtableringsår: 1921.",
    "structured": {
        "1": {
            "company_name": "TEGMA, AB",
            "pnr": "214 44",
            "address": "Malmö, Kopparbergsg 29",
            "phone_number": "040-92 2170",
            "bank_details": {
                "bankgiro": "87-4836",
                "postgiro": "38583"
            },
            "activity": "Säljer o tillverkar arbetarskyddsmaterial av alla slag",
            "employees": 65,
            "annual_turnover": 10000000,
            "capital": 50000,
            "key_personnel": [
                {
                    "name": "Dir Nils Ersin",
                    "position": "chef"
                },
                {
                    "name": "Dir Ake Tegman",
                    "position": "chef"
                },
                {
                    "name": "Skyddsing Gunnar Bergqvist",
                    "position": "teknisk chef"
                }
            ],
            "establishment_year": 1946
        },
        "2": {
            "company_name": "TEGNËR AB, C A",
            "pnr": "11447",
            "address": "Stockholm, Majorsg 17",
            "phone_number": "08-62 4000, 67 80 85",
            "bank_details": {
                "bankgiro": "726-8881",
                "postgiro": "150907-4"
            },
            "activity": "Tillverkar o säljer elektr hörselmätningsapparatur sk audiometrar samt tysta rum",
            "employees": 20,
            "capital": 100000,
            "key_personnel": [
                {
                    "name": "Dir Carl-Axel Tegnér",
                    "position": "ordförande"
                },
                {
                    "name": "fru Inger Tegnér",
                    "position": "styrelsemedlem"
                },
                {
                    "name": "C A Tegnér",
                    "position": "verkställande direktör"
                }
            ],
            "establishment_year": 1934
        },
        "3": {
            "company_name": "TEGNER EMBALLAGE AGENTURER, AB ERIK",
            "pnr": "211 25",
            "address": "Malmö, Osterg 27",
            "phone_number": "040-735 1 0",
            "postgiro": "247273",
            "activity": "Säljer emballage, i huvudsak wellpappemballage",
            "employees": 4,
            "annual_turnover": 15000000,
            "capital": 15000,
            "key_personnel": [
                {
                    "name": "Erik Tegnér",
                    "position": "verkställande direktör"
                }
            ],
            "establishment_year": 1947
        },
        "4": {
            "company_name": "TE.HÅ AB MEK VERKSTAD o VERKTYGSFABRIK",
            "pnr": "520 13",
            "address": "Tvärred",
            "phone_number": "0321-50250, 503 50",
            "bank_details": {
                "bankgiro": "53-287 2",
                "postgiro": "418680"
            },
            "activity": "Formverktyg för plastindustrin",
            "employees": 10,
            "capital": 46000,
            "key_personnel": [
                {
                    "name": "Gösta Gustafsson",
                    "position": "verkställande direktör"
                }
            ],
            "establishment_year": 1957
        },
        "5": {
            "company_name": "maskinlagret i svedala ab",
            "pnr": "233 00",
            "address": "Svedala, Box 53, Börringev 3",
            "phone_number": "040-40 20 20",
            "bank_details": {
                "bankgiro": "196-1713",
                "postgiro": "519370-1"
            },
            "activity": "Säljer o köper nya o begagnade verkstadsmaskiner",
            "employees": 7,
            "annual_turnover": 4000000,
            "capital": 60000000,
            "key_personnel": [
                {
                    "name": "Lennart Cedero",
                    "position": "verkställande direktör"
                }
            ],
            "establishment_year": 1960
        },
        "6": {
            "company_name": "PLANO AB",
            "pnr": "18141",
            "address": "Lidingö, Vasav 82",
            "phone_number": "08-765 32 00, 765 3 2 12",
            "bank_details": {
                "bankgiro": "627-4104",
                "postgiro": "157520-8"
            },
            "activity": "Tryckeri o spiralblocksfabrik",
            "capital": 30000,
            "key_personnel": [
                {
                    "name": "Bengt Söderström",
                    "position": "verkställande direktör"
                }
            ],
            "establishment_year": 1932
        },
        "7": {
            "company_name": "NYQVIST & BERGH AB",
            "pnr": "40121",
            "address": "Göteborg 1, N Hamng 36, Box 72",
            "phone_number": "031-1130 9 2, 13 37 27",
            "bank_details": {
                "bankgiro": "33-7715",
                "postgiro": "6 22820"
            },
            "activity": "Grossisthandel, försäljning av järn- o stålvaror",
            "employees": 3,
            "annual_turnover": 1500000,
            "capital": 50000,
            "key_personnel": [
                {
                    "name": "A R Nyqvist",
                    "position": "verkställande direktör"
                }
            ],
            "establishment_year": 1962
        },
        "8": {
            "company_name": "AGRAFO I SKÖVDE AB",
            "pnr": "541 01",
            "address": "Skövde 1, Box 170, Barrstigen 2",
            "phone_number": "0500-14 9 20",
            "bank_details": {
                "bankgiro": "413-9572",
                "postgiro": "173880-6"
            },
            "employees": 5,
            "capital": 25000,
            "key_personnel": [
                {
                    "name": "Berndt Jivesten",
                    "position": "platschef"
                }
            ],
            "establishment_year": 1970
        },
        "9": {
            "company_name": "FORSLUNDS MASKIN AB, H",
            "pnr": "582 20",
            "address": "Linköping, Platensg 28 o 29",
            "phone_number": "013-13 02 70",
            "bank_details": {
                "bankgiro": "120-4247",
                "postgiro": "582939-5"
            },
            "activity": "Försäljning av lantbruksmaskiner o traktorer",
            "capital": 50000,
            "key_personnel": [
                {
                    "name": "Ing Helge Forslund",
                    "position": "verkställande direktör"
                }
            ],
            "establishment_year": 1961
        },
        "10": {
            "company_name": "häl",
            "activity": "Konditori-, restaurang- o storköksutrustningar",
            "address": "Filial: 41125 Göteborg, Viktoriag 6",
            "phone_number": "031-13 85 75",
            "capital": 500000,
            "key_personnel": [
                {
                    "name": "Egil Hylén",
                    "position": "verkställande direktör"
                },
                {
                    "name": "Tege Hylén",
                    "position": "divisionschef"
                }
            ],
            "establishment_year": 1936
        },
        "11": {
            "company_name": "hyssna bobinfabrik",
            "pnr": "510 22",
            "address": "Hyssna, Box 6",
            "phone_number": "0320-390 05, 39131",
            "bank_details": {
                "bankgiro": "54-6106",
                "postgiro": "146410"
            },
            "activity": "Tillverkar bobiner, vävbommar m m för textilindustrin",
            "employees": 13,
            "annual_turnover": 400000,
            "key_personnel": [
                {
                    "name": "Johan Askerdal",
                    "position": "chef"
                },
                {
                    "name": "Erik Askerdal",
                    "position": "chef"
                }
            ],
            "establishment_year": 1886
        },
        "12": {
            "activity": "Tillverkar kontorsvaror o spelkort. Grossiströrelse i pappershandelsvaror",
            "address": "Fabrik: 632 33 Eskilstuna, Sättargl",
            "employees": 900,
            "capital": 40000,
            "key_personnel": [
                {
                    "name": "Bengt Strandberg",
                    "position": "verkställande direktör"
                }
            ],
            "establishment_year": 1845
        },
        "13": {
            "company_name": "EST I, AB",
            "pnr": "574 00",
            "address": "Vetlanda, Ekenässjön",
            "phone_number": "0383-300 38",
            "activity": "Tillverkar rörledningsarmatur o säkerhetsventiler, svarvningsarbeten av alla slag",
            "capital": 40000,
            "key_personnel": [
                {
                    "name": "Sixten Carlström",
                    "position": "verkställande direktör"
                }
            ],
            "establishment_year": 1942
        },
        "14": {
            "activity": "Idrottsdräkter, klubbmärken, reklam",
            "employees": 17,
            "annual_turnover": 900000,
            "capital": 50000,
            "key_personnel": [
                {
                    "name": "Sven Anagrius",
                    "position": "verkställande direktör"
                }
            ],
            "establishment_year": 1921
        }
    }
}