{
    "original": "AUT\n\nAktiekapital: 80 000\nVerkst dir: Börje Söderström\nEtableringsår: 1917.\n\nK LA FRE ST ROMS BRUK, AB\n\nPnr 360 72\n\nKlavreström. Tel 0474-405 00.\n\nPostgiro 6960. Tga Klafreström,\nVäxjö\n\nVerksamhet: Tillverkar höglegerat\nstålgjutgods. Mekanisk verkstad o\nplåtverkstad\nAntal anställda: 120\nÅrsomsättning: 9 200 000\n\nAktiekapital: 1500 000\nVerkst dir: O Johansson\nEtableringsår: 1736\nAktiebolagsbildning 1916 o 1961.\n\nKLEIST AB, STURE\n\nPnr 50109\n\nBorås 1, Österlångg 51. Box 625.\nTel 033-12 09 61. Tga Kleistagent\nVerksamhet: Agenturförsäljning av\ntyger o textilvaror\nStyrelse: Disp Sture Kleist (ordf),\nfru Maj-Britt Kleist\nVerkst dir: Sture Kleist\nEtableringsår: 1955.\n\nWINBERG &amp; HOGSTEDT AB\n\nPnr 21134\n\nMalmö C, Söderg 26. Tel 040-\n\n705 35. Bankgiro 26-0384. Postgiro\n\n149052\n\nVerksamhet: Konsulterande\narkitekt- o ingenjörsbyrå\nAktiekapital: 30 000\nFirmatecknare: Civiling Sture\nHög-stedt samt styrelsen\nEtableringsån 1943.\n\nSEDIN &amp; SCHMIDT AB\n\nPnr 401 26\n\nGöteborg 1, Kungspassagen, uppg\nA. Box 386. Tel 031-13 53 75,\n1359 65. Bankgiro 420-6496.\nPostgiro 427306-6. Tga Steeltrade.\nTelex 20714\n\nVerksamhet: Importerar järn o stål,\nbleckplåt, metaller, legeringar,\nmalmer, tackjärn o diverse\nindustriråvaror. Exporterar diverse\nsvenska industriprodukter\nAntal anställda: 6\nÅrsomsättning: 30 000 000\nAktiekapital: 300 000\nVerkst dir Gösta Schmidt\nEtableringsår. 1963.\n\nBYGG.AGENTURER, AB\n\nPnr 41109\n\nGöteborg, Ulla Nyg 2. Tel\n031-13 72 67, 13 72 87. Bankgiro\n44-2289. Postgiro 523558-5\nVerksamhet: Säljer\nbyggnadsmateriel\n\nAntal anställda: 5\nAktiekapital: 5 000\nVerkst dir: Bengt Wiselqvist\nEtableringsår: 1958.\n\nRINGESTEN &amp; CO KB, G\n\nPnr 113 50\n\nStockholm, Sveav 112. Tel\n08-24 34 00. Bankgiro 671-3176. PosU\ngiro 385846-1. Tga Garco, Åstorp\nVerksamhet: Kontorsmateriel,\nPer-macel industritejp\nFabrik, konton Åstorp. Tel\n042-509 35. Tga Garco\nVeikst dir: Georg Ringesten\nEtableringsår: 1948.\n\nDIVIMECANA AB\n\nPnr 13104\n\nNacka 4. Box 4018. Tel\n08-715 0990, 715 6070. Bankgiro\n746-0926. Postgiro 681048-5.\nTga Divimecana, Stockholm\nVerksamhet:\nEfterbehandlings-maskiner för datablanketter\nVarunamn: Divi\nÅrsomsättning: 2 000000\nAktiekapital: 10000\nVerkst dir: Ing Erie Hermander\nEtableringsår: 1960.\n\nBOLIDEN AB\n\nPnr 114 85\n\nStockholm, Box 5508. Stureg 22.\nTel 08-63 13 20. Bankgiro 569-3361.\nPostgiro 1166-8. Tga Bolidcomp.\nTelex 19395\n\nVerksamhet: Gruvdrift,\nsmältverksrörelse o kemisk industri.\nTillverkar blyslig, zinkslig,\nsvavelkis-slig, koppar, bly, guld, silver,\narsenik, -salter, -metall, selen,\n-föreningar, blyoxider, nickelsulfat,\nzinkklinker, blydammpellets,\nsvavelsyra, saltsyra, forsforsyra,\nflytande svaveldioxid,\naluminiumsulfat, natriumsulfat, kalciumklorid,\nkalciumfosfater, järnoxider,\nmineralfoder, träimpregneringsmedel,\ntalk\n\nGruvförvaltning: 930 50 Boliden.\nTel 0910-60600. Bankgiro\n625-4056. Postgiro 61400-8. Telex 6878.\nTga Coppermine, Skellefteå. Chef:\nDir Sigvard Ando, v verkst dir\nBolidenområdet: Centralort 930 50\nBoliden. Tel 0910-606 00. Telex\n6878. Chef: Övering J Hindrum\nGruvor: Renström, Långsele,\nLångdal, Kedträskfältet. Centralt\nanrikningsverk o centrala\nhjälpav-delningar i Boliden\nKristinebergsområdet: Centralort\n920 40 Kristineberg. Tel\n0953-200 06. Telex 8807. Chef: övering\nR Widmark. Gruvor: Kristineberg,\nRävlidmyran, Rävliden, Kimheden,\nNäsliden, Rakkejaur, Centralt\nanrikningsverk i Kristineberg.\nAdakområdet: Centralort 930 73\nAdakgruvan. Tel 0953-300 52. Chef:\nOvering K Amdahl. Gruvor:\nAdak-fältet (entreprenaddrift för Staten),\nRudtjebäcken, lokalt\nanrikningsverk vid Adakgruvan\nLaisvallområdet: Centralort 930 93\nLaisvall. Tel Laisvall 1. Telex\n6910. Chef: Overing Birger Kolsrud\nGruva: Laisvall. Centralt\nanrikningsverk\n\nAitikområdet: Centralort 972 00\nGällivare. Tel 0970-320 36. Telex\n8667. Chef: övering O Jacobsson\nGruva: Aitik. Centralt\nanrikningsverk\n\nGarpenbergsdistriktet: Centralort\n77073 Garpenberg. Tel 0225-202 00.\nTelex 7520. Chef: Dir K Johansson\nGruvor: Garpenberg, Svärdsjö,\nSaxberget, ljusnarsberg, Kaveltorp,\nVassbo (Idre). Anrikningsverk i\nGarpenberg, Saxberget o Vassbo\n\nRönnskärsverken: 932 00\nSkellefte-hamn. Tel 0910-315 00. Bankgiro\n615-6020. Postgiro 60704-4. Telex\n6874. Tga Bolidsmelt,\nSkellefte-hamn. Kopparverk, blyverk,\nädel-metallverk, arsenik- o selenverk,\nsvavelsyrafabrik m m. Chef: Dir\nFolke Nilsson, v verkst dir\nReymersholmsverken: 25101\nHelsingborg, Industrig 83. Tel\n042-13 91 00. Bankgiro 863-8231.\nPostgiro 32139-8. Telex 72218. Tga\nBolidreym, Helsingborg.\nSvavelsyrafabrik, kemiska fabriker för\nframställning av aluminium- o\nnatrium-sulfater, natrium- o\nkalciumfosfater, kalciumklorid m m. Chef: Dir\nSigvard Hellestam, v verkst dir\nAntal anställda: 5 700\nÅrsomsättning: 919 900 000\nAktiekapital: 277 585 000\nStyrelse: Dir B Norén (ordf), dir\nHarry Brynielsson, dir Nils\nElfström, bankdir Folke Fessé (v ordf),\ndir A Lamarche, dir Ake Palm, dir\nSven Wahlström, bankdir Alf\nÅkerman\n\nVerkst dir: Ake Palm\nFörsäljn-dir: Tom B Börresen,\nv verkst dir\n\nChef för utveckling o teknisk\nsamordning: Torsten Jensfelt,\nv verkst dir\nEtableringsår: 1925\nAntog nuvarande namn 1966.\n\nBOHLINS JÄRNHANDEL AB\n\nPnr 544 00\n\nHjo, Hamng 16. Tel 0503-100 24,\n10117. Bankgiro 21-6367.\nPostgiro 96277\n\nVerksamhet: Säljer järnvaror,\nmaskiner, redskap, kapitalvaror,\nbyggnadsmateriel\nAktiekapital: 100 000\nVerkst dir: Sven Arvidson\nJärnhandlare: Töre Arvidson\nEtableringsår: 1936.\n\nÄETÄTRYCK, AB\n\nPnr 102 61\n\nStockholm 4, Box 4048. Finnbodav\n2, Nacka. Tel 08-44 91 80. Postgiro\n407250. Tga Bonnierprint.\nTelex 10043\n\nVerksamhet: Boktryckeri, offset- o\ndjuptryckeri, bokbinderi o\nreklamservice. Utför bok- o katalogtryck,\nbroschyrer, tidskrifter, folders,\naffischer, etiketter mm\nAntal anställda: 120\nÅrsomsättning: 8 500 000\nAktiekapital: 5 000\nStyrelse: Bokförl Lukas Bonnier\n(ordf), dir Olof Bergendahl, bokförl\nGerard Bonnier, dlr Johan Bonnier,\ndir Stig Hedenström, dir Töre\nNilsson\n\nVerkst dir. Stig Hedenström\nEtableringsån 1939\nOmbildat till aktiebolag 1941.\n\nÅHFELDT&amp; FRANK, AB\n\nPnr 252 53\n\nHelsingborg, Ängelholmsv 27. Tel\n042-12 64 75. Bankgiro 652-8384.\nPostgiro 331992-8. Tga Afa\nVerksamhet: Offsettryckeri.\n\nÅFORS GLASBRUK, AB\n\nPnr 360 63\n\nEriksmåla. Tel 0471-412 80.\nBankgiro 615-7200. Postgiro 7775-0.\nTga Aforsbruk\n\nVerksamhet: Tillverkar kristall\nsamt slipat hushållsglas\nVerkst dir. Erik Rosén\nEtableringsår. 1876.\n\nMP-BOLAGEN, AB\n\nPnr 574 01\n\nVetlanda 1, Storg 25. Box 8. Tel\n0383-150 00. Bankgiro 289-7023.\nPostgiro 478478-1. Tga Empewood.\nTelex 3715 MPWOOD S\n\nVerksamhet: Export av massaved,\ntimmer, stamblock, träflis o andra\nrundvirkessortiment.\nInköpsverksamhet med 11 avdelningskontor\növer södra Sverige. Tillverkningen\nomfattar bl a sågning av trävaror,\nbarkning av gran-, tall- o\nbjörk-massaved samt tillverkning av\nflis, tillverkning av stålprofiler s k\nMP-byggprofil samt kabelstegar o\nstativ för el-branschen\nRundvirkesterminaler: Lidnäs\n(Småland) AB MP-bolagen. Tel\n0472-741 15\n\nUlvåker (Västergötland) AB\nMP-bolagen. Tel 0500-602 29\nSvenljunga (Västergötland) AB\nMP-bolagen. Tel 0325-104 60\nMantorp (Östergötland) AB\nMP-bolagen. Tel 0142-207 41\nTräflis: Ystad (Skåne) AB\nMP-bolagen. Tel 0411-130 61\nSågade granträvaror: Trelleborg\n(Skåne) AB MP-bolagen\nRamsågverk, Gislöv. Tel 0410-342 17\nAntal anställda: 110\nÅrsomsättning: 60 000 000\nAktiekapital: 2 000 000\nVerkst dir: W G von Seydlitz\nEtableringsår: 1955\nOmbildat till aktiebolag 1958.\n\nMULLSJO INDUSTRI AB\n\nPnr 43134\n\nMölndal, Klippg 1. Tel 031-27 20 45.\nBankgiro 36-4875. Postgiro 2429 23.\nTga Mullin, Göteborg\nVerksamhet: Tillverkar persienner\nsamt material o maskiner\nVarunamn: Belami\nAntal anställda: 30\nÅrsomsättning: 1500 000\nAktiekapital: 100000\nVerkst din Olof Fridlund\nEtableringsår: 1948.",
    "structured": {
        "1": {
            "company_name": "Boliden AB",
            "establishment_year": 1925,
            "pnr": "114 85",
            "address": "Stockholm, Box 5508, Stureg 22",
            "phone_number": "08-63 13 20",
            "bank_details": {
                "bankgiro": "569-3361",
                "postgiro": "1166-8"
            },
            "activity": "Gruvdrift, smältverksrörelse o kemisk industri. Tillverkar blyslig, zinkslig, svavelkis-slig, koppar, bly, guld, silver, arsenik, -salter, -metall, selen, -föreningar, blyoxider, nickelsulfat, zinkklinker, blydammpellets, svavelsyra, saltsyra, forsforsyra, flytande svaveldioxid, aluminiumsulfat, natriumsulfat, kalciumklorid, kalciumfosfater, järnoxider, mineralfoder, träimpregneringsmedel, talk",
            "employees": 5700,
            "annual_turnover": 919900000,
            "capital": 277585000,
            "key_personnel": {
                "1": {
                    "name": "Ake Palm",
                    "position": "Verkst dir"
                },
                "2": {
                    "name": "Tom B Börresen",
                    "position": "Försäljn-dir, v verkst dir"
                },
                "3": {
                    "name": "Torsten Jensfelt",
                    "position": "Chef för utveckling o teknisk samordning, v verkst dir"
                }
            }
        },
        "2": {
            "company_name": "Äetätryck, AB",
            "establishment_year": 1939,
            "pnr": "102 61",
            "address": "Stockholm 4, Box 4048, Finnbodav 2, Nacka",
            "phone_number": "08-44 91 80",
            "postgiro": "407250",
            "activity": "Boktryckeri, offset- o djuptryckeri, bokbinderi o reklamservice. Utför bok- o katalogtryck, broschyrer, tidskrifter, folders, affischer, etiketter mm",
            "employees": 120,
            "annual_turnover": 8500000,
            "capital": 5000,
            "key_personnel": {
                "1": {
                    "name": "Lukas Bonnier",
                    "position": "Bokförl (ordf)"
                },
                "2": {
                    "name": "Olof Bergendahl",
                    "position": "dir"
                },
                "3": {
                    "name": "Gerard Bonnier",
                    "position": "bokförl"
                },
                "4": {
                    "name": "Johan Bonnier",
                    "position": "dlr"
                },
                "5": {
                    "name": "Stig Hedenström",
                    "position": "dir"
                },
                "6": {
                    "name": "Töre Nilsson",
                    "position": "dir"
                }
            }
        },
        "3": {
            "company_name": "Åhfeldt & Frank, AB",
            "establishment_year": null,
            "pnr": "252 53",
            "address": "Helsingborg, Ängelholmsv 27",
            "phone_number": "042-12 64 75",
            "bank_details": {
                "bankgiro": "652-8384",
                "postgiro": "331992-8"
            },
            "activity": "Offsettryckeri."
        },
        "4": {
            "company_name": "Åfors Glasbruk, AB",
            "establishment_year": 1876,
            "pnr": "360 63",
            "address": "Eriksmåla",
            "phone_number": "0471-412 80",
            "bank_details": {
                "bankgiro": "615-7200",
                "postgiro": "7775-0"
            },
            "activity": "Tillverkar kristall samt slipat hushållsglas",
            "employees": null,
            "annual_turnover": null,
            "capital": null,
            "key_personnel": {
                "1": {
                    "name": "Erik Rosén",
                    "position": "Verkst dir"
                }
            }
        },
        "5": {
            "company_name": "MP-Bolagen, AB",
            "establishment_year": 1955,
            "pnr": "574 01",
            "address": "Vetlanda 1, Storg 25, Box 8",
            "phone_number": "0383-150 00",
            "bank_details": {
                "bankgiro": "289-7023",
                "postgiro": "478478-1"
            },
            "activity": "Export av massaved, timmer, stamblock, träflis o andra rundvirkessortiment. Inköpsverksamhet med 11 avdelningskontor över södra Sverige. Tillverkningen omfattar bl a sågning av trävaror, barkning av gran-, tall- o björk-massaved samt tillverkning av flis, tillverkning av stålprofiler s k MP-byggprofil samt kabelstegar o stativ för el-branschen",
            "employees": 110,
            "annual_turnover": 60000000,
            "capital": 2000000,
            "key_personnel": {
                "1": {
                    "name": "W G von Seydlitz",
                    "position": "Verkst dir"
                }
            }
        },
        "6": {
            "company_name": "Mullsjo Industri AB",
            "establishment_year": 1948,
            "pnr": "43134",
            "address": "Mölndal, Klippg 1",
            "phone_number": "031-27 20 45",
            "bank_details": {
                "bankgiro": "36-4875",
                "postgiro": "2429 23"
            },
            "activity": "Tillverkar persienner samt material o maskiner. Varunamn: Belami",
            "employees": 30,
            "annual_turnover": 1500000,
            "capital": 100000,
            "key_personnel": {
                "1": {
                    "name": "Olof Fridlund",
                    "position": "Verkst din"
                }
            }
        }
    }
}