{
    "original": "BENGTSSONS MASKIN, AB\n\nPnr 200 21\n\nMalmö 21, Box 21046. Kruseg 34.\nTel 040-18 00 20. Bankgiro\n640-0105. Postgiro 37523-8. Tga\nBengtssons. Telex 32403 BENGTSN S\nVerksamhet: Specialföretag i\ntransmissioner o transportanläggningar\nVarunamn: Fissenewert, Flexi-Bett,\nFYomme, IWIS, PFAFF, REX,\nThomas\n\nFilial: 171 23 Solna 1, Box 1210.\nKlippg 16. Tel 08-8200 00.\nTelex 17043 BENGTSN S\nAntal anställda: 32\nAktiekapital: 400000\nStyrelse: Disp E Tindberg, ing B\nTindberg, ing G Tindberg, bankdir\nG Rönbeck\n\nÄgare: Familjen Tindberg\nEtableringsår: 1913\nOmbildat till aktiebolag 1939.\n\nBENGTSSONS MEK VERKSTAD\nAB, BRÖDERNA\n\nPnr 340 20\n\nLiatoip. Tel 0476-20350, 202 20\nVerksamhet: Specialfabrik för\nkugg- o kedjehjul\nAntal anställda: 60\nÅrsomsättning: 3 600 000\nAktiekapital: 100 000\nVerkst dir: Torsten Bengtsson\nEtableringsår 1947.\n\nBENGTSSON SKEPPSHANDEL\nAB, ALGOT\n\nPnr 292 00\n\nKarlshamn, Agatan 12. Tel\n0454-100 80, 114 00. Bankgiro 65-6582.\nPostgiro 86962. Tga Fournering\nVerksamhet:\nSkeppshandel-försäljning till fartyg o lustbåtar\nAntal anställda: 9\nÅrsomsättning: 1000 000\nAktiekapital: 55 000\nVerkst dir: Sven Bengtsson\nEtableringsår: 1908.\n\nB LA\n\nÅrsomsättning: 14 000000\n\nAktiekapital: 100 000\n\nStyrelse: Dlr Hans Blomstedt(ordf),\n\ndisp Bertil Ericsson, kamrer\nKnut Sikmark\n\nVerkst dir: Hans Blomstedt\nPlatschef: Disp Bertil Ericsson\nEtableringsår: 1960.\n\nBLOMSTRAND BYGGNADS AB,\nHOLGER\n\nPnr 414 62\n\nGöteborg, Djurgårdsg 9. Tel\n031-24 94 32 , 24 94 38. Bankgiro\n337-6399. Postgiro 242811-8\nVerksamhet: Uppför byggnader\nAntal anställda: 59\nÅrsomsättning: 7 000 000\nAktiekapital: 35 000\nVerkst dir: Holger Blomstrand\nEtableringsår: 1947.\n\nSCA EMBALLAGE AB\n\nPnr 33100\n\nVärnamo. Tel 0370-118 00. Bankgiro\n29-1698. Postgiro 81334.\nTelex 70190 SCAEMB S\nVerksamhet: Tillverkar emballage\ni wellpapp o cellplast vid fabriker\ni Värnamo o Järfälla\nAntal anställda: 325\nÅrsomsättning: 31000 000\nAktiekapital: 1000 000\nVerkst dir: Bengt Rudén\nEtableringsår: 1932\nDotterbolag till Svenska\nCellulosa AB.\n\nSCABA\nBLANDNINGSTEKNIK AB\n\nPnr 182 51\n\nDjursholm 1, Box 12. Bragev 30.\nTel 08-753 04 90. Bankgiro\n617-2704. Telex 10956 UCAB S\nVerksamhet: Omrörare för alla\nförekommande uppgifter\nAntal anställda: 10\nÅrsomsättning: 1 000 000\nAktiekapital: 50 000\nVerkst dir: Ulf Christierson\nEtableringsår: 1970.\n\nTEGELKONTORET\n\nPnr 501 02\n\nBorås 1, Kungsg 50. Box 56. Tel\n033-1250 54, 1250 55. Postgiro\n97953\n\nVerksamhet: Försäljningskontor\nför tegel\n\nÄgare o chef: Dir Mats Johansson\nEtableringsår: 1952.\n\nPRI\n\nmatbröd, kaffebröd o skorpor i\nparti\n\nDotterbolag: Nybro. Priems\nKonditorier AB. Tel 0481-11541\nAntal anställda: 50\nÅrsomsättning: 3 700 000\nAktiekapital: 200 000\nVerkst dir: Thor Priem\nFörsäljn-chef: Sixten Nilsson\nEtableringsår: 1912.\n\nPR|ESTMAN INDUSTRI.\nDIESEL AB\n\nPnr 195 01\n\nMärsta 1, Fack. O Bang 3. Tel\n0760-11125. Bankgiro 700-3247.\nPostgiro 152044-4. Tga Insel,\nStockholm. Telex 10948 INSEL S\nVerksamhet: Grävmaskiner,\nkranar, gripskopor, dredgers\nAntal anställda: 50\nÅrsomsättning: 10 000 000\nAktiekapital: 4 000 000\nVerkst din Lennart Anderson\nEtableringsår 1942.\n\nPRILLS MEKANISKA\nVERKSTAD, AB\n\nPnr 603 63\n\nNorrköping, Hammarg 67. Tel\n011-13 15 57. Bankgiro 610-0093.\nPostgiro 369363-7\n\nVerksamhet: Legotillverkning av\nmaskindetaljer\nAktiekapital: 50 000\nVerkst dir: Ing Aleksy Prill\nEtableringsår: 1949.\n\nERKÅS KONFEKTION, AB\n\nPnr 50002\n\nBorås 2, Box 22051. Alingsåsv 10.\nTel 033-11 83 39, 12 58 86.\nPostgiro 492669\n\nVerksamhet: Tillverkar skjortor o\nblusar\n\nAntal anställda: 60\nÅrsomsättning: 3 700000\nAktiekapital: 15 000\nVerkst din Karl Gustav Nilsson\nEtableringsån 1955.\n\nERN\n\nEHRLANDER &amp; CO, PAUL\n\nPnr 41707\n\nGöteborg, Stenkolsg 1 E. Tel\n031-22 35 50, 22 35 55. Bankgiro\n50-6744. Postgiro 421351\nVerksamhet: Gips o fartygsbeslag\ni parti\n\nERLANDSSONS\nMETALLFABRIK. AB\n\nPnr 330 20\n\nAnderstorp, Box 23. Brageg. Tel\n0371-16810. Bankgiro 488-0175.\nPostgiro 84490-2\nVerksamhet: Mekaniska vispar,\nrostfria slevar o ösor, kedjor m m.\nRörbockning. Utför legoarbeten\nAntal anställda: 15\nÅrsomsättning: 1500000\nAktiekapital: 120 000\nStyrelse: Allan Fridström (ordf),\nBengt Magnusson\nVerkst dir: Roland Andersson\nEtableringsår: 1901.\n\nERLANDSSON AB,\nROR-LEDNINGSFIRMA B\n\nPnr 462 00\n\nVänersborg, Kyrkog 13. Tel\n0521-110 85. 158 50. Bankgiro 888-7192.\nPostgiro 292512-1\nVerksamhet: VVS-installationer\nAntal anställda: 14\nÅrsomsättning: 1500 000\nAktiekapital: 25 000\nVerkst din Kurt Erlandsson\nEtableringsån 1932\nRepresentant för Electrolux AB\n(vacuumtoalettsystem).\n\nEHRLIN, AB ALFRED\n\nPnr 573 00\n\nTranås, Vasag 33. Box 200. Tel\n0140-14215. Bankgiro 365-6261.\nPostgiro 143563-5\nVerksamhet: Tillverkar skåp,\nbokhyllor, bord, stolar o tevagnar\nAntal anställda: 45\nÅrsomsättning: 4 000 000\nAktiekapital: 148 500\nVerkst dir: Jan Ehrlin\nEtableringsår: 1945.\n\nERMA-HAVOLINE AB, KEM\nTEKN FABRIKEN\n\nPnr 11140\n\nStockholm. Kammak arg 18. Tel\n08-201161. 213162. Bankgiro\n570-9944. Postgiro 152390-1\nVerksamhet: Tillverkar tvätt- o\nrengöringsmedel, tvål, pasta, pulver,\ntabletter, creme, diskmedel m m\nVerkst dir: Fabr O H Malmgren\nEtableringsår: 1935.\n\nTRAVE-LINE, AB\n\nPnr 25102\n\nHelsingborg 1, Box 16. Järnvägsg\n\n9. Tel 042-1201 80. Bankgiro\n864-1417. Postgiro 321790-8. Tga\nLinjebuss. Telex 72220 LB BOKN S\nVeiksamhet: Bil- o\npassagerare-färjetrafik mellan\nHelsingborg-Kö penhamn-Travemiinde.\nDotterbolag till Linjebuss\nInternational AB.\nSe detta bolag.\n\nTRE KRONOR, KVARN AB\n\nPnr 104 65\n\nStockholm 15, Kvarnholmen. Tel\n08-44 92 60. Telex 1490 kooperativa\nsthlm. Tga Kronkvarn\nVeiksamhet: Tillverkar mjöl, gryn,\nrostade flingor, kaksatser-snabbak,\nknäckebröd, makaroner, fodervaror.\nSäljer dessutom kex o vissa\nbageriprodukter, ris o baljväxter\nKvarnar: Nacka, Kvarnholmen.\nTel 08-44 92 60\nGöteborg. Tel 031-22 81 20\nTeckomatorp, Gissleberga. Tel\n0418-600 27\n\nFoderfabriker. Nacka,\nKvarnholmen. Tel 08-44 92 60\nÅhus. Tel 044-24 0516\nVarunamn: Juvel\nAntal anställda: 600\nÅrsomsättning: 290 000 000\nAktiekapital: 1375 000\nVerkst dir. Rolf Andersson\nEtableringsån 1897.\n\nTRE KRONOR, KVARN AB\n\nGöteborgskvarnen\n\nPnr 402 72\n\nGöteborg 8, Bratteråsg 32. Box\n8878. Tel 031-22 81 20. Tga Kvarnen\nVerksamhet: Kvarnindustri för\nframställning av vetemjöl, rågmjöl,\nkli- o fodermjöl\nVarunamn: Juvel\nAntal anställda: 99\nAktiekapital: 3 500 000\nStyrelse: Dir Harry Hjalmarsson\n(ordf), dir Nils Thedin, dir Kurt\nLindfors, dir Karl-Axel Linderoth,\ndir Gunnar Ekman, dir Bertil Tronét,\ndir John Sallborg\nVerkst din Rolf Andersson\nPlatschef: Folke Malmström\nEtableringsån 1925\nDotterbolag till Kooperativa\nFörbundet, Stockholm.\n\nTRE KRONOR,\nMINERALVATTENFABRIKEN\n\nPnr 172 34\n\nSundbyberg, Vegag 26-28. Tel\n08-28 2655. Bankgiro 74-3583.\nPostgiro 8100\n\nVerksamhet: Tillverkar o säljer\nCoca-Cola, Fanta\nVarunamn: Coca-Cola, Fanta\nAntal anställda: 105\nChef: Disp Sven Wikberg\nEtableringsån 1953\nDotterföretag till\nPripp-Bryggerier-naAB.\n\nTRE KOK AB\n\nPnr 104 35\n\nStockholm 23, Box 23143. Sveav\n163. Tel 08-22 70 20. Bankgiro\n731-3422 . Postgiro 707490-9\nVerksamhet: Marknadsför kött-,\ngrönsaks- o djurmatskonserver\nAntal anställda: 39\nÅrsomsättning: 67 800 000\n\n■Aktiekapital: 800 000\nVeikst dir: Ingvar Edling\nEtableringsår: 1965.\n\nOLA\n\nOLAUSSON &amp; SUN ER, AB C A\n\nPnr 570 81\n\nJärnforsen, Box 38. Tfel\n0495-500 34. Bankgiro 290-5271.\nPostgiro 335608-6. Tga Olab.\nTelex 3932 OLAB S\nVerksamhet: Tillverkar sågade\no hyvlade trävaror\nAntal anstäUda: 50\nÅrsomsättning: 8 000 000\nAktiekapital: 150000\nStyrelse: Disp Sture Olausson\n(ordf), dir Carl Anton Olausson\nVerkst dir: Disp Sture Olausson\nEtableringsår: 1920\nOmbildat till aktiebolag 1953.\n\nOHLCÉN &amp; NILSSON AB\n\nPnr 11122\n\nStockholm, Kungsg 66. Tel\n08-23 27 70. Bankgiro 563-5321.\nPostgiro 2240-0. Tga Ohlcenit\nVerksamhet: Smörjoljor,\nmaskin-o industriförnödenheter\nAntal anställda: 20\nÅrsomsättning: 3 500000\nAktiekapital: 300 000\nVerkst dir: Disp E Håkan Ohlcén\nEtableringsår: 1910.\n\nOLEBOLAGET OLOF\nERICSON AB\n\nPnr 40122 Gbg 1\n\nPartiUe. Box 127, Gbg 1. Tel\n031-44 0680. Bankgiro 50-6541.\nPostgiro 47053. Tga Olebolag\nVerksamhet: Livsmedel för storkök,\nskeppshandel, kemisk-tekniska\nprodukter\n\nAktiekapital: 270000\n\nVerkst din Generalkonsul Olof\n\nEricson\n\nEtableringsår: 1948.\n\nESKILSTUNAMAGASINET, AB\n\nPnr 63105\n\nEskilstuna 1, Box 369. Stora Nyby,\nStenkvista. Tel 016-13 70 60.\nBankgiro 601-3338. Postgiro 10715-1.\nTga Magasinet. Telex 40991\nVerksamhet: Engrosförsäljning i\nbyggnadsvaror, artiklar för trädgård\no fritid, hem o hobby, marinartiklar,\nWilkinson Sword trädgårdsredskap,\nNorlett gräsklippare, Husqvarnar\nVIKING o BRNO jakt- o sportvapen,\nSellier &amp; Bellot ammunition, Arnold\nPalmer golf m m\n\nAvdelningskontor: 116 47 Stockholm,\nBellmansg 26. Tel 08-44 33 44.\nTelex 1611\n\n421 02Västra Frölunda 2, Box 2063.\nFröhusg 8. Tel 031-45 07 90.\nTelex 20899\nVarunamn: EME\nAntal anställda: 70\nÅrsomsättning: 23 000 000\nAktiekapital: 800 000\nStyrelse: Fru Karin Alderin (ordf),\ndir John Alderin, disp Stanley\nSonesson\n\nVerkst dir: John Alderin\nV verkst dir: Björn Schullström\nFörsäljn-chef: Stanley Sonesson\nEtableringsår: 1898.\n\nESLÖVS LASTBILCENTRAL\nEK FOR\n\nPnr 24100\n\nEslöv, Industriv 1. Tel\n0413-13165. Bankgiro 866-0466.\nPost-giro 247898-0\n\nVerksamhet Uthyr lastmaskiner o\n\nliftdumpers\n\nAntal anställda: 110\n\nÅrsomsättning: 10000 000\n\nChef: Föreståndare Arne Andersson\n\nEtableringsår: 1940.\n\ngåvans slujdfabrik\n\nPnr 570 25\n\nFlisby. Tel 0380-801 26, 80168\nVerksamhet: Tillverkar trappstegar,\npiskställ mm\n\nÄgare o chef: Henry Franzén.\n\ngällivare stalkonstruk.\ntioner, ab\n\nPnr 98100\n\nKiruna, Lastv 14. Tel 0980-187 10.\n\nBankgiro 574-4354\n\nVerksamhet: Grovplåtslageri, smi-\n\ndesarbeten, licenssvetsning samt\n\nleg oarbeten\n\nAntal anställda: 30\n\nÅrsomsättning: 2 000 000\n\nAktiekapital: 45 000\n\nVerkst dir: Rune Pettersson\n\nEtableringsår: 1971.\n\ngällstads textiltryck,\nab\n\nPnr 52010\n\nGäUstad, Box 93. Tel 0321-700 22.\nBankgiro 84-0646. Postgiro\n\n385783\n\nVerksamhet: Utför handtryck s k\nfilmtryck i lön för konfektionärer,\nhemt e xtilfabrikanter, trikåfabriker\nAntal anstäUda: 15\nÅrsomsättning: 800 000\nAktiekapital: 120 000\nFabrikschef: Disp Ingvar Forsell\nEtableringsår: 1944.",
    "structured": {
        "1": {
            "company_name": "BENGTSSONS MASKIN, AB",
            "pnr": "200 21",
            "address": "Malmö 21, Box 21046. Kruseg 34.",
            "phone_number": "040-18 00 20",
            "bank_details": {
                "bankgiro": "640-0105",
                "postgiro": "37523-8"
            },
            "activity": "Specialföretag i transmissioner o transportanläggningar",
            "employees": 32,
            "capital": 400000,
            "key_personnel": [
                {
                    "name": "Disp E Tindberg",
                    "position": "Styrelse"
                },
                {
                    "name": "ing B Tindberg",
                    "position": "Styrelse"
                },
                {
                    "name": "ing G Tindberg",
                    "position": "Styrelse"
                },
                {
                    "name": "bankdir G Rönbeck",
                    "position": "Styrelse"
                }
            ],
            "establishment_year": 1913
        },
        "2": {
            "company_name": "BENGTSSONS MEK VERKSTAD AB, BRÖDERNA",
            "pnr": "340 20",
            "address": "Liatoip.",
            "phone_number": "0476-20350, 202 20",
            "activity": "Specialfabrik för kugg- o kedjehjul",
            "employees": 60,
            "annual_turnover": 3600000,
            "capital": 100000,
            "key_personnel": {
                "name": "Torsten Bengtsson",
                "position": "Verkst dir"
            },
            "establishment_year": 1947
        },
        "3": {
            "company_name": "BENGTSSON SKEPPSHANDEL AB, ALGOT",
            "pnr": "292 00",
            "address": "Karlshamn, Agatan 12",
            "phone_number": "0454-100 80, 114 00",
            "activity": "Skeppshandel-försäljning till fartyg o lustbåtar",
            "employees": 9,
            "annual_turnover": 1000000,
            "capital": 55000,
            "key_personnel": {
                "name": "Sven Bengtsson",
                "position": "Verkst dir"
            },
            "establishment_year": 1908
        },
        "4": {
            "company_name": "BLOMSTRAND BYGGNADS AB, HOLGER",
            "pnr": "414 62",
            "address": "Göteborg, Djurgårdsg 9",
            "phone_number": "031-24 94 32 , 24 94 38",
            "activity": "Uppför byggnader",
            "employees": 59,
            "annual_turnover": 7000000,
            "capital": 35000,
            "key_personnel": {
                "name": "Holger Blomstrand",
                "position": "Verkst dir"
            },
            "establishment_year": 1947
        },
        "5": {
            "company_name": "SCA EMBALLAGE AB",
            "pnr": "33100",
            "address": "Värnamo",
            "phone_number": "0370-118 00",
            "activity": "Tillverkar emballage i wellpapp o cellplast vid fabriker i Värnamo o Järfälla",
            "employees": 325,
            "annual_turnover": 31000000,
            "capital": 1000000,
            "key_personnel": {
                "name": "Bengt Rudén",
                "position": "Verkst dir"
            },
            "establishment_year": 1932
        },
        "6": {
            "company_name": "SCABA BLANDNINGSTEKNIK AB",
            "pnr": "182 51",
            "address": "Djursholm 1, Box 12. Bragev 30",
            "phone_number": "08-753 04 90",
            "activity": "Omrörare för alla förekommande uppgifter",
            "employees": 10,
            "annual_turnover": 1000000,
            "capital": 50000,
            "key_personnel": {
                "name": "Ulf Christierson",
                "position": "Verkst dir"
            },
            "establishment_year": 1970
        },
        "7": {
            "company_name": "TEGELKONTORET",
            "pnr": "501 02",
            "address": "Borås 1, Kungsg 50. Box 56",
            "phone_number": "033-1250 54, 1250 55",
            "activity": "Försäljningskontor för tegel",
            "key_personnel": {
                "name": "Dir Mats Johansson",
                "position": "Ägare o chef"
            },
            "establishment_year": 1952
        },
        "8": {
            "company_name": "PRI",
            "activity": "Tillverkar matbröd, kaffebröd o skorpor i parti",
            "employees": 50,
            "annual_turnover": 3700000,
            "capital": 200000,
            "key_personnel": [
                {
                    "name": "Thor Priem",
                    "position": "Verkst dir"
                },
                {
                    "name": "Sixten Nilsson",
                    "position": "Försäljn-chef"
                }
            ],
            "establishment_year": 1912
        },
        "9": {
            "company_name": "PR|ESTMAN INDUSTRI. DIESEL AB",
            "pnr": "195 01",
            "address": "Märsta 1, Fack. O Bang 3",
            "phone_number": "0760-11125",
            "activity": "Grävmaskiner, kranar, gripskopor, dredgers",
            "employees": 50,
            "annual_turnover": 10000000,
            "capital": 4000000,
            "key_personnel": {
                "name": "Lennart Anderson",
                "position": "Verkst dir"
            },
            "establishment_year": 1942
        },
        "10": {
            "company_name": "PRILLS MEKANISKA VERKSTAD, AB",
            "pnr": "603 63",
            "address": "Norrköping, Hammarg 67",
            "phone_number": "011-13 15 57",
            "activity": "Legotillverkning av maskindetaljer",
            "capital": 50000,
            "key_personnel": {
                "name": "Ing Aleksy Prill",
                "position": "Verkst dir"
            },
            "establishment_year": 1949
        },
        "11": {
            "company_name": "ERKÅS KONFEKTION, AB",
            "pnr": "50002",
            "address": "Borås 2, Box 22051. Alingsåsv 10",
            "phone_number": "033-11 83 39, 12 58 86",
            "activity": "Tillverkar skjortor o blusar",
            "employees": 60,
            "annual_turnover": 3700000,
            "capital": 15000,
            "key_personnel": {
                "name": "Karl Gustav Nilsson",
                "position": "Verkst din"
            },
            "establishment_year": 1955
        }
    }
}