{
    "original": "VELOUR-VERKEN I FINJAAB\n\nPnr 28015\n\nFinja. Tel 0451-160 72. Postgiro\n330831-9\n\nVerksamhet: Framställer\nvelourise-rat papper o kartong samt\nvelouri-serade förpackningsdetaljer m m.\nFlockförsäljning\nAntal anställda: 6\nÅrsomsättning: 250 000\nAktiekapital: 50000\nStyrelse: Fru Hedvig Nordborg\n(ordf), adv Claes Renée\nVerkst dir: Fru Hedvig Nordborg\nDisp: Thorbjörn Johansen\nEtableringsår: 1946.\n\nMÅRTENSSON, GOTTHARD\n\nPnr 264 00\n\nKlippan, Abyg 11. Box 23. Tel\n0435-102 33. Bankgiro 86-6784.\nPostgiro 172763\n\nVerksamhet: Säljer läder o gummi\ni parti\n\nÄgare o chef: Arne Mårtensson\nEtableringsår 1921.\n\nMÅRTENSSONS RUR &amp; MEK\nVERKSTADS AB, TH\n\nPnr 291 05\n\nKristianstad 5, Karlsg 22. Box\n5052. Tel 044-1159 40. Bankgiro\n65-8002. Postgiro 120490\nVerksamhet: Värme- o sanitära\ninstallationer\nAntal anstäUda: 35\nÅrsomsättning: 3 500 000\nAktiekapital: 10 000\nVerkst dir: Thage Mårtensson\nEtableringsår: 1958.\n\nMÅÅS-FJETTERSTRUM,\nMÄRTA, VERKSTADEN FUR\nSVENSKA MATTOR och\nVÄVNADER AB\n\nPnr 11128\n\nStockholm, Myntg 5. Tel\n08-201956\n\nVerksamhet: TiUverkar mattor o\nvävnader\n\nAntal anstäUda: 53\nAktiekapital: 202 000\nVerkst dir: Torsten Lundvall\nEtableringsår 1942.\n\nÄST\n\nIngeniörsfirman Asplunds\nFörsäljningsbolag, Stockholm. Se denna\nfirma.\n\nVarunamn: Feller, Fribourg, Huba,\nJucker, Moser-Glaser, Sace, Saia,\nSprecher &amp; Schuh, Zelisko\nChef: R Torbjörn Asplund\nEtableringsår: 1936.\n\nLAGERQVIST, AB A J\n\nPnr 401 25\n\nGöteborg 1, Lundby Hamng 14. Box\n314. Tel 031-23 2911. Bankgiro\n251-06 1 8. Postgiro 6782-7\nVerksamhet: Aggregat för\nskumplast o plastbeläggning.\nPlastråvaror\n\nVarunamn: Bibbithane, Tritorga\nAktiekapital: 255 000\nVerkst dir: Civiling Ingvar Nilsson\nEtableringsår: 1948.\n\nSVÄNGSTA MATTVÄVERI AB\n\nPnr 290 70\n\nSvängsta, Box 20. Tel 0454-225 60.\nTelex 4501 SMÅTT S. Tga\nSvängstamattan\n\nVerksamhet: Mattor\nAntal anställda: 180\nÅrsomsättning: 10000 000\nAktiekapital: 750 000\nVerkst dir: Lars-Ake Norlander\nEtableringsår: 1955.\n\nMELIN AB, E\n\nPnr 41121\n\nGöteborg, Stora Badhusg 18. Tel\n031-13 74 58, 13 74 34. Bankgiro\n511-5233. Postgiro 242077-6\nVerksamhet: Säljer kontorsmöbler,\nkontorsmaskiner samt inredningar\nav Lundqvists Snickeriers AB\ntillverkning\n\nAntal anstäUda: 7\nÅrsomsättning: 1850 000\nAktiekapital: 20 000\nVerkst dir: Ing L Melin\nEtableringsår: 1946\nOmbildat till aktiebolag 1963.\n\nMELINS AB, GUSTAF\n\nPnr 402 22\n\nGöteborg 5, Grafiska v. Box 5057.\nTel 031-400140. Postgiro 41207-2.\nTga Wezätamelins. Telex 20872\nVerksamhet: Marknadsför biblar o\npsalmböcker, presentartiklar,\nfotoalbum\n\nFörsäljningskontor: 13101 Nacka 1,\nRyssviksv 2. Fack. Tel 08-716 91 70\nVerkst dir: Jonas Forssman\nDisp: Karl-Erik Hjerling.\n\nMELIN &amp; CO, AB PEDER\n\nPnr 41109\n\nGöteborg, Lilla Nyg 2. Tel\n031-112312. Bankgiro 506-6675.\nPost-giro 12092-3. Tga Peder\nVerksamhet: Grosshandel med kött\no konserver\n\nÅrsomsättning: 2 000 000\nAktiekapital: 65 000\nEtableringsår: 1891.\n\n/VY&gt;\n\n\n\nMEL KA, AB\n\nPnr 405 03 Gbg\n\nMölndal, Göteborgsv 97. Tel\n031-27 22 60. TgaMelka.\nTelex 200 73 MELKA S\nVerksamhet: Tillverkar skjortor,\nrockar, sports o fritidskläder\nVerkst dir: Gunnar Dahlsten\nEtableringsår: 1944.\n\nMELKERHEDS MEK VERK.\nSTAD AB, BRUDERNA\n\nPnr 85243\n\nSundsvaU, Ostermov 35. Tel\n060-1133 74. Bankgiro 206-4053.\nPostgiro 643328-8\n\nVerksamhet: Legoarbeten,\nsvarvning, fräsning 8 o 10\" svarvar.\nServiceverkstad för Vadstena/Göta\nPump AB\nAntal anställda: 8\nAktiekapital: 10 000\nÄgare o chefer: S Melkerhed,\nB Melkerhed\nEtableringsår: 1964.\n\nSANDSJOFORS INDUSTRI AB\n\nPnr 570 20\n\nBodafors. Tel 0380-35150.\nBankgiro 837-8259. Postgiro 442750-6\nVerksamhet: Fabrikstillverkade\nbyggnader i volymelement\nAntal anställda: 50\nÅrsomsättning: 4 000 000\nAktiekapital: 60 000\nVerkst dir: Töre Patriksson\nEtableringsår: 1922.\n\nmataki, ab\n\nPnr 201 21\n\nMalmö 1, Box 185. Djäkneg 2. Tel\n040-730 00. Bankgiro 640-3828.\nPostgiro 14017-8. Tga Mataki.\nTelex 3119 MATAKI S\nVerksamhet: Fabriker för\ntillverkning av byggnadspapp av alla slag\nsamt kem tekn produkter i Malmö.\nVägmaterialfabriker i Malmö, Södra\nSandby, Åstorp, Huskvarna\nNorrköping, Åtvidaberg m fi platser.\nTillverkar bl a takpapp,\nbyggnadspapp, asfalt-, tjär- o\nplastprodukter, takkonserveringsmedel o\nträ,-skyddsmedel. Utför taktäckningar,\nisoleringar o vägarbeten. Bolaget\ndriver import o engroshandel med\nindustrikemikalier\nFörsäljningskontor: 416 60 Göteborg,\nSankt Paul ig 5. Tel 031-80 01 35\n171 04 Solna 4, Kristinelundsv 8 B.\nBox 472. Tel 08-83 42 70\nAntal anställda: 450\nÅrsomsättning: 71000 000\nAktiekapital: 4 000000\nStyrelse: Bankdir Claes Lindskog\n(ordf), dir Bjarne Colbjörnsen, dir\nFred Thomsen\nVerkst dir: Erik Möller\nV verkst dir Ekonomichef Erik\nHansson\n\nEtableringsår: 1904.\n\nmatell &amp; nordstrom\narkitektkontor\n\nPnr 753 30\n\nUppsala, Sal ag 29 A. Tel 018-\n\n14 90 55. Postgiro 540300-1\nVerksamhet: Konsulterande\narkitektrörelse. Totalprojektering\nAntal anstäUda: 28\nÅrsomsättning: 2 000 000\nChefer: Ark SAR Hans Mateli, ark\nSAR Anders Nordström\nEtableringsår: 1960.\n\nHALDENSFÄRGERI AB\n\nPnr 510 20\n\nFritsla. Tel 0320-702 80.\nBankgiro 53-1109. Postgiro 13468\nVerksamhet: Utför färgning,\nbril-lantblekning o appretering av\ngarner av ull, bomull o syntetfiber i\nsåväl hank som x-rullar o koner\nsamt vävnader o rundtrikå,\nfilmtryckeri\n\nAntal anställda: 110\nÅrsomsättning: 5 000 000\nAktiekapital: 400 000\nVetkst dir: Holger Åkerlund\nEtableringsår: 1850-talet\nOmbildat till aktiebolag 1946.\n\nHALDEX AB\n\nPnr 30104\n\nHalmstad 1, Knäredsg. Box 250.\nTel 035-11 85 60. Tga Haldex.\nTelex 38084\n\nVerksamhet: Tillverkar taxametrar,\nspeedpilots, trippmätare,\nfjädervågar, takometrar o trafikräknare\nAntal anställda: 225\nÅrsomsättning: 12500 000\nAktiekapital: 500 000\nVerkst din Lennart Borgström\nPlatschef: Dart Holmquist\nEtableringsår: 1887\nOmbildat 1920 o 1950.\nDotterföretag: Haldex-Stockholm AB,\nStockholm, Halda Ltd., London.\n\nHALI HÄNDELS- &amp;\nAGENTURFIRMA\n\nPnr 417 31\n\nGöteborg, Vädertjänstg 23. Tel\n031-5315 30\n\nVerksamhet: Agenturfirma.\nRepresentant för Holmberg &amp; Co,\nVäst-Berlin (dynamiska mikrofoner,\nkapslar, hörtalset mm), Magnetfabrik\nBonn, Bonn (alla slags\npermanent-magneter), Odenwälder\nKunststoff-werke, Buchen/Odenw (radio- o\nTV-rattar o detaljer). Bergmann &amp;\nHillebrand, Karlsruhe (radio- o\nTV-dekor, perforerade plåtar mm),\nG Moe limann KG, Velbert/Rhld\n(alla slags radio-, TV- o\nmöbelbeslag) samtliga firmor i Västtyskland\nVarunamn: Holme o\nÅrsomsättning: 2 500 000\nChef: Giovanni Morichetto\nEtableringsår. 1952.\n\nLINDBACKA AB\n\nPnr 70102\n\nÖrebro 1, Box 30. Tel 019-17 20 02.\nPostgiro 161661\n\nVerksamhet: Tillverkar formgjorda\ngummidetaljer i massiv o cellgummi\nAntal anställda: 16\nÅrsomsättning: 1 500 000\nAktiekapital: 80 000\nVerkst dir: Ragnar T:son Aqvist\nEtableringsår: 1938.",
    "structured": {
        "1": {
            "company_name": "VELOUR-VERKEN I FINJAAB",
            "pnr": "28015",
            "address": "Finja",
            "phone_number": "0451-160 72",
            "postgiro": "330831-9",
            "activity": "Framställer velourise-rat papper o kartong samt velouri-serade förpackningsdetaljer m m. Flockförsäljning",
            "employees": 6,
            "annual_turnover": 250000,
            "capital": 50000,
            "key_personnel": [
                {
                    "name": "Fru Hedvig Nordborg",
                    "position": "ordf"
                },
                {
                    "name": "adv Claes Renée",
                    "position": "unknown"
                },
                {
                    "name": "Fru Hedvig Nordborg",
                    "position": "Verkst dir"
                },
                {
                    "name": "Thorbjörn Johansen",
                    "position": "Disp"
                }
            ],
            "establishment_year": 1946
        },
        "2": {
            "company_name": "MÅRTENSSON, GOTTHARD",
            "pnr": "264 00",
            "address": "Klippan, Abyg 11. Box 23",
            "phone_number": "0435-102 33",
            "bankgiro": "86-6784",
            "postgiro": "172763",
            "activity": "Säljer läder o gummi i parti",
            "establishment_year": 1921
        },
        "3": {
            "company_name": "MÅRTENSSONS RUR & MEK VERKSTADS AB, TH",
            "pnr": "291 05",
            "address": "Kristianstad 5, Karlsg 22. Box 5052",
            "phone_number": "044-1159 40",
            "bankgiro": "65-8002",
            "postgiro": "120490",
            "activity": "Värme- o sanitära installationer",
            "employees": 35,
            "annual_turnover": 3500000,
            "capital": 10000,
            "key_personnel": [
                {
                    "name": "Thage Mårtensson",
                    "position": "Verkst dir"
                }
            ],
            "establishment_year": 1958
        },
        "4": {
            "company_name": "MÅÅS-FJETTERSTRUM, MÄRTA, VERKSTADEN FUR SVENSKA MATTOR och VÄVNADER AB",
            "pnr": "11128",
            "address": "Stockholm, Myntg 5",
            "phone_number": "08-201956",
            "activity": "TiUverkar mattor o vävnader",
            "employees": 53,
            "capital": 202000,
            "key_personnel": [
                {
                    "name": "Torsten Lundvall",
                    "position": "Verkst dir"
                }
            ],
            "establishment_year": 1942
        },
        "5": {
            "company_name": "ÄST",
            "pnr": "unknown",
            "activity": "unknown",
            "establishment_year": 1936
        },
        "6": {
            "company_name": "LAGERQVIST, AB A J",
            "pnr": "401 25",
            "address": "Göteborg 1, Lundby Hamng 14. Box 314",
            "phone_number": "031-23 2911",
            "bankgiro": "251-06 1 8",
            "postgiro": "6782-7",
            "activity": "Aggregat för skumplast o plastbeläggning. Plastråvaror",
            "employees": 0,
            "capital": 255000,
            "key_personnel": [
                {
                    "name": "Civiling Ingvar Nilsson",
                    "position": "Verkst dir"
                }
            ],
            "establishment_year": 1948
        },
        "7": {
            "company_name": "SVÄNGSTA MATTVÄVERI AB",
            "pnr": "290 70",
            "address": "Svängsta, Box 20",
            "phone_number": "0454-225 60",
            "telex": "4501 SMÅTT S. Tga Svängstamattan",
            "activity": "Mattor",
            "employees": 180,
            "annual_turnover": 10000000,
            "capital": 750000,
            "key_personnel": [
                {
                    "name": "Lars-Ake Norlander",
                    "position": "Verkst dir"
                }
            ],
            "establishment_year": 1955
        },
        "8": {
            "company_name": "MELIN AB, E",
            "pnr": "41121",
            "address": "Göteborg, Stora Badhusg 18",
            "phone_number": "031-13 74 58, 13 74 34",
            "bankgiro": "511-5233",
            "postgiro": "242077-6",
            "activity": "Säljer kontorsmöbler, kontorsmaskiner samt inredningar av Lundqvists Snickeriers AB tillverkning",
            "employees": 7,
            "annual_turnover": 1850000,
            "capital": 20000,
            "key_personnel": [
                {
                    "name": "Ing L Melin",
                    "position": "Verkst dir"
                }
            ],
            "establishment_year": 1946
        },
        "9": {
            "company_name": "MELINS AB, GUSTAF",
            "pnr": "402 22",
            "address": "Göteborg 5, Grafiska v. Box 5057",
            "phone_number": "031-400140",
            "postgiro": "41207-2",
            "telex": "20872 (Tga Wezätamelins)",
            "activity": "Marknadsför biblar o psalmböcker, presentartiklar, fotoalbum",
            "establishment_year": "unknown"
        },
        "10": {
            "company_name": "MELIN & CO, AB PEDER",
            "pnr": "41109",
            "address": "Göteborg, Lilla Nyg 2",
            "phone_number": "031-112312",
            "bankgiro": "506-6675",
            "postgiro": "12092-3",
            "activity": "Grosshandel med kött o konserver",
            "annual_turnover": 2000000,
            "capital": 65000,
            "establishment_year": 1891
        },
        "11": {
            "company_name": "MEL KA, AB",
            "pnr": "405 03 Gbg",
            "address": "Mölndal, Göteborgsv 97",
            "phone_number": "031-27 22 60",
            "activity": "Tillverkar skjortor, rockar, sports o fritidskläder",
            "key_personnel": [
                {
                    "name": "Gunnar Dahlsten",
                    "position": "Verkst dir"
                }
            ],
            "establishment_year": 1944
        },
        "12": {
            "company_name": "MELKERHEDS MEK VERK. STAD AB, BRUDERNA",
            "pnr": "85243",
            "address": "SundsvaU, Ostermov 35",
            "phone_number": "060-1133 74",
            "bankgiro": "206-4053",
            "postgiro": "643328-8",
            "activity": "Legoarbeten, svarvning, fräsning 8 o 10\" svarvar. Serviceverkstad för Vadstena/Göta Pump AB",
            "employees": 8,
            "capital": 10000,
            "key_personnel": [
                {
                    "name": "S Melkerhed",
                    "position": "unknown"
                },
                {
                    "name": "B Melkerhed",
                    "position": "unknown"
                }
            ],
            "establishment_year": 1964
        },
        "13": {
            "company_name": "SANDSJOFORS INDUSTRI AB",
            "pnr": "570 20",
            "address": "Bodafors",
            "phone_number": "0380-35150",
            "bankgiro": "837-8259",
            "postgiro": "442750-6",
            "activity": "Fabrikstillverkade byggnader i volymelement",
            "employees": 50,
            "annual_turnover": 4000000,
            "capital": 60000,
            "key_personnel": [
                {
                    "name": "Töre Patriksson",
                    "position": "Verkst dir"
                }
            ],
            "establishment_year": 1922
        },
        "14": {
            "company_name": "mataki, ab",
            "pnr": "201 21",
            "address": "Malmö 1, Box 185. Djäkneg 2",
            "phone_number": "040-730 00",
            "bankgiro": "640-3828",
            "postgiro": "14017-8",
            "activity": "Fabriker för tillverkning av byggnadspapp av alla slag samt kem tekn produkter i Malmö. Vägmaterialfabriker i Malmö, Södra Sandby, Åstorp, Huskvarna Norrköping, Åtvidaberg m fi platser. Tillverkar bl a takpapp, byggnadspapp, asfalt-, tjär- o plastprodukter, takkonserveringsmedel o trä,-skyddsmedel. Utför taktäckningar, isoleringar o vägarbeten. Bolaget driver import o engroshandel med industrikemikalier",
            "employees": 450,
            "annual_turnover": 71000000,
            "capital": 4000000,
            "key_personnel": [
                {
                    "name": "Erik Möller",
                    "position": "V verkst dir Ekonomichef"
                }
            ],
            "establishment_year": 1904
        },
        "15": {
            "company_name": "matell & nordstrom arkitektkontor",
            "pnr": "753 30",
            "address": "Uppsala, Sal ag 29 A",
            "phone_number": "018-14 90 55",
            "postgiro": "540300-1",
            "activity": "Konsulterande arkitektrörelse. Totalprojektering",
            "employees": 28,
            "annual_turnover": 2000000,
            "key_personnel": [
                {
                    "name": "Ark SAR Hans Mateli",
                    "position": "unknown"
                },
                {
                    "name": "ark SAR Anders Nordström",
                    "position": "unknown"
                }
            ],
            "establishment_year": 1960
        },
        "16": {
            "company_name": "HALDENSFÄRGERI AB",
            "pnr": "510 20",
            "address": "Fritsla",
            "phone_number": "0320-702 80",
            "bankgiro": "53-1109",
            "postgiro": "13468",
            "activity": "Utför färgning,bril-lantblekning o appretering av garner av ull, bomull o syntetfiber i såväl hank som x-rullar o koner samt vävnader o rundtrikå, filmtryckeri",
            "employees": 110,
            "annual_turnover": 5000000,
            "capital": 400000,
            "key_personnel": [
                {
                    "name": "Holger Åkerlund",
                    "position": "Vetkst dir"
                }
            ],
            "establishment_year": "1850-talet"
        },
        "17": {
            "company_name": "HALDEX AB",
            "pnr": "30104",
            "address": "Halmstad 1, Knäredsg. Box 250",
            "phone_number": "035-11 85 60",
            "telex": "38084",
            "activity": "Tillverkar taxametrar, speedpilots, trippmätare, fjädervågar, takometrar o trafikräknare",
            "employees": 225,
            "annual_turnover": 12500000,
            "capital": 500000,
            "key_personnel": [
                {
                    "name": "Lennart Borgström",
                    "position": "Verkst din"
                },
                {
                    "name": "Dart Holmquist",
                    "position": "Platschef"
                }
            ],
            "establishment_year": 1887
        },
        "18": {
            "company_name": "HALI HÄNDELS- & AGENTURFIRMA",
            "pnr": "417 31",
            "address": "Göteborg, Vädertjänstg 23",
            "phone_number": "031-5315 30",
            "activity": "Agenturfirma. Representant för Holmberg & Co, Väst-Berlin (dynamiska mikrofoner, kapslar, hörtalset mm), Magnetfabrik Bonn, Bonn (alla slags permanent-magneter), Odenwälder Kunststoff-werke, Buchen/Odenw (radio- o TV-rattar o detaljer). Bergmann & Hillebrand, Karlsruhe (radio- o TV-dekor, perforerade plåtar mm), G Moe limann KG, Velbert/Rhld (alla slags radio-, TV- o möbelbeslag) samtliga firmor i Västtyskland",
            "activity_swedish": "Agenturfirma. Representant för Holmberg & Co, Väst-Berlin (dynamiska mikrofoner, kapslar, hörtalset mm), Magnetfabrik Bonn, Bonn (alla slags permanent-magneter), Odenwälder Kunststoff-werke, Buchen/Odenw (radio- o TV-rattar o detaljer). Bergmann & Hillebrand, Karlsruhe (radio- o TV-dekor, perforerade plåtar mm), G Moe limann KG, Velbert/Rhld (alla slags radio-, TV- o möbelbeslag) samtliga firmor i Västtyskland",
            "annual_turnover": 2500000,
            "key_personnel": [
                {
                    "name": "Giovanni Morichetto",
                    "position": "Chef"
                }
            ],
            "establishment_year": 1952
        },
        "19": {
            "company_name": "LINDBACKA AB",
            "pnr": "70102",
            "address": "Örebro 1, Box 30",
            "phone_number": "019-17 20 02",
            "postgiro": "161661",
            "activity": "Tillverkar formgjorda gummidetaljer i massiv o cellgummi",
            "employees": 16,
            "annual_turnover": 1500000,
            "capital": 80000,
            "key_personnel": [
                {
                    "name": "Ragnar T:son Aqvist",
                    "position": "Verkst dir"
                }
            ],
            "establishment_year": 1938
        }
    }
}