{
    "original": "WÄNGEL AB, G A\n\nPnr 212 16\n\nMalmö O, O Farmv 18. Tel\n040-93 6105. Bankgiro 640-3984.\nPostgiro 37602-0. Tga Gawe\nVerksamhet: Färgeri för trikåväv,\ngarn o strumpor. Kem tvätt\nAktiekapital: 50 000\nVerkst dir: Civilekonom R Jarby\nEtableringsår: 1904.\n\nWANGSON INGENJORSBYRÅ\nAB, VANG\n\nPnr 701 03\n\nÖrebro 1, Västra g 8. Box 99. Tel\n019-1197 75. Bankgiro 281-7864.\nPostgiro 372357-4\n\nVerksamhet: Teknisk konsult inom\nvärme, ventilation o sanitet\nAvdelningskontor. 542 00 Mariestad,\nKyrkog 4. Tel 0501-135 01\nAntal anställda: 25\nAktiekapital: 90 000\nVerkst dir: Ing Vang Wangson\nEtableringsår: 1950.\n\nVANSBRO PARTI- &amp;\nAGENTURAFFÄR\n\nPnr 780 50\n\nVansbro, Box 33. Tel 0281-100 86,\n10211. Bankgiro 79-8937. Postgiro\n7678\n\nVerksamhet: Tillverkar o\nensam-försäljer Sjuls o Toppsy\nskurapparater, käppar, moppar, rullar o stativ\nVarunamn: Sjuls, Toppsy\nAntal anställda: 12\nChef: Fru Henny Westman\nEtableringsår: 1923.\n\nHDI\n\nVerkst dlr: Carl Höglund\nEtableringsàr: 1865\nOmbildat till aktiebolag 1944.\n\nHUG BÖDA INDUSTRIER AB\n\nPnr 660 81\n\nHögboda. Box 4. Tel 0554-200 72,\n200 81. Postgiro 283070-1\nVeiksamhet: Tillverkar sågade o\nhyvlade trävaror\nFörsäljningskontor. Töcksfors.\nTel 0573-212 80\n\nSågverk: Billingsfors. Tel\n0533-500 40\n\nAntal anställda: 60\nÅrsomsättning: 12 000 000\nAktiekapital: 300 000\nVeikst dir: Nils Anderson\nEtableringsàr: 1953.\n\nHOGDAHLS GLASMASTER I. &amp;\nRAMAFFÄR AB, C\n\nPnr 93100\n\nSkellefteå, Skepparg 10 A. Tel\n0910-109 23, 102 63\nVerksamhet: Fullständigt\nglasmäs-teri, alla slags bilrutor,\nsäkerhetsglas för förarhytter, vilkatillverkas\nav Bröderna Lundbergs AB,\nglas-sliperi, glas i parti o minut\nFabrik: Skellefteå, Högströmsg 12.\nTel 0910-109 23\n\nVerkst dir: Carl Alfred Högdahl\nEtableringsàr: 1934.\n\nHOGFORS AKTIEBOLAG\n\nPnr 113 24\n\nStockholm, Dalag 34. Tel\n08-32 10 20, 32 12 12. Bankgiro\n231-2718. Postgiro 83230-3.\nTgaHöeg-forsab. Telex 10327 HOGFORS S\nVerksamhet: Tillverkar sågade o\nhyvlade trävaror samt\nskogsprodukter\n\nFabrik: Silverhöjden. Silverhöjdens\nSågverk. Tel 0240-622 00\nAntal anställda: 130\nÅrsomsättning: 11500 000\nAktiekapital: 400 000\nStyrelse: Bankdir Ture Bergman,\ndisp Olof Hedin, förvaltare Assar\nAronsson\n\nVerkst dir: Olof Hedin\nEtableringsàr: 1897.\n\nHOGFORSBRUKSNYA\nGJUTERI AB\n\nPnr 710 73\n\nHögforsbmk. Tel 0580-22135.\nPostgiro 676333-8\nVeiksamhet: Tackjärnsgjuteri i\nHögforsbruk. Tillverkar\nstålverks-kokiller o grovt handformat gods\nmed stycke vikter upp till 15 ton\nVarunamn: HF\nAntal anställda: 20\nAktiekapital: 100 000\nStyrelse: Adv Hans-Erik Mattsson,\ndlr Bertil Gustafsson, disp John\nAxel Franzén\n\nVerkst din Bertil Gustafsson\nPlatschef: Gustav Engström\nFöretaget administreras av\nAsker-sundsverken AB, Askersund, (se\ndetta bolag).\n\nHÖGLUNDS INDUSTRIER\n\nPnr 661 00\n\nSäffle, Brov 1. Värmlandsbro. Tel\n\n0533-400 02, 400 10. Bankgiro\n115-0630. Postgiro 342693-9\nVerksamhet: Tillverkar o säljer\nlastbilsflak, kranar, karosserier\nVarunamn: Höglunds Flak\nAntal anställda: 14\nÅrsomsättning: 1 300 000\nÄgare o chefen Fabr Törd\nHöglund, fabr Gustaf KvaldSn\nEtableringsàr: 1950.\n\nHÖGLUNDS METALLAFFÄR,\nAB ADOLF\n\nPnr 95101\n\nLuleå 1, Box 64. Tel 09 20-28 2 20.\nBankgiro 36-9610. Postgiro\n67193-3-Tga Metallhöglund\nVerksamhet: Köper o säljer alla\nslag av stål o metallskrot,\nindustri- o avfallsråvaror. Lagerför\nstångmaterial, plåt, räls, tråd etc\nAntal anställda: 30\nÅrsomsättning: 7 000 000\nAktiekapital: 200 000\nVerkst dir: Adolf Höglund\nEtableringsàr 1925\nOmbildat till aktiebolag 1946.\n\nHÖGLUND, BYGGNADS AB\nMANFRED\n\nPnr 80102\n\nGävle 1, Strömsbrov 20, Box 39.\nTel 026-12 97 20. Bankgiro 78-3916.\nPostgiro 511454\n\nVerksamhet: Uppför husbyggnader\nAntal anställda: 250\nÅrsomsättning: 25 000 000\nAktiekapital: 300 000\nVeikst dir. Byggmäst Manfred\nHöglund\n\nEtableringsàr: 1959.\n\nHOGSHULTS\nMETALL-FABRIK AB\n\nPnr 330 31\n\nKulltorp. Tel 0370-820 34.\nPostgiro 277030-3\n\nVerksamhet: Tillverkar\nbyggnadsbeslag i metall, specialitet:\ndörrtrycken o skyltar jämte övriga\nmassartiklar\nAktiekapital: 20 000\nVerkst dir: Fabr Harry Johansson\nEtableringsàr 1961.\n\nHÖGLUND INGENJORSBYRÅ\nAB, B E\n\nPnr 89100\n\nÖrnsköldsvik, Storg 16. Tel\n0660-177 55. Bankgiro 307-4267.\nPostgiro 596930-8\n\nVerksamhet Konsulterande\ningenjörer inom byggfacket\nFilialer. 85235 Sundsvall. Erik\nHöglund Ingenjörsbyrå AB, Nybrog\n29. Tel 060-15 90 67\n802 23 Gävle. B E Höglund &amp; Co\nIngenjörsbyrå AB, Karlav 4. Tel\n026-18 0178\nAntal anställda: 21\nÅrsomsättning: 1100 000\nAktiekapital: 35 000\nVerkst dir Ing Erik Höglund\nEtableringsàr: 1961.\n\nHÖGLUND &amp; CO, KAROSSERI\nAB H\n\nPnr 66100\n\nSäffle, Amålsv. Box 59. Tel\n0533-125 80. Bankgiro 114-9160.\nPostgiro 136278-9\n\nVerksamhet: Tillverkar\nomnibus-karosserier av lättmetall\nAntal anställda: 85\nÅrsomsättning: 6 500 000\nAktiekapital: 150 000\nVerkst dir: Bo Johansson\nEtableringsàr 1914.\n\nTREBEC, AB\n\nPnr 102 45\n\nStockholm 5, Box 5208, Florag 2.\nTel 08-23 69 50. Bankgiro 700-2793.\nPostgiro 352777-7. Tga Trebecab.\nTelex 19166\n\nVeiksamhet: Säljer kem produkter\nAntal anställda: 9\nÅrsomsättning: 26000 000\nAktiekapital: 1080 000\nVerkst din Torsten Lilja\nEtableringsår: 1937.\n\nTREGE, GULDSMEDS.\nAKTIEBOLAGET\n\nPnr 411 15\n\nGöteborg C, Kyrkog 25. Tel\n031-13 7415, 113365. Bankgiro\n42-0190. Postgiro 44882\nVerksamhet: Grosshandel med\nserviceverkstad\nAntal anställda: 8\nAktiekapital: 150 000\nVerkst dir: Agne Alexanderson\nEtableringsår: 1933\nOmbildat till aktiebolag 1960.\n\nTRELLEBORGS GUMMI.\nFABRIKS AB\n\nPnr 23101\n\nTrelleborg 1, Nyg 102. Fack. Tel\n0410-150 00. Bankgiro 665-9023.\nPostgiro 20700-1. Tga\nTrelleborggummi. Telex 32950 TRELLE S\nVerksamhet: Tillverkar\nindustrigummi (slang, formgods,\ntransportband, kilrem o andra tekniska\ngummiartiklar), däck o slangar\nBetr plast (inkl byggprodukter) se\nAB Trelleborgplast\nBetr försäljningsbolag se Svenskt\nInköpsregister under rubrik\nGummi-o kautschukvaror\nAntal anställda: 6 700\nÅrsomsättning: 501100 000\nVerkst dir o koncernchef: Ake\nStåhlbrandt\n\nV verkst dir:r: Einar Mörck, Jan\nErik Leander\nEtableringsår: 1905\nTrelleborgs Gummifabriks AB\nsamarbetar sedan 1965 under gemensam\nkoncernledning med Helsingborgs\nGummifabriks AB Tretorn.\n\nTRELLEBORGS MEKANISKA\nVERKSTADS AB\n\nPnr 231 00\n\nTrelleborg, Bryggareg 9-11. Tel\n0410-15180. Bankgiro 237-6614.\nPostgiro 432751-6\nVerksamhet: Tillverkar\nvärmepannor. Mekanisk verkstad\nVarunamn: TMV-Pannan\nAntal anställda: 50\nÅrsomsättning: 4 000 000\nVerkst dir: Ing Stig Möller\nEtableringsår: 1953.\n\nSKENINGE BOKTRYCKERI AB\n\nPnr 596 00\n\nSkänninge, Box 60. Tel\n0142-40174. Bankgiro 130-0334.\nPostgiro 25077-9\n\nVerksamhet: Tryckning av\nbroschyrer, blanketter, reklamtryck o böcker\nAntal anställda: 8\nAktiekapital: 6000\nEtableringsår: 1920.\n\nSKEPPS- och\nFISKERI-TILLBEHOR, AB\n\nPnr 40076\n\nGöteborg 44, Box 44 004. Tel\n031-5120 45. Bankgiro 500-1201.\nPostgiro 420014-3\n\nVerksamhet: Skepps- o\nfiskeriut-rustning\n\nVerkst dir: Olof V Lundgren\nEtableringsår: 1949.\n\nPRIMO, TRYCKERI AB\n\nPnr 57201\n\nOskarshamn 1, Box 12. Slottsg 5.\nTel 0491-14260. Bankgiro\n856-5608. Postgiro 12780-3\nVerksamhet: Tidskrifter,\nbroschyrer, kataloger o blanketter.\nSpecialitet: blankettryck\nFörsäljningskontor: Stockholm 1,\nVästmannag 1. Tel 08-219400\nMalmö 23, Box 23056. Tel\n040-94 83 00\n\nAntal anställda: 55\nÅrsomsättning: 6 000 000\nAktiekapital: 5 000\nVerkst dir: Disp Nils Lundström\nEtableringsår: 1958.\n\nPRIMULATOR AB\n\nse Mustad AB, J.\n\nPRIMUS SVENSKA FURSÄLJ.\nNINGS AB\n\nPnr 127 20\n\nSkärholmen 1, Fack. Storsätragränd\n4. Tel 08-462680. Bankgiro\n711-8805. Postgiro 831100-3. Tga\nSwe-prim. Telex 1135\n\nVerksamhet: Marknadsför\nbiltillbehör o fritidsartiklar\nAntal anställda: 75\nÅrsomsättning: 80 000 000\nAktiekapital: 100 000\nEtableringsår: 1968.\n\nTEK\n\nTEGS ELEKTRISKA AB\n\nPnr 90104\n\nUmeå 1, Box 316. Tel 090-12 23 40.\nBankgiro 400-4495. Postgiro\n296804-8\n\nVerksamhet Utför elektr\ninstalla-tioner av alla slag.\nButiksförsäljning av till branschen hörande varor\nAntal anställda: 20\nÅrsomsättning: 2 000 000\nInstallatör: Arne Bergqvist\nEtableringsår: 1947.\n\nTEGELBRUKENS FÖRSÄLJ.\nNINGS AB\n\nPnr 103 84\n\nStockholm 7, Norrlandsg 11. Box\n7206. Tel 08-23 31 15. Bankgiro\n576-8924. Postgiro 4677-1\nVerksamhet: Säljer alla slags\ntegelvaror\n\nAntal anställda: 12\nÅrsomsättning: 11000 000\nAktiekapital: 300 000\nVerkst dir. Jan-Erik Rittner\nEtableringsår: 1928.\n\nTEGELCENTRALEN I\nSKÅNE, AB\n\nPnr 200 10\n\nMalmö 17, Persens v 16. Box\n17118. Tel 040-734 20. Bankgiro\n644-9029. Postgiro 430612-2\nVerksamhet: Säljer tegelvaror\nAvdelningskontor: Göteborg.\nTol-torpsg 137, pa Mölndal. Box 14007,\nGbg 14. Tel 031-27 2140\nJönköping, V Storg 21. Tel\n036-16 50 75\n\nAntal anställda: 25\nÅrsomsättning: 32000 000\nAktiekapital: 300 000\nVeikst din Knut Wråke\nEtableringsår: 1955.\n\nSVENSKA PRESSBYRÅN, AB\n\nPnr 104 25\n\nStockholm 30, Strandbergsg 61.\nFack. Tel 08-54 00 60. Bankgiro\n561-1116. Postgiro 95-0. Tga\nPressbyrån. Telex 1860\nVerksamhet: Pressdistribution,\nkioskhandel\nAntal anställda: 6 157\nÅrsomsättning: 1088 770 000\nAktiekapital: 10 000 000\nVerkst dir: Kjell-Otto Jacobson\nEtableringsår: 1905.\n\nFAMORIT I MALMÖ AB\n\nPnr 240 17\n\nSödra Sandby, Box 55. Tel\n046-519 19\n\nVerksamhet: Utför\ngolvbeläggningar i massa, mosaik, betong,\nplastbetong o epoxi\nAntal anställda: 14\nAktiekapital: 5 000\nVerkst dir: Ragnar Hamilton\nEtableringsår: 1963.\n\nCONTROL DATA SWEDEN AB\n\nPnr 12612\n\nStockholm 42, Box 42107.\nVästberga Allé 5, Hägersten. Tel\n08-84 02 00\n\nVerksamhet: Försäljning o\nuthyrning av datorer o försäljning av\ndatatjänster samt därmed\nsammanhängande verksamhet\nVarunamn: Control Data\nAntal anställda: 90\nÅrsomsättning: 12 000 000\nAktiekapital: 1000 000\nVerkst dir: Rune Casemyr\nEtableringsår: 1963.\n\nEXAKTO\n\nPnr 190 40\n\nRosersberg, Nyborgsv 10. Tel\n0760-355 30. Bankgiro 748-0528.\nPostgiro 660085-2\n\nVerksamhet: Tillverkar paneler,\nchassier, instrumentlådor.\nLegotillverkning av tunnplåtsarbeten\ninom elektronikområdet\nÅrsomsättning: 155000\nChef: Kenneth Jansson\nEtableringsår: 1964.",
    "structured": {
        "1": {
            "company_name": "WÄNGEL AB",
            "activity": "Färgeri för trikåväv, garn o strumpor. Kem tvätt",
            "establishment_year": 1904,
            "capital": 50000,
            "key_personnel": [
                {
                    "name": "R Jarby",
                    "position": "Verkst dir (Verkställande direktör)"
                }
            ]
        },
        "2": {
            "company_name": "WANGSON INGENJORSBYRÅ AB",
            "activity": "Teknisk konsult inom värme, ventilation o sanitet",
            "establishment_year": 1950,
            "capital": 90000,
            "key_personnel": [
                {
                    "name": "Ing Vang Wangson",
                    "position": "Verkst dir (Verkställande direktör)"
                }
            ]
        },
        "3": {
            "company_name": "VANSBRO PARTI- & AGENTURAFFÄR",
            "activity": "Tillverkar o ensam-försäljer Sjuls o Toppsy skurapparater, käppar, moppar, rullar o stativ",
            "establishment_year": 1923,
            "employees": 12,
            "key_personnel": [
                {
                    "name": "Fru Henny Westman",
                    "position": "Chef"
                }
            ]
        },
        "4": {
            "company_name": "HDI",
            "key_personnel": [
                {
                    "name": "Carl Höglund",
                    "position": "Verkst dlr (Verkställande direktör)"
                }
            ],
            "establishment_year": 1865,
            "note": "Ombildat till aktiebolag 1944."
        },
        "5": {
            "company_name": "HUG BÖDA INDUSTRIER AB",
            "activity": "Tillverkar sågade o hyvlade trävaror",
            "establishment_year": 1953,
            "employees": 60,
            "annual_turnover": 12000000,
            "capital": 300000,
            "key_personnel": [
                {
                    "name": "Nils Anderson",
                    "position": "Veikst dir (Verkställande direktör)"
                }
            ]
        },
        "6": {
            "company_name": "HOGDAHLS GLASMASTER I & RAMAFFÄR AB",
            "activity": "Fullständigt glasmästeri, alla slags bilrutor, säkerhetsglas för förarhytter, vilka tillverkas av Bröderna Lundbergs AB",
            "establishment_year": 1934,
            "key_personnel": [
                {
                    "name": "Carl Alfred Högdahl",
                    "position": "Verkst dir (Verkställande direktör)"
                }
            ]
        },
        "7": {
            "company_name": "HOGFORS AKTIEBOLAG",
            "activity": "Tillverkar sågade o hyvlade trävaror samt skogsprodukter",
            "establishment_year": 1897,
            "employees": 130,
            "annual_turnover": 11500000,
            "capital": 400000,
            "key_personnel": [
                {
                    "name": "Olof Hedin",
                    "position": "Verkst dir (Verkställande direktör)"
                }
            ]
        },
        "8": {
            "company_name": "HOGFORSBRUKSNYA GJUTERI AB",
            "activity": "Tackjärnsgjuteri i Högforsbruk. Tillverkar stålverkskokiller o grovt handformat gods med stycke vikter upp till 15 ton",
            "establishment_year": null,
            "employees": 20,
            "capital": 100000,
            "key_personnel": [
                {
                    "name": "Bertil Gustafsson",
                    "position": "Verkst din (Verkställande direktör)"
                }
            ],
            "note": "Företaget administreras av Askersundsverken AB, Askersund, (se detta bolag)"
        },
        "9": {
            "company_name": "HÖGLUNDS INDUSTRIER",
            "activity": "Tillverkar o säljer lastbilsflak, kranar, karosserier",
            "establishment_year": 1950,
            "employees": 14,
            "annual_turnover": 1300000,
            "note": "Ägare o chefen Fabr Törd Höglund, fabr Gustaf KvaldSn"
        },
        "10": {
            "company_name": "HÖGLUNDS METALLAFFÄR AB ADOLF",
            "activity": "Köper o säljer alla slag av stål o metallskrot, industri- o avfallsråvaror. Lagerför stångmaterial, plåt, räls, tråd etc",
            "establishment_year": 1925,
            "employees": 30,
            "annual_turnover": 7000000,
            "capital": 200000,
            "key_personnel": [
                {
                    "name": "Adolf Höglund",
                    "position": "Verkst dir (Verkställande direktör)"
                }
            ],
            "note": "Ombildat till aktiebolag 1946"
        }
    }
}