{
    "original": "LAMELLGOLV AB\n\nPnr 11135\n\nStockholm, Kungsg 18. Tel\n08-23 34 65\n\nVerksamhet:\nGolvbeläggningsmaterial, plastgolvplattor, träfönster\nAktiekapital: 350 000\nVerkst dir: Gösta Kahr\nEtableringsår: 1942.\n\nBENNYSSONS SNICKERIER AB\n\nPnr 603 63\n\nNorrköping, Hammarg 58. Tel\n011-1349 00. Postgiro 413026\nVerksamhet: Tillverkar o säljer\nalla slags byggnadssnickerier\nÄgare: K A Bennysson\nEtableringsår: 1954.\n\nESKIL, SMIDESFABRIKEN\n\nPnr 630 05\n\nEskilstuna 5, Box 5048.\nFörsäljning o inköp Björkhagsv 20,\nSundbyberg. Tel 08-28 38 95. Postgiro\n140587\n\nVarunamn: Eskil\n\nChef o firmatecknare: Ing Hubert\n\nAndréen\n\nEtableringsår: 1931.\n\nKJELLSTROM, AB BRÖDERNA\n\nPnr 10401\n\nStockholm 60, Fack. Tel\n08-27 27 05. Bankgiro 446-9052.\nPostgiro 73134-9. Tga Silva\nVerksamhet: Tillverkar marin-,\nflyg- o orienteringskompasser,\nformpressade fanérprodukter såsom\nbrickor, möbeldetaljer,\nbandyklubbor o skosulor. Slöjdprodukter av\nteak m m. Skidbindningar o\nplastprodukter\nVarunamn: Silva\nAktiekapital: 180 000\nVerkst dir: Alvar Kjellström\nEtableringsår: 1934.\n\nKJELLSTROMS FOTO &amp;\nREPRO AB\n\nPnr 416 64\n\nGöteborg, N Agatan 10,\nHantverkshuset Stampen. Tel 031-801900.\nBankgiro 107-7106. Postgiro\n44287-1\n\nLJUSKOPIERING\n\nMETEBFØRSTORING AR\n\nARKIVFOTOGRAFERING\n\nDIA\n\nOFFSETTRYCK\nIBM-SÄTTNING\nOFFSETPLATAR\nBOKBINDERI\nDISTRIBUTION och\nADRESS-SERVICE\n\nAntal anställda: 30\nAktiekapital: 50 000\nVerkst dir: Leif Attenfelt\nEtableringsår: 1932\nOmbildat till aktiebolag 1946.\n\nKJÄLLSTROMS MEK\nVERKSTAD AB\n\nPnr 530 20\n\nKvänum. Tel 0512-924 00.\nBankgiro 22-0020. Postgiro 71495. Tga\nKjällve\n\nVerksamhet: Tillverkar o säljer\ntransportörer för lantbruk\nAntal anställda: 130\nÅrsomsättning: 12 000 000\nAktiekapital: 600 000\nVerkst dir: Stig Kjällström\nEtableringsår: 1890.\n\nURANIA, HÄNDELS-AB\n\nPnr 114 34\n\nStockholm, Smålandsg 2. Tel\n08-23 06 80. Bankgiro 731-6581.\nPostgiro 57595-1\n\nVerksamhet: Urmakeriartiklar\nengros\n\nAntal anställda: 22\nAktiekapital: 50 000\nVerkst din Gerald Nagler\nEtableringsån 1936.\n\nURSVIKENS MEKANISKA\nVERKSTADS AB\n\nPnr 930 30\n\nUrsviken, Pack. Tel 0910-308 10.\nBankgiro 37-0804. Postgiro\n61602-9. Tga Verkstaden,\nSkellefteå. Telex 6883\nVerksamhet: Tillverkar hydrauliska\ngradsaxar, kantpressar,\nenpelar-pressar, verkstadspressar o\nskepps-byggnadspressar\nAntal anställda: 150\nÅrsomsättning: 12 500 000\nAktiekapital: 1200 000\nVerkst dir: Verner Eriksson\nKamrer: Elmer Lindmark\nVerkstadschef: Per Persson\nKonstr-chef: Egon Eriksson\nEtableringsår: 1885.\n\nOSTLUNDS BYGGNADS AB\n\nPnr 113 47\n\nStockholm, Ynglingag 18. Tel\n08-34 9190. Bankgiro 576-2276.\nPostgiro 256813-7. Tga öbalag\nVerksamhet: Byggnadsrörelse för\nIndustri- o bostadshus\nAntal anställda: 90\nÅrsomsättning: 12 000 000\nAktiekapital: 480 000\nStyrelse: Dir O G Olsson (ordf),\ndir Kurt Sandberg, fru A-L\nWester-dahl, ing R Bergholm\nVerkst dir: Byggnadsing Rolf\nBergholm\n\nEtableringsår: 1944.\n\nTVÄRÅNS SÄG AB\n\nPnr 970 20\n\nKoskullskulle, Box 7. Tel 0970-\n\n302 90. Bankgiro 61-1237.\nPostgiro 486889-9\n\nVerksamhet: Sågade o hyvlade\nträvaror o försäljning av trävaror o\nbyggplattor\nAntal anställda: 28\nÅrsomsättning: 3 500 000\nAktiekapital: 385 000\nStyrelse: Dir Gideon A Westerlund\n(ordf), herr Ame Johansson\nFörsäljn-chef: Rune Karlsson\nEtableringsån 1933.\n\nTVÄTTERIMASKINER I\nMALMÖ AB\n\nPnr 200 21\n\nMalmö 21, Kruse g 30. Box 21050.\nTel 040-93 53 70.Bankgiro 64-0446.\nPostgiro 431525. Telex 32563\nhei-nex s. Tga Laundry\nVerksamhet: Säljer alla slags\ntvät-terimaskiner, centrifuger,\ntorktum-lare, varmmanglar o pressar\nAntal anställda: 17\nÅrsomsättning: 4 000 000\n\nAktiekapital: 50000\nVerkst din Slgurd Heintz\nEtableringsår: 1937.\n\nLB BYGGNADS AB\n\nPnr 295 00\n\nBromölla, Storg 2. Box 75. Tel\n0456-280 30. Bankgiro 674-1953.\nPostgiro 496754-3\nVerksamhet:\nByggnadsentreprenader avseende småhus, hyreshus o\nfabriksb yggnader\nAntal anställda: 125\nÅrsomsättning: 20 000 000\nAktiekapital: 50 000\nStyrelse: Dir Lennart Bengtsson\n(ordf), adv Nils Gustin, disp Erik\nOlsson\n\nVerkst dir: Lennart Bengtsson\nDisp: Erik Olsson\nEtableringsår: 1964.\n\nFRIGOSCANDIA AB\n\nPnr 25101\n\nHelsingborg 1, Fack. Rusthållsg 21.\nTel042-14 4020. Bankgiro 269-0733.\nPostgiro 345865-0. Tga\nHelsing-borgfrys. Telex 72265 FREEZE S\nVerksamhet: Frys- o kyllagring,\ninfrys ning, upptining samt\nfrys-transpcrter\nAntal anställda: 350\nAktiekapital: 15 000 000\nVerkst dir: Töre Lauritzson\nEtableringsår: 1948.\n\nhüttner ab, max\n\nPnr 103 82\n\nStockholm 7, Box 7046.\nNorr-landsg 18. Tel 08-24 06 60.\nBankgiro 56-0189. Postgiro 1495. Tga\nHuettnerur.\n\nTelex 10415 HYTTNER S\nVerksamhet: Säljer ur, tillbehör o\ndelar i parti\nAntal anställda: 50\nAktiekapital: 500 000\nVerkst dir. Leif Hamrin\nEtableringsår 1894.",
    "structured": {
        "1": {
            "company_name": "LAMELLGOLV AB",
            "pnr": "11135",
            "address": "Stockholm, Kungsg 18",
            "phone_number": "08-23 34 65",
            "activity": "Golvbeläggningsmaterial, plastgolvplattor, träfönster",
            "capital": 350000,
            "key_personnel": [
                {
                    "name": "Gösta Kahr",
                    "position": "Verkst dir"
                }
            ],
            "establishment_year": 1942
        },
        "2": {
            "company_name": "BENNYSSONS SNICKERIER AB",
            "pnr": "603 63",
            "address": "Norrköping, Hammarg 58",
            "phone_number": "011-1349 00",
            "bank_details": {
                "postgiro": "413026"
            },
            "activity": "Tillverkar o säljer alla slags byggnadssnickerier",
            "key_personnel": [
                {
                    "name": "K A Bennysson",
                    "position": "Ägare"
                }
            ],
            "establishment_year": 1954
        },
        "3": {
            "company_name": "ESKIL, SMIDESFABRIKEN",
            "pnr": "630 05",
            "address": "Eskilstuna 5, Box 5048",
            "phone_number": "08-28 38 95",
            "bank_details": {
                "postgiro": "140587"
            },
            "activity": "Försäljning o inköp",
            "capital": null,
            "key_personnel": [
                {
                    "name": "Ing Hubert Andréen",
                    "position": "Chef o firmatecknare"
                }
            ],
            "establishment_year": 1931
        },
        "4": {
            "company_name": "KJELLSTROM, AB BRÖDERNA",
            "pnr": "10401",
            "address": "Stockholm 60, Fack",
            "phone_number": "08-27 27 05",
            "bank_details": {
                "bankgiro": "446-9052",
                "postgiro": "73134-9"
            },
            "activity": "Tillverkar marin-, flyg- o orienteringskompasser, formpressade fanérprodukter",
            "capital": 180000,
            "key_personnel": [
                {
                    "name": "Alvar Kjellström",
                    "position": "Verkst dir"
                }
            ],
            "establishment_year": 1934
        },
        "5": {
            "company_name": "KJELLSTROMS FOTO & REPRO AB",
            "pnr": "416 64",
            "address": "Göteborg, N Agatan 10, Hantverkshuset Stampen",
            "phone_number": "031-801900",
            "bank_details": {
                "bankgiro": "107-7106",
                "postgiro": "44287-1"
            },
            "employees": 30,
            "capital": 50000,
            "key_personnel": [
                {
                    "name": "Leif Attenfelt",
                    "position": "Verkst dir"
                }
            ],
            "establishment_year": 1932
        },
        "6": {
            "company_name": "KJÄLLSTROMS MEK VERKSTAD AB",
            "pnr": "530 20",
            "address": "Kvänum",
            "phone_number": "0512-924 00",
            "bank_details": {
                "bankgiro": "22-0020",
                "postgiro": "71495"
            },
            "activity": "Tillverkar o säljer transportörer för lantbruk",
            "employees": 130,
            "annual_turnover": 12000000,
            "capital": 600000,
            "key_personnel": [
                {
                    "name": "Stig Kjällström",
                    "position": "Verkst dir"
                }
            ],
            "establishment_year": 1890
        },
        "7": {
            "company_name": "URANIA, HÄNDELS-AB",
            "pnr": "114 34",
            "address": "Stockholm, Smålandsg 2",
            "phone_number": "08-23 06 80",
            "bank_details": {
                "bankgiro": "731-6581",
                "postgiro": "57595-1"
            },
            "activity": "Urmakeriartiklar engros",
            "employees": 22,
            "capital": 50000,
            "key_personnel": [
                {
                    "name": "Gerald Nagler",
                    "position": "Verkst din"
                }
            ],
            "establishment_year": 1936
        },
        "8": {
            "company_name": "URSVIKENS MEKANISKA VERKSTADS AB",
            "pnr": "930 30",
            "address": "Ursviken, Pack",
            "phone_number": "0910-308 10",
            "bank_details": {
                "bankgiro": "37-0804",
                "postgiro": "61602-9"
            },
            "activity": "Tillverkar hydrauliska gradsaxar, kantpressar",
            "employees": 150,
            "annual_turnover": 12500000,
            "capital": 1200000,
            "key_personnel": [
                {
                    "name": "Verner Eriksson",
                    "position": "Verkst dir"
                },
                {
                    "name": "Elmer Lindmark",
                    "position": "Kamrer"
                },
                {
                    "name": "Per Persson",
                    "position": "Verkstadschef"
                },
                {
                    "name": "Egon Eriksson",
                    "position": "Konstr-chef"
                }
            ],
            "establishment_year": 1885
        },
        "9": {
            "company_name": "OSTLUNDS BYGGNADS AB",
            "pnr": "113 47",
            "address": "Stockholm, Ynglingag 18",
            "phone_number": "08-34 9190",
            "bank_details": {
                "bankgiro": "576-2276",
                "postgiro": "256813-7"
            },
            "activity": "Byggnadsrörelse för Industri- o bostadshus",
            "employees": 90,
            "annual_turnover": 12000000,
            "capital": 480000,
            "key_personnel": [
                {
                    "name": "Rolf Bergholm",
                    "position": "Verkst dir"
                }
            ],
            "establishment_year": 1944
        },
        "10": {
            "company_name": "TVÄRÅNS SÄG AB",
            "pnr": "970 20",
            "address": "Koskullskulle, Box 7",
            "phone_number": "0970-302 90",
            "bank_details": {
                "bankgiro": "61-1237",
                "postgiro": "486889-9"
            },
            "activity": "Sågade o hyvlade trävaror o försäljning av trävaror o byggplattor",
            "employees": 28,
            "annual_turnover": 3500000,
            "capital": 385000,
            "key_personnel": [
                {
                    "name": "Gideon A Westerlund",
                    "position": "Styrelseordförande"
                },
                {
                    "name": "Ame Johansson",
                    "position": "Direktör"
                }
            ],
            "establishment_year": 1933
        },
        "11": {
            "company_name": "TVÄTTERIMASKINER I MALMÖ AB",
            "pnr": "200 21",
            "address": "Malmö 21, Kruse g 30, Box 21050",
            "phone_number": "040-93 53 70",
            "bank_details": {
                "bankgiro": "64-0446",
                "postgiro": "431525"
            },
            "activity": "Säljer alla slags tvätt-terimaskiner, centrifuger, torktumlare, varmmanglar o pressar",
            "employees": 17,
            "annual_turnover": 4000000,
            "capital": 50000,
            "key_personnel": [
                {
                    "name": "Slgurd Heintz",
                    "position": "Verkst dir"
                }
            ],
            "establishment_year": 1937
        },
        "12": {
            "company_name": "LB BYGGNADS AB",
            "pnr": "295 00",
            "address": "Bromölla, Storg 2, Box 75",
            "phone_number": "0456-280 30",
            "bank_details": {
                "bankgiro": "674-1953",
                "postgiro": "496754-3"
            },
            "activity": "Byggnadsentreprenader avseende småhus, hyreshus o fabriksbyggnader",
            "employees": 125,
            "annual_turnover": 20000000,
            "capital": 50000,
            "key_personnel": [
                {
                    "name": "Lennart Bengtsson",
                    "position": "Styrelseordförande"
                },
                {
                    "name": "Nils Gustin",
                    "position": "Advokat"
                },
                {
                    "name": "Erik Olsson",
                    "position": "Disponent"
                }
            ],
            "establishment_year": 1964
        },
        "13": {
            "company_name": "FRIGOSCANDIA AB",
            "pnr": "25101",
            "address": "Helsingborg 1, Fack. Rusthållsg 21",
            "phone_number": "042-14 4020",
            "bank_details": {
                "bankgiro": "269-0733",
                "postgiro": "345865-0"
            },
            "activity": "Frys- o kyllagring, infrys ning, upptining samt frys-transpcrter",
            "employees": 350,
            "capital": 15000000,
            "key_personnel": [
                {
                    "name": "Töre Lauritzson",
                    "position": "Verkst dir"
                }
            ],
            "establishment_year": 1948
        },
        "14": {
            "company_name": "hüttner ab, max",
            "pnr": "103 82",
            "address": "Stockholm 7, Box 7046, Norrlandsg 18",
            "phone_number": "08-24 06 60",
            "bank_details": {
                "bankgiro": "56-0189"
            },
            "activity": "Säljer ur, tillbehör o delar i parti",
            "employees": 50,
            "capital": 500000,
            "key_personnel": [
                {
                    "name": "Leif Hamrin",
                    "position": "Verkst dir"
                }
            ],
            "establishment_year": 1894
        }
    }
}