{
    "original": "INDOMA, AB\n\nPnr 55102\n\nJönköping 1, Box 319. Tel\n036-112184, 115194. Bankgiro\n835-7196. Postgiro 143944-7.\nTga Indoma\n\nVerksamhet: Säljer\nindustritillbehör: smörjsprutor, smörjnipplar,\nspårringar, tätningselement, lås- o\nfjäderbrickor. Hydraulslang o\nkopplingar\nAktiekapital: 20 000\nStyrelse: Ing Rolf Ahlse, disp\nRoland Bäcker\nEtableringsår: 1953.\n\nONOS, AB\n\nPnr 290 10\n\nToUarp, önosg. Fack. Tel\n0450-105 00, 105 05. Bankgiro 95-0550.\nPostgiro 15027. Telex 4427. Tga\nOenos\n\nVerksamhet: Frukt- o\nbärprodukter, marmelad, sylt, saft o\nsaftkoncentrat, halvfabrikat för\nchoklad-o livsmedelsindustrin\nFörsäljningskontor: 41104\nGöteborg, Mårten Krakowg 1 B. Tel\n031-15 65 55\n\n12155 Johanneshov, Vikstensv 18.\nTel 08-49 0312\nAntal anställda: 150\nÅrsomsättning: 30 000 000\nAktiekapital: 1838 400\nVerkst dir: Dettmar Wollin\nEtableringsår. 1903.\n\nGRUNDÉNS REGNKLÄDERS.\nFABRIKS AB\n\nPnr 451 01\n\nUddevalla 1, Kungsg 37. Box 134.\nTel 0522-140 85. Bankgiro 42-8014.\nPostgiro 33479. Tga Regngrunden\nVerksamhet: Tillverkar o säljer\nregnkläder för arbete, sport etc i\nplastbelagd väv o gummiduk\nVarunamn: Skeppet\nAntal anställda: 50\nAktiekapital: 75 000\nVerkst dir: Olof Grundén\nEtableringsår: 1926.\n\nSVE\n\nAktiekapital: 200 000\nVerkst dir. Per-Hugo Lager\nEtableringsår: 1889.\n\nSVENSSONS TRÄVARUAFFÄR,\nAB BERNDT\n\nPnr 290 60\n\nKyrkhult, Väghult. Tel 0454-700 28.\nBankgiro 15-1672. Postgiro 70711\nVerksamhet: Byggvaror, trävaror\nAntal anställda: 20\nÅrsomsättning: 2000 000\nAktiekapital: 150 000\nVeikst dir: Disp Gunnar Svensson\nEtableringsår: 1918\nOmbildat till aktiebolag 1960.\n\nSVENSSONS SLIPERI &amp;\nSPEGELFABRIK, AB C O\n\nPnr 571 00\n\nNässjö, Industrig 34. Tel\n0380-142 89. Postgiro 22419-6\nVerksamhet: Tillverkar\nmöbelspeglar i alla stilarter. Spegelfoliering,\nkant- o facettslipning m m\nÅrsomsättning: 150 000\nAktiekapital: 23 000\nVerkst din Holger Ovelius\nEtableringsår: 1903.\n\nPALMERS PLÅTSLAGERI AB\n\nPnr 70103\n\nÖrebro 1, Myrmalmsg 6. Box 224.\nTel 019-14 04 75. Bankgiro 46-3335.\nPostgiro 615630\n\nVerksamhet: Plåtslageri- o ventilar\ntionsarbeten. Kantpressning\nAntal anstäUda: 30\nÅrsomsättning: 3000 000\nAktiekapital: 5 000\nVerkst dir: Roland Palmer\nEtableringsår: 1958.\n\nSIHA SPEDITION AB\n\nPnr 402 32\n\nGöteborg 7, Box 7146. Tel\n031-42 21 90, 42 2282. Bankgiro\n602-2875. Postgiro 528976-4.\nTelex 20022 SIHA S\nVerksamhet: Speditionsverksamhet\n(import o export)\nAktiekapital: 5 000\nChef: Bengt-Olof Hammarberg\nEtableringsår: 1968.\n\nKRONBERGS ELEKTRISKA AB\n\nPnr 54101\n\nSkövde 1, Box 47. Bangårdsg 6.\nTel 0500-105 20. Bankgiro\n210-1939. Postgiro 494790-9\nVerksamhet; El-installationer.\nSäljer belysningsarmatur\nAntal anställda: 70\nÅrsomsättning: 6 000 000\nAktiekapital: 10 000\nVerkst dir. Ing Karl-Eric Kronberg\nEtableringsår: 1956.\n\nHER\n\nHENNIX REKLAMATELJÉ,\nAB T\n\nPnr 112 61\n\nStockholm, Essinge Brog 3. Tel\n08-13 1380. Bankgiro 330-1355.\nPostgiro 358606-2\nVerksamhet: Utställningar,\nmässmontrar, fasadskyltar,\nfabrikantskyltningar, silkscreentryck\nAktiekapital: 10 000\nVerkst dir: Lars Hennix\nEtableringsår: 1951.\n\nHENRIKSBERGS\nVERK-STÄDER. AB\n\nPnr 126 02\n\nHägersten 2, Box 228. Tel\n08-46 13 07, 46 3100. Bankgiro 744-1\n3799. Postgiro 451341-2\nVerksamhet: Konstruktioner,\nverktyg, varmluftsbatterier, smides- o\nmekaniska arbeten\nAntal anstäUda: 20\nÅrsomsättning: 1000 000\nAktiekapital: 25 000\nStyrelse: Dir Einar Svensson (ordf),\nkamrer Olle Svensson, verkmäst\nBengt Svensson\nVerkst dir: Einar Svensson\nEtableringsår: 1960.\n\nHENRIKSSONS\nBRAND-REDSKAP, AB\n\nPnr 10123\n\nStockholm 1, Jakobsg 14. Box 281.\nTel 08-2078 22- 25. Bankgiro\n332-2021. Postgiro 3321-7. Tga\nSprut-bolaget\n\nVerksamhet: Tillverkar o säljer all\nslags brandredskap\nAvdelningskontor: 41114 Göteborg,\nDrottningg 27. Tel 031-117074,\n10 53 64\n\n211 36 Malmö, Baltzarsg 19. Tel\n040-97 5 9 42, 301 84\n85103 Sundsvall, Rådhusg 15. Box\n141. Tel 060-112989, 11 3082\n235 00 Vellinge, Box 67. Tel\n040-4 2 07 13\n\nVarunamn: Hebra\nAntal anstäUda: 20\nÅrsomsättning: 5000 000\nAktiekapital: 160 000\nStyrelse: Bankdir Lars-Gunnar\nÅberg (ordf), fru Dagmar Eriksson,\ndir Olov Eriksson\nVerkst dir: Olov Eriksson\nEtableringsår: 1828\nOmbildat till aktiebolag 1927.\n\nHENRIKSONS JÄRN &amp;\nMETALL AB\n\nPnr 40311\n\nGöteborg 2, Manufakturg 19. Box\n2047. Tel 031-5136 70. Bankgiro\n42-0257. Postgiro 526140\nVerksamhet: Engrosförsäljning\nhalvfabrikat av järn o metaller\nVerkst dir: Bertil H Henrikson\nEtableringsår: 1959.\n\nHENRIKSSONS\nPLÅTSLAGERI, J\n\nPnr 95100\n\nLuleå, V Malmg 13. Tel 0920-12346\nVerksamhet: Byggnadsplåtslageri,\nventilationsanläggningar o\nsvetsning\n\nChef: John Henriksson\nEtableringsår: 1909.\n\nIVARSSONS ELEKTRISKA AB\n\nPnr 701 03\n\nÖrebro 1, Box 161. Fredsg 4. Tel\n019-1243 15. Bankgiro 495-5423.\nPostgiro 139500-3\nVerksamhet: Utför elektr\ninstallationer. Säljer elektr\nhushållsapparater\n\nAntal anställda: 45\nÅrsomsättning: 2 500 000\nVerkst dir Stig Ivarsson\nEtableringsår: 1956.\n\nVEB\n\nsilor, bagerier, kemisk tekniska\nindustrier, betongvarufabriker etc\nFilialkontor: tfrebro, Drottningg\n34. Tel 019-1149 33\nAntal anställda: 60\nÅrsomsättning: 3 000 000\nAktiekapital: 160 000\nDisp: Roland Ohlsson\nEtableringsår: 1921.\n\nWEBERUDS NYA\nTEGEL-BRUKS AB\n\nPnr 240 14\n\nVeberöd. Tel 046-804 50.\nBankgiro 670-2617. Postgiro 283703-7\nVerksamhet: Tillverkar fasadtegel\no taktegel. All försäljning genom\nAB Tegelcentralen i Malmö\nVarunamn: WeBe Tegel\nAntal anställda: 65\nÅrsomsättning: 4 000 000\nAktiekapital: 1000 000\nStyrelse: Dir Oskar Webmark (ordf),\ngodsägare Bengt Iacobaeus, dir\nOwe Björck, jur kand Berndt von\nSchinkel, fru Gerda von Schinkel,\nkommendörkapten Krister von\nSchinkel\n\nVerkst dir: Bengt Iacobaeus\nEtableringsår: 1913.",
    "structured": {
        "1": {
            "company_name": "INDOMA, AB",
            "pnr": "55102",
            "address": "Jönköping 1, Box 319",
            "phone_number": "036-112184, 115194",
            "bank_details": {
                "bankgiro": "835-7196",
                "postgiro": "143944-7"
            },
            "activity": "Säljer industritillbehör: smörjsprutor, smörjnipplar, spårringar, tätningselement, lås- o fjäderbrickor. Hydraulslang o kopplingar",
            "capital": 20000,
            "key_personnel": [
                {
                    "name": "Ing Rolf Ahlse",
                    "position": ""
                },
                {
                    "name": "disp Roland Bäcker",
                    "position": ""
                }
            ],
            "establishment_year": 1953
        },
        "2": {
            "company_name": "ONOS, AB",
            "pnr": "290 10",
            "address": "ToUarp, önosg",
            "phone_number": "0450-105 00, 105 05",
            "bank_details": {
                "bankgiro": "95-0550",
                "postgiro": "15027"
            },
            "activity": "Frukt- o bärprodukter, marmelad, sylt, saft o saftkoncentrat, halvfabrikat för choklad-o livsmedelsindustrin",
            "employees": 150,
            "annual_turnover": 30000000,
            "capital": 1838400,
            "key_personnel": [
                {
                    "name": "Dettmar Wollin",
                    "position": ""
                }
            ],
            "establishment_year": 1903
        },
        "3": {
            "company_name": "GRUNDÉNS REGNKLÄDERS. FABRIKS AB",
            "pnr": "451 01",
            "address": "Uddevalla 1, Kungsg 37, Box 134",
            "phone_number": "0522-140 85",
            "bank_details": {
                "bankgiro": "42-8014",
                "postgiro": "33479"
            },
            "activity": "Tillverkar o säljer regnkläder för arbete, sport etc i plastbelagd väv o gummiduk",
            "employees": 50,
            "capital": 75000,
            "key_personnel": [
                {
                    "name": "Olof Grundén",
                    "position": ""
                }
            ],
            "establishment_year": 1926
        },
        "4": {
            "company_name": "SVE",
            "capital": 200000,
            "key_personnel": [
                {
                    "name": "Per-Hugo Lager",
                    "position": ""
                }
            ],
            "establishment_year": 1889
        },
        "5": {
            "company_name": "SVENSSONS TRÄVARUAFFÄR, AB BERNDT",
            "pnr": "290 60",
            "address": "Kyrkhult, Väghult",
            "phone_number": "0454-700 28",
            "bank_details": {
                "bankgiro": "15-1672",
                "postgiro": "70711"
            },
            "activity": "Byggvaror, trävaror",
            "employees": 20,
            "annual_turnover": 2000000,
            "capital": 150000,
            "key_personnel": [
                {
                    "name": "Disp Gunnar Svensson",
                    "position": ""
                }
            ],
            "establishment_year": 1918
        },
        "6": {
            "company_name": "SVENSSONS SLIPERI & SPEGELFABRIK, AB C O",
            "pnr": "571 00",
            "address": "Nässjö, Industrig 34",
            "phone_number": "0380-142 89",
            "postgiro": "22419-6",
            "activity": "Tillverkar möbelspeglar i alla stilarter. Spegelfoliering, kant- o facettslipning m m",
            "annual_turnover": 150000,
            "capital": 23000,
            "key_personnel": [
                {
                    "name": "Holger Ovelius",
                    "position": ""
                }
            ],
            "establishment_year": 1903
        },
        "7": {
            "company_name": "PALMERS PLÅTSLAGERI AB",
            "pnr": "70103",
            "address": "Örebro 1, Myrmalmsg 6, Box 224",
            "phone_number": "019-14 04 75",
            "bank_details": {
                "bankgiro": "46-3335",
                "postgiro": "615630"
            },
            "activity": "Plåtslageri- o ventilationarbeten. Kantpressning",
            "employees": 30,
            "annual_turnover": 3000000,
            "capital": 5000,
            "key_personnel": [
                {
                    "name": "Roland Palmer",
                    "position": ""
                }
            ],
            "establishment_year": 1958
        },
        "8": {
            "company_name": "SIHA SPEDITION AB",
            "pnr": "402 32",
            "address": "Göteborg 7, Box 7146",
            "phone_number": "031-42 21 90, 42 2282",
            "bank_details": {
                "bankgiro": "602-2875",
                "postgiro": "528976-4"
            },
            "activity": "Speditionsverksamhet (import o export)",
            "capital": 5000,
            "key_personnel": [
                {
                    "name": "Bengt-Olof Hammarberg",
                    "position": ""
                }
            ],
            "establishment_year": 1968
        },
        "9": {
            "company_name": "KRONBERGS ELEKTRISKA AB",
            "pnr": "54101",
            "address": "Skövde 1, Box 47, Bangårdsg 6",
            "phone_number": "0500-105 20",
            "bank_details": {
                "bankgiro": "210-1939",
                "postgiro": "494790-9"
            },
            "activity": "El-installationer. Säljer belysningsarmatur",
            "employees": 70,
            "annual_turnover": 6000000,
            "capital": 10000,
            "key_personnel": [
                {
                    "name": "Ing Karl-Eric Kronberg",
                    "position": ""
                }
            ],
            "establishment_year": 1956
        },
        "10": {
            "company_name": "HENNIX REKLAMATELJÉ, AB T",
            "pnr": "112 61",
            "address": "Stockholm, Essinge Brog 3",
            "phone_number": "08-13 1380",
            "bank_details": {
                "bankgiro": "330-1355",
                "postgiro": "358606-2"
            },
            "activity": "Utställningar, mässmontrar, fasadskyltar, fabrikantskyltningar, silkscreentryck",
            "capital": 10000,
            "key_personnel": [
                {
                    "name": "Lars Hennix",
                    "position": ""
                }
            ],
            "establishment_year": 1951
        }
    }
}