{
    "original": "ekhagen, ab bröderna\n\nPnr 183 02\n\nTäby 2, Box 2001. Stockholmsv 112.\nTel 08-758 0140. Bankgiro\n625-6101. Postgiro 50510-7. Tga Herek\nVerksamhet: Tillverkar dekalkomar\nnier o presentreklam\nAvdelningskontor: 111 40 Stockholm,\nKammakarg 18. Tel 08-11 73 07\n41252 Göteborg, Sten Stureg 36.\nTel 031-18 43 98\n\n214 32 Malmö, Finlandsg 20. Tel\n040-968810\n\nVarunamn: Färgdekal, Plasti-Cal\nAntal anställda: 70\nÅrsomsättning: 4 500 000\nAktiekapital: 200 000\nVerkst dir: Gösta Ekhagen\nEtableringsår: 1925.\n\nABEROHS AB\n\nPnr 150 20\n\nJärna, Bergsg 24 A. Tel\n0755-70650. Bankgiro 616-7837.\nPostgiro 133109-9\n\nVerksamhet:\nBeställningsplåtslageri i grovplåt o rostfritt\nAntal anställda: 10\nÅrsomsättning: 600 000\nAktiekapital: 9 000\nStyrelse: Olle Larsson (ordf), Harry\nTännström\n\nVerkst dir: Harry Tännström\nEtableringsår: 1962.\n\nCELIND AB\n\nPnr 433 00\n\nPartilie, Box 60. Tel 031-44 49 81.\nBankgiro 74-5006. Postgiro 525522.\nTga Celind\n\nVerksamhet:\nBrunnsborrningsmaskiner, lådstaplare, pallastare\nAntal anställda: 40\nChef: C-E Lind\nEtableringsår: 1967.\n\nMONTAGE.SVETS AB\n\nPnr 591 00\n\nMotala. Nyg 33. Tel 0141-515 80.\nBankgiro 13-4491. Postgiro\n581732-5\n\nVerksamhet Tillverkning av\ncisterner samt en del legoarbeten\nAntal anställda: 8\nChef: Fabr Rolf Johansson\nEtableringsår: 1961.\n\nMONTERINGSPLÄT ARNE\nvon HAGE\n\nPnr 412 54\n\nGöteborg, Södra v 77. Tel\n031-2014 90, 16 95 35. Bankgiro\n514-5396. Postgiro 43744-2\nVerksamhet: Tillverkar takrännor\no stuprör\nAntal anställda: 3\nChef: Arne von Hage\nEtableringsår: 1960.\n\nTAB\n\nT\n\nTABERGS MASKINFABRIKS AB\n\nPnr 560 21\n\nTaberg. Tel 036-645 70. Postgiro\n707412. Tga Maskinfabriken\nVerksamhet: Maskiner för cellulosa-,\nfärg- o kern industrin m m\nVerkst dir: C H All erman\nEtableringsår: 1889.\n\nBLOMBORGS MEKANISKA, AB\n\nPnr 571 00\n\nNässjö, österlångg 53. Tel\n0380-11405. Bankgiro 45-2710.\nPostgiro 146448\n\nVerksamhet: Tillverkar o säljer\nmöbelbeslag\nAntal anställda: 12\nÅrsomsättning: 1000 000\nAktiekapital: 80 000\nVerkst dir: David Blomborg\nEtableringsår: 1943.\n\nSÄVSJO BORSTFABRIK, AB\n\nPnr 576 00\n\nSävsjö, Box 123. Tel 0382-103 14.\nBankgiro 83-6510. Postgiro 280353.\nTga Sävsjöborst\n\nVerksamhet: Tillverkar\nhushålls-borstar, industriborstar o penslar\nÄgare o chef: Ing C G Stubner.\n\nSÄVSJO FÄRGFABRIK AB\n\nPnr 576 00\n\nSävsjö, Hägnev. Tel 0382-112 05\nVerksamhet: Specialitet: färger för\nut- o invändigt bruk, linoljefärger,\nplastfärger, takfärger,\nimpregne-ringsfärger o -oljor, rödfärger,\nsyntetiska färger, rostskyddsfärger,\nindustrifärger, maskinlacker mm.\nStruktal-Akrylputs\nVarunamn: Ge-Geprodukter\nAktiekapital: 30 000\nVerkst dir: Göte Gyllström\nEtableringsår: 1956.\n\nSELECTA ATELJÉN, AB\n\nPnr 116 53\n\nStockholm, Rosenlundsg 50. Tel\n\n08-847217, 84 7216. Postgiro\n52020-5\n\nVeiksamhet: Screentryckeri\nAntal anställda: 7\nAktiekapital: 13 500\nVeikst dir. Fru Hildur Hemberg\nEtableringsår 1931.\n\nSE LE FA, SVERIGES LAKAR.\nFURBUNDS FÖRSÄLJNINGS\nAB\n\nPnr 114 51\n\nStockholm, Artillerig 24. Tel\n08-6306 10. Bankgiro\n167-4464.postgiro 159972-9. Tga Mediself\nVeiksamhet: Säljer kirurgiska\ninstrument, medicinsk apparatur o\nförbandsartiklar\n\nAvdelningskontor: Göteborg, Malmö\nAntal anställda: 40\nAktiekapital: 400 000\nVeikst din Karl Esbjörnsson\nEtableringsån 1941.\n\nÅBE\n\no\n\nA\n\nÅBERG. AB BRÖDERNA\n\nPnr 260 38\n\nKattaxp, Box 20. Tel 042-560 20,\n56200. Bankgiro 65-2809. Postgiro\n80800\n\nVerksamhet: Säljer fröer, utsäde,\nspannmål, foderämnen, gödning,\nkol, koks o eldningsoljor\nAntal anställda: 8\nÅrsomsättning: 1800000\nAktiekapital: 103 000\nVerkst dir: John W Andersson\nEtableringsår: 1896\nOmbildat till aktiebolag 1918.\n\nÅBERG &amp; SÖNER, AB\n\nPnr 280 70\n\nLönsboda, Vilshultsv. Tel\n0479-20141. Bankgiro 279-3404.\nPostgiro 164862-5\n\nVerksamhet: Tillverkar\nformpres-sade trädetaljer\nAktiekapital: 61 500\nVerkst dir: Ragnar Åberg\nEtableringsår: 1913.\n\nMETRO GOLDWYN-MAYER AB\n\nPnr 103 60\n\nStockholm 3, Fack. Kungsg 18.\nTel 08-23 2105. Bankgiro 16-8779.\nPostgiro 992. Tga Metrofilms\nVeiksamhet: Filmbyrå\nAntal anställda: 25\nÅrsomsättning: 6 350 000\nAktiekapital: 215 000\nVerkst dir: Abbé Drisin\nFilmchef: Harald Wickman\nKontorschef: Gunnar Karnefors\nReklamchef: Monica Truwert\nLagerchef: Arvid Larsson\nEtableringsår: 1925\nDotterbolag till Metro\nGoldwyn-Mayer Int Inc, New York.\n\nMETRO LJUSREKLAM AB\n\nPnr 19121\n\nSollentuna, Box 108. Tel 0760-\n\n34140. Bankgiro 748-0031. Postgiro\n126756-6\n\nVeiksamhet: Säljer o tillverkar\nneon- o plastskyltar\nAntal anställda: 70\nAktiekapital: 50 000\nVerkst dir: Karl-Evert Heej\nEtableringsår: 1957.",
    "structured": {
        "1": {
            "company_name": "Ekhagen, ab bröderna",
            "address": "Täby 2, Box 2001. Stockholmsv 112.",
            "phone_number": "08-758 0140",
            "bank_details": {
                "bankgiro": "625-6101",
                "postgiro": "50510-7"
            },
            "activity": "Tillverkar dekalkomarnier o presentreklam",
            "employees": 70,
            "annual_turnover": 4500000,
            "capital": 200000,
            "key_personnel": [
                {
                    "name": "Gösta Ekhagen",
                    "position": "Verkst dir"
                }
            ],
            "establishment_year": 1925
        },
        "2": {
            "company_name": "ABEROHS AB",
            "address": "Järna, Bergsg 24 A",
            "phone_number": "0755-70650",
            "bank_details": {
                "bankgiro": "616-7837",
                "postgiro": "133109-9"
            },
            "activity": "Beställningsplåtslageri i grovplåt o rostfritt",
            "employees": 10,
            "annual_turnover": 600000,
            "capital": 9000,
            "key_personnel": [
                {
                    "name": "Olle Larsson",
                    "position": "ordf"
                },
                {
                    "name": "Harry Tännström",
                    "position": "Verkst dir"
                }
            ],
            "establishment_year": 1962
        },
        "3": {
            "company_name": "CELIND AB",
            "address": "Partilie, Box 60",
            "phone_number": "031-44 49 81",
            "bank_details": {
                "bankgiro": "74-5006",
                "postgiro": "525522"
            },
            "activity": "Brunnsborrningsmaskiner, lådstaplare, pallastare",
            "employees": 40,
            "key_personnel": [
                {
                    "name": "C-E Lind",
                    "position": "Chef"
                }
            ],
            "establishment_year": 1967
        },
        "4": {
            "company_name": "MONTAGE.SVETS AB",
            "address": "Motala. Nyg 33",
            "phone_number": "0141-515 80",
            "bank_details": {
                "bankgiro": "13-4491",
                "postgiro": "581732-5"
            },
            "activity": "Tillverkning av cisterner samt en del legoarbeten",
            "employees": 8,
            "key_personnel": [
                {
                    "name": "Fabr Rolf Johansson",
                    "position": "Chef"
                }
            ],
            "establishment_year": 1961
        },
        "5": {
            "company_name": "MONTERINGSPLÄT ARNE von HAGE",
            "address": "Göteborg, Södra v 77",
            "phone_number": "031-2014 90, 16 95 35",
            "bank_details": {
                "bankgiro": "514-5396",
                "postgiro": "43744-2"
            },
            "activity": "Tillverkar takrännor o stuprör",
            "employees": 3,
            "key_personnel": [
                {
                    "name": "Arne von Hage",
                    "position": "Chef"
                }
            ],
            "establishment_year": 1960
        },
        "6": {
            "company_name": "TABERGS MASKINFABRIKS AB",
            "address": "Taberg",
            "phone_number": "036-645 70",
            "postgiro": "707412",
            "activity": "Maskiner för cellulosa-, färg- o kern industrin m m",
            "key_personnel": [
                {
                    "name": "C H All erman",
                    "position": "Verkst dir"
                }
            ],
            "establishment_year": 1889
        },
        "7": {
            "company_name": "BLOMBORGS MEKANISKA, AB",
            "address": "Nässjö, österlångg 53",
            "phone_number": "0380-11405",
            "bank_details": {
                "bankgiro": "45-2710",
                "postgiro": "146448"
            },
            "activity": "Tillverkar o säljer möbelbeslag",
            "employees": 12,
            "annual_turnover": 1000000,
            "capital": 80000,
            "key_personnel": [
                {
                    "name": "David Blomborg",
                    "position": "Verkst dir"
                }
            ],
            "establishment_year": 1943
        },
        "8": {
            "company_name": "SÄVSJO BORSTFABRIK, AB",
            "address": "Sävsjö, Box 123",
            "phone_number": "0382-103 14",
            "bank_details": {
                "bankgiro": "83-6510",
                "postgiro": "280353"
            },
            "activity": "Tillverkar hushålls-borstar, industriborstar o penslar",
            "key_personnel": [
                {
                    "name": "Ing C G Stubner",
                    "position": "Ägare o chef"
                }
            ]
        },
        "9": {
            "company_name": "SÄVSJO FÄRGFABRIK AB",
            "address": "Sävsjö, Hägnev",
            "phone_number": "0382-112 05",
            "activity": "Specialitet: färger för ut- o invändigt bruk, linoljefärger, plastfärger, takfärger, impregne-ringsfärger o -oljor, rödfärger, syntetiska färger, rostskyddsfärger, industrifärger, maskinlacker mm.",
            "employees": 0,
            "capital": 30000,
            "key_personnel": [
                {
                    "name": "Göte Gyllström",
                    "position": "Verkst dir"
                }
            ],
            "establishment_year": 1956
        },
        "10": {
            "company_name": "SELECTA ATELJÉN, AB",
            "address": "Stockholm, Rosenlundsg 50",
            "phone_number": "08-847217, 84 7216",
            "postgiro": "52020-5",
            "activity": "Screentryckeri",
            "employees": 7,
            "capital": 13500,
            "key_personnel": [
                {
                    "name": "Fru Hildur Hemberg",
                    "position": "Veikst dir"
                }
            ],
            "establishment_year": 1931
        },
        "11": {
            "company_name": "SE LE FA, SVERIGES LAKAR. FURBUNDS FÖRSÄLJNINGS AB",
            "address": "Stockholm, Artillerig 24",
            "phone_number": "08-6306 10",
            "bank_details": {
                "bankgiro": "167-4464",
                "postgiro": "159972-9"
            },
            "activity": "Säljer kirurgiska instrument, medicinsk apparatur o förbandsartiklar",
            "employees": 40,
            "capital": 400000,
            "key_personnel": [
                {
                    "name": "Karl Esbjörnsson",
                    "position": "Veikst din"
                }
            ],
            "establishment_year": 1941
        },
        "12": {
            "company_name": "ÅBERG. AB BRÖDERNA",
            "address": "Kattaxp, Box 20",
            "phone_number": "042-560 20, 56200",
            "bank_details": {
                "bankgiro": "65-2809",
                "postgiro": "80800"
            },
            "activity": "Säljer fröer, utsäde, spannmål, foderämnen, gödning, kol, koks o eldningsoljor",
            "employees": 8,
            "annual_turnover": 1800000,
            "capital": 103000,
            "key_personnel": [
                {
                    "name": "John W Andersson",
                    "position": "Verkst dir"
                }
            ],
            "establishment_year": 1896
        },
        "13": {
            "company_name": "ÅBERG & SÖNER, AB",
            "address": "Lönsboda, Vilshultsv",
            "phone_number": "0479-20141",
            "bank_details": {
                "bankgiro": "279-3404",
                "postgiro": "164862-5"
            },
            "activity": "Tillverkar formpres-sade trädetaljer",
            "capital": 61500,
            "key_personnel": [
                {
                    "name": "Ragnar Åberg",
                    "position": "Verkst dir"
                }
            ],
            "establishment_year": 1913
        },
        "14": {
            "company_name": "METRO GOLDWYN-MAYER AB",
            "address": "Stockholm 3, Fack. Kungsg 18",
            "phone_number": "08-23 2105",
            "bank_details": {
                "bankgiro": "16-8779",
                "postgiro": "992"
            },
            "activity": "Filmbyrå",
            "employees": 25,
            "annual_turnover": 6350000,
            "capital": 215000,
            "key_personnel": [
                {
                    "name": "Abbé Drisin",
                    "position": "Verkst dir"
                },
                {
                    "name": "Harald Wickman",
                    "position": "Filmchef"
                },
                {
                    "name": "Gunnar Karnefors",
                    "position": "Kontorschef"
                },
                {
                    "name": "Monica Truwert",
                    "position": "Reklamchef"
                },
                {
                    "name": "Arvid Larsson",
                    "position": "Lagerchef"
                }
            ],
            "establishment_year": 1925,
            "dotterbolag": "Metro Goldwyn-Mayer Int Inc, New York"
        },
        "15": {
            "company_name": "METRO LJUSREKLAM AB",
            "address": "Sollentuna, Box 108",
            "phone_number": "0760-34140",
            "bank_details": {
                "bankgiro": "748-0031",
                "postgiro": "126756-6"
            },
            "activity": "Säljer o tillverkar neon- o plastskyltar",
            "employees": 70,
            "capital": 50000,
            "key_personnel": [
                {
                    "name": "Karl-Evert Heej",
                    "position": "Verkst dir"
                }
            ],
            "establishment_year": 1957
        }
    }
}