{
    "original": "EKDAHLS KONFEKTIONS AB\n\nPnr 300 02\n\nHalmstad 2, Box 2070. Sperlingsg.\nTel 035-10 00 50. Bankgiro 53-02 0 2.\nPostgiro 112561. Tga Galamode\nVerksamhet: Fabrik för tillverkning\nav klänningar\nAntal anställda: 80\nÅrsomsättning: 4000000\nAktiekapital: 70 000\nVerkst dir: Disp Gunnar Ekdahl\nEtableringsår: 1957.\n\nBORJESSON AB, AUG\n\nPnr 292 00\n\nKarlshamn, Ronnebyg 8. Tel\n0454-103 60,10597. Bankgiro 86-2143.\nPostgiro 30273\n\nVerksamhet: Engros- o\ndetaljförsäljning av sängkläder, trikåvaror\nAntal anställda: 11\nÅrsomsättning: 1150 000\n\nAktiekapital: 50 000\n\nVerkst dir: Konsul Albert Börjesson\n\nEtableringsår: 1888.\n\nWISTA, HANDELSFIRMAN\n\nPnr 43102\n\nMölndal 2, Abäcksg 6. Box 2014.\nTel 031-16 1525, 16 2520. Postgiro\n420890-2. Tga Wistab\nVerksamhet: Import av\nritkontors-utensilier. Specialitet:\nkantmaskiner\n\nVarunamn: Wisto\nÄgare o chef: Göte Ackert\nEtableringsår: 1949.\n\nWISTRAND AB.\nINGENJÖRS-FIRMAN HANS\n\nPnr 51035\n\nBollebygd, Angpannev 3. Tel\n033-856 40. Bankgiro 532-1922.\nPostgiro 438069-7\n\nVerksamhet: Utför kem rengöring\nav ångpannor samt säljer\nvatten-reningsutrustning för ångpannor o\nswimmingpools\nAntal anställda: 7\nAktiekapital: 42 000\n\nStyrelse: Fru Inga Wistrand\nChef: Fru Inga Wistrand\nEtableringsår: 1960.\n\nAJCO TRIKÄFABRIK AB\n\nPnr 41502\n\nGöteborg, Artillerig 23. Tel\n031-25 00 30. Tga Ajcotricot\nVerksamhet: Tillverkar\njerseyklänningar o jerseyväv\nFörsäljningskontor: Stockholm C,\nKungsg 56. Tel 08-21 26 00\nKöpenhamn K. Danajco Mode A/S,\nVimmelskaftet 42 A. Tel Palae\n9607\n\nVarunamn: Ajco, Ajco jersey\nAktiekapital: 400 000\nStyrelse: Ing Bengt Löfmark, disp\nArne Törnebrandt, kamrer Bengt\nOlssön, kamrer Ralph Wilson\nVerkst dir: Ing Bengt Löfmark\nEtableringsår: 1878\nOmbildat till aktiebolag 1926.\nNuvarande namn 1945.\n\nÅJO KYLINDUSTRI AB\n\nPnr 43011\n\nTräslövsläge, Box 54. Tel\n0340-700 68, 700 53. Bankgiro 42-5189.\nTga Ajokyl, Varberg\nVerksamhet: Tillverkar kylskåp,\nkyldiskar o flaskkylare\nVarunamn: Åjo\nAntal anställda: 10\nÅrsomsättning: 2 000 000\nAktiekapital: 20 000\nStyrelse: Fabr Albert Olsson\n(ordf), disp Buster Olsson, ing\nEsse Olsson\n\nVerkst dir: Disp Buster Olsson\nEtableringsår: 1948\nOmbildat till aktiebolag 1959.\n\nAK INREDE AB\n\nPnr 140 11\n\nVårby, Fittja Industriområde. Tel\n08-710 08 30. Bankgiro 734-4443.\nPostgiro 554388-9\nVerksamhet: Egna specialritade\nmöbler i serieproduktion för:\nStudentbostäder, elev-, personal- o\nungkarlsbostäder, ålderdomshem,\nvårdhem, handikappade, motell\nsamt kontor. Belysning o mattor\nKontor: 217 42 Malmö, Kronborgsv\n8. Tel 040-10 03 70\nAntal anställda: 19\nÅrsomsättning: 7 000 000\nAktiekapital: 10 000\nVerkst dir: Ark Allan Karlsson\nEtableringsår: 1965.\n\nTENGBERG AB, OVE\n\nPnr 724 65\n\nVästerås. Köpingsv 42. Tel\n021-14 03 30, 14 08 40. Bankgiro\n63-4711. Postgiro 231120\nVerksamhet: Säljer kompletta\nkontorsinredningar, såsom möbler,\nmattor. gardiner m m, även för\npersonalrum, omklädningsrum m m.\nKontorsmaskiner såsom\nelektrostat-kopiering, kontorsoffset,\nelektroniska räknare samt 3 M:s visuella\nprodukter\nAntal anställda: 3\nÅrsomsättning: 1200 000\nAktiekapital: 5 000\nVerkst dir: Ove Tengberg\nEtableringsår: 1964\nOmbildat till aktiebolag 1967.\n\nTENGBLAD&amp; CO, AB\n\nPnr 431 35\n\nMölndal, Agatan 26 A. Tel\n031-27 09 22, 27 25 81. Bankgiro\n43-9823. Postgiro 45508\nVerksamhet: Tapetfabrik\n\"Tencota-peter’’\n\nAntal anställda: 12\nChef: Erik Tengblad\nEtableringsår: 1934.\n\nTENGGRENSTORPS TEGEL,\nAB\n\nPnr 46201\n\nVänersborg 1, Box 113. Tel\n0521-11011. 165 50. Bankgiro 888-7580.\nPostgiro 33360-9\nVerksamhet: Säljer allt i tegel\nAntal anställda: 5\nÅrsomsättning: 1700000\nAktiekapital: 50 000\nStyrelse: Disp Axel Bergstrand\n(ordf), fru Anna-Lisa Bergstrand,\ning Ivar Wulf\n\nVerkst dir: Disp Axel Bergstrand\nEtableringsår: 1958.\n\nTENHULTS\nIMPREGNERINGS-VERK, AB\n\nPnr 560 27\n\nTenhult, Äng sv 12. Tel 036-91660.\nBankgiro 837-2070. Postgiro\n100883-8\n\nVerksamhet Utför\ntryckimpregne-ring av trävaror samt säljer\ntryck-impregnerade trävaror\nAntal anställda: 15\nÅrsomsättning: 4 000 000\nAktiekapital: 35 000\nVerkst dir Gunnar Langemar\nEtableringsår 1956.\n\nHERBO, INGENIÖRSFIRMAN\n\nPnr 595 00\n\nMjölby, Kungsv 55.Tel 0142-100 15.\nBankgiro 128-3399. Postgiro\n382632-8\n\nVerksamhet: Konsulterande\ningenjörsfirma o maskinagentur\nChef: Civiling H Blomér\nEtableringsår: 1942.\n\nKILNER &amp; CO AB, GERHARD\n\nPnr 41707\n\nGöteborg, Stenkolsg 1 B. Tel\n031-2248 59, 22 48 60. Bankgiro\n50-8776. Postgiro 46763. Tga Gerkil\nVerksamhet: Tillverkar\nfartygaartiklar såsom klaffventiler\nAktiekapital: 50000\nVerkst dir: Gerhard Kilner\nDisp: Bengt Kilner\nEtableringsår: 1941.\n\nKILSHAMMARS MEKANISKA\nVERKSTAD KB\nH BÄCKSTRUM\n\nPnr 68101\n\nKristinehamn 1, Karlstadsv 42. Box\n40. Tel 0550-105 47. Bankgiro\n81-9939. Postgiro 23184\nVerksamhet: Tillverkar\ntråddrag-ningsmaskiner, spolverk o\nlinslag-ningsmaskiner för järn- o ståltråd.\nSpecialmaskiner o verktyg.\nLego-bearbetning: Svarvning i 20\" x 4\nm:s supportsvarv med gap 1450\nmm, bordhyvling 2000 x 700 x\n700 mm\n\nAntal anställda: 20\nÄgare o chef: Ing Lennart\nBäckström\n\nEtableringsår: 1920.\n\nSVECIA COMMERCE, AB\n\nPnr 17107\n\nSolna 7, Järvstigen 11. Box 725.\nTel 08-85 0110. Bankgiro 23-5202.\nPostgiro 159446. Tga Sveciacom.\nTelex 10769\n\nVerksamhet: Säljer slipmaterial o\nbandtraktordelar\nVarunamn: Atlantic, Hermes\nAntal anställda: 35\nÅrsomsättning: 5 000 000\nAktiekapital: 200 000\nVerkst din Kjell-Ake Sundqvist\nEtableringsår: 1950.\n\nSVECIA SILKSCREEN\nMASKINER AB\n\nPnr 145 53\n\nNorsborg, Fittja Industriområde,\nhus 1. Tel 08-7100180. Bankgiro\n100-0390. Postgiro 647901-8. Tga\nSveciascreen.\nTelex 17643 SVECIA S\nVerksamhet: Tillverkar o säljer\nmaskiner för silkscreentryck\nAntal anställda: 80\nÅrsomsättning: 8 000 000\nAktiekapital: 50 000\nVerkst dir: Ake Svantesson\nV verkst dir: Bruno Antman\nEtableringsår: 1964.\n\nINDUMATIK, AB\n\nPnr 600 10\n\nNoriköping 10, Västgöteg 13. Box\n10058. Tel 011-18 83 44. Bankgiro\n82-4528. Postgiro 666440-3\nVerksamhet: Tillverkar\nbagerimaskiner, förpackningsmaskiner o\nplastmaskiner\nAntal anstäUda: 6\nÅrsomsättning: 600 000\nAktiekapital: 5 000\nStyrelseordf: Dir Karl Olsson\nVerkst dir: Karl Olsson\nEtableringsår: 1964.\n\nINDUSTRI.\n\nse i övrigt resp namn.\n\nINDUSTRI &amp;\nBYGGNADS-VENTILATIONER, AB\n\nPnr 750 03\n\nUppsala 3, Verkstadsg 17. Box\n3034. Tel 018-10 21 30. Bankgiro\n80-2596. Postgiro 512922\nVerksamhet: Tillverkar o monterar\nventilationstekniska anläggningar\nAntal anstäUda: 20\nÅrsomsättning: 1000000\nChef: Dir Stig Karlsson\nEtableringsår: 1957.\n\nHUSUMS SNICKERI AB\n\nPnr 890 35\n\nHusum. Tel 0663-10145. Bankgiro\n76-9325. Postgiro 296096-1\nVerksamhet: Tillverkar\nmagasinskärror, rundstav, laddkäppar för\nsprängningsarbeten m m\nAntal anställda: 5\nÅrsomsättning: 300 000\nAktiekapital: 25 000\nVerkst dir: N Y Gustafsson\nEtableringsår 1947.",
    "structured": {
        "firms": [
            {
                "company_name": "EKDAHLS KONFEKTIONS AB",
                "pnr": "300 02",
                "address": "Halmstad 2, Box 2070. Sperlingsg.",
                "phone_number": "035-10 00 50",
                "bank_details": {
                    "bankgiro": "53-02 0 2",
                    "postgiro": "112561"
                },
                "activity": "Fabrik för tillverkning av klänningar",
                "employees": 80,
                "annual_turnover": 4000000,
                "capital": 70000,
                "key_personnel": [
                    {
                        "name": "Disp Gunnar Ekdahl",
                        "position": "Verkst dir"
                    }
                ],
                "establishment_year": 1957
            },
            {
                "company_name": "BORJESSON AB, AUG",
                "pnr": "292 00",
                "address": "Karlshamn, Ronnebyg 8",
                "phone_number": "0454-103 60,10597",
                "bank_details": {
                    "bankgiro": "86-2143",
                    "postgiro": "30273"
                },
                "activity": "Engros- o detaljförsäljning av sängkläder, trikåvaror",
                "employees": 11,
                "annual_turnover": 1150000,
                "capital": 50000,
                "key_personnel": [
                    {
                        "name": "Konsul Albert Börjesson",
                        "position": "Verkst dir"
                    }
                ],
                "establishment_year": 1888
            },
            {
                "company_name": "WISTA, HANDELSFIRMAN",
                "pnr": "43102",
                "address": "Mölndal 2, Abäcksg 6. Box 2014",
                "phone_number": "031-16 1525, 16 2520",
                "bank_details": {
                    "postgiro": "420890-2"
                },
                "activity": "Import av ritkontors-utensilier. Specialitet: kantmaskiner",
                "owners": "Göte Ackert",
                "establishment_year": 1949
            },
            {
                "company_name": "WISTRAND AB. INGENJÖRS-FIRMAN HANS",
                "pnr": "51035",
                "address": "Bollebygd, Angpannev 3",
                "phone_number": "033-856 40",
                "bank_details": {
                    "bankgiro": "532-1922",
                    "postgiro": "438069-7"
                },
                "activity": "Utför kem rengöring av ångpannor samt säljer vatten-reningsutrustning för ångpannor o swimmingpools",
                "employees": 7,
                "capital": 42000,
                "key_personnel": [
                    {
                        "name": "Fru Inga Wistrand",
                        "position": "Styrelse"
                    },
                    {
                        "name": "Fru Inga Wistrand",
                        "position": "Chef"
                    }
                ],
                "establishment_year": 1960
            },
            {
                "company_name": "AJCO TRIKÄFABRIK AB",
                "pnr": "41502",
                "address": "Göteborg, Artillerig 23",
                "phone_number": "031-25 00 30",
                "activity": "Tillverkar jerseyklänningar o jerseyväv",
                "sales_office": "Stockholm C, Kungsg 56. Tel 08-21 26 00, Köpenhamn K. Danajco Mode A/S, Vimmelskaftet 42 A. Tel Palae 9607",
                "annual_turnover": 400000,
                "capital": 400000,
                "key_personnel": [
                    {
                        "name": "Ing Bengt Löfmark",
                        "position": "Styrelse"
                    },
                    {
                        "name": "disp Arne Törnebrandt",
                        "position": "disp"
                    },
                    {
                        "name": "kamrer Bengt Olssön",
                        "position": "kamrer"
                    },
                    {
                        "name": "kamrer Ralph Wilson",
                        "position": "kamrer"
                    }
                ],
                "establishment_year": 1878
            },
            {
                "company_name": "ÅJO KYLINDUSTRI AB",
                "pnr": "43011",
                "address": "Träslövsläge, Box 54",
                "phone_number": "0340-700 68, 700 53",
                "bank_details": {
                    "bankgiro": "42-5189"
                },
                "activity": "Tillverkar kylskåp, kyldiskar o flaskkylare",
                "annual_turnover": 2000000,
                "capital": 20000,
                "key_personnel": [
                    {
                        "name": "Fabr Albert Olsson",
                        "position": "Styrelse (ordf)"
                    },
                    {
                        "name": "disp Buster Olsson",
                        "position": "disp"
                    },
                    {
                        "name": "ing Esse Olsson",
                        "position": "ing"
                    }
                ],
                "establishment_year": 1948
            },
            {
                "company_name": "AK INREDE AB",
                "pnr": "140 11",
                "address": "Vårby, Fittja Industriområde",
                "phone_number": "08-710 08 30",
                "bank_details": {
                    "bankgiro": "734-4443",
                    "postgiro": "554388-9"
                },
                "activity": "Egna specialritade möbler i serieproduktion för: Studentbostäder, elev-, personal- o ungkarlsbostäder, ålderdomshem, vårdhem, handikappade, motell samt kontor. Belysning o mattor",
                "office": "217 42 Malmö, Kronborgsv 8. Tel 040-10 03 70",
                "employees": 19,
                "annual_turnover": 7000000,
                "capital": 10000,
                "key_personnel": [
                    {
                        "name": "Ark Allan Karlsson",
                        "position": "Verkst dir"
                    }
                ],
                "establishment_year": 1965
            },
            {
                "company_name": "TENGBERG AB, OVE",
                "pnr": "724 65",
                "address": "Västerås, Köpingsv 42",
                "phone_number": "021-14 03 30, 14 08 40",
                "bank_details": {
                    "bankgiro": "63-4711",
                    "postgiro": "231120"
                },
                "activity": "Säljer kompletta kontorsinredningar, såsom möbler, mattor. gardiner m m, även för personalrum, omklädningsrum m m. Kontorsmaskiner såsom elektrostat-kopiering, kontorsoffset, elektroniska räknare samt 3 M:s visuella produkter",
                "employees": 3,
                "annual_turnover": 1200000,
                "capital": 5000,
                "key_personnel": [
                    {
                        "name": "Ove Tengberg",
                        "position": "Verkst dir"
                    }
                ],
                "establishment_year": 1964
            },
            {
                "company_name": "TENGBLAD& CO AB",
                "pnr": "431 35",
                "address": "Mölndal, Agatan 26 A",
                "phone_number": "031-27 09 22, 27 25 81",
                "bank_details": {
                    "bankgiro": "43-9823",
                    "postgiro": "45508"
                },
                "activity": "Tapetfabrik 'Tencota-peter’’",
                "employees": 12,
                "chief": "Erik Tengblad",
                "establishment_year": 1934
            },
            {
                "company_name": "TENGRENSTORPS TEGEL, AB",
                "pnr": "46201",
                "address": "Vänersborg 1, Box 113",
                "phone_number": "0521-11011, 165 50",
                "bank_details": {
                    "bankgiro": "888-7580",
                    "postgiro": "33360-9"
                },
                "activity": "Säljer allt i tegel",
                "employees": 5,
                "annual_turnover": 1700000,
                "capital": 50000,
                "key_personnel": [
                    {
                        "name": "Disp Axel Bergstrand",
                        "position": "Styrelse (ordf)"
                    },
                    {
                        "name": "fru Anna-Lisa Bergstrand",
                        "position": "fru"
                    },
                    {
                        "name": "ing Ivar Wulf",
                        "position": "ing"
                    }
                ],
                "establishment_year": 1958
            },
            {
                "company_name": "TENHULTS IMPREGNERINGS-VERK, AB",
                "pnr": "560 27",
                "address": "Tenhult, Äng sv 12",
                "phone_number": "036-91660",
                "bank_details": {
                    "bankgiro": "837-2070",
                    "postgiro": "100883-8"
                },
                "activity": "Utför tryckimpregne-ring av trävaror samt säljer tryck-impregnerade trävaror",
                "employees": 15,
                "annual_turnover": 4000000,
                "capital": 35000,
                "key_personnel": [
                    {
                        "name": "Gunnar Langemar",
                        "position": "Verkst dir"
                    }
                ],
                "establishment_year": 1956
            },
            {
                "company_name": "HERBO, INGENIÖRSFIRMAN",
                "pnr": "595 00",
                "address": "Mjölby, Kungsv 55",
                "phone_number": "0142-100 15",
                "bank_details": {
                    "bankgiro": "128-3399",
                    "postgiro": "382632-8"
                },
                "activity": "Konsulterande ingenjörsfirma o maskinagentur",
                "chief": "Civiling H Blomér",
                "establishment_year": 1942
            },
            {
                "company_name": "KILNER & CO AB, GERHARD",
                "pnr": "41707",
                "address": "Göteborg, Stenkolsg 1 B",
                "phone_number": "031-2248 59, 22 48 60",
                "bank_details": {
                    "bankgiro": "50-8776",
                    "postgiro": "46763"
                },
                "activity": "Tillverkar fartygaartiklar såsom klaffventiler",
                "capital": 50000,
                "key_personnel": [
                    {
                        "name": "Gerhard Kilner",
                        "position": "Verkst dir"
                    },
                    {
                        "name": "Bengt Kilner",
                        "position": "Disp"
                    }
                ],
                "establishment_year": 1941
            },
            {
                "company_name": "KILSHAMMARS MEKANISKA VERKSTAD KB",
                "pnr": "68101",
                "address": "Kristinehamn 1, Karlstadsv 42. Box 40",
                "phone_number": "0550-105 47",
                "bank_details": {
                    "bankgiro": "81-9939",
                    "postgiro": "23184"
                },
                "activity": "Tillverkar tråddrag-ningsmaskiner, spolverk o linslag-ningsmaskiner för järn- o ståltråd. Specialmaskiner o verktyg.",
                "lego-bearbetning": "Svarvning i 20\" x 4 m:s supportsvarv med gap 1450 mm, bordhyvling 2000 x 700 x 700 mm",
                "employees": 20,
                "chief": "Ing Lennart Bäckström",
                "establishment_year": 1920
            },
            {
                "company_name": "SVECIA COMMERCE, AB",
                "pnr": "17107",
                "address": "Solna 7, Järvstigen 11. Box 725",
                "phone_number": "08-85 0110",
                "bank_details": {
                    "bankgiro": "23-5202",
                    "postgiro": "159446"
                },
                "activity": "Säljer slipmaterial o bandtraktordelar",
                "varunamn": "Atlantic, Hermes",
                "employees": 35,
                "annual_turnover": 5000000,
                "capital": 200000,
                "key_personnel": [
                    {
                        "name": "Kjell-Ake Sundqvist",
                        "position": "Verkst din"
                    }
                ],
                "establishment_year": 1950
            },
            {
                "company_name": "SVECIA SILKSCREEN MASKINER AB",
                "pnr": "145 53",
                "address": "Norsborg, Fittja Industriområde, hus 1",
                "phone_number": "08-7100180",
                "bank_details": {
                    "bankgiro": "100-0390",
                    "postgiro": "647901-8"
                },
                "activity": "Tillverkar o säljer maskiner för silkscreentryck",
                "employees": 80,
                "annual_turnover": 8000000,
                "capital": 50000,
                "key_personnel": [
                    {
                        "name": "Ake Svantesson",
                        "position": "Verkst dir"
                    },
                    {
                        "name": "Bruno Antman",
                        "position": "V verkst dir"
                    }
                ],
                "establishment_year": 1964
            },
            {
                "company_name": "INDUMATIK, AB",
                "pnr": "600 10",
                "address": "Noriköping 10, Västgöteg 13. Box 10058",
                "phone_number": "011-18 83 44",
                "bank_details": {
                    "bankgiro": "82-4528",
                    "postgiro": "666440-3"
                },
                "activity": "Tillverkar bagerimaskiner, förpackningsmaskiner o plastmaskiner",
                "employees": 6,
                "annual_turnover": 600000,
                "capital": 5000,
                "key_personnel": [
                    {
                        "name": "Dir Karl Olsson",
                        "position": "Styrelseordf"
                    },
                    {
                        "name": "Karl Olsson",
                        "position": "Verkst dir"
                    }
                ],
                "establishment_year": 1964
            },
            {
                "company_name": "INDUSTRI & BYGGNADS-VENTILATIONER, AB",
                "pnr": "750 03",
                "address": "Uppsala 3, Verkstadsg 17. Box 3034",
                "phone_number": "018-10 21 30",
                "bank_details": {
                    "bankgiro": "80-2596",
                    "postgiro": "512922"
                },
                "activity": "Tillverkar o monterar ventilationstekniska anläggningar",
                "employees": 20,
                "annual_turnover": 1000000,
                "chief": "Dir Stig Karlsson",
                "establishment_year": 1957
            },
            {
                "company_name": "HUSUMS SNICKERI AB",
                "pnr": "890 35",
                "address": "Husum",
                "phone_number": "0663-10145",
                "bank_details": {
                    "bankgiro": "76-9325",
                    "postgiro": "296096-1"
                },
                "activity": "Tillverkar magasinskärror, rundstav, laddkäppar för sprängningsarbeten m m",
                "employees": 5,
                "annual_turnover": 300000,
                "capital": 25000,
                "key_personnel": [
                    {
                        "name": "N Y Gustafsson",
                        "position": "Verkst dir"
                    }
                ],
                "establishment_year": 1947
            }
        ]
    }
}