{
    "original": "TÄRNSJO ÅNGGARVERI AB\n\nPnr 740 45\n\nTärnsjö. Tel 0292-505 00. Bankgiro\n812-2269. Postgiro 22138-2. Tga\nTärnsjögarv\n\nVerksamhet: Tillverkar platt-,\nrem-o skoovanläder, sy- o Skoremmar\nav råläder, alla slags\nsadelmakeriet trav- o arbetsselar,\nsportartiklar\n\nAntal anställda: 45\nÅrsomsättning: 3 000 000\nAktiekapital: 100000\nVerkst din Torsten Åström\nAdministration o ekonomiavd:\nkamrer Sven-Olov Åkerlund\nEtableringsår. 1873\nOmbildat till aktiebolag 1935.\n\nTÖCKSFORS SNICKERI.\nFABRIK\n\nPnr 670 10\n\nTöcksfors. Tel 0573-210 56.\nBankgiro 116-3138. Postgiro 277150-9\n\nVerksamhet: Tillverkar\nbyggnads-snickerier. Specialitet:\nköksinredningar, dörrar, fönster o trappor\nÄgare o chefen David Olof Olsson,\nGustav Rickard Olsson\nEtableringsår 1931.\n\nFEMO-VERKEN, AB\n\nPnr 510 47\n\nFristad. Box 12. Tel 033-603 16,\n607 16. Bankgiro 84-4825.\nPostgiro 241720. Tga Femoverken\n\nVERKTYG, BRANDSPRUTOR\nSMÖRJ KANNOR och ELEKTRISK\nBELYSNINGSARMATUR\n\nVarunamn: Femo\nAktiekapital: 75 000\nVerkst dir Erik Nilsson\nEtableringsår: 1943.\n\nLIBRO AB, HANDELSFIRMAN\n\nPnr 403 13\n\nGöteborg 2, Ingenjörsg 5 o 3. Box\n2130. Tel 031-17 3140. Bankgiro\n513-6593. Postgiro 42612-2.\nTga Librex. Telex 20622\nVerksamhet: Import o export\nFilialer: Tokyo, Japan. Libro\nJapan Co Ltd. Telex 2572\nKöpenhamn. A/S Librodan,\nKron-prinsensvej 16. Tel Gothab\n0136-2585\n\nAntal anställda: 30\nChef: Dir Armand Johansson\nDisp: Allan Gustafsson\nEtableringsår: 1950.\n\nLIDANS MOTORVERKSTAD,\nAB\n\nPnr 53101\n\nLidköping 1, Kållandsg 22. Box 54.\nTel 0510-20259, 20286. Tga Lidan\nVerksamhet: Tillverkar spel o\nvinschar. Specialitet: Hydrauliska\ndäcksmaskiner för fartyg\nVarunamn: Lidan\nAntal anställda: 35\nÅrsomsättning: 2 500 000\nAktiekapital: 50 000\nVerkst dir: C G Friman\nVerkstadsing: Th Friman\nEtableringsår: 1910.\n\nSJUDING &amp; CO, JOHN\n\nPnr 171 52\n\nSolna, Gårdsv 2-4. Tel 08-83 03 85.\nBankgiro 576-2117. Postgiro\n158571-0\n\nVeiksamhet: Tillverkar\ndentalartik-lar. Legotillverkning i\nautomatsvarvar o centerlessmaskiner\nAntal anställda: 55\nÅrsomsättning: 8 000 000\nChef: Ing Magnus Engström\nVerkstadschef: Ing Klas Tofft\nKamrer Lars Håård\nEtableringsån 1917\nDotterbolag: Sjödings\nDentalpro-dukter AB.\n\nSJÖGRENS SKYDDSVANTE,\nAB\n\nPnr 293 00\n\nOlofström. Tel 0454-463 00.\nBankgiro 15-1711. Postgiro 164153.\nTga Safety, Karlshamn. Telex 4515\nVerksamhet: Tillverkar o\nimporterar personlig\narbetarskyddsutrustning. Bil- o b åt inredningar\nAntal anställda: 200\nÅrsomsättning: 18000 000\nAktiekapital: 500 000\nStyrelse: Dir Karl Granfors (ordf),\ndir Nils Gunnar Nilsson, dir\nValter Sjögren\n\nVerkst din Nils Gunnar Nilsson\nEtableringsån 1939\nOmbildat till aktiebolag 1960.\n\nSJÖGRENS MASKIN AB, H\n\nPnr 78101\n\nBorlänge 1. Box 56. Tel\n0243-115 56. Bankgiro 79-4549.\nPostgiro 291074. Tga Radimatic\nVeiksamhet: Tillverkar Radimatic\ngängmaskiner\nAntal anställda: 12\nÅrsomsättning: 1500 000\nÄgare o chefer Helge Sjögren,\nElsie Sjögren.\n\nSJÖGREN, BYGGNADS AB\nHARRY\n\nPnr 50106\n\nBorås 1, Sandgärdsg 7. Box 381.\nTel 033-13 60 80. Bankgiro 83-9265.\nPostgiro 137304\n\nVeiksamhet: Byggnadsfirma för\nbostads-, affärs- o industribyggnader\nAvdelningskontor: Jönköping. Tel\n036-1196 35\n\nGöteborg. Tel 031-87 03 40\nMariestad. Tel 0501-138 15\n\nAntal anställda: 870\n\nÅrsomsättning: 100000 000\nAktiekapital: 1000 000\nVeikst din Byggmäst Harry\nSjögren\n\nEtableringsån 1945.\n\nBJÖRKMAN &amp; HENSTAM BIL AB\n\nPnr 72137\n\nVästerås, Box 974. Strömledningsg\n5. Tel 021-14 43 50. Bankgiro\n808-8957. Postgiro 664050-2\nVerksamhet: Representant för\nSAAB-Scania AB\nAntal anställda: 75\nÅrsomsättning: 30 000 000\nAktiekapital: 150 000\nVerkst dir: Bertil Björkman\nEtableringsår: 1964.\n\nBJÖRKMAN AB, G A\n\nPnr 21618\n\nMalmö, Bülow Hübes v 16. Tel\n040-16 03 01, 1603 02. Postgiro\n435316-5. Tga Gabagentur.\nTelex 32436\n\nVerksamhet: Säljer stålrör,\nmetaller, fälgar, gångjärn o styrstag\nEtableringsår: 1960.\n\nHEL\n\n36003. Gbg36. Tel 031-15 7001\nAntal anställda: 40\nÅrsomsättning: 5 000 000\nAktiekapital: 120 000\nVetkst dir: J Magnusson\nEtableringsàr: 1919.\n\nHELLQWIST &amp; CO AB, G\n\nPnr 573 00\n\nTranås, ö Järnvägsg 8. Tel\n0140-130 85. Bankgiro 365-6337.\nPostgiro 130643-0\n\nVerksamhet: Tillverkar dampälsar,\npälsmössor o päls hattar\nAntal anställda: 20\nÅrsomsättning: 2 000 000\nAktiekapital: 150 000\nVerkst dir: Sture Alenius\nEtableringsàr: 1937.\n\nHELLMANS GJUTERI OCH\nMEK VERKSTADS AB\n\nPnr 778 01\n\nNorberg 1, Nytg 1. Box 54. Tel\n0223-20132, 21132. Bankgiro\n231-6321. Postgiro 133019-0\nVerksamhet: Gjuteri o mekanisk\nverkstad\n\nAntal anställda: 40\nÅrsomsättning: 2 200 000\nAktiekapital: 50 000\nVerkst dir: Alvar G Hellman\nEtableringsàr: 1930.\n\nHELLMANS\nKONSTRUKTIONS-BYRÅ AB\n\nPnr 117 21\n\nStockholm, Hornsg 40. Tel\n08-4013 31, 4013 36. Bankgiro\n44-7189. Postgiro 55986\nVerksamhet: Processer o\nutrustningar till kemiska industrin\nAktiekapital: 50 000\nVerkst dir: Civiling L-G Hellman\nEtableringsàr: 1958.\n\nHELLMAN &amp; TRYGG TRYCK.\nTEKNIK AB\n\nPnr 59103\n\nMotala 3, Box 342. Merkuriusg. Tel\n0141-185 33. Bankgiro 822-0550.\nPostgiro 205163-9\nVerksamhet: Reproduktionsanstalt\nAntal anställda: 17\nAktiekapital: 60 000\nVerkst dir: Jan Trygg\nEtableringsàr: 1961.\n\nHELLMER PLÅTINDUSTRI AB\n\nPnr60105\n\nNorrköping 5, Box 460.\nFredriks-dalsg 25. Tel 011-18 64 00.\nBankgiro 125-1313. Postgiro 132899-6\n\ni:i\n\nVerksamhet: Tillverkar rostfri\nmanufaktur med höga krav på ytfinish.\nVerkstadsplåtslageri med inriktning\npå precision samt konventionellt\nbyggnadsplåtslageri\nAntal anställda: 40\nÅrsomsättning: 3 500 0 00\nAktiekapital: 50 000\nVerkst dir: Ing Bengt Hellmer\n\nEtableringsàr: 1926\nOmbildat till aktiebolag 1959.\nNamnändring 1969.\n\nHELLSTEN AB, OTTO\n\nPnr 11130\n\nStockholm, Skeppsbron 30. Tel\n08-10 02 01, 10 6195. Bankgiro\n729-5116. Postgiro 191376-3. Tga\nHelistens. Telex 19179\nVerksamhet: Skeppsmäkleri\nAktiekapital: 90 000\nVerkst dir: Richard Kjellberg\nEtableringsàr: 1819.\n\nHELLSTRANDS INDUSTRI AB\n\nPnr 113 40\n\nStockholm, Rörstrandsg 8. Tel\n08-30 50 70. Postgiro 350943\nVerksamhet: Tillverkar o säljer\npersienner o jalusier\nAntal anställda: 3\nÅrsomsättning: 200 000\nAktiekapital: 20 000\nVerkst dir: Ing Ivan Hellstrand\nEtableringsàr 1951.\n\nSCANMEDA, AB\n\nPnr 411 21\n\nGöteborg, Stora Badhusg 20. Tel\n031-1752 95. Bankgiro 50-1248.\nPostgiro 643994. Tga Scanmeda.\nTelex 2255\n\nVerksamhet: Generalagent för ICI\nPharmaceuticals Division,\nStorbritannien\nAntal anstäUda: 27\nÅrsomsättning: 18000 000\nAktiekapital: 800 000\nVerkst dir: Roland Corsing\nEtableringsår: 1964\nIngår jämte Scanmeda i Danmark,\nFinland o Norge i Fortiagruppen.\n\nSCANOMATIC LTD, AB\n\nPnr 262 01\n\nÄngelholm 1, Box 61. Tel\n0431-30242. Bankgiro 672-3241.\nPostgiro 590299-4. Tga Scanomatic\nVerksamhet Tillverkar handstöpta\nantikljus o dekorationsljus\nAntal anstäUda: 20\nÅrsomsättning: 1000 000\nAktiekapital: 5 000\nVerkst dir: Civilekonom Eugén\nJakobsson\nEtableringsår: 1962.\n\nmaskinkop ab\n\nPnr 753 23\n\nUppsala, Danmarksg 55. Tel\n018-111220. Telex 74 2 2 VALMET S.\nTga Maskinköp\n\nVerksamhet: Säljer lantbruks-,\nskogs- o industrimaskiner\nAntal anställda: 45\nÅrsomsättning: 8 000 000\nAktiekapital: 1800 000\nVeikst dir: Lars Colliander\nEtableringsår: 1964.\n\nTJÄRNANS BETONG AB\n\nPnr 776 00\n\nHedemora, Box 3306. Tel\n0225-330 02, 330 88. Bankgiro 795-5206.\nPostgiro 399838-2\nVerksamhet: Tillverkar betong,\nFibo-produkter, EW bjälklag\nAntal anställda: 18\nÅrsomsättning: 1800 000\nAktiekapital: 120 000\nVerkst dir: Lars-Ake Norgren\nEtableringsår: 1952.\n\nTJÄRNBERG, BYGGNADS\nAB O\n\nPnr 89101\n\nÖrnsköldsvik 1, Storg 3. Box 190.\nTel 0660-105 85. Postgiro 62962\nVerksamhet: Entreprenadfirma för\nbostads- o affärshus samt\nindustribyggnader, lasarett, skolor mm\nAntal anställda: 325\nAktiekapital: 175 000\nVerkst din Civiling Gunnar\nTjernberg\n\nEtableringsår 1918\nOmbildat till aktiebolag 1954.\n\nTJÄRNVIKS SNICKERI.\nFABRIK, AB\n\nPnr 820 77\n\nGnarp. Tel 0652-200 33, 203 30.\nBankgiro 77-5538. Postgiro 25075\nVerksamhet: Tillverkar\nbyggnadssnickerier, köksinredningar o\nträ-varor\n\nAntal anställda: 100\nÅrsomsättning: 6 500 000\nAktiekapital: 500 000\nÄgare o chefer: Olle Andersson,\nSven Andersson\nEtableringsår. 1925.\n\nPLANKONSULT AB\n\nPnr 116 20\n\nStockholm, Högbergsg 30 A. Tel\n08-23 26 05. Bankgiro 28-4770.\nPostgiro 603022\n\nVerksamhet: Konsulterande\ningenjörs- o arkitektrörelse\nAntal anställda: 25\nÅrsomsättning: 1800 000\nAktiekapital: 5 000\nVerkst dir: Tekn lic Ebbe\nEber-hardson\n\nEtableringsår: 1961.",
    "structured": {
        "1": {
            "company_name": "TÄRNSJO ÅNGGARVERI AB",
            "pnr": "740 45",
            "address": "Tärnsjö",
            "phone_number": "0292-505 00",
            "bank_details": {
                "bankgiro": "812-2269",
                "postgiro": "22138-2"
            },
            "activity": "Tillverkar platt-, rem-o skoovanläder, sy- o Skoremmar av råläder, alla slags sadelmakeriet trav- o arbetsselar, sportartiklar",
            "employees": 45,
            "annual_turnover": 3000000,
            "capital": 100000,
            "key_personnel": [
                {
                    "name": "Torsten Åström",
                    "position": "Verkst din"
                },
                {
                    "name": "Sven-Olov Åkerlund",
                    "position": "kamrer"
                }
            ],
            "establishment_year": 1873
        },
        "2": {
            "company_name": "TÖCKSFORS SNICKERI. FABRIK",
            "pnr": "670 10",
            "address": "Töcksfors",
            "phone_number": "0573-210 56",
            "bank_details": {
                "bankgiro": "116-3138",
                "postgiro": "277150-9"
            },
            "activity": "Tillverkar byggnads-snickerier. Specialitet: köksinredningar, dörrar, fönster o trappor",
            "establishment_year": 1931
        },
        "3": {
            "company_name": "FEMO-VERKEN, AB",
            "pnr": "510 47",
            "address": "Fristad",
            "phone_number": "033-603 16, 607 16",
            "bank_details": {
                "bankgiro": "84-4825",
                "postgiro": "241720"
            },
            "activity": "Tillverkar Verktyg, brandsprutor, smörjkannor och elektrisk belysningsarmatur. Varunamn: Femo",
            "capital": 75000,
            "key_personnel": [
                {
                    "name": "Erik Nilsson",
                    "position": "Verkst dir"
                }
            ],
            "establishment_year": 1943
        },
        "4": {
            "company_name": "LIBRO AB, HANDELSFIRMAN",
            "pnr": "403 13",
            "address": "Göteborg 2, Ingenjörsg 5 o 3, Box 2130",
            "phone_number": "031-17 3140",
            "bank_details": {
                "bankgiro": "513-6593",
                "postgiro": "42612-2"
            },
            "activity": "Import o export",
            "employees": 30,
            "establishment_year": 1950
        },
        "5": {
            "company_name": "LIDANS MOTORVERKSTAD, AB",
            "pnr": "53101",
            "address": "Lidköping 1, Kållandsg 22, Box 54",
            "phone_number": "0510-20259, 20286",
            "activity": "Tillverkar spel o vinschar. Specialitet: Hydrauliska däcksmaskiner för fartyg. Varunamn: Lidan",
            "employees": 35,
            "annual_turnover": 2500000,
            "capital": 50000,
            "key_personnel": [
                {
                    "name": "C G Friman",
                    "position": "Verkst dir"
                },
                {
                    "name": "Th Friman",
                    "position": "Verkstadsing"
                }
            ],
            "establishment_year": 1910
        },
        "6": {
            "company_name": "SJUDING & CO, JOHN",
            "pnr": "171 52",
            "address": "Solna, Gårdsv 2-4",
            "phone_number": "08-83 03 85",
            "bank_details": {
                "bankgiro": "576-2117",
                "postgiro": "158571-0"
            },
            "activity": "Tillverkar dentalartik-lar. Legotillverkning i automatsvarvar o centerlessmaskiner",
            "employees": 55,
            "annual_turnover": 8000000,
            "establishment_year": 1917
        },
        "7": {
            "company_name": "SJÖGRENS SKYDDSVANTE, AB",
            "pnr": "293 00",
            "address": "Olofström",
            "phone_number": "0454-463 00",
            "bank_details": {
                "bankgiro": "15-1711",
                "postgiro": "164153"
            },
            "activity": "Tillverkar o importerar personlig arbetarskyddsutrustning, bil- o b åt inredningar",
            "employees": 200,
            "annual_turnover": 18000000,
            "capital": 500000,
            "key_personnel": [
                {
                    "name": "Karl Granfors",
                    "position": "Verkst din"
                }
            ],
            "establishment_year": 1939
        },
        "8": {
            "company_name": "SJÖGRENS MASKIN AB, H",
            "pnr": "78101",
            "address": "Borlänge 1, Box 56",
            "phone_number": "0243-115 56",
            "bank_details": {
                "bankgiro": "79-4549",
                "postgiro": "291074"
            },
            "activity": "Tillverkar Radimatic gängmaskiner",
            "employees": 12,
            "annual_turnover": 1500000,
            "key_personnel": [
                {
                    "name": "Helge Sjögren",
                    "position": "Ägare o chefer"
                },
                {
                    "name": "Elsie Sjögren",
                    "position": "Ägare o chefer"
                }
            ]
        },
        "9": {
            "company_name": "SJÖGREN, BYGGNADS AB HARRY",
            "pnr": "50106",
            "address": "Borås 1, Sandgärdsg 7, Box 381",
            "phone_number": "033-13 60 80",
            "bank_details": {
                "bankgiro": "83-9265",
                "postgiro": "137304"
            },
            "activity": "Byggnadsfirma för bostads-, affärs- o industribyggnader",
            "employees": 870,
            "annual_turnover": 100000000,
            "capital": 1000000,
            "key_personnel": [
                {
                    "name": "Byggmäst Harry Sjögren",
                    "position": "Verkst din"
                }
            ],
            "establishment_year": 1945
        },
        "10": {
            "company_name": "BJÖRKMAN & HENSTAM BIL AB",
            "pnr": "72137",
            "address": "Västerås, Box 974, Strömledningsg 5",
            "phone_number": "021-14 43 50",
            "bank_details": {
                "bankgiro": "808-8957",
                "postgiro": "664050"
            },
            "activity": "Representant för SAAB-Scania AB",
            "employees": 75,
            "annual_turnover": 30000000,
            "capital": 150000,
            "key_personnel": [
                {
                    "name": "Bertil Björkman",
                    "position": "Verkst dir"
                }
            ],
            "establishment_year": 1964
        }
    }
}