{
    "original": "hållsta mekaniska\nverkstad, ab\n\nPnr 63370\n\nEskilstuna, Industriv 6, Hållsta.\nTel 016-21060. Bankgiro 831-2373.\nPostgiro 267454-7\nVerksamhet: Svarvning, fräsning o\ngängning. Automatsvarvade\nstoppskruvar. Specialitët:\nstandardiserade bultartiklar samt skärtrissor\ntill alla röravskärare\nAntal anställda: 12\nÅrsomsättning: 1500000\nAktiekapital: 75000\nVerkst dir Töre Grandin\nEtableringsår: 1964.\n\nFRI\n\nFRIDMAN, AB C A\n\nPnr 652 24\n\nKarlstad, Herrgårdsg 3. Tel\n054-115115. Bankgiro 100-0363.\nPostgiro 76316-9. Tga Fridmanson.\nTelex 66102 FRIDMAN S\nVerksamhet: Försäljning av m\nastoner, redskap o förnödenheter för\ncharkuteri er o slakterier\nVarunamn: CAF\nAntal anställda: 10\nÅrsomsättning: 4 000 000\nAktiekapital: 100000\nStyrelse: Civilekonom Magnus\nFridman (ordf), dir G Johansson, kamrer\nE Stolpe, ekonom B Fridman\nVerkst dir: Gunnar Johansson\nEtableringsår: 1888.\n\nAHL-, se AL.\n\nAl-GRUPPEN AB\n\nPnr 11129\n\nStockholm, Järntorget 78. Tel\n08-24 06 70. Bankgiro 297-8062.\nPostgiro 405 850-9\n\nVerksamhet: Integrerad\nbyggprojek-tering, lokalprogram,\nfunktions-studier, tekniska o\ntekniskt/ekonomiska analyser, utveckling av\nbyggsystem etc.\n\nDelägare i ai-gruppen: Bengt\nHide-mark Gösta Danielson\nArkitektkontor AB, Ingenjörsfirman\nJacobson &amp; Widmark AB, Folke Johanson\nIngenjörsbyrå AB, Lars-Erik\nBengtsson AB\nÅrsomsättning: 2 000000\nAktiekapital: 100 000\nVerkst dir: Ark SAR Bengt\nHlde-mark\n\nEtableringsår: 1966.\n\nNYH\n\nPlatschef: Overing Bo Rapp\nFörsäljn-ing: Kjell Holmberg\nKassa: Töre Rundberg\nRitkontor Kenth Broberg\nVerkstäder. Birger Karlsson,\nVerner Pettersson\nSågverksinsp: Olle Ericsson\nEtableringsår: 1600-talet\nOmbildat till aktiebolag 1929.\nÄgare: Sala Maskinfabriks AB,\nSala.\n\nNYHEMS MEKANISKA\nVERKSTAD, AB\n\nPnr 30004\n\nHalmstad 4, Knäredsg. Box 4007.\nTel 035-1187 60. Bankgiro 33-8971.\nPostgiro 30534. Tga Erex\nVerksamhet: Utför\npressningsarbeten, rörbockningsarbeten,\nsvetsning o lödning, förnickling,\nför-kromning, förzinkning\nAntal anställda: 260\nÅrsomsättning: 18 000 000\nAktiekapital: 1000 000\nStyrelse: Dir Ulf Schële (ordf), dir\nUlf Rex, verkstadschef Ingmar Rex,\ning Bo Rex, disp Sven Nilsson\nVerkst dir: Ulf Rex\nDisp: Sven Nilsson\nVerkstadschef: Ingmar Rex\nEtableringsår: 1919\nOmbildat till aktiebolag 1934.\n\nNYHEMSPRODUKTER\nRUD BERGGREN, AB\n\nPnr 112 56\n\nStockholm, Rålambsv 66 A. Tel\n08-5166 82. Bankgiro 233-1718,\n806-4529. Postgiro 464920-8\nVerksamhet: Grosshandel med\nkemisk-tekniska artiklar\nÅrsomsättning: 39 800\nAktiekapital: 10 000\nVerkst dir: Rudolf Berggren\nEtableringsår: 1950.\n\nARA JÖNKÖPING AB\n\nPnr 551 02\n\nJönköping 1, Box 466. Kämpev 7.\nTel 036-11 87 60. Bankgiro\n271-7429. Postgiro 75817-7\nVerksamhet: Säljer eldnings-,\ndiesel- o smörjoljor, koks m m\nAntal anställda: 17\nÅrsomsättning: 10 000 000\nAktiekapital: 100 000\nPlatschef: Disp Yngve Norén\nEtableringsår: 1919.\n\nBURROUGHS AB\n\nPnr 115 22\n\nStockholm, Banérg 10. Tel\n08-63 58 80. Tga Burad\nVerksamhet: Räkne-, fakturerings-,\nbokförings- o EDB-maskiner\nAktiekapital: 125 000\nVerkst dir: Th Nilsson\nEtableringsår: 1957.\n\nTROËDSSON &amp; CO AB, NILS\n\nPnr 401 23\n\nGöteborg 1. Box 208. Gullbergs\nStrandg 1. Tel 031-17 52 20.\nBankgiro 506-5172. Postgiro 12340-6.\nTga Tro. Telex 2550\nVerksamhet: Ir&gt; o utländska\nträslag o byggnadsmaterial\nAntal anställda: 130\nAktiekapital: 2 000 000\nVerkst din Töre Bergbrant\nEtableringsår: 1944.\n\nTROËDSSON PAPER CO AB,\nNILS\n\nPnr 401 23\n\nGöteborg 1, Gullbergs Strandg 1.\nBox 217. Tel 031-17 52 20.\nBankgiro 506-7301. Postgiro 49055-7.\nTga Troed. Telex 20641TROED S\nVerksamhet: Export av papper,\npapp o kartong\nAktiekapital: 300 000\nVerkst dir: Bengt Hellström\nEtableringsår: 1944.\n\nTROENTORPS\nTOFFEL-F AB RIK AB\n\nPnr 260 90\n\nBåstad. Tel 0431-732 00. Bankgiro\n650-8766. Postgiro 388720-5\nVerksamhet: Trätoffeltillverkning\nVarunamn: Båstad-Toffeln\nAntal anställda: 80\nÅrsomsättning: 5 000 000\nAktiekapital: 170 000\nChefer: Fabr Börje Johansson,\nfabr-chef Stig Johansson\nEtableringsån 1907\nOmbildat till aktiebolag 1965.\n\nTROFÉ AB\n\nPnr 560 20\n\nBankgiro 835-8327. Postgiro\n144142-7. Tga Trofé\nVerksamhet: Säljer korsetter,\nbysthållare o liknande artiklar\nVarunamn: Trofé\nAntal anställda: 60\nÅrsomsättning: 3 000 000\nAktiekapital: 10 000\nVerkst dir: Karl P Erenhag\nDisp: Ingemar Ehrnström\nEtableringsår: 1951\nOmbildat till aktiebolag 1962.\nDotterbolag till AB Slättens\nIndustrier, Norrahammar.\n\nTROLLBO AB\n\nPnr 78012\n\nStora Sked vi. Tel 0225-440 00.\n\nBankgiro 792-7338. Postgiro\n338137-3\n\nVerksamhet: Tillverkar betongvaror\nAntal anställda: 30\nÅrsomsättning: 3000 000\nAktiekapital: 300 000\nStyrelse: Adv Lennart Zedendahl\n(ordf), dir H W Bergman, bergsing\nErik Bergman\n\nVerkst dir: Ragnar Källberg\nEtableringsår: 1948.\n\nSTOCKHOLMS KLICHÉ AB\n\nPnr 113 30\n\nStockholm, Hudiksvallsg 6. Tel\n08-34 94 85. Bankgiro 722-5261.\nPostgiro 605950-5\n\nVerksamhet: Tillverkar o säljer\nklichéer\n\nAntal anstäUda: 10\nÅrsomsättning: 1000 000\nAktiekapital: 50 000\nStyrelse: Adv Erie Lindé (ordf), dir\nRemy A Ek, kemigraf Bo\nHelgesson, kemigraf Georg Wennström\nVerkst dir: Remy A Ek\nEtableringsår: 1959.\n\nSTOCKHOLMS\nKÖLA-FABRIK, AB\n\nPnr 11130\n\nStockholm, Skeppsbron 16. Tel\n08-214750. Postgiro 52825. Tga\nParadkola\n\nVerksamhet: Tillverkar\nkonfektyre r\n\nFabrik: Sundbyberg, Stationsg 6.\nTel 08-28 20 58\nAntal anstäUda: 25\nAktiekapital: 500 000\nVerkst dir: Oscar Fried\nEtableringsår: 1931.\n\nSTOCKHOLMS KOPIERINGS.\nANSTALT TORVALD HULT AB\n\nPnr 11151\n\nStockholm, Drottningg 31. Tel\n08-1418 95, 11 10 92. Bankgiro\n56-0627. Postgiro 3669-9. Tga\nHult-kopior\n\nVerksamhet: Ljuskopiering\nAntal anstäUda: 10\nAktiekapital: 30 000\nStyrelseordf: Dir Sylvi Hult\nVerkst dir: Sylvi Hult\nEtableringsår: 1905.\n\nSTOCKHOLMS KRAV\nATT-FABRIK, AB\n\nPnr 104 30\n\nStockholm 45, Drottningg 110. Box\n45086. Tel 08-30 60 16. Bankgiro\n72-8788. Postgiro 452200. Tga\nCordon-bleu\n\nVerksamhet: Tillverkar\nslipsar,but-terflies o rosetter\nAntal anställda: 20\nÅrsomsättning: 1350 000\nAktiekapital: 50 000\nVerkst dir: Bertil Weitz\nEtableringsår: 1950.\n\nSTOCKHOLMS LJUSKOPIERING\nAB\n\nPnr 12173\n\nJohanneshov, Importörv 23. Tel\n08-91 92 80. Bankgiro 744-4045.\nPostgiro 657154-1\nÅrsomsättning: 140000\nAktiekapital: 5 000\nVerkst dir: Ing Jonas Englund\nEtableringsår: 1962.\n\nINDUSTRI-REPARATIONER\n\nPnr 63005\n\nEskilstuna 5, Hejarg 5. Box 5024.\nTel 016-11 17 63. Bankgiro\n604-4366. Postgiro 583494-0\nVerksamhet: Maskinrenoveringar o\nmek arbeten\n\nÄgare o chef: Sigurd Ericson\nEtableringsår: 1961.\n\nGEIJER &amp; SÖNER, AB\n\nPnr 360 62\n\nLångasjö. Tel 0477-502 60.\nBankgiro 85-4973. Postgiro 9372. Tga\nGeijerträ. Telex 4613\nVerksamhet: Sågverk o\nträvaruexport\n\nAntal anställda: 60\nAktiekapital: 600 000\nVerkst dir: Disp Herbert Geijer\nEtableringsår: 1902.",
    "structured": {
        "1": {
            "company_name": "hållsta mekaniska verkstad, ab",
            "activity": "Svarvning, fräsning o gängning. Automatsvarvade stoppskruvar. Specialitët: standardiserade bultartiklar samt skärtrissor till alla röravskärare",
            "establishment_year": 1964,
            "employees": 12,
            "annual_turnover": 1500000,
            "capital": 75000
        },
        "2": {
            "company_name": "FRI",
            "activity": "Försäljning av m astoner, redskap o förnödenheter för charkuteri er o slakterier",
            "establishment_year": 1888,
            "employees": 10,
            "annual_turnover": 4000000,
            "capital": 100000
        },
        "3": {
            "company_name": "Al-GRUPPEN AB",
            "address": "Järntorget 78",
            "activity": "Integrerad byggprojek-tering, lokalprogram, funktions-studier, tekniska o tekniskt/ekonomiska analyser, utveckling av byggsystem etc.",
            "establishment_year": 1966,
            "annual_turnover": 2000000,
            "capital": 100000
        },
        "4": {
            "company_name": "NYH",
            "establishment_year": "1600-talet",
            "owner": "Sala Maskinfabriks AB, Sala"
        },
        "5": {
            "company_name": "NYHEMS MEKANISKA VERKSTAD, AB",
            "address": "Knäredsg. Box 4007",
            "activity": "Utför pressningsarbeten, rörbockningsarbeten, svetsning o lödning, förnickling, för-kromning, förzinkning",
            "establishment_year": 1919,
            "employees": 260,
            "annual_turnover": 18000000,
            "capital": 1000000
        },
        "6": {
            "company_name": "NYHEMSPRODUKTER RUD BERGGREN, AB",
            "address": "Rålambsv 66 A",
            "activity": "Grosshandel med kemisk-tekniska artiklar",
            "establishment_year": 1950,
            "annual_turnover": 39800,
            "capital": 10000
        },
        "7": {
            "company_name": "ARA JÖNKÖPING AB",
            "address": "Box 466. Kämpev 7",
            "activity": "Säljer eldnings-, diesel- o smörjoljor, koks m m",
            "establishment_year": 1919,
            "employees": 17,
            "annual_turnover": 10000000,
            "capital": 100000
        },
        "8": {
            "company_name": "BURROUGHS AB",
            "address": "Banérg 10",
            "activity": "Räkne-, fakturerings-, bokförings- o EDB-maskiner",
            "establishment_year": 1957,
            "capital": 125000
        },
        "9": {
            "company_name": "TROËDSSON & CO AB, NILS",
            "address": "Box 208. Gullbergs Strandg 1",
            "activity": "Ir&gt; o utländska träslag o byggnadsmaterial",
            "establishment_year": 1944,
            "employees": 130,
            "capital": 2000000
        },
        "10": {
            "company_name": "TROËDSSON PAPER CO AB, NILS",
            "address": "Gullbergs Strandg 1. Box 217",
            "activity": "Export av papper, papp o kartong",
            "establishment_year": 1944,
            "capital": 300000
        },
        "11": {
            "company_name": "TROENTORPS TOFFEL-F AB RIK AB",
            "activity": "Trätoffeltillverkning",
            "establishment_year": 1907,
            "employees": 80,
            "annual_turnover": 5000000,
            "capital": 170000
        },
        "12": {
            "company_name": "TROFÉ AB",
            "activity": "Säljer korsetter, bysthållare o liknande artiklar",
            "establishment_year": 1951,
            "employees": 60,
            "annual_turnover": 3000000,
            "capital": 10000,
            "owner": "Dotterbolag till AB Slättens Industrier, Norrahammar"
        },
        "13": {
            "company_name": "TROLLBO AB",
            "address": "Stora Sked vi",
            "activity": "Tillverkar betongvaror",
            "establishment_year": 1948,
            "employees": 30,
            "annual_turnover": 3000000,
            "capital": 300000
        },
        "14": {
            "company_name": "STOCKHOLMS KLICHÉ AB",
            "address": "Hudiksvallsg 6",
            "activity": "Tillverkar o säljer klichéer",
            "establishment_year": 1959,
            "employees": 10,
            "annual_turnover": 1000000,
            "capital": 50000
        },
        "15": {
            "company_name": "STOCKHOLMS KÖLA-FABRIK, AB",
            "address": "Skeppsbron 16",
            "activity": "Tillverkar konfektyre r",
            "establishment_year": 1931,
            "employees": 25,
            "capital": 500000
        },
        "16": {
            "company_name": "STOCKHOLMS KOPIERINGS. ANSTALT TORVALD HULT AB",
            "address": "Drottningg 31",
            "activity": "Ljuskopiering",
            "establishment_year": 1905,
            "employees": 10,
            "capital": 30000
        },
        "17": {
            "company_name": "STOCKHOLMS KRAV ATT-FABRIK, AB",
            "address": "Drottningg 110. Box 45086",
            "activity": "Tillverkar slipsar, butterflies o rosetter",
            "establishment_year": 1950,
            "employees": 20,
            "annual_turnover": 1350000,
            "capital": 50000
        },
        "18": {
            "company_name": "STOCKHOLMS LJUSKOPIERING AB",
            "address": "Importörv 23",
            "activity": "N/A",
            "establishment_year": 1962,
            "annual_turnover": 140000,
            "capital": 5000
        },
        "19": {
            "company_name": "INDUSTRI-REPARATIONER",
            "address": "Hejarg 5. Box 5024",
            "activity": "Maskinrenoveringar o mek arbeten",
            "establishment_year": 1961,
            "owner": "Sigurd Ericson"
        },
        "20": {
            "company_name": "GEIJER & SÖNER, AB",
            "address": "Långasjö",
            "activity": "Sågverk o trävaruexport",
            "establishment_year": 1902,
            "employees": 60,
            "capital": 600000
        }
    }
}