{
    "original": "ERGO, ELEKTRISKA AB\n\nPnr 723 35\n\nVästerås, Ängsg4. Tel 021-1443 45.\nBankgiro 808-6167. Postgiro 8702-3,\nTga Ergo\n\nVerksamhet: Tillverkar elektriska\napparater, värmeskåp, värmepaneler,\nmarkupptiningsaggregat samt\nel-uppvärmda brandposter\nVarunamn: Ergo\nAntal anställda: 30\nÅrsomsättning: 3 600 000\nAktiekapital: 120 000\nVerkst dir: Georg Hammarqvist\nDisp: Per Hammarqvist\nEtableringsår 1922.\n\nPALMGREN AB, JOH\n\nPnr 102 42\n\nStockholm 5, Sibylleg 7. Box 5076.\nTel 08-67 93 35. Postgiro 50204-7.\nTga Sadel\n\nVeiksamhet: Tillverkar alla slags\nlädervaror etc för resor, ritt,\nindustri o militära ändamål. Säljer filt.\nKungUg hovsadelmakare\nAktiekapital: 200 000\nEtableringsår: 1896\nOmbildat till aktiebolag 1945.\n\nPALMGREN INREDNING AB,\nLARS\n\nPnr 41121\n\nGöteborg, Stora Badhusg 16. Tel\n031-1784 85. Bankgiro 371-5984.\nPostgiro 429618\n\nVerksamhet: Tillverkar o levererar\ninredningar för offentlig miljö\nAntal anstäUda: 4\nÅrsomsättning: 2 000 000\nAktiekapital: 10 000\nVerkst dir: Lars Palmgren\nEtableringsår: 1968.\n\nRYDBERG &amp; STREIFFERT AB\n\nPnr 411 08\n\nGöteborg, Trädgårdsg 4. Tel\n031-132450, 13 2451. Bankgiro\n847-8737. Postgiro 48802-3.\nTga Erresscoal. Telex 20871\nVerksamhet: Stenkol, koks o\neldningsolja\nVarunamn: Erress\nAktiekapital: 100 000\nVerkst dir: Bertil W Rydberg\nEtableringsår 1944.\n\nGRYTS BRUK, AB\n\nPnr 690 71\n\nHjortkvam. Tel 0582-302 10.\nBank-303-3032. Postgiro 80656-2. Tga\nGrytsbruk, Örebro\nVerksamhet: Tillverkar trådspik o\nkalldragen tråd, armeringsnät o\nandra svetsade o bockade\narme-ringsdetaljer, varmförzinkning\nAntal anstäUda: 100\nÅrsomsättning: 14 000 000\nAktiekapital: 2 000000\nVerkst dir: Bruksdisp Rutger\nWijkander\n\nEtableringsår: 1904.\n\nHÄLSINGLANDS REPSLAGERI\n\nPnr 820 76\n\nJättendal. Tel 0652-130 32.\nBankgiro 785-3153. Postgiro 133952-2\nVerksamhet:Säljer jutesäckar,\nrör-mokarlin o packningsgarn\nÅrsomsättning: 175 000\nÄgare o chef: Verner Lindwall\nEtableringsår: 1936.\n\nHÄLSINGLANDS SKOGSBYRÅ,\nAB\n\nPnr 828 00\n\nEdsbyn. Byg 6. Tel 0271-218 70.\nBankgiro 780-7449. Postgiro\n478244-7\n\nVerksamhet: Skogsavverkning,\nmarkberedning, inköp o försäljning\nav rundvirke, skogsvärdering,\nkonsultverksamhet\nAntal anställda: 30\nÅrsomsättning: 1700 000\nAktiekapital: 200000\nVerkst dir Lars Torgny Bjarne\nEtableringsår: 1967.\n\nEFFPE GLASS-STRUTAR AB\n\nPnr 575 00\n\nEksjö, Qvarnarp. Box 127. Tel\n0381-11663. Bankgiro 266-4605.\nPostgiro 481219-4. Tga Effpe\nVerksamhet: Glass-strutar o rån\nAntal anställda: 10\nÅrsomsättning: 600 000\nAktiekapital: 75 000\nVerkst dir: Rune A Hjelte\nEtableringsår: 1953.\n\nmanhart ab\n\nPnr 114 24\n\nStockholm, östermalmsg 5. Tel\n08-24 04 35. Bankgiro 728-4425.\nPostgiro 190755-9. Tga Manhart\nVerksamhet: Engrosförsäljning av\nyttertrikå, socks o strumpor för\nherrar\n\nVerkst dir: Curt Hartman\nDisp: Bengt Hellsten\nEtableringsår: 1941.\n\nmann &amp; co, ingenjörs.\nfirma\n\nPnr 551 02\n\nJönköping 1, Box 9. Tel\n036-110413, 111117. Bankgiro\n34-1958. Postgiro 73400. Tga Mann\nVerksamhet: Säljer textil- o\ntri-kåmaskiner, specialsymaskiner\nChef: Wolfgang Mann.\n\nmänner ab, olof\n\nPnr 431 22\n\nMölndal 1, Box 178. Tel\n031-87 04 00. Bankgiro 42-0125.\nPostgiro 40670. Tga Olofmanner.\nTelex 2382\n\nVerksamhet: Tillverkar metaller i\ntackor o legeringar. Säljer metaller\ni halvfabrikat samt gjuteriartiklar.\nKöper o säljer järn o metallskrot\n\nFilialer Karlstad. Tel 054-15 35 00\nMalmö. Tel 040-93 34 10\nStockholm. Tel 08-7560040\nVarunamn: Manal, Manbrons,\nMansil\n\nAntal anställda: 120\nAktiekapital: 2084 000\nVerkst dir: Lars Männer\nEtableringsår: 1922.\n\nmannerstål, gross.\nhandelsfirma magni\n\nPnr 440 20\n\nVårgårda, Parkg 25. Tel 0322-\n\n203 00. Bankgiro 89-4940. Postgiro\n6822\n\nVerksamhet: Byggnadsbeslag,\nTvär-well, Benty-Cell, vipportar,\npresenningar, plastbackar\nÄgare o chef: Ing Magni\nManner-stål\n\nEtableringsår: 1949.\n\nSTR\n\nSTRIDSBERG &amp; BIÖRCK, AB\n\nPnr 46100\n\nTrollhättan, Gullöfors. Tel\n0520-126 60. Bankgiro 55-1755. Postgiro\n6080. Tga Stridbiörck.\nTelex 42023 STEIDE S\nVerksamhet: Sågblads- o\nmaskinknivfabrik med stålverk, stålgjuteri,\nvalsverk o mekanisk verkstad\nFilial: Stockholm K, Bergsg 6. Tel\n08-52 53 30. Disp: Kurt Lindfors\nAntal anställda: 350\nÅrsomsättning: 22 000 000\nAktiekapital: 2 000 000\nStyrelse: Bankdir Harald\nMagnusson (ordf), dir Arne Egnell,\ncivilekonom C R Ekman, dir Sigurd\nStridsberg, övering Erik von\nWachen-feldt\n\nVerkst dir: Arne Egnell\nFörsäljn-chef: Lars Losman\nInköpschef: Helge Almquist\nProd-chef: Nils Stjernlöf\nEtableringsår: 1868\nOmbildat till aktiebolag 1911.\n\nSTRIEMBOLAGEN AB\n\nPnr 17203\n\nSundbyberg 3, Fack. Högklintav 7.\nTel 08-29 0140. Bankgiro\n161-3504. Postgiro 250163-3. Tga\nStriembolagen\n\nVerksamhet: Tillverkar o säljer\nhushållsprodukter design Sigvard\nBernadotte. Generalagenturer i\nhushålls- o konstglas, porslin,\npresentartiklar, keramik,\nemaljerade kokkärl, rostfria bestick o\nPyrex ugnsfast glas\nVarunamn: Bellobox, Birgitta\nkeramik, Eckhoff, Finncristall, Fuga,\nLargo, Lasi, Lotus emaljerade\nkokkärl, Modernum, Opus, Porsgrund\nporslin, Pyrex, Sanirose,\nStoret-tes\n\nAntal anställda: 15\nAktiekapital: 200 000\nStyrelse: Greve Sigvard Bernadotte\n(ordf), generaldir A O Kolehmainen,\nkapten C Bertil Nyström er\nVerkst dir: j Gunnar Olson\nProduktchefer: Rolf Fredriksson,\nLars Molin\n\nKamrer: Roland Nilsson\nEtableringsår: 1964.\n\nSTRING-SEFFLE\nMÖBELFABRIK, AB\n\nPnr 661 00\n\nSäffle, Säteriv 20. Box 85. Tel\n0533-126 70. Bankgiro 114-9699.\nPostgiro 131900-3. Tga Stringtrade\nVerksamhet: Tillverkar ostoppade\nträmöbler o förvaringsmöbler.\nSpecialitet: Hyllsystem o soffbord\nVarunamn: Seffle, String, Triang\nAntal anställda: 100\nÅrsomsättning: 8 000 000\nStyrelse: Dir Erik Persson (ordf),\ngodsägare Edv Söderberg, dir\nGunnar Johannesson\nVerkst dir: Gunnar Johannesson\nFörsäljning: B Holmedahl\n\nEtableringsår: String Design AB\n1947, AB Seffle Möbelfabrik 1909.\nNuvarande namn o bolag 1971\nDotterföretag till Varia Industri\nAB. Flen.\n\nSTRÖJA, AB\n\nPnr 149 00\n\nNynäshamn, Frejg 19. Tel\n0752-109 92. Bankgiro 620-0372. Post&gt;\ngiro 384328-1\n\nVerksamhet: Utför sprutgjutning o\nformpressning i plaster\nAntal anställda: 5\nÅrsomsättning: 700 000\nAktiekapital: 110 000\nVerkst dir: Sture Sämsjö\nEtableringsår: 1947.\n\nARA-BOLAGEN AB\n\nPnr 10241\n\nStockholm 5, Grev Tureg 19. Box\n5028. Tel 08-63 56 00. Bankgiro\n16-0777. Postgiro 50980. Telex\n1314. Tga Arabolagen\nVerksamhet: Kol, koks, olja\nAktiekapital: 10000 000\nVerkst dir: O Berg\nEtableringsår: 1928.\n\nARABYGG I\nÖSTERGÖTLAND AB\n\nPnr 602 22\n\nNorrköping 1, Bråddg 7. Tel\n011-12 99 00. Bankgiro 41-2772.\nPostgiro 393210-0. Tga Arabygg\nVerksamhet: Säljer\nbyggnadsmaterial. Entreprenadverksamhet\n(plattsättning, taktäckning,\ngolvläggning). Representerar ledande\ntillverkare inom o utom landet\nAntal anställda: 100\nÅrsomsättning: 21000 000\nAktiekapital: 500 000\nStyrelse: Dir Hans Larsson (ordf),\ndir Gustaf Mattisson, dir Jon\nOck-lind, disp Töre Carlson\nVerkst dir: Jon Ocklind\nPlatschef: Disp Töre Carlson\nFörsäljn-chef: Nils Rosvall\nEntreprenadchef: Björn Westlund\nKamrer: Ake Anderson\nKassör: Alvar Eriksson\nEtableringsår: 1970.\n\nBALTISKA SLIPSKIVS AB\n\nPnr 763 02\n\nHallstavik 2, Box 218. Tel\n0175-207 22, 215 22. Bankgiro 80-4825.\nPostgiro 23676\n\nVerksamhet: Tillverkar slipskivor,\nslipsegment o brynen\nAktiekapital: 20 800\nStyrelse: Fabr Karl Gustav\nFahlström (ordf), fabr Emil Olof\nFahlström, fabr Evald M G Fahlström\nVerkst dir: Fabr Evald M G\nFahlström\n\nEtableringsår: 1915.",
    "structured": {
        "1": {
            "company_name": "ERGO, ELEKTRISKA AB",
            "pnr": "723 35",
            "address": "Västerås, Ängsg4",
            "phone_number": "021-1443 45",
            "bank_details": {
                "bankgiro": "808-6167",
                "postgiro": "8702-3"
            },
            "activity": "Tillverkar elektriska apparater, värmeskåp, värmepaneler, markupptiningsaggregat samt el-uppvärmda brandposter",
            "employees": 30,
            "annual_turnover": 3600000,
            "capital": 120000,
            "key_personnel": [
                {
                    "name": "Georg Hammarqvist",
                    "position": "Verkst dir"
                },
                {
                    "name": "Per Hammarqvist",
                    "position": "Disp"
                }
            ],
            "establishment_year": 1922
        },
        "2": {
            "company_name": "PALMGREN AB, JOH",
            "pnr": "102 42",
            "address": "Stockholm 5, Sibylleg 7. Box 5076",
            "phone_number": "08-67 93 35",
            "postgiro": "50204-7",
            "activity": "Tillverkar alla slags lädervaror etc för resor, ritt, industri o militära ändamål. Säljer filt. KungUg hovsadelmakare",
            "capital": 200000,
            "establishment_year": 1896,
            "ombildning": "1945"
        },
        "3": {
            "company_name": "PALMGREN INREDNING AB, LARS",
            "pnr": "41121",
            "address": "Göteborg, Stora Badhusg 16",
            "phone_number": "031-1784 85",
            "bank_details": {
                "bankgiro": "371-5984",
                "postgiro": "429618"
            },
            "activity": "Tillverkar o levererar inredningar för offentlig miljö",
            "employees": 4,
            "annual_turnover": 2000000,
            "capital": 10000,
            "key_personnel": {
                "name": "Lars Palmgren",
                "position": "Verkst dir"
            },
            "establishment_year": 1968
        },
        "4": {
            "company_name": "RYDBERG & STREIFFERT AB",
            "pnr": "411 08",
            "address": "Göteborg, Trädgårdsg 4",
            "phone_number": "031-132450, 13 2451",
            "bank_details": {
                "bankgiro": "847-8737",
                "postgiro": "48802-3"
            },
            "activity": "Stenkol, koks o eldningsolja",
            "capital": 100000,
            "key_personnel": {
                "name": "Bertil W Rydberg",
                "position": "Verkst dir"
            },
            "establishment_year": 1944
        },
        "5": {
            "company_name": "GRYTS BRUK, AB",
            "pnr": "690 71",
            "address": "Hjortkvam",
            "phone_number": "0582-302 10",
            "bank_details": {
                "bank": "303-3032",
                "postgiro": "80656-2"
            },
            "activity": "Tillverkar trådspik o kalldragen tråd, armeringsnät o andra svetsade o bockade armeringsdetaljer, varmförzinkning",
            "employees": 100,
            "annual_turnover": 14000000,
            "capital": 2000000,
            "key_personnel": {
                "name": "Bruksdisp Rutger Wijkander",
                "position": "Verkst dir"
            },
            "establishment_year": 1904
        },
        "6": {
            "company_name": "HÄLSINGLANDS REPSLAGERI",
            "pnr": "820 76",
            "address": "Jättendal",
            "phone_number": "0652-130 32",
            "bank_details": {
                "bankgiro": "785-3153",
                "postgiro": "133952-2"
            },
            "activity": "Säljer jutesäckar, rörmokarlin o packningsgarn",
            "annual_turnover": 175000,
            "key_personnel": {
                "name": "Verner Lindwall",
                "position": "Ägare o chef"
            },
            "establishment_year": 1936
        },
        "7": {
            "company_name": "HÄLSINGLANDS SKOGSBYRÅ, AB",
            "pnr": "828 00",
            "address": "Edsbyn. Byg 6",
            "phone_number": "0271-218 70",
            "bank_details": {
                "bankgiro": "780-7449",
                "postgiro": "478244-7"
            },
            "activity": "Skogsavverkning, markberedning, inköp o försäljning av rundvirke, skogsvärdering, konsultverksamhet",
            "employees": 30,
            "annual_turnover": 1700000,
            "capital": 200000,
            "key_personnel": {
                "name": "Lars Torgny Bjarne",
                "position": "Verkst dir"
            },
            "establishment_year": 1967
        },
        "8": {
            "company_name": "EFFPE GLASS-STRUTAR AB",
            "pnr": "575 00",
            "address": "Eksjö, Qvarnarp. Box 127",
            "phone_number": "0381-11663",
            "bank_details": {
                "bankgiro": "266-4605",
                "postgiro": "481219-4"
            },
            "activity": "Glass-strutar o rån",
            "employees": 10,
            "annual_turnover": 600000,
            "capital": 75000,
            "key_personnel": {
                "name": "Rune A Hjelte",
                "position": "Verkst dir"
            },
            "establishment_year": 1953
        },
        "9": {
            "company_name": "manhart ab",
            "pnr": "114 24",
            "address": "Stockholm, östermalmsg 5",
            "phone_number": "08-24 04 35",
            "bank_details": {
                "bankgiro": "728-4425",
                "postgiro": "190755-9"
            },
            "activity": "Engrosförsäljning av yttertrikå, socks o strumpor för herrar",
            "key_personnel": [
                {
                    "name": "Curt Hartman",
                    "position": "Verkst dir"
                },
                {
                    "name": "Bengt Hellsten",
                    "position": "Disp"
                }
            ],
            "establishment_year": 1941
        },
        "10": {
            "company_name": "mann & co, ingenjörs. firma",
            "pnr": "551 02",
            "address": "Jönköping 1, Box 9",
            "phone_number": "036-110413, 111117",
            "bank_details": {
                "bankgiro": "34-1958",
                "postgiro": "73400"
            },
            "activity": "Säljer textil- o tri-kåmaskiner, specialsymaskiner",
            "key_personnel": {
                "name": "Wolfgang Mann",
                "position": "Chef"
            },
            "establishment_year": 0
        },
        "11": {
            "company_name": "männer ab, olof",
            "pnr": "431 22",
            "address": "Mölndal 1, Box 178",
            "phone_number": "031-87 04 00",
            "bank_details": {
                "bankgiro": "42-0125",
                "postgiro": "40670"
            },
            "activity": "Tillverkar metaller i tackor o legeringar. Säljer metaller i halvfabrikat samt gjuteriartiklar. Köper o säljer järn o metallskrot",
            "branches": [
                {
                    "city": "Karlstad",
                    "phone_number": "054-15 35 00"
                },
                {
                    "city": "Malmö",
                    "phone_number": "040-93 34 10"
                },
                {
                    "city": "Stockholm",
                    "phone_number": "08-7560040"
                }
            ],
            "brands": [
                "Manal",
                "Manbrons",
                "Mansil"
            ],
            "employees": 120,
            "capital": 2084000,
            "key_personnel": {
                "name": "Lars Männer",
                "position": "Verkst dir"
            },
            "establishment_year": 1922
        },
        "12": {
            "company_name": "mannerstål, gross. handelsfirma magni",
            "pnr": "440 20",
            "address": "Vårgårda, Parkg 25",
            "phone_number": "0322-203 00",
            "bank_details": {
                "bankgiro": "89-4940",
                "postgiro": "6822"
            },
            "activity": "Byggnadsbeslag, Tvär-well, Benty-Cell, vipportar, presenningar, plastbackar",
            "key_personnel": {
                "name": "Ing Magni Manner-stål",
                "position": "Ägare o chef"
            },
            "establishment_year": 1949
        },
        "13": {
            "company_name": "STRIDSBERG & BIÖRCK, AB",
            "pnr": "46100",
            "address": "Trollhättan, Gullöfors",
            "phone_number": "0520-126 60",
            "bank_details": {
                "bankgiro": "55-1755",
                "postgiro": "6080"
            },
            "activity": "Sågblads- o maskinknivfabrik med stålverk, stålgjuteri, valsverk o mekanisk verkstad",
            "branch": {
                "city": "Stockholm K",
                "address": "Bergsg 6",
                "phone_number": "08-52 53 30"
            },
            "employees": 350,
            "annual_turnover": 22000000,
            "capital": 2000000,
            "key_personnel": {
                "name": "Arne Egnell",
                "position": "Verkst dir"
            },
            "establishment_year": 1911
        },
        "14": {
            "company_name": "STRIEMBOLAGEN AB",
            "pnr": "17203",
            "address": "Sundbyberg 3, Fack. Högklintav 7",
            "phone_number": "08-29 0140",
            "bank_details": {
                "bankgiro": "161-3504",
                "postgiro": "250163-3"
            },
            "activity": "Tillverkar o säljer hushållsprodukter design Sigvard Bernadotte. Generalagenturer i hushålls- o konstglas, porslin, presentartiklar, keramik, emaljerade kokkärl, rostfria bestick o Pyrex ugnsfast glas",
            "brands": [
                "Bellobox",
                "Birgitta keramik",
                "Eckhoff",
                "Finncristall",
                "Fuga",
                "Largo",
                "Lasi",
                "Lotus emaljerade kokkärl",
                "Modernum",
                "Opus",
                "Porsgrund porslin",
                "Pyrex",
                "Sanirose",
                "Storet-tes"
            ],
            "employees": 15,
            "capital": 200000,
            "key_personnel": [
                {
                    "name": "Greve Sigvard Bernadotte",
                    "position": "Styrelse ordförande"
                },
                {
                    "name": "j Gunnar Olson",
                    "position": "Verkst dir"
                }
            ],
            "establishment_year": 1964
        },
        "15": {
            "company_name": "STRING-SEFFLE MÖBELFABRIK, AB",
            "pnr": "661 00",
            "address": "Säffle, Säteriv 20. Box 85",
            "phone_number": "0533-126 70",
            "bankgiro": "114-9699",
            "postgiro": "131900-3",
            "activity": "Tillverkar ostoppade trämbler o förvaringsmöbler. Specialitet: Hyllsystem o soffbord",
            "brands": [
                "Seffle",
                "String",
                "Triang"
            ],
            "employees": 100,
            "annual_turnover": 8000000,
            "key_personnel": [
                {
                    "name": "Erik Persson",
                    "position": "Styrelse ordförande"
                },
                {
                    "name": "Gunnar Johannesson",
                    "position": "Verkst dir"
                }
            ],
            "establishment_year": 1971
        },
        "16": {
            "company_name": "STRÖJA, AB",
            "pnr": "149 00",
            "address": "Nynäshamn, Frejg 19",
            "phone_number": "0752-109 92",
            "bank_details": {
                "bankgiro": "620-0372",
                "postgiro": "384328-1"
            },
            "activity": "Utför sprutgjutning o formpressning i plaster",
            "employees": 5,
            "annual_turnover": 700000,
            "capital": 110000,
            "key_personnel": {
                "name": "Sture Sämsjö",
                "position": "Verkst dir"
            },
            "establishment_year": 1947
        },
        "17": {
            "company_name": "ARA-BOLAGEN AB",
            "pnr": "10241",
            "address": "Stockholm 5, Grev Tureg 19. Box 5028",
            "phone_number": "08-63 56 00",
            "bank_details": {
                "bankgiro": "16-0777",
                "postgiro": "50980"
            },
            "activity": "Kol, koks, olja",
            "capital": 10000000,
            "key_personnel": {
                "name": "O Berg",
                "position": "Verkst dir"
            },
            "establishment_year": 1928
        },
        "18": {
            "company_name": "ARABYGG I ÖSTERGÖTLAND AB",
            "pnr": "602 22",
            "address": "Norrköping 1, Bråddg 7",
            "phone_number": "011-12 99 00",
            "bank_details": {
                "bankgiro": "41-2772",
                "postgiro": "393210-0"
            },
            "activity": "Säljer byggnadsmaterial. Entreprenadverksamhet (plattsättning, taktäckning, golvläggning). Representerar ledande tillverkare inom o utom landet",
            "employees": 100,
            "annual_turnover": 21000000,
            "capital": 500000,
            "key_personnel": {
                "name": "Hans Larsson",
                "position": "Styrelse ordförande"
            },
            "establishment_year": 1970
        },
        "19": {
            "company_name": "BALTISKA SLIPSKIVS AB",
            "pnr": "763 02",
            "address": "Hallstavik 2, Box 218",
            "phone_number": "0175-207 22, 215 22",
            "bank_details": {
                "bankgiro": "80-4825",
                "postgiro": "23676"
            },
            "activity": "Tillverkar slipskivor, slipsegment o brynen",
            "capital": 20800,
            "key_personnel": [
                {
                    "name": "Fabr Karl Gustav Fahlström",
                    "position": "Styrelse ordförande"
                },
                {
                    "name": "Fabr Evald M G Fahlström",
                    "position": "Verkst dir"
                }
            ],
            "establishment_year": 1915
        }
    }
}