{
    "original": "WRETHMAN, AB HENRIK\n\nPnr 103 63\n\nStockholm 3, Kungsg 29. Box 3161.\nTel 08-23 26 65. Postgiro 4824-9.\nTelex 19914. Tga Wrethman\nVerksamhet: Agentur i planglas o\nmaskinblåsta dricksglas\nAntal anställda: 10\nAktiekapital: 42 000\nStyrelse: Dir Sigurd Wrethman\n(ordf), adv Sven Gullström\nVeikst dir: Sigurd Wrethman\nEtableringsår: 1910.\n\nWRETMAN RESTAURANGER\nAB, TÖRE\n\nPnr 103 82\n\nStockholm 7, Birger Jarlsg 4. Box\n7050. Tel 08-24 27 00. Bankgiro\n160-5468. Postgiro 2219-4\nVerksamhet: Restaurangrörelse\nRestaurangen Stockholm. AB\nOperakällaren, Operahuset. Tel\n08-24 27 00. Källarmästare: Sigurd\nLarsson, Lauri Nilsson\nStockholm. AB Hotel &amp; Restaurant\nRiche, Birger Jarlsg 4. Tel\n08-107022. Källarmästare: Nils Ahlin\nStockholm. AB Restaurant\nStall-mästaregården. Norrtull. Tel\n08-337915. Källarmästare: Gösta\nNorden\n\nAntal anställda: 482\nÅrsomsättning: 36 580 000\nAktiekapital: 200 000\nVeikst dir: Töre Wretman\nV verkst dir: Jan Ling\nStyrelse: Dir Bertil Kugelberg\n(ordf). Simon Bonnier, adv Håkan\nLindén, hovtraktör Töre Wretman\nEkonomidir: Sven Akerstrand\nEtableringsår: 1945.\n\nEVERS &amp; CO. KNUT\n\nPnr 50255\n\nBorås. Ulvens g 15. Tel\n033-1109 61. Bankgiro 53-1249.\nPostgiro 80513. Tga Eversco\nVerksamhet: Agentur för bomull,\null, shoddy o industrigarner\nVerkst dir: Konsul Knut Evers\nDir: Ingvar Evers\nEtableringsår: 1904.\n\nBACKLUND, F\n\nPnr 113 41\n\nStockholm, Norrbackag 22. Tel\nOS-SO 95 54. Bankgiro 72-6107.\nPostgiro 159235\n\nVerksamhet: Importerar\nnatursvamp o sämskskinn.\n\nBACKLUNDS\nMASKINAFFÄR AB, K-A\n\nPnr 460 30\n\nSollebrunn, Box 137. Tel\n0322-40281. Bankgiro 891-6264.\nPostgiro 79097-2\n\nVerksamhet: Säljer traktorer o\nlantbruksmaskiner\nAktiekapital: 25 000\nVerkst dir: K-A Backlund\nEtableringsår: 1956.\n\nFLYBERGS PLÅTSLAGERI\n\nPnr 693 00\n\nDegerfors, Box 2776. Källstigen 7.\nTel 0586-406 91. Bankgiro 104-9006.\nPostgiro 344054-2\nVerksamhet: Byggnadsplåtslageri,\nventilationsarbeten, takmålningar\nChef: Nils Flyberg\nEtableringsår: 1949.\n\nWOLBER IMPORT AB\n\nPnr 116 45\n\nStockholm, Katarinav 20. Tel\n08-44 98 10. Postgiro 50 11 66. Tga\nWolberimport\n\nVerksamhet: Säljer kontors- o\ntryckerimaskiner\nAktiekapital: 150000\nVeikst dir: Voldemar Berzins\nEtableringsår: 1952.\n\nSVENSKA KIRSCH AB\n\nPnr 13101\n\nNacka 1, Planiav 1. Box 63. Tel\n08-716 28 50. Bankgiro 746-0033.\nPostgiro 55051-7. Tga Larbo\nVerksamhet: Tillverkar\ngardinstänger\n\nAktiekapital: 100 000\nVerkst din Gert Tillberg\nEtableringsår 1933.\n\nLYCKEABORGS BRUK, AB\n\nPnr 370 21\n\nTorskors. Tel 0455-450 29, 45092.\nBankgiro 86-1386. Postgiro 38345.\nTelex 43043\n\nVerksamhet: Tillverkar\nmontörvagnar för bilverkstäder,\nverktygslådor, länkrullar o hjul, klippspik o\nklippdyckert samt kabelgenomgångar\nAntal anställda: 75\nAktiekapital: 250 000\nDisp: J-E Blomqvist\nEtableringsår: 1759\nOmbildat till aktiebolag 1948.\n\nLYCKSELE ENTREPRENAD.\nBYRÅ, AB\n\nPnr 92100\n\nLycksele, Prästbolsv 22. Box 172.\nTel 0950-122 67, 11818. Bankgiro\n202-6326. Postgiro 514321-9\nVerksamhet: Entreprenader för\nvatten- o avloppsanläggningar,\nvägbyggnader, bergsprängnings- o\ngrundläggningsarbeten\nAntal anställda: 9\nÅrsomsättning: 700 000\nAktiekapital: 15 000\nVerkst dir: Göte Johansson\nEtableringsår: 1958\nOmbildat till aktiebolag 1959.\n\nLYFA.ELECTRIC AB\n\nPnr 21145\n\nMalmö. Davidshallsg 16-18. Tel\n040-1112 13 , 323 93. Bankgiro\n260-4601. Postgiro 149867-4. Tga\nLyfa-electric\n\nVerksamhet; Importerar o säljer\nLYFA elektriska\nbelysningsarmaturer o HDW-K\nfelsökningsinstrument. Agentur för SOLIS hårtorkar,\nvärmedynor samt kvartslampor\nAntal anställda: 6\nÅrsomsättning: 1500 000\nAktiekapital: 120 000\nVerkst dir. Ing Töre Westberg\nEtableringsår. 1945.\n\nPANDURO HOBBY AB\n\nPnr 211 43\n\nMalmö, S Förstadsg 3. Tel\n040-777 60. Postgiro 74152-0\nVerksamhet: säljer hobby- o\nterapimaterial\n\nAntal anställda: 27\nÅrsomsättning: 3 500 000\nAktiekapital: 200000\nVerkst dir: Jörgen Panduro\nEtableringsår: 1960.\n\nhenes revisionsbyrå. stig\n\nPnr 93101\n\nSkellefteå 1, Box 236. Kanalg 59.\nTel 0910-17100. Bankgiro\n611-7444. Postgiro 258084^3\nVerksamhet: Utför revision,\nsiffer-granskning o bokslut\nAntal anställda: 26\nChef: Aukt rev Stig Hene\nEtableringsår: 1959.\n\nRYBERG, AB ERNST\n\nPnr 116 41\n\nStockholm, Tegelviksg 71-73. Tel\n08-44 98 80. Bankgiro 44-6935.\nPostgiro 4780. Telex 17066. Tga Saltsill\nVerksamhet: Importörer av salt,\nsaltad sill, kabeljo, torrfisk o lax\nAntal anställda: 50\nÅrsomsättning: 15 000 000\nAktiekapital: 25 0 000\nVerkst dir: Lars Ryberg\nEtableringsår 1920.",
    "structured": {
        "1": {
            "company_name": "WRETHMAN, AB HENRIK",
            "pnr": "103 63",
            "address": "Stockholm 3, Kungsg 29. Box 3161",
            "phone_number": "08-23 26 65",
            "postgiro": "4824-9",
            "activity": "Agentur i planglas o maskinblåsta dricksglas",
            "employees": 10,
            "capital": 42000,
            "key_personnel": [
                {
                    "name": "Sigurd Wrethman",
                    "position": "Dir"
                },
                {
                    "name": "Sven Gullström",
                    "position": "adv"
                }
            ],
            "establishment_year": 1910
        },
        "2": {
            "company_name": "WRETMAN RESTAURANGER AB, TÖRE",
            "pnr": "103 82",
            "address": "Stockholm 7, Birger Jarlsg 4. Box 7050",
            "phone_number": "08-24 27 00",
            "bankgiro": "160-5468",
            "postgiro": "2219-4",
            "activity": "Restaurangrörelse",
            "employees": 482,
            "annual_turnover": 36580000,
            "capital": 200000,
            "key_personnel": [
                {
                    "name": "Töre Wretman",
                    "position": "Veikst dir"
                },
                {
                    "name": "Jan Ling",
                    "position": "V verkst dir"
                }
            ],
            "establishment_year": 1945
        },
        "3": {
            "company_name": "EVERS & CO. KNUT",
            "pnr": "50255",
            "address": "Borås, Ulvens g 15",
            "phone_number": "033-1109 61",
            "bankgiro": "53-1249",
            "postgiro": "80513",
            "activity": "Agentur för bomull, ull, shoddy o industrigarner",
            "key_personnel": [
                {
                    "name": "Knut Evers",
                    "position": "Verkst dir"
                },
                {
                    "name": "Ingvar Evers",
                    "position": "Dir"
                }
            ],
            "establishment_year": 1904
        },
        "4": {
            "company_name": "BACKLUND, F",
            "pnr": "113 41",
            "address": "Stockholm, Norrbackag 22",
            "phone_number": "OS-SO 95 54",
            "bankgiro": "72-6107",
            "postgiro": "159235",
            "activity": "Importerar natursvamp o sämskskinn"
        },
        "5": {
            "company_name": "BACKLUNDS MASKINAFFÄR AB, K-A",
            "pnr": "460 30",
            "address": "Sollebrunn, Box 137",
            "phone_number": "0322-40281",
            "bankgiro": "891-6264",
            "postgiro": "79097-2",
            "activity": "Säljer traktorer o lantbruksmaskiner",
            "capital": 25000,
            "key_personnel": {
                "name": "K-A Backlund",
                "position": "Verkst dir"
            },
            "establishment_year": 1956
        },
        "6": {
            "company_name": "FLYBERGS PLÅTSLAGERI",
            "pnr": "693 00",
            "address": "Degerfors, Box 2776. Källstigen 7",
            "phone_number": "0586-406 91",
            "bankgiro": "104-9006",
            "postgiro": "344054-2",
            "activity": "Byggnadsplåtslageri, ventilationssarbeten, takmålningar",
            "key_personnel": {
                "name": "Nils Flyberg",
                "position": "Chef"
            },
            "establishment_year": 1949
        },
        "7": {
            "company_name": "WOLBER IMPORT AB",
            "pnr": "116 45",
            "address": "Stockholm, Katarinav 20",
            "phone_number": "08-44 98 10",
            "postgiro": "50 11 66",
            "activity": "Säljer kontors- o tryckerimaskiner",
            "capital": 150000,
            "key_personnel": {
                "name": "Voldemar Berzins",
                "position": "Veikst dir"
            },
            "establishment_year": 1952
        },
        "8": {
            "company_name": "SVENSKA KIRSCH AB",
            "pnr": "13101",
            "address": "Nacka 1, Planiav 1. Box 63",
            "phone_number": "08-716 28 50",
            "bankgiro": "746-0033",
            "postgiro": "55051-7",
            "activity": "Tillverkar gardinstänger",
            "capital": 100000,
            "key_personnel": {
                "name": "Gert Tillberg",
                "position": "Verkst dir"
            },
            "establishment_year": 1933
        },
        "9": {
            "company_name": "LYCKEABORGS BRUK, AB",
            "pnr": "370 21",
            "address": "Torskors",
            "phone_number": "0455-450 29, 45092",
            "bankgiro": "86-1386",
            "postgiro": "38345",
            "telex": "43043",
            "activity": "Tillverkar montörvagnar för bilverkstäder, verktygslådor, länkrullar o hjul, klippspik o klippdyckert samt kabelgenomgångar",
            "employees": 75,
            "capital": 250000,
            "disp": "J-E Blomqvist",
            "establishment_year": 1759,
            "ombildat_till_aktiebolag": 1948
        },
        "10": {
            "company_name": "LYCKSELE ENTREPRENAD. BYRÅ, AB",
            "pnr": "92100",
            "address": "Lycksele, Prästbolsv 22. Box 172",
            "phone_number": "0950-122 67, 11818",
            "bankgiro": "202-6326",
            "postgiro": "514321-9",
            "activity": "Entreprenader för vatten- o avloppsanläggningar, vägbyggnader, bergsprängnings- o grundläggningsarbeten",
            "employees": 9,
            "annual_turnover": 700000,
            "capital": 15000,
            "key_personnel": {
                "name": "Göte Johansson",
                "position": "Verkst dir"
            },
            "establishment_year": 1958,
            "ombildat_till_aktiebolag": 1959
        },
        "11": {
            "company_name": "LYFA.ELECTRIC AB",
            "pnr": "21145",
            "address": "Malmö, Davidshallsg 16-18",
            "phone_number": "040-1112 13 , 323 93",
            "bankgiro": "260-4601",
            "postgiro": "149867-4",
            "activity": "Importerar o säljer LYFA elektriska belysningsarmaturer o HDW-K felsökningsinstrument. Agentur för SOLIS hårtorkar, värmedynor samt kvartslampor",
            "employees": 6,
            "annual_turnover": 1500000,
            "capital": 120000,
            "key_personnel": {
                "name": "Ing Töre Westberg",
                "position": "Verkst dir"
            },
            "establishment_year": 1945
        },
        "12": {
            "company_name": "PANDURO HOBBY AB",
            "pnr": "211 43",
            "address": "Malmö, S Förstadsg 3",
            "phone_number": "040-777 60",
            "postgiro": "74152-0",
            "activity": "säljer hobby- o terapimaterial",
            "employees": 27,
            "annual_turnover": 3500000,
            "capital": 200000,
            "key_personnel": {
                "name": "Jörgen Panduro",
                "position": "Verkst dir"
            },
            "establishment_year": 1960
        },
        "13": {
            "company_name": "henes revisionsbyrå. stig",
            "pnr": "93101",
            "address": "Skellefteå 1, Box 236. Kanalg 59",
            "phone_number": "0910-17100",
            "bankgiro": "611-7444",
            "postgiro": "258084^3",
            "activity": "Utför revision, siffer-granskning o bokslut",
            "employees": 26,
            "key_personnel": {
                "name": "Aukt rev Stig Hene",
                "position": "Chef"
            },
            "establishment_year": 1959
        },
        "14": {
            "company_name": "RYBERG, AB ERNST",
            "pnr": "116 41",
            "address": "Stockholm, Tegelviksg 71-73",
            "phone_number": "08-44 98 80",
            "bankgiro": "44-6935",
            "postgiro": "4780",
            "telex": "17066",
            "activity": "Importörer av salt, saltad sill, kabeljo, torrfisk o lax",
            "employees": 50,
            "annual_turnover": 15000000,
            "capital": 250000,
            "key_personnel": {
                "name": "Lars Ryberg",
                "position": "Verkst dir"
            },
            "establishment_year": 1920
        }
    }
}