{
    "original": "ADA\n\nparé för skåp- o personbilar\nAntal anställda: 13\nÅrsomsättning: 3 500 000\nDir: B Ulvesten\nInköpschef: K Karlsson\nEtableringsår: 1961.\n\nABV - VÄGFORBÄTTRINGAR\nAB\n\nPnr 102 24\n\nStockholm 12, Box 12148.\nSegel-båtsv 9. Tel 08-1318 00. Bankgiro\n575-2167. Postgiro 2248-3. Tga\nVägförbättring\n\nVerksamhet:\nByggnadsentreprenörfirma\n\nAntal anställda: 5 000\nÅrsomsättning: 540 000 000\nAktiekapital: 6 425 000\nVerkst dir: Civiling C-O Ohlsson\nEtableringsår 1918.\n\nLINDBLOM, AB TAGE\n\nPnr 121 73\n\nJohanneshov, Importörv 19. Tel\n08-81 01 25. Bankgiro 729-5165.\nPostgiro 51360. Tga Colonius\nVerksamhet: Agentur-o\nförsäljningsföretag inom livsmedelshandeln\nAntal anställda: 13\nÅrsomsättning: 20 000 000\nAktiekapital: 80 000\nChef: Dir Sven-Erik Edberg\nEtableringsår: 1922.\n\nNY KVAR N-TI DAN, KRAFT AB\n\nPnr 540 18\n\nTidan. Tel 0500-704 20. Bankgiro\n548-9257. Postgiro 76133-8\nVerksamhet: Distribution av\nelektrisk energi\nAntal anställda: 18\nAktiekapital: 855 000\nVerkst dir: Lars Thureborn\nEtableringsår: 1916.\n\nAGRIVET AB\n\nPnr 751 03\n\nUppsala 1, Box 17. Tel\n018-1111 00. Bankgiro 23-0108.\nPostgiro 1307-8. Tga Pharmacia.\nTelex 7427 PHARMUP S\nVerksamhet: Marknadsföring av\nveterinärmedicinska preparat o\nprodukter för användning inom\nanimalieproduktionen\nAntal anställda: 7\nÅrsomsättning: 1 600 000\n\nAktiekapital: 5 000\nVerkst dir. Lars Johansson\nEtableringsår: 1966\nDotterbolag till Pharmacia AB.\n\nAGROMIN AB\n\nPnr 216 21\n\nMalmö, Fyrspannsg 13. Tel\n040-1605 05, 1605 15. Bankgiro\n348-4334. Postgiro 633343-9.\nTga Agromin\n\nVerksamhet: Tillverkar o säljer\nkemiska preparat o produkter till\nlantbruk, trädgårdsmästerier,\nindustri o hantverk\nAntal anställda: 3\nÅrsomsättning: 1800 000\nAktiekapital: 5 000\nVerkst dir: Erik Blohm\nEtableringsår: 1965.\n\nINTERGRAPHIC AB\n\nPnr 163 21\n\nSpånga 1, Kälvestav 104. Box 72.\nTel 08-36 22 90, 36 26 90. Bankgiro\n23-6087. Postgiro 706250\nVerksamhet: Tillverkar\nIGE-offset-plåt\n\nAktiekapital: 5 000\nFirmatecknare: Ing Gunnar Haag,\ndisp Nils Holmin\nEtableringsår: 1963.\n\nGEAS KONSTHARTS AB\n\nPnr 332 00\n\nGislaved, N Storg 14. Tel\n0371-116 90. Bankgiro 14-3041. Postgiro\n288090\n\nVerksamhet: Tillverkar\nplastartiklar. Specialitet: klädhängare\nAktiekapital: 20 000\nVerkst dir: Ingvar Ambjörnsson\nEtableringsår: 1942.\n\nGEBA KONTORSTJÄNST\nGUSTAF BJERNE AB\n\nPnr 252 25\n\nHelsingborg, Bollbrog 8. Tel\n042-1164 01. 12 83 00. Bankgiro\n652-9143. Postgiro 170175-4\nVerksamhet: Säljer kontors- o rit-\n\nmateriel\n\nAktiekapital: 50 000\nVerkst dir: Gustaf Bjerne\nEtableringsår: 1940.\n\nFORSLUNDS MOTOR AB\n\nPnr 800 06\n\nGävle 6, Box 6150. Tel\n026-129250. Bankgiro 783-7107.\nPostgiro 264060-5\n\nVerksamhet: Bilhandels- o\nverkstadsrörelse (Volvo)\nAntal anställda: 260\nÅrsomsättning: 83 000 000\nAktiekapital: 2 214 000\nVerkst dir: Paul Paulsson\nEtableringsår: 1944.\n\nFORSLUNDS\nVERK-STÄDER, AB\n\nPnr 58104\n\nLinköping 1, Platensg 27. Box 403.\nTel 013-10 23 00. Bankgiro 12-0096.\nPostgiro 29426\n\nVerksamhet: Säljer Opel, Vauxhall\no Bedford person- o lastbilar\nAntal anställda: 64\nÅrsomsättning: 13 000 000\nAktiekapital: 130 000\nVerkst dir: Lennart Forslund\nEtableringsår: 1899.\n\nSAN\n\nVaranamn: ESA\nAntal anstäUda: 14\nÅrsomsättning: 4 500 000\nAktiekapital: 40 000\n\nStyrelse: Adv Carl-Gunder\nHedström (ordf), dir Björn Eriksson\nVerkst dir: Björn Eriksson\nEtableringsår: 1900\nOmbildat tUl aktiebolag 1943.\n\nSANDBERG AB,\nBYGGNADS-FIRMA ERLING\n\nPnr 582 21\n\nLinköping, Industrig 4. Tel\n013-1112 50. Bankgiro 347-0283.\nPostgiro 164087-9\n\nVerksamhet: Byggnadsentreprenör\nAktiekapital: 50 000\nVerkst dir: Byggmäst Erling\nSandberg\n\nEtableringsår 1962.\n\nSANDBERG AB, TEXTIL.\nAGENTUR HARALD O\n\nPnr 103 84\n\nStockholm 7, Norrmalmstorg 1.\nBox 7258. Tel 08-106251. Tga\nHaldlng. Telex 10599\nVeiksamhet: Agenturrörelse i\ndamtyger\n\nÅrsomsättning: 3 000 000\nAktiekapital: 5 000\nVerkst dir: Harald Sandberg\nEtableringsår: 1938.\n\nSANDBERG MASKINAFFÄR,\nIVAR T\n\nPnr 650 03\n\nKarlstad 3, Treffenbergsv 11. Box\n3054. Tel 054-11 01 99, 11 78 09.\nBankgiro 100-2286. Postgiro\n264657\n\nVerksamhet: Säljer motorer,\nstationära o marin, elektr aggregat,\nkonsulterande ingenjörsbyrå.\nSpecialitet: tillverkar\nsnöröjningsutrust-ningar\n\nVarunamn: ITS\n\nÄgare o chef: Ivar T Sandberg\nEtableringsår: 1930.\n\nTHYLIN BIL AB, CURT\n\nPnr 93101\n\nSkellefteå 1, Box 57. Kanalg 59-61,\nNV-huset. Tel 0910-170 60.\nBankgiro 203-9600. Postgiro 386086-3\nVeiksamhet: Auktoriserad\nåterförsäljare för General Motors (ej\nVauxhall); verkstad o reservdelar\nAntal anställda: 60\nÅrsomsättning: 12500000\nAktiekapital: 185 000\nVerkst dir Curt Thylin\nEtableringsån 1947\nGM-agentur sedan 1957.\n\nTYLLINGE AB\n\nPnr 594 00\n\nGamleby, Tyllinge. Tel 0493-330 71,\n330 72\n\nVerksamhet: Säljer skogsprodukter\nsamt sågade o hyvlade trävaror\nÅrsomsättning: 4 500 000\nAktiekapital: 2 800 000\nVerkst dir: Disp Johan Rosenmüller\nEtableringsår: 1897.\n\nBROTEKNIK AB\n\nPnr 59103\n\nMotala 3, Vinterg 7. Fack 308.\nTel 0141-165 60\n\nVerksamhet: Förslag, projektering,\nkonstruktions- o arbetsritningar\nAntal anställda: 10\nÅrsomsättning: 650 000\nAktiekapital: 25 000\nVerkst dir: Civiling Karl Karlsson\nEtableringsår: 1962.\n\nBROTTBY MEKANISKA\nVERKSTADS AB\n\nPnr 43135\n\nMölndal, Agatan 32. Tel\n031-27 50 90. Bankgiro 549-9025.\nPostgiro 240495-2. Tga Brottvar.\nTelex 20799\n\nVerksamhet: Tillverkar variatorer\no maskinbelysningar\nAntal anställda: 45\nÅrsomsättning: 4 000 000\nAktiekapital: 50 000\nVerkst dir: Civiling Sven B\nRennerfelt\n\nEtableringsår: 1938.",
    "structured": {
        "1": {
            "company_name": "ADA",
            "activity": "paré för skåp- o personbilar",
            "establishment_year": 1961
        },
        "2": {
            "company_name": "ABV - VÄGFORBÄTTRINGAR AB",
            "pnr": "102 24",
            "address": "Stockholm 12, Box 12148, Segel-båtsv 9",
            "phone_number": "08-1318 00",
            "bank_details": {
                "bankgiro": "575-2167",
                "postgiro": "2248-3"
            },
            "activity": "Byggnadsentreprenörfirma",
            "employees": 5000,
            "annual_turnover": 540000000,
            "capital": 6425000,
            "key_personnel": [
                {
                    "name": "Civiling C-O Ohlsson",
                    "position": "Verkst dir"
                }
            ],
            "establishment_year": 1918
        },
        "3": {
            "company_name": "LINDBLOM, AB TAGE",
            "pnr": "121 73",
            "address": "Johanneshov, Importörv 19",
            "phone_number": "08-81 01 25",
            "bank_details": {
                "bankgiro": "729-5165",
                "postgiro": "51360"
            },
            "activity": "Agentur-o försäljningsföretag inom livsmedelshandeln",
            "employees": 13,
            "annual_turnover": 20000000,
            "capital": 80000,
            "key_personnel": [
                {
                    "name": "Dir Sven-Erik Edberg",
                    "position": "Chef"
                }
            ],
            "establishment_year": 1922
        },
        "4": {
            "company_name": "NY KVAR N-TI DAN, KRAFT AB",
            "pnr": "540 18",
            "address": "Tidan",
            "phone_number": "0500-704 20",
            "bank_details": {
                "bankgiro": "548-9257",
                "postgiro": "76133-8"
            },
            "activity": "Distribution av elektrisk energi",
            "employees": 18,
            "capital": 855000,
            "key_personnel": [
                {
                    "name": "Lars Thureborn",
                    "position": "Verkst dir"
                }
            ],
            "establishment_year": 1916
        },
        "5": {
            "company_name": "AGRIVET AB",
            "pnr": "751 03",
            "address": "Uppsala 1, Box 17",
            "phone_number": "018-1111 00",
            "bank_details": {
                "bankgiro": "23-0108",
                "postgiro": "1307-8"
            },
            "activity": "Marknadsföring av veterinärmedicinska preparat o produkter för användning inom animalieproduktionen",
            "employees": 7,
            "annual_turnover": 1600000,
            "capital": 5000,
            "key_personnel": [
                {
                    "name": "Lars Johansson",
                    "position": "Verkst dir"
                }
            ],
            "establishment_year": 1966,
            "parent_company": "Pharmacia AB"
        },
        "6": {
            "company_name": "AGROMIN AB",
            "pnr": "216 21",
            "address": "Malmö, Fyrspannsg 13",
            "phone_number": "040-1605 05, 1605 15",
            "bank_details": {
                "bankgiro": "348-4334",
                "postgiro": "633343-9"
            },
            "activity": "Tillverkar o säljer kemiska preparat o produkter till lantbruk, trädgårdsmästerier, industri o hantverk",
            "employees": 3,
            "annual_turnover": 1800000,
            "capital": 5000,
            "key_personnel": [
                {
                    "name": "Erik Blohm",
                    "position": "Verkst dir"
                }
            ],
            "establishment_year": 1965
        },
        "7": {
            "company_name": "INTERGRAPHIC AB",
            "pnr": "163 21",
            "address": "Spånga 1, Kälvestav 104, Box 72",
            "phone_number": "08-36 22 90, 36 26 90",
            "bank_details": {
                "bankgiro": "23-6087",
                "postgiro": "706250"
            },
            "activity": "Tillverkar IGE-offset-plåt",
            "capital": 5000,
            "key_personnel": [
                {
                    "name": "Ing Gunnar Haag",
                    "position": "Firmatecknare"
                },
                {
                    "name": "Nils Holmin",
                    "position": "disp"
                }
            ],
            "establishment_year": 1963
        },
        "8": {
            "company_name": "GEAS KONSTHARTS AB",
            "pnr": "332 00",
            "address": "Gislaved, N Storg 14",
            "phone_number": "0371-116 90",
            "bank_details": {
                "bankgiro": "14-3041",
                "postgiro": "288090"
            },
            "activity": "Tillverkar plastartiklar. Specialitet: klädhängare",
            "capital": 20000,
            "key_personnel": [
                {
                    "name": "Ingvar Ambjörnsson",
                    "position": "Verkst dir"
                }
            ],
            "establishment_year": 1942
        },
        "9": {
            "company_name": "GEBA KONTORSTJÄNST GUSTAF BJERNE AB",
            "pnr": "252 25",
            "address": "Helsingborg, Bollbrog 8",
            "phone_number": "042-1164 01, 12 83 00",
            "bank_details": {
                "bankgiro": "652-9143",
                "postgiro": "170175-4"
            },
            "activity": "Säljer kontors- o ritmateriel",
            "capital": 50000,
            "key_personnel": [
                {
                    "name": "Gustaf Bjerne",
                    "position": "Verkst dir"
                }
            ],
            "establishment_year": 1940
        },
        "10": {
            "company_name": "FORSLUNDS MOTOR AB",
            "pnr": "800 06",
            "address": "Gävle 6, Box 6150",
            "phone_number": "026-129250",
            "bank_details": {
                "bankgiro": "783-7107",
                "postgiro": "264060-5"
            },
            "activity": "Bilhandels- o verkstadsrörelse (Volvo)",
            "employees": 260,
            "annual_turnover": 83000000,
            "capital": 2214000,
            "key_personnel": [
                {
                    "name": "Paul Paulsson",
                    "position": "Verkst dir"
                }
            ],
            "establishment_year": 1944
        },
        "11": {
            "company_name": "FORSLUNDS VERK-STÄDER AB",
            "pnr": "58104",
            "address": "Linköping 1, Platensg 27, Box 403",
            "phone_number": "013-10 23 00",
            "bank_details": {
                "bankgiro": "12-0096",
                "postgiro": "29426"
            },
            "activity": "Säljer Opel, Vauxhall o Bedford person- o lastbilar",
            "employees": 64,
            "annual_turnover": 13000000,
            "capital": 130000,
            "key_personnel": [
                {
                    "name": "Lennart Forslund",
                    "position": "Verkst dir"
                }
            ],
            "establishment_year": 1899
        },
        "12": {
            "company_name": "SAN",
            "activity": "Varanamn: ESA",
            "employees": 14,
            "annual_turnover": 4500000,
            "capital": 40000,
            "key_personnel": [
                {
                    "name": "Adv Carl-Gunder Hedström",
                    "position": "Styrelse"
                },
                {
                    "name": "Björn Eriksson",
                    "position": "dir, Verkst dir"
                }
            ],
            "establishment_year": 1900,
            "reorganization_year": 1943
        },
        "13": {
            "company_name": "SANDBERG AB, BYGGNADS-FIRMA ERLING",
            "pnr": "582 21",
            "address": "Linköping, Industrig 4",
            "phone_number": "013-1112 50",
            "bank_details": {
                "bankgiro": "347-0283",
                "postgiro": "164087-9"
            },
            "activity": "Byggnadsentreprenör",
            "capital": 50000,
            "key_personnel": [
                {
                    "name": "Byggmäst Erling Sandberg",
                    "position": "Verkst dir"
                }
            ],
            "establishment_year": 1962
        },
        "14": {
            "company_name": "SANDBERG AB, TEXTIL. AGENTUR HARALD O",
            "pnr": "103 84",
            "address": "Stockholm 7, Norrmalmstorg 1, Box 7258",
            "phone_number": "08-106251",
            "activity": "Agenturrörelse i damtyger",
            "annual_turnover": 3000000,
            "capital": 5000,
            "key_personnel": [
                {
                    "name": "Harald Sandberg",
                    "position": "Verkst dir"
                }
            ],
            "establishment_year": 1938
        },
        "15": {
            "company_name": "SANDBERG MASKINAFFÄR, IVAR T",
            "pnr": "650 03",
            "address": "Karlstad 3, Treffenbergsv 11, Box 3054",
            "phone_number": "054-11 01 99, 11 78 09",
            "bank_details": {
                "bankgiro": "100-2286",
                "postgiro": "264657"
            },
            "activity": "Säljer motorer, stationära o marin, elektr aggregat, konsulterande ingenjörsbyrå. Specialitet: tillverkar snöröjningsutrustningar",
            "reorganization_year": 1943,
            "establishment_year": 1930
        },
        "16": {
            "company_name": "THYLIN BIL AB, CURT",
            "pnr": "93101",
            "address": "Skellefteå 1, Box 57, Kanalg 59-61, NV-huset",
            "phone_number": "0910-170 60",
            "bank_details": {
                "bankgiro": "203-9600",
                "postgiro": "386086-3"
            },
            "activity": "Auktoriserad återförsäljare för General Motors (ej Vauxhall); verkstad o reservdelar",
            "employees": 60,
            "annual_turnover": 12500000,
            "capital": 185000,
            "key_personnel": [
                {
                    "name": "Curt Thylin",
                    "position": "Verkst dir"
                }
            ],
            "establishment_year": 1947
        },
        "17": {
            "company_name": "TYLLINGE AB",
            "pnr": "594 00",
            "address": "Gamleby, Tyllinge",
            "phone_number": "0493-330 71, 330 72",
            "activity": "Säljer skogsprodukter samt sågade o hyvlade trävaror",
            "annual_turnover": 4500000,
            "capital": 2800000,
            "key_personnel": [
                {
                    "name": "Disp Johan Rosenmüller",
                    "position": "Verkst dir"
                }
            ],
            "establishment_year": 1897
        },
        "18": {
            "company_name": "BROTEKNIK AB",
            "pnr": "59103",
            "address": "Motala 3, Vinterg 7, Fack 308",
            "phone_number": "0141-165 60",
            "activity": "Förslag, projektering, konstruktions- o arbetsritningar",
            "employees": 10,
            "annual_turnover": 650000,
            "capital": 25000,
            "key_personnel": [
                {
                    "name": "Civiling Karl Karlsson",
                    "position": "Verkst dir"
                }
            ],
            "establishment_year": 1962
        },
        "19": {
            "company_name": "BROTTBY MEKANISKA VERKSTADS AB",
            "pnr": "43135",
            "address": "Mölndal, Agatan 32",
            "phone_number": "031-27 50 90",
            "bank_details": {
                "bankgiro": "549-9025",
                "postgiro": "240495-2"
            },
            "activity": "Tillverkar variatorer o maskinbelysningar",
            "employees": 45,
            "annual_turnover": 4000000,
            "capital": 50000,
            "key_personnel": [
                {
                    "name": "Civiling Sven B Rennerfelt",
                    "position": "Verkst dir"
                }
            ],
            "establishment_year": 1938
        }
    }
}