{
    "original": "CEKA FORPACKNING AB\n\nPnr 16130\n\nBromma, Ekbacksv 32-34. Tel\n08-25 28 00. Bankgiro 11-8585.\nPostgiro 52696. Tga Cekaförpackning.\nTelex 1577 CEKA S\nVerksamhet: Tillverkar\nförpackningar. Offset-, bok- o djuptryck\nAntal anstäUda: 130\nÅrsomsättning: 25 000 000\nAktiekapital: 160800\nVerkst dir: Alf Christensson\nEtableringsår: 1916\nOmbildat till aktiebolag 1931.\n\nCELANDER FÖRSER\nLIND-GREN ARKITEKTKONTOR AB\n\nPnr 414 51\n\nGöteborg, Karl Johansg 98. Tel\n031-124970. Bankgiro 51-2946.\nPostgiro 240502-5\nVerksamhet: Husprojektering för\nbostäder\n\nAntal anställda: 28\nAktiekapital: 7 500\nVerkst dir: Ark SAR Stig Lindgren\nEtableringsår: 1962.\n\nSTRAUCH, INGENJÖRSFIRMA\n\nPnr 162 12\n\nVällingby 1, Grimstag 123. Box 102.\nTel 08-87 03 15. Bankgiro 168-8399.\nPostgiro 59057-0. Tga Strastock\nVerksamhet: säljer kullagerdubbar,\nmätverktyg, magnetfilter,\nhand-tachometrar, mät- o\nregleringsinstrument för temperatur o\nvarvtal, rotorpumpar, vibrationsdämpare\nVarunamn: Argo, Gimetall, Helios,\nMotoco, Rheintacho, IMC-Waukesha\nAntal anställda: 4\nÅrsomsättning: 3 000 000\nÄgare o chefen Ing Hans Strauch,\nänkefru M Strauch\nEtableringsån 1930.\n\nLUNDHOLM &amp; CO AB, F W\n\nPnr 900 02\n\nUmeå2, Box 2016. Tel 090-1127 37.\nBankgiro 79-9856. Postgiro\n279525-0. Tga Lundholmsplog\nVerksamhet: Tillverkar snöplogar,\nvägsladdar, stubbrivare, lastfickor,\nvattentankar, utläggarslädar m m\nVarunamn: Lyckseleplogen\nAntal anställda: 35\nÅrsomsättning: 2 400 000\nVerkst dir: Ing F G Lundholm.\n\nLUNDIN &amp; ERIKSON AB\n\nPnr 400 13\n\nGöteborg 36, Importhallen,\nPartihallarna. Box 36025. Tel\n031-80 06 55. Bankgiro 848-2382.\nPostgiro 520318-7. Tga Lunder.\nTelex 20989 LUNDER S\nVerksamhet: Importerar färsk frukt\no grönsaker\nAktiekapital: 25 000\nVerkst dir: Holger Lundin\nEtableringsår: 1955.\n\nDAHLÉN &amp; CO JÄRN AB\n\nPnr 41117\n\nGöteborg, V Hamng 13. Tel 031-\n\n11 04 3 0. 1173 80. Bankgiro\n848-3414. Postgiro 428205-9. Tga\nDal-steel. Telex 21184 DAHLÉN S\nVerksamhet: Säljer järn engros,\nplåt, varm- o kallvalsad\nAktiekapital: 100000\nFirmatecknare: Arne Dahlén, Bror\nHagelin\n\nEtableringsår: 1953.\n\nDAHL ENS\nFÅTÖLJ-INDUSTRI, AB\n\nPnr 520 25\n\nDalum, Box 142. Tel 0321-320 82,\n32070. Bankgiro 84-3316.\nPostgiro 282527. Tga Dahlénmöbler\nVerksamhet: Stoppmöbler.\nSpecial-tillverkar roterande fåtöljer\nstoppade på stålrörsstommar\nAntal anställda: 30\nÅrsomsättning: 2 000 000\nAktiekapital: 75000\nÄgare o chefer: Arne Dahlén,\nSten-Ebbe Dahlén\nEtableringsår: 1944.\n\nWOLRATHS RÖR AB\n\nPnr 750 03\n\nUppsala 3, Väderkvarnsg 16. Box\n3039. Tel 018-14 92 00. Bankgiro\n80-5072. Postgiro 476358\nVerksamhet:\nRörledningsentreprenör. Säljer värme- o\nsanitetsmate-rial\n\nAntal anställda: 50\nAktiekapital: 200 000\nStyrelse: Dir Erie Wolrath, dir\nFolke Wolrath, dir Arne Wahlgren\nVerkst dir: Ing Ame Wahlgren\nArbetschef: Ing Karl-Erik\nSvanberg\n\nEtableringsår: 1939.\n\nFLORELL&amp; PETTERSSON\n\nPnr 660 22\n\nTösse, Box 51. Tel 0532-20123.\n\nBankgiro 534-7083. Postgiro 99573-8\n\nVerksamhet: Gängbackar o gäng-\n\nkloppor, system Thürmer\n\nÄgare o chefer: Otto Florell, Johan\n\nPettersson\n\nEtableringsår: 1933.\n\nEGNAHEMS PANNOR EGOR, AB\n\nPnr 28101\n\nHässleholm 1, Box 71. Dragarv.\nTel 0451-14010. Bankgiro\n270-1571. Postgiro 413167-8. Tga Egor\nVerksamhet: Tillverkar o säljer\nvillapannor. Försäljes genom\nVVS-Marketing, Norrköping\nVamnamn: Duplomat, Complet\nAntal anställda: 85\nÅrsomsättning: 8000 000\nAktiekapital: 100 000\nVerkst dir: Harry Elg\nInköpschef: j Grahn\nKamrer: Stig Wessfelt\nEtableringsår: 1959.\n\nBORRE AB, ESKIL\n\nPnr 41118\n\nGöteborg, Magasinsg 15-17. Tel\n031-11 25 25,13 25 44.\nBankgiro42-0260. Postgiro 12048. Tga Borres\nVerksamhet: Generalagent för\nVieille-Montagne zinkvitt o\nFlei-schers Kjemiske Fabrikker A/S,\nBergen. Importörer av andra\npigment. Grosshandelsrörelse i färger\no fernissor\nAntal anställda: 5\nAktiekapital: 50 000\nÄgare: Fru Gunvor öhrnberg\nEtableringsår: 1913\nOmbildat till aktiebolag 1957.\n\nBORREGAARDSVENSKA AB\n\nPnr 402 22\n\nGöteborg 5, Sten Stureg 34. Box\n5074. Tel 031-810070. Telex\n2568. Tga Supralan\nVerksamhet: Säljer rayonull,\nrayon-ullgarn o syntetgarn. Kemikalier\nAntal anställda: 8\nÅrsomsättning: 25 000 000\nAktiekapital: 10 000\nVerkst din Jess K Magelssen jr\nEtableringsår: 1955.\n\nKAL\n\nKALEA, AB\n\nPnr 40011\n\nGöteborg 18, Spinnmästareg 8. Box\n18015. Tel 031-813010. Bankgiro\n51-0690. Postgiro 12313. Tga Kalea\nVerksamhet: Person- o varuhissar\nsamt elinstallationer\nAntal anställda: 70\nÅrsomsättning: 9 000 000\nAktiekapital: 100 000\nVerkst dir: Roland Strömbeck\nEtableringsår: 1912.\n\nKALENDERFURETAGEN,\nAB Förenade\n\nPnr 104 30\n\nStockholm 45, Sveav 53. Box 45054.\nTel 08-23 25 50\n\nVerksamhet: Utgivare av nedan\nnämnda publikationer. Utför genom\nsin Fotolist-Tjänst\nbeställningsarbeten (kalendrar, kataloger o\nliknade trycksaker)\nPublikationer:\n\nKompass-Sverige. Bankgiro\n168-8011. Postgiro 656300-1\nSveriges Handelskalender.\nBankgiro 168-7896. Postgiro 198976-3\nStorabonnenternas telefonkatalog.\n(Stor-Tele). Bankgiro 168-7995.\nPostgiro 555595-8\nNord-Tele. Postgiro 406869-8\nHurtig-Tele-Kataloget. Postgiro\n406869-8\n\nSveriges Förmögenhetskalender,\nSveriges Taxeringskalender,\nStockholms Taxeringskalender,\nTaxeringskalenderns Adressregister\nBankgiro 168-7987. Postgiro\n198976-3\n\nAntal anställda: 51\nÅrsomsättning: 4 600 000\nAktiekapital: 5 000\nVerkst dir: Arne Gårdlund\nFörsäljn-chef: Bertil Norén\nEtableringsår: 1859\nDotterbolag: AB Katalogtjänst,\nStockholm.\n\nFöretaget äges av Albert Bonniers\nFörlag AB, Stockholm.\n\nKALENDERFURLAGET I\nVÄSTERÅS AB\n\nPnr 721 08\n\nVästerås 1, Box 438. Kronv 32 A.\nTel 021-120210. Bankgiro\n350-6581. Postgiro 96537-6\nVerksamhet: Utgiver\ntaxeringskalendrar länsvis\nAntal anställda: 8\nÅrsomsättning: 1500000\nAktiekapital: 10 000\nStyrelse: Red Olof Wärmlöf (ordf),\nrevisor Ingvar Hertzwall\nVeikst dir: Olof Wärmlöf\nEtableringsår: 1967.\n\nERN\n\nVerksamhet:\nByggnadsentreprenör-firma för affärs- o bostadshus,\ngruppbebyggelser,\nindustribyggnader o offentliga byggnader\nAntal anställda: 70\nÅrsomsättning: 7 000 000\nAktiekapital: 66 000\nVerkst dir: Byggmäst Ernfrid\nAndersson\n\nArbetschef: Gösta Andersson\nEtableringsàr: 1937\nOmbildat till aktiebolag 1944.\n\nEHRNI, HÄNDELS- &amp;\nAGENTURFIRMA\n\nPnr 111 57\n\nStockholm, Slöjdg 9. Tel 08-11 86 58.\nBankgiro 69-4026. Postgiro\n198879-9\n\nVerksamhet: Säljer sportartiklar o\nmodetyger\n\nChef: Willi Ehrenreich\nEtableringsàr: 1938.\n\nERNITRON AB\n\nPnr 19148\n\nSollentuna, Frestav 69. Tel\n08-9618 00, 9618 20. Bankgiro 16-1687.\nPostgiro 706682\n\nVerksamhet: Fjärrkontroll,\nelektronik, reläer även för tryckta kort\nAntal anställda: 6\nÅrsomsättning: 1000 000\nAktiekapital: 30 000\nVerkst din Fred Jakobsson\nEtableringsàr: 1964.\n\nERNST RDM &amp; CO AB\n\nPnr 402 23\n\nGöteborg 5, Box 5138. Berzeliig\n14. Tel 031-8100 00. Bankgiro\n84-8080. Postgiro 25471. Tga\nErn-strömco. Telex 2518 ERN ST CO S\nVerksamhet: Byggnadsmaterial\nFilialer: Malmö C, ückerög 6. Box\n193, Malmö 1. Tel 040-93 76 86\nStockholm, Vretenborgsv 11. Box\n42035, Sthlm 42. Tel 08-18 02 50\nSundsvall, Heffnersv 32. Tel\n060-15 02 20\n\nÖrebro, Tackjärnsg 5. Tel\n019-1245 00\n\nVarunamn: Serponit, Serpofix, Silux,\n\nErnex, Carter\n\nAntal anställda: 90\n\nAktiekapital: 900 000\n\nVerkst dir: Gerhard Hobohm\n\nEtableringsàr: 1918.\n\nERO-FRYS AB\n\nPnr 67101\n\nArvika 1, Mötterudsv. Box 138. Tel\n0570-140 50. Bankgiro 102-9594.\nPostgiro 22155-6. Telex 5758\nVerksamhet: Tillverkar kombinerar\nde kyl- o frysskåp, frysdiskar\nAntal anställda: 250\nÅrsomsättning: 30 0 00 000\nAktiekapital: 500 000\nVerkst dir: Hans Uddbom\nEtableringsàr: 1962\nDotterbolag till Husqvarna\nVapenfabriks AB, Huskvarna.\n\nERPE AB, INGENJÖRSFIRMAN\n\nPnr 116 24\n\nStockholm, Asög 113-119. Tel\n08-42 3150, 423155. Bankgiro\n746-6071. Postgiro 454135-5\n\nVerksamhet: Finmek tillverkning o\n\nagenturverksamhet\n\nAktiekapital: 30 000\n\nVerkst dir: Ing Olof Johansson\n\nEtableringsàr: 1951\n\nOmbildat till aktiebolag 1961.\n\nERR-BEE, AB\n\nPnr 41122\n\nGöteborg. Kastellg 8-10. Tel\n031-13 2 3 8 3, 13 6 6 94. Bankgiro\n223-9465. Postgiro 43371-4\nVerksamhet: Tillverkar Err-Bee\nbil- o båtvårdsmedel\nVarunamn: Err-Bee\nAntal anställda: 4\nÅrsomsättning: 250 000\nAktiekapital: 10 000\nVerkst dir: Torbjörn Bärring\nEtableringsàr: 1933.\n\nERSTORPS GRUS AB\n\nPnr 612 00\n\nFinspång. Tel 0122-890 00.\nBankgiro 67-4853. Postgiro 288876\nVerksamhet: Sand-, grus- o\nsingelproduktion. Säljer fabriksbetong\nAntal anställda: 18\nÅrsomsättning: 4 750 000\nAktiekapital: 45 000\nStyrelse: Järnarb Karl Bengtsson\n(ordf), Gösta Klinga, Helge\nErikson, Torild Lindvall, byggn-chef\nTorsten Blomquist\nVerkst dir: Byggn-chef Torsten\nBlomquist\n\nEtableringsàr: 1945.\n\nERT TRAILER &amp; SPEDITION\nAB\n\nPnr 25101\n\nHelsingborg 1, Box 1003. Nyg 42.\nTel 042-18 01 85. Bankgiro\n200-9876. Postgiro 235800-0\nVerksamhet: Internationella\ntransporter över hela Europa\nAntal anställda: 20\nÅrsomsättning: 12 000 000\nAktiekapital: 75 000\nVerkst dir. Gunnar Richt\nEtableringsàr 1968.",
    "structured": {
        "1": {
            "company_name": "CEKA FORPACKNING AB",
            "pnr": "16130",
            "address": "Bromma, Ekbacksv 32-34",
            "phone_number": "08-25 28 00",
            "bank_details": {
                "bankgiro": "11-8585",
                "postgiro": "52696"
            },
            "activity": "Tillverkar förpackningar. Offset-, bok- o djuptryck",
            "employees": 130,
            "annual_turnover": 25000000,
            "capital": 160800,
            "key_personnel": [
                {
                    "name": "Alf Christensson",
                    "position": "Verkst dir"
                }
            ],
            "establishment_year": 1916
        },
        "2": {
            "company_name": "CELANDER FÖRSER LIND-GREN ARKITEKTKONTOR AB",
            "pnr": "414 51",
            "address": "Göteborg, Karl Johansg 98",
            "phone_number": "031-124970",
            "bank_details": {
                "bankgiro": "51-2946",
                "postgiro": "240502-5"
            },
            "activity": "Husprojektering för bostäder",
            "employees": 28,
            "capital": 7500,
            "key_personnel": [
                {
                    "name": "Stig Lindgren",
                    "position": "Verkst dir"
                }
            ],
            "establishment_year": 1962
        },
        "3": {
            "company_name": "STRAUCH, INGENJÖRSFIRMA",
            "pnr": "162 12",
            "address": "Vällingby 1, Grimstag 123, Box 102",
            "phone_number": "08-87 03 15",
            "bank_details": {
                "bankgiro": "168-8399",
                "postgiro": "59057-0"
            },
            "activity": "Säljer kullagerdubbar, mätverktyg, magnetfilter, hand-tachometrar, mät- o regleringsinstrument för temperatur o varvtal, rotorpumpar, vibrationsdämpare",
            "employees": 4,
            "annual_turnover": 3000000,
            "key_personnel": [
                {
                    "name": "Ing Hans Strauch",
                    "position": "Ägare o chefen"
                },
                {
                    "name": "M Strauch",
                    "position": "Ägare o chefen"
                }
            ],
            "establishment_year": 1930
        },
        "4": {
            "company_name": "LUNDHOLM & CO AB, F W",
            "pnr": "900 02",
            "address": "Umeå2, Box 2016",
            "phone_number": "090-1127 37",
            "bank_details": {
                "bankgiro": "79-9856",
                "postgiro": "279525-0"
            },
            "activity": "Tillverkar snöplogar, vägsladdar, stubbrivare, lastfickor, vattentankar, utläggarslädar m m",
            "employees": 35,
            "annual_turnover": 2400000,
            "key_personnel": [
                {
                    "name": "Ing F G Lundholm",
                    "position": "Verkst dir"
                }
            ],
            "establishment_year": null
        },
        "5": {
            "company_name": "LUNDIN & ERIKSON AB",
            "pnr": "400 13",
            "address": "Göteborg 36, Importhallen, Partihallarna, Box 36025",
            "phone_number": "031-80 06 55",
            "bank_details": {
                "bankgiro": "848-2382",
                "postgiro": "520318-7"
            },
            "activity": "Importerar färsk frukt o grönsaker",
            "capital": 25000,
            "key_personnel": [
                {
                    "name": "Holger Lundin",
                    "position": "Verkst dir"
                }
            ],
            "establishment_year": 1955
        }
    }
}