{
    "original": "WIDEBOLAGET AB\n\nPnr 212 25\n\nMalmö, Agatan 7. Tel 040-93 43 30.\nBankgiro 871-3026. Postgiro\n148230-0. Tga Widebolaget\nVerksamhet: Säljer\nbyggnadsmaterial, kemikalier etc\nVarunamn: Muranite, Wibo\nAktiekapital: 90 000\nChef: Disp Greger Bergström\nEtableringsår: 1940.\n\nHANSSON &amp; CO, AB HUGO\n\nPnr 95100\n\nLuleå, Hornsg 8. Tel 0920-173 81,\n129 64. Bankgiro 75-2621.\nPostgiro 60094. Tga Hansson\nVerksamhet: Tillverkar formluckor\nm m\n\nAntal anställda: 60\nÅrsomsättning: 3 500 000\nAktiekapital: 90 000\nVerkst dir: Hugo Hansson\nEtableringsår: 1920.\n\nHANSONS MEK VERKSTAD,\nAB J HILDING\n\nPnr 725 90\n\nVästerås,Kungsåra.Tel 021-21100.\nBankgiro 985-3078. Postgiro\n129851-2\n\nVerksamhet: Legotillverkning av\nmaskiner, maskindetaljer o\nutrustningar till större\nmaskinanläggningar. Legobearbetning av\nmaskindetaljer. Plåtslageri,\nmonterings-o reparationsarbeten. Specialitet:\nBearbetning av gods i stora\ndimensioner\n\nAntal anställda: 110\nÅrsomsättning: 8 000 000\nAktiekapital: 100 000\nStyrelse: Fabrikör Hilding Hanson\n(ordf), dir Ivar Dybeck, fru Ingegerd\nHanson\n\nFöretagschef: Fabrikör Hilding\nHanson\n\nEtableringsår: 1958\nOmbildat till aktiebolag 1963.\n\nHANSSON, AB JOH\n\nPnr 750 03\n\nUppsala 3, Väderkvarnsg 34. Box\n3011. Tel 018-13 90 70. Bankgiro\n80-2109. Postgiro 161242\nVerksamhet: Handel med\nspannmål o konstgödsel\nAntal anställda: 19\nÅrsomsättning: 8 500 000\nAktiekapital: 130 400\nVerkst dir: Fru Anne-Marie\nHansson-Buckau\nEtableringsår: 1897.\n\nNILSSONS ÅKERI AB, INGE\n\nPnr 284 00\n\nPerstorp, Box 31. Ringarev 25. Tel\n0435-306 35. Bankgiro 673-9429.\nPostgiro 333668-2\nVerksamhet: Fjärrtransporter\nAntal anställda: 85\nÅrsomsättning: 9 000 000\nAktiekapital: 500 000\nVerkst dir: Inge Nilsson\nEtableringsår: 1934\nOmbildat till aktiebolag 1953.\n\nNILSSONS SNICKERI.\nFABRIK AB, J\n\nPnr 261 52\n\nLandskrona, Vinterg 8. Tel\n0418-10112. Bahkgiro 86-8544. Postgiro\n91999-3\n\nVerksamhet: Tillverkar inredningar\nför butiker, banker, hotell o sjukhus\nAntal anställda: 35\nÅrsomsättning: 2 000 000\nAktiekapital: 20 000\nVerkst dir: Fabr Gustav Nilsson\nEtableringsår: 1904.\n\nTÄCKFABRIKEN\n\nPnr 340 15\n\nVittaryd. Tel 0370-450 30.\nBankgiro 291-6849. Postgiro 273424-2\nVerksamhet: Tillverkar täcken,\nkuddar, madrasser, sovsäckar,\ncampingtäcken o överkast\nAntal anställda: 20\n\nÅrsomsättning: 2100000\nChef: Sigvard von Porat\nEtableringsår. 1931.\n\nTÄCKLINDS EFTR, R\nVOGEL-GESANG, M\n\nPnr 102 43\n\nStockholm 5, Box 5108. Nybrog 7.\nTel 08-6179 56, 6179 57. Postgiro\n4679. Tga Signalroth\nVerksamhet: Järnvägsteknisk byrå.\nRepresentant för Grüter, Grage &amp;\nCo KG SOEST, Västtyskland.\nSkjutbord för vagnar o lok,\nvändskivor för lok-vagnar o bilar,\nrangeringsanläggningar, vinschar\nVarunamn: Grüter, Grage &amp; Co KG\nÄgare o chef: R Vogelgesang.\n\nTÄRNAN, AB SYFABRIKEN\n\nPnr 60002\n\nNorrköping 2, Hantverkareg 20. Box\n2019. Tel 011-13 9710. Postgiro\n298051. Tga Sytab\nVerksamhet: Tillverkar sängkläder\nm m\n\nAntal anställda: 42\nAktiekapital: 100 000\nVerkst dir B Hilmer Fredriksson\nEtableringsån 1946.\n\nGRÖNBERG &amp; BROCH AB\n\nPnr 115 40\n\nStockholm, Tegeludds v 32. Tel\n08-67 07 70. Bankgiro 700-0599.\nPostgiro 1305-2. Tga Typmaskin\nVerksamhet: Import av\ntryckeriförnödenheter o sjukvårdsmaterial\nAktiekapital: 5 000\nVerkst dir: Just Broch\nEtableringsår: 1901.\n\nGRÖNBERGS MASKINAFFÄR\nEFTR\n\nPnr 42131\n\nVästra Frölunda, Frökotteg 15.\nTel 031-45 1120, 4512 20, 47 94 41.\nBankgiro 107-7486. Postgiro\n520423-5\n\nVerksamhet: Säljer nya o\nbegagnade maskiner för järn o\nmetallbearbetning, samt nya o begagnade\nsnickerimaskiner\nÄgare o chef: Lennart Strömberg\nEtableringsår: 1930.\n\nSCH\n\nAntal anstäUda: 11\nÅrsomsättning: 18 000 000\nAktiekapital: 100 000\nStyrelse: Jur kand Thomas\nAlexandersson, dir Per Ulfstedt, dir\nB Schauman, dir V Linander\nVerkst dir Villy Linander\nEkonomichef: Olav Degerholm\nProd-chef: Ingemar Dolk\nEtableringsàr: 1968\nDotterbolag till Oy Wilh Schauman\nAB, Helsingfors, Finland.\n\nSCHEJA AB, BO L\n\nPnr 114 46\n\nStockholm, Humlegårdsg 5. Tel\n08-61 3230, 61 89 30. Bankgiro\n57-5725. Postgiro 257200. Telex\n1589. Tga Boelscheja\nVerksamhet: Agenturfirma\nAntal anstäUda: 8\nÅrsomsättning: 12 000 000\nAktiekapital: 20 000\nVerkst dir. Bo L Scheja\nEtableringsàr 1947.\n\nSON\n\nAktiekapital: 50 000\nVerkst dir: Ing J O Krantz\nEtableringsàr: 1915.\n\nSOLINGE SNICKERIFABRIK\n\nPnr 740 47\n\nHarbonäs, Solinge. Tel 0292-30078\n\nVerksamhet: Tillverkar portar o\n\nvikväggar i olika träslag\n\nAntal anställda: 20\n\nÅrsomsättning: 1 000 000\n\nÄgare o chef: Pabr Ernst Bäckström\n\nEtableringsàr: 1944.\n\nSOLLEBOLAGEN AB\n\nPnr 460 40\n\nNossebro. Tel 0512-506 50. Telex\n5262. Tga Sollebolag\nVerksamhet: Säljer fröer, utsäden,\nspannmål, foder- o gödselmedel\nAktiekapital: 400 000\nVerkst dir: Conrad Berg\nEtableringsàr: 1933.\n\nSOLLEBRUNNS CEMENT.\nGJUTERI, AB\n\nPnr 460 30\n\nSollebrunn. Tel 0322-40132\nVerksamhet: Betongvaror\nAktiekapital: 110 000\nVerkst dir: Gustaf Gillberg\nEtableringsån 1945.\n\nSOLLEBRUNNS FÅTÖLJ.\nINDUSTRI, AB\n\nPnr 460 30\n\nSollebrunn, Box 27. Tel 0322-401 53.\nBankgiro 891-6470. Postgiro\n294485-8\n\nVerksamhet: Stoppning o\nförsäljning av soffor o fåtöljer\nAntal anställda: 4\nÅrsomsättning: 150 000\nAktiekapital: 25 000\nVerkst dir: Sven Henriksson\nEtableringsàr: 1946.\n\nSOLLEFTEÅ BRYGGERI AB\n\nPnr 881 00\n\nSollefteå, Storg 99. Tel 0620-121 20,\n123 15\n\nVerksamhet: Tillverkar malt- o\nläskedrycker\nAntal anställda: 66\nÅrsomsättning: 13 750 000\nAktiekapital: 450 000\nStyrelseordf: Dir Harry Hjalmarson\nVerkst dir: Bengt Thorén\nEtableringsàr: 1857.\n\nSOLLEFTEÅ\nCEMENT-VARUFABRIK AB\n\nPnr 881 00\n\nSollefteå, Granvåg 5005. Tel\n0620-117 54. 103 68. Bankgiro 187-7695.\nPostgiro 388217-2\nVerksamhet: Tillverkar o säljer\nfärdig fabriksbetong mm\nAntal anställda: 20\nÅrsomsättning: 2 000000\nAktiekapital: 30 000\nVerkst dir: Sven Wikström\nEtableringsàr: 1927.\n\nSOLLENTUNA\nBIL-DEMONTERING AB\n\nPnr 191 21\n\nSollentuna 1, Kronåsv 6. Box 28.\n\nTel 08-35 53 01, 3572 80. Bankgiro\n350-6326. Postgiro 643095-3\nVerksamhet: Bilskrotning o\nförsäljning av begagnade bildelar\nAktiekapital: 30 000\nÄgare: Hans Cardell, Karl-Hugo\nWerner\n\nEtableringsàr: 1970.\n\nSOLNA KARTONG AB\n\nPnr 171 52\n\nSolna, Gårdsv 2. Tel 08-83 08 95.\nBankgiro 136-2714. Postgiro\n499970-2\n\nVerksamhet: Tillverkar kartonger.\nUtför fodring av skyltar mm\nAntal anställda: 30\nÅrsomsättning: 2 200 000\nAktiekapital: 20 000\nVerkst dir: Bertil Säf strand\nEtableringsàr: 1948.\n\nSOLNA PRESSGJUTERI, AB\n\nPnr 19154\n\nSollentuna, Hovslagarv 5. Tel\n08-35 26 20. Bankgiro 171-2140.\nPostgiro 329120-0\n\nVerksamhet: Pressgjutning av\nbeställningsgods\nAntal anställda: 50\nÅrsomsättning: 4 000 000\nAktiekapital: 100 000\nVerkst dir: Pabr Einar Sundström\nEtableringsàr: 1946.\n\nSOLNA VERKTYGS AB\n\nPnr 16130\n\nBromma, Ekbacksv 42. Tel\n08-80 0104,80 0108. Bankgiro 39-0930.\nPostgiro 411616. Tga Swabolag\nVerksamhet: Säljer verktyg o\nverktygsmaskiner samt tillverkar\nhårdmetallverktyg\nAktiekapital: 5 000\nVerkst dir: Herbert Johansson\nEtableringsàr: 1957.\n\nSOLOTHERM AB\n\nPnr 402 31\n\nGöteborg 7, Värmlandsg 16. Box\n7015. Tel 031-1408 28. Bankgiro\n84-5904. Postgiro 154990.\nTga Solotherm. Telex 20659\nVerksamhet: Barometrar,\nsimartik-lar, solglasögon o termometrar\nAntal anställda: 10\nAktiekapital: 50 000\nFörsäljn-chef: Gösta Berntsson\nEtableringsån 1938.\n\nELCOMA, AB\n\nPnr 102 50\n\nStockholm 27, Pack. Lidingöv 50.\nTel 08-67 97 80. Bankgiro 17-5739.\nPostgiro 402950. Telex 10776\nVerksamhet: Säljer\nelektronikkomponenter\n\nVarunamn: Philips, Mullard, Valvo,\n\nA.W. Haydon, Polymotor\n\nAntal anställda: 55\n\nStyrelse: Dir Olle Franzén (ordf).\n\ndir Curt Rödöö, dir Bengt Carlman\n\n(suppl)\n\nVerkst dir: Curt Rödöö\n\nEtableringsår: 1966\n\nDotterbolag till Svenska AB Philips.\n\nELDAFO, INGENJÖRSFIRMA\nAB\n\nPnr 162 30\n\nVällingby, Kvarnhagsg 126. Tel\n08-89 65 00, 89 7200. Bankgiro\n747-23 27. Postgiro 455755-9\nVerksamhet: Säljer\nkommunikationsradio o amatörradio\nAntal anställda: 3\nEtableringsår: 1961.\n\nHJO FABRIKS AB\n\nPnr 544 00\n\nHjo, Almedalsg. Tel 0503-105 00.\nBankgiro 216-4549. Postgiro\n374000-8\n\nVerksamhet: Tillverkar o säljer\nThebeco elektr manglar\nVarunamn: Thebeco\nAntal anställda: 35\nÅrsomsättning: 5 000000\nAktiekapital: 75 000\nStyrelseordf: Fabr Arne Stenestam\nVerkst dir: Fabr Tage Schill\nFörsäljn-chef: Gunnar Yngve .\nEtableringsår: 1957.\n\nSNI\n\nSMALANDS MOTOR, AB\n\nPnr 38101\n\nKalmar 1, Pack. Södra v 68-70.\nTel 0480-156 90. Bankgiro 14-8247.\nPostgiro 278643-2\nVerksamhet: Bilförsäljning.\nRepresentant för Saab o Plymouth. Säljer\nMF-traktorer o trösk or samt\nlantbruksmaskiner. Utför reparationer\nFilialer: 382 00 Nybro, Sågareg 13.\nTel 0481-140 95\n\n361 00 Emmaboda, Torgg 4. Tel\n0471-104 00\nAntal anställda: 50\nÅrsomsättning: 17 007 900\nAktiekapital: 100 000\nVerkst dir: Arnold Karlsson\nDisponent: Roger Georgsson\nEtableringsår: 1965.",
    "structured": {
        "1": {
            "company_name": "WIDEBOLAGET AB",
            "address": "Malmö, Agatan 7",
            "phone_number": "040-93 43 30",
            "bank_details": {
                "bankgiro": "871-3026",
                "postgiro": "148230-0"
            },
            "activity": "Säljer byggnadsmaterial, kemikalier etc",
            "capital": 90000,
            "key_personnel": [
                {
                    "name": "Disp Greger Bergström",
                    "position": "Chef"
                }
            ],
            "establishment_year": 1940
        },
        "2": {
            "company_name": "HANSSON & CO, AB HUGO",
            "address": "Luleå, Hornsg 8",
            "phone_number": "0920-173 81",
            "bank_details": {
                "bankgiro": "75-2621",
                "postgiro": "60094"
            },
            "activity": "Tillverkar formluckor m m",
            "employees": 60,
            "annual_turnover": 3500000,
            "capital": 90000,
            "key_personnel": [
                {
                    "name": "Hugo Hansson",
                    "position": "Verkst dir"
                }
            ],
            "establishment_year": 1920
        },
        "3": {
            "company_name": "HANSONS MEK VERKSTAD, AB J HILDING",
            "address": "Västerås,Kungsåra",
            "phone_number": "021-21100",
            "bank_details": {
                "bankgiro": "985-3078",
                "postgiro": "129851-2"
            },
            "activity": "Legotillverkning av maskiner, maskindetaljer o utrustningar till större maskinanläggningar. Legobearbetning av maskindetaljer. Plåtslageri, monterings-o reparationsarbeten. Specialitet: Bearbetning av gods i stora dimensioner",
            "employees": 110,
            "annual_turnover": 8000000,
            "capital": 100000,
            "key_personnel": [
                {
                    "name": "Fabrikör Hilding Hanson",
                    "position": "Styrelse (ordf)"
                },
                {
                    "name": "Ivar Dybeck",
                    "position": "Dir"
                },
                {
                    "name": "Ingegerd Hanson",
                    "position": "Fru"
                }
            ],
            "establishment_year": 1958
        },
        "4": {
            "company_name": "HANSSON, AB JOH",
            "address": "Uppsala 3, Väderkvarnsg 34. Box 3011",
            "phone_number": "018-13 90 70",
            "bank_details": {
                "bankgiro": "80-2109",
                "postgiro": "161242"
            },
            "activity": "Handel med spannmål o konstgödsel",
            "employees": 19,
            "annual_turnover": 8500000,
            "capital": 130400,
            "key_personnel": [
                {
                    "name": "Fru Anne-Marie Hansson-Buckau",
                    "position": "Verkst dir"
                }
            ],
            "establishment_year": 1897
        },
        "5": {
            "company_name": "NILSSONS ÅKERI AB, INGE",
            "address": "Perstorp, Box 31. Ringarev 25",
            "phone_number": "0435-306 35",
            "bank_details": {
                "bankgiro": "673-9429",
                "postgiro": "333668-2"
            },
            "activity": "Fjärrtransporter",
            "employees": 85,
            "annual_turnover": 9000000,
            "capital": 500000,
            "key_personnel": [
                {
                    "name": "Inge Nilsson",
                    "position": "Verkst dir"
                }
            ],
            "establishment_year": 1934
        }
    }
}