{
    "original": "FLO\n\nVerksamhet: Tillverkar o säljer\nsmakråvaror för livsmedelsindustrin\nAntal anställda: 18\nÅrsomsättning: 4 000 000\nAktiekapital: 80 000\nVerkst din Henry Björklund\nEtableringsår: 1967.\n\nflemefa metallvaru- &amp;\nverktygsfabrik ab\n\nPnr 56013\n\nHok, Box 110. Tel 0393-21047.\nBankgiro 98-5466. Postgiro 134803\nVerksamhet: Lättmetallmanufaktur.\n\nPressning o stansning i alla\nmetaller\n\nAktiekapital: 20 000\nEtableringsår: 1937.\n\nflens bokförings- &amp;\nrevisionsbyrå\n\nPnr 642 00\n\nFlen, S Kungsg 7 A. Tel\n0157-124 50. Bankgiro 828-9381.\nPostgiro 12822-3\n\nVerksamhet: Utför årsbokföring,\n\nbokslut, deklarationer o revision\n\nAntal anställda: 8\n\nChef: Revisor Per-Anders Thöver-\n\nstam\n\nEtableringsår: 1951.\n\nINGVARS EL &amp; DIESEL, AB\n\nPnr 824 01\n\nHudiksvall 1, Drottningg 15. Box\n106. Tel 0650-155 30\nVerksamhet: Diesel- o bilelektrisk\nspecialverkstad\nAntal anställda: 16\nÅrsomsättning: 1 500 000\nAktiekapital 10000\nEtableringsår: 1963.\n\nINKA-TEKNIK AB, INGEN.\nlüRSFIRMA\n\nPnr 122 37\n\nEnskede, Sockenv 391. Tel\n08-4939 82, 48 45 09. Bankgiro\n481-0164. Postgiro 199814-5. Tga\nInka-Teknik\n\nVerksamhet: Tillverkar\nmätinstrument, tachometrar för fartyg, tåg\no rälsbussar samt specialskruv m m\nAntal anställda: 14\nÅrsomsättning: 800 000\nAktiekapital: 40 000\nVerkst dir: Ing Ingvar Björk\nEtableringsår: 1946\nOmbildat till aktiebolag 1959.\n\n|NOR AB, INSTRUMENT.\nFIRMAN\n\nPnr 213 64\n\nMalmö SO,Emilstorpsg 32.\nTel040-94 2155. Bankgiro 26-5218.\nPostgiro 148603. Telex 32452. Tga\nInstinor\n\nVerksamhet: Säljer manometrar,\ntermometrar, hygrometrar m m\nAktiekapital: 50 000\nVerkst dir: Ing Alfred Brakl\nEtableringsår: 1940.\n\nKONSUMENTINTERJUVER AB\n\nPnr 220 09\n\nLund 9, Sunnanv 14 E. Fack. Tel\n046-14 6040. Bankgiro 118-3672.\nTelex 32270\n\nVerksamhet: Postala kollektiva\nundersökningar\nAntal anställda: 10\nVerkst dir: Civilekonom Jan\nTeglund\n\nEtableringsår: 1969.\n\nBEL\n\nBELL &amp; HOWELL AB\n\nPnr 172 30\n\nSundbyberg, Vinterg 1. Tel\n08-28 25 25. Bankgiro 161-2860.\nPostgiro 567370-2. Tga Behowswed.\nTelex 17133 BEHOW S\nVerksamhet: Säljer filmkameror,\nfilmprojektorer o fotoprodukter\nAntal anställda: 46\nÅrsomsättning: 14 000 000\nAktiekapital: 525 000\nVerkst dir: Walter Kotke\nEtableringsår: 1965.\n\nMONTOIL, AB\n\nPnr 100 55\n\nStockholm 10, Banérg 37. Fack.\nTel 08-67 07 25. Bankgiro 44-7113.\nPostgiro 252914. Telex 1664. Tga\nMontoil\n\nVerksamhet: Import av kemikalier\no kemiska råvaror\nAntal anstäUda: 10\nAktiekapital: 200 000\nVerkst dir: Alf Sigge\nEtableringsår: 1945.\n\nALUSEAL, AB\n\nPnr 100 61\n\nStockholm 11, Fack. Tjärhovsg\n25-29. Tel 08-4137 35. Bankgiro\n224-9183. Postgiro 359945-3\nVerksamhet: Tillverkning o\nförsäljning av elektriska\napparatutrustningar, tryckknappar o\ntryckknappslådor\n\nAntal anställda: 5\nÅrsomsättning: 1500 000\nAktiekapital: 30 000\nStyrelse: Ing Ingemar Törhagen,\ndir Olof Wåhlin\nChef: Ingemar Törhagen\nEtableringsår: 1967.\n\nBARA TEGELBRUK, AB\n\nPnr 23040\n\nBara. Tel 040-44 71 84, 44 71 85.\nBankgiro 277-7068. Postgiro\n88180-5\n\nVerksamhet: Tillverkar gult\nfasadtegel\n\nAntal anstäUda: 22\nÅrsomsättning: 2000 000\nAktiekapital: 80 000\nVerkst dir: Axel Nyberg\nEtableringsår: 1933.\n\nCANDOR, KEMISKA AB\n\nPnr 60101\n\nNorrköping 1, Fack. Tel\n011-18 63 60. Bankgiro 610-2362.\nPostgiro 253045-9. Tga Candorkemi.\nTelex 64113\n\nVerksamhet: Anläggningar o\nkemikalier för galvanisk o kemisk\nytbehandling\nAntal anställda: 72\nÅrsomsättning: 18 000 000\nAktiekapital: 500 000\nStyrelse: Dir Nils Wahlström, dir\nGunnar Ekström, dir Börje Dickert\nVerkst dir: Nils Wahlström\nPlatschef: Rolf Bergvall\nEtableringsår: 1946.\n\nDAL\n\nD\n\nD &amp; E TRADING AB\n\nPnr 136 25\n\nHanden, Box 524. Vikingav 55.\nTel 08-777 2936, 777 2937.\nBankgiro 280-9101. Postgiro 33359-1.\nTga Detrade, Stockholm\nVerksamhet: Rullade glidlager,\nsintrade bussningar o detaljer,\nräffelpinnar, blindnit o\nelektromagneter\n\nVarunamn: EKS, Kerpin, WB 800,\nWICO\n\nAktiekapital: 100 000\nStyrelse: Ing Bertil Deijfen (ordf),\nciviling Ake Deijfen, ing Bernt\nEliasson\n\nVerkst dir: Ake Deijfen\nFörsäljningschef: Bernt Eliasson\nEtableringsår: 1966.\n\nSÄVSJO PLÅTINDUSTRI AB\n\nPnr 576 00\n\nSävsjö, Smedg. Tel 0382-10677.\n\nBankgiro 836-5876. Postgiro\n389613-1\n\nVerksamhet: Tillverkar alla slags\nstålkarmar för lasarettsbyggnader\no skolor, stålprofiler för\ngipsmellanväggar. Försäljning av\nbranddörrar. Utför rostfria arbeten\nAntal anställda: 10\nÅrsomsättning: 1400 000\nAktiekapital: 15 000\nVerkst dir: Civiling Ake Stillemark.\n\nSÄVSJO PLÅT &amp; SMIDE AB\n\nPnr 576 00\n\nSävsjö, Industriområdet. Tel\n0382-102 62, 114 62. Bankgiro 836-5504.\nPostgiro 348858-2\nVerksamhet: Tillverkar fälgar för\nindustri- o jordbruks traktorer m m\nAntal anställda: 28\nÅrsomsättning: 4 000 000\nAktiekapital: 160 000\nVerkst dir: Karl-Erik Nilsson\nEtableringsår: 1957.",
    "structured": {
        "1": {
            "company_name": "FLO",
            "activity": "Tillverkar o säljer smakråvaror för livsmedelsindustrin",
            "employees": 18,
            "annual_turnover": 4000000,
            "capital": 80000,
            "establishment_year": 1967
        },
        "2": {
            "company_name": "Flemefa Metallvaru- & Verktygsfabrik AB",
            "pnr": "56013",
            "address": "Hok, Box 110",
            "phone_number": "0393-21047",
            "bank_details": {
                "bankgiro": "98-5466",
                "postgiro": "134803"
            },
            "activity": "Lättmetallmanufaktur. Pressning o stansning i alla metaller",
            "capital": 20000,
            "establishment_year": 1937
        },
        "3": {
            "company_name": "Flens Bokförings- & Revisionsbyrå",
            "pnr": "642 00",
            "address": "Flen, S Kungsg 7 A",
            "phone_number": "0157-124 50",
            "bank_details": {
                "bankgiro": "828-9381",
                "postgiro": "12822-3"
            },
            "activity": "Utför årsbokföring, bokslut, deklarationer o revision",
            "employees": 8,
            "key_personnel": [
                {
                    "name": "Revisor Per-Anders Thöverstam"
                }
            ],
            "establishment_year": 1951
        },
        "4": {
            "company_name": "Ingvars El & Diesel, AB",
            "pnr": "824 01",
            "address": "Hudiksvall 1, Drottningg 15, Box 106",
            "phone_number": "0650-155 30",
            "activity": "Diesel- o bilelektrisk specialverkstad",
            "employees": 16,
            "annual_turnover": 1500000,
            "capital": 10000,
            "establishment_year": 1963
        },
        "5": {
            "company_name": "Inka-Teknik AB, Ingen. lürsfirma",
            "pnr": "122 37",
            "address": "Enskede, Sockenv 391",
            "phone_number": "08-4939 82, 48 45 09",
            "bank_details": {
                "bankgiro": "481-0164",
                "postgiro": "199814-5"
            },
            "activity": "Tillverkar mätinstrument, tachometrar för fartyg, tåg o rälsbussar samt specialskruv m m",
            "employees": 14,
            "annual_turnover": 800000,
            "capital": 40000,
            "key_personnel": [
                {
                    "name": "Ing Ingvar Björk",
                    "position": "Verkst dir"
                }
            ],
            "establishment_year": 1946
        },
        "6": {
            "company_name": "Nor AB, Instrument. Firman",
            "pnr": "213 64",
            "address": "Malmö SO, Emilstorpsg 32",
            "phone_number": "040-94 2155",
            "bank_details": {
                "bankgiro": "26-5218",
                "postgiro": "148603"
            },
            "activity": "Säljer manometrar, termometrar, hygrometrar m m",
            "capital": 50000,
            "key_personnel": [
                {
                    "name": "Ing Alfred Brakl",
                    "position": "Verkst dir"
                }
            ],
            "establishment_year": 1940
        },
        "7": {
            "company_name": "Konsumentinterjuver AB",
            "pnr": "220 09",
            "address": "Lund 9, Sunnanv 14 E",
            "phone_number": "046-14 6040",
            "bank_details": {
                "bankgiro": "118-3672"
            },
            "activity": "Postala kollektiva undersökningar",
            "employees": 10,
            "key_personnel": [
                {
                    "name": "Civilekonom Jan Teglund",
                    "position": "Verkst dir"
                }
            ],
            "establishment_year": 1969
        },
        "8": {
            "company_name": "Bell & Howell AB",
            "pnr": "172 30",
            "address": "Sundbyberg, Vinterg 1",
            "phone_number": "08-28 25 25",
            "bank_details": {
                "bankgiro": "161-2860",
                "postgiro": "567370-2"
            },
            "activity": "Säljer filmkameror, filmprojektorer o fotoprodukter",
            "employees": 46,
            "annual_turnover": 14000000,
            "capital": 525000,
            "key_personnel": [
                {
                    "name": "Walter Kotke",
                    "position": "Verkst dir"
                }
            ],
            "establishment_year": 1965
        },
        "9": {
            "company_name": "Montoil, AB",
            "pnr": "100 55",
            "address": "Stockholm 10, Banérg 37",
            "phone_number": "08-67 07 25",
            "bank_details": {
                "bankgiro": "44-7113",
                "postgiro": "252914"
            },
            "activity": "Import av kemikalier o kemiska råvaror",
            "employees": 10,
            "capital": 200000,
            "key_personnel": [
                {
                    "name": "Alf Sigge",
                    "position": "Verkst dir"
                }
            ],
            "establishment_year": 1945
        },
        "10": {
            "company_name": "Aluseal, AB",
            "pnr": "100 61",
            "address": "Stockholm 11, Fack. Tjärhovsg 25-29",
            "phone_number": "08-4137 35",
            "bank_details": {
                "bankgiro": "224-9183",
                "postgiro": "359945-3"
            },
            "activity": "Tillverkning o försäljning av elektriska apparatutrustningar, tryckknappar o tryckknappslådor",
            "employees": 5,
            "annual_turnover": 1500000,
            "capital": 30000,
            "key_personnel": [
                {
                    "name": "Ingemar Törhagen",
                    "position": "Chef"
                }
            ],
            "establishment_year": 1967
        },
        "11": {
            "company_name": "Bara Tegelbruk, AB",
            "pnr": "23040",
            "address": "Bara",
            "phone_number": "040-44 71 84, 44 71 85",
            "bank_details": {
                "bankgiro": "277-7068",
                "postgiro": "88180-5"
            },
            "activity": "Tillverkar gult fasadtegel",
            "employees": 22,
            "annual_turnover": 2000000,
            "capital": 80000,
            "key_personnel": [
                {
                    "name": "Axel Nyberg",
                    "position": "Verkst dir"
                }
            ],
            "establishment_year": 1933
        },
        "12": {
            "company_name": "Candor, Kemiska AB",
            "pnr": "60101",
            "address": "Norrköping 1, Fack",
            "phone_number": "011-18 63 60",
            "bank_details": {
                "bankgiro": "610-2362",
                "postgiro": "253045-9"
            },
            "activity": "Anläggningar o kemikalier för galvanisk o kemisk ytbehandling",
            "employees": 72,
            "annual_turnover": 18000000,
            "capital": 500000,
            "key_personnel": [
                {
                    "name": "Nils Wahlström",
                    "position": "Verkst dir"
                },
                {
                    "name": "Rolf Bergvall",
                    "position": "Platschef"
                }
            ],
            "establishment_year": 1946
        },
        "13": {
            "company_name": "D & E Trading AB",
            "pnr": "136 25",
            "address": "Handen, Box 524, Vikingav 55",
            "phone_number": "08-777 2936, 777 2937",
            "bank_details": {
                "bankgiro": "280-9101",
                "postgiro": "33359-1"
            },
            "activity": "Rullade glidlager, sintrade bussningar o detaljer, räffelpinnar, blindnit o elektromagneter",
            "varunamn": "EKS, Kerpin, WB 800, WICO",
            "capital": 100000,
            "key_personnel": [
                {
                    "name": "Ing Bertil Deijfen",
                    "position": "ordf"
                },
                {
                    "name": "Ake Deijfen",
                    "position": "civiling"
                },
                {
                    "name": "Bernt Eliasson",
                    "position": "ing"
                }
            ],
            "establishment_year": 1966
        },
        "14": {
            "company_name": "Sävsjo Plåtindustri AB",
            "pnr": "576 00",
            "address": "Sävsjö, Smedg",
            "phone_number": "0382-10677",
            "bank_details": {
                "bankgiro": "836-5876",
                "postgiro": "389613-1"
            },
            "activity": "Tillverkar alla slags stålkarmar för lasarettsbyggnader o skolor, stålprofiler för gipsmellanväggar. Försäljning av branddörrar. Utför rostfria arbeten",
            "employees": 10,
            "annual_turnover": 1400000,
            "capital": 15000,
            "key_personnel": {
                "name": "Civiling Ake Stillemark",
                "position": "Verkst dir"
            }
        },
        "15": {
            "company_name": "Sävsjo Plåt & Smide AB",
            "pnr": "576 00",
            "address": "Sävsjö, Industriområdet",
            "phone_number": "0382-102 62, 114 62",
            "bank_details": {
                "bankgiro": "836-5504",
                "postgiro": "348858-2"
            },
            "activity": "Tillverkar fälgar för industri- o jordbruks traktorer m m",
            "employees": 28,
            "annual_turnover": 4000000,
            "capital": 160000,
            "key_personnel": {
                "name": "Karl-Erik Nilsson",
                "position": "Verkst dir"
            },
            "establishment_year": 1957
        }
    }
}