{
    "original": "WEN-PLAST, AB\n\nPnr 271 00\n\nYstad, Herrestadsg 20. Tel\n0411-118 00, 133 15. Bankgiro 873-1770.\nPostgiro 436224-0\nVerksamhet: Serieproduktion av\ndörrar i glasfiberarmerad polyester\ni format enligt SIS standard\nVarunamn: Wen-Plast\nAntal anställda: 30\nÅrsomsättning: 9600 000\nAktiekapital: 90000\nStyrelse: Major J H Zethraeus\n(ordf), dir W B Jonsson, disp Sven\nSwärdh\n\nVeikst dir: Disp Sven Swärdh\nEtableringsår: 1955.\n\nVENTILATOR, INDUSTRI AB\n\nPnr 12630\n\nHägersten, Västbergav 25. Tel\n08-45 28 30. Bankgiro 47-7930.\nPostgiro 53070-9. Tga Ventovent\nVerksamhet: Tillverkar o säljer\nfläktar o ventilationsanläggningar\nAntal anställda: 190\nÅrsomsättning: 23 000 000\nAktiekapital: 1000 000\nVerkst din Civiling Sven\nRomedahl\n\nEtableringsår: 1931\nOmbildat till aktiebolag 1952.\n\nVENTILATORVERKEN, AB\n\nPnr 214 50\n\nMalmö, N Grängesbergsg 15. Tel\n040-867 80. Bankgiro 640-1731.\nPostgiro 38476-8\nVerksamhet: Tillverkar fläktar,\nventilations- o\nmaterialtransport-anläggningar, varmluftsapparater,\nve ntilations materie 1\nAktiekapital: 145 000\nVerkst dir. Sven Nilsson\nEtableringsår: 1918.\n\nKULLSBERGS KALK AB\n\nPnr 795 00\n\nRättvik. Tel 0248-172 00.\nBankgiro 798-0501. Postgiro 11909-9\n\nr ULLS BERGS\n\nR X T T V I K\n\n0248-17200\n\nVerksamhet: Tillverkar bränd kalk\no kalksten för industriändamål\nVarunamn: Kullsbergskalk\nAntal anställda: 50\nÅrsomsättning: 5 000 000\nAktiekapital: 500 000\nStyrelse: Adv Lennart Zedendahl\n(ordf), dir Ragnar Källberg, dir H W\nBergman, insp Torsten Drake,\nbergsing Erik Bergman\nVerkst dir: H W Bergman\nEtableringsår: 1898\nDotterbolag: Trollbo AB, Stora\nSked vi.\n\nKUMLA BYGGVAROR\nO WIRÉN &amp; CO KB\n\nPnr 692 00\n\nKumla, Box 90. V Bang 48. Tel\n019-709 45. Bankgiro 606-0834.\nPostgiro 467548-4\nVerksamhet: Säljer byggmaterial o\nträvaror samt kol. koks o ved.\nHyvleri\n\nAntal anställda: 15\nÅrsomsättning: 4 500 000\nInsatskapital: 110 000\nPlatschef: Disp Ingvar Rickardson\nKamrer: Sven Svärd\nRepresentant: Paul Pettersson\nLagerchef: Karl-Ake Folkesson\nEtableringsår: 1952\nÄgare: AB Interpares, Örebro.\n\nKUMLA FODER- &amp;\nUTSÄDES AB\n\nPnr 692 00\n\nKumla, Box 115. Tel 019-709 00.\nBankgiro 82-0877. Postgiro 20781.\nTga Furage. Telex 73219\nVerksamhet: Handel med\nspannmål, gräsfrö, foder- o gödselmedel\nsamt stråfoder\n\nAvdelningskontor: Fellingsbro,\nÖrebro, öttum\nAntal anställda: 60\nÅrsomsättning: 25 000 000\nAktiekapital: 250000\nVerkst dir: Anders Willerman\nEtableringsår: 1902\nOmbildat till aktiebolag 1919.\n\nKUMLA KARTONG AB\n\nPnr 692 00\n\nKumla, V Drottningg 38. Tel\n019-754 80. Bankgiro 404-8047.\nPostgiro 722892-7\n\nVerksamhet: Förpackningsindustri\nAktiekapital: 75 000\nVerkst dir: Hugo Ringström\nEtableringsår: 1924.\n\nKUMLA MEKANISKA\nVERKSTAD AB\n\nPnr 692 00\n\nKumla, Box 82. Tel 019-754 1 5.\nBankgiro 606-0446. Postgiro\n333807-6\n\nVerksamhet:\nPlåtrundningsmaski-ner\n\nAntal anställda: 50\nÅrsomsättning: 4 500 000\nAktiekapital: 50 000\nVerkst dir: Kjell Eriksson\nEtableringsår: 1946.\n\nCOMBIN-MASKINER\n\nPnr 414 60\n\nGöteborg, Allmänna Vägen 32. Tel\n031-1274 22. Bankgiro 512-7535.\nPostgiro 426148-3\nVerksamhet: Variatorer för\nsteglöst variabel varvtalsreglering\nÄgare o chef: Ing L Skagby\nEtableringsår: 1953.\n\nSAHLIN, BRÖDERNA\n\nPnr 460 60\n\nVargön, Gunnarstorpsv 21. Tel\n0521-204 59. Postgiro 104939-4\nVerksamhet: Tillverkar o säljer\nskärgiljotiner för pappersrullar\nÄgare: Karl Sahlin, Olof Sahlin,\nRolf Sahlin\nEtableringsår: 1955.\n\nCENTRAL-REKLAM, AB\n\nPnr 633 51\n\nEskilstuna, Carlav 78-80. Tel\n016-14 76 00, 14 76 01. Bankgiro\n601-7628. Postgiro 103346-3\nVerksamhet: Reklambyrå.\nFramställer trycksaker o förpackningar,\nplanerar o bygger\nutställningsmontrar, tillverkar inom- o\nutomhus-skyltar\n\nAntal anställda: 9\nÅrsomsättning: 400 000\nAktiekapital: 5 000\nVerkst dir: Gunnar örn\nEtableringsår: 1963.\n\nG SA PRODUKTION\n\nPnr 402 21\n\nGöteborg 5, Skåneg 26. Box 5015.\nTel 031-16 66 25\n\nGSA PRODUKTION\n\nVerksamhet: Utför mekaniska\narbeten, snickerier, montering o\nbokbinderiarbeten. Rehabiliterings- o\nhandikapphjälpmedel,\nhobby-terapimaterial. Båtartiklar\nAntal anställda: 400\nÅrsomsättning: 3 500 000\nChef: Stig östergren\nFörsäljn-chef: Ralf Hultén\nEtableringsår: 1947.\n\nLUNDS GLASMÄSTERI AB\n\nPnr 222 32\n\nLund, Trollebergsv 33. Tel\n046-116963, 12 53 63. Bankgiro\n277-7837. Postgiro 249456-5\nVerksamhet: Glasmästeri. Säljer\ntavlor, speglar, presentartiklar\nAktiekapital: 15 000\nVerkst dir: Disp Edvin Andersson\nEtableringsår: 1945.\n\nLUNDS MEKANISKA\nVERKSTAD, AB\n\nPnr 22104\n\nLund 1, Trollebergsv 14. Box 1117.\nTel 046-124120. Bankgiro\n263-4699. Postgiro 71735-6. Tga\nLundsverkstad\n\nVerksamhet: Tillverkar plåtarbeten,\ntransportanläggningar,\ngjuterima-skiner o gjutskänkar. Metallisering\nAntal anställda: 90\nÅrsomsättning: 3 600 000\nAktiekapital: 1000 000\nVerkst dir: Mauritz Hain\nPlatschef: Ing Olle Larsson\nEtableringsår: 1897.\n\nLUND och VALENTIN\nARKITEKTKONTOR AB\n\nPnr 411 25\n\nGöteborg, Viktoriag 19. Tel 031-\n\n2007 20. Bankgiro 985-7111.\nPost-giro 425460-3\n\nVerksamhet: Arkitektkontor\nAntal anställda: 45\nÅrsomsättning: 3 000 000\nAktiekapital: 20 200\nStyrelse: Ark Rune Lund (ordf),\nfru Inga-Maj Lund, ark Alf\nValentin, fru Marit Valentin\nÄgare o chefer: Ark Rune Lund,\nark Alf Valentin\nEtableringsår: 1952\nOmbildat till aktiebolag 1960.\n\nLUNDHS METALLFABRIK\nAB, AUG\n\nPnr 632 25\n\nEskilstuna, Asg 3. Tel 016-1318 17.\nBankgiro 847-0106. Postgiro\n179841-2\n\nVerksamhet: Tillverkar tryckta\nmetallsaker. Specialitet: kokkärl av\naluminium\nAntal anställda: 8\nÅrsomsättning: 700 000\nAktiekapital: 40 000\nVerkst dir: Stig Johansson\nEtableringsår: 1920\nOmbildat till aktiebolag 1960.\n\nLUND &amp; CO, AB HARALD\n\nPnr 55102\n\nJönköping 1, Barnarpsg 28. Box\n55. Tel 036-114200, 1144 40.\nBankgiro 140-1421. Postgiro\n338855-0\n\nVerksamhet: Pappersgrossist\nAntal anställda: 7\nÅrsomsättning: 2 000 000\nAktiekapital: 25 000\nVerkst dir: Harald Lund\nEtableringsår: 1959.\n\nALRICO, AB\n\nPnr 401 21\n\nGöteborg 1, Mölndalsv 95. Box\n100. Tel 031-165717. Bankgiro\n420004. Postgiro 423328. Tga\nAlrico\n\nVerksamhet: Grossist i leksaker,\nprydnadsporslin (endast japanskt)\no presentartiklar\nAktiekapital: 200 000\nVerkst dir: Bengt Hedlund\nEtableringsår: 1951.\n\nGNOSJOPLAST AB\n\nPnr 33030\n\nGnosjö, Box 105. Spikg 4. Tel\n0370-92100. Bankgiro 813-0379.\nPostgiro 230040-8\nVerksamhet: Formblåsta\nplastflaskor i PVC, Polyeten o Plypropen,\nformblåsta förpackningar för\nindustriändamål samt extrudering o\nbeläggning av rör, tråd, spiraler m m\nAntal anställda: 7\nÅrsomsättning: 800 000\nAktiekapital: 150 000\nFabrikschef: Wells Persson\nEtableringsår: 1967.",
    "structured": {
        "1": {
            "company_name": "WEN-PLAST, AB",
            "pnr": "271 00",
            "address": "Ystad, Herrestadsg 20",
            "phone_number": "0411-118 00, 133 15",
            "bank_details": {
                "bankgiro": "873-1770",
                "postgiro": "436224-0"
            },
            "activity": "Serieproduktion av dörrar i glasfiberarmerad polyester i format enligt SIS standard",
            "employees": 30,
            "annual_turnover": 9600000,
            "capital": 90000,
            "key_personnel": [
                {
                    "name": "Major J H Zethraeus",
                    "position": "ordf"
                },
                {
                    "name": "W B Jonsson",
                    "position": "dir"
                },
                {
                    "name": "Sven Swärdh",
                    "position": "disp"
                },
                {
                    "name": "Sven Swärdh",
                    "position": "veikst dir"
                }
            ],
            "establishment_year": 1955
        },
        "2": {
            "company_name": "VENTILATOR, INDUSTRI AB",
            "pnr": "12630",
            "address": "Hägersten, Västbergav 25",
            "phone_number": "08-45 28 30",
            "bank_details": {
                "bankgiro": "47-7930",
                "postgiro": "53070-9"
            },
            "activity": "Tillverkar o säljer fläktar o ventilationsanläggningar",
            "employees": 190,
            "annual_turnover": 23000000,
            "capital": 1000000,
            "key_personnel": [
                {
                    "name": "Civiling Sven Romedahl",
                    "position": "Tga Ventovent"
                }
            ],
            "establishment_year": 1931
        },
        "3": {
            "company_name": "VENTILATORVERKEN, AB",
            "pnr": "214 50",
            "address": "Malmö, N Grängesbergsg 15",
            "phone_number": "040-867 80",
            "bank_details": {
                "bankgiro": "640-1731",
                "postgiro": "38476-8"
            },
            "activity": "Tillverkar fläktar, ventilations- o materialtransport-anläggningar, varmluftsapparater",
            "capital": 145000,
            "key_personnel": [
                {
                    "name": "Sven Nilsson",
                    "position": "Verkst dir"
                }
            ],
            "establishment_year": 1918
        },
        "4": {
            "company_name": "KULLSBERGS KALK AB",
            "pnr": "795 00",
            "address": "Rättvik",
            "phone_number": "0248-172 00",
            "bank_details": {
                "bankgiro": "798-0501",
                "postgiro": "11909-9"
            },
            "activity": "Tillverkar bränd kalk o kalksten för industriändamål",
            "employees": 50,
            "annual_turnover": 5000000,
            "capital": 500000,
            "key_personnel": [
                {
                    "name": "Adv Lennart Zedendahl",
                    "position": "ordf"
                },
                {
                    "name": "Ragnar Källberg",
                    "position": "dir"
                },
                {
                    "name": "H W Bergman",
                    "position": "dir"
                },
                {
                    "name": "Torsten Drake",
                    "position": "insp"
                },
                {
                    "name": "Erik Bergman",
                    "position": "bergsing"
                },
                {
                    "name": "H W Bergman",
                    "position": "Verkst dir"
                }
            ],
            "establishment_year": 1898
        },
        "5": {
            "company_name": "KUMLA BYGGVAROR O WIRÉN & CO KB",
            "pnr": "692 00",
            "address": "Kumla, Box 90, V Bang 48",
            "phone_number": "019-709 45",
            "bank_details": {
                "bankgiro": "606-0834",
                "postgiro": "467548-4"
            },
            "activity": "Säljer byggmaterial o trävaror samt kol. koks o ved. Hyvleri",
            "employees": 15,
            "annual_turnover": 4500000,
            "capital": 110000,
            "key_personnel": [
                {
                    "name": "Disp Ingvar Rickardson",
                    "position": "Platschef"
                },
                {
                    "name": "Sven Svärd",
                    "position": "Kamrer"
                },
                {
                    "name": "Paul Pettersson",
                    "position": "Representant"
                },
                {
                    "name": "Karl-Ake Folkesson",
                    "position": "Lagerchef"
                }
            ],
            "establishment_year": 1952
        },
        "6": {
            "company_name": "KUMLA FODER- & UTSÄDES AB",
            "pnr": "692 00",
            "address": "Kumla, Box 115",
            "phone_number": "019-709 00",
            "bank_details": {
                "bankgiro": "82-0877",
                "postgiro": "20781"
            },
            "activity": "Handel med spannmål, gräsfrö, foder- o gödselmedel samt stråfoder",
            "employees": 60,
            "annual_turnover": 25000000,
            "capital": 250000,
            "key_personnel": [
                {
                    "name": "Anders Willerman",
                    "position": "Verkst dir"
                }
            ],
            "establishment_year": 1902
        },
        "7": {
            "company_name": "KUMLA KARTONG AB",
            "pnr": "692 00",
            "address": "Kumla, V Drottningg 38",
            "phone_number": "019-754 80",
            "bank_details": {
                "bankgiro": "404-8047",
                "postgiro": "722892-7"
            },
            "activity": "Förpackningsindustri",
            "capital": 75000,
            "key_personnel": [
                {
                    "name": "Hugo Ringström",
                    "position": "Verkst dir"
                }
            ],
            "establishment_year": 1924
        },
        "8": {
            "company_name": "KUMLA MEKANISKA VERKSTAD AB",
            "pnr": "692 00",
            "address": "Kumla, Box 82",
            "phone_number": "019-754 1 5",
            "bank_details": {
                "bankgiro": "606-0446",
                "postgiro": "333807-6"
            },
            "activity": "Plåtrundningsmaskiner",
            "employees": 50,
            "annual_turnover": 4500000,
            "capital": 50000,
            "key_personnel": [
                {
                    "name": "Kjell Eriksson",
                    "position": "Verkst dir"
                }
            ],
            "establishment_year": 1946
        },
        "9": {
            "company_name": "COMBIN-MASKINER",
            "pnr": "414 60",
            "address": "Göteborg, Allmänna Vägen 32",
            "phone_number": "031-1274 22",
            "bank_details": {
                "bankgiro": "512-7535",
                "postgiro": "426148-3"
            },
            "activity": "Variatorer för steglöst variabel varvtalsreglering",
            "key_personnel": [
                {
                    "name": "Ing L Skagby",
                    "position": "Ägare o chef"
                }
            ],
            "establishment_year": 1953
        },
        "10": {
            "company_name": "SAHLIN, BRÖDERNA",
            "pnr": "460 60",
            "address": "Vargön, Gunnarstorpsv 21",
            "phone_number": "0521-204 59",
            "postgiro": "104939-4",
            "activity": "Tillverkar o säljer skärgiljotiner för pappersrullar",
            "key_personnel": [
                {
                    "name": "Karl Sahlin",
                    "position": "Ägare"
                },
                {
                    "name": "Olof Sahlin",
                    "position": "Ägare"
                },
                {
                    "name": "Rolf Sahlin",
                    "position": "Ägare"
                }
            ],
            "establishment_year": 1955
        },
        "11": {
            "company_name": "CENTRAL-REKLAM, AB",
            "pnr": "633 51",
            "address": "Eskilstuna, Carlav 78-80",
            "phone_number": "016-14 76 00, 14 76 01",
            "bank_details": {
                "bankgiro": "601-7628",
                "postgiro": "103346-3"
            },
            "activity": "Reklambyrå. Framställer trycksaker o förpackningar, planerar o bygger utställningsmontrar, tillverkar inom- o utomhusskyltar",
            "employees": 9,
            "annual_turnover": 400000,
            "capital": 5000,
            "key_personnel": [
                {
                    "name": "Gunnar örn",
                    "position": "Verkst dir"
                }
            ],
            "establishment_year": 1963
        },
        "12": {
            "company_name": "G SA PRODUKTION",
            "pnr": "402 21",
            "address": "Göteborg 5, Skåneg 26, Box 5015",
            "phone_number": "031-16 66 25",
            "activity": "Utför mekaniska arbeten, snickerier, montering o bokbinderiarbeten. Rehabiliterings- o handikapphjälpmedel, hobby-terapimaterial. Båtartiklar",
            "employees": 400,
            "annual_turnover": 3500000,
            "key_personnel": [
                {
                    "name": "Stig östergren",
                    "position": "Chef"
                },
                {
                    "name": "Ralf Hultén",
                    "position": "Försäljn-chef"
                }
            ],
            "establishment_year": 1947
        },
        "13": {
            "company_name": "LUNDS GLASMÄSTERI AB",
            "pnr": "222 32",
            "address": "Lund, Trollebergsv 33",
            "phone_number": "046-116963, 12 53 63",
            "bank_details": {
                "bankgiro": "277-7837",
                "postgiro": "249456-5"
            },
            "activity": "Glasmästeri. Säljer tavlor, speglar, presentartiklar",
            "capital": 15000,
            "key_personnel": [
                {
                    "name": "Disp Edvin Andersson",
                    "position": "Verkst dir"
                }
            ],
            "establishment_year": 1945
        },
        "14": {
            "company_name": "LUNDS MEKANISKA VERKSTAD, AB",
            "pnr": "22104",
            "address": "Lund 1, Trollebergsv 14, Box 1117",
            "phone_number": "046-124120",
            "bank_details": {
                "bankgiro": "263-4699",
                "postgiro": "71735-6"
            },
            "activity": "Tillverkar plåtarbeten, transportanläggningar, gjuterimaskiner o gjutskänkar. Metallisering",
            "employees": 90,
            "annual_turnover": 3600000,
            "capital": 1000000,
            "key_personnel": [
                {
                    "name": "Mauritz Hain",
                    "position": "Verkst dir"
                },
                {
                    "name": "Ing Olle Larsson",
                    "position": "Platschef"
                }
            ],
            "establishment_year": 1897
        },
        "15": {
            "company_name": "LUND och VALENTIN ARKITEKTKONTOR AB",
            "pnr": "411 25",
            "address": "Göteborg, Viktoriag 19",
            "phone_number": "031-2007 20",
            "bank_details": {
                "bankgiro": "985-7111",
                "postgiro": "425460-3"
            },
            "activity": "Arkitektkontor",
            "employees": 45,
            "annual_turnover": 3000000,
            "capital": 20200,
            "key_personnel": [
                {
                    "name": "Ark Rune Lund",
                    "position": "ordf"
                },
                {
                    "name": "Inga-Maj Lund",
                    "position": "fru"
                },
                {
                    "name": "Ark Alf Valentin",
                    "position": "ark"
                },
                {
                    "name": "Marit Valentin",
                    "position": "fru"
                }
            ],
            "establishment_year": 1952
        },
        "16": {
            "company_name": "LUNDHS METALLFABRIK AB, AUG",
            "pnr": "632 25",
            "address": "Eskilstuna, Asg 3",
            "phone_number": "016-1318 17",
            "bank_details": {
                "bankgiro": "847-0106",
                "postgiro": "179841-2"
            },
            "activity": "Tillverkar tryckta metallsaker. Specialitet: kokkärl av aluminium",
            "employees": 8,
            "annual_turnover": 700000,
            "capital": 40000,
            "key_personnel": [
                {
                    "name": "Stig Johansson",
                    "position": "Verkst dir"
                }
            ],
            "establishment_year": 1920
        },
        "17": {
            "company_name": "LUND & CO, AB HARALD",
            "pnr": "55102",
            "address": "Jönköping 1, Barnarpsg 28, Box 55",
            "phone_number": "036-114200, 1144 40",
            "bank_details": {
                "bankgiro": "140-1421",
                "postgiro": "338855-0"
            },
            "activity": "Pappersgrossist",
            "employees": 7,
            "annual_turnover": 2000000,
            "capital": 25000,
            "key_personnel": [
                {
                    "name": "Harald Lund",
                    "position": "Verkst dir"
                }
            ],
            "establishment_year": 1959
        },
        "18": {
            "company_name": "ALRICO, AB",
            "pnr": "401 21",
            "address": "Göteborg 1, Mölndalsv 95, Box 100",
            "phone_number": "031-165717",
            "bank_details": {
                "bankgiro": "420004",
                "postgiro": "423328"
            },
            "activity": "Grossist i leksaker, prydnadsporslin (endast japanskt) o presentartiklar",
            "capital": 200000,
            "key_personnel": [
                {
                    "name": "Bengt Hedlund",
                    "position": "Verkst dir"
                }
            ],
            "establishment_year": 1951
        },
        "19": {
            "company_name": "GNOSJOPLAST AB",
            "pnr": "33030",
            "address": "Gnosjö, Box 105, Spikg 4",
            "phone_number": "0370-92100",
            "bank_details": {
                "bankgiro": "813-0379",
                "postgiro": "230040-8"
            },
            "activity": "Formblåsta plastflaskor i PVC, Polyeten o Plypropen, formblåsta förpackningar för industriändamål samt extrudering o beläggning av rör, tråd, spiraler m m",
            "employees": 7,
            "annual_turnover": 800000,
            "capital": 150000,
            "key_personnel": [
                {
                    "name": "Wells Persson",
                    "position": "Fabrikschef"
                }
            ],
            "establishment_year": 1967
        }
    }
}