{
    "original": "OLSSON AB, H L\n\nPnr 232 00\n\nArlöv, Hammarv. Tel 040-43 42 05.\nPostgiro 149588-6\nVerksamhet: Smidesverkstad o\nplåtslageri. Utför även\nstålkonstruktioner o grovplåtsarbeten\nAntal anstäUda: 50\nÅrsomsättning: 5 000 000\nAktiekapital: 50000\nVerkst dir: Torsten Bergström\nV veikst dir: Civiling Arne Hall\nEtableringsår 1945.\n\nOLSSON, HANDELS AB\nHJALMAR\n\nPnr 440 64\n\nBönnäng. Tel 0304-750 02, 75142\nVeiksamhet: Säljer\nbyggnadsmaterial o trävaror\nAntal anstäUda: 20\nAktiekapital: 50 000\nStyrelse: Dir Rolf Hjalmarson,\nSture Hjalmarsson\nVerkst dir: Rolf Hjalmarson\nEtableringsår: 1923\nOmbildat till aktiebolag 1946.\n\nOLSSON SMIDE &amp; GROVPLÅT.\nSLAGERI, AB HOLGER\n\nPnr 72350\n\nVästerås, Barkborreg 2. Tel\n021-180250. Bankgiro 808-9153.\nPostgiro 127245-9\n\nVerksamhet: utför legoarbeten i\nbyggnadssmide,\nbyggnadsplåtslageri; stålkonstruktioner i grov-,\nmedium- o tunnplåt. Balkkonstruktioner.\nKallknäckta, öppna o svetsade\nprofiler samt klippning, bockning\no kapning. Maskinstativ,\nrörledningar o cisterner\nAntal anstäUda: 75\nÅrsomsättning: 5 000 000\nAktiekapital: 100 000\nVerkst dir: Holger Olsson\nEtableringsår: 1956\nOmbildat till aktiebolag 1960.\n\nOHLSSONS BOKTRYCKERI,\nAB HAKAN\n\nPnr 22104\n\nLund 1, Box 1025. Stora\nGråbrö-dersg 17 B. Tel 046-12 4 2 4 0.\nBankgiro 406-5389. Postgiro 10038-8.\nTga Håkanohlsson\nVerksamhet: Moderbolag med\ngemensam förvaltning för AB Håkan\nOhlssons Förlag, Berlingska\nBoktryckeri- &amp; Stilgjuteri AB,\nBerlings Grafiska AB, se dessa bolag\nAktiekapital: 300 000\nVerkst dir: Boktryckare Per-Håkan\nOhlsson\n\nEtableringsår: 1862.\nOmbildat till aktiebolag 1937.\n\nOHLSSONS FORLAG, AB\nHAKAN\n\nPnr 221 04\n\nLund 1, Sankt Anneg 4. Box 1025.\nTel 046-12 42 40. Bankgiro\n660-6081. Postgiro 6928-6. Tga\nHåkanohlsson\n\nVerksamhet: Undervisningsmateriel,\nAV-hjälpmedel, lageditioner o\nannan facklitteratur, blanketter,\nkontorsmateriel\n\nFilialkontor: 113 26 Stockholm,\nVästmannag 78. Tel 08-32 06 03\n\nAntal anställda: 70\nAktiekapital: 10 000\nVerkst dir: Erie Nord\nEtableringsår: 1862.\n\nOLSSONS HANDSKFABRIK, J\n\nPnr 890 32\n\nJärved, Box 280. Tel 0660-40170.\nBankgiro 188-5847. Postgiro\n28882-9\n\nVerksamhet: Tillverkar\narbetshand-skar av läder. Strumpor o vantar av\nylle samt sockor o tofflor av filt\nÄgare o chef: Robert Olsson\nEtableringsår: 1907.\n\nALI-INDUSTRIER, AB\n\nPnr 21611\n\nMalmö, Kalkbrottsg 61. Tel\n040-15 97 57, 15 07 75. Bankgiro\n644-3022. Postgiro 433814-1\nVerksamhet: Tillverkar o säljer\nbabykläder o babyutrustning\nAntal anställda: 25\nÅrsomsättning: 1500000\nAktiekapital: 5 000\nVerkst dir: Lennart Lindgren\nEtableringsår: 1953.\n\nALIN &amp; CO AB, INGENIORS.\nFIRMAN\n\nPnr 100 56\n\nStockholms Frihamn. Tel\n08-62 88 55. Bankgiro 721-3028.\nPostgiro 3462-9. Tga Telfer. Telex\n10156\n\nVerksamhet: Maskiner o utrustning\nför verkstäder, järnbruk o varv\nVarunamn: Dupar\nVerkst dir: Erik Conradson\nEtableringsår: 1948.\n\nEK, BRÖDERNA\n\nPnr 55005\n\nJönköping 5, Box 5030. Lillg 20.\nTel 036-12 63 87, 12 38 71.\nBankgiro 544-9186. Postgiro 346085-4\nVerksamhet: Grosshandelsfirma\ninom värme, sanitet o olja\nChefer: Hans Ek, Lennart Ek\nFtableringsår: 1950.\n\nEK, AB BRÖDERNA\n\nPnr 753 33\n\nUppsala, Svartbäcksg 79. Tel 018-\n\nEK, AUTOMAT AB GUSTAV\n\nPnr 401 22\n\nGöteborg 1, Arkaden. Box 176.\nTel 031-133424. Bankgiro\n51-0240. Postgiro 41144\nVerksamhet: Säljer musik- o\nspelautomater\n\nAktiekapital: 25 000\nVerkst dir: Gustav Ek\nEtableringsår: 1958.\n\nEKS MEKANISKA VERKSTAD\nAB,RAGNAR\n\nPnr 330 21\n\nReftele. Tel 0371-20250.\nBankgiro 142-7327\n\nVerksamhet: Porm- o pressverktyg,\nautomatmaskiner, rostfria\nkabel-klämmor, massartiklar efter prov\neller ritning, formsprutning i plast\nAktiekapital: 45 000\nVerkst dir: Ragnar Ek\nEtableringsår: 1945.\n\nEKA (ESKILSTUNA\nKNIVFABRIKS AB)\n\nPnr 63102\n\nEskilstuna 1, Box 6. Sättarg 4. Tel\n016-13 7 7 20. TgaEkaknivar\nVerksamhet: Knivar,\npresentartiklar (fickknivar)\nVarunamn: EKA-knivar\nAntal anställda: 35\nÅrsomsättning: 2 500 000\nAktiekapital: 300000\nVerkst dir: Torbjörn Evrell\nEtableringsår: 1882\nNuvarande namn 1917.\n\nEKARVERKEN, AB\n\nPnr 22104\n\nLund 1, Box 1077. Falkv 14. Tel\n046-116095, 1180 31. Bankgiro\n660-6495. Postgiro 247989-7. Tga\nEk ar lås\n\nVerksamhet: Tillverkar alla slags\n\nkiosker, cafeterler, kontorsbaracker,\n\nmanskapsbodar\n\nAntal anställda: 40\n\nÅrsomsättning: 3 000 000\n\nAktiekapital: 20 000\n\nVerkst dir: Byggmäst Nils T\n\nAndersson\n\nEtableringsår: 1947.\n\nEKBERGS VERKSTÄDER,\nAB BRUDERNA\n\nPnr 891 03\n\nÖrnsköldsvik 3, Box 203.\nViktoria-esplanaden 10. Tel 0660-107 10.\nBankgiro 18-8482. Postgiro63371-9.\nTelex 6068\n\nVerksamhet: Tillverkar\nbandsuglå-dor, filtsuglådor, urvattnare,\nlutfilter, tryckkärl,\ndestillationsapparater, kylare,\nklorkompresso-rer, klorceller, härdlådor,\nglödg-grytor, deglar, rörmanufaktur o\ntitanarbeten\nAntal anställda: 160\nÅrsomsättning: 23000 000\nVerkst dir: Gunnar Ekberg\nKamrer: S Ostlund\nFörsäljn-chef: L Blomberg\nEtableringsår: 1919.\n\nEKBERGS REVISIONSBYRÅ\nAB, E\n\nPnr 552 40\n\nJönköping, Hoppets torg 5. Tel\n036-114901, 16 2235. Postgiro 342320-9\nVerksamhet: Revisionsbyrå\nAntal anställda: 7\nÅrsomsättning: 450 000\nAktiekapital: 100 000\nÄgare o chef: Evert Ekberg\nEtableringsår: 1940.\n\nOREGRUNDS SÅG &amp; HYVLERI\n\nPnr 740 71\n\nÖregrund, Kärrdal. Box 484 A. Tel\n0173-301 11. Bankgiro 236-6102.\nPostgiro 98837-8\nVerksamhet: Sågverk\nÅrsomsättning: 200 000\nChef: Henry Danielsson\nEtableringsår: 1935.\n\nSTEN &amp; TRÄ, AB\n\nPnr 113 26\n\nStockholm, Frej g 32. Tel\n08-23 4415. Bankgiro 73-4581.\nPost-giro 265231\n\nVerksamhet: Projektering o\nleveranser av monteringsfärdiga hus\nAntal anställda: 17\nÅrsomsättning: 4 500 000\nAktiekapital: 50 000\nVerkst dir: Ing Stig Lambertsson\nEtableringsår: 1948.\n\nALS\n\nALNEFELT &amp; TOLLBOM\nARKITEKTKONTOR AB\n\nPnr 722 15\n\nVästerås, Vasag 24. Tel\n021-110295. Bankgiro 808-6035.\nPostgiro 490838-0\n\nVerksamhet: Arkitektrörelse\nAntal anställda: 10\nÅrsomsättning: 700 000\nAktiekapital: 5 000\nVerkst dir: V Alnefelt\nEtableringsår: 1955.\n\nALNU MEKANISKA\nVERKSTAD, AB\n\nPnr 860 24\n\nAlnö, Smedsgården. Tel 060-560 00.\nBankgiro 180-0630. Postgiro\n336320-7. Tga Alnö\n\nlAMVI\n\n_w_\n\nVerksamhet:\nBeställningstillverkning av bl a stålkonstruktioner,\ncisterner, tryckkärl,\ntransportanordningar, syrafasta arbeten för\ncellulosaindustrin. Utför\nmekaniska bearbetningar av skilda slag\nsamt reparation o service för\nindustrin. Rördragningar för industrin 1\nsvart o syrafast material\nAntal anställda: 100\nÅrsomsättning: 7 000 000\nAktiekapital: 100 000\nÄgare o chefer: Olof Nilsson,\nAnders Erikson\nEtableringsår: 1956\nOmbildat till aktiebolag 1963.\n\nALP AB, MEK VERKSTADEN\n\nPnr 56010\n\nSkillingaryd, Skolg 61. Box 22.\nTel 0370-70198. Bankgiro\n141-3681. Postgiro 144782-0\nVerksamhet: Tillverkar\nmutterbrickor, nitbrickor,\nunderläggsbrickor, galvaniserade skrapgaller,\ngallerduk, lastpallsbeslag o d\nAntal anställda: 15\nAktiekapital: 30 000\nÅrsomsättning: 1200 000\nVerkst dir: Olof Palm\nEtableringsår: 1939\nOmbildat till aktiebolag 1941.\n\nALPHA MOTOR AB, B &amp; W\n\nPnr 41121\n\nGöteborg, Skeppsbron 4. Tel\n031-176295, 176290. Bankgiro\n511-4053. Postgiro 41253-6. Tga Alpha.\nTelex 2274 KILSHIP S\nVerksamhet: Säljer motorer o\nreservdelar till motorer\nAktiekapital: 50 000\nVerkst dir: Lennart Kihlberg\nEtableringsår: 1953.\n\nTUREBODA LIMTRÄ AB\n\nPnr 545 00\n\nTöreboda, Box49. Tel 0506-116 10.\nBankgiro 217-1163. Postgiro\n172400-4. Tga Träkonstruktion\nVerksamhet: Tillverkar\ntakkonstruktioner o standardbyggnader\nför industri, idrott, jordbruk,\nskolor m m\n\nVarunamn: Töreboda\nTräkonstruktioner\n\nAntal anställda: 100\nÅrsomsättning: 14 000 000\nAktiekapital: 580 000\nStyrelse: Försäljn-chef Gunnar\nGustafsson (ordf), dir Bertil\nFim-merstad, verkmäst Axel Andersson,\nciviling Karl-Axel Edgren, dlr Ivan\nEdman, civiling Erik Engström,\nciviling Kurt Tenning\nVerkst dir: Civiling Kurt Tenning\nEtableringsår: 1925.\n\nTOREBODA LIMTRÄ I\nVÄSTERVIK AB\n\nPnr 593 01\n\nVästervik 1, Box 102. Tel\n0490-169 10\n\nVerksamhet: Tillverkar raka\nlim-träbalkar\n\nAntal anställda: 23\nÅrsomsättning: 3 400 000\nAktiekapital: 300000\nVerkst dir Civiling Kurt Tenning\nEtableringsår: 1969.\n\nHAM\n\nAktiekapital: 14 200\nVerkst dir: Folke L Petersson\nEtableringsår: 1937.\n\nHALLSTRÖM &amp; NISSES,\nBYGGNADSAKTIEBOLAGET\n\nPnr 85184\n\nSundsvall, Landsvägsallén 4. Tel\nTel 060-15 58 00. Bankgiro\n180-1331. Postgiro 82009. Tga\nHallström &amp; Nisses\nAvdelningskontor: 114 40\nStockholm, Nybrog 36. Tel 08-63 06 30\n90245Umeå. OKyrkog 16. Tel\n090-1259 00\n\n93100 Skellefteå, Kanalg 71. Tel\n0910-766 70\n\n72213 Västerås,\nDomkyrkoespla-naden 9. Tel 021-12 04 90\n803 55 Giivle, Nyg 11. Tel\n026-18 82 45\n\nAntal anställda: 1500\nÅrsomsättning: 200 000 000\nAktiekapital: 2 000 000\nVerkst dir: Civiling Göran Källqvist\nEtableringsår: 1929\nKoncernföretag: Sundsvalls Värftie\n&amp; Sanitet AB, Elektriska AB Pollux\no Fövaltnings AB Castor,\nsamtliga i Sundsvall, Swiss Thermo AB\nAB i Söderhamn samt\nByggnadsfirman Bäckström &amp; Strömberg KB i\nUmeå.\n\nHALMSTADS CEMENT.\nGJUTERI AB\n\nPnr 302 44\n\nHalmstad, Skyttev 29. Tel\n035-1135 65. Bankgiro 42-3531.\nPostgiro 324745\n\nVerksamhet: Tillverkar gångplattor\ni olika utföranden m m\nAntal anställda: 5\nÅrsomsättning: 300 000\nAktiekapital: 25 100\nVerkst dir: Axel Carlsson\nEtableringsår: 1946.\n\nOLSSON HAB, MARTIN\n\nPnr 100 28\n\nStockholm 49, Igeldammsg 22. Box\n49005. Tel 08-5412 80. Tga\nMartin-olskaffe\n\nVerksamhet: Kafferosteri. Säljer\nkaffe, konserver o delikatesser i\nparti o till storförbrukare\nAvdelningskontor Umeå, Storg 35.\nTel 090-12 10 30, 1210 31\nAntal anställda: 150\nAktiekapital: 240 000\nVerkst dir: Bengt Oldmark\nEtableringsår. 1897.\n\nNILSSON LÄDER &amp; SKODON\nAB, AND\n\nPnr 294 00\n\nSölvesborg. Tel 0456-109 30,\n109 32\n\nVerksamhet: Tillverkar o säljer\nskor, sandaletter o stövlar\nÅrsomsättning: 10000 000\nAktiekapital: 263 400\nVerkst din Folke NUsson\nEtableringsån 1881.",
    "structured": {
        "1": {
            "company_name": "OLSSON AB",
            "activity": "Smidesverkstad o plåtslageri. Utför även stålkonstruktioner o grovplåtsarbeten",
            "establishment_year": 1945,
            "employees": 50,
            "annual_turnover": 5000000,
            "capital": 50000,
            "key_personnel": [
                {
                    "name": "Torsten Bergström",
                    "position": "Verkst dir"
                },
                {
                    "name": "Civiling Arne Hall",
                    "position": "V veikst dir"
                }
            ]
        },
        "2": {
            "company_name": "OLSSON, HANDELS AB HJALMAR",
            "activity": "Säljer byggnadsmaterial o trävaror",
            "establishment_year": 1923,
            "employees": 20,
            "capital": 50000,
            "key_personnel": [
                {
                    "name": "Rolf Hjalmarson",
                    "position": "Styrelse Dir"
                },
                {
                    "name": "Sture Hjalmarsson",
                    "position": ""
                },
                {
                    "name": "Rolf Hjalmarson",
                    "position": "Verkst dir"
                }
            ]
        },
        "3": {
            "company_name": "OLSSON SMIDE & GROVPLÅT. SLAGERI, AB HOLGER",
            "activity": "Utför legoarbeten i byggnadssmide, byggnadsplåtslageri; stålkonstruktioner i grov-, medium- o tunnplåt. Balkkonstruktioner. Kallknäckta, öppna o svetsade profiler samt klippning, bockning o kapning. Maskinstativ, rörledningar o cisterner",
            "establishment_year": 1956,
            "employees": 75,
            "annual_turnover": 5000000,
            "capital": 100000,
            "key_personnel": [
                {
                    "name": "Holger Olsson",
                    "position": "Verkst dir"
                }
            ]
        },
        "4": {
            "company_name": "OHLSSONS BOKTRYCKERI, AB HAKAN",
            "activity": "Moderbolag med gemensam förvaltning för AB Håkan Ohlssons Förlag, Berlingska Boktryckeri- & Stilgjuteri AB, Berlings Grafiska AB, se dessa bolag",
            "establishment_year": 1862,
            "employees": null,
            "capital": 300000,
            "key_personnel": [
                {
                    "name": "Boktryckare Per-Håkan Ohlsson",
                    "position": "Verkst dir"
                }
            ]
        },
        "5": {
            "company_name": "OHLSSONS FORLAG, AB HAKAN",
            "activity": "Undervisningsmateriel, AV-hjälpmedel, lageditioner o annan facklitteratur, blanketter, kontorsmateriel",
            "establishment_year": 1862,
            "employees": 70,
            "capital": 10000,
            "key_personnel": [
                {
                    "name": "Erie Nord",
                    "position": "Verkst dir"
                }
            ]
        },
        "6": {
            "company_name": "OLSSONS HANDSKFABRIK, J",
            "activity": "Tillverkar arbetshandskar av läder. Strumpor o vantar av ylle samt sockor o tofflor av filt",
            "establishment_year": 1907,
            "employees": null,
            "capital": null,
            "key_personnel": [
                {
                    "name": "Robert Olsson",
                    "position": "Ägare o chef"
                }
            ]
        },
        "7": {
            "company_name": "ALI-INDUSTRIER, AB",
            "activity": "Tillverkar o säljer babykläder o babyutrustning",
            "establishment_year": 1953,
            "employees": 25,
            "annual_turnover": 1500000,
            "capital": 5000,
            "key_personnel": [
                {
                    "name": "Lennart Lindgren",
                    "position": "Verkst dir"
                }
            ]
        },
        "8": {
            "company_name": "ALIN & CO AB, INGENIORS. FIRMAN",
            "activity": "Maskiner o utrustning för verkstäder, järnbruk o varv",
            "establishment_year": 1948,
            "employees": null,
            "capital": null,
            "key_personnel": [
                {
                    "name": "Erik Conradson",
                    "position": "Verkst dir"
                }
            ]
        },
        "9": {
            "company_name": "EK, BRÖDERNA",
            "activity": "Grosshandelsfirma inom värme, sanitet o olja",
            "establishment_year": 1950,
            "employees": null,
            "capital": null,
            "key_personnel": [
                {
                    "name": "Hans Ek",
                    "position": "Chefer"
                },
                {
                    "name": "Lennart Ek",
                    "position": "Chefer"
                }
            ]
        },
        "10": {
            "company_name": "EK, AB BRÖDERNA",
            "establishment_year": null
        }
    }
}