{
    "original": "ACCORD RECORDING CO AB\n\nPnr 115 32\n\nStockholm, Erik Dahlbergsg 37.\nTel 08-6251 13, 111206. Postgiro\n456631\n\nVerksamhet: Inspelning av\ngrammofonskivor o därmed jämförbar\nverksamhet\nAktiekapital: 8 000\nVerkst dir: Erik Lundberg\nEtableringsår: 1951.\n\nLINDEBERG AB, VICTOR\n\nPnr 781 00\n\nBorlänge, Målarg 16. Tel\n0243-103 08. Bankgiro 794-5926.\nPostgiro 9974-7. Tga Libo\nVerksamhet: Manufaktur o\nkortvaror i parti\nAktiekapital: 150000\nVerkst dir: Erik Lindeberg\nEtableringsår: 1916.\n\nKÄCE AB\n\nPnr 640 32\n\nMalmköping, Landsvägsg 1. Tel\n0157-205 50, 204 54. Bankgiro\n61-8327. Postgiro 9606. Tga Elheat\nVerksamhet: Tillverkar\nvärmeapparater samt elektrisk utrustning\nAktiekapital: 100 000\nPlatschef: Disp Sven Stockengren\nEtableringsår: 1950.\n\nWIRÉNS GJUTERI. AB\n\nPnr 433 02\n\nPartille 2. Box 2034. Göteborgsv\n44. Tel 031-26 20 90. Bankgiro\n446-1315. Postgiro 46330-7\nVerksamhet: Tillverkar tung- o\nlättmetallsgjutgods o\nmaskinbearbetning\n\nAntal anställda: 39\nÅrsomsättning: 3 500 000\nAktiekapital: 40 000\nVerkst dir. Gjuterichef Stig\nAndersson\n\nKamrer: Frk Birgit Andersson\nEtableringsår: 1919.\n\nJIR\n\nStålinredningar, Combitainers,\nLastpallar, Klädskåp,\nLastbryggor, Gaffeltruckar,\nButiksinredningar\n\nAntal anställda: 6\nÅrsomsättning: 8 000 000\nAktiekapital: 10 000\nVerkst dir: Helmer Jinvall\nEtableringsàr: 1948.\n\nJIRVING, AB GUNNAR\n\nPnr 14105\n\nHuddinge 5, Box 5005. Gamla\nSödertäljev 125. Tel 08-46 25 00.\nBankgiro 574-7290. Postgiro\n354841-9. Tga Industrij irving.\nTelex 17919 JIRVING S\nVerksamhet: Säljer verktyg,\nmaskiner o montageanordningar för\nVVS-El- o byggnadsbranschen,\nperforerad plåt, profiler o bultartiklar\nVarunamn: Jirva, Unistrut\nAntal anställda: 45\nÅrsomsättning: 11000 000\nAktiekapital: 500 000\nVerkst dir: Gunnar Jirving\nEtableringsàr: 1948\nOmbildat till aktiebolag 1958.\n\nJI-TE AB\n\nPnr 265 01\n\nAstoip 1, Box 93. Tel 042-509 50.\nBankgiro 671-3507. Postgiro\n9333-6. Tga Jitebolaget.\nTelex 72348\n\nVerksamhet: Tillverkar o säljer\ninner- o ytterdörrar\nAntal anstäUda: 600\nÅrsomsättning: 80 000 000\nAktiekapital: 600 000\nVerkst dir: Sverker Ovesson\nEtableringsàr: 1902.\n\nJOBELIUS, PLATTSÄTTNINGS\nAB KNUT\n\nPnr 163 57\n\nSpånga, Winquists v 10-12. Tel\n08-36 27 50. Bankgiro 743-5654. Post&gt;\ngiro 339771-8\n\nVerksamhet: Utför kakel- o\nplattbeläggningar av alla slag\nAntal anställda: 55\nÅrsomsättning: 5 000000\nAktiekapital: 150 000\nVerkst din Knut Jobelius\nEtableringsàr 1957.\n\nTEMETO FÖRSÄLJNINGS AB\n\nPnr 642 00\n\nFlen, Aseg 3. Box 117. Tel\n0157-12410. Telex 64100. Tga Temeto\nVerksamhet: Försäljningsbolag för\nERMETO Original rörkopplingar,\nprecisionsstålrör, ventiler, slangar\nmm. Tecalsan nylonrör o slangar.\nStauff rörklammer.\nSmörjutrustningar för bilverkstäder o industrier.\nCentralsmörj anläggningar:\nExacto-lub med olja. Biflux med fett o\nolja\n\nVarunamn: EO. Ermeto, Stauff,\n\nTecalsan, Temeto\n\nAntal anställda: 20\n\nAktiekapital: 300 000\n\nStyrelse: Adv Per Håkan Osvald\n\n(ordf), dir Pierre Dufour, dir Assar\n\nHellmér\n\nVerkst dir: Assar Hellmér\nEtableringsår: 1966.\n\nTEMPELAAR KONSULTBYRÅ\nAB\n\nPnr 203 13\n\nMalmö 4, Box 4204. Baltzarsg 25.\nTel 040-737 35. Bankgiro 16-4762.\nPostgiro 6339 77\n\nVerksamhet: Konsulterande i\ndatabehandling sfrågor\nAvdelningskontor: 251 03\nHälsingborg 1, Box 213. Tel 042-1805 46\nAntal anställda: 20\nAktiekapital: 10 000\nVerkst dir: Maiinus Tempelaar\nEtableringsår: 1966.\n\nTEMPELMAN, GEORG\n\nPnr 11130\n\nStockholm, Skeppsbron 44. Tel\n08-24 23 55. Postgiro 52741. Telex\n10108. Tga Tempelmans\nVerksamhet: Generalagent för\nLip-ton Ltd, Slazengers Ltd, Lines\nBros Ltd m fi\nVarunamn: Lipton\nAntal anställda: 25\nÅrsomsättning: 15 000 000\nAktiekapital: 1000 000\nÄgare o chef: Gillis Tempelman\nEtableringsår: 1885.\n\nI-SKYLT AB\n\nPnr 150 30\n\nMariefred, Box 28. Tel 0159-101 52,\n105 53. Bankgiro 61-8747. Postgiro\n273123-0\n\nVerksamhet: Eloxering, etsning,\noffsettryck o screentryck. Speciar\nlitet: maskin o reklamskyltar\nAntal anställda: 15\nÅrsomsättning: 860000\nAktiekapital: 30000\nVerkst dir: Tage Lindström\nFörsäljning: Lars Lindström\nEtableringsår 1954.\n\nISOLATOR,\nHANDELSBOLAGET\n\nPnr 701 04\n\nÖrebro 1, Karlslundsg 25-29. Box\n306. Tel 019-12 46 00. Bankgiro\n614-5429. Postgiro 141860-7\nVerksamhet: Grossiströrelse för\nisoleringsmaterial\nÅrsomsättning: 3 000 000\nChef: Dir Gustaf Rosén\nEtableringsår 1939.\n\nTAPETLAGRET AB\n\nPnr 80104\n\nGävle 1, Box 277. N Skepparg\n11-13. Tel 026-1802 70. Bankgiro\n603-5869. Postgiro 264166-0\nVerksamhet: Säljer färger o\nvägg-beklädnadsmaterial i parti o minut\nFilialer: Falun, Sundsvall,\nUppsala, Örnsköldsvik, Östersund\nAntal anställda: 40\nÅrsomsättning: 10000 000\nAktiekapital: 600 000\nStyrelse: Dir Gunnar Lundh (ordf),\nfru Anna Lundh, disp Lennart\nHanstorp\n\nVerkst dir. Gunnar Lundh\nEtableringsàr 1943.\n\nBERKEL AB\n\nPnr 12108\n\nJohanneshov 8, Svärdlångsv 32.\nBox 829. Tel 08-45 28 70. Tga\nLekreb. Telex 17764\nVerksamhet: Butiks- o\nindustrivågar, charkuteri-, bageri-,\nstor-köks- o restaurangmaskiner,\ndiskmaskiner\n\nAvdelningskontor: 417 05 Göteborg,\nGamla Tuvev 23. Tel 031-5168 50,\n5155 20. Verkmäst: R Tellin\n214 42 Malmö, Vitmölleg 5. Tel\n040-11 29 67, 12 55 51. Verkmäst: J\nFlodin\n\nVarunamn: Berkel, Hobart\nAktiekapital: 250 000\nVerkst dir: Bo Wallstedt\nEtableringsår: 1909.\n\nJUNGER &amp; JUNGER, AB\n\nPnr 400 20\n\nGöteborg 14, Mölndals v 91. Box\n14026. Tel 031-20 0645. Bankgiro\n420-0994. Postgiro 12347. Tga\nJungers. Telex 20663 JUNGERS S\nVerksamhet: Utrustning för grafisk\nindustri o\nförpackningsframställning\n\nAvdelningskontor: 113 51 Stockholm,\nLuntmakareg 85. Tel 08-30 44 03\nAntal anställda: 25\nVerkst dir: Bengt Hedman\nEtableringsår 1917.",
    "structured": {
        "SwedishFirms": [
            {
                "company_name": "ACCORD RECORDING CO AB",
                "pnr": "115 32",
                "address": "Stockholm, Erik Dahlbergsg 37",
                "phone_number": "08-6251 13",
                "bank_details": {
                    "postgiro": "456631"
                },
                "activity": "Inspelning av grammofonskivor o därmed jämförbar verksamhet",
                "capital": 8000,
                "key_personnel": [
                    {
                        "name": "Erik Lundberg",
                        "position": "Verkst dir"
                    }
                ],
                "establishment_year": 1951
            },
            {
                "company_name": "LINDEBERG AB, VICTOR",
                "pnr": "781 00",
                "address": "Borlänge, Målarg 16",
                "phone_number": "0243-103 08",
                "bank_details": {
                    "bankgiro": "794-5926",
                    "postgiro": "9974-7"
                },
                "activity": "Manufaktur o kortvaror i parti",
                "capital": 150000,
                "key_personnel": [
                    {
                        "name": "Erik Lindeberg",
                        "position": "Verkst dir"
                    }
                ],
                "establishment_year": 1916
            },
            {
                "company_name": "KÄCE AB",
                "pnr": "640 32",
                "address": "Malmköping, Landsvägsg 1",
                "phone_number": "0157-205 50, 204 54",
                "bank_details": {
                    "bankgiro": "61-8327",
                    "postgiro": "9606"
                },
                "activity": "Tillverkar värmeapparater samt elektrisk utrustning",
                "capital": 100000,
                "key_personnel": [
                    {
                        "name": "Disp Sven Stockengren",
                        "position": "Platschef"
                    }
                ],
                "establishment_year": 1950
            },
            {
                "company_name": "WIRÉNS GJUTERI. AB",
                "pnr": "433 02",
                "address": "Partille 2, Box 2034, Göteborgsv 44",
                "phone_number": "031-26 20 90",
                "bank_details": {
                    "bankgiro": "446-1315",
                    "postgiro": "46330-7"
                },
                "activity": "Tillverkar tung- o lättmetallsgjutgods o maskinbearbetning",
                "employees": 39,
                "annual_turnover": 3500000,
                "capital": 40000,
                "key_personnel": [
                    {
                        "name": "Gjuterichef Stig Andersson",
                        "position": "Verkst dir"
                    },
                    {
                        "name": "Frk Birgit Andersson",
                        "position": "Kamrer"
                    }
                ],
                "establishment_year": 1919
            },
            {
                "company_name": "JIR",
                "activity": "Stålinredningar, Combitainers, Lastpallar, Klädskåp, Lastbryggor, Gaffeltruckar, Butiksinredningar",
                "employees": 6,
                "annual_turnover": 8000000,
                "capital": 10000,
                "key_personnel": [
                    {
                        "name": "Helmer Jinvall",
                        "position": "Verkst dir"
                    }
                ],
                "establishment_year": 1948
            },
            {
                "company_name": "JIRVING, AB GUNNAR",
                "pnr": "14105",
                "address": "Huddinge 5, Box 5005, Gamla Södertäljev 125",
                "phone_number": "08-46 25 00",
                "bank_details": {
                    "bankgiro": "574-7290",
                    "postgiro": "354841-9"
                },
                "activity": "Säljer verktyg, maskiner o montageanordningar för VVS-El- o byggnadsbranschen, perforerad plåt, profiler o bultartiklar",
                "employees": 45,
                "annual_turnover": 11000000,
                "capital": 500000,
                "key_personnel": [
                    {
                        "name": "Gunnar Jirving",
                        "position": "Verkst dir"
                    }
                ],
                "establishment_year": 1948
            },
            {
                "company_name": "JI-TE AB",
                "pnr": "265 01",
                "address": "Astoip 1, Box 93",
                "phone_number": "042-509 50",
                "bank_details": {
                    "bankgiro": "671-3507",
                    "postgiro": "9333-6"
                },
                "activity": "Tillverkar o säljer inner- o ytterdörrar",
                "employees": 600,
                "annual_turnover": 80000000,
                "capital": 600000,
                "key_personnel": [
                    {
                        "name": "Sverker Ovesson",
                        "position": "Verkst dir"
                    }
                ],
                "establishment_year": 1902
            },
            {
                "company_name": "JOBELIUS, PLATTSÄTTNINGS AB KNUT",
                "pnr": "163 57",
                "address": "Spånga, Winquists v 10-12",
                "phone_number": "08-36 27 50",
                "bank_details": {
                    "bankgiro": "743-5654",
                    "postgiro": "339771-8"
                },
                "activity": "Utför kakel- o plattbeläggningar av alla slag",
                "employees": 55,
                "annual_turnover": 5000000,
                "capital": 150000,
                "key_personnel": [
                    {
                        "name": "Knut Jobelius",
                        "position": "Verkst dir"
                    }
                ],
                "establishment_year": 1957
            },
            {
                "company_name": "TEMETO FÖRSÄLJNINGS AB",
                "pnr": "642 00",
                "address": "Flen, Aseg 3, Box 117",
                "phone_number": "0157-12410",
                "telex": "64100",
                "activity": "Försäljningsbolag för ERMETO Original rörkopplingar, precisionsstålrör, ventiler, slangar mm. Tecalsan nylonrör o slangar. Stauff rörklammer. Smörjutrustningar för bilverkstäder o industrier. Centralsmörjanläggningar: Exacto-lub med olja. Biflux med fett o olja",
                "employees": 20,
                "capital": 300000,
                "key_personnel": [
                    {
                        "name": "Assar Hellmér",
                        "position": "Verkst dir"
                    }
                ],
                "establishment_year": 1966
            },
            {
                "company_name": "TEMPELAAR KONSULTBYRÅ AB",
                "pnr": "203 13",
                "address": "Malmö 4, Box 4204, Baltzarsg 25",
                "phone_number": "040-737 35",
                "bankgiro": "16-4762",
                "postgiro": "6339 77",
                "activity": "Konsulterande i databehandling sfrågor",
                "branch_office": "251 03 Hälsingborg 1, Box 213, Tel 042-1805 46",
                "employees": 20,
                "capital": 10000,
                "key_personnel": [
                    {
                        "name": "Maiinus Tempelaar",
                        "position": "Verkst dir"
                    }
                ],
                "establishment_year": 1966
            },
            {
                "company_name": "TEMPELMAN, GEORG",
                "pnr": "11130",
                "address": "Stockholm, Skeppsbron 44",
                "phone_number": "08-24 23 55",
                "postgiro": "52741",
                "telex": "10108",
                "activity": "Generalagent för Lip-ton Ltd, Slazengers Ltd, Lines Bros Ltd m fi",
                "employees": 25,
                "annual_turnover": 15000000,
                "capital": 1000000,
                "owners": "Gillis Tempelman",
                "establishment_year": 1885
            },
            {
                "company_name": "I-SKYLT AB",
                "pnr": "150 30",
                "address": "Mariefred, Box 28",
                "phone_number": "0159-101 52, 105 53",
                "bankgiro": "61-8747",
                "postgiro": "273123-0",
                "activity": "Eloxering, etsning, offsettryck o screentryck. Speciar litet: maskin o reklamskyltar",
                "employees": 15,
                "annual_turnover": 860000,
                "capital": 30000,
                "key_personnel": [
                    {
                        "name": "Tage Lindström",
                        "position": "Verkst dir"
                    },
                    {
                        "name": "Lars Lindström",
                        "position": "Försäljning"
                    }
                ],
                "establishment_year": 1954
            },
            {
                "company_name": "ISOLATOR, HANDELSBOLAGET",
                "pnr": "701 04",
                "address": "Örebro 1, Karlslundsg 25-29, Box 306",
                "phone_number": "019-12 46 00",
                "bankgiro": "614-5429",
                "postgiro": "141860-7",
                "activity": "Grossiströrelse för isoleringsmaterial",
                "annual_turnover": 3000000,
                "key_personnel": [
                    {
                        "name": "Dir Gustaf Rosén",
                        "position": "Chef"
                    }
                ],
                "establishment_year": 1939
            },
            {
                "company_name": "TAPETLAGRET AB",
                "pnr": "80104",
                "address": "Gävle 1, Box 277, N Skepparg 11-13",
                "phone_number": "026-1802 70",
                "bankgiro": "603-5869",
                "postgiro": "264166-0",
                "activity": "Säljer färger o vägg-beklädnadsmaterial i parti o minut",
                "branch_offices": "Falun, Sundsvall, Uppsala, Örnsköldsvik, Östersund",
                "employees": 40,
                "annual_turnover": 10000000,
                "capital": 600000,
                "key_personnel": [
                    {
                        "name": "Gunnar Lundh",
                        "position": "Styrelse (ordf)"
                    },
                    {
                        "name": "Anna Lundh",
                        "position": "Fru"
                    },
                    {
                        "name": "Lennart Hanstorp",
                        "position": "Disp"
                    },
                    {
                        "name": "Gunnar Lundh",
                        "position": "Verkst dir"
                    }
                ],
                "establishment_year": 1943
            },
            {
                "company_name": "BERKEL AB",
                "pnr": "12108",
                "address": "Johanneshov 8, Svärdlångsv 32, Box 829",
                "phone_number": "08-45 28 70",
                "telex": "17764",
                "activity": [
                    "Butiks- o industrivågar",
                    "charkuteri-, bageri-",
                    "stor-köks- o restaurangmaskiner",
                    "diskmaskiner"
                ],
                "branch_offices": [
                    {
                        "location": "417 05 Göteborg",
                        "address": "Gamla Tuvev 23",
                        "phone_number": "031-5168 50, 5155 20",
                        "verkmäst": "R Tellin"
                    },
                    {
                        "location": "214 42 Malmö",
                        "address": "Vitmölleg 5",
                        "phone_number": "040-11 29 67, 12 55 51",
                        "verkmäst": "J Flodin"
                    }
                ],
                "capital": 250000,
                "key_personnel": [
                    {
                        "name": "Bo Wallstedt",
                        "position": "Verkst dir"
                    }
                ],
                "establishment_year": 1909
            },
            {
                "company_name": "JUNGER & JUNGER, AB",
                "pnr": "400 20",
                "address": "Göteborg 14, Mölndals v 91, Box 14026",
                "phone_number": "031-20 0645",
                "bankgiro": "420-0994",
                "postgiro": "12347",
                "telex": "20663 JUNGERS S",
                "activity": "Utrustning för grafisk industri o förpackningsframställning",
                "branch_offices": "113 51 Stockholm, Luntmakareg 85",
                "employees": 25,
                "key_personnel": [
                    {
                        "name": "Bengt Hedman",
                        "position": "Verkst dir"
                    }
                ],
                "establishment_year": 1917
            }
        ]
    }
}