{
    "original": "ELEKTROSTIL, AB\n\nPnr 383 00\n\nMönsterås, Pionjärg 10. Tel\n0499-11500, 11501\n\nVerksamhet: Säljer elektr armatur\nen gros. Tillverkar lampskärmar\nFirmatecknare: Fabr G Söderström\nEtableringsår: 1942.\n\nELEKTROTEKNISKA\nKONTROLLBYRÄN\n\nPnr 600 05\n\nNorrköping 5, Box 5042. Lindg 12.\nTel 011-12 87 60. Bankgiro 28-4119.\nPostgiro 125459-8\nVerksamhet: Besiktning av\nbyggnadshissar. byggnadskranar mm\nAntal anställda: 3\nÅrsomsättning: 275 000\nChef: Ing Gunnar Nerdal\nEtableringsår: 1957.\n\nfalke, ab ernst\n\nPnr 252 55\n\nHelsingborg, Väpnareg 8. Tel\n042-1133 27, 1133 48. Bankgiro\n269-0329. Postgiro 324 785-5\nVerksamhet: Skogrossist\nAktiekapital: 25 000\nVerkst dir: Boris Bengtsson\nEtableringsår: 1947.\n\nNILSSONS TRYCKERI AB\n\nPnr 280 20\n\nBjärnum, Nyg. Box 70. Tel\n0451-206 10. Bankgiro 265-3764.\nPostgiro 287607-6\n\nVerksamhet: Blankettryckeri,\nspeci-alité: större upplagor\nAntal anstäUda: 21\nÅrsomsättning: 2 000 000\nAktiekapital: 25 000\nÄgare o chefer: Boktr Assar\nNilsson, Töre Jacobsson\nEtableringsår: 1944.\n\nHEDMANS REVISIONSBYRÅ AB\n\nPnr 81101\n\nSandviken 1, Box 30. Hyttg 16 B.\nTel 026-25 99 50. Bankgiro\n679-6700. Postgiro 8587-8\nVerksamhet: Utför revisioner,\nekonomiska utredningar, bokslut,\ndeklarationer, skatteutredningar o\nbesvär\n\nAntal anställda: 9\nÅrsomsättning: 300 000\nAktiekapital: 5 000\nStyrelse: Adv Ake Gernandt (ordf),\nrevisor SRS Per Erik Pousette\nVerkst dir: Revisor SRS Bertil\nHedman\n\nEtableringsår: 1949\nOmbildat till aktiebolag 1958.\n\nHEEDMANS SNICKERI.\nVERKSTAD, AB JOHN\n\nPnr 95100\n\nLuleå, Yrkesg 11. Tel 0920-117 9 2.\nPostgiro 60723-4\n\nVerksamhet: Tillverkar köks- o\nbutiksinredningar, byggnadssnickerier av alla slag\nÅrsomsättning: 300 000\nAktiekapital: 5 000\nVerkst dir: John Heedman\nEtableringsår 1947\nOmbildat till aktiebolag 1960.\n\nHEDRICO AB\n\nPnr 650 02\n\nKa listad 2, Box 2007. Tel\n054-18 04 70. Bankgiro 43-8859.\nPostgiro 133950\n\nVerksamhet: Grossistförsäljning\nav papper, leksaker, kortvaror, jul-,\npåsk- o presentartiklar\nAntal anställda: 35\nVeikst dir: Gustaf Qvisth\nEtableringsår: 1937.\n\nHEDSTRÖM &amp; ALMQVIST\nTRÄVARU AB\n\nPnr 11135\n\nStockholm, Kungsg 18. Tel\n08-20 56 84, 20 16 84. Bankgiro72-7099.\nPostgiro 59212-1. Tga Träbolaget\nVerksamhet: Trävaror en gros\nÅrsomsättning: 1200 000\nAktiekapital: 50 000\nVerkst dir: Erik Almqvist\nEtableringsår: 1913.\n\nVVS-UTRUSTNING AB\n\nPnr 41317\n\nGöteborg, Hjorthagsg 10 D. Tel\n031-4217 11. Bankgiro 358-5106.\nPostgiro 420313-9\nVerksamhet: Tillverkning o\nförsäljning av vätskeavskiljare\navsedd i första hand som\navlopps-vattenrenare samt golvbrunnar,\nbetäckningar m m\nAntal anställda: 3\nÅrsomsättning: 300 000\nAktiekapital: 5 000\nStyrelse: Ing Ingemar Larsson\n(ordf), ing Ingvar Johansson, fru\nElly Wassberg\n\nVerkst dir: Fru Elly Wassberg\nEtableringsår: 1965.\n\nVALBACKENS TEGELBRUKS\nAB\n\nPnr 831 00\n\nÖstersund, Prästg 24. Ttel\n063-11385, 196 65. Bankgiro 77-7847.\nPostgiro 30737\n\nVerksamhet: Tillverkar fasad- o\nmurtegel, järnhandel\nAntal anställda: 37\nÅrsomsättning: 4 500 000\nAktiekapital: 300 000\nVerkst dir: Kjell Staverfelt\nEtableringsår 1899.\n\nESSPEGOLV AB\n\nPnr 411 37\n\nGöteborg, Vasag 45 B. Tel\n031-1671 66, 20 56 80. Bankgiro\n36-4820. Postgiro 527848-6\nVerksamhet: Säljer o lägger\ngolvbeläggningsmaterial\nAntal anställda: 7\nAktiekapital: 25000\nVerkst dir: Stellan Peterson, Göran\nWennergren\nEtableringsår: 1959.\n\nAUTOINDUSTRI, AB\n\nPnr 300 04\n\nHalmstad 4, Knäredsg. Box 4007.\nTel 035-1188 55. Bankgiro\n109-9654. Postgiro 119572-6.\nTelex 3534\n\nVerksamhet: Försäljer\nsäkerhetsbälten SAFE konventionella o\nrull-bälten samt sjukvårdsbälten\nAntal anställda: 4\nÅrsomsättning: 4500 000\nAktiekapital: 5 000\nVerkst dir: Ulf Rex\nEtableringsår 1966.\n\nTELEVISIONS, o SMALFILM\n\nPnr 11145\n\nStockholm, Birger Jarlsg 31. Tel\n08-10 10 41. Bankgiro 16-0930.\nPostgiro 495200. Tga Telefilmcomp\nVerksamhet: Bedriver import o\nexport av film till\ntelevisionsstationer, speciellt i Sverige o\nSkandinavien, men också i övriga världen.\nImport o export av biograffilmer.\nOrganisation av internationella\nfilmproduktioner. Distribuerar 16\nmm film i Sverige till skolor o\norganisationer\n\nDistributionsavdelning för 16 mm\nfilmuthyrning: Stockholm VA,\nDö-belnsgl2. Tel 08-34 6051,346052\nAntal anställda: 7\nVerkst dir Ove Wallius\nEtableringsår: 1956\nDotterbolag: Film AB TVS, Investr\nment AB STRIX samt Swedish\nFilmproduction Investment AB.\n\nTELFA, AB\n\nPnr 400 20 Gbg 14\nMölndal, Flöjelbergsg 8 A. Box\n14041, Gbg 14. Tel 031-87 02 80.\nBankgiro 49-1221. Postgiro 520233.\nTga Telfacorp\n\nVerksamhet: Säljer\npersiennmaterial, båtar o båttillbehör\nAntal anställda: 14\nAktiekapital: 250 000\nVerkst dir Gunnar Anderson\nEtableringsår 1952.\n\nNILSONS GUMMI AB, ERNST\n\nPnr 172 21\n\nSundbyberg 1, Box 14. Järnvägsg\n68. Tel 08-28 29 20. Bankgiro\n160-6581. Postgiro 8758-5. Tga\nErnst-ni lg ummi\n\nVerksamhet: Säljer gummiringar o\nutför ringreparationer\nAntal anstäUda: 17\nÅrsomsättning: 1800 000\nAktiekapital: 100 000\nVerkst din Holger Lundestam\nEtableringsår: 1957.\n\nSGS-SEMICONDUCTOR AB\n\nPnr 19501\n\nMärsta 1, Industrig 2. Fack. Tel\n0760-401 20. Bankgiro 70-0636.\nPostgiro 709760.\nTelex 10932 SGS S\nVerksamhet Tillverkar o säljer\nkisel Planar dioder, transistorer o\nintegrerade kretsar\nAntal anstäUda: 150\nAktiekapital: 6 0 00 000\nVerkst dir. Glenn Marshall\nEtableringsår 1965.",
    "structured": {
        "1": {
            "company_name": "ELEKTROSTIL, AB",
            "activity": "Säljer elektr armatur en gros. Tillverkar lampskärmar",
            "establishment_year": 1942
        },
        "2": {
            "company_name": "ELEKTROTEKNISKA KONTROLLBYRÄN",
            "activity": "Besiktning av byggnadshissar. byggnadskranar mm",
            "employees": 3,
            "annual_turnover": 275000,
            "capital": 5000,
            "key_personnel": [
                {
                    "name": "Ing Gunnar Nerdal",
                    "position": "Chef"
                }
            ],
            "establishment_year": 1957
        },
        "3": {
            "company_name": "falke, ab ernst",
            "activity": "Skogrossist",
            "capital": 25000,
            "key_personnel": [
                {
                    "name": "Boris Bengtsson",
                    "position": "Verkst dir"
                }
            ],
            "establishment_year": 1947
        },
        "4": {
            "company_name": "NILSSONS TRYCKERI AB",
            "activity": "Blankettryckeri, speci-alité: större upplagor",
            "employees": 21,
            "annual_turnover": 2000000,
            "capital": 25000,
            "key_personnel": [
                {
                    "name": "Boktr Assar Nilsson",
                    "position": "Ägare o chefer"
                },
                {
                    "name": "Töre Jacobsson",
                    "position": "Ägare o chefer"
                }
            ],
            "establishment_year": 1944
        },
        "5": {
            "company_name": "HEDMANS REVISIONSBYRÅ AB",
            "activity": "Utför revisioner, ekonomiska utredningar, bokslut, deklarationer, skatteutredningar o besvär",
            "employees": 9,
            "annual_turnover": 300000,
            "capital": 5000,
            "key_personnel": [
                {
                    "name": "Adv Ake Gernandt",
                    "position": "Styrelse (ordf)"
                },
                {
                    "name": "Per Erik Pousette",
                    "position": "Revisor SRS"
                },
                {
                    "name": "Bertil Hedman",
                    "position": "Verkst dir"
                }
            ],
            "establishment_year": 1949
        },
        "6": {
            "company_name": "HEEDMANS SNICKERI. VERKSTAD, AB JOHN",
            "activity": "Tillverkar köks- o butiksinredningar, byggnadssnickerier av alla slag",
            "annual_turnover": 300000,
            "capital": 5000,
            "key_personnel": [
                {
                    "name": "John Heedman",
                    "position": "Verkst dir"
                }
            ],
            "establishment_year": 1947
        },
        "7": {
            "company_name": "HEDRICO AB",
            "activity": "Grossistförsäljning av papper, leksaker, kortvaror, jul-, påsk- o presentartiklar",
            "employees": 35,
            "key_personnel": [
                {
                    "name": "Gustaf Qvisth",
                    "position": "Verkst dir"
                }
            ],
            "establishment_year": 1937
        },
        "8": {
            "company_name": "HEDSTRÖM & ALMQVIST TRÄVARU AB",
            "activity": "Trävaror en gros",
            "annual_turnover": 1200000,
            "capital": 50000,
            "key_personnel": [
                {
                    "name": "Erik Almqvist",
                    "position": "Verkst dir"
                }
            ],
            "establishment_year": 1913
        },
        "9": {
            "company_name": "VVS-UTRUSTNING AB",
            "activity": "Tillverkning o försäljning av vätskeavskiljare avsedd i första hand som avlopps-vattenrenare samt golvbrunnar, betäckningar m m",
            "employees": 3,
            "annual_turnover": 300000,
            "capital": 5000,
            "key_personnel": [
                {
                    "name": "Ingemar Larsson",
                    "position": "Styrelse (ordf)"
                },
                {
                    "name": "Ingvar Johansson",
                    "position": "Styrelse"
                },
                {
                    "name": "Elly Wassberg",
                    "position": "Styrelse"
                },
                {
                    "name": "Elly Wassberg",
                    "position": "Verkst dir"
                }
            ],
            "establishment_year": 1965
        },
        "10": {
            "company_name": "VALBACKENS TEGELBRUKS AB",
            "activity": "Tillverkar fasad- o murtegel, järnhandel",
            "employees": 37,
            "annual_turnover": 4500000,
            "capital": 300000,
            "key_personnel": [
                {
                    "name": "Kjell Staverfelt",
                    "position": "Verkst dir"
                }
            ],
            "establishment_year": 1899
        },
        "11": {
            "company_name": "ESSPEGOLV AB",
            "activity": "Säljer o lägger golvbeläggningsmaterial",
            "employees": 7,
            "capital": 25000,
            "key_personnel": [
                {
                    "name": "Stellan Peterson",
                    "position": "Verkst dir"
                },
                {
                    "name": "Göran Wennergren",
                    "position": "Verkst dir"
                }
            ],
            "establishment_year": 1959
        },
        "12": {
            "company_name": "AUTOINDUSTRI, AB",
            "activity": "Försäljer säkerhetsbälten SAFE konventionella o rull-bälten samt sjukvårdsbälten",
            "employees": 4,
            "annual_turnover": 4500000,
            "capital": 5000,
            "key_personnel": [
                {
                    "name": "Ulf Rex",
                    "position": "Verkst dir"
                }
            ],
            "establishment_year": 1966
        },
        "13": {
            "company_name": "TELEVISIONS, o SMALFILM",
            "activity": "Bedriver import o export av film till televisioner, speciellt i Sverige o Skandinavien, men också i övriga världen. Import o export av biograffilmer. Organisation av internationella filmproduktioner. Distribuerar 16 mm film i Sverige till skolor o organisationer",
            "employees": 7,
            "key_personnel": [
                {
                    "name": "Ove Wallius",
                    "position": "Verkst dir"
                }
            ],
            "establishment_year": 1956
        },
        "14": {
            "company_name": "TELFA, AB",
            "activity": "Säljer persiennmaterial, båtar o båttillbehör",
            "employees": 14,
            "capital": 250000,
            "key_personnel": [
                {
                    "name": "Gunnar Anderson",
                    "position": "Verkst dir"
                }
            ],
            "establishment_year": 1952
        },
        "15": {
            "company_name": "NILSONS GUMMI AB, ERNST",
            "activity": "Säljer gummiringar o utför ringreparationer",
            "employees": 17,
            "annual_turnover": 1800000,
            "capital": 100000,
            "key_personnel": [
                {
                    "name": "Holger Lundestam",
                    "position": "Verkst dir"
                }
            ],
            "establishment_year": 1957
        },
        "16": {
            "company_name": "SGS-SEMICONDUCTOR AB",
            "activity": "Tillverkar o säljer kisel Planar dioder, transistorer o integrerade kretsar",
            "employees": 150,
            "capital": 6000000,
            "key_personnel": [
                {
                    "name": "Glenn Marshall",
                    "position": "Verkst dir"
                }
            ],
            "establishment_year": 1965
        }
    }
}