{
    "original": "GRO\n\nGRONING AB, IVAR\n\nPnr 791 00\n\nFalun, Asg 24. Tel 023-108 30,\n108 34. Bankgiro 466-5089.\nPostgiro 70554-1. Tga Groening. Telex\n84045\n\nVerksamhet: Säljer trävaror o\nträfiberplattor\nAktiekapital: 40 000\nVerkst dir: Ivar Grö ning\nEtableringsår: 1947.\n\nTRÅ\n\n149074-7. Tga Transhud.\nTelex 3121\n\nVerksamhet: Import av ràa hudar o\nskinn\n\nAntal anställda: 6\nÅrsomsättning: 19 000 000\nAktiekapital: 900 000\nVerkst dir: Edgar R Bachrach\nEtableringsår: 1935.\n\nSVENSKA COOPERHEAT AB\n\nPnr 433 00\n\nPartille, Järnstångsv 7. Tel\n031-44 40 00, 44 52 57. Bankgiro\n202-8314. Postgiro 424207-9\nVerksamhet:\nGlödgningsutrustning-ar, glödgningsugnar. Utför\nlegovär-mebehandlingar\nAntal anställda: 8\nÅrsomsättning: 2 000 000\nAktiekapital: 25 000\nVerkst dir: Björn Kjessler\nEtableringsår: 1968.\n\nSVENSKA CYKELSTÄLL.\nFABRIKEN, AB\n\nPnr 59101\n\nMotala 1, Norrsten. Box 98. Tel\n0141-31170. Bankgiro 984-4440.\nPostgiro 389900-2\nVerksamhet: Tillverkar cykelställ,\ncykelgarage, piskställningar,\nplåtbyggnader, parksoffor,\npapperskorgar, lekplatsutrustningar, staket\nmm\n\nVarunamn: SCM\nAktiekapital: 150 000\nVerkst dir: Ingemar Ternberg\nEtableringsår: 1948.\n\nSVENSKA ORIENT LINIEN, AB\n\nPnr 403 17\n\nGöteborg 2, Packhusplatsen 6. Box\n2522. Tel 17 20 20, riks031-17 51 00.\nBankgiro 500-5533. Postgiro\n44820-9. Tga Esoel.\nTelex 2239 ESOEL S\nVerksamhet: Rederirörelse\nAntal anställda: 483\nÅrsomsättning: 92 219 000\nAktiekapital: 30 000 000\nVerkst dir: Folke Kristensen\nEtableringsår: 1957.\n\nSVENSKA OST ASIATISKA\nKOMPANIET, AB\n\nPnr 403 17\n\nGöteborg 2, Packhusplatsen 6. Box\n2524. Tel 031-17 20 20. Tga\nOst-asiat\n\nVerksamhet: Rederirörelse\nFilial: 10322 Stockholm 16, Gustav\nAdolfs torg 16. Box 16080. Tel\n08-23 7140\nAntal anställda: 906\nÅrsomsättning: 195 000 000\nAktiekapital: 30 000 000\nVerkst dir. K von Sydow\nEtableringsår 1907.\n\nSEGENMARK, AB P A\n\nPnr 19147\n\nSollentuna, Industriv 4. Tel\n08-35 25 40. Tga Segenmarkco\nVeiksamhet: Säljer kontorsmaskiner\nAktiekapital: 25 000\nVerkst dir: A Segenmark\nEtableringsår 1954.\n\nRINGBORG AB, J\n\nPnr 60105\n\nNariköping 1, Bråddg 1. Box 408.\nTel 011-18 62 60. Bankgiro\n609-8479. Postgiro 11101-3.\nTga Iringborg. Telex 64170\nVerksamhet: Spedition,\nskeppsmäk-leri o befraktning. Agentur för\ntunga kemikalier\nAntal anställda: 35\nAktiekapital: 800 000\nStyrelse: Herr Lars Ringborg\n(ordf), herr Bo Ringborg, herr Bernt\nRingborg, fru Gunilla Ringborg,\nherr Gösta Ringborg\nVerkst dir: Gösta Ringborg\nEtableringsår: 1799\nOmbildat till aktiebolag 1908.\n\nRINGDAHL MASKINER AB\n\nPnr 103 11\n\nStockholm 2,Munkbron 5. Box 2024.\nTel 08-2167 44, 2167 45. Bankgiro\n174-9050. Postgiro 604594. Tga\nRingmatrade. Telex 10643\nVerksamhet: Säljer maskiner o\nförbrukningsmaterial för pappers- o\ncellulosaindustrin\nAntal anställda: 12\nÅrsomsättning: 5000 000\nAktiekapital: 5 000\nVerkst dir: Ing Bernt Ringdahl\nEtableringsår: 1964.\n\nDJUPGRAVYR\n\nPnr 436 00\n\nAskim, Nämndemansstigen 10. Tel\n031-28 39 50. Bankgiro 49-2315.\nPostgiro 47611\nVerksamhet: Maskingraverade\nskyltar. Varmpräglingar\nÄgare o chef: O Pilbrand\nEtableringsår: 1953.\n\nHUGIN KASSAREGISTER AB\n\nPnr 102 62\n\nStockholm 4. Hammarby Fabriksv\n19-21. Box 4180. Tel 08-2451 00.\nPostgiro 150699. Telex 10650. Tga\nHuginmaskin\n\nVerksamhet: Tillverkar o säljer\nkassaregister\nAntal anställda: 1193\nAktiekapital: 2000 000\nÅrsomsättning: 117330 000\nVerkst dir: Erik Winberg\nEtableringsår: 1936.\n\nT EM\n\nTELE.INVEST AB (TEAB)\n\nPnr 402 41\n\nGöteborg 12, Karl Johansg 100.\nBox 12028. Tel 031-42 0135.\nBankgiro 852-6196. Postgiro 427500-4.\nTga Teab. Telex 20090\nVerksamhet: Elektronik, ultraljud,\nkomponenter\nAntal anställda: 10\nAktiekapital: 200 000\nÄgare o chef: C M Frisk\nEtableringsår: 1953.\n\nNILSSON, AB E W\n\nPnr 632 21\n\nEskilstuna, Kungsg 76. Tel\n016-13 7450. Postgiro 25228. Telex\n40984. Tga Eve bolaget\nVerksamhet: Säljer skrot o metall\nDotterbolag: Södertälje. Södertälje\nSkrot AB, Oxelgrensv. Tel\n0755-32144\n\nFilialer: Flen, Vattug. Tel\n0157-120 06\n\nKöping, Järnvägsg.Tel0221-11288\nAktiekapital: 350 000\nDisp: Fritz Andersson\nEtableringsår: 1926\nOmbildat till aktiebolag 1930.\n\nNILSSON MUSIK AB, ERIC\n\nPnr 632 21\n\nEskilstuna, Kungsg 34. Tel\n016-13 75 00. Tga Musiknilsson\nVerksamhet: Musikinstrument i\ndetalj o engros\nAntal anställda: 15\nAktiekapital: 75 000\n\nVerkst dir: Fru Aina Nilsson\nEtableringsår: 1921\nOmbildat till aktiebolag 1945.\n\nNILSSONS FABRIKS AB,ERIK\n\nPnr 50102\n\nBorås 1, Box 30. Lilla Brog 9.\nTel 033-12 5100\n\nVerksamhet: Tillverkar yttertrikå\nAktiekapital: 300000\nVerkst dir: Ulf C-H Nilsson\nEtableringsår: 1906.",
    "structured": {
        "1": {
            "company_name": "GRONING AB, IVAR",
            "pnr": "791 00",
            "address": "Falun, Asg 24",
            "phone_number": "023-108 30",
            "bank_details": {
                "bankgiro": "466-5089",
                "postgiro": "70554-1"
            },
            "activity": "Säljer trävaror o träfiberplattor",
            "capital": 40000,
            "key_personnel": [
                {
                    "name": "Ivar Grö ning",
                    "position": "Verkst dir"
                }
            ],
            "establishment_year": 1947
        },
        "2": {
            "company_name": "TRÅ",
            "pnr": "149074-7",
            "activity": "Import av ràa hudar o skinn",
            "employees": 6,
            "annual_turnover": 19000000,
            "capital": 900000,
            "key_personnel": [
                {
                    "name": "Edgar R Bachrach",
                    "position": "Verkst dir"
                }
            ],
            "establishment_year": 1935
        },
        "3": {
            "company_name": "SVENSKA COOPERHEAT AB",
            "pnr": "433 00",
            "address": "Partille, Järnstångsv 7",
            "phone_number": "031-44 40 00",
            "bank_details": {
                "bankgiro": "202-8314",
                "postgiro": "424207-9"
            },
            "activity": "Glödgningsutrustning-ar, glödgningsugnar. Utför legovär-mebehandlingar",
            "employees": 8,
            "annual_turnover": 2000000,
            "capital": 25000,
            "key_personnel": [
                {
                    "name": "Björn Kjessler",
                    "position": "Verkst dir"
                }
            ],
            "establishment_year": 1968
        },
        "4": {
            "company_name": "SVENSKA CYKELSTÄLL. FABRIKEN, AB",
            "pnr": "59101",
            "address": "Motala 1, Norrsten. Box 98",
            "phone_number": "0141-31170",
            "bank_details": {
                "bankgiro": "984-4440",
                "postgiro": "389900-2"
            },
            "activity": "Tillverkar cykelställ, cykelgarage, piskställningar, plåtbyggnader, parksoffor, papperskorgar, lekplatsutrustningar, staket mm",
            "capital": 150000,
            "key_personnel": [
                {
                    "name": "Ingemar Ternberg",
                    "position": "Verkst dir"
                }
            ],
            "establishment_year": 1948
        },
        "5": {
            "company_name": "SVENSKA ORIENT LINIEN, AB",
            "pnr": "403 17",
            "address": "Göteborg 2, Packhusplatsen 6. Box 2522",
            "phone_number": "17 20 20, riks031-17 51 00",
            "bank_details": {
                "bankgiro": "500-5533",
                "postgiro": "44820-9"
            },
            "activity": "Rederirörelse",
            "employees": 483,
            "annual_turnover": 92219000,
            "capital": 30000000,
            "key_personnel": [
                {
                    "name": "Folke Kristensen",
                    "position": "Verkst dir"
                }
            ],
            "establishment_year": 1957
        },
        "6": {
            "company_name": "SVENSKA OST ASIATISKA KOMPANIET, AB",
            "pnr": "403 17",
            "address": "Göteborg 2, Packhusplatsen 6. Box 2524",
            "phone_number": "031-17 20 20",
            "activity": "Rederirörelse",
            "filial": {
                "name": "10322 Stockholm 16, Gustav Adolfs torg 16. Box 16080",
                "phone_number": "08-23 7140"
            },
            "employees": 906,
            "annual_turnover": 195000000,
            "capital": 30000000,
            "key_personnel": [
                {
                    "name": "K von Sydow",
                    "position": "Verkst dir"
                }
            ],
            "establishment_year": 1907
        },
        "7": {
            "company_name": "SEGENMARK, AB P A",
            "pnr": "19147",
            "address": "Sollentuna, Industriv 4",
            "phone_number": "08-35 25 40",
            "activity": "Säljer kontorsmaskiner",
            "capital": 25000,
            "key_personnel": [
                {
                    "name": "A Segenmark",
                    "position": "Verkst dir"
                }
            ],
            "establishment_year": 1954
        },
        "8": {
            "company_name": "RINGBORG AB, J",
            "pnr": "60105",
            "address": "Nariköping 1, Bråddg 1. Box 408",
            "phone_number": "011-18 62 60",
            "bank_details": {
                "bankgiro": "609-8479",
                "postgiro": "11101-3"
            },
            "activity": "Spedition, skeppsmäk-leri o befraktning. Agentur för tunga kemikalier",
            "employees": 35,
            "key_personnel": [
                {
                    "name": "Gösta Ringborg",
                    "position": "Verkst dir"
                }
            ],
            "establishment_year": 1799
        },
        "9": {
            "company_name": "RINGDAHL MASKINER AB",
            "pnr": "103 11",
            "address": "Stockholm 2,Munkbron 5. Box 2024",
            "phone_number": "08-2167 44, 2167 45",
            "bank_details": {
                "bankgiro": "174-9050",
                "postgiro": "604594"
            },
            "activity": "Säljer maskiner o förbrukningsmaterial för pappers- o cellulosaindustrin",
            "employees": 12,
            "annual_turnover": 5000000,
            "capital": 5000,
            "key_personnel": [
                {
                    "name": "Ing Bernt Ringdahl",
                    "position": "Verkst dir"
                }
            ],
            "establishment_year": 1964
        },
        "10": {
            "company_name": "DJUPGRAVYR",
            "pnr": "436 00",
            "address": "Askim, Nämndemansstigen 10",
            "phone_number": "031-28 39 50",
            "bank_details": {
                "bankgiro": "49-2315",
                "postgiro": "47611"
            },
            "activity": "Maskingraverade skyltar. Varmpräglingar",
            "owner_and_ceo": "O Pilbrand",
            "establishment_year": 1953
        },
        "11": {
            "company_name": "HUGIN KASSAREGISTER AB",
            "pnr": "102 62",
            "address": "Stockholm 4. Hammarby Fabriksv 19-21. Box 4180",
            "phone_number": "08-2451 00",
            "postgiro": "150699",
            "telex": "10650",
            "activity": "Tillverkar o säljer kassaregister",
            "employees": 1193,
            "capital": 2000000,
            "annual_turnover": 1173300000,
            "key_personnel": [
                {
                    "name": "Erik Winberg",
                    "position": "Verkst dir"
                }
            ],
            "establishment_year": 1936
        },
        "12": {
            "company_name": "T EM TELE.INVEST AB (TEAB)",
            "pnr": "402 41",
            "address": "Göteborg 12, Karl Johansg 100. Box 12028",
            "phone_number": "031-42 0135",
            "bank_details": {
                "bankgiro": "852-6196",
                "postgiro": "427500-4"
            },
            "telex": "20090",
            "activity": "Elektronik, ultraljud, komponenter",
            "employees": 10,
            "capital": 200000,
            "owner_and_ceo": "C M Frisk",
            "establishment_year": 1953
        },
        "13": {
            "company_name": "NILSSON, AB E W",
            "pnr": "632 21",
            "address": "Eskilstuna, Kungsg 76",
            "phone_number": "016-13 7450",
            "postgiro": "25228",
            "telex": "40984",
            "activity": "Säljer skrot o metall",
            "subsidiary": "Södertälje. Södertälje Skrot AB, Oxelgrensv",
            "branch_offices": [
                {
                    "location": "Flen, Vattug",
                    "phone_number": "0157-120 06"
                },
                {
                    "location": "Köping, Järnvägsg",
                    "phone_number": "0221-11288"
                }
            ],
            "capital": 350000,
            "disponent": "Fritz Andersson",
            "establishment_year": 1926
        },
        "14": {
            "company_name": "NILSSON MUSIK AB, ERIC",
            "pnr": "632 21",
            "address": "Eskilstuna, Kungsg 34",
            "phone_number": "016-13 75 00",
            "activity": "Musikinstrument i detalj o engros",
            "employees": 15,
            "capital": 75000,
            "key_personnel": [
                {
                    "name": "Fru Aina Nilsson",
                    "position": "Verkst dir"
                }
            ],
            "establishment_year": 1921
        },
        "15": {
            "company_name": "NILSSONS FABRIKS AB, ERIK",
            "pnr": "50102",
            "address": "Borås 1, Box 30. Lilla Brog 9",
            "phone_number": "033-12 5100",
            "activity": "Tillverkar yttertrikå",
            "capital": 300000,
            "key_personnel": [
                {
                    "name": "Ulf C-H Nilsson",
                    "position": "Verkst dir"
                }
            ],
            "establishment_year": 1906
        }
    }
}