{
    "original": "ekman &amp; becksén ab\n\nPnr 400 14\n\nGöteborg 53, Box 53012.\nKristine-lundsg 16. Tel 031-18 76 80,\n18 76 82. Bankgiro 420-0465.\nPostgiro 47890-9. TgaCafig. Telex\n2232\n\nVerksamhet: Import o agenturer.\nRåvaror för livsmedelsindustrien.\nKemikalier. Konserverade o\ndjupfrysta livsmedel. Kolonialvaror\nAvdelningskontor: 112 27\nStockholm, Kungsbroplan 2. Tel\n08-54 37 24\n\nAntal anställda: 7\nAktiekapital: 45 000\nVerkst dir: Gösta Pettersson\nEtableringsår: 1941\nOmbildat till aktiebolag 1942.\n\nekman &amp; brundin ab\n\nPnr 114 31\n\nStockholm, Plorag 5. Tel\n08-23 33 40. Bankgiro 120-0344.\nPostgiro 500044-3\n\nVerksamhet: Tillverkar o säljer\nfisknät\n\nAntal anställda: 20\nÅrsomsättning: 2 300 000\nAktiekapital: 50 000\nVerkst dir: Lars M Carneheim\nEtableringsår: 1951.\n\nKINNAREDS KARTONG, AB\n\nPnr 310 74\n\nKinnared. Box 50. Tel 0345-300 01.\nBankgiro 54-6328. Postgiro 573632-7\nVerksamhet: Tillverkar kartonger i\nhård papp\nAntal anställda: 4\nÅrsomsättning: 350 000\nAktiekapital: 10 000\nVerkst dir: Erie Mattsson\nEtableringsår: 1941\nOmbildat till aktiebolag 1960.\n\nKINNAREDS TEXTIL, AB\n\nPnr 510 20\n\nFritsla. Tel 0320-702 80. Bankgiro\n53-1108. Postgiro 171500-2\nVerksamhet: Tillverkar korsettväv,\npoplin o rips för damhattar\nAntal anställda: 16\n\nÅrsomsättning: 1000 000\nAktiekapital: 80 000\nVerkst dir: Holger Åkerlund\nEtableringsår: 1942.\n\nKINNARPS KONTORS.\nMUBLER, AB\n\nPnr 520 44\n\nKinnaip, Box 85. Tel 0515-333 70.\nBankgiro 54-1619. Postgiro 29439-7\nVeiksamhet: Tillverkar o säljer\nkontorsmöbler\nAntal anställda: 100\nÅrsomsättning: 25 000 000\nAktiekapital: 100 000\nVerkst din Jarl Andersson\nEtableringsår: 1942\nOmbildat till aktiebolag 1960.\n\nKINNASAND, AB\n\nPnr 51101\n\nKinna 1, Box 66. Tel 0320-11500.\nBankgiro 54-6161.\nTelex 36043 KISAND S\nVerksamhet: Tillverkar\ninredningstextilier o textiltapeter\nAntal anställda: 175\nÅrsomsättning: 20 000 000\nAktiekapital: 601000\nVerkst dir: Sven Engdahl\nEtableringsår: 1918.\n\nJERNRACO, AB\n\nPnr 123 57\n\nFarsta 1, Piprensarv 32. Tel\n08-93 35 00, 93 64 00. Bankgiro\n747-1105. Postgiro 707900-7. Tga\nJernraco, Stockholm\nVerksamhet: Importerar o säljer\nmetallsågblad, bågfilställningar mm\nAktiekapital: 5 000\nVerkst dir: Svante Malmgren\nEtableringsår: 1964.\n\nHP PLAST AB\n\nPnr 12702\n\nSkärholmen 2, Lilla Sällskapets v\n38. Box 2074. Tel 08-8804 35. Post\ngiro 508546-9. Tga HOEP-Plast\nVerksamhet: Tillverkar polyeten i\npåsar, säckar, slang, ark o rullar\nmed eller utan tryck. Jordbruks- o\nbyggnadsfolie samt presenningar\nAktiekapital: 10 000\nVerkst dir Hans Gunnar Palmér\nEtableringsår: 1953\nOmbildat till aktiebolag 1958.\n\nHR-TRANSPORTER\nHELLBERG &amp; REMNEMO\n\nPnr 70106\n\nÖrebro 1, Adolfsbergsv 4. Box 483.\nTel 019-1122 68, 13 0100.\nBankgiro 614-7458. Postgiro 667283\nVerksamhet: Akeriiörelse\nAntal anställda: 6\nÅrsomsättning: 480 000\nChefer: Henry Hellberg, Ingemar\nRemnemo\n\nKamrer: Olle Welin\nEtableringsår: 1964.\n\nHS FABRIKERNA AB\n\n(Hillerstorps Stängselfabrik)\n\nPnr 330 33\n\nHillers torp. Tel 0370-22015,22165.\nBankgiro 54-3207. Postgiro 274959\nVerksamhet: Tillverkar pappers-,\npotatis- o skyltkorgar, skyltställ\nVarunamn: HS\nAntal anställda: 18\nÅrsomsättning: 2 000 000\nAktiekapital: 15 000\nVerkst dir: Nüs Heijel\nEtableringsår: 1931.\n\nHSB:s INDUSTRIER AB\nBOROHUS\n\nPnr 100 21\n\nStockholm 18, Fack. Tel\n08-54 05 40. Tga Håessbe\nVerksamhet: Monteringsfärdiga\nträhus, barnstugor, paviljonger,\nbyggnadssnickerier, torkskåp\nVarunamn: Borohus\nAntal anställda: 1458\n\nÅrsomsättning: 132 600 000\nAktiekapital: 1000000\nVerkst dir Sven Kypengren\nEtableringsår: 1936.\n\nHT AGENTURER\n\nPnr 115 26\n\nStockholm, Gyllenstiernsg 14. Tel\n08-63 26 16. Bankgiro 43-0848\nPostgiro 658928. Tga Hateagenturer\nVerksamhet: Agenturer för maskiner\no verktyg\n\nChef: Ing Harold Piehler\nEtableringsår: 1962.\n\nSTÅLSTÄMPELFABRIKEN AB\n\nPnr 63101\n\nEskilstuna 1, Vasbergsg 7. Box 8.\nTel 016-13 06 54, 13 05 50. Bankgiro\n148-7115. Postgiro 683980-7. Tga\nStämpelfabriken\nVerksamhet: Tillverkar stål- o\nbrännstämplar, matthållare mm\nAntal anställda: 4\nÅrsomsättning: 200 000\nVerkst dir: Lars G Lundin\nEtableringsår: 1907.\n\nJOHANSSON, GOT TH\n\nPnr 930 55\n\nJörn, Box 317. Tel 0916-102 95.\nPostgiro 485341. Tga\nJohanssonsvilt\n\nVerksamhet: Partihandel i lingon,\nblåbär, hjortron, renkött,\nskogsfågel, hudar o skinn\nEtableringsår: 1961.\n\nJOHANSSON &amp; CO AB,\nGUNNAR\n\nPnr 450 70\n\nHamburgsund, Box 70. Tel\n0525-333 50. Bankgiro 433-6384.\nPostgiro 176728-4\n\nVerksamhet: Handel o åkerirörelse\nAntal anställda: 46\nÅrsomsättning: 4 000 000\nAktiekapital: 300 000\nVerkst dir: Ingemar Gunnarsson\nEtableringsår: 1927.\n\nJOHANSSON AB, BILFIRMA\nGUSTAF E\n\nPnr 52100\n\nFalköping, Göteborgsv 4. Tel\n0515-130 50. Bankgiro 541-5336.\nPost-giro 361232-2\n\nVerksamhet: Säljer bilar, traktorer,\nreservdelar, tillbehör\nAntal anställda: 150\nÅrsomsättning: 34 800 000\nAktiekapital: 100 000\nVerkst dir: Stig Johansson\nEtableringsår: 1955.\n\nARNOLDS SÄNGKLÄDER AB\n\nPnr 73101\n\nKöping 1, Box 174. Tel\n0221-157 00. Bankgiro 607-09 24.\nPostgiro 327094-9\n\nVerksamhet: Tillverkar o säljer\nsängkläder av alla slag\nFabriker: 73101 Köping,\nHummel-bäcksg 3. Tel 0221-157 00\nAgenter: Jens Bergman, Gröna g 8,\n55257 Jönköping. Tel 036-12 17 61\nArne Josefsson, Box 56, 860 14\nViskan. Tel 0691-12213\nAntal anställda: 14\nÅrsomsättning: 1000000\nAktiekapital: 5 000\nVerkst dir: Fabr George Arnold\nEtableringsår: 1966.\n\nTRÅ\n\nTRANSPORTKOMPANIET, AB\n\nPnr 102 70\n\nStockholm 9, Hornsbruksg 28. Pack.\nTel 08-68 05 80. Bankgiro 44-6698.\nPostgiro 954. Tga Transportkomp.\nTelex 19361\n\nVerksamhet: Internationell\nspedi-tionsverksamhet\nAktiekapital: 1 500 000\nVerkst din Anders Frykman.\n\nTRANSPORTKONSULT, AB\n\nPnr 11136\n\nStockholm, Drottningg 71 D. Tel\n08-24 69 70. Bankgiro 728-8012.\nPostgiro 256730-3. Tga Transult\nVerksamhet: Rationalisering av\nhanterings- o transportmetoder\nAntal anställda: 15\nAktiekapital: 30 000\nVerkst dir: Ing Knut Petersson\n(Ledamot i SKIF)\nEtableringsàr: 1946\nFöretaget är medlem i Konsults\nföreningen.\n\nTRANSPORTMASKINER AB\n\nPnr 12612\n\nStockholm 42, Box 42054.\nVästberga Allé 36, Hägersten. Tel\n08-45 29 00. Bankgiro 29-5097.\nPostgiro 50690. Tga Motornytt.\nTelex 10853\n\nVerksamhet: Specialfordon.\nBilverkstadsutrustningar, domkrafter\nAntal anställda: 18\nAktiekapital: 125 000\nVerkst dir: Carl-Olof Wikstedt\nEtableringsàr: 1960.\n\nTRANSPORT-PRODUKTER\n\nPnr 11648\n\nStockholm, Sankt Paulsg 23. Tel\n08-4145 31, 4145 51. Postgiro\n550123\n\nVerksamhet: Tillverkar o säljer\ntransportvagnar, kärror etc. Säljer\nlänkrullar o hjul\nAntal anställda: 9\nChef: Gustav Larsson\nEtableringsàr: 1955.\n\nTRANSPORTUTRUSTNINGAR\nAB TURAB\n\nPnr 600 05\n\nNorrköping 5, Box 5046. Almg 10.\nTel 011-18 14 50. Bankgiro 74-3074.\nPostgiro 237677-0\nVerksamhet: Tillverkar båttrailer,\nsläpvagnar, specialvagnar,\narbets-bodar o jaktstugor\nVerkst din Tage Ericsson\nEtableringsàr: 1957\nOmbildat till aktiebolag 1970.\n\nTRANSPORTVERKEN AB\n\nPnr 265 01\n\nÅstorp 1, Osterg 19. Box 39. Tel\n042-51615. Bankgiro 671-3796.\nPostgiro 22152-3. Tga Conveyor\nVerksamhet: Tillverkar\ntransport-o lyftanordningar, vagnar o hjul.\nImport- o agenturrörelse i samma\nbransch\n\nVarunamn: Gepard\nAntal anställda: 45\nÅrsomsättning: 4 000 000\nAktiekapital; 30 000\n\nStyrelseordf: U Aronsohn\nVerkst dir: Ing U Aronsohn\nEtableringsàr. 1959.\n\nTRANSSPED, AB\n\nPnr 41113\n\nGöteborg, Packhusplatsen 2. Tel\n031-1132 21, 1132 26. Bankgiro\n795-8382. Postgiro 528954-1. Tga\nTranssped. Telex 2373 CHARLES S\nVerksamhet: Spedition\nAntal anställda: 7\nAktiekapital: 10 000\nVerkst dir: Bengt Wingren\nEtableringsàr: 1967.\n\nTRANS-TEKNO, AB\n\nPnr 436 00\n\nAskim, Stenstigen 1. Tel\n031-28 28 09. Bankgiro 43-9961.\nPost-giro 624250\n\nVerksamhet:\nContainertransport-redskap\n\nAktiekapital: 5 000\nVerkst dir: Bertil Björklund\nEtableringsàr: 1960.\n\nTRANÅS GULDLISTFABRIK,\nAB\n\nPnr 573 02\n\nTranås 2. Box 2073. Tel\n0140-302 45. Bankgiro 365-5859.\nPostgiro 70107-8. Tga Tranåslist\nVerksamhet: Tillverkar ramlist o\nramar. Säljer inramade\nreproduktioner\n\nAntal anställda: 65\nÅrsomsättning: 3 500 000\nAktiekapital: 100 000\nStyrelse: Dir Erik Hellberg (ordf),\ndir Mats-Olof Hellberg, fru Svea\nHellberg, fru Inga Schönberg, fru\nAnna-Brita Sjögren\nVerkst dir: Mats-Olof Hellberg\nFörsäljn-chef: Disp Patrik Myrén\nEtableringsàr: 1920\nOmbildat till aktiebolag 1950.\n\nTRANÅS KARTONG &amp;\nTRYCKERI AB\n\nPnr 573 01\n\nTranås 1, Box 23. Tel 0140-10015.\nBankgiro 130-4989. Postgiro\n83000-0. Tga Tranåskartong\nVerksamhet: Kartongfabrik, bok-,\noffset-, reklam- o kartongtryckeri,\nbokbinderi, reklambyrå samt\nsäljer emballageartiklar en gros\nAntal anställda: 30\nÅrsomsättning: 2 800 000\nAktiekapital: 115 000\nVerkst din Olle Svenler\nDisp: Törd Svenler\nEtableringsån 1914.\n\nTRANÅS MEKANISKA\nVERKSTAD\n\nPnr 573 00\n\nTranås, Vaktg 8. Box\n245.Tel0140-123 95, 12619. Bankgiro 36-5696.\nPostgiro 98755\n\nVerksamhet: Tillverkar\nträbearbetningsmaskiner\nAntal anställda: 11\nÅrsomsättning: 325 000\nChef: D Rosin\nEtableringsàr: 1930.\n\nTRANÅS MÖBELFABRIKS AB\n\nPnr 573 01\n\nTranås 1, Box 30. Vasag 25. Tel\n0140-10020. Bankgiro 60-0995.\nPostgiro 299845\nVerksamhet: Tillverkar o säljer\nhemmöbler (soff- o lampbord)\nAntal anställda: 40\nÅrsomsättning: 3 500 000\nAktiekapital: 20 000\nStyrelse: Dir Sten Nilsson (ordf),\nherr Harry Hagsjö, herr Stephen\nJohnsson\n\nVerkst dir Sten Nilsson\nEtableringsàr: 1966.\n\nTRANÅS ROSTFRIA. AB\n\nPnr 573 01\n\nTranås 1, Rundelv 2. Box 21. Tel\n0140-10115. Bankgiro 365-7004.\nPostgiro 293421-4. Tga Stainless\nVerksamhet: Levererar inredningar\nför industrier, sjukhus,\nlaboratorier o storkök, dörrar o fönster i\nrostfritt stål. Egen snickerifabrik\nAntal anställda: 110\nÅrsomsättning: 10 000 000\nAktiekapital: 200 000\nVerkst dir: Karl Gustafson\nV verkst dir: Jan Karlsson\nEtableringsàr. 1945.\n\nTRANÅS SKINNBEREDERI,\nAB\n\nPnr 573 01\n\nTranås 1, Box 46. Vasag 1. Tel\n0140-100 50. Bankgiro 365-7020.\nPostgiro 11666-5. Tga Berederiet\nVerksamhet: Bereder o färgar alla\nslags pälsskinn\nAntal anställda: 280\nÅrsomsättning: 28 000 000\nAktiekapital: 500 000\nVerkst din Gustav Johansson\nEtableringsån 1917.\n\nJUN\n\nBankgiro 347-0093. Postgiro\n5260-5\n\nVerksamhet: Försäljning o service\nav lantbruks- o entreprenadmaskiner\nAntal anställda: 120\nÅrsomsättning: 30 000 000\nAktiekapital: 150 000\nVerkst dir: Lennart Jöhncke\nEtableringsår. 1957.\n\nÅHLÉN &amp; HOLM AB\n\nPnr 104 60\n\nStockholm 20, Ringv 100. Fack.\nTel 08-44 99 00. Postgiro 20-8.\nTga Ahlénholm\nVerksamhet: Varuhus Åhléns,\nTempo, Meeths\nAktiekapital: 85 500000\nVerkst din Rune Höglund\nEtableringsån 1899.\n\nÅHLÉN &amp; ÅKERLUNDS\nFORLAGS AB\n\nPnr 105 44\n\nStockholm, Torsg 21. Tel\n08-3490 00. Telex 10043. Tga Förlaget\nVerksamhet: Tidskriftsförlag,\ndjuptryck, offsettryck, boktryck o\ntid-ningsbinderi\nAktiekapital: 14 000 000\nVerkst dir. Lukas Bonnier\nEtableringsån 1915.",
    "structured": {
        "1": {
            "company_name": "ekman & becksén ab",
            "activity": "Import o agenturer. Råvaror för livsmedelsindustrien. Kemikalier. Konserverade o djupfrysta livsmedel. Kolonialvaror",
            "establishment_year": 1941
        },
        "2": {
            "company_name": "ekman & brundin ab",
            "activity": "Tillverkar o säljer fisknät",
            "employees": 20,
            "annual_turnover": 2300000,
            "capital": 50000,
            "establishment_year": 1951
        },
        "3": {
            "company_name": "KINNAREDS KARTONG, AB",
            "activity": "Tillverkar kartonger i hård papp",
            "employees": 4,
            "annual_turnover": 350000,
            "capital": 10000,
            "establishment_year": 1941
        },
        "4": {
            "company_name": "KINNAREDS TEXTIL, AB",
            "activity": "Tillverkar korsettväv, poplin o rips för damhattar",
            "employees": 16,
            "annual_turnover": 1000000,
            "capital": 80000,
            "establishment_year": 1942
        },
        "5": {
            "company_name": "KINNARPS KONTORS. MUBLER, AB",
            "activity": "Tillverkar o säljer kontorsmöbler",
            "employees": 100,
            "annual_turnover": 25000000,
            "capital": 100000,
            "establishment_year": 1942
        },
        "6": {
            "company_name": "KINNASAND, AB",
            "activity": "Tillverkar inredningstextilier o textiltapeter",
            "employees": 175,
            "annual_turnover": 20000000,
            "capital": 601000,
            "establishment_year": 1918
        },
        "7": {
            "company_name": "JERNRACO, AB",
            "activity": "Importerar o säljer metallsågblad, bågfilställningar mm",
            "capital": 5000,
            "establishment_year": 1964
        },
        "8": {
            "company_name": "HP PLAST AB",
            "activity": "Tillverkar polyeten i påsar, säckar, slang, ark o rullar med eller utan tryck. Jordbruks- o byggnadsfolie samt presenningar",
            "capital": 10000,
            "establishment_year": 1953
        },
        "9": {
            "company_name": "HR-TRANSPORTER HELLBERG & REMNEMO",
            "activity": "Akeriiörelse",
            "employees": 6,
            "annual_turnover": 480000,
            "establishment_year": 1964
        },
        "10": {
            "company_name": "HS FABRIKERNA AB (Hillerstorps Stängselfabrik)",
            "activity": "Tillverkar pappers-, potatis- o skyltkorgar, skyltställ",
            "employees": 18,
            "annual_turnover": 2000000,
            "capital": 15000,
            "establishment_year": 1931
        },
        "11": {
            "company_name": "HSB:s INDUSTRIER AB BOROHUS",
            "activity": "Monteringsfärdiga trähus, barnstugor, paviljonger, byggnadssnickerier, torkskåp",
            "employees": 1458,
            "annual_turnover": 132600000,
            "capital": 1000000,
            "establishment_year": 1936
        },
        "12": {
            "company_name": "HT AGENTURER",
            "activity": "Agenturer för maskiner o verktyg",
            "establishment_year": 1962
        },
        "13": {
            "company_name": "STÅLSTÄMPELFABRIKEN AB",
            "activity": "Tillverkar stål- o brännstämplar, matthållare mm",
            "employees": 4,
            "annual_turnover": 200000,
            "establishment_year": 1907
        },
        "14": {
            "company_name": "JOHANSSON, GOT TH",
            "activity": "Partihandel i lingon, blåbär, hjortron, renkött, skogsfågel, hudar o skinn",
            "establishment_year": 1961
        },
        "15": {
            "company_name": "JOHANSSON & CO AB, GUNNAR",
            "activity": "Handel o åkerirörelse",
            "employees": 46,
            "annual_turnover": 4000000,
            "capital": 300000,
            "establishment_year": 1927
        },
        "16": {
            "company_name": "JOHANSSON AB, BILFIRMA GUSTAF E",
            "activity": "Säljer bilar, traktorer, reservdelar, tillbehör",
            "employees": 150,
            "annual_turnover": 34800000,
            "capital": 100000,
            "establishment_year": 1955
        },
        "17": {
            "company_name": "ARNOLDS SÄNGKLÄDER AB",
            "activity": "Tillverkar o säljer sängkläder av alla slag",
            "employees": 14,
            "annual_turnover": 1000000,
            "capital": 5000,
            "establishment_year": 1966
        },
        "18": {
            "company_name": "TRÅ TRANSPORTKOMPANIET, AB",
            "activity": "Internationell spedition",
            "capital": 1500000
        },
        "19": {
            "company_name": "TRANSPORTKONSULT, AB",
            "activity": "Rationalisering av hanterings- o transportmetoder",
            "employees": 15,
            "capital": 30000,
            "establishment_year": 1946
        },
        "20": {
            "company_name": "TRANSPORTMASKINER AB",
            "activity": "Specialfordon. Bilverkstadsutrustningar, domkrafter",
            "employees": 18,
            "capital": 125000,
            "establishment_year": 1960
        },
        "21": {
            "company_name": "TRANSPORT-PRODUKTER",
            "activity": "Tillverkar o säljer transportvagnar, kärror etc. Säljer länkrullar o hjul",
            "employees": 9,
            "establishment_year": 1955
        },
        "22": {
            "company_name": "TRANSPORTUTRUSTNINGAR AB TURAB",
            "activity": "Tillverkar båttrailer, släpvagnar, specialvagnar, arbets-bodar o jaktstugor",
            "establishment_year": 1957
        },
        "23": {
            "company_name": "TRANSPORTVERKEN AB",
            "activity": "Tillverkar transport-o lyftanordningar, vagnar o hjul. Import- o agenturrörelse i samma bransch",
            "employees": 45,
            "annual_turnover": 4000000,
            "capital": 30000,
            "establishment_year": 1959
        },
        "24": {
            "company_name": "TRANSSPED, AB",
            "activity": "Spedition",
            "employees": 7,
            "capital": 10000,
            "establishment_year": 1967
        },
        "25": {
            "company_name": "TRANS-TEKNO, AB",
            "activity": "Containertransport-redskap",
            "capital": 5000,
            "establishment_year": 1960
        },
        "26": {
            "company_name": "TRANÅS GULDLISTFABRIK, AB",
            "activity": "Tillverkar ramlist o ramar. Säljer inramade reproduktioner",
            "employees": 65,
            "annual_turnover": 3500000,
            "capital": 100000,
            "establishment_year": 1920
        },
        "27": {
            "company_name": "TRANÅS KARTONG & TRYCKERI AB",
            "activity": "Kartongfabrik, bok-, offset-, reklam- o kartongtryckeri, bokbinderi, reklambyrå samt säljer emballageartiklar en gros",
            "employees": 30,
            "annual_turnover": 2800000,
            "capital": 115000,
            "establishment_year": 1914
        },
        "28": {
            "company_name": "TRANÅS MEKANISKA VERKSTAD",
            "activity": "Tillverkar träbearbetningsmaskiner",
            "employees": 11,
            "annual_turnover": 325000,
            "establishment_year": 1930
        },
        "29": {
            "company_name": "TRANÅS MÖBELFABRIKS AB",
            "activity": "Tillverkar o säljer hemmöbler (soff- o lampbord)",
            "employees": 40,
            "annual_turnover": 3500000,
            "capital": 20000,
            "establishment_year": 1966
        },
        "30": {
            "company_name": "TRANÅS ROSTFRIA. AB",
            "activity": "Levererar inredningar för industrier, sjukhus, laboratorier o storkök, dörrar o fönster i rostfritt stål. Egen snickerifabrik",
            "employees": 110,
            "annual_turnover": 10000000,
            "capital": 200000,
            "establishment_year": 1945
        },
        "31": {
            "company_name": "TRANÅS SKINNBEREDERI, AB",
            "activity": "Bereder o färgar alla slags pälsskinn",
            "employees": 280,
            "annual_turnover": 28000000,
            "capital": 500000,
            "establishment_year": 1917
        },
        "32": {
            "company_name": "JUN",
            "activity": "Försäljning o service av lantbruks- o entreprenadmaskiner",
            "employees": 120,
            "annual_turnover": 30000000,
            "capital": 150000,
            "establishment_year": 1957
        },
        "33": {
            "company_name": "ÅHLÉN & HOLM AB",
            "activity": "Varuhus Åhléns, Tempo, Meeths",
            "capital": 85500000,
            "establishment_year": 1899
        },
        "34": {
            "company_name": "ÅHLÉN & ÅKERLUNDS FORLAGS AB",
            "activity": "Tidskriftsförlag, djuptryck, offsettryck, boktryck o tidningsbinderi",
            "capital": 14000000,
            "establishment_year": 1915
        }
    }
}