{
    "original": "TORNO MASKIN AB\n\nPnr 101 25\n\nStockholm 1, Barnhusg 22. Box\n404. Tel 08-24 31 20. Bankgiro 72-\n\n8752. Postgiro 609820. Tga\nTornomaskin. Telex 17132 HANSUN S\nVarunamn: Elite, Ser ax, Torno\nAktiekapital: 100 000\nVerkst dir: Lars Ericsson\nEtableringsår: 1960.\n\nIRE AB. INDUSTRI\n\nPnr 560 10\n\nSkiUingaryd, Box 2. Tel\n0370-70610. Bankgiro 672-4199.\nPostgiro 172410-3. Tgalre\nVerksamhet: Tillverkar o säljer\nstoppmöbler, fåtöljer o sittsoffor\nÅrsomsättning: 6 000 000\nAktiekapital: 110 000\nVerkst dir: Gerhard Ihreborn\nEtableringsår: 1937.\n\nENGHEDSTEXTIL AB\n\nPnr 540 20\n\nBlikstorp. Tel 0502-301 60\nVerksamhet: Tillverkar dam- o\nbarnunderkläder i nylon o bomull\nVeikst dir: Alvar Ahlgren.\n\nENGQVIST &amp; BERNDTSSON AB\n\nPnr 400 10\n\nGöteborg 3, Engelbrektsg 13. Box\n3012. Tel 031-13 77 55, 13 77 56.\nBankgiro 84-7757. Postgiro 42694\nVerksamhet: Säljer\nmaskinförnödenheter\n\nÄgare o chef: Per Erik Engqvist\nEtableringsår: 1916.\n\nNIC\n\nNICROMA\nFORNICKLINGS-FABRIKEN A BRINK AB\n\nPnr 600 03\n\nNorrköping 3, Dragsg 11. Box 3017.\nTel 011-1317 03, 18 83 90. Bankgiro\n824-2828. Postgiro 381516-4\nVerksamhet: Utför förkromning,\nförnickling, förkoppring,\nkadmie-ring, förzinkning, fosfatering\nAntal anställda: 18\nÅrsomsättning: 1400 000\nChef: Fabr Arne Brink\nEtableringsår: 1947.\n\nBERGSTRAND &amp; CO AB, S\n\nPnr 102 41\n\nStockholm 5, Grevg 64. Box 5004.\nTel 08-63 11 65. Postgiro 555499-3.\nTelex 1800. Tga Bergchart\nBerg-sale\n\nVerksamhet: Skeppsmäkleri o rederi\nAntal anställda: 28\nÅrsomsättning: 3 500 000\nAktiekapital: 100 000\nVerkst dir: Stig Bergstrand\nEtableringsår: 1957.\n\nBERGSTRÖMS\nKONSTRUKTIONSBYRÄ AB\n\nPnr 803 50\n\nGävle, Drottningg 47. Tel\n026-1184 54, 18 5 9 30. Bankgiro\n19-4027. Postgiro 545160-4\nVerksamhet: Konsulterande\nverksamhet inom maskinkonstruktioner\no industriella rörkonstruktioner\nAntal anställda: 20\nÅrsomsättning: 1 000 000\nAktiekapital: 10 000\nVerkst dir: Ing Rolf Bergström\nEtableringsår: 1959.\n\nBERGSTRÖMS\nTRÄ-SVARVERI AB\n\nPnr 602 37\n\nNorrköping, Oskarsg 7. Tel\n011-12 27 44. Postgiro 176217\nVerksamhet: Tillverkar träarmatur\no ljusstakar\nAntal anställda: 10\nÅrsomsättning: 270 000\nAktiekapital: 25 000\nVerkst dir: Göte Bergström\nEtableringsår: 1928.\n\nBERGSTRÖM,\nMOTORFIRMA ARNE\n\nPnr 60002\n\nNorrköping 2, Hantverkareg 34. Box\n2057. Tel 011-10 24 60, 13 93 60.\nBankgiro 82-4234. Postgiro 141530\nVerksamhet: Säljer bilar,\nmotorcyklar o reservdelar. Bilverkstad\n\nAntal anställda: 8\nÅrsomsättning: 2 000 000\nChef: Arne Bergström\nEtableringsår: 1937.\n\nLL-BOLAGEN AB\n\nPnr 44301\n\nLerum 1, Fack. Tel 0302-223 55.\nBankgiro 570-2238. Postgiro\n720850-7\n\nVerksamhet: säljer dockskåp,\ndockskåpsmöbler, lampor till dockskåp\nVarunamn: Lundby\nAntal anställda: 10\nÅrsomsättning: 4 200 000\nAktiekapital: 75 000\nVeikst dir: Per-Hugo Börnfelt\nEtableringsår: 1961\nDotterbolag: AB Lundby\nLeksaksfabrik, Lerum.\n\nLN KONSULT I HÖGANÄS AB\n\nPnr 263 00\n\nHöganäs, Storg 64. Box 58. Tel\n042-433 31, 433 36. Bankgiro\n270-5754. Postgiro 664630-1\nVerksamhet: Konsulterande\narkitekt- o ingenjörsbyrå\nAntal anstäUda: 7\nÅrsomsättning: 500 000\nAktiekapital: 10 000\nChefer: Byggn-ing Hans Laufeld,\nbyggn-ing Gunnar Nilsson\nEtableringsår: 1965.\n\nHYG\n\nÅrsomsättning: 600 000\nAktiekapital: 10 000\nVerkst dir. K S Landström\nEtableringsår. 1964.\n\nERIKSSON &amp; GILLJAM AB\n\nPnr 172 03\n\nSundbyberg 3, Box 342. Englundav\n2. Tel 08-29 0 4 80. Bankgiro\n17-0153. Postgiro 255176. Tga Ergill,\nStockholm. Telex 10309\nVerksamhet: Bil-, traktor- o\nindustridäck, cykeldäck. Tekniska\ngummivaror. Golvbeläggning\nFilialer: 417 08 Göteborg,\nPolstjär-neg 4. Tel 031-513115\n211 24 Malmö, Tärnög 2. Tel\n040-1803 30\n\n852 31 Sundsvall, Köpmang 16. Tel\n060-12 42 87, 12 42 88\nAntal anställda: 41\nAktiekapital: 100 000\nStyrelse: Dir Rune Gilljam (ordf),\nfru Greta Eriksson, herr John Eriks’\nson, fru Inga-Lill Gilljam\nVerkst dir: Rune Gilljam\nFörsäljn-chef för bilringar: Börje\nSäfström\n\nTekniska gummivaror o\ngolvbeläggningar: Harald Hauff\nKamrer: Elvin Johansson\nEtableringsår: 1947.\n\nKEMOSTÅL AB\n\nPnr 41101\n\nGöteborg, Stampg 38. Tel\n031-197115. Bankgiro 420-1034.\nPostgiro 240140-4. Tga Kemostal.\nTelex 2585 KEMO S\nVerksamhet: Blåsmaskiner, kätting,\npumpar o luftreningsanläggningar\nAktiekapital: 75 000.\n\nKENWOOD\n\nSvenska Thorn AB\nBromma 20, Box 20075. Bällstav\n34-36. Tel 08-98 19 10. Bankgiro\n724-9568. Postgiro 55202-6. Tga\nSwedthorn. Telex 10106\nVerksamhet: Marknadsför Kenwood\nhush ållsm aski n er\nAktiekapital: 100 000\nVerkst dir: Lars Ljunggren.\n\nKERAMISKA MEDDELANDEN\n\nPnr 137 00\n\nVästerhaninge, Ringv 62. Tel\n0750-210 35. Bankgiro 508-3001.\nPostgiro 508300-1. Tga Burtonpottery,\nStockholm\n\nVerksamhet: Utger tidskriften\nScan-dinavian Ceramic Communications\nUtgivare: Keram-ing Erk Burton\nEtableringsår: 1966.\n\n\"De fyra elementen\" — symbol\nfor Ing - firma KERAM - KONSULT\noch KERAMISKA MEDDELANDEN\n\nKERAM.KONSULT,\nING ENIURSF IRMA\n\nPnr 137 00\n\nVästerhaninge, Ringv 62. Tel\n0750-210 35. Bankgiro 508-3001.\nPostgiro 508300-1. Tga\nBurtonpottery, Stockholm\n\nVerksamhet: Krukmakeri. Konsult.\nUtger Keramiska Meddelanden\nVarunamn: Erk-krukmakare\nInnehavare: Keram-ing Erk Burton\nEtableringsår: 1964.\n\nVENTILATIONSTEKNIK, AB\n\nPnr 54100\n\nSkövde, Fabriksg 3. Tel\n0500-340 00. Bankgiro 365-0116.\nPostgiro 75320-2\n\nVerksamhet:\nVentilationsentreprenader. Tillverkar o säljer produkter\ninom ventilationsbranschen\nÅterförsäljare: Ingenjörsfirman\nSefovent AB, Box 9006. 550 09\nJönköping 9. Tel 036-765 21, 765 22\nAntal anställda: 41\nÅrsomsättning: 4 500 000\nAktiekapital: 80 000\nVerkst din Gunnar Thunberg\nEtableringsår: 1963.",
    "structured": {
        "1": {
            "company_name": "TORNO MASKIN AB",
            "pnr": "101 25",
            "address": "Stockholm 1, Barnhusg 22. Box 404",
            "phone_number": "08-24 31 20",
            "bank_details": {
                "bankgiro": "72-8752",
                "postgiro": "609820"
            },
            "activity": "Varunamn: Elite, Ser ax, Torno",
            "capital": 100000,
            "key_personnel": [
                {
                    "name": "Lars Ericsson",
                    "position": "Verkst dir"
                }
            ],
            "establishment_year": 1960
        },
        "2": {
            "company_name": "IRE AB. INDUSTRI",
            "pnr": "560 10",
            "address": "SkiUingaryd, Box 2",
            "phone_number": "0370-70610",
            "bank_details": {
                "bankgiro": "672-4199",
                "postgiro": "172410-3"
            },
            "activity": "Verksamhet: Tillverkar o säljer stoppmöbler, fåtöljer o sittsoffor",
            "annual_turnover": 6000000,
            "capital": 110000,
            "key_personnel": [
                {
                    "name": "Gerhard Ihreborn",
                    "position": "Verkst dir"
                }
            ],
            "establishment_year": 1937
        },
        "3": {
            "company_name": "ENGHEDSTEXTIL AB",
            "pnr": "540 20",
            "address": "Blikstorp",
            "phone_number": "0502-301 60",
            "activity": "Verksamhet: Tillverkar dam- o barnunderkläder i nylon o bomull",
            "key_personnel": [
                {
                    "name": "Alvar Ahlgren",
                    "position": "Veikst dir"
                }
            ]
        },
        "4": {
            "company_name": "ENGQVIST & BERNDTSSON AB",
            "pnr": "400 10",
            "address": "Göteborg 3, Engelbrektsg 13. Box 3012",
            "phone_number": "031-13 77 55, 13 77 56",
            "bank_details": {
                "bankgiro": "84-7757",
                "postgiro": "42694"
            },
            "activity": "Verksamhet: Säljer maskinförnödenheter",
            "key_personnel": [
                {
                    "name": "Per Erik Engqvist",
                    "position": "Ägare o chef"
                }
            ],
            "establishment_year": 1916
        },
        "5": {
            "company_name": "NICROMA FORNICKLINGS-FABRIKEN A BRINK AB",
            "pnr": "600 03",
            "address": "Norrköping 3, Dragsg 11. Box 3017",
            "phone_number": "011-1317 03, 18 83 90",
            "bank_details": {
                "bankgiro": "824-2828",
                "postgiro": "381516-4"
            },
            "activity": "Verksamhet: Utför förkromning, förnickling, förkoppring, kadmie-ring, förzinkning, fosfatering",
            "employees": 18,
            "annual_turnover": 1400000,
            "key_personnel": [
                {
                    "name": "Fabr Arne Brink",
                    "position": "Chef"
                }
            ],
            "establishment_year": 1947
        },
        "6": {
            "company_name": "BERGSTRAND & CO AB, S",
            "pnr": "102 41",
            "address": "Stockholm 5, Grevg 64. Box 5004",
            "phone_number": "08-63 11 65",
            "postgiro": "555499-3",
            "activity": "Verksamhet: Skeppsmäkleri o rederi",
            "employees": 28,
            "annual_turnover": 3500000,
            "capital": 100000,
            "key_personnel": [
                {
                    "name": "Stig Bergstrand",
                    "position": "Verkst dir"
                }
            ],
            "establishment_year": 1957
        },
        "7": {
            "company_name": "BERGSTRÖMS KONSTRUKTIONSBYRÄ AB",
            "pnr": "803 50",
            "address": "Gävle, Drottningg 47",
            "phone_number": "026-1184 54, 18 5 9 30",
            "bank_details": {
                "bankgiro": "19-4027",
                "postgiro": "545160-4"
            },
            "activity": "Verksamhet: Konsulterande verksamhet inom maskinkonstruktioner o industriella rörkonstruktioner",
            "employees": 20,
            "annual_turnover": 1000000,
            "capital": 10000,
            "key_personnel": [
                {
                    "name": "Ing Rolf Bergström",
                    "position": "Verkst dir"
                }
            ],
            "establishment_year": 1959
        },
        "8": {
            "company_name": "BERGSTRÖMS TRÄ-SVARVERI AB",
            "pnr": "602 37",
            "address": "Norrköping, Oskarsg 7",
            "phone_number": "011-12 27 44",
            "postgiro": "176217",
            "activity": "Verksamhet: Tillverkar träarmatur o ljusstakar",
            "employees": 10,
            "annual_turnover": 270000,
            "capital": 25000,
            "key_personnel": [
                {
                    "name": "Göte Bergström",
                    "position": "Verkst dir"
                }
            ],
            "establishment_year": 1928
        },
        "9": {
            "company_name": "BERGSTRÖM, MOTORFIRMA ARNE",
            "pnr": "60002",
            "address": "Norrköping 2, Hantverkareg 34. Box 2057",
            "phone_number": "011-10 24 60, 13 93 60",
            "bank_details": {
                "bankgiro": "82-4234",
                "postgiro": "141530"
            },
            "activity": "Verksamhet: Säljer bilar, motorcyklar o reservdelar. Bilverkstad",
            "employees": 8,
            "annual_turnover": 2000000,
            "key_personnel": [
                {
                    "name": "Arne Bergström",
                    "position": "Chef"
                }
            ],
            "establishment_year": 1937
        },
        "10": {
            "company_name": "LL-BOLAGEN AB",
            "pnr": "44301",
            "address": "Lerum 1, Fack",
            "phone_number": "0302-223 55",
            "bank_details": {
                "bankgiro": "570-2238",
                "postgiro": "720850-7"
            },
            "activity": "Verksamhet: säljer dockskåp, dockskåpsmöbler, lampor till dockskåp",
            "capital": 75000,
            "key_personnel": [
                {
                    "name": "Per-Hugo Börnfelt",
                    "position": "Veikst dir"
                }
            ],
            "establishment_year": 1961,
            "dotterbolag": "AB Lundby Leksaksfabrik, Lerum"
        },
        "11": {
            "company_name": "LN KONSULT I HÖGANÄS AB",
            "pnr": "263 00",
            "address": "Höganäs, Storg 64. Box 58",
            "phone_number": "042-433 31, 433 36",
            "bank_details": {
                "bankgiro": "270-5754",
                "postgiro": "664630-1"
            },
            "activity": "Verksamhet: Konsulterande arkitekt- o ingenjörsbyrå",
            "employees": 7,
            "annual_turnover": 500000,
            "capital": 10000,
            "key_personnel": [
                {
                    "name": "Byggn-ing Hans Laufeld",
                    "position": "Chefer"
                },
                {
                    "name": "Byggn-ing Gunnar Nilsson",
                    "position": "Chefer"
                },
                {
                    "name": "K S Landström",
                    "position": "Verkst dir"
                }
            ],
            "establishment_year": 1965
        },
        "12": {
            "company_name": "ERIKSSON & GILLJAM AB",
            "pnr": "172 03",
            "address": "Sundbyberg 3, Box 342. Englundav 2",
            "phone_number": "08-29 0 4 80",
            "bank_details": {
                "bankgiro": "17-0153",
                "postgiro": "255176"
            },
            "activity": "Verksamhet: Bil-, traktor- o industridäck, cykeldäck. Tekniska gummivaror. Golvbeläggning",
            "filialer": "417 08 Göteborg, Polstjär-neg 4\n211 24 Malmö, Tärnög 2\n852 31 Sundsvall, Köpmang 16",
            "employees": 41,
            "annual_turnover": 100000,
            "capital": 100000,
            "key_personnel": [
                {
                    "name": "Rune Gilljam",
                    "position": "Styrelse: Dir (ordf)"
                },
                {
                    "name": "Greta Eriksson",
                    "position": "Styrelse: Fru"
                },
                {
                    "name": "John Eriksson",
                    "position": "Styrelse: Herr"
                },
                {
                    "name": "Inga-Lill Gilljam",
                    "position": "Styrelse: Fru"
                },
                {
                    "name": "Rune Gilljam",
                    "position": "Verkst dir"
                },
                {
                    "name": "Börje Säfström",
                    "position": "Försäljn-chef för bilringar"
                },
                {
                    "name": "Harald Hauff",
                    "position": "Tekniska gummivaror o golvbeläggningar"
                },
                {
                    "name": "Elvin Johansson",
                    "position": "Kamrer"
                }
            ],
            "establishment_year": 1947
        },
        "13": {
            "company_name": "KEMOSTÅL AB",
            "pnr": "41101",
            "address": "Göteborg, Stampg 38",
            "phone_number": "031-197115",
            "bank_details": {
                "bankgiro": "420-1034",
                "postgiro": "240140-4"
            },
            "activity": "Verksamhet: Blåsmaskiner, kätting, pumpar o luftreningsanläggningar",
            "capital": 75000
        },
        "14": {
            "company_name": "KENWOOD Svenska Thorn AB",
            "pnr": "Bromma 20, Box 20075. Bällstav 34-36",
            "phone_number": "08-98 19 10",
            "bank_details": {
                "bankgiro": "724-9568",
                "postgiro": "55202-6"
            },
            "activity": "Verksamhet: Marknadsför Kenwood hush ållsm aski n er",
            "capital": 100000,
            "key_personnel": [
                {
                    "name": "Lars Ljunggren",
                    "position": "Verkst dir"
                }
            ]
        },
        "15": {
            "company_name": "KERAMISKA MEDDELANDEN",
            "pnr": "137 00",
            "address": "Västerhaninge, Ringv 62",
            "phone_number": "0750-210 35",
            "bank_details": {
                "bankgiro": "508-3001",
                "postgiro": "508300-1"
            },
            "activity": "Verksamhet: Utger tidskriften Scandinavian Ceramic Communications",
            "key_personnel": [
                {
                    "name": "Keram-ing Erk Burton",
                    "position": "Utgivare"
                }
            ],
            "establishment_year": 1966
        },
        "16": {
            "company_name": "KERAM.KONSULT, ING ENIURSF IRMA",
            "pnr": "137 00",
            "address": "Västerhaninge, Ringv 62",
            "phone_number": "0750-210 35",
            "bank_details": {
                "bankgiro": "508-3001",
                "postgiro": "508300-1"
            },
            "activity": "Verksamhet: Krukmakeri. Konsult. Utger Keramiska Meddelanden",
            "dotterbolag": "Erk-krukmakare",
            "establishment_year": 1964
        },
        "17": {
            "company_name": "VENTILATIONSTEKNIK, AB",
            "pnr": "54100",
            "address": "Skövde, Fabriksg 3",
            "phone_number": "0500-340 00",
            "bank_details": {
                "bankgiro": "365-0116",
                "postgiro": "75320-2"
            },
            "activity": "Verksamhet: Ventilationsentreprenader. Tillverkar o säljer produkter inom ventilationsbranschen",
            "resellers": "Ingenjörsfirman Sefovent AB, Box 9006. 550 09 Jönköping 9"
        }
    }
}