{
    "original": "ÅMELLSMÖBLER AB\n\nPnr 15010\n\nGnesta. Tel 0158-104 40, 10140.\nBankgiro 283-8597. Postgiro\n287300-8\n\nVerksamhet: Tillverkar o säljer\nmöbler i gammal stil\nAntal anställda: 30\nÅrsomsättning: 1600 000\nAktiekapital: 300 000\nVerkst dir. Nils Lundström\nEtableringsår: 1945.\n\nCONNER, C\n\nPnr 16142\n\nBromma, Morav 25. Tel 08-26 16 11.\nTga Connerkid\n\nVerksamhet: Agentur för hudar o\nskinn en gros\nÅrsomsättning: 3 000000\nÄgare o chef: C Conner\nEtableringsår: 1954.\n\nARNEK ANNONSBYRÅ AB\n\nPnr 59101\n\nMotala 1, Box 18. Stjärnorpsg 5.\nTel 0141-160 20. Postgiro 165354-2\nVerksamhet: Auktoriserad\nreklamkonsult - Av TU nominerad\nannonsförmedlare\nAntal anställda: 32\nÅrsomsättning: 10000 000\nAktiekapital: 300000\nStyrelse: Adv Arnold Andersson\n(ordf), dir Olle Flodin, fru\nMargaretha Arnek-Nerelius\nVerkst dir: Olle Flodin\nEtableringsår: 1945.\n\nHUSBERGS EFTR, A\n\nPnr 753 32\n\nUppsala, Svartbäcksg 19. Tel\n018-1309 94\n\nVerksamhet: Repvaror, båttillbehör,\nfiskredskap o vapen\nFilial: Västerås, Kungsg 4. Tel\n021-130107\n\nÄgare o chef: Henry Karlbom\nEtableringsår: 1870.\n\nTOVERUMS BRUK, AB\n\nPnr 598 00\n\nVimmerby, Stora Torget 2. Box\n118. Tel 0492-121 25. Bankgiro\n857-5151. Postgiro 274701-2\nVerksamhet: Sågverksrörelse o\nskogsbruk\n\nAntal anställda: 100\nÅrsomsättning: 7 000 000\nAktiekapital: 70 000\nVerkst dir: Ake Peterson\nEtableringsån 1735.\n\nMARKSTROM &amp; CO AB\n\nPnr 57014\n\nNye, Farstorp. Tel 0383-800 04.\nBankgiro 28-9700. Postgiro 72767\nVerksamhet: Tillverkar stolar,\nkarmstolar o fåtöljer\nAntal anställda: 28\nAktiekapital: 70 000\nVerkst dir: Harald B V Dahlberg\nEtableringsår: 1899\nOmbildat till aktiebolag 1936.\n\nMARKSTROMS GULDSMEDS\nAB, K G\n\nPnr 75104\n\nUppsala 1, Box 165. Svartbäcksg6.\nTel 018-14 90 35. Bankgiro\n230-0085. Postgiro 37417-7\nVerksamhet: Tillverkar o säljer\nguldsmedsvaror\nAntal anställda: 48\nÅrsomsättning: 7 200 000\nVerkst dir: Ulf Danielsson\nEtableringsår: 1849.\n\nBRU\n\nBRUUN,AB J\n\nPnr 38100\n\nKalmar, S Långg 10. Tel\n0480-15100. Tga Bruun\nVerksamhet: Spannmål, foder- o\ngödningsämnen, kemikalier m m.\nByggnadsvaror. Lantbruksmaskiner\nAvdelningskontor: Bergkvara. Tel\n0486-202 19\n\nBorgholm, Hamnv. Tel 0485-113 90\nEksjö, Stora Torget 2. Tel\n0381-10161\n\nJönköping, O Strandg. Tel\n036-1196 90\n\nKarlskrona, pa Torskors. Tel\n0455-235 50\n\nMörbylånga. Tel 0485-400 83\nOskarshamn. Tel 0491-14150\nSävsjö, V Järnvägsg. Tel\n0382-100 23\n\nTidaholm, Marbog. Tel 0502-123 40\nTranås, Nyg 9. Tel 0140-101 25\nVetlanda, Magasinsg 11. Tel\n0383-13040\n\nVimmerby. Tel 0492-100 48\nVästervik, Bredg 7. Tel 0490-103 33\nVäxjö. Tel 0470-224 80\nAntal anställda: 387\nAktiekapital: 5 400 000\nStyrelse: Adv Töre Högsell (ordf),\nbankdir Torsten Blennow, konsul\nRolf Bruun, lektor Helge Bruun,\ndir Gunnar Busck, disp Per L\nCarlsson, disp Ivar Lundberg\nVerkst dir: Rolf Bruun\nEtableringsår. 1871\nOmbildat till aktiebolag 1905.\n\nBRUSAFORS-HALLEFORS, AB\n\nPnr 570 85\n\nSilverdalen. Tel 0495-404 00.\nBankgiro 446-6066. Postgiro\n15115-9. TgaHebe, Hultsfred.\nTelex 3929 HEBE S\nVerksamhet: Tillverkar papper,\nsulfit- o slipmassa, sågade\nträvaror, papperspåsar, plastprodukter m m\nAntal anställda: 750\nÅrsomsättning: 65 000 000\nAktiekapital: 10 000 000\nStyrelse: Dir Matts Carlgren (ordf),\nfil dr Ragnar Kempe, dir Bengt\nLyberg, dir Wilhelm Peppler,\nbankdir Gösta Olson\nVerkst dir: Bengt Lyberg\nEtableringsår: 1903.\n\nSUNDIN AB, TRYGGVE\n\nPnr 114 57\n\nStockholm, Riddarg 23 A. Tel\n08-63 03 60. Bankgiro 572-9405.\nPostgiro 57521-7. Tga Trysun.\nTelex 10475\n\nVerksamhet: Agenturfirma. Tele-,\nelektronik- o elektriska\nkomponenter\n\nChef: Tryggve Sundin\nEtableringsår: 1927.\n\nSTÄDCENTRALEN, AB\n\nPnr 102 44\n\nStockholm 5, Grev Tureg 26. Box\n5158. Tel 08-63 13 50. Bankgiro\n16-1024. Postgiro 59253\nVerksamhet: Entreprenadstädning\nAntal anställda: 2 200\nAktiekapital: 300 000\nStyrelse: Dir Louis R Angleryd\nVerkst dir: Civiling Bruno H\nLinder\n\nEtableringsår: 1940\n\nDotterbolag: Städkompaniet AB.\n\nSTÄDERNAS VAKT AB\n\nPnr 852 30\n\nSundsvall. Huvudkontor Storg 1.\nTel 060-15 07 05\n\nSTÄDERNAS VAKT\n\nETT SECURITAS-FÖRETAG\n\nVerksamhet: Bevakning\nEkonomiavdelning: Malmö. Tel\n040-745 00. Bankgiro 56-7622.\nPostgiro 193335\nAktiekapital: 500 000\nÅrsomsättning: 28 000 000\nVerkst dir: Hj Stenbeck\nFöretagschef: Dir Gustav\nLudvigsson\n\nEtableringsår: 1943.\n\nTHULINVERKEN, AB\n\nPnr 26102\n\nLandskrona 2, Pack. Mariebergsg\n11. Tel 0418-16280. Bankgiro\n26-0053. Postgiro 32749. Tga\nThulinverken. Telex 72416\nVerksamhet: Mekanisk verkstad\nför tillverkning av utrustningar\nför järnvägs- o vägfordon,\nfjädrande hjul för rälsfordon samt\nmaskiner o maskindelar\nAntal anställda: 300\nÅrsomsättning: 18 000 000\nAktiekapital: 1200 000\nStyrelse: Bankdir Axel Roos (ordf),\ndir Carl-Axel Nilsson, bruksdisp\nLars De Geer, dir Carl-Sigvard\nRoos, dir Stig Törnebohm, adv Ake\nWettermark\n\nVerkst dir: Stig Törnebohm\nPlatschef: Dir Sture Söderström\nFörsäljningsavd: Ing K-E Embro\n(allm maskinarb)\nInköpsavd: Ing Göte Stensmyr\nEtableringsår: 1915\nÄges av Svenska AB\nBromsregulator.\n\nTULLBERG, AB HASSE W\n\nPnr 10531\n\nStockholm, Vasag 16. Tel\n08-22 95 00, 22 95 40. Tga\nBlankettförlag. Telex 1598\nFörlagschef: Paul Troborg\nEtableringsår: 1871\nAnslutet till Esselte Öbergs AB.\n\nTULLBERG, AB R S\n\nPnr 264 00\n\nKlippan, Storg 47. Box 30. Tel\n0435-120 80. Bankgiro 65-7202.\nPostgiro 10199\n\nVerksamhet: Boktryck, offset,\nståltryck o bokbinderi\nFilial: Stockholm SO, Bellmansg\n27. Tel 08-43 63 82\nAntal anställda: 90\nÅrsomsättning: 7 000 000\nAktiekapital: 200 000\nStyrelse: Disp Malte Nytzén (ordf),\ndir Anders Davidson. ing Bo\nTullberg, disp Gösta Tullberg\nVerkst dir: Disp Gösta Tullberg\nEtableringsår: 1909\nOmbildat till aktiebolag 1924.\n\nTULLHOLMENS AB\n\nPnr 65105\n\nKarlstad 1, Sågverksg 61. Box 334.\nTel 054-1178 35, 1178 81.\nBankgiro 100-1338. Postgiro 331609-8.\nTga Tullholmo\n\nVerksamhet: Tillverkar\nvindstrappor o inredningssnickerier\nVarunamn: Columbitrappan,\nTH-Trappan\n\nAntal anställda: 10\nÅrsomsättning: 1000000\nAktiekapital: 320 000\nVerkst dir: Disp Karl-Erik Englén\nEtableringsår: 1947.",
    "structured": {
        "1": {
            "company_name": "ÅMELLSMÖBLER AB",
            "pnr": "15010",
            "address": "Gnesta",
            "phone_number": "0158-104 40, 10140",
            "bank_details": {
                "bankgiro": "283-8597",
                "postgiro": "287300-8"
            },
            "activity": "Tillverkar o säljer möbler i gammal stil",
            "employees": 30,
            "annual_turnover": 1600000,
            "capital": 300000,
            "key_personnel": [
                {
                    "name": "Nils Lundström",
                    "position": "Verkst dir"
                }
            ],
            "establishment_year": 1945
        },
        "2": {
            "company_name": "CONNER, C",
            "pnr": "16142",
            "address": "Bromma, Morav 25",
            "phone_number": "08-26 16 11",
            "activity": "Agentur för hudar o skinn en gros",
            "annual_turnover": 3000000,
            "key_personnel": [
                {
                    "name": "C Conner",
                    "position": "Ägare o chef"
                }
            ],
            "establishment_year": 1954
        },
        "3": {
            "company_name": "ARNEK ANNONSBYRÅ AB",
            "pnr": "59101",
            "address": "Motala 1, Box 18, Stjärnorpsg 5",
            "phone_number": "0141-160 20",
            "postgiro": "165354-2",
            "activity": "Auktoriserad reklamkonsult - Av TU nominerad annonsförmedlare",
            "employees": 32,
            "annual_turnover": 10000000,
            "capital": 300000,
            "key_personnel": [
                {
                    "name": "Adv Arnold Andersson",
                    "position": "Styrelse (ordf)"
                },
                {
                    "name": "Olle Flodin",
                    "position": "Verkst dir"
                },
                {
                    "name": "fru Margaretha Arnek-Nerelius",
                    "position": "Styrelse"
                }
            ],
            "establishment_year": 1945
        },
        "4": {
            "company_name": "HUSBERGS EFTR, A",
            "pnr": "753 32",
            "address": "Uppsala, Svartbäcksg 19",
            "phone_number": "018-1309 94",
            "activity": "Repvaror, båttillbehör, fiskredskap o vapen",
            "filial": "Västerås, Kungsg 4, Tel 021-130107",
            "key_personnel": [
                {
                    "name": "Henry Karlbom",
                    "position": "Ägare o chef"
                }
            ],
            "establishment_year": 1870
        },
        "5": {
            "company_name": "TOVERUMS BRUK, AB",
            "pnr": "598 00",
            "address": "Vimmerby, Stora Torget 2, Box 118",
            "phone_number": "0492-121 25",
            "bank_details": {
                "bankgiro": "857-5151",
                "postgiro": "274701-2"
            },
            "activity": "Sågverksrörelse o skogsbruk",
            "employees": 100,
            "annual_turnover": 7000000,
            "capital": 70000,
            "key_personnel": [
                {
                    "name": "Ake Peterson",
                    "position": "Verkst dir"
                }
            ],
            "establishment_year": 1735
        },
        "6": {
            "company_name": "MARKSTROM & CO AB",
            "pnr": "57014",
            "address": "Nye, Farstorp",
            "phone_number": "0383-800 04",
            "bank_details": {
                "bankgiro": "28-9700",
                "postgiro": "72767"
            },
            "activity": "Tillverkar stolar, karmstolar o fåtöljer",
            "employees": 28,
            "capital": 70000,
            "key_personnel": [
                {
                    "name": "Harald B V Dahlberg",
                    "position": "Verkst dir"
                }
            ],
            "establishment_year": 1899,
            "ombildat_till_aktiebolag_year": 1936
        },
        "7": {
            "company_name": "MARKSTROMS GULDSMEDS AB, K G",
            "pnr": "75104",
            "address": "Uppsala 1, Box 165, Svartbäcksg6",
            "phone_number": "018-14 90 35",
            "bank_details": {
                "bankgiro": "230-0085",
                "postgiro": "37417-7"
            },
            "activity": "Tillverkar o säljer guldsmedsvaror",
            "employees": 48,
            "annual_turnover": 7200000,
            "key_personnel": [
                {
                    "name": "Ulf Danielsson",
                    "position": "Verkst dir"
                }
            ],
            "establishment_year": 1849
        }
    }
}