{
    "original": "JANSSON, AB KLAES\n\nPnr 10129\n\nStockholm 1, Bryggarg 3. Box 648.\nTel 08-10 79 19, 10 79 91. Bankgiro\n\n563-4886. Postgiro 51367-1\nVerksamhet: Glassliperi,\nspegelfabrik, glashandel engros\nAktiekapital: 45 000\nVerkst dir: Erik Jansson\nEtableringsår. 1899.\n\nJANSON AB,\nAUTOMOBIL-FIRMA RAGNAR\n\nPnr 43102 Mölndal 2\nGöteborg. Kaserntorget 9. Box\n2024. Mölndal 2. Tel 031-17 48 90.\nBankgiro 505-7732. Postgiro\n46975-9. Tga Bilraja\nVerksamhet: Bilförsäljning,\nreservdelsförsäljning o bilreparationer.\nSäljer båtar o båtmotorer samt\nreparerar motorer\n\nFilialer: Göteborg H, Virvelvindsg\n6. Tel 031-51 15 04\nMölndal, Göteborgsv 133. Tel\n031-17 48 90\n\nAntal anställda: 114\nÅrsomsättning: 16300 000\nAktiekapital: 180 200\nStyrelse: Kapten Carol Wallenberg\n(ordf), dir Leif Janson, dir Orvar\nJanson, dir Lennart Sundborn\nVerkst dir: Lennart Sundborn\nEtableringsår: 1941.\n\nJANSSON &amp; CO AB,\nBYGGNADSFIRMAN SVEN\n\nPnr 810 65\n\nSkärplin ge, Box 1251. Tel\n0294-21108. Bankgiro 80-6012. Postgiro\n343956\n\nVerksamhet: Husbyggnader\nAntal anställda: 60\nÅrsomsättning: 4000000\nAktiekapital: 20000\nVerkst dir: Byggmäst Sven Jansson\nEtableringsår: 1955.\n\nJANSSONS JÄRNHANDEL,\nAB TH\n\nPnr 815 01\n\nTierp 1. Järnvägsesplanaden 9.\nBox 45. Tel 0293-114 40. Bankgiro\n236-2028. Postgiro 27749-1.\nTga Järnbolaget\nVerksamhet: Säljer järn- o\nstålvaror, verktyg, handredskap m m\nAntal anställda: 25\nÅrsomsättning: 4 200 000\nAktiekapital: 300 000\nVerkst dir: Carl Lundhammar\nEtableringsår: 1902.\n\nWRETMANS BOKTRYCKERI AB\n\nPnr 753 22\n\nUppsala, O Agatan 33. Tel\n018-1000 60. Bankgiro 233-8077.\nPostgiro 13062-5\n\nVerksamhet: Böcker, broschyrer,\ntidskrifter o affärstryck\nAntal anställda: 12\nAktiekapital: 75 000\nVerkst dir: Boktr Simon Tofters\nEtableringsår: 1889.\n\nEWEMASKINER, AB\n\nPnr 150 13\n\nTrosa, Nyängsv. Tel 0156-128 90.\nTga Ewetorkar\n\nVerksamhet: Tillverkar\nvirkestorkar, juster- o sorterverk\nAntal anställda: 40\nÅrsomsättning: 5 000 000\n\nAktiekapital: 90 000\nStyrelse: E H Wickman, G\nWickman\n\nVerkst dir: G Wickman\nEtableringsår: 1936\nOmbildat till aktiebolag 1944.\n\nEWERS AB, ERIC\n\nPnr 102 52\n\nStockholm 27, Valhallav 184. Box\n27192. Tel 08-63 53 20. Tga\nEwers-textil. Telex 10765\nVerksamhet: Möbel- o gardintyg,\nmattor i parti\n\nFilialer Göteborg C, Vasag43 A.\nTel 031-18 53 98, 18 53 99\nMalmö C, Gustav Adolfs torg 10.\nTel 040-128832, 128932\nAktiekapital: 300 000\nVerkst dir: Erie Ewers jr\nEtableringsår: 1946.\n\nBACKMANS VERKSTÄDER, AB\n\nPnr 710 73\n\nHögforsbruk, Box 25. Tel 05 80-\n\n220 01, 220 25. Bankgiro 81-9858.\nPostgiro 643354\nVerksamhet: Konstruktion,\ntillverkning o montage av\nsiloanläggningar kompletta med i- o\nurlast-ningasanordningar. Tillverkning\nav järn o plåtkonstruktioner samt\nmaskinbearbetningar, svarvar upp\ntill 3 m:s diameter\nFilialverkstad: Falun. Tel\n023-33125\n\nAntal anställda: 50\nÅrsomsättning: 4 500 000\nAktiekapital: 50 000\nVerkst dir: Fru G Backman\nEtableringsår: 1963.\n\nBACKMAN-EDGREN-JANSSON\nAB, ARKITEKTFIRMAN\n\nPnr 681 00\n\nKristinehamn, Trädgårdsg 8. Tel\n0550-154 60. Bankgiro 110-1344.\nPostgiro 580674-1\nVerksamhet: Utför projektering av\nhusbyggnader\nAntal anställda: 7\nÅrsomsättning: 700000\nAktiekapital: 15 000\nVerkst dir: Ing Ivar Backman\nEtableringsår: 1961.\n\nGOTLANDS TIDNINGAR AB\n\nPnr 621 01\n\nVisby 1, Specksrum 5. Box 21. Tel\n0498-152 3 0. Bankgiro 355-7469.\nPostgiro 1894 90-6\nVerksamhet: Tidnings- o\nciviltryckeri. Utger Gotlands Folkblad o\nGotlänningen\nAktiekapital: 250 000\nVerkst dir: Axel Larsson\nEtableringsår: 1957.\n\nFLOSJONS SÅGVERKS AB\n\nPnr 780 44\n\nDala-Floda, Box 27. Tel 0241-\n\n22211. 220 02. Bankgiro 236-7027.\nPostgiro 91662-7\nVerksamhet: Sågade o hyvlade\nträvaror, monteringsfärdiga trähus\nAntal anställda: 15\nÅrsomsättning: 1500000\nAktiekapital: 50 000\nVerkst din Edvin Redhe\nEtableringsår: 1940.\n\nWOJIDKOW &amp; H.K.H. AB. B\n\nPnr 214 50\n\nMalmö. N Grängesbergsg 11. Tel\n040-804 7 5. Bankgiro 87-4339.\nPostgiro 439607. Tga Sprayer\nVerksamhet: Mekanisk verkstad.\nMaskinkonstruktioner samt\nsjukhus-o simhallsbad\nAntal anställda: 40\nÅrsomsättning: 2 500 000\nAktiekapital: 60 000\nVerkst dir: Harry Lundgren.\n\nVOLANDERFüRETAGEN AB\n\nPnr 12162\n\nJohanneshov, Hallv 11. Tel\n08-5903 70. Bankgiro 284-5071.\nPostgiro 294683-8. Tga Vintage\nVerksamhet: Charkuteritillverkning.\nRestaurangrörelse:\nLunchserveringar\n\nAntal anställda: 325\nÅrsomsättning: 30 000 000\nAktiekapital: 360 000\nVerkst dir: Karl Herman Malmström\nMarknadschef: Dir Folke\nBarkvall\n\nEkonomichef: Gunnar Rydström\nKamrer: Hans Geiryd\nEtableringsår: 1931.\n\nSVENSKA KLÄMLAMPAN, AB\n\nPnr 216 63\n\nMalmö, Järnyxeg 12. Tel\n040-94 6005, 94 60 35. Bankgiro\n876-6514. Postgiro 531025-5\nVerksamhet: Tillverkar o säljer\ntillfälliga el-anläggningar för\nbyggnadsindustrin samt olika\nbelysningsarmaturer for bygge o\nindustri. Säljer förbrukningsmaterial\nsåsom kabel, glödlampor,\nsäkringar m m\n\nFörsäljningskontor: 126 06\nHägersten, Box 608. Tel 08-46 1151\nAntal anställda: 7\nÅrsomsättning: 3 000 000\nAktiekapital; 45 000\nVerkst dir. Bengt Olsson\nEtableringsår: 1952.\n\nNORDSTJERNAN, REDERI AB\n\nPnr 103 80\n\nStockholm 7, Stureplan 3. Fack.\nTel 2205 00, riks 08-22 05 20.\nPostgiro 2638. Tga Johnsons.\nTelex 17100 JOHNSON S\nVerksamhet: Upprätthåller\nreguljära sjöfartsförbindelser med\nSydamerika, Centralamerika, Karibiska\nhamnar, Nordamerikas o Kanadas\nvästkust o Hawaii samt mellan\nPersiska Viken o Japan\nAntal anställda: 2 324\nÅrsomsättning: 403 600 000\nAktiekapital: 21000 000\nStyrelse: Hovrättspresident Maths\nHeuman (ordf), dir Allan Björklund,\nbergsing Axel Ax:son Johnson, dir\nBo Ax:son Johnson, dir Per A\nNorlin\n\nVerkst dir: Bergsing Axel Ax:son\nJohnson\n\nEtableringsår: 1890.\n\nDEL\n\nÅrsomsättning: 2800 000\nAktiekapital: 100 000\nEtableringsàr: 1919.\n\nDAWIDSSONS\nMASKIN-AFFÄR AB, G L\n\nPnr 70211\n\nÖrebro, Stortorget 8. Tel\n019-13 64 50. Bankgiro 81-5429.\nPostgiro 9387\n\nVerksamhet: Säljer\nkontorsmaskiner, kontorsmöbler m m\nChef: Roland Dawidsson\nEtableringsàr: 1921.\n\nDAYTON VÄG AB\n\nPnr 11136\n\nStockholm, Holländarg 14. Tel\n08-20 94 95. Bankgiro 483-4149.\nPostgiro 255140\nVerksamhet: Säljer o reparerar\nvågar o kassaregister\nVarunamn: Dayton\nAktiekapital: 10 000\nÄgare o chef: Enar Lindberg\nEtableringsàr: 1934.\n\nDE FÖRENADE\nKOLSYREFABRIKERNAS AB\n\nPnr 100 73\n\nStockholm 44, Box 44029.\nLöv-holmsbrinken 6. Tel 08-19 04 60.\nPostgiro 22208. Tga Kolsyre\nVerksamhet: Tillverkar o säljer\nkolsyra o torr-is\n\nFabriker: Göteborg, von Utfallsg.\nTel 031-2 6 2140\n\nKöping, Box 44. Nya Hamnv. Tel\n0221-197 06\n\nMalmö 30, Box 30042. Limhamnsv\n116. Tel 040-15 8015\nAntal anställda: 100\nÅrsomsättning: 12 000 000\nAktiekapital: 2 280 000\nStyrelseordf: Gunnar Ekman\nVerkst dir Dag Vendil\nDir: Bengt Arve\nEtableringsàr 1900.\n\nDE FÖRENADE\nURMAKARNE, AB\n\nPnr 211 29\n\nMalmö, Stora Kvarng 49 B. Tel\n040-12 85 55, 12 28 08. Bankgiro\n640-3927. Postgiro 24417-8\nVerksamhet: Ur engros\nAntal anställda: 8\nÅrsomsättning: 1300 000\nAktiekapital: 6 000\nVerkst dlr: Erik Wetterstrand\nEtableringsàr: 1962.\n\nDE TRE STÄMPELBOLAGEN I\nSTOCKHOLM AB\n\nPnr 101 20\n\nStockholm 1, Box 25. Ulvsundav\n180. Tel 08-9814 70. Bankgiro\n72-4972. Postgiro 3129\nVerksamhet: Tillverkar o säljer\nstämplar\n\nAntal anställda: 30\nÅrsomsättning: 3 000 000\n\nVerkst dir: Algot Bengtsson\nEtableringsàr: 1921\nOmbildat till aktiebolag 1956.\n\nDEBER-KONTROLL, AB\n\nPnr 18108\n\nLidingö 8, Box 806. Merkuriusv\n\n11 B. Tel 08-766 01 75. Bankgiro\n745-4168. Postgiro 5484-1. Tga\n\nIdess\n\nVerksamhet: Elektroniska\nnivåkontroller o nivåmätare för vätskor,\nfasta ämnen o gaser i vätskeform.\nElektroniska flödesmätare för\nvatten i öppna kanaler. Digitala\ntemperaturmätutrustningar\nVarunamn: Deber\nAntal anställda: 12\nÅrsomsättning: 1500 000\n.Aktiekapital: 5 000\nVerkst dir: Bengt Kamph\nEtableringsàr: 1945.\n\nDECO BOSÄTTNINGS AB\n\nPnr 252 38\n\nHelsingborg, Erik Dahlbergsg 15-17.\nTel 042-1133 55, 12 85 77.Bankgiro\n653-1479. Postgiro 263321-2\nVerksamhet: Keramikfabrik\nAntal anställda: 68\nÅrsomsättning: 2 800 000\nAktiekapital: 40 000\nVerkst dir: Allan Möllerström\nEtableringsàr: 1954.\n\nDEFIBRATOR AB\n\nPnr 102 51\n\nStockholm 27, Sandhamnsg 81. Box\n27073. Tel 08-23 0440. Postgiro\n197771. Telex 19026 DEFIBER S.\nTga Defibrator\n\nVerksamhet: Maskiner o processer\nför tillverkning av massa, papper\no fiberplattor\n\nVerkstäder. 151 02 Södertälje 2,\nHertig Karls v 57. Pack. Tel\n0755-395 40. Telex 102 38 DEVERK S\nAntal anställda: 260\nAktiekapital: 4 000 000\nStyrelse: Tekn dr Arne Asplund\n(ordf), adv Stellan Graaf (v ordf),\ndir Bengt Asplund, dir Gösta\nAsplund, bankdir Bertil Odelfelt,\nbankdir Arne Hedskog\nVerkst dir: Bengt Asplund\nEtableringsàr: 1933.\n\nDEIJENBERG AB, VICTOR\n\nPnr 25006\n\nHelsingborg 6, Box 6012. Drottn\nningg 134. Tel 042-14 2350,\n14 23 51. Tga Deijen\nVerksamhet: Säljer harts, kasein\nm m i parti\nAktiekapital: 270000\nVerkst dir: Victor Deijenberg\nEtableringsàr: 1922.\n\nDEJOVERKEN, AB\n\nPnr 16210\n\nVällingby 1, Krossg 22. Pack. Tel\n08-38 02 65. Tga Dejong\nVerksamhet: Tillverkar vikdörrar,\nnyckelskåp o byggnadsbeslag\nAntal anställda: 20\nAktiekapital: 100000\nVerkst dir: A M de Jong\nEtableringsàr: 1932.\n\nDEKAL-REKLAM\n\nPnr 462 00\n\nVänersborg, Trollv 29. Tel\n0521-162 26. Postgiro 430993\nVerksamhet: Importerar alla slag\nav dekalkomanier\nÄgare o chef: G Zaar\nEtableringsàr: 1950.\n\nDEKÅ, BYGGNADS AB\n\nPnr 28101\n\nHässleholm 1, Box 79. Idrottsv 4.\nTel 0451-142 75. Bankgiro\n866-3551. Postgiro 148215-7\nVerksamhet: Uppför bostads-,\nindustri- o administrationsbyggnader\nAntal anställda: 240\nÅrsomsättning: 30000 000\nAktiekapital: 151200\nVerkst dir: Ing Gösta Kindberg\nEtableringsàr: 1938.\n\nDELBORN AB, CURT\n\nPnr 41109\n\nGöteborg, O Hamng 2. Tel\n031-1108 70. Bankgiro 337-5482.\nPostgiro 523145-1. Tga Delblan\nVerksamhet: Import o export.\nTennfolier\n\nÅrsomsättning: 400 000\nAktiekapital: 10 000\nVerkst dir: Curt Delborn\nEtableringsàr: 1957.\n\nDELINS FASTIGHETS AB\n\nPnr 111 56\n\nStockholm, Kungsg 35. Tel\n08-1108 84, 1108 94. Bankgiro\n56-0454. Postgiro 157235\nVerksamhet: Tomtexploatering samt\nförsäljning av fritidstomter\nAntal anställda: 7\nÅrsomsättning: 1200 000\nAktiekapital: 1050000\nVerkst dir: Göran Delin\nEtableringsàr 1910.",
    "structured": {
        "1": {
            "company_name": "JANSSON, AB KLAES",
            "pnr": "10129",
            "address": "Stockholm 1, Bryggarg 3. Box 648",
            "phone_number": "08-10 79 19, 10 79 91",
            "bank_details": {
                "bankgiro": "563-4886",
                "postgiro": "51367-1"
            },
            "activity": "Glassliperi, spegelfabrik, glashandel engros",
            "capital": 45000,
            "key_personnel": [
                {
                    "name": "Erik Jansson",
                    "position": "Verkst dir"
                }
            ],
            "establishment_year": 1899
        },
        "2": {
            "company_name": "JANSON AB, AUTOMOBIL-FIRMA RAGNAR",
            "pnr": "43102",
            "address": "Göteborg, Kaserntorget 9. Box 2024",
            "phone_number": "031-17 48 90",
            "bank_details": {
                "bankgiro": "505-7732",
                "postgiro": "46975-9"
            },
            "activity": "Bilförsäljning, reservdelsförsäljning o bilreparationer. Säljer båtar o båtmotorer samt reparerar motorer",
            "employees": 114,
            "annual_turnover": 16300000,
            "capital": 180200,
            "key_personnel": [
                {
                    "name": "Kapten Carol Wallenberg",
                    "position": "Styrelse, ordf"
                },
                {
                    "name": "Leif Janson",
                    "position": "dir"
                },
                {
                    "name": "Orvar Janson",
                    "position": "dir"
                },
                {
                    "name": "Lennart Sundborn",
                    "position": "Verkst dir"
                }
            ],
            "establishment_year": 1941
        },
        "3": {
            "company_name": "JANSSON & CO AB, BYGGNADSFIRMAN SVEN",
            "pnr": "810 65",
            "address": "Skärplinge, Box 1251",
            "phone_number": "0294-21108",
            "bank_details": {
                "bankgiro": "80-6012",
                "postgiro": "343956"
            },
            "activity": "Husbyggnader",
            "employees": 60,
            "annual_turnover": 4000000,
            "capital": 20000,
            "key_personnel": [
                {
                    "name": "Byggmäst Sven Jansson",
                    "position": "Verkst dir"
                }
            ],
            "establishment_year": 1955
        },
        "4": {
            "company_name": "JANSSONS JÄRNHANDEL, AB TH",
            "pnr": "815 01",
            "address": "Tierp 1, Järnvägsesplanaden 9. Box 45",
            "phone_number": "0293-114 40",
            "bank_details": {
                "bankgiro": "236-2028",
                "postgiro": "27749-1"
            },
            "activity": "Säljer järn- o stålvaror, verktyg, handredskap m m",
            "employees": 25,
            "annual_turnover": 4200000,
            "capital": 300000,
            "key_personnel": [
                {
                    "name": "Carl Lundhammar",
                    "position": "Verkst dir"
                }
            ],
            "establishment_year": 1902
        },
        "5": {
            "company_name": "WRETMANS BOKTRYCKERI AB",
            "pnr": "753 22",
            "address": "Uppsala, O Agatan 33",
            "phone_number": "018-1000 60",
            "bank_details": {
                "bankgiro": "233-8077",
                "postgiro": "13062-5"
            },
            "activity": "Böcker, broschyrer, tidskrifter o affärstryck",
            "employees": 12,
            "capital": 75000,
            "key_personnel": [
                {
                    "name": "Boktr Simon Tofters",
                    "position": "Verkst dir"
                }
            ],
            "establishment_year": 1889
        }
    }
}