{
    "original": "GEN\n\nAktiekapital: 75 000\nStyrelse: Dir C Georg Th\nDahlberg (ordf), fru Gulli H K\nDahlberg\n\nVerkst dir: C Georg Th Dahlberg\nEtableringsår. 1967.\n\nTHORE. 0 M\n\nPnr 250 03\n\nHelsingborg 3, Box 3045.\nStagne-liusg 3. Tel 042-116812, 117612.\nPostgiro 544274-4. Tga Allians.\nTelex 72212\n\nVerksamhet: Rederirörelse\nVerkst dir Skeppsred O M Thore.\n\nTORELL PUMP AB\n\nPnr 13104\n\nNacka 4, Krokv 12. Box 4034. Tel\n08-716 72 04. Bankgiro 700-4526.\nPostgiro 598870-4. Tga Torellpump,\nStockholm. Telex 10469\nVerksamhet: Försäljer\ncentrifugalpumpar, skruvpumpar, kolvpumpar,\nfläktar, kompressorer,\navstängningsluckor o vattenreningsanläggningar\nAktiekapital: 20 000\nVerkst din Sten Torell\nEtableringsår 1962.\n\nNORRKOPINGS STUVERI AB\n\nPnr 601 03\n\nNorrköping 1, Hospitalsg 75. Box\n108. Tel 011-12 90 80. Bankgiro\n609-9980. Postgiro 363876-4.\nTga Stuveribolaget\nVerksamhet: Lossning o lastning av\nfartyg, båt- o vaktmanstjänst,\nuthyrning av truckar, lastmaskiner,\nmobilkranar o presenningar samt\nwiresplitsning\nAntal anställda: 221\nAktiekapital: 85 000\nStyrelse: Disp Lars Gabrielson\n(ordf), konsul Lars Ringborg, dir\nHans Hök\n\nVerkst dir: Konsul Moody\nKling-ström\n\nEtableringsår: 1907\nDotterbolag: Valdemarsviks\nStuveri AB, Valdemarsvik.\n\nNORRKUPINGS TIDNINGAR\n\nPnr 601 83\n\nNorrköping, Stohagsg 2. Tel\nOHIO 01 40. Bankgiro 125-0729.\nPostgiro 28480-2. Telex 64051\nAvdelningskontor: Finspång,\nKatrineholm, Skärblacka, Söderköping,\nValdemarsvik, Vingåker\nVerkst dir: Lars Thermaenius\nChefred o ansvarig utgivare: Bengt\nLundgren\n\nAnnonschef: Stefan Joëlius\nDistributionschef: Gunnar Olsson\nEkonomichef: Karl Erik Pettersson\nEtableringsår: 1758.\n\nNORRKUPINGS TROTTOAR.\nPLATTFABRIK, AB\n\nPnr 60103\n\nNorrköping 1, Slottsg 33. Box 146.\nTel 011-12 94 85. Bankgiro\n824-5359. Postgiro 95707-6\nVerksamhet: Tillverkar o säljer\ngångbaneplattor o kantsten av\nbetong för beläggning på trottoarer,\nrefuger, takterasser, parker,\nträdgårdar, torg o liknande platser\nAntal anstäUda: 30\nÅrsomsättning: 2 000 000\nAktiekapital: 100 000\nVerkst dir: Georg Larnemark\nEtableringsår: 1927\nOmbildat till aktiebolag 1932.\n\nNORRKUPINGS\nTRÄ-IMPORT AB\n\nPnr 60102\n\nNorrköping 1, Box 32. Slottsg 2-16.\nTel 011-13 44 50. Bankgiro\n609-9998. Postgiro 9917-6. Tga\nTräimport. Telex 64139 TRAEIMP S\nVerksamhet: Handel med råvaror\nav ädelträ samt faner, plywood, lar\nmell- o spånplattor. Tillverkning\nav fanér vid egen fanérfabrik\nAntal anställda: 85\nAktiekapital: 1600 000\nVerkst dir: Arne Haslum\nFörsälj-chef: Sven Ahlström\nEtableringsår: 1923\nDotterbolag till Skandinaviska\nTräimport AB, Stockholm.\n\nNORRKUPINGS VADD.\nINDUSTRI AB\n\nPnr 602 23\n\nNorrköping, Butängsg 32. Tel\nOll-IO 61 50. Bankgiro 125-2618.\nPostgiro 411879-0\n\nVerksamhet: Tillverkar plymåer\nför möbelindustrin\nÄgare o chef: Evert Johansson\nEtableringsår: 1958.\n\nMcCULLOCH SKANDINAVIEN AB\n\nPnr 126 30\n\nHägersten, Elektrav 5. Tel\n08-18 82 55. Bankgiro 663-8001.\nPostgiro 545410-3\n\nVerksamhet: Säljer motorsågar,\nel-svetsar„ go-kartmotorer\nVarunamn: McCULLOCH\nAntal anställda: 15\nÅrsomsättning: 4 000 000\nAktiekapital: 25 000\nVerkst dir: Jan van Tuyl\nEtableringsår: 1967.\n\nFULCRUM AB\n\nPnr 11436\n\nStockholm, S tur eg 34. Tel\n08-2319 05. Postgiro 151259.\nTga Fulcrum. Telex 1885\nVerksamhet: Bankirrörelse\nAntal anställda: 10\nAktiekapital: 9 000 000\nStyrelse: Prof HugoTheorell (ordf),\ndir K Birger Strid, dir Hans\nWesterlund\n\nVerkst dir: K Birger Strid\nV verkst dir: Hans Westerlund\nEtableringsår: 1935.\n\nKULL AB, ÅKE\n\nPnr 400 14\n\nGöteborg 53, Box 53021. Tel\n031-81 33 30. Bankgiro 491-3141.\nPostgiro 722657-4. Tga Kullab.\nTelex 20685 KULLAB S\nVerksamhet: Agenturer för\nutländska stålverk o ventiler\nAktiekapital: 25 000\nVerkst dir: Ake Kull\nEtableringsår: 1961.\n\nMADESJU-NYBRO SPARBANK\n\nPnr 382 00\n\nNybro, Box 85. N Stationsg 2. Tel\nTel 0481-119 60. Bankgiro\n981-2116. Postgiro 143500-7\nVerksamhet: Bankrörelse\nAntal anställda: 37\nVerkst din Nils Eriksson\nKamrerare: Birger Bolander,\nKarl-Gunnar Johansson, Bertil Telö\nEtableringsår 1870.\n\nDALA-FLODA SNICKERI AB\n\nPnr 780 44\n\nDala-Floda, Box 613. Tel\n0241-223 50. Bankgiro 236-7068.\nPostgiro 99780-9\n\nVerksamhet: Tillverkar\nbostadsinredning, kartongförpackade skåp\nAntal anställda: 80\nÅrsomsättning: 8 000 000\nAktiekapital: 300 000\nVerkst dir: Holger Arnberg\nEtableringsår: 1945.\n\nLINDGREN &amp; CO AB, STIG\n\nPnr 653 41\n\nKarlstad,Kolvg 3. Tel 054-115730.\nBankgiro 100-3110. Postgiro\n262811-3\n\nVerksamhet: Säljer frukt o\ngrönsaker i parti\nAntal anställda: 40\nÅrsomsättning: 7 000 000\nAktiekapital: 75 000\nStyrelseordf: Dir Stig Lindgren\nEtableringsår: 1937\nOmbildat till aktiebolag 1967.\n\nLINDHOLM PLASTICS AB\n\nPnr 162 40\n\nVällingby, Brändöv 3-7. Tel\n08-38 1215, 38 04 94. Bankgiro\n74-5112. Postgiro 270153\nVerksamhet: Tillverkar tekniska\nindustridetaljer i termoplastiska o\nhärdbara material\nAntal anställda: 8\nÅrsomsättning: 700 000\nAktiekapitel: 100 000\nVerkst dir: Ing Per-Olof Lindholm\nEtableringsår: 1947\nOmbildat till aktiebolag 1963.\n\nLINDHOLM RIT.\nINSTRUMENT AB\n\nPnr 12172\n\nJohanneshov, Järnlundsv 1. Tel\n08-18 32 00, 19 8010. Bankgiro\n74-4705. Postgiro 51099\nVerksamhet: Tillverkar o säljer\nritinstrument av egen tillverkning\nAntal anställda: 12\nÅrsomsättning: 300 000\nAktiekapital: 20 000\nVerkst dir: Sven E Fröde\nEtableringsår: 1851.\n\nGREAT LAKES SALES AB\n\nPnr 701 06\n\nUrebro 1, Box 458. Tel\n019-14 81 10, 14 81 11. Postgiro\n715420-6. Telex 73221\nVerksamhet Säljer\ngrafitelektroder, grafitanoder, grafitdetaljer o\ngrafitpulver\nAktiekapital: 24 000\nStyrelse: Dir Arend M Versteegh\n\n(ordf), mr M A Wrotniak, dir\nGunnar Dahlén\nVerkst dir: C M Peterson\nFörsäljningschef: Bergsing Roland\nWiestål\n\nEtableringsår: 1970.",
    "structured": {
        "0": {
            "company_name": "Thore Rederirörelse",
            "establishment_year": 1967,
            "activity": "Rederirörelse",
            "capital": 75000,
            "key_personnel": [
                {
                    "name": "Dir C Georg Th Dahlberg",
                    "position": "Styrelse/VD"
                }
            ]
        },
        "1": {
            "company_name": "Torell Pump AB",
            "establishment_year": 1962,
            "activity": "Försäljer centrifugalpumpar, skruvpumpar, kolvpumpar, fläktar, kompressorer, avstängningsluckor o vattenreningsanläggningar",
            "capital": 20000,
            "key_personnel": [
                {
                    "name": "Verkst din Sten Torell",
                    "position": "Verkst dir"
                }
            ]
        },
        "2": {
            "company_name": "Norrkopings Stuveri AB",
            "establishment_year": 1907,
            "activity": "Lossning o lastning av fartyg, båt- o vaktmanstjänst, uthyrning av truckar, lastmaskiner, mobilkranar o presenningar samt wiresplitsning",
            "capital": 85000,
            "employees": 221,
            "key_personnel": [
                {
                    "name": "Disp Lars Gabrielson",
                    "position": "Styrelse/VD"
                },
                {
                    "name": "konsul Lars Ringborg",
                    "position": "Styrelse"
                },
                {
                    "name": "dir Hans Hök",
                    "position": "Styrelse"
                },
                {
                    "name": "Konsul Moody Kling-ström",
                    "position": "Verkst dir"
                }
            ]
        },
        "3": {
            "company_name": "Norrkopings Tidningar",
            "establishment_year": 1758,
            "activities": {
                "Norrköping": "Stohagsg 2",
                "Avdelningskontor": "Finspång, Katrineholm, Skärblacka, Söderköping, Valdemarsvik, Vingåker"
            },
            "key_personnel": [
                {
                    "name": "Lars Thermaenius",
                    "position": "Verkst dir"
                },
                {
                    "name": "Bengt Lundgren",
                    "position": "Chefred o ansvarig utgivare"
                },
                {
                    "name": "Stefan Joëlius",
                    "position": "Annonschef"
                },
                {
                    "name": "Gunnar Olsson",
                    "position": "Distributionschef"
                },
                {
                    "name": "Karl Erik Pettersson",
                    "position": "Ekonomichef"
                }
            ]
        },
        "4": {
            "company_name": "Norrkopings Trottoar Plattfabrik AB",
            "establishment_year": 1927,
            "activity": "Tillverkar o säljer gångbaneplattor o kantsten av betong för beläggning på trottoarer, refuger, takterasser, parker, trädgårdar, torg o liknande platser",
            "capital": 100000,
            "employees": 30,
            "annual_turnover": 2000000,
            "key_personnel": [
                {
                    "name": "Georg Larnemark",
                    "position": "Verkst dir"
                }
            ]
        },
        "5": {
            "company_name": "Norrkopings Trä-Import AB",
            "establishment_year": 1923,
            "activity": "Handel med råvaror av ädelträ samt faner, plywood, larmell- o spånplattor. Tillverkning av fanér vid egen fanérfabrik",
            "capital": 1600000,
            "employees": 85,
            "key_personnel": [
                {
                    "name": "Arne Haslum",
                    "position": "Verkst dir"
                },
                {
                    "name": "Sven Ahlström",
                    "position": "Försälj-chef"
                }
            ],
            "parent_company": "Skandinaviska Träimport AB, Stockholm"
        },
        "6": {
            "company_name": "Norrkopings Vadd Industri AB",
            "establishment_year": 1958,
            "activity": "Tillverkar plymåer för möbelindustrin",
            "key_personnel": [
                {
                    "name": "Evert Johansson",
                    "position": "Ägare o chef"
                }
            ]
        },
        "7": {
            "company_name": "McCulloch Skandinavien AB",
            "establishment_year": 1967,
            "activity": "Säljer motorsågar, el-svetsar, go-kartmotorer",
            "capital": 25000,
            "employees": 15,
            "annual_turnover": 4000000,
            "key_personnel": [
                {
                    "name": "Jan van Tuyl",
                    "position": "Verkst dir"
                }
            ]
        },
        "8": {
            "company_name": "Fulcrum AB",
            "establishment_year": 1935,
            "activity": "Bankirrörelse",
            "capital": 9000000,
            "employees": 10,
            "key_personnel": [
                {
                    "name": "Prof HugoTheorell",
                    "position": "Styrelseordf"
                },
                {
                    "name": "K Birger Strid",
                    "position": "Verkst dir/V verkst dir"
                },
                {
                    "name": "Hans Westerlund",
                    "position": "V verkst dir"
                }
            ]
        },
        "9": {
            "company_name": "Kull AB, Åke",
            "establishment_year": 1961,
            "activity": "Agenturer för utländska stålverk o ventiler",
            "capital": 25000,
            "key_personnel": [
                {
                    "name": "Ake Kull",
                    "position": "Verkst dir"
                }
            ]
        },
        "10": {
            "company_name": "Madesju-Nybro Sparbank",
            "establishment_year": 1870,
            "activity": "Bankrörelse",
            "employees": 37,
            "key_personnel": [
                {
                    "name": "Nils Eriksson",
                    "position": "Verkst din"
                },
                {
                    "name": "Birger Bolander",
                    "position": "Kamrerare"
                },
                {
                    "name": "Karl-Gunnar Johansson",
                    "position": "Kamrerare"
                },
                {
                    "name": "Bertil Telö",
                    "position": "Kamrerare"
                }
            ]
        },
        "11": {
            "company_name": "Dala-Floda Snickeri AB",
            "establishment_year": 1945,
            "activity": "Tillverkar bostadsinredning, kartongförpackade skåp",
            "capital": 300000,
            "employees": 80,
            "annual_turnover": 8000000,
            "key_personnel": [
                {
                    "name": "Holger Arnberg",
                    "position": "Verkst dir"
                }
            ]
        },
        "12": {
            "company_name": "Lindgren & Co AB, Stig",
            "establishment_year": 1937,
            "activity": "Säljer frukt o grönsaker i parti",
            "capital": 75000,
            "employees": 40,
            "annual_turnover": 7000000,
            "key_personnel": [
                {
                    "name": "Stig Lindgren",
                    "position": "Styrelseordf"
                }
            ]
        },
        "13": {
            "company_name": "Lindholm Plastics AB",
            "establishment_year": 1947,
            "activity": "Tillverkar tekniska industridetaljer i termoplastiska o härdbara material",
            "capital": 100000,
            "employees": 8,
            "annual_turnover": 700000,
            "key_personnel": [
                {
                    "name": "Ing Per-Olof Lindholm",
                    "position": "Verkst dir"
                }
            ]
        },
        "14": {
            "company_name": "Lindholm Rit. Instrument AB",
            "establishment_year": 1851,
            "activity": "Tillverkar o säljer ritinstrument av egen tillverkning",
            "capital": 20000,
            "employees": 12,
            "annual_turnover": 300000,
            "key_personnel": [
                {
                    "name": "Sven E Fröde",
                    "position": "Verkst dir"
                }
            ]
        },
        "15": {
            "company_name": "Great Lakes Sales AB",
            "establishment_year": 1970,
            "activity": "Säljer grafitelektroder, grafitanoder, grafitdetaljer o grafitpulver",
            "capital": 24000,
            "key_personnel": [
                {
                    "name": "Arend M Versteegh",
                    "position": "Styrelseordf"
                },
                {
                    "name": "M A Wrotniak",
                    "position": "Styrelse"
                },
                {
                    "name": "Gunnar Dahlén",
                    "position": "Styrelse"
                },
                {
                    "name": "C M Peterson",
                    "position": "Verkst dir"
                },
                {
                    "name": "Bergsing Roland Wiestål",
                    "position": "Försäljningschef"
                }
            ]
        }
    }
}