{
    "original": "LIN\n\nLINKOPIA EK FOR\n\nPnr 581 84\n\nLinköping, Roxeng 11. Tel\n013-102440. Bankgiro 120-5111.\nPostgiro 498335-9.\nTelex 64924 LINCOOP S\nVerksamhet Fotolaboratorium,\nengroshandel, finansinstitut\nAntal anställda: 330\nÅrsomsättning: 45 000 000\nAndelskapital: 3 200 000\nVerkst dir: Sven-Eric Egerborn\nEtableringsår: 1956.\n\nLINKÖPINGS\nAUTO-ELEK-TRISKA GUSTAFSSON &amp; CO\n\nPnr 58103\n\nLinköping 1, Bantorget 1. Box 352.\nTel 013-12 72 09, 12 77 09.\nBankgiro 120-0468. Postgiro 279527-6\nVerksamhet: Försäljning o\nreparation av elektr detaljer för bil o\nflyg, diesel-, el-handverktyg,\nbil-värmare. Specialitet: Bosch service.\nAntal anställda: 10\nÅrsomsättning: 1100 000\nChef: Köpman S Arne Gustafsson\nEtableringsår: 1945.\n\nLINKÖPINGS BYGGNADS.\nMATERIAL, AB\n\nPnr 58102\n\nLinköping 1, Sveag 4. Box 138.\nTel 013-129130. Bankgiro\n120-0450. Postgiro 77844-9\nVerksamhet: Säljer\nbyggnadsmaterial, trävaror o snickerier\nAntal anställda: 6\nÅrsomsättning: 2 700 000\nAktiekapital: 45 000\nStyrelse: Byggn-ing Helge Netz\n(crdf), kamrer Stig Johansson\nVerkst dir: Stig Johansson\nEtableringsår: 1931.\n\nLINKÖPINGS EXPRESS &amp;\nORDERCENTRAL AB\n\nPnr 581 03\n\nLinköping 1, Box 337. Rudsjög 1.\nTel 013-13 0100. Bankgiro\n607-8208. Postgiro 27992-7\nVerksamhet: Lastbilsåkeri.\nLevererar grus från egna grustag\nAntal anställda: 105\nÅrsomsättning: 12 000 000\nAktiekapital: 300 000\nVerkst dir: Yngve Lundell\nEtableringsår: 1950.\n\nLINKÖPINGS FORNICKLINGS\nAB NICRO\n\nPnr 58102\n\nLinköping 1, Kolfallsg 8. Box 13.\nTel 013-12 8123, 12 23 65.\nBankgiro 346-9574. Postgiro 334714-3\nVerksamhet: Elektrogalvanisk\nytbehandling. Specialitet: automat\nförzinkning\n\nFilial: Tranås, Hörng 1. Tel\n0140-114 84\n\nAntal anställda: 25\nÅrsomsättning: 2 000 000\nChef: Uno Nordén.\n\nLINKÖPINGS KARTONG.\nINDUSTRI\n\nPnr 582 25\n\nLinköping, Drottningg 1. Tel\n013-12 29 68, 12 29 86. Bankgiro 120-\n\n5319. Postgiro 85660-9. Tga\nKartongindustri\n\nVerksamhet: Tillverkar emballage\nför industri o affärer, såväl finare\nsom grövre\n\nChefer: Fabr Gösta Liwell, fabr\nKarl E Liwell\nEtableringsår: 1933.\n\nLINKOPJNGS KYLARE.\nFABRIK AB\n\nPnr 580 03\n\nLinköping 3, Barhällsg 10. Box\n3080. Tel 013-13 05 00, 14 0100.\nBankgiro 120-6259. Postgiro\n11025-4\n\nVerksamhet: Tillverkar kylare o\nvärmeväxlare för motorer\nAntal anställda: 24\nÅrsomsättning: 3500 000\nAktiekapital: 120 000\nStyrelse: Dir E Larsson (ordf),\nkamrer Ake Hilding, herr B-G\nLarsson\n\nVerkst dir: E Larsson\nEtableringsår: 1957.\n\nLINKÖPINGS LINNE.\nFABRIKS AB\n\nPnr 252 57\n\nHelsingborg, Regementsv 1. Tel\n042-18 0 2 75. Bankgiro 120-1532.\nPostgiro 6290-1\n\nVerksamhet: Tillverkar o säljer\nskjortor\n\nAktiekapital: 379 500\nVerkst dir: Lars Béen\nEtableringsår: 1910.\n\nFLYGLEVERANSER, AB\n\nPnr 12612\n\nStockholm 42, Box 42131.\nVretens-borgsv 5, Hägersten. Tel\n08-459135. Bankgiro 330-1439.\nPostgiro 15887-8. Tga Leveransbolag.\nTelex 17450\n\nVerksamhet: Säljer flygmaskiner o\nflygmateriel\nAktiekapital: 50 000\nStyrelse: Dir Bengt Axel Lindberg\n(ordf), dir Nils Fredrik Richard\nBernström, ing Georg Malmström\nVerkst dir: Ing Georg Malmström\nEtableringsår: 1940.\n\nOLA\n\nPlatschef: Disp Töre Lundberg\nEtaberingsår 1939\nNamnändring 1948.\n\nOLANDER AB, GÖSTA\n\nPnr 102 32\n\nStockholm 6, Eugeniav. Box 6083.\nTel 08-33 26 60. Tga\nOelander-metall\n\nVerksamhet: Handel med metaller,\njärn- o metallskrot\nAntal anställda: 14\n•Aktiekapital: 30000\nVerkst dir Gösta Olander\nEtableringsår: 1955.\n\nGOLV-KÄLLAN AB\n\nPnr 116 23\n\nStockholm SO, Kocksg 21. Tel\n08-40 34 18, 40 34 19. Bankgiro\n57-3336. Postgiro 551456\nVerksamhet: Levererar o lägger\ngolvbeläggningsmaterial\nAktiekapital: 25 000\nVerkst dir: Sven Kjellman\nEtableringsår: 1956.\n\nOSK\n\nAktiekapital: 30 000 000\nVeikst dir: Olle Gimstedt\nEtableringsår: 1958.\n\nOSCÅRSON &amp; CO KONFEK.\nTIONS AB\n\nPnr 50102\n\nBorås 1, Box 44. Humleg 13. Tel\n033-1277 30. Bankgiro 843-5083.\nPostgiro 26 35 55-5\nVerksamhet: Tillverkar barn- o\nsportkonfektion, udda konfektion\nför tonår, byxor för barn, goss,\nflick o dam\n\nRepresentant: 112 46 Stockholm.\nFirma Stig Hultman, Fridhemsg 70.\nTel 08-54 5013\nAntal anställda: 140\nÅrsomsättning: 10 000 000\nAktiekapital: 180 000\ndieter: Georg Oscarson, Anders\nOscarson\n\nEtableringsår: 1943.\n\nOSCARSSONS SCHAKT.\nMASKINER AB\n\nPnr 115 41\n\nStockholm, Oregrundsg 13. Tel\n08-67 94 90. Bankgiro 203-5681.\nPostgiro 409038-7\n\nVerksamhet: Entreprenadrörelse\nAntal anställda: 12\nÅrsomsättning: 8 000 000\nAktiekapital: 60 000\nStyrelse: Dir Erie Oscarsson (ordf),\nkamrer Karl-Georg Arvidsson,\nentreprenör Seth Olofsson\nVerkst dir: Erie Oscarsson\nEtableringsår: 1968.\n\nJÄRN &amp; MASKIN, AB\n\nPnr 651 02\n\nKarlstad 1, Sågverksg 12. Box 40.\nTel 054-11 22 90, 18 28 77. Bankgiro\n100-4944. Postgiro 567652-3\nVerksamhet: Specialitet: kullager\no rullager samt verktyg o\nmaskintillbehör, slipmaterial\nChef: Kjell Johansson\nEtableringsår 1926.\n\nNOM\n\ndetaljer på beställning.\nStängselnät o häfttråd\nÅrsomsättning: 7 000 000\nVerkst dir: Sixten Norhed\nEtableringsår: 1937.\n\nSTIWEX PENSELINDUSTRI, AB\n\nPnr 560 23\n\nBankeryd. Tel 036-771 50. Bankgiro\n54-5435. Postgiro 292072\nVerksamhet: Tillverkar alla slags\npenslar o målningsrullar\nAntal anstäUda: 65\nÅrsomsättning: 5 000 000\nAktiekapital: 90 000\nVerkst dir: Fabr Yngve Westmar\nEtableringsår: 1946.\n\nGALVATOR, AB\n\nPnr 184 00\n\nAkersberga, Centralv. Tel\n0764-21600. Bankgiro 483-45 94.\nPostgiro 356000-0\n\nVerksamhet: Utför ytbehandling,\nsåsom hårdförkromning\nAntal anställda: 12\nAktiekapital: 10 000\nVerkst dir: Adolf Demmers\nEtableringsår: 1949.\n\nHOLST, CARL G\n\nPnr 21121\n\nMalmö, Västerg 40. Tel 040-31875,\n31975. Bankgiro 732-3819. Post\ngiro 154605-0. Tga Cargeholst\nVerksamhet: Säljer formar för\nplastindustrin. Standarddelar för\nplast-o stansverktyg. Glassmältdeglar\nVarunamn: EOC, Sommer, Sustan\nChef: Dir Gustaf Holst\nEtableringsår: 1946.",
    "structured": {
        "1": {
            "company_name": "LINKOPIA EK FOR",
            "activity": "Fotolaboratorium, engroshandel, finansinstitut",
            "establishment_year": 1956,
            "pnr": "581 84",
            "address": "Linköping, Roxeng 11",
            "phone_number": "013-102440",
            "bank_details": {
                "bankgiro": "120-5111",
                "postgiro": "498335-9"
            },
            "employees": 330,
            "annual_turnover": 45000000,
            "capital": 3200000,
            "key_personnel": [
                {
                    "name": "Sven-Eric Egerborn",
                    "position": "Verkst dir"
                }
            ]
        },
        "2": {
            "company_name": "LINKÖPINGS AUTO-ELEK-TRISKA GUSTAFSSON & CO",
            "activity": "Försäljning o reparation av elektr detaljer för bil o flyg, diesel-, el-handverktyg, bil-värmare. Specialitet: Bosch service",
            "establishment_year": 1945,
            "pnr": "58103",
            "address": "Linköping 1, Bantorget 1, Box 352",
            "phone_number": "013-12 72 09, 12 77 09",
            "bank_details": {
                "bankgiro": "120-0468",
                "postgiro": "279527-6"
            },
            "employees": 10,
            "annual_turnover": 1100000,
            "key_personnel": [
                {
                    "name": "Köpman S Arne Gustafsson",
                    "position": "Chef"
                }
            ]
        },
        "3": {
            "company_name": "LINKÖPINGS BYGGNADS. MATERIAL, AB",
            "activity": "Säljer byggnadsmaterial, trävaror o snickerier",
            "establishment_year": 1931,
            "pnr": "58102",
            "address": "Linköping 1, Sveag 4, Box 138",
            "phone_number": "013-129130",
            "bank_details": {
                "bankgiro": "120-0450",
                "postgiro": "77844-9"
            },
            "employees": 6,
            "annual_turnover": 2700000,
            "capital": 45000,
            "key_personnel": [
                {
                    "name": "Byggn-ing Helge Netz (crdf)",
                    "position": "Styrelse"
                },
                {
                    "name": "Stig Johansson",
                    "position": "Verkst dir"
                }
            ]
        },
        "4": {
            "company_name": "LINKÖPINGS EXPRESS & ORDERCENTRAL AB",
            "activity": "Lastbilsåkeri. Levererar grus från egna grustag",
            "establishment_year": 1950,
            "pnr": "581 03",
            "address": "Linköping 1, Box 337, Rudsjög 1",
            "phone_number": "013-13 0100",
            "bank_details": {
                "bankgiro": "607-8208",
                "postgiro": "27992-7"
            },
            "employees": 105,
            "annual_turnover": 12000000,
            "capital": 300000,
            "key_personnel": [
                {
                    "name": "Yngve Lundell",
                    "position": "Verkst dir"
                }
            ]
        },
        "5": {
            "company_name": "LINKÖPINGS FORNICKLINGS AB NICRO",
            "activity": "Elektrogalvanisk ytbehandling. Specialitet: automat förzinkning",
            "establishment_year": 0,
            "pnr": "58102",
            "address": "Linköping 1, Kolfallsg 8, Box 13",
            "phone_number": "013-12 8123, 12 23 65",
            "bank_details": {
                "bankgiro": "346-9574",
                "postgiro": "334714-3"
            },
            "employees": 25,
            "annual_turnover": 2000000,
            "key_personnel": [
                {
                    "name": "Uno Nordén",
                    "position": "Chef"
                }
            ]
        }
    }
}