{
    "original": "TÖCKSFORS VERKSTADS AB\n\nPnr 67010\n\nTöcksfors, Box 5. Tel 0573-215 20.\nBankgiro 116-3369. Postgiro\n395063-1\n\nVerksamhet: Tillverkar elektr\nkablar för bilindustrin, kabelnät o\nspecialkomponenter for\ndatamaskiner samt elektr kallmanglar\nAntal anställda: 240\nAktiekapital: 600000\nStyrelse: Kommunalkamrer Hilding\nHalvardsson (ordf), dir Rune\nAndersson, köpman Sune Sahlin,\njärnh Elof Patriksson, byggmäst\nRoy Persson\n\nVerkst dir: Rune Andersson\nEtableringsår: 1963.\n\nFENDERBOLAGEN AB\n\nPnr 141 21\n\nHuddinge 1, Box 1031. Lillerudsv.\nTel 08-757 43 79, 757 66 96.\nBankgiro 19-6087. Postgiro 129330. Tga\nFenderbol\n\nVerksamhet: Tillverkar\n\"Cord-kappfender\". Gummifendrar för\nkajer o fartyg\n\nVarunamn: Cordkappfender\nÅrsomsättning: 800 000\nAktiekapital: 5 000\nStyrelse: Dir Erie Westerberg\n(ordf), verkmäst Verner Westerberg\nVerkst dir: Erie Westerberg\nEtableringsår: 1952.\n\nFENGERSFORS BRUKS NYA\nAB\n\nPnr 660 20\n\nFengersfors. Tel 0532-23100.\nBankgiro 632-2192. Postgiro 242915-7.\nTga Fengersfors. Telex 5319\nVerksamhet: Tillverkar finpapper\no MG, affischpapper\nAntal anställda: 70\nAktiekapital: 100 000.\n\nFENIX EXPRESS AB\n\nPnr 101 21\n\nStockholm 1, Birger Jarlsg 62. Box\n87. Tel 08-10 55 69, 20 55 69.\nBankgiro 167-4399. Postgiro 55295-0.\nTga Fenixexpress. Telex 1468\nVerksamhet: In o utrikes\nmöbeltransporter, kontorsflyttningar\nAntal anställda: 26\nÅrsomsättning: 850 000\nAktiekapital: 6 000\nVerkst dir: Gösta Hörgren\nEtableringsår: 1917.\n\nLIBRARIA, AB\n\nPnr 11144\n\nStockholm, Jakobsbergsg 15. Tel\n08-20 29 04, 20 29 14. Postgiro\n528 80\n\nVerksamhet: Kyrklig konst- o\ntextilateljé. Konsthantverk\nAktiekapital: 47 200\nVerkst dir: Fil lic B Runmark\nEtableringsår: 1917.\n\nSJÖDIN, AB JOHN\n\nPnr 93101\n\nSkellefteå 1, Svedjev 3. Box 43.\nTel 0910-143 80. Bankgiro 764-0717.\nPostgiro 28794-6.\nTelex 6824 SJÖDIN S\nVerksamhet: Järnvaror, byggvaror,\nbränsle, båtar o hushållsmaskiner\nAntal anställda: 85\nÅrsomsättning: 29 000 000\nAktiekapital: 632 000\nVerkst dir: Lennart Porslund\nEtableringsår 1898.\n\nLEC\n\n465 30. Bankgiro 895-6310. Postr\ngiro 172002-8\n\nVerksamhet: Transportförmedling,\nvägarbeten på entreprenad\nAntal anställda: 12\nÅrsomsättning: 18 000 000\nInsatskapital: 1350 000\nChef: Disp K G Retfter\nEtableringsår: 1940.\n\nLASTBILCENTRALEN\nMJÖLBY-SKÄNNINGE EK FOR\n\nPnr 595 00\n\nMjölby, Box 53. Linköpingsv 4.\nTel 0142-130 40. Bankgiro\n128-4363. Postgiro 616200-2\nVerksamhet: Utför alla slags\ntransporter såväl när- som fjärrtrafik\nmed tipp- o kranbilar.\nSchaktnings-o planeringsarbeten jämte\nlastnings- o lossningsuppdrag. Uthyr\nlast- o grävmaskiner, liftdumper.\nLevererar all slags sten- o\ngrusmaterial från egna\nkrossanläggningar\n\nKontor: Skänninge, Bjälbog 30.\nTel 0142-403 70, 406 70\nAntal anställda: 65\nÅrsomsättning: 9 000 000\nStyre lseordf: Ivar P Svensson\nChef: Disp Hans-Erik Larsson\nEtableringsår: 1940.\n\nLASTBILAGARNAS\nORDERKONTOR EK FOR\n\nPnr 252 32\n\nHelsingborg, Åkarnas Hus.\nLands-kronav 16. Tel 042-1206 70.\nBankgiro 653-2675. Postgiro 98177-9\nVerksamhet: Säljer transporter o\nannan därmed sammanhängande\nverksamhet\nAntal anställda: 9\nÅrsomsättning: 8 300 000\nChef: Dir Jan Nilsson\nEtableringsår: 1939.\n\nLASTNINGS- och\nLOSSNINGSTJÄNST, AB\n\nPnr 422 04\n\nHisings Backa 4, Box 4030.\nIm-portg 17 B. Tel 031-520150.\nBankgiro 851-7476. Postgiro 242040-4\nVerksamhet: Försäljning o service\nav gaffeltruckar 2-30 ton\nAntal anställda: 58\nÅrsomsättning: 12 000 000\nAktiekapital: 125 000\nVerkst dir: Poul Madsen\nEtableringsår. 1946.\n\nBJÖRKLUND &amp; CO AB, S\n\nPnr 104 60\n\nStockholm 20, Virkesv 7. Tel\n08-44 99 05. Bankgiro 57-6117. Post-\n\ngiro 55577. Tga Essbeco.\nTelex 10126\n\nVerksamhet: Säljer maskiner,\nverktyg o metaller engros\nAntal anställda: 33\nÅrsomsättning: 15 000000\nAktiekapital: 150000\nVerkst dir: Lars Andree\nInköpschef: Erik Lundgren\nEtableringsår: 1933\nOmbildat till aktiebolag 1943.\n\nBJÖRKLUNDS MEKANISKA,\nAB TAGE\n\nPnr 502 60\n\nBorås, Verkstadsg 10. Tel\n033-13 59 60, 12 5173. Bankgiro\n531-5247. Postgiro 612748-4\nVerksamhet: Sandblästring o\nmålning, sprutförzinkning, svarvning,\ngrovplåtslageri, stålkonstruktioner\nAntal anställda: 45\nÅrsomsättning: 3000 000\nAktiekapital: 60 000\nStyrelse: Tora Björklund (ordf),\nKurt Löfstrand, Inger Löfstrand\nOief: Kurt Löfstrand\nEtableringsår: 1963.\n\nmaskin.konsult\ng nord ab\n\nPnr 571 00\n\nNässjö, Kyrkog 6. Tel0380-155 70,\n115 39. Bankgiro 14-3694. Postgiro\n591850. Tga Manab\nVerksamhet: Specialmaskiner o\nanläggningar för industrin\nAktiekapital: 15 000\nVerkst dir: Ing Gustaf Nord\nEtableringsår: 1962.\n\nPLAN ANNONSBYRÅ AB\n\nPnr 11184\n\nStockholm 1, Sveav 17, Box 1408.\nTel 08-24 13 50. Bankgiro 72-2462.\nPostgiro 418610. Tga Adverop\nVerksamhet: Förmedlingsnominerad\nannonsbyrå. Auktoriserad\nreklamkonsult\n\nAntal anställda: 25\nÅrsomsättning: 23 000 000\nAktiekapital: 520 000\nVerkst dir: Arthur Ekdahl\nEtableringsår: 1958.\n\n[-PLANANDERSBYGG-KONSULT-]\n\n{+PLANANDERSBYGG-\nKONSULT+} AB\n\nPnr 582 23\n\nLinköping, Storg 32. Tel\n013-12 20 35, 12 8 8 00.Postgiro 324504\nVerksamhet: Konsulterande inom\nhusbyggnadsfacket. Utreder,\nplanerar, byggleder, kontrollerar,\nbesiktigar o värderar. Specialitet:\nrestaureringsfrågor\nÅrsomsättning: 150 000\nAktiekapital: 5 000\nVerkst dir: Byggn-ing SBR R\nPlanander\nEtableringsår: 1944\nOmbildat till aktiebolag 1960.\n\nPLANBETONG AB\n\nPnr 94 2 00\n\nÄlvsbyn, Lomtjämsg 32. Tel\n0929-115 50. Bankgiro 75-7788. Postgiro\n481335-8\n\nVerksamhet: Entreprenör för vägar,\nvatten o avlopp, schakt- o\nplaneringsarbeten, industribyggnationer o\nbetongarbeten. Uthyr vägmaskiner\nAntal anställda: 50\nÅrsomsättning: 8 000 000\nAktiekapital: 100 000\nVerkst dir: Bengt E Nilsson\nEtableringsår: 1948\nOmbildat till aktiebolag 1957.\n\nPLAN-DEX KONTOR SYSTEM\n\nPnr 217 58\n\nMalmö, Tessins v 2.Tel 040-600 27.\nBankgiro 106-5879. Postgiro\n636684-3\n\nVerksamhet: Generalagent för\nPlan-Dex planeringssystem\nEtableringsår: 1968.\n\nTJüRNARPSSLÄP, AB\n\nPnr 240 40\n\nTiörnarp, Box 24. Tel 0451-621 97,\n624 97. Bankgiro 286-3553. Post- .\ngiro 28388-7\n\nVerksamhet: Tillverkar släpvagnar\nför lastbilar o lastbilsbyggnationer\nsamt tyngre specialfordon\nVarunamn: Tjörnarpssläp\nAntal anställda: 15\nÅrsomsättning: 2 000 000\nAktiekapital: 30 000\nStyrelse: Lantbr Karl Pettersson\n(ordf), ing Sven-Olof Gustafson,\nfabr Holger Jönsson\nVerkst din Ing Sven-Olof\nGustafson\n\nEtableringsår. 1961.\n\nLINDÄSDETALJER, AB\n\nPnr 360 61\n\nLindås. Tel 0471-108 25.\nBankgiro 66-1938. Postgiro 33507.\nTelex 4855. Tga Lindåsdetaljer\nVerksamhet: Tillverkar automaU\nsvarvade detaljer o möbelbeslag\nFilial: Värnamo, Karda. Tel\n0370-281 00\n\nAntal anställda: 150\nÅrsomsättning: 15 000 000\nAktiekapital: 750 000\nVerkst dir: Henry Strömberg\nEtableringsår: 1949.\n\nLINDÖ SNICKERI\nPETTERS-SON &amp; CO\n\nPnr 600 12\n\nNorrköping 12, Box 12022. Tel\n011-44128. Bankgiro 82-6090.\nPostgiro 70179\n\nVeiksamhet: Byggnadssnickerier,\ntrappor\n\nÅrsomsättning: 180 000\nChef: Fabr Gösta Pettersson\nEtableringsår: 1952.",
    "structured": {
        "1": {
            "company_name": "TÖCKSFORS VERKSTADS AB",
            "pnr": "67010",
            "address": "Töcksfors, Box 5",
            "phone_number": "0573-215 20",
            "bank_details": {
                "bankgiro": "116-3369",
                "postgiro": "395063-1"
            },
            "activity": "Tillverkar elektr kablar för bilindustrin, kabelnät o specialkomponenter for datamaskiner samt elektr kallmanglar",
            "employees": 240,
            "capital": 600000,
            "key_personnel": [
                {
                    "name": "Kommunalkamrer Hilding Halvardsson",
                    "position": "ordf"
                },
                {
                    "name": "Rune Andersson",
                    "position": "Verkst dir"
                }
            ],
            "establishment_year": 1963
        },
        "2": {
            "company_name": "FENDERBOLAGEN AB",
            "pnr": "141 21",
            "address": "Huddinge 1, Box 1031, Lillerudsv",
            "phone_number": "08-757 43 79, 757 66 96",
            "bank_details": {
                "bankgiro": "19-6087",
                "postgiro": "129330"
            },
            "activity": "Tillverkar Cord-kappfender, Gummifendrar för kajer o fartyg",
            "annual_turnover": 800000,
            "capital": 5000,
            "key_personnel": [
                {
                    "name": "Erie Westerberg",
                    "position": "ordf"
                }
            ],
            "establishment_year": 1952
        },
        "3": {
            "company_name": "FENGERSFORS BRUKS NYA AB",
            "pnr": "660 20",
            "address": "Fengersfors",
            "phone_number": "0532-23100",
            "bank_details": {
                "bankgiro": "632-2192",
                "postgiro": "242915-7"
            },
            "activity": "Tillverkar finpapper o MG, affischpapper",
            "employees": 70,
            "capital": 100000
        },
        "4": {
            "company_name": "FENIX EXPRESS AB",
            "pnr": "101 21",
            "address": "Stockholm 1, Birger Jarlsg 62, Box 87",
            "phone_number": "08-10 55 69, 20 55 69",
            "bank_details": {
                "bankgiro": "167-4399",
                "postgiro": "55295-0"
            },
            "activity": "In o utrikes möbeltransporter, kontorsflyttningar",
            "employees": 26,
            "annual_turnover": 850000,
            "capital": 6000,
            "key_personnel": [
                {
                    "name": "Gösta Hörgren",
                    "position": "Verkst dir"
                }
            ],
            "establishment_year": 1917
        },
        "5": {
            "company_name": "LIBRARIA, AB",
            "pnr": "11144",
            "address": "Stockholm, Jakobsbergsg 15",
            "phone_number": "08-20 29 04, 20 29 14",
            "activity": "Kyrklig konst- o textilateljé, Konsthantverk",
            "capital": 47200,
            "key_personnel": [
                {
                    "name": "Fil lic B Runmark",
                    "position": "Verkst dir"
                }
            ],
            "establishment_year": 1917
        },
        "6": {
            "company_name": "SJÖDIN, AB JOHN",
            "pnr": "93101",
            "address": "Skellefteå 1, Svedjev 3, Box 43",
            "phone_number": "0910-143 80",
            "bank_details": {
                "bankgiro": "764-0717",
                "postgiro": "28794-6"
            },
            "activity": "Järnvaror, byggvaror, bränsle, båtar o hushållsmaskiner",
            "employees": 85,
            "annual_turnover": 29000000,
            "capital": 632000,
            "key_personnel": [
                {
                    "name": "Lennart Porslund",
                    "position": "Verkst dir"
                }
            ],
            "establishment_year": 1898
        },
        "7": {
            "company_name": "LEC",
            "pnr": "465 30",
            "activity": "Transportförmedling, vägarbeten på entreprenad",
            "employees": 12,
            "annual_turnover": 18000000,
            "capital": 1350000,
            "key_personnel": [
                {
                    "name": "Disp K G Retfter",
                    "position": "Chef"
                }
            ],
            "establishment_year": 1940
        },
        "8": {
            "company_name": "LASTBILCENTRALEN MJÖLBY-SKÄNNINGE EK FOR",
            "pnr": "595 00",
            "address": "Mjölby, Box 53, Linköpingsv 4",
            "phone_number": "0142-130 40",
            "bank_details": {
                "bankgiro": "128-4363",
                "postgiro": "616200-2"
            },
            "activity": "Utför alla slags transporter såväl när- som fjärrtrafik med tipp- o kranbilar, Schaktnings-o planeringsarbeten jämte lastnings- o lossningsuppdrag, Uthyr last- o grävmaskiner, liftdumper, Levererar all slags sten- o grusmaterial från egna krossanläggningar",
            "employees": 65,
            "annual_turnover": 9000000,
            "key_personnel": [
                {
                    "name": "Ivar P Svensson",
                    "position": "Styre lseordf"
                },
                {
                    "name": "Hans-Erik Larsson",
                    "position": "Disp"
                }
            ],
            "establishment_year": 1940
        },
        "9": {
            "company_name": "LASTBILAGARNAS ORDERKONTOR EK FOR",
            "pnr": "252 32",
            "address": "Helsingborg, Åkarnas Hus, Lands-kronav 16",
            "phone_number": "042-1206 70",
            "bank_details": {
                "bankgiro": "653-2675",
                "postgiro": "98177-9"
            },
            "activity": "Säljer transporter o annan därmed sammanhängande verksamhet",
            "employees": 9,
            "annual_turnover": 8300000,
            "key_personnel": [
                {
                    "name": "Jan Nilsson",
                    "position": "Chef"
                }
            ],
            "establishment_year": 1939
        },
        "10": {
            "company_name": "LASTNINGS- och LOSSNINGSTJÄNST, AB",
            "pnr": "422 04",
            "address": "Hisings Backa 4, Box 4030, Importg 17 B",
            "phone_number": "031-520150",
            "bank_details": {
                "bankgiro": "851-7476",
                "postgiro": "242040-4"
            },
            "activity": "Försäljning o service av gaffeltruckar 2-30 ton",
            "employees": 58,
            "annual_turnover": 12000000,
            "capital": 125000,
            "key_personnel": [
                {
                    "name": "Poul Madsen",
                    "position": "Verkst dir"
                }
            ],
            "establishment_year": 1946
        },
        "11": {
            "company_name": "BJÖRKLUND & CO AB, S",
            "pnr": "104 60",
            "address": "Stockholm 20, Virkesv 7",
            "phone_number": "08-44 99 05",
            "bank_details": {
                "bankgiro": "57-6117",
                "postgiro": "55577"
            },
            "activity": "Säljer maskiner, verktyg o metaller engros",
            "employees": 33,
            "annual_turnover": 15000000,
            "capital": 150000,
            "key_personnel": [
                {
                    "name": "Lars Andree",
                    "position": "Verkst dir"
                },
                {
                    "name": "Erik Lundgren",
                    "position": "Inköpschef"
                }
            ],
            "establishment_year": 1933
        },
        "12": {
            "company_name": "BJÖRKLUNDS MEKANISKA, AB TAGE",
            "pnr": "502 60",
            "address": "Borås, Verkstadsg 10",
            "phone_number": "033-13 59 60, 12 5173",
            "bank_details": {
                "bankgiro": "531-5247",
                "postgiro": "612748-4"
            },
            "activity": "Sandblästring o målning, sprutförzinkning, svarvning, grovplåtslageri, stålkonstruktioner",
            "employees": 45,
            "annual_turnover": 3000000,
            "capital": 60000,
            "key_personnel": [
                {
                    "name": "Tora Björklund",
                    "position": "ordf"
                },
                {
                    "name": "Kurt Löfstrand",
                    "position": "Oief"
                }
            ],
            "establishment_year": 1963
        },
        "13": {
            "company_name": "maskin.konsult g nord ab",
            "pnr": "571 00",
            "address": "Nässjö, Kyrkog 6",
            "phone_number": "0380-155 70, 115 39",
            "bank_details": {
                "bankgiro": "14-3694",
                "postgiro": "591850"
            },
            "activity": "Specialmaskiner o anläggningar för industrin",
            "capital": 15000,
            "key_personnel": [
                {
                    "name": "Ing Gustaf Nord",
                    "position": "Verkst dir"
                }
            ],
            "establishment_year": 1962
        },
        "14": {
            "company_name": "PLAN ANNONSBYRÅ AB",
            "pnr": "11184",
            "address": "Stockholm 1, Sveav 17, Box 1408",
            "phone_number": "08-24 13 50",
            "bank_details": {
                "bankgiro": "72-2462",
                "postgiro": "418610"
            },
            "activity": "Förmedlingsnominerad annonsbyrå, Auktoriserad reklamkonsult",
            "employees": 25,
            "annual_turnover": 23000000,
            "capital": 520000,
            "key_personnel": [
                {
                    "name": "Arthur Ekdahl",
                    "position": "Verkst dir"
                }
            ],
            "establishment_year": 1958
        },
        "15": {
            "company_name": "PLANANDERSBYGG-KONSULT AB",
            "pnr": "582 23",
            "address": "Linköping, Storg 32",
            "phone_number": "013-12 20 35, 12 8 8 00",
            "bank_details": {
                "bankgiro": "14-3694",
                "postgiro": "591850"
            },
            "activity": "Konsulterande inom husbyggnadsfacket, Specialitet: restaureringsfrågor",
            "annual_turnover": 150000,
            "capital": 5000,
            "key_personnel": [
                {
                    "name": "Byggn-ing SBR R Planander",
                    "position": "Verkst dir"
                }
            ],
            "establishment_year": 1944
        },
        "16": {
            "company_name": "PLANBETONG AB",
            "pnr": "94 2 00",
            "address": "Älvsbyn, Lomtjämsg 32",
            "phone_number": "0929-115 50",
            "bank_details": {
                "bankgiro": "75-7788",
                "postgiro": "481335-8"
            },
            "activity": "Entreprenör för vägar, vatten o avlopp, schakt- o planeringsarbeten, industribyggnationer o betongarbeten, Uthyr vägmaskiner",
            "employees": 50,
            "annual_turnover": 8000000,
            "capital": 100000,
            "key_personnel": [
                {
                    "name": "Bengt E Nilsson",
                    "position": "Verkst dir"
                }
            ],
            "establishment_year": 1948
        },
        "17": {
            "company_name": "PLAN-DEX KONTOR SYSTEM",
            "pnr": "217 58",
            "address": "Malmö, Tessins v 2",
            "phone_number": "040-600 27",
            "bank_details": {
                "bankgiro": "106-5879",
                "postgiro": "636684-3"
            },
            "activity": "Generalagent för Plan-Dex planeringssystem",
            "establishment_year": 1968
        },
        "18": {
            "company_name": "TJüRNARPSSLÄP, AB",
            "pnr": "240 40",
            "address": "Tiörnarp, Box 24",
            "phone_number": "0451-621 97, 624 97",
            "bank_details": {
                "bankgiro": "286-3553",
                "postgiro": "28388-7"
            },
            "activity": "Tillverkar släpvagnar för lastbilar o lastbilsbyggnationer samt tyngre specialfordon",
            "annual_turnover": 2000000,
            "capital": 30000,
            "key_personnel": [
                {
                    "name": "Lantbr Karl Pettersson",
                    "position": "ordf"
                },
                {
                    "name": "Ing Sven-Olof Gustafson",
                    "position": "Verkst din"
                }
            ],
            "establishment_year": 1961
        },
        "19": {
            "company_name": "LINDÄSDETALJER, AB",
            "pnr": "360 61",
            "address": "Lindås",
            "phone_number": "0471-108 25",
            "bank_details": {
                "bankgiro": "66-1938",
                "postgiro": "33507"
            },
            "activity": "Tillverkar automaU svarvade detaljer o möbelbeslag",
            "employees": 150,
            "annual_turnover": 15000000,
            "capital": 750000,
            "key_personnel": [
                {
                    "name": "Henry Strömberg",
                    "position": "Verkst dir"
                }
            ],
            "establishment_year": 1949
        },
        "20": {
            "company_name": "LINDÖ SNICKERI PETTERS-SON & CO",
            "pnr": "600 12",
            "address": "Norrköping 12, Box 12022",
            "phone_number": "011-44128",
            "bank_details": {
                "bankgiro": "82-6090",
                "postgiro": "70179"
            },
            "activity": "Byggnadssnickerier, trappor",
            "annual_turnover": 180000,
            "key_personnel": [
                {
                    "name": "Fabr Gösta Pettersson",
                    "position": "Chef"
                }
            ],
            "establishment_year": 1952
        }
    }
}