{
    "original": "FLYGFÄLTSBYRÅN, AB\n\nPnr 402 41\n\nGöteborg 12, Box 12076. Fiskhamnsg\n4. Tel 031-12 43 60. AndraLångg\n48. Tel 031-12 49 20. Tga Civing.\nTelex 206 28\n\nH3i\n\nVerksamhet: Konsulterande\ningenjörer. Byggnadsprojektering.\nIndustriprojektering. Projekt\nadministration\n\nAvdelningskontor: 29100\nKristianstad, V Boulevarden 47. Tel\n044-1156 85\n\n54100 Skövde. Kyrkog 11. Tel\n0500-146 32\nAntal anställda: 235\nÅrsomsättning: 14 000 000\nAktiekapital: 300 000\nStyrelse: Adv Kurt Mark (ordf),\nciviling Nils Lilljegren, prof Harald\nLindahl, civiling Karl Erik\nLekänder\n\nVerkst dir: Civiling N Lilljegren\nEtableringsår: 1947.\n\nSVENSKA JABSCO, AB\n\nPnr 400 20\n\nGöteborg 14, Box 14041.\nFlöjel-bergsg 8 A, Mölndal. Tel\n031-87 02 80, 87 35 80. Bankgiro\n491-5047. Postgiro 49092-0. Tga\nJabs-co. Telex 20045 TELFA S\nVerksamhet: Säljer pumpar för\nolika ändamål\nAntal anställda: 6\nÅrsomsättning: 1800 000\nAktiekapital: 25 000\nVerkst dir. Gunnar Anderson\nEtableringsår: 1962.\n\nWOHLINBILAR AB\n\nPnr 102 62\n\nStockholm 4, Box 4146. Malmgårdsv\n32. Tel 08-44 01 75. Bankgiro\n729-2493. Postgiro 258890-3\nVeiksamhet: Försäljning av nya\nOpel person- o lastbilar\nAntal anställda: 50\nÅrsomsättning: 12 000 000\nAktiekapital: 30000\nVerkst dir: Fru Maja Wohlin\nEtableringsår: 1947.\n\nHOLST AB, I G\n\nPnr 163 02\n\nSpånga 2. Duvbov 50. Box 2009.\nTel 08-760 04 60. Bankgiro\n734-0458. Postgiro 254601-8. Tga\nHolstprint\n\nVerksamhet: Säljer\nkontorskopieringsmaskiner o reprokameror\nAntal anställda: 52\nÅrsomsättning: 14 500 000\nAktiekapital: 500 000\nVerkst dir: Gösta H Holst\nEtableringsår: 1952.\n\nSCHRÖDER AB, VICTOR\n\nPnr 200 12\n\nMalmö 2, Amiralsg 6. Box 2087. Tel\n040-12 39 65. Bankgiro 64-0293.\nPostgiro 246385. Tga Victorbolag\nVerksamhet: Import o distribution\nav utländska tidskrifter av alla\nslag\n\nÅrsomsättning: 250 000\nAktiekapital: 5 000\nVeikst din Bertil Förk\nEtableringsår: 1947.\n\nGAR\n\nEtableringsår: 1946\nDotterbolag: Galon Pabrics, Inc,\nNew York, Galon Pabrics, Ltd,\nLondon\n\nDotterbolag till AB Fannyudde.\n\nGALVANO- KONSULT AB\n\nPnr 183 02\n\nTäby 2, Box 2014.Tel 08-7560275.\n\nBankgiro 625-6986. Postgiro\n\n268028\n\nVerksamhet: Anläggningar,\nutrustningsdetaljer o kemikalier för\nkemisk o galvanisk ytbehandling.\nKonsultationer\nAntal anställda: 4\nÅrsomsättning: 750 000\nAktiekapital: 15 000\nVerkst dir: Sven Gustavsson\nEtableringsår: 1964.\n\nBORLIND, BERSÉN &amp; CO\n\nPnr 403 14\n\nGöteborg 2, Packhusplatsen 2. Box\n2233. Tel 031-13 48 23. Bankgiro\n42-0259. Postgiro 40052-3.\nTga Borlinds, Borlindsale.\nTelex 2340, 2341\nVerksamhet: Skeppsmäkleri,\nspedition, haveriagenter, köp o\nförsäljning av fartyg\nÄgare o chefer: Björn Trapp,\nBengt R Hellberg\nEtableringsår: 1864.\n\nE H AB, METALLFABRIKEN\n\nPnr 330 33\n\nHillers torp. Tel 0370-220 66.\nPostgiro 75138-8\n\nVerksamhet: Tillverkar\nbiltillbehör, specialitet kranar o\nförskruv-ningar, släpvagnskontakter,\nmotor-värmar anslut ning ar\nVerkst dir: Fabr E Svensson.\n\nEIE, MASKIN AB N A\n\nPnr 124 21\n\nBandhagen 1, Box 7. Skebokvarnsv\n370. Tel 08-47 2610. Bankgiro\n578-0028. Postgiro 55798-3. Tga\nEiebolag. Telex 10346\nVerksamhet: Maskiner\nfabriksförnödenheter\nAntal anställda: 16\nÅrsomsättning: 9 000 000\nVerkst dir: Lennart Holmberg\nEtableringsår: 1930.\n\nJANSON AB, ARTUR\n\nPnr 68101\n\nKristinehamn 1, Box 57. Lagmansg\n1 B. Tel 0550-153 15. Bankgiro\n110-0130. Postgiro 71980-7. Tga\nAjäb\n\nVerksamhet: Partihandel med\nplywood. träfiberplattor, spånplattor\nAktiekapital: 200 000\nFirmatecknare: Ing Albin Janson,\nGunnar Janson\nEtableringsår: 1923.\n\nJANSSON SMIDES. &amp; MEK\nVERKSTAD, AB AXEL G\n\nPnr 100 61\n\nStockholm 11, Katarina Bang 77.\nBox 11064. Tel 08-44 05 95.\nBankgiro 568-9237. Postgiro 54139-1\nVerksamhet: Tillverkar\njärnkonstruktioner för såväl hus- som\nbrobyggnader. Grovplåtsarbeten av\nalla slag, byggnadssmide,\nmaskin-o svetsningsarbeten\nFilial: Krylbo. Tel 0226-113 95\nAntal anställda: 133\nÅrsomsättning: 11000 000\nAktiekapital: 225 000\nStyrelse: Fru Greta Jansson (ordf),\ndisp Evert Jansson, dir Bo Jansson\nVerkst dir: Evert Jansson\nEtableringsår: 1911\nOmbildat till aktiebolag 1937.\n\nJANSON AB, B S\n\nPrr 50256\n\nBorås, Elinsdalsg 6-8. Tel\n033-10 02 80. Bankgiro 531-5502.\nPostgiro 614926-4\n\nVerksamhet: Tillverkar dressar,\nbyxor, överplagg i dam-, herr- o\njunior\n\nAntal anställda: 180\nÅrsomsättning: 12 000 000\nAktiekapital: 50 000\nVerkst dir: Bengt Ake Jansson\nEtableringsår: 1963.\n\nJANSSON, VERKSTADS AB\nERICK\n\nPnr 500 06\n\nBorås 6, Mårtensg 8. Box 66011.\nTel 033-12 75 90. Bankgiro\n360-8734. Postgiro 118925-7. Tga\nJabick\n\nVerksamhet: Tillverkar spår lindade\nkamflänsrör i koppar, aluminium,\nrostfritt o järn samt kombinationer\nav desamma, batterier\n(värmeväxlare) o lamellbatterier enl\nönskemål. Gjuteri o mek\nverkstadsrörelse\n\nVarunamn: Jäbick\nAntal anställda: 40\nÅrsomsättning: 1800 000\nAktiekapital: 25 000\nStyrelse: Adv Erik Sandin (ordf).\n\nkamrer Ake Lindman,\nverkstadschef Karl-Gustav Sahlström\nVerkst dir: Erick Jansson\nEtableringsår: 1936\nOmbildat till aktiebolag 1958.\n\nJANSON AB, GUNNAR B\n\nPnr 17121\n\nSolna 1, Box 1018. Vinterg 2,\nSundbyberg. Tel 08-98 15 70. Postgiro\n157211-4. Tga Kemometall.\nTelex 19099\n\nVerksamhet: Grossist o\nagenturrörelse för kemikalier, plaster m m\nAntal anställda: 10\nAktiekapital: 30 000\nVerkst dir: Gunnar B Janson\nEtableringsår: 1957.\n\nJANSSON, MASKIN AB INGVAR\nJANSSON. INDUSTRI AB INGVAR\n\nPnr 85105\n\nSundsvall 1, Skolhusallén 17. Box\n350. Tel 060-15 4040. Postgiro\n372622. Telex 71213\nVerksamhet: Säljer marin- o\nindustrimotorer, generatoraggregat o\nsnöfordon\n\nAntal anställda: 15\nÅrsomsättning: 10 000 000\nAktiekapital: 85 000\nVerkst dir. Ingvar Jansson\nEtableringsår: 1944.\n\nJANSSONS NYSILVERFABRIK,\nAB J AXEL\n\nPnr 53101\n\nLidköping 1, Box 69. Sockerbruksg.\nTel 0510-200 69, 207 01. Bankgiro\n84-1318. Postgiro 10321. Tga\nJanssonsilver\n\nVerksamhet: Tillverkar\nbordsbestick, legoarbeten, slipning,\npolering, hårdför kromning\nAntal anställda: 25\nÅrsomsättning: 1400 000\nAktiekapital: 50 000\nVerkst dir: Disp Helge Jansson.\n\nJANSSON AB, J F\n\nPnr 750 02\n\nUppsala 2, Svartbäcksg 65. Box\n2125. Tel 018-12 00 25. Bankgiro\n80-2126. Postgiro 91109\nVerksamhet: Installationsfirma för\nvärme- o sanitetsarbeten\nAntal anställda: 40\nÅrsomsättning: 4 000 000\nAktiekapital: 75 000\nVerkst dir Ing Sten Nordenman\nKamrer: Bengt Nordenman\nEtableringsår: 1912\nOmbildat till aktiebolag 1928.\n\nJANSSONS ELEKTRISKA\nINSTALLATIONSBYRÄ\nAB. K A\n\nPnr 113 54\n\nStockholm, Roslagsg 54. Tel\n08-315144, 3185 05. Bankgiro\n572-2491. Postgiro 53019-6\nVerksamhet: El-installationer\nChef: Ing A Ståhlberg\nEtableringsår: 1924.\n\nSTJERNA, AB E\n\nPnr 524 00\n\nHerrljunga. Tel 0513-11045.\nBankgiro 84-1018. Postgiro 25933\nVerksamhet: Möbeltyger, gardiner,\nmattor o madrasser\nAntal anstäUda: 35\nAktiekapital: 150 000\nVerkst dir: Per Körberg\nEtableringsår: 1918.",
    "structured": {
        "1": {
            "company_name": "FLYGFÄLTSBYRÅN, AB",
            "address": "Göteborg 12, Box 12076. Fiskhamnsg 4.",
            "phone_number": "031-12 43 60, 031-12 49 20",
            "activity": "Konsulterande ingenjörer. Byggnadsprojektering. Industriprojektering. Projekt administration",
            "employees": 235,
            "annual_turnover": 14000000,
            "capital": 300000,
            "key_personnel": [
                {
                    "name": "Adv Kurt Mark",
                    "position": "ordf"
                },
                {
                    "name": "civiling Nils Lilljegren",
                    "position": null
                },
                {
                    "name": "prof Harald Lindahl",
                    "position": null
                },
                {
                    "name": "civiling Karl Erik Lekänder",
                    "position": null
                }
            ],
            "establishment_year": 1947
        },
        "2": {
            "company_name": "SVENSKA JABSCO, AB",
            "address": "Göteborg 14, Box 14041. Flöjel-bergsg 8 A, Mölndal",
            "phone_number": "031-87 02 80, 031-87 35 80",
            "bank_details": {
                "bankgiro": "491-5047",
                "postgiro": "49092-0"
            },
            "activity": "Säljer pumpar för olika ändamål",
            "employees": 6,
            "annual_turnover": 1800000,
            "capital": 25000,
            "key_personnel": [
                {
                    "name": "Gunnar Anderson",
                    "position": null
                }
            ],
            "establishment_year": 1962
        },
        "3": {
            "company_name": "WOHLINBILAR AB",
            "address": "Stockholm 4, Box 4146. Malmgårdsv 32",
            "phone_number": "08-44 01 75",
            "bank_details": {
                "bankgiro": "729-2493",
                "postgiro": "258890-3"
            },
            "activity": "Försäljning av nya Opel person- o lastbilar",
            "employees": 50,
            "annual_turnover": 12000000,
            "capital": 30000,
            "key_personnel": [
                {
                    "name": "Fru Maja Wohlin",
                    "position": null
                }
            ],
            "establishment_year": 1947
        },
        "4": {
            "company_name": "HOLST AB, I G",
            "address": "Spånga 2. Duvbov 50. Box 2009",
            "phone_number": "08-760 04 60",
            "bank_details": {
                "bankgiro": "734-0458",
                "postgiro": "254601-8"
            },
            "activity": "Säljer kontorskopieringsmaskiner o reprokameror",
            "employees": 52,
            "annual_turnover": 14500000,
            "capital": 500000,
            "key_personnel": [
                {
                    "name": "Gösta H Holst",
                    "position": null
                }
            ],
            "establishment_year": 1952
        },
        "5": {
            "company_name": "SCHRÖDER AB, VICTOR",
            "address": "Malmö 2, Amiralsg 6. Box 2087",
            "phone_number": "040-12 39 65",
            "bank_details": {
                "bankgiro": "64-0293",
                "postgiro": "246385"
            },
            "activity": "Import o distribution av utländska tidskrifter av alla slag",
            "annual_turnover": 250000,
            "capital": 5000,
            "key_personnel": [
                {
                    "name": "Bertil Förk",
                    "position": null
                }
            ],
            "establishment_year": 1947
        },
        "6": {
            "company_name": "GALVANO- KONSULT AB",
            "address": "Täby 2, Box 2014",
            "phone_number": "08-7560275",
            "bank_details": {
                "bankgiro": "625-6986",
                "postgiro": "268028"
            },
            "activity": "Anläggningar, utrustningsdetaljer o kemikalier för kemisk o galvanisk ytbehandling. Konsultationer",
            "employees": 4,
            "annual_turnover": 750000,
            "capital": 15000,
            "key_personnel": [
                {
                    "name": "Sven Gustavsson",
                    "position": null
                }
            ],
            "establishment_year": 1964
        },
        "7": {
            "company_name": "BORLIND, BERSÉN & CO",
            "address": "Göteborg 2, Packhusplatsen 2. Box 2233",
            "phone_number": "031-13 48 23",
            "bank_details": {
                "bankgiro": "42-0259",
                "postgiro": "40052-3"
            },
            "activity": "Skeppsmäkleri, spedition, haveriagenter, köp o försäljning av fartyg",
            "establishment_year": 1864
        },
        "8": {
            "company_name": "E H AB, METALLFABRIKEN",
            "address": "Hillers torp",
            "phone_number": "0370-220 66",
            "postgiro": "75138-8",
            "activity": "Tillverkar biltillbehör, specialitet kranar o förskruvningar, släpvagnskontakter, motor-värmar anslut ning ar",
            "key_personnel": [
                {
                    "name": "Fabr E Svensson",
                    "position": null
                }
            ]
        },
        "9": {
            "company_name": "EIE, MASKIN AB N A",
            "address": "Bandhagen 1, Box 7. Skebokvarnsv 370",
            "phone_number": "08-47 2610",
            "bank_details": {
                "bankgiro": "578-0028",
                "postgiro": "55798-3"
            },
            "activity": "Maskiner fabriksförnödenheter",
            "employees": 16,
            "annual_turnover": 9000000,
            "key_personnel": [
                {
                    "name": "Lennart Holmberg",
                    "position": null
                }
            ],
            "establishment_year": 1930
        },
        "10": {
            "company_name": "JANSON AB, ARTUR",
            "address": "Kristinehamn 1, Box 57. Lagmansg 1 B",
            "phone_number": "0550-153 15",
            "bank_details": {
                "bankgiro": "110-0130",
                "postgiro": "71980-7"
            },
            "activity": "Partihandel med plywood, träfiberplattor, spånplattor",
            "capital": 200000,
            "key_personnel": [
                {
                    "name": "Ing Albin Janson",
                    "position": null
                },
                {
                    "name": "Gunnar Janson",
                    "position": null
                }
            ],
            "establishment_year": 1923
        }
    }
}