{
    "original": "VÄSTERÅSBYGGEN, AB\n\nPnr 72211\n\nVästerås, Kungsg 5. Tel\n021-18 04 40. Bankgiro 80-8644.\nPostgiro 14989-8\n\nVerksamhet: Serviceorgan inom\nbyggnadsbranschen\nAntal anställda: 5\nAktiekapital: 5 000\nVerkst dir: Paul Waldemar\nSöderström\n\nEtableringsår: 1955.\n\nalkalion, ab\n\nPnr 43133\n\nMölndal, Möbelg 1. Tel 031-27 2035.\nBankgiro 415-7228. Postgiro 41111.\nTga Alkalab\n\nVerksamhet: Tillverkning o\nförsäljning av disk-, tvätt- o\nrengöringsmedel. Generalagent för Wyandotte\nChemicals Corporation, USA\nLokalkontor o lager:\nStockholm. Tel 08-18 8 3 60\nMalmö. Tel 040-61110\nHässleholm. Tel 0451-800 00\nSundsvall. Tel 060-10 09 19\nVarunamn: Erlon, Dryon, Poreen,\nSalute, Swarfeja, Tikon, Universal,\nZalpon\n\nAktiekapital: 5 000\n\nStyrelse: Dir Tage Ranström (ordf),\n\ndir Bill B Ericson, dir Olle Öster\n\nVerkst dir: Bill B Ericson\n\nEtableringsår: 1956\n\nDotterbolag till Astra-Dinol AB,\n\nHässleholm.\n\nahlqvist möbelfabrik,\nbruderna\n\nPnr 280 40\n\nSkånes Fagerhult. Tel\n0433-50001. Postgiro 94154-2\nVerksamhet: Tillverkar\nrotting-möbler\n\nChef: Fabr Axel Ahlqvist\nEtableringsår: 1930.\n\nahlqvist, byggnads ab\ngustav\n\nPnr 721 04\n\nVästerås 1, Engelbrektsg 9. Box\n42. Tel 021-11 03 60. Bankgiro\n35-6625. Postgiro 112941\nVerksamhet:\nByggnadsentreprenörfirma för bostads- o affärshus\nsamt industri- o\nförvaltningsbyggnader\n\nAntal anställda: 250\nÅrsomsättning: 32 000 000\nAktiekapital: 300 000\nStyrelse: Fru Barbro Ahlqvist\n(ordf), dir Gustav Ahlqvist, dir\nKnut Stiblert\nVerkst dir: Knut Stiblert\nEtableringsår: 1950\nOmbildat till aktiebolag 1957.\n\nallack, ab\n\nse Gränges Essem Allack.\n\nallans\nlädervaru-industri\n\nPnr 330 30\n\nGnosjö, Tel 0370-912 27.\nBankgiro 542-4668. Postgiro 321149-7\nVerksamhet: Tillverkar\nportmonnäer, plånböcker, etuier, fodral o\nandra smålädervaror\nAntal anställda: 18\nÅrsomsättning: 400000\nÄgare o chefer: Allan Ingemarson,\nAllan Andersson\nEtableringsår: 1946.\n\nFORSVIKS BRUK, AB\n\nPnr 540 42\n\nFors vik. Box 67. Tel 0505-410 10,\n410 48. Bankgiro 64-2355. Postgiro\n711630. Tga Forsviks, Karlsborg\nVerksamhet: Tillverkar gjutna rör\no rördelar. Beställningsgjutgods,\nexcenterpressar, mek arbeten\nVarunamn: Forsviks\nAntal anstäUda: 80\nÅrsomsättning: 4 000 000\nStyrelse: Dir L Fogelberg, fru M\nFogelberg, civiling Th Fogelberg\nEtableringsår: Bruket grundat på\n1300-talet\n\nOmbildat till aktiebolag 1869.\n\nFORSAKERS MEKANISKA\nVERKSTAD\n\nPnr 430 50\n\nKåUered. Postl 350. Tel\n031-75 0374. Postgiro 424936\nVerksamhet: Tillverkar\nmaskindetaljer\n\nÄgare o chef: Folke Olsson\nEtableringsår: 1945.\n\nBECKS IMPORT, AB\n\nPnr 21153\n\nMalmö, Monbijoug 9. Tel\n040-1148 57, 339 08. Bankgiro 87-5114.\nPostgiro 147972. Tga Beckimp\nVerksamhet: Säljer\nscenutrustningar, pumpar o fontäner\nAntal anställda: 7\nÅrsomsättning: 1500 000\nAktiekapital: 25 000\nVerkst dir: Nils A Flyckt\n(Trelleborg)\nEtableringsår: 1940.\n\nBECK &amp; SON, HOVBOK.\nBINDARE F\n\nPnr 11238\n\nStockholm, Kronobergsg 7. Tel\n08-50 02 65\n\nVerksamhet: Specialitet: gästböcker\nEtableringsår: 1840.\n\nAntal anställda: 40\nAktiekapital: 100 000\nStyrelse: Dir Leif Beckman (ordf),\ning Berndt Beckman, verkmäst Olof\nBeckman\n\nVerkst dir: Leif Beckman\nEtableringsår: 1921\nOmbildat till aktiebolag 1946.\n\nBECKER AB, PAUL\n\nPnr 26036\n\nHittaip, Box 38. Tel 042-926 44.\nBankgiro 864-1656. Postgiro\n566068-3. Tga Pebe\nVerksamhet: Importerar 0\nexporterar råvaror för pappersindustrin,\nspeciellt pappersavfall\nVerkst dir: Paul Becker\nEtableringsår: 1964.\n\nKARDELL AB, SVEN\n\nPnr 703 58\n\nÖrebro, Vallnäsg 16. Tel\n019-12 18 60. Bankgiro 358-7763.\nPostgiro 463402-8\n\nVerksamhet: städmaterial: moppar\nav bomull o nylon\nAktiekapital: 25 000\nStyrelse: Dir Sven Kardell (ordf),\nfra Ulla Kardell\n\nVerkst dir: Sven Kardell\nEtableringsår: 1945\nOmbildat till aktiebolag 1959.\n\nKARLAVERKEN I\nKUNGSBACKA AB\n\nPnr 434 01\n\nKungsbacka 1, Fack 139. Tel\n0300-40285. Bankgiro 42-6411.\nPostgiro 529911. Tga Karlaverken\nHuvudkontor o fabrik: Fjärås\nVerksamhet: Tillverkar\ntransport-materiel, såsom lastbryggor,\nrullbanor, rulltransportörer,\ntransportband, platåvagnar, bilvändskivor o\nannan transportutrustning,\nlagerinredningar m m\nAntal anställda: 50\nÅrsomsättning: 3 000 000\nAktiekapital: 136 000\nStyrelseordf: Disp Gunnar Tärby\nVerkst dir: Disp Gunnar Tärby\nEtableringsår: 1951.\n\nZAT\n\nVerksamhet: Byggnads- o\nventila-tionsplåtslageri. Utför arbeten i\nrostfritt o grövre järnplåt\nChef: Fabr Nils Zetterberg\nEtableringsån 1850.\n\nZETTERBERGS MEK\nVERKSTAD, AB\n\nPnr 740 46\n\nOstervåla, Box 5. Tel 0292-105 00.\nBankgiro 812-6294. Postgiro\n165453-2\n\nVerksamhet: Tillverkar o säljer\nhydrauliska tippanordningar,\nlastbilsflak, dumprar, boggilyftar o\nboggidrivanordningar,\nhydraulaggre-gat o tillbehör\n\nVarunamn: Marginal, Robsondrive,\nOstervåla-tippen\nAntal anställda: 120\nÅrsomsättning: 11 000 000\nAktiekapital: 100 000\nVerkst din Göte Zetterberg\nEtableringsàr: 1923\nOmbildat till aktiebolag 1959.\n\nZETTERBERG BYGGNADS\nAB. GUNNAR\n\nPnr 41109\n\nGöteborg, O Hamng 30-34. Tel\n031-17 60 90. Bankgiro 268-1336.\nPostgiro 12070-9\nVerksamhet: Husbyggnader,\nanläggningar, ombyggnader o\nreparationer\n\nAntal anställda: 110\nÅrsomsättning: 14 000 000\nAktiekapital: 300 000\nVerkst din Civiling Gunnar\nZetterberg\n\nArbetschefer: Ing Ingemar Jonsson,\ninsp Ola Olsson\nKamrer: Gudmar Bröjer\nEtableringsàr: 1921\nOmbildat till aktiebolag 1951.\n\nZEUTHEN &amp; AAGAARD, AB\n\nPnr 104 25\n\nStockholm 30, Strandbergsg 47. Box\n30028. Tel 08-22 54 00. Postgiro\n53317. Tga Rexproduct\nVerksamhet: Importerar o säljer\nstenciltryckmaskiner o tillbehör,\noffsettryckmaskiner o tillbehör,\ndikteringsmaskiner, räknemaskiner,\nfotokopieringsmaskiner samt\ntillbehör\n\nAvdelningskontor: Göteborg SV,\nFörsta Långg 12. Box 7054, Gbg 7.\nTel 031-124180\nMalmö 17, Box 17005.\nDavids-h alls g 16. Tel 040-719 85\nServicekontor: Borås, Falun,\nGävle, Jönköping, Kalmar, Karlstad,\nLinköping, Luleå, Norrköping,\nSkara, Skellefteå, Sundsvall, Umeå,\nUppsala, Västerås, Örebro\nVarunamn: Contex, Dennison,\nPho-to-Rex, Rex Recorder, Rex Rotary\nAntal anställda: 289\nÅrsomsättning: 28 000 000\nAktiekapital: 500000\nStyrelse: Adv S Waldenström, dir T\nCronberg, dir B von Reis, dir G B\nSilén, civiling O Zeuthen\nVeikst din Gösta B Silén\nEtableringsàr: 1931.\n\nZIG-ZAG FABRIKS AB\n\nPnr 640 32\n\nMalmköping, Box 50. Tel 0157-\n\n20133. Bankgiro 550-8932.\nPostgiro 579546-3\n\nVerksamhet: Tillverkning av\nbadrumsserien Furuett, förbands låd or,\netuier, heminredningsartiklar\nChef: Fabr Sven Johansson\nEtableringsàr: 1910.\n\nZODIAC SVENSKA AB\n\nPrr 104 60\n\nStockholm, Sickla Kanalv. Tel\n08-44 07 10. Bankgiro 483-54 68.\nPostgiro 196405-5. Tga Zodiac.\nTelex 10177\n\nVeiksamhet: Kommunikationsradio\no personsökningssystem\nAntal anställda: 35\nVerkst dir: Lennart Harderud\nEtableringsàr: 1964.\n\nZOÉGAS KAFFE AB\n\nPnr 252 53\n\nHälsingborg, Ängelholmsv 25. Tel\n042-126200. Bankgiro 86-3900,\n34O486. Postgiro 8000. Tga Zoega\nVerksamhet: Kafferosteri, handel\nmed kaffe o andra kolonialvaror\nsamt import o export av dessa varor\nAntal anställda: 54\nÅrsomsättning: 31700 000\nAktiekapital: 300 000\n\nVerkst dir: Thelma Zoéga\nEtableringsàr: 1886\n\nOmbildat till aktiebolag 1958.\n\nZORRO, AB\n\nPnr 11352\n\nStockholm, Döbelnsg 34 C. Tel\n08-3045 56, 32 45 16. Bankgiro\n295-8445. Postgiro 197088-8. Tga Zorro\nVerksamhet: Importerar o säljer\nplastfolier, plastbelagd väv m m.\nUtför plastsvetsning\nAktiekapital: 50 000\nVerkst dir. A Rob Pripp\nEtableringsån 1934.\n\nEGIR &amp; CO\n\nPnr 591 00\n\nMotala, Strandv 25. Tel\n0141-133 31, 17121. Bankgiro 134-1593,\n821-9198. Postgiro 443775-2\nVerksamhet: Uthyr maskiner o\nbyggnadsställningar. Utför\nsandblästring o fasadrenovering\nChef: K Egir\nEtableringsår: 1943.\n\nGRUPP.REKLAM, AB\n\nPnr 171 08\n\nSolna 8, Box 840. Villa Gröndal,\nUlriksdals Slottsområde. Tel\n08-85 02 20. Bankgiro 368-1277.\nPostgiro 405620-6\n\nVerksamhet: Utger Vi i Villa, Vi i\nFritidshus, Vi på Lantgård\nAntal anställda: 17\nAktiekapital: 5 000\nChefer: Hans Lindskog, Ulf\nSwenzén\n\nEtableringsår: 1958.\n\nGRUS- &amp; MAKADAM.\nPRODUKTER, AB\n\nPnr 402 31 Gbg 7\n\nMölndal, Jungfrustigen 4. Box 7059,\nGbg 7. Tel 031-87 02 20. Postgiro\n525595. Tga Grusmac\nVerksamhet: Driver grusgropar o\nbergkrossar. Säljer till\nbyggnadsindustrin\n\nAntal anställda: 75\nÅrsomsättning: 14 000 000\nAktiekapital: 100 000\nStyrelse: Dir Wilner Warnhammar\n(ordf), övering Sven Dahlström,\ndir Alf Kjellin\nVerkst dir: Alf Kjellin\nEtableringsår: 1958\nDotterbolag till AB Skånska\nCe-mentgjuteriet.\n\nGRUS &amp; SINGEL, AB\n\nPnr 611 01\n\nNyköping 1, Dammgruvan. Box 203.\nTel0155-148 34, 117 01. Bankgiro\n61-9082. Postgiro 298706\nVerksamhet: Tillverkar o säljer\ngrus, sand, singel, murbruk mm\nAntal anstäUda: 30\nÅrsomsättning: 3 500 000\nAktiekapital: 35 000\nVerkst dir: Ing Allan Olsson\nEtableringsår: 1946.\n\nMOON RADIO AB\n\nPnr 114 57\n\nStockholm, Riddarg 23 A. Tel\n08-63 03 60. Bankgiro 572-9405.\nPostgiro 57521-7. Tga Trysun.\nTelex 10475\n\nVerksamhet: Engrosförsäljning i\nradio- o televisionsmateriel\nNederlag: Göteborg, Erik\nDahl-bergsg 12. Tel 031-11 2275\nMalmö C, Friisg 6. Tel 040-312 23\nAntal anställda: 22\nÅrsomsättning: 5 000 000\nAktiekapital: 210 000\nVerkst dir Tryggve Sundin\nEtableringsår: 1934.\n\nERICHS AB, ÄKE\n\nPnr 217 53\n\nMalmö, Ribersborgsv 14 A. Tel\n040-9156 01, 915611. Bankgiro\n\n645-0035. Postgiro 39560-8. Telex\n32241\n\nVerksamhet: Säljer plastmaterial\no plastartiklar\nAktiekapital: 100 000\nVerkst dir: Ake Erichs\nEtableringsår: 1966.\n\nERIKSBERGS MEK\nVERKSTADS AB\n\nmed Division Lindholmen\n\nPnr 402 70\n\nGöteborg 8. Fack. Tel 22 8100,\nriks 031-513200. Postgiro 40779.\nTga Eriksbergia.\nTelex 2535 EBERGA S\n\nRIKSBERG\n\nVerksamhet: Bygger o reparerar\nfartyg i storlekar upp till 500 000\ntons dödvikt\nAntal anställda: 5 500\nÅrsomsättning: 400 000 000\nAktiekapital: 100 000 000\nVerkst dir: Bengt Eneroth\nTekn dirr: Thorsten Andersson,\nPer Alsën\n\nERIKSBERGS VÄVERI AB\n\nPnr 51101\n\nKinna 1, Box 38. Tel 0320-115 30.\nBankgiro 434-7167. Postgiro 30747.\nTga Erandertex\n\nVerksamhet: Tillverkar gardiner o\növerkasttyger\n\nFörsäljningskontor: Stockholm O,\nOstermalmsg 64. Tel 08-63 79 20\nAntal anställda: 50\nÅrsomsättning: 5 000 000\nAktiekapital: 301000\nVerkst dir: Bertil Erander\nEtableringsår: 1920\nOmbildat till aktiebolag 1932.\n\nERIKSDALS SNICKERI AB\n\nPnr 610 60\n\nTystberga. Tel 0155-60134.\nBankgiro 619-1241. Postgiro 284460-3\nVerksamhet; Tillverkar inredningar\nför skolor, kontor, sjukhus m m\nAntal anstäUda: 12\nÅrsomsättning: 700 000\nChef: Verner Andersson\nEtableringsår. 1944.",
    "structured": {
        "0": {
            "company_name": "VÄSTERÅSBYGGEN, AB",
            "pnr": "72211",
            "address": "Västerås, Kungsg 5",
            "phone_number": "021-18 04 40",
            "bank_details": {
                "bankgiro": "80-8644",
                "postgiro": "14989-8"
            },
            "activity": "Serviceorgan inom byggnadsbranschen",
            "employees": 5,
            "capital": 5000,
            "key_personnel": [
                {
                    "name": "Paul Waldemar Söderström",
                    "position": "Verkst dir"
                }
            ],
            "establishment_year": 1955
        },
        "1": {
            "company_name": "alkalion, ab",
            "pnr": "43133",
            "address": "Mölndal, Möbelg 1",
            "phone_number": "031-27 2035",
            "bank_details": {
                "bankgiro": "415-7228",
                "postgiro": "41111"
            },
            "activity": "Tillverkning o försäljning av disk-, tvätt- o rengöringsmedel. Generalagent för Wyandotte Chemicals Corporation, USA",
            "capital": 5000,
            "key_personnel": [
                {
                    "name": "Tage Ranström",
                    "position": "Styrelse: Dir"
                },
                {
                    "name": "Bill B Ericson",
                    "position": "Verkst dir"
                }
            ],
            "establishment_year": 1956
        },
        "2": {
            "company_name": "ahlqvist möbelfabrik, bruderna",
            "pnr": "280 40",
            "address": "Skånes Fagerhult",
            "phone_number": "0433-50001",
            "postgiro": "94154-2",
            "activity": "Tillverkar rotting-möbler",
            "employees": null,
            "establishment_year": 1930
        },
        "3": {
            "company_name": "ahlqvist, byggnads ab gustav",
            "pnr": "721 04",
            "address": "Västerås 1, Engelbrektsg 9. Box 42",
            "phone_number": "021-11 03 60",
            "bank_details": {
                "bankgiro": "35-6625",
                "postgiro": "112941"
            },
            "activity": "Byggnadsentreprenörfirma för bostads- o affärshus samt industri- o förvaltningsbyggnader",
            "employees": 250,
            "annual_turnover": 32000000,
            "capital": 300000,
            "key_personnel": [
                {
                    "name": "Fru Barbro Ahlqvist",
                    "position": "Styrelse: Ordf"
                },
                {
                    "name": "Gustav Ahlqvist",
                    "position": "Dir"
                },
                {
                    "name": "Knut Stiblert",
                    "position": "Dir, Verkst dir"
                }
            ],
            "establishment_year": 1950
        },
        "4": {
            "company_name": "allans lädervaru-industri",
            "pnr": "330 30",
            "address": "Gnosjö",
            "phone_number": "0370-912 27",
            "bank_details": {
                "bankgiro": "542-4668",
                "postgiro": "321149-7"
            },
            "activity": "Tillverkar portmonnäer, plånböcker, etuier, fodral o andra smålädervaror",
            "employees": 18,
            "annual_turnover": 400000,
            "key_personnel": [
                {
                    "name": "Allan Ingemarson",
                    "position": "Ägare, chef"
                },
                {
                    "name": "Allan Andersson",
                    "position": "Ägare, chef"
                }
            ],
            "establishment_year": 1946
        },
        "5": {
            "company_name": "FORSVIKS BRUK, AB",
            "pnr": "540 42",
            "address": "Fors vik. Box 67",
            "phone_number": "0505-410 10, 410 48",
            "bank_details": {
                "bankgiro": "64-2355",
                "postgiro": "711630"
            },
            "activity": "Tillverkar gjutna rör o rördelar. Beställningsgjutgods, excenterpressar, mek arbeten",
            "employees": 80,
            "annual_turnover": 4000000,
            "key_personnel": [
                {
                    "name": "L Fogelberg",
                    "position": "Dir"
                },
                {
                    "name": "M Fogelberg",
                    "position": "Fru, Dir"
                },
                {
                    "name": "Th Fogelberg",
                    "position": "Civiling, Dir"
                }
            ],
            "establishment_year": "Bruket grundat på 1300-talet, Ombildat till aktiebolag 1869"
        },
        "6": {
            "company_name": "FORSAKERS MEKANISKA VERKSTAD",
            "pnr": "430 50",
            "address": "KåUered. Postl 350",
            "phone_number": "031-75 0374",
            "postgiro": "424936",
            "activity": "Tillverkar maskindetaljer",
            "employees": null,
            "establishment_year": 1945
        },
        "7": {
            "company_name": "BECKS IMPORT, AB",
            "pnr": "21153",
            "address": "Malmö, Monbijoug 9",
            "phone_number": "040-1148 57, 339 08",
            "bank_details": {
                "bankgiro": "87-5114",
                "postgiro": "147972"
            },
            "activity": "Säljer scenutrustningar, pumpar o fontäner",
            "employees": 7,
            "annual_turnover": 1500000,
            "capital": 25000,
            "key_personnel": [
                {
                    "name": "Nils A Flyckt",
                    "position": "Verkst dir"
                }
            ],
            "establishment_year": 1940
        },
        "8": {
            "company_name": "BECK & SON, HOVBOK. BINDARE F",
            "pnr": "11238",
            "address": "Stockholm, Kronobergsg 7",
            "phone_number": "08-50 02 65",
            "activity": "Specialitet: gästböcker",
            "employees": 40,
            "capital": 100000,
            "key_personnel": [
                {
                    "name": "Leif Beckman",
                    "position": "Styrelse: Ordf, Verkst dir"
                }
            ],
            "establishment_year": "1921, Ombildat till aktiebolag 1946"
        },
        "9": {
            "company_name": "BECKER AB, PAUL",
            "pnr": "26036",
            "address": "Hittaip, Box 38",
            "phone_number": "042-926 44",
            "bank_details": {
                "bankgiro": "864-1656",
                "postgiro": "566068-3"
            },
            "activity": "Importerar 0 exporterar råvaror för pappersindustrin, speciellt pappersavfall",
            "employees": null,
            "establishment_year": 1964
        },
        "10": {
            "company_name": "KARDELL AB, SVEN",
            "pnr": "703 58",
            "address": "Örebro, Vallnäsg 16",
            "phone_number": "019-12 18 60",
            "bank_details": {
                "bankgiro": "358-7763",
                "postgiro": "463402-8"
            },
            "activity": "Städmaterial: moppar av bomull o nylon",
            "capital": 25000,
            "key_personnel": [
                {
                    "name": "Sven Kardell",
                    "position": "Styrelse: Ordf, Verkst dir"
                }
            ],
            "establishment_year": "1945, Ombildat till aktiebolag 1959"
        }
    }
}