{
    "original": "BAYER FARMA AB\n\nPnr 102 61\n\nStockholm 4, Box 4009. Asög 142.\nTel 08-44 0115, 40 20 15. Bankgiro\nTga Bayerfarma. Telex 17071\nVerksamhet: Ensamrepresentant för\nFarbenfabriken Bayers\nfarmacev-tiska specialiteter o finkemikalier\no veterinärprodukter\nVarunamn: Bayer\nAntal anställda: 18\nAktiekapital: 300 000\nVerkst dir: Börje Thulin\nFörsäljn-chef: Hans Vielhauer\nInformationsavdelningen: Chef\napotekare Jörgen Tersin\nApotekare: R Arensberg\nEtableringsår: 1961.\n\nJACOBI, FIRMA F A W\n\nPnr 112 65\n\nStockholm, Stenkullav 9. Tel\n08-13 13 50. Postgiro 53002-2. Telex\n1658. Tga Ullimport, Kemimport\nVeiksamhet: Grosshandel o\nagenturrörelse\n\nAntal anställda: 12\n\nChef: Dir P Jacobi\nEtableringsår: 1916.\n\nDAR\n\n042-970 10. Bankgiro 188-2968.\nPostgiro 686440-9\nVerksamhet: Utför isolering med\nskumplast o mineralull\nAntal anställda: 14\nAktiekapital: 20 000\nVerkst dir: Karl-Erik Birgersson\nEtableringsår: 1966.\n\nJOH\n\nning av inredningsmaterial\nEtableringsår: 1896\nOmbildat till aktiebolag 1957.\n\nJOHANSSON, AB CALEB &amp; TH\n\nPnr 313 00\n\nOskarström, Sennanv 64. Box 120.\nTel 035-60115, 60245. Bankgiro\n427-3132. Postgiro 92102-3\nVerksamhet: Säljer snickerier,\nträvaror o byggnadsmaterial\nAntal anställda: 20\nAktiekapital: 164 000\nVerkst dir: Eskil Johansson\nEtableringsår: 1930.\n\nJOHANSSONS MASKIN &amp;\nJÄRNVARU AB, CARL\n\nPnr 44020\n\nVårgårda, Box 58. Kungsg 55 A.\nTel 0322-200 12, 204 58. Bankgiro\n894-9075. Postgiro 22686-0\nVerksamhet: Järnvaror,\nlantbruksmaskiner o motorsågar\nAntal anställda: 16\nÅrsomsättning: 7 000 000\nAktiekapital: 100000\nVerkst dir. Gustaf Karlsson\nEtableringsår. 1870.\n\nVAL\n\n30 44 93,30 4 4 99. Bankgiro 72-4512.\nPostgiro 2036\n\nVerksamhet Säljer vävplast för\nbil, båt, buss samt möbelspik\nAntal anställda: 3\nAktiekapital: 75000\nVerkst dir: Hans Wahlström\nEtableringsår: 1897.\n\nHUZELLS I MALMÖ AB\n\nPnr 212 24\n\nMalmö. Lundav 143. Tel\n040-93 59 50. Bankgiro 264-2213.\nPostgiro 431575-0. Telex 32552\nVerksamhet: Maskiner o verktyg\nför bil- o gummiverkstäder,\nautomo-biltillbehör o reservdelar engros\nAktiekapital: 100 000\nVerkst dir: Sten Marcusson-Ståhl\nDisp: Sten Carlson\nEtableringsår 1952.\n\nTRYCKROR, AB\n\nPnr 200 61\n\nMalmö 30, Barlastg. Box 30062. Tel\n040-15 30 50. Bankgiro 87-0190.\nPostgiro 249937. Tga SENCON.\nTelex 32457 SENCON S\nVerksamhet: Tillverkar Sentabrör\n(förspända betongrör), Bonnarör\n(stålbetongrör) samt\ncentrifuge-rade betongrör\nAntal anstäUda: 200\nÅrsomsättning: 15 000 000\nAktiekapital: 3 600 000\nVerkst dir: Civiling Ludvig von\nMühlenfels\nEtableringsån 1944.\n\nFOGELMARK AB,ROLF\n\nPnr 411 21\n\nGöteborg, Stora Badhusg 20. Tel\n031-135282,135283.Bankgiro\n51-1659. Postgiro 520711. Tga\nRolfbox. Telex 2536\n\nVerksamhet: Säljer sågade o\nhyvlade trävaror av alla slag, ävensom\nträfiberplattor o Sundries\nAntal anställda: 4\nÅrsomsättning: 8 000 000\nAktiekapital: 30000\nVerkst dir: Rolf V Fogelmark\nEtableringsår: 1955\nSysterföretag Firma Rolf\nFogelmark.\n\nFOG EL ST ROMS AB, F\n\nPnr 124 21\n\nBandhagen 1, Box 51. Stallarholmsv\n15. Tel 08-47 29 00. Bankgiro\n478-2330. Postgiro 2974-4. Tga\nFogel-strömbolag. Telex 1863\nVerksamhet: Auktoriserade\nskeppsklarerare o speditörer, åkeri,\nmagasinering\n\nAvdelningskontor: Stockholms\nFrihamn, Göteborg, Helsingborg, Malmö\nAntal anstäUda: 27\nAktiekapital: 250 000\nVerkst dir: C-O Pettersson\nEtableringsår 1897.\n\nDENNEL AB,HAGBARD\n\nPnr 11182\n\nStockholm, Skeppsbron 18. Box\n1202. Tel 08-23 59 50. Postgiro\n151444. Tga Dennelab.\nTelex 19162, 1462\nVerksamhet: Skeppsklarerare,\nbe-fraktningsagenter o speditörer\nAktiekapital: 100000\nVerkst dir: Bo Dennel\nEtableringsår: 1936.\n\nSTIGEN AB, FOLKE\n\nPnr 41120\n\nGöteborg, Hvitfeldtsg 14. Tel\n031-17 75 75. Bankgiro 337-4600.\nPostgiro 44352-3. Tga Herbertlack.\nTelex 21107 STIGEN S\nVerksamhet: Säljer bil- o\nindustri-läcker, grundmaterial o\nslipmaterial\n\nLager: Göteborg C.Kungshöjdsg 3\nAvdelningskontor: Limhamn,\nJärn-vägsg 9. Tel 040-15 92 70,15 92 71\nSolna, Englundav 3-5. Tel\n08-29 43 00, 29 4400, 28 60 90\nUmeå 5, Jäg arv 12. Tel 090-12 26 50\nAntal anställda: 40\nÅrsomsättning: 3 500 000\nAktiekapital: 100 000\nVerkst dir: Folke Stigen\nEtableringsår: 1958.",
    "structured": {
        "0": {
            "company_name": "BAYER FARMA AB",
            "pnr": "102 61",
            "address": "Stockholm 4, Box 4009. Asög 142.",
            "phone_number": "08-44 0115, 40 20 15",
            "bank_details": {
                "bankgiro": "Bayerfarma"
            },
            "activity": "Ensamrepresentant för Farbenfabriken Bayers farmaceutiska specialiteter o finkemikalier o veterinärprodukter",
            "employees": 18,
            "capital": 300000,
            "key_personnel": [
                {
                    "name": "Börje Thulin",
                    "position": "Verkst dir"
                },
                {
                    "name": "Hans Vielhauer",
                    "position": "Försäljn-chef"
                },
                {
                    "name": "Jörgen Tersin",
                    "position": "Informationsavdelningen"
                },
                {
                    "name": "R Arensberg",
                    "position": "Apotekare"
                }
            ],
            "establishment_year": 1961
        },
        "1": {
            "company_name": "JACOBI, FIRMA F A W",
            "pnr": "112 65",
            "address": "Stockholm, Stenkullav 9",
            "phone_number": "08-13 13 50",
            "bank_details": {
                "postgiro": "53002-2"
            },
            "activity": "Grosshandel o agenturrörelse",
            "employees": 12,
            "key_personnel": [
                {
                    "name": "Dir P Jacobi",
                    "position": "Chef"
                }
            ],
            "establishment_year": 1916
        },
        "2": {
            "company_name": "DAR",
            "phone_number": "042-970 10",
            "bank_details": {
                "bankgiro": "188-2968",
                "postgiro": "686440-9"
            },
            "activity": "Utför isolering med skumplast o mineralull",
            "employees": 14,
            "capital": 20000,
            "key_personnel": [
                {
                    "name": "Karl-Erik Birgersson",
                    "position": "Verkst dir"
                }
            ],
            "establishment_year": 1966
        },
        "3": {
            "company_name": "JOH",
            "establishment_year": 1896,
            "additional_info": "Ombildat till aktiebolag 1957."
        },
        "4": {
            "company_name": "JOHANSSON, AB CALEB & TH",
            "pnr": "313 00",
            "address": "Oskarström, Sennanv 64. Box 120.",
            "phone_number": "035-60115, 60245",
            "bank_details": {
                "bankgiro": "427-3132",
                "postgiro": "92102-3"
            },
            "activity": "Säljer snickerier, trävaror o byggnadsmaterial",
            "employees": 20,
            "capital": 164000,
            "key_personnel": [
                {
                    "name": "Eskil Johansson",
                    "position": "Verkst dir"
                }
            ],
            "establishment_year": 1930
        },
        "5": {
            "company_name": "JOHANSSONS MASKIN & JÄRNVARU AB, CARL",
            "pnr": "44020",
            "address": "Vårgårda, Box 58. Kungsg 55 A",
            "phone_number": "0322-200 12, 204 58",
            "bank_details": {
                "bankgiro": "894-9075",
                "postgiro": "22686-0"
            },
            "activity": "Järnvaror, lantbruksmaskiner o motorsågar",
            "employees": 16,
            "annual_turnover": 7000000,
            "capital": 100000,
            "key_personnel": [
                {
                    "name": "Gustaf Karlsson",
                    "position": "Verkst dir"
                }
            ],
            "establishment_year": 1870
        },
        "6": {
            "company_name": "VAL",
            "phone_number": "30 44 93,30 4 4 99",
            "bank_details": {
                "bankgiro": "72-4512",
                "postgiro": "2036"
            },
            "activity": "Säljer vävplast för bil, båt, buss samt möbelspik",
            "employees": 3,
            "capital": 75000,
            "key_personnel": [
                {
                    "name": "Hans Wahlström",
                    "position": "Verkst dir"
                }
            ],
            "establishment_year": 1897
        },
        "7": {
            "company_name": "HUZELLS I MALMÖ AB",
            "pnr": "212 24",
            "address": "Malmö. Lundav 143",
            "phone_number": "040-93 59 50",
            "bank_details": {
                "bankgiro": "264-2213",
                "postgiro": "431575-0"
            },
            "activity": "Maskiner o verktyg för bil- o gummiverkstäder, automo-biltillbehör o reservdelar engros",
            "capital": 100000,
            "key_personnel": [
                {
                    "name": "Sten Marcusson-Ståhl",
                    "position": "Verkst dir"
                },
                {
                    "name": "Sten Carlson",
                    "position": "Disp"
                }
            ],
            "establishment_year": 1952
        },
        "8": {
            "company_name": "TRYCKROR, AB",
            "pnr": "200 61",
            "address": "Malmö 30, Barlastg. Box 30062",
            "phone_number": "040-15 30 50",
            "bank_details": {
                "bankgiro": "87-0190",
                "postgiro": "249937"
            },
            "activity": "Tillverkar Sentabrör (förspända betongrör), Bonnarör (stålbetongrör) samt centrifuge-rade betongrör",
            "employees": 200,
            "annual_turnover": 15000000,
            "capital": 3600000,
            "key_personnel": [
                {
                    "name": "Civiling Ludvig von Mühlenfels",
                    "position": "Verkst dir"
                }
            ],
            "establishment_year": 1944
        },
        "9": {
            "company_name": "FOGELMARK AB,ROLF",
            "pnr": "411 21",
            "address": "Göteborg, Stora Badhusg 20",
            "phone_number": "031-135282,135283",
            "bank_details": {
                "bankgiro": "51-1659",
                "postgiro": "520711"
            },
            "activity": "Säljer sågade o hyvlade trävaror av alla slag, ävensom träfiberplattor o Sundries",
            "employees": 4,
            "annual_turnover": 8000000,
            "capital": 30000,
            "key_personnel": [
                {
                    "name": "Rolf V Fogelmark",
                    "position": "Verkst dir"
                }
            ],
            "establishment_year": 1955,
            "additional_info": "Systerföretag Firma Rolf Fogelmark"
        },
        "10": {
            "company_name": "FOG EL ST ROMS AB, F",
            "pnr": "124 21",
            "address": "Bandhagen 1, Box 51. Stallarholmsv 15",
            "phone_number": "08-47 29 00",
            "bank_details": {
                "bankgiro": "478-2330",
                "postgiro": "2974-4"
            },
            "activity": "Auktoriserade skeppsklarerare o speditörer, åkeri, magasinering",
            "employees": 27,
            "capital": 250000,
            "key_personnel": [
                {
                    "name": "C-O Pettersson",
                    "position": "Verkst dir"
                }
            ],
            "establishment_year": 1897
        },
        "11": {
            "company_name": "DENNEL AB,HAGBARD",
            "pnr": "11182",
            "address": "Stockholm, Skeppsbron 18. Box 1202",
            "phone_number": "08-23 59 50",
            "bank_details": {
                "postgiro": "151444"
            },
            "activity": "Skeppsklarerare, be-fraktningsagenter o speditörer",
            "capital": 100000,
            "key_personnel": [
                {
                    "name": "Bo Dennel",
                    "position": "Verkst dir"
                }
            ],
            "establishment_year": 1936
        },
        "12": {
            "company_name": "STIGEN AB, FOLKE",
            "pnr": "41120",
            "address": "Göteborg, Hvitfeldtsg 14",
            "phone_number": "031-17 75 75",
            "bank_details": {
                "bankgiro": "337-4600",
                "postgiro": "44352-3"
            },
            "activity": "Säljer bil- o industri-läcker, grundmaterial o slipmaterial",
            "employees": 40,
            "annual_turnover": 3500000,
            "capital": 100000,
            "key_personnel": [
                {
                    "name": "Folke Stigen",
                    "position": "Verkst dir"
                }
            ],
            "establishment_year": 1958
        }
    }
}