{
    "original": "INTERSCANDIA MASKIN AB\n\nPnr 11452\n\nStockholm, Skepparg 22. Tel\n08-60 60 11, 63 16 20. Tga Interscandia\n\nVeiksamhet: Säljer jordfräsar o\n\ndikningsmaskiner\n\nAktiekapital: 5000\n\nVerkst dir: Hans Rune Aggenberg\n\nEtableringsår: 1945.\n\nTRANSITFRAKT AB\n\nPnr 25102\n\nHelsingborg 1, Box 69. Hamntorget\n3.Tel 042-12 60 70. Tga Transfrakt.\nTelex 72226\n\nVerksamhet: Biltransporter\nAntal anställda: 5\nÅrsomsättning: 2 500 000\nAktiekapital: 100 000\nVerkst dir: Ake Widner\nEtableringsår: 1966.\n\nMEL\n\nSkövde. Per-Olof Brink. Tel\n0500-174 22, 81160\n\nGöteborg. SRydeen.Tel031-28 00 10\nVarunamn: Mellby\nAntal anställda: 50\nÅrsomsättning: 6 000 000\nAktiekapital: 75 000\nVerkst dir: Oscar Andersson\nEtableringsår: 1943\nOmbildat till aktiebolag 1962.\n\nMELLERUD PLAST AB\n\nPnr 464 00\n\nMellerud, Industriområdet. Tel\n0530-120 00. Bankgiro 53-3780.\nPostgiro 95090. Tga Mellerudplast\nVerksamhet: Pormblåsning,\nformsprutning o verktygstillverkning\nAntal anställda: 70\nVerkst dir: Disp L Steen\nEtableringsår: 1962.\n\nWIGART &amp; CO AB. LUDVIG\n\nPnr 25103\n\nHelsingborg, Järnvägsg 13. Tel\n042-13 93 80. Postgiro 36939-7\nVerksamhet: Textilvaror o leksaker\nen gros\n\nAntal anställda: 120\nÅrsomsättning: 24 000 000\nAktiekapital: 930 000\nVerkst din Gösta Thomasson\nEtableringsår: 1896.\n\nGIGANTIC, MASKIN AB\n\nPnr 810 28\n\nJärbo. Tel 0290-706 10. Bankgiro\n787-6147. Postgiro 74532-3. Tga\nGigantic\n\nVerksamhet: Tillverkar o säljer\nGigantic lastmaskiner. Säljer Ford\ntraktorer\n\nVarunamn: Gigantic\nAntal anställda: 40\nÅrsomsättning: 7 000 000\nAktiekapital: 750 000\nStyrelse: Ing Hjalmar Kämpe, disp\n\nGöran Hedlund\n\nVerkst dir Ing Hjalmar Kämpe\nEtableringsår: 1923.\n\nGULLBERG &amp; CO, AB H\n\nPnr 11157\n\nStockholm, Mäster Samuelsg 42.\nTel 08-23 77 40. Bankgiro 44-6770.\nPostgiro 151056-9. Tga Gullbergs\nVerksamhet: Försäkringsfirma,\nrepresentanter i Sverige för The\nLiverpool &amp; London &amp; Globe\nInsurance Company Limited o The\nRoyal Insurance Company Limited,\nLiverpool i automobil- o\nmotorcykelförsäkringar, Royal i brand- o\nkombinerade försäkringar.\nGeneralagentur för Trygg-Hansa m fi\nbolag\n\nAntal anställda: 9\nAktiekapital: 50000\nStyrelse: Ryttmäst Ulf H:son\nGullberg (ordf), fru Birgit Gullberg,\ndir Staffan U:son Gullberg, dir Hans\nW Cappelen\n\nVerkst dir: Staffan U:son Gullberg\nEtableringsår: 1909.\n\nOPTIMUS, AB\n\nPnr 194 00\n\nUpplands Väsby. Tel 0760-301 50.\nBankgiro 745-3327. Postgiro5041-9.\nTga Optimus, Stockholm.\nTelex 17856\n\nVerksamhet: Fotogen- o\nbensinför-greningsapparater, gasolapparater.\nLås o dörrstängare\nVarunamn: Anchor, Optimus,\nPrimus, Radius, Sievert, Svea\nAntal anställda: 450\nÅrsomsättning: 30 000000\nAktiekapital: 10000 000\nVerkst. dir: Qik Grunander\nEtableringsår: 1899.\n\nKAR\n\nKARLSSONS\nKARTONG-FABRIK, AB GUST\n\nPnr 60105\n\nNorrköping 1. Pabriksg 8. Box 409.\nTel 011-122166. Bankgiro 82-6017.\nPostgiro 81640\n\nVerksamhet: Tillverkar emballage,\narkivkartonger o mappar\nAktiekapital: 30 000\nVerkst dir: Holger Rappestad\nEtableringsår: 1906\nOmbildat till aktiebolag 1942.\n\nCARLSSON I SUNDBYBERG\nAB, GUSTAF\n\nPnr 172 21 Sundbyberg 1\nBromma, Karlsbodav 16-18. Box 8,\nSundbyberg 1. Tel 08-28 27 40.\nPostgiro 72791-7. Tga Metall\nVerksamhet: Köper o säljer\njärn-o metallskrot\nAktiekapital: 50 000\nVerkst dir: Nils Berg\nV verkst dir: G Carlsson\nEtableringsår: 1916\nÄges av Stena AB, Göteborg.\n\nKARLSSON HJO AB, GUSTAV\n\nPnr 544 00\n\nHjo, Ängg. Tel 0503-100 36\nVerksamhet: Tillverkar\nskjutdörrs-beslag, magasinkärror, kabelskåp\nm m\n\nAktiekapital: 30 000\nVerkst dir: Ing Per Fritzon\nEtableringsår: 1958.\n\nCARLSSONS\nPLÄT-INDUSTRI, AB GÖSTA\n\nPnr 593 00\n\nVästervik, Perug 49. Tel\n0490-108 25\n\nVerksamhet: Tillverkar alla slags\nplåtarbeten för byggnads- o\nindustrianläggningar m m, även\nrostfritt\n\nVerkst dir: Gösta Carlsson\nEtableringsår: 1959.\n\nKARLSSON, BYGGNADS AB\nHARRY\n\nPnr 221 04\n\nLund 1, Bred g 13. Box 1136. Tel\n046-117970. Bankgiro 869-2907.\nPostgiro 37611-1\nVerksamhet: Byggnadsrörelse\nAvdelningskontor: Hälsingborg,\nDrottningg 20. Tel 042-14 6210\nAntal anställda: 400\nÅrsomsättning: 50 000 000\nAktiekapital: 250 0 00\nVerkst dir: Kurt Månsson\nEtableringsår: 1936.\n\nX-TEGEL, NYA AB\n\nPnr 136 01\n\nHanden 1, Box 12. Jordbro\nIndustriområde. Tel 0750-221 00.\nBankgiro 748-1211. Postgiro 285696-1\nVerksamhet: Skogsavdelning,\nbil-o maskinavdelning, byggvaruhus,\ngrus, murbruk, brädgård- o\nentreprenadavdelning\nAntal anställda: 65\nÅrsomsättning: 12 000 000\nAktiekapital: 25 0 000\nVerkst dir: David Ericson\nEtableringsår: 1925.\n\nYDREFORSTRÄ.\nFURÄDLINGS AB\n\nPnr 590 81\n\nGullringen, Ydrefors. Tel\n0492-800 24. Bankgiro 452-0466.\nPostgiro 143241\n\nVerksamhet: Tillverkar sågade\nträvaror\n\nAntal anställda: 15\nÅrsomsättning: 2 000 000\nAktiekapital: 100 000\nVerkst dir: Disp Oskar Andersson\nEtableringsår: 1928.\n\nSEDAPLAST AB\n\nPnr 332 00\n\nGislaved, Sågareg.Tel 0371-102 25\nVerksamhet: Tillverkar härd- o\nthermoplaster\nAktiekapital: 20 000\nVerkst dir I S L Dahl\nEtableringsår. 1946.",
    "structured": {
        "1": {
            "company_name": "INTERSCANDIA MASKIN AB",
            "pnr": "11452",
            "address": "Stockholm, Skepparg 22",
            "phone_number": "08-60 60 11, 63 16 20",
            "activity": "Säljer jordfräsar o dikningsmaskiner",
            "capital": 5000,
            "key_personnel": [
                {
                    "name": "Hans Rune Aggenberg",
                    "position": "Verkst dir"
                }
            ],
            "establishment_year": 1945
        },
        "2": {
            "company_name": "TRANSITFRAKT AB",
            "pnr": "25102",
            "address": "Helsingborg 1, Box 69",
            "phone_number": "042-12 60 70",
            "activity": "Biltransporter",
            "employees": 5,
            "annual_turnover": 2500000,
            "capital": 100000,
            "key_personnel": [
                {
                    "name": "Ake Widner",
                    "position": "Verkst dir"
                }
            ],
            "establishment_year": 1966
        },
        "3": {
            "company_name": "MEL",
            "address": "Skövde",
            "phone_number": "0500-174 22, 81160",
            "activity": "Varunamn: Mellby",
            "employees": 50,
            "annual_turnover": "6 000 000",
            "capital": 75000,
            "key_personnel": [
                {
                    "name": "Oscar Andersson",
                    "position": "Verkst dir"
                }
            ],
            "establishment_year": 1943,
            "other_info": "Ombildat till aktiebolag 1962."
        },
        "4": {
            "company_name": "MELLERUD PLAST AB",
            "pnr": "464 00",
            "address": "Mellerud, Industriområdet",
            "phone_number": "0530-120 00",
            "bank_details": {
                "bankgiro": "53-3780",
                "postgiro": "95090"
            },
            "activity": "Pormblåsning, formsprutning o verktygstillverkning",
            "employees": 70,
            "key_personnel": [
                {
                    "name": "Disp L Steen",
                    "position": "Verkst dir"
                }
            ],
            "establishment_year": 1962
        },
        "5": {
            "company_name": "WIGART & CO AB. LUDVIG",
            "pnr": "25103",
            "address": "Helsingborg, Järnvägsg 13",
            "phone_number": "042-13 93 80",
            "activity": "Verksamhet: Textilvaror o leksaker en gros",
            "employees": 120,
            "annual_turnover": "24 000 000",
            "capital": 930000,
            "key_personnel": [
                {
                    "name": "Gösta Thomasson",
                    "position": "Verkst din"
                }
            ],
            "establishment_year": 1896
        },
        "6": {
            "company_name": "GIGANTIC, MASKIN AB",
            "pnr": "810 28",
            "address": "Järbo",
            "phone_number": "0290-706 10",
            "bank_details": {
                "bankgiro": "787-6147",
                "postgiro": "74532-3"
            },
            "activity": "Verksamhet: Tillverkar o säljer Gigantic lastmaskiner. Säljer Ford traktorer",
            "employees": 40,
            "annual_turnover": "7 000 000",
            "capital": 750000,
            "key_personnel": [
                {
                    "name": "Ing Hjalmar Kämpe",
                    "position": "Styrelse"
                },
                {
                    "name": "Göran Hedlund",
                    "position": "Disp"
                },
                {
                    "name": "Ing Hjalmar Kämpe",
                    "position": "Verkst dir"
                }
            ],
            "establishment_year": 1923
        },
        "7": {
            "company_name": "GULLBERG & CO, AB H",
            "pnr": "11157",
            "address": "Stockholm, Mäster Samuelsg 42",
            "phone_number": "08-23 77 40",
            "bank_details": {
                "bankgiro": "44-6770",
                "postgiro": "151056-9"
            },
            "activity": "Försäkringsfirma, representanter i Sverige för The Liverpool & London & Globe Insurance Company Limited o The Royal Insurance Company Limited, Liverpool i automobil- o motorcykelförsäkringar, Royal i brand- o kombinerade försäkringar. Generalagentur för Trygg-Hansa m fi bolag",
            "employees": 9,
            "capital": 50000,
            "key_personnel": [
                {
                    "name": "Ryttmäst Ulf H:son Gullberg",
                    "position": "Styrelse (ordf)"
                },
                {
                    "name": "fru Birgit Gullberg",
                    "position": "Styrelse"
                },
                {
                    "name": "dir Staffan U:son Gullberg",
                    "position": "Dir"
                },
                {
                    "name": "dir Hans W Cappelen",
                    "position": "Dir"
                },
                {
                    "name": "Staffan U:son Gullberg",
                    "position": "Verkst dir"
                }
            ],
            "establishment_year": 1909
        },
        "8": {
            "company_name": "OPTIMUS, AB",
            "pnr": "194 00",
            "address": "Upplands Väsby",
            "phone_number": "0760-301 50",
            "bank_details": {
                "bankgiro": "745-3327",
                "postgiro": "5041-9"
            },
            "activity": "Fotogen- o bensinför-greningsapparater, gasolapparater. Lås o dörrstängare",
            "employees": 450,
            "annual_turnover": 30000000,
            "capital": 10000000,
            "key_personnel": [
                {
                    "name": "Qik Grunander",
                    "position": "Verkst. dir"
                }
            ],
            "establishment_year": 1899
        },
        "9": {
            "company_name": "KARLSSONS KARTONG-FABRIK, AB GUST",
            "pnr": "60105",
            "address": "Norrköping 1, Pabriksg 8, Box 409",
            "phone_number": "011-122166",
            "bank_details": {
                "bankgiro": "82-6017",
                "postgiro": "81640"
            },
            "activity": "Tillverkar emballage, arkivkartonger o mappar",
            "capital": 30000,
            "key_personnel": [
                {
                    "name": "Holger Rappestad",
                    "position": "Verkst dir"
                }
            ],
            "establishment_year": 1906,
            "other_info": "Ombildat till aktiebolag 1942."
        },
        "10": {
            "company_name": "CARLSSON I SUNDBYBERG AB, GUSTAF",
            "pnr": "172 21 Sundbyberg 1 Bromma, Karlsbodav 16-18, Box 8, Sundbyberg 1",
            "phone_number": "08-28 27 40",
            "bank_details": {
                "postgiro": "72791-7"
            },
            "activity": "Köper o säljer järn-o metallskrot",
            "capital": 50000,
            "key_personnel": [
                {
                    "name": "Nils Berg",
                    "position": "Verkst dir"
                },
                {
                    "name": "G Carlsson",
                    "position": "V verkst dir"
                }
            ],
            "establishment_year": 1916,
            "other_info": "Äges av Stena AB, Göteborg."
        },
        "11": {
            "company_name": "KARLSSON HJO AB, GUSTAV",
            "pnr": "544 00",
            "address": "Hjo, Ängg",
            "phone_number": "0503-100 36",
            "activity": "Tillverkar skjutdörrs-beslag, magasinkärror, kabelskåp m m",
            "capital": 30000,
            "key_personnel": [
                {
                    "name": "Ing Per Fritzon",
                    "position": "Verkst dir"
                }
            ],
            "establishment_year": 1958
        },
        "12": {
            "company_name": "CARLSSONS PLÄT-INDUSTRI, AB GÖSTA",
            "pnr": "593 00",
            "address": "Västervik, Perug 49",
            "phone_number": "0490-108 25",
            "activity": "Tillverkar alla slags plåtarbeten för byggnads- o industri-anläggningar m m, även rostfritt",
            "key_personnel": [
                {
                    "name": "Gösta Carlsson",
                    "position": "Verkst dir"
                }
            ],
            "establishment_year": 1959
        },
        "13": {
            "company_name": "KARLSSON, BYGGNADS AB HARRY",
            "pnr": "221 04",
            "address": "Lund 1, Bred g 13, Box 1136",
            "phone_number": "046-117970",
            "bank_details": {
                "bankgiro": "869-2907",
                "postgiro": "37611-1"
            },
            "activity": "Byggnadsrörelse",
            "other_info": "Avdelningskontor: Hälsingborg, Drottningg 20. Tel 042-14 6210",
            "employees": 400,
            "annual_turnover": "50 000 000",
            "capital": 250000,
            "key_personnel": [
                {
                    "name": "Kurt Månsson",
                    "position": "Verkst dir"
                }
            ],
            "establishment_year": 1936
        },
        "14": {
            "company_name": "X-TEGEL, NYA AB",
            "pnr": "136 01",
            "address": "Handen 1, Box 12, Jordbro Industriområde",
            "phone_number": "0750-221 00",
            "bank_details": {
                "bankgiro": "748-1211",
                "postgiro": "285696-1"
            },
            "activity": "Skogsavdelning, bil-o maskinavdelning, byggvaruhus, grus, murbruk, brädgård- o entreprenadavdelning",
            "employees": 65,
            "annual_turnover": "12 000 000",
            "capital": 250000,
            "key_personnel": [
                {
                    "name": "David Ericson",
                    "position": "Verkst dir"
                }
            ],
            "establishment_year": 1925
        },
        "15": {
            "company_name": "YDREFORSTRÄ. FURÄDLINGS AB",
            "pnr": "590 81",
            "address": "Gullringen, Ydrefors",
            "phone_number": "0492-800 24",
            "bank_details": {
                "bankgiro": "452-0466",
                "postgiro": "143241"
            },
            "activity": "Tillverkar sågade trävaror",
            "employees": 15,
            "annual_turnover": "2 000 000",
            "capital": 100000,
            "key_personnel": [
                {
                    "name": "Disp Oskar Andersson",
                    "position": "Verkst dir"
                }
            ],
            "establishment_year": 1928
        },
        "16": {
            "company_name": "SEDAPLAST AB",
            "pnr": "332 00",
            "address": "Gislaved, Sågareg",
            "phone_number": "0371-102 25",
            "activity": "Tillverkar härd- o thermoplaster",
            "capital": 20000,
            "key_personnel": [
                {
                    "name": "I S L Dahl",
                    "position": "Verkst dir"
                }
            ],
            "establishment_year": 1946
        }
    }
}