{
    "original": "GLASDON AB\n\nPnr 400 12\n\nGöteborg 19. Gibraltarg 2. Box\n19029. Tel 031-18 58 81, 18 09 20.\nBankgiro 51-4896. Postgiro\n45841-4. Tga Glasdon.\nTelex 20994\n\nVerksamhet: Säljer ur, optiska\nartiklar, termometrar,\nlaboratorieglas, glasfiberprodukter,\nkvartsprodukter samt meteorologiska\ninstrument\n\nAktiekapital: 5 000\n\nVerkst dir: Ingvar A:son Carlström\n\nEtableringsår: 1960.\n\nGLASFIBER 0\nPLASTPRODUKTER AB\n\nPnr 412 63\n\nGöteborg, Almedalsv 1. Tel\n031-40 23 28, 40 23 29. Bankgiro\n361-5184. Postgiro 527520-1\nVerksamhet: Plastmo hängrännor o\nstuprör, plastvaror, plastfolier o\nplast presenning ar\nVerkst dir Erik Carnbäck.\n\nGLASNILSON, AB\n\nPnr 252 55\n\nHelsingborg, Bergav 11. Tel\n042-12 09 50. Bankgiro 269-0 1 21.\nPostgiro 9639-6\n\nVerksamhet: Allt inom glasmästeri-\n\nbranschen\n\nAntal anstäUda: 20\n\nÅrsomsättning: 1000 000\n\nAktiekapital: 10 000\n\nVerkst dir: Sven Rithander\n\nEtableringsår: 1903.\n\nTHORGRENS TRÄ AB\n\nPnr 930 68\n\nRaggsjö, Box 2. Kvarnåsen. Tel\n0918-500 04, 500 49. Bankgiro\n76-3417. Postgiro 61753\nVerksamhet: Tillverkar sågade o\nhyvlade trävaror, lister o takstolar\nsamt fackverk, även limmade\nAntal anställda: 55\nÅrsomsättning: 6 000 000\nAktiekapital: 70 000\nStyrelse: Dir Gunnar Thorgren\n(ordf), hyvelmäst Jonas Thorgren,\nf faktor Sigurd Granholm\nVerkst dir: Gunnar Thorgren\nÖvriga chefer: Hyvelmäst Jonas\nThorgren, insp Trygve Thorgren\nEtableringsår: 1930\nOmbildat till aktiebolag 1939.\n\nTORIN REPRO, AB\n\nPnr 414 78\n\nGöteborg, Skäpplandsg 13-17. Tel\n031-4 1 4 1 00 , 4 1 4 1 04. Bankgiro\n57-0216. Postgiro 721005\nVerksamhet: Grafisk\nreproduktionsrörelse, reklamrörelse\nAntal anställda: 6\nÅrsomsättning: 350 000\nAktiekapital: 5 000\nVerkst dir: Per-Olof Jansson\nEtableringsår: 1968.\n\nBOJS PLÄTINDUSTRI, AB\n\nPnr 632 21\n\nEskilstuna, Libergsg 6. Tel\n016-1364 45. Postgiro 335180-6\nVerksamhet: Tillverkar\nfläktled-ningar, cykloner, transportlådor\nAntal anställda: 8\nÅrsomsättning: 400000\nVerkst dir: Bror O Jonsson\nEtableringsår: 1948.\n\nNYMAN, AB JOH\n\nPnr 79100\n\nFalun, Gruvg 7. Tel 023-19110.\nBankgiro 336-4288. Postgiro\n28661-7\n\nVerksamhet:\nRörledningsentreprenörer\n\nAntal anställda: 32\nÅrsomsättning: 3 500 000\nAktiekapital: 200 000\nVerkst dir. Signe Stenman.\n\nNYMANSSON, REINH\n\nPnr 41120\n\nGöteborg, Kungshöjdsg 11. Tel\n031-1153 89. Bankgiro 50-8781.\nPostgiro 40328\n\nVerksamhet: Oljor o\nindustriförnödenheter\n\nÄgare o chef: Bo Gustafson\nEtableringsår: 1880.\n\nRÄT\n\nRÄTT TID, AB\n\nPnr 203 13\n\nMalmö 4, Stora Nyg 31. Box 4200.\nTel 040-752 20. Bankgiro 260-3009.\nPostgiro 147676-1. Tga Tidbolagen\nVerksamhet: Agentur- o\nengrosför-säljning av ur o urmakeriartiklar\nAvdelningskontor: 111 47 Stockholm,\nWahrendorffsg 8. Tel 08-20 53 20\nAntal anställda: 30\nÅrsomsättning: 4 000 000\nAktiekapital: 10 000\nVerkst dir: Konsul O Jansson\nEtableringsår: 1939.\n\nRÄTTVIKS\nSPISBRÖDS-FABRIK, AB\n\nPnr 795 00\n\nRättvik. Tel 0248-110 75. Bankgiro\n798-0873. Postgiro 33782\nVerksamhet: Tillverkar spis- o\nknäckebröd\n\nVarunamn: Siljansbröd\nAntal anställda: 52\nÅrsomsättning: 5 000 000\nAktiekapital: 150 000\nVerkst dir: Erie G:son Back\nEtableringsår: 1928.\n\nBUN\n\nVerkst dir: Karl Eriksson\nEtableringsår: 1918\nOmbildat till aktiebolag 1933.\n\nBRÄNSLEIMPORTEN I\nHALMSTAD,AB\n\nPnr 30103\n\nHalmstad 1, Viktoriag 2 A. Box\n147. Tel 035-118170. Bankgiro\n423-6576. Postgiro 170705-8.\nTga Bränslebol\n\nVerksamhet: Handel med\nbränslevaror\n\nAntal anställda: 19\nAktiekapital: 175 000\nVerkst dir: Ake Brandt (Göteborg’)\nDisp: Harry Larsson\nEtableringsår 1940.\n\nBRANDSMO TRÄVARU AB\n\nPnr 25005\n\nHelsingborg 5, Landskronav 31.\nBox 5074. Tel 042-62210. Telex\n72296. Tga Bransmo\nVerksamhet: Trävaror engros,\nexport\n\nAntal anställda: 5\nÅrsomsättning: 15 000 000\nAktiekapital: 100 000\nVerkst dir. Ingemar Yllfors\nEtableringsår: 1935.\n\nEAA\n\nE\n\nEAAB-SNICKERIFABRIK\n\nPnr 582 21\n\nLinköping, Stångg 11. Tel\n013-1217 01, 10 38 85. Bankgiro\n120-1292. Postgiro 291260-8\nVerksamhet: Utför\nbeställningssnickerier\nAntal anställda: 17\nÅrsomsättning: 1000 000\nAktiekapital: 100 000\nVerkst dir: Gunnar Gavel\nFabrikschef: Nils Svenson\nEtableringsår: 1938.\n\nSUNDINS FABRIKER AB\n\nPnr 824 01\n\nHudiksvall 1, Box 514. Varvsg 2-4.\nTel 0650-152 50. Bankgiro 78-7026.\nPostgiro 77416. Tga Sundins\nVerksamhet: Tillverkar skidor,\nkolvpumpar för bilhydraulik,\nhydrauliska limpressar,\nträskarvnings-aggregat o lyftkranar\nAntal anställda: 185\nÅrsomsättning: 15 000 000\nAktiekapital: 800 000\nVerkst dir: Erie Sundin\nEtableringsår: 1952.\n\nSUNDIN PRESENTREKLAM,\nAB BROR\n\nPnr 123 47\n\nFarsta, Farstav 39. Tel\n08-64 88 81, 64 88 80. Bankgiro\n734-0094. Postgiro 150405-9\nVerksamhet: Säljer reklam- o\npresentartiklar, fick- o pappersknivar\nav Eskilstuna tillverkning med\nspecialetsning för reklamändamål\nEtableringsår: 1936.\n\nBEL\n\n0522-144 50. Bankgiro 42-8317.\nPostgiro 669410-3. Tga Beijerbygg\nVerksamhet: Försäljning av\nbyggnadsmaterial, trävaror, snickerier,\ngolvläggningar\nAntal anställda: 30\nÅrsomsättning: 15 000 000\n-Aktiekapital: 600 000\nStyrelse: Dlr Kjell Beijer (ordf),\ntekn dr Hjalmar Olson, dir Arne\nHenrikson, dlr Anders Wall\nVerkst dir: Ake Cederholm\nEtableringsår: 1966.\n\nBEIJER BYGGMATERIAL I\nVÄRNAMO AB\n\nPnr 33101\n\nVärnamo 1, Storg 4. Box 86. Tel\n0370-119 00. Postgiro 389417.\nTelex 70146\n\nVerksamhet: Säljer\nbyggnadsmateriel, betong, grus o makadam\nAntal anställda: 90\nÅrsomsättning: 35 000 000\nAktiekapital: 1 000 000\nVerkst dir: Arne Oscarsson\nEtableringsår: 1946.\n\nBEIJER BYGGMATERIAL I\nOREBKO AB\n\nPnr 70104\n\nÖrebro 1, Box 294. Storg 27. Tel\n019-13 03 00. Bankgiro 61-4658.\nPostgiro 86679. Tga Beijerbygg.\nTelex 73427 BEJBYGG S\nVerksamhet: Handel med\nbyggnadsmaterial. Golv- o\ntakentreprenader. Byggträprodukter\nAntal anställda: 128\nÅrsomsättning: 30 000000\nAktiekapital: 34 5 400\nVerkst din A Lundahl\nEtableringsår: 1938\nOmbildat till aktiebolag 1955.\n\nBEIJER BYGGMATERIAL I\nÖSTERSUND AB\n\n(f d Hård, AB J P)\n\nPnr 83101\n\nÖstersund 1, Box 19. Kyrkg 45.\nTel 063-175 00. Bankgiro 25-0045.\nPostgiro 10450-5. Tga Beijer.\nTelex 6579\n\nVerksamhet: Byggnadsmaterial,\nplattsättning, golventreprenader\nAntal anställda: 70\nÅrsomsättning: 20 000 000\nAktiekapital: 216 000\nVerkst dir: Elis Sundström\nEtableringsår: 1897.",
    "structured": {
        "1": {
            "company_name": "GLASDON AB",
            "pnr": "400 12",
            "address": "Göteborg 19. Gibraltarg 2. Box 19029",
            "phone_number": "031-18 58 81, 18 09 20",
            "bank_details": {
                "bankgiro": "51-4896",
                "postgiro": "45841-4"
            },
            "activity": "Säljer ur, optiska artiklar, termometrar, laboratorieglas, glasfiberprodukter, kvartsprodukter samt meteorologiska instrument",
            "capital": 5000,
            "key_personnel": [
                {
                    "name": "Ingvar A:son Carlström"
                }
            ],
            "establishment_year": 1960
        },
        "2": {
            "company_name": "GLASFIBER PLASTPRODUKTER AB",
            "pnr": "412 63",
            "address": "Göteborg, Almedalsv 1",
            "phone_number": "031-40 23 28, 40 23 29",
            "bank_details": {
                "bankgiro": "361-5184",
                "postgiro": "527520-1"
            },
            "activity": "Plastmo hängrännor o stuprör, plastvaror, plastfolier o plast presenning ar",
            "key_personnel": [
                {
                    "name": "Erik Carnbäck"
                }
            ]
        },
        "3": {
            "company_name": "GLASNILSON, AB",
            "pnr": "252 55",
            "address": "Helsingborg, Bergav 11",
            "phone_number": "042-12 09 50",
            "bank_details": {
                "bankgiro": "269-0 1 21",
                "postgiro": "9639-6"
            },
            "activity": "Allt inom glasmästeri-branschen",
            "employees": 20,
            "annual_turnover": 1000000,
            "capital": 10000,
            "key_personnel": [
                {
                    "name": "Sven Rithander"
                }
            ],
            "establishment_year": 1903
        },
        "4": {
            "company_name": "THORGRENS TRÄ AB",
            "pnr": "930 68",
            "address": "Raggsjö, Box 2. Kvarnåsen",
            "phone_number": "0918-500 04, 500 49",
            "bank_details": {
                "bankgiro": "76-3417",
                "postgiro": "61753"
            },
            "activity": "Tillverkar sågade o hyvlade trävaror, lister o takstolar samt fackverk, även limmade",
            "employees": 55,
            "annual_turnover": 6000000,
            "capital": 70000,
            "key_personnel": [
                {
                    "name": "Gunnar Thorgren",
                    "position": "ordf"
                },
                {
                    "name": "Jonas Thorgren",
                    "position": "hyvelmäst"
                },
                {
                    "name": "Sigurd Granholm",
                    "position": "f faktor"
                }
            ],
            "establishment_year": 1930
        },
        "5": {
            "company_name": "TORIN REPRO, AB",
            "pnr": "414 78",
            "address": "Göteborg, Skäpplandsg 13-17",
            "phone_number": "031-4 1 4 1 00 , 4 1 4 1 04",
            "bank_details": {
                "bankgiro": "57-0216",
                "postgiro": "721005"
            },
            "activity": "Grafisk reproduktionsrörelse, reklamrörelse",
            "employees": 6,
            "annual_turnover": 350000,
            "capital": 5000,
            "key_personnel": [
                {
                    "name": "Per-Olof Jansson"
                }
            ],
            "establishment_year": 1968
        },
        "6": {
            "company_name": "BOJS PLÄTINDUSTRI, AB",
            "pnr": "632 21",
            "address": "Eskilstuna, Libergsg 6",
            "phone_number": "016-1364 45",
            "postgiro": "335180-6",
            "activity": "Tillverkar fläktled-ningar, cykloner, transportlådor",
            "employees": 8,
            "annual_turnover": 400000,
            "key_personnel": [
                {
                    "name": "Bror O Jonsson"
                }
            ],
            "establishment_year": 1948
        },
        "7": {
            "company_name": "NYMAN, AB JOH",
            "pnr": "79100",
            "address": "Falun, Gruvg 7",
            "phone_number": "023-19110",
            "bank_details": {
                "bankgiro": "336-4288",
                "postgiro": "28661-7"
            },
            "activity": "Rörledningsentreprenörer",
            "employees": 32,
            "annual_turnover": 3500000,
            "capital": 200000,
            "key_personnel": [
                {
                    "name": "Signe Stenman",
                    "position": "Verkst dir"
                }
            ]
        },
        "8": {
            "company_name": "NYMANSSON, REINH",
            "pnr": "41120",
            "address": "Göteborg, Kungshöjdsg 11",
            "phone_number": "031-1153 89",
            "bank_details": {
                "bankgiro": "50-8781",
                "postgiro": "40328"
            },
            "activity": "Oljor o industriförnödenheter",
            "owner": "Bo Gustafson",
            "establishment_year": 1880
        },
        "9": {
            "company_name": "RÄTT TID, AB",
            "pnr": "203 13",
            "address": "Malmö 4, Stora Nyg 31. Box 4200",
            "phone_number": "040-752 20",
            "bank_details": {
                "bankgiro": "260-3009",
                "postgiro": "147676-1"
            },
            "activity": "Agentur- o engrosför-säljning av ur o urmakeriartiklar",
            "departments": [
                {
                    "name": "111 47 Stockholm, Wahrendorffsg 8",
                    "phone_number": "08-20 53 20"
                }
            ],
            "employees": "30",
            "annual_turnover": 4000000,
            "capital": 10000,
            "key_personnel": [
                {
                    "name": "Konsul O Jansson",
                    "position": "Verkst dir"
                }
            ],
            "establishment_year": 1939
        },
        "10": {
            "company_name": "RÄTTVIKS SPISBRÖDS-FABRIK, AB",
            "pnr": "795 00",
            "address": "Rättvik",
            "phone_number": "0248-110 75",
            "bank_details": {
                "bankgiro": "798-0873",
                "postgiro": "33782"
            },
            "activity": "Tillverkar spis- o knäckebröd",
            "trademark": "Siljansbröd",
            "employees": 52,
            "annual_turnover": 5000000,
            "capital": 150000,
            "key_personnel": [
                {
                    "name": "Erie G:son Back",
                    "position": "Verkst dir"
                }
            ],
            "establishment_year": 1928
        }
    }
}