{
    "original": "malmsten &amp; johansson, ab\n\nPnr 573 01\n\nTranås 1, Box 73. Rundelg. Tel\n0140-128 48, 10648. Bankgiro\n365-5669. Postgiro 388725-4\nVerksamhet: Säljer möbeltyger,\nmattor, såväl avpassade som\nheltäckande, i parti\nAntal anställda: 8\nÅrsomsättning: 2 000 000\nAktiekapital: 50 000\nVerkst dir: Sven Johansson\nEtableringsår 1949.\n\nELFVERSON &amp; CO KB\n\nPnr 38101\n\nKalmar 1, Box 162. Olandsg 27. Tel\n0480-12233. 127 70. Bankgiro\n272-328. Postgiro 170098-8. Tga\nElfver-sonco\n\nVerksamhet: Tillverkar svarvade o\nfigurfrästa lackerade artiklar i trä\nAntal anställda: 160\nÅrsomsättning: 8 500000\nAndelskapital: 100 000\nVerkst dir: Olof Elfverson\nEtableringsår: 1923.\n\nELFWING MASKINFIRMA,\nCIVILINGENJÖR KARL\n\nPnr 41109\n\nGöteborg, O Hamng 2. Tel\n031-13 88 18. Bankgiro 41-0075.\nPostgiro 421550\n\nVerksamhet: Diamantverktyg,\nslipapparater, hydraulik\nVarunamn: Habit, Hilma\nÄgare o chef: Civiling Karl\nElf-wing\n\nEtableringsår: 1950.\n\nFINN FRITID AB\n\nPnr 127 23\n\nSkärholmen, Box 134. Kungens\nKurva. Tel 08-7100800. Bankgiro\n22-2245. Postgiro 556966. Tga\nFinnfritid. Telex 10971 FRITID S\nVerksamhet: Säljer\nfabrikstill-verkade finska fritidshus av trä\nAntal anstäUda: 20\nÅrsomsättning: 5 000 000\nAktiekapital: 200000\nVerkst dir. Lennart H Ståhlbrandt\nEtableringsår: 1968.\n\nSTRANDS GLASS AB\n\nPnr 94101\n\nPiteå 1, Box 60. Tel 0911-603 30.\nBankgiro 61-1260. Postgiro 326240\nVeiksamhet: Tillverkar o säljer\nglass i parti. Storköksartiklar\nAntal anställda: 70\nÅrsomsättning: 9 000 000\nAktiekapital: 500 000\nVerkst dir: Martin Strand\nEtableringsår: 1938.\n\nSTRANDS KONFEKTIONS AB\n\nPnr 64100\n\nKatrineholm, Gjuterig 2. Box 67.\nTel 0150-132 55. Bankgiro 61-7121.\nPostgiro 11228\n\nVerksamhet: Tillverkar\nherrkonfektion\n\nAntal anställda: 250\nÅrsomsättning: 12 000 000\nAktiekapital: 450 000\nVerkst dir: Bengt Nyhage\nEtableringsår: 1923.\n\nBAKELITVERKEN, AB\n\nPnr 352 46\n\nVäxjö, Smedjeg 15. Tel\n0470-174 40. Bankgiro 66-7903.\nPostgiro 297973. Tga Burde\nVerksamhet: Hushålls- o\ncampingartiklar, kapsyler, lock o\ntubhattar o fotoramar\nAktiekapital: 75 000\nVerkst dir: T R Burde\nEtableringsår: 1946.\n\nBALAMUNDI AB\n\nPnr 402 72\n\nGöteborg 8, Box 8875. Exportg,\nHisings Backa. Tel 031-5 2 05 90.\nBankgiro 420-0150. Postgiro\n150160-0. Tga Balamundi,\nGöteborg. Telex 20656\n\nVerksamhet: Tillverkar heltäckande\n\ntextilmattor. Importerar golv- o\nväggmaterial från koncernbolag i Europa\nAntal anställda: 170\nÅrsomsättning: 39 000 000\nAktiekapital: 2 000 000\nStyrelse: Adv Nils Kärrlander (ordf),\ndir Raymond Berticaux, adv Bertil\nHenriques, dir Jacques Lannoye,\ndir W Th Meyer, dir Noé’1\nPoude-roux, dir Sven-Eje Sandberg, adv\nBertil Olof Södermark, adv Sten\nSödermark\n\nVerkst dir: Sven-Eje Sandberg\nMarknadsdir o v verkst dir: Harry\nBrännmark\n\nFörsäljn-dir: Axel Malmquist\nEtableringsår: 1936.\n\nCEDRAEUS, AB C-G\n\nPnr 590 20\n\nMantorp, Box 80. Tel 0142-204 05\n\nVerksamhet: Tillverkar tvätt- o\n\nrengöringsmedel\n\nVerkst din Walter Hentschel.\n\nCEE-SPRINKLER\nCOMPANY, AB\n\nPnr 11641\n\nStockholm, Tegelviksg 18. Tel\n08-44 34 93, 44 36 78. Bankgiro\n732-3108. Postgiro 406391-3. Tga\nCeesprink\n\nVerksamhet: Sprinkler- o\nfireye-anläggningar\nAntal anställda: 14\nAktiekapital: 50 000\nVerkst dir: Elof Karlsson\nEtableringsår 1950.\n\nÖSTERLENS SPARBANK\n\nPnr 272 01\n\nSimrishamn 1, Box 27. Stortorget 2.\nTel 0414-122 00. Bankgiro\n981-2884. Postgiro 134216-1\nVerksamhet: Sparbanksrörelse.\n6 st avdelningskontor\nAntal anställda: 21\nÅrsomsättning: 125 000 000\nVerkst dir: Christian Westrup\nEtableringsår: 1853.\n\nOSTERLINDS EL-AGENTUR\nAB\n\nPnr 182 02\n\nDanderyd2, Sätraängsv 4. Fack.\nTel 08-753 03 55. Bankgiro 16-7447.\nPostgiro 156084. Telex 1224. Tga\nElektrolind\n\nVeiksamhet: Agentur för, o\nförsäljning av elektriska komponenter\nAntal anställda: 5\nÅrsomsättning: 4 000 000\nAktiekapital: 10 000\nStyrelse: Grossh Gunnar Osterlind\n(ordf), disp Bo Osterlind\nVerkst dir: Grossh Gunnar Osterlind\nEtableringsår: 1961.\n\nALUMINIUM.TEKNIK\n\nPnr 610 60\n\nTystberga, Stockholmsv 28. Tel\n0155-603 79. 61113. Postgiro\n683096-2\n\nVerksamhet: Tillverkar bränsle- o\nvattentankar\n\nChef: Ing Håkan Sjöholm\nEtableringsår: 1966.\n\nHÄLLSTRÖM AB, C A\n\nPnr 802 20\n\nGävle, S Centralg 17. Tel\n026-122711,12 27 13. Bankgiro 78-3754.\nPostgiro 279440\n\nVerksamhet: Säljer trävaror,\nmasonite o byggmateriel\nAktiekapital: 50 000\nVerkst dlr: Erie Hällström\nEtableringsår: 1916.\n\nBOR|N AB, JAMES\n\nPnr 417 05\n\nGöteborg, Färgfabriksg 3. Tel\n031-5174 03, 5174 04. Bankgiro84-7922.\nPostgiro 620334. Tga Borinflex.\nTelex 20820\n\nVerksamhet: Stratoflex\nhögtrycksslang o snabbkopplingar,\nmanomefc-rar. Metallslang i olika legeringar\nVarunamn: Stratoflex, Double Seal\nAktiekapital: 10 000\nVerkst dir: James Borin\nEtableringsår: 1961.",
    "structured": {
        "1": {
            "company_name": "Malmsten & Johansson AB",
            "pnr": "573 01",
            "address": "Tranås 1, Box 73. Rundelg.",
            "phone_number": "0140-128 48, 10648",
            "bank_details": {
                "bankgiro": "365-5669",
                "postgiro": "388725-4"
            },
            "activity": "Säljer möbeltyger, mattor, såväl avpassade som heltäckande, i parti",
            "employees": 8,
            "annual_turnover": 2000000,
            "capital": 50000,
            "key_personnel": [
                {
                    "name": "Sven Johansson",
                    "position": "Verkställande direktör"
                }
            ],
            "establishment_year": 1949
        },
        "2": {
            "company_name": "Elfverson & Co KB",
            "pnr": "38101",
            "address": "Kalmar 1, Box 162. Olandsg 27.",
            "phone_number": "0480-12233, 127 70",
            "bank_details": {
                "bankgiro": "272-328",
                "postgiro": "170098-8"
            },
            "activity": "Tillverkar svarvade o figurfrästa lackerade artiklar i trä",
            "employees": 160,
            "annual_turnover": 8500000,
            "capital": 100000,
            "key_personnel": [
                {
                    "name": "Olof Elfverson",
                    "position": "Verkställande direktör"
                }
            ],
            "establishment_year": 1923
        },
        "3": {
            "company_name": "Elfwing Maskinfirma, Civilingenjör Karl",
            "pnr": "41109",
            "address": "Göteborg, O Hamng 2",
            "phone_number": "031-13 88 18",
            "bank_details": {
                "bankgiro": "41-0075",
                "postgiro": "421550"
            },
            "activity": "Diamantverktyg, slipapparater, hydraulik",
            "establishment_year": 1950
        },
        "4": {
            "company_name": "Finn Fritid AB",
            "pnr": "127 23",
            "address": "Skärholmen, Box 134. Kungens Kurva",
            "phone_number": "08-7100800",
            "bank_details": {
                "bankgiro": "22-2245",
                "postgiro": "556966"
            },
            "activity": "Säljer fabrikstillverkade finska fritidshus av trä",
            "employees": 20,
            "annual_turnover": 5000000,
            "capital": 200000,
            "key_personnel": [
                {
                    "name": "Lennart H Ståhlbrandt",
                    "position": "Verkställande direktör"
                }
            ],
            "establishment_year": 1968
        },
        "5": {
            "company_name": "Strands Glass AB",
            "pnr": "94101",
            "address": "Piteå 1, Box 60",
            "phone_number": "0911-603 30",
            "bank_details": {
                "bankgiro": "61-1260",
                "postgiro": "326240"
            },
            "activity": "Tillverkar o säljer glass i parti. Storköksartiklar",
            "employees": 70,
            "annual_turnover": 9000000,
            "capital": 500000,
            "key_personnel": [
                {
                    "name": "Martin Strand",
                    "position": "Verkställande direktör"
                }
            ],
            "establishment_year": 1938
        },
        "6": {
            "company_name": "Strands Konfektions AB",
            "pnr": "64100",
            "address": "Katrineholm, Gjuterig 2. Box 67",
            "phone_number": "0150-132 55",
            "bank_details": {
                "bankgiro": "61-7121",
                "postgiro": "11228"
            },
            "activity": "Tillverkar herrkonfektion",
            "employees": 250,
            "annual_turnover": 12000000,
            "capital": 450000,
            "key_personnel": [
                {
                    "name": "Bengt Nyhage",
                    "position": "Verkställande direktör"
                }
            ],
            "establishment_year": 1923
        },
        "7": {
            "company_name": "Bakelitverken AB",
            "pnr": "352 46",
            "address": "Växjö, Smedjeg 15",
            "phone_number": "0470-174 40",
            "bank_details": {
                "bankgiro": "66-7903",
                "postgiro": "297973"
            },
            "activity": "Hushålls- o campingartiklar, kapsyler, lock o tubhattar o fotoramar",
            "capital": 75000,
            "key_personnel": [
                {
                    "name": "T R Burde",
                    "position": "Verkställande direktör"
                }
            ],
            "establishment_year": 1946
        },
        "8": {
            "company_name": "Balamundi AB",
            "pnr": "402 72",
            "address": "Göteborg 8, Box 8875. Exportg, Hisings Backa",
            "phone_number": "031-5 2 05 90",
            "bank_details": {
                "bankgiro": "420-0150",
                "postgiro": "150160-0"
            },
            "activity": "Tillverkar heltäckande textilmattor. Importerar golv- o väggmaterial från koncernbolag i Europa",
            "employees": 170,
            "annual_turnover": 39000000,
            "capital": 2000000,
            "key_personnel": [
                {
                    "name": "Sven-Eje Sandberg",
                    "position": "Verkställande direktör"
                },
                {
                    "name": "Harry Brännmark",
                    "position": "Marknadsdirektör och vice verkställande direktör"
                },
                {
                    "name": "Axel Malmquist",
                    "position": "Försäljningsdirektör"
                }
            ],
            "establishment_year": 1936
        },
        "9": {
            "company_name": "Cedraeus AB C-G",
            "pnr": "590 20",
            "address": "Mantorp, Box 80",
            "phone_number": "0142-204 05",
            "activity": "Tillverkar tvätt- o rengöringsmedel",
            "key_personnel": [
                {
                    "name": "Walter Hentschel",
                    "position": "Verkställande direktör"
                }
            ]
        },
        "10": {
            "company_name": "Cee-Sprinkler Company AB",
            "pnr": "11641",
            "address": "Stockholm, Tegelviksg 18",
            "phone_number": "08-44 34 93, 44 36 78",
            "bank_details": {
                "bankgiro": "732-3108",
                "postgiro": "406391-3"
            },
            "activity": "Sprinkler- o fireye-anläggningar",
            "employees": 14,
            "capital": 50000,
            "key_personnel": [
                {
                    "name": "Elof Karlsson",
                    "position": "Verkställande direktör"
                }
            ],
            "establishment_year": 1950
        },
        "11": {
            "company_name": "Österlens Sparbank",
            "pnr": "272 01",
            "address": "Simrishamn 1, Box 27. Stortorget 2",
            "phone_number": "0414-122 00",
            "bank_details": {
                "bankgiro": "981-2884",
                "postgiro": "134216-1"
            },
            "activity": "Sparbanksrörelse. 6 st avdelningskontor",
            "employees": 21,
            "annual_turnover": 125000000,
            "key_personnel": [
                {
                    "name": "Christian Westrup",
                    "position": "Verkställande direktör"
                }
            ],
            "establishment_year": 1853
        },
        "12": {
            "company_name": "Osterlinds El-Agentur AB",
            "pnr": "182 02",
            "address": "Danderyd2, Sätraängsv 4",
            "phone_number": "08-753 03 55",
            "bank_details": {
                "bankgiro": "16-7447",
                "postgiro": "156084"
            },
            "activity": "Agentur för, o försäljning av elektriska komponenter",
            "employees": 5,
            "annual_turnover": 4000000,
            "capital": 10000,
            "key_personnel": [
                {
                    "name": "Grossh Gunnar Osterlind",
                    "position": "Verkställande direktör"
                }
            ],
            "establishment_year": 1961
        },
        "13": {
            "company_name": "Aluminium.Teknik",
            "pnr": "610 60",
            "address": "Tystberga, Stockholmsv 28",
            "phone_number": "0155-603 79, 61113",
            "postgiro": "683096-2",
            "activity": "Tillverkar bränsle- o vattentankar",
            "key_personnel": [
                {
                    "name": "Ing Håkan Sjöholm",
                    "position": "Chef"
                }
            ],
            "establishment_year": 1966
        },
        "14": {
            "company_name": "Hällström AB, C A",
            "pnr": "802 20",
            "address": "Gävle, S Centralg 17",
            "phone_number": "026-122711,12 27 13",
            "bank_details": {
                "bankgiro": "78-3754",
                "postgiro": "279440"
            },
            "activity": "Säljer trävaror, masonite o byggmateriel",
            "capital": 50000,
            "key_personnel": [
                {
                    "name": "Erie Hällström",
                    "position": "Verkställande direktör"
                }
            ],
            "establishment_year": 1916
        },
        "15": {
            "company_name": "Borin AB, James",
            "pnr": "417 05",
            "address": "Göteborg, Färgfabriksg 3",
            "phone_number": "031-5174 03, 5174 04",
            "bank_details": {
                "bankgiro": "84-7922",
                "postgiro": "620334"
            },
            "activity": "Stratoflex högtrycksslang o snabbkopplingar, manomefc-rar. Metallslang i olika legeringar",
            "capital": 10000,
            "key_personnel": [
                {
                    "name": "James Borin",
                    "position": "Verkställande direktör"
                }
            ],
            "establishment_year": 1961
        }
    }
}