{
    "original": "ANDERSON &amp; SÖNER AB, Y\n\nPnr 12612\n\nStockholm 42, Box 42042.\nDansba-nev 26, Hägersten. Tel 08-45 78 30,\n1968 65. Bankgiro 33-0247.\nPostgiro 554193\n\nVerksamhet: Underhåll o\nreparation av maskiner för storkök etc\nAntal anställda: 11\nÅrsomsättning: 600 000\nAktiekapital: 10 000\nVerkst dir: Yngve Anderson\nEtableringsår: 1957.\n\nANDERSON, AB ÅBJÖRN\n\nse Svedala-Arbrå AB.\n\nANDERSSONS\nLASTBILS-ÅKERI, AB ÅKE\n\nPnr 603 63\n\nNorrköping, Hammarg 71. Tel\n011-180280. Bankgiro 60-9901.\nPostgiro 177477\n\nVerksamhet: Akerirörelse o\nuthyrning av entreprenadmaskiner\nAntal anställda: 29\nÅrsomsättning: 1500 000\nAktiekapital: 60 000\nVerkst dir: Ake Andersson\nEtableringsår: 1940.\n\nANDERSTORPS\nARMATURFABRIK, AB\n\nPnr 330 20\n\nAnderstorp, Storg 23. Box 50. Tel\n0371-150 71. Bankgiro 488-0720.\nPostgiro 85060-2\n\nVerksamhet: Tillverkar elmateriel.\nPressade artiklar för bil- o\nradiobranschen\nAktiekapital: 50000\nVerkst dir: Harald Johansson\nEtableringsår: 1927.\n\nANDERSTORPS\nGUMMI-INDUSTRI AB\n\nPnr 330 20\n\nAnderstorp, Götg 9. Tel\n0371-160 80. Bankgiro 143-1261.\nPostgiro 8366-7\n\nVerksamhet:\nRegummeringsindu-stri. Säljer bildäck\nAntal anställda: 19\nÅrsomsättning: 3000 000\nAktiekapital: 100 000\nVerkst dir: Reinhold Astmar\nFörsäljn-chef: Malte Andersson\nDriftsing: Norbert Tomaszewski\nEtableringsår: 1956.\n\nwaksala tegelbruk, ab\n\nPnr 11229\n\nStockholm, Hjärneg 10. Tel\n08-5005 74\n\nTegelbruk: Uppsala. Brillinge\ntegelbruk. Tel 018-12 14 60, 1214 62\nAntal anställda: 25\nÅrsomsättning: 2 500 000\nAktiekapital: 300 000\nVerkst dir: John Baunge\nEtableringsår: 1934.\n\nARBOGA BOKTRYCKERI AB\n\nPnr 732 00\n\nArboga. Box 68. Trädgårdsg 56.\nTel 0589-129 25 (från sept 1971\n15886). Bankgiro 809-8055.\nPostgiro 28543-7\n\nVerksamhet: Reklam-, katalog-,\nbok-, tidskrifts- o affärstryck\nAntal anställda: 11\nÅrsomsättning: 725 000\nAktiekapital: 124 000\nVerkst dir: Boktr Olle Wallström\nEtableringsår: 1839.\n\nHAUSER, AB DR H\n\nPnr 412 59\n\nGöteborg, Bergsprängareg 7. Tel\n031-8104 90. Bankgiro 500-4908.\nPostgiro 521433-3. Tga Dehans.\nTelex 20774\n\nVerksamhet: Tillverkar\nsilkscreen-maskiner, -automater o torkar\nAktiekapital: 150 000\nVerkst dir: Dr H Hauser\nEtableringsår: 1956.\n\nSHUNT AB VÄRMETEKNIK\n\nPnr 330 21\n\nReftele, Box 183. Skogsforsv. Tel\n0371-207 50. Bankgiro 488-0670.\nPostgiro 144705-1. Tga\nVärmeteknik\n\nVerksamhet: Shuntventiler för\nvärmeledningar samt motorhyllor med\ntillbehör för dessa\nAntal anställda: 30\nÅrsomsättning: 4000 000\nAktiekapital: 340 000\nVerkst dir: Mats Skogsfors\nEtableringsår: 1939\nOmbildat till aktiebolag 1961.\n\nSIAB\n\nPnr 102 30\n\nStockholm 6, Fack. N Stationsg\n75-77. Tel 08-34 90 40. Bankgiro\n566-0824. Postgiro 199720-4. Tga\nIndustribyggen. Telex 19986\nVerksamhet: Byggnadsentreprenör\nför Industrier, bostäder o\nanläggningsarbeten\nAntal anstäUda: 4 000\nÅrsomsättning: 700 000 000\nAktiekapital: 3 000000\nStyrelse: Dir Sven Dahlberg (ordf),\ndir Håkan Birke, civiling Ivan Juto,\nherr Lars Wirström, dir Bertil Norén\nVeikst dir: Civiling Ivan Juto\nEtableringsår 1945.\n\nASP AB, IVAR\n\nPnr 102 32\n\nStockholm 6, Box 6101. Norrtullsg\n17. Tel 08-30 77 90, 3129 50.\nBankgiro 167-0314. Postgiro 252498-1.\nTga Sharpo\n\nVerksamhet: Säljer pappers- o\nkontorsvaror, konstnärsmaterial\nAntal anställda: 11\nÅrsomsättning: 4 000 000\nAktiekapital: 150 000\nVerkst dir: Ivar Asp\nEtableringsår: 1945.\n\nASPEMYR, INGENJÖRSFIRMA\nSVEN\n\nPnr 641 00\n\nKatrineholm, Jägareg 19. Tel\n0150-128 45. Bankgiro 617-1862.\nPostgiro 370005-1\n\nVerksamhet: Konsulterande\nverksamhet inom byggnadsfacket\nÄgare o chef: Sven Aspemyr\nEtableringsår: 1950.\n\nASPENS KONFEKTIONS.\nFABRIK AB\n\nPnr 52100\n\nFalköping, Hollenderg 31. Tel\n0515-132 90. Bankgiro 213-7677.\nPostgiro 291045-3\nVerksamhet: Tillverkar klänningar\nAntal anställda: 160\nÅrsomsättning: 11000 000\nAktiekapital: 180 000\nVerkst dir: Helge Asp\nEtableringsår: 1946.\n\nWAHLBECK, ERIK H\n\nPnr 150 32\n\nStallarholmen. Tel 0152-410 00,\n\n410 01. Bankgiro 325-1766.\nPostgiro 454542-2\n\nVerksamhet: Guld- o silverkedjor\ni metervara av tråd\nChef: Fabr Hans Wahlbeck\nEtableringsår: 1948.\n\nFARTYGSISOLERING, AB\n\nPnr 45100\n\nUddevalla, Stora Hälleviksg 4.\nTel 0522-179 83, 182 54. Bankgiro\n606-39 29. Postgiro 28822-5\nVerksamhet: Isolering å fartyg,\nindustrier o fastigheter\nAntal anställda: 20\nÅrsomsättning: 500000\nAktiekapital: 10 000\nVerkst dir: Ing Kurt Munther\nEtableringsår: 1953.\n\nFARTYGSKONSTRUKTIONER\nAB\n\nPnr 451 01\n\nUddevalla 1. Box 382. Tel\n0522-364 00. Bankgiro 36-6675.\nPostgiro 591282. Telex 42027 FKAB S\nVerksamhet: Projekt-, klass-,\nar-bets- o optiska ritningar\nAntal anställda: 50\nÅrsomsättning: 3 000 000\nAktiekapital: 20 000\nStyrelse: Ing Gustaf Mattsson\n(ordf), ing Arne Andersson, ing\nLars Mannström\nVerkst dir: Lars Mannström\nEtableringsår: 1961.\n\nVÄS\n\nVarunamn: Värnamo-VMA\nAntal anställda: 115\nÅrsomsättning: 9 000 000\nAktiekapital: 433 600\nVerkst dir: Sven Westerberg\nEtableringsår: 1917.\n\nNYA\n\nden samt redovisning, revision,\nskatteärenden, konkursärenden,\nin-kasso, förvaltnings- o\nfinansärenden. I koncernen ingår AB\nEtable-raren, AB Grundaren, AB Lobré,\nNotarius-b olagen ab, Notarius\nfinans ab. Notarius inkasso- &amp;\njuridiska byrå ab. Notarius\nrevisionsbyrå, AB Stämman\nVarunamn: Notarius\nAktiekapital: 40 000\nVerkst dir: Revisor SBRP Nils\nArvids\n\nEtableringsår: 1945.\n\nNOTNÄS ÅNGSÅG, AB\n\nse Vänerindustrier AB,\nSkogsägarnas.\n\nNOVAKEMI AB\n\nPnr 123 47\n\nFarsta, Molkomsbacken 37. Tel\n08-93 01 15. Bankgiro 173-8152.\nPostgiro 656870-3. Tga Novakemi.\nTelex 19081\n\nVerksamhet: Import o försäljning\nav industrikemikalier samt metaller\nför laboratoriebruk\nAntal anställda: 10\nAktiekapital: 20 000\nVerkst dir: Per-Erik Töreman\nEtableringsår: 1962\nDotterbolag: Erag Handels-AB,\nStockholm.\n\nNOVATOR, REDERI AB\n\nPnr 602 22\n\nNorrköping, Saltängsg 33.\nTelOll-1239 36. Bankgiro 12-5074.\nPostgiro 84955. Telex64048. TgaNova\nVerksamhet: Rederirörelse\nAntal anställda: 20\nAktiekapital: 200 000\nVerkst dir: Sven Wirström\nEtableringsår: 1933.\n\nNOVIA LIVSMEDELS.\nINDUSTRIER AB\n\n(Bjäre, Blå Band, Gustaf Bong o\n\nVätö)\n\nPnr 29110\n\nKristianstad 10, Box 10070\nHuvudkontor o fabrik: Tel\n044-12 30 00. Tga Novialivs.\nKristianstad. Telex 48051 NOVIA S\nKontor o fabrik: 301 04 Halmstad 1,\nBox 240. Tel 035-1000 20. Tga\nNovialivs, Halmstad.\nTelex 38070 NOVIA S\nVerksamhet:\n\nHalmstadsfabriken:\ntorrkonserve-rade produkter samt burksoppor\nKristianstadsfabriken:\nkonsumtionsfärdiga drycker, potatisprodukter\npå burk, saft, sylt, marmelad o\ndrinkar\n\nAntal anstäUda: 900\nArbetande styrelseordf: Ingvar\nJonsson\n\nVerkst dir: Lars Ögren\nEtableringsår: 1971\nFöretagen Bjäre, Blå Band, Gustaf\nBong o vato är from 1971 ett\nföretag o heter Novia\nLivsmedelsindustrier AB.\n\nNOVUM, AB\n\nPnr 250 04\n\nHälsingborg 4, Bendzg 29. Box 4035.\nTel 042-970 70. Bankgiro 86-3525.\n\nPostgiro 593520.\nTelex 72444 NOVUM S.\nTga Abenovum\n\nVerksamhet: Säljer elektr\ninstallationsmateriel, kopplingsur m m\nVerkst dir: Owe Näckberg\nEtableringsår: 1962.",
    "structured": {
        "1": {
            "company_name": "ANDERSON & SÖNER AB",
            "pnr": "12612",
            "address": "Stockholm 42, Box 42042. Dansba-nev 26, Hägersten.",
            "phone_number": "08-45 78 30",
            "bank_details": {
                "bankgiro": "33-0247",
                "postgiro": "554193"
            },
            "activity": "Underhåll o reparation av maskiner för storkök etc",
            "employees": 11,
            "annual_turnover": 600000,
            "capital": 10000,
            "key_personnel": [
                {
                    "name": "Yngve Anderson",
                    "position": "Verkst dir"
                }
            ],
            "establishment_year": 1957
        },
        "2": {
            "company_name": "ANDERSON, AB ÅBJÖRN"
        },
        "3": {
            "company_name": "ANDERSSONS LASTBILS-ÅKERI, AB ÅKE",
            "pnr": "603 63",
            "address": "Norrköping, Hammarg 71.",
            "phone_number": "011-180280",
            "bank_details": {
                "bankgiro": "60-9901",
                "postgiro": "177477"
            },
            "activity": "Akerirörelse o uthyrning av entreprenadmaskiner",
            "employees": 29,
            "annual_turnover": 1500000,
            "capital": 60000,
            "key_personnel": [
                {
                    "name": "Ake Andersson",
                    "position": "Verkst dir"
                }
            ],
            "establishment_year": 1940
        },
        "4": {
            "company_name": "ANDERSTORPS ARMATURFABRIK, AB",
            "pnr": "330 20",
            "address": "Anderstorp, Storg 23. Box 50.",
            "phone_number": "0371-150 71",
            "bank_details": {
                "bankgiro": "488-0720",
                "postgiro": "85060-2"
            },
            "activity": "Tillverkar elmateriel. Pressade artiklar för bil- o radiobranschen",
            "capital": 50000,
            "key_personnel": [
                {
                    "name": "Harald Johansson",
                    "position": "Verkst dir"
                }
            ],
            "establishment_year": 1927
        },
        "5": {
            "company_name": "ANDERSTORPS GUMMI-INDUSTRI AB",
            "pnr": "330 20",
            "address": "Anderstorp, Götg 9.",
            "phone_number": "0371-160 80",
            "bank_details": {
                "bankgiro": "143-1261",
                "postgiro": "8366-7"
            },
            "activity": "Regummeringsindu-stri. Säljer bildäck",
            "employees": 19,
            "annual_turnover": 3000000,
            "capital": 100000,
            "key_personnel": [
                {
                    "name": "Reinhold Astmar",
                    "position": "Verkst dir"
                },
                {
                    "name": "Malte Andersson",
                    "position": "Försäljn-chef"
                },
                {
                    "name": "Norbert Tomaszewski",
                    "position": "Driftsing"
                }
            ],
            "establishment_year": 1956
        },
        "6": {
            "company_name": "waksala tegelbruk, ab",
            "pnr": "11229",
            "address": "Stockholm, Hjärneg 10.",
            "phone_number": "08-5005 74",
            "activity": "Tegelbruk: Uppsala. Brillinge tegelbruk.",
            "employees": 25,
            "annual_turnover": 2500000,
            "capital": 300000,
            "key_personnel": [
                {
                    "name": "John Baunge",
                    "position": "Verkst dir"
                }
            ],
            "establishment_year": 1934
        },
        "7": {
            "company_name": "ARBOGA BOKTRYCKERI AB",
            "pnr": "732 00",
            "address": "Arboga, Box 68. Trädgårdsg 56.",
            "phone_number": "0589-129 25",
            "activity": "Reklam-, katalog-, bok-, tidskrifts- o affärstryck",
            "employees": 11,
            "annual_turnover": 725000,
            "capital": 124000,
            "key_personnel": [
                {
                    "name": "Boktr Olle Wallström",
                    "position": "Verkst dir"
                }
            ],
            "establishment_year": 1839
        },
        "8": {
            "company_name": "HAUSER, AB DR H",
            "pnr": "412 59",
            "address": "Göteborg, Bergsprängareg 7.",
            "phone_number": "031-8104 90",
            "bank_details": {
                "bankgiro": "500-4908",
                "postgiro": "521433-3"
            },
            "activity": "Tillverkar silkscreen-maskiner, -automater o torkar",
            "capital": 150000,
            "key_personnel": [
                {
                    "name": "Dr H Hauser",
                    "position": "Verkst dir"
                }
            ],
            "establishment_year": 1956
        },
        "9": {
            "company_name": "SHUNT AB VÄRMETEKNIK",
            "pnr": "330 21",
            "address": "Reftele, Box 183. Skogsforsv.",
            "phone_number": "0371-207 50",
            "bank_details": {
                "bankgiro": "488-0670",
                "postgiro": "144705-1"
            },
            "activity": "Shuntventiler för värmeledningar samt motorhyllor med tillbehör för dessa",
            "employees": 30,
            "annual_turnover": 4000000,
            "capital": 340000,
            "key_personnel": [
                {
                    "name": "Mats Skogsfors",
                    "position": "Verkst dir"
                }
            ],
            "establishment_year": 1939
        },
        "10": {
            "company_name": "SIAB",
            "pnr": "102 30",
            "address": "Stockholm 6, Fack. N Stationsg 75-77.",
            "phone_number": "08-34 90 40",
            "bank_details": {
                "bankgiro": "566-0824",
                "postgiro": "199720-4"
            },
            "activity": "Byggnadsentreprenör för Industrier, bostäder o anläggningsarbeten",
            "employees": 4000,
            "annual_turnover": 700000000,
            "capital": 3000000,
            "key_personnel": [
                {
                    "name": "Sven Dahlberg (ordf)",
                    "position": "Dir"
                },
                {
                    "name": "Håkan Birke",
                    "position": "Dir"
                },
                {
                    "name": "Ivan Juto",
                    "position": "civiling"
                },
                {
                    "name": "Lars Wirström",
                    "position": "herr"
                },
                {
                    "name": "Bertil Norén",
                    "position": "dir"
                },
                {
                    "name": "Ivan Juto",
                    "position": "Veikst dir"
                }
            ],
            "establishment_year": 1945
        },
        "11": {
            "company_name": "ASP AB, IVAR",
            "pnr": "102 32",
            "address": "Stockholm 6, Box 6101. Norrtullsg 17.",
            "phone_number": "08-30 77 90, 3129 50",
            "bank_details": {
                "bankgiro": "167-0314",
                "postgiro": "252498-1"
            },
            "activity": "Säljer pappers- o kontorsvaror, konstnärsmaterial",
            "employees": 11,
            "annual_turnover": 4000000,
            "capital": 150000,
            "key_personnel": [
                {
                    "name": "Ivar Asp",
                    "position": "Verkst dir"
                }
            ],
            "establishment_year": 1945
        },
        "12": {
            "company_name": "ASPEMYR, INGENJÖRSFIRMA SVEN",
            "pnr": "641 00",
            "address": "Katrineholm, Jägareg 19.",
            "phone_number": "0150-128 45",
            "bank_details": {
                "bankgiro": "617-1862",
                "postgiro": "370005-1"
            },
            "activity": "Konsulterande verksamhet inom byggnadsfacket",
            "employees": 0,
            "establishment_year": 1950,
            "key_personnel": [
                {
                    "name": "Sven Aspemyr",
                    "position": "Ägare o chef"
                }
            ]
        },
        "13": {
            "company_name": "ASPENS KONFEKTIONS. FABRIK AB",
            "pnr": "52100",
            "address": "Falköping, Hollenderg 31.",
            "phone_number": "0515-132 90",
            "bank_details": {
                "bankgiro": "213-7677",
                "postgiro": "291045-3"
            },
            "activity": "Tillverkar klänningar",
            "employees": 160,
            "annual_turnover": 11000000,
            "capital": 180000,
            "key_personnel": [
                {
                    "name": "Helge Asp",
                    "position": "Verkst dir"
                }
            ],
            "establishment_year": 1946
        },
        "14": {
            "company_name": "WAHLBECK, ERIK H",
            "pnr": "150 32",
            "address": "Stallarholmen.",
            "phone_number": "0152-410 00, 410 01",
            "bank_details": {
                "bankgiro": "325-1766",
                "postgiro": "454542-2"
            },
            "activity": "Guld- o silverkedjor i metervara av tråd",
            "establishment_year": 1948,
            "key_personnel": [
                {
                    "name": "Fabr Hans Wahlbeck",
                    "position": "Chef"
                }
            ]
        },
        "15": {
            "company_name": "FARTYGSISOLERING, AB",
            "pnr": "45100",
            "address": "Uddevalla, Stora Hälleviksg 4.",
            "phone_number": "0522-179 83, 182 54",
            "bank_details": {
                "bankgiro": "606-39 29",
                "postgiro": "28822-5"
            },
            "activity": "Isolering å fartyg, industrier o fastigheter",
            "employees": 20,
            "annual_turnover": 500000,
            "capital": 10000,
            "key_personnel": [
                {
                    "name": "Ing Kurt Munther",
                    "position": "Verkst dir"
                }
            ],
            "establishment_year": 1953
        },
        "16": {
            "company_name": "FARTYGSKONSTRUKTIONER AB",
            "pnr": "451 01",
            "address": "Uddevalla 1. Box 382.",
            "phone_number": "0522-364 00",
            "bank_details": {
                "bankgiro": "36-6675",
                "postgiro": "591282"
            },
            "activity": "Projekt-, klass-, ar-bets- o optiska ritningar",
            "employees": 50,
            "annual_turnover": 3000000,
            "capital": 20000,
            "key_personnel": [
                {
                    "name": "Ing Gustaf Mattsson",
                    "position": "Styrelseomd"
                },
                {
                    "name": "ing Arne Andersson",
                    "position": "styrelse"
                },
                {
                    "name": "Lars Mannström",
                    "position": "dir"
                }
            ],
            "establishment_year": 1961
        },
        "17": {
            "company_name": "VÄS",
            "varunamn": "Värnamo-VMA",
            "employees": 115,
            "annual_turnover": 9000000,
            "capital": 433600,
            "key_personnel": [
                {
                    "name": "Sven Westerberg",
                    "position": "Verkst dir"
                }
            ],
            "establishment_year": 1917
        },
        "18": {
            "company_name": "NYA",
            "activity": "samt redovisning, revision, skatteärenden, konkursärenden, in-kasso, förvaltnings- o finansärenden.",
            "capital": 40000,
            "key_personnel": [
                {
                    "name": "Revisor SBRP Nils Arvids",
                    "position": "Verkst dir"
                }
            ],
            "establishment_year": 1945
        },
        "19": {
            "company_name": "NOTNÄS ÅNGSÅG, AB"
        },
        "20": {
            "company_name": "NOVAKEMI AB",
            "pnr": "123 47",
            "address": "Farsta, Molkomsbacken 37.",
            "phone_number": "08-93 01 15",
            "bank_details": {
                "bankgiro": "173-8152",
                "postgiro": "656870-3"
            },
            "activity": "Import o försäljning av industrikemikalier samt metaller för laboratoriebruk",
            "employees": 10,
            "capital": 20000,
            "key_personnel": [
                {
                    "name": "Per-Erik Töreman",
                    "position": "Verkst dir"
                }
            ],
            "establishment_year": 1962
        },
        "21": {
            "company_name": "NOVATOR, REDERI AB",
            "pnr": "602 22",
            "address": "Norrköping, Saltängsg 33.",
            "phone_number": "011-1239 36",
            "bank_details": {
                "bankgiro": "12-5074",
                "postgiro": "84955"
            },
            "activity": "Rederirörelse",
            "employees": 20,
            "capital": 200000,
            "key_personnel": [
                {
                    "name": "Sven Wirström",
                    "position": "Verkst dir"
                }
            ],
            "establishment_year": 1933
        },
        "22": {
            "company_name": "NOVIA LIVSMEDELS. INDUSTRIER AB",
            "pnr": "29110",
            "address": "Kristianstad 10, Box 10070",
            "phone_number": "044-12 30 00",
            "activity": "torrkonserve-rade produkter samt burksoppor",
            "employees": 900,
            "key_personnel": [
                {
                    "name": "Ingvar Jonsson",
                    "position": "Arbetande styrelseordf"
                },
                {
                    "name": "Lars Ögren",
                    "position": "Verkst dir"
                }
            ],
            "establishment_year": 1971
        },
        "23": {
            "company_name": "NOVUM, AB",
            "pnr": "250 04",
            "address": "Hälsingborg 4, Bendzg 29. Box 4035",
            "phone_number": "042-970 70",
            "bank_details": {
                "bankgiro": "86-3525",
                "postgiro": "593520"
            },
            "activity": "Säljer elektr installationsmateriel, kopplingsur m m",
            "capital": 0,
            "key_personnel": [
                {
                    "name": "Owe Näckberg",
                    "position": "Verkst dir"
                }
            ],
            "establishment_year": 1962
        }
    }
}