{
    "original": "STOTSBERG&amp; BROBERG\n\nPnr 400 60\n\nGöteborg 6, N Gubberog 22. Box\n6034. Tel 031-15 08 17, 15 95 33.\nBankgiro 420-4392. Postgiro\n45999-0. Tga Stöbro\nVerksamhet: Agent i råvaror för\nfärg- o lackindustrin etc\nÄgare o chefer: Iwan Stötsberg,\nErnst Broberg\nEtableringsår: 1939.\n\nSELLBERG AB, C J\n\nPnr 433 00\n\nPartilie, Kyrkv 10. Box 98. Tel\n031-440720. Bankgiro 511-6371.\nPostgiro 48676-1. Tga Washing\nVerksamhet: Tillverkar\ntvättmaskiner o centrifuger\nVarunamn: Podab/Revecent\nAntal anställda: 70\nÅrsomsättning: 6 000 000\nAktiekapital: 350000\nVerkst din Carl Johan Sellberg\nEtableringsår: 1956.\n\nTRANEMO FÄRG AB\n\nPnr 510 80\n\nTranemo. Tel 0325-707 70-\nBankgiro 55-3132. Postgiro 7895. Tga\nPaint\n\nVerksamhet: Färger för måleri o\nindustri\n\nAntal anställda: 60\nÅrsomsättning: 8 500 000\nAktiekapital: 200 000\nVerkst dir: Arvid Stigsén\nEtableringsår 1919.\n\nCON\n\nVerksamhet: Agenturrörelse med\nplastråvaror, kimrök,\nplastmaskiner o tryckmaskiner\nAntal anställda: 10\nÅrsomsättning: 20000 000\nAktiekapital: 50 000\nVerkst dir: Ing Erik G Jonsson\nEtableringsår: 1959.\n\nNOR\n\nImporterar arbetshandskar,\nskyddshjälmar, slangarmatur m m\nVarunamn: Apollo, Novex\nChef: A G Nordstrand\nEtableringsår: 1954.\n\nNORDSTRAND,\nINGENJÖRS-FIRMA GÖSTA\n\nPnr 11440\n\nStockholm, Nybrog 42. Tel\n08-60 20 05. Bankgiro 16-7433. Postgiro\n3181\n\nVerksamhet: Utför rörrensning,\nlagning av avloppsrör, camber o\nfönsterisolering. Trädgårdskonst\nChef: Gösta Nordstrand\nEtableringsår: 1936.\n\nNORDSTROM &amp; CO TRÄ.\nVAROR KB\n\nPnr 100 72\n\nStockholm 43, Lövholmsv 11. Box\n43053. Tel 08-18 81 30. Bankgiro\n56-8111. Postgiro 1345\nVerksamhet: Brädgårds- o\nbyggnadsmateria lrörelse\nChef: Disp B Nordström.\n\nNORDSTROMS JERN.\nHANDEL, AB\n\nPnr 682 00\n\nFilipstad, Vikg 5. Tel 0590-100 39,\n106 84. Bankgiro 10-6203. Postgiro\n8024\n\nVerksamhet: Säljer järnvaror i parti\no minut\n\nAntal anställda: 6\nÅrsomsättning: 1700 000\nAktiekapital: 88 000\nStyrelse: Konsul Thorild Geijer\n(ordf), järnh Sture Lindberg, järnh\nKarl-Erik Melén\nVerkst dir: Karl-Erik Melén\nJärnh: Sture Lindberg\nEtableringsår: 1849\nOmbildat till aktiebolag 1904.\n\nNORDSTROMS LINBANOR, AB\n\nPnr 105 26\n\nStockholm, Kungsbroplan 3. Tel\n08-52 07 80. Bankgiro 166-04 30.\nPostgiro 51789-6. Tga Linbana.\nTelex 10085\n\nVerksamhet:\nTransportanläggningar för cellulosafabriker, sågverk,\ncement-, porslins- o\nverkstadsindustrin, gruvor, järnverk, fartyg,\nhamnar, bro- o kraftverksbyggnad\nVerkstad: Enköping. Tel\n0171-33310\n\nAntal anställda: 350\nAktiekapital: 1500 000\nVerkst dir: Arne Ahlström\nEtableringsår: 1891\nOmbildat till aktiebolag 1911.\n\nNORDSTROMS ROSTFRIA\nINDUSTRI AB\n\nPnr 252 02\n\nHelsingborg 2, Box 2100.\nGåse-bäcksv 8. Tel 042-12 04 20.\nBankgiro 268-9768. Postgiro 447923-4\nVerksamhet: Utför rostfria\nspecialarbeten för livsmedelsindustrin,\nkemisk industri, fryshus, skeppsvarv\n(pentry o kabyssinredningar),\nsjukhusinredningar, storköksutrustningar, rostfria kärl o tankar, rostfria\nplåtarbeten samt drag- o\nkantpress-ningsarbeten\n\nAntal anställda: 40\nAktiekapital: 125 000\nVerkst dir: L Laweson\nEtableringsår: 1920\nOmbildat till aktiebolag 1947.\n\nNORDSTROM &amp; SON AB\n\nPnr 10241\n\nStockholm 5, Braheg 4. Box 5027.\nTel 08-67 06 35. Bankgiro 575-7190.\nPostgiro 516-5\n\nVerksamhet: Läder, skinn- o\nrepvaror samt omslagspapper o\nbindgarn\n\nAktiekapital: 125 000\nVerkst dir: K Neiderud\nEtableringsår: 1874.\n\nSVE\n\n15 57 20. 15 40 35. Bankgiro\n214-9573. Postgiro 436167-1\nVerksamhet: Mekanisk verkstad.\nUtför svarvning, fräsning,\nexcen-terpressning, klippning, plåt- o\nrostfria arbeten\nAntal anställda: 20\nÅrsomsättning: 2 000 000\nAktiekapital: 150000\nVerkst dir: Sven Mortin\nEtableringsår: 1955.\n\nVARA TEGELBRUK, AB\n\nPnr 53401\n\nVara 1, Box 93. Tel 0512-100 32,\n10150. Bankgiro 215-4813.\nPost&gt;-giro 22266-1. Tga Tegelbruket\nVerksamhet: Tillverkar o säljer\nmurtegel o tegelrör\nAntal anställda: 21\nÅrsomsättning: 1200 000\nAktiekapital: 200 000\nVerkst dir: Disp Lennart Paulsson\nEtableringsår: 1904.\n\nÅDALENS JÄRN &amp; FÄRG, AB\n\nPnr 87201\n\nKramfors 1. Box 24. Tel\n0612-114 60. Bankgiro 186-9387.\nPostgiro 13139-1\n\nVerksamhet: Säljer järnvaror,\nbygg-o industrivaror, bränslen, färg\nAktiekapital: 30 000\nVerkst din Lennart Ohlsson\nEtableringsår: 1919.\n\nLARSSON AB, MANNE\n\nPnr 58104\n\nLinköping 1, Roxeng 2 2. Box 407.\nTel 013-14 63 00. Bankgiro\n347-0929. Postgiro 21475-9\nVerksamhet: Livsmedelsgrossist\nAktiekapital: 175 000\nVerkst dir: Sven Mannerson\nEtableringsår: 1886.\n\nLARSSONS MEK VERKSTAD,\nab martin\n\nPnr 690 70\n\nPålsboda, Box 73. S Bang. Tel\n0582-406 20. Bankgiro 822-5062.\nPostgiro 99201-6\nVerksamhet: Legotillverkning av\nhögkvalificerade tryckkärl för bl a\nkyl-, petrokemiska o kemisk\ntekniska industrianläggningar\n\nAntal anställda: 115\nÅrsomsättning: 15 000 000\nAktiekapital: 500000\nStyrelseordf: Dir Bertil Bohlin\nVerkst dir: Bertil Bohlin\nTekn service o utveckling:\nSpecial-försäljn: üvering K G Ljungqvist\nÖvrig försäljning: Ing Alf-Göran\nLundgren\n\nEkonomi: Kamrer Bertil Rehnvall\nInköp: S O Hansson\nEtableringsår. 1934\nOmbildat till aktiebolag 1943.\n\nLARSSON SNICKERI AB, PAUL\n\nPnr 710 20\n\nStora Mellösa, Alm. Tel 019-450 61.\nBankgiro 82-2432. Postgiro 177681\nVerksamhet: Tillverkar dörrar,\nglaspartier, heställningssnickerier\nAntal anställda: 7\nÅrsomsättning: 600000\n.Aktiekapital: 5 000\nVerkst dir: Thorbjörn Larsson\nEtableringsår: 1940.\n\nLARSSONS SVETS &amp; SMIDE,\nAB R\n\nPnr 53100\n\nLidköping, Sockerbruks g 9. Tel\n0510-226 59. Bankgiro 346-6976.\nPostgiro 339590-2\nVerksamhet: Utför byggnads- o\növriga smiden\nAntal anställda: 12\nÅrsomsättning: 7 00 000\nChef: Gunnar Larsson.\n\nLARSSONS\nKONSTRUKTIONS-BYRÅ AB, RUNE\n\nPnr 45100\n\nUddevalla, Västerlångg 26. Tel\n0522-160 02, 356 02. Bankgiro\n405-4078. Postgiro 671422\nVerksamhet: Konstruktioner,\nkontroller, besiktningar o värderingar\nför byggnader m m\nAntal anställda: 4\nÅrsomsättning: 300 000\nAktiekapital: 5 000\nVerkst dir: Ing Rune Larsson\nEtableringsår: 1965.\n\nLARSSONS REVISIONSBYRÅ\nAB,STEN\n\nPnr 15200\n\nSträngnäs, Källg 4. Box 86. Tel\n0152-119 00, 119 01. Bankgiro\n400-7589. Postgiro 431940-6\nVerksamhet: Ekonomiska\nutredningar, skatteärenden, bokslut\nAntal anställda: 6\nÅrsomsättning: 250 000\nAktiekapital: 5 000\nEtableringsår: 1962.\n\n|MA INDUSTRIMATERIAL, AB\n\nPnr 250 02\n\nHälsingborg 2, Box 2064. Tel\n042-1128 62, 1313 67. Bankgiro\n65-2885. Postgiro 497490\nVerksamhet: Säljer box- o\nflänspackningar, egentillverkning av\npackningssets o\nmanluckspack-ningar. Industrigummi såsom slangar\nför alla ändamål, gummiduk,\nplattor, kilremmar o flata remmar.\nImportörer av Lomoto boxpackningar\no Intradur flänspackningar samt\nmaskinförnödenheter\nVarunamn: Lomoto, Intradur\nAntal anställda: 4\nÄgare o chef: Klas Mårtensson\nEtableringsår: 1955.",
    "structured": {
        "1": {
            "company_name": "STOTSBERG&BROBERG",
            "address": "Göteborg 6, N Gubberog 22. Box 6034",
            "phone_number": "031-15 08 17, 15 95 33",
            "bank_details": {
                "bankgiro": "420-4392",
                "postgiro": "45999-0"
            },
            "activity": "Agent i råvaror för färg- o lackindustrin etc",
            "key_personnel": [
                {
                    "name": "Iwan Stötsberg",
                    "position": "Ägare"
                },
                {
                    "name": "Ernst Broberg",
                    "position": "Chef"
                }
            ],
            "establishment_year": 1939
        },
        "2": {
            "company_name": "SELLBERG AB, C J",
            "address": "Partilie, Kyrkv 10. Box 98",
            "phone_number": "031-440720",
            "bank_details": {
                "bankgiro": "511-6371",
                "postgiro": "48676-1"
            },
            "activity": "Tillverkar tvättmaskiner o centrifuger",
            "employees": 70,
            "annual_turnover": 6000000,
            "capital": 350000,
            "establishment_year": 1956
        },
        "3": {
            "company_name": "TRANEMO FÄRG AB",
            "address": "Tranemo",
            "phone_number": "0325-707 70",
            "bank_details": {
                "bankgiro": "55-3132",
                "postgiro": "7895"
            },
            "activity": "Färger för måleri o industri",
            "employees": 60,
            "annual_turnover": 8500000,
            "capital": 200000,
            "key_personnel": [
                {
                    "name": "Arvid Stigsén",
                    "position": "Verkst dir"
                }
            ],
            "establishment_year": 1919
        },
        "4": {
            "company_name": "CON",
            "activity": "Agenturrörelse med plastråvaror, kimrök, plastmaskiner o tryckmaskiner",
            "employees": 10,
            "annual_turnover": 20000000,
            "capital": 50000,
            "key_personnel": [
                {
                    "name": "Ing Erik G Jonsson",
                    "position": "Verkst dir"
                }
            ],
            "establishment_year": 1959
        },
        "5": {
            "company_name": "NOR",
            "activity": "Importerar arbetshandskar, skyddshjälmar, slangarmatur m m",
            "key_personnel": [
                {
                    "name": "A G Nordstrand",
                    "position": "Chef"
                }
            ],
            "establishment_year": 1954
        },
        "6": {
            "company_name": "NORDSTRAND, INGENJÖRS-FIRMA GÖSTA",
            "address": "Stockholm, Nybrog 42",
            "phone_number": "08-60 20 05",
            "bank_details": {
                "bankgiro": "16-7433",
                "postgiro": "3181"
            },
            "activity": "Utför rörrensning, lagning av avloppsrör, camber o fönsterisolering. Trädgårdskonst",
            "key_personnel": [
                {
                    "name": "Gösta Nordstrand",
                    "position": "Chef"
                }
            ],
            "establishment_year": 1936
        },
        "7": {
            "company_name": "NORDSTROM & SON AB",
            "address": "Stockholm 5, Braheg 4. Box 5027",
            "phone_number": "08-67 06 35",
            "bank_details": {
                "bankgiro": "575-7190",
                "postgiro": "516-5"
            },
            "activity": "Läder, skinn- o repvaror samt omslagspapper o bindgarn",
            "capital": 125000,
            "key_personnel": [
                {
                    "name": "K Neiderud",
                    "position": "Verkst dir"
                }
            ],
            "establishment_year": 1874
        },
        "8": {
            "company_name": "SVE",
            "address": "15 57 20. 15 40 35",
            "bank_details": {
                "bankgiro": "214-9573",
                "postgiro": "436167-1"
            },
            "activity": "Mekanisk verkstad. Utför svarvning, fräsning, excen-terpressning, klippning, plåt- o rostfria arbeten",
            "employees": 20,
            "annual_turnover": 2000000,
            "capital": 150000,
            "key_personnel": [
                {
                    "name": "Sven Mortin",
                    "position": "Verkst dir"
                }
            ],
            "establishment_year": 1955
        }
    }
}