{
    "original": "SVENSKA OPTISKA AB\n\nPnr 16105\n\nBromma 5, Ängbyplan 69-71. Box\n507. Tel 08-37 29 20. Bankgiro\n562-9720. Postgiro 1411-8. Tga\nSvenskoptik\n\nVerksamhet: Grosshandel med\noptiska varor, glassliperi för optiska\nglas\n\n.Antal anställda: 35\nÅrsomsättning: 4 200 000\nAktiekapital: 150 000\nStyrelse: Dir Ruben Hlittner (ordf),\ndir Leif Hamrin, dir Bertil\nKeko-nius\n\nVerkst dir: Bertil Kekonius\nEtableringsår: 1954.\n\nSCHARINS FÄRG AB\n\nPnr 26131\n\nLandskrona, Rådhustorget. Tel\n0418-226 00 , 226 01. Tga Scharin\nVerksamhet: Färg o parfymeri i\nparti o minut\n\nÄgare o chef: Gösta Ericsson\nEtableringsår 1898.\n\nSINCLAIR &amp; SON AB, JAMES\n\nPnr 421 76\n\nVästra Frölunda, Tuvg 1. Tel\n031-29 23 31, 29 28 03. Tga Sinclair\nVerksamhet: Assurans- o\nagentaffär\n\nAkUekapital: 5 000\nVerkst dir: Fru M S Sinclair\nEtableringsàr 1820\nOmbildat till aktiebolag 1938.\n\nSINCOPAC AB\n\nPnr 162 26\n\nVäUingby, Krossg 30. Tel\n08-380015. Telex 1226\nVerksamhet: Packutrustning, filmer,\nlaminater, tråg, nät, krymppåsar\nm m. Prismärkning o förslutning.\nInpackningsmaskiner\nAntal anstäUda: 35\nÅrsomsättning: 11000 000\nAkUekapital: 150 000\nVeikst dir: Ingvar Mjörnefeldt\nEtableringsàr 1961.\n\nAGA VÄRMLAND AB\n\nPnr 65106\n\nKarlstad 1, Lambergets\nindustriområde. Box 386. Tel 054-15 0170.\nBankgiro 100-2476. Postgiro\n36145-1\n\nVerksamhet: Tillverkning o\nförsäljning av acetylen\nAntal anställda: 9\nÅrsomsättning: 1600 000\nAktiekapital: 600 000\nStyrelse: Dir Christer Danielsson\n(ordf), dir Sten Isacsson, kamrer\nRune Trygg, civiling Erik Wästlund\nVerkst dir: Civiling Erik Wästlund\nEtableringsår: 1929\nDotterbolag till AGA AB, Lidingö.\n\nAGA.PLÄTFüRÄDLING AB\n\nPnr 252 30\n\nHelsingborg, Industrig 54. Tel\n042-12 63 00. Tga Radiatorbolag.\nTelex 72275\n\nVerksamhet: Tillverkar radiatorer,\nkonvektorer, radiatortermostater\nAktiekapital: 6000 000\nVerkst dir: Lars Lokrantz\nEtableringsår: 1918.\n\nBOCKENS BRYGGERIER AB\n\nPnr 800 11\n\nGävle 11, Fack. Storg 16. Strömsbro.\nHuvudkontor. Tel 026-12 92 60.\nBankgiro 783-7941. Postgiro\n81507-6. Tga Bockbryggerier\nVerksamhet: Tillverkar o säljer\nmaltr o läskedrycker\nBryggeriet Gustafsbro: Godsadress:\nGävle, Västra v 54. Tel026-1292 60\nBryggeriet Hudiksvall: Godsadress:\nHudiksvall, V Tullg 13-15. Tel\n0650-15 4 50\n\nFörsäljningsdepåer i södra\nNorrland o Mellansverige\nAntal anställda: 250\nÅrsomsättning: 45000 000\nAktiekapital: 2 400 000\nVerkst dir: Curt R Widén\nEtableringsår: 1849.\n\nUPSALA NYA TIDNING, AB\n\nPnr 751 03\n\nUppsala 1, Danmarksg 28. Box 36.\nTel 018-1002 00. Postgiro\n25144-7\n\nVerksamhet: Tidningsutgivning\nAktiekapital: 1112 000\nVerkst dir: Per V Ocklind\nEtableringsår: 1890.\n\nUPPSALA OPTISKA\nINDUSTRI, AB\n\nPnr 751 06\n\nUppsala 1, Storg 30. Box 487. Tel\n018-1113 20. Bankgiro 80-2275.\nPostgiro 90755. Tga Optik\n\nVerksamhet: Säljer glasögonoptik\no tillverkar glasögonglas, speciellt\nmultifokala o vacuumbehandlade\n(färgade)\n\nFilialer: Göteborg 1, Box 486. Tel\n031-1137 01\n\nMalmö C, Djäkneg 17. Tel\n040-379 65\n\nStockholm 19, Box 19083. Tel\n08-34 25 81\n\nUmeå, Kungsg 49. Tel 090-12 75 63\nAktiekapital: 500 000\nVerkst dir: Willi Drömer\nEtableringsår: 1937\nOmbildat till aktiebolag 1939.\n\nUPPSALA REVISIONSBYRÅ AB\n\nPnr 753 20\n\nUppsala, Kungsg 32. Tel\n018-111190. Bankgiro 405-0589.\nPost-giro 578552-2\n\nVerksamhet Revision,\nbokslutsarbete, siffergranskning, bokföring\nAntal anställda: 13\nÅrsomsättning: 850 000\nAktiekapital: 75 000\nVerkst dir. Aukt revisor Töre\nUhlén\n\nEtableringsån 1932.\n\nNORDISKA GALLERIET, AB\n\nPnr 114 39\n\nStockholm, Nybrog 11. Tel\n08-67 05 55. Bankgiro 165-5190.\nPostgiro 41-4. Tga Nordgalleri\nVerksamhet: Specialaffär för möbler\no konst. Kunglig hovleverantör\nAktiekapital: 100 000\nStyrelse: S Rindborg (ordf), C M\nHeigard, M Heigard\nVerkst dir: CM Heigard\nEtableringsår: 1913.\n\nWESTMANS WOODEXPORT\n\nPnr 417 28\n\nGöteborg, Krabbeliderna 37. Tel\n031-23 17 35. Bankgiro 848-2465.\nTga Westwood\n\nVerksamhet: Export av telådor,\nte-làdsplywood, telàdsokar m m\nÄgare o chef: A Holger Westman\nEtableringsån 1956.\n\nNORDFALKS AB\n\nPnr 43121\n\nMölndal 1, Flöjelbergsg 2. Box 63.\nTel 031-27 50 20. Bankgiro 43-9813.\nPostgiro 45685. Tga Nordfalks\nVerksamhet: Import av kryddor.\nGeneralagent för Tetley te\nVarunamn: Tetley Te\nAntal anställda: 57\nÅrsomsättning: 11000 000\nAktiekapital: 400 000\nVerkst dir: Jur kand Lars-Olof\nMattsson\n\nEtableringsår: 1946.\n\n|MA\n\nI MAS, AB\n\nPnr 114 52\n\nStockholm, Skepparg 22. Tel\n08-6316 20. Postgiro 406710\nVerksamhet; Formsprutning av\nplastdetaljer\nAntal anställda: 8\nAktiekapital: 5 000\nVeikst dir. H R Aggenberg.\n\nIMECO, ASTRA AGENCY\nCO AB\n\nPnr 12612\n\nStockholm 42, Box 42070. Tel\n08-18 83 60. Bankgiro 160-0907.\nPostgiro 602895-5. Tga Imecopharm.\nTelex 19056 MED ÄST S\nVerksamhet: Agentur: etiska\nfar-macevtiska preparat samt\ndiagnos-tika\n\nVarunamn: Imeco\n\nAktiekapital: 100 000\n\nStyrelse: Dlr Karl Ame Wegerfelt\n\n(ordf), dir Stig Jakobsson, dir Gösta\n\nMagnusson\n\nVerkst dir: Gösta Magnusson\nEtableringsår. 1959\nDotterbolag till AB Astra,\nSödertälje.\n\nIMI-AB INDUSTRIELLA\nMARKNADSINSTITUTET\n\nPnr 114 55\n\nStockholm, Grev Magnig 5. Tel\n08-62 86 80. Postgiro 403970-7\nVerksamhet: Industriella\nmarknadsundersökningar, konsultation\nAktiekapital: 10000\nVerkst dir: Börje Lindberg\nEtableringsår: 1965.",
    "structured": {
        "1": {
            "company_name": "SVENSKA OPTISKA AB",
            "pnr": "16105",
            "address": "Bromma 5, Ängbyplan 69-71. Box 507",
            "phone_number": "08-37 29 20",
            "bank_details": {
                "bankgiro": "562-9720",
                "postgiro": "1411-8"
            },
            "activity": "Grosshandel med optiska varor, glassliperi för optiska glas",
            "employees": 35,
            "annual_turnover": 4200000,
            "capital": 150000,
            "key_personnel": [
                {
                    "name": "Ruben Hlittner",
                    "position": "ordf"
                },
                {
                    "name": "Leif Hamrin",
                    "position": "dir"
                },
                {
                    "name": "Bertil Keko-nius",
                    "position": "dir"
                },
                {
                    "name": "Bertil Kekonius",
                    "position": "Verkst dir"
                }
            ],
            "establishment_year": 1954
        },
        "2": {
            "company_name": "SCHARINS FÄRG AB",
            "pnr": "26131",
            "address": "Landskrona, Rådhustorget",
            "phone_number": "0418-226 00 , 226 01",
            "activity": "Färg o parfymeri i parti o minut",
            "owner": "Gösta Ericsson",
            "establishment_year": 1898
        },
        "3": {
            "company_name": "SINCLAIR & SON AB, JAMES",
            "pnr": "421 76",
            "address": "Västra Frölunda, Tuvg 1",
            "phone_number": "031-29 23 31, 29 28 03",
            "activity": "Assurans- o agentaffär",
            "capital": 5000,
            "key_personnel": {
                "name": "Fru M S Sinclair",
                "position": "Verkst dir"
            },
            "establishment_year": 1820,
            "restructured_year": 1938
        },
        "4": {
            "company_name": "SINCOPAC AB",
            "pnr": "162 26",
            "address": "VäUingby, Krossg 30",
            "phone_number": "08-380015",
            "telex": "1226",
            "activity": "Packutrustning, filmer, laminater, tråg, nät, krymppåsar m m. Prismärkning o förslutning. Inpackningsmaskiner",
            "employees": 35,
            "annual_turnover": 11000000,
            "capital": 150000,
            "key_personnel": {
                "name": "Ingvar Mjörnefeldt",
                "position": "Verkst dir"
            },
            "establishment_year": 1961
        },
        "5": {
            "company_name": "AGA VÄRMLAND AB",
            "pnr": "65106",
            "address": "Karlstad 1, Lambergets industriområde. Box 386",
            "phone_number": "054-15 0170",
            "bank_details": {
                "bankgiro": "100-2476",
                "postgiro": "36145-1"
            },
            "activity": "Tillverkning o försäljning av acetylen",
            "employees": 9,
            "annual_turnover": 1600000,
            "capital": 600000,
            "key_personnel": [
                {
                    "name": "Christer Danielsson",
                    "position": "ordf"
                },
                {
                    "name": "Sten Isacsson",
                    "position": "dir"
                },
                {
                    "name": "Rune Trygg",
                    "position": "kamrer"
                },
                {
                    "name": "Erik Wästlund",
                    "position": "civiling"
                },
                {
                    "name": "Erik Wästlund",
                    "position": "Verkst dir"
                }
            ],
            "establishment_year": 1929
        },
        "6": {
            "company_name": "AGA.PLÄTFüRÄDLING AB",
            "pnr": "252 30",
            "address": "Helsingborg, Industrig 54",
            "phone_number": "042-12 63 00",
            "telex": "72275",
            "activity": "Tillverkar radiatorer, konvektorer, radiatortermostater",
            "capital": 6000000,
            "key_personnel": {
                "name": "Lars Lokrantz",
                "position": "Verkst dir"
            },
            "establishment_year": 1918
        },
        "7": {
            "company_name": "BOCKENS BRYGGERIER AB",
            "pnr": "800 11",
            "address": "Gävle 11, Fack. Storg 16. Strömsbro. Huvudkontor",
            "phone_number": "026-12 92 60",
            "bank_details": {
                "bankgiro": "783-7941",
                "postgiro": "81507-6"
            },
            "activity": "Tillverkar o säljer maltr o läskedrycker",
            "employees": 250,
            "annual_turnover": 45000000,
            "capital": 2400000,
            "key_personnel": {
                "name": "Curt R Widén",
                "position": "Verkst dir"
            },
            "establishment_year": 1849
        },
        "8": {
            "company_name": "UPSALA NYA TIDNING, AB",
            "pnr": "751 03",
            "address": "Uppsala 1, Danmarksg 28. Box 36",
            "phone_number": "018-1002 00",
            "postgiro": "25144-7",
            "activity": "Tidningsutgivning",
            "capital": 1112000,
            "key_personnel": {
                "name": "Per V Ocklind",
                "position": "Verkst dir"
            },
            "establishment_year": 1890
        },
        "9": {
            "company_name": "UPPSALA OPTISKA INDUSTRI, AB",
            "pnr": "751 06",
            "address": "Uppsala 1, Storg 30. Box 487",
            "phone_number": "018-1113 20",
            "bank_details": {
                "bankgiro": "80-2275",
                "postgiro": "90755"
            },
            "activity": "Säljer glasögonoptik o tillverkar glasögonglas, speciellt multifokala o vacuumbehandlade - filialer: Göteborg 1, Malmö C, Stockholm 19, Umeå",
            "capital": 500000,
            "key_personnel": {
                "name": "Willi Drömer",
                "position": "Verkst dir"
            },
            "establishment_year": 1937,
            "restructured_year": 1939
        },
        "10": {
            "company_name": "UPPSALA REVISIONSBYRÅ AB",
            "pnr": "753 20",
            "address": "Uppsala, Kungsg 32",
            "phone_number": "018-111190",
            "bank_details": {
                "bankgiro": "405-0589",
                "postgiro": "578552-2"
            },
            "activity": "Revision, bokslutsarbete, siffergranskning, bokföring",
            "employees": 13,
            "annual_turnover": 850000,
            "capital": 75000,
            "key_personnel": {
                "name": "Aukt revisor Töre Uhlén",
                "position": "Verkst dir"
            },
            "establishment_year": 1932
        },
        "11": {
            "company_name": "NORDISKA GALLERIET, AB",
            "pnr": "114 39",
            "address": "Stockholm, Nybrog 11",
            "phone_number": "08-67 05 55",
            "bank_details": {
                "bankgiro": "165-5190",
                "postgiro": "41-4"
            },
            "activity": "Specialaffär för möbler o konst - Kunglig hovleverantör",
            "capital": 100000,
            "key_personnel": {
                "name": "S Rindborg",
                "position": "ordf"
            },
            "establishment_year": 1913
        },
        "12": {
            "company_name": "WESTMANS WOODEXPORT",
            "pnr": "417 28",
            "address": "Göteborg, Krabbeliderna 37",
            "phone_number": "031-23 17 35",
            "bank_details": {
                "bankgiro": "848-2465"
            },
            "activity": "Export av telådor, te-lådsplywood, te-lådsokar m m",
            "owner": "A Holger Westman",
            "establishment_year": 1956
        },
        "13": {
            "company_name": "NORDFALKS AB",
            "pnr": "43121",
            "address": "Mölndal 1, Flöjelbergsg 2. Box 63",
            "phone_number": "031-27 50 20",
            "bank_details": {
                "bankgiro": "43-9813",
                "postgiro": "45685"
            },
            "activity": "Import av kryddor. Generalagent för Tetley te - Varunamn: Tetley Te",
            "employees": 57,
            "annual_turnover": 11000000,
            "capital": 400000,
            "key_personnel": {
                "name": "Jur kand Lars-Olof Mattsson",
                "position": "Verkst dir"
            },
            "establishment_year": 1946
        },
        "14": {
            "company_name": "MAS, AB",
            "pnr": "114 52",
            "address": "Stockholm, Skepparg 22",
            "phone_number": "08-6316 20",
            "postgiro": "406710",
            "activity": "Formsprutning av plastdetaljer",
            "employees": 8,
            "capital": 5000,
            "key_personnel": {
                "name": "H R Aggenberg",
                "position": "Verkst dir"
            }
        },
        "15": {
            "company_name": "IMECO, ASTRA AGENCY CO AB",
            "pnr": "12612",
            "address": "Stockholm 42, Box 42070",
            "phone_number": "08-18 83 60",
            "bank_details": {
                "bankgiro": "160-0907",
                "postgiro": "602895-5"
            },
            "activity": "Agentur: etiska farmacevtiska preparat samt diagnostika - Varunamn: Imeco",
            "capital": 100000,
            "key_personnel": [
                {
                    "name": "Karl Ame Wegerfelt",
                    "position": "ordf"
                },
                {
                    "name": "Stig Jakobsson",
                    "position": "dir"
                },
                {
                    "name": "Gösta Magnusson",
                    "position": "Verkst dir"
                }
            ],
            "establishment_year": 1959,
            "daughter_company_of": "AB Astra, Södertälje"
        },
        "16": {
            "company_name": "IMI-AB INDUSTRIELLA MARKNADSINSTITUTET",
            "pnr": "114 55",
            "address": "Stockholm, Grev Magnig 5",
            "phone_number": "08-62 86 80",
            "postgiro": "403970-7",
            "activity": "Industriella marknadsundersökningar, konsultation",
            "capital": 10000,
            "key_personnel": {
                "name": "Börje Lindberg",
                "position": "Verkst dir"
            },
            "establishment_year": 1965
        }
    }
}