{
    "original": "KORES, AB\n\nPnr 185 00\n\nVaxholm, Janne Gustavssons v 3.\nTel 0764-30 1 70. Postgiro 51277.\nTga Korescarbo. Telex 11254\nVerksamhet: Tillverkar\nkarbonpap-per, färgband, stencil er o\nduplice-ringsfärg, genomskriftspapper\nFabrik 1: 185 00 Vaxholm, Janne\nGustavssons v 3. Tel 0764-305 90,\n313 00\n\nFabrik 2: 602 22 Norrköping.\nHan-holmsv 51. Tel 011-11 8030\nAntal anställda: 60\nÅrsomsättning: 15 000 000\nAktiekapital: 1000 000\n\n350\n\nStyrelse: Dir Anders Thustrup\n(ordf), fru Maj Harting,\ncivilekonom Urban Harting\nVerkst dir: Civilekonom Urban\nHarting\n\nEtableringsår: 1928\nOmbildat till aktiebolag 1934.\n\nKORFITSEN AGENTURFIRMA,\nCARL\n\nPnr 104 05\n\nStockholm, Ekhagsv 2. Tel\n08-15 99 20, 15 99 21. Bankgiro\n16-6818. Postgiro 199245-2. Tga\nKor-fitsenco. Telex 10556 KORFITS S\nVerksamhet: Agenturrörelse i\nmattor o textilvaror såsom spetsar o\ndylikt för konfektionsindustrin\nAntal anställda: 5\nChef: Torgny Korfitsen\nEtableringsår: 1909.\n\nJACOBSON AB, OTTO\n\nPnr 11129\n\nStockholm, Svartmang 16. Tel\n08-1012 98, 202110. Bankgiro\n72-1714. Postgiro 50188\nVerksamhet: Grossist i papper o\nbindgarn\n\nAktiekapital: 102000\nVerkst dir: Hans Jacobson\nEtableringsår: 1899\nOmbildat till aktiebolag 1942.\n\nJAKOBSSON HUSBYGGNADS.\nkonstruktioner ab,\nroland\n\nPnr 602 24\n\nNorrköping, Strömparken 22. Tel\n011-13 8551. Bankgiro 826-2032.\nPostgiro 695560-3\nVerksamhet: Konsulterande\ningenjörsbyrå\n\nÅrsomsättning: 125 000\n\nAktiekapital: 5 000\n\nVerkst dir: Byggn-ing SBR Roland\n\nJakobsson\n\nEtableringsår: 1961.\n\nJACOBSSONS REVISIONSBYRÅ\nab, rolf\n\nPnr 41110\n\nGöteborg. O Hamnsg 5. Tel\n031-17 89 70. Bankgiro 500-1672.\nPostgiro 45295-3. Tga Auktrev\nVerksamhet: Revisioner,\nutredningar m m\nAntal anställda: 28\nÅrsomsättning: 1800 000\nAktiekapital: 80 000\nDelägare: Ake Fryklund, Claes E\nÅhrén, Lars Elvstad, Nils Rilby,\nCarl Erik Ekbom, Stig Ekwall,\nHans Hedlund\nEtableringsår: 1939\nOmbildat till aktiebolag 1945.\n\nJACOBSSON INGENJÖRSBYRÄ,\nsture\n\nPnr 702 12\n\nÖrebro. Trädgårdsg 9. Tel\n019-18 49 02, 18 49 08. Postgiro\n247506-9\n\nVerksamhet: Projekteringar,\nkonstruktioner. utredningar,\nbesiktningar o kontroll\nAntal anställda: 3\nChef: Byggn-ing SBR Sture\nJacobsson\n\nlng:r: Klas Hallström, Tommy\nAhlberg\n\nEtableringsår. 1957.\n\nCENTRUMLINJEN, REDERI AB\n\nPnr 211 20\n\nMalmö, Skeppsbron 8. Tel\n040-745 90. Postgiro 532330-8\nVerksamhet: Rederirörelse\nAntal anställda: 85\nÅrsomsättning: 10 000 000\nAktiekapital: 196 000\nVerkst dir: O Brinck.\n\nCENTRUMPROJEKTERING\nCEPRO AB\n\nPnr 100 26\n\nStockholm 34, Box 34047.\nWi-valliusg 2. Tel 08-13 1980.\nBankgiro 222-0036. Postgiro 604422-6\nVerksamhet: Konsulterande\ningenjörsverksamhet inom byggsektorn.\nSvarar för byggledning,\nkostnads-o tidplanering o utför\nkonstruktioner inom hela byggområdet\nAntal anställda: 30\nÅrsomsättning: 2 000 000\nAktiekapital: 5 000\nStyrelseordf: Tekn lic Rolf Lerfors\nVerkst dir: Rolf Lerfors\nÖveringenjör: Stig Nordqvist\nByggnadsingejör: Rune Westberg\nEtableringsår: 1967.\n\nI 16\n\nC EOS BYGGNADSVAROR AB\n\nPnr 57100\n\nNässjö, Box 234. Teleg 4. Tel\n0380-183 50. Bankgiro 452-9368.\nPostgiro 383505-5\nVerksamhet: Trävaror o\nbyggmaterial i detalj, engros o export\nAntal anställda: 70\nÅrsomsättning: 23 000 000\nAktiekapital: 150 000\nVerkst dir: N-G Karlsson\nEtableringsår: 1927.\n\nSVETS &amp; MONTAGE\n\nPnr 660 56\n\nSkattkärr, Ramg 6. Box 39. Tel\n054-600 44, 1512 35. Bankgiro 88-1570\nVerksamhet: Stålkonstruktioner o\njärnmonteringar av alla slag.\nPlåtarbeten o licenssvetsning\nAntal anställda: 16\nÅrsomsättning: 1000 000\nChef: Pabr Ingemar Olsson\nEtableringsår: 1959.\n\nSVETSINDUSTRI EINAR\nJOHANSSON\n\nPnr 581 02\n\nLinköping 1, Staby gård. Box 56.\nTel 013-12 86 78. Postgiro 384540\nVerksamhet: Tillverkar\njärnkonstruktioner, karosserier o stålhytter\nChef: Pabr Einar Johansson\nEtableringsår: 1945.\n\nSVETSKONSULT, G INSULAN.\nDER, CIVILING SVR\n\nPnr 412 75\n\nGöteborg, Kallebäcksv 17 A. Tel\n031-40 6937- Bankgiro 265-4390.\nPostgiro 323355-8\n\nVerksamhet: Rådgivande i\nsvetstek-niska o angränsande frågor\nChef: Civiling Gunnar Insulander\nEtableringsår: 1966.\n\nHAGA LASTBILCENTRAL\n\nPnr 42102\n\nVästra Frölunda 2. Box 2046.\nSyn-hållsg 10. Tel 031-45 26 02,\n45 2601. Bankgiro 444-846.\nPostgiro 243888-5\n\nVerksamhet: Utför transporter o\nentreprenadarbeten\nAntal anställda: 6\nÅrsomsättning: 6 000 000\nChef: Förest Stanley Friberg\nEtableringsår: 1945.\n\nHAGA MARMOR. &amp; SKIFFER.\nFÖRÄDLING AB\n\nPnr 652 20\n\nKarlstad, Nyg 17. Tel 054-112121.\nBankgiro 438-9284. Postgiro\n36909-0\n\nVerksamhet: Utför allt i marmor\nAktiekapital: 14 000\nVerkst dir: Thore Persson\nEtableringsår: 1951.\n\nHAGA AB, METALLVARU\n-FABRIKEN\n\nPnr 330 31\n\nKull to tp, Box 22. Tel 0370-822 60,\n820 78. Bankgiro 542-5251. Postgiro\n323386-3\n\nVerksamhet: Utför\nautomatsvarv-ning\n\nAntal anstäUda: 10\nÅrsomsättning: 1500 000\nAktiekapital: 15 000\nVerkst dir: Casper Nilsson\nEtableringsår: 1946.\n\nASSMUNDSON, AB AXEL\n\nPnr 411 40\n\nGöteborg, Fabriksg 3. Tel\n031-19 71 30\n\nVerksamhet: Byggnadsmaterial i\nparti\n\nAntal anställda: 80\nÅrsomsättning: 7 000 000\nAktiekapital: 60 000\nVerkst dir: Axel Assmundson\nEtableringsår: 1938.\n\nASSOCIATED SWEDISH\nSTEELS AB (ASSAB)\n\nPnr 101 25\n\nStockholm 1, Box 413. Vasag 8.\nTel 08-24 88 30. Bankgiro 565-2235.\nPostgiro 252887-5.Tga Assabsteel.\nTelex 10476 ASSAB S\nVerksamhet: Export av stål till\nutomeuropeiska marknader\nAntal anställda: 37\nÅrsomsättning: 48 000 000\nAktiekapital: 1500 000\nVerkst dir: Sven Gustavsson\nEtableringsår: 1945.\n\nKRYLBO TRÄFORÄDLINGS AB\n\nPnr 775 00\n\nKrylbo. Tel 0226-11500. Bankgiro\n23-3521. Postgiro 163103. Tga\nTräförädlingen\n\nVerksamhet: Sågverk, hyvleri,\nträ-emballagefabrik. Säljer\nbyggnadsmaterial\n\nAntal anställda: 60\nÅrsomsättning: 10 000 000\nAktiekapital: 150 000\nEtableringsår: 1906.\n\nKONGSKILDE SVENSKA AB\n\nPnr 232 00\n\nArlöv, Pöretagsv. Box 99. Tel\n040-43 36 30. Bankgiro 711-7666.\nPostgiro 636060-6\n\nVerksamhet: Säljer maskiner o\nredskap för jordbearbetning (harvar)\no spannmålshantering\nVarunamn: Kongskilde\nAntal anställda: 8\nÅrsomsättning: 2 500 000\nAktiekapital: 300 000\nVerkst dir: Folke Skärblom\nEtableringsår: 1967\nDotterbolag till Kongskilde\nMaskinfabrik A/S, Sorö, Danmark.\n\nKONGSTAD SHIPPING\n\nPnr 451 01\n\nUddevalla 1, Box 135. Bäverbäcksg\n\n19. Tel 0522-325 73, 325 74.\nBankgiro 763-4553. Postgiro 692984-8.\nTga Kongstadship, Kongstadtank.\nTelex 42028 KONGUVD S\nVerksamhet: Skeppsmäkleri,\nbefraktning o rederi. Linjetrafik\nUdde valla/Aberdeen\nChef: Jörgen Kongstad\nEtableringsår: 1967.\n\nKONSERV.\n\nse i övrigt resp namn.\n\nKONSERV-KOMPANIET, AB\n\nPnr 611 01\n\nNyköping 1, Partihallen, Idbäcksv\n8. Box 49. Tel 0155-173 50.\nPostgiro 297252\n\nVerksamhet: Grossist med\nspecialisering inom livsmedel o\nkonfek-tyr\n\nAntal anställda: 50\nÅrsomsättning: 28000 000\nAktiekapital: 500 000\nVerkst dir: Per Nilsson\nEtableringsår: 1947.\n\nKONST- och HANTVERKS.\nPRODUKTER AB\n\nPnr 61101\n\nNyköping 1, Bagareg 35. Box 16.\nTel 0155-175 51, 149 15. Bankgiro\n827-3476. Postgiro 380616-3\nVerksamhet: Tillverkar stilspeglar\no ramar samt utför renoveringar\nAntal anställda: 8\nAktiekapital: 18 600\nVerkst dir: Lennart J G Andersson\nEtableringsår: 1947.\n\nKONST- &amp; METALL.\nGJUTERIET\n\nPnr 50245\n\nBorås, Rosendal 1. Tel 033-13 08 04.\nBankgiro 531-7516. Postgiro\n512747-7\n\nVerksamhet: Tillverkar gjutgods\nför armaturfabriker o industri.\nTillverkar o säljer konstprodukter\ni gjutgods i olika metaller\nÄgare: Bengt Vilhelmsson, Erie\nHermansson\nEtableringsår: 1947.\n\nKONST-HANTVE RK, AB\n\nPnr 523 00\n\nUlricehamn, Källg 9. Tel\n0321-109 90. Bankgiro 53-2750.\nPostgiro 96785\n\nVerksamhet: Tillverkar\nbelysningsarmatur o lampskärmar\nAntal anställda: 20\nÅrsomsättning: 1500 000\nAktiekapital: 50 000\nVerkst dir: Olof Olofsson\nEtableringsår: 1955.\n\nKONST HARTS, AB\n\nIngår i Cementakoncernen\n\nPnr 272 01\n\nSimrishamnl.Djupadalsv. Box 12.\nTel 0414-122 50. Bankgiro\n352-4758. Postgiro 281815-1.\nTga Konstharts\nVerksamhet: Formsprutning o\nsträngsprutning av kvalificerat\nindustrigods i termoplast. Egen\nverk-ty gstillverkning\nAntal anställda: 200\n\nAktiekapital: 600 000\nVerkst dir: Carl Otto Areskoug\nEtableringsår: 1934\n\nDotterbolag till AB Cementa.\n\nKONSTRUKTIONS.\nBAKELIT, AB\n\nPnr 286 02\n\nOrkelljunga, Box 2079. Tel\n0435-603 80. Bankgiro 672-6541.\nPostgiro 383000-7\n\nVerksamhet: Tillverkar tekniska\ndetaljer i härd- o termoplast\n.Antal anställda: 225\nAktiekapital: 150 000\nVerkst dir: Anders Månson\nEtableringsår: 1947.\n\nKONSTRUKTÖR, BYGGNADS\nAB\n\nPnr 80102\n\nGävle 1, Centralplan 5, Box 1. Tel\n026-129690. Bankgiro 603-5489.\nPostgiro 263488. Tga Konstruktör\nVerksamhet: Bostads- o\nindustribyggnader, vattenverksbyggnader,\nbro- o kajbyggnader,\ngrundläggningar m m samt konstruktioner\nAntal anställda: 766\nÅrsomsättning: 86 800 000\n.Aktiekapital: 300 000\nStyrelse: Civiling Gustaf Harrbäck\n(ordf), kamrer Bengt Rahm,\nciviling Bertil österlund\nVerkst dir: Civiling Bertil\nösterlund\n\nEtableringsår: 1914.\n\nBJERHAGS INDUSTRI AB\n\nPnr 576 00\n\nSävsjö, Hjärtlandav. Tel\n0382-112 35. Bankgiro 285-4081.\nPostgiro 167751-7\n\nVeiksamhet: Tillverkar soffor o\nfåtöljer\n\nAntal anställda: 46\nÅrsomsättning: 5 000 000\n.Aktiekapital: 120 000\nEtableringsår: 1947.\n\nHESELIUS AB, ERIC\n\nPnr 80104\n\nGävle, Andra Magasinsg6, Box 3 27.\nTel 026-12 0241. Bankgiro 19-3929.\nPostgiro 13900. Tga Heselius\nVerksamhet: Glas, porslin o\nres-taurantartiklar i parti i minut\nFilial: Gävle.HeseliusGlas\noPors-lin, Drottningg22. Tel026-1201 22\nAntal anställda: 20\nAktiekapital: 200 000\nVerkst dir: Disp Gunnar Heselius\nEtableringsår: 1906.\n\nHESSELS MARKNADS\nKONSULT AB\n\nPnr 700 03\n\nÖrebro 3, Hagmarksg 23. Box 3005.\nTel 019-11 96 50. Bankgiro\n35-9045. Postgiro 674487\nVerksamhet: Ekonomiska\nkonsulter, marknadskartläggning,\nmarknadsundersökningar, säljplanering\no reklam\n\nAntal anställda; 5\nÅrsomsättning: 900 000\nVerkst dir: Bert Olof Hessel\nV verkst dir: Kent Hessel\nEtableringsår: 1966.",
    "structured": {
        "1": {
            "company_name": "KORES, AB",
            "address": "Janne Gustavssons v 3, 185 00 Vaxholm",
            "phone_number": "0764-30 1 70",
            "bank_details": {
                "postgiro": "51277"
            },
            "activity": "Tillverkar karbonpapper, färgband, stenciler o dupliceringsfärg, genomskriftspapper",
            "employees": 60,
            "annual_turnover": 15000000,
            "capital": 1000000,
            "key_personnel": [
                {
                    "name": "Anders Thustrup",
                    "position": "ordf"
                },
                {
                    "name": "Maj Harting",
                    "position": ""
                },
                {
                    "name": "Urban Harting",
                    "position": "Verkst dir"
                }
            ],
            "establishment_year": 1928
        },
        "2": {
            "company_name": "KORFITSEN AGENTURFIRMA, CARL",
            "address": "Ekhagsv 2, 104 05 Stockholm",
            "phone_number": "08-15 99 20, 15 99 21",
            "bank_details": {
                "bankgiro": "16-6818",
                "postgiro": "199245-2"
            },
            "activity": "Agenturrörelse i mattor o textilvaror såsom spetsar o dylikt för konfektionsindustrin",
            "employees": 5,
            "key_personnel": [
                {
                    "name": "Torgny Korfitsen",
                    "position": "Chef"
                }
            ],
            "establishment_year": 1909
        },
        "3": {
            "company_name": "JACOBSON AB, OTTO",
            "address": "Svartmang 16, 11129 Stockholm",
            "phone_number": "08-1012 98, 202110",
            "bank_details": {
                "bankgiro": "72-1714",
                "postgiro": "50188"
            },
            "activity": "Grossist i papper o bindgarn",
            "capital": 102000,
            "key_personnel": [
                {
                    "name": "Hans Jacobson",
                    "position": "Verkst dir"
                }
            ],
            "establishment_year": 1899
        },
        "4": {
            "company_name": "JAKOBSSON HUSBYGGNADS. konstruktioner ab, roland",
            "address": "Strömparken 22, 602 24 Norrköping",
            "phone_number": "011-13 8551",
            "bank_details": {
                "bankgiro": "826-2032",
                "postgiro": "695560-3"
            },
            "activity": "Konsulterande ingenjörsbyrå",
            "annual_turnover": 125000,
            "capital": 5000,
            "key_personnel": [
                {
                    "name": "Roland Jakobsson",
                    "position": "Verkst dir"
                }
            ],
            "establishment_year": 1961
        },
        "5": {
            "company_name": "JACOBSSONS REVISIONSBYRÅ ab, rolf",
            "address": "O Hamnsg 5, 41110 Göteborg",
            "phone_number": "031-17 89 70",
            "bank_details": {
                "bankgiro": "500-1672",
                "postgiro": "45295-3"
            },
            "activity": "Revisioner, utredningar m m",
            "employees": 28,
            "annual_turnover": 1800000,
            "capital": 80000,
            "key_personnel": [
                {
                    "name": "Ake Fryklund",
                    "position": ""
                },
                {
                    "name": "Claes E Åhrén",
                    "position": ""
                },
                {
                    "name": "Lars Elvstad",
                    "position": ""
                },
                {
                    "name": "Nils Rilby",
                    "position": ""
                },
                {
                    "name": "Carl Erik Ekbom",
                    "position": ""
                },
                {
                    "name": "Stig Ekwall",
                    "position": ""
                },
                {
                    "name": "Hans Hedlund",
                    "position": ""
                }
            ],
            "establishment_year": 1939
        },
        "6": {
            "company_name": "JACOBSSON INGENJÖRSBYRÄ, sture",
            "address": "Trädgårdsg 9, 702 12 Örebro",
            "phone_number": "019-18 49 02, 18 49 08",
            "postgiro": "247506-9",
            "activity": "Projekteringar, konstruktioner, utredningar, besiktningar o kontroll",
            "employees": 3,
            "key_personnel": [
                {
                    "name": "Sture Jacobsson",
                    "position": "Chef"
                },
                {
                    "name": "Klas Hallström",
                    "position": ""
                },
                {
                    "name": "Tommy Ahlberg",
                    "position": ""
                }
            ],
            "establishment_year": 1957
        },
        "7": {
            "company_name": "CENTRUMLINJEN, REDERI AB",
            "address": "Skeppsbron 8, 211 20 Malmö",
            "phone_number": "040-745 90",
            "postgiro": "532330-8",
            "activity": "Rederirörelse",
            "employees": 85,
            "annual_turnover": 10000000,
            "capital": 196000,
            "key_personnel": [
                {
                    "name": "O Brinck",
                    "position": "Verkst dir"
                }
            ],
            "establishment_year": null
        },
        "8": {
            "company_name": "CENTRUMPROJEKTERING CEPRO AB",
            "address": "Box 34047, Wi-valliusg 2, 100 26 Stockholm 34",
            "phone_number": "08-13 1980",
            "bank_details": {
                "bankgiro": "222-0036",
                "postgiro": "604422-6"
            },
            "activity": "Konsulterande ingenjörsverksamhet inom byggsektorn. Svarar för byggledning, kostnads-o tidplanering o utför konstruktioner inom hela byggområdet",
            "employees": 30,
            "annual_turnover": 2000000,
            "capital": 5000,
            "key_personnel": [
                {
                    "name": "Tekn lic Rolf Lerfors",
                    "position": "Styrelseordf"
                },
                {
                    "name": "Rolf Lerfors",
                    "position": "Verkst dir"
                },
                {
                    "name": "Stig Nordqvist",
                    "position": "Överingenjör"
                },
                {
                    "name": "Rune Westberg",
                    "position": "Byggnadsingejör"
                }
            ],
            "establishment_year": 1967
        },
        "9": {
            "company_name": "CEOS BYGGNADSVAROR AB",
            "address": "Box 234, Nässjö",
            "phone_number": "0380-183 50",
            "bank_details": {
                "bankgiro": "452-9368",
                "postgiro": "383505-5"
            },
            "activity": "Trävaror o byggmaterial i detalj, engros o export",
            "employees": 70,
            "annual_turnover": 23000000,
            "capital": 150000,
            "key_personnel": [
                {
                    "name": "N-G Karlsson",
                    "position": "Verkst dir"
                }
            ],
            "establishment_year": 1927
        },
        "10": {
            "company_name": "SVETS & MONTAGE",
            "address": "Ramg 6, Box 39, 660 56 Skattkärr",
            "phone_number": "054-600 44, 1512 35",
            "bank_details": {
                "bankgiro": "88-1570"
            },
            "activity": "Stålkonstruktioner o järnmonteringar av alla slag. Plåtarbeten o licenssvetsning",
            "employees": 16,
            "annual_turnover": 1000000,
            "key_personnel": [
                {
                    "name": "Pabr Ingemar Olsson",
                    "position": "Chef"
                }
            ],
            "establishment_year": 1959
        },
        "11": {
            "company_name": "SVETSINDUSTRI EINAR JOHANSSON",
            "address": "Staby gård, Box 56, 581 02 Linköping 1",
            "phone_number": "013-12 86 78",
            "postgiro": "384540",
            "activity": "Tillverkar järnkonstruktioner, karosserier o stålhytter",
            "key_personnel": [
                {
                    "name": "Pabr Einar Johansson",
                    "position": "Chef"
                }
            ],
            "establishment_year": 1945
        },
        "12": {
            "company_name": "SVETSKONSULT, G INSULANDER, CIVILING SVR",
            "address": "Kallebäcksv 17 A, 412 75 Göteborg",
            "phone_number": "031-40 6937",
            "bank_details": {
                "bankgiro": "265-4390",
                "postgiro": "323355-8"
            },
            "activity": "Rådgivande i svetstekniska o angränsande frågor",
            "key_personnel": [
                {
                    "name": "Civiling Gunnar Insulander",
                    "position": "Chef"
                }
            ],
            "establishment_year": 1966
        },
        "13": {
            "company_name": "HAGA LASTBILCENTRAL",
            "address": "Box 2046, Synhållsg 10, 42102 Västra Frölunda",
            "phone_number": "031-45 26 02, 45 2601",
            "bank_details": {
                "bankgiro": "444-846",
                "postgiro": "243888-5"
            },
            "activity": "Utför transporter o entreprenadarbeten",
            "employees": 6,
            "annual_turnover": 6000000,
            "key_personnel": [
                {
                    "name": "Förest Stanley Friberg",
                    "position": "Chef"
                }
            ],
            "establishment_year": 1945
        },
        "14": {
            "company_name": "HAGA MARMOR. & SKIFFER. FÖRÄDLING AB",
            "address": "Nyg 17, 652 20 Karlstad",
            "phone_number": "054-112121",
            "bank_details": {
                "bankgiro": "438-9284",
                "postgiro": "36909-0"
            },
            "activity": "Utför allt i marmor",
            "capital": 14000,
            "key_personnel": [
                {
                    "name": "Thore Persson",
                    "position": "Verkst dir"
                }
            ],
            "establishment_year": 1951
        },
        "15": {
            "company_name": "HAGA AB, METALLVARUFABRIKEN",
            "address": "Box 22, Kull to tp",
            "phone_number": "0370-822 60, 820 78",
            "bank_details": {
                "bankgiro": "542-5251",
                "postgiro": "323386-3"
            },
            "activity": "Utför automatsvarvning",
            "employees": 10,
            "annual_turnover": 1500000,
            "capital": 15000,
            "key_personnel": [
                {
                    "name": "Casper Nilsson",
                    "position": "Verkst dir"
                }
            ],
            "establishment_year": 1946
        },
        "16": {
            "company_name": "ASSMUNDSON, AB AXEL",
            "address": "Fabriksg 3, 411 40 Göteborg",
            "phone_number": "031-19 71 30",
            "activity": "Byggnadsmaterial i parti",
            "employees": 80,
            "annual_turnover": 7000000,
            "capital": 60000,
            "key_personnel": [
                {
                    "name": "Axel Assmundson",
                    "position": "Verkst dir"
                }
            ],
            "establishment_year": 1938
        },
        "17": {
            "company_name": "ASSOCIATED SWEDISH STEELS AB (ASSAB)",
            "address": "Box 4 13, Vasag 8, 101 25 Stockholm 1",
            "phone_number": "08-24 88 30",
            "bank_details": {
                "bankgiro": "565-2235",
                "postgiro": "252887-5"
            },
            "activity": "Export av stål till utomeuropeiska marknader",
            "employees": 37,
            "annual_turnover": 48000000,
            "capital": 1500000,
            "key_personnel": [
                {
                    "name": "Sven Gustavsson",
                    "position": "Verkst dir"
                }
            ],
            "establishment_year": 1945
        },
        "18": {
            "company_name": "KRYLBO TRÄFORÄDLINGS AB",
            "address": "Box 34047, Wi-valliusg 2, 100 26 Stockholm 34",
            "phone_number": "08-13 1980",
            "bank_details": {
                "bankgiro": "222-0036",
                "postgiro": "604422-6"
            },
            "activity": "Konsulterande ingenjörsverksamhet inom byggsektorn. Svarar för byggledning, kostnads-o tidplanering o utför konstruktioner inom hela byggområdet",
            "employees": 30,
            "annual_turnover": 2000000,
            "capital": 5000,
            "key_personnel": [
                {
                    "name": "Tekn lic Rolf Lerfors",
                    "position": "Styrelseordf"
                },
                {
                    "name": "Rolf Lerfors",
                    "position": "Verkst dir"
                },
                {
                    "name": "Stig Nordqvist",
                    "position": "Överingenjör"
                },
                {
                    "name": "Rune Westberg",
                    "position": "Byggnadsingejör"
                }
            ],
            "establishment_year": 1967
        },
        "19": {
            "company_name": "CEOS BYGGNADSVAROR AB",
            "address": "Box 234, Nässjö",
            "phone_number": "0380-183 50",
            "bank_details": {
                "bankgiro": "452-9368",
                "postgiro": "383505-5"
            },
            "activity": "Trävaror o byggmaterial i detalj, engros o export",
            "employees": 70,
            "annual_turnover": 23000000,
            "capital": 150000,
            "key_personnel": [
                {
                    "name": "N-G Karlsson",
                    "position": "Verkst dir"
                }
            ],
            "establishment_year": 1927
        },
        "20": {
            "company_name": "SVETS & MONTAGE",
            "address": "Ramg 6, Box 39, 660 56 Skattkärr",
            "phone_number": "054-600 44, 1512 35",
            "bank_details": {
                "bankgiro": "88-1570"
            },
            "activity": "Stålkonstruktioner o järnmonteringar av alla slag. Plåtarbeten o licenssvetsning",
            "employees": 16,
            "annual_turnover": 1000000,
            "key_personnel": [
                {
                    "name": "Pabr Ingemar Olsson",
                    "position": "Chef"
                }
            ],
            "establishment_year": 1959
        }
    }
}