{
    "original": "BJDRKANDER &amp; SON, AB C J\n\nPnr 62101\n\nVisby 1, Box 86. Sankt Hansg 16.\nTel 0498-126 00. Bankgiro 833-3049.\nPostgiro 189000-3. Tga Björkanders\nVerksamhet: Säljer spannmål,\nfodervaror, gödningsämnen\nAntal anställda: 19\nÅrsomsättning: 21500000\nAktiekapital: 300 000\nVerkst dir: Ivar Björkander\nEtableringsår: 1874.\n\nHAMMARBERG, FIRMA OLOF\n\nPnr 421 71\n\nVästra Frölunda, Illerg 2. Tel 031-\n\n291260, 1438 38. Bankgiro\n51-2733. Postgiro 44554^4\nVerksamhet: Tillverkar kyrkorglar\näven export\nAntal anställda: 18\nÅrsomsättning: 1500000\nChef: Nils Olof Hammarberg\nEtableringsår: 1847.\n\nSJÖGREN AB, YNGVE\n\nPnr 430 60\n\nLandvetter, Box 10. Tel\n031-7113 90, 71 13 91. Bankgiro\n364-8649. Postgiro 41363-3. Tga\nYess-chemie\n\nVerksamhet: Offsetkemikalier.\nMaskiner för grafisk industri.\nInredningar för reproduktion. Tryckfärg\nVaninamn: YS\nAntal anställda: 7\nAktiekapital: 15 000\nVerkst dir: Civiling Yngve Sjögren\nEtableringsår 1915.\n\nCARAL AB\n\nPnr 182 11\n\nDanderyd 1, Klubbv 5. Box 68.\nTel 08-755 26 75. Postgiro 511600-9.\nTga Chemcaral, Stockholm.\nTelex 10056 RYDCARL S\nVerksamhet: Säljer anläggningar,\nmaskiner o råvaror för kemiska\nindustrin\n\nAktiekapital: 5 000\n\nVerkst dir: Karl Axel Rydqvist\n\nEtableringsår: 1960.\n\nCARAVANS\nINTERNATIONAL AB\n\nPnr 250 04\n\nHelsingborg 4, Box 4017.\nDann-feltsg 12. Tel 0 4 2-970 40. Postgiro\n84920-8. Telex 72426 LM Cl S\nVerksamhet: Generalagent för Cl\nhusvagnar, OBI tält\nVarunamn: Eccles, Europa, OBI,\nSprite, Wilk\nAktiekapital: 100 000\nVerkst dir: Jörgen Christiansen\nEtableringsår: 1955.\n\nCARDELLS BLECK- &amp;\nPLÅTSLAGERI AB\n\nPnr 552 42\n\nJönköping, Stenhuggarg 17. Tel\n036-11 15 58,12 68 69. Bankgiro\n544-9160. Postgiro 328738-0\nVerksamhet: Tillverkar\nventilations- o spånanläggningar\nAntal anställda: 25\nÅrsomsättning: 2 000 000\nAktiekapital: 15 000\nVerkst dir: Berndt Cardell\nEtableringsår: 1921.\n\nMODIN, JÄRN AB BRÖDERNA\n\nPnr 74100\n\nKnivsta, Box 17. Apoteksv 7 A.\nTel 018-38 05 90. Bankgiro\n233-4027. Postgiro 26199-0\nVerksamhet: Järn- o maskinaffär\nÄgare: Dir Bertil Modin\nEtableringsår: 1909.\n\nr MODIN &amp; CO PLÄT.\nINDUSTRI AB\n\nPnr 68100\n\nKristinehamn, Kungsg 37.\nTel0550-108 71. Postgiro 15355-1\nVerksamhet: Utför\nexcenterpress-ning, kantpressning o svetsning\nAntal anstäUda: 6\nÅrsomsättning: 400 000\nAktiekapital: 50 000\nVerkst dir: Fabr Ewert Modin\nEtableringsår: 1914.\n\nSCANIA.UNION AB\n\nPnr 560 41\n\nMuUsjö, Box 22. Tel 0392-106 50.\nTga Scua\n\nVerksamhet: Tillverkar apparater\nför rökgaskontroll: C02-mätare,\ndragmätare, sotmätare, oljefilter o\nventilkedjor, oljenivåmätare\nEnsamförsäljare C02-mätare,\ndragmätare, sotmätare, flamspeglar:\nAB Odest Ingenjörsfirma. Tågag 63,\nHelsingborg. Tel 042-13 22 50\nVarunamn: Scua\nVerkst dir: Sture T Rimbäck\nEtableringsår 1956.\n\nMOTALA STRÖMS KRAFT AB\n\nPnr 59100\n\nMotala, Poppelg 3. Tel\n0141-163 30. Postgiro 71217. Tga Krafts\nbolaget\n\nFilialer: Askersund. Tel\n0583-100 87\n\nBorensberg. Tel 0141-400 32\nBorensbergs Kraftstation. Tel\n0141-400 26\n\nVadstena. Tel 0143-10106\nOdeshög. Tel 0144-10113\nAntal anställda: 126\nÅrsomsättning: 24185 000\nAktiekapital: 2 347 000\nStyrelse: Driftdir Sven Lalander\n(ordf), bostadschef Thore\nPettersson, kraftverksdir Erland Kaijser,\nkraftverksdir Karl Lundholm,\nagronom Christer Orrenius, ekonomidir\nSven Ekdahl\n\nVerkst dir. Nils G Samzelius\nEtableringsån 1903.\n\nMOTALA STRÖMS SNICKERI.\nFABRIK\n\nPnr 59100\n\nMotala, Verkstadsv 25 A. Tel\n\n0141-11754, 11412. Bankgiro\n82-1944. Postgiro 297118\nVerksamhet: Tillverkar\nbyggnads-snickerier, fönster o dörrar\nAntal anställda: 30\nÅrsomsättning: 2500 000\nVerkst din Herman Andersson\nEtableringsår: 1945.\n\nSLUURS MASKINER, AB\n\nPnr 102 26\n\nStockholm 12, Box 12240. Sankt\nGöransg 160 A. Tel 08-1315 00.\nBankgiro 330-0191. Postgiro\n1850-7. Tga Maskinslöör.\nTelex 1460\n\nVerksamhet: Lantbruksmaskiner\nAntal anställda: 32\nÅrsomsättning: 226 000 000\nAktiekapital: 4 000 000\nVerkst dir: Paul Hökfelt\nEtableringsår: 1926.\n\nARLINO BYGGNADSVAROR AB\n\nPnr 17124\n\nSolna 1, Box 1268. Tel 08-83 06 35.\nBankgiro 80-8626. Postgiro\n559528-5\n\nVerksamhet:\nEntreprenadverksamhet enbart inom golv\nAntal anställda: 40\nÅrsomsättning: 5 000 000\nAktiekapital: 15 000\nVerkst dir: Lars Rundqvist\nEtableringsår: 1960.\n\nMEK\n\nMEKANIA.VERKEN, AB\n\nPnr 560 41\n\nMullsjö, Box 48. Tel 0392-103 07.\nBankgiro 549-1733. Postgiro\n294582-2\n\nVerksamhet: Tillverkar biltillbehör\nsåsom vindrutespolare,\nskyddsgal-ler för strålkastare, ventilatorer m m\nsamt projektordukar\nAntal anställda: 44\nÅrsomsättning: 4 000 000\nAktiekapital: 75 000\nVerkst dir: Fabr Göte Friberg\nEtableringsår: 1946\nOmbildat till aktiebolag 1968.\n\nMEKANIK I KARLSTAD AB,\nVERKSTADEN\n\nPnr 651 02\n\nKarlstad 1, Box 41. Lantvärnsg 11.\nTel 054-15 65 65. Bankgiro 43-8976.\nPostgiro 399481\n\nVerksamhet: Se Karlstads\nMotorrenoverings AB KAMAB\nAktiekapital: 50 000\nVerkst dir: Sven Blomgren.\n\nMEKANIK INGENJURSFIRMA\n\nPnr 11139\n\nStockholm, Regeringsg 85. Tel\n08-1198 20, 1100 98. Bankgiro\n726-9251. Postgiro 150105. Tga\nMekanik. Telex 1542\nVerksamhet: Säljer\nverktygsmaskiner o verktyg\n\nVarunamn: Acme-Gridley, Chicago\nPneumatic (CP), Karl Hilller GmbH,\nSheffield Corp, H W Ward &amp; Co\nVerkst dir: Civiling G Lundgren\nEtableringsår: 1936.",
    "structured": {
        "1": {
            "company_name": "BJDRKANDER & SON, AB C J",
            "pnr": "62101",
            "address": "Visby 1, Box 86. Sankt Hansg 16.",
            "phone_number": "0498-126 00",
            "bank_details": {
                "bankgiro": "833-3049",
                "postgiro": "189000-3"
            },
            "activity": "Säljer spannmål, fodervaror, gödningsämnen",
            "employees": 19,
            "annual_turnover": 21500000,
            "capital": 300000,
            "key_personnel": [
                {
                    "name": "Ivar Björkander",
                    "position": "Verkst dir"
                }
            ],
            "establishment_year": 1874
        },
        "2": {
            "company_name": "HAMMARBERG, FIRMA OLOF",
            "pnr": "421 71",
            "address": "Västra Frölunda, Illerg 2",
            "phone_number": "031-291260, 1438 38",
            "bank_details": {
                "bankgiro": "51-2733",
                "postgiro": "44554^4"
            },
            "activity": "Tillverkar kyrkorglar även export",
            "employees": 18,
            "annual_turnover": 1500000,
            "key_personnel": [
                {
                    "name": "Nils Olof Hammarberg",
                    "position": "Chef"
                }
            ],
            "establishment_year": 1847
        },
        "3": {
            "company_name": "SJÖGREN AB, YNGVE",
            "pnr": "430 60",
            "address": "Landvetter, Box 10",
            "phone_number": "031-7113 90, 71 13 91",
            "bank_details": {
                "bankgiro": "364-8649",
                "postgiro": "41363-3"
            },
            "activity": "Offsetkemikalier. Maskiner för grafisk industri.",
            "employees": 7,
            "capital": 15000,
            "key_personnel": [
                {
                    "name": "Civiling Yngve Sjögren",
                    "position": "Verkst dir"
                }
            ],
            "establishment_year": 1915
        },
        "4": {
            "company_name": "CARAL AB",
            "pnr": "182 11",
            "address": "Danderyd 1, Klubbv 5. Box 68",
            "phone_number": "08-755 26 75",
            "postgiro": "511600-9",
            "activity": "Säljer anläggningar, maskiner o råvaror för kemiska industrin",
            "capital": 5000,
            "key_personnel": [
                {
                    "name": "Karl Axel Rydqvist",
                    "position": "Verkst dir"
                }
            ],
            "establishment_year": 1960
        },
        "5": {
            "company_name": "CARAVANS INTERNATIONAL AB",
            "pnr": "250 04",
            "address": "Helsingborg 4, Box 4017. Dann-feltsg 12",
            "phone_number": "0 4 2-970 40",
            "postgiro": "84920-8",
            "activity": "Generalagent för Cl husvagnar, OBI tält",
            "capital": 100000,
            "key_personnel": [
                {
                    "name": "Jörgen Christiansen",
                    "position": "Verkst dir"
                }
            ],
            "establishment_year": 1955
        },
        "6": {
            "company_name": "CARDELLS BLECK- & PLÅTSLAGERI AB",
            "pnr": "552 42",
            "address": "Jönköping, Stenhuggarg 17",
            "phone_number": "036-11 15 58,12 68 69",
            "bank_details": {
                "bankgiro": "544-9160",
                "postgiro": "328738-0"
            },
            "activity": "Tillverkar ventilations- o spånanläggningar",
            "employees": 25,
            "annual_turnover": 2000000,
            "capital": 15000,
            "key_personnel": [
                {
                    "name": "Berndt Cardell",
                    "position": "Verkst dir"
                }
            ],
            "establishment_year": 1921
        },
        "7": {
            "company_name": "MODIN, JÄRN AB BRÖDERNA",
            "pnr": "74100",
            "address": "Knivsta, Box 17. Apoteksv 7 A",
            "phone_number": "018-38 05 90",
            "bank_details": {
                "bankgiro": "233-4027",
                "postgiro": "26199-0"
            },
            "activity": "Järn- o maskinaffär",
            "key_personnel": [
                {
                    "name": "Dir Bertil Modin",
                    "position": "Ägare"
                }
            ],
            "establishment_year": 1909
        },
        "8": {
            "company_name": "MODIN & CO PLÄT. INDUSTRI AB",
            "pnr": "68100",
            "address": "Kristinehamn, Kungsg 37",
            "phone_number": "0550-108 71",
            "postgiro": "15355-1",
            "activity": "Utför excenterpress-ning, kantpressning o svetsning",
            "employees": 6,
            "annual_turnover": 400000,
            "capital": 50000,
            "key_personnel": [
                {
                    "name": "Fabr Ewert Modin",
                    "position": "Verkst dir"
                }
            ],
            "establishment_year": 1914
        },
        "9": {
            "company_name": "SCANIA.UNION AB",
            "pnr": "560 41",
            "address": "MuUsjö, Box 22",
            "phone_number": "0392-106 50",
            "activity": "Tillverkar apparater för rökgaskontroll: C02-mätare, dragmätare, sotmätare, oljefilter o ventilkedjor, oljenivåmätare",
            "sole_distributor": "C02-mätare, dragmätare, sotmätare, flamspeglar: AB Odest Ingenjörsfirma. Tågag 63, Helsingborg. Tel 042-13 22 50",
            "varunamn": "Scua",
            "key_personnel": [
                {
                    "name": "Sture T Rimbäck",
                    "position": "Verkst dir"
                }
            ],
            "establishment_year": 1956
        },
        "10": {
            "company_name": "MOTALA STRÖMS KRAFT AB",
            "pnr": "59100",
            "address": "Motala, Poppelg 3",
            "phone_number": "0141-163 30",
            "postgiro": "71217",
            "filialer": "Askersund. Tel 0583-100 87, Borensberg. Tel 0141-400 32, Borensbergs Kraftstation. Tel 0141-400 26, Vadstena. Tel 0143-10106, Odeshög. Tel 0144-10113",
            "employees": 126,
            "annual_turnover": 24185000,
            "capital": 2347000,
            "styrelse": "Driftdir Sven Lalander (ordf), bostadschef Thore Pettersson, kraftverksdir Erland Kaijser, kraftverksdir Karl Lundholm, agronom Christer Orrenius, ekonomidir Sven Ekdahl",
            "key_personnel": {
                "Nils G Samzelius": "Verkst dir"
            },
            "establishment_year": 1903
        },
        "11": {
            "company_name": "MOTALA STRÖMS SNICKERI. FABRIK",
            "pnr": "59100",
            "address": "Motala, Verkstadsv 25 A",
            "phone_number": "0141-11754, 11412",
            "bankgiro": "82-1944",
            "postgiro": "297118",
            "activity": "Tillverkar byggnads-snickerier, fönster o dörrar",
            "employees": 30,
            "annual_turnover": 2500000,
            "key_personnel": [
                {
                    "name": "Herman Andersson",
                    "position": "Verkst din"
                }
            ],
            "establishment_year": 1945
        },
        "12": {
            "company_name": "SLUURS MASKINER, AB",
            "pnr": "102 26",
            "address": "Stockholm 12, Box 12240. Sankt Göransg 160 A",
            "phone_number": "08-1315 00",
            "bank_details": {
                "bankgiro": "330-0191",
                "postgiro": "1850-7"
            },
            "activity": "Lantbruksmaskiner",
            "employees": 32,
            "annual_turnover": 226000000,
            "capital": 4000000,
            "key_personnel": [
                {
                    "name": "Paul Hökfelt",
                    "position": "Verkst dir"
                }
            ],
            "establishment_year": 1926
        },
        "13": {
            "company_name": "ARLINO BYGGNADSVAROR AB",
            "pnr": "17124",
            "address": "Solna 1, Box 1268",
            "phone_number": "08-83 06 35",
            "bankgiro": "80-8626",
            "postgiro": "559528-5",
            "activity": "Entreprenadverksamhet enbart inom golv",
            "employees": 40,
            "annual_turnover": 5000000,
            "capital": 15000,
            "key_personnel": [
                {
                    "name": "Lars Rundqvist",
                    "position": "Verkst dir"
                }
            ],
            "establishment_year": 1960
        },
        "14": {
            "company_name": "MEKANIA.VERKEN, AB",
            "pnr": "560 41",
            "address": "Mullsjö, Box 48",
            "phone_number": "0392-103 07",
            "bankgiro": "549-1733",
            "postgiro": "294582-2",
            "activity": "Tillverkar biltillbehör såsom vindrutespolare, skyddsgaller för strålkastare, ventilatorer m m samt projektordukar",
            "employees": 44,
            "annual_turnover": 4000000,
            "capital": 75000,
            "key_personnel": [
                {
                    "name": "Fabr Göte Friberg",
                    "position": "Verkst dir"
                }
            ],
            "establishment_year": 1946,
            "ombildat_till_aktiebolag": 1968
        },
        "15": {
            "company_name": "MEKANIK I KARLSTAD AB, VERKSTADEN",
            "pnr": "651 02",
            "address": "Karlstad 1, Box 41. Lantvärnsg 11",
            "phone_number": "054-15 65 65",
            "bankgiro": "43-8976",
            "postgiro": "399481",
            "activity": "Se Karlstads Motorrenoverings AB KAMAB",
            "capital": 50000,
            "key_personnel": [
                {
                    "name": "Sven Blomgren",
                    "position": "Verkst dir"
                }
            ]
        },
        "16": {
            "company_name": "MEKANIK INGENJURSFIRMA",
            "pnr": "11139",
            "address": "Stockholm, Regeringsg 85",
            "phone_number": "08-1198 20, 1100 98",
            "bankgiro": "726-9251",
            "postgiro": "150105",
            "activity": "Säljer verktygsmaskiner o verktyg",
            "varunamn": "Acme-Gridley, Chicago Pneumatic (CP), Karl Hilller GmbH, Sheffield Corp, H W Ward & Co",
            "key_personnel": [
                {
                    "name": "Civiling G Lundgren",
                    "position": "Verkst dir"
                }
            ],
            "establishment_year": 1936
        }
    }
}