{
    "original": "TERMO-INDUSTRIER AB\n\nPnr 63107\n\nEskilstuna 1, Västerg 13. Box 551.\nTel 016-13 71 90. Bankgiro 82-8170.\nPostgiro 14343. TgaTiab\nVerksamhet: Tillverkar o säljer\npersonbils- o lastbils garage\nAntal anställda: 125\nÅrsomsättning: 11100 000\nAktiekapital: 300000\nVerkst dir Sten Kjellberg\nPlatschef: Dir Sigge Ericsson\nEtableringsår: 1937.\n\nTERMO.KYL AB, INGEN.\nJORSFIRMAN\n\nPnr 252 47\n\nHelsingborg. Torekovsg 7. Tel\n042-12 05 30. Bankgiro 340-4811.\nPostgiro 473506-4\nVerksamhet: Säljer allt inom\nkyl-branschen samt ger service pà\nkylanläggningar\n\nFilial: Ängelholm, Järnvägsg. Tel\n\n0431-130 30\n\nAntal anställda: 16\n\nÅrsomsättning: 2 000 000\n\nAktiekapital: 30 000\n\nDirr: Ing S Lange, fabr B Nilsson\n\nEtableringsår: 1954.\n\nKONTEK-SYSTEM AB\n\nPnr 16111\n\nBromma 11, Box 11061. Albyg 123,\nSundbyberg. Tel 08-9806 60.\nBankgiro 211-1193. Postgiro 57123-2\n\nVerksamhet; Säljer Kontek\nlönesystem omfattande apparater,\nblanketter o diverse tillbehör samt\nbrevkorgar, korg- o väggställ,\nplaneringstavlor, stämplar, pennor o\nkravbrev. Eget tryckeri\nVarunamn: Kontek\nAntal anställda: 60\nÅrsomsättning: 5 000 000\nAktiekapital: 200 000\nVerkst din Hans Brenning\nMarknadschef: Stig Almgren\nEtableringsår. 1934.\n\nKONTORS. &amp; SPECIAL.\nMASKINER\n\nPnr 83101\n\nÖstersund 1, Prästg 64. Box 196.\nTel 063-11243\n\nVerksamhet: Bagerimaskiner o\nbakugnar\n\nÄgare o chef: Allan östlund.\n\nKONTORS. CENTER\nMATTS &amp; CO AB\n\nPnr 104 35-\n\nStockholm 23, Box 23060. Hagag 29.\nTel 08-24 72 00. Bankgiro 16-1151.\nPostgiro 700290-0. Tga\nService-office. Telex 10625 SERVO S\nVerksamhet: Uthyr inredda kontor\nmed service\nAntal anställda: 7\nÅrsomsättning: 500 000\n.Aktiekapital: 5 000\nVerkst dir: A G Matts\nEtableringsår: 1963.\n\nBELLANDERSAB, J F\n\nPnr 800 06\n\nGävle 6, Box 6103. Textilg 3. Tel\n026-1290 10. Bankgiro 783-7438.\nPostgiro 5107-8. Tga\nBellander-bolag. Telex 81038\nVerksamhet: Tillverkar arbets- o\nfritidskläder\nAntal anställda: 19\nÅrsomsättning: 8 000 000\nAktiekapital: 300 000\nVerkst dir: Törd Bellander\nEtableringsår: 1891.\n\nTRÄDGÅRDSMOBLER, AB\n\nPnr 283 00\n\nOsby, Klöverv. Box 32. Tel\n0479-118 70. Bankgiro 281-6668. Postr\ngiro 348473-0. Tga Atö\nVerksamhet: Tillverkar o säljer\nsommarmöbler\nAntal anställda: 50\nÅrsomsättning: 10 000 000\nAktiekapital: 100 000\nVerkst din Lars E Steneloo\nEtableringsår: 1948.\n\nLA REINE AB\n\nPnr 24100\n\nEslöv, Trehäradsv 13. Tel\n0413-132 45. Bankgiro 866-0086.\nPostgiro 97683-6\n\nVerksamhet: Tillverkar nylonrockar\nför damer o herrar till alla\nbranscher\n\nAktiekapital: 135 000\nVerkst dir: Erik Wedberg\nEtableringsår: 1936.\n\nBROMAN, GÖSTA\n\nPnr 11145\n\nStockholm, Birger Jarlsg 37. Tel\n08-1160 53. Postgiro 58151. Tga\nGebro\n\nVerksamhet: Maskiner för kemisk\nindustri\n\nÄgare o chef: Gösta Broman\nEtableringsår: 1927.\n\nflens grus- &amp; betong ab\n\nPnr 642 00\n\nFlen, Torp. Tel 0157-128 50,\n128 51. Bankgiro 173-2759.\nPostgiro 591049-2\n\nVerksamhet: Tillverkar o säljer\nfabriksbetong, grus- o\nkrossprodukter. Krossentreprenader\nAntal anställda: 18\nÅrsomsättning: 2 400000\nAktiekapital: 50 000\nVerkst din Tom Barckman\nDriftschef: Disp Ulf Lodhammar\nEtableringsår: 1961.\n\nMEULLER AB,HELGE\n\nPnr 11130\n\nStockholm, Bredgränd 2. Tel\n08-247255. Bankgiro 161-2548.\nPostgiro 706370-4. Telex 17319\nVeiksamhet: Agenturförsäljning\nVarunamn: Metalastik\nAntal anställda: 6\nVerkst dir: Karl Helge Meuller\nEtableringsår: 1964.\n\nSÖDERSTRÖM, AB HJALMAR\n\nPnr 111 31\n\nStockholm, V Trädgårdsg 11 B.\nTel 08-11 25 73. Bankgiro\n160-1756. Postgiro 50354. Tga\nHjal-marius\n\nVerksamhet: Agentur, import o\n\nengrosaffär\n\nAktiekapital: 5 000\n\nVerkst dir: Bertil Söderström\n\nEtableringsår 1891.\n\nSÖDERSTRÖM AB,\nINGEN-JORSFIRMA STEN\n\nPnr 191 21\n\nSollentuna 1, Box 103. Poppelv\n24 F. Tel 08-35 25 00. Bankgiro\n390-0672. Postgiro 92136-1. Tga\nStanheater\n\nVerksamhet: Konstruerar o säljer\negna patenterade värmetekniska\nutrustningar, speciellt värmeväxlare\nför olja, gaser o förångare\nVarunamn: Stanex\nAntal anställda: 8\nAktiekapital: 50 000\nStyrelse: Ing Sten Söderström\n(ordf), fru IngarLisa Söderström,\nkamrer Stig Söderström\nVerkst dir: Ing Sten Söderström\nEtableringsår: 1955\nOmbildat till aktiebolag 1958.\n\nSODER.TRYCK AB\n\nPnr 125 21\n\nÄlvsjö 1, Box 39. Älvsjö v 100.\nTel 08-86 20 00, 86 84 00\nVerksamhet: Allt i boktryck\nAktiekapital: 75000\nÄgare o chefer: Elias Billing,\nHenry Billing\nEtableringsår: 1960.\n\nATLAS COPCO AB\n\nPnr 105 23 Sthlm\n\nNacka. Stockholm. Tel 08-24 30 00.\nBankgiro 160-6789. Postgiro 1526-3.\nTelex 19940 COPAB S\n\nVerksamhet Att leda o samordna\nmarknadsföringen av koncernens\nprodukter, leda den tekniska\nut-vecklingen samt finansiera o\nadministrera koncernen i sin helhet\nAktiekapital: 114 975 000\nStyrelse: Tekn dr Marcus\nWallenberg (ordf). envoyé Kurt-Allan\nBelfrage, bankdir Henry N\nSporborg, bankdir Marc Wallenberg Jr,\nprof Jan Hellner, dir Sture Ekefalk,\ndir Sture Odner, dir Erik Johnsson\n(suppl), dir Peter Wallenberg (suppl)\nVerkst dir: Erik Johnsson\nV verkst dir: Peter Wallenberg\nInköpsdir: Lennart Friberg\nEtableringsår: 1873\nNuvarande firmanamn 1956.\nSe vidare produktbolag:\nAtlas Copco MCT AB, Stockholm,\nAtlas Copco Tools AB, Stockholm.\nBeträffande den svenska\nförsäljningen se Atlas Copco Svenska\nFörsäljnings AB.\n\nATLAS COPCO MCT AB\n\nPnr 102 60 Sthlm 4\nNacka. Fack, Stockholm 4. Tel\n08-24 30 00. Bankgiro 161-1045.\nPostgiro 701574-6. Tga Copcoemcete.\nTelex 173 20 COPMCT S\nVerksamhet: Utvecklar, tillverkar\no marknadsför produkter för gruv- o\nentreprenörindustrin, t ex\nbergborrmaskiner, utrustningar för\nmekaniserad bergborrning o\nfullortsborr-ning, lastmaskiner, borrvagnar,\nmaskiner o utrustning för diamants\nborrning m m\nTillverkningsenheter:\nSicklaverken, Nacka\nAvosverken, Örebro\nAntal anställda: 2800\nAktiekapital: 30 000 000\nStyrelse: Tekn dr Marcus\nWallenberg (ordf), envoyé Kurt-Allan\nBelfrage, bankdir Henry N\nSporborg, bankdir Marc Wallenberg Jr,\nprof Jan Hellner, dir Sture Odner,\ndir Erik Johnsson, dir Sture\nEke-falk, dir Bo Gyllenberg, dir Bengt\nAndersson (suppl), dir Peter\nWallenberg (suppl)\nVerkst dir: Bo Gyllenberg\nEtableringsår: 1968\nDotterbolag till Atlas Copco AB,\nStockholm.\n\nATLAS COPCO SVENSKA\nFÖRSÄLJNINGS AB\n\nPnr 131 01\n\nNacka 1, Fack. Tel 08-24 25 40,\nBankgiro 160-6144. Postgiro\n255 265-1. Telex 1825 COPSNAC S\nVerksamhet: Säljer på den svenska\nmarknaden Atlas Copco produkter\n.Intal anställda: 620\nAktiekapital: 10 000000\nVerkst dir: Einar Liwendahl\nEtableringsår: 1945.",
    "structured": {
        "1": {
            "company_name": "TERMO-INDUSTRIER AB",
            "pnr": "63107",
            "address": "Eskilstuna 1, Västerg 13. Box 551.",
            "phone_number": "016-13 71 90",
            "bank_details": {
                "bankgiro": "82-8170",
                "postgiro": "14343"
            },
            "activity": "Tillverkar o säljer personbils- o lastbils garage",
            "employees": 125,
            "annual_turnover": 11100000,
            "capital": 300000,
            "key_personnel": [
                {
                    "name": "Sten Kjellberg"
                },
                {
                    "name": "Sigge Ericsson"
                }
            ],
            "establishment_year": 1937
        },
        "2": {
            "company_name": "TERMO.KYL AB, INGEN. JORSFIRMAN",
            "pnr": "252 47",
            "address": "Helsingborg. Torekovsg 7.",
            "phone_number": "042-12 05 30",
            "bank_details": {
                "bankgiro": "340-4811",
                "postgiro": "473506-4"
            },
            "activity": "Säljer allt inom kyl-branschen samt ger service pà kylanläggningar",
            "employees": 16,
            "annual_turnover": 2000000,
            "capital": 30000,
            "key_personnel": [
                {
                    "name": "Ing S Lange"
                },
                {
                    "name": "fabr B Nilsson"
                }
            ],
            "establishment_year": 1954
        },
        "3": {
            "company_name": "KONTEK-SYSTEM AB",
            "pnr": "16111",
            "address": "Bromma 11, Box 11061. Albyg 123, Sundbyberg.",
            "phone_number": "08-9806 60",
            "bank_details": {
                "bankgiro": "211-1193",
                "postgiro": "57123-2"
            },
            "activity": "Säljer Kontek lönesystem omfattande apparater, blanketter o diverse tillbehör samt brevkorgar, korg- o väggställ, planeringstavlor, stämplar, pennor o kravbrev. Eget tryckeri",
            "employees": 60,
            "annual_turnover": 5000000,
            "capital": 200000,
            "key_personnel": [
                {
                    "name": "Hans Brenning"
                },
                {
                    "name": "Stig Almgren"
                }
            ],
            "establishment_year": 1934
        },
        "4": {
            "company_name": "KONTORS. CENTER MATTS & CO AB",
            "pnr": "104 35-",
            "address": "Stockholm 23, Box 23060. Hagag 29.",
            "phone_number": "08-24 72 00",
            "bank_details": {
                "bankgiro": "16-1151",
                "postgiro": "700290-0"
            },
            "activity": "Uthyr inredda kontor med service",
            "employees": 7,
            "annual_turnover": 500000,
            "capital": 5000,
            "key_personnel": [
                {
                    "name": "A G Matts"
                }
            ],
            "establishment_year": 1963
        },
        "5": {
            "company_name": "BELLANDERSAB, J F",
            "pnr": "800 06",
            "address": "Gävle 6, Box 6103. Textilg 3.",
            "phone_number": "026-1290 10",
            "bank_details": {
                "bankgiro": "783-7438",
                "postgiro": "5107-8"
            },
            "activity": "Tillverkar arbets- o fritidskläder",
            "employees": 19,
            "annual_turnover": 8000000,
            "capital": 300000,
            "key_personnel": [
                {
                    "name": "Törd Bellander"
                }
            ],
            "establishment_year": 1891
        },
        "6": {
            "company_name": "TRÄDGÅRDSMOBLER, AB",
            "pnr": "283 00",
            "address": "Osby, Klöverv. Box 32.",
            "phone_number": "0479-118 70",
            "bank_details": {
                "bankgiro": "281-6668",
                "postgiro": "348473-0"
            },
            "activity": "Tillverkar o säljer sommarmöbler",
            "employees": 50,
            "annual_turnover": 10000000,
            "capital": 100000,
            "key_personnel": [
                {
                    "name": "Lars E Steneloo"
                }
            ],
            "establishment_year": 1948
        },
        "7": {
            "company_name": "LA REINE AB",
            "pnr": "24100",
            "address": "Eslöv, Trehäradsv 13.",
            "phone_number": "0413-132 45",
            "bank_details": {
                "bankgiro": "866-0086",
                "postgiro": "97683-6"
            },
            "activity": "Tillverkar nylonrockar för damer o herrar till alla branscher",
            "capital": 135000,
            "key_personnel": [
                {
                    "name": "Erik Wedberg"
                }
            ],
            "establishment_year": 1936
        },
        "8": {
            "company_name": "BROMAN, GÖSTA",
            "pnr": "11145",
            "address": "Stockholm, Birger Jarlsg 37.",
            "phone_number": "08-1160 53",
            "postgiro": "58151",
            "activity": "Maskiner för kemisk industri",
            "key_personnel": [
                {
                    "name": "Gösta Broman"
                }
            ],
            "establishment_year": 1927
        },
        "9": {
            "company_name": "flens grus- & betong ab",
            "pnr": "642 00",
            "address": "Flen, Torp",
            "phone_number": "0157-128 50",
            "bank_details": {
                "bankgiro": "173-2759",
                "postgiro": "591049-2"
            },
            "activity": "Tillverkar o säljer fabriksbetong, grus- o krossprodukter. Krossentreprenader",
            "employees": 18,
            "annual_turnover": 2400000,
            "capital": 50000,
            "key_personnel": [
                {
                    "name": "Tom Barckman"
                },
                {
                    "name": "Ulf Lodhammar"
                }
            ],
            "establishment_year": 1961
        },
        "10": {
            "company_name": "MEULLER AB,HELGE",
            "pnr": "11130",
            "address": "Stockholm, Bredgränd 2",
            "phone_number": "08-247255",
            "bank_details": {
                "bankgiro": "161-2548",
                "postgiro": "706370-4"
            },
            "activity": "Agenturförsäljning",
            "employees": 6,
            "key_personnel": [
                {
                    "name": "Helge Meuller"
                }
            ],
            "establishment_year": 1964
        },
        "11": {
            "company_name": "SÖDERSTRÖM, AB HJALMAR",
            "pnr": "111 31",
            "address": "Stockholm, V Trädgårdsg 11 B",
            "phone_number": "08-11 25 73",
            "bank_details": {
                "bankgiro": "160-1756",
                "postgiro": "50354"
            },
            "activity": "Agentur, import o engrosaffär",
            "capital": 5000,
            "key_personnel": [
                {
                    "name": "Bertil Söderström"
                }
            ],
            "establishment_year": 1891
        },
        "12": {
            "company_name": "SÖDERSTRÖM AB, INGEN-JORSFIRMA STEN",
            "pnr": "191 21",
            "address": "Sollentuna 1, Box 103. Poppelv 24 F",
            "phone_number": "08-35 25 00",
            "bank_details": {
                "bankgiro": "390-0672",
                "postgiro": "92136-1"
            },
            "activity": "Konstruerar o säljer egna patenterade värmetekniska utrustningar, speciellt värmeväxlare för olja, gaser o förångare",
            "employees": 8,
            "annual_turnover": 5000000,
            "capital": 50000,
            "key_personnel": [
                {
                    "name": "Ing Sten Söderström"
                },
                {
                    "name": "fru IngarLisa Söderström"
                },
                {
                    "name": "kamrer Stig Söderström"
                }
            ],
            "establishment_year": 1955
        },
        "13": {
            "company_name": "SODER.TRYCK AB",
            "pnr": "125 21",
            "address": "Älvsjö 1, Box 39. Älvsjö v 100",
            "phone_number": "08-86 20 00, 86 84 00",
            "activity": "Allt i boktryck",
            "capital": 75000,
            "key_personnel": [
                {
                    "name": "Elias Billing"
                },
                {
                    "name": "Henry Billing"
                }
            ],
            "establishment_year": 1960
        },
        "14": {
            "company_name": "ATLAS COPCO AB",
            "pnr": "105 23 Sthlm",
            "address": "Nacka. Stockholm",
            "phone_number": "08-24 30 00",
            "bank_details": {
                "bankgiro": "160-6789",
                "postgiro": "1526-3"
            },
            "activity": "Att leda o samordna marknadsföringen av koncernens produkter, leda den tekniska ut-vecklingen samt finansiera o administrera koncernen i sin helhet",
            "capital": 114975000,
            "key_personnel": [
                {
                    "name": "Tekn dr Marcus Wallenberg",
                    "position": "ordf"
                },
                {
                    "name": "envoyé Kurt-Allan Belfrage"
                },
                {
                    "name": "bankdir Henry N Sporborg"
                },
                {
                    "name": "bankdir Marc Wallenberg Jr"
                },
                {
                    "name": "prof Jan Hellner"
                },
                {
                    "name": "dir Sture Ekefalk"
                },
                {
                    "name": "dir Sture Odner"
                },
                {
                    "name": "dir Erik Johnsson",
                    "position": "suppl"
                },
                {
                    "name": "dir Peter Wallenberg",
                    "position": "suppl"
                }
            ],
            "establishment_year": 1873,
            "current_firm_name": "Atlas Copco Svenska Försäljnings AB"
        },
        "15": {
            "company_name": "ATLAS COPCO MCT AB",
            "pnr": "102 60 Sthlm 4",
            "address": "Nacka. Fack, Stockholm 4",
            "phone_number": "08-24 30 00",
            "bank_details": {
                "bankgiro": "161-1045",
                "postgiro": "701574-6"
            },
            "activity": "Utvecklar, tillverkar o marknadsför produkter för gruv- o entreprenörindustrin, t ex bergborrmaskiner, utrustningar för mekaniserad bergborrning o fullortsborr-ning, lastmaskiner, borrvagnar, maskiner o utrustning för diamants borrning m m",
            "employees": 2800,
            "capital": 30000000,
            "key_personnel": [
                {
                    "name": "Tekn dr Marcus Wallenberg",
                    "position": "ordf"
                },
                {
                    "name": "envoyé Kurt-Allan Belfrage"
                },
                {
                    "name": "bankdir Henry N Sporborg"
                },
                {
                    "name": "bankdir Marc Wallenberg Jr"
                },
                {
                    "name": "prof Jan Hellner"
                },
                {
                    "name": "dir Sture Odner"
                },
                {
                    "name": "dir Erik Johnsson"
                },
                {
                    "name": "dir Sture Ekefalk"
                },
                {
                    "name": "dir Bo Gyllenberg"
                },
                {
                    "name": "dir Bengt Andersson",
                    "position": "suppl"
                },
                {
                    "name": "dir Peter Wallenberg",
                    "position": "suppl"
                }
            ],
            "establishment_year": 1968
        },
        "16": {
            "company_name": "ATLAS COPCO SVENSKA FÖRSÄLJNINGS AB",
            "pnr": "131 01",
            "address": "Nacka 1, Fack",
            "phone_number": "08-24 25 40",
            "bank_details": {
                "bankgiro": "160-6144",
                "postgiro": "255 265-1"
            },
            "activity": "Säljer på den svenska marknaden Atlas Copco produkter",
            "employees": 620,
            "capital": 10000000,
            "key_personnel": [
                {
                    "name": "Einar Liwendahl"
                }
            ],
            "establishment_year": 1945
        }
    }
}