{
    "original": "AKTINO ELEKTRO AB\n\nPnr 126 21\n\nHägersten X, Box 40. Glidgränd 13.\nTel 08-46 08 90, 46 08 91. Tga\nAktino, Stockholm\nVerksamhet: Tillverkar o säljer\nelektriska apparater\nAktiekapital: 20 000\nVerkst dir: J G Nordström\nEtableringsår: 1949.\n\nLOVDALENS INDUSTRI AB\n\nPnr 285 01\n\nMarkaryd 1, Järnvägsg 13. Box 57.\nTel 0433-112 50. Bankgiro\n279-5177. Postgiro 126030-6\nVerksamhet: Tillverkar gallerdurk,\nsteg, trappor, spiraltrappor m m\nAntal anställda: 30\nAktiekapital: 10 000\nVerkst dir: Sixten Vetterlein.\n\nLOWENER, AB V\n\nPnr 17120\n\nSolna 1, Vretenv 2. Fack. Tel\n08-9801 60. Bankgiro 727-0325.\nPostgiro 2756-5. Tga Stållöwener.\nTelex 19908.\n\nVerksamhet: Verktygsmaskiner,\nverktyg, bilverkstads- o\nservicestationsutrustningar, maskintät-ningar, industritruckar, traverser\nAvdelningskontor: Göteborg,\nIm-portg 2-4. Tel 031-52 02 60\nHelsingborg, Florettg 9. Tel\n042-1803 20\n\nVarunamn: Bechler, Bee-Line,\nBoehringer, Brown &amp; Sharpe, Bupi,\nBöwe, dayton, Clean-O-Matic,\nCleveland Tramrail, Christen,\nCrypton, DeVlieg, Diedesheim,\nExcel, Fog, Fox, Geometric,\nGrä-bener, Hadef, Haeusler, Hardinge,\nHayes, Hecker, Heidenreich &amp;\nHar-beck. Hofmann, Jacobs, Jahrl,\nKitchen &amp; Wade, Le Tourneau Inc,\n\nMatheys, Microbore, Mondiale,\nMtlller, Nikon, Perth-o-Meter,\nPhoenix, Pul-Lift, Rust-Oleum, Rlisch,\nSaacke, Schramifa, Simplex,\nSriap-On, Soutl&gt;Bend, Stahlwille,\nStave-ly-Archdale, Stavely-Asquith,\nSta-vely-Drummond, Stavely-Lapointe,\nToyo, Trebel, Walker, Walton,\nVDF, Welter, Weltrawo, VLC,\nWohlenberg, Wolf, V-Ringen, Yale,\nYamamoto, Obergs\nAntal anställda: 110\nÅrsomsättning: 35 000 000\nAktiekapital: 250 000\nVerkst dir: G Fredriksson\nEtableringsår: 1898.\n\nSVENSK FINSÄKRING\n\nPnr 117 21\n\nStockholm, Hornsg 78. Tel\n08-840220. Bankgiro 746-0116.\nPostgiro 190186-7. Tga Prestoteknik\nVerksamhet: Tillverkning av\nelektronikkomponenter\n\nÅrsomsättning: 400 000\nVerkst din Ing Knut F Bratt\nEtableringsår: 1941.\n\nEKDAHLVERKEN AB\n\nPnr 360 51\n\nHovmantorp. Tel 0478-405 50.\nBankgiro 357-1825. Postgiro 332330-0\n\nFörpackat bra med\nMt EKDAHLS PACKBORD\n\nStyrelse: Ark Lars Ekedorff, ark\nJan Ekström, dir Tage Swahn\nVerkst dir: Ark SAR Lars Ekedorff\nChef: Ark SAR Jan Ekström\nEtableringsår: 1952\nNuvarande namn 1963.\n\nEKEGREN BOKTRYCKERI\nAB, BROR\n\nPnr 15121\n\nSödertälje 1, Järnag 3. Box 76.\nTel 0755-302 58. 314 58. Bankgiro\n622-4356. Postgiro 134778-0\nVerksamhet: Boktryckeri. Reklam-,\naccidens- o affischtryck\nAntal anställda: 16\nÅrsomsättning: 970 000\nAktiekapital: 30 000\nVerkst dir Fru Lillemor\nEkegren-Holmqvist\n\nEtableringsår: 1924.\n\nVerksamhet: Tillverkar packbord,\nklisterapparater, hyllvagnar,\nkartong* o fotosaxar, handskärmaskiner\nAntal anställda: 20\nÅrsomsättning: 2 000 000\nAktiekapital: 60000\nVerkst dir: Lennart Ekdahl\nEtableringsår: 1947.\n\nEKEBERGSLUNDS\nTRÄFOR-ÄDLING AB\n\nPnr 290 72\n\nAsarom. Box 425. Tel 0454-201 39.\nBankgiro 65-6624. Postgiro 293507\nVerksamhet: Tillverkar trävaror o\nbyggnadsmaterial\nAntal anställda: 15\nAktiekapital: 50 000\nVerkst dir: Karl Svensson\nEtableringsår: 1936.\n\nWISENIUS MÖBLER AB\n\nPnr 412 53\n\nGöteborg, Berzeliig 11. Tel\n031-200160. Bankgiro 36-2611. Post\ngiro 45399\n\nVerksamhet: Tillverkar o säljer\nkontorsmöbler\nAntal anställda: 6\nÅrsomsättning: 1 000 000\nAktiekapital: 10 000\nVeikst din Erland Wisenius\nEtableringsån 1952.\n\nVISKADALENS JACQUARD.\nVÄVERI, AB\n\nPnr 51100\n\nKinna, Bollareslätt. Tel\n0320-480 58. 482 27. Bankgiro 546-1371.\nPostgiro 136105-4\nVerksamhet: Tillverkar borddukar,\nbordduksväv, aidaväv o förkläden\nAntal anställda: 20\nÅrsomsättning: 2 000 000\nAktiekapital: 30 000\nEtableringsår: 1937.\n\nVISKADALENS\nMÖBELINDUSTRI\n\nPnr 51101\n\nKinna 1. Kasthallsv. Box 87. Tel\n0320-108 08. 11808. Bankgiro\n546-1348. Postgiro 360522-7. Tga\nViskamöbler\n\nVerksamhet: Tillverkar stoppade\nsittmöbler, fåtöljer o soffor, klädda\ni läder, mockaskinn eller tyg\nChef: Fabr Gunnar Björklund\nEtableringsån 1947.\n\nBORJESSON AB, H G\n\nPnr 402 22\n\nGöteborg 5, Box 5101.\nGyllen-krooksg 14. Tel 031-81 0030.\nBankgiro 785-2528. Postgiro 49195-1\nVerksamhet: Inredningar till\nkontor, offentliga lokaler, butiker o\nrestauranger\nAntal anställda: 25\nAktiekapital: 75000\nVerkst dir: Rolf Börjesson\nEtableringsår: 1944.\n\nERICSON &amp; CO, AB C 0\n\nPnr 59101\n\nMotala 1, Agneshögsg. Box 192. Tel\n0141-16190. Bankgiro 82-1922.\nPostgiro 173217. Tga Ceo\nVerksamhet: Tillverkar skinnkläder\nAntal anställda: 140\nAktiekapital: 150 000\nVerkst dir: Erie Ericson\nEtableringsår: 1918.\n\nKINDBORG, JOHN\n\nPnr 37100\n\nKarlskrona, Drottningg 61. Tel\n0455-11280. Postgiro 324527.\nTga Kindborg. Telex 4859\nVerksamhet: Auktoriserad\nskeppsklarerare, speditör o\nbefraktnings-agent\n\nChef: Arthur Johannisson\nEtableringsår: 1864.\n\nWEDEVÄGS BRUKS AB\n\nPnr 71044\n\nVedevåg. Tel 0581-261 00. Telex\n73343. Tga Wedevågbruk,\nLindesberg\n\nVerksamhet: Tillverkar spadar,\ngrepar, krattor, skaft, spiralborrar,\nbrotschar, driftar, (dragbrotschar),\nchuckar, gängapparater,\nborrspets-slipmaskiner o dragbro\ntschmaski-ner. Färger o läcker speciellt för\nindustriell produktmålning\nAntal anställda: 450\nÅrsomsättning: 30 000 000\nAktiekapital: 3000 000\nVerkst dir: Bruksdisp Lars\nDegefors\n\nEtableringsår: Grundat under\n1500-talet.\n\nWEDHOLMS AB\n\nPnr 61100\n\nNyköping, Blommenhovsv. Tel\n0155-179 00. Bankgiro 82-7244.\n\nPostgiro 72320. Telex 64023. Tga\nWedholms\n\nVerksamhet: Specialitet: apparater\no utrustning i rostfritt, särskilt för\nlivsmedelsindustrin, såsom\nkyltankar o tankbilar, större o mindre\nför-varingstankar, kokgrytor för\nstorkök etc, mejerimaskiner,\ntransport-flaskor\n\nAntal anställda: 400\nÅrsomsättning: 47 000 000\nAktiekapital: 7 000 000\nVerkst dir: Lennart Ridderstråle\nEtableringsår: 1879\nOmbildat till aktiebolag 1904.\nDotterbolag: AB Claesson o Petersén,\nAB Mejerikontoret.\n\nWEDIN, AB BRÖDERNA\n\nPnr 870 52\n\nNyland, Box 50. Tel 0612-224 00.\nBankgiro 187-1375. Postgiro\n72027-6. Tga Brödernawedin\nVerksamhet: Egen tillverkning av\nfritids- o sportskor\nAntal anställda: 200\nÅrsomsättning: 20 000 000\nAktiekapital: 150 000\nVerkst dir. Sven Wedin\nEtableringsån 1918.\n\nHEDBERGS VERKSTÄDER\n\nPnr 283 00\n\nOsby, Smedjeg. Tel 0479-103 82.\nPostgiro 143537\n\nVerksamhet: Tillverkar balpressar\nAntal anställda: 40\nÄgare o chef: Axel Hedberg\nEtableringsår: 1898.\n\nHEDBERGS PATENTBYRÅ\nAB, ALFONS\n\nPnr 41133\n\nGöteborg, Aschebergsg 35. Tel\n031-18 4600, 18 46 20. Bankgiro\n50-0608. Postgiro 40186. Tga\nPro-tection\n\nVerksamhet: Handläggning av\npatent-, varumärkes-o mönsterärenden\nAntal anställda: 20\nAktiekapital: 25 000\nStyrelseordf: Dir Evald\nFerking-hoff\n\nVerkst dir: Ing Evald Ferkinghoff\nEtableringsår: 1924\nOmbildat till aktiebolag 1966.\n\nHEDBERG, ELOF\n\nPnr 251 03\n\nHelsingborg 1, Box 153. Kungsg\n18. Tel 042-12 62 30. Bankgiro\n340-4274. Postgiro 23139-9. Tga Elof.\nTelex 72264\n\nVerksamhet: Trävaror i parti\nÄgare o chef: Grosshandl Einar\nHedberg\n\nDisp: Bertil Thunberg\nEtableringsår 1893.",
    "structured": {
        "1": {
            "company_name": "AKTINO ELEKTRO AB",
            "pnr": "126 21",
            "address": "Hägersten X, Box 40. Glidgränd 13.",
            "phone_number": "08-46 08 90, 46 08 91",
            "activity": "Tillverkar o säljer elektriska apparater",
            "capital": 20000,
            "key_personnel": [
                {
                    "name": "J G Nordström",
                    "position": "Verkst dir"
                }
            ],
            "establishment_year": 1949
        },
        "2": {
            "company_name": "LOVDALENS INDUSTRI AB",
            "pnr": "285 01",
            "address": "Markaryd 1, Järnvägsg 13.",
            "phone_number": "0433-112 50",
            "bank_details": {
                "bankgiro": "279-5177",
                "postgiro": "126030-6"
            },
            "activity": "Tillverkar gallerdurk, steg, trappor, spiraltrappor m m",
            "employees": 30,
            "capital": 10000,
            "key_personnel": [
                {
                    "name": "Sixten Vetterlein",
                    "position": "Verkst dir"
                }
            ],
            "establishment_year": 1898
        },
        "3": {
            "company_name": "LOWENER, AB V",
            "pnr": "17120",
            "address": "Solna 1, Vretenv 2.",
            "phone_number": "08-9801 60",
            "bank_details": {
                "bankgiro": "727-0325",
                "postgiro": "2756-5"
            },
            "activity": "Verktygsmaskiner, verktyg, bilverkstads- o servicestationsutrustningar, maskintätningar, industritruckar, traverser",
            "employees": 110,
            "annual_turnover": 35000000,
            "capital": 250000,
            "key_personnel": [
                {
                    "name": "G Fredriksson",
                    "position": "Verkst dir"
                }
            ],
            "establishment_year": 1898
        },
        "4": {
            "company_name": "SVENSK FINSÄKRING",
            "pnr": "117 21",
            "address": "Stockholm, Hornsg 78.",
            "phone_number": "08-840220",
            "bank_details": {
                "bankgiro": "746-0116",
                "postgiro": "190186-7"
            },
            "activity": "Tillverkning av elektronikkomponenter",
            "annual_turnover": 400000,
            "key_personnel": [
                {
                    "name": "Ing Knut F Bratt",
                    "position": "Verkst din"
                }
            ],
            "establishment_year": 1941
        },
        "5": {
            "company_name": "EKDAHLVERKEN AB",
            "pnr": "360 51",
            "address": "Hovmantorp.",
            "phone_number": "0478-405 50",
            "bank_details": {
                "bankgiro": "357-1825",
                "postgiro": "332330-0"
            },
            "activity": "Förpackat bra med Mt EKDAHLS PACKBORD",
            "key_personnel": [
                {
                    "name": "Ark SAR Jan Ekström",
                    "position": "Chef"
                }
            ],
            "establishment_year": 1952
        },
        "6": {
            "company_name": "EKEGREN BOKTRYCKERI AB, BROR",
            "pnr": "15121",
            "address": "Södertälje 1, Järnag 3.",
            "phone_number": "0755-302 58, 314 58",
            "bank_details": {
                "bankgiro": "622-4356",
                "postgiro": "134778-0"
            },
            "activity": "Boktryckeri. Reklam-, accidens- o affischtryck",
            "employees": 16,
            "annual_turnover": 970000,
            "capital": 30000,
            "key_personnel": [
                {
                    "name": "Fru Lillemor Ekegren-Holmqvist",
                    "position": "Verkst dir"
                }
            ],
            "establishment_year": 1924
        },
        "7": {
            "company_name": "EKEBERGSLUNDS TRÄFORÄDLING AB",
            "pnr": "290 72",
            "address": "Asarom. Box 425.",
            "phone_number": "0454-201 39",
            "bank_details": {
                "bankgiro": "65-6624",
                "postgiro": "293507"
            },
            "activity": "Tillverkar trävaror o byggnadsmaterial",
            "employees": 15,
            "capital": 50000,
            "key_personnel": [
                {
                    "name": "Karl Svensson",
                    "position": "Verkst dir"
                }
            ],
            "establishment_year": 1936
        },
        "8": {
            "company_name": "WISENIUS MÖBLER AB",
            "pnr": "412 53",
            "address": "Göteborg, Berzeliig 11.",
            "phone_number": "031-200160",
            "bank_details": {
                "bankgiro": "36-2611",
                "postgiro": "45399"
            },
            "activity": "Tillverkar o säljer kontorsmöbler",
            "employees": 6,
            "annual_turnover": 1000000,
            "capital": 10000,
            "key_personnel": [
                {
                    "name": "Erland Wisenius",
                    "position": "Veikst din"
                }
            ],
            "establishment_year": 1952
        },
        "9": {
            "company_name": "VISKADALENS JACQUARD. VÄVERI, AB",
            "pnr": "51100",
            "address": "Kinna, Bollareslätt.",
            "phone_number": "0320-480 58, 482 27",
            "bank_details": {
                "bankgiro": "546-1371",
                "postgiro": "136105-4"
            },
            "activity": "Tillverkar borddukar, bordduksväv, aidaväv o förkläden",
            "employees": 20,
            "annual_turnover": 2000000,
            "capital": 30000,
            "establishment_year": 1937
        },
        "10": {
            "company_name": "VISKADALENS MÖBELINDUSTRI",
            "pnr": "51101",
            "address": "Kinna 1, Kasthallsv. Box 87.",
            "phone_number": "0320-108 08, 11808",
            "bank_details": {
                "bankgiro": "546-1348",
                "postgiro": "360522-7"
            },
            "activity": "Tillverkar stoppade sittmöbler, fåtöljer o soffor, klädda i läder, mockaskinn eller tyg",
            "position": "Chef",
            "name": "Gunnar Björklund"
        },
        "establishment_year": 1947
    }
}