{
    "original": "BER\n\nningsuppdrag. Levererar all slags\nsten- o grusmaterial från egna\nkrossanläggningar\nAntal anställda: 20\nÅrsomsättning: 2000 000\nAktiekapital: 35 000\nStyrelse: Sven Falk (ordf), Bernt\nBerg, Yngve Olsson\nVerkst dir: Bernt Berg\nKamrer: Yngve Olsson\nEtableringsår: 1963.\n\nAFFÄRSINDEX AB\n\nPnr 17141\n\nSolna, Englundav 7. Tel\n08-98 04 75. Bankgiro 238-7702.\nPostgiro 251614-4\n\nVerksamhet:\nMarknadsundersökningar\n\nAntal anställda: 55\nAktiekapital: 50 000\nVerkst dir: Erkki Laakso\nEtableringsår: 1958.\n\nNORDIN &amp; CO BIL-AB\n\nPnr 831 01\n\nÖstersund 1, Rådhusg 100. Box 167.\nTel 063-172 90. Bankgiro 250-0858.\nPostgiro 176690-6\nVerksamhet: Bilförsäljning för\nPhi-lipsonskoncernen\nAntal anställda: 70\nÅrsomsättning: 12 000 000\nAktiekapital: 195 000\nVerkst dir: Oscar Smith\nEtableringsår: 1946.\n\nSCADO, AB\n\nPnr 261 35\n\nLandskrona, Varvsv. Tel\n0418-16950. Bankgiro 500-7190.\nPostgiro 590310-9.\nTelex 72289 SCADOLA S\nVerksamhet: Tillverkar\nkonsthart-ser o andra syntetiska\norganiskt-kemiska produkter för färg- o\nlackindustrin samt polyesterharts\nAntal anställda: 34\nÅrsomsättning: 9 000 000\nAktiekapital: 2000 000\nVerkst dir: Lennart Tellenmark\nEtableringsår: 1961.\n\nERMI, AB\n\nPnr 37101\n\nKarlskrona 1, Fack. Tel\n0455-23010. Tga Ermibolag. Telex 4819\nVerksamhet: Konstruktion o\ntillverkning av elektriska mätare o\nelstängsel\nFörsäljning:\n\nBERGMAN &amp; BEVING AB\n100 55 Stockholm 10, Fack. Tel\n08-246040. Telex 19929. Tga\nBergeving\n\n201 24 Malmö 1. Box 407. Tel\n040-767 60. Telex 3109. Tga Bergeving\n\n400 24 Göteborg 35, Box 35010.\nTel 031-19 26 70. Tga Bergeving\nVarunamn: Ermi\nAntal anställda: 260\nAktiekapital: 3 500 000\nVerkst din L-E Thörnberg\nEtableringsår: 1955.\n\nNORDPUMP, AB\n\nPnr 141 46\n\nHuddinge, Dalhemsv 44. Tel\n08-774 47 21. Bankgiro 617-3041.\nPostgiro 165566-1. Tga Norpump.\nTelex 10595\n\nVerksamhet: Korrosion o\nutskydds-färger\n\nVerkst dlr: Rune Runbjer\nEtableringsår: 1965.\n\nINTERHYDRAULIK AB\n\nPnr 16130\n\nBromma. Ekbacksv 42. Tel\n08-26 71 15, 26 71 16. Bankgiro\n23-9440. Postgiro 401860. Tga\nSwabolag\n\nVerksamhet: Tillverkar hydrauliska\npressar samt tillbehör till dessa\nVeikst dir: Pabr Herbert Johansson.\n\nINTER.IMPEX C T ERIKSSON\nAB\n\nPnr 18103\n\nLidingö 3, Tornv 2. Box 317. Tel\n08-766 02 90. Telex 10155 CTE S\nVerksamhet: Maskiner o mätdon,\nverktyg o industriförnödenheter\nFilial: Stockholm O, Artillerig 12.\nTel 08-63 36 50\n\nVarunamn: ESO, Laubscher,\nPrä-difa, Tetrabor, Vidmar\nAktiekapital: 15 000\nVerkst dir. C T Eriksso»\nEtableringsår: 1947.\n\nTECE.TRÄ, AB\n\nPnr 930 32\n\nörviken, Box 80. Tel 0910-320 32,\n32142. Postgiro 487730-4\nVerksamhet: Tillverkar tunnor,\nträtuber, baljor, kaggar o\nbastu-stävor. Sågverksrörelse\nAntal anställda: 60\nÅrsomsättning: 3 000 000\nVerkst dir: Thure Cristoferson.\n\nTED BATES AB\n\nPnr 114 86\n\nStockholm 5, Box 5601. Friggag 10.\nTel 08-24 45 60. Bankgiro 722-1054.\nPostgiro 2763-1. Tga Advertising.\nTelex 10813\n\nVerksamhet: Annonsbyrå med\nfullservice\n\nAvdelningskontor: 413 01 Göteborg,\nN Allég 6. Tel 031-17 5175\n25104 Helsingborg 1, Box 233.\nTrädgårdsg 13. Tel 042-12 78 30.\nTelex 72293\nAntal anställda: 160\nÅrsomsättning: 56 000 000\nAktiekapital: 272 000\nStyrelse: Adv Sten Lindskog, adv\nStig Orander, dir Gunnar H Rune,\ndir Ralf W Schalin\nVerkst dir: Ralf W Schalin\nEtableringsår: 1936.\n\nGECEA GEORGE CERVIN AB\n\nPnr 43130\n\nMölndal, Bifrostg 4. Tel\n031-87 00 55. Bankgiro 506-7590.\nPostgiro 421912-7. Tga Gecea\nVerksamhet: Säljer nöjesbåtar o\nmotorer till dessa, trimplan,\nbåt-möbler o båttillbehör. Generalagent\nför Boatleveler Mfg, S:t Louis,\nUSA (elektr hydrauliska trimplan)\nVarunamn: Insta Trim\nAntal anstäUda: 7\nÅrsomsättning: 5 000 000\nAktiekapital: 100 000\nVerkst dir George Cervin\nEtableringsår: 1962.\n\nGEC-ELLIOTT AUTOMATION\nAB\n\nPnr 12612\n\nStockholm 42, Box 42105. Elektrav\n31, Hägersten. Tel 08-18 80 60.\nBankgiro 569-6109. Postgiro\n652750-1. Tga Elliot auto.\nTelex 10335\nAktiekapital: 300 000\nVerkst dir: Töre Wallin\nEtableringsår: 1961.\n\nSVE\n\nSVENSK SKRUV, AB\n\nPnr 310 70\n\nTorup. Tel 0345-204 10. Bankgiro\n42-7065. Postgiro 13058.\nTga Svenskskruv\n\nVerksamhet: Tillverkar träskruv i\njärn, mässing o aluminium\nAntal anställda: 12\nÅrsomsättning: 1000 000\nAktiekapital: 300 000\nVerkst dir: Dawid Bauréus\nEtableringsår: 1943\nDotterbolag till Bårebo AB. Torup.\n\nSVENSK SPRIT, AB\n\nPnr 11146\n\nStockholm, Biblioteksg 6-8. Tel\n08-23 27 80. Bankgiro 700-1712.\nPostgiro 1822. Tga Svensksprit\nVerksamhet: Försäljningsorgan för\ncellulosaindustrins spritfabriker\nVerkst dir: Gösta Hall\nEtableringsår: 1918.",
    "structured": {
        "1": {
            "company_name": "BER",
            "activity": "Bergmaterial",
            "establishment_year": 1963,
            "employees": 20,
            "annual_turnover": 2000000,
            "capital": 35000,
            "key_personnel": [
                {
                    "name": "Sven Falk",
                    "position": "ordf"
                },
                {
                    "name": "Bernt Berg",
                    "position": null
                },
                {
                    "name": "Yngve Olsson",
                    "position": null
                }
            ]
        },
        "2": {
            "company_name": "AFFÄRSINDEX AB",
            "pnr": "17141",
            "address": "Solna, Englundav 7",
            "phone_number": "08-98 04 75",
            "bank_details": {
                "bankgiro": "238-7702",
                "postgiro": "251614-4"
            },
            "activity": "Marknadsundersökningar",
            "establishment_year": 1958,
            "employees": 55,
            "capital": 50000,
            "key_personnel": [
                {
                    "name": "Erkki Laakso",
                    "position": "Verkst dir"
                }
            ]
        },
        "3": {
            "company_name": "NORDIN & CO BIL-AB",
            "pnr": "831 01",
            "address": "Östersund 1, Rådhusg 100, Box 167",
            "phone_number": "063-172 90",
            "bank_details": {
                "bankgiro": "250-0858",
                "postgiro": "176690-6"
            },
            "activity": "Bilförsäljning för Phi-lipsonskoncernen",
            "establishment_year": 1946,
            "employees": 70,
            "annual_turnover": 12000000,
            "capital": 195000,
            "key_personnel": [
                {
                    "name": "Oscar Smith",
                    "position": "Verkst dir"
                }
            ]
        },
        "4": {
            "company_name": "SCADO, AB",
            "pnr": "261 35",
            "address": "Landskrona, Varvsv.",
            "phone_number": "0418-16950",
            "bank_details": {
                "bankgiro": "500-7190",
                "postgiro": "590310-9"
            },
            "activity": "Tillverkar konstharts- o andra syntetiska organiskt-kemiska produkter för färg- o lackindustrin samt polyesterharts",
            "establishment_year": 1961,
            "employees": 34,
            "annual_turnover": 9000000,
            "capital": 2000000,
            "key_personnel": [
                {
                    "name": "Lennart Tellenmark",
                    "position": "Verkst dir"
                }
            ]
        },
        "5": {
            "company_name": "ERMI, AB",
            "pnr": "37101",
            "address": "Karlskrona 1, Fack",
            "phone_number": "0455-23010",
            "activity": "Konstruktion o tillverkning av elektriska mätare o elstängsel",
            "establishment_year": null
        },
        "6": {
            "company_name": "BERGMAN & BEVING AB",
            "pnr": "100 55 Stockholm 10, Fack",
            "phone_number": "08-246040",
            "activity": "Varunamn: Ermi",
            "establishment_year": 1955,
            "employees": 260,
            "capital": 3500000,
            "key_personnel": [
                {
                    "name": "L-E Thörnberg",
                    "position": "Verkst din"
                }
            ]
        },
        "7": {
            "company_name": "NORDPUMP, AB",
            "pnr": "141 46",
            "address": "Huddinge, Dalhemsv 44",
            "phone_number": "08-774 47 21",
            "bank_details": {
                "bankgiro": "617-3041",
                "postgiro": "165566-1"
            },
            "activity": "Korrosion o utskydds-färger",
            "establishment_year": 1965,
            "employees": null
        },
        "8": {
            "company_name": "INTERHYDRAULIK AB",
            "pnr": "16130",
            "address": "Bromma, Ekbacksv 42",
            "phone_number": "08-26 71 15, 26 71 16",
            "bank_details": {
                "bankgiro": "23-9440",
                "postgiro": "401860"
            },
            "activity": "Tillverkar hydrauliska pressar samt tillbehör till dessa",
            "establishment_year": null
        },
        "9": {
            "company_name": "INTER.IMPEX C T ERIKSSON AB",
            "pnr": "18103",
            "address": "Lidingö 3, Tornv 2, Box 317",
            "phone_number": "08-766 02 90",
            "activity": "Varunamn: ESO, Laubscher, Prä-difa, Tetrabor, Vidmar",
            "capital": 15000,
            "key_personnel": [
                {
                    "name": "C T Eriksso?",
                    "position": "Verkst dir"
                }
            ],
            "establishment_year": 1947
        },
        "10": {
            "company_name": "TECE.TRÄ, AB",
            "pnr": "930 32",
            "address": "Örviken, Box 80",
            "phone_number": "0910-320 32, 32142",
            "postgiro": "487730-4",
            "activity": "Tillverkar tunnor, trätuber, baljor, kaggar o bastustävor. Sågverksrörelse",
            "establishment_year": null,
            "employees": 60,
            "annual_turnover": 3000000,
            "key_personnel": [
                {
                    "name": "Thure Cristoferson",
                    "position": "Verkst dir"
                }
            ]
        },
        "11": {
            "company_name": "TED BATES AB",
            "pnr": "114 86",
            "address": "Stockholm 5, Box 5601, Friggag 10",
            "phone_number": "08-24 45 60",
            "bankgiro": "722-1054",
            "postgiro": "2763-1",
            "activity": "Annonsbyrå med fullservice",
            "establishment_year": 1936,
            "employees": 160,
            "annual_turnover": 56000000,
            "capital": 272000,
            "key_personnel": [
                {
                    "name": "Adv Sten Lindskog",
                    "position": null
                },
                {
                    "name": "Adv Stig Orander",
                    "position": null
                },
                {
                    "name": "dir Gunnar H Rune",
                    "position": null
                },
                {
                    "name": "dir Ralf W Schalin",
                    "position": "Verkst dir"
                }
            ]
        },
        "12": {
            "company_name": "GECEA GEORGE CERVIN AB",
            "pnr": "43130",
            "address": "Mölndal, Bifrostg 4",
            "phone_number": "031-87 00 55",
            "bank_details": {
                "bankgiro": "506-7590",
                "postgiro": "421912-7"
            },
            "activity": "Säljer nöjesbåtar o motorer till dessa, trimplan, båtmöbler o båttillbehör. Generalagent för Boatleveler Mfg, S:t Louis, USA (elektr hydrauliska trimplan)",
            "varunamn": "Insta Trim",
            "establishment_year": 1962,
            "employees": 7,
            "annual_turnover": 5000000,
            "capital": 100000,
            "key_personnel": [
                {
                    "name": "George Cervin",
                    "position": "Verkst dir"
                }
            ]
        },
        "13": {
            "company_name": "GEC-ELLIOTT AUTOMATION AB",
            "pnr": "12612",
            "address": "Stockholm 42, Box 42105, Elektrav 31, Hägersten",
            "phone_number": "08-18 80 60",
            "bankgiro": "569-6109",
            "postgiro": "652750-1",
            "capital": 300000,
            "key_personnel": [
                {
                    "name": "Töre Wallin",
                    "position": "Verkst dir"
                }
            ],
            "establishment_year": 1961
        },
        "14": {
            "company_name": "SVENSK SKRUV, AB",
            "pnr": "310 70",
            "address": "Torup",
            "phone_number": "0345-204 10",
            "bankgiro": "42-7065",
            "postgiro": "13058",
            "activity": "Tillverkar träskruv i järn, mässing o aluminium",
            "establishment_year": 1943,
            "employees": 12,
            "annual_turnover": 1000000,
            "capital": 300000,
            "key_personnel": [
                {
                    "name": "Dawid Bauréus",
                    "position": "Verkst dir"
                }
            ]
        },
        "15": {
            "company_name": "SVENSK SPRIT, AB",
            "pnr": "11146",
            "address": "Stockholm, Biblioteksg 6-8",
            "phone_number": "08-23 27 80",
            "bankgiro": "700-1712",
            "postgiro": "1822",
            "activity": "Försäljningsorgan för cellulosaindustrins spritfabriker",
            "verkst dir": "Gösta Hall",
            "establishment_year": 1918
        }
    }
}