{
    "original": "CARLSSON, M &amp; E\n\nPnr 52011\n\nVegby, Box 53. Tel 0321-720 23.\nBankgiro 84^0654. Postgiro 95166-5\nVerksamhet: Tillverkar klänningar,\nbyxor, koftor, cardigan, jumpers,\ndressar, mössor o halsdukar\nAntal anställda: 50\nÅrsomsättning: 2 000 000\nVerkst dir: Paul Josefsson\nEtableringsår: 1933.\n\nCARLSSON AB, INGENJÖRS.\nFIRMAN NILS\n\nPnr 126 02\n\nHägersten 2, Hägerstens Allé. Box\n226. Tel 08-97 32 00, 97 3215.\nPostgiro 198181-0\nVerksamhet: Konsulterande\ningenjörsbyrå för husbyggnader\nAktiekapital: 5 000\nVeikst dir; Nils Carlsson\nEtableringsår: 1953.\n\npat\n\nVerksamhet Automatisering o\nombyggnad av standardmaskiner.\nProjektering, konstruktion o\ntillverkning av specialmaskiner.\nFörsäljning o applicering av styrsystem\ntyp LME. Säljer\nautomatiserings-komponenter. Konsultation\nChef: Uno Parbo\nEtableringsår: 1967.\n\nCARLSSON &amp; ÖSTERBERG\n\nPnr 41102\n\nGöteborg, Polhemsplatsen 7. Tel\n031-15 52 40, 15 5916. Bankgiro\n50-9745. Postgiro 41683-4\nVerksamhet: Tillverkning,\nförsäljning, reparation o service av\ngeodetiska instrument. Utför\nfinmekaniska arbeten\nAntal anställda: 18\nÅrsomsättning: 1700 000\nChef: Fabr Gunnar Malmberg\nVerkstadsing: Bertil Malmberg\nEtableringsår: 1906.\n\nGOI\n\nGEFLE KOLIMPORT, AB\n\nPnr 802 22\n\nGävle, S Strandg 16. Tel\n026-1242 88, 1243 88. Bankgiro\n19-3925. Postgiro 30395. Tga\nKolimport\n\nVerksamhet: Handel med\neldningsoljor, koks o kol jämte därmed\nförenlig verksamhet\nAntal anställda: 22\nÅrsomsättning: 7 00 0 000\nAktiekapital: 600 000\nStyrelse: Pru Gerd Sundgren (ordf),\ndlr Ove Sundberg, disp Viktor\nSundgren\n\nVerkst dir: Disp Viktor Sundgren\nEtableringsår: 1903.\n\ndanielsson ab, bröderna\n\nPnr 161 11\n\nBromma 11, Box 11045. Gjuteriv\n21. Tel 08-28 93 50. Bankgiro\n33-1087. Postgiro 158586\nVerksamhet: Tillverkar metall- o\nplastskyltar, skalor, skyltställ.\nUtför etsning, gravering,\nindusti-lackering, eloxering, offset- o\nscreentryckning samt plåtarbeten\nAntal anställda: 70\nÅrsomsättning: 5 000 000\nAktiekapital: 80 000\nStyrelse: Fabr Olof Danielsson\n(ordf), dir Sture Danielsson, fru\nHilda Danielsson, kamrer Erik\nRossander\n\nVerkst dir: Sture K F Danielsson\nEtableringsår: 1916.\n\ndanielson, forssberg &amp;\nco ab\n\nPnr 122 21\n\nEnskede 1, Box 39. Blåsutv 31-33.\nTel 08-39 04 25. Bankgiro\n734-0490. Postgiro 29-9. Tga Force\nVerksamhet: Säljer brandsläckare,\nkatalytiska bensin- o\ngasolele-ment samt bil- o\nindustriförnödenheter\n\nVarunamn: Dunton-Nokorode,\nKant-Rust, Nokorode, Permatex\nForm-A-Gasket, Pyrene, Snö-Force, Thermix\nAntal anställda: 14\nAktiekapital: 100 000\nVerkst dir: Björn Sparring\nEtableringsår: 1919\nOmbildat till aktiebolag 1961.\n\ndanielsson\nfastighetsbyrå wikström &amp;\nnorström ab, arne\n\nPnr 41136\n\nGöteborg, Kungsportsavenyn 14.\nTel 031-17 72 60. Bankgiro 112-\n\nB 5\n\n2571. Postgiro 721310-1\nVerksamhet: Fastighetsmäklare.\nIndustri o bostäder\nAntal anställda: 6\nAktiekapital: 5 000\nStyrelse: Mäklare L Nordström\nVerkst dir: Ing Arne Wikström\nEtableringsår: 1955\nOmbildat 1969.\n\ndanielson &amp; co ab, j\n\nPnr 115 28\n\nStockholm, Sandhamnsg 29.\nTel 08-63 04 10. Postgiro 51825.\nTga Danos. Telex 10101\nVerksamhet: Säljer\nverktygsmaskiner, gjuteri- o smidesmaskiner,\ntransportutrustningar samt elektr\nhandverktyg, skärvätskor mm\nServiceverkstad: Stockholm O,\nValhallav 38. Tel 08-30 67 65\nVarunamn: Alpa, Arku, Black &amp;\nDecker, Curtis, Denison,\nDiedes-heim, Donau, Heuer-Pressen, Huck,\nKitchen &amp; Walker, Menn, Nagel,\nNiederberger, Reinecker,\nRhein-stahl, Semel, Stotz, Sykes,\nVoll-mer, Weisser, Wolters\nAktiekapital: 350000\nVerkst dir: Lars Danielson\nEtableringsår: 1930.\n\nREJMES BIL AB, TAGE\n\nPnr 602 28\n\nNorrköping, Lindöv 60. Tel\n011-13 9740. Bankgiro 349-2097.\nPostgiro 166911-8\n\nVerksamhet: Auktoriserad\nåterförsäljare för Volvo\nAntal anställda: 200\nÅrsomsättning: 50 000 000\nAktiekapital: 600 000\nVerkst dir: Tage Rejme.\n\nREKLAMBAND, SVENSKA\nREKLAMB ANDFABRIKEN\nNYA AB\n\nPnr 66100\n\nSäffle, Fågelv 3. Box 93. Tel\n0533-13131. Bankgiro 420-1646.\nPostgiro 9080-3. Tga Reklamband\nVerksamhet: Reklambandfabrik\nÅrsomsättning: 380 000\nAktiekapital: 60 000\nVerkst dir: Rudolf Berg\nEtableringsår: 1915.\n\nREKLAMKONSULTATION\nRK AB\n\nPnr 41115\n\nGöteborg, Kungspassagen. Tel\n031-17 53 90. Bankgiro 54-9919.\nPostgiro 49022. Tga Reclama.\nTelex 20922 RECLAMA S\nVerksamhet: Annonsbyrå\nAntal anställda: 30\nÅrsomsättning: 12 000 000\nAktiekapital: 250 000\nStyrelse: Stig Königson (ordf),\nJohnny Andersson, Jack Fredrikson\nVerkst dir: Johnny Andersson\nEkonomichef: Herbert Ericson\nEtableringsår: 1959.\n\nDURO-OFFSET, AB\n\nPnr 212 28\n\nMalmö, Johanneslustg 1. Tel\n040-18 09 60. Bankgiro 874-8394.\nPostgiro 430200-6\n\nVerksamhet: Offsettryckeri.\nSpecialitet: fyrfärgstryck.\nReproduktionsateljé\n\nAntal anställda: 15\nAktiekapital: 15 000\nVerkst dir: Göte Erikson\nEtableringsår: 1950.\n\nVIA-V ALV, BYGGNADS AB\n\nPnr 16140\n\nBromma, Thaliav 17. Tel\n08-2 6 07 4 9 , 80 34 40. Bankgiro\n560-6165. Postgiro 608854-6\nVerksamhet: Byggnadsrörelse.\nBro-o vattenbyggnadsarbeten\nÅrsomsättning: 1000 000\nAktiekapital: 30 000\nChef: Torvald Carlsson\nEtableringsår: 1960.\n\nARENA, AB TEXTILFABRIKEN\n\nPnr 51100\n\nKinna. Tel 0320-115 75. Bankgiro\n43-4706. Postgiro 361176. Tga\nTextura\n\nVerksamhet: Tillverkning av\nmöbeltyger o dekorativa textilier\nAntal anställda: 55\nAktiekapital: 120 000\nVerkst dir: Lennart Otell\nEtableringsår: 1947.\n\nSOHLBERG AB, AXEL\n\nPnr 450 50\n\nMunkedal 1, Box 2060. Tel\n0524-10510. Bankgiro 439-4508.\nPostgiro 70117-7. Tga Asab\nVerksamhet: Trävaru- o\nbyggmaterialaffär\n\nAntal anstäUda: 30\n\nÅrsomsättning: 4 000 000\nAktiekapital: 150 000\nVerkst dir: Bengt Johanson\nKamrer: Ake Johansson\nEtableringsår: 1905\nOmbildat till aktiebolag 1946.\n\nSOLBERGS BETONGVARU\nAB, O\n\nPnr 460 50\n\nGrästorp. Tel 0514-101 21,10281\n\nVerksamhet: Betongvaror o\nsiloanläggningar\n\nAktiekapital: 100 000\nVerkst dir: O Solberg.\n\nSOLBERGA MEKANISKA\nVERKSTADS AB\n\nPnr 57100\n\nNässjö, Solberga. Tel 0380-522 00.\nBankgiro 45-2780. Postgiro 27897.\nTga Verkstaden\n\nVerksamhet: Tillverkar\nborrmaskiner o träsvarvar, specialmaskiner\nför borrning o gängning m m\nAntal anstäUda: 45\nÅrsomsättning: 3 300 000\nAktiekapital: 200 000\nStyrelse: Disp Nils-Gustaf Widfeldt\n(ordf), ing Bengt Widfeldt\nEtableringsår 1900.",
    "structured": {
        "1": {
            "company_name": "M & E CARLSSON",
            "pnr": "52011",
            "address": "Vegby, Box 53",
            "phone_number": "0321-720 23",
            "bank_details": {
                "bankgiro": "84^0654",
                "postgiro": "95166-5"
            },
            "activity": "Tillverkar klänningar, byxor, koftor, cardigan, jumpers, dressar, mössor o halsdukar",
            "employees": 50,
            "annual_turnover": 2000000,
            "key_personnel": [
                {
                    "name": "Paul Josefsson",
                    "position": "Verkst dir"
                }
            ],
            "establishment_year": 1933
        },
        "2": {
            "company_name": "CARLSSON AB, INGENJÖRS. FIRMAN NILS",
            "pnr": "126 02",
            "address": "Hägersten 2, Hägerstens Allé, Box 226",
            "phone_number": "08-97 32 00, 97 3215",
            "postgiro": "198181-0",
            "activity": "Konsulterande ingenjörsbyrå för husbyggnader",
            "capital": 5000,
            "key_personnel": [
                {
                    "name": "Nils Carlsson",
                    "position": "Veikst dir"
                }
            ],
            "establishment_year": 1953
        },
        "3": {
            "company_name": "pat",
            "activity": "Verksamhet Automatisering o ombyggnad av standardmaskiner. Projektering, konstruktion o tillverkning av specialmaskiner. Försäljning o applicering av styrsystem typ LME. Säljer automatiserings-komponenter",
            "key_personnel": [
                {
                    "name": "Uno Parbo",
                    "position": "Chef"
                }
            ],
            "establishment_year": 1967
        },
        "4": {
            "company_name": "CARLSSON & ÖSTERBERG",
            "pnr": "41102",
            "address": "Göteborg, Polhemsplatsen 7",
            "phone_number": "031-15 52 40, 15 5916",
            "bank_details": {
                "bankgiro": "50-9745",
                "postgiro": "41683-4"
            },
            "activity": "Tillverkning, försäljning, reparation o service av geodetiska instrument. Utför finmekaniska arbeten",
            "employees": 18,
            "annual_turnover": 1700000,
            "key_personnel": [
                {
                    "name": "Fabr Gunnar Malmberg",
                    "position": "Chef"
                },
                {
                    "name": "Bertil Malmberg",
                    "position": "Verkstadsing"
                }
            ],
            "establishment_year": 1906
        },
        "5": {
            "company_name": "GOI GEFLE KOLIMPORT, AB",
            "pnr": "802 22",
            "address": "Gävle, S Strandg 16",
            "phone_number": "026-1242 88, 1243 88",
            "bank_details": {
                "bankgiro": "19-3925",
                "postgiro": "30395"
            },
            "activity": "Handel med eldningsoljor, koks o kol jämte därmed förenlig verksamhet",
            "employees": 22,
            "annual_turnover": 7000000,
            "capital": 600000,
            "key_personnel": [
                {
                    "name": "Pru Gerd Sundgren",
                    "position": "Styrelse (ordf)"
                },
                {
                    "name": "Ove Sundberg",
                    "position": "dlr"
                },
                {
                    "name": "Viktor Sundgren",
                    "position": "disp Verkst dir"
                }
            ],
            "establishment_year": 1903
        },
        "6": {
            "company_name": "danielsson ab, bröderna",
            "pnr": "161 11",
            "address": "Bromma 11, Box 11045, Gjuteriv 21",
            "phone_number": "08-28 93 50",
            "bank_details": {
                "bankgiro": "33-1087",
                "postgiro": "158586"
            },
            "activity": "Tillverkar metall- o plastskyltar, skalor, skyltställ. Utför etsning, gravering, industi-lackering, eloxering, offset- o screentryckning samt plåtarbeten",
            "employees": 70,
            "annual_turnover": 5000000,
            "capital": 80000,
            "key_personnel": [
                {
                    "name": "Olof Danielsson",
                    "position": "Styrelse (ordf)"
                },
                {
                    "name": "Sture Danielsson",
                    "position": "dir"
                },
                {
                    "name": "Hilda Danielsson",
                    "position": "fru"
                },
                {
                    "name": "Erik Rossander",
                    "position": "kamrer"
                },
                {
                    "name": "Sture K F Danielsson",
                    "position": "Verkst dir"
                }
            ],
            "establishment_year": 1916
        },
        "7": {
            "company_name": "danielson, forssberg & co ab",
            "pnr": "122 21",
            "address": "Enskede 1, Box 39, Blåsutv 31-33",
            "phone_number": "08-39 04 25",
            "bank_details": {
                "bankgiro": "734-0490",
                "postgiro": "29-9"
            },
            "activity": "Säljer brandsläckare, katalytiska bensin- o gasolele-ment samt bil- o industriförnödenheter",
            "varunamn": "Dunton-Nokorode, Kant-Rust, Nokorode, Permatex Form-A-Gasket, Pyrene, Snö-Force, Thermix",
            "employees": 14,
            "capital": 100000,
            "key_personnel": [
                {
                    "name": "Björn Sparring",
                    "position": "Verkst dir"
                }
            ],
            "establishment_year": 1919
        },
        "8": {
            "company_name": "danielsson fastighetsbyrå wikström & norström ab, arne",
            "pnr": "41136",
            "address": "Göteborg, Kungsportsavenyn 14",
            "phone_number": "031-17 72 60",
            "bankgiro": "112-B 5 2571",
            "activity": "Fastighetsmäklare. Industri o bostäder",
            "employees": 6,
            "capital": 5000,
            "key_personnel": [
                {
                    "name": "L Nordström",
                    "position": "Styrelse (Mäklare)"
                },
                {
                    "name": "Arne Wikström",
                    "position": "Verkst dir"
                }
            ],
            "establishment_year": 1955
        },
        "9": {
            "company_name": "danielson & co ab, j",
            "pnr": "115 28",
            "address": "Stockholm, Sandhamnsg 29",
            "phone_number": "08-63 04 10",
            "postgiro": "51825",
            "activity": "Säljer verktygsmaskiner, gjuteri- o smidesmaskiner, transportutrustningar samt elektr handverktyg, skärvätskor mm",
            "service_verkstad": {
                "location": "Stockholm O, Valhallav 38",
                "phone_number": "08-30 67 65"
            },
            "varunamn": "Alpa, Arku, Black & Decker, Curtis, Denison, Diedes-heim, Donau, Heuer-Pressen, Huck, Kitchen & Walker, Menn, Nagel, Niederberger, Reinecker, Rhein-stahl, Semel, Stotz, Sykes, Voll-mer, Weisser, Wolters",
            "capital": 350000,
            "key_personnel": [
                {
                    "name": "Lars Danielson",
                    "position": "Verkst dir"
                }
            ],
            "establishment_year": 1930
        },
        "10": {
            "company_name": "REJMES BIL AB, TAGE",
            "pnr": "602 28",
            "address": "Norrköping, Lindöv 60",
            "phone_number": "011-13 9740",
            "bankgiro": "349-2097",
            "postgiro": "166911-8",
            "activity": "Auktoriserad återförsäljare för Volvo",
            "employees": 200,
            "annual_turnover": 50000000,
            "capital": 600000,
            "key_personnel": [
                {
                    "name": "Tage Rejme",
                    "position": "Verkst dir"
                }
            ]
        },
        "11": {
            "company_name": "REKLAMBAND, SVENSKA REKLAMB ANDFABRIKEN NYA AB",
            "pnr": "66100",
            "address": "Säffle, Fågelv 3, Box 93",
            "phone_number": "0533-13131",
            "bankgiro": "420-1646",
            "postgiro": "9080-3",
            "activity": "Reklambandfabrik",
            "annual_turnover": 380000,
            "capital": 60000,
            "key_personnel": [
                {
                    "name": "Rudolf Berg",
                    "position": "Verkst dir"
                }
            ],
            "establishment_year": 1915
        },
        "12": {
            "company_name": "REKLAMKONSULTATION RK AB",
            "pnr": "41115",
            "address": "Göteborg, Kungspassagen",
            "phone_number": "031-17 53 90",
            "bankgiro": "54-9919",
            "postgiro": "49022",
            "activity": "Annonsbyrå",
            "employees": 30,
            "annual_turnover": 12000000,
            "capital": 250000,
            "key_personnel": [
                {
                    "name": "Stig Königson",
                    "position": "Styrelse (ordf)"
                },
                {
                    "name": "Johnny Andersson",
                    "position": "Styrelse"
                },
                {
                    "name": "Herbert Ericson",
                    "position": "Ekonomichef"
                },
                {
                    "name": "Johnny Andersson",
                    "position": "Verkst dir"
                }
            ],
            "establishment_year": 1959
        },
        "13": {
            "company_name": "DURO-OFFSET, AB",
            "pnr": "212 28",
            "address": "Malmö, Johanneslustg 1",
            "phone_number": "040-18 09 60",
            "bankgiro": "874-8394",
            "postgiro": "430200-6",
            "activity": "Offsettryckeri. Specialitet: fyrfärgstryck. Reproduktionsateljé",
            "employees": 15,
            "capital": 15000,
            "key_personnel": [
                {
                    "name": "Göte Erikson",
                    "position": "Verkst dir"
                }
            ],
            "establishment_year": 1950
        },
        "14": {
            "company_name": "VIA-V ALV, BYGGNADS AB",
            "pnr": "16140",
            "address": "Bromma, Thaliav 17",
            "phone_number": "08-2 6 07 4 9 , 80 34 40",
            "bankgiro": "560-6165",
            "postgiro": "608854-6",
            "activity": "Byggnadsrörelse. Bro-o vattenbyggnadsarbeten",
            "annual_turnover": 1000000,
            "capital": 30000,
            "key_personnel": [
                {
                    "name": "Torvald Carlsson",
                    "position": "Chef"
                }
            ],
            "establishment_year": 1960
        },
        "15": {
            "company_name": "ARENA, AB TEXTILFABRIKEN",
            "pnr": "51100",
            "address": "Kinna",
            "phone_number": "0320-115 75",
            "bankgiro": "43-4706",
            "postgiro": "361176",
            "activity": "Tillverkning av möbeltyger o dekorativa textilier",
            "employees": 55,
            "capital": 120000,
            "key_personnel": [
                {
                    "name": "Lennart Otell",
                    "position": "Verkst dir"
                }
            ],
            "establishment_year": 1947
        },
        "16": {
            "company_name": "SOHLBERG AB, AXEL",
            "pnr": "450 50",
            "address": "Munkedal 1, Box 2060",
            "phone_number": "0524-10510",
            "bankgiro": "439-4508",
            "postgiro": "70117-7",
            "activity": "Trävaru- o byggmaterialaffär",
            "employees": 30,
            "annual_turnover": 4000000,
            "capital": 150000,
            "key_personnel": [
                {
                    "name": "Bengt Johanson",
                    "position": "Verkst dir"
                },
                {
                    "name": "Ake Johansson",
                    "position": "Kamrer"
                }
            ],
            "establishment_year": 1905
        },
        "17": {
            "company_name": "SOLBERGS BETONGVARU AB, O",
            "pnr": "460 50",
            "address": "Grästorp",
            "phone_number": "0514-101 21,10281",
            "activity": "Betongvaror o siloanläggningar",
            "capital": 100000,
            "key_personnel": [
                {
                    "name": "O Solberg",
                    "position": "Verkst dir"
                }
            ]
        },
        "18": {
            "company_name": "SOLBERGA MEKANISKA VERKSTADS AB",
            "pnr": "57100",
            "address": "Nässjö, Solberga",
            "phone_number": "0380-522 00",
            "bankgiro": "45-2780",
            "postgiro": "27897",
            "activity": "Tillverkar borrmaskiner o träsvarvar, specialmaskiner för borrning o gängning m m",
            "employees": 45,
            "annual_turnover": 3300000,
            "capital": 200000,
            "key_personnel": [
                {
                    "name": "Nils-Gustaf Widfeldt",
                    "position": "Styrelse (ordf)"
                },
                {
                    "name": "Bengt Widfeldt",
                    "position": "ing"
                }
            ],
            "establishment_year": 1900
        }
    }
}