{
    "original": "BESON-TRYCK, AB\n\nPnr 212 28\n\nMalmö, Stålkuleg 3. Tel\n040-93 48 30. Bankgiro 641-0617.\nPostgiro 148542-4\n\nVerksamhet: Reklam- o\nblanketttryck i boktryck o offset\nAntal anställda: 24\nAktiekapital: 150000\nVerkst dir: Elvir B Nilsson\nEtableringsår: 1951.\n\nLILUX BELYSNING AB\n\nPnr 113 55\n\nStockholm, Roslagsg 4. Tel\n08-24 94 20. Bankgiro 11-8630.\nPostgiro 459830. Telex 17358 lux s.\nTga Luxannelli\n\nVerksamhet: Engrosförsäljning o\nprojektering av belysningsarmatur\nUtställning o Försäljningskontor:\n113 57 Stockholm, Jarlaplan 2. Tel\n08-24 94 20\nAntal anställda: 32\nÅrsomsättning: 6 700 000\nAktiekapital: 150000\nStyrelse: Adv Lars Samzelius\n(ordf), dir Bo G Anneli, dir Törd\nBergstedt\n\nVeikst dir: Bo G Anneli\nDisp: Stig Gröndahl\nEtableringsår: 1962.\n\nLAMINO AB\n\nPnr 260 90\n\nBåstad, Industriområdet. Tel\n0431-715 55, 715 56. Bankgiro 870-5915.\nPostgiro 38084-0\nVerksamhet: Tillverkar artiklar i\nglasfiberarmerad plast\nAntal anställda: 10\nÅrsomsättning: 600 000\nAktiekapital: 30 000\nPlatschef: Kamrer Stig Andersson\nEtableringsår: 1956.\n\nLAMKES FÖRSÄLJNINGS AB/\nLAMKESMASKINTEKNISKA AB\n\nPnr 11157\n\nStockholm, Sveav 17. Tel\n08-112347, 112348. Postgiro 403960.\nTga Maskinlamke\nVerksamhet: Tillverkar o\nprojekterar maskinutrustningar för\nspannmålsanläggningar, foderfabriker o\nkvarnar\n\nAntal anställda: 30\nÅrsomsättning: 9 000 000\nAktiekapital: 100 000\nVerkst dir: Sven Axelsson\nEtableringsår: 1944.\n\nLAMM MASKINAFFÄR,\nAB CARL\n\nPnr 103 64\n\nStockholm 3, Kungsg 29. Box 3236.\nTel 08-23 26 40. Postgiro 800. Tga\nCarllamm\n\nVerksamhet: Kontorsmaskiner m m\nAntal anställda: 190\nAktiekapital: 400 000\nVerkst dir: Lars Lamm\nEtableringsår: 1916.\n\nLAMMHULTS MEKANISKA\nVERKSTAD AB\n\nPnr 360 30\n\nLammhult, Box 26. Tel\n0472-607 20. Bankgiro 275-4109.\nPostgiro 299496-0\n\nVerksamhet: Stolar o bord för\noffentliga miljöer\nAntal anställda: 40\nÅrsomsättning: 5 000000\nAktiekapital: 200 0 00\nChef: Disp E Ståhl\nEtableringsår: 1945.\n\nSESAMPRINT AB\n\nPnr 200 41\n\nMalmö 8, Box 8090. Västmanlandsg\n3. Tel 040-88870, 887 91.\nBankgiro 641-2688. Postgiro 437384-1.\nTga Sesamprint\n\nVerksamhet: Säljer Sesam\nljuskopierings papper, Pen-Tex ritfilm\nAktiekapital: 25 000\nVerkst dir: Ing Henrik Olsson\nEtableringsån 1957.\n\nBENZLER &amp; CO AB\n\nPnr 171 22\n\nSolna 1, Box 1067. Centralv 1. Tel\n08-83 44 00. Bankgiro 17-1231.\nPostgiro 1793. Tga Transmission.\nTelex 19917\n\nVerksamhet: Allt inom\ntransmissionsbranschen\n\nFilialer. 41672 Göteborg, L\nMunke-bäcksg 6. Tel 031-25 00 80\n21135 Malmö, Djäkneg 4. Tel\n040-70275\n\nVarunamn: Centrax, Desch, Fenner,\nFluidrive, Godfrey, Köbo, Renk,\nSADI, Santasalo, Stopmaster,\nStromag, Sisu, Twin Disc,\nDuff-Nor-ton, Manifold, Bockwoldt\nAntal anställda: 75\nÅrsomsättning: 45 000 000\nAktiekapital: 500 000\nStyrelse: Dir Axel Benzler (ordf),\nBengt Benzler, Tage Lindholm\nVerkst dir: Bengt Benzler\nEtableringsår: 1944.\n\nE AG LAS, AB\n\nPnr 850 09\n\nSundsvall 9. Box 9015. Högomsg\n23. Tel 060-15 4960. Postgiro\n608140\n\nVerksamhet: Säljer glas i parti\nAktiekapital: 120 000\nVerkst dir: Leif Ryd\nEtableringsår: 1898.\n\nRAHMQVIST AB, ERIC\n\nPnr 17103\n\nSolna 3, Råsundav 15. Box 330.\nTel 08-83 43 30. Bankgiro 74-7414.\nPostgiro 6643\n\nVerksamhet: Specialartiklar inom\nkontorsmaterialbranschen\nVarunamn: Zenith\nAntal anställda: 49\nÅrsomsättning: 5 000 000\nAktiekapital: 50 000\nVerkst dir: Erie Rahmqvist\nEtableringsår: 1954.\n\nVerkst dlr: Byggn-ing Owe\nForss-berg\n\nEtableringsår: 1946.\n\nTORKELSON, AB RAGNVALD\n\nPnr 280 40\n\nSkånes Fagerhult, Box 74. Tel\n0433-303 89, 303 88. Bankgiro\n279-6548. Postgiro 348709-7. Tga\nTor-comp\n\nVerksamhet: Tillverkar stålrörs- o\nkompletteringsmöbler\nAntal anställda: 16\nÅrsomsättning: 4 500 000\nAktiekapital: 110 000\nVerkst dir: Fabr Ragnvald\nTorkelson\n\nEtableringsår: 1951.\n\nNÄTTRABY BRUKS AB\n\nPnr 37024\n\nNättraby, Box 38. Tel 0455-49010.\nTga Nettrabruk.\nTelex 43002 NAEBY S\nVerksamhet: Tillverkar\ncellulosavadd, facial tissue,\npappersservetter, torkdukar, pappersdukar o\nandra konverterade produkter\nAktiekapital: 75000\nStyrelse: Dlr F G Thulin (ordf),\ndir G Dahlsten\nVerkst din G Dahlsten\nPlastchef: Overing M Gedda\nKamrer: G Sandberg\nEtableringsår: 1941.",
    "structured": {
        "1": {
            "company_name": "BESON-TRYCK, AB",
            "pnr": "212 28",
            "address": "Malmö, Stålkuleg 3",
            "phone_number": "040-93 48 30",
            "bank_details": {
                "bankgiro": "641-0617",
                "postgiro": "148542-4"
            },
            "activity": "Reklam- o blanketttryck i boktryck o offset",
            "employees": 24,
            "capital": 150000,
            "key_personnel": [
                {
                    "name": "Elvir B Nilsson"
                }
            ],
            "establishment_year": 1951
        },
        "2": {
            "company_name": "LILUX BELYSNING AB",
            "pnr": "113 55",
            "address": "Stockholm, Roslagsg 4",
            "phone_number": "08-24 94 20",
            "bank_details": {
                "bankgiro": "11-8630",
                "postgiro": "459830"
            },
            "activity": "Engrosförsäljning o projektering av belysningsarmatur",
            "employees": 32,
            "annual_turnover": 6700000,
            "capital": 150000,
            "key_personnel": [
                {
                    "name": "Tga Luxannelli"
                }
            ],
            "establishment_year": 1962
        },
        "3": {
            "company_name": "LAMINO AB",
            "pnr": "260 90",
            "address": "Båstad, Industriområdet",
            "phone_number": "0431-715 55, 715 56",
            "bank_details": {
                "bankgiro": "870-5915",
                "postgiro": "38084-0"
            },
            "activity": "Tillverkar artiklar i glasfiberarmerad plast",
            "employees": 10,
            "annual_turnover": 600000,
            "capital": 30000,
            "key_personnel": [
                {
                    "name": "Kamrer Stig Andersson"
                }
            ],
            "establishment_year": 1956
        },
        "4": {
            "company_name": "LAMKES FÖRSÄLJNINGS AB/",
            "pnr": "11157",
            "address": "Stockholm, Sveav 17",
            "phone_number": "08-112347, 112348",
            "postgiro": "403960",
            "activity": "Tillverkar o projekterar maskinutrustningar för spannmålsanläggningar, foderfabriker o kvarnar",
            "employees": 30,
            "annual_turnover": 9000000,
            "capital": 100000,
            "key_personnel": [
                {
                    "name": "Sven Axelsson"
                }
            ],
            "establishment_year": 1944
        },
        "5": {
            "company_name": "LAMM MASKINAFFÄR, AB CARL",
            "pnr": "103 64",
            "address": "Stockholm 3, Kungsg 29, Box 3236",
            "phone_number": "08-23 26 40",
            "postgiro": "800",
            "activity": "Kontorsmaskiner m m",
            "employees": 190,
            "capital": 400000,
            "key_personnel": [
                {
                    "name": "Lars Lamm"
                }
            ],
            "establishment_year": 1916
        },
        "6": {
            "company_name": "LAMMHULTS MEKANISKA VERKSTAD AB",
            "pnr": "360 30",
            "address": "Lammhult, Box 26",
            "phone_number": "0472-607 20",
            "bank_details": {
                "bankgiro": "275-4109",
                "postgiro": "299496-0"
            },
            "activity": "Stolar o bord för offentliga miljöer",
            "employees": 40,
            "annual_turnover": 5000000,
            "capital": 200000,
            "key_personnel": [
                {
                    "name": "Disp E Ståhl"
                }
            ],
            "establishment_year": 1945
        },
        "7": {
            "company_name": "SESAMPRINT AB",
            "pnr": "200 41",
            "address": "Malmö 8, Box 8090, Västmanlandsg 3",
            "phone_number": "040-88870, 887 91",
            "bank_details": {
                "bankgiro": "641-2688",
                "postgiro": "437384-1"
            },
            "activity": "Säljer Sesam ljuskopieringspapper, Pen-Tex ritfilm",
            "capital": 25000,
            "key_personnel": [
                {
                    "name": "Ing Henrik Olsson"
                }
            ],
            "establishment_year": 1957
        },
        "8": {
            "company_name": "BENZLER & CO AB",
            "pnr": "171 22",
            "address": "Solna 1, Box 1067, Centralv 1",
            "phone_number": "08-83 44 00",
            "bank_details": {
                "bankgiro": "17-1231",
                "postgiro": "1793"
            },
            "activity": "Allt inom transmissionsbranschen",
            "employees": 75,
            "annual_turnover": 45000000,
            "capital": 500000,
            "key_personnel": [
                {
                    "name": "Bengt Benzler"
                }
            ],
            "establishment_year": 1944
        },
        "9": {
            "company_name": "E AG LAS, AB",
            "pnr": "850 09",
            "address": "Sundsvall 9, Box 9015, Högomsg 23",
            "phone_number": "060-15 4960",
            "postgiro": "608140",
            "activity": "Säljer glas i parti",
            "capital": 120000,
            "key_personnel": [
                {
                    "name": "Leif Ryd"
                }
            ],
            "establishment_year": 1898
        },
        "10": {
            "company_name": "RAHMQVIST AB, ERIC",
            "pnr": "17103",
            "address": "Solna 3, Råsundav 15, Box 330",
            "phone_number": "08-83 43 30",
            "bank_details": {
                "bankgiro": "74-7414",
                "postgiro": "6643"
            },
            "activity": "Specialartiklar inom kontorsmaterialbranschen",
            "employees": 49,
            "annual_turnover": 5000000,
            "capital": 50000,
            "key_personnel": [
                {
                    "name": "Erie Rahmqvist"
                }
            ],
            "establishment_year": 1954
        },
        "11": {
            "company_name": "TORKELSON, AB RAGNVALD",
            "pnr": "280 40",
            "address": "Skånes Fagerhult, Box 74",
            "phone_number": "0433-303 89, 303 88",
            "bank_details": {
                "bankgiro": "279-6548",
                "postgiro": "348709-7"
            },
            "activity": "Tillverkar stålrörs- o kompletteringsmöbler",
            "employees": 16,
            "annual_turnover": 4500000,
            "capital": 110000,
            "key_personnel": [
                {
                    "name": "Fabr Ragnvald Torkelson"
                }
            ],
            "establishment_year": 1951
        },
        "12": {
            "company_name": "NÄTTRABY BRUKS AB",
            "pnr": "37024",
            "address": "Nättraby, Box 38",
            "phone_number": "0455-49010",
            "activity": "Tillverkar cellulosavadd, facial tissue, pappersservetter, torkdukar, pappersdukar o andra konverterade produkter",
            "capital": 75000,
            "key_personnel": [
                {
                    "name": "G Dahlsten"
                }
            ],
            "establishment_year": 1941
        }
    }
}