{
    "original": "FULDA GUMMI AB\n\nPnr 13101\n\nNacka 1, Fack. Augustendalsv.\nTel 08-716 29 30: Bankgiro\n746-0470. Postgiro 571300-3. Telex\n10619\n\nVerksamhet: Generalagent för Fulda\nGummiwerke GMBH\nVarunamn: Fulda\nAktiekapital: 150000\nEtableringsår: 1960.\n\nFULLWOOD SWEDEN AB\n\nPrr 532 00\n\nSkara, Britagården. Tel\n0511-13170. Bankgiro 821-7671.\nPostgiro 288740-4\n\nVerksamhet: Säljer o installerar\nmjölkmas kinsanläggning ar\nAntal anställda: 7\nÅrsomsättning: 800000\nAktiekapital: 25 000\nVerkst dir: Sven Johan Persson\nEtableringsår: 1966.\n\nMADSEN, AB AXEL E\n\nPnr 820 32\n\nStugsund, Box 103. Tel\n0270-54122, 54111. Bankgiro 61-2619.\nPostgiro 36805.\nTga Madsen, Söderhamn.\nTelex 81019\n\nVerksamhet: Säljer kol, koks, o\nolja. Skeppsklarering.\nBefrakt-ningsagenter. Spedition\nAntal anställda: 10\nÅrsomsättning: 2 500000\nAktiekapital: 75 000\nStyrelse: Dir Thorsten Dunér\n(ordf), dir Arne Haverdahl\nVerkst dir: Skeppsmäkl Bror\nOhr-ner\n\nEtableringsår: 1896.\n\nKULLAPLAST AB\n\nPnr 263 00\n\nHöganäs. Tel 042-424 55. Bankgiro\n445-6133. Postgiro 671095-8\n\nVerksamhet: Tillverkar\nplastemballage (Polyeten)\nAntal anställda: 28\nÅrsomsättning: 5 000 000\nAktiekapital: 5000\nVerkst dir: Axel Skoglund\nEtableringsån 1965.\n\nDALABAGEIER, AB\n\nPnr 751 06\n\nUppsala, Box 395.Tel 018-139370.\nBankgiro 802-6536. Postgiro 8558-9\nVerksamhet: Tillverkar mjukbröd,\nkonditorivaror o skorpor\nAntal anställda: 376\nÅrsomsättning: 35 000 000\nAktiekapital: 1000 000\nVerkst dir: Nils Ljungkvist\nEtableringsår: 1950.\n\nLINDHOLM AB, AKE\n\nPnr 14146\n\nHuddinge, Dalhemsv 52. Tel\n08-7740165. BankgirS 74-6809.\nPostgiro 456242\n\nVerksamhet: Säljer självhäftande\netiketter för märkning, tejp av olika\nslag, dataetiketter samt filt i\nremsor o cirklar\nVarunamn: Brady\nÄgare och chef: Ake Lindholm\nEtableringsår: 1953.\n\nLINDKVIST, LINDQUIST,\nLINDQVIST\n\nLINDQUIST &amp; LARSSON, AB\n\nPnr 330 30\n\nGnosjö, Kapellg 4. Box 193. Tel\n0 370-9 10 68 , 9 12 8 2. Bankgiro\n542-4403. Postgiro 143126-1\nVerksamhet: Tillverkar damväskor,\nreklamartiklar, plånböcker,\nportmonnäer, skärp, etuier i läder o\nsvetsad plast. Utför\nbeställningsarbeten efter ritning eller prov i\nsvetsad plastfolie\nAntal anställda: 20\nÅrsomsättning: 1000 000\nAktiekapital: 24 000\nVerkst dir: Henry Lindquist\nEtableringsår: 1938\nOmbildat till aktiebolag 1957.\n\nLINDQVIST, MASKIN AB\nBRUDERNA\n\nPnr 783 00\n\nSäter, Box 5. Tel 0225-510 80.\nBankgiro 79-8722. Postgiro 98159.\nTga Lindsaw\n\nVerksamhet: Tillverkar o säljer\nsågverksmaskiner o -förnödenheter\nAntal anställda: 35\nÅrsomsättning: 3 000 000\nAktiekapital: 100 000\nVerkst dir: Nils Lindqvist\nEtableringsår: 1933\nOmbildat till aktiebolag 1953.\n\nLINDQUIST &amp; WAHL.\nST RUM, AB\n\nPnr 200 29\n\nMalmö 29, Box 29007. Tel\n040-49 06 40. Bankgiro 156-4251.\nPostgiro 38304-2\n\nVerksamhet: Tillverkar färger o\nfernissor\n\nAktiekapital: 300000\nVerkst dir: Bertil Wahlström\nEtableringsår: 1931.\n\nLINDQVISTS VERKSTÄDER\nAB, BRÖDERNA\n\nPnr 124 40\n\nBandhagen, Harpsundsv 211. Tel\n08-86 04 20. Bankgiro 57-3358.\nPostgiro 199915\n\nVerksamhet: Utför alla slag av\nmekaniska artjeten. Tillverkar\nkugghjul, snäckväxlaro växellådor.\nUtför kuggskärning o kuggslipning\nAntal anställda: 150\nÅrsomsättning: 10 000000\nAktiekapital: 300 000\nVerkst dir: Gunnar Emanuel\nLindqvist\n\nEtableringsår: 1943.\n\nLINDQVIST AB,\nCIVIL-INGENJÖR ARNE\n\nPnr 752 23\n\nUppsala, Stureg 20. Tel018-10 0030.\nBankgiro 230-3915. Postgiro\n579608-1\n\nVerksamhet: Rådgivande i\nbyggnadsteknik, utreder, projekterar o\nupprättar\nbyggnadskonstruktions-handlingar för bostäder, skolor,\nvårdanläggningar, kontors- o\naffärshus, sportanläggningar,\nindustrianläggningar m m\nAntal anställda: 16\n\nÅrsomsättning: 800000\nAktiekapital: 5 000\nVerkst dir: civiling Arne Lindqvist\nEtableringsår: 1965.\n\nGRAVYRBOLAGET\n\nPnr 41101\n\nGöteborg, Friggag 3. Tel\n031-1914 85. Postgiro 48410-5\nVerksamhet: Tillverkar o säljer\nskyltar, stämplar o bokstäver av\nalla slag\n\nChef: Fru Annalisa Johanneson\nEtableringsår: 1942.\n\nGREAT LAKESCARBON\nSWEDEN AB\n\nPnr 87101\n\nHärnösand 1, Varvsallén 13. Box\n220. Tel 0611-105 30. Bankgiro\n15-5659. Postgiro 715420. Telex 71278\nVerksamhet: Tillverkar syntetisk\ngrafit\n\nVarunamn: GLC-Sweden\nAntal anställda: 200\nAktiekapital: 22 000 000\nStyrelse: Dir Arend M Versteegh\n(ordf), bruksdisp Lars Edlund, dir\nGöran Philipson, dir Gunnar\nPersson, Mr Joseph G Solari, Mr Martin\nM Turban\n\nVerkst dir: Mr Chester Max\nPeterson\n\nProd-chef: Mr R E Chase\nTekn chef: Mr D S Meletiou\nEkonomichef: Civilek Ake Westling\nAnläggn-chef: Civiling Per\nSandström\n\nEtableringsår: 1967.\n\nSUBJECTORab\n\nPnr 112 32\n\nStockholm, Flemingg 59. Tel\n08-54 07 35, 53 70 35. Tga Subjector\nVerksamhet: Material för o\ntillverkning av inredningar i Apton\nbyggsystem. Textapparater\nAktiekapital: 50 000\nVerkst dir: B Bergendahl\nEtableringsår: 1962.\n\nTRANEMO TEXTIL AB\n\nPnr 510 80\n\nTranemo. Tel 0325-707 50.\nBankgiro 553-1355. Postgiro 88336-3\nVerksamhet: Konfektionsavdelning:\nUddabyxor i kommission.\nMaskinavdelning: Utför\nprecisionsarbeten i moderna\nverktygsmaskiner. Legotillverkning\nAntal anställda: 90\nÅrsomsättning: 3 000 000\nAktiekapital: 90 000\nVerkst din Gustav Kjöllerström\nEtableringsår: 1934.\n\nTRANEMO TRIKÅINDUSTRI\nAB\n\nPnr 510 80\n\nTranemo, Box 110. Tel\n0325-70191. Bankgiro 553-1363.\nPostgiro 77000-8\n\nVerksamhet: Tillverkar stickad\nyt-tertrikå för sport o fritid\nAntal anställda: 25\nAktiekapital: 30 000\nVerkst dir: Carl G Blåberg\nEtableringsår: 1945.\n\nÅBYGGE-VERKEN, AB\n\nPnr 805 90\n\nGävle 1, Postl 9324. Tel\n026-682 90\n\nVerksamhet: Kyldiskar, frysboxar,\nkylelement\nAktiekapital: 48 000\nVerkst dir: I Nordlund\nEtableringsår: 1953.\n\nÅDALENS INDUSTRI.\nSERVICE, AB\n\nPnr 87016\n\nRamvik, Box 33. Tel 0612^105 00,\n40100. Bankgiro 18-7024. Postgiro\n642390-9\n\nVerksamhet: Tillverkar alla slags\ntransportanordningar o vagnar för\nsågverks o cellulosaindustrien\nAntal anställda: 35\nÅrsomsättning: 2 500 000\nAktiekapital: 5 000\nÄgare o chefer R Näktergal, P O\nAndersson\n\nEtableringsår: 1963.\n\nLAR\n\nLARSSON, AB GUSTAF\n\nPnr 61101\n\nNyköping 1, V Storg 7-9. Box 154.\nTel 0155-17770. Bankgiro\n827-2239. Postgiro 11780\nVerksamhet: Säljer järn o stål,\nbyggvaror m m\nAktiekapital: 450 000\nVerkst dir. Gerhard Nilsson\nEtableringsår: 1890\nOmbildat tül aktiebolag 1919.\n\nLARSSON AB,\nMASKIN-FIRMA GÖSTA\n\nPnr 703 75\n\nÖrebro, Kyrkv 52. Tel 019-23 28 74,\n23 28 75. Bankgiro 471-6411.\nPostgiro 118306-0\n\nVerksamhet: Säljer HYSTER\ngaffeltruckar o CROWN staplare o\nlyffc-vagnar samt begagnade maskiner.\nMaskinuthyrning. Serviceverkstad\no fältservice. Auktoriserad Hyster\nservice o försäljning\nAntal anställda: 12\nÅrsomsättning: 1200 000\nAktiekapital: 100 000\nVerkst dir: Gösta Larsson\nEtableringsår 1944.\n\nLARSON, AFFÄRSREKLAM\nGOTE\n\nPnr 602 26\n\nNorrköping, Kristinag 7. Tel\n011-12 5859. Bankgiro 79-8133.\nPost-giro 214150\n\nVerksamhet: Tillverkar\nentreprenörsskyltar till byggnadsplatser,\nutställningsreklam o\nutställningsmontrar m m\nAntal anställda: 4\nChef: Göte Larson\nEtableringsår: 1930.\n\nLARSON, BYGGNADS AB\nHERMAN\n\nPnr 152 00\n\nSträngnäs, Trädgårds g 23. Tel\n0152-128 70. Bankgiro 602-8260. Postgiro\n140444-1\n\nVerksamhet: Byggnadsrörelse o\n\nfastighetsförvaltning\n\nAntal anställda: 70\n\nÅrsomsättning: 5 000 000\n\nAktiekapital: 100 000\n\nStyrelse: Byggmäst Herman Larson\n\n(ordf), ing Carl-Herman Larson,\n\nkamrer Nils Larson\n\nVerkst dir: Ing Carl-Herman Larson\n\nKamrer Nils Larson\n\nEtableringsår: 1933\n\nOmbildat till aktiebolag 1968.\n\nLARSSON &amp; CO, AB K G\n\nPnr 580 03\n\nLinköping 3, Gillbergag. Box 3055.\nTel 013-13 0310. Bankgiro\n120-1284. Postgiro 268808-3\nVerksamhet: Engrosförsäljning av\nindustriförnödenheter, speciellt\ntill byggnadsbranschen\nAntal anställda: 7\nÅrsomsättning: 1500 000\nAktiekapital: 34 000\nStyrelse: Disp Bertil Johansson\n(ordf), försäljn-chef Roland\nLarsson, byggmäst Erling Sandberg\nVerkst dir: Bertil Johansson\nEtableringsår: 1945.\n\nLARSSON KONTORSMASKINER\nAB, K G\n\nPnr 701 04\n\nÖrebro 1, Stortorget 15. Box 317.\nTel 019-11 95 50. Bankgiro\n815-7315. Postgiro 97230-7. Tga Koge\nVerksamhet: Säljer\nkontorsmaskiner o kontorsmöbler\nAntal anställda: 11\nÅrsomsättning: 1800 000\nAktiekapital: 60000\nVerkst dir: Karl Gustav Larsson\nEtableringsår: 1933.\n\nLARSSON &amp; CO BYGGNADS\nAB, L JOH\n\nPnr 413 01\n\nGöteborg SV, N Allëg 5. Tel\n031-17 5280. Bankgiro 50-8819.\nPost&gt;-giro 42671\n\nVerksamhet: Entreprenader inom\nbyggnadsbranschen\nAntal anställda: 163\nÅrsomsättning: 17 079 000\nAktiekapital: 108 000\nVerkst dir: Sten Carlsson\nEtableringsår: 1933.\n\nLARSSON TRYCKERI AB,\nLUDVIG\n\nPnr 701 03\n\nÖrebro 1, Skvadronv 7 A. Box 180.\nTel 019-1136 44, 13 2044.\nBankgiro 614-7169. Postgiro 397381-5\nVerksamhet: Blanketter, reklam,\netiketter, tidningar o böcker i\nboktryck o offset\nAntal anställda: 17\nÅrsomsättning: 1000 000\nAktiekapital: 35 000\nVerkst dir: A Lindqvist\nEtableringsår: 1924.\n\nLARSSONS BORST, o PENSEL.\nFABRIK, AB M\n\nPnr 270 40\n\nOnslunda, Box 107. Tel 0417-300 02,\n302 02. Bankgiro 287-0657.\nPostgiro 30003-8. Tga Borstakongen\nVerksamhet: Tillverkar borstvalsar\nför textil- o pappersindustrin,\nhushushålls- o stålborstar, penslar\nVarunamn: Borstakongen\nAntal anställda: 42\nAktiekapital: 50 000\nVerkst dir: Sigurd Larsson\nExportchef: Ewe Larsson\nEtableringsår: 1875.",
    "structured": {
        "1": {
            "company_name": "FULDA GUMMI AB",
            "address": "Nacka 1, Fack. Augustendalsv.",
            "phone_number": "08-716 29 30",
            "bank_details": {
                "bankgiro": "746-0470",
                "postgiro": "571300-3"
            },
            "activity": "Generalagent för Fulda Gummiwerke GMBH",
            "capital": 150000,
            "establishment_year": 1960
        },
        "2": {
            "company_name": "FULLWOOD SWEDEN AB",
            "address": "Skara, Britagården",
            "phone_number": "0511-13170",
            "bank_details": {
                "bankgiro": "821-7671",
                "postgiro": "288740-4"
            },
            "activity": "Säljer o installerar mjölkmaskinsanläggningar",
            "employees": 7,
            "annual_turnover": 800000,
            "capital": 25000,
            "key_personnel": [
                {
                    "name": "Sven Johan Persson",
                    "position": "Verkst dir"
                }
            ],
            "establishment_year": 1966
        },
        "3": {
            "company_name": "MADSEN, AB AXEL E",
            "address": "Stugsund, Box 103",
            "phone_number": "0270-54122, 54111",
            "bank_details": {
                "bankgiro": "61-2619",
                "postgiro": "36805"
            },
            "activity": "Säljer kol, koks, o olja. Skeppsklarering. Befraktningsagenter. Spedition",
            "employees": 10,
            "annual_turnover": 2500000,
            "capital": 75000,
            "key_personnel": [
                {
                    "name": "Thorsten Dunér",
                    "position": "ordf"
                },
                {
                    "name": "Arne Haverdahl",
                    "position": "dir"
                },
                {
                    "name": "Skeppsmäkl Bror Ohr-ner",
                    "position": "Verkst dir"
                }
            ],
            "establishment_year": 1896
        },
        "4": {
            "company_name": "KULLAPLAST AB",
            "address": "Höganäs",
            "phone_number": "042-424 55",
            "bank_details": {
                "bankgiro": "445-6133",
                "postgiro": "671095-8"
            },
            "activity": "Tillverkar plastemballage (Polyeten)",
            "employees": 28,
            "annual_turnover": 5000000,
            "capital": 5000,
            "key_personnel": [
                {
                    "name": "Axel Skoglund",
                    "position": "Verkst dir"
                }
            ],
            "establishment_year": 1965
        },
        "5": {
            "company_name": "DALABAGEIER, AB",
            "address": "Uppsala, Box 395",
            "phone_number": "018-139370",
            "bank_details": {
                "bankgiro": "802-6536",
                "postgiro": "8558-9"
            },
            "activity": "Tillverkar mjukbröd, konditorivaror o skorpor",
            "employees": 376,
            "annual_turnover": 35000000,
            "capital": 1000000,
            "key_personnel": [
                {
                    "name": "Nils Ljungkvist",
                    "position": "Verkst dir"
                }
            ],
            "establishment_year": 1950
        },
        "6": {
            "company_name": "LINDHOLM AB, AKE",
            "address": "Huddinge, Dalhemsv 52",
            "phone_number": "08-7740165",
            "bank_details": {
                "bankgiro": "74-6809",
                "postgiro": "456242"
            },
            "activity": "Säljer självhäftande etiketter för märkning, tejp av olika slag, dataetiketter samt filt i remsor o cirklar",
            "key_personnel": [
                {
                    "name": "Ake Lindholm",
                    "position": "Ägare och chef"
                }
            ],
            "establishment_year": 1953
        },
        "7": {
            "company_name": "LINDKVIST, LINDQUIST, LINDQVIST LINDQUIST & LARSSON, AB",
            "address": "Gnosjö, Kapellg 4, Box 193",
            "phone_number": "0 370-9 10 68 , 9 12 8 2",
            "bank_details": {
                "bankgiro": "542-4403",
                "postgiro": "143126-1"
            },
            "activity": "Tillverkar damväskor, reklamartiklar, plånböcker, portmonnäer, skärp, etuier i läder o svetsad plast. Utför beställningsarbeten efter ritning eller prov i svetsad plastfolie",
            "employees": 20,
            "annual_turnover": 1000000,
            "capital": 24000,
            "key_personnel": [
                {
                    "name": "Henry Lindquist",
                    "position": "Verkst dir"
                }
            ],
            "establishment_year": 1957
        },
        "8": {
            "company_name": "LINDQVIST, MASKIN AB BRUDERNA",
            "address": "Säter, Box 5",
            "phone_number": "0225-510 80",
            "bank_details": {
                "bankgiro": "79-8722",
                "postgiro": "98159"
            },
            "activity": "Tillverkar o säljer sågverksmaskiner o -förnödenheter",
            "employees": 35,
            "annual_turnover": 3000000,
            "capital": 100000,
            "key_personnel": [
                {
                    "name": "Nils Lindqvist",
                    "position": "Verkst dir"
                }
            ],
            "establishment_year": 1953
        },
        "9": {
            "company_name": "LINDQUIST & WAHL. ST RUM, AB",
            "address": "Malmö 29, Box 29007",
            "phone_number": "040-49 06 40",
            "bank_details": {
                "bankgiro": "156-4251",
                "postgiro": "38304-2"
            },
            "activity": "Tillverkar färger o fernissor",
            "capital": 300000,
            "key_personnel": [
                {
                    "name": "Bertil Wahlström",
                    "position": "Verkst dir"
                }
            ],
            "establishment_year": 1931
        },
        "10": {
            "company_name": "LINDQVISTS VERKSTÄDER AB, BRÖDERNA",
            "address": "Bandhagen, Harpsundsv 211",
            "phone_number": "08-86 04 20",
            "bank_details": {
                "bankgiro": "57-3358",
                "postgiro": "199915"
            },
            "activity": "Utför alla slag av mekaniska artjeten. Tillverkar kugghjul, snäckväxlaro växellådor. Utför kuggskärning o kuggslipning",
            "employees": 150,
            "annual_turnover": 10000000,
            "capital": 300000,
            "key_personnel": [
                {
                    "name": "Gunnar Emanuel Lindqvist",
                    "position": "Verkst dir"
                }
            ],
            "establishment_year": 1943
        },
        "11": {
            "company_name": "LINDQVIST AB, CIVIL-INGENJÖR ARNE",
            "address": "Uppsala, Stureg 20",
            "phone_number": "018-10 0030",
            "bank_details": {
                "bankgiro": "230-3915",
                "postgiro": "579608-1"
            },
            "activity": "Rådgivande i byggnadsteknik, utreder, projekterar o upprättar byggnadskonstruktions-handlingar för bostäder, skolor, vårdanläggningar, kontors- o affärshus, sportanläggningar, industri-anläggningar m m",
            "employees": 16,
            "annual_turnover": 800000,
            "capital": 5000,
            "key_personnel": [
                {
                    "name": "civiling Arne Lindqvist",
                    "position": "Verkst dir"
                }
            ],
            "establishment_year": 1965
        },
        "12": {
            "company_name": "GRAVYRBOLAGET",
            "address": "Göteborg, Friggag 3",
            "phone_number": "031-1914 85",
            "postgiro": "48410-5",
            "activity": "Tillverkar o säljer skyltar, stämplar o bokstäver av alla slag",
            "key_personnel": [
                {
                    "name": "Fru Annalisa Johanneson",
                    "position": "Chef"
                }
            ],
            "establishment_year": 1942
        },
        "13": {
            "company_name": "GREAT LAKESCARBON SWEDEN AB",
            "address": "Härnösand 1, Varvsallén 13, Box 220",
            "phone_number": "0611-105 30",
            "bank_details": {
                "bankgiro": "15-5659",
                "postgiro": "715420"
            },
            "activity": "Tillverkar syntetisk grafit",
            "employees": 200,
            "capital": 22000000,
            "key_personnel": [
                {
                    "name": "Arend M Versteegh",
                    "position": "ordf"
                },
                {
                    "name": "Lars Edlund",
                    "position": "bruksdisp"
                },
                {
                    "name": "Göran Philipson",
                    "position": "dir"
                },
                {
                    "name": "Gunnar Persson",
                    "position": "dir"
                },
                {
                    "name": "Joseph G Solari",
                    "position": "Mr"
                },
                {
                    "name": "Martin M Turban",
                    "position": "Mr"
                }
            ],
            "key_personnel_2": [
                {
                    "name": "Chester Max Peterson",
                    "position": "Verkst dir"
                }
            ],
            "key_personnel_3": [
                {
                    "name": "R E Chase",
                    "position": "Prod-chef"
                },
                {
                    "name": "D S Meletiou",
                    "position": "Tekn chef"
                },
                {
                    "name": "Ake Westling",
                    "position": "Ekonomichef"
                },
                {
                    "name": "Per Sandström",
                    "position": "Anläggn-chef"
                }
            ],
            "establishment_year": 1967
        },
        "14": {
            "company_name": "SUBJECTORab",
            "address": "Stockholm, Flemingg 59",
            "phone_number": "08-54 07 35, 53 70 35",
            "activity": "Material för o tillverkning av inredningar i Apton byggsystem. Textapparater",
            "capital": 50000,
            "key_personnel": [
                {
                    "name": "B Bergendahl",
                    "position": "Verkst dir"
                }
            ],
            "establishment_year": 1962
        },
        "15": {
            "company_name": "TRANEMO TEXTIL AB",
            "address": "Tranemo",
            "phone_number": "0325-707 50",
            "bank_details": {
                "bankgiro": "553-1355",
                "postgiro": "88336-3"
            },
            "activity": "Konfektionsavdelning: Uddabyxor i kommission. Maskinavdelning: Utför precisionsarbeten i moderna verktygsmaskiner. Legotillverkning",
            "employees": 90,
            "annual_turnover": 3000000,
            "capital": 90000,
            "key_personnel": [
                {
                    "name": "Gustav Kjöllerström",
                    "position": "Verkst dir"
                }
            ],
            "establishment_year": 1934
        }
    }
}