{
    "original": "TONÉ-DORREN, AB\n\nPnr 330 26\n\nSmålands Burseryd, Hällabäck.\nTel 0371-52010. Bankgiro\n550-7116. Postgiro 98388-2\nVerksamhet: Tillverkar alla slags\ndörrar för ut- o invändigt bruk\nAntal anställda: 8\nÅrsomsättning: 500 000\nAktiekapital: 25 000\nVerkst dir: Gösta Norenfors\nEtableringsår: 1880\nOmbildat till aktiebolag 1955.\n\nTONI.LEE AB\n\nPnr 281 00\n\nHässleholm, Kristianstadsv. Tel\n0451-140 80. Bankgiro 344-9105.\nPostgiro 282098-3\nVerksamhet: Tillverkar yrkesplagg\ni terylene o nylon\nAntal anstäUda: 150\nÅrsomsättning: 7 000 000\nAktiekapital: 50000\nVerkst dir Bertil Jönsson\nEtableringsår 1947.\n\nSVENSKA HOECHST AB\n\nPnr 402 20\n\nGöteborg 5, Fack.Göteborgsv 91 B,\nMölndal. Tel 031-27 52 80. Bankgiro\n501-2224. Postgiro 40981-3. Tga\nHoechstanilin. Telex 2275\n\nVerksamhet: Bolaget säljer som\ngeneralagent för Farbwerke Hoeehst\nAG, Frankfurt (MVHoechst,\nVästtyskland: Anilinfärger,\ntextilhjälpmedel, växer, syntetisk borst,\nkemikalier, läkemedel, plaster,\nsyntetfibrer, folier, växtskydds- o\ngödselmedel etc. Tillverkar vid fabrik i\nMölndal (Gbgs o Bohus 1)\nljusko-pieringspapper o ljuskänslig väv,\nsamt säljer ljuskopieringsmaskiner,\nfärdigprep offsetplåtar (Ozasol) o\napparatur för grafiska branschen\nAvdelningskontor: Borås,\nOster-långg 63. Tel 033-12 5141, 12 59 41\n212 11 Malmö, Fredriksbergsg 16.\nTel 040-775 50. Telex 32509\n126 12 Stockholm 42, Box 42026.\nVretensborgsv 14, Hägersten. Tel\n08-19 00 70. Telex 10456\nReprokontor: Stockholm.\nVretensborgsv 14, pa Hägersten. Tel\n08-19 00 60\n\nStockholm, Braheg 49. Citylager.\nTel 08-23 14 25\n\n212 28 Malmö, Knivg 8. Tel\n040-93 53 50\n\n902 45 Umeå, Kungsg 133. Tel\n090-1160 20\n\nVarunamn: Albamit, Alberit,\nAlpo-lit, Blàkorn, Cellophan, Dolan,\nFrigen, Genolon K, Genopak,\nGeno-therm, Guttagena, Hostadur,\nHosta-flex, Hostaflon, Hostaform,\nHostalen, Hostalit, Hostaphan, Hostyren,\nIsogenopac, Mowilith, Mowiol,\nMo-wital, Ozalid, Ozasol, Suprathen,\nSupronyl, Trespaphan, Tre vira,\nTrevira hochfest\nAntal anställda: 278\nAktiekapital: 4 000 000\nStyrelse: Dir Nils Ljungdahl(ordf),\nciviling Sixten Arnold, dir Ernst\nMueller, dir Dieter zur Loye, adv\nGösta Sjögren, dir K-H Spilker,\nadv Gösta Åkerlund\nVerkst dir: Civiling Sixten Arnold.\n\nSVENSKA HOOVER AB\n\nPnr 171 36\n\nSolna. Dalv 12. Tel 08-83 0640.\nBankgiro 330-6008. Postgiro\n681910-6. Tga Hooverab.\nTelex 10749 HOOVER S\nVerksamhet: Köper, säljer o\ndistribuerar hushållsapparater till\nåter-fösäljare runtom i landet\nFilial: 413 03 Göteborg, Första\nLångg 22. Tel 031-42 02 75\nVarunamn: Hoover\nEtableringsår: 1957.\n\nSVE\n\nSVENSKA MASKIN.\nAFFÄREN AB\n\nPnr 33101\n\nVärnamo 1, Postg 3. Box 68. Tel\n0370-115 00. Bankgiro 542-5509.\nPostgiro 30426-1. Tga\nMaskinaffären. Telex 70055 MACHINE S\nVerksamhet: Försäljning av\nverktygsmaskiner, plåtbearbetningsma-skiner samt verktyg o\nindustriutrustningar\nAntal anställda: 70\nÅrsomsättning: 35 000 000\nAktiekapital: 100 000\nVerkst dir: Anton Johansson\nEtableringsår: 1912.\n\nSVENSKA MASKINSKYLT.\nFABRIKEN, AB\n\nPnr 58104\n\nLinköping 1, Oskarsg 3. Box 386.\nTel 013-13 0180. Bankgiro\n120-1193. Postgiro 28283-0. Tga\nMaskinskyltar\n\nVerksamhet: Etsade, tryckta,\nfärg-eloxerade, graverade o gjutna\nme-tallskyltar, skalor o\ninstrumenttavlor. Klichéanstalt\nFilial: Stockholm C, Kungsg 65.\nTel 08-20 39 03- Chef: H E\nLiljestrand\n\nAntal anställda: 75\nÅrsomsättning: 3 000 000\nAktiekapital: 65 000\nVerkst dir: Axel Karlsson\nEtableringsår: 1916.\n\nSVENSKA MASKINVERKEN, AB\n\nse Svenska Järnvägsverkstäderna,\nAB.\n\nSVENSKA MEDIMEKANIK, AB\n\nPnr 460 10\n\nLödöse, Box 7. Tel 0520-604 00.\nBankgiro 412-3162.\nTelex 2428 OTERED S\nVerksamhet: Tillverkning av\nartiklar inom medicinska området\n.Antal anställda: 6\nAktiekapital: 10 000\nStyrelse: Gösta Johansson, Gösta\nGullmarstrand.\n\nSVENSKA MEJERI.ARTIKLAR\n\nPnr 41253\n\nGöteborg, Berzeliig 15. Tel\n031-18 08 84. Bankgiro 362-7304.\nPostgiro 40403-8\n\nVerksamhet: Säljer\nmejeriprepara-ter o förnödenheter engros\nChef: Erik Johansson\nEtableringsår: 1936.\n\nSVENSKA MEJERIERNAS\nRIKSFÖRENING (SMR)\n\nPnr 10110\n\nStockholm 1, Vasag 16. Fack. Tel\n08-23 87 00. Bankgiro 330-0282.\nPostgiro 56299-1. Tga\nRiksmejerier. Telex 1333 BUTTER S\nVerksamhet: Riksorganisation för\nden lantbrukskooperativa\nmejeriindustrin, Handlägger\nmejeriindustrins centrala branschkontakter\nmed myndigheter o andra organisar\ntioner, forskning o produktteknisk\nverksamhet, organisationsfrågor,\ncentrala marknadsföringsåtgärder.\n\nsmörhandel, export av\nmejeriprodukter m m\nAntal anställda: 216\nÅrsomsättning: 325 000 000\nStyrelseordf: Bengt O Edlund\nVerkst dir: Bengt Dock\nEtableringsår: 1932.\n\nSVENSKA METALL.\nVERKEN, AB\n\nse Gränges och Gränges Essem AB.\n\nSVENSKA MOLYKOTE AB\n\nPnr 114 35\n\nStockholm, Grev Tureg 2. Tel\n08-219960. Bankgiro 731-6912.\nPost-giro 559225-8. TgaMolykote\nVerksamhet: Säljer smörjmedel på\nmolybdendisulfidbas, Dow Corning\nsilikonsmörjmedel\nFilialer: 412 62 Göteborg,\nFridkullag 2. Tel 031-18 10 60\nVarunamn: Dow Corning, Molykote\nAktiekapital: 120 000\nVerkst din Börje österlind\nEtableringsår: 1958.\n\nVERRINA, AB\n\nPnr 560 23\n\nBankeryd. Tel 036-772 50. Bankgiro\n83-6963. Postgiro 581167. Tga\nVerrina, Jönköping\nVerksamhet: Tillverkar moderna\ndörrhandtag av glas o plast\nAktiekapital: 45 000\nStyrelse: Dir Bigge Miller (ordf),\ndir Torsten Hansson, fru\nMargareta Lundquist\nVerkst dir: Torsten Hansson\nEtableringsår: 1963.\n\nLANTBRUKSKEMI, AB\n\nPnr 21137\n\nMalmö, Fabriksg 2 B. Tel\n040-615 76. Bankgiro 689-9215. Postr\ngiro 530771-5. Tga Lantbrukskemi\nVerksamhet: Kemisk analys\nAntal anställda: 3\nÅrsomsättning: 80 000\nAktiekapital: 5 000\nVerkst dir: Frih Ove Barnekow\nEtableringsår: 1946.\n\nLANTMÄNNENS CENTRAL.\nFURENING I JÖNKÖPING\nU P A\n\nPnr 550 02\n\nJönköping 2, O Strandg 3. Box\n2178. Tel 036-1196 60. Bankgiro\n34-1944. Postgiro 11624. Tga\nCentralförening\n\nVerksamhet: Handel med\njordbruksprodukter\n\nAntal anställda: 197\nÅrsomsättning: 74 596 000\nInsatskapital: 4 556 000\nVerkst dir: Nils R Skoog\nEtableringsår: 1909.\n\nLANTMÄNNENS CENTRAL.\nFÖRENING I KALMAR,\nEK FOR\n\nPnr 38101\n\nKalmar 1, N Långg 1. Box 126. Tel\n0480-224 00. Bankgiro 853-6419.\nPostgiro 29476-9\n\nVerksamhet: Kraftfoder,\nkonstgödsel, spannmål, potatis,\nlantbruksmaskiner, byggnadsvaror, oljor\nm m\n\nAntal anställda: 411\nÅrsomsättning: 116 000 000\nVerkst dir: K G H:son Bergström\nEtableringsår: 1942.\n\nUNA\n\nVerksamhet: Tillverkar\nbleckem-ballage för livsmedels-, färg- o\nkemisk tekniska industrin\nAntal anställda: 35\nÅrsomsättning: 6 000 000\nÄgare o chefer: Fabr Ragnar\nSvensson, fabr Lars Petersson\nEtableringsår: 1907.\n\nULRICEHAMNS\nKARTONGFABRIK. AB\n\nPnr 523 00\n\nUlricehamn, Boråsv 30 B. Tel\n0321-105 03\n\nVerksamhet: Tillverkar\nförpackningskartonger av alla sorter\nAktiekapital: 15 000\nFirmatecknare: Ake Markbrant,\nRune Lindgren\nEtableringsår: 1935\nOmbildat till aktiebolag 1941.\n\nULRICEHAMNS KON FE K.\nTIONSINDUSTRI, AB\n\nPnr 523 00\n\nUlricehamn, Boråsv 30 B. Box 117.\nTel 0321-123 50. Bankgiro 84-4229.\nPostgiro 143753\nVerksamhet: Tillverkar o säljer\nherr- o juniorkostymer\nAktiekapital: 50 000\nVerkst dir: Gustav Svensson\nEtableringsår: 1937.\n\nLUN\n\nVerksamhet: Entreprenörer för väg-,\nvatten- o brobyggnader,\nflygfältsarbeten samt hus- o industribyggnad\nAntal anställda: 1057\nÅrsomsättning: 130 000000\nAktiekapital: 2000 000\nVerkst dir: Civiling Anders\nGruvstad\n\nEtableringsår: 1895\nOmbildat till aktiebolag 1935.\n\nLUNDH, AB RUNE\n\nPnr 240 13\n\nGenarp. Tel 040-48 03 80. Tga\nRunius. Telex 32267\nVerksamhet: Grossist inom\nköttbranschen, export o import (även\ntarmar o livsmedelsmaskiner)\nAntal anställda: 40\nÅrsomsättning: 25000 000\nAktiekapital: 120 000\nVerkst dir: Rune Lundh\nEtableringsår: 1953.\n\nSMIDESBOLAGET\n\nPnr 778 02\n\nNorberg 2. Box 2313. Tel\n0223-21130. Postgiro 105877\nVerksamhet: Tillverkar o säljer\ntrapp- o balkongräcken\nAntal anstäUda: 6\nÄgare: Ake Bergström\nEtableringsår. 1956.\n\nBASTMAN, AB GEORG A\n\nPnr 114 34\n\nStockholm, Nybrog 1. Tel\n08-10 75 90, 1075 05. Postgiro 3689-7.\nTga Sportmagasinet\nVerksamhet: Säljer vapen,\namuni-tion o fiskredskap\nAntal anställda: 15\nÅrsomsättning: 2100000\nAktiekapital: 88 000\nVerkst dir: Fru Anna-Lisa\nDit-zinger\n\nEtableringsår: 1877.\n\nPRESS &amp; SON, AB L\n\nPnr 16111\n\nBromma 11, Ranhammarsv 9. Box\n11080. Tel 08-80 30 60. Bankgiro\n567-5673. Postgiro 58541-4\nVerksamhet: Tillverkar o exporterar\nelektr linjemateriel såsom\navgre-ningsklämmor o kabelskor, rör o\nrörfästen för båttäckning,\ninredningar m m. Plastpresenningar.\nAl-profiler för utställningar,\ninredningar o montrar. Utför\nlegoarbeten\n\nVarunamn: Kilfästet, Syma-System\nAntal anställda: 5\nÅrsomsättning: 500 000\nAktiekapital: 35 000\nChef: Gunnar Press\nEtableringsår: 1934.",
    "structured": {
        "0": {
            "company_name": "TONÉ-DORREN, AB",
            "pnr": "330 26",
            "address": "Smålands Burseryd, Hällabäck.",
            "phone_number": "0371-52010",
            "bank_details": {
                "bankgiro": "550-7116",
                "postgiro": "98388-2"
            },
            "activity": "Tillverkar alla slags dörrar för ut- o invändigt bruk",
            "employees": 8,
            "annual_turnover": 500000,
            "capital": 25000,
            "key_personnel": [
                {
                    "name": "Gösta Norenfors",
                    "position": "Verkst dir"
                }
            ],
            "establishment_year": 1880
        },
        "1": {
            "company_name": "TONI.LEE AB",
            "pnr": "281 00",
            "address": "Hässleholm, Kristianstadsv.",
            "phone_number": "0451-140 80",
            "bank_details": {
                "bankgiro": "344-9105",
                "postgiro": "282098-3"
            },
            "activity": "Tillverkar yrkesplagg i terylene o nylon",
            "employees": 150,
            "annual_turnover": 7000000,
            "capital": 50000,
            "key_personnel": [
                {
                    "name": "Bertil Jönsson",
                    "position": "Verkst dir"
                }
            ],
            "establishment_year": 1947
        },
        "2": {
            "company_name": "SVENSKA HOECHST AB",
            "pnr": "402 20",
            "address": "Göteborg 5, Fack.Göteborgsv 91 B, Mölndal",
            "phone_number": "031-27 52 80",
            "bank_details": {
                "bankgiro": "501-2224",
                "postgiro": "40981-3"
            },
            "activity": "Bolaget säljer som generalagent för Farbwerke Hoeehst AG, Frankfurt (MVHoechst, Västtyskland: Anilinfärger, textilhjälpmedel, växer, syntetisk borst, kemikalier, läkemedel, plaster, syntetfibrer, folier, växtskydds- o gödselmedel etc. Tillverkar vid fabrik i Mölndal (Gbgs o Bohus 1) ljusko-pieringspapper o ljuskänslig väv, samt säljer ljuskopieringsmaskiner, färdigprep offsetplåtar (Ozasol) o apparatur för grafiska branschen",
            "employees": 278,
            "annual_turnover": null,
            "capital": 4000000,
            "key_personnel": [
                {
                    "name": "Dir Nils Ljungdahl",
                    "position": "Styrelseordf"
                },
                {
                    "name": "civiling Sixten Arnold",
                    "position": "Styrelse"
                },
                {
                    "name": "dir Ernst Mueller",
                    "position": "Styrelse"
                },
                {
                    "name": "dir Dieter zur Loye",
                    "position": "Styrelse"
                },
                {
                    "name": "adv Gösta Sjögren",
                    "position": "Styrelse"
                },
                {
                    "name": "dir K-H Spilker",
                    "position": "Styrelse"
                },
                {
                    "name": "adv Gösta Åkerlund",
                    "position": "Styrelse"
                }
            ],
            "establishment_year": null
        },
        "3": {
            "company_name": "SVENSKA HOOVER AB",
            "pnr": "171 36",
            "address": "Solna. Dalv 12",
            "phone_number": "08-83 0640",
            "bank_details": {
                "bankgiro": "330-6008",
                "postgiro": "681910-6"
            },
            "activity": "Köper, säljer o distribuerar hushållsapparater till åter-fösäljare runtom i landet",
            "employees": null,
            "annual_turnover": null,
            "capital": null,
            "key_personnel": null,
            "establishment_year": 1957
        },
        "4": {
            "company_name": "SVENSKA MASKIN. AFFÄREN AB",
            "pnr": "33101",
            "address": "Värnamo 1, Postg 3. Box 68",
            "phone_number": "0370-115 00",
            "bank_details": {
                "bankgiro": "542-5509",
                "postgiro": "30426-1"
            },
            "activity": "Försäljning av verktygsmaskiner, plåtbearbetningsma-skiner samt verktyg o industriutrustningar",
            "employees": 70,
            "annual_turnover": 35000000,
            "capital": 100000,
            "key_personnel": [
                {
                    "name": "Anton Johansson",
                    "position": "Verkst dir"
                }
            ],
            "establishment_year": 1912
        }
    }
}