{
    "original": "NORDSTROM &amp; TINGGREN AB\n\nPnr 42122\n\nVästra Frölunda 1, Lërgöksg 12.\nBox 122. Tel 031-49 03 60.\nTga Tinggrens. Telex 2578\nVerksamhet: Försäljningsbolag för\nGrycksbo Pappersbruk,\nPapyrusbruken o Munkedals AB,\nFinpapper engros\n\nAgent- o grosshandelsrörelse i\nemballage- o förbrukningsartiklar\nKontor: 20013 Malmö 27, Vinkelg\n15. Box 27039. Tel 040-180810.\nTelex 32451\nAntal anställda: 95\nÅrsomsättning: 100 000 000\nAktiekapital: 900 000\nVerkst dir: Gunnar Wennerström\nEtableringsår: 1873.\n\nRUNELANDHS MASKINER AB\n\nPnr 381 00\n\nKalmar, N vägen 8. Tel 0480-159 40.\nTga Runmas\n\nVerksamhet: Säljer snickeri-,\nhyvleri- o sågverksmaskiner\nAktiekapital: 200 000\nDisp: Einar Franzén\nEtableringsår: 1932.\n\nIND\n\nINDUSTRIAVFALL I SUNDS.\nVALL AB\n\nPnr 852 37\n\nSundsvall, Sidsjöv 4. Tel\n060-1258 10\n\nVerksamhet: Inköp o bearbetning\nav jäm-, metall- o glasskrot,\ntextil-, plast-, gummi- o pappersavfall.\nBedriver även handel med begagnad\nmateriel\n\nFilialer: 95100 Luleå, Banv. Tel\n0920-24490\n\n79200 Mora. Box 127. Tel\n0250-36162, 136 58\nAntal anstäUda: 30\nAktiekapital: 500 000\nEtableringsår: 1965\nAv Persöner AB, Ystad, delägt\nföretag.\n\nINDUSTRIAVFALL\nSODERGREN &amp; SVENSSON AB\n\nPnr 302 50\n\nHalmstad, Svetsareg 8. Tel\n035-12 36 90, 122141. Bankgiro 53-0346\nPostgiro 511802\nVerksamhet: Köper skrotavfall,\npappersavfall, textilier o metaller\nFüial: Anderstorp. Anderstorps\nMetall o Råvaruhandel AB. Tel\n0371-15950\n\nAktiekapital: 20 000\nFirmatecknare: F O Södergren,\nH A Svensson\nEtableringsår. 1958.\n\nALMQUIST &amp; CO AB, JAN\n\nPnr 25103\n\nHelsingborg 1, Box 193. Bruksg 22.\nTel 042-13 70 11. Bankgiro\n642-2232. Postgiro 713733-4\nVerksamhet: Tillverkar o säljer\nalla slags vykort o reklambilder.\nAccidenstryck, lagerförda vykort\nAntal anställda: 9\n\nAktiekapital: 3C000\nVerkst dir: Jan Y Almquist\nEtableringsår: 1968.\n\nJACOBSON &amp; WIDMARK, AB\n\nPnr 18133\n\nLidingö, Stockholmsv 18. Tel\n08-76700 60. Bankgiro 62-7424.\nPostgiro 155386. Telex 17184 JWLI S\nVerksamhet:\nByggnadskonstruktioner o geoteknik\nAktiekapital: 450 000\nVerkst dir. Civiling Folke\nJacobson\n\nEtableringsår: 1937.\n\nINCENTIVE AB\n\nPnr 11147\n\nStockholm, Arsenalsg 4. Tel\n08-23 45 00. Bankgiro 161-1631. Tga\n\nIncentive\n\nVeiksamhet: Utvecklingsbolag\nÅrsomsättning: 850 000000\n(koncernen)\n\nAktiekapital: 64 94 0 000\nVeikst dir: Sten Gustafsson\nEtableringsår: 1963.\n\nGRAVE AB, RUDOLPH\n\nPnr 171 20\n\nSolna 1, Pyramidv 9. Pack. Tel\n08-83 00 80. Postgiro 1456. Telex\n10515. Tga Grave\nVerksamhet:\nLaboratorieutrustningar, vågar\nAntal anställda: 110\nÅrsomsättning: 20 000000\nAktiekapital: 2 000 000\nVerkst dir: K E Larsson\nEtableringsår: 1874.\n\nBJERNERSJO MEKANISKA AB\n\nPnr 595 00\n\nMjölby, Box 180. Kyrkog 15. Tel\n0142-109 18, 14462. Bankgiro\n128-4256. Postgiro 321361-8\nVerksamhet: Tillverkar\nsopmaskiner o skogskranar\nVarunamn: Bemab\nAntal anställda: 15\nÅrsomsättning: 1500 000\nAktiekapital: 20 000\nVerkst dir: Erie Bjernersjö\nEtableringsår: 1962.\n\nHEURLINS REKLAM AB\n\nPnr 162 20\n\nVällingby, Jämtlandsg 153 A. Tel\n08-37 70 00,37 7001. Bankgiro\n56-3617. Postgiro 51647\nVerksamhet:\nScreentryck-utställ-ningar\n\nAntal anställda: 11\nÅrsomsättning: 1000 000\nAktiekapital: 20 000\nVerkst dir: Alf Heurlin\nEtableringsår: 1949.\n\nROCHE.PRODUKTER AB\n\nPnr 102 41\n\nStockholm 5, Nybrog 30. Box 5006.\nTel 08-67 05 60. Bankgiro 170-1457.\nPostgiro 156443-4. Tga Hofroche.\nTelex 10729\n\nVerksamhet: Säljer farmacevtiska\npreparat, vitaminprodukter,\nfinke-mikalier o kosmetika\nAntal anställda: 35\nAktiekapital: 250000\nStyrelse: Adv Erik Felländer (ordf),\ndr A W Jann, dir Lennart Westman\nVerkst dir: Lennart Westman\nEtableringsår: 1939\nDotterbolag till F Hoffmann-La\nRoche &amp; Co AG, Basel, Schweiz.\n\nROCKHAMMARS BRUKS AB\n\nPnr 710 40\n\nFrövi. Tel 0581-702 00. Bankgiro\n463-1271. Postgiro 75910-0.\nTga Rockhammar, Lindesberg.\nTelex 73409 ROCKHAM S\nVerksamhet: Tillverkar mekanisk\npappersmassa, porös wallboard, sår\ngade o hyvlade trävaror samt\nmonteringsfärdiga hus\nVarunamn: Rockhammar Board\nAntal anställda: 220\nÅrsomsättning: 30000 000\nAktiekapital: 1500 000\nStyrelse: Dir A C Ahrel (ordf), ing\nI Ahrel, dir Kurt Hellström, adv\nLars Sjöberg, disp Arne Melin\nVerkst dir Ing I Ahrel\nEtableringsån 1895\nOmbildat till aktiebolag 1917.\nBruket grundat under 1500-talet.\n\nROCKNER COMPANY AB\n\nPnr 310 40\n\nHarplinge. Tel 035-524 55, 525 94.\nBankgiro 434-2333. Postgiro\n241066-0\n\nVerksamhet: Tillverkar o säljer\ntransportkylaggregat o frysaggregat\nför såväl butiksvagnar,\ndistributionsvagnar som vagnar för\nhängande last. Inreder o isolerar\nbutiksvagnar\n\nVerkst din Sonja Åberg\nVerkstadschef: Ing Vallis Åberg\nEtableringsår: 1938.",
    "structured": {
        "1": {
            "company_name": "NORDSTROM & TINGGREN AB",
            "pnr": "42122",
            "address": "Västra Frölunda 1, Lërgöksg 12. Box 122",
            "phone_number": "031-49 03 60",
            "bank_details": {
                "bankgiro": "Tga Tinggrens",
                "postgiro": "Telex 2578"
            },
            "activity": "Försäljningsbolag för Grycksbo Pappersbruk, Papyrusbruken o Munkedals AB, Finpapper engros",
            "employees": 95,
            "annual_turnover": 100000000,
            "capital": 900000,
            "key_personnel": [
                {
                    "name": "Gunnar Wennerström",
                    "position": "Verkst dir"
                }
            ],
            "establishment_year": 1873
        },
        "2": {
            "company_name": "RUNELANDHS MASKINER AB",
            "pnr": "381 00",
            "address": "Kalmar, N vägen 8",
            "phone_number": "0480-159 40",
            "bank_details": {
                "bankgiro": "Tga Runmas"
            },
            "activity": "Säljer snickeri-, hyvleri- o sågverksmaskiner",
            "capital": 200000,
            "key_personnel": [
                {
                    "name": "Einar Franzén",
                    "position": "Disp"
                }
            ],
            "establishment_year": 1932
        },
        "3": {
            "company_name": "INDUSTRIAVFALL I SUNDS. VALL AB",
            "pnr": "852 37",
            "address": "Sundsvall, Sidsjöv 4",
            "phone_number": "060-1258 10",
            "activity": "Inköp o bearbetning av jäm-, metall- o glasskrot, textil-, plast-, gummi- o pappersavfall. Bedriver även handel med begagnad materiel",
            "employees": 30,
            "capital": 500000,
            "establishment_year": 1965
        },
        "4": {
            "company_name": "SODERGREN & SVENSSON AB",
            "pnr": "302 50",
            "address": "Halmstad, Svetsareg 8",
            "phone_number": "035-12 36 90, 122141",
            "bank_details": {
                "bankgiro": "53-0346",
                "postgiro": "511802"
            },
            "activity": "Köper skrotavfall, pappersavfall, textilier o metaller",
            "capital": 20000,
            "key_personnel": [
                {
                    "name": "F O Södergren",
                    "position": "Firmatecknare"
                },
                {
                    "name": "H A Svensson",
                    "position": "Firmatecknare"
                }
            ],
            "establishment_year": 1958
        },
        "5": {
            "company_name": "ALMQUIST & CO AB, JAN",
            "pnr": "25103",
            "address": "Helsingborg 1, Box 193. Bruksg 22",
            "phone_number": "042-13 70 11",
            "bank_details": {
                "bankgiro": "642-2232",
                "postgiro": "713733-4"
            },
            "activity": "Tillverkar o säljer alla slags vykort o reklambilder. Accidenstryck, lagerförda vykort",
            "employees": 9,
            "capital": 30000,
            "key_personnel": [
                {
                    "name": "Jan Y Almquist",
                    "position": "Verkst dir"
                }
            ],
            "establishment_year": 1968
        },
        "6": {
            "company_name": "JACOBSON & WIDMARK, AB",
            "pnr": "18133",
            "address": "Lidingö, Stockholmsv 18",
            "phone_number": "08-76700 60",
            "bank_details": {
                "bankgiro": "62-7424",
                "postgiro": "155386"
            },
            "activity": "Byggnadskonstruktioner o geoteknik",
            "capital": 450000,
            "key_personnel": [
                {
                    "name": "Civiling Folke Jacobson",
                    "position": "Verkst dir"
                }
            ],
            "establishment_year": 1937
        },
        "7": {
            "company_name": "INCENTIVE AB",
            "pnr": "11147",
            "address": "Stockholm, Arsenalsg 4",
            "phone_number": "08-23 45 00",
            "bank_details": {
                "bankgiro": "161-1631"
            },
            "activity": "Utvecklingsbolag",
            "annual_turnover": 850000000,
            "capital": 64940000,
            "key_personnel": [
                {
                    "name": "Sten Gustafsson",
                    "position": "Verkst dir"
                }
            ],
            "establishment_year": 1963
        },
        "8": {
            "company_name": "GRAVE AB, RUDOLPH",
            "pnr": "171 20",
            "address": "Solna 1, Pyramidv 9. Pack",
            "phone_number": "08-83 00 80",
            "postgiro": "1456",
            "activity": "Laboratorieutrustningar, vågar",
            "employees": 110,
            "annual_turnover": 20000000,
            "capital": 2000000,
            "key_personnel": [
                {
                    "name": "K E Larsson",
                    "position": "Verkst dir"
                }
            ],
            "establishment_year": 1874
        },
        "9": {
            "company_name": "BJERNERSJO MEKANISKA AB",
            "pnr": "595 00",
            "address": "Mjölby, Box 180. Kyrkog 15",
            "phone_number": "0142-109 18, 14462",
            "bank_details": {
                "bankgiro": "128-4256",
                "postgiro": "321361-8"
            },
            "activity": "Tillverkar sopmaskiner o skogskranar",
            "employees": 15,
            "annual_turnover": 1500000,
            "capital": 20000,
            "key_personnel": [
                {
                    "name": "Erie Bjernersjö",
                    "position": "Verkst dir"
                }
            ],
            "establishment_year": 1962
        },
        "10": {
            "company_name": "HEURLINS REKLAM AB",
            "pnr": "162 20",
            "address": "Vällingby, Jämtlandsg 153 A",
            "phone_number": "08-37 70 00,37 7001",
            "bank_details": {
                "bankgiro": "56-3617"
            },
            "activity": "Screentryck-utställ-ningar",
            "employees": 11,
            "annual_turnover": 1000000,
            "capital": 20000,
            "key_personnel": [
                {
                    "name": "Alf Heurlin",
                    "position": "Verkst dir"
                }
            ],
            "establishment_year": 1949
        },
        "11": {
            "company_name": "ROCHE.PRODUKTER AB",
            "pnr": "102 41",
            "address": "Stockholm 5, Nybrog 30. Box 5006",
            "phone_number": "08-67 05 60",
            "bank_details": {
                "bankgiro": "170-1457",
                "postgiro": "156443-4"
            },
            "activity": "Säljer farmacevtiska preparat, vitaminprodukter, finke-mikalier o kosmetika",
            "employees": 35,
            "capital": 250000,
            "key_personnel": [
                {
                    "name": "Lennart Westman",
                    "position": "Verkst dir"
                }
            ],
            "establishment_year": 1939
        },
        "12": {
            "company_name": "ROCKHAMMARS BRUKS AB",
            "pnr": "710 40",
            "address": "Frövi",
            "phone_number": "0581-702 00",
            "bank_details": {
                "bankgiro": "463-1271",
                "postgiro": "75910-0"
            },
            "activity": "Tillverkar mekanisk pappersmassa, porös wallboard, sårgade o hyvlade trävaror samt monteringsfärdiga hus",
            "employees": 220,
            "annual_turnover": 30000000,
            "capital": 1500000,
            "key_personnel": [
                {
                    "name": "Ing I Ahrel",
                    "position": "Verkst dir"
                }
            ],
            "establishment_year": "1895. Ombildat till aktiebolag 1917. Bruket grundat under 1500-talet"
        },
        "13": {
            "company_name": "ROCKNER COMPANY AB",
            "pnr": "310 40",
            "address": "Harplinge",
            "phone_number": "035-524 55, 525 94",
            "bank_details": {
                "bankgiro": "434-2333",
                "postgiro": "241066-0"
            },
            "activity": "Tillverkar o säljer transportkylaggregat o frysaggregat för såväl butiksvagnar, distributionsvagnar som vagnar för hängande last. Inreder o isolerar butiksvagnar",
            "key_personnel": [
                {
                    "name": "Sonja Åberg",
                    "position": "Verkst din"
                },
                {
                    "name": "Ing Vallis Åberg",
                    "position": "Verkstadschef"
                }
            ],
            "establishment_year": 1938
        }
    }
}