{
    "original": "ARBOGA HÅRDKROM AB\n\nPnr 732 00\n\nArboga, Jädersv. Tel 0589-135 30,\n15175. Bankgiro 80-9867.\nPostgiro 38 94 39\n\nVerksamhet: Specialfirma för\nhårdkrom\n\nAntal anställda: 25\nVerkst dir Nils Mattson\nEtableringsår: 1949.\n\nARBOGA KVARN &amp;\nMALT-FABRIK, AB\n\nPnr 732 00\n\nArboga, Hamng 5. Tel 0589-102 38\nVerksamhet: Framställer malt\nAktiekapital: 226 250\nEtableringsår: 1821.\n\nFKI KONSULTER AB\n\nPnr 117 28\n\nStockholm, Hornsg 124. Tel 08-\n\n69 0250\n\nVerksamhet: Konsulterande\nverksamhet inom VVS-facket\nAntal anstäUda: 70\nÅrsomsättning: 5 000 000\nAktiekapital: 20 000\nVerkst dir. Carl Åbom.\n\nFLAGGCENTER AB\n\nPnr 117 43\n\nStockholm, Årsta Skolgränd 4. Tel\n08-18 03 25. Bankgiro 63-2995.\nPostgiro 357171\n\nVerksamhet: Tillverkar flaggor o\nflaggstänger.\n\nFLAKING AB\n\nPnr 691 03\n\nKarlskoga, Maskinv 8. Tel\n0586-328 10. 328 25. Postgiro 687490-3\nVerksamhet: Tillverkar\npersonbilsläpkärror\nAntal anstäUda: 8\nÅrsomsättning: 700 000\nAktiekapital: 5 000\nVerkst dir: Bertil Granlund\nEtableringsår: 1952.\n\nRAGNERT AB MOSSFABRIK, E\n\nPnr 211 43\n\nMalmö, S Förstadsg 16. Tel\n040-34123. Bankgiro 348-4078.\nPostgiro 37735-8\n\nVerksamhet: Konfektionering av\ndamhattar o dammössor\nAntal anstäUda: 20\nÅrsomsättning: 800 000\nAktiekapital: 50 000\nVerkst dir: Erie Ragnert\nEtableringsår: 1956.\n\nJUNESCO, AB\n\nPnr 280 70\n\nLönsboda. Tel 0479-205 00.\nBankgiro 279-3180. Tga Junesco\nVerksamhet: Tillverkar herr- o\ndamkonfektion: rockar, kappor etc\nAntal anställda: 225\nÅrsomsättning: 15100 000\nVerkst dir: Henrik Carlén.\n\nJUNEX KONFEKTIONS AB\n\nPnr 56101\n\nHuskvarna 1, Box 55. Tel\n036-13 27 00. Bankgiro 835-6222.\nPostgiro 5477-5. Tga Junex.\nTelex 70023\n\nVeiksamhet: Tillverkar kostymer,\njackets, uddabyxor, rockar, kappor\nAntal anställda: 750\nÅrsomsättning: 40 000 000 (inkl\ndotterbolag)\nAktiekapital: 5 000 000\nVerkst dir: Henrik Carlén\nEtableringsår: 1927.\n\nERIKSSON &amp; CO, AB KNUT\n\nPnr 78101\n\nBorlänge 1, Box 139. Tel\n0243-390 65. Bankgiro 794-5744.\nPost&gt;-giro 160895-9\n\nVerksamhet: Konstruerar o säljer\ngrus- o sorteringsanläggningar\nAktiekapital: 50 000\nVerkst dir: Ing Birger Swahn\nEtableringsår: 1898.\n\nELTJÄNST I LIDKÖPING AB\n\nPnr 531 00\n\nLidköping, Kållandsg 24. Tel\n0.510-250 10. Postgiro 172875\nVerksamhet: Säljer o reparerar\nmotorer o transformatorer\nAntal anställda: 6\nAktiekapital: 70 000\nVerkst dir: Nils Gustafsson\nEtableringsår: 1940.\n\nELVOMETER AB,\nINGENJÖRSFIRMAN\n\nPnr 14145\n\nHuddinge, Kvarnbergsv 29. Tel\n08-757 02 00, 757 4000. Bankgiro\n73-0211. Postgiro 194307. Tga\nElvometer\n\nVerksamhet: Meteorologiska\ninstrument\n\nAntal anställda: 15\nAktiekapital: 100 000\nVerkst dir: Bo Lönnstedt\nEtableringsår: 1942.\n\nASPLUND AB, S 0\n\nPnr 412 73\n\nGöteborg, Berggrensg 12. Tel\n031-40 28 02, 40 28 04. Bankgiro 32-9690.\nPostgiro 610300\n\nVerksamhet: Projektering av\nbyggnadsverk. Databehandling\nAntal anställda: 6\nÅrsomsättning: 1000 000\nAktiekapital: 20000\nVerkst dir: Prof S O Asplund\nEtableringsår: 1966.\n\nLAGERSTEDT &amp; KRANTZ AB\n\nPnr 16113\n\nBromma 13, Slaggv 6. Box 1347.\nTel 08-26 29 20. Telex 1458. Tga\nJärnkrantz\n\nVerksamhet: Agenturaffär o\ngrosshandel i VVS\n\nAvdelningskontor: Göteborg H,\nStålverksg 9. Tel 031-51 33 00\nMalmö. Box 18061, Malmö 18. Tel\n040-49 17 15\nAntal anställda: 25\nAktiekapital: 50 000\nFirmatecknare: A Behm, L\nSchu-berth\n\nEtableringsår: 1933.\n\nMELBERGS MASKIN AB\n\nPnr 73104\n\nKöping 4, Box 35. Tel 0221-321 70.\nBankgiro 60-6823. Postgiro 471423.\nTga Melmab\n\nVerksamhet: Köper o säljer\nbegagnade sågverks- o snickerimaskiner\nAntal anställda: 11\nÅrsomsättning: 2 500 000\nChef: Dir Herbert Melberg\nEtableringsår: 1945.\n\nMELCRO AB, INGENIDRS.\nFIRMA\n\nPnr 172 06\n\nSundbyberg 6, Vackra v 14. Box\n605. Tel 08-29 98 78, 29 98 95.\nBankgiro 743-5738. Postgiro\n352231-5. Tga Ingmelcro\nVerksamhet: Importerar o säljer\npa-ketströmställare, elektro-kompo-nenter, elektromotorer\nÅrsomsättning: 750 000\nAktiekapital: 50 000\nVerkst dir: Ing Curt Cronelöv\nEtableringsår: 1948\nOmbildat till aktiebolag 1961.\n\nMELINS METALLGJUTERI AB\n\nPnr 330 20\n\nAnderstorp, Box 105. Norra v 5.\nTel 0371-16115. Bankgiro\n488-1058. Postgiro 28797-9\n\nSoffgruppen\nSpecialiti\n\nGjutgods för oljebrännare,\nskyltar,trädgirdsmöbler, mm.\nPressgjutning i zink och\naluminium.\n\nTillverkning av conneccors ’\n\nFormsprutning i plast METALL\n\nVerksamhet: Hand-, kokill- o\nmaskinformat gjutgods i aluminium.\nKapacitet 25 ton per vecka\nAntal anställda: 50\nÅrsomsättning: 4 000 000\nAktiekapital: 150 000\nVerkst dir: Sixten Melin\nEtableringsår: 1908\nOmbildat till aktiebolag 1951.\n\nMELINS BURSFABRIK, AB A\n\nPnr 330 20\n\nAnderstorp. Tel 0371-16155.\nBankgiro 488-0456. Postgiro 70113-6\nVerksamhet: Tillverkar o säljer\nbälten, livremmar, plånböcker,\nport-monnäer, etuier, portföljer, väskor,\nreklamartiklar m m\nAntal anstäUda: 90\nÅrsomsättning: 6 000 000\nAktiekapital: 120 000\nVerkst dir: Erik Melin\nEtableringsår: 1886.\n\nVÄR\n\nVerkst dlr: Civiling Anders\nGranström\n\nEtableringsår. 1963.",
    "structured": {
        "1": {
            "company_name": "ARBOGA HÅRDKROM AB",
            "pnr": "732 00",
            "address": "Arboga, Jädersv.",
            "phone_number": "0589-135 30",
            "bank_details": {
                "bankgiro": "80-9867",
                "postgiro": "38 94 39"
            },
            "activity": "Specialfirma för hårdkrom",
            "employees": 25,
            "key_personnel": [
                {
                    "name": "Nils Mattson",
                    "position": "Verkst dir"
                }
            ],
            "establishment_year": 1949
        },
        "2": {
            "company_name": "ARBOGA KVARN & MALT-FABRIK, AB",
            "pnr": "732 00",
            "address": "Arboga, Hamng 5",
            "phone_number": "0589-102 38",
            "activity": "Framställer malt",
            "capital": 226250,
            "establishment_year": 1821
        },
        "3": {
            "company_name": "FKI KONSULTER AB",
            "pnr": "117 28",
            "address": "Stockholm, Hornsg 124",
            "phone_number": "08-69 0250",
            "activity": "Konsulterande verksamhet inom VVS-facket",
            "employees": 70,
            "annual_turnover": 5000000,
            "capital": 20000,
            "key_personnel": [
                {
                    "name": "Carl Åbom",
                    "position": "Verkst dir"
                }
            ]
        },
        "4": {
            "company_name": "FLAGGCENTER AB",
            "pnr": "117 43",
            "address": "Stockholm, Årsta Skolgränd 4",
            "phone_number": "08-18 03 25",
            "bank_details": {
                "bankgiro": "63-2995",
                "postgiro": "357171"
            },
            "activity": "Tillverkar flaggor o flaggstänger"
        },
        "5": {
            "company_name": "FLAKING AB",
            "pnr": "691 03",
            "address": "Karlskoga, Maskinv 8",
            "phone_number": "0586-328 10, 328 25",
            "bank_details": {
                "postgiro": "687490-3"
            },
            "activity": "Tillverkar personbilsläpkärror",
            "employees": 8,
            "annual_turnover": 700000,
            "capital": 5000,
            "key_personnel": [
                {
                    "name": "Bertil Granlund",
                    "position": "Verkst dir"
                }
            ],
            "establishment_year": 1952
        },
        "6": {
            "company_name": "RAGNERT AB MOSSFABRIK, E",
            "pnr": "211 43",
            "address": "Malmö, S Förstadsg 16",
            "phone_number": "040-34123",
            "bank_details": {
                "bankgiro": "348-4078",
                "postgiro": "37735-8"
            },
            "activity": "Konfektionering av damhattar o dammössor",
            "employees": 20,
            "annual_turnover": 800000,
            "capital": 50000,
            "key_personnel": [
                {
                    "name": "Erie Ragnert",
                    "position": "Verkst dir"
                }
            ],
            "establishment_year": 1956
        },
        "7": {
            "company_name": "JUNESCO, AB",
            "pnr": "280 70",
            "phone_number": "0479-205 00",
            "bank_details": {
                "bankgiro": "279-3180"
            },
            "activity": "Tillverkar herr- o damkonfektion: rockar, kappor etc",
            "employees": 225,
            "annual_turnover": 15100000,
            "key_personnel": [
                {
                    "name": "Henrik Carlén",
                    "position": "Verkst dir"
                }
            ]
        },
        "8": {
            "company_name": "JUNEX KONFEKTIONS AB",
            "pnr": "56101",
            "address": "Huskvarna 1, Box 55",
            "phone_number": "036-13 27 00",
            "bank_details": {
                "bankgiro": "835-6222",
                "postgiro": "5477-5"
            },
            "activity": "Tillverkar kostymer, jackets, uddabyxor, rockar, kappor",
            "employees": 750,
            "annual_turnover": 40000000,
            "capital": 5000000,
            "key_personnel": [
                {
                    "name": "Henrik Carlén",
                    "position": "Verkst dir"
                }
            ],
            "establishment_year": 1927
        },
        "9": {
            "company_name": "ERIKSSON & CO, AB KNUT",
            "pnr": "78101",
            "address": "Borlänge 1, Box 139",
            "phone_number": "0243-390 65",
            "bank_details": {
                "bankgiro": "794-5744",
                "postgiro": "160895-9"
            },
            "activity": "Konstruerar o säljer grus- o sorteringsanläggningar",
            "capital": 50000,
            "key_personnel": [
                {
                    "name": "Ing Birger Swahn",
                    "position": "Verkst dir"
                }
            ],
            "establishment_year": 1898
        },
        "10": {
            "company_name": "ELTJÄNST I LIDKÖPING AB",
            "pnr": "531 00",
            "address": "Lidköping, Kållandsg 24",
            "phone_number": "0.510-250 10",
            "bank_details": {
                "postgiro": "172875"
            },
            "activity": "Säljer o reparerar motorer o transformatorer",
            "employees": 6,
            "capital": 70000,
            "key_personnel": [
                {
                    "name": "Nils Gustafsson",
                    "position": "Verkst dir"
                }
            ],
            "establishment_year": 1940
        }
    }
}