{
    "original": "ATLAS, BIL-AB\n\nPnr 330 20\n\nAnderstorp. Tel 0371-16160.\nBankgiro 488-0118. Postgiro 468411-4\n\nVerksamhet: Tillverkar\nbiltillbehör o verktyg, försäljning en gros\nAktiekapital: 100 000\nFirmatecknare: G A E Johansson,\nO S J Svenningson\nEtableringsår: 1951.\n\nVÄS\n\n56050. Bankgiro 812-8241.\nPost-giro 661114-9\n\nVerksamhet: Montering av\nprofilerad plåt\n\nAntal anställda: 13\nÅrsomsättning: 700 000\nAktiekapital: 10 000\nVerkst dir: Stig Johansson\nEtableringsår: 1966.\n\nallbo möbler ab\n\nPnr 340 21\n\nDiö, Box 207. Tel 0476-210 81,\n210 25. Bankgiro 276-1096.\nPostgiro 140200-7\n\nVerksamhet: Tillverkar\nkompletteringsmöbler\nAntal anställda: 23\nÅrsomsättning: 1000 000\nAktiekapital: 30 000\nVerkst dir: Göte Nilsson\nEtableringsår: 1945.\n\nalleghenu-longdoz\nSVENSKA AB\n\nPnr 412 85\n\nGöteborg. Mölndalsv 85. Tel\n031-16 1180. Bankgiro 405-3442.\nTelex 21180 ALLEGDOZ S\nVerksamhet: Försäljer rostfri plåt\no specialkvaliteter i rostfritt\nVarunamn: HWT, MF-I, OR-I\nVerkst dir: Ing Sven Olof Lundahl.\n\nallehanda, tryckeri ab\n\nPnr 23101\n\nTrelleborg 1, Box 73. Osterg\n29-31. Tel 04 1 0-150 55. Bankgiro\n352-4949. Postgiro 28000-8. Tga\nAllehanda. Telex 32959\nVerksamhet: Framställer\nfacktidskrifter o böcker\nAntal anställda: 90\nAktiekapital: 50 000\nVerkst dir: Robert Ohlsson\nEtableringsår: 1908.\n\nallektro ab,\ningenjörs-firman\n\nPnr 113 30\n\nStockholm, Gävleg 10. Tel\n08-30 23 56, 33 55 28. Tga Allektro\nVerksamhet: Säljer elektr motorer\no apparater\nAktiekapital: 15 000\nVerkst dir: Ing Boris Palasoff\nEtableringsår: 1942.\n\nFORSSA BRUKS AKTIEBOLAG\n\nPnr 820 64\n\nNäsviken, Box 44. Tel 0650-304 00.\nBankgiro 78-7019. Postgiro 8008.\nTgaForssån. Telex 8227\nVerksamhet: Tillverkar papp,\nkartong, transportförpackningar av\nsolid papp samt idkar\nskogshantering. Försäljningen av\ntransportförpackningar av solid papp\nhand-haves av dotterföretaget AB\nKraftbox, Näsviken\nAntal anstäUda: 225\nÅrsomsättning: 25 000 000\nAktiekapital: 2 650000\nStyrelse: Dir Esbjörn Ulfsäter\n(ordf), hemmansägare Anders\nLarsson, avd-chef Nils Sjöberg, disp\nGösta Holm, disp Rune Eriksson,\ndir Pär Svensson\nVerkst din Dir Pär Svensson\nEkonomichef: Kamrer Sture Jönsson\nEtableringsår: 1868.\n\nKARDBESLAG, AB\n\nPnr 600 06\n\nNorrköping 6, Lindöv 21-23. Box\n6053. Tel 011-13 40 60. Telex\n64118. Tga Kardbeslag\nVerksamhet: Tillverkar kardbeslag\no textilförnödenheter\nAntal anställda: 120\nÅrsomsättning: 7 000 000\nAktiekapital: 1000 000\nVerkst dir: J Hübner\nEtableringsår: 1921.\n\nITE FABRIKS AB\n\nPnr 23 9 00\n\nOlofström, Box 35. Tel\n0454-404 25. Bankgiro 151-7028.\nPostgiro 674330-6\n\nVerksamhet: Tillverkar pressade\nplåtartiklar, snabbspännen m m\nAntal anställda: 15\n\nIVE\n\nÅrsomsättning: 1500 000\nAktiekapital: 70 000\nVerkst dir. Hans Rasmusson\nEtableringsår: 1950.\n\nRES\n\nRestaurangchef: Sven Palmkvist\nKongresschef: Elling Carlström\nEkonomichef: Olle Törngren\nEtableringsàr: 1704.\n\nRESTAURANGROULETTER, AB\n\nPnr 171 38\n\nSolna, Ràsundav 121. Tel\n08-83 3 2 00 , 27 60 00. Bankgiro\n501-5946. Postgiro 626200-0\nVetksamhet: Uthyrning o\nförsäljning av rouletter, spelautomater,\nförströelsespel samt black jack\no bingo\n\nVerkst dir: Ing Bill Lindwall\nKamrer: Gunnar Norlander\nAktiekapital: 35000\nÅrsomsättning: 9000 000\nAntal anställda: 1 200\nEtableringsàr: 1963.\n\nRESTAURANTFDRNUDEN.\nHETER\n\nPnr 416 64\n\nGöteborg, Ranängsg 5-7. Tel\n031-19 1 8 92, 19 0 7 41. Bankgiro\n848-4917. Postgiro 162417\nVerksamhet: Engrofirma i glas,\nporslin, linne, papper, silver,\nrost-fritt, möbler, maskiner o\nköksutensilier\n\nÄgare o chef: Ralph Glimnell\nEtableringsàr: 1934.\n\nRESTAURATORERNAS\nINKUPS AB\n\nPnr 114 38\n\nStockholm, Grev Tureg 57. Tel\n08-63 18 80. Bankgiro 235-1898.\nPostgiro 53320-8. Tga\nRestaurant-inköp\n\nVerksamhet: Försäljning till hotell\no restauranger av samtlig utrustning\n(ej livsmedel)\n\nFilial: Malmö C, Stortorget 13. Tel\n040-12 51 51\nAntal anställda: 18\nÅrsomsättning: 5000 000\nAktiekapital: 180 400\nStyrelse: Dir Nils H Hedström\n(ordf), dlr Lars Ernmark\nVerkst din Lars Ernmaik\nEtableringsàr: 1931\nOmbildat till aktiebolag 1946.\n\nRESTERODS TRIKÅ AB\n\nPnr 450 10\n\nLjungskile, Box 38. Tel\n0522-206 20. Bankgiro 426-2200.\nPostgiro 37487-6\n\nVerksamhet: Tillverkar herr- o\ngossunderkläder\nAntal anställda: 46\nÅrsomsättning: 2500 000\nAktiekapital: 150 000\nVerkst dir. Karl A Mattsson\nEtableringsàr: 1934.\n\nREUTERFELDT,\nCARL-FREDRIK\n\nPnr 402 22\n\nGöteborg 5, Wadmansg 4, Box 5087.\nTel 031-16 34 05. Bankgiro\n847-7390. Postgiro 47906-3\nVetksamhet: Säljer lyftklorna\n\"Bul-dog\", tubpressar, molybdenisulfid\n\"Molypan\", oljeståndsglas\n\"Plexo-dan\"\n\nÄgare o chef: Carl-Fredrik\nReu-terfeldt\n\nEtableringsàr: 1935.\n\nREUTERSBERGS TRÄ.\nFDRÄDLING\n\nPnr 510 90\n\nLimmared. Tel 0325-430 07, 430 17.\nBankgiro 63-3564. Postgiro 281564\nVerksamhet: Hyvelbänkar,\nsouvenirer, hushållsartiklar i serier\nÄgare o chef: Fru E Lundgren\nEtableringsàr: 1942.\n\nREVENUE VÄSKINDUSTRI AB\n\nPnr 57020\n\nBodafors, Box 18. Tel 0380-300 06,\n300 26. Bankgiro 144-0304.\nPostgiro 196019-4\n\nVerksamhet: Tillverkar o säljer\ndamväskor o reseffekter\nAntal anställda: 12\nÅrsomsättning: 600 000\nAktiekapital: 80 000\nVerkst dir: E Lind\nEtableringsàr: 1944.\n\nREVISIONSBYRÅER\n\nse resp namn.\n\nREX, AB MASKINFABRIKEN\n\nPnr 30103\n\nHalmstad 1, Box 111. Skansg 3.\nTel 035-11 80 90. Bankgiro 42-3605.\nPostgiro 32466. TgaMaskinrex\nVerksamhet: Tillverkar cyklar,\nmopeder. Utför mekaniska arbeten\nVarunamn: Rex\nAntal anställda: 125\nÅrsomsättning: 11000 000\nAktiekapital: 1000 000\nVerkst dir: Ernst Rothstein\nEtableringsån 1896\nOmbildat till aktiebolag 1909.\n\nREX, AB SKOFABRIKEN\n\nPnr 701 04\n\nÖrebro 1, Vallnäsv 5-7. Box 230.\nTel 019-1194 70. Postgiro 96940-2.\nTga Rex\n\nVerksamhet: Tillverkar skor\nAntal anställda: 80\nÅrsomsättning: 7 000 000\nAktiekapital: 1200 000\nVerkst dir: Ragnar T:son Aqvist\nEtableringsàr: 1913.\n\nREXOLIN CHEMICALS AB\n\nPnr 25102\n\nHelsingborg 1, Box 50. Högastensg.\nTel 042-614 60. Bankgiro 652-9077.\nPostgiro 14397-4. Tga Rex olin.\nTelex 72353\n\nVerksamhet: Tillverkar\nkemisktekniska produkter för industri,\nlantbruk o för farmaceutiskt ända.\nmål, icke joniska tvättmedel av\netylenoxidkondensationstyp,\nfett-syrealkanolamider, avhärdningsme-del, komplexbindande medel\nbaserade på etylendiamintetraättiksyra\no nitrilotriätüksyra,\nväxtskydds-medel, p-Toluolsulfonsyra,\nEthoxy-guin, Diethylaminoethanol,\nDime-thylaminoethanol, Methylcarbamat,\npiperazine o dess salter,\nMeproba-mat, Piperonyl Butoxide\nAntal anställda: 250\nÅrsomsättning: 42 000 000\n\nAktiekapital: 300 000\nStyrelse: Adv Bengt Linders (ordf),\ndlr Georg L Busch, dir Torsten\nLilja, dir Bengt Möllbom, dir\nChrister Ragnartz\n\nVerkst dir: Georg L Busch\nEtableringsån 1924.\n\nANPAC AB\n\nPnr 217 73\n\nMalmö, Trollenäsg 14. Tel\n040-15 59 45. Bankgiro 643-5051.\nPostgiro 147582-1\n\nVerksamhet: Bil-, cykel- o vulka-\n\nniseringstillbehör\n\nAktiekapital: 15 000\nVerkst dir: Erie Bjurhovd\nEtableringsår: 1954.\n\nANSVAR, ÖMSESIDIGT\nFÖRSÄKRINGSBOLAG FOR\nHELNYKTRA\n\nPnr 102 42\n\nStockholm 5, Karlav 58. Box 5071.\nTel 08-63 00 80. Bankgiro 56-5306.\nPostgiro 55366. Tga Ansvar.\nTelex 10408\n\nVerksamhet: Försäkringsrörelse\nAntal anställda: 493\nÅrsomsättning: 99 500000\nVerkst dir: Gunnar Nelker\nEtableringsår: 1932\nDotterbolag: Ansvar Int. Ins. Co\nLtd Försäkrings AB.\n\nANTENSSÅGVERK AB\n\nPnr 440 08\n\nAn ten, Box 21. Tel 0322-720 84.\nBankgiro 400-5021. Postgiro\n23057-3\n\nVerksamhet: Tillverkar\nmonterings-färdiga trähus\nAntal anställda: 35\nÅrsomsättning: 2 700 000\nAktiekapital: 50 000\nVerkst dir: Stig Carlsson\nEtableringsår: 1896.\n\nE B ü METALLGJUTERI, AB\n\nPnr 630 05\n\nEskilstuna 5, Box 5008. Pressarg\n6. Tel 016-1374 85. Bankgiro\n604-4176. Postgiro 74630-5\n\nVerksamhet: Tillverkar kokill- o\npressgjutgods av lättmetall.\nSpecialitet: ventilationsmateriel\nVarunamn: E B O\nÅrsomsättning: 3 500 000\nAntal anställda: 32\nAktiekapital: 105 000\nChef: Ing Ove Ostlund\nEtableringsår: 1922.\n\nECKERSTRDM&amp; SAMUELSON,\nMASKINAFFÄREN\n\nPnr 21125\n\nMalmö, Osterg 4. Tel 040-12 57 16,\n124121. Bankgiro 640-2127.\nPostgiro 38649-0\n\nVerksamhet: Säljer\nkontorsmaskiner o möbler\n\nChefer: Nils S Eckerström, O\n\nSamuelson\n\nEtableringsår: 1927.\n\nOREBRO ILEXPRESS AB\n\nPnr 703 69\n\nÖrebro, Bettcrpsg 14. Tel\n019-1118 84. Bankgiro 508-9651.\nPostgiro 446442-6\n\nVerksamhet: Transporter,\nflyttningar o magasinering\nAntal anställda: 8\nÅrsomsättning: 36100\nAktiekapital: 50 000\nEtableringsår: 1958\nÄgare: AB Godstrafik &amp;\nBil-spedition, Göteborg.\n\nOREBRO\nKAROSSER!-FABRIK, AB\n\nPnr 700 03\n\nÖrebro 3, Oskarsv 40. Box 3061.\nTel 019-1123 67. Bankgiro\n815-8131. Postgiro 28371-3\nVerksamhet: Tillverkar kiosker o\ninredningar. S)ecialkarosser\nAntal anställda: 20\nAktiekapital: 100 000\nVerkst dir Harry Bergström\nEtableringsår: 1920.\n\nOREBRO KEXFABRIK, AB\n\nPrr 703 63\n\nÖrebro, Ribbingsg 1-3. Tel\n019-1&amp;P7 90. Bankgiro 463-2113.\nPostgiro 7832-9. Tga Kexfabriken\nVerksamhet: Tillverkar kex\nAktiekapital: 2700 000\nVerkst dir. Urban Rydén\nEtableringsår: 1896.\n\nOREBRO LANS ELEKTRISKA\nFÖRENING U PA\n\nPnr 702 25\n\nÖrebro, Borgmästarg 9. Tel\n019-1306 55. Bankgiro 815-5723.\nPostgiro 28377-0\n\nVerksamhet: Konsultation\nbeträffande eldistribution o elinstallationer.\nBesiktningar\nAntal anställda: 12\nÅrsomsättning: 800 000\nInsatskapital: 58 000\nVerkst dir: Civiling Sven Bergljung\nEtableringsår: 1918.\n\nOREBRO LANS LANTMANS\nCENTRALFüRENING\n\nPnr 70106\n\nÖrebro 1, Kanalv 10-12. Box 437.\nTel 019-1198 00. Postgiro 28399.\n\nTga Centralförening\nVerksamhet: Fröer, utsäde,\ngödselmedel, potatis, spannmål,\nfodermedel, stråfoder,\njordbrukskemikalier o oljor. Jordbruksmaskiner o\nbyggnadsmaterial. 12 filialkontor\nAntal anställda: 235\nÅrsomsättning: 125 000 000\nVerkst dir: Nils Andersson\nEtableringsår: 1906.\n\nOREBRO LANS\nTRÄDGÅRDSHALL EK FOR\n\nPrr 702 20\n\nÖrebro, Lindv 4. Tel 019-11 98 35.\nBankgiro 954-5047. Postgiro\n396953-2\n\nVerksamhet: Säljer frukt,\ngrönsaker o blommor engros\nAntal anställda: 42\nÅrsomsättning: 10 200 000\nChef: Disp Thore Norlin\nEtableringsår: 1961.",
    "structured": {
        "1": {
            "company_name": "ATLAS, BIL-AB",
            "pnr": "330 20",
            "address": "Anderstorp",
            "phone_number": "0371-16160",
            "bank_details": {
                "bankgiro": "488-0118",
                "postgiro": "468411-4"
            },
            "activity": "Tillverkar biltillbehör o verktyg, försäljning en gros",
            "capital": 100000,
            "key_personnel": [
                {
                    "name": "G A E Johansson",
                    "position": "Firmatecknare"
                },
                {
                    "name": "O S J Svenningson",
                    "position": "Firmatecknare"
                }
            ],
            "establishment_year": 1951
        },
        "2": {
            "company_name": "VÄS",
            "pnr": "56050",
            "bank_details": {
                "bankgiro": "812-8241",
                "postgiro": "661114-9"
            },
            "activity": "Montering av profilerad plåt",
            "employees": 13,
            "annual_turnover": 700000,
            "capital": 10000,
            "key_personnel": [
                {
                    "name": "Stig Johansson",
                    "position": "Verkst dir"
                }
            ],
            "establishment_year": 1966
        },
        "3": {
            "company_name": "allbo möbler ab",
            "pnr": "340 21",
            "address": "Diö, Box 207",
            "phone_number": "0476-210 81, 210 25",
            "bank_details": {
                "bankgiro": "276-1096",
                "postgiro": "140200-7"
            },
            "activity": "Tillverkar kompletteringsmöbler",
            "employees": 23,
            "annual_turnover": 1000000,
            "capital": 30000,
            "key_personnel": [
                {
                    "name": "Göte Nilsson",
                    "position": "Verkst dir"
                }
            ],
            "establishment_year": 1945
        },
        "4": {
            "company_name": "alleghenu-longdoz SVENSKA AB",
            "pnr": "412 85",
            "address": "Göteborg, Mölndalsv 85",
            "phone_number": "031-16 1180",
            "bank_details": {
                "bankgiro": "405-3442"
            },
            "activity": "Försäljer rostfri plåt o specialkvaliteter i rostfritt",
            "key_personnel": [
                {
                    "name": "Ing Sven Olof Lundahl",
                    "position": "Verkst dir"
                }
            ]
        },
        "5": {
            "company_name": "allehanda, tryckeri ab",
            "pnr": "23101",
            "address": "Trelleborg 1, Box 73",
            "phone_number": "04 1 0-150 55",
            "bank_details": {
                "bankgiro": "352-4949",
                "postgiro": "28000-8"
            },
            "activity": "Framställer facktidskrifter o böcker",
            "employees": 90,
            "capital": 50000,
            "key_personnel": [
                {
                    "name": "Robert Ohlsson",
                    "position": "Verkst dir"
                }
            ],
            "establishment_year": 1908
        },
        "6": {
            "company_name": "allektro ab, ingenjörs-firman",
            "pnr": "113 30",
            "address": "Stockholm, Gävleg 10",
            "phone_number": "08-30 23 56, 33 55 28",
            "activity": "Säljer elektr motorer o apparater",
            "capital": 15000,
            "key_personnel": [
                {
                    "name": "Ing Boris Palasoff",
                    "position": "Verkst dir"
                }
            ],
            "establishment_year": 1942
        },
        "7": {
            "company_name": "FORSSA BRUKS AKTIEBOLAG",
            "pnr": "820 64",
            "address": "Näsviken, Box 44",
            "phone_number": "0650-304 00",
            "bank_details": {
                "bankgiro": "78-7019",
                "postgiro": "8008"
            },
            "activity": "Tillverkar papp, kartong, transportförpackningar av solid papp samt idkar skogshantering",
            "employees": 225,
            "annual_turnover": 25000000,
            "capital": 2650000,
            "key_personnel": [
                {
                    "name": "Dir Esbjörn Ulfsäter",
                    "position": "(ordf)"
                },
                {
                    "name": "Anders Larsson",
                    "position": "hemmansägare"
                },
                {
                    "name": "Nils Sjöberg",
                    "position": "avd-chef"
                },
                {
                    "name": "Gösta Holm",
                    "position": "disp"
                },
                {
                    "name": "Rune Eriksson",
                    "position": "disp"
                },
                {
                    "name": "Pär Svensson",
                    "position": "dir"
                }
            ],
            "establishment_year": 1868
        },
        "8": {
            "company_name": "KARDBESLAG, AB",
            "pnr": "600 06",
            "address": "Norrköping 6, Lindöv 21-23, Box 6053",
            "phone_number": "011-13 40 60",
            "telex": "64118",
            "activity": "Tillverkar kardbeslag o textilförnödenheter",
            "employees": 120,
            "annual_turnover": 7000000,
            "capital": 1000000,
            "key_personnel": [
                {
                    "name": "J Hübner",
                    "position": "Verkst dir"
                }
            ],
            "establishment_year": 1921
        },
        "9": {
            "company_name": "ITE FABRIKS AB",
            "pnr": "23 9 00",
            "address": "Olofström, Box 35",
            "phone_number": "0454-404 25",
            "bank_details": {
                "bankgiro": "151-7028",
                "postgiro": "674330-6"
            },
            "activity": "Tillverkar pressade plåtartiklar, snabbspännen m m",
            "employees": 15,
            "annual_turnover": 1500000,
            "capital": 70000,
            "key_personnel": [
                {
                    "name": "Hans Rasmusson",
                    "position": "Verkst dir"
                }
            ],
            "establishment_year": 1950
        }
    }
}