{
    "original": "SVENSKA AB PHILIPS\n\nPnr 102 50\n\nStockholm 27, Lidingöv 50. Fack.\nTel 08-63 50 00. Bankgiro 16-8200.\nPostgiro 845-8. Tga Philamp.\nTelex 17190\n\nVerksamhet Säljer\nelektrotekniska artiklar\n\nFilialer: 40126 Göteborg 1,\nBurg-greveg 15. Tel 031-19 76 00\n20013 Malmö, Kosterög 5.\nIndustrihamnen. Tel 040-93 5100\nVarunamn: Philips\nAntal anställda: 1291\nÅrsomsättning: 421700 000\nAktiekapital: 40 000 000\nStyrelse: Adv Hans Ihre (ordf), dir\nOlle Franzén, dir B Kugelberg,\namiral Ake Lindemalm, prof Sune\nRusck\n\nVerkst dir: Olle Franzén\nDirektion: Dankert Punt v verkst\ndir, Nils Backmark v verkst dir,\nCarl Johan Tjeder, Lars Malm\nEtableringsår: 1923.\n\nSVENSKA PIANO.\nFABRIKEN, AB\n\nPnr 111 20\n\nStockholm, Vasag 23-25. Tel\n08-1028 82. Bankgiro 403-7982.\nPostgiro 409800-0. Tga Svenskpiano\nVerksamhet: Pianon, flyglar, orglar,\nelorglar o epokinstrument\nVerkst dir: Börje Thalén\nEtableringsår: 1917.\n\nSVENSKA PLASTFABRIKEN\nAB\n\nPnr 123 57\n\nFarsta, Cigarrv 16. Tel 08-94 29 94,\n\n94 29 95\n\nVerksamhet: Utför formpressning i\ntermo- o härdplaster.\nVerktygstillverkning.\n\nSVENSKA PLASTICS\nKEMISK INDUSTRI\n\nPnr 11454\n\nStockholm, Styrmansg 24. Tel 08-\n\n62 25 45\n\nVerksamhet: Lim o flytande plast\n\nför industri o hantverk\n\nÄgare o chef: Civiling K G Kru-\n\nsell\n\nEtableringsår 1946.\n\nSVENSKA PLATT.\nFÖRSÄLJNINGS AB\n\nPnr 11140\n\nStockholm, Döbelnsg 1. Tel\n08-233100. Bankgiro 235-1344.\nPostgiro 56272-8. Tga Plattbolaget\nVerksamhet: Säljer golv- o\nväggplattor, mosaik, chamotte o klinker\nVarunamn: SPA\nAntal anställda: 10\nÅrsomsättning: 6 000 000\nAktiekapital: 30 000\nStyrelse: Dir Elam Tunhammar\n(ordf), dir Ake Roos,\ngeneralkonsul Nils Sterner, dir Stig Sunne\nVerkst dir: Per Cornéer\nEtableringsår 1933\nDotterbolag till AB Iföverken o\nUpsala Ekeby AB, båda i\nStockholm.\n\nSVENSKA PLESSEY AB\n\nPnr 172 03\n\nSundbyberg 3, Humbleg 1 A. Box\n326. Tel 08-28 92 75. Bankgiro\n238-2281. Postgiro 497766-6. Tga\nPaintoncompany. Telex 10558\nVerksamhet: Elektronik\nAktiekapital: 55 000\nVerkst dir: Ingvar Chevalier\nEtableringsår: 1955.\n\nÅFORSGRUPPEN, AB\n\nPnr 360 52\n\nKosta. Tel 0478-503 00. Bankgiro\n\n615-7200. Postgiro 7775-0. Tga\n\nKostabolaget\n\nVerksamhet: Servis- o konstglas,\narmaturer, konstsmide m m\nAntal anställda: 700\nÅrsomsättning: 36 000 000\nAktiekapital: 4 000 000\nStyrelse: Prof Ulf af Trolle (ordf),\ndir Erie Afors. dir Jan Afors, dir\nOlof Kahr, dir Erik Rosén\nVerkst dir: Erik Rosén.\n\nÅGERUPS KLICHÉ.\nANSTALT AB\n\nPnr 63104\n\nEskilstuna 1, Libergsg 4. Box 295.\nTel 016-13 68 68, 14 11 88.\nBankgiro 601-5515. Postgiro 328747-1\nVerksamhet: Klichéer, teckningar,\nretuscher o offsetplåtar\nAktiekapital: 30000\nVerkst dir. Sture Agerup\nEtableringsån 1946\nOmbildat till aktiebolag 1959.\n\nÅGREN &amp; HOLMBERGS\nBOKTRYCKERI AB\n\nPnr 733 00\n\nSala, Agnélig. Tel 0224-133 30.\nBankgiro 23-2028. Postgiro 5363.\nTelex 7523\n\nVerksamhet: Tidnings- o\nboktryckeri. Utgivare av Sala Allehanda,\nAvesta Tidning o Fagersta^Posten\nAktiekapital: 100 000\nVerkst dir: Charles Söderström.\n\nÅGREN &amp; KARELL AB\n\nPnr 75104\n\nUppsala 1, Svartbäcksg 6. Box\n205. Tel 018-13 15 57. Bankgiro\n230-2081. Postgiro 94600-4\nVerksamhet: Klänningar, kappor,\nklänningstyger, linne- o\nbomullsvävnader, gardiner mm\nVerkst din Bertil Samuelsson\nEtableringsån 1810\nOmbildat till aktiebolag 1926.\n\nÅGRENS SPEDITION AB,\nAXEL H\n\nPnr 403 10\n\nGoteborg 2. O Hamng 17. Fack.\nTel 031-17 53 20. Tga Agrensped.\nTelex 20938 ÅGREN S\nVerksamhet: Internationell\nspedition o containertrafik, lagring o\ndistribution\n\nVeikst dir: Tage Dehner\nDotterbolag till Ahlsell &amp; Ågren AB.\n\nÅGREN. AB CLAES\n\nPnr 382 00\n\nNybro, Långg 17. Tel 0481-11955\nVeiksamhet: Byggnadsmaterial,\ngolvavdelning samt betongvaror\nAktiekapital: 500 000\nVeikst dir: Leif Ågren\nEtableringsån 1897.\n\nSVENSKA DATAETIKETT AB\n\nPnr 25103\n\nHelsingborg 1, Box 209. Bendzg 29.\nTel 042-970 50. Bankgiro 610-6268.\nPostgiro 289700-7. Tga Datakett\nVerksamhet: Special tryckeri för\nsjälvhäftande etiketter, specialitet\ndataetiketter\n\nFörsäljningskontor: 194 00 Upplands\nVäsby, Skultunagränd 14. Tel\n0760-826 23\n\nAntal anställda: 25\nÅrsomsättning: 4 000 000\nAktiekapital: 50 000\nAdm dir: Bengt Thelin\nTekn dir: Svend-Aage Olsen\nEtableringsår: 1967.\n\nSVENSKA DATAREGISTER AB\nSWEDA\n\nPnr 17123\n\nSolna 1, Tritonv 9. Box 1200. Tel\n08-28 94 20’. Bankgiro 171-1244.\nPostgiro 154176-2. Tga Swedafab,\nStockholm. Telex 10425 SWEDA S\nVerksamhet: Tillverkar\nkassaregister o säljdataregister\n\nAktiekapital: 6 000 000\nVeikst dir: Lennart V Nordenhall\nEtableringsår: 1936.\n\nFRITZELL, AB NILS\n\nPnr 124 21\n\nBandhagen 1, Harpsundsv 113. Box\n32. Tel 08-47 25 20. Bankgiro\n47-8621. Postgiro 253358. Telex 10042.\nTga Enfritzell\n\nVerksamhet: Säljer armatur,\npumpar o kompensatorer\nAntal anställda: 20\nAktiekapital: 120 000\nVerkst dir: Nils Fritzell\nEtableringsår: 1951.\n\nTRETORN DREV AB\n\nPnr 25101\n\nHelsingborg 1, Fack. Rönnowsg 10.\nTel 042-14 44 40. Bankgiro\n410-2653. Postgiro 396820-3. Tga\nTretorn. Telex 72372\nVerksamhet: Direktreklam samt\nspecialuppdrag inom\nmarknadsföringsområdet\n\nFilial: 104 35 Stockholm 23, Box\n23060. Hagag 29. Tel 08-24 72 00\nVarunamn: Drev\nAntal anställda: 4\nÅrsomsättning: 3 000 000\nAktiekapital: 45 000\nVerkst din Bo C: son Lindberg\nMarknadschef: Leif Fogelberg\nDistriktschef: Allan Linder\nEtableringsår: 1970.\n\nALINGSÅS SIDENVÄVERI, AB\n\nPnr 44100\n\nAlingsås, Sidenv. Tel 0322-14120.\nBankgiro 531-1840. Postgiro\n90303-9. Tga Siden.\nTelex 2493 ALISI S\nVerksamhet: Tillverkar tyger o\nvävnader av konstsilke o\nsyntetiska fibrer såsom nylonvävnader,\nrayonsilke vävnader, terylenevävnader,\nsyntettrikå (Crimplene, Diolén)\nm fi\n\nVarunamn: Alisi\nAntal anställda: 70\nÅrsomsättning: 10 000 000\nAktiekapital: 400 000\nVerkst dir: Bertil Davidson\nEtableringsår: 1933.\n\nALINGSÅS\nSNICKERIFABRIKS AB\n\nPnr 441 00\n\n-Alingsås, Göteborgsv 10. Tel\n0322-100 50, 112 50. Bankgiro 43-6506.\nPostgiro 164004. Tga Angsågen\nVerksamhet: Säljer trävaror,\nbyggnadssnickerier m m\nAntal anställda: 12\nÅrsomsättning: 1800 000\nAktiekapital: 80 000\nVerkst dir: P-O Carlsson\nEtableringsår: 1892.\n\nOLSON AB, ELIS\n\nPnr 417 05\n\nGöteborg, Gamla Tuvev 18. Tel\n031-23 50 60. Bankgiro 513-6171.\nPostgiro 42680-9\n\nVerksamhet: Bleckplåtsdekorering\nAntal anstäUda: 60\nÅrsomsättning: 4 000 000\nAktiekapital: 500 000\nStyrelse: Adv Stig Wiberg (ordf),\ndlr Christian Ameln, dlr Georg\nDicander, konsul Ewald Luckey,\ndisp Per Brolund, dir Kjell\nNihl-berg\n\nVerkst dir: Ingvar Carlsson\nKamrer: Nils Strömberg\nTryckeriföreståndare: G Davidsson\nEtableringsår: 1910\nOmbildat till aktiebolag 1928.\n\nOHLSSON FABRIKS. &amp;\nHANDELS AB, ERIK\n\nPnr 501 08\n\nBorås 1, Osterlångg 11. Box 527.\nTel 033-1108 00, 130370.\nBankgiro 531-1428. Postgiro 263297-4.\nTga Erwo\n\nVeiksamhet: Garner, sytråd o\ntextilmaskiner\nVarunamn: Erwo\nAntal anstäUda: 10\nAktiekapital: 100 000\nVerkst dir: Erik Ohlsson\nEtableringsår: 1937\nOmbildat till aktiebolag 1957.\n\nOLSSON INLÄGGSSULFABRIK,\nG A\n\nPnr 212 28\n\nMalmö, Knivg 19. Tel 040-93 16 56.\nBankgiro 643-5150. Postgiro\n39407-2\n\nVerksamhet: Tillverkar\ninläggssulor o korkhälar, partiförsäljning av\nskoutensilier\n\nÄgare o chef: Fabr Gustaf A\nOlsson\n\nEtableringsår: 1934.\n\nVÄS\n\n847-8042. Postgiro 41941-6\n\nVerksamhet: Import o försäljning\n\nav dentalvaror\n\nAntal anställda: 50\n\nÅrsomsättning: 7 000 000\n\nÄgare o chef: Dir Gustaf Björkman\n\nEtableringsår. 1928.\n\nVÄSTRA SVERIGES\nDENTALLABORATORIUM\n\nPnr 400 10\n\nGöteborg 3, Box 3048.\nVasaplatsen 2. Tel 031-17 5 6 90. Bankgiro\n847-8042. Postgiro 48424-6\nVerksamhet: Dentaltekniskt\nlaboratorium\n\nAntal anställda: 52\n\nÄgare o chef: Dir Gustaf Björkman\n\nEtableringsår: 1928.\n\nVÄSTRA SVERIGES\nINGENJüRSBYRA\n\nPnr 530 10\n\nVedum. S Torget. Tel 0512-40 1 65.\n40185. Bankgiro 220-6373.\nPostgiro 429844\n\nVerksamhet; Konsulterande i\nvatten- o avloppsanläggningar\nAntal anställda: 4\nÅrsomsättning: 250 000\nChef: Ing Ake Larin\nEtableringsår: 1954.\n\nWESTRA WERMLANDS SPAR.\nBANK\n\nPnr 67101\n\nArvika 1. Box 26. Tel 0570-13160\nBankgiro 98-1431. Postgiro 90715\nVeiksamhet: Bankrörelse.\n\nVÄSTRA ÅKERIET\n\nPnr 703 58\n\nÖrebro, Industrig 10. Tel\n019-1165 51, 18 69 25. Bankgiro\n495-5662. Postgiro 341471-1\nVerksamhet: Bedriver åkerirörelse\ni beställningstrafik\nAntal anställda: 20\nÅrsomsättning: 1300 000\nChef: Allan Larsson\nEtableringsår: 1930.\n\nVÄSTSVENSKA KYLHUS.\nAKTIEBOLAGET\n\"COLDSTORES\"\n\nPnr 402 74\n\nGöteborg 8, Box 8959. Ringög.\nTel 031-5137 20. Bankgiro\n508-7176. Postgiro 48093-9. Tga\nCoo-llng. Telex 2354\n\nVerksamhet: Fryshusrörelse med\ninfrysning o fryslagring\nAntal anställda: 50\nAktiekapital: 1000 000\nStyrelse: Adv Johan Ramberg\n(ordf), landsretssagfüSrer Kaj\nPetersen\n\nVeikst dir: Evert Hännestrand\nEtableringsår 1941.\n\nVÄSTSVENSKA LANTMÄN\nFURENING UPA\n\nPnr 53101\n\nLidköping 1, O Hamnen. Box 123.\nTel 0510-22140. Postgiro 10892-8\nVerksamhet: Inköp av produkter,\nsäljer förnödenheter. Jordbruk\nAntal anställda: 921\n\nÅrsomsättning: 330 000 000\nVerkst dir: Gunnar Svensson\nEtableringsår: 1895.\n\nVÄSTSVENSKA\nMASKIN-AKTIEBOLAGET\n\nPnr 650 07\n\nKarlstad 7, Box 7046. Ljungg 4.\nTel 054-1810 23. Bankgiro\n535-6480. Postgiro 328510-3. Tga Væma\nVerksamhet: Säljer\nverkstadsmaskiner o maskintillbehör\nVarunamn: Stuk-Egal\nAktiekapital: 50 000\nVerkst dir: Gösta Löfgren\nEtableringsår: 1946.\n\nVÄSTSVENSKA\nTRYCKIMPREGNERINGS AB\n\nPnr 530 16\n\nStora Levene, Box 129. Tel\n0512-602 65. Bankgiro 462-8293.\nPostgiro 675990-6\n\nVerksamhet: Tryckimpregnering\nav trävaror med Hylosan\nÅrsomsättning: 500000\nAktiekapital; 45 000\nVerkst dir. Erik Hermansson\nEtableringsår 1965.\n\nVÄSTSVERIGES ALLMÄNNA\nRESTAURANT AKTIEBOLAG,\nVARA\n\nPnr 400 10\n\nGöteborg 3, Viktoriag 3. Fack. Tel\n031-1712 70. Bankgiro 337-5185,\n501-0962. Postgiro 42330-1\nVerksamhet: Hotell- o\nrestaurangrörelse\n\nAntal anställda: 1 600\nAktiekapital: 1000000\nVeikst dir Bengt Bengtsson\nV verkst dir: Sigurd Laweson\nEtableringsår 1921.\n\nVÄTTERSTADS\nBYGGLEDNING AB\n\nPnr 552 80\n\nJönköping, Solstigen 4. Tel\n036-79418. Bankgiro 545-1471.\nPost-giro 680869-5\n\nVerksamhet; Byggledning,\nbesiktningar, kontroller\nAntal anställda: 6\nÅrsomsättning: 350 000\nAktiekapital: 5 000\nVerkst dir: SBR ing Olle Olsson\nEtableringsår. 1966.\n\nSYSTEM ABSTRACTA AB\n\nPnr 212 25\n\nMalmö, Murmansg 130. Tel\n040-93 59 20. Bankgiro 653-1081.\nPostgiro 267384\n\nVerksamhet: Säljer hallar för lager,\n\nutställningar, verkstad\n\nAntal anställda: 6\n\nÅrsomsättning: 2 500 000\n\nAktiekapital: 300 000\n\nVerkst dir: Civilekonom Johan\n\nDieden\n\nEtableringsår: 1961.\n\nAUTOKREDIT, AB\n\nPnr 114 34\n\nStockholm, Birger Jarlsg 8. Tel\n08-23 5615. Bankgiro 700-0110.\nPostgiro 1991-9. Tga Autokredit\nsamhet\n\nVerksamhet: Handels- o\nfinansverk-Antal anställda: 9\nÅrsomsättning: 60 000 00\nAktiekapital: 500 000\nVerkst dir: Ingemar Dahlberg\nEtableringsår: 1928.",
    "structured": {
        "1": {
            "company_name": "SVENSKA AB PHILIPS",
            "activity": "Säljer elektrotekniska artiklar",
            "establishment_year": 1923,
            "employees": 1291,
            "annual_turnover": 421700000,
            "capital": 40000000,
            "key_personnel": [
                {
                    "name": "Adv Hans Ihre",
                    "position": "ordf"
                },
                {
                    "name": "dir Olle Franzén",
                    "position": null
                },
                {
                    "name": "dir B Kugelberg",
                    "position": null
                },
                {
                    "name": "amiral Ake Lindemalm",
                    "position": null
                },
                {
                    "name": "prof Sune Rusck",
                    "position": null
                }
            ]
        },
        "2": {
            "company_name": "SVENSKA PIANO. FABRIKEN, AB",
            "activity": "Pianon, flyglar, orglar, elorglar o epokinstrument",
            "establishment_year": 1917
        },
        "3": {
            "company_name": "SVENSKA PLASTFABRIKEN AB",
            "activity": "Utför formpressning i termo- o härdplaster. Verktygstillverkning",
            "establishment_year": null
        },
        "4": {
            "company_name": "SVENSKA PLASTICS KEMISK INDUSTRI",
            "activity": "Lim o flytande plast för industri o hantverk",
            "establishment_year": 1946
        },
        "5": {
            "company_name": "SVENSKA PLATT. FÖRSÄLJNINGS AB",
            "activity": "Säljer golv- o väggplattor, mosaik, chamotte o klinker",
            "establishment_year": 1933,
            "employees": 10,
            "annual_turnover": 6000000,
            "capital": 30000,
            "key_personnel": [
                {
                    "name": "Dir Elam Tunhammar",
                    "position": "ordf"
                },
                {
                    "name": "dir Ake Roos",
                    "position": null
                },
                {
                    "name": "generalkonsul Nils Sterner",
                    "position": null
                },
                {
                    "name": "dir Stig Sunne",
                    "position": null
                }
            ]
        },
        "6": {
            "company_name": "SVENSKA PLESSEY AB",
            "activity": "Elektronik",
            "establishment_year": 1955,
            "capital": 55000
        },
        "7": {
            "company_name": "ÅFORSGRUPPEN, AB",
            "activity": "Servis- o konstglas, armaturer, konstsmide m m",
            "establishment_year": null,
            "employees": 700,
            "annual_turnover": 36000000,
            "capital": 4000000,
            "key_personnel": [
                {
                    "name": "Prof Ulf af Trolle",
                    "position": "ordf"
                },
                {
                    "name": "dir Erie Afors",
                    "position": null
                },
                {
                    "name": "dir Jan Afors",
                    "position": null
                },
                {
                    "name": "dir Olof Kahr",
                    "position": null
                },
                {
                    "name": "dir Erik Rosén",
                    "position": null
                }
            ]
        },
        "8": {
            "company_name": "ÅGERUPS KLICHÉ. ANSTALT AB",
            "activity": "Klichéer, teckningar, retuscher o offsetplåtar",
            "establishment_year": 1946
        },
        "9": {
            "company_name": "ÅGREN & HOLMBERGS BOKTRYCKERI AB",
            "activity": "Tidnings- o boktryckeri. Utgivare av Sala Allehanda, Avesta Tidning o Fagersta^Posten",
            "establishment_year": null
        },
        "10": {
            "company_name": "ÅGREN & KARELL AB",
            "activity": "Klänningar, kappor, klänningstyger, linne- o bomullsvävnader, gardiner mm",
            "establishment_year": 1810
        },
        "11": {
            "company_name": "ÅGRENS SPEDITION AB, AXEL H",
            "activity": "Internationell spedition o containertrafik, lagring o distribution",
            "establishment_year": null
        },
        "12": {
            "company_name": "ÅGREN. AB CLAES",
            "activity": "Byggnadsmaterial, golvavdelning samt betongvaror",
            "establishment_year": 1897
        },
        "13": {
            "company_name": "SVENSKA DATAETIKETT AB",
            "activity": "Special tryckeri för självhäftande etiketter, specialitet dataetiketter",
            "establishment_year": 1967,
            "employees": 25,
            "annual_turnover": 4000000,
            "capital": 50000,
            "key_personnel": [
                {
                    "name": "Bengt Thelin",
                    "position": "Adm dir"
                },
                {
                    "name": "Svend-Aage Olsen",
                    "position": "Tekn dir"
                }
            ]
        },
        "14": {
            "company_name": "SVENSKA DATAREGISTER AB SWEDA",
            "activity": "Tillverkar kassaregister o säljdataregister",
            "establishment_year": 1936,
            "capital": 6000000
        },
        "15": {
            "company_name": "FRITZELL, AB NILS",
            "activity": "Säljer armatur, pumpar o kompensatorer",
            "establishment_year": 1951,
            "employees": 20,
            "capital": 120000
        },
        "16": {
            "company_name": "TRETORN DREV AB",
            "activity": "Direktreklam samt specialuppdrag inom marknadsföringsområdet",
            "establishment_year": 1970,
            "employees": 4,
            "annual_turnover": 3000000,
            "capital": 45000
        },
        "17": {
            "company_name": "ALINGSÅS SIDENVÄVERI, AB",
            "activity": "Tillverkar tyger o vävnader av konstsilke o syntetiska fibrer såsom nylonvävnader, rayonsilke vävnader, terylenevävnader, syntettrikå (Crimplene, Diolén) m fi",
            "establishment_year": 1933,
            "employees": 70,
            "annual_turnover": 10000000,
            "capital": 400000
        },
        "18": {
            "company_name": "ALINGSÅS SNICKERIFABRIKS AB",
            "activity": "Säljer trävaror, byggnadssnickerier m m",
            "establishment_year": 1892,
            "employees": 12,
            "annual_turnover": 1800000,
            "capital": 80000
        },
        "19": {
            "company_name": "OLSON AB, ELIS",
            "activity": "Bleckplåtsdekorering",
            "establishment_year": 1910,
            "employees": 60,
            "annual_turnover": 4000000,
            "capital": 500000,
            "key_personnel": [
                {
                    "name": "Adv Stig Wiberg",
                    "position": "ordf"
                },
                {
                    "name": "dlr Christian Ameln",
                    "position": null
                },
                {
                    "name": "dlr Georg Dicander",
                    "position": null
                },
                {
                    "name": "konsul Ewald Luckey",
                    "position": null
                },
                {
                    "name": "disp Per Brolund",
                    "position": null
                },
                {
                    "name": "dir Kjell Nihl-berg",
                    "position": null
                }
            ]
        },
        "20": {
            "company_name": "OHLSSON FABRIKS. & HANDELS AB, ERIK",
            "activity": "Garner, sytråd o textilmaskiner",
            "establishment_year": 1937,
            "capital": 100000
        },
        "21": {
            "company_name": "OLSSON INLÄGGSSULFABRIK, G A",
            "activity": "Tillverkar inläggssulor o korkhälar, partiförsäljning av skoutensilier",
            "establishment_year": 1934
        },
        "22": {
            "company_name": "VÄS",
            "activity": "Import o försäljning av dentalvaror",
            "employees": 50,
            "annual_turnover": 7000000
        },
        "23": {
            "company_name": "VÄSTRA SVERIGES DENTALLABORATORIUM",
            "activity": "Dentaltekniskt laboratorium",
            "employees": 52
        },
        "24": {
            "company_name": "VÄSTRA SVERIGES INGENJÖRSBYRA",
            "activity": "Konsulterande i vatten- o avloppsanläggningar",
            "employees": 4,
            "annual_turnover": 250000
        },
        "25": {
            "company_name": "WESTRA WERMLANDS SPAR. BANK",
            "activity": "Bankrörelse"
        },
        "26": {
            "company_name": "VÄSTRA ÅKERIET",
            "activity": "Bedriver åkerirörelse i beställningstrafik",
            "employees": 20,
            "annual_turnover": 1300000
        },
        "27": {
            "company_name": "VÄSTSVENSKA KYLHUS. AKTIEBOLAGET \"COLDSTORES\"",
            "activity": "Fryshusrörelse med infrysning o fryslagring",
            "employees": 50,
            "capital": 1000000,
            "key_personnel": [
                {
                    "name": "Adv Johan Ramberg",
                    "position": "ordf"
                },
                {
                    "name": "landsretssagförrer Kaj Petersen",
                    "position": null
                }
            ]
        },
        "28": {
            "company_name": "VÄSTSVENSKA LANTMÄN FÖRENING UPA",
            "activity": "Inköp av produkter, säljer förnödenheter. Jordbruk",
            "employees": 921,
            "annual_turnover": 330000000
        },
        "29": {
            "company_name": "VÄSTSVENSKA MASKIN-AKTIEBOLAGET",
            "activity": "Säljer verkstadsmaskiner o maskintillbehör",
            "establishment_year": 1946
        },
        "30": {
            "company_name": "VÄSTSVENSKA TRYCKIMPREGNERINGS AB",
            "activity": "Tryckimpregnering av trävaror med Hylosan",
            "annual_turnover": 500000,
            "capital": 45000
        },
        "31": {
            "company_name": "VÄSTSVERIGES ALLMÄNNA RESTAURANT AKTIEBOLAG, VARA",
            "activity": "Hotell- o restaurangrörelse",
            "employees": 1600,
            "capital": 1000000
        },
        "32": {
            "company_name": "VÄTTERSTADS BYGGLEDNING AB",
            "activity": "Byggledning, besiktningar, kontroller",
            "employees": 6,
            "annual_turnover": 350000,
            "capital": 5000
        },
        "33": {
            "company_name": "SYSTEM ABSTRACTA AB",
            "activity": "Säljer hallar för lager, utställningar, verkstad",
            "employees": 6,
            "annual_turnover": 250000,
            "capital": 300000
        },
        "34": {
            "company_name": "AUTOKREDIT, AB",
            "activity": "Handels- o finansverksamhet",
            "employees": 9,
            "annual_turnover": 6000000,
            "capital": 500000
        }
    }
}