{
    "original": "NORDALS HÄRADS SPARBANK\n\nPnr 464 00\n\nMellerud, Box 72. Köpmantorget 1.\nTel 0530-114 85. Bankgiro 981-2348.\nPostgiro 172908-6\nVerksamhet: Bankrörelse\nFilialer: 660 06 Bäekefors. Tel\n0530-601 90\n\n45063 Högsäter. Tel 0530-910 46\n460 76 Asensbruk. Tel 0530-303 00\nAntal anställda: 21\nVerkst dir: Folke Bäckström.\n\nNORDBAKELS, AB\n\nPnr 400 13\n\nGöteborg 36, von Holtensg 1, Box\n36063. Tel 031-19 2500. Bankgiro\n42-0136. Postgiro 46729.\nTga Nordbakels. Telex 2224\nVerksamhet: Halvfabrikat för\nbageri- o konditoribranschen samt\nrestauranger o storkök\nAntal anställda: 160\nÅrsomsättning: 50 000 000\nAktiekapital: 1750 000\nVerkst dir: Birger Norlander\nEtableringsår: 1942.\n\nNORDBERGS VAGNFABRIK\nAB, GUSTAF\n\nPnr 11161\n\nStockholm, Tegnërg 37. Tel\n08-10 8611, 21 26 38. Postgiro 155416\nVerksamhet: Reparerar bilar o\nkarosserier\n\nAntal anställda: 8\nÅrsomsättning: 600 000\nAktiekapital: 22 000\nVerkst dir: Nils Nordberg\nEtableringsån 1901.\n\nWIKMAN &amp; MALMKJELL AB\n\nPnr 104 22\n\nStockholm 22, Fack. Hantverkarg 8.\nTel 08-5205 05. Bankgiro 166-0075.\n\n694\n\nPostgiro 604278-2. Tga Wimatool.\nTelex 10607\n\nVerksamhet: Säljer\nverktygsmaskiner o mätverktyg\nAntal anställda: 16\nÅrsomsättning: 10 000 000\nAktiekapital: 150 000\nÄgare o chefer: Civiling Ulf\nWikman, ing K O Malmkjell\nEtableringsår: 1959.\n\nFROSTA GUMMIFABRIKS AB\n\nPnr 233 00\n\nSvedala, Börringev. Fabrik o\norderkontor. Tel 040-40 11 10. Bankgiro\n870-3563. Postgiro 247502-8. Tga\nFrostafoam\n\nVerksamhet: Tillverkar\nskumgummiartiklar\n\nEkonomiavdelning o övriga\nadministrativa avdelningar:\nTranås. Tel 0140-130 30\nAktiekapital: 100 000\nVeikst dir: Bo Fjaestad\nPlatschef: Ingvar Lindeberg\nEtableringsår 1949.\n\nELE\n\nVerkst dir: Hans Werthén\nV verkst din Gösta Bystedt\nEtableringsår. 1919.\n\nELECTROLUX STÄDUTEN.\nSIL|ER AB\n\nPnr 10545\n\nStockholm, Luxbacken 1. Tel\n08-13 1210. 13 0100. Bankgiro\n735-2255. Postgiro 700975-6\nVerksamhet Försäljning av\nstäd-maskiner, städredskap o\nkemisktekniska produkter, städ planering\no utbildning\nAntal anställda: 21\nÅrsomsättning: 8 000 000\nAktiekapital: 250 000\nVerkst dir: Bo Palmberg\nEtableringsår: 1963.\n\nELECTROLUX SVENSKA\nFOR-SÄLJNING5AKTIEBOLAG\n\nPnr 105 45\n\nStockholm, Luxbacken 1, Lilla\nEssingen. Tel 08-13 01 00.\nPostgiro 50125. Tga Electrolux.\nTelex 17520 ELHEAD S\nVerksamhet: Säljer\nhushållsapparater\n\nAntal anställda: 990\nÅrsomsättning: 159 675 000\nAktiekapital: 6000000\nVerkst dir. Gösta Bystedt\nEtableringsår: 1927.\n\nWAHLBECKS FABRIKER, AB\n\nPnr 581 01\n\nLinköping 1, Fack. Tel 013-12 91 40.\nBankgiro 120-0294. Postgiro\n11429-8. Tga Wahlbecks.\nTelex WAHLBEC S\nVerksamhet: Textilindustri.\nTillverkar o säljer mattor, bindgarn,\ntågvirke, band m m\nFörsäljning: Mattor-AB Wahlbecks\nFabriker, Mattförsäljningen,\nLinköping. (Försäljn-dir: Einar\nGul-lers)\n\nBindgarn o tågvirke\nmm-Wahl-becks-Tågvirkesbolagen, AB,\n40121 Göteborg 1, Grönsakstorget\n2. Box 80. Tel 031-17 78 90. Telex\n2547 cordage gbg. (dir: Töre\nBörjesson)\n\nAvdelningskontor: 103 83\nStockholm 7, Smålands g 4. Tel\n08-24 98 75\n\nAntal anställda: 500\nÅrsomsättning: 65 000 000\nAktiekapital: 2 000 000\nStyrelse: Dir Gunnar Ehrlemark\n(ordf), dir Olle Wahlbeck, dir Björn\nClaughton-Wallin, dir Ebbe\nWahlbeck, dir Jörgen Blegvad\nVerkst dir: Olle Wahlbeck\nEtableringsår: 1876\nOmbildat ti.ll aktiebolag 1936.\n\nWAHLBECK KONSTRUK.\nTIONSBYRÅ, B\n\nPnr 601 04\n\nNorrköping 1, Drottningg 5. Box\n244. Tel 011-16 86 92, 12 50 92.\nBankgiro 349-1057. Postgiro\n511763-5\n\nVerksamhet: Konstruerar\nVVS-an-läggningar för industrier\nAntal anställda: 6\nChef: Ing Bertil Wahlbeck\nEtableringsår: 1959.\n\nINDUSTRIMODELL, AB\n\nPnr 550 02\n\nJönköping 2, Box 2046. Tel\n036-12 5295. Bankgiro 835-7204.\nPostgiro 278249-8\n\nVerksamhet: Tillverkar trä-,\njärn-o metallmodeller, kompletta\nbrätt-utrustningar. Utför mek arbeten,\nkilrepssklvor\nAntal anställda: 17\nAns omsättning: 1000000\nAktiekapital: 60 000\nStyrelse: Fabr Assar Petersson\n(ordf), fabr Ladhe Petersson\nEtableringsår: 1944\nNuvarande namn o bolag 1957.\n\nINDUSTRIMONTERING AB\n\nPnr 14146\n\nHuddinge, Dalhemsv 48. Tel\n08-757 27 75. Bankgiro 331-4507.\nPostgiro 255703-1\nVerksamhet: Tillverkar\nstålkonstruktioner. Utför grovplåtsarbeten\nAntal anställda: 110\nÅrsomsättning: 9 000 000\nAktiekapital: 150000\nVettet dir: Per Arne Bodfäldt\nEtableringsår 1946.\n\nHULIN, AB OLOV\n\nPnr 430 70\n\nSävedalen, Sotenäsv 16. Tel\n031-26 44 10. Bankgiro 50-9703.\nPostgiro 44112\n\nVerksamhet: Trikåvarugrossist\nAktiekapital: 50 000\nVerkst dir: Olov Hulin\nEtableringsår: 1931.\n\nHULTS SKYLTINDUSTRI AB\n\nPnr 352 46\n\nVäxjö, Verkstadsg 14. Tel\n0470-13705, 136 02. Bankgiro 668-4492.\nPostgiro 670052-0\nVerksamhet: Tillverkar o säljer\nljusskyltar\nAntal anställda: 25\nÅrsomsättning: 2 000 000\nAktiekapital: 25 000\nVerkst din Jan Hult\nEtableringsår. 1969.\n\nKRISZAT AB, W\n\nPnr 11147\n\nStockholm, Hamng 13. Tel\n08-1169 95. Bankgiro 168-7979.\nPostgiro 156931-8. Tga Kriszatab\nVerksamhet: Geodetiska o optiska\ninstrument\n\nVarunamn: Kordinatografer\nAktiekapital: 50000\nVerkst dir: Woldemar Kriszat\nEtableringsår: 1925\nOmbildat till aktiebolag 1937.\n\nKRITBRUKSBOLAGET I\nMALMÖ, AB\n\nPnr 200 29\n\nMalmö 29, Box 29031. Tel\n040-4917 40. Bankgiro 64-0047. Postr\ngiro 38778. Tga Malmökrita\n\nPigment för färg-,\nplast-och\n\ngummiindustrin\n\nVerksamhet: Tillverkar slammad\nkrita, finfraktionerad krita,\nytbehandlad krita o foderkrita\nFörsäljning: Malmsten &amp; Bergvall,\n\nGöteborg\n\nVarunamn: Sjöhästen\nAntal anställda: 35\nÅrsomsättning: 2 500 000\nAktiekapital: 500 000\nStyrelse: Disp Gunnar Berup (ordf),\nark Axel Sjöberg, dir Hugo Sjöberg\nVerkst dir: Hugo Sjöberg\nKamrer: Nils Hellborg\nEtableringsår: 1914.\n\nFASADRENOVERING, AB\n\nPnr 692 00\n\nKumla, Box 63. Tel 019-754 75.\nBankgiro 606-2111. Postgiro\n385386-8\n\nVerksamhet: Putsningsarbeten\nAntal anställda: 59\nÅrsomsättning: 3 900 000\nAktiekapital: 15 000\nVerkst dir: Albert Svensson\nEtableringsår: 1954.\n\nMEKANOVERKEN, AB\n\nPnr 33012\n\nForsheda, Box 100. Tel\n0370-812 80. Bankgiro 29-1622. Postgiro\n330677. Tga Mekano\n\nVerksamhet: Tillverkar\nhusgerådsartiklar samt pressade massartiklar\nVarunamn: M V Forsheda\nAntal anställda: 45\nÅrsomsättning: 3 500 000\nAktiekapital: 40 000\nVerkst dir: Sune Sjöberg\nFörsäljn-chef: Vilhelm Lundberg\nVerkmäst: Per Bennedahl\nEtableringsår: 1946.",
    "structured": {
        "1": {
            "company_name": "NORDALS HÄRADS SPARBANK",
            "pnr": "464 00",
            "address": "Box 72. Köpmantorget 1. Mellerud",
            "phone_number": "0530-114 85",
            "bank_details": {
                "bankgiro": "981-2348",
                "postgiro": "172908-6"
            },
            "activity": "Bankrörelse",
            "employees": 21,
            "key_personnel": [
                {
                    "name": "Folke Bäckström",
                    "position": "Verkst dir"
                }
            ]
        },
        "2": {
            "company_name": "NORDBAKELS, AB",
            "pnr": "400 13",
            "address": "Göteborg 36, von Holtensg 1, Box 36063",
            "phone_number": "031-19 2500",
            "bank_details": {
                "bankgiro": "42-0136",
                "postgiro": "46729"
            },
            "activity": "Halvfabrikat för bageri- o konditoribranschen samt restauranger o storkök",
            "employees": 160,
            "annual_turnover": 50000000,
            "capital": 1750000,
            "key_personnel": [
                {
                    "name": "Birger Norlander",
                    "position": "Verkst dir"
                }
            ],
            "establishment_year": 1942
        },
        "3": {
            "company_name": "NORDBERGS VAGNFABRIK AB, GUSTAF",
            "pnr": "11161",
            "address": "Stockholm, Tegnërg 37",
            "phone_number": "08-10 8611, 21 26 38",
            "postgiro": "155416",
            "activity": "Reparerar bilar o karosserier",
            "employees": 8,
            "annual_turnover": 600000,
            "capital": 22000,
            "key_personnel": [
                {
                    "name": "Nils Nordberg",
                    "position": "Verkst dir"
                }
            ],
            "establishment_year": 1901
        },
        "4": {
            "company_name": "WIKMAN & MALMKJELL AB",
            "pnr": "104 22",
            "address": "Stockholm 22, Fack. Hantverkarg 8",
            "phone_number": "08-5205 05",
            "bank_details": {
                "bankgiro": "166-0075",
                "postgiro": "604278-2"
            },
            "activity": "Säljer verktygsmaskiner o mätverktyg",
            "employees": 16,
            "annual_turnover": 10000000,
            "capital": 150000,
            "key_personnel": [
                {
                    "name": "Civiling Ulf Wikman",
                    "position": "Ägare"
                },
                {
                    "name": "Ing K O Malmkjell",
                    "position": "Ing"
                }
            ],
            "establishment_year": 1959
        },
        "5": {
            "company_name": "FROSTA GUMMIFABRIKS AB",
            "pnr": "233 00",
            "address": "Svedala, Börringev. Fabrik o orderkontor",
            "phone_number": "040-40 11 10",
            "bank_details": {
                "bankgiro": "870-3563",
                "postgiro": "247502-8"
            },
            "activity": "Tillverkar skumgummiartiklar",
            "annual_production_value": "Ekonomiavdelning o övriga administrativa avdelningar: Tranås. Tel 0140-130 30",
            "capital": 100000,
            "key_personnel": [
                {
                    "name": "Bo Fjaestad",
                    "position": "Veikst dir"
                },
                {
                    "name": "Ingvar Lindeberg",
                    "position": "Platschef"
                }
            ],
            "establishment_year": 1949
        },
        "6": {
            "company_name": "ELECTROLUX STÄDUTEN. SIL|ER AB",
            "pnr": "10545",
            "address": "Stockholm, Luxbacken 1",
            "phone_number": "08-13 1210, 13 0100",
            "bank_details": {
                "bankgiro": "735-2255",
                "postgiro": "700975-6"
            },
            "activity": "Försäljning av städ-maskiner, städredskap o kemisktekniska produkter, stéd planering o utbildning",
            "employees": 21,
            "annual_turnover": 8000000,
            "capital": 250000,
            "key_personnel": [
                {
                    "name": "Bo Palmberg",
                    "position": "Verkst dir"
                }
            ],
            "establishment_year": 1963
        },
        "7": {
            "company_name": "ELECTROLUX SVENSKA FOR-SÄLJNING5AKTIEBOLAG",
            "pnr": "105 45",
            "address": "Stockholm, Luxbacken 1, Lilla Essingen",
            "phone_number": "08-13 01 00",
            "postgiro": "50125",
            "activity": "Säljer hushållsapparater",
            "employees": 990,
            "annual_turnover": 159675000,
            "capital": 6000000,
            "key_personnel": [
                {
                    "name": "Gösta Bystedt",
                    "position": "Verkst dir"
                }
            ],
            "establishment_year": 1927
        },
        "8": {
            "company_name": "WAHLBECKS FABRIKER, AB",
            "pnr": "581 01",
            "address": "Linköping 1, Fack",
            "phone_number": "013-12 91 40",
            "bankgiro": "120-0294",
            "postgiro": "11429-8",
            "activity": "Textilindustri. Tillverkar o säljer mattor, bindgarn, tågvirke, band m m",
            "employees": 500,
            "annual_turnover": 65000000,
            "capital": 2000000,
            "key_personnel": [
                {
                    "name": "Einar Gullers",
                    "position": "Försäljn-dir"
                },
                {
                    "name": "Töre Börjesson",
                    "position": "dir"
                }
            ],
            "establishment_year": 1876
        },
        "9": {
            "company_name": "WAHLBECK KONSTRUK. TIONSBYRÅ, B",
            "pnr": "601 04",
            "address": "Norrköping 1, Drottningg 5. Box 244",
            "phone_number": "011-16 86 92, 12 50 92",
            "bankgiro": "349-1057",
            "postgiro": "511763-5",
            "activity": "Konstruerar VVS-anläggningar för industrier",
            "employees": 6,
            "key_personnel": [
                {
                    "name": "Ing Bertil Wahlbeck",
                    "position": "Chef"
                }
            ],
            "establishment_year": 1959
        },
        "10": {
            "company_name": "INDUSTRIMODELL, AB",
            "pnr": "550 02",
            "address": "Jönköping 2, Box 2046",
            "phone_number": "036-12 5295",
            "bankgiro": "835-7204",
            "postgiro": "278249-8",
            "activity": "Tillverkar trä-, järn-o metallmodeller, kompletta brätt-utrustningar. Utför mek arbeten, kilrepssklvor",
            "employees": 17,
            "annual_turnover": 1000000,
            "capital": 60000,
            "key_personnel": [
                {
                    "name": "Fabr Assar Petersson",
                    "position": "ordf"
                },
                {
                    "name": "Fabr Ladhe Petersson",
                    "position": "fabr"
                }
            ],
            "establishment_year": 1944
        },
        "11": {
            "company_name": "INDUSTRIMONTERING AB",
            "pnr": "14146",
            "address": "Huddinge, Dalhemsv 48",
            "phone_number": "08-757 27 75",
            "bankgiro": "331-4507",
            "postgiro": "255703-1",
            "activity": "Tillverkar stålkonstruktioner. Utför grovplåtsarbeten",
            "employees": 110,
            "annual_turnover": 9000000,
            "capital": 150000,
            "key_personnel": [
                {
                    "name": "Per Arne Bodfäldt",
                    "position": "Vettet dir"
                }
            ],
            "establishment_year": 1946
        },
        "12": {
            "company_name": "HULIN, AB OLOV",
            "pnr": "430 70",
            "address": "Sävedalen, Sotenäsv 16",
            "phone_number": "031-26 44 10",
            "bankgiro": "50-9703",
            "activity": "Trikåvarugrossist",
            "capital": 50000,
            "key_personnel": [
                {
                    "name": "Olov Hulin",
                    "position": "Verkst dir"
                }
            ],
            "establishment_year": 1931
        },
        "13": {
            "company_name": "HULTS SKYLTINDUSTRI AB",
            "pnr": "352 46",
            "address": "Växjö, Verkstadsg 14",
            "phone_number": "0470-13705, 136 02",
            "bankgiro": "668-4492",
            "postgiro": "670052-0",
            "activity": "Tillverkar o säljer ljusskyltar",
            "employees": 25,
            "annual_turnover": 2000000,
            "capital": 25000,
            "key_personnel": [
                {
                    "name": "Jan Hult",
                    "position": "Verkst din"
                }
            ],
            "establishment_year": 1969
        },
        "14": {
            "company_name": "KRISZAT AB, W",
            "pnr": "11147",
            "address": "Stockholm, Hamng 13",
            "phone_number": "08-1169 95",
            "bankgiro": "168-7979",
            "postgiro": "156931-8",
            "activity": "Geodetiska o optiska instrument",
            "employees": 35,
            "capital": 50000,
            "key_personnel": [
                {
                    "name": "Woldemar Kriszat",
                    "position": "Verkst dir"
                }
            ],
            "establishment_year": 1925
        },
        "15": {
            "company_name": "KRITBRUKSBOLAGET I MALMÖ, AB",
            "pnr": "200 29",
            "address": "Malmö 29, Box 29031",
            "phone_number": "040-4917 40",
            "bankgiro": "64-0047",
            "postgiro": "38778",
            "activity": "Tillverkar slammad krita, finfraktionerad krita, ytbehandlad krita o foderkrita",
            "employees": 35,
            "annual_turnover": 2500000,
            "capital": 500000,
            "key_personnel": [
                {
                    "name": "Hugo Sjöberg",
                    "position": "Verkst dir"
                },
                {
                    "name": "Nils Hellborg",
                    "position": "Kamrer"
                }
            ],
            "establishment_year": 1914
        },
        "16": {
            "company_name": "FASADRENOVERING, AB",
            "pnr": "692 00",
            "address": "Kumla, Box 63",
            "phone_number": "019-754 75",
            "bankgiro": "606-2111",
            "postgiro": "385386-8",
            "activity": "Putsningsarbeten",
            "employees": 59,
            "annual_turnover": 3900000,
            "capital": 15000,
            "key_personnel": [
                {
                    "name": "Albert Svensson",
                    "position": "Verkst dir"
                }
            ],
            "establishment_year": 1954
        },
        "17": {
            "company_name": "MEKANOVERKEN, AB",
            "pnr": "33012",
            "address": "Forsheda, Box 100",
            "phone_number": "0370-812 80",
            "bankgiro": "29-1622",
            "postgiro": "330677",
            "activity": "Tillverkar husgerådsartiklar samt pressade massartiklar",
            "employees": 45,
            "annual_turnover": 3500000,
            "capital": 40000,
            "key_personnel": [
                {
                    "name": "Sune Sjöberg",
                    "position": "Verkst dir"
                },
                {
                    "name": "Vilhelm Lundberg",
                    "position": "Försäljn-chef"
                },
                {
                    "name": "Per Bennedahl",
                    "position": "Verkmäst"
                }
            ],
            "establishment_year": 1946
        }
    }
}