{
    "original": "BJÖRKGREN AB, HARALD\n\nPnr 17151\n\nSolna, Hagalundsg 25. Tel\n08-730 03 45. Bankgiro 56-3500.\nTelex 10768\n\nVerksamhet: Agenturer inom\nelektronik o finmekanik\nAktiekapital: 50000\nVerkst dir: Ing Mats Björkgren\nEtableringsår: 1925.\n\nBJÖRKHOLM, BYGGNADS\nAB ERIK\n\nPnr 724 65\n\nVästerås, Birgittav 24. Tel\n021-1453 10, 187055. Bankgiro\n68-1895. Postgiro 109527\nVerksamhet: Byggnadsentreprenör.\nUtför schaktningar\nAntal anställda: 35\nÅrsomsättning: 3 500 000\nAktiekapital: 10 000\nVerkst dir: Byggmäst Erik\nBjörkholm\n\nEtableringsår: 1955.\n\nBJÖRKLUND &amp; CO MEKANISKA\nVERKSTAD AB\n\nPnr 630 08\n\nEskilstuna8, Box8011. Vikingag29.\nTel 0 26-13 66 58. Postgiro 290604-8\nVerksamhet: Tillverkar\nkonservöppnare, termometerbeslag. Utför\npressarbeten o automatsvarvning\nVarunamn: Boco\nAktiekapital: 50 000\nVerkst dir: Fabr Erik Björklund\nEtableringsår: 1945.\n\nBJÖRKLUND &amp; ERIXON,\nSMIDES AB\n\nPnr 641 00\n\nKatrineholm, Portunag 11. Tel\n0150-137 39. Bankgiro 61-7178.\nPostgiro 104478\n\nVerksamhet: Balkkonstruktioner o\nbyggnadssmide\nAntal anställda: 15\nÅrsomsättning: 245 000\nAktiekapital: 5 000\nFirmatecknare: Karl Olov\nBjörklund, Bror Erixon, Arne Björklund\nEtableringsår: 1960.\n\nMODIG, NILS\n\nPnr 402 61\n\nGöteborg 17, Björcksg 49. Box\n17048. Tel 031-250265. Bankgiro\n51-5235. Postgiro 425798. Tga\nEnnemtex. Telex 2385 MODIG S\nVerksamhet: Maskiner, tiUbehör o\nservice för textiUndustrin\nÄgare o chef: Nils Modig\nEtableringsår: 1948.\n\nCAREN AB\n\nPnr 112 28\n\nStockholm, Pipersg 31. Tel\n08-54 52 90. Bankgiro 563-6139.\nPostgiro 197248-8\n\nVerksamhet: Tillverkar allt i\nskyltdockor\n\nAktiekapital: 5 000\nVerkst dir: E H Carenfelt\nEtableringsår: 1958.\n\nSJOGÄRD AB, UNO\n\nPnr 41135\n\nGöteborg, Chalmersg 19. Tel 031-\n\n201068, 20 1089. Bankgiro 50-0607.\nPostgiro 425422. Tga Chemtrade\nVerksamhet: Import o export,\nhandel i fast räkning samt\nagentur-rörelse i tunga kemikalier för\npappers-, färg-, gummi-, plast- o kem\ntekn industrierna\nAntal anställda: 3\nÅrsomsättning: 3 500 000\nAktiekapital: 100 000\nVeikst dir. Uno Sjögärd\nEtableringsån 1952\nOmbildat till aktiebolag 1963.\n\nSJÖHEDS MEK VERKSTAD, AB\n\nPnr 310 63\n\nÄlvsered, Postl 570. Tel\n0325-31047. Bankgiro 552-8195.\nPostgiro 233190-8\n\nVerksamhet: Tillverkar\ngaffeltruckar för brädgårdar, industrier m m\nAntal anställda: 9\nÅrsomsättning: 500000\nAktiekapital: 60 000\nVerkst dir: Sven Sjöhede\nEtableringsår: 1942.\n\nSCANIA-BILAR I ÖREBRO AB\n\nPnr 70106\n\nÖrebro 1, Box 446. Osterängsg 2.\nTel 019-12 48 00. Bankgiro\n463-1206. Postgiro 141350-9\nVerksamhet: Säljer o reparerar\nVolkswagen person- o\ntransport-bilar, Scania lastbilar o bussar.\nReservdels-, däck- o\nbensinförsäljning\n\nVarunamn: Volkswagen, Scania\nAntal anstäUda: 240\nÅrsomsättning: 36 000 000\nAktiekapital: 2 000 000\nVerkst dir: Göran Molén\nEtableringsår: 1933\nDotterbolag till Saab-Scania,\nSödertälje.\n\nSCANIA-BUSSAR AB\n\nPnr 64100\n\nKatrineholm, Vingåkersv 71. Box\n6. Tel 0150-131 50.\nTga Scaniabuss. Telex 64026\nVerksamhet: Tillverkar bussar o\nbusschassier\nAntal anstäUda: 420\nÅrsomsättning: 54 000000\nAktiekapital: 5 000 000\nStyrelse: Dir Erik Nilsson (ordf),\ndir Carl-Johan Lewenhagen, dir\nSverker Sjöström, dir Rolf Sundeman\nVerkst dir: Rolf Sundeman\nEtableringsår: 1967.\n\nSCANIA.METALL KB,\nWIDELL &amp; NORD\n\nPnr 21125\n\nMalmö, Sankt Gertrudsg 3. Tel\n040-747 10. Bankgiro 700-0946.\nPostgiro 450676-2. Tga Metallscania.\nTelex 32402 SCANMET S\nVerksamhet: Grossiströrelse i\nmetallskrot o metaller, såväl import\nsom export\n\nÅrsomsättning: 30 000 000\nAndelskapital: 50 000\nEtableringsår 1950.\n\nSLÄTTENS INDUSTRIER, AB\n\nPnr 560 20\n\nNorrahammar. Tel 036-610 20.\nBankgiro 83-5832. Postgiro 144142.\nTga Slättens\n\nVerksamhet: Tillverkar o säljer\nhammocks, trädgårdsparasoller,\nträdgårdsmöbler o d\nVarunamn: Slättens\nAntal anställda: 50\nÅrsomsättning: 8 000 000\nAktiekapital: 180 000\nVerkst dir: Karl P Erenhag\n\nSME\n\nDriftchef: Ake Freij\n\nKamrer: Sture Böris\n\nEtableringsår: 1932\n\nOmbildat till aktiebolag 1959. Dot-\n\nterbolag: Trofé AB, Norrahammar.\n\nSLUINGE INDUSTRI AB\n\nPnr 310 50\n\nSlöinge, Box 97. Tel 0346-40370.\nBankgiro 43-3957. Postgiro 672388\nVerksamhet: Glassfabrik,\nkaramellfabrik (fruktmarmelad)\nAntal anställda: 35\nÅrsomsättning: 3 000 000\nAktiekapital: 50 000\nStyrelse: Distr-chef Bernt\nSten-ström(ordf), kamrer Boris Eriksson,\ndisp Olof Stenström\nVerkst dir: Disp Olof Stenström\nPlatschef: Boris Eriksson\nEtableringsår: 1961.\n\nSLUINGE TRÄ.\nFURÄDLINGS AB\n\nPnr 310 50\n\nSlöinge, Box 5. Tel 0346-400 06,\n402 66. Bankgiro 43-3904. Postgiro\n135495. Tga Träförädling\nVerksamhet: Fabrik för\nbyggnadssnickerier. Sågverk. Säljer trävaror\no byggmaterial\nAntal anställda: 25\nÅrsomsättning: 1800 000\nAktiekapital: 120 000\nVerkst dir: Sven-Erik Christianson\nEtableringsår: 1901.\n\nAR LEMARK GLAS, AB\n\nPnr 21611\n\nMalmö, Kalkbrotts g 61. Tel\n040-15 30 15. Bankgiro 847-8091.\nPostgiro 539632-0. Tga Arlemarkglas\nVerksamhet: Engrosförsäljning av\nplanglas, bilrutor o plastglas\nAvdelningskontor: Huskvarna,\nLinnég 3. Tel 036-13 50 55, 13 50 56\nVerkst dir: E Ariemark\nEtableringsår: 1960.\n\nMOTALA TRIKÄFABRIK, AB\n\nPnr 591 01\n\nMotala 1, Sjö g 17. Box 28. Tel\n0141-16300. Bankgiro 134-1700.\nPostgiro 32083-8. Tga Trickson\nVerksamhet: Tillverkar barn-,\ndam-o herrunderkläder, sportdräkter\nAntal anställda: 95\nÅrsomsättning: 3 000 000\nAktiekapital: 380000\nVerkst din Disp Arthur Olsson\nEtableringsår: 1899.\n\nTIVOKEMI AB\n\nPnr 21137\n\nMalmö, Stora Nyg 21. Tel\n040-129710,129711. Bankgiro 87-5574.\nPostgiro 531742. Tga Tivotrade\nVerksamhet: Tillverkar speciallim\nför industrin\nAktiekapital: 100000\nVerkst dir: H Homann\nEtableringsår. 1959.\n\nMEKANISERINGSVERKEN AB\n\nPnr 695 00\n\nLaxå, Lassåna. Tel 0584-11138.\nBankgiro 574-8660. Postgiro\n213090-4\n\nVerksamhet: Tillverkar form- o\npressverktyg\nAntal anställda: 14\nÅrsomsättning: 700 000\nAktiekapital: 50 000\nStyrelse: Dir Sture Emilson (ordf),\nfabr Sven O Kumlin, fabr Ingemar\nÄrneteg\n\nVerkst dir: Ingemar Ärneteg\nEtableringsår: 1963.",
    "structured": {
        "1": {
            "company_name": "BJÖRKGREN AB, HARALD",
            "pnr": "17151",
            "address": "Solna, Hagalundsg 25",
            "phone_number": "08-730 03 45",
            "bank_details": {
                "bankgiro": "56-3500"
            },
            "activity": "Agenturer inom elektronik o finmekanik",
            "capital": 50000,
            "key_personnel": [
                {
                    "name": "Ing Mats Björkgren",
                    "position": "Verkst dir"
                }
            ],
            "establishment_year": 1925
        },
        "2": {
            "company_name": "BJÖRKHOLM, BYGGNADS AB ERIK",
            "pnr": "724 65",
            "address": "Västerås, Birgittav 24",
            "phone_number": "021-1453 10, 187055",
            "bank_details": {
                "bankgiro": "68-1895",
                "postgiro": "109527"
            },
            "activity": "Byggnadsentreprenör. Utför schaktningar",
            "employees": 35,
            "annual_turnover": 3500000,
            "capital": 10000,
            "key_personnel": [
                {
                    "name": "Byggmäst Erik Björkholm",
                    "position": "Verkst dir"
                }
            ],
            "establishment_year": 1955
        },
        "3": {
            "company_name": "BJÖRKLUND & CO MEKANISKA VERKSTAD AB",
            "pnr": "630 08",
            "address": "Eskilstuna8, Box8011. Vikingag29",
            "phone_number": "0 26-13 66 58",
            "bank_details": {
                "postgiro": "290604-8"
            },
            "activity": "Tillverkar konservöppnare, termometerbeslag. Utför pressarbeten o automatsvarvning",
            "capital": 50000,
            "key_personnel": [
                {
                    "name": "Fabr Erik Björklund",
                    "position": "Verkst dir"
                }
            ],
            "establishment_year": 1945
        },
        "4": {
            "company_name": "BJÖRKLUND & ERIXON, SMIDES AB",
            "pnr": "641 00",
            "address": "Katrineholm, Portunag 11",
            "phone_number": "0150-137 39",
            "bank_details": {
                "bankgiro": "61-7178",
                "postgiro": "104478"
            },
            "activity": "Balkkonstruktioner o byggnadssmide",
            "employees": 15,
            "annual_turnover": 245000,
            "capital": 5000,
            "key_personnel": [
                {
                    "name": "Karl Olov Björklund",
                    "position": "Firmatecknare"
                },
                {
                    "name": "Bror Erixon",
                    "position": "Firmatecknare"
                },
                {
                    "name": "Arne Björklund",
                    "position": "Firmatecknare"
                }
            ],
            "establishment_year": 1960
        },
        "5": {
            "company_name": "MODIG, NILS",
            "pnr": "402 61",
            "address": "Göteborg 17, Björcksg 49. Box 17048",
            "phone_number": "031-250265",
            "bank_details": {
                "bankgiro": "51-5235",
                "postgiro": "425798"
            },
            "activity": "Maskiner, tiUbehör o service för textiUndustrin",
            "key_personnel": [
                {
                    "name": "Nils Modig",
                    "position": "Ägare o chef"
                }
            ],
            "establishment_year": 1948
        }
    }
}