{
    "original": "STÅNGÅ SNICKERIFABRIK AB\n\nPnr 860 20\n\nNjurunda, Box 710. Tel 060-300 11,\n\n30015. Bankgiro 775-9533.\nPostgiro 284628-5\n\nVerksamhet: Tillverkar\nbyggnadssnickerier. Specialitet: fönster\nAntal anställda: 10\nÅrsomsättning: 800 000\nAktiekapital: 35 000\nVerkst dir: Gustaf Kjellström\nEtableringsår: 1960.\n\nMARKSLOJD AB\n\nPnr 51100\n\nKinna, Backagårdsv. Tel\n0320-106 80. Bankgiro 546-1660.\nPostgiro 618080-6\n\nVerksamhet: Tillverkar o säljer\nsvarvat trä såsom\nbelysningsarmaturer o ljusstakar. Lampskärmar i\ntextil\n\nAntal anställda: 25\n\nÅrsomsättning: 4 000 000\nAktiekapital: 180 000\nStyrelse: Dir Owe Westlander\nVerkst dir: Owe Westlander\nEtableringsår: 1963.\n\nCE GE HANDTRYCK\n\nPnr 17147\n\nSolna, Hannebergsg 24. Tel\n08-83 38 79\n\nVerksamhet: Tillverkar standar,\nutför textiltryck\n\nÄgare o chef: Carl Gustav Jonsson\nEtableringsår: 1957.\n\nCEAB, CERVINS\nELEKTRISKA AB\n\nPnr 413 21\n\nGöteborg, Fyrverkareg 14. Tel\n031-20 12 10, 1841 34. Bankgiro\n44-2307. Postgiro 47985\nVerksamhet: Elektriska\ninstallationer\n\nAntal anställda: 15\nÅrsomsättning: 1500 000\nAktiekapital: 10 000\nVerkst dir: Ing Carl-Axel Cervin\nEtableringsår: 1960.\n\nBÄC\n\n7T7 1600, 77716 01. Bankgiro\n733-3297. Postgiro 199349-2. Tga\nBåknol\n\nVerksamhet; Kemisk-teknisk fabrik\nför tillverkning av\nfuktisolerings-material o tätningsmedel till\nbyggnads- o anläggningsindustrin\nFabrik o försäljn-kontor: 136 44\nHanden, Hantverkarv 41. Tel\n08-77716 00, 777 16 01\nAntal anställda: 9\nÅrsomsättning: 1100 000\nAktiekapital: 60 000\nVerkst dir. Ing Gustaf Båke\nFörsäljn-chef: Ing Stig Kanbåge\nFabrikschef: Verkm Richard\nSandgren\n\nEtableringsår: 1960.\n\nARBMAN AB, STIG\n\nPnr 101 10\n\nStockholm 1, Kungsg 62. Fack. Tel\n08-14 1740. Bankgiro 167-0579.\nPostgiro 353656-2. Tga\nArbman-reklam. Telex 17097\nVerksamhet: Annonsbyrå\nAntal anställda: 100\nÅrsomsättning: 50 000000\nAktiekapital: 300 000\nVerkst din Léon Nordin\nEtableringsår: 1953.\n\nMAS\n\nmaskinprodukter jonsson\n&amp; häljestig ab\n\nPnr 33102\n\nVärnamo 2, Box 2082. Tel\n0370-156 70. Bankgiro 141-8136.\nPostgiro 325270-7\n\nVerksamhet: Tillverkar\nsnäckväx-lar. Fräsning av kugghjul o\nsnäckhjulssatser. Kuggstänger\nVarunamn: EMPRO\nAntal anstäUda: 38\nÅrsomsättning: 4 000 000\nAktiekapital: 40 000\nVerkst dir: Kurt Häljestig\nEtableringsår: 1946\nOmbildat till aktiebolag 1960.\n\nmaskinskyltfabriken ab\nornamentik\n\nPnr 632 21\n\nEskilstuna, Ståhlbergsv 13. Tel\n016-13 78 10. Bankgiro 828-048 9.\nPostgiro 10696-3\n\nVeiksamhet: Tillverkar etsade-,\nanodoxiderade infärgade, tryckta\no graverade skyltar, skalor,\ninstrumenttavlor, instrumentpaneler o\nfrontar. Dekaler o självhäftande\neti-ketter. Reklamtryck. Schabloner.\nMaskingravyr. Eloxering av\naluminium. Tryckta ledningskretsar\nAktiekapital: 500 000\nVerkst dir: Civiling Rolf Dahlberg\nEtableringsår: 1905.\n\nJUTEX, AGENTURFIRMA\n\nPnr 23011\n\nFalsterbo, Skärfläckev 11. Tel\n040-47 03 66. Tga Jutex\nVerksamhet: Säljer sil-, sikt- o\nfilterduk av nylon, polyester,\nsiden o metall\n\nÄgare o chef: Dir E Balk-Möller\nEtableringsår: 1937.\n\nELDRIFT, AB\n\nPnr 11659\n\nStockholm, Havreg 11-13. Tel\n08-44 41 26, 44 41 02. Bankgiro\n57-3325. Postgiro 254097\nVerksamhet: Lindar om o reparerar\nelmotorer, svetsmaskiner o andra\nelektr maskiner o apparater\nAktiekapital: 15 000\nVerkst dir: Ake Ljungberg\nEtableringsår: 1947.\n\nLJUNGSKO, AB\n\nPnr 311 00\n\nFalkenberg. Tel 0346-17210.\nBankgiro 36-1324. Postgiro 464127\nVerksamhet: Tillverkar klistrade o\nsandalsydda barn- o promenadskor\nAntal anställda: 50\nÅrsomsättning: 2700000\nStyrelseordf: Dir Sven H Nilsson\nEtableringsår: 1946.\n\nLJUNGSTRUMS KON FE K.\nTIONSFABRIK, AB\n\nPnr 643 00\n\nVingåker. Tel 0151-11515. Tga\nSirklaeder\n\nVerksamhet: Tillverkar herrkläder\nAntal anställda: 1100\nÅrsomsättning: 45 000 000\nAktiekapital: 400 000\nVerkst dir: V Ljungström\nEtableringsår: 1925.\n\nADÉLLS PATENTBYRÄ, B-l\n\nPnr 552 59\n\nJönköping, Bellevueg 5 B. Tel\n036-1210 34. Bankgiro 140-1686.\nPostgiro 46222C-5\nVerksamhet: Utför patent- o\nvarumärkesansökningar för in- o\nutlandet, mönsterskydd\nChef: Civiling B-I Adéll.\n\nADÉN COMPANY AB\n\nPnr 11139\n\nStockholm, Regeringsg 89. Tel\n08-10 63 15. Tga Adencompany\nVerksamhet: Import o export av\nkemikalier o maskiner\nAktiekapital: 10 000\nVerkst dir: G Adén\nEtableringsår: 1947.",
    "structured": {
        "1": {
            "company_name": "STÅNGÅ SNICKERIFABRIK AB",
            "pnr": "860 20",
            "address": "Njurunda, Box 710",
            "phone_number": "060-300 11",
            "bank_details": {
                "bankgiro": "775-9533",
                "postgiro": "284628-5"
            },
            "activity": "Tillverkar byggnadssnickerier",
            "annual_turnover": 800000,
            "capital": 35000,
            "key_personnel": [
                {
                    "name": "Gustaf Kjellström",
                    "position": "Verkst dir"
                }
            ],
            "establishment_year": 1960
        },
        "2": {
            "company_name": "MARKSLOJD AB",
            "pnr": "51100",
            "address": "Kinna, Backagårdsv",
            "phone_number": "0320-106 80",
            "bank_details": {
                "bankgiro": "546-1660",
                "postgiro": "618080-6"
            },
            "activity": "Tillverkar o säljer svarvat trä",
            "annual_turnover": 4000000,
            "capital": 180000,
            "key_personnel": [
                {
                    "name": "Owe Westlander",
                    "position": "Styrelse: Dir"
                },
                {
                    "name": "Owe Westlander",
                    "position": "Verkst dir"
                }
            ],
            "establishment_year": 1963
        },
        "3": {
            "company_name": "CE GE HANDTRYCK",
            "pnr": "17147",
            "address": "Solna, Hannebergsg 24",
            "phone_number": "08-83 38 79",
            "activity": "Tillverkar standar, utför textiltryck",
            "key_personnel": [
                {
                    "name": "Carl Gustav Jonsson",
                    "position": "Ägare o chef"
                }
            ],
            "establishment_year": 1957
        },
        "4": {
            "company_name": "CEAB, CERVINS ELEKTRISKA AB",
            "pnr": "413 21",
            "address": "Göteborg, Fyrverkareg 14",
            "phone_number": "031-20 12 10, 1841 34",
            "bank_details": {
                "bankgiro": "44-2307",
                "postgiro": "47985"
            },
            "activity": "Elektriska installationer",
            "annual_turnover": 1500000,
            "capital": 10000,
            "key_personnel": [
                {
                    "name": "Ing Carl-Axel Cervin",
                    "position": "Verkst dir"
                }
            ],
            "establishment_year": 1960
        },
        "5": {
            "company_name": "BÄC",
            "address": "136 44 Handen, Hantverkarv 41",
            "phone_number": "08-77716 00, 777 16 01",
            "bank_details": {
                "bankgiro": "733-3297",
                "postgiro": "199349-2"
            },
            "activity": "Kemisk-teknisk fabrik för tillverkning",
            "annual_turnover": 1100000,
            "capital": 60000,
            "key_personnel": [
                {
                    "name": "Ing Gustaf Båke",
                    "position": "Verkst dir"
                },
                {
                    "name": "Ing Stig Kanbåge",
                    "position": "Försäljn-chef"
                },
                {
                    "name": "Verkm Richard Sandgren",
                    "position": "Fabrikschef"
                }
            ],
            "establishment_year": 1960
        },
        "6": {
            "company_name": "ARBMAN AB, STIG",
            "pnr": "101 10",
            "address": "Stockholm 1, Kungsg 62",
            "phone_number": "08-14 1740",
            "bank_details": {
                "bankgiro": "167-0579",
                "postgiro": "353656-2"
            },
            "activity": "Annonsbyrå",
            "annual_turnover": 50000000,
            "capital": 300000,
            "key_personnel": [
                {
                    "name": "Léon Nordin",
                    "position": "Verkst dir"
                }
            ],
            "establishment_year": 1953
        },
        "7": {
            "company_name": "MAS maskinprodukter jonsson & häljestig ab",
            "pnr": "33102",
            "address": "Värnamo 2, Box 2082",
            "phone_number": "0370-156 70",
            "bank_details": {
                "bankgiro": "141-8136",
                "postgiro": "325270-7"
            },
            "activity": "Tillverkar snäckväx-lar",
            "annual_turnover": 4000000,
            "capital": 40000,
            "key_personnel": [
                {
                    "name": "Kurt Häljestig",
                    "position": "Verkst dir"
                }
            ],
            "establishment_year": 1946
        },
        "8": {
            "company_name": "maskinskyltfabriken ab ornamentik",
            "pnr": "632 21",
            "address": "Eskilstuna, Ståhlbergsv 13",
            "phone_number": "016-13 78 10",
            "bank_details": {
                "bankgiro": "828-048 9",
                "postgiro": "10696-3"
            },
            "activity": "Tillverkar etsade-",
            "annual_turnover": null,
            "capital": 500000,
            "key_personnel": [
                {
                    "name": "Civiling Rolf Dahlberg",
                    "position": "Verkst dir"
                }
            ],
            "establishment_year": 1905
        },
        "9": {
            "company_name": "JUTEX, AGENTURFIRMA",
            "pnr": "23011",
            "address": "Falsterbo, Skärfläckev 11",
            "phone_number": "040-47 03 66",
            "activity": "Säljer sil-, sikt- o filterduk av nylon",
            "key_personnel": [
                {
                    "name": "Dir E Balk-Möller",
                    "position": "Ägare o chef"
                }
            ],
            "establishment_year": 1937
        },
        "10": {
            "company_name": "ELDRIFT, AB",
            "pnr": "11659",
            "address": "Stockholm, Havreg 11-13",
            "phone_number": "08-44 41 26, 44 41 02",
            "bank_details": {
                "bankgiro": "57-3325",
                "postgiro": "254097"
            },
            "activity": "Lindar om o reparerar elmotorer",
            "capital": 15000,
            "key_personnel": [
                {
                    "name": "Ake Ljungberg",
                    "position": "Verkst dir"
                }
            ],
            "establishment_year": 1947
        },
        "11": {
            "company_name": "LJUNGSKO, AB",
            "pnr": "311 00",
            "address": "Falkenberg",
            "phone_number": "0346-17210",
            "bank_details": {
                "bankgiro": "36-1324",
                "postgiro": "464127"
            },
            "activity": "Tillverkar klistrade o sandalsydda",
            "annual_turnover": 2700000,
            "key_personnel": [
                {
                    "name": "Dir Sven H Nilsson",
                    "position": "Styrelseordf"
                }
            ],
            "establishment_year": 1946
        },
        "12": {
            "company_name": "LJUNGSTRUMS KON FE K. TIONSFABRIK, AB",
            "pnr": "643 00",
            "address": "Vingåker",
            "phone_number": "0151-11515",
            "activity": "Tillverkar herrkläder",
            "annual_turnover": 45000000,
            "capital": 400000,
            "key_personnel": [
                {
                    "name": "V Ljungström",
                    "position": "Verkst dir"
                }
            ],
            "establishment_year": 1925
        },
        "13": {
            "company_name": "ADÉLLS PATENTBYRÄ, B-l",
            "pnr": "552 59",
            "address": "Jönköping, Bellevueg 5 B",
            "phone_number": "036-1210 34",
            "bank_details": {
                "bankgiro": "140-1686",
                "postgiro": "46222C-5"
            },
            "activity": "Utför patent- o varumärkesansökningar",
            "key_personnel": [
                {
                    "name": "Civiling B-I Adéll",
                    "position": "Chef"
                }
            ]
        },
        "14": {
            "company_name": "ADÉN COMPANY AB",
            "pnr": "11139",
            "address": "Stockholm, Regeringsg 89",
            "phone_number": "08-10 63 15",
            "activity": "Import o export av kemikalier o maskiner",
            "capital": 10000,
            "key_personnel": [
                {
                    "name": "G Adén",
                    "position": "Verkst dir"
                }
            ],
            "establishment_year": 1947
        }
    }
}