{
    "original": "VIKARBYVERKEN, AB\n\nPnr 790 60\n\nVikarbyn, Västbjörka. Tel\n0248-20160. Bankgiro 798-0717.\nPostgiro 358567-6. Tga Viverk, Rättvik\nVerksamhet: Tillverkar jord- o\nsonderingsborrar samt\ntransportvagnar. Utför grovplåts- o mek\narbeten\n\nAntal anställda: 6\nÅrsomsättning: 250 000\nAktiekapital: 45000\nVerkst din Skommar Hans\nAndersson\nEtableringsår: 1948.\n\nJOK\n\n2039. Tel 031-513140. Bankgiro\n33-7647. Postgiro 41061. Tga\nJohn-fredab\n\nVerksamhet: VVS-grossist\nAntal anställda: 40\nAktiekapital: 200 000\nVerkst dir: Fru G Ander-Nyholm\nEtableringsår: 1908.\n\nSKOGLUND, AB GÖSTA M\n\nPnr 10273\n\nStockholm 9, Box 9225. Arstaängsv\n1. Tel 08-68 0565. Bankgiro\n573-4074. Postgiro 551402-1. Tga\nSkog-paper\n\nVerksamhet: Försäljning av\nbyggnadsvaror. Akerirörelse\nAntal anställda: 25\nÅrsomsättning: 2 000000\nAktiekapital: 125 000\nVerkst dir: Gösta Skoglund\nEtableringsår: 1948.\n\nSKOGLOSA MEK VERKSTAD\nAB\n\nPnr 290 28\n\nOnnestad, Box 176. Tel 044-70440,\n704 49. Bankgiro 236-1368. Postgiro\n441733-3\n\nVerksamhet: Tillverkar inredning o\nsvetsade rörkonstruktioner för\ndjurstallar mm. Beställningsarbeten.\nSmekab rörkorsklammern\nVarunamn: Smekab\nAntal anställda: 25\nÅrsomsättning: 2600 000\nAktiekapital: 100 000\nVerkst dir: Ing Göran Skoglösa\nVerkstadschef: Ing Lars Fröjd\nEtableringsår: 1961.\n\nBASF SVENSKA AB\n\nPnr 400 14\n\nGöteborg 53, Box 53008.\nKungs-portsavenyn 31-35. Tel031-81 3260.\nBankgiro 50-0565. Postgiro 49255.\nTga Basimport. Telex 2327\nVerksamhet: Säljer anilinfärger,\nkemikalier, tonband, databand etc\nAvdelningskontor: 50107 Borås 1,\nSandgärdsg 12-16. Box 427. Tel\n033-1023 20\n\n217 53 Malmö, Ribersborgsv 14 D.\nTel 040-9160 05\n\n171 54 Solna, Vretenv 6. Tel\n08-98 08 40\n\nAntal anställda: 71\nÅrsomsättning: 72 200 000\nAktiekapital: 1500 000\n\nStyrelse: Dir Bertil Thorburn (ordf),\ndir Christian Erasmi, dir Holger\n\nOlsson\n\nVerkst dir: Holger Olsson\nEtableringsår: 1953\nAgent för Badische Anilin- &amp;\nSodafabrik AG.\n\nBASKARPSAND, AB\n\nPnr 560 40\n\nHabo. Tel 036-43150. Bankgiro\n21-8236. Postgiro 32726\nVerksamhet: säljer gjuterisand,\nfilter- o blästersand, skursand,\ngolvsand mm för byggnadsindustrin\nAktiekapital: 200000\nVerkst dir: Folke Mårtensson\nEtableringsår: 1949.\n\nDRYCOLOR AB\n\nPnr 200 31\n\nMalmö 15, Box 15028. Järnyxeg 7.\nTel 040-94 62 60, 94 62 50.\nBankgiro 451-5487. Postgiro 631755-6.\nTga Drycolor.\nTelex 32608 DRYCOL S\nVerksamhet: Tillverkar färgpigment\no färgkoncentrat för plastindustrin\nVarunamn: Drycolor\nAktiekapital: 100 000\nStyrelse: Konsul Torsten Bjurman\n(crdf), ing Peter Jürgensen, disp\nGeert Jürgensen\nVerkst dir: Peter Jürgensen\nEtableringsår: 1964.\n\n\"D.S.\"\nSTÅLMOBEL-FABRIKEN MALMÖ AB\n\nPnr 235 00\n\nVellinge, Hököpinge. Tel\n040-46 64 43, 4667 43. Bankgiro\n64-0407. Postgiro 38830\n\nVerksamhet: Tillverkar\nstålrörs-konstruktioner för sjukhus\nAktiekapital: 10000\nÄgare: Fabrikör I Borgström, frk\nC Dahlberg\nEtableringsår: 1935.\n\nDU PONT de NEMOURS\nNORDISKA AB\n\nPnr 195 00\n\nMärsta, Industrig 1. Tel\n0760-120 60. Bankgiro 446-9755.\nPostgiro 52594-9. Tga Norddupont.\nTelex 10907\n\nVerksamhet: Tillverkar o säljer\nfärger o läcker samt säljer plaster,\nplastfilmer, syntetfibrer,\nindustri-o biokemikalier, elektrokemikalier,\nanalysinstrument, Preon-produkter\no Teflon finish\nFörsäljningskontor:\nSyntetfibrer: Göteborg, Götg 16.\nTel 031-17 79 35\nElektrokemikalier: Helsingborg,\nS Storg 5. Tel 042-12 07 74\nPlaster: Helsingborg, S Storg 5.\nTel 042-12 07 70\n\nPlaster, plastfilmer, syntetfibrer,\nindustri- o biokemikalier,\nPreon-produkter: Herlev/Köpenhamn,\nMarielundvej 41. Tel 91 61 00\nPlaster o syntetfibrer: Helsingfors\n10, P Rautatiekatu 21 C. Tel\n44 06 88\n\nAntal anställda: 248\nÅrsomsättning: 75 000 000\nAktiekapital: 5000000\nVerkst dir: N Envall\nEtableringsår: 1961.\n\nEKPARKETT, AB\n\nPnr 31101\n\nFalkenberg 1, Box 101. Hamnv. Tel\n0346-140 20. Bankgiro 712-4498.\nPostgiro 368180-6. Tga Ekparkett\nVerksamhet: Tillverkar\nlamellpar-kettbrädor i ek o exklusiva träslag\nAntal anställda: 70\nÅrsomsättning: 9000 000\nAktiekapital: 500 000\nVerkst dir: Göran Hellner\nPlatschef: Disp Kurt Johansson\nEtableringsår: 1933\nDotterbolag till Trelleborgs\nGummifabriks AB.\n\nEKSJÖ GOLV AB\n\nPnr 575 00\n\nEksjö, Broarpsv 23. Tel\n0381-132 25. Bankgiro 266-6311.\nPostgiro 644510-0\n\nVerksamhet: Säljer o utför\ngolvbeläggningar. Säljer mattor\nAntal anställda: 11\nÅrsomsättning: 1800 000\nAktiekapital: 25 000\nStyrelse: Byggmäst Gösta Eek\n(ordf), arbetschef Lennart Carlsson,\ngolvläggare Bernt Gustafsson\nVerkst din Gösta Eek\nKamrer: Torsten Carlsson\nArbetschef: Lennart Carlsson\nEtableringsån 1964.\n\nBYGGPAUL AB\n\nPnr 721 20\n\nVästerås 1, Box 704. V Kyrkog 9.\nTel 021-12 01 00. Bankgiro 80-1926.\nPostgiro 271273. Tga Byggpaul.\nTelex 40609 AROS S\nVerksamhet: Bygger o projekterar\nindustri-, förvaltnings- o\nvattenbyggnader, bostäder o broar\nAvdelningskonton Piteå, Storg 33.\nTel 0911-148 22\nHudiksvall, Kålhagsg 36. Tel\n0650-167 92, 167 93\nKarlstad. Box 128. Tel 054-18 70 40\nAntal anställda: 750\nÅrsomsättning: 102 000 000\nAktiekapital: 500 000\nStyrelse: Dir Arne Mattson (ordf),\növering Jan Andberger, adv Björn\nBygge, dir Bengt Mattson, övering\nGunnar Sundberg, dir Karl\nWennersten\n\nVerkst dir: Bengt Mattson\nEtableringsår: 1915\nOmbildat till aktiebolag 1937.\nByggpaul AB ingår jämte Kramo\nMontage AB o Ekebro AB (se även\ndessa företag) som dotterbolag i\nkoncernen Paul Anderson\nIndustrier AB, Västerås.\n\nBYGGPLANERING,\nAB RAGNAR WALE &amp; CO\n\nPnr 102 45\n\nStockholm 5, Box 5242. Linnég\n12-14. Tel 08-23 82 20. Bankgiro\n447-1751. Postgiro 15363-5\nVerksamhet: Konsulterande\ningenjörsbyrå\nAntal anställda: 28\nÅrsomsättning: 2 400 000\nAktiekapital: 30 000\nVerkst dir: Civiling Göran Wale\nEtableringsår: 1959.\n\nHAK\n\nAntal anställda: 11\nInsatskapital: 60000\nChef: Jan Hagenfeldt\nEtableringsår: 1947.\n\nTERRAB AB, TEKNISK REPRO\noch RITMATERIEL\n\nPnr 200 44\n\nMalmö 13, Box 13044. N\nGränges-bergsg 19. Tel 040-868 90.\nBankgiro 151-0205. Postgiro 636160-4.\nTga Terrab. Telex 32622\nVerksamhet: Specialföretag för\nritningsblanketter o ritfilm\nAvdelningskontor: 16212 Vällingby,\nBox 190. Tel 08-37 48 00\n\nVarunamn: Ammo, Arkitex,\nPerma-trace, TerrarDraft, Terra-Trace\nAntal anställda: 7\nAktiekapital: 50 000\nVerkst dir: Ing Thord Rönngard\nEtableringsår: 1968.\n\nekonomi emballage\n\nPnr 16135\n\nBromma, Drottningholmsv 312. Tel\nTel 08-2513 16, 25 0913. Bankgiro\n58-8988. Postgiro 256761\nVerksamhet: Alla slag av\nträemballage\n\nChef: Thorsten Lax\nEtableringsår: 1964.",
    "structured": {
        "1": {
            "company_name": "VIKARBYVERKEN, AB",
            "pnr": "790 60",
            "address": "Vikarbyn, Västbjörka",
            "phone_number": "0248-20160",
            "bank_details": {
                "bankgiro": "798-0717",
                "postgiro": "358567-6"
            },
            "activity": "Tillverkar jord- o sonderingsborrar samt transportvagnar. Utför grovplåts- o mekarbeten",
            "employees": 6,
            "annual_turnover": 250000,
            "capital": 45000,
            "key_personnel": [
                {
                    "name": "Hans Andersson",
                    "position": "Verkst din"
                }
            ],
            "establishment_year": 1948
        },
        "2": {
            "company_name": "JOK",
            "address": "2039",
            "phone_number": "031-513140",
            "bank_details": {
                "bankgiro": "33-7647",
                "postgiro": "41061"
            },
            "activity": "VVS-grossist",
            "employees": 40,
            "capital": 200000,
            "key_personnel": [
                {
                    "name": "Fru G Ander-Nyholm",
                    "position": "Verkst dir"
                }
            ],
            "establishment_year": 1908
        },
        "3": {
            "company_name": "SKOGLUND, AB GÖSTA M",
            "pnr": "10273",
            "address": "Stockholm 9, Box 9225, Arstaängsv 1",
            "phone_number": "08-68 0565",
            "bank_details": {
                "bankgiro": "573-4074",
                "postgiro": "551402-1"
            },
            "activity": "Försäljning av byggnadsvaror. Akerirörelse",
            "employees": 25,
            "annual_turnover": 2000000,
            "capital": 125000,
            "key_personnel": [
                {
                    "name": "Gösta Skoglund",
                    "position": "Verkst dir"
                }
            ],
            "establishment_year": 1948
        },
        "4": {
            "company_name": "SKOGLOSA MEK VERKSTAD AB",
            "pnr": "290 28",
            "address": "Onnestad, Box 176",
            "phone_number": "044-70440, 704 49",
            "bank_details": {
                "bankgiro": "236-1368",
                "postgiro": "441733-3"
            },
            "activity": "Tillverkar inredning o svetsade rörkonstruktioner för djurstallar mm. Beställningsarbeten. Smekab rörkorsklammern",
            "employees": 25,
            "annual_turnover": 2600000,
            "capital": 100000,
            "key_personnel": [
                {
                    "name": "Ing Göran Skoglösa",
                    "position": "Verkst dir"
                },
                {
                    "name": "Ing Lars Fröjd",
                    "position": "Verkstadschef"
                }
            ],
            "establishment_year": 1961
        },
        "5": {
            "company_name": "BASF SVENSKA AB",
            "pnr": "400 14",
            "address": "Göteborg 53, Box 53008, Kungs-portsavenyn 31-35",
            "phone_number": "031-81 3260",
            "bank_details": {
                "bankgiro": "50-0565",
                "postgiro": "49255"
            },
            "activity": "Säljer anilinfärger, kemikalier, tonband, databand etc",
            "branches": {
                "city": "Borås 1",
                "address": "Sandgärdsg 12-16",
                "phone_number": "033-1023 20"
            },
            "employees": 71,
            "annual_turnover": 72200000,
            "capital": 1500000,
            "key_personnel": [
                {
                    "name": "Holger Olsson",
                    "position": "Verkst dir"
                }
            ],
            "establishment_year": 1953
        },
        "6": {
            "company_name": "BASKARPSAND, AB",
            "pnr": "560 40",
            "address": "Habo",
            "phone_number": "036-43150",
            "bank_details": {
                "bankgiro": "21-8236",
                "postgiro": "32726"
            },
            "activity": "Säljer gjuterisand, filter- o blästersand, skursand, golvsand mm för byggnadsindustrin",
            "capital": 200000,
            "key_personnel": [
                {
                    "name": "Folke Mårtensson",
                    "position": "Verkst dir"
                }
            ],
            "establishment_year": 1949
        },
        "7": {
            "company_name": "DRYCOLOR AB",
            "pnr": "200 31",
            "address": "Malmö 15, Box 15028, Järnyxeg 7",
            "phone_number": "040-94 62 60, 94 62 50",
            "bank_details": {
                "bankgiro": "451-5487",
                "postgiro": "631755-6"
            },
            "activity": "Tillverkar färgpigment o färgkoncentrat för plastindustrin",
            "capital": 100000,
            "key_personnel": [
                {
                    "name": "Peter Jürgensen",
                    "position": "Verkst dir"
                }
            ],
            "establishment_year": 1964
        },
        "8": {
            "company_name": "\"D.S.\" STÅLMOBEL-FABRIKEN MALMÖ AB",
            "pnr": "235 00",
            "address": "Vellinge, Hököpinge",
            "phone_number": "040-46 64 43, 4667 43",
            "bank_details": {
                "bankgiro": "64-0407",
                "postgiro": "38830"
            },
            "activity": "Tillverkar stålrörskonstruktioner för sjukhus",
            "capital": 10000,
            "owners": [
                "Fabrikör I Borgström",
                "frk C Dahlberg"
            ],
            "establishment_year": 1935
        },
        "9": {
            "company_name": "DU PONT de NEMOURS NORDISKA AB",
            "pnr": "195 00",
            "address": "Märsta, Industrig 1",
            "phone_number": "0760-120 60",
            "bank_details": {
                "bankgiro": "446-9755",
                "postgiro": "52594-9"
            },
            "activity": "Tillverkar o säljer färger o läcker samt säljer plaster, plastfilmer, syntetfibrer, industri- o biokemikalier, elektrokemikalier, analysinstrument, Preon-produkter o Teflon finish",
            "branches": {
                "syntetfibrer": "Göteborg, Götg 16",
                "elektrokemikalier": "Helsingborg, S Storg 5",
                "plaster": "Helsingborg, S Storg 5",
                "Herlev/Köpenhamn": "Marielundvej 41",
                "Helsingfors": "10, P Rautatiekatu 21 C"
            },
            "employees": 248,
            "annual_turnover": 75000000,
            "capital": 5000000,
            "key_personnel": [
                {
                    "name": "N Envall",
                    "position": "Verkst dir"
                }
            ],
            "establishment_year": 1961
        },
        "10": {
            "company_name": "EKPARKETT AB",
            "pnr": "31101",
            "address": "Falkenberg 1, Box 101, Hamnv",
            "phone_number": "0346-140 20",
            "bank_details": {
                "bankgiro": "712-4498",
                "postgiro": "368180-6"
            },
            "activity": "Tillverkar lamellparkettbrädor i ek o exklusiva träslag",
            "employees": 70,
            "annual_turnover": 9000000,
            "capital": 500000,
            "key_personnel": [
                {
                    "name": "Göran Hellner",
                    "position": "Verkst dir"
                },
                {
                    "name": "Kurt Johansson",
                    "position": "Platschef"
                }
            ],
            "establishment_year": 1933
        },
        "11": {
            "company_name": "EKSJÖ GOLV AB",
            "pnr": "575 00",
            "address": "Eksjö, Broarpsv 23",
            "phone_number": "0381-132 25",
            "bank_details": {
                "bankgiro": "266-6311",
                "postgiro": "644510-0"
            },
            "activity": "Säljer o utför golvbeläggningar. Säljer mattor",
            "employees": 11,
            "annual_turnover": 1800000,
            "capital": 25000,
            "key_personnel": [
                {
                    "name": "Gösta Eek",
                    "position": "Verkst din"
                },
                {
                    "name": "Lennart Carlsson",
                    "position": "Arbetschef"
                },
                {
                    "name": "Bernt Gustafsson",
                    "position": "Golvläggare"
                }
            ],
            "establishment_year": 1964
        },
        "12": {
            "company_name": "BYGGPAUL AB",
            "pnr": "721 20",
            "address": "Västerås 1, Box 704, V Kyrkog 9",
            "phone_number": "021-12 01 00",
            "bank_details": {
                "bankgiro": "80-1926",
                "postgiro": "271273"
            },
            "activity": "Bygger o projekterar industri-, förvaltnings- o vattenbyggnader, bostäder o broar",
            "branches": {
                "Piteå": "Storg 33",
                "Hudiksvall": "Kålhagsg 36",
                "Karlstad": "Box 128"
            },
            "employees": 750,
            "annual_turnover": 102000000,
            "capital": 500000,
            "key_personnel": [
                {
                    "name": "Arne Mattson",
                    "position": "Styrelse ordf"
                },
                {
                    "name": "Jan Andberger",
                    "position": "Övering"
                },
                {
                    "name": "Björn Bygge",
                    "position": "Adv"
                },
                {
                    "name": "Bengt Mattson",
                    "position": "Dir"
                },
                {
                    "name": "Gunnar Sundberg",
                    "position": "Övering"
                },
                {
                    "name": "Karl Wennersten",
                    "position": "Dir"
                }
            ],
            "establishment_year": 1915
        },
        "13": {
            "company_name": "BYGGPLANERING, AB RAGNAR WALE & CO",
            "pnr": "102 45",
            "address": "Stockholm 5, Box 5242, Linnég 12-14",
            "phone_number": "08-23 82 20",
            "bank_details": {
                "bankgiro": "447-1751",
                "postgiro": "15363-5"
            },
            "activity": "Konsulterande ingenjörsbyrå",
            "employees": 28,
            "annual_turnover": 2400000,
            "capital": 30000,
            "key_personnel": [
                {
                    "name": "Göran Wale",
                    "position": "Verkst dir"
                }
            ],
            "establishment_year": 1959
        },
        "14": {
            "company_name": "HAK",
            "employees": 11,
            "investment_capital": 60000,
            "key_personnel": {
                "name": "Jan Hagenfeldt",
                "position": "Chef"
            },
            "establishment_year": 1947
        },
        "15": {
            "company_name": "TERRAB AB, TEKNISK REPRO och RITMATERIEL",
            "pnr": "200 44",
            "address": "Malmö 13, Box 13044, N Grängesbergsg 19",
            "phone_number": "040-868 90",
            "bank_details": {
                "bankgiro": "151-0205",
                "postgiro": "636160-4"
            },
            "activity": "Specialföretag för ritningsblanketter o ritfilm",
            "branches": {
                "Vällingby": "Box 190"
            },
            "brands": [
                "Ammo",
                "Arkitex",
                "Perma-trace",
                "TerraDraft",
                "Terra-Trace"
            ],
            "employees": 7,
            "capital": 50000,
            "key_personnel": {
                "name": "Ing Thord Rönngard",
                "position": "Verkst dir"
            },
            "establishment_year": 1968
        },
        "16": {
            "company_name": "ekonomi emballage",
            "pnr": "16135",
            "address": "Bromma, Drottningholmsv 312",
            "phone_number": "08-2513 16, 25 0913",
            "bank_details": {
                "bankgiro": "58-8988",
                "postgiro": "256761"
            },
            "activity": "Alla slag av träemballage",
            "key_personnel": {
                "name": "Thorsten Lax",
                "position": "Chef"
            },
            "establishment_year": 1964
        }
    }
}