{
    "original": "RUB\n\n10262. Tga Rubber\nVerksamhet: Generalagent o\nförsäljningsorganisation för AS Den\nNorske Remfabrik.\nATLAS industrigummi:\nTransportband, drivremmar, kilremmar,\nslangar, slitgummi, formgummi etc\nVarunamn: ATLAS\nÅrsomsättning: 5 500 000\nAktiekapital: 150 000\nVerkst dir: Sven Holmquist\nEtableringsàr: 1923.\n\nRUBBER HYDRAUL AB\n\nPnr 186 00\n\nVallentuna, Box 10. Olsborgsv.\nTel 0762-22125. Telex 10262\nVerksamhet: Dunlop\nhydraulslang-program. Strömnes cylindrar,\nventiler o hydraullås.\nRörförskruv-ningar o precisionsstålrör enl DIN.\nKonstruktioner o konsultverksamhet\nAntal anställda: 5\nAktiekapital: 100000\nStyrelse: Disp Ulf Holmquist (ordf),\ndir Sven Holmquist\nVerkst dir: Ing Nils Hansson\nEtableringsàr: 1971.\n\nRUBBER &amp; PLASTICS AB\n\nPnr 103 85\n\nStockholm 7, Kungsgl5. Box 7310\nTel 08-24 34 60. Bankgiro 576-8643.\nPostgiro 501261-2. Telex 10132.\nTga Rubberplast\n\nVerksamhet: Agentur för råvaror o\nmaskiner för gummi- o plastindustrin\nAntal anställda: 15\nÅrsomsättning: 24 000 000\nAktiekapital: 50 000\nVerkst dir. Claes Ax:son Philip\nEtableringsån 1949.\n\nHARBRECHT, BYGGNADS-AB\nBRÖDERNA\n\nPnr 574 01\n\nVetlanda 1, Box 134. Kyrkog 38.\nTel 0383-121 60. Bankgiro\n289-8138. Postgiro 519210-9\nVerksamhet: Byggnadsrörelse.\nUtför Perginolbeläggning\nAntal anställda: 60\nÅrsomsättning: 5 000 000\nAktiekapital: 50 000\nVerkst dir: Ing Erich Harbrecht\nEtableringsår: 1964.\n\nALM\n\nALLSERVICE\nREKLAMBYRÄ AB\n\nPnr 104 62\n\nStockholm 17, Pack. Gamla\nSöder-täljev 125, Segektorp. Tel\n08-88 03 40. Bankgiro 732-0559.\nPostgiron 357507-3, 159557-8,195290-2\nVerksamhet: Adressering o\ndistribution av brev, korsband,\nskyltma-terial, kataloger, presentreklam\netc. Bokbinderiarbeten.\nKupong-svarsservice. Efterkravssändningar\nmed redovisningskonton.\nLagerhållning med månadsrapportering.\nEmballage. Tryckservice\nAntal anställda: 30\nÅrsomsättning: 3 000 000\nAktiekapital: 40000\nVeikst dir: Sten Söderström\nEtableringsår: 1949\nOmbildat till aktiebolag 1960.\n\nALL-SPEDITION AB\n\nPnr 201 23\n\nMalmö 1, Box 334. Carlsg 54. Tel\n040-75955. Bankgiro 870-4314.\nPostgiro 435200-1. Tga Allsped.\nTelex 323331 STJERNA S\nVerksamhet: Internationella\ntransporter o spedition\n\nAvdelningskontor: 41110 Göteborg,\nO Hamng 19 B. Tel 031-11 07 39\n104 25 Stockholm 30, Box 30009.\nNordenflychtsv 62. Tel 08-13 17 40\nAktiekapital: 15 000\nStyrelse: Skeppsredare Egon\nStjerna, skeppsmäklare Ossian Stjerna\nVerkst dir: Ossian Stjerna\nSpeditionschef: Nils Sjöö\nEtableringsår: 1953.\n\nALEX TRÄINDUSTRIER, AB\n\nPnr 360 73\n\nLenhovda. Tel 0474-205 50.\nBankgiro 292-6038. Postgiro 277312-5.\nTga Alex, Växjö. Telex 4674\nVerksamhet: Tillverkar sågade o\nhyvlade trävaror\nÅrsomsättning: 10 000 000\nAktiekapital: 300 000\nVerkst dir: Artur Alexandersson\nEtableringsår: 1955.\n\nCERNELLE, AB\n\nPnr 262 00\n\nÄngelholm, Vegeholm 6250. Tel\n042-692 30. Bankgiro 67-2202.\nPostgiro 443700. Tga Cernelle\nVerksamhet: Framställer läkemedel\nbaserade på Cemitinextrakt\nAntal anställda: 65\nÅrsomsättning: 7 000 000\nAktiekapital: 100 000\nVerkst dir Disp Gösta Carlsson\nEtableringsår: 1936.\n\nCERTUS I BORÅS AB,\nMASKINFIRMA\n\nPnr 502 63\n\nBorås, Get ängs v 7. Tel\n033-1371 60. Bankgiro 531-1238.\nPostgiro 54984-0\n\nVerksamhet: Tillverkar o säljer för\nkonfektions- o trikåindustrin\n.Antal anställda: 30\nÅrsomsättning: 5 000 000\n.Aktiekapital: 102 000\nVerkst dir: Karl Schwägerl\nEtableringsår: 1932.\n\nFRÖBERG &amp; SJÖBERG, AB\n\nPnr 85101\n\nSundsvall 1, Fack. N Väger 8. Tel\n060-15 73 60. Postgiro 442910\nVerksamhet: Auktoriserad GM- o\nRenault-försäljare med tillhörande\nreservdels- o verkstadsrörelse\nAntal anställda: 50\nÅrsomsättning: 18 400 000\nAktiekapital: 400 000\nVerkst dir: Gust Stenberg\nV verkst dir: Ove Dahlberg\nEtableringsår: 1918.\n\nSMITH &amp; STENSSON AB\n\nPnr 411 15\n\nGöteborg, Kungspassagen, uppg A.\nTel 031-1164 35, 1164 95.\nBankgiro 84-7900. Postgiro 241346.\nTga Stensteel. Telex 20818\nVerksamhet: Säljer järn, stål,\ngjut-gods, smide, precisionsgjutgods,\nankare, kätting, fartygspropellrar,\nfilter o lastbommar\nAntal anstäUda: 7\nAktiekapital: 200 000\nStyrelse: Adv Hans Johnson, disp\nPer Olof Fredberg\nEtableringsår: 1946.\n\nTIGERSTAD AB, RUNE\n\nPnr 580 03\n\nLinköping 3, Slöjdg 19. Box 3004.\nTel 013-125001, 124031.\nBankgiro 607-9719. Postgiro 76905-9\nVaksamhet: Säljer kontorsartiklar\nav alla slag samt skriv- o\nräknemaskiner\n\nChef: Rune Tigerstad.\n\nTI KA, AB\n\nPnr 90102\n\nUmeå 1, Box 59. Mariehemsv 8. Tel\n090-1187 80. Postgiro 577037-5.\nTga Tika\n\nVerksamhet: Läkemedelsföretag\nLokalkontor: 12612 Stockholm 42,\nUpplags v 10. Fack. Tel 08-1818 38,\n18 83 60\n\nVarunamn: Tika\nAktiekapital: 233 000\nStyrelse: Dir Karl Arne Wegerfelt\n(ordf), dir Stig Jakobsson, dir Bo\nLindén\n\nVerkst dir: Bo Lindén\nEtableringsår 1925\nDotterbolag till AB Astra,\nSödertälje.\n\nTIKAMIN, AB\n\nPnr 28101\n\nHässleholm 1, S Industrig. Box 149.\nTel 0451-800 00. Bankgiro\n270-1407. Postgiro 381313-6. Tga\nTikamin. Telex 4442 TIKAMIN S\nVerksamhet: Försäljning av\nrostskyddsmedel (DINITROL),\nrostbort-tagningsmedel, tätningsmedel o\nkontakt lim\n\nLokalkontor o lager Göteborg. Tel\n031-27 20 35\n\nStockholm. Tel 08-18 83 60\nSundsvall. Tel 060-11 8150\nVarunamn: Annitrol, Collexin,\nDi-nitrol, Tik af äst, Tikatät\nAktiekapital: 1000 000\nStyrelse: Dir Tage Ranström (ordf),\ndir Bill B Ericson, dir Erik\nMalmström\n\nVerkst dir: Bill B Ericson\nEtableringsår: 1942\nDotterbolag till Astra-Dinol AB,\nHässleholm.\n\nTILAFABRIKEN, AB\n\nPnr 231 01\n\nTrelleborg 1, Alg 19. Box 62. Tel\n0410-16510. Bankgiro 28-7977.\nPostgiro 143076. Tga Tilafabriken\nVerksamhet: Tillverkar\nTila-plat-tan o Lackoplattan\nAntal anställda: 150\nAktiekapital: 600 000\nVerkst dir Jan Hakestam\nEtableringsår: 1934.\n\nTILLBERGA LASTBILDEMON.\nTERING\n\nPnr 725 90\n\nVästerås, Anstå. Tel 021-244 20,\n244 22. Bankgiro 831-9303.\nPostgiro 648422-4\n\nVerksamhet: Lastbildemonterlng.\nSäljer begagnade lastbilsdelar\nChef: Bo Lännhuldt\nEtableringsår: 1964.\n\nLUNDBERG &amp; KULLBERG AB\n\nPnr 401 20\n\nGöteborg 1, Marieholmsg 80. Box\n30. Tel 031-46 0240. Bankgiro\n420-1190. Postgiro 12169-9. Tga Metall.\nTelex 2333\n\nVerksamhet: Försäljning en gros\nav aluminium o -halvfabrikat, bly\no -halvfabrikat, koppar o\n-halvfabrikat, mässing o -halvfabrikat,\nbleckplåt, galvaniserad plåt,\nrostfri, syrafast o eldhärdig plåt,\nzinkplåt, lackerad galvaniserad plåt o\nlackerad aluminiumplåt, Purgo\nrensventiler, tenn o -halvfabrikat,\nplåtslagerimaterial\nAntal anställda: 22\nÅrsomsättning: 11400000\nAktiekapital: 525 000\nStyrelse: Dir Gert Andersson (ordf),\ndir Agnes Jansson, kamrer Ernst\nRud Petersson\nVerkst dir: Agnes Jansson\nDisp: Törd Bratt\nKamrer: Rud Petersson\nEtableringsår: 1872.\n\nLUNDBERGS MEKANISKA\nVERKSTAD AB, BRÖDERNA\n\nPnr 93100\n\nSkellefteå, Mullbergsv 11. Tel\n0910-170 90. Bankgiro 764-0592.\nPostgiro 67068-7. Telex 6886\nVerksamhet: Tillverkar\nhydrauliska lastmaskiner som monteras på\nBolinder-Munktell traktorer\nAntal anställda: 255\nVerkst dir: Helge Karinen\nEtableringsår: 1945.\n\nULVEX AB\n\nPnr 16130\n\nBromma, Ekbacksv 10. Tel\n08-26 25 60. Bankgiro 744-0167.\nPostgiro 10899-3. Tga Ulvsundagummi,\nStockholm\n\nVästbergafabriken: Vretensborgsv\n16, 126 30 Hägersten. Tel\n08-19 03 25. Tga Litek, Stockholm\n\nmmr\n\ndet välkända varumärket för\nskumgummimadrasser, skrapmattor och\noljeslangar.\n\nVerksamhet:\n\nVid Ulvsundafabriken:\n\n(tidigare Ulvsunda Gummifabriks\nAB) slangar av alla slag.\nSpecialitet: oljeslangar. Formgjorda\ngummidetaljer, sprutade gummipro-\n\nfiler, gummipackningar,\nslangkrökar, gummiduk o tekniska\ngummi-detaljer, Ulvex-mattor o andra\nform-gjorda gummimattor samt Ulvex\narbetstrallar, gummi- o plastvalsar\nför grafisk o annan industri,\ncellplastprodukter: isolerplattor för\nbyggnadsindustri, flytvästar o\nlivbojar. Ulvex skumgummi- o Videx\npolyetermadrasser,\ngrammofonskivor, kassetter till bandspelare\nVid Västbergafabriken:\n(tidigare Stockholms Gummiindustri\nAB) formgjorda gummiartiklar till\nbil-, el- o verkstadsindustrin,\nförslutningar o andra gummiprodukter\nför farmaceutisk! bruk\nVarunamn: Brisen, Hexyl, Printex,\nUlvex, Videx\nAntal anställda: 550\nÅrsomsättning: 40 000 000\nAktiekapital: 3 200 000\nVerkst dir: Civiling Bengt Lizell\nPlatschef Västbergafabriken: Dir\nAke Erikson\n\nFörsäljn-chef: Dir Anders Key\nKontorschef: Kamrer Henry Brunell\nProduktionschef: Civiling Olov\nEkman\n\nInköpschef: Ing Sven Ringberg\nEtableringsår: 1917.\nDotterbolag till Trelleborgs\nGummifabriks AB.\n\nULVFORS AB, H\n\nPnr 763 01\n\nHallstavik 1, Box 80. Tel\n0175-22100\n\nVerksamhet: Tillverkar\ndamunderkläder i rayon o nyloncharmeuse\nAntal anställda: 50\nÅrsomsättning: 3 500 000\nAktiekapital: 200 000\nStyrelse: Fabr Henry Ulvfors\n(ordf), disp Lars Ulvfors\nVerkst dir: Disp Lars Ulvfors\nEtableringsår: 1927.",
    "structured": {
        "1": {
            "company_name": "TGA Rubber",
            "activity": "Generalagent o försäljningsorganisation för AS Den Norske Remfabrik",
            "establishment_year": 1923,
            "annual_turnover": 5500000,
            "capital": 150000,
            "key_personnel": [
                {
                    "name": "Sven Holmquist",
                    "position": "Verkst dir"
                }
            ]
        },
        "2": {
            "company_name": "Rubber Hydraul AB",
            "pnr": "186 00",
            "address": "Vallentuna, Box 10. Olsborgsv",
            "phone_number": "0762-22125",
            "activity": "Dunlop hydraulslang-program",
            "employees": 5,
            "capital": 100000,
            "key_personnel": [
                {
                    "name": "Disp Ulf Holmquist",
                    "position": "ordf"
                },
                {
                    "name": "Sven Holmquist",
                    "position": "dir"
                },
                {
                    "name": "Ing Nils Hansson",
                    "position": "Verkst dir"
                }
            ],
            "establishment_year": 1971
        },
        "3": {
            "company_name": "Rubber & Plastics AB",
            "pnr": "103 85",
            "address": "Stockholm 7, Kungsgl5. Box 7310",
            "phone_number": "08-24 34 60",
            "bank_details": {
                "bankgiro": "576-8643",
                "postgiro": "501261-2"
            },
            "activity": "Agentur för råvaror o maskiner för gummi- o plastindustrin",
            "employees": 15,
            "annual_turnover": 24000000,
            "capital": 50000,
            "key_personnel": [
                {
                    "name": "Claes Ax:son Philip",
                    "position": "Verkst dir"
                }
            ],
            "establishment_year": 1949
        },
        "4": {
            "company_name": "Harbrecht, Byggnads-AB Bröderna",
            "pnr": "574 01",
            "address": "Vetlanda 1, Box 134. Kyrkog 38",
            "phone_number": "0383-121 60",
            "bank_details": {
                "bankgiro": "289-8138",
                "postgiro": "519210-9"
            },
            "activity": "Byggnadsrörelse. Utför Perginolbeläggning",
            "employees": 60,
            "annual_turnover": 5000000,
            "capital": 50000,
            "key_personnel": [
                {
                    "name": "Ing Erich Harbrecht",
                    "position": "Verkst dir"
                }
            ],
            "establishment_year": 1964
        },
        "5": {
            "company_name": "Alm Allservice Reklambyrå AB",
            "pnr": "104 62",
            "address": "Stockholm 17, Pack. Gamla Södertäljev 125, Segektorp",
            "phone_number": "08-88 03 40",
            "bank_details": {
                "bankgiro": "732-0559",
                "postgiro": "357507-3, 159557-8,195290-2"
            },
            "activity": "Adressering o distribution av brev, korsband, skyltmaterial, kataloger, presentreklam etc. Bokbinderiarbeten. Kupongsvarsservice. Efterkravssändningar med redovisningskonton. Lagerhållning med månadsrapportering. Emballage. Tryckservice",
            "employees": 30,
            "annual_turnover": 3000000,
            "capital": 40000,
            "key_personnel": [
                {
                    "name": "Sten Söderström",
                    "position": "Verkst dir"
                }
            ],
            "establishment_year": 1949
        }
    }
}