{
    "original": "van LEER SVENSKA AB\n\nPnr 137 01\n\nVästerhaninge 1, Box 78. Tel\n0750-21110. Bankgiro 333-7334.\nPostgiro 449920-8. Tga Sweddrums.\nTelex 17288\n\nVerksamhet: Tillverkar plåtfat\nAktiekapital: 1000 000\nVerkst dir: Jules Taeymans\nEtableringsår: 1954.\n\nLEIFA VERKTYGSMEKANO,\nAB\n\nPnr 213 63\n\nMalmö, Nya Agnesfridsv 186. Tel\n040-21 64 60. Bankgiro 116-7337.\nPostgiro 633297-7\nVerksamhet: Stans- o formverktyg,\nfixturer, mekaniska arbeten\nAktiekapital: 5 000\nVerkst dir: Leif Andersson\nEtableringsår: 1964.\n\nBERO FASAD AB\n\nPnr 402 24\n\nGöteborg 5, Box 5219. Södra v 12.\nTel 031-20 07 30\nVerksamhet: Utför\nfasadbeklädnader av aluminium\n.Antal anställda: 10\nÅrsomsättning: 500 000\nAktiekapital: 5 000\nEtableringsår: 1968.\n\nWIKLUND, AB A\n\nPnr 100 52\n\nStockholm 29, Lidingöv 75. Fack.\nTel 08-63 15 20. Bankgiro 160-4354.\nPostgiro 801-1. Tga Wikmanlund\nVerksamhet: Bilhandel, bilservice\nVerkst dir: Lars Jaeger\nEtableringsår: 1891.\n\nEIR, SJUKFÖRSÄKRINGS AB\n\nPnr 103 40\n\nStockholm 40, Pack. Sveav 20. Tel\n08-2214 60.\n\nEISER AB\n\nPnr 501 03\n\nBorås 1, Nils Jacobssonsg 5. Box\n121. Tel 033-1270 20. Bankgiro\n839-2771. Postgiro 9350-0. Tga\nEiser. Telex 36034\nVerksamhet: Trikå- o strumpfabrik.\nSpinneri o färgeri\nAntal anställda: 2 300\nÅrsomsättning: 144 000 000\nAktiekapital: 28 280 000\nVerkst din Sven Engblom\nV verkst din Rune üfverberg\nEtableringsår 1913.\n\nCEWE -SELFA AB\n\nPnr 61101\n\nNyköping 1, Box 295. Brukslagarv\n5. Tel 0155-880 00. Bankgiro\n619-0748. Postgiro 77697-1. Tga Cewe\nVerksamhet: Tillverkar elektr\napparater för industri o lantbruk,\nsåsom stickproppar, vägguttag,\nväggintag, skarvuttag,\nmotorskyddsbry-tare, startkopplare, strömställare,\nkapslad materiel för centraler samt\nfördelningscentraler med\nsäkrings-brytare, byggplatscentraler m m\nFörsäljningskontor: 117 34\nStockholm, Hornsbruksg 15 B. Tel 08-\n\n84\t02 45\n\n414 51 Göteborg, Lilla g 3. Tel\n031-14 51 77, 24 84 39\n21120 Malmö, N Neptunig 21. Tel\n040-725 60\n\n85\t2 35 Sundsvall, Nybrog 17. Tel\n060-15 10 21, 15 24 44, 15 24 57\nVarunamn: Cewe, Selfa, Relka\nAntal anställda: 540\nÅrsomsättning: 40 000 000\nAktiekapital: 10 000 000\nStyrelse: Dir Torsten Lindström\n(ordf), civilekonom ekonomidir\nLennart Flycht, ing Folke\nWesterberg\n\nVerkst dir: Civiling Hans\nWesterberg\n\nEtableringsår: 1919.\n\nFYLEVERKEN AB\n\nPnr 275 00\n\nSjöbo. Eriksdal. Tel 0416-150 55.\nBankgiro 282-7087. Postgiro\n157681-8\n\nVerksamhet: Utvinner kvartssand,\nsom levereras tvättad o\nkomgra-derad. Framställer kvartsmjöl samt\nblästersand m fi sandsorter i torkat\neller fuktigt skick. Producerar\neldfast lera o bindelera samt\nkaolin-lera. Framställer leror för keramisk\ntillverkning\n\nHuvudkontor: 113 22 Stockholm,\nOdeng 87. Tel 08-34 37 52\nAntal anställda: 55\nÅrsomsättning: 2 600 000\nAktiekapital: 325 000\nVerkst dir: Per Wretlind\n(Stockholm)\n\nEtableringsår: 1938.\n\nHEY\n\nHEVA METALLFABRIK\n\nPnr 330 30\n\nGnosjö. Tel 0370-91196. Postgiro\n465941\n\nVerksamhet: Tillverkar dragna o\nstansade massartiklar i järn o\nmetall. Detaljer för oljebrännare.\nKulfång för luftgevär, hållare för\nköks-o toalettpapper (patenterad)\nÄgare o chefer: Helmer\nIngemarsson, Valter Ingemarsson.\n\nHEWLETT-PACKARD\nSVERIGE AB\n\nPnr 17120\n\nSolna 1, Svetsarv 7. Fack. Tel\n08-981250. Bankgiro 74-6659.\nPostgiro 503331. Telex 10721. Tga\nMeasurements\n\nVerksamhet: Import o försäljning\nav elektroniska mätinstrument\nAntal anställda: 50\nÅrsomsättning: 30000 000\nAktiekapital: 50 000\nVerkst dir: L Ericson\nEtableringsår: 1962 .\n\nVER\n\nVERKTYGS.PRODUKTION AB\n\nPnr 582 31\n\nLinköping, Slöjdg9. Tel\n013-12 88 86. Bankgiro 120-0478.\nPostgiro 112130-0\n\nVerksamhet: Tillverkar verktyg o\nspecialmaskiner för\nmassproduktion av detaljer i järn , stål, metall,\nplast o papper\nAktiekapital: 15 000\nVerkst dir: Ing E Elias Pettersson\nEtableringsår 1944.\n\nVERKTYGS-SERVICE APS,\nAB\n\nPnr 162 27\n\nVällingby, Grimstag 164. Tel\n08-382610, 38 2611. Bankgiro\n610-9490. Postgiro 551622-4\nVerksamhet: Tillverkar fixturer,\njiggar o stansverktyg\nVarunamn: APS\nChef: Kurt Wolf.\n\nVERKTYGSTILLVERKNING,\nAB\n\nPnr 214 30\n\nMalmö, Västmanlandsg 3. Tel\n040-1943 10, 18 54 20. Bankgiro\n874-8337. Postgiro 248857-5\nVerksamhet: Konstruerar o\ntillverkar verktyg för ex centerpress ning,\njiggar o fixturer, samt\nspecialutrustning för industrier\nAntal anställda: 25\nÅrsomsättning: 1500 000\nAktiekapital: 10 000\nEtableringsår: 1946.\n\nKONFEKTIONS.METALL, AB\n\nPnr 580 03\n\nLinköping 3, Industrig 36. Box\n3023. Tel 013-1257 00, 1246 08.\nBankgiro 607-8141. Postgiro\n140985-3\n\nVerksamhet: Tillverkar knappar,\nspännen, säkerhetsnålar m m\n■Antal anställda: 35\nÅrsomsättning: 3 000 000\nAktiekapital: 25 000\nVerkst dir: Ing Bertil Eriksson\nEtableringsår: 1939.\n\nKONFEKTYRLAGRET\nKOLONIAL &amp; KONSERV AB\n\nPnr 11641\n\nStockholm, Tegelviksg 20. Tel\n08-40 38 48, 40 53 50. Bankgiro\n245-0286. Postgiro 4613-6\nVerksamhet: Säljer kontektyrer\nengros\n\nAntal anställda: 10\nÅrsomsättning: 9 000 000\nAktiekapital: 26 000\nVerkst dir: Evert Hall\nEtableringsår: 1875.\n\nIMUDICO AB\n\nPnr 115 28\n\nStockholm, Sandhamnsg 39. Tel 08-\n\nBankgiro 168-4240. Postgiro\n11847-1. Tga Turntable.\nTelex 10046\n\nVeiksamhet: Förlagsrörelse o\nnotförsäljning\nAktiekapital: 110 000\nChef: Dir Anders Holmstedt\nEtableringsår: 1923.\n\nIMU/INSTITUTET FOR\nMARKNADSUNDERSÖKNINGAR AB\n\nPnr 104 32\n\nStockholm 19,Odeng 40. Box 19073.\nTel 08-15 14 60. Bankgiro 57-6267.\nPostgiro 156889-8\nVerksamhet:\nMarknadsundersökningar. Konsumentindex\nAktiekapital: 100 000\nVerkst dir: Pol mag Jan Agvall\nEtableringsår. 1932.",
    "structured": {
        "0": {
            "company_name": "van LEER SVENSKA AB",
            "pnr": "137 01",
            "address": "Västerhaninge 1, Box 78",
            "phone_number": "0750-21110",
            "bank_details": {
                "bankgiro": "333-7334",
                "postgiro": "449920-8"
            },
            "activity": "Tillverkar plåtfat",
            "capital": 1000000,
            "key_personnel": [
                {
                    "name": "Jules Taeymans",
                    "position": "Verkst dir"
                }
            ],
            "establishment_year": 1954
        },
        "1": {
            "company_name": "LEIFA VERKTYGSMEKANO, AB",
            "pnr": "213 63",
            "address": "Malmö, Nya Agnesfridsv 186",
            "phone_number": "040-21 64 60",
            "bank_details": {
                "bankgiro": "116-7337",
                "postgiro": "633297-7"
            },
            "activity": "Stans- o formverktyg, fixturer, mekaniska arbeten",
            "capital": 5000,
            "key_personnel": [
                {
                    "name": "Leif Andersson",
                    "position": "Verkst dir"
                }
            ],
            "establishment_year": 1964
        },
        "2": {
            "company_name": "BERO FASAD AB",
            "pnr": "402 24",
            "address": "Göteborg 5, Box 5219, Södra v 12",
            "phone_number": "031-20 07 30",
            "activity": "Utför fasadbeklädnader av aluminium",
            "employees": 10,
            "annual_turnover": 500000,
            "capital": 5000,
            "establishment_year": 1968
        },
        "3": {
            "company_name": "WIKLUND, AB A",
            "pnr": "100 52",
            "address": "Stockholm 29, Lidingöv 75, Fack",
            "phone_number": "08-63 15 20",
            "bank_details": {
                "bankgiro": "160-4354",
                "postgiro": "801-1"
            },
            "activity": "Bilhandel, bilservice",
            "key_personnel": [
                {
                    "name": "Lars Jaeger",
                    "position": "Verkst dir"
                }
            ],
            "establishment_year": 1891
        },
        "4": {
            "company_name": "EIR, SJUKFÖRSÄKRINGS AB",
            "pnr": "103 40",
            "address": "Stockholm 40, Pack, Sveav 20",
            "phone_number": "08-2214 60"
        },
        "5": {
            "company_name": "EISER AB",
            "pnr": "501 03",
            "address": "Borås 1, Nils Jacobssonsg 5, Box 121",
            "phone_number": "033-1270 20",
            "bank_details": {
                "bankgiro": "839-2771",
                "postgiro": "9350-0"
            },
            "activity": "Trikå- o strumpfabrik. Spinneri o färgeri",
            "employees": 2300,
            "annual_turnover": 144000000,
            "capital": 28280000,
            "key_personnel": [
                {
                    "name": "Sven Engblom",
                    "position": "V verkst dir"
                },
                {
                    "name": "Rune üfverberg",
                    "position": "V verkst dir"
                }
            ],
            "establishment_year": 1913
        },
        "6": {
            "company_name": "CEWE -SELFA AB",
            "pnr": "61101",
            "address": "Nyköping 1, Box 295, Brukslagarv 5",
            "phone_number": "0155-880 00",
            "bank_details": {
                "bankgiro": "619-0748",
                "postgiro": "77697-1"
            },
            "activity": "Tillverkar elektr apparater för industri o lantbruk, såsom stickproppar, vägguttag, väggintag, skarvuttag, motorskyddsbry-tare, startkopplare, strömställare, kapslad materiel för centraler samt fördelningscentraler med säkrings-brytare, byggplatscentraler m m",
            "sales_office": {
                "stockholm": "117 34 Stockholm, Hornsbruksg 15 B, Tel 08-84 02 45",
                "gothenburg": "414 51 Göteborg, Lilla g 3, Tel 031-14 51 77, 24 84 39",
                "malmo": "21120 Malmö, N Neptunig 21, Tel 040-725 60",
                "sundsvall": "85 2 35 Sundsvall, Nybrog 17, Tel 060-15 10 21, 15 24 44, 15 24 57"
            },
            "product_name": "Cewe, Selfa, Relka",
            "employees": 540,
            "annual_turnover": 40000000,
            "capital": 10000000,
            "board_of_directors": [
                "Dir Torsten Lindström (ordf), civilekonom ekonomidir Lennart Flycht, ing Folke Westerberg"
            ],
            "key_personnel": {
                "civiling Hans Westerberg": "Verkst dir"
            },
            "establishment_year": 1919
        },
        "7": {
            "company_name": "FYLEVERKEN AB",
            "pnr": "275 00",
            "address": "Sjöbo, Eriksdal",
            "phone_number": "0416-150 55",
            "bank_details": {
                "bankgiro": "282-7087",
                "postgiro": "157681-8"
            },
            "activity": "Utvinner kvartssand, som levereras tvättad o komgra-derad. Framställer kvartsmjöl samt blästersand m fi sandsorter i torkat eller fuktigt skick. Producerar eldfast lera o bindelera samt kaolin-lera. Framställer leror för keramisk tillverkning",
            "main_office": {
                "stockholm": "113 22 Stockholm, Odeng 87, Tel 08-34 37 52"
            },
            "employees": 55,
            "annual_turnover": 2600000,
            "capital": 325000,
            "key_personnel": {
                "Per Wretlind (Stockholm)": "Verkst dir"
            },
            "establishment_year": 1938
        },
        "8": {
            "company_name": "HEY HEVA METALLFABRIK",
            "pnr": "330 30",
            "address": "Gnosjö",
            "phone_number": "0370-91196",
            "postgiro": "465941",
            "activity": "Tillverkar dragna o stansade massartiklar i järn o metall. Detaljer för oljebrännare. Kulfång för luftgevär, hållare för köks-o toalettpapper (patenterad)",
            "owners_and_managers": [
                "Helmer Ingemarsson",
                "Valter Ingemarsson"
            ]
        },
        "9": {
            "company_name": "HEWLETT-PACKARD SVERIGE AB",
            "pnr": "17120",
            "address": "Solna 1, Svetsarv 7, Fack",
            "phone_number": "08-981250",
            "bank_details": {
                "bankgiro": "74-6659",
                "postgiro": "503331"
            },
            "activity": "Import o försäljning av elektroniska mätinstrument",
            "employees": 50,
            "annual_turnover": 30000000,
            "capital": 50000,
            "key_personnel": {
                "L Ericson": "Verkst dir"
            },
            "establishment_year": 1962
        },
        "10": {
            "company_name": "VER VERKTYGS.PRODUKTION AB",
            "pnr": "582 31",
            "address": "Linköping, Slöjdg9",
            "phone_number": "013-12 88 86",
            "bank_details": {
                "bankgiro": "120-0478",
                "postgiro": "112130-0"
            },
            "activity": "Tillverkar verktyg o specialmaskiner för massproduktion av detaljer i järn , stål, metall, plast o papper",
            "capital": 15000,
            "key_personnel": {
                "Ing E Elias Pettersson": "Verkst dir"
            },
            "establishment_year": 1944
        },
        "11": {
            "company_name": "VERKTYGS-SERVICE APS, AB",
            "pnr": "162 27",
            "address": "Vällingby, Grimstag 164",
            "phone_number": "08-382610, 38 2611",
            "bank_details": {
                "bankgiro": "610-9490",
                "postgiro": "551622-4"
            },
            "activity": "Tillverkar fixturer, jiggar o stansverktyg",
            "product_name": "APS",
            "manager": "Kurt Wolf"
        },
        "12": {
            "company_name": "VERKTYGSTILLVERKNING, AB",
            "pnr": "214 30",
            "address": "Malmö, Västmanlandsg 3",
            "phone_number": "040-1943 10, 18 54 20",
            "bank_details": {
                "bankgiro": "874-8337",
                "postgiro": "248857-5"
            },
            "activity": "Konstruerar o tillverkar verktyg för ex centerpress ning, jiggar o fixturer, samt specialutrustning för industrier",
            "employees": 25,
            "annual_turnover": 1500000,
            "capital": 10000,
            "establishment_year": 1946
        },
        "13": {
            "company_name": "KONFEKTIONS.METALL, AB",
            "pnr": "580 03",
            "address": "Linköping 3, Industrig 36, Box 3023",
            "phone_number": "013-1257 00, 1246 08",
            "bank_details": {
                "bankgiro": "607-8141",
                "postgiro": "140985-3"
            },
            "activity": "Tillverkar knappar, spännen, säkerhetsnålar m m",
            "employees": 35,
            "annual_turnover": 3000000,
            "capital": 25000,
            "key_personnel": {
                "Ing Bertil Eriksson": "Verkst dir"
            },
            "establishment_year": 1939
        },
        "14": {
            "company_name": "KONFEKTYRLAGRET KOLONIAL & KONSERV AB",
            "pnr": "11641",
            "address": "Stockholm, Tegelviksg 20",
            "phone_number": "08-40 38 48, 40 53 50",
            "bank_details": {
                "bankgiro": "245-0286",
                "postgiro": "4613-6"
            },
            "activity": "Säljer kontektyrer engros",
            "employees": 10,
            "annual_turnover": 9000000,
            "capital": 26000,
            "key_personnel": {
                "Evert Hall": "Verkst dir"
            },
            "establishment_year": 1875
        },
        "15": {
            "company_name": "IMUDICO AB",
            "pnr": "115 28",
            "address": "Stockholm, Sandhamnsg 39",
            "phone_number": "08-XXXXX",
            "bank_details": {
                "bankgiro": "168-4240",
                "postgiro": "11847-1"
            },
            "activity": "Förlagsrörelse o notförsäljning",
            "capital": 110000,
            "key_personnel": {
                "Anders Holmstedt": "Chef"
            },
            "establishment_year": 1923
        },
        "16": {
            "company_name": "IMU/INSTITUTET FOR MARKNADSUNDERSÖKNINGAR AB",
            "pnr": "104 32",
            "address": "Stockholm 19, Odeng 40, Box 19073",
            "phone_number": "08-15 14 60",
            "bank_details": {
                "bankgiro": "57-6267",
                "postgiro": "156889-8"
            },
            "activity": "Marknadsundersökningar. Konsumentindex",
            "capital": 100000,
            "key_personnel": {
                "Jan Agvall": "Verkst dir"
            },
            "establishment_year": 1932
        }
    }
}