{
    "original": "IGELSTAVERKEN AB\n\nPnr 104 22\n\nStockholm 22, Norr Mälarstrand 20.\nBox 22087. Tel08-520520, 52 01 60.\nBankgiro 57-4785. Postgiro 92800.\nTelex 10992. Tga Itawood\nVerksamhet: Tillverkar sågade o\nhyvlade trävaror o snickerier, även\nimpregnerade\n\nSågverk: Igelsta, Södertälje. Tel\n0755-325 25\n\nSkogstorp, Eskilstuna. Tel\n016-252 60\n\nTunaberg, Nyköping. Tel\n0155-512 00\n\nAntal anställda: 300\nÅrsomsättning: 27 000 000\nAktiekapital: 3 000 000\nVerkst dir: Jägmäst Jan Häckner\nEtableringsår 1958.\n\nRÖNNE, AB N O\n\nPnr 850 09\n\nSundsvall 9, Verkstadsg 3. Fack.\nTel 060-15 58 50. Postgiro 70814.\nTga Norönne\n\nVerksamhet: Säljer\nindustriförnödenheter, trädgårdsmaskiner.\nGeneralagent för Wheel Horse\nträdgårdstraktorer, Wolseley jordfräsar, Okay\nisbanemaskiner\n\nFilial: 212 25 Malmö, Strömg 9. Tel\n040-18 53 11\n\nRepresentanter för: Solvay &amp; Cie,\nAB Bofors-Tidaholmsverken\nVeikst dir: Sture Henningsohn\nAktiekapital: 200 000\nEtableringsår 1916.\n\nBERGTEX AB\n\nPnr 340 14\n\nLagan, Industrig 5. Tel\n0372-304 80 , 304 81. Bankgiro 147-3289.\nPostgiro 363130-6\nVerksamhet: Tillverkar sängar,\nsängpaneler, sängöverkast\nAntal anställda: 20\nÅrsomsättning: 1700 000\nAktiekapital: 30 000\nVerkst dir: Arne Andersson\nEtableringsår: 1962.\n\nVAR\n\nAktiekapital: 420 000\nVerkst dir: Thord Waplan\nEtableringsår: 1909.\n\nÅBOHOLMSVERKEN AB\n\nPnr 596 00\n\nSkänninge, Box 130. Tel\n0142-406 20. Bankgiro 130-0870.\nPost-giro 577806-3\n\nVerksamhet: Tillverkar o säljer\n\nkapellstativ\n\nAntal anställda: 10\n\nAktiekapital: 10000\n\nVeikst dir. Nils Johansson\n\nEtableringsår 1961.\n\nDRAKEN ILTRYCK, AB\n\nPnr 113 59\n\nStockholm, Sveav 90. Tel\n08-15 0075. Postgiro 504620\nVerksamhet: Utför offsettryck,\nreklam, bokomslag, blanketter m m.\nSpecialitet: färgtryck\nAntal anställda: 23\nÅrsomsättning: 2 500000\nAktiekapital: 5 000\nStyrelse: Hovrättsrådet Bengt\nLassen, disp Björn Wickman\nVerkst dir: Disp Björn G Wickman\nEtableringsår: 1954.\n\nILFORD FOTO AB\n\nPnr 40010\n\nGöteborg 3, Box 3052. Fröodlareg\n7, Västra Frölunda. Tel\n031-4508 70. Bankgiro 420-4475.\nPostgiro 40557-1. Tga lif ord\nVerksamhet: Säljer fotopapper,\nkemikalier, tillbehör, grafiska\nartiklar o röntgenfilm\nAntal anställda: 38\nÅrsomsättning: 10 000 000\nAktiekapital: 480 000\nVerkst dir. George Frimann-Clausen\nEtableringsår. 1896.\n\nBRUZAHOLMSVIROR, AB\n\nPnr 570 34\n\nBruzaholm. Tel 0381-201 70.\nBankgiro 451-4238. Postgiro 74455-7.\nTga Bruzaholmsviror. Telex 3713\nVerksamhet: Tillverkar viror o\ndukar av metall- o syntetmaterial,\nspeciellt för trämasse-, cellulosa-,\nwallboard- o pappersindustrin\nVarunamn: Bruzaholmsviror\nAntal anstäUda: 250\nÅrsomsättning: 22 000 000\nStyrelse: Adv Bengt Skantze (ordf),\ndir Sven-Erik Johansson, disp Erik\nBengtson\n\nVerkst dir Disp Erik Bengtson\nEtableringsår: 1906.\n\nBRYGGERIER\n\nse resp namn.\n\nBRÅBO VERKSTÄDER\n\nPnr 616 00\n\nÅby, Katrineholmsv. Box 115. Tel\n011-60105, 63610. Bankgiro\n611-1231. Postgiro 543619-6\nVerksamhet: Utför mekaniska\nlego-arbeten såsom svarvning, fräsning,\nborrning, hyvling o svetsning.\nBygger maskiner eller delar därav\nenligt kundens ritningar.\nTillverkar detaljer till hydrauliska\nanordningar\n\nAntal anställda: 25\nVerkst dir: Ing B Tufvander\nEtableringsår: 1960.\n\nBRÅKENHIELM &amp; CO AB,\nGUNNAR\n\nPnr 16111\n\nBromma 11, Ranhammarsv 22. Box\n11038. Tel 08-26 02 40. Bankgiro\n745-4119. Postgiro 454938-2.\nTga Brokisship\n\nVerksamhet: Maskinimport.\nTryck-lufthammare för demolering\nAktiekapital: 10 000\nÄgare o chef: Gunnar Bråkenhielm\nEtableringsår: 1923.\n\nSELLBERGS AB, A Z\n\nPnr 104 35\n\nStockholm 23, Fack. Sveav 163.\nTel 08-22 7040. Bankgiro 576-2018.\nPostgiro 5 6485-6. TgaSellbergtrans.\nTelex 1083 SELLCON S\nVeiksamhet: Transporter,\nschaktning, tunga transporter, renhållning\nAntal anställda: 1500\nAktiekapital: 15 000000\nVerkst dir. Kurt Sandberg\nEtableringsån 1882.\n\nSKANDINAVISKA FARTYGS.\nAGENTUREN, AB\n\nPnr 41121\n\nGöteborg, Skeppsbron 4. Tel\n031-1134 54. Telex 2579. Tga\nSkand-agent\n\nVerksamhet: Specialitet: köp o\nförsäljning av fartyg\nEtableringsår: 1928.\n\nSKANDINAVISKA GLASÖGON\n-FABRIKEN AB SKAGA\n\nPnr 550 07\n\nJönköping 7, Gräshagsg 11. Box\n7036. Tel 036-16 0130. Bankgiro\n545-4335. Postgiro 390374-7. Tga\nSkaga\n\nVerksamhet: Tillverkar o säljer\nglasögonbågar av högsta kvalitet\nAntal anställda: 100\nÅrsomsättning: 5 500 000\nAktiekapital: 150 000\nVerkst dir: Lajos Låzår\nEtableringsår: 1949.\n\nSKANDINAVISKA\nGLODLAMP-FABRIKEN, AB\n\nPnr 61100\n\nNyköping, Brunnsg 5. Tel\n0155-175 50. Bankgiro 827-2387.\nPost-giro 8840-1. Tga Skandialampan\nVerksamhet: Tillverkar elektr\nglödlampor\n\nVarunamn: Skandia\n\nAktiekapital: 1800 000\n\nEtableringsår: 1897\n\nDotterbolag till Svenska AB Philips,\n\nStockholm.\n\nSKANDINAVISKA GRANIT AB\n\nPnr 417 07\n\nGöteborg, Kalkbruksg 1. Tel 031-\n\n510635, 51 9210\n\nSe vidare Kullgrens Enka AB.\n\nSKANDINAVISKA\nINSTRUMENT AB\n\nPnr 114 60\n\nStockholm, Narvav 7. Tel\n08-6018 11, 60 18 35. Bankgiro\n560-5050. Postgiro 116611-5. Tga\nSkandinstrument. Telex 1358\nVerksamhet: Anläggningar för kemi,\npetrokemi, atomkraft, vattenrening\no vattenreglering. Armatur för\nav-lopp, gas, olja, vatten, värme, ånga,\nasfaltkokare, brandredskap,\ngasapparater, kompressorer,\nmanometrar, stålflaskor för komprimerade\ngaser, svetsomformare etc\nAktiekapital: 50 000\nVerkst dir: Jan Oberg\nEtableringsår: 1956.\n\nSKANDINAVISKA\nJOHNS-MANVILLE AB\n\nPnr 411 24\n\nGöteborg C, Vasag 12. Tel\n031-031-178650. Bankgiro 84-8424.\nPostgiro 46601. Tga Johnmanvil\nVerksamhet: Säljer\nfiltrerhjälpme-del, filters, isolerprodukter\nAktiekapital: 100 000\nVerkst dir: Mr H E Wood\nEtableringsår: 1963.\n\nSKA\n\nSKANDINAVISKA JUTE\nSPINNERI &amp; VÄVERI AB\n\nPnr 313 00\n\nOskarström. Tel 035-604 00.\nBankgiro 42-7327. Postgiro 15500. Telex\n3527. Tga Jutespinneriet\nVerksamhet: Spinneri, väveri,\nberedning o filtavdelning\nVarunamn: Tasso\nAntal anställda: 450\nÅrsomsättning: 35 000 000\nAktiekapital: 7 500 000\nVerkst dir: Jan Blum\nEtableringsår: 1889.\n\nSKANDINAVISKA KONTROLL\nAB\n\nPnr 103 84\n\nStockholm 7, Box 7217. Mäster\nSa-muelsg 10. Tel 08-14 09 40.\nBankgiro 330-1686. Postgiro 37565-9.\nTelex 10359\n\nVerksamhet: Varukontroll, teknisk\ninspektion o besiktningar\nFilialer. 403 12 Göteborg 2, Box\n2065\n\n20011 Malmö 6, Box 6057\nAntal anställda: 30\nÅrsomsättning: 2 000 000\nAktiekapital: 100 000\nVerkst dir Gert Löllbach\nEtableringsår: 1920.\n\nSKANDINAVISKA\nKUGGHJULS AB\n\nPnr 201 21\n\nMalmö 1, Limhamnsv 111-113. Box\n186. Tel 040-16 00 00, 16 0090\nVerksamhet: Tillverkar kugghjul,\nkuggväxlar, trädgårdstraktorer,\nmotorgräsklippare, motorhäckklippa-re, avfettningstankar o härdtankar\nAntal anställda: 115\nÅrsomsättning: 4151000\nAktiekapital: 280 000\nStyrelse: Dir Erik Söderbom (ordf),\ndir Bo Dahlgren, dir Axel Löfström,\ncivilekonom Lennart Bergström,\ndir Björn Lindhe\nVerkst dir: Axel Löfström\nV verkst dir: Håkan Billgren\nEtableringsår: 1945\nIngår i Flerongruppen, Malmö.\n\nSKANDINAVISKA MALM- och\nMETALL AB\n\nPnr 103 82\n\nStockholm 7, Kungsg 6. Box 7094.\nTel 08-23 35 20. Bankgiro 56-0429.\nPostgiro 195602. Tga Malmmetall.\nTelex 1552\n\nVerksamhet: Import o export av\nmalmer, metaller o legeringar\nAktiekapital: 2 250 000\nVerkst dir: L Haas\nEtableringsår: 1917.\n\nSKANDINAVISKA MASKIN.\nMEKANO AB\n\nPnr 594 00\n\nGamleby, Hammarsv 19. Tel\n0493-108 55. Tga Maskinmekano\nVerksamhet: Tillverkar ramsågar,\ndiamantramsågar, kantsågar med\nmanuell eller helautomatisk drift,\nslipmaskiner för manuell eller\nhelautomatisk drift, sliphuvuden för\ngranit, fräs o sågmaskiner för\nlätt-betongindustrin, lyftkranar o\nborrvagnar, wire-sågar, slipmaskiner\n\nför suglådslock till\ncellulosaindustrin. Säljer siliciumkarbid,\nalumi-niumoxid (Korund), diamantverktyg\nAntal anställda: 32\nÅrsomsättning: 3 200 000\nAktiekapital: 80 000\nVerkst dir: Fabr Per-Olof\nFransson\n\nEtableringsår: 1948\nOmbildat till aktiebolag 1962.\n\nSKANDINAVISKA MO LAN AB\n\nPnr 235 00\n\nVellinge. Tel 040-42 04 18.\nBankgiro 404-1224. Postgiro 534005-4\nVerksamhet: Tillverkar o säljer\narbetarskyddmaterial. Damm- o\nskyddshöljen i PVC o silikon\nVarunamn: Dimoplast, Molan\nVerkst dir: Ingemar Christoffersson\nEtableringsår: 1970.\n\nSKANDINAVISKA\nMOLYBDEN AB\n\nPnr 281 01\n\nHässleholm 1, Fack. Tel\n0451-52215. Bankgiro 561-1645.\nPostgiro 292051-0\n\nHt^åde\n\nVerksamhet: importerar o tillverkar\nspecialsmörjmedel för alla\nindustriella behov. Säljer molybdendisulfid,\ngrafitpulver o aluminiumcomplex\nVarunamn: Molylube\nVerkst dir: clarence Wivanger\nEtableringsår: 1961.",
    "structured": {
        "1": {
            "company_name": "IGELSTAVERKEN AB",
            "pnr": "104 22",
            "address": "Stockholm 22, Norr Mälarstrand 20. Box 22087",
            "phone_number": "08-520520, 52 01 60",
            "bank_details": {
                "bankgiro": "57-4785",
                "postgiro": "92800"
            },
            "activity": "Tillverkar sågade o hyvlade trävaror o snickerier, även impregnerade",
            "employees": 300,
            "annual_turnover": 27000000,
            "capital": 3000000,
            "key_personnel": [
                {
                    "name": "Jägmäst Jan Häckner",
                    "position": "Verkst dir"
                }
            ],
            "establishment_year": 1958
        },
        "2": {
            "company_name": "RÖNNE, AB N O",
            "pnr": "850 09",
            "address": "Sundsvall 9, Verkstadsg 3",
            "phone_number": "060-15 58 50",
            "postgiro": "70814",
            "activity": "Säljer industriförnödenheter, trädgårdsmaskiner. Generalagent för Wheel Horse trädgårdstraktorer, Wolseley jordfräsar, Okay isbanemaskiner",
            "employees": null,
            "capital": 200000,
            "key_personnel": [
                {
                    "name": "Sture Henningsohn",
                    "position": "Veikst dir"
                }
            ],
            "establishment_year": 1916
        },
        "3": {
            "company_name": "BERGTEX AB",
            "pnr": "340 14",
            "address": "Lagan, Industrig 5",
            "phone_number": "0372-304 80 , 304 81",
            "bank_details": {
                "bankgiro": "147-3289",
                "postgiro": "363130-6"
            },
            "activity": "Tillverkar sängar, sängpaneler, sängöverkast",
            "employees": 20,
            "annual_turnover": 1700000,
            "capital": 30000,
            "key_personnel": [
                {
                    "name": "Arne Andersson",
                    "position": "Verkst dir"
                }
            ],
            "establishment_year": 1962
        },
        "4": {
            "company_name": "VAR",
            "capital": 420000,
            "key_personnel": [
                {
                    "name": "Thord Waplan",
                    "position": "Verkst dir"
                }
            ],
            "establishment_year": 1909
        },
        "5": {
            "company_name": "ÅBOHOLMSVERKEN AB",
            "pnr": "596 00",
            "address": "Skänninge, Box 130",
            "phone_number": "0142-406 20",
            "bank_details": {
                "bankgiro": "130-0870",
                "postgiro": "577806-3"
            },
            "activity": "Tillverkar o säljer kapellstativ",
            "employees": 10,
            "capital": 10000,
            "key_personnel": [
                {
                    "name": "Nils Johansson",
                    "position": "Veikst dir"
                }
            ],
            "establishment_year": 1961
        },
        "6": {
            "company_name": "DRAKEN ILTRYCK, AB",
            "pnr": "113 59",
            "address": "Stockholm, Sveav 90",
            "phone_number": "08-15 0075",
            "postgiro": "504620",
            "activity": "Utför offsettryck, reklam, bokomslag, blanketter m m. Specialitet: färgtryck",
            "employees": 23,
            "annual_turnover": 2500000,
            "capital": 5000,
            "key_personnel": [
                {
                    "name": "Disp Björn Wickman",
                    "position": "Styrelse"
                },
                {
                    "name": "Disp Björn G Wickman",
                    "position": "Verkst dir"
                }
            ],
            "establishment_year": 1954
        },
        "7": {
            "company_name": "ILFORD FOTO AB",
            "pnr": "40010",
            "address": "Göteborg 3, Box 3052. Fröodlareg 7, Västra Frölunda",
            "phone_number": "031-4508 70",
            "bank_details": {
                "bankgiro": "420-4475",
                "postgiro": "40557-1"
            },
            "activity": "Säljer fotopapper, kemikalier, tillbehör, grafiska artiklar o röntgenfilm",
            "employees": 38,
            "annual_turnover": 10000000,
            "capital": 480000,
            "key_personnel": [
                {
                    "name": "George Frimann-Clausen",
                    "position": "Verkst dir"
                }
            ],
            "establishment_year": 1896
        },
        "8": {
            "company_name": "BRUZAHOLMSVIROR, AB",
            "pnr": "570 34",
            "address": "Bruzaholm",
            "phone_number": "0381-201 70",
            "bank_details": {
                "bankgiro": "451-4238",
                "postgiro": "74455-7"
            },
            "activity": "Tillverkar viror o dukar av metall- o syntetmaterial, speciellt för trämasse-, cellulosa-, wallboard- o pappersindustrin",
            "employees": 250,
            "annual_turnover": 22000000,
            "key_personnel": [
                {
                    "name": "Adv Bengt Skantze",
                    "position": "Styrelse"
                },
                {
                    "name": "Sven-Erik Johansson",
                    "position": "Dir"
                },
                {
                    "name": "Erik Bengtson",
                    "position": "Disp"
                },
                {
                    "name": "Disp Erik Bengtson",
                    "position": "Verkst dir"
                }
            ],
            "establishment_year": 1906
        },
        "9": {
            "company_name": "BRÅBO VERKSTÄDER",
            "pnr": "616 00",
            "address": "Åby, Katrineholmsv. Box 115",
            "phone_number": "011-60105, 63610",
            "bank_details": {
                "bankgiro": "611-1231",
                "postgiro": "543619-6"
            },
            "activity": "Utför mekaniska lego-arbeten såsom svarvning, fräsning, borrning, hyvling o svetsning. Bygger maskiner eller delar därav enligt kundens ritningar. Tillverkar detaljer till hydrauliska anordningar",
            "employees": 25,
            "key_personnel": [
                {
                    "name": "Ing B Tufvander",
                    "position": "Verkst dir"
                }
            ],
            "establishment_year": 1960
        },
        "10": {
            "company_name": "BRÅKENHIELM & CO AB, GUNNAR",
            "pnr": "16111",
            "address": "Bromma 11, Ranhammarsv 22. Box 11038",
            "phone_number": "08-26 02 40",
            "bank_details": {
                "bankgiro": "745-4119",
                "postgiro": "454938-2"
            },
            "activity": "Maskinimport. Tryck-lufthammare för demolering",
            "capital": 10000,
            "key_personnel": [
                {
                    "name": "Gunnar Bråkenhielm",
                    "position": "Ägare o chef"
                }
            ],
            "establishment_year": 1923
        },
        "11": {
            "company_name": "SELLBERGS AB, A Z",
            "pnr": "104 35",
            "address": "Stockholm 23, Fack. Sveav 163",
            "phone_number": "08-22 7040",
            "bank_details": {
                "bankgiro": "576-2018",
                "postgiro": "5 6485-6"
            },
            "activity": "Transporter, schaktning, tunga transporter, renhållning",
            "employees": 1500,
            "capital": 15000000,
            "key_personnel": [
                {
                    "name": "Kurt Sandberg",
                    "position": "Verkst dir"
                }
            ],
            "establishment_year": 1882
        },
        "12": {
            "company_name": "SKANDINAVISKA FARTYGS. AGENTUREN, AB",
            "pnr": "41121",
            "address": "Göteborg, Skeppsbron 4",
            "phone_number": "031-1134 54",
            "activity": "Specialitet: köp o försäljning av fartyg",
            "establishment_year": 1928
        },
        "13": {
            "company_name": "SKANDINAVISKA GLASÖGON -FABRIKEN AB SKAGA",
            "pnr": "550 07",
            "address": "Jönköping 7, Gräshagsg 11. Box 7036",
            "phone_number": "036-16 0130",
            "bank_details": {
                "bankgiro": "545-4335",
                "postgiro": "390374-7"
            },
            "activity": "Tillverkar o säljer glasögonbågar av högsta kvalitet",
            "employees": 100,
            "annual_turnover": 5500000,
            "capital": 150000,
            "key_personnel": [
                {
                    "name": "Lajos Låzår",
                    "position": "Verkst dir"
                }
            ],
            "establishment_year": 1949
        }
    }
}