{
    "original": "HELLBERG AB, JOHN\n\nPnr 104 65\n\nStockholm 15, S Mälarstrand 21.\nBox 15069. Tel 08-4215 45,\n43 25 30. Bankgiro 72-0119.\nPostgiro 58112. Tga Ultravy\nVerksamhet: Optiska artiklar en\ngros\n\nAntal anställda: 9\n\nÅrsomsättning: 700 000\nAktiekapital: 40 000\nVerkst dir: Kurt Emanuel\nPettersson\n\nEtableringsår: 1935.\n\nHELLBERG KB,\nBYGGNADS-FIRMAN VILHELM\n\nPnr 122 41\n\nEnskede, Bjulev 8. Tel 08-9184 00,\n9184 01. Bankgiro 478-7677.\nPostgiro 153685-3\n\nVerksamhet: Byggnadsrörelse för\n\nny-, om- o tillbyggnader\n\nAntal anställda: 55\n\nÅrsomsättning: 3 500 000\n\nChef: Byggmäst Vilhelm Hellberg\n\nEtableringsår: 1937\n\nOmbildat till kommanditbolag 1955.\n\nHELLESENSSVENSKA AB\n\nPnr 11451\n\nStockholm, Artillerig 16. Tel\n08-67 00 65. Bankgiro 732-0393.\nPost-giro 1965-3. Tga Nimac\nVerksamhet: säljer Hellesens\nbrunstensbatterier, alkaliska\nbrunstensbatterier samt kvicksilverbatterier.\nHandlyktor, ficklampor samt\ndiverse annan batteridriven apparatur\nAntal anställda: 11\nAktiekapital: 150 000\nChef: Disp Jan Sahlén\nKontorschef: Kamrer Johan W\nOlson\n\nEtableringsår: 1908\nDotterbolag till A/S Hellesens,\nKöpenhamn.\n\nHELLIDENS VATTENPASS &amp;\nSNICKERIFABRIK\n\nPnr 52200\n\nTidaholm, Kullö. Tel 0502-102 93.\nPostgiro 334455-3. Tga Vattenpass\nVerksamhet: Träförädlingsfabrik\nAntal anställda: 12\nFimiatecknare: Erik Svensson,\nLåge Bodin\nEtableringsår: 1947.\n\nHELLQVISTS\nPAPPERS-INDUSTRI AB\n\nPnr 572 00\n\nOskarshamn, Skolg 7. Tel\n0491-104 74. Bankgiro 148-6489.\nPostgiro 10860-5\n\nVerksamhet: Tillverkar kuvert,\nprovsäckar, Specialitet:\nfönsterkuvert\n\nAntal anställda: 45\n\nÄgare o chef: Gunnar Hellqvist\n\nEtableringsår: 1921.\n\nEYRA INDUSTRIER, AB\n\nPnr 703 63\n\nÖrebro, Virkesv. Industriområdet,\nHolmen. Tel 019-12 4185. Bankgiro\n495-5027. Postgiro 99111-7\nVerksamhet: Tillverkar\nbordsbestick m m. Utför pressningsarbeten\nAntal anställda: 25\nÅrsomsättning: 1 300 000\nAktiekapital: 112000\nVerkst dir: Ake Gustavsson\nEtableringsår: 1947.\n\nKARLSHAMNS TRÄVARU AB\n\nPnr 292 00\n\nKarlshamn, Regeringsg 76. Tel\n0454-11013, 139 74. Postgiro\n578050-7. Tga Karlrune\nVerksamhet: Köper o säljer\nträvaror, huvudsakligen för export\nAntal anställda: 3\nÅrsomsättning: 7 000 000\nAktiekapital: 30000\nVerkst dir: K G Söderholm\nEtableringsår: 1961.\n\nKARLSKOGA AUTOMAT.\nSVARVNING AB\n\nPnr 69100\n\nKarlskoga, Maskinv 14. Tel\n0586-376 00. Bankgiro 60-5441.\nPostgiro 32899\n\nVerksamhet: Legotillverkning av\nautomatsvarvade detaljer\nAntal anställda: 7\nÅrsomsättning: 500 000\nAktiekapital: 20 000\nChefer: Fabr Gunnar Adrian, fabr\nEdvard Nyström\nEtableringsår: 1949.\n\nVOXNANSKRAFT AB\n\nPnr 103 62\n\nStockholm 3, Box 3118. Kammakarg\n7. Tel 08-23 33 50. Bankgiro\n160-9205. Postgiro 706810-9. Tga\nCon-cession. Telex 10081 SEVOXC S\nVerksamhet: Produktion,\nförsäljning o förmedling av elektrisk\nkraft\n\nÅrsomsättning: 158 000 000\nAktiekapital: 70 000 000\nStyrelse: Tfekn dr Marcus\nWallenberg (ordf), generalkonsul Ragnar\nSöderberg, tekn dr Ake TVrethem,\ndir Ulf Glimstedt, dir Tbrsten\nNard-ström(suppl), dir Ake Ericsson\n(suppl)\n\nVerkst dir: Uf Glimstedt\nEtableringsår: 1958\nDotterbolag: Dönje Kraft AB,\nNorr-änge Kraft AB, Brännälvens Kraft\nAB, AB Sembs Kraftstation.\nVox-nanprojekt AB.\n\nV.PLUGGEN AB\n\nPnr 11127\n\nStockholm, Kornhamnstorg 6. Tel\n08-2189 94, 2189 97. Bankgiro\n16-0412. Postgiro 50537\nVeiksamhet: Säljer trä o\nplastplugg samt tillhörande verktyg\nÅrsomsättning: 450 000\nAktiekapital: 88 000\nVerkst dir: Isidor Fall\nEtableringsår 1894.\n\nWRAMBORGS TRIKÅ.\nFABRIK AB\n\nPnr 212 25\n\nMalmö. Stillmansg 9. Tel\n040-9352 30. Bankgiro 641-3330.\nPostgiro 149563-9. Tga Wramtex\nVerksamhet: Tillverkar som\nspecia-lité herr-, dam- o barnstrumpcr,\nstrumpbyxor\nAktiekapital: 250 000\nVerkst dir: Albin Wramborg\nEtableringsår: 1944\nOmbildat till aktiebolag 1951.\n\nWRANGES OPTISKA AB\n\nPnr 400 60\n\nGöteborg 6, Gradmansplatsen 1.\nBox 6085. Tel 031-1984 70.\nBankgiro 36-2235. Postgiro 41289-0\nVerksamhet: Säljer optiska artiklar\nAntal anställda: 4\nÅrsomsättning: 300 000\nAktiekapital: 20 000\nStyrelse: Sven Wrange (ordf),\nGunnar Wrange\nVerkst dir: Gunnar Wrange\nEtableringsår: 1918\nOmbildat till aktiebolag 1959.\n\nWRANGES JUVELERARE AB,\nSVEN\n\nPnr 400 60\n\nGöteborg 6, Redbergsv 17. Box\n6085. Tel 031-151615, 1564 48.\nBankgiro 36-2195. Postgiro41289-0\nVerksamhet: Guldsmedsvaror,\nde-taljförsäljning o tillverkning.\nTillverkar förlovningsringar,\nprydnadsringar, alliansringar, juvelringar\nmm\n\nAntal anställda: 8\nÅrsomsättning: 750 000\nAktiekapital: 87 000\nStyrelse: Sven Wrange (ordf),\nGunnar Wrange\nVeikst dir Sven Wrange\nEtableringsår 1918\nOmbildat till aktiebolag 1959.\n\nVRENA MEKANISKA\nVERKSTAD\n\nPnr 640 33\n\nBettna, Box 69. Tel 0155-922 00.\nBankgiro 82-7328. Postgiro 203626\nVerksamhet: Svetsade\nkonstruktioner o specialmaskiner, även rostfritt\nAntal anställda: 35\nÅrsomsättning: 1 800 000\nChef: Fabr Gunnar A W Johansson\nEtableringsår. 1958.\n\nLIDÉN &amp; SÖNER AB, B A\n\nPnr 102 61\n\nStockholm 4, Barnängsg 60. Box\n4044. Tel 08-23 20 45. Bankgiro\n235-1633. Postgiro 51421-6.\nTga Pennfabriken\nVerksamhet: Säljer ritmateriel o\nkonstnärsmateriel\nAntal anställda: 20\nÅrsomsättning: 2000 000\nAktiekapital: 25 000\nVerkst dir: Bertram A Lidén\nEtableringsår: 1939.\n\nDYNAMOBORSTFABRIKEN, AB\n\nPnr 592 00\n\nVadstena, Stråg 2. Box 15. Tel\n0143-115 55. Bankgiro 127-0420.\nPostgiro 9300-5. Tga Essdewe\nVerksamhet: Tillverkar elektr\nborstar, elektrografit samt\npulvermetallurgiska produkter\n\nVarunamn: Carbex, Densofit,\nEssdewe, SD, SDW\nAktiekapital: 100 000\nVerkst dir: Ing Per-Olof Olsson\nEtableringsår: 1887\nOmbildat till aktiebolag 1946.\n\nDYRÉLFABRIKEN\n\nPnr 83100\n\nÖstersund, Ope 2760. Tel\n063-35155, 35144. Postgiro 168552\nVerksamhet: Massartiklar av plåt,\ntråd m m. Hörn- o kantskydd,\nklämmer o spikbleck för emballering av\nwallboard o trävaror. Press verktyg,\nfiskredskap\nVarunamn: Dyrél\nAntal anställda: 4\nÅrsomsättning: 200 000\nÄgare o chef: Ake Dyrelius\nEtableringsår: 1948.\n\nREKLAMTÄNDSTICKAN, AB\n\nPnr 302 50\n\nHalmstad, Pilefeltsg 64. Tel\n035-12 49 19, 124150. Bankgiro\n531-8506. Postgiro 717981-5\nVerksamhet: Tillverkar\nreklamtändstickor\nAntal anställda: 8\nAktiekapital: 5 000\nEtableringsår: 1968.\n\nmalmsten ab, carl\n\nPnr 11451\n\nStockholm, Strandv 5. Tel\n08-23 33 80. Bankgiro 56-4589. Postgiro\n153191\n\nVeiksamhet: Tillverkar möbler,\ntextilier o inredningar. Formgivning\nÅrsomsättning: 2 100000\nAktiekapital: 108 000\nStyrelseordf: Dir Ernst Bergkvist\nVerkst dir: Prof Carl Malmsten\nEtableringsår: 1916.\n\nmalmö butiks.\nmontering, ab\n\nPnr 211 31\n\nMalmö, O Förstadsg 10. Tel\n040-12 95 93. Bankgiro 263-4418.\nPostgiro 37643-4\n\nVerksamhet: Inredningsdetaljer,\nskyltställ\n\nAktiekapital: 15 300\nVerkst dir: Erik Demuth\nEtableringsår: 1922.\n\nmalmö byggmästares\ngemensamma byggnads\nab bgb\n\nPnr 211 35\n\nMalmö, Kalendeg 9. Tel 040-\n\n394 30. Bankgiro 26-0143. Postgiro\n\n246824\n\nVerksamhet:\nIntressesammanslutning i byggnadsfrågor\nAntal anställda: 15\nAktiekapital: 700 000\nVeikst dir: Civiling Bengt Ch\nJansson\n\nEtableringsår: 1944.\n\nSOBELPÄLS, AB\n\nPnr 573 01\n\nTranås 1, Box 192. V Järnvägsg 13.\nTel 0140-100 65. Bankgiro\n130-4658. Postgiro 379188-6\nVerksamhet: Tillverkar o säljer\npälsar en gros\nAntal anställda: 40\nÅrsomsättning: 4 500 000\nAktiekapital: 15 000\nVerkst dir: Harald Sätermo\nEtableringsår: 1961.\n\nTRANSPACK, AB\n\nPnr 25255\n\nHelsingborg, Gevärsg 4. Tel\n042-1803 45. Bankgiro 730-0981.\nPostgiro 369270-4\n\nVerksamhet: Tillverkar\npolyeten-påsar med flerfärgstryck\nAntal anställda: 37\nÅrsomsättning: 4 500000\nFirmatecknare: Karl-Richard\nAxelson, Anders Sune Pehrsson\nEtableringsår: 1967.\n\nTRANSPORT, ÅKERI.\nFÖRENINGEN\n\nPnr 113 27\n\nStockholm, Surbrunns g 61. Tel\n08-3317 27, 3183 93. Bankgiro\n72-4513. Postgiro 192109\nVerksamhet: Akerirörelse\nAntal anställda: 4\nStyrelse: Ryttmäst Jan Lotelius\n(ordf), åkeriäg Sven Andersson,\nåkeriäg Arne Gustavsson, dir\nRu-nard Jansson, dir Paul Lundström,\ndir Evert Mattsson, kamrer\nKarl-Erik Wesström\n\nFörest: Kamrer Bengt Isaksson\nEtableringsår 1924.\n\nTRANSPORT. AB I\nJÖNKÖPING TRANSAB\n\nPnr 552 67\n\nJönköping, Porfyrv 9. Tel\n036-1183 85. Bankgiro 855-0683.\nPostgiro 236677-1\n\nVeiksamhet: Order- o fakturerings-\n\ncentral för lastbilar\n\nAntal anställda: 6\n\nÅrsomsättning: 7 000 000\n\nAktiekapital: 134 000\n\nVeikst dir. Åkeriäg Göran Larsson\n\nEtableringsår. 1968.\n\nTRANSPORTANORDNINGAR,\nINGENJURSFIRMA\n\nPnr 113 28\n\nStockholm, Upplandsg 54. Tel\n08-34 49 39\n\nVerksamhet: Transportanordningar\nÄgare o chef: R Domeij\nEtableringsår: 1955.\n\nTRANSPORTBOLAGET I\nSÖDERTÄLJE AB\n\nPnr 151 03\n\nSödertälje 3, Morabergsv 17. Box\n3016. Tel 0755-398 40. Bankgiro\n17-0678. Postgiro 108924\nVerksamhet: Renhållning\nAntal anställda: 15\nÅrsomsättning: 1 800 000\nAktiekapital: 60 000\nVerkst dir: Hans Andersson.\n\nTRANSPORT-CENTRALEN\nEK FOR\n\nPnr 302 50\n\nHalmstad, Gjutareg 1. Tel\n035-1040 70. Bankgiro 423-5370.\nPostgiro 170308-1\n\nVerksamhet: Entreprenadarbeten\nmed gräv- o lastmaskiner, lastbilar\no dumprar. Lokal- o fjärrtransporter\nAntal anställda: 100\nÅrsomsättning: 7 000 000\nChef: S-O Nyström\nEtableringsår: 1940.",
    "structured": {
        "1": {
            "company_name": "HELLBERG AB",
            "address": "Stockholm 15, S Mälarstrand 21. Box 15069",
            "phone_number": "08-4215 45, 43 25 30",
            "bank_details": {
                "bankgiro": "72-0119",
                "postgiro": "58112"
            },
            "activity": "Optiska artiklar en gros",
            "employees": 9,
            "annual_turnover": 700000,
            "capital": 40000,
            "key_personnel": [
                {
                    "name": "Kurt Emanuel Pettersson"
                }
            ],
            "establishment_year": 1935
        },
        "2": {
            "company_name": "HELLBERG KB, BYGGNADS-FIRMAN VILHELM",
            "address": "Enskede, Bjulev 8",
            "phone_number": "08-9184 00, 9184 01",
            "bank_details": {
                "bankgiro": "478-7677",
                "postgiro": "153685-3"
            },
            "activity": "Byggnadsrörelse för ny-, om- o tillbyggnader",
            "employees": 55,
            "annual_turnover": 3500000,
            "establishment_year": 1937
        },
        "3": {
            "company_name": "HELLESENSSVENSKA AB",
            "address": "Stockholm, Artillerig 16",
            "phone_number": "08-67 00 65",
            "bank_details": {
                "bankgiro": "732-0393",
                "postgiro": "1965-3"
            },
            "activity": "säljer Hellesens brunstensbatterier, alkaliska brunstensbatterier samt kvicksilverbatterier. Handlyktor, ficklampor samt diverse annan batteridriven apparatur",
            "employees": 11,
            "capital": 150000,
            "key_personnel": [
                {
                    "name": "Disp Jan Sahlén",
                    "position": "Chef"
                },
                {
                    "name": "Kamrer Johan W Olson",
                    "position": "Kontorschef"
                }
            ],
            "establishment_year": 1908
        },
        "4": {
            "company_name": "HELLIDENS VATTENPASS & SNICKERIFABRIK",
            "address": "Tidaholm, Kullö",
            "phone_number": "0502-102 93",
            "postgiro": "334455-3",
            "activity": "Träförädlingsfabrik",
            "employees": 12,
            "key_personnel": [
                {
                    "name": "Erik Svensson",
                    "position": "Fimiatecknare"
                },
                {
                    "name": "Låge Bodin",
                    "position": "Fimiatecknare"
                }
            ],
            "establishment_year": 1947
        },
        "5": {
            "company_name": "HELLQVISTS PAPPERS-INDUSTRI AB",
            "address": "Oskarshamn, Skolg 7",
            "phone_number": "0491-104 74",
            "bankgiro": "148-6489",
            "postgiro": "10860-5",
            "activity": "Tillverkar kuvert, provsäckar. Specialitet: fönsterkuvert",
            "employees": 45,
            "owner": "Gunnar Hellqvist",
            "establishment_year": 1921
        },
        "6": {
            "company_name": "EYRA INDUSTRIER, AB",
            "address": "Örebro, Virkesv. Industriområdet, Holmen",
            "phone_number": "019-12 4185",
            "bankgiro": "495-5027",
            "postgiro": "99111-7",
            "activity": "Tillverkar bordsbestick m m. Utför pressningsarbeten",
            "employees": 25,
            "annual_turnover": 1300000,
            "capital": 112000,
            "key_personnel": [
                {
                    "name": "Ake Gustavsson",
                    "position": "Verkst dir"
                }
            ],
            "establishment_year": 1947
        },
        "7": {
            "company_name": "KARLSHAMNS TRÄVARU AB",
            "address": "Karlshamn, Regeringsg 76",
            "phone_number": "0454-11013, 139 74",
            "postgiro": "578050-7",
            "activity": "Köper o säljer trävaror, huvudsakligen för export",
            "employees": 3,
            "annual_turnover": 7000000,
            "key_personnel": [
                {
                    "name": "K G Söderholm",
                    "position": "Verkst dir"
                }
            ],
            "establishment_year": 1961
        },
        "8": {
            "company_name": "KARLSKOGA AUTOMAT. SVARVNING AB",
            "address": "Karlskoga, Maskinv 14",
            "phone_number": "0586-376 00",
            "bankgiro": "60-5441",
            "postgiro": "32899",
            "activity": "Legotillverkning av automatsvarvade detaljer",
            "employees": 7,
            "annual_turnover": 500000,
            "capital": 20000,
            "key_personnel": [
                {
                    "name": "Fabr Gunnar Adrian",
                    "position": "Chef"
                },
                {
                    "name": "Fabr Edvard Nyström",
                    "position": "Chef"
                }
            ],
            "establishment_year": 1949
        },
        "9": {
            "company_name": "VOXNANSKRAFT AB",
            "address": "Stockholm 3, Box 3118. Kammakarg 7",
            "phone_number": "08-23 33 50",
            "bankgiro": "160-9205",
            "postgiro": "706810-9",
            "activity": "Produktion, försäljning o förmedling av elektrisk kraft",
            "annual_turnover": 158000000,
            "capital": 70000000,
            "key_personnel": [
                {
                    "name": "Tfekn dr Marcus Wallenberg",
                    "position": "Styrelseordf"
                },
                {
                    "name": "Ragnar Söderberg",
                    "position": "Styrelse"
                },
                {
                    "name": "Ake TVrethem",
                    "position": "Styrelse"
                },
                {
                    "name": "Ulf Glimstedt",
                    "position": "Verkst dir"
                }
            ],
            "establishment_year": 1958
        },
        "10": {
            "company_name": "V.PLUGGEN AB",
            "address": "Stockholm, Kornhamnstorg 6",
            "phone_number": "08-2189 94, 2189 97",
            "bankgiro": "16-0412",
            "postgiro": "50537",
            "activity": "Säljer trä o plastplugg samt tillhörande verktyg",
            "annual_turnover": 450000,
            "capital": 88000,
            "key_personnel": [
                {
                    "name": "Isidor Fall",
                    "position": "Verkst dir"
                }
            ],
            "establishment_year": 1894
        },
        "11": {
            "company_name": "WRAMBORGS TRIKÅ. FABRIK AB",
            "address": "Malmö, Stillmansg 9",
            "phone_number": "040-9352 30",
            "bankgiro": "641-3330",
            "postgiro": "149563-9",
            "activity": "Tillverkar som specialité herr-, dam- o barnstrumpcr, strumpbyxor",
            "capital": 250000,
            "key_personnel": [
                {
                    "name": "Albin Wramborg",
                    "position": "Verkst dir"
                }
            ],
            "establishment_year": 1944
        },
        "12": {
            "company_name": "WRANGES OPTISKA AB",
            "address": "Göteborg 6, Gradmansplatsen 1. Box 6085",
            "phone_number": "031-1984 70",
            "bankgiro": "36-2235",
            "postgiro": "41289-0",
            "activity": "Säljer optiska artiklar",
            "employees": 4,
            "annual_turnover": 300000,
            "capital": 20000,
            "key_personnel": [
                {
                    "name": "Sven Wrange",
                    "position": "Styrelseordf"
                },
                {
                    "name": "Gunnar Wrange",
                    "position": "Styrelse"
                }
            ],
            "establishment_year": 1918
        },
        "13": {
            "company_name": "WRANGES JUVELERARE AB, SVEN",
            "address": "Göteborg 6, Redbergsv 17. Box 6085",
            "phone_number": "031-151615, 1564 48",
            "bankgiro": "36-2195",
            "postgiro": "41289-0",
            "activity": "Guldsmedsvaror, detaljförsäljning o tillverkning. Tillverkar förlovningsringar, prydnadsringar, alliansringar, juvelringar mm",
            "employees": 8,
            "annual_turnover": 750000,
            "capital": 87000,
            "key_personnel": [
                {
                    "name": "Sven Wrange",
                    "position": "Styrelseordf"
                },
                {
                    "name": "Gunnar Wrange",
                    "position": "Styrelse"
                },
                {
                    "name": "Sven Wrange",
                    "position": "Verkst dir"
                }
            ],
            "establishment_year": 1918
        },
        "14": {
            "company_name": "VRENA MEKANISKA VERKSTAD",
            "address": "Bettna, Box 69",
            "phone_number": "0155-922 00",
            "bankgiro": "82-7328",
            "postgiro": "203626",
            "activity": "Svetsade konstruktioner o specialmaskiner, även rostfritt",
            "employees": 35,
            "annual_turnover": 1800000,
            "key_personnel": [
                {
                    "name": "Gunnar A W Johansson",
                    "position": "Chef"
                }
            ],
            "establishment_year": 1958
        },
        "15": {
            "company_name": "LIDÉN & SÖNER AB, B A",
            "address": "Stockholm 4, Barnängsg 60. Box 4044",
            "phone_number": "08-23 20 45",
            "bankgiro": "235-1633",
            "postgiro": "51421-6",
            "activity": "Säljer ritmateriel o konstnärsmateriel",
            "employees": 20,
            "annual_turnover": 2000000,
            "capital": 25000,
            "key_personnel": [
                {
                    "name": "Bertram A Lidén",
                    "position": "Verkst dir"
                }
            ],
            "establishment_year": 1939
        },
        "16": {
            "company_name": "DYNAMOBORSTFABRIKEN, AB",
            "address": "Vadstena, Stråg 2. Box 15",
            "phone_number": "0143-115 55",
            "bankgiro": "127-0420",
            "postgiro": "9300-5",
            "activity": "Tillverkar elektr borstar, elektrografit samt pulvermetallurgiska produkter",
            "brands": [
                "Carbex",
                "Densofit",
                "Essdewe",
                "SD",
                "SDW"
            ],
            "capital": 100000,
            "key_personnel": [
                {
                    "name": "Ing Per-Olof Olsson",
                    "position": "Verkst dir"
                }
            ],
            "establishment_year": 1887
        },
        "17": {
            "company_name": "DYRÉLFABRIKEN",
            "address": "Östersund, Ope 2760",
            "phone_number": "063-35155, 35144",
            "postgiro": "168552",
            "activity": "Massartiklar av plåt, tråd m m. Hörn- o kantskydd, klämmer o spikbleck för emballering av wallboard o trävaror. Press verktyg, fiskredskap",
            "brand": "Dyrél",
            "employees": 4,
            "annual_turnover": 200000,
            "owner": "Ake Dyrelius",
            "establishment_year": 1948
        },
        "18": {
            "company_name": "REKLAMTÄNDSTICKAN, AB",
            "address": "Halmstad, Pilefeltsg 64",
            "phone_number": "035-12 49 19, 124150",
            "bankgiro": "531-8506",
            "postgiro": "717981-5",
            "activity": "Tillverkar reklamtändstickor",
            "employees": 8,
            "capital": 5000,
            "establishment_year": 1968
        },
        "19": {
            "company_name": "MALMSTEN AB, CARL",
            "address": "Stockholm, Strandv 5",
            "phone_number": "08-23 33 80",
            "bankgiro": "56-4589",
            "postgiro": "153191",
            "activity": "Tillverkar möbler, textilier o inredningar. Formgivning",
            "annual_turnover": 2100000,
            "capital": 108000,
            "key_personnel": [
                {
                    "name": "Ernst Bergkvist",
                    "position": "Styrelseordf"
                },
                {
                    "name": "Carl Malmsten",
                    "position": "Verkst dir"
                }
            ],
            "establishment_year": 1916
        },
        "20": {
            "company_name": "MALMÖ BUTIKS-MONTERING, AB",
            "address": "Malmö, O Förstadsg 10",
            "phone_number": "040-12 95 93",
            "bankgiro": "263-4418",
            "postgiro": "37643-4",
            "activity": "Inredningsdetaljer, skyltställ",
            "capital": 15300,
            "key_personnel": [
                {
                    "name": "Erik Demuth",
                    "position": "Verkst dir"
                }
            ],
            "establishment_year": 1922
        }
    }
}