{
    "original": "KULL &amp; HALLBERG AB\n\nPnr 302 43\n\nHalmstad, Storg 17. Tel 035-1186 00.\nPostgiro 14885. Tga Kull.\nTelex 38052 KULLHST S\nVerksamhet: Byggmaterial,\nmaskinförnödenheter, varmförzinkning,\nstållinor\n\nAktiekapital: 600 000\n\nVerkst dir: Konsul Gunnar Nordlöf\n\nEtableringsår: 1901.\n\nBYGGKONSULT, AB\n\nPnr 752 40\n\nUppsala, Lindsbergsg 15. Tel\n018-10 02 75. Bankgiro 14-5538.\nPostgiro 660630-5\nVerksamhet Byggledning,\nbygg-kontroll, projektering\nAntal anställda: 8\nÅrsomsättning: 400 000\nAktiekapital: 5 000\nVerkst dir. Per Eriksson\nEtableringsår: 1964.\n\nULLHOLM, AB K A\n\nPnr 58101\n\nLinköping 1, Sveag 3. Fack. Tel\n013-12 96 70. Bankgiro 120-1946.\nPostgiro 6163-0. Tga Ullholms\nVerksamhet: Strumpfabrik o\nengros-handel\n\nVarunamn: Ulla\nAntal anställda: 26\nAktiekapital: 1215 000\nVerkst dir Sture von der Burg\nEtableringsår. 1916\nOmbildat till aktiebolag 1924.\n\nULLMAN &amp; CO AB, J G\n\nPnr 400 24\n\nGöteborg 35, Box 35026.\nPrästgårdsängen 8. Tel 031-40 99 83.\nBankgiro 420-1950. Postgiro\n41023-3. Tga Ullman\nVerksamhet: Pälsvaror en gros.\nMaskiner för slakterier\nAntal anställda: 14\nÅrsomsättning: 6 130 000\nAktiekapital: 250 000\nVerkst dir. Göran Ullman\nEtableringsår. 1882.\n\nFRÖDING AGENTURER, THURE\n\nPnr 416 74\n\nGöteborg, Trebackeg 2. Tel\n031-2180 60. TgaPerdingco\nVerksamhet: Agenturer i järn- o\nglasvaror\n\nVarunamn: Anchor Hocking USA\nChef: Thure Fröding\nEtableringsår: 1946.\n\nSVENSKS ROSTFRIA, R\n\nPnr 37012\n\nHallabro, Box 32. Tel 0457-510 98.\nPostgiro 143046-1\nVerksamhet: Tillverkar maskiner\no rostfria inredningar för\nlivsmedelsindustrin\nAntal anställda: 13\nÅrsomsättning: 1000 000\nÄgare: Fabr Rune Svensk\nEtableringsår: 1945.\n\nSVENSKA AB ALFRED OLSEN\n&amp; CO\n\nPnr 171 20\n\nSolna 1, Råsundav 166. Fack. Tel\n08-82 06 09. Postgiro 52328. Tga\nAolsen\n\nVerksamhet: Import av\nsmörjoljor\n\nAktiekapital: 1000 000\nStyrelse: Adv Erie Köhler (ordf),\ndir Lars Borgh, dir B G Fahlander\nVerkst dir: B G Fahlander\nFörsäljn-chef: Disp Sune Bengtsson\nEtableringsår: 1933.\n\nSVENSKA AMERIKA\nLINIEN, AB\n\nPnr 403 13\n\nGöteborg 2, Box 2185. Tel\n031-17 20 20, 17 5100. Bankgiro\n50-0546. Postgiro 41270. Telex 2250.\nTga Hemland\n\nVerksamhet: Rederirörelse\nAntal anställda: 958\nÅrsomsättning: 91755 000\nAktiekapital: 50 000 000\nVerkst dir: Erik Wijk\nEtableringsår: 1911.\n\nÅDALENS TRÄVARU AB\n\nPnr 901 04\n\nUmeå 1, Box 310. Tel 090-12 47 80,\n12 47 85. Bankgiro 76-7878.\nPostgiro 519100. Tga Rolfwood\nVerksamhet: Trävaror engros\n-export, trävaror för\nförädlingsindustri, listverk o byggnation\nVerkst dir. Jan Wisén.\n\nÅDALS- HUS AKTIEBOLAG\n\nPnr 87201\n\nKramfors 1, Box 12. Tel 0612-\n\n115 80. Bankgiro 601-0219.\nPostgiro 172270-1. Tga Adals-Hus\nVerksamhet Tillverkar o säljer\nmonteringsfärdiga trähus i\nstor-blocksystem med hög\nförädlingsgrad\n\nAntal anställda: 110\nÅrsomsättning: 14 000 000\nAktiekapital: 4 0 00 000\nVerkst din Sven Casselbrant\nKonstr-chef: Ing Kjell Ostman\nProduktionschef: Ing Anders\nPettersson\n\nMaiknadschef: Ekonom Stig\nEricsson\n\nInköpschef: Ing Gunnar Strandberg\nEtableringsår: 1968.\n\nVARBERGS TRANSPORT AB\n\nPnr 432 00\n\nVarberg, Box 166. Kungsg 6. Tel\n0340-185 90. Bankgiro 233-8713.\nPostgiro 162500-3. Telex 3479\nVerksamhet Utför internationella\nlandsvägstransporter\nAntal anställda: 7\nÅrsomsättning: 4 000 000\nAktiekapital: 6 000\nVerkst din Willy Andersson,\nGösta Hedlin\n\nSpeditörer: Hans-Erik Berndtsson,\nSören Strömberg\nEtableringsår: 1965.\n\nVARBERGS TRÄ.\nFORÄDLING, AB\n\nPnr 432 00\n\nVarberg, Brunnsbergsv. Box 29.\nTel 0340-160 70. Bankgiro\n354-7692. Postgiro 36917-3\nVerksamhet: Säljer\nbyggnadssnickerier, inredningar o trävaror\nAntal anställda: 115\n\nAktiekapital: 142 500\nVerkst dir: Verner Nilsson\nEtableringsår: 1934.\n\nVARBERGS\nTRÄ-IMPREGNERING AB\n\nPnr 432 00\n\nVarberg, Nya Industriområdet. Tel\n0340-180 75. Bankgiro 354-9359.\nPostgiro 463330-1\nVerksamhet: Säljer trävaror o\nbyggnadsmaterial\nAntal anställda: 15\nAktiekapital: 75 000\nVerkst dir: Joh Alfr Johansson\nEtableringsår: 1952.\n\nWARBERGS\nTRÄVARU-EXPORT AB\n\nPnr 432 00\n\nVarberg, Norrg 3. Tel 0340-163 75.\nBankgiro 42-5204. Postgiro 36918.\nTga Träexporten\n\nVerksamhet: Säljer wallboard,\nplywood, lamell o trävaror en gros.\nExporterar sågade trävaror o\nslipers\n\nAntal anställda: 3\nÅrsomsättning: 5 000 000\nAktiekapital: 100 000\nVerkst dir: Karl Bendix\nDisp: Ake Bendix\nEtableringsår: 1910\nOmbildat till aktiebolag 1933.\n\nVARBERGSORTENS\nLASTBIL-CENTRAL EK FOR\n\nPnr 432 00\n\nVarberg, Stormhallsv 4. Tel\n0340-16040. Bankgiro 425-3142.\nPostgiro 389770-9\n\nVerksamhet Transportförmedling.\nEntreprenader\nAntal anställda: 25\nÅrsomsättning: 17 000 000\nChef: Disp Ove Börjesson.\n\nWARDS ATEL|IER AB\n\nPnr 543 01\n\nTibro 1, Box 96. Tel 0504-123 40.\nBankgiro 221-4328. Postgiro\n448589-2. Tga Wards\nVerksamhet: Tillverkar o säljer\nmöbler\n\nAntal anställda: 75\nÅrsomsättning: 10 000 000\nAktiekapital: 250 000\nVerkst dir: Våge Ward\nEtableringsår: 1958.\n\nWARD (SCANDINAVIA) AB,\nTHOS W\n\nPnr 113 56\n\nStockholm VA, Birger Jarlsg 131 A.\nTel 08-34 25 85, 34 25 86. Bankgiro\n70-0278. Postgiro 500380. Telex\n19935. Tga Wardsman\nVerksamhet: Säljer grävmaskiner\no kranar\n\nAntal anställda: 10\nÅrsomsättning: 2 400 000\nAktiekapital: 400 000\nVerkst dir Hans Lennart\nLander-holm\n\nEtableringsår: 1948.\n\nJOHANSSON AB, GUSTAV R\n\nPnr 34100\n\nLjungby, Fabriksg. Tel\n0372-135 20. Postgiro 88292-8\nVerksamhet: Utför schaktningar o\ntransporter, även fjärrtraflk\nAntal anställda: 65\nÅrsomsättning: 6 000 000\nAktiekapital: 250000\nVerkst din Gustav R Johansson.\n\nJOHANSSON &amp; CO I HYSSNA\nAB, H\n\nPnr 510 22\n\nHyssna. Tel 0320-392 25, 393 63.\nBankgiro 15-3084. Postgiro 473221\nVerksamhet: Tillverkar\nskyddskläder för olika yrkeskategorier\nEtableringsår: 1954.\n\nJOHANSSONS MEK VERKSTAD,\nHARRY\n\nPnr 54100\n\nSkövde, Kaplansg 20.\nMarinsjöom-rådet. Tel 0500-138 77, 814 25\nVeiksamhet: Pressningsarbeten,\nsvarvning, alla slags mek arbeten\nÄgare o chef: Fabr Harry\nJohansson.\n\nJOHANSSON, AB HELGE\n\nPnr 14200\n\nTrångsund, Lännagårdsv 18. Tel\n08-764 92 93, 764 92 94.\nBankgiro48-1019. Postgiro 41365. Tga Heljo\nVerksamhet: Tillverkar o säljer\ntät-ningsmedel, kondensskydds-,\nunderreds- o rostskyddsmedelmassor\nVarunamn: Tiger Rubber\n.Antal anställda: 13\nÅrsomsättning: 2 000 000\nAktiekapital: 50 000\nVerkst dir: A-S Sandberg\nEtableringsår: 1943.\n\nHOSJO MURBRUKS AB\n\nPnr 79107\n\nFalun 7, Box 1295. Tel 023-32037,\n320 77. Bankgiro 46-7108. Postgiro\n93924\n\nVerksamhet: Säljer betonggrus,\nsand, stenmjöl, singel, makadam\nAntal anställda: 16\nÅrsomsättning: 1800 000\nAktiekapital: 30 000\nVerkst dir: Alf Nygren\nEtableringsår: 1938.\n\nIKATRYCK, AB\n\nPnr 104 32\n\nStockholm 19, Box 19101.Tuleg 19.\nTel 08-15 19 90. Bankgiro\n167-0249. Postgiro 51784-7\nVeiksamhet: Bok- o offsettryck.\nSpecialitet: blanketter, folders o\nkataloger\n\nAntal anställda: 26\nÅrsomsättning: 1700000\nAktiekapital: 40 400\nStyrelse: Overing Lars Malmsten\n(ordf), dir Per Malmsten, herr Hans\nSöderman\n\nVerkst dir: Per Malmsten\nTekn chef: Hans Söderman\nEtableringsår: 1921.",
    "structured": {
        "1": {
            "company_name": "KULL & HALLBERG AB",
            "pnr": "302 43",
            "address": "Halmstad, Storg 17",
            "phone_number": "035-1186 00",
            "postgiro": "14885",
            "activity": "Verksamhet: Byggmaterial, maskinförnödenheter, varmförzinkning, stållinor",
            "capital": 600000,
            "key_personnel": [
                {
                    "name": "Konsul Gunnar Nordlöf",
                    "position": "Verkst dir"
                }
            ],
            "establishment_year": 1901
        },
        "2": {
            "company_name": "BYGGKONSULT, AB",
            "pnr": "752 40",
            "address": "Uppsala, Lindsbergsg 15",
            "phone_number": "018-10 02 75",
            "bankgiro": "14-5538",
            "postgiro": "660630-5",
            "activity": "Verksamhet Byggledning, bygg-kontroll, projektering",
            "employees": 8,
            "annual_turnover": 400000,
            "capital": 5000,
            "key_personnel": [
                {
                    "name": "Per Eriksson",
                    "position": "Verkst dir"
                }
            ],
            "establishment_year": 1964
        },
        "3": {
            "company_name": "ULLHOLM, AB K A",
            "pnr": "58101",
            "address": "Linköping 1, Sveag 3",
            "phone_number": "013-12 96 70",
            "bankgiro": "120-1946",
            "postgiro": "6163-0",
            "activity": "Verksamhet: Strumpfabrik o engros-handel",
            "employees": 26,
            "capital": 1215000,
            "key_personnel": [
                {
                    "name": "Sture von der Burg",
                    "position": "Verkst dir"
                }
            ],
            "establishment_year": 1916
        },
        "4": {
            "company_name": "ULLMAN & CO AB, J G",
            "pnr": "400 24",
            "address": "Göteborg 35, Box 35026, Prästgårdsängen 8",
            "phone_number": "031-40 99 83",
            "bankgiro": "420-1950",
            "postgiro": "41023-3",
            "activity": "Verksamhet: Pälsvaror en gros. Maskiner för slakterier",
            "employees": 14,
            "annual_turnover": 6130000,
            "capital": 250000,
            "key_personnel": [
                {
                    "name": "Göran Ullman",
                    "position": "Verkst dir"
                }
            ],
            "establishment_year": 1882
        },
        "5": {
            "company_name": "FRÖDING AGENTURER, THURE",
            "pnr": "416 74",
            "address": "Göteborg, Trebackeg 2",
            "phone_number": "031-2180 60",
            "activity": "Verksamhet: Agenturer i järn- o glasvaror",
            "key_personnel": [
                {
                    "name": "Thure Fröding",
                    "position": "Chef"
                }
            ],
            "establishment_year": 1946
        },
        "6": {
            "company_name": "SVENSKS ROSTFRIA, R",
            "pnr": "37012",
            "address": "Hallabro, Box 32",
            "phone_number": "0457-510 98",
            "postgiro": "143046-1",
            "activity": "Verksamhet: Tillverkar maskiner o rostfria inredningar för livsmedelsindustrin",
            "employees": 13,
            "annual_turnover": 1000000,
            "owner": "Fabr Rune Svensk",
            "establishment_year": 1945
        },
        "7": {
            "company_name": "SVENSKA AB ALFRED OLSEN & CO",
            "pnr": "171 20",
            "address": "Solna 1, Råsundav 166",
            "phone_number": "08-82 06 09",
            "postgiro": "52328",
            "activity": "Verksamhet: Import av smörjoljor",
            "capital": 1000000,
            "key_personnel": [],
            "establishment_year": 1933
        },
        "8": {
            "company_name": "SVENSKA AMERIKA LINIEN, AB",
            "pnr": "403 13",
            "address": "Göteborg 2, Box 2185",
            "phone_number": "031-17 20 20, 17 5100",
            "bankgiro": "50-0546",
            "postgiro": "41270",
            "activity": "Verksamhet: Rederirörelse",
            "employees": 958,
            "annual_turnover": 91755000,
            "capital": 50000000,
            "key_personnel": [
                {
                    "name": "Erik Wijk",
                    "position": "Verkst dir"
                }
            ],
            "establishment_year": 1911
        },
        "9": {
            "company_name": "ÅDALENS TRÄVARU AB",
            "pnr": "901 04",
            "address": "Umeå 1, Box 310",
            "phone_number": "090-12 47 80, 12 47 85",
            "bankgiro": "76-7878",
            "postgiro": "519100",
            "activity": "Verksamhet: Trävaror engros export, trävaror för förädlingsindustri, listverk o byggnation",
            "key_personnel": [
                {
                    "name": "Jan Wisén",
                    "position": "Verkst dir"
                }
            ]
        },
        "10": {
            "company_name": "ÅDALS- HUS AKTIEBOLAG",
            "pnr": "87201",
            "address": "Kramfors 1, Box 12",
            "phone_number": "0612-115 80",
            "bankgiro": "601-0219",
            "postgiro": "172270-1",
            "activity": "Verksamhet: Tillverkar o säljer monteringsfärdiga trähus i stor-blocksystem med hög förädlingsgrad",
            "employees": 110,
            "annual_turnover": 14000000,
            "capital": 4000000,
            "key_personnel": [
                {
                    "name": "Sven Casselbrant",
                    "position": "Verkst dir"
                },
                {
                    "name": "Ing Kjell Ostman",
                    "position": "Konstr-chef"
                },
                {
                    "name": "Ing Anders Pettersson",
                    "position": "Produktionschef"
                },
                {
                    "name": "Ekonom Stig Ericsson",
                    "position": "Maiknadschef"
                },
                {
                    "name": "Ing Gunnar Strandberg",
                    "position": "Inköpschef"
                }
            ],
            "establishment_year": 1968
        },
        "11": {
            "company_name": "VARBERGS TRANSPORT AB",
            "pnr": "432 00",
            "address": "Varberg, Box 166, Kungsg 6",
            "phone_number": "0340-185 90",
            "bankgiro": "233-8713",
            "postgiro": "162500-3",
            "activity": "Verksamhet Utför internationella landsvägstransporter",
            "employees": 7,
            "annual_turnover": 4000000,
            "capital": 6000,
            "key_personnel": [
                {
                    "name": "Willy Andersson",
                    "position": "Verkst dir"
                },
                {
                    "name": "Gösta Hedlin",
                    "position": "Verkst dir"
                },
                {
                    "name": "Hans-Erik Berndtsson",
                    "position": "Speditörer"
                },
                {
                    "name": "Sören Strömberg",
                    "position": "Speditörer"
                }
            ],
            "establishment_year": 1965
        },
        "12": {
            "company_name": "VARBERGS TRÄ. FORÄDLING, AB",
            "pnr": "432 00",
            "address": "Varberg, Brunnsbergsv. Box 29",
            "phone_number": "0340-160 70",
            "bankgiro": "354-7692",
            "postgiro": "36917-3",
            "activity": "Verksamhet: Säljer byggnadssnickerier, inredningar o trävaror",
            "employees": 115,
            "capital": 142500,
            "key_personnel": [
                {
                    "name": "Verner Nilsson",
                    "position": "Verkst dir"
                }
            ],
            "establishment_year": 1934
        },
        "13": {
            "company_name": "VARBERGS TRÄ-IMPREGNERING AB",
            "pnr": "432 00",
            "address": "Varberg, Nya Industriområdet",
            "phone_number": "0340-180 75",
            "bankgiro": "354-9359",
            "postgiro": "463330-1",
            "activity": "Verksamhet: Säljer trävaror o byggnadsmaterial",
            "employees": 15,
            "capital": 75000,
            "key_personnel": [
                {
                    "name": "Joh Alfr Johansson",
                    "position": "Verkst dir"
                }
            ],
            "establishment_year": 1952
        },
        "14": {
            "company_name": "WARBERGS TRÄVARU-EXPORT AB",
            "pnr": "432 00",
            "address": "Varberg, Norrg 3",
            "phone_number": "0340-163 75",
            "bankgiro": "42-5204",
            "postgiro": "36918",
            "activity": "Verksamhet: Säljer wallboard, plywood, lamell o trävaror en gros. Exporterar sågade trävaror o slipers",
            "employees": 3,
            "annual_turnover": 5000000,
            "capital": 100000,
            "key_personnel": [
                {
                    "name": "Karl Bendix",
                    "position": "Verkst dir"
                },
                {
                    "name": "Ake Bendix",
                    "position": "Disp"
                }
            ],
            "establishment_year": 1910
        },
        "15": {
            "company_name": "VARBERGSORTENS LASTBIL-CENTRAL EK FOR",
            "pnr": "432 00",
            "address": "Varberg, Stormhallsv 4",
            "phone_number": "0340-16040",
            "bankgiro": "425-3142",
            "postgiro": "389770-9",
            "activity": "Verksamhet: Transportförmedling. Entreprenader",
            "employees": 25,
            "annual_turnover": 17000000,
            "key_personnel": [
                {
                    "name": "Disp Ove Börjesson",
                    "position": "Chef"
                }
            ]
        },
        "16": {
            "company_name": "WARDS ATEL|IER AB",
            "pnr": "543 01",
            "address": "Tibro 1, Box 96",
            "phone_number": "0504-123 40",
            "bankgiro": "221-4328",
            "postgiro": "448589-2",
            "activity": "Verksamhet: Tillverkar o säljer möbler",
            "employees": 75,
            "annual_turnover": 10000000,
            "capital": 250000,
            "key_personnel": [
                {
                    "name": "Våge Ward",
                    "position": "Verkst dir"
                }
            ],
            "establishment_year": 1958
        },
        "17": {
            "company_name": "WARD (SCANDINAVIA) AB, THOS W",
            "pnr": "113 56",
            "address": "Stockholm VA, Birger Jarlsg 131 A",
            "phone_number": "08-34 25 85, 34 25 86",
            "bankgiro": "70-0278",
            "postgiro": "500380",
            "activity": "Verksamhet: Säljer grävmaskiner o kranar",
            "employees": 10,
            "annual_turnover": 2400000,
            "capital": 400000,
            "key_personnel": [
                {
                    "name": "Hans Lennart Lander-holm",
                    "position": "Verkst dir"
                }
            ],
            "establishment_year": 1948
        },
        "18": {
            "company_name": "JOHANSSON AB, GUSTAV R",
            "pnr": "34100",
            "address": "Ljungby, Fabriksg",
            "phone_number": "0372-135 20",
            "postgiro": "88292-8",
            "activity": "Verksamhet: Utför schaktningar o transporter, även fjärrtraflk",
            "employees": 65,
            "annual_turnover": 6000000,
            "capital": 250000,
            "key_personnel": [
                {
                    "name": "Gustav R Johansson",
                    "position": "Verkst din"
                }
            ]
        },
        "19": {
            "company_name": "JOHANSSON & CO I HYSSNA AB, H",
            "pnr": "510 22",
            "address": "Hyssna",
            "phone_number": "0320-392 25, 393 63",
            "bankgiro": "15-3084",
            "postgiro": "473221",
            "activity": "Verksamhet: Tillverkar skyddskläder för olika yrkeskategorier",
            "establishment_year": 1954
        },
        "20": {
            "company_name": "JOHANSSONS MEK VERKSTAD, HARRY",
            "pnr": "54100",
            "address": "Skövde, Kaplansg 20",
            "phone_number": "0500-138 77, 814 25",
            "activity": "Veiksamhet: Pressningsarbeten, svarvning, alla slags mek arbeten",
            "key_personnel": [
                {
                    "name": "Fabr Harry Johansson",
                    "position": "Ägare o chef"
                }
            ]
        },
        "21": {
            "company_name": "JOHANSSON, AB HELGE",
            "pnr": "14200",
            "address": "Trångsund, Lännagårdsv 18",
            "phone_number": "08-764 92 93, 764 92 94",
            "bankgiro": "48-1019",
            "postgiro": "41365",
            "activity": "Verksamhet: Tillverkar o säljer tät-ningsmedel, kondensskydds-, underreds- o rostskyddsmedelmassor",
            "employees": 13,
            "annual_turnover": 2000000,
            "capital": 50000,
            "key_personnel": [
                {
                    "name": "A-S Sandberg",
                    "position": "Verkst dir"
                }
            ],
            "establishment_year": 1943
        },
        "22": {
            "company_name": "HOSJO MURBRUKS AB",
            "pnr": "79107",
            "address": "Falun 7, Box 1295",
            "phone_number": "023-32037, 320 77",
            "bankgiro": "46-7108",
            "postgiro": "93924",
            "activity": "Verksamhet: Säljer betonggrus, sand, stenmjöl, singel, makadam",
            "employees": 16,
            "annual_turnover": 1800000,
            "capital": 30000,
            "key_personnel": [
                {
                    "name": "Alf Nygren",
                    "position": "Verkst dir"
                }
            ],
            "establishment_year": 1938
        },
        "23": {
            "company_name": "IKATRYCK, AB",
            "pnr": "104 32",
            "address": "Stockholm 19, Tuleg 19",
            "phone_number": "08-15 19 90",
            "bankgiro": "167-0249",
            "postgiro": "51784-7",
            "activity": "Veiksamhet: Bok- o offsettryck. Specialitet: blanketter, folders o kataloger",
            "employees": 26,
            "annual_turnover": 1700000,
            "capital": 40400,
            "key_personnel": [
                {
                    "name": "Overing Lars Malmsten",
                    "position": "Styrelse Ordf"
                },
                {
                    "name": "Per Malmsten",
                    "position": "Dir"
                },
                {
                    "name": "Hans Söderman",
                    "position": "Tekn chef"
                }
            ],
            "establishment_year": 1921
        }
    }
}