{
    "original": "NILSEN &amp; CO LTD AB\n\nPnr 11147\n\nStockholm C, Arsenalsg 4. Tel\n08-1059 28,2123 43. Bankgiro\n56-0338, 70-0119. Postgiro 155543.\nTelex 1547. Tga Nilsenco\nVerksamhet: Export av trävaror\nAntal anställda: 14\nÅrsomsättning: 10 000000\nAktiekapital: 400000\nVerkst dir: B Brynildsen\nEtableringsår. 1916.\n\nVANSBRO SILKETRYCK\n\nPnr 780 50\n\nVansbro. Tel 0281-10177, 103 44.\nBankgiro 79-8961. Postgiro 98821\nVerksamhet: Tillverkar\ndekalkoma-nier alla sorter. Skyltar,\nreklamalster. Utför färgtryck på plast,\nmetall, kartong etc\nAntal anställda: 9\nÄgare o chef: Fabr Börje Hedberg\nEtableringsår: 1946.\n\nINGELSTEN &amp; CO, AB\n\nPnr 330 20\n\nAnders torp. Tel 0371-15121.\nBankgiro 488-0324. Postgiro 133617-1\nVerksamhet: Utför djupdragning o\nexcenterpressning\nAktiekapital: 75 000\nÄgare o chefer: E J I Ingelsten,\nEl V Modén\nEtableringsår: 1937\nOmbildat till aktiebolag 1951.\n\nINGEMANSSON, AB IVAN\n\nPnr 330 30\n\nGnosjö, Box 122. Tel 03 70-91167\nVerksamhet: Tillverkar klämmer\nav järn o rostfritt stål. Böjlig\nmetallslang för El-installationer,\näven plastöverdragen\nAktiekapital: 89400\nVerkst dir: Daniel Ingemansson\nEtableringsår: 1954.\n\nINGENIORS.\n\nse i övrigt resp namn.\n\nINGENJORSGRUPPEN, AB\n\nPnr 232 00\n\nArlöv, Bernstorpsv 18. Box 48. Tel\n040-49 12 63 , 49 30 13. Bankgiro\n405-5430. Postgiro 148273-6\nVerksamhet: Konsulterande\nverksamhet, maskinkonstruktioner,\ntransportanordningar, automatiska\ntillverkningsliner, kontroll o\nbesiktningar\n\nAntal anställda: 9\n\nÅrsomsättning: 600 000\nAktiekapital: 10 000\nVerkst dir: Ing Bertil Pernum\nEtableringsår: 1965.\n\nSCAPA AB\n\nPnr 342 00\n\nAlvesta. Tel 0472-130 00.\nBankgiro 334^5105. Postgiro 339335-2.\nTga Scapa. Telex 4671 SCAPA S\nVerksamhet: Tillverkar soffgrupper\no res års ängar\nAntal anställda: 215\nÅrsomsättning: 29 000 000\nAktiekapital: 1000 000\nVerkst dir: Lennart Jernbeck\nEtableringsår 1959.\n\nSCAPRO (SCANDINAVIAN\nPRODUCE CO AB)\n\nPnr 16115\n\nBromma 15, Alviksv 65. Box 15034.\nTel 08-26 25 10. Tga Scaprocomp.\n\nTelex 17376 SCAPRO S\nVerksamhet: Export o import. Til\nInverkar elektr artiklar\nVarunamn: Secur\nAktiekapital: 60 000\nVerkst dir: Ake Lundin\nEtableringsår 1934.\n\nRYD.VERKEN AB\n\nPnr 360 10\n\nRyd, Box 43. Tel 0459-805 85.\nBankgiro 412-0028. Postgiro\n594600-9\n\nVerksamhet: Tillverkar jiggar,\nfixturer, pressverktyg m m till\nmekanisk verkstadsindustri\nAntal anställda: 20\nÅrsomsättning: 1500 000\nAktiekapital: 100 000\nStyrelse: Dir Sven Paulsson,\nfru Brita Paulsson\nVerkst dir: Sven Paulsson\nEtableringsår: 1970.\n\nRYDO MEKANISKA\nVERK-STAD, AB\n\nPnr 31071\n\nRydöbruk. Tel 0345-204 30.\nBankgiro 799-9394. Postgiro 233290-6\nVerksamhet: Tillverkar\ninvallnings-pumpar o säckhållare. Legoarbeten\nAntal anställda: 21\nAktiekapital: 100 000\nVerkst dir: Göte Jarreby\nEtableringsår: 1967.\n\nMAR\n\nFilial: 285 00 Markaryd, Timsfors.\nTel 0433-11010\nAntal anställda: 7\nÅrsomsättning: 43 000 000\nVerkst dir: Sven-Ove Andersson\nKamrer: Lars Carlsson\nEtableringsår 1875.\n\nANDRÉN &amp; SUNER\n\nPnr 114 57\n\nStockholm, Kaptensg 6. Tel 08-\n\n67 92 00. Tga Andrénplast.\n\nTelex 1857 ANDREN S\n\nVerksamhet: Plaster\n\nFilial: 20110 Malmö 1, Fack. Tel\n\n040-10 03 00\n\nAntal anställda: 30\n\nÄgare o chef: Bo Andrén\n\nEtableringsår: 1935.\n\nOLIVETTI SVENSKA AB\n\nPnr 103 42\n\nStockholm 40, Sergels torg 12. Box\n40084. Tel 08-24 17 60. Bankgiro\n700-4377. Postgiro 55662-1. Tga\nOlivetti. Telex 17399 OLISVEN S\nVerksamhet: Säljer\nkontorsmaskiner, skriv- o räknemaskiner,\nbokförings- o faktureringsmaskiner\ndatamaskiner samt terminaler\nAvdelningskontor i: Anderstorp,\nBorås, Eskilstuna, Falun, Gävle,\nGöteborg, Halmstad, Hälsingborg,\nJönköping, Kalmar, Karlskrona,\nKarlstad, Katrineholm, Kiruna,\nKristianstad, Linköping, Ljusdal,\nLuleå, Malmö, Norrköping, Skara,\nSkellefteå, Skövde, Stockholm,\nSundsvall, Söderhamn, Tranås,\nUddevalla, Umeå, Uppsala,\nVästerås, Växjö, Örebro, Östersund\nAntal anstäUda: 300\nAktiekapital: 6 000 000\nVerkst dir: Sergio Nanni\nEtableringsår: 1939.\n\nOLJEDESTRUKTION AB,\nINGENIURSFIRMA\n\nPnr 17142\n\nSolna, Nybodag 6 B. Tel\n08-83 06 75, 756 60 87. Bankgiro\n743-0424. Postgiro 606757-3\nVerksamhet: Oljesaneringar till\nlands o sjöss. Cisternrengöringar\nAntal anstäUda: 30\nÅrsomsättning: 3 000 000\nAktiekapital: 25 000\nVerkst dir: Ing Arne Larsson.\n\nOLJEKONSUMENTERNAS\nFURBUND EK FUR\n\nPnr 104 25\n\nStockholm 30, Strandbergsg 12.\nFack. Tel 08-54 15 00. Bankgiro\n16-7806. Postgiro 807200. Telex\n1494. Tga Oljekonsumenter\nVerksamhet: Import, inköp o\nförsäljning av biltillbehör, gasol,\nga-solmateriel, kemiska produkter,\nkol, koks, petroleumprodukter o\nvärmeteknisk materiel. Rederi\nVarunamn: OK\nAntal anställda: 1501\nÅrsomsättning: 883 875 799\nInsatskapital: 26 058 660\nVerkst dir: Sten Kjellberg\nEtableringsår: 1945.\n\nOLJEVÄRME, KARLSSON &amp;\nLINDBERG, AB\n\nPnr 60214\n\nNorrköping, Blomsterv 9. Tel\n011-13 36 30, 16 81 35. Bankgiro\n82-6062. Postgiro 109919\nVerksamhet: Utför\noljeeldningsinstallationer\nAntal anstäUda: 7\nÅrsomsättning: 600 000\n\nAktiekapital: 30000\nVerkst dir: R Lindberg\nEtableringsår: 1956.\n\nIRENIUS, AB\n\nPnr 104 30\n\nStockholm 43, Kungstensg48. Box\n45045. Tel 08-34 9140. Bankgiro\n563-4852. Postgiro 155065-6\nVerksamhet: Tillverkar\ndörrskyltar, orienterings- o anslagstavlor,\nmagnettavlor, våningsregister,\netsade o graverade skyltar,\nmetallbokstäver, fasadbokstäver,\nvägvisare\n\nVarunamn: ABI\nAktiekapital: 50 000\nVerkst dir: Gustav Andersson\nEtableringsår: 1938.\n\nBERGENUDD &amp; CO, KB\n\nPnr 96100\n\nBoden, Garvareg 3. Tel\n0921-122 35, 11266. Bankgiro 600-7355.\nPostgiro 326226-8\nVerksamhet: Industribyggnader,\nhus- o byggnadsarbeten,\nkostnadsberäkningar o värderingar\nVerkst dir: Filip Bergenudd\nEtableringsår: 1947.\n\nBERGER &amp;C0 AB, Y\n\nPnr 40122\n\nGöteborg 1, Amerikahuset,\nBar-lastg 2. Box 133. Tel 031-12 46 80.\nTga Bergercomp. Telex 20633\nVerksamhet: Import av garner o\nvävnader. Sundries\nVarunamn: Ybelle\nAntal anställda: 20\nAktiekapital: 200000\nVerkst din O Gudmundsson\nEtableringsår: 1959.",
    "structured": {
        "1": {
            "company_name": "NILSEN & CO LTD AB",
            "pnr": "11147",
            "address": "Stockholm C, Arsenalsg 4",
            "phone_number": "08-1059 28,2123 43",
            "bank_details": {
                "bankgiro": "56-0338",
                "postgiro": "70-0119"
            },
            "activity": "Export av trävaror",
            "employees": 14,
            "annual_turnover": 10000000,
            "capital": 400000,
            "key_personnel": [
                {
                    "name": "B Brynildsen",
                    "position": "Verkstdir"
                }
            ],
            "establishment_year": 1916
        },
        "2": {
            "company_name": "VANSBRO SILKETRYCK",
            "pnr": "780 50",
            "address": "Vansbro",
            "phone_number": "0281-10177, 103 44",
            "bank_details": {
                "bankgiro": "79-8961",
                "postgiro": "98821"
            },
            "activity": "Tillverkar dekalkoma-nier alla sorter. Skyltar, reklamalster. Utför färgtryck på plast, metall, kartong etc",
            "employees": 9,
            "key_personnel": [
                {
                    "name": "Fabr Börje Hedberg",
                    "position": "Ägare o chef"
                }
            ],
            "establishment_year": 1946
        },
        "3": {
            "company_name": "INGELSTEN & CO, AB",
            "pnr": "330 20",
            "address": "Anders torp",
            "phone_number": "0371-15121",
            "bank_details": {
                "bankgiro": "488-0324",
                "postgiro": "133617-1"
            },
            "activity": "Utför djupdragning o excenterpressning",
            "capital": 75000,
            "key_personnel": [
                {
                    "name": "E J I Ingelsten",
                    "position": "Ägare"
                },
                {
                    "name": "El V Modén",
                    "position": "Chefer"
                }
            ],
            "establishment_year": 1937
        },
        "4": {
            "company_name": "INGEMANSSON, AB IVAN",
            "pnr": "330 30",
            "address": "Gnosjö, Box 122",
            "phone_number": "03 70-91167",
            "activity": "Tillverkar klämmer av järn o rostfritt stål. Böjlig metallslang för El-installationer, även plastöverdragen",
            "capital": 89400,
            "key_personnel": [
                {
                    "name": "Daniel Ingemansson",
                    "position": "Verkstdir"
                }
            ],
            "establishment_year": 1954
        },
        "5": {
            "company_name": "INGENJORSGRUPPEN, AB",
            "pnr": "232 00",
            "address": "Arlöv, Bernstorpsv 18, Box 48",
            "phone_number": "040-49 12 63 , 49 30 13",
            "bank_details": {
                "bankgiro": "405-5430",
                "postgiro": "148273-6"
            },
            "activity": "Konsulterande verksamhet, maskinkonstruktioner, transportanordningar, automatiska tillverkningsliner, kontroll o besiktningar",
            "employees": 9,
            "annual_turnover": 600000,
            "capital": 10000,
            "key_personnel": [
                {
                    "name": "Ing Bertil Pernum",
                    "position": "Verkstdir"
                }
            ],
            "establishment_year": 1965
        },
        "6": {
            "company_name": "SCAPA AB",
            "pnr": "342 00",
            "address": "Alvesta",
            "phone_number": "0472-130 00",
            "bank_details": {
                "bankgiro": "334^5105",
                "postgiro": "339335-2"
            },
            "activity": "Tillverkar soffgrupper o res års ängar",
            "employees": 215,
            "annual_turnover": 29000000,
            "capital": 1000000,
            "key_personnel": [
                {
                    "name": "Lennart Jernbeck",
                    "position": "Verkstdir"
                }
            ],
            "establishment_year": 1959
        },
        "7": {
            "company_name": "SCAPRO (SCANDINAVIAN PRODUCE CO AB)",
            "pnr": "16115",
            "address": "Bromma 15, Alviksv 65, Box 15034",
            "phone_number": "08-26 25 10",
            "bank_details": {
                "bankgiro": "N/A",
                "postgiro": "N/A"
            },
            "activity": "Export o import. Til Inverkar elektr artiklar",
            "capital": 60000,
            "key_personnel": [
                {
                    "name": "Ake Lundin",
                    "position": "Verkstdir"
                }
            ],
            "establishment_year": 1934
        },
        "8": {
            "company_name": "RYD.VERKEN AB",
            "pnr": "360 10",
            "address": "Ryd, Box 43",
            "phone_number": "0459-805 85",
            "bank_details": {
                "bankgiro": "412-0028",
                "postgiro": "594600-9"
            },
            "activity": "Tillverkar jiggar, fixturer, pressverktyg m m till mekanisk verkstadsindustri",
            "employees": 20,
            "annual_turnover": 1500000,
            "capital": 100000,
            "key_personnel": [
                {
                    "name": "Sven Paulsson",
                    "position": "Styrelse"
                },
                {
                    "name": "fru Brita Paulsson",
                    "position": "Styrelse"
                },
                {
                    "name": "Sven Paulsson",
                    "position": "Verkstdir"
                }
            ],
            "establishment_year": 1970
        },
        "9": {
            "company_name": "RYDO MEKANISKA VERK-STAD, AB",
            "pnr": "31071",
            "address": "Rydöbruk",
            "phone_number": "0345-204 30",
            "bank_details": {
                "bankgiro": "799-9394",
                "postgiro": "233290-6"
            },
            "activity": "Tillverkar invallnings- pumpar o säckhållare. Legoarbeten",
            "employees": 21,
            "capital": 100000,
            "key_personnel": [
                {
                    "name": "Göte Jarreby",
                    "position": "Verkstdir"
                }
            ],
            "establishment_year": 1967
        },
        "10": {
            "company_name": "MAR",
            "address": "Filial: 285 00 Markaryd, Timsfors",
            "phone_number": "0433-11010",
            "employees": 7,
            "annual_turnover": 43000000,
            "key_personnel": [
                {
                    "name": "Sven-Ove Andersson",
                    "position": "Verkstdir"
                },
                {
                    "name": "Lars Carlsson",
                    "position": "Kamrer"
                }
            ],
            "establishment_year": 1875
        },
        "11": {
            "company_name": "ANDRÉN & SUNER",
            "pnr": "114 57",
            "address": "Stockholm, Kaptensg 6",
            "phone_number": "08-67 92 00",
            "bank_details": {
                "bankgiro": "N/A",
                "postgiro": "N/A"
            },
            "activity": "Plaster",
            "employees": 30,
            "key_personnel": [
                {
                    "name": "Bo Andrén",
                    "position": "Ägare o chef"
                }
            ],
            "establishment_year": 1935
        },
        "12": {
            "company_name": "OLIVETTI SVENSKA AB",
            "pnr": "103 42",
            "address": "Stockholm 40, Sergels torg 12, Box 40084",
            "phone_number": "08-24 17 60",
            "bank_details": {
                "bankgiro": "700-4377",
                "postgiro": "55662-1"
            },
            "activity": "Säljer kontorsmaskiner, skriv- o räknemaskiner, bokförings- o faktureringsmaskiner datamaskiner samt terminaler",
            "employees": 300,
            "capital": 6000000,
            "key_personnel": [
                {
                    "name": "Sergio Nanni",
                    "position": "Verkstdir"
                }
            ],
            "establishment_year": 1939
        },
        "13": {
            "company_name": "OLJEDESTRUKTION AB, INGENIURSFIRMA",
            "pnr": "17142",
            "address": "Solna, Nybodag 6 B",
            "phone_number": "08-83 06 75, 756 60 87",
            "bank_details": {
                "bankgiro": "743-0424",
                "postgiro": "606757-3"
            },
            "activity": "Oljesaneringar till lands o sjöss. Cisternrengöringar",
            "employees": 30,
            "annual_turnover": 3000000,
            "capital": 25000,
            "key_personnel": [
                {
                    "name": "Ing Arne Larsson",
                    "position": "Verkstdir"
                }
            ]
        },
        "14": {
            "company_name": "OLJEKONSUMENTERNAS FURBUND EK FUR",
            "pnr": "104 25",
            "address": "Stockholm 30, Strandbergsg 12",
            "phone_number": "08-54 15 00",
            "bank_details": {
                "bankgiro": "16-7806",
                "postgiro": "807200"
            },
            "activity": "Import, inköp o försäljning av biltillbehör, gasol, gasolmateriel, kemiska produkter, kol, koks, petroleumprodukter o värmeteknisk materiel. Rederi",
            "employees": 1501,
            "annual_turnover": 883875799,
            "insatskapital": 26058660,
            "key_personnel": [
                {
                    "name": "Sten Kjellberg",
                    "position": "Verkstdir"
                }
            ],
            "establishment_year": 1945
        },
        "15": {
            "company_name": "OLJEVÄRME, KARLSSON & LINDBERG, AB",
            "pnr": "60214",
            "address": "Norrköping, Blomsterv 9",
            "phone_number": "011-13 36 30, 16 81 35",
            "bank_details": {
                "bankgiro": "82-6062",
                "postgiro": "109919"
            },
            "activity": "Utför oljeeldningsinstallationer",
            "employees": 7,
            "annual_turnover": 600000,
            "capital": 30000,
            "key_personnel": [
                {
                    "name": "R Lindberg",
                    "position": "Verkstdir"
                }
            ],
            "establishment_year": 1956
        },
        "16": {
            "company_name": "IRENIUS, AB",
            "pnr": "104 30",
            "address": "Stockholm 43, Kungstensg48, Box 45045",
            "phone_number": "08-34 9140",
            "bank_details": {
                "bankgiro": "563-4852",
                "postgiro": "155065-6"
            },
            "activity": "Tillverkar dörrskyltar, orienterings- o anslagstavlor, magnettavlor, våningsregister, etsade o graverade skyltar, metallbokstäver, fasadbokstäver, vägvisare",
            "capital": 50000,
            "key_personnel": [
                {
                    "name": "Gustav Andersson",
                    "position": "Verkstdir"
                }
            ],
            "establishment_year": 1938
        },
        "17": {
            "company_name": "BERGENUDD & CO, KB",
            "pnr": "96100",
            "address": "Boden, Garvareg 3",
            "phone_number": "0921-122 35, 11266",
            "bank_details": {
                "bankgiro": "600-7355",
                "postgiro": "326226-8"
            },
            "activity": "Industribyggnader, hus- o byggnadsarbeten, kostnadsberäkningar o värderingar",
            "key_personnel": [
                {
                    "name": "Filip Bergenudd",
                    "position": "Verkstdir"
                }
            ],
            "establishment_year": 1947
        },
        "18": {
            "company_name": "BERGER & C0 AB, Y",
            "pnr": "40122",
            "address": "Göteborg 1, Amerikahus",
            "phone_number": "031-12 46 80",
            "bank_details": {
                "bankgiro": "N/A",
                "postgiro": "N/A"
            },
            "activity": "Import av garner o vävnader. Sundries",
            "employees": 20,
            "capital": 200000,
            "key_personnel": [
                {
                    "name": "O Gudmundsson",
                    "position": "Verkstdir"
                }
            ],
            "establishment_year": 1959
        }
    }
}