{
    "original": "GRYTGOLS BRUKS AB\n\nPnr 610 11\n\nGrytgöl. Tel 0122-430 40. Godsadr\nLjusfallshammar. Postgiro 6617.\nTga Grytgolwire, Finspång\nVerksamhet Tråddrageri o\nhäftklam-mertill verkning\nÅrsomsättning: 7 000 000\nAktiekapital: 825 000\nVerkst dir: Bergsing Jan Hagstedt\nFörsäljn-chef: Ing S Eideland\nEtableringsår: 1893.\n\nGRYTHYTTANS STÅL.\nMUBLER, AB\n\nPnr 710 60\n\nGrythyttan. Tel 0591-143 50.\nBankgiro 603-4037. Postgiro 34028-1.\nTga Lindqvists\n\nVerksamhet: Tillverkar stålmöbler\nsåsom industri-, restaurang-,\nskol-o trädgårdsmöbler, legoprodukter\nSnickerifabrik: Lindesberg. Tel\n0581-105 53\n\nÅrsomsättning: 10 000 000\nAktiekapital: 300 000\nVerkst dir: Lars B Lindqvist\nFörsäljning stålmöbler: Disp O\nLindqvist\n\nFörsäljning Legoprodukter:\nProduktchef Rune Lindqvist\nInköpschef: Björn Svenson\nProduktionschef: S O Brandel\nEtableringsår: 1895\nOmbildat till aktiebolag 1950.\n\nGRYTHYTTE SKIFFERVERK,\nAB\n\nPnr 710 60\n\nGrythyttan. Tel 0591-143 00.\nBankgiro 603-4045. Postgiro 33470-6.\nTga Skifferverket. Telex 5663\nVerksamhet: Tillverkar\nbyggnadsmaterial, byggnadssten, takplattor,\ntaktäckningsmaterial,\nträdgårdsplattor o trappor av natursten.\nUtför taktäckning samt krossmaterial\nför takpapp- o kemisktekniska\nindustrin\n\nAktiekapital: 350 000\nVerkst dir: Ture Wikström\nEtableringsår: 1917.\n\nEIN\n\nTel 0472-607 50. Bankgiro\n275-4067. Postgiro 275555-1\nVerksamhet: Tillverkar\nstoppmöbler\n\nAntal anställda: 30\nÅrsomsättning: 4 000 000\nAktiekapital: 30 100\nVerkst dir: Pabr Erie Ståhl\nEtableringsår: 1943\nOmbildat till aktiebolag 1947.\n\nEFFLEX, AB\n\nPnr 260 73\n\nÖstra Ljungby, Box 90. Tel 0435-\n\n214 70. Bankgiro 500-813.\nPostgiro 373340-9\n\nVerksamhet: Hyvlade o målade\nlistverk, ektrösklar samt\nbyggnadselement\n\nAntal anställda: 17\nÅrsomsättning: 2000000\nAktiekapital: 5 000\nVerkst dir: Anders Moberg\nPlatschef: Disp K G Björck\nEtableringsår. 1955.\n\nmanali, ab\n\nPnr 11348\n\nStockholm, Hagag 14. Tel\n08-31 25 25, 31 06 14. Bankgiro\n56-8100. Postgiro 3278. Tga Manali\nVerksamhet: Försäljning av\nbiltillbehör o karosseribeslag\nAntal anställda: 8\nÅrsomsättning: 750 000\nAktiekapital: 50000\nStyrelse: Dir Olle Birke (ordf), Edv\nAndersson, Gösta Pettersson\nVerkst dir: Olle Birke\nEtableringsår: 1923.\n\nSTROKIRKS TRYCKERI AB\n\nPnr 54101\n\nSkövde 1, Box 22. Ratt v 3. Tel\n0500-830 20. Bankgiro 210-0634.\nPostgiro 31386-6\n\nVerksamhet: Allsidig produktion i\nboktryck o offset för reklam,\nböcker, telefonkataloger,\npersonaltidningar o blanketter. Reklamateljé\nAntal anställda: 35\nÅrsomsättning: 300 000\nAktiekapital: 165 000\nVerkst dir: ing Lennart Gustafson\nEtableringsår: 1903.\n\nARAFART, AB\n\nPnr 10241\n\nStockholm 5, Grev Tureg 19. Box\n5028. Tel 08-63 56 00. Bankgiro\n16-0777. Postgiro 50980. Telex\n1314, 1315. Tga Arabolagen\nVerksamhet: Rederi, skeppsmäkleri\no befraktning\n\nAktiekapital: 25 000\nVerkst dir: O Berg\nEtableringsår: 1954.\n\nBANAN-KOMPANIET, AB\n\nPnr 100 56\n\nStockholms Frihamn. Tel 08-\n\n67 91 60. Bankgiro 160-1111.\nPostgiro 110-7. Tga Bananer.\nTelex 19112\n\nVerksamhet: Import o distribution\nav bananer, frukter o grönsaker\nsamt vissa specialvaror för\nlivsmedelshandeln\nAntal anställda: 900\nÅrsomsättning: 180 000 000\nAktiekapital: 5 000 000\nVerkst dir: Peter Wieslander\nEtableringsår: 1909.\n\nBANCKSAGENTUR-AB,\nINGEMAR\n\nPnr 451 00\n\nUddevalla, Föreningsg 12. Tel\n0522-166 66, 166 76\n\nVerksamhet: Agenturrörelse med\nyttertrikotage, klänningar, kappor o\ndräkter\n\nÅrsomsättning: 1500 000\nAktiekapital: 5 000\nVerkst dir: Ingemar Banck\nEtableringsår: 1959.\n\nBANCO-BRYGGERIER I\nMALMÖ AB\n\nPnr 212 28\n\nMalmö, Scheeleg 23. Tel\n040-94 54 90. Bankgiro 264-7279.\nPostgiro 245642-4\n\nVerksamhet: Säljer o distribuerar\nbryggeriprodukter\nAntal anstäUda: 65\nÅrsomsättning: 8 600 000\nAktiekapital: 400 000\nVerkst dir: Einar Nilsson\nEtableringsår: 1965.\n\nBANCO-BRYGGERIER I\n5KRUV AB\n\nPnr 36053\n\nSkruv, Box 103. Tel 0478-203 00.\nBankgiro 357-0132. Postgiro\n344150-8\n\nVerksamhet: Tillverkar o säljer\nöl o läskedrycker med\ndistriktskontor i Växjö o Jönköping\nVarunamn: Banco, Dacke\nFörsäljn-chef: Bo Nilsson\nInköpschef: Lennart Ljung\nEtableringsår: 1949.\n\nBAND. 0 SPIRALFABRIKEN,\nAB\n\nPnr 21145\n\nMalmö, Davidshallsg 18. Tel\n040-12 64 50. Bankgiro 641-6622.\nPostgiro 630275-6\n\nVerksamhet: Tillverkar rak- o\ndia-gonalskurna band\nAntal anställda: 9\nÅrsomsättning: 1000 000\nAktiekapital: 72 000\nVerkst dir: John Stewart\nEtableringsår: 1957.\n\nAKMA, MASKIN AB\n\nPnr 381 01\n\nKalmar 1, Box 138. ölandsg 4. Tel\n0480-220 10. Bankgiro 655-7235.\nPostgiro 468220-9. Tga Akma.\nTelex 4813\n\nVerksamhet: Grossistförsäljning\nav maskiner, verktyg o\nmaskinförnödenheter\n\nAvdelningskontor: 55102 Jönköping,\nBox 440. Apotekargränd 4. Tel\n036-1188 60. Telex 70145\n200 22 Malmö, Box 3101. S\nBull-toftav 17. Tel 040-18 07 30\nAktiekapital: 360 000\nStyrelse: Kr Strtimpel (ordf), P L\nCarlson, Stig Segerberg, Evert\nJansson, B Strümpel, L E Persson\nVerkst dir: Evert Jansson\nEtableringsår: 1948\nNamnändring 1953.\n\nAKRON-MASKINER, AB\n\nPnr 530 40\n\nJäipås. Tel 0510-914 00. Bankgiro\n221-9061. Postgiro 144351-4. Tga\nAkronmaskiner\n\nVerksamhet: Propellerfläktar,\ntransportskruvar, spannmålstorkar,\nvarmluftspannor, golvsveperplåt,\nel motorer o hövändare\nAntal anställda: 35\nÅrsomsättning: 6 500 000\nEtableringsår: 1944.\n\nSVENSK FILMPRODUKTION\n\nPnr 300 07\n\nHalmstad 7, Box 7035. Tel\n035-305 75. Bankgiro 53-0360.\nPostgiro 492724-0\n\nVerksamhet: Film för\nindustriinformation o reklam\nChef: Sven Kristensson\nEtableringsår: 1959.\n\nVISKANS KRAFTAKTIEBOLAG\n\nPnr 50108\n\nBorås 1, Box 551. Asbog 8. Tel\n033-12 79 10. Bankgiro 839-2912.\nPostgiro 30137-4\nVerksamhet; Elkraftproduktion o\neldistribution\nAntal anställda: 69\nÅrsomsättning: 13 000 000\nAktiekapital: 3 900 000\nVerkst dir. Sune Dalin\nEtableringsån 1913.\n\nWISKANIA AB.\nFÖRSÄLJ-NINGSBOLAGET\n\nPnr 500 06\n\nBorås 6, Gässlösav 28. Box 66091.\nTel 033-12 77 60. Bankgiro\n531-2111. Postgiro 389014-2. Tga\nWiskania\n\nVerksamhet: Grossistförsäljning av\nskodon\n\nAntal anställda: 12\nÅrsomsättning: 7 000 000\nAktiekapital: 15 000\nVerkst dir: G Rangert\nEtableringsår: 1943.\n\nEKEBRO AB\n\nPnr 701 02\n\nÖrebro 1, Box 37. Brog 2. Tel\n019-140280. Bankgiro 40-1927.\nPostgiro 277220\n\nVerksamhet: Tillverkar betong o\nbetongprodukter. Utför\npålslag-ning o golvläggning\nAvdelningskontor: Västerås\nFabriker: Otebro, Västerås,\nArboga, Hallsberg\nÖveringeniör: Arne Nordin\nSe vidare Byggpaul AB, Västerås.\n\nEKEQUIST &amp; LILJEGREN\n\nPnr 433 00\n\nPartilie, Eckens väg. Box 18. Tel\n031-44 13 38, 4411 97. Bankgiro\n55-0520. Postgiro 244475\nVerksamhet: Uthyr\nbyggnadsmaskiner\n\nAntal anställda: 8\nÅrsomsättning: 900000\nChef: Ing Bertil Liljegren\nEtableringsår: 1953.",
    "structured": {
        "1": {
            "company_name": "GRYTGOLS BRUKS AB",
            "pnr": "610 11",
            "address": "Grytgöl",
            "phone_number": "0122-430 40",
            "bank_details": {
                "postgiro": "6617"
            },
            "activity": "Tråddrageri och häftklammer tillverkning",
            "annual_turnover": 7000000,
            "capital": 825000,
            "key_personnel": [
                {
                    "name": "Bergsing Jan Hagstedt",
                    "position": "Verkst dir"
                },
                {
                    "name": "Ing S Eideland",
                    "position": "Försäljn-chef"
                }
            ],
            "establishment_year": 1893
        },
        "2": {
            "company_name": "GRYTHYTTANS STÅLMÖBLER, AB",
            "pnr": "710 60",
            "address": "Grythyttan",
            "phone_number": "0591-143 50",
            "bank_details": {
                "bankgiro": "603-4037",
                "postgiro": "34028-1"
            },
            "activity": "Tillverkar stålmöbler såsom industri-, restaurang-, skol- och trädgårdsmöbler",
            "employees": null,
            "annual_turnover": 10000000,
            "capital": 300000,
            "key_personnel": [
                {
                    "name": "Lars B Lindqvist",
                    "position": "Verkst dir"
                },
                {
                    "name": "Disp O Lindqvist",
                    "position": "Försäljning stålmöbler"
                }
            ],
            "establishment_year": 1895
        },
        "3": {
            "company_name": "GRYTHYTTE SKIFFERVERK, AB",
            "pnr": "710 60",
            "address": "Grythyttan",
            "phone_number": "0591-143 00",
            "bank_details": {
                "bankgiro": "603-4045",
                "postgiro": "33470-6"
            },
            "activity": "Tillverkar byggnadsmaterial, byggnadssten, takplattor, taktäckningsmaterial, trädgårdsplattor och trappor av natursten",
            "employees": null,
            "annual_turnover": null,
            "capital": 350000,
            "key_personnel": [
                {
                    "name": "Ture Wikström",
                    "position": "Verkst dir"
                }
            ],
            "establishment_year": 1917
        },
        "4": {
            "company_name": "EIN",
            "pnr": null,
            "address": null,
            "phone_number": "0472-607 50",
            "bank_details": {
                "bankgiro": "275-4067",
                "postgiro": "275555-1"
            },
            "activity": "Tillverkar stoppmöbler",
            "employees": 30,
            "annual_turnover": 4000000,
            "capital": 30100,
            "key_personnel": [
                {
                    "name": "Pabr Erie Ståhl",
                    "position": "Verkst dir"
                }
            ],
            "establishment_year": 1943
        },
        "5": {
            "company_name": "EFFLEX, AB",
            "pnr": "260 73",
            "address": "Östra Ljungby, Box 90",
            "phone_number": "0435-214 70",
            "bank_details": {
                "bankgiro": "500-813",
                "postgiro": "373340-9"
            },
            "activity": "Hyvlade och målade listverk, ektrösklar samt byggnadselement",
            "employees": 17,
            "annual_turnover": 2000000,
            "capital": 5000,
            "key_personnel": [
                {
                    "name": "Anders Moberg",
                    "position": "Verkst dir"
                },
                {
                    "name": "Disp K G Björck",
                    "position": "Platschef"
                }
            ],
            "establishment_year": 1955
        },
        "6": {
            "company_name": "manali, ab",
            "pnr": "11348",
            "address": "Stockholm, Hagag 14",
            "phone_number": "08-31 25 25, 31 06 14",
            "bank_details": {
                "bankgiro": "56-8100",
                "postgiro": "3278"
            },
            "activity": "Försäljning av biltillbehör och karosseribeslag",
            "employees": 8,
            "annual_turnover": 750000,
            "capital": 50000,
            "key_personnel": [
                {
                    "name": "Olle Birke",
                    "position": "Styrelse: Dir (ordf)"
                }
            ],
            "establishment_year": 1923
        },
        "7": {
            "company_name": "STROKIRKS TRYCKERI AB",
            "pnr": "54101",
            "address": "Skövde 1, Box 22",
            "phone_number": "0500-830 20",
            "bank_details": {
                "bankgiro": "210-0634",
                "postgiro": "31386-6"
            },
            "activity": "Allsidig produktion i boktryck och offset för reklam, böcker, telefonkataloger, personaltidningar och blanketter. Reklamateljé",
            "employees": 35,
            "annual_turnover": 300000,
            "capital": 165000,
            "key_personnel": [
                {
                    "name": "Ing Lennart Gustafson",
                    "position": "Verkst dir"
                }
            ],
            "establishment_year": 1903
        },
        "8": {
            "company_name": "ARAFART, AB",
            "pnr": "10241",
            "address": "Stockholm 5, Grev Tureg 19, Box 5028",
            "phone_number": "08-63 56 00",
            "bank_details": {
                "bankgiro": "16-0777",
                "postgiro": "50980"
            },
            "activity": "Rederi, skeppsmäkleri och befraktning",
            "employees": null,
            "annual_turnover": null,
            "capital": 25000,
            "key_personnel": [
                {
                    "name": "O Berg",
                    "position": "Verkst dir"
                }
            ],
            "establishment_year": 1954
        },
        "9": {
            "company_name": "BANAN-KOMPANIET, AB",
            "pnr": "100 56",
            "address": "Stockholms Frihamn",
            "phone_number": "08-67 91 60",
            "bank_details": {
                "bankgiro": "160-1111",
                "postgiro": "110-7"
            },
            "activity": "Import och distribution av bananer, frukter och grönsaker samt vissa specialvaror för livsmedelshandeln",
            "employees": 900,
            "annual_turnover": 180000000,
            "capital": 5000000,
            "key_personnel": [
                {
                    "name": "Peter Wieslander",
                    "position": "Verkst dir"
                }
            ],
            "establishment_year": 1909
        },
        "10": {
            "company_name": "BANCKSAGENTUR-AB, INGEMAR",
            "pnr": "451 00",
            "address": "Uddevalla, Föreningsg 12",
            "phone_number": "0522-166 66, 166 76",
            "bank_details": null,
            "activity": "Agenturrörelse med yttertrikotage, klänningar, kappor och dräkter",
            "employees": null,
            "annual_turnover": 1500000,
            "capital": 5000,
            "key_personnel": [
                {
                    "name": "Ingemar Banck",
                    "position": "Verkst dir"
                }
            ],
            "establishment_year": 1959
        },
        "11": {
            "company_name": "BANCO-BRYGGERIER I MALMÖ AB",
            "pnr": "212 28",
            "address": "Malmö, Scheeleg 23",
            "phone_number": "040-94 54 90",
            "bank_details": {
                "bankgiro": "264-7279",
                "postgiro": "245642-4"
            },
            "activity": "Säljer och distribuerar bryggeriprodukter",
            "employees": 65,
            "annual_turnover": 8600000,
            "capital": 400000,
            "key_personnel": [
                {
                    "name": "Einar Nilsson",
                    "position": "Verkst dir"
                }
            ],
            "establishment_year": 1965
        },
        "12": {
            "company_name": "BANCO-BRYGGERIER I SKRUV AB",
            "pnr": "36053",
            "address": "Skruv, Box 103",
            "phone_number": "0478-203 00",
            "bank_details": {
                "bankgiro": "357-0132",
                "postgiro": "344150-8"
            },
            "activity": "Tillverkar och säljer öl och läskedrycker med distriktskontor i Växjö och Jönköping",
            "employees": null,
            "annual_turnover": null,
            "capital": null,
            "key_personnel": [
                {
                    "name": "Bo Nilsson",
                    "position": "Försäljn-chef"
                }
            ],
            "establishment_year": 1949
        },
        "13": {
            "company_name": "BAND. 0 SPIRALFABRIKEN, AB",
            "pnr": "21145",
            "address": "Malmö, Davidshallsg 18",
            "phone_number": "040-12 64 50",
            "bank_details": {
                "bankgiro": "641-6622",
                "postgiro": "630275-6"
            },
            "activity": "Tillverkar rak- och diagonaliskurna band",
            "employees": 9,
            "annual_turnover": 1000000,
            "capital": 72000,
            "key_personnel": [
                {
                    "name": "John Stewart",
                    "position": "Verkst dir"
                }
            ],
            "establishment_year": 1957
        },
        "14": {
            "company_name": "AKMA, MASKIN AB",
            "pnr": "381 01",
            "address": "Kalmar 1, Box 138, ölandsg 4",
            "phone_number": "0480-220 10",
            "bank_details": {
                "bankgiro": "655-7235",
                "postgiro": "468220-9"
            },
            "activity": "Grossistförsäljning av maskiner, verktyg och maskinförnödenheter",
            "employees": null,
            "annual_turnover": null,
            "capital": 360000,
            "key_personnel": [
                {
                    "name": "Evert Jansson",
                    "position": "Verkst dir"
                }
            ],
            "establishment_year": 1948
        },
        "15": {
            "company_name": "AKRON-MASKINER, AB",
            "pnr": "530 40",
            "address": "Jäipås",
            "phone_number": "0510-914 00",
            "bank_details": {
                "bankgiro": "221-9061",
                "postgiro": "144351-4"
            },
            "activity": "Propellerfläktar, transportskruvar, spannmålstorkar, varmluftspannor, golvsveperplåt, el motorer och hövändare",
            "employees": 35,
            "annual_turnover": 6500000,
            "capital": null,
            "key_personnel": null,
            "establishment_year": 1944
        },
        "16": {
            "company_name": "SVENSK FILMPRODUKTION",
            "pnr": "300 07",
            "address": "Halmstad 7, Box 7035",
            "phone_number": "035-305 75",
            "bank_details": {
                "bankgiro": "53-0360",
                "postgiro": "492724-0"
            },
            "activity": "Film för industriinformation och reklam",
            "employees": null,
            "annual_turnover": null,
            "capital": null,
            "key_personnel": [
                {
                    "name": "Sven Kristensson",
                    "position": "Chef"
                }
            ],
            "establishment_year": 1959
        },
        "17": {
            "company_name": "VISKANS KRAFTAKTIEBOLAG",
            "pnr": "50108",
            "address": "Borås 1, Box 551, Asbog 8",
            "phone_number": "033-12 79 10",
            "bank_details": {
                "bankgiro": "839-2912",
                "postgiro": "30137-4"
            },
            "activity": "Elkraftproduktion och eldistribution",
            "employees": 69,
            "annual_turnover": 13000000,
            "capital": 3900000,
            "key_personnel": [
                {
                    "name": "Sune Dalin",
                    "position": "Verkst dir"
                }
            ],
            "establishment_year": 1913
        },
        "18": {
            "company_name": "WISKANIA AB. FÖRSÄLJ-NINGSBOLAGET",
            "pnr": "500 06",
            "address": "Borås 6, Gässlösav 28, Box 66091",
            "phone_number": "033-12 77 60",
            "bank_details": {
                "bankgiro": "531-2111",
                "postgiro": "389014-2"
            },
            "activity": "Grossistförsäljning av skodon",
            "employees": 12,
            "annual_turnover": 7000000,
            "capital": 15000,
            "key_personnel": [
                {
                    "name": "G Rangert",
                    "position": "Verkst dir"
                }
            ],
            "establishment_year": 1943
        },
        "19": {
            "company_name": "EKEBRO AB",
            "pnr": "701 02",
            "address": "Örebro 1, Box 37, Brog 2",
            "phone_number": "019-140280",
            "bank_details": {
                "bankgiro": "40-1927",
                "postgiro": "277220"
            },
            "activity": "Tillverkar betong och betongprodukter. Utför pålslagning och golvläggning",
            "employees": null,
            "annual_turnover": null,
            "capital": null,
            "key_personnel": [
                {
                    "name": "Arne Nordin",
                    "position": "Överingenjör"
                }
            ],
            "establishment_year": null
        },
        "20": {
            "company_name": "EKEQUIST & LILJEGREN",
            "pnr": "433 00",
            "address": "Partilie, Eckens väg, Box 18",
            "phone_number": "031-44 13 38, 4411 97",
            "bank_details": {
                "bankgiro": "55-0520",
                "postgiro": "244475"
            },
            "activity": "Uthyr byggnadsmaskiner",
            "employees": 8,
            "annual_turnover": 900000,
            "capital": null,
            "key_personnel": [
                {
                    "name": "Ing Bertil Liljegren",
                    "position": "Chef"
                }
            ],
            "establishment_year": 1953
        }
    }
}