{
    "original": "RODEN, FASTIGHETS AB\n\nPnr 76100\n\nNorrtälje, Bangårdsg 22. Tel\n0176-12341, 11888. Bankgiro 45-1808.\nPostgiro 648602\nVerksamhet: Exploaterar råmark\ntill fritids tomter. Säljer\nfritidstomter\n\nAntal anställda: 8\n\nÅrsomsättning: 1000 000\n\nAktiekapital: 100000\n\nStyrelse: Dir Karl Axel Garff (ordf),\n\nfru Ingrid Garff\n\nVerkst dir: Karl Axel Garff\n\nEtableringsår: 1963.\n\nFRÖBERG AB, SVEN\n\nPnr 78101\n\nBorlänge 1, Industrig 8. Box 1. Tel\n0243-123 80. Bankgiro 794-5058.\nPostgiro 28699-7\nVerksamhet: Säljer byggvaror i\nparti o minut. Golvbeläggningar\nAntal anställda: 30\nÅrsomsättning: 7 300 000\nAktiekapital: 50 000\nChef: Rolf Sandström\nEtableringsår: 1928.\n\nKJE\n\nÅrsomsättning: 600 000\nAktiekapital: 5 000\nVeikst dir: Kuno Gustafsson\nEtableringsår: 1957.\n\nJAKOBSSON AB, HANS.AGNE\n\nPnr 285 01\n\nMarkaryd 1, Box 56. Tel\n0433-107 10. Bankgiro 27-9552. Postgiro\n381231. Telex 72412. TgaHajab\nVerksamhet: Tillverkar elektr\nbelysningsarmatur, ljusstakar\nAntal anställda: 85\nÅrsomsättning: 6 000 000\nAktiekapital: 385 000\nVerkst din Ark Hans-Agne\nJakobsson\n\nEtableringsår: 1951.\n\nJACOBSON\nELEKTROKON-SULTER AB, INGVAR\n\nPnr 46100\n\nTrollhättan. Torgg 11. Tel\n0520-115 87\n\nVerksamhet Plànering av\nbelys-ningsanläggningar o elektr\ninstallationer\n\nAntal anställda: 4\nAktiekapital: 5 000\nVeikst dir: Ing Ingvar Jacobson\nEtableringsår. 1951.\n\nINDESIT SVENSKA AB\n\nPnr 422 02\n\nHisings Backa 2, Box 2015.\nEx-portg. Tel 031-52 02 00. Bankgiro\n501-0376. Postgiro 242288-9. Tga\nIndesit. Telex 21182 INDESIT S\nVeiksamhet: Säljer\nhushållsmaskiner engros. Representant för\nIndesit SpA, Torino, Italien\nFilial: 163 04 Spånga 4, Box 4071.\nLättingebacken 14-18. Tel\n08-362925\n\nVaiunamn: Indesit\n\nAntal anställda: 11\n\nÅrsomsättning: 5 000 000\n\nAktiekapital: 2 000 000\n\nStyrelse: Adv Bengt LUttners (ordf),\n\ndir Lars Carstens, herr Emilio Mo-\n\nrino\n\nVeikst dir Lars Carstens\nKamrer. Bo Wilhelmsson\nEtableringsår. 1966.\n\nBJERKING INGENJURSBYRÅ\nAB\n\nPnr 752 22\n\nUppsala, Götg 3. Tel 018-14 94 80.\nPostgiro 271044-0\nVerksamhet: Konsulterande\nverksamhet inom hus-,\nindustribyggnader o geoteknik\nAntal anställda: 45\nAktiekapital: 25 000\nVerkst dir: Olof B odén\nEtableringsår: 1943\nOmbildat till aktiebolag 1957.\n\nBJERKÄS AB\n\nPnr 417 04\n\nGöteborg, Kvilleg 9 B. Tel\n031-5124 38, 5124 39. Bankgiro\n513-7310. Postgiro 40407-9\nVerksamhet: Butiksinredningar o\nmek verkstad\n\nAntal anställda: 30\nÅrsomsättning: 2 000000\nAktiekapital: 60 000\nVerkst dir: Olle Gertorp\nEtableringsår: 1927.\n\nBJERNEDS\nREVISIONSBYRÅ AB\n\nPnr 40010\n\nGöteborg 3, Karl Gustavsg 19.\nBox 3024. Tel 031-17 53 30.\nBankgiro 50-6103. Postgiro 421002\nVerksamhet: Revision,\nredovisningsteknisk rådgivning\nFilial: Trollhättan. Tel 0520-16170\nAntal anställda: 14\nÅrsomsättning: 700 000\nAktiekapital: 5 000\nVerkst dir: Bengt Bjerned\nEtableringsår: 1947.\n\nhenningsson mek verk.\nSTAD, AB ANDERS\n\nPnr 734 01\n\nHallstahammar 1, Vattug 9. Box\n105. Tel 0220-10048, 119 20.\nPostgiro 142980-2\n\nVerksamhet: Tillverkar\nbyggnads-smide, mobilkranar o traktorer\nAntal anställda: 8\nAktiekapital: 10 000\nVerkst dir: Anders Henningsson\nKamrer: Gurli Henningsson\nEtableringsår: 1920.\n\nÅKE\n\nÅKERLUNDS\nBOMULLSSPINNERI AB\n\nPnr 501 02\n\nBorås 1, Druveforsv 8. Box 63. Tel\n033-13 71 30. Bankgiro 83-9294.\nPostgiro 98110. Telex 36006\nVerksamhet: Försäljning från lager\nav garner för texülindustria\nGarn-färgning å koniska korsrullar\nAntal anställda: 30\nÅrsomsättning: 16 000 000\nAktiekapital: 1400 000\nVerkst din Civiling Carl-Otto\nEiserman\n\nFörsäljn-chef: Kamrer Helmer\n\nPettersson\n\nEtableringsår: 1898.\n\nSPÅNGA SNICKERIFABRIK, AB\n\nPnr 643 00\n\nVingåker. Tel 0151-106 16,10462.\nBankgiro 830-9122. Postgiro\n93316-8\n\nVerksamhet: Tillverkar trappor,\nspecialinredningar mm, emballage\no lådor. Säljer träfiberplattor,\nplywood (svensk o finsk), trävaror\nm m\n\nAntal anstäUda: 40\nÅrsomsättning: 3 000 000\nAktiekapital: 50 000\nChef: Fabr Arne Emilson\nEtableringsår: 1942.\n\nSVANBERG AB, CARL\n\nPnr 350 03\n\nVäxjö 3, Box 3002. Blästerg 4. Tel\n0470-12373. Bankgiro 668-1381.\nPostgiro 80576-2\n\nVerksamhet: Bokbinderi o tryckeri\nTryckeri: 35104 Växjö 1, Box 91.\nNyg 12. Tel 0470-165 03\nAntal anställda: 50\nÅrsomsättning: 3 000 000\nAktiekapital: 50 000\nStyrelse: Dir John Lorentzi (ordf),\ndir Stig Franzén, dir Olle Bohlin\nVerkst dir: stig Franzén\nDisp: Bertil Stenkvist\nFaktor: John Pettersson\nIngår i Gummessons Grafiska\nGrupp AB.\n\nSVANBERG,\nINGENIORS-FIRMA DAVID\n\nPnr 114 25\n\nStockholm, Rådmansg 14. Tel 08-\n\n2172 34, 21 72 56. Postgiro 51422.\nTga Svankemi\n\nVerksamhet: Säljer maskiner o\nutrustning för farmacevtiska, kemisk\ntekniska, kosmetiska industrier\nsamt diverse råvaror o\nfinkemikalier\n\nEtableringsår: 1930.",
    "structured": {
        "1": {
            "company_name": "RODEN, FASTIGHETS AB",
            "pnr": "76100",
            "address": "Norrtälje, Bangårdsg 22",
            "phone_number": "0176-12341, 11888",
            "bank_details": {
                "bankgiro": "45-1808",
                "postgiro": "648602"
            },
            "activity": "Exploaterar råmark till fritids tomter. Säljer fritidstomter",
            "employees": 8,
            "annual_turnover": 1000000,
            "capital": 100000,
            "key_personnel": [
                {
                    "name": "Karl Axel Garff",
                    "position": "Dir (ordf)"
                },
                {
                    "name": "Ingrid Garff",
                    "position": "fru"
                },
                {
                    "name": "Karl Axel Garff",
                    "position": "Verkst dir"
                }
            ],
            "establishment_year": 1963
        },
        "2": {
            "company_name": "FRÖBERG AB, SVEN",
            "pnr": "78101",
            "address": "Borlänge 1, Industrig 8, Box 1",
            "phone_number": "0243-123 80",
            "bank_details": {
                "bankgiro": "794-5058",
                "postgiro": "28699-7"
            },
            "activity": "Säljer byggvaror i parti o minut. Golvbeläggningar",
            "employees": 30,
            "annual_turnover": 7300000,
            "capital": 50000,
            "key_personnel": [
                {
                    "name": "Rolf Sandström",
                    "position": "Chef"
                }
            ],
            "establishment_year": 1928
        },
        "3": {
            "company_name": "KJE",
            "activity": "N/A",
            "annual_turnover": 600000,
            "capital": 5000,
            "key_personnel": [
                {
                    "name": "Kuno Gustafsson",
                    "position": "Veikst dir"
                }
            ],
            "establishment_year": 1957
        },
        "4": {
            "company_name": "JAKOBSSON AB, HANS.AGNE",
            "pnr": "285 01",
            "address": "Markaryd 1, Box 56",
            "phone_number": "0433-107 10",
            "bank_details": {
                "bankgiro": "27-9552",
                "postgiro": "381231"
            },
            "activity": "Tillverkar elektr belysningsarmatur, ljusstakar",
            "employees": 85,
            "annual_turnover": 6000000,
            "capital": 385000,
            "key_personnel": [
                {
                    "name": "Hans-Agne Jakobsson",
                    "position": "Verkst dir"
                }
            ],
            "establishment_year": 1951
        },
        "5": {
            "company_name": "JACOBSON ELEKTROKON-SULTER AB, INGVAR",
            "pnr": "46100",
            "address": "Trollhättan, Torgg 11",
            "phone_number": "0520-115 87",
            "activity": "Plànering av belys-ningsanläggningar o elektr installationer",
            "employees": 4,
            "capital": 5000,
            "key_personnel": [
                {
                    "name": "Ing Ingvar Jacobson",
                    "position": "Veikst dir"
                }
            ],
            "establishment_year": 1951
        },
        "6": {
            "company_name": "INDESIT SVENSKA AB",
            "pnr": "422 02",
            "address": "Hisings Backa 2, Box 2015",
            "phone_number": "031-52 02 00",
            "bank_details": {
                "bankgiro": "501-0376",
                "postgiro": "242288-9"
            },
            "activity": "Säljer hushållsmaskiner engros. Representant för Indesit SpA, Torino, Italien",
            "employees": 11,
            "annual_turnover": 5000000,
            "capital": 2000000,
            "key_personnel": [
                {
                    "name": "Lars Carstens",
                    "position": "Veikst dir"
                },
                {
                    "name": "Bo Wilhelmsson",
                    "position": "Kamrer"
                }
            ],
            "establishment_year": 1966
        },
        "7": {
            "company_name": "BJERKING INGENJURSBYRÅ AB",
            "pnr": "752 22",
            "address": "Uppsala, Götg 3",
            "phone_number": "018-14 94 80",
            "postgiro": "271044-0",
            "activity": "Konsulterande verksamhet inom hus-, industribyggnader o geoteknik",
            "employees": 45,
            "capital": 25000,
            "key_personnel": [
                {
                    "name": "Olof B odén",
                    "position": "Verkst dir"
                }
            ],
            "establishment_year": 1943
        },
        "8": {
            "company_name": "BJERKÄS AB",
            "pnr": "417 04",
            "address": "Göteborg, Kvilleg 9 B",
            "phone_number": "031-5124 38, 5124 39",
            "bank_details": {
                "bankgiro": "513-7310",
                "postgiro": "40407-9"
            },
            "activity": "Butiksinredningar o mek verkstad",
            "employees": 30,
            "annual_turnover": 2000000,
            "capital": 60000,
            "key_personnel": [
                {
                    "name": "Olle Gertorp",
                    "position": "Verkst dir"
                }
            ],
            "establishment_year": 1927
        },
        "9": {
            "company_name": "BJERNEDS REVISIONSBYRÅ AB",
            "pnr": "40010",
            "address": "Göteborg 3, Karl Gustavsg 19, Box 3024",
            "phone_number": "031-17 53 30",
            "bank_details": {
                "bankgiro": "50-6103",
                "postgiro": "421002"
            },
            "activity": "Revision, redovisningsteknisk rådgivning",
            "employees": 14,
            "annual_turnover": 700000,
            "capital": 5000,
            "key_personnel": [
                {
                    "name": "Bengt Bjerned",
                    "position": "Verkst dir"
                }
            ],
            "establishment_year": 1947
        },
        "10": {
            "company_name": "HENNINGSSON MEK VERK. STAD, AB ANDERS",
            "pnr": "734 01",
            "address": "Hallstahammar 1, Vattug 9, Box 105",
            "phone_number": "0220-10048, 119 20",
            "postgiro": "142980-2",
            "activity": "Tillverkar byggnads-smide, mobilkranar o traktorer",
            "employees": 8,
            "capital": 10000,
            "key_personnel": [
                {
                    "name": "Anders Henningsson",
                    "position": "Verkst dir"
                },
                {
                    "name": "Gurli Henningsson",
                    "position": "Kamrer"
                }
            ],
            "establishment_year": 1920
        },
        "11": {
            "company_name": "ÅKE ÅKERLUNDS BOMULLSSPINNERI AB",
            "pnr": "501 02",
            "address": "Borås 1, Druveforsv 8, Box 63",
            "phone_number": "033-13 71 30",
            "bank_details": {
                "bankgiro": "83-9294"
            },
            "activity": "Försäljning från lager av garner för texülindustria Garn-färgning å koniska korsrullar",
            "employees": 30,
            "annual_turnover": 16000000,
            "capital": 1400000,
            "key_personnel": [
                {
                    "name": "Civiling Carl-Otto Eiserman",
                    "position": "Verkst dir"
                },
                {
                    "name": "Kamrer Helmer Pettersson",
                    "position": "Försäljn-chef"
                }
            ],
            "establishment_year": 1898
        },
        "12": {
            "company_name": "SPÅNGA SNICKERIFABRIK, AB",
            "pnr": "643 00",
            "address": "Vingåker",
            "phone_number": "0151-106 16,10462",
            "bank_details": {
                "bankgiro": "830-9122",
                "postgiro": "93316-8"
            },
            "activity": "Tillverkar trappor, specialinredningar mm, emballage o lådor. Säljer träfiberplattor, plywood (svensk o finsk), trävaror m m",
            "employees": 40,
            "annual_turnover": 3000000,
            "capital": 50000,
            "key_personnel": [
                {
                    "name": "Arne Emilson",
                    "position": "Chef"
                }
            ],
            "establishment_year": 1942
        },
        "13": {
            "company_name": "SVANBERG AB, CARL",
            "pnr": "350 03",
            "address": "Växjö 3, Box 3002, Blästerg 4",
            "phone_number": "0470-12373",
            "bank_details": {
                "bankgiro": "668-1381",
                "postgiro": "80576-2"
            },
            "activity": "Bokbinderi o tryckeri",
            "employees": 50,
            "annual_turnover": 3000000,
            "capital": 50000,
            "key_personnel": [
                {
                    "name": "John Lorentzi",
                    "position": "Dir (ordf)"
                },
                {
                    "name": "Stig Franzén",
                    "position": "dir"
                },
                {
                    "name": "Olle Bohlin",
                    "position": "dir"
                },
                {
                    "name": "Stig Franzén",
                    "position": "Verkst dir"
                },
                {
                    "name": "Bertil Stenkvist",
                    "position": "Disp"
                },
                {
                    "name": "John Pettersson",
                    "position": "Faktor"
                }
            ]
        },
        "14": {
            "company_name": "SVANBERG, INGENIORS-FIRMA DAVID",
            "pnr": "114 25",
            "address": "Stockholm, Rådmansg 14",
            "phone_number": "08-2172 34, 21 72 56",
            "postgiro": "51422",
            "activity": "Säljer maskiner o utrustning för farmacevtiska, kemisk tekniska, kosmetiska industrier samt diverse råvaror o finkemikalier",
            "establishment_year": 1930
        }
    }
}