{
    "original": "NORDENGREN PATENTER AB\n\nPnr 26139\n\nLandskrona, Strandv 49. Tel\n0418-135 10. Tga Nordpatent\nVerksamhet: Säljer kontinuerliga\nvakuumfilter för kemisk industri\nAktiekapital: 10 000\nVerkst dir: Civiling Rolf\nNordengren\n\nEtableringsår: 1956.\n\nBEA LIVSMEDEL AB\n\nPnr 116 69\n\nStockholm, Tideliusg 36. Tel\n08-84 03 80. Bankgiro 174-4797.\nPostgiro 252261\n\nVerksamhet: Försäljning av\nlivsmedel\n\nAntal anställda: 275\nÅrsomsättning: 68 000 000\nAktiekapital: 200000\nVerkst dir: Brea- Andersson\nEtableringsår: 1943.\n\nFORTIA, AB\n\nPnr 41105\n\nGöteborg. Götg 16. Tel 031-17 86 80.\nBankgiro 50-1611. Postgiro 568805.\nTga Fortiagroup. Telex 2255\nVerksamhet: Moderbolag för bl a\nPharmacia, Consiva AB, Meda,\nMediplast, Famaco\nÅrsomsättning: 470 000 000\n(koncernen)\n\nAktiekapital: 15 000 000\nStyrelse: Bankdir S Lindblad (ordf),\nciviling E Göth, civiling C R\nBlomstedt, dir B Skånsberg, prof BE\nIngelmark, grossh A Lundberg,\ngrossh E Malmsten, civiling G\nVirding (suppl), adv L F Rosengren\n(suppl), civilekonom L V Fröberg\n(suppl)\n\nVerkst dir: Arne Lundberg\nV verkst dir: E Malmsten\nEtableringsår: 1921.\n\nTRÄ FORÄDLINGS AB\n\nPnr 360 73\n\nLenhovda, Box 46. Tel\n0474-220 23. Bankgiro 66-9548.\nPostgiro 117909. Tga TraeSaev\nVerksamhet: Tillverkar\nträemballage, huvudsakligen bryggeri- o\nmejeribackar samt charkuteri- o\nägglådor\n\nAntal anställda: 36\nÅrsomsättning: 2 300 000\nAktiekapital: 75 000\nVerkst dir: Sture Magnusson\nEtableringsår: 1957.\n\nNOR\n\nVerksamhet: Tillverkar o säljer\nfaner av in- o utländska träslag\nVerkst dir: Civiling Johan Bohman\nEtableringsår: 1943.\n\nBODAFORS-VERKEN AB\n\nPnr 570 20\n\nBodafors, Industrig 7-9. Box 16.\nTel 0380-304 20. Bankgiro\n144-0031. Postgiro 445027-6\nVerksamhet: Stålrörstillverkning av\ntrappstegar, skarvstegar, piskställ\nAntal anställda: 45\nÅrsomsättning: 3 500 000\nAktiekapital: 225 000\nVerkst dir: Fabr Bengt Nilsson\nEtableringsår: 1954.\n\nSYDLÄDER AB\n\nPnr 262 01\n\nÄngelholm 1, Box 71. Tel\n0431-13620. Bankgiro 415-5222.\nPostgiro 33587-7. Tga Sydläder\nVerksamhet: Tillverkar o säljer\nsportbollar av läder, tekniska\nläderartiklar såsom manschetter,\npackningar o bälgar, flata o runda\ndrivremmar, syremmar o lädersnören\nVarunamn: Star, Starex, Top Star,\nStjärn m fi\nAntal anställda: 50\nÅrsomsättning: 5 000 000\nAktiekapital: 200 000\nVeikst dir. Bengt Asell\nEtableringsår. 1914.\n\nSCHALLING OPTIK AB\n\nPnr 411 25\n\nGöteborg, Viktoriag 12. Tel\n031-13 72 74, 13 44 73. Bankgiro\n337-5052. Postgiro 44606-2.\nTga Schallingoptik\nVerksamhet: Optiska artiklar en\ngros\n\nAntal anstäUda: 10\nÅrsomsättning: 900 000\nAktiekapital: 50 000\nStyrelse: Dir Erik Källqvist (ordf),\nfru Ella Källqvist\nVeikst dir: Erik Källqvist\nEtableringsår: 1960.\n\nSCHARFENBERG &amp; CO AB,\nHUGO\n\nPnr 433 00\n\nPartille, Transformatorv. Box 6.\nTel 031-44 07 80. Bankgiro 26-8104.\nPætglro 40560. Tga Scharfenberg\n\nVerksamhet: Tapisserivaror, garn\no väv i parti\n\nAvdelningskontor Stockholm C,\nKammak arg 6 B. Tel 08-21 30 76\nAktiekapital: 300 000\nVeikst dir Bertil Ekwall\nEtableringsår: 1892.\n\nLABASSCO, AB\n\nPnr 402 24\n\nGöteborg 5, Box 5205. Almedalsv\n1 D. Tel 031-4046 95, 4047 70.\nBankgiro 799-9188. Postgiro\n720054-6. Tga Labassco\nVerksamhet: Säljer\nlaboratorieut-rustning, förbrukningsartiklar,\napparater, instrument\nAntal anställda: 11\nÅrsomsättning: 3 000 000\nAktiekapital: 100 000\nVerkst din Elon Segerbo\nFörsäljn-chef: Thomas Ahlstedt\nEtableringsår: 1967.\n\nLABORA AB, INSTRUMENT.\nFIRMAN\n\nPnr 114 20\n\nStockholm, Birger Jarlsg 110. Tel\n08-3157 75, 319085. Postgiro\n252708. Tga Laborglas\n\nVerksamhet: Säljer laboratorieglas,\nlaboratorieinstrument o apparater\ntill laboratorier inom högskolor,\nindustrier, sjukhus m fi\nAntal anställda: 12\nÅrsomsättning: 4 000 000\nÄgare o chef: Dir Gösta Evald\nRydström\n\nEtableringsår: 1946\nOmbildat till aktiebolag 1968.\n\nLACKERINGSBOLAGET AB\n\nPnr 724 61\n\nVästerås, Västermalmsg 2 A. Tel\n021-13 0410, 13 0414, 12 2121.\nBankgiro 82-8288. Postgiro 417813\nVerksamhet: Tillverkning av\nprefabricerad byggnadslist\nAntal anställda: 50\nÅrsomsättning: 2 000 000\nAktiekapital: 50 000\nVerkst dir: Arne Söderlund\nEtableringsår: 1958.\n\nSVE\n\nNyhamns kemiska fabrik,\nVivsta-varvs sulfatfabrik, pappersbruk o\nsågverk\n\nEtableringsår: 1929\n\nDotterbolag: Bålforsens\nKraftaktiebolag (Båkab), Sunds AB, AB\nCellulosatransport, SCA\nEmballage AB.\n\nSVENSKA CHARKUTERI.\nMASKIN-FABRIKEN\n\nPnr 172 35\n\nSundbyberg, Järnvägsg 3. Tel\n08-282635. Bankgiro 743-5092.\nPostgiro 81081-2\n\nVerksamhet: Tillverkar\ncharkuteri-maskiner\n\nAntal anställda: 5\nÅrsomsättning: 200 000\nÄgare o chefer: Fabr Kurt\nPeterson, fabr Harry Peterson\nEtableringsår: 1908.\n\nSVENSKA CHOKLAD.\nFABRIKS AB\n\nPnr 590 60\n\nLjungsbro, Fack. Tel 013-655 00.\nBankgiro 120-2480. Postgiro\n6589-6. Tga Cloetta. Telex 64945\nVerksamhet: Tillverkar o säljer\nchoklad, kakaoprodukter, konfekt,\nmarmelad, kex, mandelbiskvier etc\nKontor med lager: Stockholm,\nOdeng 52. Tel 08-34 02 40. Lager\nIndustrig 4. Tel 08-53 33 90\nGöteborg, Stora Badhusg 16.\nTel 031-17 42 55\nMalmö, Murmansg 130. Tel\n040-93 51 60\n\nVarunamn: Cloetta\nAntal anställda: 651\nAktiekapital: 1200000\nVerkst din Rolf Nordéus\nV verkst dir: Marknadsdir Lennart\nGranlund\n\nInköpschef: Harry Carlzén\n\nEtableringsår 1892\n\nFirman Cloetta etablerad 1873.\n\nSVENSKA CITIZEN AB\n\nPnr 114 55\n\nStockholm, Grev Magnig 6. Tel\n08-67 92 20. Bankgiro 561-4409.\nPostgiro 402535-9\n\nVerksamhet: Ur o urdelar.\nGeneralagent i japanska ur\nDotterföretag: Norsk Citizen A/S,\nBrockmanns g 9, Oslo 4, Norge\nVarunamn: Citizen\nAntal anställda: 12\nÅrsomsättning: 4 000 000\nAktiekapital: 60 000\nStyrelse: Dir Rudolf Kalderén\n(ordf), dir Göran Kalderén\nVeikst dir: Göran Kalderén\nRepresentanter: Lennart\nWarne-berg, Leif Stolt. Ulf Dahl\nEtableringsår 1966\nRepresentant för Citizen Trading\nCo., Ltd, Tokyo, Japan.\n\nSVENSKA AB CLEANOSOL\n\nPnr 29101\n\nKristianstad 1, Box 160. Industrig\n33. Tel 044-115410. Bankgiro\n657-9361. Postgiro 335864-5. Tga\nClea-nosol\n\nVerksamhet: Fabrikation o\nutläggning av Cleanosol\nplastic-trafik-linjemassa o trafiklinjefärg för\ngator o vägar m m\n\nVarunamn: Cleanosol\nAntal anställda: 51\nÅrsomsättning: 6 000 000\nAktiekapital: 200 000\nVerkst dir: Bo Magnusson\nEtableringsår: 1948.",
    "structured": {
        "1": {
            "company_name": "NORDENGREN PATENTER AB",
            "address": "Landskrona, Strandv 49",
            "phone_number": "0418-135 10",
            "activity": "Säljer kontinuerliga vakuumfilter för kemisk industri",
            "capital": 10000,
            "establishment_year": 1956
        },
        "2": {
            "company_name": "BEA LIVSMEDEL AB",
            "address": "Stockholm, Tideliusg 36",
            "phone_number": "08-84 03 80",
            "bank_details": {
                "bankgiro": "174-4797",
                "postgiro": "252261"
            },
            "activity": "Försäljning av livsmedel",
            "employees": 275,
            "annual_turnover": 68000000,
            "capital": 200000,
            "establishment_year": 1943
        },
        "3": {
            "company_name": "FORTIA, AB",
            "address": "Göteborg, Götg 16",
            "phone_number": "031-17 86 80",
            "bank_details": {
                "bankgiro": "50-1611",
                "postgiro": "568805"
            },
            "activity": "Moderbolag för bl a Pharmacia, Consiva AB, Meda, Mediplast, Famaco",
            "annual_turnover": 470000000,
            "capital": 15000000,
            "key_personnel": [
                {
                    "name": "Bankdir S Lindblad",
                    "position": "ordf"
                },
                {
                    "name": "civiling E Göth",
                    "position": ""
                },
                {
                    "name": "civiling C R Blomstedt",
                    "position": ""
                },
                {
                    "name": "dir B Skånsberg",
                    "position": ""
                },
                {
                    "name": "prof BE Ingelmark",
                    "position": ""
                }
            ],
            "establishment_year": 1921
        },
        "4": {
            "company_name": "TRÄ FORÄDLINGS AB",
            "address": "Lenhovda, Box 46",
            "phone_number": "0474-220 23",
            "bank_details": {
                "bankgiro": "66-9548",
                "postgiro": "117909"
            },
            "activity": "Tillverkar träemballage, huvudsakligen bryggeri- o mejeribackar samt charkuteri- o ägglådor",
            "employees": 36,
            "annual_turnover": 2300000,
            "capital": 75000,
            "establishment_year": 1957
        },
        "5": {
            "company_name": "NOR",
            "activity": "Tillverkar o säljer faner av in- o utländska träslag",
            "establishment_year": 1943
        },
        "6": {
            "company_name": "BODAFORS-VERKEN AB",
            "address": "Bodafors, Industrig 7-9, Box 16",
            "phone_number": "0380-304 20",
            "bank_details": {
                "bankgiro": "144-0031",
                "postgiro": "445027-6"
            },
            "activity": "Stålrörstillverkning av trappstegar, skarvstegar, piskställ",
            "employees": 45,
            "annual_turnover": 3500000,
            "capital": 225000,
            "establishment_year": 1954
        },
        "7": {
            "company_name": "SYDLÄDER AB",
            "address": "Ängelholm 1, Box 71",
            "phone_number": "0431-13620",
            "bank_details": {
                "bankgiro": "415-5222",
                "postgiro": "33587-7"
            },
            "activity": "Tillverkar o säljer sportbollar av läder, tekniska läderartiklar såsom manschetter, packningar o bälgar, flata o runda drivremmar, syremmar o lädersnören",
            "employees": 50,
            "annual_turnover": 5000000,
            "capital": 200000,
            "establishment_year": 1914
        },
        "8": {
            "company_name": "SCHALLING OPTIK AB",
            "address": "Göteborg, Viktoriag 12",
            "phone_number": "031-13 72 74, 13 44 73",
            "bank_details": {
                "bankgiro": "337-5052",
                "postgiro": "44606-2"
            },
            "activity": "Optiska artiklar en gros",
            "employees": 10,
            "annual_turnover": 900000,
            "capital": 50000,
            "key_personnel": [
                {
                    "name": "Dir Erik Källqvist",
                    "position": "ordf"
                },
                {
                    "name": "fru Ella Källqvist",
                    "position": ""
                }
            ],
            "establishment_year": 1960
        },
        "9": {
            "company_name": "SCHARFENBERG & CO AB, HUGO",
            "address": "Partille, Transformatorv. Box 6",
            "phone_number": "031-44 07 80",
            "bank_details": {
                "bankgiro": "26-8104",
                "postgiro": "40560"
            },
            "activity": "Tapisserivaror, garn o väv i parti",
            "capital": 300000,
            "key_personnel": [
                {
                    "name": "Bertil Ekwall",
                    "position": ""
                }
            ],
            "establishment_year": 1892
        },
        "10": {
            "company_name": "LABASSCO, AB",
            "address": "Göteborg 5, Box 5205, Almedalsv 1 D",
            "phone_number": "031-4046 95, 4047 70",
            "bank_details": {
                "bankgiro": "799-9188",
                "postgiro": "720054-6"
            },
            "activity": "Säljer laboratorieut-rustning, förbrukningsartiklar, apparater, instrument",
            "employees": 11,
            "annual_turnover": 3000000,
            "capital": 100000,
            "key_personnel": [
                {
                    "name": "Elon Segerbo",
                    "position": "Verkst dir"
                },
                {
                    "name": "Thomas Ahlstedt",
                    "position": "Försäljn-chef"
                }
            ],
            "establishment_year": 1967
        },
        "11": {
            "company_name": "LABORA AB, INSTRUMENT. FIRMAN",
            "address": "Stockholm, Birger Jarlsg 110",
            "phone_number": "08-3157 75, 319085",
            "bank_details": {
                "postgiro": "252708"
            },
            "activity": "Säljer laboratorieglas, laboratorieinstrument o apparater till laboratorier inom högskolor, industrier, sjukhus m fi",
            "employees": 12,
            "annual_turnover": 4000000,
            "key_personnel": [
                {
                    "name": "Gösta Evald Rydström",
                    "position": "Ägare o chef"
                }
            ],
            "establishment_year": 1946
        },
        "12": {
            "company_name": "LACKERINGSBOLAGET AB",
            "address": "Västerås, Västermalmsg 2 A",
            "phone_number": "021-13 0410, 13 0414, 12 2121",
            "bank_details": {
                "bankgiro": "82-8288",
                "postgiro": "417813"
            },
            "activity": "Tillverkning av prefabricerad byggnadslist",
            "employees": 50,
            "annual_turnover": 2000000,
            "capital": 50000,
            "key_personnel": [
                {
                    "name": "Arne Söderlund",
                    "position": "Verkst dir"
                }
            ],
            "establishment_year": 1958
        },
        "13": {
            "company_name": "SVE",
            "activity": "Nyhamns kemiska fabrik, Vivsta-varvs sulfatfabrik, pappersbruk o sågverk",
            "establishment_year": 1929
        },
        "14": {
            "company_name": "SVENSKA CHARKUTERI. MASKIN-FABRIKEN",
            "address": "Sundbyberg, Järnvägsg 3",
            "phone_number": "08-282635",
            "bank_details": {
                "bankgiro": "743-5092",
                "postgiro": "81081-2"
            },
            "activity": "Tillverkar charkuteri-maskiner",
            "employees": 5,
            "annual_turnover": 200000,
            "key_personnel": [
                {
                    "name": "Fabr Kurt Peterson",
                    "position": "Ägare o chefer"
                }
            ],
            "establishment_year": 1908
        },
        "15": {
            "company_name": "SVENSKA CHOKLAD. FABRIKS AB",
            "address": "Ljungsbro, Fack",
            "phone_number": "013-655 00",
            "bank_details": {
                "bankgiro": "120-2480",
                "postgiro": "6589-6"
            },
            "activity": "Tillverkar o säljer choklad, kakaoprodukter, konfekt, marmelad, kex, mandelbiskvier etc",
            "employees": 651,
            "capital": 1200000,
            "key_personnel": [
                {
                    "name": "Rolf Nordéus",
                    "position": "V verkst dir"
                },
                {
                    "name": "Marknadsdir Lennart Granlund",
                    "position": ""
                }
            ],
            "establishment_year": 1892
        },
        "16": {
            "company_name": "SVENSKA CITIZEN AB",
            "address": "Stockholm, Grev Magnig 6",
            "phone_number": "08-67 92 20",
            "bank_details": {
                "bankgiro": "561-4409",
                "postgiro": "402535-9"
            },
            "activity": "Ur o urdelar. Generalagent i japanska ur",
            "employees": 12,
            "annual_turnover": 4000000,
            "capital": 60000,
            "key_personnel": [
                {
                    "name": "Rudolf Kalderén",
                    "position": "ordf"
                },
                {
                    "name": "Göran Kalderén",
                    "position": "Veikst dir"
                }
            ],
            "establishment_year": 1966
        },
        "17": {
            "company_name": "SVENSKA AB CLEANOSOL",
            "address": "Kristianstad 1, Box 160, Industrig 33",
            "phone_number": "044-115410",
            "bank_details": {
                "bankgiro": "657-9361",
                "postgiro": "335864-5"
            },
            "activity": "Fabrikation o utläggning av Cleanosol plastic-trafik-linjemassa o trafiklinjefärg för gator o vägar m m",
            "employees": 51,
            "annual_turnover": 6000000,
            "capital": 200000,
            "key_personnel": [
                {
                    "name": "Bo Magnusson",
                    "position": "Verkst dir"
                }
            ],
            "establishment_year": 1948
        }
    }
}