{
    "original": "HACKEFORS PORSLIN AB\n\nPnr 585 90\n\nLinköping, Hackefors. Tel\n013-10 20 90. Bankgiro 120-2738.\nPostgiro 7688-5. Tga Hackeforsbruk\nVerksamhet: Porslinsindustri,\nhus-hålls- o prydnadsporslin\nAntal anställda: 50\nÅrsomsättning: 2 000 000\nAktiekapital: 150 000\nStyrelse: G Ivar Franson (ordf),\nAke Elmberg\nVerkst dir: Ake Elmberg\nEtableringsår: 1929.\n\nSVENSKA TEMPUS, AB\n\nPnr 12611 Sthlm 32\nHägersten, Jakobsdalsv 12. Box\n32015, Sthlm 32. Tel 08-190290.\nPnr 12611\n\nStockholm 32, Box 32015.\nJakobsdalsv 12, Hägersten. Tel\n08-19 02 90. Bankgiro 569-5259.\nPostgiro 50928-1’. Tga Tempus\nVerksamhet: Tillverkar o säljer\nhandbrandsläckare, slangrullar,\npulver- o lättskumsaggregat,\nkolsyreanläggningar, oljelänsor samt\nbrandalarm\n\nAvdelningskonton 413 03 Göteborg,\nAndréeg 13. Tel 031-12 40 70\n232 00 Ar löv, Arlövs Industriby,\nHus nr 3. Tel 040-43 43 50\n602 23 Norrköping, Fabriksg 7.\nTel 011-10 25 50\n852 43 Sundsvall, Ostermov 41.\nTel 060-12 43 90\n\nVarunamn: Bore, Hydrox, Röde Orm,\nTempus\n\nAntal anställda: 90\nÅrsomsättning: 15 000 000\nAktiekapital: 500 000\nVerkst dir: Alf Ahlqvist\nEtableringsår 1922.\n\nTIVEDSLAMELL, AB\n\nPnr 543 01\n\nTibro 1, Järnvägsg. Box 21. Tel\n0504-123 00. Bankgiro 221-3627.\nPostgiro 476977-4\nVerksamhet: Tillverkar o säljer\nlamellträ\n\nVarunamn: Tivedslamell\nAntal anställda: 49\nÅrsomsättning: 7 200 000\nAktiekapital: 240 000\nVeikst dir. Sune Hallström\nEtableringsår: 1954.\n\nMEKANISKA FJÄDRAR AB\n\nPnr 380 10\n\nTorsås, Box 115. Tel 0486-105 80.\nBankgiro 982-8922. Postgiro\n666580-6\n\nVerksamhet: Tillverkar o säljer allt\ni fjädrar såsom spiralfjädrar,\ntryck-o dragfjädrar, platt- o vridfjädrar,\nfasonfjädrar o tråddetaljer i runt o\nplatt material samt\ngrammofonfjädrar o ventilfjädrar, blockspiraler o\nmagnapullfjädrar. Pressdetaljer i\nplåt o band. Konstsmide med\nvarunamn ’Äkta Torsmide’. Egen\nverktygsfabrik. Modern härdverkstad\nmed automatiska genomgångsugnar\nFörsäljningsrepresentant för\nNorrland: 851 02 Sundsvall. Cesab Stål\nAB. Tel 060-15 44 60. Telex 71284\nAntal anställda: 75\nAktiekapital: 40 000\nVerkst dir: Stig Lundquist\nEtableringsår: 1964.\n\nMEKANISKA PROVNINGS.\nANSTALTEN TOM NORDENS.\nSON AB\n\nPnr 116 45\n\nStockholm, Katarinav 18. Tel\n08-44 5 6 33 , 44 56 32. Bankgiro\n478-2611. Postgiro 152046-9.\nTga Consulting\n\nVerksamhet: Konsulterande\ningen-jörsbyrå för ånganläggningar,\nvärmekraftanläggningar, industriell\nvärme-, eldnings- o maskinteknik,\nbesiktningar av ångpannor o\ntryckkärl, leverans o\nrevisionsbesiktningar av kolsyre-, sprinkler- o\nbrandal armanläggning ar\nAntal anställda: 6\nVerkst dir: Civiling Tom\nNordensson\n\nEtableringsår: 1910.\n\nMEK VERKSTÄDER\n\nse i övrigt resp namn.\n\nMEKANO, VERKSTADS AB\n\nPnr 252 27\n\nHälsingborg, Motorg 5. Tel\n042-1263 55. Bankgiro 65-2924.\nPostgiro 30575. Tga Mekano\nVerksamhet: Tillverkar\ntransportanläggningar, rengöringsmaskiner\nför bryggeri-, mejeri-,\ncharkuteri-o mek industrin samt för fordon\nVarunamn: Mekano\nAntal anställda: 75\nAktiekapital: 500 000\nVerkst dir: Stig Bergman\nEtableringsår: 1917.\n\nMICKI LEKSAKER AB\n\nPnr 360 32\n\nGemla, Box 79. Tel 0470-670 45.\nBankgiro 668-08 05. Postgiro\n283550-2. Tga Micki, Växjö\nVerksamhet: Tillverkar träleksaker,\nprydnadshyllor\nAntal anställda: 60\nÅrsomsättning: 3 000 000\nAktiekapital: 135 000\nVeikst dir: Lars Aronsson\nEtableringsår: 1944.\n\nHEJARSMIDE, AB\n\nPnr 199 00\n\nEnköping, Bangårdsg 6. Tel\n0171-303 70\n\nVerksamhet: Tillverkar alla slags\nhejade detaljer\nAktiekapital: 100 000\nVerkst dir: Lars Jonsson\nEtableringsår: 1931.\n\nVALLA CEMENTGJUTERI, AB\n\nPnr 640 23\n\nValla, Storg 35. Box 28. Tel\n0150-600 30. Bankgiro 624-4289.\nPost-giro 92075-1\n\nVerksamhet: Tillverkar betongrör,\nkabelskydd av betong\nAntal anställda: 12\nÅrsomsättning: 1 100 000\nVerkst dir: Per Hilborn\nEtableringsår: 1919.\n\nSAWO EXPORT AB\n\nPnr 292 00\n\nKarlshamn, Drottningg 7. Box 135.\nTel 0454-138 36, 138 37. Tga Sa-\n\nwoex. Telex 4551\nVeiksamhet: Trävaruexport\nAntal anställda: 3\nÅrsomsättning: 8 000 000\nAktiekapital: 50 000\nVerkst dir: Töre Arnmark\nEtableringsår: 1961.\n\nmalmberg, g\n\nPnr 302 50\n\nHalmstad, Pilefeltsg 44. Tel\n035-1129 96. Bankgiro 42-3587.\nPostgiro 328900\n\nVerksamhet: Utför ytbehandling\nsåsom förnickling, förkromning,\nförzinkning etc\nAntal anställda: 5\nChef: G Malmberg\nEtableringsår: 1938.\n\nAMERICAN PRESS, AB\n\nPnr 260 61\n\nHyllinge, Smedg. Tel 042-251 80.\nBankgiro 340-4928. Postgiro\n112749-7\n\nVerksamhet: Kemisk tvätt,\nvittvätt, industritvätt, mattvätt,\nskoreparationer, plasttoffel- o\nträ-tcffeltillverkning. Tvättbutiker i\nHälsingborg, Landskrona, Malmö,\nLund, Halmstad, Kristianstad\nVarunamn: American Press,\nHyllinge Ortopedic\nAntal anställda: 100\nVerkst dir: Eskil Jacobsson\nEtableringsår: 1951\nDotterbolag: AB Hyllinge\nProdukter, AB Pressco.\n\nAMERIKANSKA FILM.\nIMPORTEN AB\n\nPnr 111 21\n\nStockholm, Drottningg 56. Tel\n08-23 36 40. Bankgiro 72-7033.\nPostgiro 456427. Telex 10051. Tga\nAmerfilm\n\nVerksamhet: Säljer film o maskiner\nför röntgen: kino o grafiskt\nAntal anställda: 31\nÅrsomsättning: 12150000\nAktiekapital: 200 000\nVerkst dir: Ingmar Matsgård\nEtableringsår: 1947.\n\nAMERIKANSKA\nGUMMI-REPARATIONSVERKSTADEN\nCHARLES GUSTAFSSON AB\n\nPnr 552 40\n\nJönköping, S Strandg 11-17. Tel\n036-160335. Bankgiro 860-0314.\nPostgiro 73982-1\nVerksamhet: Säljer o reparerar\ndäck o slangar, regummeringar\nAntal anställda: 12\n\nÅrsomsättning: 2 000 000\nChef: B Klint\nEtableringsår: 1927.\n\nAMERIKANSKA\nTELE-PRODUKTER AB\n\nPnr 127 40\n\nSkärholmen 4, Box 4084.\nStång-holmsbacken 33-35. Tel\n08-710 99 50, 710 99 60. Bankgiro\n568-9930. Postgiro 159150-2. Tga Tele-\n\nproducts\n\nVerksamhet: Importerar o säljer\nelektroniska instrument, datasystem\nAntal anställda: 3\nÅrsomsättning: 950 000\nAktiekapital: 5 000\nVerkst dir: Civiling Robert Olsson.\n\nAMERKO\n\nPnr 112 32\n\nStockholm, Flemingg 59. Tel 08-\n\n5407 35, 54 75 35. Tga Amerko\nVerksamhet: Import o export av\nfläktar o snabbkopplingar i plast\nför rör o slang. Rens- o\nkapmaski-ner för rör\n\nChef: Dir B Bergendahl\nEtableringsår: 1950.",
    "structured": {
        "0": {
            "companyName": "HACKEFORS PORSLIN AB",
            "address": "Linköping, Hackefors",
            "phone_number": "013-10 20 90",
            "bank_details": {
                "bankgiro": "120-2738",
                "postgiro": "7688-5"
            },
            "activity": "Porslinsindustri, hus-hålls- o prydnadsporslin",
            "employees": 50,
            "annual_turnover": 2000000,
            "capital": 150000,
            "key_personnel": [
                {
                    "name": "G Ivar Franson",
                    "position": "ordf"
                },
                {
                    "name": "Ake Elmberg",
                    "position": "Verkst dir"
                }
            ],
            "establishment_year": 1929
        },
        "1": {
            "companyName": "SVENSKA TEMPUS, AB",
            "address": "Hägersten, Jakobsdalsv 12, Box 32015",
            "phone_number": "08-190290",
            "bank_details": {
                "bankgiro": "569-5259",
                "postgiro": "50928-1"
            },
            "activity": "Tillverkar o säljer handbrandsläckare, slangrullar, pulver- o lättskumsaggregat, kolsyreanläggningar, oljelänsor samt brandalarm",
            "employees": 90,
            "annual_turnover": 15000000,
            "capital": 500000,
            "key_personnel": [
                {
                    "name": "Alf Ahlqvist",
                    "position": "Verkst dir"
                }
            ],
            "establishment_year": 1922
        },
        "2": {
            "companyName": "TIVEDSLAMELL, AB",
            "address": "Tibro 1, Järnvägsg. Box 21",
            "phone_number": "0504-123 00",
            "bank_details": {
                "bankgiro": "221-3627",
                "postgiro": "476977-4"
            },
            "activity": "Tillverkar o säljer lamellträ",
            "employees": 49,
            "annual_turnover": 7200000,
            "capital": 240000,
            "key_personnel": [
                {
                    "name": "Sune Hallström",
                    "position": "Veikst dir"
                }
            ],
            "establishment_year": 1954
        },
        "3": {
            "companyName": "MEKANISKA FJÄDRAR AB",
            "address": "Torsås, Box 115",
            "phone_number": "0486-105 80",
            "bank_details": {
                "bankgiro": "982-8922",
                "postgiro": "666580-6"
            },
            "activity": "Tillverkar o säljer allt i fjädrar såsom spiralfjädrar, tryck-o dragfjädrar, platt- o vridfjädrar, fasonfjädrar o tråddetaljer i runt o platt material samt grammofonfjädrar o ventilfjädrar, blockspiraler o magnapullfjädrar. Pressdetaljer i plåt o band. Konstsmide med varunamn ’Äkta Torsmide’. Egen verktygsfabrik. Modern härdverkstad med automatiska genomgångsugnar. Försäljningsrepresentant för Norrland: 851 02 Sundsvall. Cesab Stål AB.",
            "employees": 75,
            "capital": 40000,
            "key_personnel": [
                {
                    "name": "Stig Lundquist",
                    "position": "Verkst dir"
                }
            ],
            "establishment_year": 1964
        },
        "4": {
            "companyName": "MEKANISKA PROVNINGS. ANSTALTEN TOM NORDENSSON AB",
            "address": "Stockholm, Katarinav 18",
            "phone_number": "08-44 5 6 33 , 44 56 32",
            "bank_details": {
                "bankgiro": "478-2611",
                "postgiro": "152046-9"
            },
            "activity": "Konsulterande ingen-jörsbyrå för ånganläggningar, värmekraftanläggningar, industriell värme-, eldnings- o maskinteknik, besiktningar av ångpannor o tryckkärl, leverans o revisionsbesiktningar av kolsyre-, sprinkler- o brandal armanläggning ar",
            "employees": 6,
            "key_personnel": [
                {
                    "name": "Civiling Tom Nordensson",
                    "position": "Verkst dir"
                }
            ],
            "establishment_year": 1910
        },
        "5": {
            "companyName": "MEK VERKSTÄDER"
        },
        "6": {
            "companyName": "MEKANO, VERKSTADS AB",
            "address": "Hälsingborg, Motorg 5",
            "phone_number": "042-1263 55",
            "bank_details": {
                "bankgiro": "65-2924",
                "postgiro": "30575"
            },
            "activity": "Tillverkar transportanläggningar, rengöringsmaskiner för bryggeri-, mejeri-, charkuteri-o mek industrin samt för fordon",
            "employees": 75,
            "capital": 500000,
            "key_personnel": [
                {
                    "name": "Stig Bergman",
                    "position": "Verkst dir"
                }
            ],
            "establishment_year": 1917
        },
        "7": {
            "companyName": "MICKI LEKSAKER AB",
            "address": "Gemla, Box 79",
            "phone_number": "0470-670 45",
            "bank_details": {
                "bankgiro": "668-08 05",
                "postgiro": "283550-2"
            },
            "activity": "Tillverkar träleksaker, prydnadshyllor",
            "employees": 60,
            "annual_turnover": 3000000,
            "capital": 135000,
            "key_personnel": [
                {
                    "name": "Lars Aronsson",
                    "position": "Veikst dir"
                }
            ],
            "establishment_year": 1944
        },
        "8": {
            "companyName": "HEJARSMIDE, AB",
            "address": "Enköping, Bangårdsg 6",
            "phone_number": "0171-303 70",
            "activity": "Tillverkar alla slags hejade detaljer",
            "capital": 100000,
            "key_personnel": [
                {
                    "name": "Lars Jonsson",
                    "position": "Verkst dir"
                }
            ],
            "establishment_year": 1931
        },
        "9": {
            "companyName": "VALLA CEMENTGJUTERI, AB",
            "address": "Valla, Storg 35, Box 28",
            "phone_number": "0150-600 30",
            "bank_details": {
                "bankgiro": "624-4289",
                "postgiro": "92075-1"
            },
            "activity": "Tillverkar betongrör, kabelskydd av betong",
            "employees": 12,
            "annual_turnover": 1100000,
            "key_personnel": [
                {
                    "name": "Per Hilborn",
                    "position": "Verkst dir"
                }
            ],
            "establishment_year": 1919
        },
        "10": {
            "companyName": "SAWO EXPORT AB",
            "address": "Karlshamn, Drottningg 7, Box 135",
            "phone_number": "0454-138 36, 138 37",
            "bank_details": {
                "bankgiro": "624-4289",
                "postgiro": "92075-1"
            },
            "activity": "Trävaruexport",
            "employees": 3,
            "annual_turnover": 8000000,
            "capital": 50000,
            "key_personnel": [
                {
                    "name": "Töre Arnmark",
                    "position": "Verkst dir"
                }
            ],
            "establishment_year": 1961
        },
        "11": {
            "companyName": "malmberg, g",
            "address": "Halmstad, Pilefeltsg 44",
            "phone_number": "035-1129 96",
            "bank_details": {
                "bankgiro": "42-3587",
                "postgiro": "328900"
            },
            "activity": "Utför ytbehandling såsom förnickling, förkromning, förzinkning etc",
            "employees": 5,
            "key_personnel": [
                {
                    "name": "G Malmberg",
                    "position": "Chef"
                },
                "establishment_year: 1938"
            ],
            "12": {
                "companyName": "AMERICAN PRESS, AB",
                "address": "Hyllinge, Smedg",
                "phone_number": "042-251 80",
                "bank_details": {
                    "bankgiro": "340-4928",
                    "postgiro": "112749-7"
                },
                "activity": "Kemisk tvätt, vittvätt, industritvätt, mattvätt, skoreparationer, plasttoffel- o trä-tcffeltillverkning. Tvättbutiker i Hälsingborg, Landskrona, Malmö, Lund, Halmstad, Kristianstad",
                "employees": 100,
                "key_personnel": [
                    {
                        "name": "Eskil Jacobsson",
                        "position": "Verkst dir"
                    }
                ],
                "establishment_year": 1951
            },
            "13": {
                "companyName": "AMERIKANSKA FILM. IMPORTEN AB",
                "address": "Stockholm, Drottningg 56",
                "phone_number": "08-23 36 40",
                "bank_details": {
                    "bankgiro": "72-7033",
                    "postgiro": "456427"
                },
                "activity": "Säljer film o maskiner för röntgen: kino o grafiskt",
                "employees": 31,
                "annual_turnover": 12150000,
                "capital": 200000,
                "key_personnel": [
                    {
                        "name": "Ingmar Matsgård",
                        "position": "Verkst dir"
                    }
                ],
                "establishment_year": 1947
            },
            "14": {
                "companyName": "AMERIKANSKA GUMMI-REPARATIONSVERKSTADEN CHARLES GUSTAFSSON AB",
                "address": "Jönköping, S Strandg 11-17",
                "phone_number": "036-160335",
                "bank_details": {
                    "bankgiro": "860-0314",
                    "postgiro": "73982-1"
                },
                "activity": "Säljer o reparerar däck o slangar, regummeringar",
                "employees": 12,
                "annual_turnover": 2000000,
                "key_personnel": [
                    {
                        "name": "B Klint",
                        "position": "Chef"
                    }
                ],
                "establishment_year": 1927
            },
            "15": {
                "companyName": "AMERIKANSKA TELE-PRODUKTER AB",
                "address": "Skärholmen 4, Box 4084. Stång-holmsbacken 33-35",
                "phone_number": "08-710 99 50, 710 99 60",
                "bank_details": {
                    "bankgiro": "568-9930",
                    "postgiro": "159150-2"
                },
                "activity": "Importerar o säljer elektroniska instrument, datasystem",
                "employees": 3,
                "annual_turnover": 950000,
                "capital": 5000,
                "key_personnel": [
                    {
                        "name": "Civiling Robert Olsson",
                        "position": "Verkst dir"
                    }
                ],
                "establishment_year": null
            },
            "16": {
                "companyName": "AMERKO",
                "address": "Stockholm, Flemingg 59",
                "phone_number": "08-5407 35, 54 75 35",
                "activity": "Import o export av fläktar o snabbkopplingar i plast för rör o slang. Rens- o kapmaski-ner för rör",
                "key_personnel": [
                    {
                        "name": "B Bergendahl",
                        "position": "Chef"
                    }
                ],
                "establishment_year": 1950
            }
        }
    }
}