{
    "original": "AEG, ELEKTRISKA AB\n\nPnr 171 91\n\nSolna, Svetsarv 10. Tel\n08-29 00 80. Tga Elektron\nVerksamhet: Elektr materiel,\napparater o maskiner. Elektr\nanläggningar o installationer. Elektronik\no teleutrustning\n\nFörsäljningskontor: 171 91 Solna,\n\nSvetsarv 10. Tel 08-29 00 80\n\n801 06 Gävle 1, Box 527- Lötängsg\n\n2. Tel 026-18 82 60\n\n20110 Malmö 1, Pack. Norden-\n\nskiöldsg 11. Tel 040-71140\n\n401 20 Göteborg 1, Box 59. Kilsg\n\n4-8. Tel 031-80 00 20\n\n601 03 Norrköping 1, Box 197.\n\nMalmg 5. Tel 011-106640\n\n551 02 Jönköping 1, Box 25. Myntg\n\n23. Tel 036-16 0315\n\n580 03 Linköping 3, Box 3045.\n\nöstgötag 32. Tel 013-12 29 58\n\n651 08 Karlstad 1, Box 516. Ramg 7.\n\nTel 054-18 5140\n\n701 01 Örebro 1, Pack. Predsg 4.\n\nTel 019-13 96 25, 13 96 26\n\n850 08 Sundsvall 8, Box 8019. En-\n\nhörningsv 24. Tel 060-1216 00\n\n931 01 Skellefteå 1, Box 362. Nyg\n\n39. Tel 0910-14210\n\n981 01 Kirunal, Box 105. Järnvägsg.\n\nTel 0980-147 70\n\nVarunamn: AEG-Telefunken\n\nÅrsomsättning: 400 000 000\n\nAktiekapital: 15 000 000\n\nVerkst dir: I Norlindh.\n\nAERO MATERIEL AB\n\nPnr 122 33\n\nEnskede, Sandsborg sv 50. Tel\n08-49 2510. Bankgiro 13-6109. Postr\ngiro 50665. Tga Aeromateriel.\nTelex 19982 AEROMAT S\nVerksamhet: Importerar o tillverkar\nflygmateriel, hydraulik o\nelektronikkomponenter\nAntal anställda: 35\n\nAFT\n\nAktiekapital: 350 000\nVerkst dir: Lars Harting\nEtableringsår: 1927.\n\nBERGS TRÄFORÄDLING, AB\n\nPnr 590 61\n\nVretakloster, Box 3. Tel\n013-60036. Bankgiro 120-2282.\nPostgiro 11544-4\n\nVerksamhet: Tillverkar sågade o\nhyvlade trävaror, formluckor,\nsnickerier o övrigt byggnadsmaterial\nAntal anställda: 10\nÅrsomsättning: 1000 000\nAktiekapital: 40 000\n\nVerkst dir: Disp Erie Gustavsson\nEtableringsår: 1944.\n\nHARTMANNS PRODUKTER, AB\n\nPnr 115 41\n\nStockholm, s Hamnv 50. Tel\n08-22 50 80. Bankgiro 577-5697.\nPostgiro 192692-2. Tga Hartmannpro\ndukt. Telex 17900 NYMANS S\nVerksamhet: Säljer stålinredningar\no kontorsmöbler\n\nVarunamn: Cardinal, Speed Moving,\nVital\n\nAktiekapital: 250 000\nChef: Ing Sven Ullmark\nEtableringsår: 1943\nOmbildat till aktiebolag 1954.\n\nHARWELL AB, INGENIORS.\nFIRMAN\n\nPnr 235 00\n\nVellinge, Malmöv 28. Tel\n040-42 07 65. Bankgiro 875-5969.\nPost-giro 437232-2. Tga Harwell\nVerksamhet: Betongblandare o\nbetongstationer\nAntal anstäUda: 5\nÅrsomsättning: 1000 000\nAktiekapital: 5 000\nVerkst dir: N Y Hårde\nEtableringsår: 1956.\n\nBJUVEX AUTOMAT AB\n\nPnr 267 00\n\nBjuv, N Storg 19. Tel 042-789 70.\nBankgiro 340-5974. Postgiro\n646670-0\n\nVerksamhet: Försäljning o\nuthyrning av serveringsautomater med\negna generalagenturer\nAntal anställda: 30\nÅrsomsättning: 5 000 000\nVerkst dir: Sven Andersson\nEtableringsår: 1954.\n\nBJÄRE INDUSTRIER, AB\n\nse Novia Livsmedelsindustrier AB.\n\nBJÄRNUMS\nMÖBELFABRIKER, AB\n\nPnr 280 20\n\nBjämum, Box 69. Tel 0451-200 15,\n20190. Bankgiro 86-6319. Postgiro\n23550-7\n\nVerksamhet: Tillverkar stapelbara\nstolar, möbler för samlingslokaler,\nålderdomshem etc\nAntal anställda: 60\nÅrsomsättning: 5 200 000\nAktiekapital: 73700\nVerkst dir: Annie Cederholm\nEtableringsår: 1919.\n\nBJÄRNUMS\nREDSKAPSFABRIK AB\n\nPnr 280 20\n\nBjärnum, Box 68. Tel 0451-20075.\nBankgiro 569-4492. Postgiro 29554-3\nVerksamhet: Skyfflar o spadar i\nstål- o lättmetallplåt, handredskap\nAntal anställda: 8\nAktiekapital: 85 000\nFabr: Einar Jönsson\nEtableringsår: 1880.\n\nBJÄRNUMS\nSTÅLPRODUKTER AB\n\nPnr 280 20\n\nBjärnum, Box 96. Tel 0451-206 20,\n210 36. Bankgiro 265-3962. Postgiro\n646166-9\n\nVerksamhet: Tillverkar\nlunchrumsmöbler o arbetsstolar.\nExcenter-pressning, rörbocknings- o\nsvets-ningsarbeten. Legoarbeten. Diverse\nmaterialhanteringsutrustning\nAntal anställda: 30\nÅrsomsättning: 2 000 000\nAktiekapital: 25 000\nVerkst dir: Anders Krahner\nEtableringsår: 1964.\n\nÅSBRINKS MASKIN AB\n\nPnr 222 38\n\nLund. Bondev 8. Tel 046-12 42 60.\nTga Sperco. Telex 32260\nVerksamhet Försäljning av\nbyggnadskompressorer\nAvdelningskontor. 402 52 Göteborg\n13. Gamlestadsv. Box 13070. Tel\n031-25 04 00\n\n14123 Huddinge. Sjödalsv 21. Box\n1121. Tel 08-757 28 80\nÅrsomsättning: 3 000 000\nAktiekapital: 800 000\nVerkst dir: Knut Linse\nEtableringsår: 1931.\n\nKARBONKEMI, AB\n\nPnr 412 66\n\nGöteborg, Fredrika Bremersg 10.\nTel 031-40 56 22. Bankgiro 84-7773.\nPostgiro 5282 52. Telex 20706. Tga\nKarbonkemi\n\nVerksamhet: Maskiner med\ntillbehör för plastindustrin\nAktiekapital: 10000\nVerkst dir: Gerhard Göpfert\nEtableringsår: 1959.\n\nTAU\n\nkuterimaskiner. Sorteringsfabrik\nAktiekapital: 640 000\nVerkst dir: Carl-Gösta Stolpe\nEtableringsår: 1925.\n\nNOR\n\nNORDQVIST &amp; FULTON AB\n\nPnr 41117\n\nGöteborg, V Hamng 9. Tel\n031-1344 23, 1104 66. Bankgiro 42-0394.\nPostgiro 427935. Tga Nordton\nVerksamhet: Agentur o partiaffär\ni torkad frukt, kolonialvaror, ost\no konserver\nAntal anställda: 3\nAktiekapital: 6 000\nVerkst dir: Olof Fallström\nEtableringsår: 1924\nOmbildat till aktiebolag 1942.\n\nNORDKVIST, AB OSKAR\n\nPnr 23200\n\nArlöv, Hammarv. Tel 040-43 50 30.\nBankgiro 264-7683. Postgiro\n38777-9\n\nVerksamhet: Tillverkar allt i\nrostfritt o järn. Industriplåtslageri\nAntal anställda: 45\nÅrsomsättning: 4 000 000\nAktiekapital: 75 000\nVerkst dir: Oskar Nordkvist\nEtableringsår: 1923.\n\nNORDLAND IMPORT\nEXPORT AB\n\nPnr 701 04\n\nÖrebro 1, Box 240. Lövstag 7. Tel\n019-12 40 30. Bankgiro 817-4476.\nPostgiro 476766-1. Tga Nordland.\nTelex 73238\n\nVerksamhet: Representerar\nutländska tillverkare av byggprodukter\nAntal anställda: 25\nÅrsomsättning: 9 000 000\nAktiekapital: 100000\nVerkst dir: Stig Janson\nEtableringsår: 1955.\n\nNORDLANDER &amp; HÖGLUND,\nBYGGNADS AB\n\nPnr 871 01\n\nHärnösand 1, Box 296. Tel\n0611-156 80. Bankgiro 767-9368.\nPostgiro 76241-9\n\nVerksamhet: Byggnadsrörelse\nAktiekapital: 76 000\nFirmatecknare: P E Nordlander,\nSture Sjödin\nEtableringsår: 1951.\n\nATLAS RESOR AB\n\nPnr 401 24\n\nGöteborg 1, Box 273. Vegag 3. Tel\n031-12 44 70. Bankgiro 231-3062.\nPostgiro 629631-3. Tga\nAtlastra-vel. Telex 20807\nVerksamhet: Researrangör\nAntal anställda: 125\nÅrsomsättning: 40 000 000\nAktiekapital: 50 000\nStyrelse: Dir Lennart Lindgren\n(ordf), dir Rolf Blomgren, dir Nils\nHenning Grötterud, dir Georg\nWennerholm\n\nVerkst dir: Georg Wennerholm\nEtableringsår: 1966.\n\nATLAS SVENSKA\nFÖRSÄLJNINGS AB, VS\n\nPnr 200 13\n\nMalmö 27, Tärnög 2, Industrihamnen.\nBox 27029. Tel 040-93 61 50.\nBankgiro 264-2049. Postgiro 435156-5\nVerksamhet: Kylskåp o frysboxar,\nfrysskåp, tvättmaskiner,\ndiskmaskiner, manglar, spisar o spisfläktar\nAktiekapital: 250 000\nVerkst dir: Gunnar Ekblad\nEtableringsår: 1954.\n\nallers forlag ab\n\nPnr 25185\n\nHelsingborg, Tallg 10. Tel\n042-126180. Bankgiro 43-7802.\nPostgiro 14400. Tga Allers. Telex 72273\nVerksamhet: Trycker o utger\ntidningarna Allers, Femina, Hänt i\nVeckan, novelltidningen Siesta\nsamt serietidningen Familjen\nFlinta. Dessutom tryckes Det\nBästa, Lyckoslanten, kataloger etc\nAllers Annonsavdelningar:\nStockholm NO, Tysta g 12. Tel\n08-67 98 70. Telex 1498\nGöteborg S, Fridkullag 20B. Tel\n031-2079 92\n\nMalmö C, Stora Nyg. 5. Tel\n040-12 08 80\n\nAntal anställda: 655\nÅrsomsättning: 92000 000\nAktiekapital: 6 000 000\nStyrelse: Adv Ake Wettermark\n(ordf), dir Jörgen Äller, dir Svend\nÄller, dir Malte Cato, dir Gunnar\nFrick, dir Olof Ljunggren\nVerkst dir: Malte Cato\nEtableringsår: 1894\nDotterbolag: AB Skånskt\nDjuptryck, Helsingborg. Pallin &amp; Lund\nMek Verkstad AB, Helsingborg.\nFastighets AB Furiren nr 12,\nStockholm, Äller GmbH, Ulzburg,\nVäst Tyskland.\n\nall-galvan ab\n\nPnr 112 28\n\nStockholm, Bergsg 45. Tel\n08-52 78 77. Postgiro 254340\nVerksamhet: Elektrolytisk\nbehandling av metall\nAktiekapital: 12 000\nVerkst dir: Sigfrid Ostman\nEtableringsår: 1946.",
    "structured": {
        "1": {
            "company_name": "AEG, ELEKTRISKA AB",
            "pnr": "171 91",
            "address": "Solna, Svetsarv 10",
            "phone_number": "08-29 00 80",
            "activity": "Elektr materiel, apparater o maskiner. Elektr anläggningar o installationer. Elektronik o teleutrustning",
            "establishment_year": 0
        },
        "2": {
            "company_name": "AERO MATERIEL AB",
            "pnr": "122 33",
            "address": "Enskede, Sandsborg sv 50",
            "phone_number": "08-49 2510",
            "bank_details": {
                "bankgiro": "13-6109",
                "postgiro": "50665"
            },
            "activity": "Importerar o tillverkar flygmateriel, hydraulik o elektronikkomponenter",
            "employees": 35,
            "establishment_year": 1927
        },
        "3": {
            "company_name": "BERGS TRÄFORÄDLING, AB",
            "pnr": "590 61",
            "address": "Vretakloster, Box 3",
            "phone_number": "013-60036",
            "bank_details": {
                "bankgiro": "120-2282",
                "postgiro": "11544-4"
            },
            "activity": "Tillverkar sågade o hyvlade trävaror, formluckor, snickerier o övrigt byggnadsmaterial",
            "employees": 10,
            "annual_turnover": 1000000,
            "capital": 40000,
            "key_personnel": [
                {
                    "name": "Disp Erie Gustavsson",
                    "position": "Verkst dir"
                }
            ],
            "establishment_year": 1944
        },
        "4": {
            "company_name": "HARTMANNS PRODUKTER, AB",
            "pnr": "115 41",
            "address": "Stockholm, s Hamnv 50",
            "phone_number": "08-22 50 80",
            "bank_details": {
                "bankgiro": "577-5697",
                "postgiro": "192692-2"
            },
            "activity": "Säljer stålinredningar o kontorsmöbler",
            "key_personnel": [
                {
                    "name": "Ing Sven Ullmark",
                    "position": "Chef"
                }
            ],
            "establishment_year": 1943
        }
    }
}