{
    "original": "JIM S-MDBLER, AB\n\nPnr 828 01\n\nEdsbyn, Fack 51. Tel 0271-20 1 65,\n203 70. Bankgiro 193-5105.\nPostgiro 131626-4. Tga Jims\nVerksamhet: Tillverkar\ninrednings-snickerier för skolor, sjukhus m fi\nfinare inredningsarbeten,\nfurumöbler\n\nAntal anställda: 10\n\nÅrsomsättning: 600 000\n\nAktiekapital: 45 000\n\nÄgare o chefer: Torsten Pettersson,\n\nWalfrid Chrig\n\nEtableringsår. 1947\n\nOmbildat till aktiebolag 1965.\n\nJINO KONFEKTION AB\n\nPnr 200 73\n\nMalmö 19, Lorensborgsg 19. Fack.\nTel 040-867 70. Bankgiro 34-8215.\nPostgiro 245681\n\nVerksamhet: Tillverkar kostymer\n(herr), blazers o byxor\nVarunamn: Jino\nAntal anställda: 61\nÅrsomsättning: 2 000 000\nAktiekapital: 50000\nVerkst din Sven Espmarker\nEtableringsår: 1947.\n\nNILFISK, AB\n\nPnr 21137\n\nMalmö, Stora Nyg 36. Tel\n040-12 85 00, 12 87 00. Tga Nilfisk\nVerksamhet: Hushålls-, o\nindustridammsugare. Golvbonare\nVarunamn: Nilfisk\nAntal anstäUda: 50\nÅrsomsättning: 7 000 000\nAktiekapital: 45 000\nEtableringsån 1939.\n\nNIHLMARKS TRÄVARUAFFÄR,\nAB GUSTAF\n\nPnr 401 24\n\nGöteborg 1, Mårten Krakowg 8.\nBox 276. Tel 031-1713 20. Bank-\n\ngiro 50-6524. Postgiro 42700.Telex\n20762. Tga Nihlmark\nVerksamhet: Brädgård, snickerifar\nbrik, golvläggning\nAntal anställda: 90\nÅrsomsättning: 18 900 000\nAktiekapital: 600000\nVerkst dir: Agne Gislev\nEtableringsån 1919.\n\nHALLBÄCK &amp; SÖNER AB, C M\n\nPnr 21120\n\nMalmö C, Stormg 4. Tel\n040-1259 53, 12 06 53. Tga\nHallbäcksöner\n\nVerksamhet: Speditionsfirma\nAktiekapital: 25 000\nEtableringsår: 1925.\n\nHALLEN ENTREPRENAD AB,\nJ R\n\nPnr 80105\n\nGävle 1, Tredje Tvärg 3. Box 371.\nTel 026-11 1815, 18 36 80.\nBankgiro 603-6347. Postgiro 613131-2\nVerksamhet: Utför sandblästring o\nmålning av järnkonstruktioner.\nIndustrirengöringar, sprutförzànk-ning o metallisering\nAntal anställda: 25\nAktiekapital: 15 000\nStyrelse: Dir Jack Hallén (ordf)\nfru Gun Hallén\nVerkst dir: Jack Hallén\nEtableringsår: 1963.\n\nVANSITO, AB\n\nPnr 582 24\n\nLinköping, Bokhållareg 2 B. Tel\n013-14 62 45. Bankgiro 607-9818.\nPostgiro 262816-2. Tga Vansito\nVerksamhet: Finförädlade\npappersvaror, dekorationer speciellt för\njul- o påskhögtider. Export o import\nVarunamn: Mr Strong, Vansito,\nÄngla\n\nAktiekapital: 25 000\nVerkst dir: Allan Rundquist\nDir-ass: Jan-Christer Rundquist\nEtableringsår: 1942.\n\nINGERSOLL.RAND AB\n\nPnr 16125\n\nBromma 1, Fack. Gårdsfogdev 14.\nTel 08-98 05 40. Bankgiro 743-5274.\nPostgiro 254529-1. Telex 10420\nVerksamhet: Försäljning av\nkompressorer, bergborrmaskiner,\ntryck-luftverktyg, pumpar, skrapspel etc\nVarunamn: Ingersoll-Rand\nAntal anställda: 120\nAktiekapital: 150 000\nVerkst dir: Al Keenan\nEtableringsår: 1946.\n\n|MA\n\n042-518 45, 518 46. Bankgiro\n141-9027. Postgiro 545995-3\nVerksamhet: Svarvning, fräsning,\nslipning, borrning o gängning\nAntal anställda: 18\nÅrsomsättning: 950 000\nAktiekapital: 25 000\nVeikst dir. Ingrid Nilsson\nEtableringsår: 1960.\n\nSCANTELE AB\n\nPnr 11641\n\nStockholm, Tengdahlsg 24. Tel\n08-24 58 25. Bankgiro 196-0202.\nPostgiro 574300-0. Tga Telescand.\nTelex 10368\n\nVerksamhet: Säljer elektroniska\ninstrument o komponenter\nAntal anställda: 20\nÅrsomsättning: 10 000 000\nAktiekapital: 125 000\nVeikst dir: K-V Fredrikson\nEtableringsår. 1961.\n\nSCANVOX\n\nLJUDÅTERGIVNING AB\n\nPnr 40012\n\nGöteborg 19, Box 19045. Florav 3,\nSävedalen. Tel 031-26 71 00,\n5624 80. Bankgiro 415-1155.\nPostgiro 721168-3\n\nVeiksamhet Mono- och\nstereoinspelningar. Grammofonskiveproduktion. Förstärkaranläggningar\nChef: Civiling Sven Forshamn\nEtableringsår: 1964.\n\nRYLANDER, AB BRÖDERNA\n\nPnr 79101\n\nFalun 1, Hyttg 31. Box 1. Tel\n023-186 60. Bankgiro 464-2633.\nPostgiro 90820-2\n\nVerksamhet: Tillverkar \"Eryl\"\ndubbelpannor o lågtrycksångpannor,\noljecisterner, expansionskärl,\nelpannor, varmvattenberedare etc.\nByggnadsplåtslageri, värme- o\nsanitära installationer,\noljeeldningsanläggningar\nVarunamn: Eryl\nAntal anställda: 80\nÅrsomsättning: 5 000 000\nAktiekapital: 30 000\nStyrelse: Ing Erik Rylander (ordf),\nkamrer Gunnar Rylander, ing\nTorsten Rylander\nVerkst dir: Ing Erik Rylander\nEtableringsår. 1905\nOmbildat till aktiebolag 1929.\n\nRYLANDER AB, INGENJÖRS.\nFIRMA UNO\n\nPnr 21140\n\nMalmö, S Tullg 3. Tel 040-704 00.\nBankgiro 641-1433. Postgiro\n530753-3\n\nVerksamhet: Konsulterande\ningenjörer inom produktionsteknisk\nrationalisering, maskinkonstruktion,\nautomatisk styrning av\nproduktionssystem, produktutveckling,\nformgivning, industriell organisation,\nar-betsmätning ADB\nAntal anställda: 45\nAktiekapital: 100 000\nVerkst dir. Civiling Uno Rylander\nOvering: Stig Andersson\nEtableringsår: 1954\nOmbildat till aktiebolag 1961.\n\nRYNO REKLAM AB\n\nPnr 113 46\n\nStockholm, Sveav 145. Tel\n08-33 53 50, 33 53 30. Bankgiro\n73-5071. Postgiro 51109\nVerksamhet: Auktoriserad\nreklamkonsult\n\nÅrsomsättning: 800 000\nAktiekapital: 10 000\nVerkst dir: Ulf Lundquist\nEtableringsår: 1958.\n\nLJU\n\nLJUNGBERGS TEXTIL.\nTRYCK AB\n\nPnr 440 03\n\nFloda, Box 51. Tel 0302-30311,\n303 81. Bankgiro 889-7043.\nPost-giro 244423-0\n\nVerksamhet: Löntryckning o\nfärgning\n\nAntal anställda: 30\nÅrsomsättning: 1200000\nAktiekapital: 85 000\nVerkst dir: Erik Gustaf Ljungberg\nEtableringsår: 1948.\n\nLJUNGBERGS METALL.\nFABRIK, AB J G\n\nPnr 55102\n\nJönköping 1, Hulukvarnsg 10. Box\n49. Tel 036-1109 08, 1102 21.\nBankgiro 835-6347. Postgiro\n23119-1. Tga Metalljungberg\nVerksamhet: Tillverkar\nbyggnadsbeslag, båtbeslag o möbelbeslag\nAntal anställda: 13\nÅrsomsättning: 850 000\nAktiekapital: 102 000\nVerkst dir: Carl-Axel Gawelli\nEtableringsår: 1889.\n\nANDREÉNS TRÄHUS AB\n\nPnr 574 01\n\nVetlanda 1, Box 5. Gamla Ostanåv.\nTel 0383-147 80. Bankgiro\n145-0683. Postgiro 413006-8\nVerksamhet: Tillverkar o säljer\nmonteringsfärdiga trähus\nAntal anställda: 25\nÅrsomsättning: 4 200 000\nAktiekapital: 50 000\nVerkst dir: Ing Willy Andréen\nEtableringsår: 1963.",
    "structured": {
        "1": {
            "company_name": "JIM S-MDBLER, AB",
            "pnr": "828 01",
            "address": "Edsbyn, Fack 51. Tel 0271-20 1 65, 203 70",
            "bank_details": {
                "bankgiro": "193-5105",
                "postgiro": "131626-4"
            },
            "activity": "Tillverkar inrednings-snickerier för skolor, sjukhus m fi finare inredningsarbeten, furumöbler",
            "employees": 10,
            "annual_turnover": 600000,
            "capital": 45000,
            "key_personnel": [
                {
                    "name": "Torsten Pettersson",
                    "position": "Ägare"
                },
                {
                    "name": "Walfrid Chrig",
                    "position": "Chef"
                }
            ],
            "establishment_year": 1947
        },
        "2": {
            "company_name": "JINO KONFEKTION AB",
            "pnr": "200 73",
            "address": "Malmö 19, Lorensborgsg 19",
            "bank_details": {
                "bankgiro": "34-8215",
                "postgiro": "245681"
            },
            "activity": "Tillverkar kostymer (herr), blazers o byxor Varunamn: Jino",
            "employees": 61,
            "annual_turnover": 2000000,
            "capital": 50000,
            "key_personnel": [
                {
                    "name": "Sven Espmarker",
                    "position": "Verkst din"
                }
            ],
            "establishment_year": 1947
        },
        "3": {
            "company_name": "NILFISK, AB",
            "pnr": "21137",
            "address": "Malmö, Stora Nyg 36",
            "phone_number": "040-12 85 00, 12 87 00",
            "bank_details": {
                "bankgiro": "N/A",
                "postgiro": "N/A"
            },
            "activity": "Hushålls-, o industridammsugare. Golvbonare",
            "employees": 50,
            "annual_turnover": 7000000,
            "capital": 45000,
            "establishment_year": 1939
        },
        "4": {
            "company_name": "NIHLMARKS TRÄVARUAFFÄR, AB GUSTAF",
            "pnr": "40124",
            "address": "Göteborg 1, Mårten Krakowg 8. Box 276",
            "phone_number": "031-1713 20",
            "bank_details": {
                "bankgiro": "50-6524",
                "postgiro": "42700"
            },
            "activity": "Brädgård, snickerifar brik, golvläggning",
            "employees": 90,
            "annual_turnover": 18900000,
            "capital": 600000,
            "key_personnel": [
                {
                    "name": "Agne Gislev",
                    "position": "Verkst dir"
                }
            ],
            "establishment_year": 1919
        },
        "5": {
            "company_name": "HALLBÄCK & SÖNER AB, C M",
            "pnr": "21120",
            "address": "Malmö C, Stormg 4",
            "phone_number": "040-1259 53, 12 06 53",
            "activity": "Speditionsfirma",
            "capital": 25000,
            "establishment_year": 1925
        },
        "6": {
            "company_name": "HALLEN ENTREPRENAD AB, J R",
            "pnr": "80105",
            "address": "Gävle 1, Tredje Tvärg 3. Box 371",
            "phone_number": "026-11 1815, 18 36 80",
            "bank_details": {
                "bankgiro": "603-6347",
                "postgiro": "613131-2"
            },
            "activity": "Utför sandblästring o målning av järnkonstruktioner. Industrirengöringar, sprutförzànk-ning o metallisering",
            "employees": 25,
            "capital": 15000,
            "key_personnel": [
                {
                    "name": "Jack Hallén",
                    "position": "Styrelse"
                },
                {
                    "name": "Gun Hallén",
                    "position": "Styrelse"
                },
                {
                    "name": "Jack Hallén",
                    "position": "Verkst dir"
                }
            ],
            "establishment_year": 1963
        },
        "7": {
            "company_name": "VANSITO, AB",
            "pnr": "58224",
            "address": "Linköping, Bokhållareg 2 B",
            "phone_number": "013-14 62 45",
            "bank_details": {
                "bankgiro": "607-9818",
                "postgiro": "262816-2"
            },
            "activity": "Finförädlade pappersvaror, dekorationer speciellt för jul- o påskhögtider. Export o import"
        },
        "8": {
            "company_name": "INGERSOLL.RAND AB",
            "pnr": "16125",
            "address": "Bromma 1, Fack. Gårdsfogdev 14",
            "phone_number": "08-98 05 40",
            "bank_details": {
                "bankgiro": "743-5274",
                "postgiro": "254529-1"
            },
            "activity": "Försäljning av kompressorer, bergborrmaskiner, tryck-luftverktyg, pumpar, skrapspel etc",
            "employees": 120,
            "annual_turnover": 150000,
            "key_personnel": [
                {
                    "name": "Al Keenan",
                    "position": "Verkst dir"
                }
            ],
            "establishment_year": 1946
        },
        "9": {
            "company_name": "MA",
            "phone_number": "042-518 45, 518 46",
            "bank_details": {
                "bankgiro": "141-9027",
                "postgiro": "545995-3"
            },
            "activity": "Svarvning, fräsning, slipning, borrning o gängning",
            "employees": 18,
            "annual_turnover": 950000,
            "capital": 25000,
            "key_personnel": [
                {
                    "name": "Ingrid Nilsson",
                    "position": "Verkst dir"
                }
            ],
            "establishment_year": 1960
        },
        "10": {
            "company_name": "SCANTELE AB",
            "pnr": "11641",
            "address": "Stockholm, Tengdahlsg 24",
            "phone_number": "08-24 58 25",
            "bank_details": {
                "bankgiro": "196-0202",
                "postgiro": "574300-0"
            },
            "activity": "Säljer elektroniska instrument o komponenter",
            "employees": 20,
            "annual_turnover": 10000000,
            "capital": 125000,
            "key_personnel": [
                {
                    "name": "K-V Fredrikson",
                    "position": "Verkst dir"
                }
            ],
            "establishment_year": 1961
        },
        "11": {
            "company_name": "SCANVOX LJUDÅTERGIVNING AB",
            "pnr": "40012",
            "address": "Göteborg 19, Box 19045. Florav 3, Sävedalen",
            "phone_number": "031-26 71 00, 5624 80",
            "bank_details": {
                "bankgiro": "415-1155",
                "postgiro": "721168-3"
            },
            "activity": "Mono- och stereoinspelningar. Grammofonskiveproduktion. Förstärkaranläggningar",
            "employees": 12,
            "annual_turnover": 850000,
            "capital": 102000,
            "key_personnel": [
                {
                    "name": "Sven Forshamn",
                    "position": "Chef"
                }
            ],
            "establishment_year": 1964
        },
        "12": {
            "company_name": "RYLANDER, AB BRÖDERNA",
            "pnr": "79101",
            "address": "Falun 1, Hyttg 31. Box 1",
            "phone_number": "023-186 60",
            "bank_details": {
                "bankgiro": "464-2633",
                "postgiro": "90820-2"
            },
            "activity": "Tillverkar \"Eryl\" dubbelpannor o lågtrycksångpannor, oljecisterner, expansionskärl, elpannor, varmvattenberedare etc. Byggnadsplåtslageri, värme- o sanitära installationer, oljeeldningsanläggningar",
            "employees": 80,
            "annual_turnover": 5000000,
            "capital": 30000,
            "key_personnel": [
                {
                    "name": "Ing Erik Rylander",
                    "position": "Styrelse"
                },
                {
                    "name": "Gunnar Rylander",
                    "position": "Styrelse"
                },
                {
                    "name": "Torsten Rylander",
                    "position": "Styrelse"
                }
            ],
            "establishment_year": 1905
        },
        "13": {
            "company_name": "RYLANDER AB, INGENJÖRS. FIRMA UNO",
            "pnr": "21140",
            "address": "Malmö, S Tullg 3",
            "phone_number": "040-704 00",
            "bank_details": {
                "bankgiro": "641-1433",
                "postgiro": "530753-3"
            },
            "activity": "Konsulterande ingenjörer inom produktionsteknisk rationalisering, maskinkonstruktion, automatisk styrning av produktionssystem, produktutveckling, formgivning, industriell organisation, ar-betsmätning ADB",
            "employees": 45,
            "annual_turnover": 100000,
            "capital": 100000,
            "key_personnel": [
                {
                    "name": "Civiling Uno Rylander",
                    "position": "Verkst dir"
                },
                {
                    "name": "Stig Andersson",
                    "position": "Overing"
                }
            ],
            "establishment_year": 1954
        },
        "14": {
            "company_name": "RYNO REKLAM AB",
            "pnr": "11346",
            "address": "Stockholm, Sveav 145",
            "phone_number": "08-33 53 50, 33 53 30",
            "bank_details": {
                "bankgiro": "73-5071",
                "postgiro": "51109"
            },
            "activity": "Auktoriserad reklamkonsult",
            "annual_turnover": 800000,
            "capital": 10000,
            "key_personnel": [
                {
                    "name": "Ulf Lundquist",
                    "position": "Verkst dir"
                }
            ],
            "establishment_year": 1958
        },
        "15": {
            "company_name": "LJUNGBERGS TEXTIL. TRYCK AB",
            "pnr": "44003",
            "address": "Floda, Box 51",
            "phone_number": "0302-30311, 303 81",
            "bank_details": {
                "bankgiro": "889-7043",
                "postgiro": "244423-0"
            },
            "activity": "Löntryckning o färgning",
            "employees": 30,
            "annual_turnover": 1200000,
            "capital": 85000,
            "key_personnel": [
                {
                    "name": "Erik Gustaf Ljungberg",
                    "position": "Verkst dir"
                }
            ],
            "establishment_year": 1948
        },
        "16": {
            "company_name": "LJUNGBERGS METALL. FABRIK, AB J G",
            "pnr": "55102",
            "address": "Jönköping 1, Hulukvarnsg 10. Box 49",
            "phone_number": "036-1109 08, 1102 21",
            "bank_details": {
                "bankgiro": "835-6347",
                "postgiro": "23119-1"
            },
            "activity": "Tillverkar byggnadsbeslag, båtbeslag o möbelbeslag",
            "employees": 13,
            "annual_turnover": 850000,
            "capital": 102000,
            "key_personnel": [
                {
                    "name": "Carl-Axel Gawelli",
                    "position": "Verkst dir"
                }
            ],
            "establishment_year": 1889
        },
        "17": {
            "company_name": "ANDREÉNS TRÄHUS AB",
            "pnr": "57401",
            "address": "Vetlanda 1, Box 5. Gamla Ostanåv",
            "phone_number": "0383-147 80",
            "bank_details": {
                "bankgiro": "145-0683",
                "postgiro": "413006-8"
            },
            "activity": "Tillverkar o säljer monteringsfärdiga trähus",
            "employees": 25,
            "annual_turnover": 4200000,
            "capital": 50000,
            "key_personnel": [
                {
                    "name": "Ing Willy Andréen",
                    "position": "Verkst dir"
                }
            ],
            "establishment_year": 1963
        }
    }
}