{
    "original": "BUCHHOLZ, B\n\nPnr 41137\n\nGöteborg, Kristinelundsg 5. Tel\n031-16 10 66. Tga Buchholzfirma\nVerksamhet: Agenturaffär\nÄgare o chef: L Buchholz\nEtableringsår: 1884.\n\nPSYKOLOGKONSULT AB\n\nPnr 11143\n\nStockholm, Norrlandsg 12. Tel\n08-10 96 45. Bankgiro 71-0872.\nPostgiro 403586\n\nVerksamhet: Förpacknings- o\nreklam-förprövningar samt personalurval\nAntal anställda: 4\nÅrsomsättning: 400 000\nAktiekapital: 5100\nVerkst dir: Uno Guttormsson\nEtableringsår: 1966.\n\nNORRBOTTENS FRYS AB\n\nPnr 953 00\n\nHaparanda, Ringv 74. Tel\n0922-11311. Bankgiro 205-2637.\nPostgiro 486830-3. Telex 80423\nVerksamhet: Köper o fryser ner\nbär, fisk o renkött samt förädlar\nbär o fisk. Utför legoarbeten o\n-lagring i livsmedelsbranscher\n\nAntal anställda: 30\nÅrsomsättning: 12 000 000\nAktiekapital: 610 000\nVerkst dir: Gunnar Falk\nEtableringsår: 1964.\n\nAXIO BYGGNADS AB\n\nPnr 123 51\n\nFarsta, Nordmarksv 17. Tel\n08-93 04 10. Bankgiro 746-1296.\nPostgiro 602460-8\n\nVerksamhet: Byggnadsverksamhet\navseende främst industribyggnader\no anläggningsarbeten\nAntal anställda: 50\nÅrsomsättning: 5 000 000\nAktiekapital: 100 000\nVerkst dir: Harald Axiö\nEtableringsår: 1963.\n\nSVEA, MÖBELFABRIKEN\n\nPnr 280 20\n\nBjärnum, Box 44. Tel 0451-200 82.\n\nBankgiro 265-3483. Postgiro\n174049-7\n\nVerksamhet: Tillverkar möbler\nsåsom bäddsoffor o dagbäddar\nAntal anställda: 6\nÅrsomsättning: 400 000\nChefer: David Persson, W\nKristensson\n\nEtableringsår: 1944.\n\nTELAC, AB\n\nPnr 172 24\n\nSundbyberg 1, Box 141.\nEsplanaden 10. Tel 08-29 03 35. Postgiro\n680000. Telex 10698\nVerksamhet Importerar antenner,\nantennförstärkare, skivspelare,\nHI-Fi-förstärkare. Ljud- o\nakustikanläggningar. Säljer radiorör,\ntransistorer, komponenter för radio- o\nTV-service. Exporterar\nhögtalar-lådor. grammofonlådor o diverse\nelektroniska apparater. Installerar\nsvagströmsanläggningar\nVarunamn: Elac, Freitag, Kathrein,\nNewcord, Nogoton, Polytron, Telac,\nUniton\n\nAntal anställda: 30\nÅrsomsättning: 9 000000\nAktiekapital: 100 000\nVerkst dir: Lennart Carlsson\nFörsäljn-chef: Bo Litzën\nTekn chef: Ingvar Olsson\nService o installationer: Björn\nLindgren\n\nEtableringsår 1968\nGeneralagent för Newcord,\nDanmark, Elac o Kathrein, Wolfgang\nFreitag, Delektronik,\nVästtyskland, Polytrona AG, Uniton\nCom-merce, Schweiz.\n\nTELEFLEX SVENSKA AB\n\nPnr 195 01\n\nMärsta 1, Box 58. Bristag. Tel\n0760-11120. Bankgiro 627-4211.\nPostgiro 557383-7. Tga Teleflex.\nTelex 10966\n\nVerksamhet: Importerar o\ntillverkar marinreglage, fönsterreglage,\nreglage för flygplan, bilar,\nventilation o övrig industri\nVarunamn: Teleflex\nAntal anställda: 40\nAktiekapital: 540 000\nStyrelse: Adv Wilhelm Törsleff\n(ordf), H G Burrage, fru Rosa\nBeckman\n\nVerkst dir: K W Henrichsen\nEtableringsår 1957.\n\nAUDE, AB\n\nPnr 400 60\n\nGöteborg 6, Box 6079. Olskroksg\n18. Tel 031-19 41 15, 19 4125.\nBankgiro 420-0143. Postgiro\n49795-8\n\nVerksamhet: S äljer biltillbehör en\n\ngros\n\nAntal anställda: 5\nÅrsomsättning: 1500000\nAktiekapital: 35 000\nVerkst dir: Manne Fleischer\nEtableringsår: 1944.\n\nAUGUSTSSONS\nTANKTRAN-SPORT AB, BRÖDERNA\n\nPnr 260 73\n\nÖstra Ljungby, Box 43. Tel\n0435-212 30, 212 40. Postgiro 663643-5\nVerksamhet: Tankbiltransporter\nAvdelningskontor: Lund, Skördev 18.\nTel 046-12 16 17\nAntal anställda: 3\nÅrsomsättning: 290 000\nAktiekapital: 50 000\nVerkst din Akeriägare Ernst\nAugustsson\nEtableringsår: 1964.\n\nAUGUSTSSONS ÅKERI AB,\nBRÖDERNA\n\nPnr 260 73\n\nÖstra Ljungby, Box 43. Tel\n0435-212 30 , 212 40. Bankgiro 657-3240.\nPostgiro 123437-6\nVerksamhet: Akerirörelse. Även\ntransporter av flytande o\npulveriserade varor\nAntal anställda: 27\nÅrsomsättning: 3 000 000\nAktiekapital: 100 000\nVerkst dir: Ivar Augustsson\nEtableringsår: 1947.\n\nAUGUSTSSONS\nBYGG-NADSAB, ALFR\n\nPnr 511 00\n\nKinna, Elinshöjd. Tel 0320-102 38,\n124 18. Bankgiro 54-6118. Postgiro\n321560\n\nVerksamhet: Hus- o\nindustribyggnader\n\nAntal anställda: 65\nÅrsomsättning: 6 000 000\nAktiekapital: 100000\nVerkst dir: Byggmäst Alfr\nAugustsson\n\nEtableringsår: 1925.\n\nAUKTIONS- &amp; FASTIGHETS.\nFIRMAN PETTERSSON &amp; SON AB\n\nPnr 57100\n\nNässjö, Bangårdsg 17. Tel\n0380-18030. Bankgiro 45-2994. Postgiro\n207877-2\n\nVerksamhet: Fastighetsförsäljning.\nAuktioner\n\nFilialer: 552 40 Jönköping, Kanalg\n2. Tel 036-1182 40\n\n575\t00 Eksjö, Västerlångg 12. Tel\n0381-12841\n\n595 00 Mjölby, Ekhamra. Tel\n0142-720 94\n\n576\t00 Sävsjö, Mossaryd. Tel\n0382-91029\n\n573 00 Tranås, Agatan 26. Tel\n0140-163 00\n\n598 00 Vimmerby, Storg 31. Tel\n0492-123 30\nAntal anställda: 17\nÅrsomsättning: 40 000 000\nAktiekapital: 50 000\nVerkst dir: Folke Pettersson\nKamrer: Ulf Sandwall, Birgit\nOrdrop\n\nEtableringsår: 1959.\n\nAURORA AB,\nNYSILVERFABRIKEN\n\nPnr 41140\n\nGöteborg, N Kustbaneg 19. Tel\n031-15 54 01, 15 54 03. Bankgiro\n50-7987. Postgiro 12333\nVerksamhet: Elektrogalvanisk\nfabrik\n\nAntal anställda: 20\nÅrsomsättning: 700 000\nAktiekapital: 200 000\nVerkst dir: Johan Hellsing\nEtableringsår: 1945.\n\nSVENSSON, AB RUNE\n\nPnr 596 00\n\nSkänninge, Stora Vallg 1. Box 143.\nTel 0142-410 25. Bankgiro\n34-6984. Postgiro 377955. Tga\nRun-sven. Telex 5598\nVerksamhet: Tillverkar camping- o\nhushållsartiklar\nAntal anställda: 100\nÅrsomsättning: 12000 000\nAktiekapital: 400 000\nVeikst dir: Rune Svensson\nEtableringsår 1953.\n\nEDM\n\nBankgiro 102-9545. Postgiro\n368651-6\n\nVerksamhet: Tillverkar sågade\nträvaror\n\nAntal anställda: 45\nÅrsomsättning: 5 000 000\nAktiekapital: 150000\nVerkst dir: Sven Olofsson\nEtableringsàr: 1953.\n\nEDAPLAST, AB\n\nPnr 203 11\n\nMalmö 4, Storg 9. Box 4013. Tel\n040-74385. Bankgiro 348-3146.\nPostgiro 431820. Tga Heidexag\nVerksamhet: Tillverkar o säljer\nteijp\n\nVarunamn: Edaplast-Tape\nAktiekapital: 25 000\nVerkst dir: K Heide\nEtableringsàr: 1952.\n\nE-DATA, EINAR EKLUNDS\nDATA AB\n\nPnr 632 21\n\nEskilstuna, Kungsg 5. Tel\n016-12 2160. Bankgiro 65-56 56.\nPostgiro 215160\n\nVerksamhet: Datatjänster o\nuppläggning av datasystem\nAntal anställda: 2\nÅrsomsättning: 100 000\nAktiekapital: 20 000\nStyrelse: Aukt revisor Einar Eklund\n(ordf), revisor Holger Lust (suppl)\nEtableringsàr 1969.\n\nSVENSKA GULF OIL AB\n\nPnr 17120\n\nSolna 1, Gulfhuset, Råsundav 166.\nFack. Tel 08-83 05 00. Telex\n10013. Tga Svenskagulf\nVerksamhet: Import o försäljning av\npetroleumprodukter\nAktiekapital: 6 000 000\nVerkst dir: Bengt G Fahlander\nEtableringsår: 1928.\n\nSVENSKA HANDELS, o\nINDUSTRI AB GÅN\n\nPnr 103 40\n\nStockholm 40, Kungsg 31-33. Fack.\nTel 08-2014 53. Tga Handelsindustri\nVerksamhet: Import o export\nAktiekapital: 5 000\nVerkst din Harry Englund\nEtableringsår: 1959.",
    "structured": {
        "1": {
            "company_name": "BUCHHOLZ, B",
            "activity": "Agenturaffär",
            "establishment_year": 1884
        },
        "2": {
            "company_name": "PSYKOLOGKONSULT AB",
            "address": "Norrlandsg 12, Stockholm",
            "phone_number": "08-10 96 45",
            "bank_details": {
                "bankgiro": "71-0872",
                "postgiro": "403586"
            },
            "activity": "Förpacknings- o reklam-förprövningar samt personalurval",
            "employees": 4,
            "annual_turnover": 400000,
            "capital": 5100,
            "key_personnel": [
                {
                    "name": "Uno Guttormsson",
                    "position": "Verkst dir"
                }
            ],
            "establishment_year": 1966
        },
        "3": {
            "company_name": "NORRBOTTENS FRYS AB",
            "address": "Ringv 74, Haparanda",
            "phone_number": "0922-11311",
            "bank_details": {
                "bankgiro": "205-2637",
                "postgiro": "486830-3"
            },
            "activity": "Köper o fryser ner bär, fisk o renkött samt förädlar bär o fisk. Utför legoarbeten o -lagring i livsmedelsbranscher",
            "employees": 30,
            "annual_turnover": 12000000,
            "capital": 610000,
            "key_personnel": [
                {
                    "name": "Gunnar Falk",
                    "position": "Verkst dir"
                }
            ],
            "establishment_year": 1964
        },
        "4": {
            "company_name": "AXIO BYGGNADS AB",
            "address": "Nordmarksv 17, Farsta",
            "phone_number": "08-93 04 10",
            "bank_details": {
                "bankgiro": "746-1296",
                "postgiro": "602460-8"
            },
            "activity": "Byggnadsverksamhet avseende främst industribyggnader o anläggningsarbeten",
            "employees": 50,
            "annual_turnover": 5000000,
            "capital": 100000,
            "key_personnel": [
                {
                    "name": "Harald Axiö",
                    "position": "Verkst dir"
                }
            ],
            "establishment_year": 1963
        },
        "5": {
            "company_name": "SVEA, MÖBELFABRIKEN",
            "address": "Box 44, Bjärnum",
            "phone_number": "0451-200 82",
            "bank_details": {
                "bankgiro": "265-3483",
                "postgiro": "174049-7"
            },
            "activity": "Tillverkar möbler såsom bäddsoffor o dagbäddar",
            "employees": 6,
            "annual_turnover": 400000,
            "establishment_year": 1944
        },
        "6": {
            "company_name": "TELAC, AB",
            "address": "Box 141, Sundbyberg 1",
            "phone_number": "08-29 03 35",
            "bank_details": {
                "postgiro": "680000"
            },
            "activity": "Importerar antenner, antennförstärkare, skivspelare, HI-Fi-förstärkare. Ljud- o akustikanläggningar",
            "employees": 30,
            "annual_turnover": 9000000,
            "capital": 100000,
            "key_personnel": [
                {
                    "name": "Lennart Carlsson",
                    "position": "Verkst dir"
                },
                {
                    "name": "Bo Litzën",
                    "position": "Försäljn-chef"
                },
                {
                    "name": "Ingvar Olsson",
                    "position": "Tekn chef"
                },
                {
                    "name": "Björn Lindgren",
                    "position": "Service o installationer"
                }
            ],
            "establishment_year": 1968
        },
        "7": {
            "company_name": "TELEFLEX SVENSKA AB",
            "address": "Box 58, Märsta 1, Bristag",
            "phone_number": "0760-11120",
            "bank_details": {
                "bankgiro": "627-4211",
                "postgiro": "557383-7"
            },
            "activity": "Importerar o tillverkar marinreglage, fönsterreglage, reglage för flygplan, bilar, ventilation o övrig industri",
            "employees": 40,
            "capital": 540000,
            "key_personnel": [
                {
                    "name": "Adv Wilhelm Törsleff",
                    "position": "Styrelse"
                },
                {
                    "name": "H G Burrage",
                    "position": "Styrelse"
                },
                {
                    "name": "fru Rosa Beckman",
                    "position": "Styrelse"
                },
                {
                    "name": "K W Henrichsen",
                    "position": "Verkst dir"
                }
            ],
            "establishment_year": 1957
        },
        "8": {
            "company_name": "AUDE, AB",
            "address": "Box 6079, Göteborg 6, Olskroksg 18",
            "phone_number": "031-19 41 15",
            "bank_details": {
                "bankgiro": "420-0143",
                "postgiro": "49795-8"
            },
            "activity": "S äljer biltillbehör en gros",
            "employees": 5,
            "annual_turnover": 1500000,
            "capital": 35000,
            "key_personnel": [
                {
                    "name": "Manne Fleischer",
                    "position": "Verkst dir"
                }
            ],
            "establishment_year": 1944
        },
        "9": {
            "company_name": "AUGUSTSSONS TANKTRANSPORT AB, BRÖDERNA",
            "address": "Box 43, Östra Ljungby",
            "phone_number": "0435-212 30",
            "bank_details": {
                "postgiro": "663643-5"
            },
            "activity": "Tankbiltransporter",
            "employees": 3,
            "annual_turnover": 290000,
            "capital": 50000,
            "key_personnel": [
                {
                    "name": "Akeriägare Ernst Augustsson",
                    "position": "Verkst din"
                }
            ],
            "establishment_year": 1964
        },
        "10": {
            "company_name": "AUGUSTSSONS ÅKERI AB, BRÖDERNA",
            "address": "Box 43, Östra Ljungby",
            "phone_number": "0435-212 30",
            "bank_details": {
                "bankgiro": "657-3240",
                "postgiro": "123437-6"
            },
            "activity": "Akerirörelse. Även transporter av flytande o pulveriserade varor",
            "employees": 27,
            "annual_turnover": 3000000,
            "capital": 100000,
            "key_personnel": [
                {
                    "name": "Ivar Augustsson",
                    "position": "Verkst dir"
                }
            ],
            "establishment_year": 1947
        },
        "11": {
            "company_name": "AUGUSTSSONS BYGGNADSAB, ALFR",
            "address": "Elinshöjd, Kinna",
            "phone_number": "0320-102 38",
            "bank_details": {
                "bankgiro": "54-6118",
                "postgiro": "321560"
            },
            "activity": "Hus- o industribyggnader",
            "employees": 65,
            "annual_turnover": 6000000,
            "capital": 100000,
            "key_personnel": [
                {
                    "name": "Byggmäst Alfr Augustsson",
                    "position": "Verkst dir"
                }
            ],
            "establishment_year": 1925
        },
        "12": {
            "company_name": "AUKTIONS- & FASTIGHETS. FIRMAN PETTERSSON & SON AB",
            "address": "Bangårdsg 17, Nässjö",
            "phone_number": "0380-18030",
            "bank_details": {
                "bankgiro": "45-2994",
                "postgiro": "207877-2"
            },
            "activity": "Fastighetsförsäljning. Auktioner",
            "branches": [
                "55240 Jönköping, Kanalg 2",
                "57500 Eksjö, Västerlångg 12",
                "59500 Mjölby, Ekhamra",
                "57600 Sävsjö, Mossaryd",
                "57300 Tranås, Agatan 26",
                "59800 Vimmerby, Storg 31"
            ],
            "employees": 17,
            "annual_turnover": 40000000,
            "capital": 50000,
            "key_personnel": [
                {
                    "name": "Folke Pettersson",
                    "position": "Verkst dir"
                },
                {
                    "name": "Ulf Sandwall",
                    "position": "Kamrer"
                },
                {
                    "name": "Birgit Ordrop",
                    "position": "Kamrer"
                }
            ],
            "establishment_year": 1959
        },
        "13": {
            "company_name": "AURORA AB, NYSILVERFABRIKEN",
            "address": "N Kustbaneg 19, Göteborg",
            "phone_number": "031-15 54 01",
            "bank_details": {
                "bankgiro": "50-7987",
                "postgiro": "12333"
            },
            "activity": "Elektrogalvanisk fabrik",
            "employees": 20,
            "annual_turnover": 700000,
            "capital": 200000,
            "key_personnel": [
                {
                    "name": "Johan Hellsing",
                    "position": "Verkst dir"
                }
            ],
            "establishment_year": 1945
        },
        "14": {
            "company_name": "SVENSSON, AB RUNE",
            "address": "Stora Vallg 1, Skänninge",
            "phone_number": "0142-410 25",
            "bank_details": {
                "bankgiro": "34-6984",
                "postgiro": "377955"
            },
            "activity": "Tillverkar camping- o hushållsartiklar",
            "employees": 100,
            "annual_turnover": 12000000,
            "capital": 400000,
            "key_personnel": [
                {
                    "name": "Rune Svensson",
                    "position": "Verkst dir"
                }
            ],
            "establishment_year": 1953
        },
        "15": {
            "company_name": "EDM",
            "bank_details": {
                "bankgiro": "102-9545",
                "postgiro": "368651-6"
            },
            "activity": "Tillverkar sågade trävaror",
            "employees": 45,
            "annual_turnover": 5000000,
            "capital": 150000,
            "key_personnel": [
                {
                    "name": "Sven Olofsson",
                    "position": "Verkst dir"
                }
            ],
            "establishment_year": 1953
        },
        "16": {
            "company_name": "EDAPLAST, AB",
            "address": "Storg 9, Malmö 4, Box 4013",
            "phone_number": "040-74385",
            "bank_details": {
                "bankgiro": "348-3146",
                "postgiro": "431820"
            },
            "activity": "Tillverkar o säljer teijp",
            "varunamn": "Edaplast-Tape",
            "capital": 25000,
            "key_personnel": [
                {
                    "name": "K Heide",
                    "position": "Verkst dir"
                }
            ],
            "establishment_year": 1952
        },
        "17": {
            "company_name": "E-DATA, EINAR EKLUNDS DATA AB",
            "address": "Kungsg 5, Eskilstuna",
            "phone_number": "016-12 2160",
            "bank_details": {
                "bankgiro": "65-56 56",
                "postgiro": "215160"
            },
            "activity": "Datatjänster o uppläggning av datasystem",
            "employees": 2,
            "annual_turnover": 100000,
            "capital": 20000,
            "key_personnel": [
                {
                    "name": "Einar Eklund",
                    "position": "Styrelse (ordf)"
                },
                {
                    "name": "Holger Lust",
                    "position": "Styrelse (suppl)"
                }
            ],
            "establishment_year": 1969
        },
        "18": {
            "company_name": "SVENSKA GULF OIL AB",
            "address": "Gulfhuset, Råsundav 166, Solna 1",
            "phone_number": "08-83 05 00",
            "bank_details": {
                "telex": "10013"
            },
            "activity": "Import o försäljning av petroleumprodukter",
            "capital": 6000000,
            "key_personnel": [
                {
                    "name": "Bengt G Fahlander",
                    "position": "Verkst dir"
                }
            ],
            "establishment_year": 1928
        },
        "19": {
            "company_name": "SVENSKA HANDELS, o INDUSTRI AB GÅN",
            "address": "Kungsg 31-33, Stockholm 40",
            "phone_number": "08-2014 53",
            "activity": "Import o export",
            "capital": 5000,
            "key_personnel": [
                {
                    "name": "Harry Englund",
                    "position": "Verkst dir"
                }
            ],
            "establishment_year": 1959
        }
    }
}