{
    "original": "GRANSHOLMS AB\n\nPnr 360 32\n\nGemla. Tel 0470-670 80. Tga\nGransholm, Växjö\n\nVerksamhet: Finpappersbruk,\nskriv- o skolmaterieltillverkning\nVerkst dir: Folke Ljungdahl\nEtableringsår: 1901\nDotterbolag till AB Sture\nLjungdahl, Nybro\n\nGRANSTRAND AB, BRÖDERNA\n\nPnr 560 10\n\nSkillingaryd, Box 79. Tel\n0370-706 60. Bankgiro 14-1313. Postgiro\n493956\n\nVerksamhet: Tillverkar o säljer\nfåtöljer o sittsoffor\n\nAntal anstäUda: 85\nÅrsomsättning: 7 000 000\nChef: Fabr K-E Granstrand\nEtableringsår: 1944.\n\nGRANSTRÖM, BYGGNADS AB\nEVERT\n\nPnr 851 04\n\nSundsvaU 1, Thuleg 10. Box 236.\nTel 060-15 44 50. Bankgiro\n180-3030. Postgiro 348599-2\nVerksamhet: Ny- o ombyggnader av\nindustri-, hus- o vattenbyggnader\nAntal anstäUda: 85\nÅrsomsättning: 12 000 000\nAktiekapital: 100 000\nVerkst dir: Byggn-ing Evert\nGranström\n\nEtableringsår: 1954.\n\nLANGSTEN ANNONSBYRÅ AB\n\nPnr 17120\n\nSolna 1, Nybodag 1. Fack. Tel\n08-82 0260. Bankgiro 33-0140.\nPostgiro 650064. Tga Langstenad.\nTelex 10646 LANGSAD S\nVerksamhet: Auktoriserad\nreklambyrå\n\nAntal anställda: 31\nEtableringsår: 1960.\n\nLAN I LARSSON &amp; NILSSON,\nAB\n\nPnr 214 44\n\nMalmö S, Kopparbergsg 10. Tel\n040-803 50. Bankgiro 64-4048.\nPostgiro 148325. Tga Lani\nVerksamhet: Tillverkar madrasser,\nsängar o möbler (vilmöbler)\nAntal anställda: 108\nÅrsomsättning: 7 000 000\n\n366\n\nAktiekapital: 200 000\nVerkst dir: Ark Olle Jangård\nEtableringsår: 1908.\n\nBER\n\nBERGGREN &amp; CO,\nINGENIÖRSFIRMA\n\nPnr 16146\n\nBromma, Rörläggarv 30. Tel\n08-2619 89. Bankgiro 16-6079.\nPostgiro 452381-7\n\nVerksamhet: Reparerar elektr o\nmek instrument o apparater\nAntal anställda: 5\nÅrsomsättning: 150 000\nÄgare o chef: Ing Thorleif Berggren\nEtableringsår: 1947.\n\nBERGGRENS\n\nMEK VERKSTAD EFTR\n\nBRÖDERNA BLOMQVIST, A\n\nPnr 703 64\n\nÖrebro, N Sofiag 11. Tel\n019-110110. Bankgiro 81-7316.\nPostgiro 469415-4\n\nVerksamhet: Utför svarvning,\nfräsning o maskinreparationer\nAntal anställda: 3\nÅrsomsättning: 170000\nChef: Sigvard Blomqvist\nEtableringsår: 1954.\n\nJEPPSSON, AB SVEN\n\nPnr 292 00\n\nKarlshamn, Box 66. Sölvesborgsv 1.\nTel 0454-160 00. Bankgiro\n862-1443. Postgiro 137139-2\nVerksamhet: Bilförsäljning,\nbilverkstäder o biluthyrning\nAntal anställda: 220\nÅrsomsättning: 30 000 000\nAktiekapital: 500 000\nVerkst dir: Sven Jepson\nEtableringsår: 1937.\n\nHANSA-NORDIC BOLAGEN\n\nPnr 42122\n\nVästra Frölunda 1, Box 156.\nLer-göksg 12. Tel 031-45 01 80.\nBankgiro 514-8044. Postgiro 49060-7.\nTga Hansanordic. Telex 2558\nVeiksamhet: Biltillbehör,\nelektronik, industridetaljer,\npresentartiklar, cigarettändare, sport o\nbåttillbehör\n\nAntal anställda: 49\nÅrsomsättning: 25 000 0 00\nAktiekapital: 5 000\nVeikst dir: Gunnar Wennerström\nEtableringsår: 1951.\n\nGALCO, AB\n\nPnr 18121\n\nLidingö 1, Box 118. Vasav 76. Tel\n08-767 03 80. Bankgiro 729-2105.\nPostgiro 871-4. Tga Galco.\nTelex 10807\n\nVerksamhet: Tillverkar brevpärmar\no hålslag Agrippa samt\nkortsystempärmar Viscard, diverse\nstålpres-sade detaljer såsom bildetaljer o\nreningsdysor.\n\nSäljer som agenter elektr\nisolationsmaterial, silikongummiartik-lar, glimmer o mikanit, glasväv,\nträlaminat, vulkanfiber, presspan,\nasbestvaror, laminat för\nmönsterkort, kablar o kopplingstråd,\nstansade detaljer, isolerlacker o\ngjut-hartser för elektronik,\nmikrovågs-absorberande material\nVarunamn: Agrippa, Conus, Master,\nSigma, Triplex\nAntal anställda: 105\nÅrsomsättning: 13 000 000\nAktiekapital: 300 000\nVerkst dir. Sven Winqvist\nEtableringsår: 1923.\n\nSVENSKA MURBRUKS AB\n\nPnr 11135\n\nStockholm, Kungsg 34. Tel\n08-22 33 60. Bankgiro 476-8909.\nPostgiro 52115-3. Tga Svenska\nMurbruksbolaget\n\nVerksamhet: Tillverkar o säljer\nmur- o putsbruk\nAntal anställda: 14\nÅrsomsättning: 1800 000\nAktiekapital: 600 000\nStyrelse: Bankdir Gösta Olson\n(ordf), dir Victor Hasselblad, dir\nArne Henrikson, pol mag Lennart\nHenrikson, lantmäst Magnus Toll\nVerkst dir. Arne Henrikson\nTekn chef: Disp Lars Löfstedt\nKontorschef: Kamrer Erie Clamme\nFörsäljn-chef: Karl-Ivar Granqvist\nEtableringsår: 1919.\n\nSVENSKA MURCO\nPETROLEUM AB\n\nPnr 104 30\n\nStockholm 45, Sveav45.Box 45094.\nTel 08-24 87 60. Bankgiro\n195-6556. Postgiro 621200-5. Tga\nMur-copetroleum\n\nVerksamhet: Bensin o bensinstar\ntioner\n\nVarunamn: Murco\nAktiekapital: 20 900 000\nVerkst dir: Ebbe Hammar\nEtableringsår. 1961.\n\nSVENSKA MÄTT- &amp;\nTUMSTOCKFABRIKEN\n\nPnr 510 35\n\nBollebygd, Hultafors. Tel\n033-950 03, 950 95. Bankgiro 533-6086.\nPostgiro 8163-8. Tga Måttfabriken\nVerksamhet: Tillverkar måttstockar\no längdmått av trä,\navvägningsstänger, skolmateriel såsom\nlinjaler, vinkelhakar, gradskivor,\ntavel-linjaler mm\nAntal anställda: 65\nÅrsomsättning: 4 000 000\nVerkst din Disp Hilmer Kollén\nEtableringsår: 1883\nÄgare: Hultafors AB, Hultafors.\n\nSVENSKA MÄSSAN GOTEBORG\n\nPnr 412 51\n\nGöteborg, Orgrytev 4. Tel\n031-2000 00. Bankgiro 51-0300.\nPost-giro 12484-2. Tga Mässan.\nTelex 20600 MAESSAN S\n\nArrangerar\nInternationella Svenska Mässan\n\nsamt\n\nElf ack Sjukvård &amp; HälsV\n\nMaritime Inredning\nBygge - Bostad - Miljö mfl\n\nBeskyddare H M Gustaf VI Adolf\nStyrelse: Landshövd Per Nyström\n(ordf), l:e v ordf civiling C R\nBlomstedt, 2:e v ordf dir Sigurd\nLjung-crantz\n\nVeikst dir: Erie Ehrengren\nEtableringsår: 1918.\n\nMISS MARY OF SWEDEN AB\n\nPnr 500 04\n\nBorås 4, Box 44038. Björkhemsg\n38. Tel 033-10 0165. Bankgiro\n646-3319. Postgiro 671110-5\nVerksamhet: Tillverkar o\nexporterar behå o korsetter\nAntal anställda: 185\nÅrsomsättning: 15 000 000\nAktiekapital: 5 000\nVerkst dir: Ingemar Rydström\nEtableringsår: 1965.\n\nDALA BILCENTRUM AB\n\nPnr 79101\n\nFalun 1, Tegelv 2. Box 255. Tel\n023-192 20. Bankgiro 464-2898.\nPostgiro 8315-4\n\nVerksamhet: Auktoriserad\nåterförsäljare för SAAB/ANA\nAntal anställda: 47\nÅrsomsättning: 17 600 000\nAktiekapital: 400 000\nVerkst dir: Karl-Erik Andersson\nEtableringsår: 1961.\n\nDALA GUMMI AB\n\nPnr 79101\n\nFalun 1, Ing arvet. Box 235. Tel\n023-182 70. Bankgiro 79-2712.\nPostgiro 29512\n\nVerksamhet Regummerar o säljer\ndäck o slangar i parti o detalj\nAntal anställda: 50\nVerkst dir: Eine Sjölund\nEtableringsår: 1926.\n\nÅHRLINS BIL AB\n\nPnr 80104\n\nGävle 1, Box 232. Byggmästarg\n1-3. Tel 026-1156 80. Bankgiro\n603-5992. Postgiro 291289-7\nVerksamhet: Bilförsäljning,\nverkstad o lagerförsäljning\nAntal anställda: 17\nÅrsomsättning: 5 000 000\nAktiekapital: 185 000\nVerkst dir. Ingemar Lindqvist\nEtableringsår: 1946.",
    "structured": {
        "1": {
            "company_name": "GRANSHOLMS AB",
            "pnr": "360 32",
            "address": "Gemla. Tel 0470-670 80. Tga Gransholm, Växjö",
            "activity": "Finpappersbruk, skriv- och skolmaterieltillverkning",
            "establishment_year": 1901
        },
        "2": {
            "company_name": "GRANSTRAND AB, BRÖDERNA",
            "pnr": "560 10",
            "address": "Skillingaryd, Box 79. Tel 0370-706 60",
            "bank_details": {
                "bankgiro": "14-1313",
                "postgiro": "493956"
            },
            "activity": "Tillverkar och säljer fåtöljer och sittsoffor",
            "employees": 85,
            "annual_turnover": 7000000,
            "capital": null,
            "establishment_year": 1944
        },
        "3": {
            "company_name": "GRANSTRÖM, BYGGNADS AB EVERT",
            "pnr": "851 04",
            "address": "SundsvaU 1, Thuleg 10. Box 236. Tel 060-15 44 50",
            "bank_details": {
                "bankgiro": "180-3030",
                "postgiro": "348599-2"
            },
            "activity": "Ny- och ombyggnader av industri-, hus- och vattenbyggnader",
            "employees": 85,
            "annual_turnover": 12000000,
            "annual_production_value": null,
            "capital": 100000,
            "key_personnel": [
                {
                    "name": "Byggn-ing Evert Granström",
                    "position": "Verkst dir"
                }
            ],
            "establishment_year": 1954
        },
        "4": {
            "company_name": "LANGSTEN ANNONSBYRÅ AB",
            "pnr": "17120",
            "address": "Solna 1, Nybodag 1. Fack. Tel 08-82 0260",
            "bank_details": {
                "bankgiro": "33-0140",
                "postgiro": "650064"
            },
            "activity": "Auktoriserad reklambyrå",
            "employees": 31,
            "establishment_year": 1960
        },
        "5": {
            "company_name": "LAN I LARSSON & NILSSON, AB",
            "pnr": "214 44",
            "address": "Malmö S, Kopparbergsg 10. Tel 040-803 50",
            "bank_details": {
                "bankgiro": "64-4048",
                "postgiro": "148325"
            },
            "activity": "Tillverkar madrasser, sängar och möbler (vilmöbler)",
            "employees": 108,
            "annual_turnover": 7000000,
            "capital": 200000,
            "key_personnel": [
                {
                    "name": "Ark Olle Jangård",
                    "position": "Verkst dir"
                }
            ],
            "establishment_year": 1908
        },
        "6": {
            "company_name": "BERGGREN & CO, INGENIÖRSFIRMA",
            "pnr": "16146",
            "address": "Bromma, Rörläggarv 30. Tel 08-2619 89",
            "bank_details": {
                "bankgiro": "16-6079",
                "postgiro": "452381-7"
            },
            "activity": "Reparerar elektriska och mekaniska instrument och apparater",
            "employees": 5,
            "annual_turnover": 150000,
            "key_personnel": [
                {
                    "name": "Ing Thorleif Berggren",
                    "position": "Ägare och chef"
                }
            ],
            "establishment_year": 1947
        },
        "7": {
            "company_name": "BERGGRENS MEK VERKSTAD EFTR BRÖDERNA BLOMQVIST, A",
            "pnr": "703 64",
            "address": "Örebro, N Sofiag 11. Tel 019-110110",
            "bank_details": {
                "bankgiro": "81-7316",
                "postgiro": "469415-4"
            },
            "activity": "Utför svarvning, fräsning och maskinreparationer",
            "employees": 3,
            "annual_turnover": 170000,
            "key_personnel": [
                {
                    "name": "Sigvard Blomqvist",
                    "position": "Chef"
                }
            ],
            "establishment_year": 1954
        },
        "8": {
            "company_name": "JEPPSSON, AB SVEN",
            "pnr": "292 00",
            "address": "Karlshamn, Box 66. Sölvesborgsv 1. Tel 0454-160 00",
            "bank_details": {
                "bankgiro": "862-1443",
                "postgiro": "137139-2"
            },
            "activity": "Bilförsäljning, bilverkstäder och biluthyrning",
            "employees": 220,
            "annual_turnover": 30000000,
            "capital": 500000,
            "key_personnel": [
                {
                    "name": "Sven Jepson",
                    "position": "Verkst dir"
                }
            ],
            "establishment_year": 1937
        },
        "9": {
            "company_name": "HANSA-NORDIC BOLAGEN",
            "pnr": "42122",
            "address": "Västra Frölunda 1, Box 156. Ler-göksg 12. Tel 031-45 01 80",
            "bank_details": {
                "bankgiro": "514-8044",
                "postgiro": "49060-7"
            },
            "activity": "Biltillbehör, elektronik, industridetaljer, presentartiklar, cigarettändare, sport och båttillbehör",
            "employees": 49,
            "annual_turnover": 25000000,
            "capital": 5000,
            "key_personnel": [
                {
                    "name": "Gunnar Wennerström",
                    "position": "Verkst dir"
                }
            ],
            "establishment_year": 1951
        },
        "10": {
            "company_name": "GALCO, AB",
            "pnr": "18121",
            "address": "Lidingö 1, Box 118. Vasav 76. Tel 08-767 03 80",
            "bank_details": {
                "bankgiro": "729-2105",
                "postgiro": "871-4"
            },
            "activity": "Tillverkar brevpärmar o hålslag Agrippa samt kortsystempärmar Viscard, diverse stålpressade detaljer såsom bildetaljer och rengöringsdysor",
            "employees": 105,
            "annual_turnover": 13000000,
            "capital": 300000,
            "key_personnel": [
                {
                    "name": "Sven Winqvist",
                    "position": "Verkst dir"
                }
            ],
            "establishment_year": 1923
        },
        "11": {
            "company_name": "SVENSKA MURBRUKS AB",
            "pnr": "11135",
            "address": "Stockholm, Kungsg 34. Tel 08-22 33 60",
            "bank_details": {
                "bankgiro": "476-8909",
                "postgiro": "52115-3"
            },
            "activity": "Tillverkar o säljer mur- o putsbruk",
            "employees": 14,
            "annual_turnover": 1800000,
            "capital": 600000,
            "key_personnel": [
                {
                    "name": "Arne Henrikson",
                    "position": "Verkst dir"
                },
                {
                    "name": "Lars Löfstedt",
                    "position": "Tekn chef"
                },
                {
                    "name": "Erie Clamme",
                    "position": "Kontorschef"
                }
            ],
            "establishment_year": 1919
        },
        "12": {
            "company_name": "SVENSKA MURCO PETROLEUM AB",
            "pnr": "104 30",
            "address": "Stockholm 45, Sveav45. Box 45094. Tel 08-24 87 60",
            "bank_details": {
                "bankgiro": "195-6556",
                "postgiro": "621200-5"
            },
            "activity": "Bensin och bensinstationer",
            "employees": null,
            "annual_turnover": null,
            "capital": 20900000,
            "key_personnel": [
                {
                    "name": "Ebbe Hammar",
                    "position": "Verkst dir"
                }
            ],
            "establishment_year": 1961
        },
        "13": {
            "company_name": "SVENSKA MÄTT- & TUMSTOCKFABRIKEN",
            "pnr": "510 35",
            "address": "Bollebygd, Hultafors. Tel 033-950 03, 950 95",
            "bank_details": {
                "bankgiro": "533-6086",
                "postgiro": "8163-8"
            },
            "activity": "Tillverkar måttstockar och längdmått av trä, avvägningsstänger, skolmateriel såsom linjaler, vinkelhakar, gradskivor, tavelinjaler mm",
            "employees": 65,
            "annual_turnover": 4000000,
            "key_personnel": [
                {
                    "name": "Hilmer Kollén",
                    "position": "Verkst din Disp"
                }
            ],
            "establishment_year": 1883
        },
        "14": {
            "company_name": "SVENSKA MÄSSAN GOTEBORG",
            "pnr": "412 51",
            "address": "Göteborg, Orgrytev 4. Tel 031-2000 00",
            "bank_details": {
                "bankgiro": "51-0300",
                "postgiro": "12484-2"
            },
            "activity": "Arrangerar Internationella Svenska Mässan samt Elf ack Sjukvård & HälsV Maritime Inredning Bygge - Bostad - Miljö mfl",
            "employees": null,
            "annual_turnover": null,
            "capital": null,
            "key_personnel": [
                {
                    "name": "Erie Ehrengren",
                    "position": "Veikst dir"
                }
            ],
            "establishment_year": 1918
        },
        "15": {
            "company_name": "MISS MARY OF SWEDEN AB",
            "pnr": "500 04",
            "address": "Borås 4, Box 44038. Björkhemsg 38. Tel 033-10 0165",
            "bank_details": {
                "bankgiro": "646-3319",
                "postgiro": "671110-5"
            },
            "activity": "Tillverkar och exporterar behåar och korsetter",
            "employees": 185,
            "annual_turnover": 15000000,
            "capital": 5000,
            "key_personnel": [
                {
                    "name": "Ingemar Rydström",
                    "position": "Verkst dir"
                }
            ],
            "establishment_year": 1965
        },
        "16": {
            "company_name": "DALA BILCENTRUM AB",
            "pnr": "79101",
            "address": "Falun 1, Tegelv 2. Box 255. Tel 023-192 20",
            "bank_details": {
                "bankgiro": "464-2898",
                "postgiro": "8315-4"
            },
            "activity": "Auktoriserad återförsäljare för SAAB/ANA",
            "employees": 47,
            "annual_turnover": 17600000,
            "capital": 400000,
            "key_personnel": [
                {
                    "name": "Karl-Erik Andersson",
                    "position": "Verkst dir"
                }
            ],
            "establishment_year": 1961
        },
        "17": {
            "company_name": "DALA GUMMI AB",
            "pnr": "79101",
            "address": "Falun 1, Ingarvet. Box 235. Tel 023-182 70",
            "bank_details": {
                "bankgiro": "79-2712",
                "postgiro": "29512"
            },
            "activity": "Regummerar och säljer däck och slangar i parti och detalj",
            "employees": 50,
            "annual_turnover": null,
            "capital": null,
            "key_personnel": [
                {
                    "name": "Eine Sjölund",
                    "position": "Verkst dir"
                }
            ],
            "establishment_year": 1926
        },
        "18": {
            "company_name": "ÅHRLINS BIL AB",
            "pnr": "80104",
            "address": "Gävle 1, Box 232. Byggmästarg 1-3. Tel 026-1156 80",
            "bank_details": {
                "bankgiro": "603-5992",
                "postgiro": "291289-7"
            },
            "activity": "Bilförsäljning, verkstad och lagerförsäljning",
            "employees": 17,
            "annual_turnover": 5000000,
            "capital": 185000,
            "key_personnel": [
                {
                    "name": "Ingemar Lindqvist",
                    "position": "Verkst dir"
                }
            ],
            "establishment_year": 1946
        }
    }
}