{
    "original": "VOLKSWAGEN I\nSTOCKHOLM AB\n\nPnr 102 20\n\nStockholm 12, Lindhagensplan.\nFack. Tel 08-22 76 60. Bankgiro\n167-8200. Postgiro 59002-6. Tga\nStockholmsvewe\n\nVerksamhet: Försäljning o service\nav Volkswagen o Porsche\nAntal anställda: 800\nAktiekapital: 6 000 000\nVerkst dir: Torbjörn Ek\nEtableringsår. 1954.\n\nWOLLSJü\nTOFFELFABRIK, AB\n\nPnr 222 31\n\nLund, Trastv 10. Tel 046-115168.\nBankgiro 873-0061. Postgiro\n71815-5\n\nVerksamhet: Tillverkar\nträtoffel-bottnar\n\nAktiekapital: 270 000\nVerkst dir: Owe Nilsson\nEtableringsår: 1922.\n\nSVENSKA AB IVERS LEE\n\nPnr 22101\n\nLund 1, Pack. Tel 046-1240 10.\nTga Saniseal. Telex 32207\nVerksamhet: Kontraktpaketering\nAntal anställda: 240\nÅrsomsättning: 20 000 000\nAktiekapital: 100 000\nVerkst dir: Gunnar Brime\nEtableringsår: 1948.\n\nELEKTROVERKEN, AB\n\nPnr 801 02\n\nGävle 1, Box 77. Akarg 71. Tel\n026-1154 50. Postgiro 509640-9.\nTga Elektro. Telex 81102\nVerksamhet: Tillverkar\nlågspän-ningsställverk, automatikutrustningar, lågspänningsbrytare,\nmotorskydd, bansignalmateriel\n.Antal anställda: 185\nÅrsomsättning: 14000 000\nAktiekapital: 5 000\nVerkst dir: Ingemar Norlindh\nPlatschef: Ing Sune Lorentzon\nEtableringsår: 1948\nDotterbolag till Elektriska AB\nAEG, Stockholm.\n\nELEKTRO-VICI\nAKTIEBOLAG\n\nPnr 104 25\n\nStockholm 30, Nordenflycht^ 62.\nBox 30010. Tel 08-53 36 00,\n54 2 3 95. Bankgiro 73-3816.\nPostgiro 356358. Tga Viciproducts\nVerksamhet Elektromekanisk\nverkstad\n\nVarunamn: Vici\n\nAntal anställda: 15\n\nÅrsomsättning: 2 000 000\n\nAktiekapital: 75 000\n\nVerkst dir: Bruksdisp L Degefors.\n\nELEMA-SCHONANDER AB\n\nPnr 17195\n\nSolna, Industriv 23. Tel 08-83 40 00.\nBankgiro726-1761. Postgiro 3613-7.\nTga Elema. Telex 19958 ELEMA S\nVerksamhet: Röntgen-,\nelektrome-dicin o dentalapparater\nAntal anställda: 1 400\nAktiekapital: 15 000 000\nVerkst din Dr B Rudewald\nEtableringsår: 1917.\n\nELEMENTHUS, AB\n\nIngår i Cementakoncernen\nPnr 780 40\n\nMockfjärd. Tel 0241-206 00.\nBankgiro 560-5860, 799-8024. Postgiro\n356919-1. Telex 84024\nVerksamhet; Färdigmonterade\nvillor i trä. Export till Västtyskland\nAntal anställda: 850\nÅrsomsättning: 90 000 000\nAktiekapital: 10 000 000\nVerkst dir: Civilekonom Carl-Axel\nRönnbo\n\nEtableringsår: 1949.\n\nFLOBY SILKETRIKA, AB\n\nPnr 520 40\n\nFloby, Box 7. Tel 0515-40080.\nBankgiro 542-1151. Postgiro\n93518-9\n\nVerksamhet: Tillverkar barn-,\ndam- o herrunderkläder, pyjamas\nAntal anställda: 30\nÅrsomsättning: 1400000\nAktiekapital: 96000\nVerkst dir: Valentin Johansson\nEtableringsår: 1930.\n\nFLOBY SÄG &amp;\nTRA-VARUAFFÄR, AB\n\nPnr 52040\n\nFloby. Tel 0515-403 40. Postgiro\n269562-5\n\nVerksamhet: Säljer\növerskotts-material från försvaret\nAntal anställda: 3\nÅrsomsättning: 125 000\nAktiekapital: 100 000\nVerkst din Olle Gustavsson\nEtableringsår: 1952.\n\nekesioo, ab karl\n\nPnr 16110\n\nBromma 10, Smält v 5-7,\nBällsta-hamnen. Fack. Tel 08-28 9200.\nTelex 1817. Tga Ekab\n\nVerksamhet: Partihandel med\nträvaror, snickerier o byggmaterial\nAntal anställda: 57\nÅrsomsättning: 16 700 000\nAktiekapital: 500 000\nVerkst dir: Jägmäst Harry Ekesiöö\nEtableringsår: 1922.\n\nCELER, AB\n\nPnr 104 60\n\nStockholm 20, Hammarby Fabriksv\n53. Tel 08-44 96 20. Bankgiro\n330-1876. Postgiro 854-0. Tga\nCele-ritas. Telex 10061\nVerksamhet: Tillverkar\nskeppscafeteria, dricksvattenkylare\nAntal anställda: 25\nÅrsomsättning: 2 500 000\nAktiekapital: 170 000\nVerkst dir Carl Håkanson\nEtableringsår: 1912.\n\nABETA, ELEKTRISKA AB\n\nPnr 431 22\n\nMölndal 1, Huvudkontor:\nKungs-backav 13. Box 167. Tel\n031-87 00 40. Bankgiro 260-1607.\nPostgiro 14079-8. Tga Abeta\nVerksamhet: Säljer elektr artiklar\no installationsmateriel en gros\nFilialen 500 11 Borås 11,\nKäll-bäcksrydsg 6. Box 11103. Tel\n033-10 23 65\n\n400 40 Göteborg 4, Fiskhamnsg 4.\nBox 4082. Tel 031-42 0280\n201 22 Malmö 1, Stillmansg 8.\nBox 254. Tel 040-93 52 80\n451 00 Uddevalla, Skalbanksv 6.\nTel 0522-130 33, 321 15\nÅrsomsättning: 15 000 000\nAktiekapital: 1000 000\nVerkst dir: P-E Knutsson\nEtableringsår: 1919.\n\nMON\n\nserviceuppdrag, svetsning, värme o\nsanitet Säljer utrustningar till\npappers- o cellulosaindustrin\nAntal anställda: 70\nÅrsomsättning: 5 000 000\nChef: Ing Allan Ohlsson\nEtableringsår: 1963.\n\nTABERGS YLLEFABRIKS AB\n\nPnr 560 21\n\nTaberg. Tel 036-64500. Tga\nYllefabriken\n\nVerksamhet: Tillverkar avpassade o\nheltäckningsmattor samt möbeltyger\nVarunamn: Tabergsmattan\nÅrsomsättning: 17 000 000\nAktiekapital: 900 000\nVerkst dir. Hans Wistmar.\n\nTABERGSMDBLER, AB\n\nPnr 560 21\n\nTaberg, Box 11. Tel 036-64065,\n643 65. Bankgiro 545-3667.\nPostgiro 23425-2\n\nVerksamhet: Tillverkar o säljer\nbokhyllsseiier\nAntal anställda: 25\nÅrsomsättning: 3 200 000\nAktiekapital: 100 000\nVerkst dir: Rolf Erik Peterson\nEtableringsår: 1928.\n\nBLOMDAHL &amp; CO, BERTIL\n\nPnr 421 06\n\nVästra Frölunda 6, Box 6007.\nSol-höjdsg 26. Tel 031-29 29 50,\n29 30 62. Bankgiro 44-1761.\nPostgiro 244956. Tga Fotoblomdahl\nVerksamhet: Tillverkar o säljer\nfotoartiklar\nAntal anställda: 3\nÅrsomsättning: 900 000\nChef: Dir Karl Axel Lindau\nEtableringsår: 1946.\n\nBLOMDAHLS TRÄVARU AB,\nWILGOT\n\nPnr 524 00\n\nHerrljunga, Box 38. Nedergården.\nTel 0513-101 52. Bankgiro 84-1029.\nPostgiro 172084\nVerksamhet: Trävaror för export\no hemmamarknaden\nAntal anställda: 35\nÅrsomsättning: 4 000 000\nAktiekapital: 120 000\nVerkst dir: Thorsten Blomdahl\nEtableringsår: 1935.",
    "structured": {
        "1": {
            "company_name": "VOLKSWAGEN I STOCKHOLM AB",
            "pnr": "102 20",
            "address": "Stockholm 12, Lindhagensplan",
            "phone_number": "08-22 76 60",
            "bank_details": {
                "bankgiro": "167-8200",
                "postgiro": "59002-6"
            },
            "activity": "Försäljning o service av Volkswagen o Porsche",
            "employees": 800,
            "capital": 6000000,
            "key_personnel": [
                {
                    "name": "Torbjörn Ek",
                    "position": "Verkst dir"
                }
            ],
            "establishment_year": 1954
        },
        "2": {
            "company_name": "WOLLSJü TOFFELFABRIK, AB",
            "pnr": "222 31",
            "address": "Lund, Trastv 10",
            "phone_number": "046-115168",
            "bank_details": {
                "bankgiro": "873-0061"
            },
            "activity": "Tillverkar trätoffel-bottnar",
            "capital": 270000,
            "key_personnel": [
                {
                    "name": "Owe Nilsson",
                    "position": "Verkst dir"
                }
            ],
            "establishment_year": 1922
        },
        "3": {
            "company_name": "SVENSKA AB IVERS LEE",
            "pnr": "22101",
            "address": "Lund 1, Pack",
            "phone_number": "046-1240 10",
            "activity": "Kontraktpaketering",
            "employees": 240,
            "annual_turnover": 20000000,
            "capital": 100000,
            "key_personnel": [
                {
                    "name": "Gunnar Brime",
                    "position": "Verkst dir"
                }
            ],
            "establishment_year": 1948
        },
        "4": {
            "company_name": "ELEKTROVERKEN, AB",
            "pnr": "801 02",
            "address": "Gävle 1, Box 77, Akarg 71",
            "phone_number": "026-1154 50",
            "bank_details": {
                "postgiro": "509640-9"
            },
            "activity": "Tillverkar lågspänningsställverk, automatikutrustningar, lågspänningsbrytare, motorskydd, bansignalmateriel",
            "employees": 185,
            "annual_turnover": 14000000,
            "capital": 5000,
            "key_personnel": [
                {
                    "name": "Ingemar Norlindh",
                    "position": "Verkst dir"
                },
                {
                    "name": "Ing Sune Lorentzon",
                    "position": "Platschef"
                }
            ],
            "establishment_year": 1948
        },
        "5": {
            "company_name": "ELEKTRO-VICI AKTIEBOLAG",
            "pnr": "104 25",
            "address": "Stockholm 30, Nordenflycht^ 62, Box 30010",
            "phone_number": "08-53 36 00, 54 2 3 95",
            "bank_details": {
                "bankgiro": "73-3816",
                "postgiro": "356358"
            },
            "activity": "Elektromekanisk verkstad",
            "employees": 15,
            "annual_turnover": 2000000,
            "capital": 75000,
            "key_personnel": [
                {
                    "name": "Bruksdisp L Degefors",
                    "position": "Verkst dir"
                }
            ],
            "establishment_year": null
        },
        "6": {
            "company_name": "ELEMA-SCHONANDER AB",
            "pnr": "17195",
            "address": "Solna, Industriv 23",
            "phone_number": "08-83 40 00",
            "bank_details": {
                "bankgiro": "726-1761",
                "postgiro": "3613-7"
            },
            "activity": "Röntgen-, elektromedicin o dentalapparater",
            "employees": 1400,
            "capital": 15000000,
            "key_personnel": [
                {
                    "name": "Dr B Rudewald",
                    "position": "Verkst din"
                }
            ],
            "establishment_year": 1917
        },
        "7": {
            "company_name": "ELEMENTHUS, AB",
            "pnr": "780 40",
            "address": "Mockfjärd",
            "phone_number": "0241-206 00",
            "bank_details": {
                "bankgiro": "560-5860, 799-8024",
                "postgiro": "356919-1"
            },
            "activity": "Färdigmonterade villor i trä. Export till Västtyskland",
            "employees": 850,
            "annual_turnover": 90000000,
            "capital": 10000000,
            "key_personnel": [
                {
                    "name": "Civilekonom Carl-Axel Rönnbo",
                    "position": "Verkst dir"
                }
            ],
            "establishment_year": 1949
        },
        "8": {
            "company_name": "FLOBY SILKETRIKA, AB",
            "pnr": "520 40",
            "address": "Floby, Box 7",
            "phone_number": "0515-40080",
            "bank_details": {
                "bankgiro": "542-1151",
                "postgiro": "93518-9"
            },
            "activity": "Tillverkar barn-, dam- o herrunderkläder, pyjamas",
            "employees": 30,
            "annual_turnover": 1400000,
            "capital": 96000,
            "key_personnel": [
                {
                    "name": "Valentin Johansson",
                    "position": "Verkst dir"
                }
            ],
            "establishment_year": 1930
        },
        "9": {
            "company_name": "FLOBY SÄG & TRA-VARUAFFÄR, AB",
            "pnr": "52040",
            "address": "Floby",
            "phone_number": "0515-403 40",
            "bank_details": {
                "postgiro": "269562-5"
            },
            "activity": "Säljer överskotts-material från försvaret",
            "employees": 3,
            "annual_turnover": 125000,
            "capital": 100000,
            "key_personnel": [
                {
                    "name": "Olle Gustavsson",
                    "position": "Verkst din"
                }
            ],
            "establishment_year": 1952
        },
        "10": {
            "company_name": "EKESIOO, AB KARL",
            "pnr": "16110",
            "address": "Bromma 10, Smält v 5-7, Bällstahamnen",
            "phone_number": "08-28 9200",
            "activity": "Partihandel med trävaror, snickerier o byggmaterial",
            "employees": 57,
            "annual_turnover": 16700000,
            "capital": 500000,
            "key_personnel": [
                {
                    "name": "Jägmäst Harry Ekesiöö",
                    "position": "Verkst dir"
                }
            ],
            "establishment_year": 1922
        },
        "11": {
            "company_name": "CELER, AB",
            "pnr": "104 60",
            "address": "Stockholm 20, Hammarby Fabriksv 53",
            "phone_number": "08-44 96 20",
            "bank_details": {
                "bankgiro": "330-1876",
                "postgiro": "854-0"
            },
            "activity": "Tillverkar skeppscafeteria, dricksvattenkylare",
            "employees": 25,
            "annual_turnover": 2500000,
            "capital": 170000,
            "key_personnel": [
                {
                    "name": "Carl Håkanson",
                    "position": "Verkst dir"
                }
            ],
            "establishment_year": 1912
        },
        "12": {
            "company_name": "ABETA, ELEKTRISKA AB",
            "pnr": "431 22",
            "address": "Mölndal 1, Huvudkontor: Kungsbackav 13, Box 167",
            "phone_number": "031-87 00 40",
            "bank_details": {
                "bankgiro": "260-1607",
                "postgiro": "14079-8"
            },
            "activity": "Säljer elektr artiklar o installationsmateriel en gros",
            "employees": null,
            "annual_turnover": 15000000,
            "capital": 1000000,
            "key_personnel": [
                {
                    "name": "P-E Knutsson",
                    "position": "Verkst dir"
                }
            ],
            "establishment_year": 1919
        },
        "13": {
            "company_name": "MON",
            "activity": "serviceuppdrag, svetsning, värme o sanitet Säljer utrustningar till pappers- o cellulosaindustrin",
            "employees": 70,
            "annual_turnover": 5000000,
            "key_personnel": [
                {
                    "name": "Ing Allan Ohlsson",
                    "position": "Chef"
                }
            ],
            "establishment_year": 1963
        },
        "14": {
            "company_name": "TABERGS YLLEFABRIKS AB",
            "pnr": "560 21",
            "address": "Taberg",
            "phone_number": "036-64500",
            "activity": "Tillverkar avpassade o heltäckningsmattor samt möbeltyger",
            "annual_turnover": 17000000,
            "capital": 900000,
            "key_personnel": [
                {
                    "name": "Hans Wistmar",
                    "position": "Verkst dir"
                }
            ]
        },
        "15": {
            "company_name": "TABERGSMDBLER, AB",
            "pnr": "560 21",
            "address": "Taberg, Box 11",
            "phone_number": "036-64065, 643 65",
            "bank_details": {
                "bankgiro": "545-3667",
                "postgiro": "23425-2"
            },
            "activity": "Tillverkar o säljer bokhyllsseiier",
            "employees": 25,
            "annual_turnover": 3200000,
            "capital": 100000,
            "key_personnel": [
                {
                    "name": "Rolf Erik Peterson",
                    "position": "Verkst dir"
                }
            ],
            "establishment_year": 1928
        },
        "16": {
            "company_name": "BLOMDAHL &amp; CO, BERTIL",
            "pnr": "421 06",
            "address": "Västra Frölunda 6, Box 6007, Solhöjdsg 26",
            "phone_number": "031-29 29 50, 29 30 62",
            "bank_details": {
                "bankgiro": "44-1761",
                "postgiro": "244956"
            },
            "activity": "Tillverkar o säljer fotoartiklar",
            "employees": 3,
            "annual_turnover": 900000,
            "key_personnel": [
                {
                    "name": "Dir Karl Axel Lindau",
                    "position": "Chef"
                }
            ],
            "establishment_year": 1946
        },
        "17": {
            "company_name": "BLOMDAHLS TRÄVARU AB, WILGOT",
            "pnr": "524 00",
            "address": "Herrljunga, Box 38, Nedergården",
            "phone_number": "0513-101 52",
            "bank_details": {
                "bankgiro": "84-1029",
                "postgiro": "172084"
            },
            "activity": "Trävaror för export o hemmamarknaden",
            "employees": 35,
            "annual_turnover": 4000000,
            "capital": 120000,
            "key_personnel": [
                {
                    "name": "Thorsten Blomdahl",
                    "position": "Verkst dir"
                }
            ],
            "establishment_year": 1935
        }
    }
}