{
    "original": "RYDBERG AB, RUNE\n\nPnr 41103\n\nGöteborg, Burggreveg 23. Tel\n031-197175. Bankgiro 67-3228.\nPostgiro 629302. Telex 20931. Tga\nPomarius\n\nVerksamhet: Import av färsk frukt\no grönsaker\nAntal anställda: 8\nÅrsomsättning: 15 000 000\nAktiekapital: 100 000\nVerkst dir: Rune Rydberg\nEtableringsår: 1966.\n\nERICHS ARMATUR AB\n\nPnr 214 34\n\nMalmö, Palm g 19 B. Tel 040-92 24 45.\nBankgiro 640-6425. Postgiro\n632340-6. Telex 32241\nVerksamhet: Säljer armatur, filter,\nvärmeväxlare o motormanöverdon\nAktiekapital: 100000\nVerkst dir: Kurt Hagbrand\nEtableringsår 1965.\n\nDENBO AB\n\nPnr 343 00\n\nÄlmhult, Pjätteryd. Tel 047 6-41115,\n411 10. Bankgiro 671-8217.\nPostgiro 76340-9\n\nVerksamhet: Säljer möbeltyger o\ngardiner i parti\nAntal anställda: 7\nÅrsomsättning: 3 000 000\nAktiekapital: 25 000\n\nVerkst dir: Leif\nAarestrup-Michael-sen\n\nEtableringsår: 1963.\n\nEGE-MOBLER, AB\n\nPnr 33100\n\nVärnamo, Växjöv. Tel\n0370-105 65, 10671. Bankgiro 554-4879.\nPostgiro 137287-9\nVerksamhet: Kompletteringsmöbler\nsamt trädetaljer i stora serier\nAntal anställda: 7\nAktiekapital: 25 000\nVerkst dir: Gustav Johansson\nEtableringsår: 1958.\n\nTRYCK-KONTAKTEN AB\n\nPnr 112 20\n\nStockholm, N Mälarstrand 8-10.\nTel 08-24 08 40\n\nVerksamhet: Konstruerar o\ntillverkar emballage o skyltställ\nÅrsomsättning: 700 000\nAktiekapital: 20 000\nVerkst dir: Lars-Erik Björkman\nEtableringsår. 1962.\n\nFODERVÄVNADER, AB\n\nPnr 501 04\n\nBorås 1, Viskastrandsg. Box 165.\nTel 033-13 6160. Bankgiro\n889-6581. Postgiro 583785-1. Tga\nFodervävnader. Telex 36108\nVerksamhet: Tillverkar rayon- o\nkonstfibervävnader\nAntal anställda: 240\nÅrsomsättning: 35 000 000\nAktiekapital: 3 000 000\nVerkst dir: Lars Enslöw\nEtableringsår: 1962.\n\nFOGA FÖRSÄLJNINGS AB\n\nPnr 330 10\n\nBredaryd, Box 58. Tel 0370-802 85\nVerksamhet: Försäljning av\ngummidetaljer för lantbruk samt\ndrickes-hoar o svinvattenventiler\nVarunamn: Fogum\nAktiekapital: 9 000.\n\nFOGBLAD REKLAM\nOFFSETTRYCK AB\n\nPnr 70211\n\nÖrebro, Rudbecksg 1. Tel\n019-13 99 55. Bankgiro 463-4697\n\nVerksamhet: Trycksaker, layout o\noriginal teckningar\nÅrsomsättning: 100 000\nChef: Birger Fogblad\nEtableringsår: 1965.\n\nall\n\nPostgiro 75957\n\nVerksamhet: Pilmtryck av textilier\nChefer: Lennart Asén, Rune\nLarsson\n\nEtableringsår: 1957.\n\nalingsas träyaruaffär\nab\n\nPnr 441 00\n\nAlingsås, Järnvägsg. Tel\n0322-104 11. 138 11. Bankgiro 436-5078.\nPostgiro 325492-7. Tga Alingsås\nVerksamhet: Tillverkar o säljer\nträvaror o byggnadsmaterial\nAntal anställda: 12\nÅrsomsättning: 2 500 000\nAktiekapital: 50 000\nVerkst dir: Disp Ake Holm\nEtableringsår: 1946.\n\nATLANTRÄKAN AB\n\nPnr 103 82\n\nStockholm 7, Box 7065. Kungsg 33.\nTel 08-23 15 20. Bankgiro 201-1179.\nPostgiro 408790-4. Tga\nAtlant-shrimp. Telex 10080 KALEB S\nVerksamhet: Säljer skaldjur, lax o\növriga fiskprodukter\nAntal anställda: 5\nÅrsomsättning: 5 000 000\nAktiekapital: 5 000\nVerkst dir: Erik Karlström\nEtableringsår: 1968.\n\nVES\n\nAntal anställda: 20\nÅrsomsättning: 1 500 000\nAktiekapital: 75 000\nStyrelse: Faktor Erik B Westlund\n(ordf), faktor Lars Westlund\nVerkst dir: Faktor Erik B Westlund\nEtableringsår: 1924.\n\nWESTLUNDS KONFEKTIONS.\nFABRIK, AB E\n\nPnr 512 01\n\nSvenljunga 1, Box 62. Tel\n0325-113 50. Bankgiro 84-24 20. Postgiro\n72152. Tga Westlund Konf\nVerksamhet: Tillverkar damkappor,\nfritidskläder o byxor av alla slag\nAntal anställda: 175\nÅrsomsättning: 9 000 000\nAktiekapital: 1000 000\nVerkst dir: Valle Berg\nEtableringsår. 1936.\n\nARMERAD BETONG, AB\n\nPnr 20122\n\nMalmö 1, Box 246. O Promenaden\n7 A. Tel 040-704 50. Bankgiro\n640-1293. Postgiro 37820-8.\nTga Armeradbetong.\nTelex 32412 ARMERAD S\nVerksamhet: Entreprenör för\nbyggnads, anläggnings- o vvs-arbeten\nAvdelningskontor: 100 21 Stockholm\n18, Pol hems g 29. Fack. Tel\n08-24 79 00\n\n403 1 7 Göteborg 2, Kungsg 20.\n\nBox 2517. Tel 031-17 70 30\n\n601 01 Norrköping 1, Bråddg 13.\n\nFack. Tel 011-12 94 25\n\n701 30 Örebro 1, Storg 13. Box 920.\n\nTel 019-13 61 60\n\n551 02 Jönköping 1, V Storg 16.\n\nBox 629. Tel 036-1198 40\n\n801 04 Gävle 1, Drottningg 54. Box\n\n267. Tel 026-180080\n\n381 01 Kalmar 1, N Vägen 37. Box\n\n67. Tel 0480-155 90\n\n651 08 Karlstad 1, Tingvallag 1 B.\n\nBox 486. Tel 054-15 65 50\n\n710 40 Frövi, N Bang 28. Box 45.\n\nTel 0581-307 10\n\nAntal anställda: 5000\n\nÅrsomsättning: 550 000 000\n\nAktiekapital: 13 000 000\n\nStyrelse: Dir Alvar Lindencrona\n\n(ordf), dir Gösta Lewenhaupt,\n\nbankdir Hans Cavalli-Björkman,\n\ndir Bo Dahlgren, dir Göran Ekelund\n\nVerkst dir Göran Ekelund\n\nTekn dir: Karl Elis Bowin\n\nAdm dir: Ake Kjäll\n\nEtableringsår: 1916.",
    "structured": {
        "1": {
            "company_name": "RYDBERG AB",
            "pnr": "41103",
            "address": "Göteborg, Burggreveg 23",
            "phone_number": "031-197175",
            "bank_details": {
                "bankgiro": "67-3228",
                "postgiro": "629302"
            },
            "activity": "Import av färsk frukt o grönsaker",
            "employees": 8,
            "annual_turnover": 15000000,
            "capital": 100000,
            "key_personnel": [
                {
                    "name": "Rune Rydberg",
                    "position": null
                }
            ],
            "establishment_year": 1966
        },
        "2": {
            "company_name": "ERICHS ARMATUR AB",
            "pnr": "214 34",
            "address": "Malmö, Palm g 19 B",
            "phone_number": "040-92 24 45",
            "bank_details": {
                "bankgiro": "640-6425",
                "postgiro": "632340-6"
            },
            "activity": "Säljer armatur, filter, värmeväxlare o motormanöverdon",
            "capital": 100000,
            "key_personnel": [
                {
                    "name": "Kurt Hagbrand",
                    "position": null
                }
            ],
            "establishment_year": 1965
        },
        "3": {
            "company_name": "DENBO AB",
            "pnr": "343 00",
            "address": "Älmhult, Pjätteryd",
            "phone_number": "047 6-41115, 411 10",
            "bank_details": {
                "bankgiro": "671-8217",
                "postgiro": "76340-9"
            },
            "activity": "Säljer möbeltyger o gardiner i parti",
            "employees": 7,
            "annual_turnover": 3000000,
            "capital": 25000,
            "key_personnel": [
                {
                    "name": "Leif Aarestrup-Michaelsen",
                    "position": null
                }
            ],
            "establishment_year": 1963
        },
        "4": {
            "company_name": "EGE-MOBLER, AB",
            "pnr": "33100",
            "address": "Värnamo, Växjöv",
            "phone_number": "0370-105 65, 10671",
            "bank_details": {
                "bankgiro": "554-4879",
                "postgiro": "137287-9"
            },
            "activity": "Kompletteringsmöbler samt trädetaljer i stora serier",
            "employees": 7,
            "capital": 25000,
            "key_personnel": [
                {
                    "name": "Gustav Johansson",
                    "position": null
                }
            ],
            "establishment_year": 1958
        },
        "5": {
            "company_name": "TRYCK-KONTAKTEN AB",
            "pnr": "112 20",
            "address": "Stockholm, N Mälarstrand 8-10",
            "phone_number": "08-24 08 40",
            "activity": "Konstruerar o tillverkar emballage o skyltställ",
            "annual_turnover": 700000,
            "capital": 20000,
            "key_personnel": [
                {
                    "name": "Lars-Erik Björkman",
                    "position": null
                }
            ],
            "establishment_year": 1962
        },
        "...": "..."
    }
}