{
    "original": "LAGAHOLM AB\n\nPnr 31201\n\nLaholm 1, Box 47. Mellbystrandsv\n60. Tel 0430-113 45. Bankgiro\n659-1200. Tga Lagab\nVerksamhet: Tillverkar\ntransportanordningar för container,\nLAGAB-flexi lösflaksystem,\ntransportbussar, person- o skolbussar\nAntal anställda: 60\nÅrsomsättning: 5 000 000\nAktiekapital: 100 000\nVerkst dir. Sven Boije Bengtsson\nV verkst dir o teknisk chef:\nCarl-Eric Arvidsson\n\nKonstr-chef: Christer Svensson\nFörsäljning: Hans Drott\nEtableringsår: 1969.\n\nLAGANS BOBINFABRIK\n\nE Sjöstrand &amp; Co\n\nPnr 34014\n\nLagan, Industrig 4. Tel 0372-300 33.\nBankgiro 146-0138. Postgiro\n687669-6\n\nVerksamhet: Tillverkar\nträtoffel-bottnar, toffelläster o skoblock i\nträ\n\nAntal anställda: 10\nÅrsomsättning: 500 000\nChef: Fabr Erie Sjöstrand\nEtableringsår: 1936.\n\nELC\n\nAntal anställda: 5\nÄgare o chef: H Hällgren\nEtableringsår: 1944.\n\nBERGVIK OCH ALA AB\n\nPnr 82601\n\nSödeitiamn 1, Box 19. Kyrkog 16.\nTel 0270-166 00. Tga Bergvik.\nTelex 81170, 81171\nVerksamhet: Trävaror, sulfit- o\nsulfatmassa, såpa, elenergi\nAntal anställda: 1 700\nÅrsomsättning: 165 000 000\nAktiekapital: 62 000 000\nVerkst dir: L Gabrielsson\nEtableringsår: 1852.\n\nBERGVIKS\nHARTSPRODUKTER AB\n\nPnr 826 01\n\nSödeitiamn 1, Box 19. Tel\n0270-166 00. Tga Bergvik. Telex 81169\nVerksamhet: Tillverkar tallolja,\nharts, hartsbeck, lackhartser m m\nAntal anställda: 100\nÅrsomsättning: 40 000 000\nAktiekapital: 100 000\nVerkst dir: A Wahlstedt\nEtableringsår: 1940\nÄges av Bergvik o Ala AB o\nSvenska Cellulosa AB.\nDotterföretag: Garvämnes AB\nWeibull, Landskrona.\n\nBERGVINGS\nKONFEKTION AB, E\n\nPnr 520 15\n\nHökenim. Tel 033-74200. Bankgiro\n532-7879. Postgiro 81427-7\nVerksamhet: Tillverkar byxor o\nkjolar i ylle o bomull\nAktiekapital: 100 000\nVerkst dir: Enar Bergving\nEtableringsår: 1961.\n\nBERGA FÄRGERI &amp;\nULLSPINNERI AB\n\nPnr 780 12\n\nStora Skedvi. Tel 0225-450 00.\nBankgiro 466-0031. Postgiro\n26749-2\n\nVerksamhet: Spinning o färgning\nav kardgarner, beredning av\nyllevävnader. Specialitet: beredning\nav handvävda tyger, plädar mm\nVarunamn: Bergå\nAntal anställda: 80\nAktiekapital: 52 000\nVerkst dir: Gustaf Fält\nEtableringsår: 1856.\n\nHOLMDAHL AB,HARRY\n\nPnr 27100\n\nYstad, Herrestadsg. Tel\n0411-136 75. Bankgiro 264-2189.\nPostgiro 148077-1. Tga Hoaby\nVerksamhet: Tillverkar arkivdörrar,\nbrand dörrar, kylrumsdörrar,\ntruckdörrar av gummi, stålkarmar samt\nförvaringsskåp av stål\n\nAntal anställda: 35\nÅrsomsättning: 2 800 000\nAktiekapital: 200 000\nVerkst dir: Allan Nossman\nEtableringsår: 1941.\n\nSMALANDS-HUS, AB\n\nPnr 576 00\n\nSävsjö, Box 125. Tel 0382-112 40.\nBankgiro 285-4859. Postgiro\n593310\n\nVerksamhet: Tillverkar o säljer\nmonteringsfärdiga villor ,\nfritidshus, skolor mm\nAntal anställda: 40\nÅrsomsättning: 6 500000\nAktiekapital: 85 000\nVerkst dir: Edvin Niklasson\nEtableringsår: 1962.\n\nHJELMQUIST, STIG\n\nPnr 573 00\n\nTranås, V Järnvägsg 5. Box 6. Tel\n0140-100 00. Telex 3707. Tga\nHjelmquist\n\nVerksamhet: Generalagenturer\nÄgare o chef: Dir Stig Hjelmquist\nEtableringsår: 1934.\n\nHJELMSFORS YLLE.\nFABRIK, AB\n\nPnr 434 00\n\nKungsbacka, Kungsg 1-3.\nTel0300-115 55. Bankgiro 426-4081.\nPost-giro 95834-8\n\nVerksamhet: Tillverkar o säljer\ngarner\n\nAntal anställda: 30\nAktiekapital: 125 000\nVerkst dir: Ing Bengt Åström\nEtableringsår: 1898.\n\nHJERNE &amp; SON, HÄNDELSBO.\nLAGET\n\nPnr 117 38\n\nStockholm, Bergsunds strand 40.\nTel 08-68 1100,68 1101. Bankgiro\n73-0209. Postgiro 57076-2\nVerksamhet: Säljer färger o tapeter\nen gros o detalj\nAntal anställda: 11\nÅrsomsättning: 2 000 000\nChef: sten Dahlner\nEtableringsår: 1923.\n\nALB\n\nVerksamhet: Grossistförsäljning\nav Briofan o Viscosan\nÅrsomsättning: 200 000\nAktiekapital: 25 000\nVerkst dir: Hasse Gustafsson\nEtableringsår: 1934.\n\nHAN\n\nHANSON KEMISK-TEKNISK\nFABRIK AB, GÖSTA W\n\nPnr 450 52\n\nDingle, Box 48. Tel 0524-405 01,\n405 02. Bankgiro 108-5802.\nPostgiro 421714^7\n\nVerksamhet: Industritejp,\nsjälv-häftande filtrerings- o\ntätnings-lister\n\nAktiekapital: 20 000\nVerkst dir: Gösta Hanson\nEtableringsår: 1942.\n\nBLEKINGE LANS TIDNING, AB\n\nPnr 371 00\n\nKarlskrona, Landbrog 15. Tel\n0455-250 00. Bankgiro 86-1370.\nPostgiro 9662. Tga BLT. Telex 4857\nVerksamhet: Tidningstryckeri,\nklichéanstalt, boktryckeri\nAktiekapital: 600 000\nVerkst dir: Valdo Carlström\nEtableringsår: 1869.\n\nJOHANSSON, AB RAGNAR\n\nPnr 126 55\n\nHägersten, Kinmanssonsv 64. Tel\n08-4665 60. Bankgiro 29-5867,\n57-3346. Postgiro 195797\nVerksamhet: Tillverkar\nhögtryckskärl för luft, vatten o ånga\nAntal anställda: 25\nÅrsomsättning: 1 200 000\nAktiekapital: 10 000\nVerkst dir: Ing Ragnar Johansson\nEtableringsår 1937.\n\nJOHANSSON &amp; CO AB,\nRIKARD\n\nPnr 104 25\n\nStockholm 30, Strandbergsg 20. Box\n30011. Tel 08-54 13 50. Bankgiro\n56-0227. Postgiro 2919. Tga\nCar-bcrik. Telex 19067 CARBRIK S\nVerksamhet: Säljer Tyrolit\nslipskivor, slipsegment, slipstift,\nslip-toppar, brynen, Tyrolit Secur\nväv-armerade slipskivor o kapskivor,\nVitex fiberrondeller, slipduk o\nslippapper samt Carborex\nslipskivor\n\nVarunamn: Carborex, Secur,\nTycar-bo, Tyralum, Tyrolit, Vitex\nAntal anställda: 45\nAktiekapital: 640 000\nVerkst dir: Carl-Gustaf Syrén\nV verkst dir: Olov Hällström\nSlipskive-avd: Rune Lindgren\nSecur-Vitex-avd: Bertil Emell\nEtableringsår: 1924\nOmbildat till aktiebolag 1950\nDotterbolag: Slipskivefabriken\nSvea AB, Stockholm.\n\nJOHANSSON &amp; CO, AB SVEN\n\nPnr 330 30\n\nGnosjö, Bårebo. Tel 03 70-95 0 05.\nPostgiro 71335-4\n\nVerksamhet: Tillverkar\nhusgerådsartiklar i rostfritt stål, kläd-o by\nx-hängare, trådarbeten\nAntal anställda: 40\nÅrsomsättning: 3 000 000\nAktiekapital: 180 000\n\nÄgare o chefer: Fabr David\nJohansson, fabr Elof Johansson\nEtableringsår: 1914\nOmbildat till aktiebolag 1945.\n\nJOHANSSON, AB TAGE\n\nPnr 402 72\n\nGöteborg 8, Generatorsg 1. Box\n\n8887. Tel 031-5133 40. Bankgiro\n\n51-3613. Postgiro 48977\n\nVerksamhet: Grossist inom VVS-\n\nbranschen\n\nAntal anställda: 80\n\nAktiekapital: 5 000\n\nPlatschef: Disp Arne Danielson\n\nEtableringsår: 1944.\n\nDotterbolag till Ahlsell &amp; Ågren AB,\n\nStockholm.\n\nJOHANSSONS TRÄINDUSTRI,\nTAGE\n\nPnr 330 23\n\nSmålandsstenar, Löbbo. Tel\n0371-940 24. Postgiro 447571\nVerksamhet: Tillverkar vindflöjlar,\nljusstakar, möbelben m m. Utför\nsvarvningsarbeten i trä, i så väl\nsvenska som utländska träslag\nChef: Tage Johansson\nEtableringsår: 1950.\n\nJOHANSONS TRYCKERI AB,\nUNO\n\nPnr 778 01\n\nNorberg 1, Malmg 20. Box 34. Tel\n0223-203 09, 208 00. Bankgiro\n23-1641. Postgiro 288737\nVerksamhet: Tryckeri o bokbinderi.\nAffärs- o reklamtryck\nAntal anställda: 18\nÅrsomsättning: 1 000 000\nAktiekapital: 30 000\nVerkst dir: Boktr Carl-Olof Unoson\nEtableringsår: 1909.\n\nJOHANSSON, BYGGNADS AB\nVERNER\n\nPnr 722 11\n\nVästerås, Bondeg 8 A. Tel\n021-18 03 65. Bankgiro 808-6126.\nPostgiro 137959-3\n\nVerksamhet: Byggnads- o\nentreprenadrörelse\nAntal anställda: 35\nÅrsomsättning: 2700 000\nAktiekapital: 45 000\nStyrelse: Ing Folke Johansson\n(ordf), fru Hildur Johansson\nVerkst dir: Ing Folke Johansson\nChef: Ing Folke Johansson\nEtableringsår: 1925.",
    "structured": {
        "1": {
            "company_name": "LAGAHOLM AB",
            "pnr": "31201",
            "address": "Laholm 1, Box 47. Mellbystrandsv 60",
            "phone_number": "0430-113 45",
            "bank_details": {
                "bankgiro": "659-1200"
            },
            "activity": "Tillverkar transportanordningar för container, LAGAB-flexi lösflaksystem, transportbussar, person- o skolbussar",
            "employees": 60,
            "annual_turnover": 5000000,
            "capital": 100000,
            "key_personnel": [
                {
                    "name": "Sven Boije Bengtsson",
                    "position": "Verkst dir"
                },
                {
                    "name": "Carl-Eric Arvidsson",
                    "position": "V verkst dir o teknisk chef"
                }
            ],
            "establishment_year": 1969
        },
        "2": {
            "company_name": "LAGANS BOBINFABRIK",
            "pnr": "34014",
            "address": "Lagan, Industrig 4",
            "phone_number": "0372-300 33",
            "bank_details": {
                "bankgiro": "146-0138",
                "postgiro": "687669-6"
            },
            "activity": "Tillverkar trätoffel-bottnar, toffelläster o skoblock i trä",
            "employees": 10,
            "annual_turnover": 500000,
            "establishment_year": 1936,
            "key_personnel": [
                {
                    "name": "Erie Sjöstrand",
                    "position": "Chef"
                }
            ]
        },
        "3": {
            "company_name": "ELC",
            "employees": 5,
            "activity": "Ägare o chef: H Hällgren",
            "establishment_year": 1944
        },
        "4": {
            "company_name": "BERGVIK OCH ALA AB",
            "pnr": "82601",
            "address": "Södeitiamn 1, Box 19. Kyrkog 16",
            "phone_number": "0270-166 00",
            "bank_details": {
                "tga": "Bergvik",
                "telex": "81170, 81171"
            },
            "activity": "Trävaror, sulfit- o sulfatmassa, såpa, elenergi",
            "employees": 1700,
            "annual_turnover": 165000000,
            "capital": 62000000,
            "key_personnel": [
                {
                    "name": "L Gabrielsson",
                    "position": "Verkst dir"
                }
            ],
            "establishment_year": 1852
        },
        "5": {
            "company_name": "BERGVIKS HARTSPRODUKTER AB",
            "pnr": "826 01",
            "address": "Södeitiamn 1, Box 19",
            "phone_number": "0270-166 00",
            "bank_details": {
                "tga": "Bergvik",
                "telex": "81169"
            },
            "activity": "Tillverkar tallolja, harts, hartsbeck, lackhartser m m",
            "employees": 100,
            "annual_turnover": 40000000,
            "capital": 100000,
            "key_personnel": [
                {
                    "name": "A Wahlstedt",
                    "position": "Verkst dir"
                }
            ],
            "establishment_year": 1940
        },
        "6": {
            "company_name": "BERGVINGS KONFEKTION AB, E",
            "pnr": "520 15",
            "address": "Hökenim",
            "phone_number": "033-74200",
            "bank_details": {
                "bankgiro": "532-7879",
                "postgiro": "81427-7"
            },
            "activity": "Tillverkar byxor o kjolar i ylle o bomull",
            "capital": 100000,
            "key_personnel": [
                {
                    "name": "Enar Bergving",
                    "position": "Verkst dir"
                }
            ],
            "establishment_year": 1961
        },
        "7": {
            "company_name": "BERGA FÄRGERI & ULLSPINNERI AB",
            "pnr": "780 12",
            "address": "Stora Skedvi",
            "phone_number": "0225-450 00",
            "bank_details": {
                "bankgiro": "466-0031",
                "postgiro": "26749-2"
            },
            "activity": "Spinning o färgning av kardgarner, beredning av yllevävnader. Specialitet: beredning av handvävda tyger, plädar mm. Varunamn: Bergå",
            "employees": 80,
            "capital": 52000,
            "key_personnel": [
                {
                    "name": "Gustaf Fält",
                    "position": "Verkst dir"
                }
            ],
            "establishment_year": 1856
        },
        "8": {
            "company_name": "HOLMDAHL AB,HARRY",
            "pnr": "27100",
            "address": "Ystad, Herrestadsg",
            "phone_number": "0411-136 75",
            "bank_details": {
                "bankgiro": "264-2189",
                "postgiro": "148077-1",
                "tga": "Hoaby"
            },
            "activity": "Tillverkar arkivdörrar, brand dörrar, kylrumsdörrar, truckdörrar av gummi, stålkarmar samt förvaringsskåp av stål",
            "employees": 35,
            "annual_turnover": 2800000,
            "capital": 200000,
            "key_personnel": [
                {
                    "name": "Allan Nossman",
                    "position": "Verkst dir"
                }
            ],
            "establishment_year": 1941
        },
        "9": {
            "company_name": "SMALANDS-HUS, AB",
            "pnr": "576 00",
            "address": "Sävsjö, Box 125",
            "phone_number": "0382-112 40",
            "bank_details": {
                "bankgiro": "285-4859",
                "postgiro": "593310"
            },
            "activity": "Tillverkar o säljer monteringsfärdiga villor , fritidshus, skolor mm",
            "employees": 40,
            "annual_turnover": 6500000,
            "capital": 85000,
            "key_personnel": [
                {
                    "name": "Edvin Niklasson",
                    "position": "Verkst dir"
                }
            ],
            "establishment_year": 1962
        },
        "10": {
            "company_name": "HJELMQUIST, STIG",
            "pnr": "573 00",
            "address": "Tranås, V Järnvägsg 5",
            "phone_number": "0140-100 00",
            "telex": "3707",
            "activity": "Generalagenturer",
            "aggare": "Dir Stig Hjelmquist",
            "establishment_year": 1934
        },
        "11": {
            "company_name": "HJELMSFORS YLLE. FABRIK, AB",
            "pnr": "434 00",
            "address": "Kungsbacka, Kungsg 1-3",
            "phone_number": "0300-115 55",
            "bank_details": {
                "bankgiro": "426-4081",
                "postgiro": "95834-8"
            },
            "activity": "Tillverkar o säljer garner",
            "employees": 30,
            "capital": 125000,
            "key_personnel": [
                {
                    "name": "Ing Bengt Åström",
                    "position": "Verkst dir"
                }
            ],
            "establishment_year": 1898
        },
        "12": {
            "company_name": "HJERNE & SON, HÄNDELSBO. LAGET",
            "pnr": "117 38",
            "address": "Stockholm, Bergsunds strand 40",
            "phone_number": "08-68 1100, 68 1101",
            "bank_details": {
                "bankgiro": "73-0209",
                "postgiro": "57076-2"
            },
            "activity": "Säljer färger o tapeter en gros o detalj",
            "employees": 11,
            "annual_turnover": 2000000,
            "chef": "Sten Dahlner",
            "establishment_year": 1923
        },
        "13": {
            "company_name": "ALB",
            "activity": "Grossistförsäljning av Briofan o Viscosan",
            "annual_turnover": 200000,
            "capital": 25000,
            "key_personnel": {
                "name": "Hasse Gustafsson",
                "position": "Verkst dir"
            },
            "establishment_year": 1934
        },
        "14": {
            "company_name": "HANSON KEMISK-TEKNISK FABRIK AB, GÖSTA W",
            "pnr": "450 52",
            "address": "Dingle, Box 48",
            "phone_number": "0524-405 01, 405 02",
            "bank_details": {
                "bankgiro": "108-5802",
                "postgiro": "421714^7"
            },
            "activity": "Industritejp, själv-häftande filtrerings- o tätnings-lister",
            "capital": 20000,
            "key_personnel": {
                "name": "Gösta Hanson",
                "position": "Verkst dir"
            },
            "establishment_year": 1942
        },
        "15": {
            "company_name": "BLEKINGE LANS TIDNING, AB",
            "pnr": "371 00",
            "address": "Karlskrona, Landbrog 15",
            "phone_number": "0455-250 00",
            "bank_details": {
                "bankgiro": "86-1370",
                "postgiro": "9662"
            },
            "activity": "Tidningstryckeri, klichéanstalt, boktryckeri",
            "employees": 600000,
            "capital": 600000,
            "key_personnel": {
                "name": "Valdo Carlström",
                "position": "Verkst dir"
            },
            "establishment_year": 1869
        },
        "16": {
            "company_name": "JOHANSSON, AB RAGNAR",
            "pnr": "126 55",
            "address": "Hägersten, Kinmanssonsv 64",
            "phone_number": "08-4665 60",
            "bank_details": {
                "bankgiro": "29-5867",
                "postgiro": "195797"
            },
            "activity": "Tillverkar högtryckskärl för luft, vatten o ånga",
            "employees": 25,
            "annual_turnover": 1200000,
            "capital": 10000,
            "key_personnel": {
                "name": "Ing Ragnar Johansson",
                "position": "Verkst dir"
            },
            "establishment_year": 1937
        },
        "17": {
            "company_name": "JOHANSSON & CO AB, RIKARD",
            "pnr": "104 25",
            "address": "Stockholm 30, Strandbergsg 20",
            "phone_number": "08-54 13 50",
            "bank_details": {
                "bankgiro": "56-0227",
                "postgiro": "2919",
                "tga": "Car-bcrik",
                "telex": "19067 CARBRIK S"
            },
            "activity": "Säljer Tyrolit slipskivor, slipsegment, slipstift, slip-toppar, brynen, Tyrolit Secur väv-armerade slipskivor o kapskivor, Vitex fiberrondeller, slipduk o slippapper samt Carborex slipskivor",
            "varunamn": "Carborex, Secur, Tycar-bo, Tyralum, Tyrolit, Vitex",
            "employees": 45,
            "capital": 640000,
            "key_personnel": [
                {
                    "name": "Carl-Gustaf Syrén",
                    "position": "Verkst dir"
                },
                {
                    "name": "Olov Hällström",
                    "position": "V verkst dir"
                },
                {
                    "name": "Rune Lindgren",
                    "position": "Slipskive-avd"
                },
                {
                    "name": "Bertil Emell",
                    "position": "Secur-Vitex-avd"
                }
            ],
            "establishment_year": 1924
        },
        "18": {
            "company_name": "JOHANSSON & CO, AB SVEN",
            "pnr": "330 30",
            "address": "Gnosjö, Bårebo",
            "phone_number": "03 70-95 0 05",
            "postgiro": "71335-4",
            "activity": "Tillverkar husgerådsartiklar i rostfritt stål, kläd-o by x-hängare, trådarbeten",
            "employees": 40,
            "annual_turnover": 3000000,
            "capital": 180000,
            "key_personnel": [
                {
                    "name": "David Johansson",
                    "position": "Fabr"
                },
                {
                    "name": "Elof Johansson",
                    "position": "Fabr"
                }
            ],
            "establishment_year": 1914
        },
        "19": {
            "company_name": "JOHANSSON, AB TAGE",
            "pnr": "402 72",
            "address": "Göteborg 8, Generatorsg 1",
            "phone_number": "031-5133 40",
            "bank_details": {
                "bankgiro": "51-3613",
                "postgiro": "48977"
            },
            "activity": "Grossist inom VVS-branschen",
            "employees": 80,
            "capital": 5000,
            "platschef": "Disp Arne Danielson",
            "establishment_year": 1944,
            "dotterbolag": "Ahlsell & Ågren AB, Stockholm"
        },
        "20": {
            "company_name": "JOHANSSONS TRÄINDUSTRI, TAGE",
            "pnr": "330 23",
            "address": "Smålandsstenar, Löbbo",
            "phone_number": "0371-940 24",
            "postgiro": "447571",
            "activity": "Tillverkar vindflöjlar, ljusstakar, möbelben m m. Utför svarvningsarbeten i trä, i så väl svenska som utländska träslag",
            "chef": "Tage Johansson",
            "establishment_year": 1950
        },
        "21": {
            "company_name": "JOHANSONS TRYCKERI AB, UNO",
            "pnr": "778 01",
            "address": "Norberg 1, Malmg 20",
            "phone_number": "0223-203 09, 208 00",
            "bank_details": {
                "bankgiro": "23-1641",
                "postgiro": "288737"
            },
            "activity": "Tryckeri o bokbinderi. Affärs- o reklamtryck",
            "employees": 18,
            "annual_turnover": 1000000,
            "capital": 30000,
            "key_personnel": {
                "name": "Boktr Carl-Olof Unoson",
                "position": "Verkst dir"
            },
            "establishment_year": 1909
        },
        "22": {
            "company_name": "JOHANSSON, BYGGNADS AB VERNER",
            "pnr": "722 11",
            "address": "Västerås, Bondeg 8 A",
            "phone_number": "021-18 03 65",
            "bankgiro": "808-6126",
            "postgiro": "137959-3",
            "activity": "Byggnads- o entreprenadrörelse",
            "employees": 35,
            "annual_turnover": 2700000,
            "capital": 45000,
            "styrelse": "Ing Folke Johansson (ordf), fru Hildur Johansson",
            "verkst dir": "Ing Folke Johansson",
            "chef": "Ing Folke Johansson",
            "establishment_year": 1925
        }
    }
}