{
    "original": "VIBRASUG, AB\n\nPnr 121 03\n\nJohanneshov 3, Box 336. Svalövsv\n1. Tel 08-59 00 65. Bankgiro\n810-7740. Postgiro 450150-8. Tga\nVibrasug\n\nVerksamhet: Tillverkning,\nförsäljning, montering o service av\nVibra-sugaren Sanator,\ndesinfektions-apparaten Desinator o\nstädutrust-ningar\n\nAntal anställda: 13\nÅrsomsättning: 2 500 000\nAktiekapital: 100 000\n\nVerkst dir: Ekonom Rolf Hallström\nEtableringsår: 1967.\n\nVIBRO-VERKEN, AB\n\nIngår i Cementakoncernen\n\nPnr 171 22\n\nSolna 1, Box 1103. Aldermansv\n17-21. Tel 08-82 0160. Tga Vibro.\nTelex 1531\n\nVerksamhet: Betongvibratorer,\njordpackningsmaskiner,\nindustri-vibratorer\n\nAvdelningskontor: Göteborg.\nBar&gt;-gårdsg 35, pa Kållered. Tel\n031-7512 35\n\nMalmö. Hammarv, Industribyn, pa\nAr löv. Tel 040-43 40 20\nSundsvall, Nyg 41. Tel 060-1565 23\nFabriker: Karlskrona, Gullberna.\nTel 0455-229 30. Telex 4841\nLjungby. Skåneg 2. Tel0372-12540.\nTelex 4691\n\nAktiekapital: 10 000 000\nVerkst dir: Sven Jonson\nEtableringsår: 1940.\n\nARI AB\n\nPnr 89101\n\nÖrnsköldsvik 1, Masking 2, Box\n249. Tel 0660-102 20. Postgiro\n62432-0. Tga Maskinfabriken.\nTelex 6042\n\nVerksamhet: Tillverkar Ari\nsågverksmaskiner, flishuggmaskiner o\ntransportanordningar\nVarunamn: Ari\nAktiekapital: 480 000\nVerkst dir: Paul Säfsten\nEtableringsår: 1938.\n\nARIADNE AB,\nINREDNINGSBOLAGET\n\nPnr 30104\n\nHalmstad 1, Box 182. Köpmansg 8.\nTel 035-12 24 80. 1196 80\nVerksamhet: Tillverkar o säljer\nsystem för varuvisning till affärer\nÄgare o chefer: Erik Tehler, Erik\nBondesson\nEtableringsår: 1951.\n\nMEMA GULD &amp; SILVER AB\n\nPnr 53101\n\nLidköping 1, Brantabäcksg4. Box 17.\nTel 0510-22125. Bankgiro 34-6616.\nPostgiro 32783. Tga Mema\nVeiksamhet: Tillverkar\nbordsbestick o bordsartiklar i silver o\nförsilvrat\nVarunamn: Mema\nAntal anstäUda: 50\nÅrsomsättning: 4400 000\nAktiekapital: 165 200\nStyrelse: f Bankdir Henry Axén\n(ordf), disp Hugo Bennman, disp\nSven E Ericsson\nVerkst dir: Sven E Ericsson jr\nEtableringsår: 1912\nOmbildat 1922.\n\nMEMOTEKNIK AB\n\nPnr 93101\n\nSkellefteå 1, Box 233. Tel\n0910-774 70. Bankgiro 204-0806.\nPostgiro 487421-0\n\nQ\n\nVeiksamhet: Memofon\ntelefonsystem, elektroniska anläggningar o\nsystem för dörr- o telefonsignaler.\nLjus växlare för reklamändamål.\nResultattavlor o\nvoteringsanläggningar. Trådlös larm o\nmanöversystem. Effektomvandlare.\nHel-transistoriserade ljudanläggningar.\nSpecialutrustningar för kyrkor.\nAutomatik för industrier\nVarunamn: Memofon, Memolight\nAntal anstäUda: 10\nÅrsomsättning: 1 000 000\nAktiekapital: 50 000\nStyrelse: Carl-Erik Steinwall,\nIngeborg Steinwall\nVerkst dir: C E Steinwall\nEtableringsår: 1965.\n\nTRANSINTRO. AB\n\nPnr 112 51\n\nStockholm. Strandbergsg 49. Tel\n08-1313 65. Bankgiro 48-1415.\nPostgiro 198182. Telex 17244\ninterel s\n\nVerksamhet: Utvecklar, konstruerar\no tillverkar ljudutrustningar o\nundervisningsinstrument.\nFöretaget har ett helägt dotterbolag,\nRe-ma Electronic AB, som utvecklar\no tillverkar elektronisk\nstyrutrustning för sågverk\nAntal anställda: 50\nÅrsomsättning: 3 000 000\nAktiekapital: 1000 000\nStyrelse: Adv Bengt Westerling\n(ordf), èkonomidir Arne Henriksson\nbankdir Stefan Ljungberg, ing Hans\nWiener, civilekonom Bror Falklind\nVeikst dir: Hans Dirtoft\nEtableringsår 1955.\n\nmalmberg, ab elof\n\nPnr 801 02\n\nGävle 1, Box 97. Tel 026-115140\nVerksamhet: Tillverkar flytvästar,\nryggsäckar, tält samt utrustning\nför skidåkning, ishockey, bandy,\norientering, trav, hund, jakt,\nbåg-skytte o fotboll\nÅrsomsättning: 20 000 000\nAktiekapital: 480 000\nStyrelse: Vice stadsjurist Osten\nMalmberg (ordf), disp G Elfving,\ndir L Malmberg ■■■■\nVerkst dir: Lennart Malmberg\nEtableringsår: 1905\nDotterbolag: AB Sölvesborgs\nSkofabrik, Sölvesborg.\n\nmalmberg, ab frank\n\nPnr 18146\n\nLidingö, Bullerbackstigen 2.Tel\n08-765 60 4 8 , 765 60 4 9. Bankgiro\n627-4138. Postgiro 3391-0. Tga Monel\nVerksamhet: Elektrisk\nIsoleringsmaterial i parti, plaster mm\nAktiekapital: 40000\nDisp: H Peterzon\nEtableringsår: 1912.\n\nAMBO, AB\n\nPnr 24100\n\nEslöv, Box 114. Dsterg 23. Tel\n0413-132 55. Bankgiro 866-0607.\nPostgiro 266654-3. Tga Ambo\nVerksamhet: Tillverkar påsar,\nsäckar, slang, folie o knutlösa nät i\npolyeten samt pressgods i\nhärdplast\n\nVarunamn: Poly-Net\nAntal anställda: 50\nÅrsomsättning: 4 500 000\nAktiekapital: 90 000\nVerkst dir: Carl Bolin\nFörsäljning: C-G Persson\nEtableringsår: 1943\nOmbildat till aktiebolag 1953.\n\nAMEC-PRODUKTER, AB\n\nPnr 112 28\n\nStockholm, Bergsg 29. Tel\n08-50 89 30, 5137 71. Bankgiro\n72-3744. Postgiro 556105-5\nVerksamhet:\nGrosshandelsförsäljning av häftverktyg, häftapparater\no häftklammer till industrier o\nstorförbrukare\nAktiekapital: 20 000\nÄgare o chef: Civilekonom C H\nSöderlindh\nEtableringsår: 1957.\n\nBRATTS KOL &amp; KOKS AB\n\nPnr 41107\n\nGöteborg, Drottningg 69. Tel\n031-113171,1157 52. Bankgiro\n84-8079. Postgiro 40030. Tga Kolbratt.\nTelex 2252\n\nVerksamhet: Säljer kol, koks, oljor o\ngödningsmedel. Fastighetsmäklare\nAktiekapital: 100 000\nVerkst dir: Ake Brandt\nEtableringsår 1877.\n\nGÄVLE PLÅT AB\n\nPnr 802 24\n\nGävle, Sockerbruksg 58. Tel\n026-12 87 78. Bankgiro 336-7265.\nPostgiro 363320-3\n\nVerksamhet: Ventilationstrummor,\njärnkonstruktioner o smidesarbeten\nAntal anställda: 15\nÅrsomsättning: 1000000\nAktiekapital: 15 000\nVerkst dir: Ing Bo G Söderström\nEtableringsår: 1947.\n\nBOR\n\nAktiekapital: 200 000\nÄgare o chefer: Civiling Oskar\nBillig, ing Gustaf Billig\nEtableringsår: 1901.\n\nBORÅS DRAPERI- &amp;\nGARDINFABRIK, AB\n\nPnr 502 35\n\nBorås, Johannelundsg 34. Tel\n033-13 74 40. Tga Curtain. Telex\n36122\n\nVerksamhet: Tillverkar gardiner\nAktiekapital: 300 000\nVerkst dir: Pål Pålsson\nEtableringsår: 1907.\n\nCARLSSON AB, ALVAR\n\nPnr 11135\n\nStockholm, Kungsg 54. Tel\n08-23 33 25, 23 33 26. Bankgiro\n48-3491. Postgiro 57272. Tga Permond\nVerksamhet: Tillverkar o säljer\nkem tekn artiklar\nAntal anställda: 13\nÅrsomsättning: 1000 000\nAktiekapital: 120 000\nVerkst din Alvar Carlsson\nEtableringsår: 1933.",
    "structured": {
        "1": {
            "company_name": "VIBRASUG, AB",
            "activity": "Tillverkning, försäljning, montering o service av Vibra-sugaren Sanator, desinfektions-apparaten Desinator o städutrust-ningar",
            "establishment_year": 1967,
            "employees": 13,
            "annual_turnover": 2500000,
            "capital": 100000,
            "key_personnel": [
                {
                    "name": "Rolf Hallström",
                    "position": "Ekonom"
                }
            ]
        },
        "2": {
            "company_name": "VIBRO-VERKEN, AB",
            "activity": "Betongvibratorer, jordpackningsmaskiner, industri-vibratorer",
            "establishment_year": 1940,
            "capital": 10000000,
            "key_personnel": [
                {
                    "name": "Sven Jonson",
                    "position": "Verkst dir"
                }
            ]
        },
        "3": {
            "company_name": "ARI AB",
            "activity": "Tillverkar Ari sågverksmaskiner, flishuggmaskiner o transportanordningar",
            "establishment_year": 1938,
            "capital": 480000,
            "key_personnel": [
                {
                    "name": "Paul Säfsten",
                    "position": "Verkst dir"
                }
            ]
        },
        "4": {
            "company_name": "ARIADNE AB, INREDNINGSBOLAGET",
            "activity": "Tillverkar o säljer system för varuvisning till affärer",
            "establishment_year": 1951
        },
        "5": {
            "company_name": "MEMA GULD & SILVER AB",
            "activity": "Tillverkar bordsbestick o bordsartiklar i silver o försilvrat",
            "establishment_year": 1912,
            "employees": 50,
            "annual_turnover": 4400000,
            "capital": 165200,
            "key_personnel": [
                {
                    "name": "Sven E Ericsson jr",
                    "position": "Verkst dir"
                }
            ]
        },
        "6": {
            "company_name": "MEMOTEKNIK AB",
            "activity": "Memofon telefonsystem, elektroniska anläggningar o system för dörr- o telefonsignaler. Ljus växlare för reklamändamål. Resultattavlor o voteringsanläggningar. Trådlös larm o manöversystem. Effektomvandlare. Hel-transistoriserade ljudanläggningar. Specialutrustningar för kyrkor. Automatik för industrier",
            "establishment_year": 1965,
            "employees": 10,
            "annual_turnover": 1000000,
            "capital": 50000,
            "key_personnel": [
                {
                    "name": "C E Steinwall",
                    "position": "Verkst dir"
                }
            ]
        },
        "7": {
            "company_name": "TRANSINTRO. AB",
            "activity": "Utvecklar, konstruerar o tillverkar ljudutrustningar o undervisningsinstrument. Företaget har ett helägt dotterbolag, Re-ma Electronic AB, som utvecklar o tillverkar elektronisk styrutrustning för sågverk",
            "establishment_year": 1955,
            "employees": 50,
            "annual_turnover": 3000000,
            "capital": 1000000,
            "key_personnel": [
                {
                    "name": "Hans Dirtoft",
                    "position": "Veikst dir"
                }
            ]
        },
        "8": {
            "company_name": "malmberg, ab elof",
            "activity": "Tillverkar flytvästar, ryggsäckar, tält samt utrustning för skidåkning, ishockey, bandy, orientering, trav, hund, jakt, båg-skytte o fotboll",
            "establishment_year": 1905,
            "annual_turnover": 20000000,
            "capital": 480000,
            "key_personnel": [
                {
                    "name": "Lennart Malmberg",
                    "position": "Verkst dir"
                }
            ]
        },
        "9": {
            "company_name": "malmberg, ab frank",
            "activity": "Elektrisk Isoleringsmaterial i parti, plaster mm",
            "establishment_year": 1912,
            "capital": 40000,
            "key_personnel": [
                {
                    "name": "H Peterzon",
                    "position": "Disp"
                }
            ]
        },
        "10": {
            "company_name": "AMBO, AB",
            "activity": "Tillverkar påsar, säckar, slang, folie o knutlösa nät i polyeten samt pressgods i härdplast",
            "establishment_year": 1943,
            "employees": 50,
            "annual_turnover": 4500000,
            "capital": 90000,
            "key_personnel": [
                {
                    "name": "Carl Bolin",
                    "position": "Verkst dir"
                },
                {
                    "name": "C-G Persson",
                    "position": "Försäljning"
                }
            ]
        },
        "11": {
            "company_name": "AMEC-PRODUKTER, AB",
            "activity": "Grosshandelsförsäljning av häftverktyg, häftapparater o häftklammer till industrier o storförbrukare",
            "establishment_year": 1957,
            "capital": 20000,
            "key_personnel": [
                {
                    "name": "C H Söderlindh",
                    "position": "Ägare o chef"
                }
            ]
        },
        "12": {
            "company_name": "BRATTS KOL & KOKS AB",
            "activity": "Säljer kol, koks, oljor o gödningsmedel. Fastighetsmäklare",
            "establishment_year": 1877,
            "capital": 100000,
            "key_personnel": [
                {
                    "name": "Ake Brandt",
                    "position": "Verkst dir"
                }
            ]
        },
        "13": {
            "company_name": "GÄVLE PLÅT AB",
            "activity": "Ventilationstrummor, järnkonstruktioner o smidesarbeten",
            "establishment_year": 1947,
            "employees": 15,
            "annual_turnover": 1000000,
            "capital": 15000,
            "key_personnel": [
                {
                    "name": "Ing Bo G Söderström",
                    "position": "Verkst dir"
                }
            ]
        },
        "14": {
            "company_name": "BOR",
            "capital": 200000,
            "key_personnel": [
                {
                    "name": "Oskar Billig",
                    "position": "Ägare o chefer"
                }
            ],
            "establishment_year": 1901
        },
        "15": {
            "company_name": "BORÅS DRAPERI- & GARDINFABRIK, AB",
            "activity": "Tillverkar gardiner",
            "establishment_year": 1907,
            "capital": 300000,
            "key_personnel": [
                {
                    "name": "Pål Pålsson",
                    "position": "Verkst dir"
                }
            ]
        },
        "16": {
            "company_name": "CARLSSON AB, ALVAR",
            "activity": "Tillverkar o säljer kem tekn artiklar",
            "establishment_year": 1933,
            "employees": 13,
            "annual_turnover": 1000000,
            "capital": 120000,
            "key_personnel": [
                {
                    "name": "Alvar Carlsson",
                    "position": "Verkst din"
                }
            ]
        }
    }
}