{
    "original": "HOGANÄSMOB LER AB\n\nPnr 263 01\n\nHöganäs 1. Box 30. Tel 042-452 90.\nBankgiro 340-5628. Postgiro\n337070-7\n\nVerksamhet: Tillverkar\nstålrörs-möbler för kontor o restauranger\nAntal anställda: 56\nÅrsomsättning: 4 800 000\nAktiekapital: 40 000\nVerkst dir: Bertil Gustafson\nEtableringsår: 1957.\n\nARY FANÉRPRODUKTER, AB\n\nPnr 382 00\n\nNybro, Gröndalsg 7. Box 20. Tel\n0481-140 85. Bankgiro 856-1359.\nPostgiro 340294-8. Tga Arytrade,\nKalmar\n\nVerksamhet: Tillverkar\nformpres-sade serveringsbrickor o\nformpres-sade fanérdetaljer såsom\nfåtöljstommar. stolsitsar, ryggbrickor\nm m. Vakuumformad plast\nAvdelningskontor: Stockholm VA,\nBirger Jarlsg 71. Tel 08-10 22 18\nVarunamn: Ary\nAntal anställda: 95\nÅrsomsättning: 6 000 000\nAktiekapital: 200 000\n\nStyrelse: Dlr H Bengtner (ordf),\nryttmäst F Wrede, kamrer L\nEdse-nius, fru G-L Bengtner\nVerkst din H Bengtner\nEtableringsår. 1947.\n\nSVENSK LECA, AB\n\nPnr 20110\n\nMalmö 1, Pack. Skeppsbron 11. Tel\n040-742 00. Postgiro 533430-5. Tga\nSvenskleca\n\nVerksamhet: Fabrik för\ntillverkning av värmeisoleringsmaterial o\nporballastmaterial av expanderad\nbränd lera\n\nFabrik o försäljningskontor: 580 06\nLinköping 6, Gärstad. Box 6075.\nTel 013-111430\nAntal anställda: 69\nÅrsomsättning: 8 500 000\nAktiekapital: 4 500 000\nStyrelse: Bankdir Gösta Fries,\nlandsretssagf Henrik Hoffmeyer,\ndir Rutger Larson, ambassadör Sten\nLindh, dir Elam Tunhammar, dir\nSune Wetterlundh\nVerkst dir: Ake Rydberg\nEtableringsår: 1961.\n\nSVENSK LEVERANS.\nTIDNING AB\n\nPnr 101 23\n\nStockholm 1, Torsg 2. Box 247.\nTel 08-1179 27, 117948. Bankgiro\n400-7233. Postgiro 409023-9\nVerksamhet: Organ för svenskt\nnäringsliv o offentlig upphandling\nAktiekapital: 10 300.\n\nSVENSK LJUDTEKNIK, AB\n\nPnr 201 22\n\nMalmö 1, Box 234. S Förstadsg 8.\nTel 040-11 37 10. Bankgiro\n874-7537. Postgiro 431015-7. Tga Svea-\n\nvox\n\nVerksamhet: Säljer elektr\nhörapparater\n\nAntal anställda: 20\n\nAktiekapital: 165 000\nVerkst dir: Walter Krahlmark\nEtableringsår: 1951.\n\nBILDEVE I HELSINGBORG AB\n\nPnr 25102\n\nHelsingborg 1, Box 28. Carl Krooksg\n30. Tel 042-18 0 0 00. Bankgiro\n652-9887. Postgiro 160167-3\nVerksamhet: Bilförsäljning. Volvo\npersonbilar o lastbilar.\nBilverk-stader o bensinstationer\nAvdelningskontor: Höganäs,\nTriangelplatsen. Tel 042-423 20\nAntal asntäUda: 201\nÅrsomsättning: 41923 000\nAktiekapital: 1000 000\nVerkst dir: K E Ossian Falkengren\nEtableringsår: 1943.\n\nBILDEVE I\nMUNKALJUNGBY AB\n\nPnr 260 80\n\nMunkaljungby, Box 25. Tel\n0431-307 30. Bankgiro 672-2086.\nPostgiro 167394-6\n\nVerksamhet: Tillverkar hisskorgar,\nhydrauliska lyftredskap,\nbetongformar samt plåt- o\njärnkonstruktioner\n\nAntal anstäUda: 47\nÅrsomsättning: 2 000 000\nAktiekapital: 100 000\nVerkst dir: Nils Viebke\nEtableringsår: 1930.\n\nBILDEVE I STOCKHOLM AB\n\nPnr 11447\n\nStockholm, Linnég 17. Tel\n08-67 00 60. Bankgiro 56-4527.\nPostgiro 193911. Tga Bildeve\nVerksamhet: Säljer Deves\nhydrauliska hissar, lyftare o kolvringar\nsamt bilservicelyftare\nVarunamn: Deves\nAntal anstäUda: 40\nÅrsomsättning: 6 000 000\nAktiekapital: 300 000\nVerkst dir: Algot L Viebke\nEtableringsår: 1943.\n\nBILFRAKT BJUV EK FOREN\n\nPnr 267 00\n\nBjuv. Tel 042-789 30. Bankgiro\n671-4281. Postgiro 518303-3\nVerksamhet: Inrikes\ntransportförmedling\n\nAntal anstäUda: 7\nÅrsomsättning: 9 500 000\nChef: Göthe Persson\nEtableringsår: 1959.\n\nSMÅLANDSSLUJD, AB\n\nPnr 33100\n\nVärnamo, Hjälshammar. Tel\n0370-240 1 3. Bankgiro 141-8268.\nPost-giro 288265-2\n\nVerksamhet: Tillverkar\nhushållsartiklar i teak o furu såsom\nsalladskålar, brickor, sillstånkor, sal-\n\nladiärer, smör- o brödställ,\nkrydd-satser etc, utför träljusstakar i\nolika modeller o träslag.\nBeställningsartiklar efter ritning m m\nAntal anstäUda: 40\nÅrsomsättning: 1 500 000\nAktiekapital: 75 000\nVerkst din Ragnar Höglund\nEtableringsår: 1944\nOmbildat till aktiebolag 1952.\n\nSMÅLANDSSTENARS\nMEKANISKA VERKSTAD, AB\n\nPnr 330 23\n\nSmålandsstenar, Parkg. Tel\n0371-310 40. Bankgiro 427-6275. Postgiro\n22598-7\n\nVerksamhet: Tillverkar o säljer\nexcenterpressar, specialpressar o\nautomatmaskiner\nAntal anstäUda: 55\nÅrsomsättning: 6 000 000\nAktiekapital: 260 000\nVerkst dir: Ture Peterson\nEtableringsår: 1921.\n\nSMÅLANDSSTENARS ÅNGSÅG\n&amp; SNICKERIFABRIK, AB\n\nPnr 330 23\n\nSmålandsstenar, Fack 22. Tel\n0371-31100. Bankgiro 427-6291.\nPostgiro 22590-4. Tga Trä\nVerksamhet: Tillverkar sågade o\nhyvlade trävaror, kökssnickerier\nsamt monteringsfärdiga hus\nAntal anstäUda: 116\nÅrsomsättning: 16 000 000\nAktiekapital: 1008 000\nVerkst dir: Erie Storck\nEtableringsår: 1874.\n\nSMÅLANDS.TIDNINGENS\nTRYCKERI AB\n\nPnr 575 00\n\nEksjö, Stora Torget 4. Box 95. Tel\n0381-132 00. Bankgiro 14-4574.\nPostgiro 28300. Telex 3717\nVerksamhet: Utger\nSmålands-Tidningen, Smålands Dagblad,\nVefc-landa-Posten o Tranås Tidning\n(Hallpressen). Nettoupplaga 35 500\nexemplar\n\nAntal anstäUda: 125\nÅrsomsättning: 10 900 000\nAktiekapital: 120 000\nVerkst dir: Stig Fredriksson\nV verkst dir: Arne Argus\nEtableringsår: 1918\nDotterbolag till H Halls\nBoktryckeri AB, Jönköping.\n\nSMÅLANDSÅKERIER AB\n\nPnr 552 42\n\nJönköping, John Bauersg 5. Tel\n036-1183 50. Bankgiro 342-0098.\nPostgiro 6545\n\nVerksamhet: utför tjänster inom\ntransportbranschen\nAntal anställda: 6\nÅrsomsättning: 10 000 000\nAktiekapital: 120 000\nVerkst dir: Uno Ryttegård\nEtableringsår: 1957.\n\nJAGER &amp; DEBONG, AB\n\nPnr 100 53\n\nStockholm 37, Tredje Bassängv.\nFack. Tel 08-67 05 70. Bankgiro\n16-7418. Postgiro 50794. Tga\nJaegerdebong\n\nVerksamhet: Tillverkar o säljer en\ngros alla slags fodermedel,\nspannmål, gödningsämnen, utsäden,\nstråfoder, fågelfröer o\njordbrukskemikalier\n\nVarunamn: Debongs\nAntal anställda: 28\nAktiekapital: 350 000\nVerkst dir: Disp Sven E Debong\nEtableringsår: 1930.\n\nAHLZÉN, AB CARL\n\nPnr 651 02\n\nKarlstad 1, Box 5. Tyggårdsviken.\nTel 054-1566 30. Bankgiro\n100-0603. Postgiro 70958-4\nVerksamhet: Byggnadsmaterial o\nsnickerier, trävaror\nAntal anställda: 23\nAktiekapital: 150000\nVerkst dir: Stefan Järund\nEtableringsår: 1917.\n\nADLER KARLSSON AB\n\nPnr 292 00\n\nKarlshamn, Bellevuev 7. Tel\n0454-106 88, 11806. Bankgiro 86-2121.\nPostgiro 33163\n\nVerksamhet: Säljer emballage i\nparti\n\nAktiekapital: 30 000\nVerkst dir: Fru Elsa Karlsson\nEtableringsår: 1934.\n\nCA-VERKEN AB\n\nPnr 57600\n\nSävsjö, Box 112. Tel 03 82-116 20.\nBankgiro 285-4156. Postgiro\n124577-8. Tga CA-Verken\nVerksamhet: Tillverkar\npneumatiska o hydrauliska komponenter\nVarunamn: Ceve\nAntal anställda: 35\nÅrsomsättning: 2 500 000\nAktiekapital: 150 000\nVerkst dir: Ing Anders Carlegren\nEtableringsår: 1957.\n\nC D KONSULT CASSELMO &amp;\nDAHL, AB\n\nPnr 400 52\n\nGöteborg 50, Januarig 4. Box\n50013. Tel 031-46 02 10. Bankgiro\n43-1085. Postgiro 627811\nVerksamhet: Konsulterande\ningenjörer inom VVS\nAntal anställda: 13\nAktiekapital: 5 000\nVerkst dir: Ing Ulf Casselmo\nEtableringsår: 1965.\n\nÅMETALL AB\n\nPnr 267 00\n\nBjuv, Mörarpsv. Postl 318 A. Tel\n042-783 29. Bankgiro 671-3945.\nPostgiro 582481-8\nVerksamhet: Mekanisk verkstad\nAntal anställda: 15\nAktiekapital: 5 000\nVerkst din Fabr Knut Pettersson\nEtableringsån 1961.",
    "structured": {
        "1": {
            "company_name": "HOGANÄSMOB LER AB",
            "activity": "Tillverkar stålrörs-möbler för kontor o restauranger",
            "establishment_year": 1957,
            "employees": 56,
            "annual_turnover": 4800000,
            "capital": 40000,
            "key_personnel": [
                {
                    "name": "Bertil Gustafson",
                    "position": "Verkst dir"
                }
            ]
        },
        "2": {
            "company_name": "ARY FANÉRPRODUKTER, AB",
            "activity": "Tillverkar formpres-sade serveringsbrickor o formpres-sade fanérdetaljer såsom fåtöljstommar, stolsitsar, ryggbrickor m m. Vakuumformad plast",
            "establishment_year": 1947,
            "employees": 95,
            "annual_turnover": 6000000,
            "capital": 200000,
            "key_personnel": [
                {
                    "name": "H Bengtner",
                    "position": "Styrelseordförande"
                },
                {
                    "name": "F Wrede",
                    "position": "Ryttmästare"
                },
                {
                    "name": "L Edsenius",
                    "position": "Kamrer"
                },
                {
                    "name": "G-L Bengtner",
                    "position": "Fru"
                },
                {
                    "name": "H Bengtner",
                    "position": "Verkst dir"
                }
            ]
        },
        "3": {
            "company_name": "SVENSK LECA, AB",
            "activity": "Fabrik för tillverkning av värmeisoleringsmaterial o porballastmaterial av expanderad bränd lera",
            "establishment_year": 1961,
            "employees": 69,
            "annual_turnover": 8500000,
            "capital": 4500000,
            "key_personnel": [
                {
                    "name": "Gösta Fries",
                    "position": "Bankdirektör"
                },
                {
                    "name": "Henrik Hoffmeyer",
                    "position": "Landsretssagf"
                },
                {
                    "name": "Rutger Larson",
                    "position": "Dir"
                },
                {
                    "name": "Sten Lindh",
                    "position": "Ambassadör"
                },
                {
                    "name": "Elam Tunhammar",
                    "position": "Dir"
                },
                {
                    "name": "Sune Wetterlundh",
                    "position": "Dir"
                },
                {
                    "name": "Ake Rydberg",
                    "position": "Verkst dir"
                }
            ]
        },
        "4": {
            "company_name": "SVENSK LJUDTEKNIK, AB",
            "activity": "Säljer elektr hörapparater",
            "establishment_year": 1951,
            "employees": 20,
            "annual_turnover": null,
            "capital": 165000,
            "key_personnel": [
                {
                    "name": "Walter Krahlmark",
                    "position": "Verkst dir"
                }
            ]
        },
        "5": {
            "company_name": "BILDEVE I HELSINGBORG AB",
            "activity": "Bilförsäljning. Volvo personbilar o lastbilar. Bilverk-stader o bensinstationer",
            "establishment_year": 1943,
            "employees": 201,
            "annual_turnover": 41923000,
            "capital": 1000000,
            "key_personnel": [
                {
                    "name": "K E Ossian Falkengren",
                    "position": "Verkst dir"
                }
            ]
        }
    }
}