{
    "original": "SMT MACHINE COMPANY AB\n\nPnr 723 48\n\nVästerås, Björnöv 20. Tel\n021-12 0340. Bankgiro 11-1000.\nPostgiro 118780. Telex 40602. Tga\n\nSwedemachine\n\nVerksamhet: Tillverkning av\nsvarvar, borr- o fräsmaskiner samt\nverktyg\n\nFiUal: SMT Karlskogaverken. Tel\n0586-360 90\n\nSMT Ronnebyverken. Tel\n0457-128 70\n\nDotterbolag: AB Thorns Mek\nVerkstad. Tel 08-52 02 25\nAbene AB. Tel 08-44 06 45\nAntal anstäUda: 800\nÅrsomsättning: 82 000 000\nAktiekapital: 18 00,0 000\nVerkst dir: Lennart Jansson\nEtableringsår: 1969.\n\nLUNDBERGS BRANDREDSKAP\n\nPnr 93100\n\nSkellefteå, Morög 39. Tel\n0910-753 95. Bankgiro 659-7231.\nPostgiro 488689-1\n\nVerksamhet; Säljer brandsläckare\no tillbehör. Utför omladdning,\növersyn o konträktservice\nChef: Kurt-Olof Lundberg\nEtableringsår. 1967.\n\nSTÅHLBERG &amp; NILSSON AB\n\nPnr 125 21\n\nÄlvsjö 1, Långsjöv 51 A. Box 25.\nTel 08-47 29 80. Bankgiro 731-0162.\nPostgiro 58559-6. Tga Diagonal.\nTelex 10626\n\nVerksamhet: Agentur- o\ngrosshandel: elmotorer, elreläer m m\nAntal anstäUda: 10\nAktiekapital: 100 000\nVerkst dir: Agge Ståhlberg\nEtableringsår: 1928.\n\nULTRALJUD AB\n\nPnr 19106\n\nSollentuna 6, Box 6015. Tel\n08-714 04 41. Postgiro 465795\nVerksamhet: Säljer o installerar\nmaterialprovningsutrustningar\nAntal anställda: 5\nÅrsomsättning: 1000 000\nAktiekapital: 5 000\nVerkst din Civiling Johan Wendt\nEtableringsår: 1951.\n\nHANSSON, AB KAJ\n\nPnr 400 31\n\nGöteborg 25, Doktor Fries Torg.\nBox 25070. Tel 031-82 35 00.\nBankgiro 10-6184. Postgiro 49900\nVerksamhet: Försäljning av\nelektronikapparater o komponenter\nAktiekapital: 10 000\nVerkst dir: Kaj Hansson\nEtableringsår: 1967.\n\nHAGA TEGEL AB\n\nPnr 19901\n\nEnköping 1, Box 93. Haga. Tel\n0171-333 35. Bankgiro 230-9524.\nPostgiro 6481-6\n\nVerksamhet: Tillverkar fasadtegel,\nbeklädnadstegel rött o brunt,\nmurtegel o 20-tegel\nAntal anstäUda: \"30\nAktiekapital: 400 000\nVerkst dir: Bengt Lyckman\nEtableringsår: 1883.\n\nSVETSMEKANO\n\nPnr 596 00\n\nSkänninge, Industrig. Tel\n0142-403 83, kontor 413 47. Bankgiro\n130-1027. Postgiro 542671-3\nVerksamhet: Utför mekaniska\narbeten. El- o gassvetsning. Specialitèt:\nspannmålslådor, källarinredningar,\nnätväggar, nätdörrar o takstolar.\nJärn- o stålkonstruktioner\nAntal anställda: 10\nÅrsomsättning: 1300 000\nChef: Pabr Einar Engblom\nEtableringsår: 1960.\n\nBLOKK,\nFABRIKS-AKTIEBOLAGET\n\nPnr 631 03\n\nEskilstuna 1, Box 247. Kungsg 78.\nTel 016-11 71 60. Bankgiro\n367-9842. Postgiro 170489-9\nVerksamhet: Tillverkar fönster,\ndörrar, butiksfasader o wirelås\nVaranamn: Blokk\nAktiekapital: 40 000\nVerkst dir: Disp Carl Lewerentz\nEtableringsår: 1930\nDotterbolag: AB Idesta, Swedish\nSteel Products Ltd AB, AB\nSvenska Stålprodukter, alla i Eskilstuna.\n\nBLOMS ÅKERI AB\n\nPnr 580 03\n\nLinköping 3, Box 3068. Tel\n013-1302 20. Bankgiro 34-6971.\nPostgiro 264612\n\nVerksamhet: Akerirörelse\nAntal anställda: 140\nÅrsomsättning: 18 000 000\nAktiekapital: 50 000\nVerkst dir: Sture Ernskog.\n\nBLOM SÅGVERK &amp; HYVLERI,\nHELGE\n\nPnr 598 00\n\nVimmerby, Box 99. Lindhult. Tel\n0492-106 78. Postgiro 175535-4\nVerksamhet: Sågverk o\nträvaruexport\n\nSågverk: Rumskulla. Tel 0496-400 58\nVirkesterminal: Oskarshamn,\nBräd-holmskajen. Tel 0491-115 78\nAntal anställda: 20\nÅrsomsättning: 15 000 000\nChef: Trävaruhandl Helge Blom\nEtableringsår: 1933.\n\nBLOMS BOKTRYCKERI\nAB, LINKOLN\n\nPnr 111 20\n\nStockholm, Gamla Brog 38. Tel\n08-23 20 40. Bankgiro 33-1033.\nPostgiro 3540-2\nVerksamhet: Trycksaker\nAntal anställda: 15\nAktiekapital: 50000\nVerkst dir: Lars Ojdahl\nEtableringsår: 1898.\n\nBLOMBERGS\nNYA AB, ORIEL\n\nPnr 71100\n\nLindesberg, Box 89. Smedjeg 15.\nTel 0581-12470. Bankgiro\n821-4108. Postgiro 70672-1\nVerksamhet: Tryckeri för\ntillverkning av blanketter i snabbset\nAntal anställda: 45\nAktiekapital: 70 000\nVerkst din Disp Bengt Bengtsson\nEtableringsår: 1914.\n\nSVENSSON AB, GÖSTA\n\nPnr 826 01\n\nSöderhamn 1, Tullg 11. Box 65.\nTel 0270-122 61. Bankgiro\n78-9598. Postgiro 295196\nVerksamhet: Tillverkar spiskåpor\no laboratorieskåp\nAntal anställda: 10\nAktiekapital: 30 000\nVerkst din Gösta Svensson\nEtableringsår: 1942.\n\nSVENSSON TEXTIL AB,\nGÖSTA\n\nPnr 42102\n\nVästra Frölunda 2, Frökontrollsg 5.\nFack. Tel 031-45 01 10. Bankgiro\n42-0446. Postgiro 48463.\nTga Carptrad. Telex 2212\nVerksamhet: Mattor o möbeltyger i\nparti, import, frihamnslager samt\nrederi\n\nAntal anställda: 57\nAktiekapital: 500 000\nVerkst dir: Gösta Svensson\nEtableringsår: 1938.\n\nJOHANSSONS SÖNER, M\n\nPnr 330 30\n\nGnosjö, Söderby. Tel 0370-912 38.\nPostgiro 85012-3. Tga Johansson\nVerksamhet: Tillverkar\ngjuterisik-tar, oljesilar o bensinsilar\nÄgare o chefer: Gunnar Johansson,\nMagnus Johansson\nEtableringsår: 1894.",
    "structured": {
        "1": {
            "company_name": "SMT MACHINE COMPANY AB",
            "pnr": "723 48",
            "address": "Västerås, Björnöv 20",
            "phone_number": "021-12 0340",
            "bank_details": {
                "bankgiro": "11-1000",
                "postgiro": "118780"
            },
            "activity": "Tillverkning av svarvar, borr- o fräsmaskiner samt verktyg",
            "employees": 800,
            "annual_turnover": 82000000,
            "capital": 18000000,
            "key_personnel": [
                {
                    "name": "Lennart Jansson",
                    "position": "Verkst dir"
                }
            ],
            "establishment_year": 1969
        },
        "2": {
            "company_name": "LUNDBERGS BRANDREDSKAP",
            "pnr": "93100",
            "address": "Skellefteå, Morög 39",
            "phone_number": "0910-753 95",
            "bank_details": {
                "bankgiro": "659-7231",
                "postgiro": "488689-1"
            },
            "activity": "Säljer brandsläckare o tillbehör. Utför omladdning, översyn o konträktservice",
            "establishment_year": 1967,
            "key_personnel": [
                {
                    "name": "Kurt-Olof Lundberg",
                    "position": "Chef"
                }
            ]
        },
        "3": {
            "company_name": "STÅHLBERG & NILSSON AB",
            "pnr": "125 21",
            "address": "Älvsjö 1, Långsjöv 51 A, Box 25",
            "phone_number": "08-47 29 80",
            "bank_details": {
                "bankgiro": "731-0162",
                "postgiro": "58559-6"
            },
            "activity": "Agentur- o grosshandel: elmotorer, elreläer m m",
            "employees": 10,
            "capital": 100000,
            "key_personnel": [
                {
                    "name": "Agge Ståhlberg",
                    "position": "Verkst dir"
                }
            ],
            "establishment_year": 1928
        },
        "4": {
            "company_name": "ULTRALJUD AB",
            "pnr": "19106",
            "address": "Sollentuna 6, Box 6015",
            "phone_number": "08-714 04 41",
            "postgiro": "465795",
            "activity": "Säljer o installerar materialprovningsutrustningar",
            "employees": 5,
            "annual_turnover": 1000000,
            "capital": 5000,
            "key_personnel": [
                {
                    "name": "Civiling Johan Wendt",
                    "position": "Verkst dir"
                }
            ],
            "establishment_year": 1951
        },
        "5": {
            "company_name": "HANSSON, AB KAJ",
            "pnr": "400 31",
            "address": "Göteborg 25, Doktor Fries Torg, Box 25070",
            "phone_number": "031-82 35 00",
            "bank_details": {
                "bankgiro": "10-6184",
                "postgiro": "49900"
            },
            "activity": "Försäljning av elektronikapparater o komponenter",
            "capital": 10000,
            "key_personnel": [
                {
                    "name": "Kaj Hansson",
                    "position": "Verkst dir"
                }
            ],
            "establishment_year": 1967
        },
        "6": {
            "company_name": "HAGA TEGEL AB",
            "pnr": "19901",
            "address": "Enköping 1, Box 93, Haga",
            "phone_number": "0171-333 35",
            "bank_details": {
                "bankgiro": "230-9524",
                "postgiro": "6481-6"
            },
            "activity": "Tillverkar fasadtegel, beklädnadstegel rött o brunt, murtegel o 20-tegel",
            "employees": 30,
            "capital": 400000,
            "key_personnel": [
                {
                    "name": "Bengt Lyckman",
                    "position": "Verkst dir"
                }
            ],
            "establishment_year": 1883
        },
        "7": {
            "company_name": "SVETSMEKANO",
            "pnr": "596 00",
            "address": "Skänninge, Industrig",
            "phone_number": "0142-403 83, kontor 413 47",
            "bank_details": {
                "bankgiro": "130-1027",
                "postgiro": "542671-3"
            },
            "activity": "Utför mekaniska arbeten. El- o gassvetsning. Specialitèt: spannmålslådor, källarinredningar, nätväggar, nätdörrar o takstolar. Järn- o stålkonstruktioner",
            "employees": 10,
            "annual_turnover": 1300000,
            "key_personnel": [
                {
                    "name": "Pabr Einar Engblom",
                    "position": "Chef"
                }
            ],
            "establishment_year": 1960
        },
        "8": {
            "company_name": "BLOKK, FABRIKS-AKTIEBOLAGET",
            "pnr": "631 03",
            "address": "Eskilstuna 1, Box 247, Kungsg 78",
            "phone_number": "016-11 71 60",
            "bank_details": {
                "bankgiro": "367-9842",
                "postgiro": "170489-9"
            },
            "activity": "Tillverkar fönster, dörrar, butiksfasader o wirelås",
            "varanamn": "Blokk",
            "capital": 40000,
            "key_personnel": [
                {
                    "name": "Disp Carl Lewerentz",
                    "position": "Verkst dir"
                }
            ],
            "establishment_year": 1930,
            "dotterbolag": [
                "AB Idesta",
                "Swedish Steel Products Ltd AB",
                "AB Svenska Stålprodukter"
            ]
        },
        "9": {
            "company_name": "BLOMS ÅKERI AB",
            "pnr": "580 03",
            "address": "Linköping 3, Box 3068",
            "phone_number": "013-1302 20",
            "bank_details": {
                "bankgiro": "34-6971",
                "postgiro": "264612"
            },
            "activity": "Akerirörelse",
            "employees": 140,
            "annual_turnover": 18000000,
            "capital": 50000,
            "key_personnel": [
                {
                    "name": "Sture Ernskog",
                    "position": "Verkst dir"
                }
            ]
        },
        "10": {
            "company_name": "BLOM SÅGVERK & HYVLERI, HELGE",
            "pnr": "598 00",
            "address": "Vimmerby, Box 99, Lindhult",
            "phone_number": "0492-106 78",
            "postgiro": "175535-4",
            "activity": "Sågverk o trävaruexport",
            "employees": 20,
            "annual_turnover": 15000000,
            "key_personnel": [
                {
                    "name": "Trävaruhandl Helge Blom",
                    "position": "Chef"
                }
            ],
            "establishment_year": 1933
        },
        "11": {
            "company_name": "BLOMS BOKTRYCKERI AB, LINKOLN",
            "pnr": "111 20",
            "address": "Stockholm, Gamla Brog 38",
            "phone_number": "08-23 20 40",
            "bank_details": {
                "bankgiro": "33-1033",
                "postgiro": "3540-2"
            },
            "activity": "Trycksaker",
            "employees": 15,
            "capital": 50000,
            "key_personnel": [
                {
                    "name": "Lars Ojdahl",
                    "position": "Verkst dir"
                }
            ],
            "establishment_year": 1898
        },
        "12": {
            "company_name": "BLOMBERGS NYA AB, ORIEL",
            "pnr": "71100",
            "address": "Lindesberg, Box 89, Smedjeg 15",
            "phone_number": "0581-12470",
            "bank_details": {
                "bankgiro": "821-4108",
                "postgiro": "70672-1"
            },
            "activity": "Tryckeri för tillverkning av blanketter i snabbset",
            "employees": 45,
            "capital": 70000,
            "key_personnel": [
                {
                    "name": "Disp Bengt Bengtsson",
                    "position": "Verkst din"
                }
            ],
            "establishment_year": 1914
        },
        "13": {
            "company_name": "SVENSSON AB, GÖSTA",
            "pnr": "826 01",
            "address": "Söderhamn 1, Tullg 11, Box 65",
            "phone_number": "0270-122 61",
            "bank_details": {
                "bankgiro": "78-9598",
                "postgiro": "295196"
            },
            "activity": "Tillverkar spiskåpor o laboratorieskåp",
            "employees": 10,
            "capital": 30000,
            "key_personnel": [
                {
                    "name": "Gösta Svensson",
                    "position": "Verkst din"
                }
            ],
            "establishment_year": 1942
        },
        "14": {
            "company_name": "SVENSSON TEXTIL AB, GÖSTA",
            "pnr": "42102",
            "address": "Västra Frölunda 2, Frökontrollsg 5, Fack",
            "phone_number": "031-45 01 10",
            "bank_details": {
                "bankgiro": "42-0446",
                "postgiro": "48463"
            },
            "activity": "Mattor o möbeltyger i parti, import, frihamnslager samt rederi",
            "employees": 57,
            "capital": 500000,
            "key_personnel": [
                {
                    "name": "Gösta Svensson",
                    "position": "Verkst dir"
                }
            ],
            "establishment_year": 1938
        },
        "15": {
            "company_name": "JOHANSSONS SÖNER, M",
            "pnr": "330 30",
            "address": "Gnosjö, Söderby",
            "phone_number": "0370-912 38",
            "postgiro": "85012-3",
            "activity": "Tillverkar gjuterisik-tar, oljesilar o bensinsilar",
            "key_personnel": [
                {
                    "name": "Gunnar Johansson",
                    "position": "Ägare o chefer"
                },
                {
                    "name": "Magnus Johansson",
                    "position": "Ägare o chefer"
                }
            ],
            "establishment_year": 1894
        }
    }
}