{
    "original": "ST I TO AB\n\nPnr 262 00\n\nÄngelholm, Industrig 3. Tel 0431-\n\n123 25. Bankgiro 294-1524.\nPostgiro 463810-2\n\nVerksamhet: Utför\nautomatsvarv-ning i samtliga stångmaterial samt\nfinmekaniska arbeten\nÄgare o chef: Stig Thomasson\nEtableringsår: 1949.\n\nNOMO KULLAGER AB\n\nPnr 11160\n\nStockholm, Drottningg 81 B. Tel\n08-23 3110. Bankgiro 572-9462.\nPostgiro 554855-7. Tga\nMaskinmotor. Telex 10032\nVerksamhet: Försäljer\nmaskinförnödenheter. Specialitet: kul- o\nrullager, låsringar o\ntätningsele-ment\n\nFilial: Göteborg O, Sankt Paulig\n25 A. Tel 031-800240\nVarunamn: Anderton, Fafnir, MPB,\nRBC, Steyr, Timken, Torrington,\nUnibal-Rose\nAntal anställda: 30\nEtableringsår: 1949\nOmbildat till aktiebolag 1957.\nEtt Nordisk Maskin företag.\nDotterbolag: Laakeri Oy Nomo,\nHelsingfors.\n\nNOMOS, AB\n\nPnr 21121\n\nMalmö, Västerg 35. Tel 040-308 80,\n973355. Bankgiro 87-0456.\nPostgiro 246324. Tga Solano\nVerksamhet: Agenturer. Import o\nexport av kemikalier o maskiner\nAntal anställda: 4\nAktiekapital: 50000\nVerkst dir: Ernst Wahlqvist\nEtableringsår: 1943.\n\nVÄRMEMATERIAL VVS AB\n\nPnr 57100\n\nNässjö, Industrig 42. Box 207. Tel\n0380-13250\n\nVerksamhet: Grossist i rör, värme\no sanitet\n\nAktiekapital: 50 000\nVerkst dir Disp Valdemar\nKornstrand\n\nEtableringsår: 1938.\n\nHOLSBYVERKEN, AB\n\nPnr 57015\n\nHolsbybmnn. Tel 0383-502 01,\n50213. Tga Holsbyverken\nVerksamhet: Tillverkar handels- o\noylindergjutgods,\nmodellutrustningar o utför bearbetning av\ngjutgods. Beställningsgjutgods i\nSIS-kvaliteterna 0115-0130, segjärn o\nmeehanite. Modelltillverkning\nAntal anställda: 165\nÅrsomsättning: 14 000 000\nAktiekapital: 150 000\nStyrelse: Bankdir Bror Carlsson\n(ordf), ing Ewert Ytterell,\ndu-Helge Engström\nVerkst dir: Ing Ewert Ytterell\nEtableringsår: 1948.\n\nHOLST GOLVBELÄGGNING,\nAB BRÖDERNA\n\nPnr 57100\n\nNässjö, Rådhusg 8. Tel\n0380-137 78\n\nVerksamhet: Utför\ngolvbeläggningar, slipning o ytbehandling av\ngolv\n\nAktiekapital: 66 000\nVerkst dir: Hilding Holst\nEtableringsår: 1960.\n\nGAHMS FÖRSÄLJNINGS AB, G\n\nPnr 117 28\n\nStockholm SV, Hornsg 160. Tel\n08-69 03 00. Bankgiro 23-6760.\nPostgiro 52324. Tga Ledergahm\nVerksamhet: Säljer läderarbeten\no lädervaror samt reseffekter\nAntal anställda: 42\nÅrsomsättning: 4100 000\nAktiekapital: 450 000\nVerkst dir: Bengt af Kleen\nEtableringsår: 1929.\n\nSKEPPSHULTS GJUTERI AB\n\nPnr 330 24\n\nSkeppshult, Box 69. Tel 0371-36270.\nBankgiro 427-6267. Postgiro\n22601-9. Tga Gjuteriet\nVerksamhet: Byggnads-, handels-,\nhushålls-, sanitets- o\nbeställnings-gjutgods. Specialitet: stekpannor\nAntal anstäUda: 46\nÅrsomsättning: 3 500 000\nAktiekapital: 111000\nVerkst dir: Fru Gunnel Wennberg\nV verkst dir: Roland Lindström\nEtableringsår: 1906.\n\nSKEPPSUPPHUGGNING I\nGOTEBORG AB\n\nPnr 402 72\n\nGöteborg 8, Tingstad. Box 8880.\nTel 031-23 65 36, 2215 74. Bankgiro\n186-2168. Postgiro 629250-2.\nTga Scrapmetal.\nTelex 2551 IRONMET S\nVerksamhet: Nedskrotning av\nfartyg, köp o försäljning av järn o\nmetaller\n\nAktiekapital: 30 000\nVerkst dir. T Johannisson\nEtableringsår: 1966.\n\nSKF STAL\n\nse Svenska Kullagerfabriken\nStåldivisionen SKF Stål.\n\nSKF-MALCUS AB\n\nPnr 30103\n\nHalmstad 1, Box 170. Kristian IV:s\nväg 3. Tel 035-1183 00. Bankgiro\n423-5511. Postgiro 14707-4. Tga\nMalcus. Telex 38056\nVerksamhet: Tillverkar o säljer\nspiralborrar, gängtappar o gängsnitt,\nslipmaskiner såsom\nplanslipmaski-ner, centerlessüpmaskiner o\nrund-slipmaskiner\nVarunamn: Malcus, SKF\nAntal anstäUda: 680\nÅrsomsättning: 46 000 000\nAktiekapital: 10000 000\nVerkst dir: Töre Nyberg.\n\nSKIDSTA - HUS AB\n\nPnr 870 32\n\nUUånger. Tel 0613-104 60.\nBankgiro 771-4116. Postgiro 276747-3\nVerksamhet: Tillverkar o säljer\nfritidshus, villor o garage\nAntal anställda: 45\nÅrsomsättning: 8 000 000\nAktiekapital: 50 000\nVerkst dir: Sven Erik Edholm\nEtableringsår: 1952\n\nSCANCONTACT, AB\n\nPnr 11528\n\nStockholm, Sandhamnsg 39. Tel\n08-60 66 77, 67 66 90. Postgiro\n353815-4. Tga Scandinavex.\nTelex 10186\n\nVerksamhet: Export, import o\nrepresentation\n\nÅrsomsättning: 10 000 000\nAktiekapital: 100 000\nVerkst dir Conny Jepsen\nEtableringsår: 1953.\n\nSCANDIA MARKNADSTJÄNST,\nAB\n\nPnr 124 34\n\nBandhagen, Skebokvamsv 340. Tel\n08-9964 90, 9964 91. Postgiro\n254687, 405990\n\nVerksamhet: Agentur i\npappersvaror\n\nAntal anställda: 300\n\nÅrsomsättning: 2 500 000\nAktiekapital: 5 000\nVerkst dir: Georg Åberg\nEtableringsår: 1963\nSamma firmanamn sedan 1958.\n\nSCANDIA PHOTOPRESS AB\n\nPnr 20121\n\nMalmö 1, Box 143. Kruseg 19. Tel\n040-93 60 00. Bankgiro 64-0709.\nPostgiro 24550-6.\nTelex 32502 SCANPHO S\nVerksamhet: Bildbyrå. Producerar\no säljer bilder o film till press,\nreklam o PR\nAntal anställda: 32\nÅrsomsättning: 1500 000\nAktiekapital: 5 000\nVeikst dir: Olof Wahlgren\nEtableringsår: 1968.\n\nSVE\n\nPostgiro 554280-8. Tga\nPeearbu-reau. Telex 10820 ADVISOR S\nVerksamhet: Konsulter för svenska\no internationella organisationer o\nindustrier. Byråns verksamhet\nomfattar utredningar o analyser,\nplanering o genomförande av\nlångsiktiga PRrprogram samt interna o\nexterna informationsfrågor. Byrån\nsamarbetar med ett flertal utländska\nkonsultförtag\nAntal anställda: 8\nAktiekapital: 5 000\nStyrelseordf: Lars Bunge-Meyer\nVerkst dir: Lars Bunge-Meyer\nEtableringsår: 1956.\n\nSVENSKA PRECISIONS.\nGJUTERIET MOLL &amp; CO\n\nPnr 652 21\n\nKarlstad, Sågverksg 39. Tel\n054-150310. Bankgiro 100-3243.\nPostgiro 111021-2\n\nVerksamhet: Tillverkar o bearbetar\npressgjutgods som\nbeställningsarbete\n\nVarunamn: Stello\nAntal anställda: 55\nÅrsomsättning: 4 500 000\nÄgare o chefer: O Hultström,\nJohan Nilsson, G Fransson\nEtableringsår: 1912.\n\nSVENSKA PRECISIONS.\nVERKTYG, AB\n\nPnr 13102\n\nNacka 2, Planiav 32. Fack. Tel\n08-71625 10. Bankgiro 263-8390.\nPostgiro 58952-3. Tga Espeve.\nTelex 10839 ESPEVE S\nVerksamhet: Tillverkar\ngängapparater samt dränkbara länspumpar\nAntal anställda: 160\nÅrsomsättning: 14 000 000\nAktiekapital: 1 200 000\nVerkst dir: Göran Forslund\nEtableringsår: 1942.\n\nGRÄ\n\no 2 k för Televerket, kabel\ntäckningssten (för) till olika Elverk,\ncement-hålsten, ringar, rör o rördelar,\nträdgårdsplattor\nAntal anställda: 12\nÅrsomsättning: 1600 000\nAktiekapital: 50 000\nStyrelse: Dir Arne Malm (ordf),\ndisp Bengt Malm\nVerkst dir: Arne Malm\nEtableringsår: 1960.\n\nHALLENBORG + ANDERSON\nAB, INGENJÖRSFIRMAN\n\nPnr 400 14\n\nGöteborg 53, Götabergsg 28. Box\n53001. Tel 031-20 06 50. Bankgiro\n491-2762. Postgiro 623285-4.\nTga Eltric. Telex 21147\nVerksamhet: Tillverkar elektr o\nelektropneumatiska manöver- o\nreglerutrustningar. Generalagent\n\nför KUHNKE-pneumatik, SEITZ,\nHUBER, ANTON+RICHTER\nmag-netventiler\n\nVarunamn: Kuax-rotor,\nKuhnke-miniatyr, Seitz, Huba, Anton +\nRichter\n\nAntal anställda: 15\nAktiekapital: 50 000\nStyrelse: Civiling Bengt\nHallenborg (ordf), civiling Bengt E\nAhl-quist, civiling Lars-Gunnar\nAnderson\n\nVerkst dir Civiling Lars-Gunnar\nAnderson\n\nEtableringsår: 1962.\n\nHALLENHEIM, AB GUNNAR\n\nPnr 16203\n\nVällingby 3, Hässelby Torg 10.\nBox 342. Tel 08-38 60 12, 89 45 30.\nBankgiro 747-2368. Postgiro\n505962-1. Tga Geheim\nVerksamhet: Säljer apoteksvaror,\nkem tekn preparat o\nelektro-me-dicinska apparater samt utövar\ndärmed förenlig verksamhet\nAntal anställda: 22\nAktiekapital: 75 000\nVerkst dir: Gunnar Hallenheim\nEtableringsår: 1954\nOmbildat till aktiebolag 1963.\n\nHALLENIUS MASKIN.\nTEKNISKA KONSTRUKTIONS.\nBYRÄ, RAGNAR\n\nPnr 412 55\n\nGöteborg, Johannebergsg 26. Tel\n031-201153. Postgiro 527349-5\nVerksamhet: Konstruktion o\nutvecklingsarbeten. Tillverkar maskiner o\ntransportanordningar m m.\nSpecialitet: automatiska pallastare,\nlådavlastare, -hissar o -staplare\nÄgare o chef: Civiling Ragnar\nHallenius\n\nEtableringsår: 1959.",
    "structured": {
        "1": {
            "company_name": "ST I TO AB",
            "pnr": "262 00",
            "address": "Ängelholm, Industrig 3. Tel 0431-123 25",
            "bank_details": {
                "bankgiro": "294-1524",
                "postgiro": "463810-2"
            },
            "activity": "Utför automatsvarvning i samtliga stångmaterial samt finmekaniska arbeten",
            "key_personnel": [
                {
                    "name": "Stig Thomasson",
                    "position": "Ägare o chef"
                }
            ],
            "establishment_year": 1949
        },
        "2": {
            "company_name": "NOMO KULLAGER AB",
            "pnr": "11160",
            "address": "Stockholm, Drottningg 81 B. Tel 08-23 3110",
            "bank_details": {
                "bankgiro": "572-9462",
                "postgiro": "554855-7"
            },
            "activity": "Försäljer maskinförnödenheter. Specialitet: kul- o rullager, låsringar o tätningselement",
            "employees": 30,
            "establishment_year": 1949
        },
        "3": {
            "company_name": "NOMOS, AB",
            "pnr": "21121",
            "address": "Malmö, Västerg 35. Tel 040-308 80, 973355",
            "bank_details": {
                "bankgiro": "87-0456",
                "postgiro": "246324"
            },
            "activity": "Agenturer. Import o export av kemikalier o maskiner",
            "employees": 4,
            "annual_production_value": "Tga Solano",
            "capital": 50000,
            "key_personnel": [
                {
                    "name": "Ernst Wahlqvist",
                    "position": "Verkst dir"
                }
            ],
            "establishment_year": 1943
        },
        "4": {
            "company_name": "VÄRMEMATERIAL VVS AB",
            "pnr": "57100",
            "address": "Nässjö, Industrig 42. Box 207. Tel 0380-13250",
            "activity": "Grossist i rör, värme o sanitet",
            "capital": 50000,
            "key_personnel": [
                {
                    "name": "Disp Valdemar Kornstrand",
                    "position": "Verkst dir"
                }
            ],
            "establishment_year": 1938
        },
        "5": {
            "company_name": "HOLSBYVERKEN, AB",
            "pnr": "57015",
            "address": "Holsbybmnn. Tel 0383-502 01, 50213",
            "activity": "Tillverkar handels- o ylindergjutgods, modellutrustningar o utför bearbetning av gjutgods. Beställningsgjutgods i SIS-kvaliteterna 0115-0130, segjärn o meehanite. Modelltillverkning",
            "employees": 165,
            "annual_turnover": 14000000,
            "capital": 150000,
            "key_personnel": [
                {
                    "name": "Bankdir Bror Carlsson",
                    "position": "Styrelseordf"
                },
                {
                    "name": "Ing Ewert Ytterell",
                    "position": "Styrelse"
                },
                {
                    "name": "du-Helge Engström",
                    "position": "Styrelse"
                },
                {
                    "name": "Ing Ewert Ytterell",
                    "position": "Verkst dir"
                }
            ],
            "establishment_year": 1948
        },
        "6": {
            "company_name": "HOLST GOLVBELÄGGNING, AB BRÖDERNA",
            "pnr": "57100",
            "address": "Nässjö, Rådhusg 8. Tel 0380-137 78",
            "activity": "Utför golvbeläggningar, slipning o ytbehandling av golv",
            "capital": 66000,
            "key_personnel": [
                {
                    "name": "Hilding Holst",
                    "position": "Verkst dir"
                }
            ],
            "establishment_year": 1960
        },
        "7": {
            "company_name": "GAHMS FÖRSÄLJNINGS AB, G",
            "pnr": "117 28",
            "address": "Stockholm SV, Hornsg 160. Tel 08-69 03 00",
            "bank_details": {
                "bankgiro": "23-6760",
                "postgiro": "52324"
            },
            "activity": "Säljer läderarbeten o lädervaror samt reseffekter",
            "employees": 42,
            "annual_turnover": 4100000,
            "capital": 450000,
            "key_personnel": [
                {
                    "name": "Bengt af Kleen",
                    "position": "Verkst dir"
                }
            ],
            "establishment_year": 1929
        },
        "8": {
            "company_name": "SKEPPSHULTS GJUTERI AB",
            "pnr": "330 24",
            "address": "Skeppshult, Box 69. Tel 0371-36270",
            "bank_details": {
                "bankgiro": "427-6267",
                "postgiro": "22601-9"
            },
            "activity": "Byggnads-, handels-, hushålls-, sanitets- o beställnings-gjutgods. Specialitet: stekpannor",
            "employees": 46,
            "annual_turnover": 3500000,
            "capital": 111000,
            "key_personnel": [
                {
                    "name": "Fru Gunnel Wennberg",
                    "position": "V verkst dir"
                },
                {
                    "name": "Roland Lindström",
                    "position": "V verkst dir"
                }
            ],
            "establishment_year": 1906
        },
        "9": {
            "company_name": "SKEPPSUPPHUGGNING I GOTEBORG AB",
            "pnr": "402 72",
            "address": "Göteborg 8, Tingstad. Box 8880. Tel 031-23 65 36, 2215 74",
            "bank_details": {
                "bankgiro": "186-2168",
                "postgiro": "629250-2"
            },
            "activity": "Nedskrotning av fartyg, köp o försäljning av järn o metaller",
            "capital": 30000,
            "key_personnel": [
                {
                    "name": "T Johannisson",
                    "position": "Verkst dir"
                }
            ],
            "establishment_year": 1966
        },
        "10": {
            "company_name": "SKF-MALCUS AB",
            "pnr": "30103",
            "address": "Halmstad 1, Box 170. Kristian IV:s väg 3. Tel 035-1183 00",
            "bank_details": {
                "bankgiro": "423-5511",
                "postgiro": "14707-4"
            },
            "activity": "Tillverkar o säljer spiralborrar, gängtappar o gängsnitt, slipmaskiner såsom planslipmaskiner, centerlessüpmaskiner o rund-slipmaskiner",
            "employees": 680,
            "annual_turnover": 46000000,
            "capital": 10000000,
            "key_personnel": [
                {
                    "name": "Töre Nyberg",
                    "position": "Verkst dir"
                }
            ],
            "establishment_year": 0
        }
    }
}