{
    "original": "PR CONTACT, AB\n\nPnr 103 84\n\nStockholm 7, Hamng 13. Box 7193.\nTel 08-2170 05. Postgiro 559495.\nTga Peerce. Telex 10520\nVerksamhet: Konsulter i public\nrelations\n\nAntal anställda: 4\nÅrsomsättning: 250 000\nAktiekapital: 20 000\nStyrelseordf: Dir Kåge Hedström\nVerkst dir: Kåge Hedström\nEtableringsår: 1958.\n\nGOT\n\nGÖTE AB. METALL\n\nPnr 33100\n\nVärnamo, Klockarev 4. Tel\n0370-134 65, 134 75. Bankgiro 291-7425.\nPostgiro 132243-7\nVerksamhet: Automatsvarvning i\njärn o mässing\nAntal anställda: 32\nÅrsomsättning: 4 800 000\nAktiekapital: 200 000\nVerkst dir: Em Söderblom\nEtableringsår: 1937\nOmbildat till aktiebolag 1952.\n\nGÖTES VERKSTADS AB\n\nPnr 652 21\n\nKarlstad, Lantvärnsg 10. Tel\n054-15 6935. Bankgiro 102-6376.\nPostgiro 360242-2\n\nVerksamhet: Mekanisk verkstad,\ngrovplåtslageri o montageavdelning\nAntal anställda: 60\nÅrsomsättning: 4100 000\nAktiekapital: 52 500\nVerkst dir: Göte Gustafsson\nEtableringsår: 1956.\n\nGOTEBORGS ALLMÄNNA\nVAKT AB\n\nPnr 414 64\n\nGöteborg V, Kommendörsg 33. Tel\n031-24 03 02. Bankgiro 44-1823.\nPostgiro 624070. Tga Avakt\nVerksamhet: Bevakningsföretag\nAntal anställda: 45\nAktiekapital: 5 000\nFöreståndare: Arvid Rillnert\nEtableringsår: 1962.\n\nESKILS GRÄVMASKINER AB\n\nPnr 642 00\n\nFlen, Lötv 13. Box 4. Tel\n0157-11972, 115 91. Bankgiro 61-8312.\nPostgiro 175418\nVerksamhet: Entreprenadrörelse\nmed grävmaskiner o schaktmaskiner\nAntal anställda: 35\nÅrsomsättning: 2 000 000\nAktiekapital: 75 000\nVerkst dir: Eskil Andersson\nEtableringsår: 1948.\n\nBENTFORSAB\n\nPnr 591 00\n\nMotala, Utsiktsv 14. Tel\n0141-51511, 134 96. Postgiro 616244.\nTga Bentfors\n\nVerksamhet: Tillverkar\nmellanläggsmaterial\nAktiekapital: 25 000\nVerkst dir: Waldemar Bentfors\nEtableringsår: 1967..\n\nLAM\n\n20 0170. Bankgiro 362-6207.\nPostgiro 48188-7. Tga Lacomp.\nTelex 20928\n\nVerksamhet: Säljer svetsmaskiner,\nsvetstillbehör, gasskärmaskiner,\nskyddsglasögon o\nluftdestillations-anläggningar\nAntal anställda: 30\nÅrsomsättning: 9 000 000\nAktiekapital: 500 000\nVerkst dir: Olof Lakander\nEtableringsår: 1943\nOmbildat till aktiebolag 1951.\n\nLAMELLDURRAR, AB\n\nPnr 543 01\n\nTibro 1, Nygàrdsg. Box 74. Tel\n0504-116 40. Postgiro 178542.\nTga Lamella\n\nVerksamhet: Inredningar för\nadministrationsbyggnader, skolor,\nsjukhus, hotell m m\nAntal anställda: 70\nÅrsomsättning: 6 000 000\nAktiekapital: 30 000\nVerkst dir: Evert Pettersson\nEtableringsår: 1950.\n\nKJE\n\nVerksamhet: Säljer cellulosa,\nlamellträ, papper, plywood,\nplywood-balkar, spånskivor, rå tallolja o\nterpentin\n\nAktiekapital: 2100 000\nVeikst dir: I Thorsson\nEtableringsår: 1917.\n\nKJELLBERGS\nKAROSSERI-FABRIK, AB\n\nPnr 890 28\n\nGuUänget, Box 273. Sportv 1. Tel\n0660-11954, 11959. Bankgiro\n772-5120. Postgiro 366064-4\nVerksamhet: Tillverkar o reparerar\nkarosser o hytter\nAntal anställda: 22\nÅrsomsättning: 1500 000\nAktiekapital: 10 000\nStyrelse: Dir Karl Kjellberg (ordf),\nfru Greta Kjellberg, revisor Georg\nKarlsson\n\nVerkst dir: Karl Kjellberg\nVerkmäst: Ing Kurt Grundström\nKamrer: Fru Maj-Britt Larsmark\nEtableringsår: 1947.\n\nKJELLBERGS SUCCESSORS\nAB\n\nPnr 103 20\n\nStockholm 16, Drottningg 14. Fack.\nTel 08-23 62 60. Bankgiro 446-9250.\nPostgiro 1417-5. Tga Kjellbergs.\nTelex 19977 KAB S\nVerksamhet: Export av järn, stål,\nmaskiner o andra\nindustriprodukter. Import av textil, råvaror,\nporslin, optik, foto, radio, järnvaror,\nelektriska artiklar etc\nAvdelningskontor: Borås,\nSkara-borgsv 25.Tel033-120079,11 2962\nGöteborg, Skeppsbroplatsen 1\nAktiekapital: 2 000 000\nVerkst dir: E Hellmann\nEtableringsår: 1919\nAvdelningskontor i Köpenhamn,\nSandnes, Dublin, Kairo, Athén,\nTo-kio, Osaka.\n\nKJELLBERG AB, GUST\n\nPnr 60102\n\nNorrköping 1, Box 16. Flemingg 30.\nTel 011-12 0126, 13 29 04.\nBankgiro 824-4477. Postgiro 11283-9.\nTga Gustelberg\n\nVerksamhet: Import o\npartiförsäljning av kemikalier, färger, trassel\nm m\n\nAktiekapital: 150 000\nVerkst dir: Bertil Palmqvist\nEtableringsår: 1910\nOmbildat till aktiebolag 1938.\n\nKJELLERUP\nTIMBER-agency,jacob\n\nPnr 302 45\n\nHalmstad, Bredg 7. Tel\n035-10 03 30. Tga Jackwood.\nTelex 38059\n\nVerksamhet: Agentur för export av\nsvenska trävaror\n\nKontor: Köpenhamn, O Sögade 32.\nTel 11 50 57. Telex 2257\nAntal anställda: 9\nÅrsomsättning: 30 000 000\nChef: Jacob Kjellerup\nEtableringsår: 1952.\n\nNERMANS STÄMPLAR\n\nPnr 65105\n\nKarlstad 1, Box 347. O Torgg 19.\nTel 054-15 65 80. Bankgiro\n100-2203. Postgiro 96711-7. Tga\nAke-nerman\n\nVerksamhet: Stämplar för kontor\no produktion. Stämplingsmaskiner,\noffset o direkttryck till\nproduktions-o transportlinjer. Elektriska\nbrännstämplar. Gravyrer, skyltar o\nstansar. Numreringsapparater.\nStämpel-färger o stämpeldynor\nChef: Civilekonom Måns Nerman\nFabrikschef: Gunnar Sundström\nFörsäljn-chef: Sigge Warnelid\nEtableringsår: 1921.\n\nNERMANS TRYCKSAKER\nNERMAN &amp; CO, M\n\nPnr 65102\n\nKarlstad 1, N Kyrkog 1. Box 46.\nKarlstad 1, Box 46. N Kyrkog 1.\nTel 054-15 6 5 8 0. Bankgiro\n410-0278. Postgiro 96712-5. Tga\nAkenerman\n\nVerksamhet: Utför reklam- o\nkatalogarbeten. Ateljé service\nAntal anställda: 60\nChef: Civilekonom Måns Nerman\nEtableringsår 1920.\n\nNESSEN AB, BYGGNADS.\nFIRMAN NILS\n\nPnr 112 23\n\nStockholm, Bergsg 1. Tel\n08-2231 30. Bankgiro 72-3782.\nPostgiro 2517. Tga Nessenhouse\nVerksamhet: Byggnadsentreprenader\nAntal anställda: 554\nÅrsomsättning: 54 000 000\nAktiekapital: 500000\nStyrelse: Adv Bo Sten Bosson\nLeijonhufvud (ordf), civiling Stig\nLarson, byggn-ing Nils Nessen\nVeikst dir. Stig Larson\nEkonomichef: Civilekonom Robert\nTiirner\n\nEtableringsår 1942.\n\nURVERKEN\n\nPnr 116 21\n\nStockholm, Götg 66. Tel\n08-42 22 22. Postgiro 253046-7\nVerksamhet: Automat- o\nrevolver-svarvning, kuggfräsning,\nkuggväxlar. Finmek tillverkningar\nAntal anställda: 10\nÄgare o chef: Fabr Stellan C\nJosefson\n\nEtableringsår: 1946.\n\nOSTLUND, AB ALLAN\n\nPnr 83101\n\nÖstersund 1, Prästg 64. Box 196.\nTel 063-246 80. Bankgiro 25-0042.\nPostgiro 132330\n\nVerksamhet:\nPapper,plast,dekora-tionsmateriel, emballage, kortvaror\ni parti\n\nVarunamn: Gellin\nAktiekapital: 100 000\nVerkst dir: Allan Ostlund\nEtableringsår: 1920\nOmbildat till aktiebolag 1945.\n\nOSTLUNDS MASKINFABRIK,\nAB P E\n\nPnr 736 00\n\nKungsör. Tel 0227-110 50. Bankgiro\n811-0116. Postgiro 26278-2\nVerksamhet: Automatsvarvade\ndetaljer, blanka bultvaror,\nkallpres-sad skruv o bult, cykeldelar m m\nAntal anställda: 165\nÅrsomsättning: 9 500 000\nAktiekapital: 210 000\nVerkst dir Jacob Ostlund\nEtableringsår: 1910.\n\nOSTMAN &amp; NORELL.\nBYGGNADS AB\n\nPnr 88100\n\nSollefteå, Strömg 2. Tel 0620-123 45\nVerksamhet: Byggnadsrörelse\nAntal anställda: 225\nÅrsomsättning: 25 000 000\nAktiekapital: 1700 000\nVerkst dir: Sven Ewald\nEtableringsår: 1949.\n\nOSTMAN MASKINFABRIK AB,\nCARL\n\nPnr 216 12\n\nMalmö, Birger Jarlsg 5. Tel\n040-15 15 87. 15 25 78. Bankgiro\n869-0091. Postgiro 249364-1. Tga\nCarma\n\nVerksamhet: Tillverkar\nhalvfabrikat för formverktyg\nAntal anställda: 20\nÅrsomsättning: 900 000\n\nAktiekapital: 60 000\n\nVerkst dir: Curt Douglas Ostman\n\nEtableringsån 1945.\n\nÖSTRA BRYGGERI AB i\nHALMSTAD\n\nPnr 30102\n\nHalmstad 1, Gamletullsg 1. Box 95.\nTel 035-1190 55. Bankgiro 53-0191.\nPostgiro 264484\n\nVerksamhet: Bryggeri o läskedrycks-\n\nfabrikation\n\nAntal anställda: 60\n\nÅrsomsättning: 6 300 000\n\nAktiekapital: 816 000\n\nVerkst dir: Bengt Anjou\n\nEtableringsår: 1863.\n\nÖSTRA GREVIE CEMENT.\nGJUTERI AB\n\nPnr 23017\n\nÖstra Grevie. Tel 040-48 72 70.\nBankgiro 640-4024. Postgiro\n435878-4\n\nVerksamhet: Tillverkar o säljer\nErge betongbjälklag o grundbalkar\nAntal anställda: 30\nÅrsomsättning: 3 500 000\nAktiekapital: 150 000\nVerkst dir: Christer Ekstrand\nEtableringsår: 1944.\n\nMOT\n\nMORNEON\n\nPnr 1X7 20\n\nStockholm, Bellmansg 2. Tel\n08-23 35 1 0. Bankgiro 446-8385.\nPostgiro 259214-5\n\nVerksamhet: Tillverkar o säljer\nplast- o neonskyltar\nAntal anställda: 40\nÅrsomsättning: 4 000 000\nÄgare o chef: Ing Ruben Morne\nEtableringsår. 1947.",
    "structured": {
        "1": {
            "company_name": "PR CONTACT, AB",
            "pnr": "103 84",
            "address": "Stockholm 7, Hamng 13. Box 7193.",
            "phone_number": "08-2170 05",
            "postgiro": "559495",
            "activity": "Konsulter i public relations",
            "employees": 4,
            "annual_turnover": 250000,
            "capital": 20000,
            "key_personnel": [
                {
                    "name": "Dir Kåge Hedström",
                    "position": "Styrelseordf"
                },
                {
                    "name": "Kåge Hedström",
                    "position": "Verkst dir"
                }
            ],
            "establishment_year": 1958
        },
        "2": {
            "company_name": "GÖTE AB. METALL",
            "pnr": "33100",
            "address": "Värnamo, Klockarev 4",
            "phone_number": "0370-134 65, 134 75",
            "bankgiro": "291-7425",
            "postgiro": "132243-7",
            "activity": "Automatsvarvning i järn och mässing",
            "employees": 32,
            "annual_turnover": 4800000,
            "capital": 200000,
            "key_personnel": [
                {
                    "name": "Em Söderblom",
                    "position": "Verkst dir"
                }
            ],
            "establishment_year": 1937
        },
        "3": {
            "company_name": "GÖTES VERKSTADS AB",
            "pnr": "652 21",
            "address": "Karlstad, Lantvärnsg 10",
            "phone_number": "054-15 6935",
            "bankgiro": "102-6376",
            "postgiro": "360242-2",
            "activity": "Mekanisk verkstad, grovplåtslageri och montageavdelning",
            "employees": 60,
            "annual_turnover": 4100000,
            "capital": 52500,
            "key_personnel": [
                {
                    "name": "Göte Gustafsson",
                    "position": "Verkst dir"
                }
            ],
            "establishment_year": 1956
        },
        "4": {
            "company_name": "GOTEBORGS ALLMÄNNA VAKT AB",
            "pnr": "414 64",
            "address": "Göteborg V, Kommendörsg 33",
            "phone_number": "031-24 03 02",
            "bankgiro": "44-1823",
            "postgiro": "624070",
            "activity": "Bevakningsföretag",
            "employees": 45,
            "capital": 5000,
            "key_personnel": [
                {
                    "name": "Arvid Rillnert",
                    "position": "Föreståndare"
                }
            ],
            "establishment_year": 1962
        },
        "5": {
            "company_name": "ESKILS GRÄVMASKINER AB",
            "pnr": "642 00",
            "address": "Flen, Lötv 13. Box 4",
            "phone_number": "0157-11972, 115 91",
            "bankgiro": "61-8312",
            "postgiro": "175418",
            "activity": "Entreprenadrörelse med grävmaskiner och schaktmaskiner",
            "employees": 35,
            "annual_turnover": 2000000,
            "capital": 75000,
            "key_personnel": [
                {
                    "name": "Eskil Andersson",
                    "position": "Verkst dir"
                }
            ],
            "establishment_year": 1948
        },
        "6": {
            "company_name": "BENTFORSAB",
            "pnr": "591 00",
            "address": "Motala, Utsiktsv 14",
            "phone_number": "0141-51511, 134 96",
            "postgiro": "616244",
            "activity": "Tillverkar mellanläggsmaterial",
            "capital": 25000,
            "key_personnel": [
                {
                    "name": "Waldemar Bentfors",
                    "position": "Verkst dir"
                }
            ],
            "establishment_year": 1967
        },
        "7": {
            "company_name": "LAM",
            "bankgiro": "362-6207",
            "postgiro": "48188-7",
            "activity": "Säljer svetsmaskiner, svetstillbehör, gasskärmaskiner, skyddsglasögon och luftdestillations-anläggningar",
            "employees": 30,
            "annual_turnover": 9000000,
            "capital": 500000,
            "key_personnel": [
                {
                    "name": "Olof Lakander",
                    "position": "Verkst dir"
                }
            ],
            "establishment_year": 1951
        },
        "8": {
            "company_name": "LAMELLDURRAR, AB",
            "pnr": "543 01",
            "address": "Tibro 1, Nygàrdsg. Box 74",
            "phone_number": "0504-116 40",
            "postgiro": "178542",
            "activity": "Inredningar för administrationsbyggnader, skolor, sjukhus, hotell m m",
            "employees": 70,
            "annual_turnover": 6000000,
            "capital": 30000,
            "key_personnel": [
                {
                    "name": "Evert Pettersson",
                    "position": "Verkst dir"
                }
            ],
            "establishment_year": 1950
        },
        "9": {
            "company_name": "KJE",
            "activity": "Säljer cellulosa, lamellträ, papper, plywood, plywood-balkar, spånskivor, rå tallolja och terpentin",
            "capital": 2100000,
            "key_personnel": [
                {
                    "name": "I Thorsson",
                    "position": "Verkst dir"
                }
            ],
            "establishment_year": 1917
        },
        "10": {
            "company_name": "KJELLBERGS KAROSSERI-FABRIK, AB",
            "pnr": "890 28",
            "address": "GuUänget, Box 273. Sportv 1",
            "phone_number": "0660-11954, 11959",
            "bankgiro": "772-5120",
            "postgiro": "366064-4",
            "activity": "Tillverkar och reparerar karosser och hytter",
            "employees": 22,
            "annual_turnover": 1500000,
            "capital": 10000,
            "key_personnel": [
                {
                    "name": "Karl Kjellberg (ordf)",
                    "position": "Styrelse"
                },
                {
                    "name": "Greta Kjellberg",
                    "position": "Styrelse"
                },
                {
                    "name": "Georg Karlsson",
                    "position": "Revisor"
                },
                {
                    "name": "Karl Kjellberg",
                    "position": "Verkst dir"
                },
                {
                    "name": "Kurt Grundström",
                    "position": "Verkmäst"
                },
                {
                    "name": "Maj-Britt Larsmark",
                    "position": "Kamrer"
                }
            ],
            "establishment_year": 1947
        }
    }
}