{
    "original": "HALMSTADS STUVERI AB\n\nPnr 302 45\n\nHalmstad. Tel 035-1107 51.\nBankgiro 530-0934. Postgiro 27 825 2-2.\nTga Stuveribolaget\nVerksamhet: Loss- o\nlastningsarbeten i Halmstads hamn\nAntal anställda: 90\nAktiekapital: 469000\nVerkst dir: Torsten Anderson\nEtableringsår: 1908.\n\nTORLINGS TRÄVARU AB\n\nPnr 544 00\n\nHjo, Box 56. Industrig. Tel\n0503-11110. Bankgiro 216-3392.\nPostgiro 37358-9\n\nVerksamhet: Ramsågverk, hyvleri\no impregneringsanläggning\n\nAntal anställda: 65\nÅrsomsättning: 8500 000\nAktiekapital: 750000\nVerkst dir. Gösta Törling\n\nTORNBERG. EGON\n\nPnr 252 30\n\nHelsingborg, Planteringsv 88. Tel\n042-12 26 35, 12 47 65\nVerksamhet: Säljer Preti o Centurio\nautopolish o möbelpolish\nChef: Egon Törnberg\nEtableringsår: 1952.\n\nMICHELIN GUMMIRINGAR AB\n\nPnr 12609\n\nHägersten 9, Instrumentv 2. Box 951.\nTel 08-18 80 00. Bankgiro 735-0077.\nPostgiro 2265-7. Tga Pneumiclin.\nTelex 19359\n\nVerksamhet: Grosshandel med\nbildäck, slangar o tillbehör\nVarunamn: Michelin\nAktiekapital: 300 000\nEtableringsår: 1927.\n\nFROSTS HUDAFFÄR, AB\n\nPnr 11135\n\nStockholm C, Kungsg 48. Tel\n08-113719, 1137 18. Postgiro 198697.\nTelex 19974. Tga Lederfrost\nVerksamhet: Exporterar råa hudar\no skinn\n\nAntal anställda: 10\nÅrsomsättning: 35 000 000\n\nAktiekapital: 500 000\nVerkst dir: Oscar Pontån\nEtableringsår: 1860.\n\nEJENDAL AB, VALFRID\n\nPnr 793 00\n\nLeksand, Box 48. Tel 0247-114 10.\nBankgiro 796-2053. Postgiro\n146780-2\n\nVerksamhet: Säljer handskar i\n\nparti\n\nAntal anställda: 11\nÅrsomsättning: 7000 000\nAktiekapital: 100 000\nVerkst din Valfrid Ejendal\nEtableringsån 1963.\n\nAHLIN, AB NILS\n\nPnr 252 20\n\nHelsingborg, Långvinkelsg 17.\nTel 042-12 0 0 20. Bankgiro\n269-0543. Postgiro 9122-3\nVerksamhet: Järnvarugrossist\nAntal anställda: 34\nAktiekapital: 100000\nVerkst dir: Kerstin Göthe\nV verkst dir: Disp Sigurd Hansson\nEtableringsår: 1901.\n\nALINGSÅS ARMATURFABRIK,\nAB\n\nPnr 44100\n\nAlingsås, Metallg. Tel\n0322-107 97, 12340. Bankgiro 889-6029.\nPostgiro 162378-4\nVerksamhet: Tillverkar\nstandardarmatur för ånga, värme, vatten,\ngas o specialarmatur\nAntal anställda: 35\nÅrsomsättning: 3 400 000\nAktiekapital: 180 000\nVerkst dir: Nils Larsson\nEtableringsår: 1932.\n\nHUHN AB, GUSTAV\n\nPnr 12104\n\nJohanneshov 4, Rusthållarv 6. Box\n405. Tel 08-39 39 34. 39 3935.\nTelex 10633. Tga Huhnseal\nVerksamhet: Tillverkar tätningar o\npackningar för rörliga\nmaskinelement\n\nVerkst dir: Civiling Dieter Huhn\nEtableringsår: 1949\nSyster o dotterföretag i\nVästtyskland, Schweiz, Italien o Canada.\n\nHUITFELDT ARKITEKT.\nKONTOR AB, ARILD\n\nPnr 402 61\n\nGöteborg 17, Box 17041. Tel\n031-25 86 30 , 25 8 6 60. Bankgiro\n848-2416. Postgiro 527099-6\nVerksamhet: Arkitektkontor för\nindustrier, kontorshus, varuhus,\nbostadshus m m\nAktiekapital: 5 000\nVerkst dir: Arild Huitfeldt\nEtableringsår: 1959.\n\nHULANDER &amp; ANDERSSON\nMEK VERKSTAD, AB\n\nPnr 53100\n\nLidköping, Vallg 12. Tel\n0510-226 79. Bankgiro 212-1993.\nPostgiro 339149-7\n\nVerksamhet: Mekaniska\nverstads-arbeten o järnkonstruktioner\nChef: Elof R Hulander\nEtableringsår: 1946.\n\nTELEKONTROLL, AB\n\nPnr 401 27\n\nGöteborg 1, Ceresg 26. Box 466.\nTel 031-23 51 30. Bankgiro\n42-0515. Postgiro 195392.\nTelex 20893 TELEKON S.\nTga Telekontroll\n\nVeiksamhet:\nPersonsökareanlägg-ningar, centralantenner, elektriska\növervakningsanläggningar,\nhissautomatik, fabrik för elektriska o\nelektroniska utrustningar\nAvdelningskontor: Stockholm. Tel\n08-13 17 90\n\nFabrik: Herrljunga. Elektroniska\navd. Tel 0513-11680\nMekaniska avd. Tel 0513-116 80\nVarunamn: Epsilon, Telecontal,\nTelecourier\nAntal anställda: 180\nÅrsomsättning: 12 000 000\nAktiekapital: 300 000\nStyrelse: Civiling Veine\nAndersson, kamrer Bengt Ternborn\nVerkst dir Civiling Veine\nAndersson\n\nEtableringsår: 1955.\n\nTELEMETRIC INSTRUMENT\nAB\n\nPnr 172 03\n\nSundbyberg 3, Humbleg 15. Box\n341. Tel 08-29 30 90-93. Bankgiro\n74-4487. Postgiro 400900.\nTelex 10775. Tga Telemetric,\nStockholm\n\nVerksamhet: Importerar o säljer\nutrustningar för mätning o reglering\nav temperaturtryck, varvtal o andra\nvariabler inom industriella\nprocesstekniken. Elektroniska\nkomponenter för elektronikindustrin o\nlaboratorier\n\nFilial: 212 28 Malmö, Scheeleg 13.\nTel 040-18 55 00, 18 55 01\nAntal anställda: 10\nÅrsomsättning: 3 000 000\nAktiekapital: 5 000\nStvrelse: Ing Torsten Lindholm\n(ordf), ing Bertil Lindén, ing Axel\nWestrenius\n\nVerkst dir: Ing Bertil Lindén\nV verkst dir: Ing Axel Westrenius\nEtableringsår: 1965.\n\nNIL\n\nKamrer: Sven Mårtensson\nEtableringsår: 1908\nOmbildat till aktiebolag 1944.\n\nNILSSON, BYGGNADSFIRMAN\nCLAES\n\nPnr 59041\n\nRimforsa, Kalmarv 38. Tel\n0494-205 29, 204 88. Bankgiro 63-0843.\nPostgiro 649266\n\nVerksamhet: Nybyggnader,\nreparationer mm\nAntal anställda: 25\nÅrsomsättning: 2 500 000\nChef: Byggn-ing Claes Nilsson\nEtableringsår 1966.\n\nSYLVAN AB, EIVIND K:SON\n\nPnr 41121\n\nGöteborg, Stora Badhusg 20. Tel\n031-1137 73, 1156 42. Bankgiro\n442-2093. Postgiro 240977-9. Tga\nSylvano. Telex 20731\nVerksamhet: Importagenturer för\nförsäljning av dieselmotorer,\ngeneratoraggregat, kompressorer,\npumpar, marina o industriella\nväxellådor, marina o industriella\noljebase-rade kemikalier, tankrengörings\nmaskiner, marina hissar,\npropeller-axellager\nAntal anställda: 8\nAktiekapital: 50 000\nStyrelseordf: Civiling Eivind K: son\nSylvan\n\nChef: Civiling Eivind K:son Sylvan\nAvd-chef: Ing Alf Simonsson\nEtableringsår: 1934.",
    "structured": {
        "1": {
            "company_name": "HALMSTADS STUVERI AB",
            "pnr": "302 45",
            "address": "Halmstad",
            "phone_number": "035-1107 51",
            "bank_details": {
                "bankgiro": "530-0934",
                "postgiro": "27 825 2-2"
            },
            "activity": "Loss- o lastningsarbeten i Halmstads hamn",
            "employees": 90,
            "capital": 469000,
            "key_personnel": [
                {
                    "name": "Torsten Anderson"
                }
            ],
            "establishment_year": 1908
        },
        "2": {
            "company_name": "TORLINGS TRÄVARU AB",
            "pnr": "544 00",
            "address": "Hjo, Box 56. Industrig",
            "phone_number": "0503-11110",
            "bank_details": {
                "bankgiro": "216-3392",
                "postgiro": "37358-9"
            },
            "activity": "Ramsågverk, hyvleri o impregneringsanläggning",
            "employees": 65,
            "annual_turnover": 8500000,
            "capital": 750000,
            "key_personnel": [
                {
                    "name": "Gösta Törling"
                }
            ],
            "establishment_year": 1908
        },
        "3": {
            "company_name": "TORNBERG. EGON",
            "pnr": "252 30",
            "address": "Helsingborg, Planteringsv 88",
            "phone_number": "042-12 26 35, 12 47 65",
            "activity": "Säljer Preti o Centurio autopolish o möbelpolish",
            "key_personnel": [
                {
                    "name": "Egon Törnberg"
                }
            ],
            "establishment_year": 1952
        },
        "4": {
            "company_name": "MICHELIN GUMMIRINGAR AB",
            "pnr": "12609",
            "address": "Hägersten 9, Instrumentv 2. Box 951",
            "phone_number": "08-18 80 00",
            "bank_details": {
                "bankgiro": "735-0077",
                "postgiro": "2265-7"
            },
            "activity": "Grosshandel med bildäck, slangar o tillbehör",
            "capital": 300000,
            "establishment_year": 1927
        },
        "5": {
            "company_name": "FROSTS HUDAFFÄR, AB",
            "pnr": "11135",
            "address": "Stockholm C, Kungsg 48",
            "phone_number": "08-113719, 1137 18",
            "bank_details": {
                "postgiro": "198697"
            },
            "activity": "Exporterar råa hudar o skinn",
            "employees": 10,
            "annual_turnover": 35000000,
            "capital": 500000,
            "key_personnel": [
                {
                    "name": "Oscar Pontån"
                }
            ],
            "establishment_year": 1860
        },
        "6": {
            "company_name": "EJENDAL AB, VALFRID",
            "pnr": "793 00",
            "address": "Leksand, Box 48",
            "phone_number": "0247-114 10",
            "bank_details": {
                "bankgiro": "796-2053",
                "postgiro": "146780-2"
            },
            "activity": "Säljer handskar i parti",
            "employees": 11,
            "annual_turnover": 7000000,
            "capital": 100000,
            "key_personnel": [
                {
                    "name": "Valfrid Ejendal"
                }
            ],
            "establishment_year": 1963
        },
        "7": {
            "company_name": "AHLIN, AB NILS",
            "pnr": "252 20",
            "address": "Helsingborg, Långvinkelsg 17",
            "phone_number": "042-12 0 0 20",
            "bank_details": {
                "bankgiro": "269-0543",
                "postgiro": "9122-3"
            },
            "activity": "Järnvarugrossist",
            "employees": 34,
            "capital": 100000,
            "key_personnel": [
                {
                    "name": "Kerstin Göthe"
                },
                {
                    "name": "Disp Sigurd Hansson"
                }
            ],
            "establishment_year": 1901
        },
        "8": {
            "company_name": "ALINGSÅS ARMATURFABRIK, AB",
            "pnr": "44100",
            "address": "Alingsås, Metallg",
            "phone_number": "0322-107 97, 12340",
            "bank_details": {
                "bankgiro": "889-6029",
                "postgiro": "162378-4"
            },
            "activity": "Tillverkar standardarmatur för ånga, värme, vatten, gas o specialarmatur",
            "employees": 35,
            "annual_turnover": 3400000,
            "capital": 180000,
            "key_personnel": [
                {
                    "name": "Nils Larsson"
                }
            ],
            "establishment_year": 1932
        },
        "9": {
            "company_name": "HUHN AB, GUSTAV",
            "pnr": "12104",
            "address": "Johanneshov 4, Rusthållarv 6. Box 405",
            "phone_number": "08-39 39 34, 39 3935",
            "activity": "Tillverkar tätningar o packningar för rörliga maskinelement",
            "key_personnel": [
                {
                    "name": "Civiling Dieter Huhn"
                }
            ],
            "establishment_year": 1949
        },
        "10": {
            "company_name": "HULTFELDT ARKITEKT. KONTOR AB, ARILD",
            "pnr": "402 61",
            "address": "Göteborg 17, Box 17041",
            "phone_number": "031-25 86 30 , 25 8 6 60",
            "bank_details": {
                "bankgiro": "848-2416",
                "postgiro": "527099-6"
            },
            "activity": "Arkitektkontor för industrier, kontorshus, varuhus, bostadshus m m",
            "capital": 5000,
            "key_personnel": [
                {
                    "name": "Arild Huitfeldt"
                }
            ],
            "establishment_year": 1959
        },
        "11": {
            "company_name": "HULANDER & ANDERSSON MEK VERKSTAD, AB",
            "pnr": "53100",
            "address": "Lidköping, Vallg 12",
            "phone_number": "0510-226 79",
            "bank_details": {
                "bankgiro": "212-1993",
                "postgiro": "339149-7"
            },
            "activity": "Mekaniska verstads-arbeten o järnkonstruktioner",
            "key_personnel": [
                {
                    "name": "Elof R Hulander"
                }
            ],
            "establishment_year": 1946
        },
        "12": {
            "company_name": "TELEKONTROLL, AB",
            "pnr": "401 27",
            "address": "Göteborg 1, Ceresg 26. Box 466",
            "phone_number": "031-23 51 30",
            "bank_details": {
                "bankgiro": "42-0515",
                "postgiro": "195392"
            },
            "activity": "Personsökareanlägg-ningar, centralantenner, elektriska övervakningsanläggningar, hissautomatik, fabrik för elektriska o elektroniska utrustningar",
            "employees": 180,
            "annual_turnover": 12000000,
            "capital": 300000,
            "key_personnel": [
                {
                    "name": "Civiling Veine Andersson"
                },
                {
                    "name": "kamrer Bengt Ternborn"
                }
            ],
            "establishment_year": 1955
        },
        "13": {
            "company_name": "TELEMETRIC INSTRUMENT AB",
            "pnr": "172 03",
            "address": "Sundbyberg 3, Humbleg 15. Box 341",
            "phone_number": "08-29 30 90-93",
            "bank_details": {
                "bankgiro": "74-4487",
                "postgiro": "400900"
            },
            "activity": "Importerar o säljer utrustningar för mätning o reglering av temperaturtryck, varvtal o andra variabler inom industriella processtekniken. Elektroniska komponenter för elektronikindustrin o laboratorier",
            "employees": 10,
            "annual_turnover": 3000000,
            "capital": 5000,
            "key_personnel": [
                {
                    "name": "Ing Bertil Lindén"
                },
                {
                    "name": "Ing Axel Westrenius"
                }
            ],
            "establishment_year": 1965
        },
        "14": {
            "company_name": "NIL",
            "key_personnel": [
                {
                    "name": "Sven Mårtensson"
                }
            ],
            "establishment_year": 1908
        },
        "15": {
            "company_name": "NILSSON, BYGGNADSFIRMAN CLAES",
            "pnr": "59041",
            "address": "Rimforsa, Kalmarv 38",
            "phone_number": "0494-205 29, 204 88",
            "bank_details": {
                "bankgiro": "63-0843",
                "postgiro": "649266"
            },
            "activity": "Nybyggnader, reparationer mm",
            "employees": 25,
            "annual_turnover": 2500000,
            "key_personnel": [
                {
                    "name": "Byggn-ing Claes Nilsson"
                }
            ],
            "establishment_year": 1966
        },
        "16": {
            "company_name": "SYLVAN AB, EIVIND K:SON",
            "pnr": "41121",
            "address": "Göteborg, Stora Badhusg 20",
            "phone_number": "031-1137 73, 1156 42",
            "bank_details": {
                "bankgiro": "442-2093",
                "postgiro": "240977-9"
            },
            "activity": "Importagenturer för försäljning av dieselmotorer, generatoraggregat, kompressorer, pumpar, marina o industriella växellådor, marina o industriella oljebase-rade kemikalier, tankrengörings maskiner, marina hissar, propeller-axellager",
            "employees": 8,
            "capital": 50000,
            "key_personnel": [
                {
                    "name": "Civiling Eivind K: son Sylvan"
                },
                {
                    "name": "Ing Alf Simonsson"
                }
            ],
            "establishment_year": 1934
        }
    }
}