{
    "original": "VIT\n\nget 3. Tel 042-12 79 60. Bankgiro\n65-3119. Postgiro 14235. Tga\nWitt. Telex 72226 WITT S\nVerksamhet; Skeppsmäkleri o\nspedition\n\nAntal anställda: 17\nVerkst din Ake Widner\nEtableringsår: 1888.\n\nTEKNICUS, KONSULTFIRMAN\n\nPnr 123 21\n\nFarsta. Farstaplan 29. Box 121.\nTel 08-94 02 40. Bankgiro\n747-0750. Postgiro 602887-2\nVerksamhet: Konsulterande\ningenjörer. Specialitet: materialhantering,\ntransportanordningar,\nindustriplanering\n\nAvdelningskontor: Umeå, O Kyrkog\n8. Tel 090-1158 00\nAntal anställda: 31\nChef: Ing Gösta Wikberg\nEtableringsår: 1959.\n\nROB\n\n714 00. Bankgiro 470-4490.\nPostgiro 397489-6\n\nVerksamhet: Tillverkar o säljer\nmalt&gt;- o läskedrycker\nAntal anställda: 170\nAktiekapital: 1000 000\nVerkst dir. Disp Nisse Westlund\nEtableringsår: 1856.\n\nRANPAC AB\n\nPnr 432 00\n\nVarberg, Box 62. S Hamng 4. Tel\n0340-130 50, 13 6 70. Telex 3476\nVeiksamhet: Generalagent för\nRaackmanns Fabriker A/S,\nHorsens, Danmark\n\nFilial: Stockholm. Tel 08-36 9810\nAntal anställda: 5\nÅrsomsättning: 8 000 000\nVeikst dir: Rune Anthin\nEtableringsår. 1963.\n\nÅSLJUNGA-PALLEN\n\nPnr 286 00\n\nCfrkelljunga 2, Vemmentorp 520.\nTel 0435-802 60, 802 73. Bankgiro\n340-5222. Postgiro 31186-0\nVerksamhet: Tillverkar lastpallar,\npallrarnar o grövre emballage\nAntal anställda: 45\nÅrsomsättning: 5 000 000\nAktiekapital: 50 000\nVerkst dir. Olle Nilsson\nEtableringsår 1952.\n\nÅSLUND &amp; CO MEK\nVERKSTAD AB\n\nPnr 85104\n\nSundsvall 1, Heffners\nindustriområde. Box 204. Tel 060-11 14 63.\nBankgiro 35-0898. Postgiro 297980\nVerksamhet: Järn- o\nstålkonstruktioner. Skeppsreparationer\nAntal anställda: 30\nÅrsomsättning: 1000 000\nAktiekapital: 65 000\nChefer: Bo Andersson, Gunnar\nIsacson\n\nEtableringsår: 1952.\n\nWINGQVIST, L J\n\nPnr 510 20\n\nFritsla. Tel 0320-70210. Bankgiro\n54-2306. Postgiro 30791. Tga\nWing-qvist\n\nVerksamhet: Spinneri, färgeri,\nappretur o väveri\nAntal anställda: 60\nChef: Ignar Andén\nEtableringsån 1860.\n\nPLASTBETONG AB\n\nPnr 172 34\n\nSundbyberg, Vattug 4. Tel\n08-2804 00, 291212. Bankgiro\n863-5526. Postgiro 458279-7\nVerksamhet: Tillverkare av o\nentreprenör för plastbetongprodukter\nVarunamn: Plastbetong\nAktiekapital: 30 000\nVerkst dir: Ing Gösta Råland\nEtableringsår: 1960.\n\nPLASTBOLAGET\n\nPlastikmanufaktur, AB\n\nPnr 592 00\n\nVadstena, Kronoängen. Box 12. Tel\n0143-115 90. Bankgiro 12-7002.\nPostgiro 38 289 3. Tga Plastman\nVerksamhet: Fabrik för\nformsprutning av termoplaster. Tillverkar\ntekniska industridetaljer, handtag,\ndörrtrycken, skaft, beslag m m\nAntal anställda: 100\nÅrsomsättning: 4 500 000\nAktiekapital: 80 000\nVerkst dir: Ing Carl-Eric Dahlgren\nEtableringsår: 1947.\n\nHAPECO, AB\n\nPnr 382 00\n\nNybro, Kalmarv 14. Tel\n0481-104 52, 127 00. Tga Hapeco\nVerksamhet: Glassmältningsdeglar\no eldfast material\nAntal anställda: 8\nAktiekapital: 100 000\nVerkst dir: Ing Lars Leonhardt\nEtableringsår: 1919.\n\nHANSON VÄRME.VENTILA.\nTION.SANITET, AB OSCAR\n\nPnr 30102\n\nHalmstad 1, Pilefältsg 48. Box 74.\nTel 035-10 0150. Bankgiro 42-3541.\nPostgiro 170466\n\nVerksamhet: Värme-,\nventilations-o sanitetsinstallationer\nAntal anställda: 130\nÅrsomsättning: 10 000 000\nAktiekapital: 150 000\nVerkst dir: Ing Sture Hanson\nEtableringsår: 1916.\n\nJOHANSSON, AB K G\n\nPnr 38100\n\nKalmar, Husängsv 7. Tel\n0480-28120\n\nVerksamhet: Inköp o bearbetning av\njärn-, metall- o glasskrot, textil-,\nplast-, gummi- o pappers avfall.\nBedriver även handel med nytt jäm\nAntal anställda: 35\nAktiekapital: 75 000\nVerkst dir: Konsul Ake Raihle\n(Ystad)\n\nEtableringsår: 1917\n\nFöretaget ingår i Persönerkoncer-\n\nnen.\n\nJOHANSSONS BYGGNADS AB,\nKARL\n\nPnr 750 03\n\nUppsala 3, Storg 28. Box 3041. Tel\n018-14 92 40. Postgiro 130539\nVerksamhet: Byggnadsrörelse\nAntal anställda: 450\nÅrsomsättning: 50000 000\nAktiekapital: 300 000\nVerkst dir: Nils Jorild\nEtableringsår. 1922.\n\nSVENSSON AB, GUST FR\n\nPnr 602 27\n\nNorrköping, Hospitalsg 24. Tel\n011-1215 70, 12 83 70. Bankgiro\n125-0752. Postgiro 176775-5\nVerksamhet: Glasmästeri,\nglassli-peri, bilrutor o konst\nAntal anställda: 11\nAktiekapital: 50 000\nVerkst dir: Folke Blomström\nEtableringsår: 1903.",
    "structured": {
        "1": {
            "company_name": "VIT",
            "phone_number": "042-12 79 60",
            "bank_details": {
                "bankgiro": "65-3119",
                "postgiro": "14235"
            },
            "activity": "Skeppsmäkleri och spedition",
            "employees": 17,
            "establishment_year": 1888
        },
        "2": {
            "company_name": "TEKNICUS, KONSULTFIRMAN",
            "pnr": "123 21",
            "address": "Farsta, Farstaplan 29, Box 121",
            "phone_number": "08-94 02 40",
            "bank_details": {
                "bankgiro": "747-0750",
                "postgiro": "602887-2"
            },
            "activity": "Konsulterande ingenjörer. Specialitet: materialhantering, transportanordningar, industriplanering",
            "employees": 31,
            "establishment_year": 1959
        },
        "3": {
            "company_name": "ROB",
            "address": "714 00",
            "bank_details": {
                "bankgiro": "470-4490",
                "postgiro": "397489-6"
            },
            "activity": "Tillverkar och säljer malt- och läskedrycker",
            "employees": 170,
            "capital": 1000000,
            "establishment_year": 1856
        },
        "4": {
            "company_name": "RANPAC AB",
            "pnr": "432 00",
            "address": "Varberg, Box 62, S Hamng 4",
            "phone_number": "0340-130 50, 13 6 70",
            "bank_details": {
                "bankgiro": "Unknown",
                "postgiro": "Unknown"
            },
            "activity": "Generalagent för Raackmanns Fabriker A/S, Horsens, Danmark",
            "employees": 5,
            "annual_turnover": 8000000,
            "establishment_year": 1963
        },
        "5": {
            "company_name": "ÅSLJUNGA-PALLEN",
            "pnr": "286 00",
            "address": "Cfrkelljunga 2, Vemmentorp 520",
            "phone_number": "0435-802 60, 802 73",
            "bank_details": {
                "bankgiro": "340-5222",
                "postgiro": "31186-0"
            },
            "activity": "Tillverkar lastpallar, pallrarnar och grövre emballage",
            "employees": 45,
            "annual_turnover": 5000000,
            "capital": 50000,
            "establishment_year": 1952
        },
        "6": {
            "company_name": "ÅSLUND & CO MEK VERKSTAD AB",
            "pnr": "85104",
            "address": "Sundsvall 1, Heffners industriområde, Box 204",
            "phone_number": "060-11 14 63",
            "bank_details": {
                "bankgiro": "35-0898",
                "postgiro": "297980"
            },
            "activity": "Järn- och stålkonstruktioner. Skeppsreparationer",
            "employees": 30,
            "annual_turnover": 1000000,
            "capital": 65000,
            "key_personnel": [
                {
                    "name": "Bo Andersson",
                    "position": ""
                },
                {
                    "name": "Gunnar Isacson",
                    "position": ""
                }
            ],
            "establishment_year": 1952
        },
        "7": {
            "company_name": "WINGQVIST, L J",
            "pnr": "510 20",
            "address": "Fritsla",
            "phone_number": "0320-70210",
            "bank_details": {
                "bankgiro": "54-2306",
                "postgiro": "30791"
            },
            "activity": "Spinneri, färgeri, appretur och väveri",
            "employees": 60,
            "capital": 0,
            "key_personnel": [
                {
                    "name": "Ignar Andén",
                    "position": ""
                }
            ],
            "establishment_year": 1860
        },
        "8": {
            "company_name": "PLASTBETONG AB",
            "pnr": "172 34",
            "address": "Sundbyberg, Vattug 4",
            "phone_number": "08-2804 00, 291212",
            "bank_details": {
                "bankgiro": "863-5526",
                "postgiro": "458279-7"
            },
            "activity": "Tillverkare av och entreprenör för plastbetongprodukter",
            "capital": 30000,
            "key_personnel": [
                {
                    "name": "Ing Gösta Råland",
                    "position": ""
                }
            ],
            "establishment_year": 1960
        },
        "9": {
            "company_name": "PLASTBOLAGET, Plastikmanufaktur AB",
            "pnr": "592 00",
            "address": "Vadstena, Kronoängen, Box 12",
            "phone_number": "0143-115 90",
            "bank_details": {
                "bankgiro": "12-7002",
                "postgiro": "38 289 3"
            },
            "activity": "Fabrik för formsprutning av termoplaster. Tillverkar tekniska industridetaljer, handtag, dörrtrycken, skaft, beslag m m",
            "employees": 100,
            "annual_turnover": 4500000,
            "capital": 80000,
            "key_personnel": [
                {
                    "name": "Ing Carl-Eric Dahlgren",
                    "position": ""
                }
            ],
            "establishment_year": 1947
        },
        "10": {
            "company_name": "HAPECO, AB",
            "pnr": "382 00",
            "address": "Nybro, Kalmarv 14",
            "phone_number": "0481-104 52, 127 00",
            "bank_details": {
                "bankgiro": "Unknown",
                "postgiro": "Unknown"
            },
            "activity": "Glassmältningsdeglar och eldfast material",
            "employees": 8,
            "capital": 100000,
            "key_personnel": [
                {
                    "name": "Ing Lars Leonhardt",
                    "position": ""
                }
            ],
            "establishment_year": 1919
        },
        "11": {
            "company_name": "HANSON VÄRME.VENTILATION.SANITET, AB OSCAR",
            "pnr": "30102",
            "address": "Halmstad 1, Pilefältsg 48, Box 74",
            "phone_number": "035-10 0150",
            "bank_details": {
                "bankgiro": "42-3541",
                "postgiro": "170466"
            },
            "activity": "Värme-, ventilations- och sanitetsinstallationer",
            "employees": 130,
            "annual_turnover": 10000000,
            "capital": 150000,
            "key_personnel": [
                {
                    "name": "Ing Sture Hanson",
                    "position": ""
                }
            ],
            "establishment_year": 1916
        },
        "12": {
            "company_name": "JOHANSSON, AB K G",
            "pnr": "38100",
            "address": "Kalmar, Husängsv 7",
            "phone_number": "0480-28120",
            "activity": "Inköp och bearbetning av järn-, metall- och glasskrot, textil-, plast-, gummi- och pappersavfall. Handlar även med nytt",
            "employees": 35,
            "capital": 75000,
            "key_personnel": [
                {
                    "name": "Konsul Ake Raihle (Ystad)",
                    "position": ""
                }
            ],
            "establishment_year": 1917
        },
        "13": {
            "company_name": "JOHANSSONS BYGGNADS AB, KARL",
            "pnr": "750 03",
            "address": "Uppsala 3, Storg 28, Box 3041",
            "phone_number": "018-14 92 40",
            "bank_details": {
                "postgiro": "130539"
            },
            "activity": "Byggnadsrörelse",
            "employees": 450,
            "annual_turnover": 50000000,
            "capital": 300000,
            "key_personnel": [
                {
                    "name": "Nils Jorild",
                    "position": ""
                }
            ],
            "establishment_year": 1922
        },
        "14": {
            "company_name": "SVENSSON AB, GUST FR",
            "pnr": "602 27",
            "address": "Norrköping, Hospitalsg 24",
            "phone_number": "011-1215 70, 12 83 70",
            "bank_details": {
                "bankgiro": "125-0752",
                "postgiro": "176775-5"
            },
            "activity": "Glasmästeri, glasslipperi, bilrutor och konst",
            "employees": 11,
            "capital": 50000,
            "key_personnel": [
                {
                    "name": "Folke Blomström",
                    "position": ""
                }
            ],
            "establishment_year": 1903
        }
    }
}