{
    "original": "malmkopings ror, ab\n\nPnr 640 32\n\nMalmköping, Byg 2. Tel\n0157-202 05 , 205 44. Bankgiro 61-8346.\nPostgiro 103344\n\nVerksamhet: Installation av värme,\n\nvatten o sanitet\n\nAntal anställda: 10\n\nÅrsomsättning: 1500 000\n\nAktiekapital: 30 000\n\nStyrelse: Dir Georg Berg (ordf), ing\n\nPer-Göran Berg\n\nVerkst dir: Georg Berg\nEtableringsår 1947\n\nOmbildat till aktiebolag 1953.\n\nmalmkopings trå.\nfurädling ab\n\nPnr 640 32\n\nMalmköping. Tel 0157-200 69,\n202 88. Bankgiro 61-8350.\nPostgiro 23748\n\nVeiksamhet: Tillverkar o säljer\nohyvlade o hyvlade trävaror\nAktiekapital: 10 000\nVerkst dir: Byggmäst Sven\nLindqvist\n\nEtableringsår: 1910.\n\nmalmros’\nfartygs-agentur, ab\n\nPnr 231 00\n\nTrelleborg, Industrig 1. Tel\n0410-125 30, 135 30. Bankgiro 287-9799.\nPostgiro 434218-4. Tga Service.\nTelex 32968 SERVICE S\nVerksamhet: Befraktningsagenter,\nhaveriombud, speditörer,\nskeppsmäklare\n\nAntal anställda: 4\nAktiekapital: 100 000\nVerkst dir. Stig Nordberg\nEtableringsår: 1947.\n\nFINDUS, AB\n\nPnr 267 00\n\nBjuv, Fack. Tel 042-708 00.\nBankgiro 170-9500. Postgiro 10206-1.\nTga Findus. Telex 72200\nVerksamhet: Tillverkar o säljer\nlivsmedel. Produktionen omfattar\ndjupfrysta o konserverade\nprodukter\n\n.Antal anstäUda: 2 000\nÅrsomsättning: 300 000 000\nAktiekapital: 30 000 000\nVerkst dir: Ulf Sundberg\nEtableringsår: 1905.\n\nAU T\n\nFilial: 212 25 Malmö, Agatan 7.\nTel 040-18 63 80\nAntal anställda: 13\nÅrsomsättning: 2500 000\nAktiekapital: 260 000\nStyrelse: Dir Olle Skog, dir Sven\nStenheim\n\nChef: Dir Olle Skog\nEtableringsår: 1956\nOmbildat till aktiebolag 1959.\n\nAUTONORDIC BILIMPORT AB\n\nPnr 403 16\n\nGöteborg 2, Box 2417. Tel\n031-1150 61\n\nVerksamhet: Säljer bilar o bildelar\nAktiekapital: 25 000\nVerkst dir: Ing G Törneli\nEtableringsår: 1965.\n\nTINGSTROM AB, L\n\nPnr 401 27 Gbg 1\n\nMölndal, Agatan. Box 476. Gbg 1.\nTel 031-27 25 00, 27 5500\nVerksamhet: Säljer verktyg o\nmaskiner\n\nVarunamn: Devcon, Dihardt,\nI. S.-12, Lug-AU, Normdelar,\nPla-nit, Rego\n\nAktiekapital: 50 000\nVerkst dir: E Wiberger\nEtableringsår: 1954.\n\nhem\n\nhema industrier ab\n\nPnr 952 00\n\nKalix, Skytt eg. Tel 0923-12120.\nBankgiro 75-6770. Postgiro 481545.\nTga Hema\n\nVerksamhet: Tillverkar takräck o\n\nskidställ för bilar, snöskopan\n\n’Tipp’, ’Hema’ betongspik o skid-\n\nbindningar\n\nAntal anställda: 40\n\nÅrsomsättning: 4 000 000\n\nAktiekapital: 50 000\n\nStyrelse: Dir Henning Eriksson,\n\nfabr Folke Eriksson\n\nVerkst dir: Henning Eriksson\n\nEtableringsår: 1954.\n\nLINDKVIST &amp; CO AB, LARS\n\nPnr 11139\n\nStockholm, Drottninghusgränd 1.\nTel 08-23 48 65. Bankgiro 565-2334.\nPostgiro 152854-6\nVerksamhet: Agentur o en\ngrosförsäljning av skodon o skotillbehör\nAntal anställda: 10\nÅrsomsättning: 3 000 000\nAktiekapital: 5 000\nVerkst din Lars Eriksson\nEtableringsån 1939.\n\nHED\n\nAktiekapital: 50 000\nEtableringsån 1969\nDotterbolag till Heby-textil AB.\n\nHEBY.TEXTIL AB\n\nPnr 740 40\n\nHeby, Box 108. Tel 0224-307 30.\nBankgiro 81-0723. Postgiro 298070\nVerksamhet: Tillverkar yttertrikå,\nchenillevävnader, sängöverkast,\nbadkappor o mattor. Pärgeri\nAntal anställda: 120\nAktiekapital: 800 000\nVeikst dir: Gunnar Lindström\nEtableringsår: 1918.\n\nTORNGREN SKANDINAVIA KB\n\nPnr 111 60\n\nStockholm, Välling 12. Tel\n08-23 32 55. Bankgiro 412-9318.\nPostgiro 350538-5. Tga Getetrade.\nTelex 1587\n\nVerksamhet: Säljer stållinor,\nsmörjmedel, grusmaskiner, stroppar o\ntågvirke\n\nVarunamn: Klingfast, Leadolene,\nSego-Klingfast-Linor\nInsatskapital: 70 000\nEtableringsår 1947.\n\nEXQVISITA STYLE AB\n\nPnr 113 48\n\nStockholm, Hagag 3. Tel\n08-23 0840. Bankgiro 28-3899.\nPostgiro 507260. Tga Exqvisita\nVerksamhet: Tillverkar o säljer\nkontors- o biblioteksbokhyllan\nExqvisita\n\nÅrsomsättning: 1300 000\nVerkst din Bengt Julin\nDisp: G-A Ekehammar\nEtableringsår: 1954.\n\nFINSTA CEMENTGJUTERI, AB\n\nPnr 762 00\n\nRimbo. Finsta. Tel 0175-600 26,\n60130. Bankgiro 80-5855. Postgiro\n36141\n\nVerksamhet: Tillverkar\nfabriks-blandad betong, betongrör m m\nAntal anställda: 40\nÅrsomsättning: 3 500 000\n\nAktiekapital: 30 000\nVerkst dir: Sten Nord\nEtableringsår: 1919.",
    "structured": {
        "1": {
            "company_name": "malmkopings ror, ab",
            "address": "Malmköping, Byg 2",
            "phone_number": "0157-202 05 , 205 44",
            "bank_details": {
                "bankgiro": "61-8346",
                "postgiro": "103344"
            },
            "activity": "Installation av värme, vatten o sanitet",
            "employees": 10,
            "annual_turnover": 1500000,
            "capital": 30000,
            "key_personnel": [
                {
                    "name": "Dir Georg Berg",
                    "position": "ordf"
                },
                {
                    "name": "ing Per-Göran Berg",
                    "position": ""
                }
            ],
            "establishment_year": 1947
        },
        "2": {
            "company_name": "malmkopings trå. furädling ab",
            "address": "Malmköping",
            "phone_number": "0157-200 69, 202 88",
            "bank_details": {
                "bankgiro": "61-8350",
                "postgiro": "23748"
            },
            "activity": "Tillverkar o säljer ohyvlade o hyvlade trävaror",
            "capital": 10000,
            "key_personnel": [
                {
                    "name": "Byggmäst Sven Lindqvist",
                    "position": ""
                }
            ],
            "establishment_year": 1910
        },
        "3": {
            "company_name": "malmros’ fartygs-agentur, ab",
            "address": "Trelleborg, Industrig 1",
            "phone_number": "0410-125 30, 135 30",
            "bank_details": {
                "bankgiro": "287-9799",
                "postgiro": "434218-4"
            },
            "activity": "Befraktningsagenter, haveriombud, speditörer, skeppsmäklare",
            "employees": 4,
            "capital": 100000,
            "key_personnel": [
                {
                    "name": "Stig Nordberg",
                    "position": ""
                }
            ],
            "establishment_year": 1947
        },
        "4": {
            "company_name": "FINDUS, AB",
            "address": "Bjuv, Fack",
            "phone_number": "042-708 00",
            "bank_details": {
                "bankgiro": "170-9500",
                "postgiro": "10206-1"
            },
            "activity": "Tillverkar o säljer livsmedel. Produktionen omfattar djupfrysta o konserverade produkter",
            "employees": 2000,
            "annual_turnover": 300000000,
            "capital": 30000000,
            "key_personnel": [
                {
                    "name": "Ulf Sundberg",
                    "position": ""
                }
            ],
            "establishment_year": 1905
        },
        "5": {
            "company_name": "AU T",
            "address": "Filial: 212 25 Malmö, Agatan 7",
            "phone_number": "040-18 63 80",
            "employees": 13,
            "annual_turnover": 2500000,
            "capital": 260000,
            "key_personnel": [
                {
                    "name": "Dir Olle Skog",
                    "position": ""
                },
                {
                    "name": "dir Sven Stenheim",
                    "position": ""
                }
            ],
            "establishment_year": 1956
        },
        "6": {
            "company_name": "AUTONORDIC BILIMPORT AB",
            "address": "Göteborg 2, Box 2417",
            "phone_number": "031-1150 61",
            "activity": "Säljer bilar o bildelar",
            "capital": 25000,
            "key_personnel": [
                {
                    "name": "Ing G Törneli",
                    "position": ""
                }
            ],
            "establishment_year": 1965
        },
        "7": {
            "company_name": "TINGSTROM AB, L",
            "address": "Mölndal, Agatan. Box 476. Gbg 1",
            "phone_number": "031-27 25 00, 27 5500",
            "activity": "Säljer verktyg o maskiner",
            "capital": 50000,
            "key_personnel": [
                {
                    "name": "E Wiberger",
                    "position": ""
                }
            ],
            "establishment_year": 1954
        },
        "8": {
            "company_name": "hema industrier ab",
            "address": "Kalix, Skytt eg",
            "phone_number": "0923-12120",
            "bank_details": {
                "bankgiro": "75-6770",
                "postgiro": "481545"
            },
            "activity": "Tillverkar takräck o skidställ för bilar, snöskopan 'Tipp', 'Hema' betongspik o skid-bindningar",
            "employees": 40,
            "annual_turnover": 4000000,
            "capital": 50000,
            "key_personnel": [
                {
                    "name": "Dir Henning Eriksson",
                    "position": ""
                },
                {
                    "name": "fabr Folke Eriksson",
                    "position": ""
                }
            ],
            "establishment_year": 1954
        },
        "9": {
            "company_name": "LINDKVIST & CO AB, LARS",
            "address": "Stockholm, Drottninghusgränd 1",
            "phone_number": "08-23 48 65",
            "bank_details": {
                "bankgiro": "565-2334",
                "postgiro": "152854-6"
            },
            "activity": "Agentur o en grossförsäljning av skodon o skotillbehör",
            "employees": 10,
            "annual_turnover": 3000000,
            "capital": 5000,
            "key_personnel": [
                {
                    "name": "Lars Eriksson",
                    "position": ""
                }
            ],
            "establishment_year": 1939
        },
        "10": {
            "company_name": "HED",
            "capital": 50000,
            "establishment_year": 1969,
            "details": "Dotterbolag till Heby-textil AB."
        },
        "11": {
            "company_name": "HEBY.TEXTIL AB",
            "address": "Heby, Box 108",
            "phone_number": "0224-307 30",
            "bank_details": {
                "bankgiro": "81-0723",
                "postgiro": "298070"
            },
            "activity": "Tillverkar yttertrikå, chenillevävnader, sängöverkast, badkappor o mattor. Pärgeri",
            "employees": 120,
            "capital": 800000,
            "key_personnel": [
                {
                    "name": "Gunnar Lindström",
                    "position": ""
                }
            ],
            "establishment_year": 1918
        },
        "12": {
            "company_name": "TORNGREN SKANDINAVIA KB",
            "address": "Stockholm, Välling 12",
            "phone_number": "08-23 32 55",
            "bank_details": {
                "bankgiro": "412-9318",
                "postgiro": "350538-5"
            },
            "activity": "Säljer stållinor, smörjmedel, grusmaskiner, stroppar o tågvirke",
            "capital": 70000,
            "establishment_year": 1947
        },
        "13": {
            "company_name": "EXQVISITA STYLE AB",
            "address": "Stockholm, Hagag 3",
            "phone_number": "08-23 0840",
            "bank_details": {
                "bankgiro": "28-3899",
                "postgiro": "507260"
            },
            "activity": "Tillverkar o säljer kontors- o biblioteksbokhyllan Exqvisita",
            "annual_turnover": 1300000,
            "key_personnel": [
                {
                    "name": "Bengt Julin",
                    "position": "Verkst din"
                },
                {
                    "name": "G-A Ekehammar",
                    "position": "Disp"
                }
            ],
            "establishment_year": 1954
        },
        "14": {
            "company_name": "FINSTA CEMENTGJUTERI, AB",
            "address": "Rimbo. Finsta",
            "phone_number": "0175-600 26, 60130",
            "bank_details": {
                "bankgiro": "80-5855",
                "postgiro": "36141"
            },
            "activity": "Tillverkar fabriks-blandad betong, betongrör m m",
            "employees": 40,
            "annual_turnover": 3500000,
            "capital": 30000,
            "key_personnel": [
                {
                    "name": "Sten Nord",
                    "position": "Verkst dir"
                }
            ],
            "establishment_year": 1919
        }
    }
}