{
    "original": "LIND, LINDH\nLINDS ATELJÉER, AB\n\nPnr 25104\n\nHelsingborg 1, Box 257. Ingenjörsg\n7. Tel 042-13 94 45. Bankgiro\n653-1545. Postgiro 170058-2\nVerksamhet: Tillverkar stämplar o\nduplikatklichéer, säljer skyltar av\nalla slag\n\nAntal anställda: 13\nAktiekapital: 20 000\nVerkst dir: Disp Curt Lind\nEtableringsår: 1914.\n\nANDERSSON, AB HILMER\n\nPnr 67040\n\nAmotfors, Adolfsfors. Tel\n0571-330 01, 330 31. Bankgiro 104-2456.\nPostgiro 22877-5\n\nVerksamhet: Tillverkar o säljer\nsågade o hyvlade trävaror\nAntal anställda: 115\n\nÅrsomsättning: 18 000 000\nAktiekapital: 20 1 000\nVerkst dir: Yngve Andersson.\n\nANDERSON &amp; CO AB,\nRORBOLAGET HJ\n\nPnr 502 34\n\nBorås, Skaraborgsv 40. Tel\n033-1127 99, 1120 99. Bankgiro\n53-1149. Postgiro 82253\nVerksamhet: Värme-, sanitets- o\nventilationsanläggningar\nAntal anställda: 24\nÅrsomsättning: 2 000 000\nAktiekapital: 150 000\nVerkst dir: Sixten Anderson\nEtableringsår: 1927.\n\nPRAKTISKA NYHETER, AB\n\nPnr 114 58\n\nStockholm, Linnég 51-53. Tel\n08-67 00 70. Bankgiro 447-0019.\nPostgiro 1329-2. Tga Crispinus.\nTelex 73360\n\nVerksamhet: Brunit skärplatta,\nWoly skovårdsmedel, maskiner\nVarunamn: Brunit, Primo\nAntal anställda: 15\nAktiekapital: 350 000\nVerkst dir: Harry Brunner\nDisp: P Heller\nEtableringsår: 1908.\n\nPRAMBERGS\nMETALLVARUFABRIK, S\n\nPnr 244 00\n\nKävlinge, Bäckv 15. Tel 046-317 48.\nBankgiro 260-7083. Postgiro\n536420-3\n\nVerksamhet: Tillverkar bly- o\ntrådplomber samt plomberingstråd\nÄgare o chef: Sten Pramberg\nEtableringsår 1960.\n\nGOTEBORGS ASFALT AB\n\nPnr 417 07\n\nGöteborg, Stålverksg 16. Tel\n031-23 23 50\n\nVerksamhet: Golvläggning samt\nsäljer fogmassa o asfalt.\nEntreprenadarbeten\nAntal anställda: 20\nÅrsomsättning: 2 500 000\nAktiekapital: 45 000\nVerkst dir: Ing Stig Nilsson\nEtableringsår: 1922.\n\nPLEXI PRODUKTER AB\n\nPnr 114 55\n\nStockholm, Storg 30. Tel\n08-60 60 81, 60 60 89. Bankgiro\n44-7126. Postgiro 3235\nVerksamhet: Säljer bearbetad\nacryl-plast, kupoler, telefonhytter\nAntal anställda: 3\nÅrsomsättning: 600 000\nAktiekapital: 20 000\nFirmatecknare: Sven Jonsson,\nBertil Olander\nEtableringsår: 1961.\n\nPLIBRICO ELDFAST\nMATERIAL AB\n\nPnr 411 01\n\nGöteborg, stampg 38. Tel\n031-1971 05. Bankgiro 852-4480.\nPostgiro 422071-1. Tga Eldfast.\nTelex 20013\n\nVerksamhet: Eldfasta infodringar\nför ångpannor o industriugnar.\nKonstruktion o tillverkning av\nsopförbränningsugnar. Försäljning av\nhögeldfasta stamp-, ram- o\ngjut-massor samt eldfast cement\nVarunamn: Plibrico, Pliram,\nPli-casto, Pligun, Plistix, Demon,\nPli-mag\n\nAntal anstäUda: 30\nÅrsomsättning: 5 000 000\nAktiekapital: 345 000\nVerkst dir: Magnus Björkman\nEtableringsår: 1937.\n\nANDÉN AB, LENNART\n\nPnr 500 05\n\nBorås 5, S Kyrkog 31. Box 55028.\nTel 033-10 31 10, 10 31 11. Bankgiro\n560-0176. Postgiro 9560-4.\nTga Landab. Telex 36119\nVerksamhet: Textil-, plast- o\nflockningsmaskiner o tillbehör,\ninstrument o utrustning för\nberö-rlngsfri mätning o styrning,\nståltråd o linor, lim\nVaranamn: MOVIPORT\nAntal anställda: 4\nAktiekapital: 60 000\nÄgare o chef: Civiling Lennart Andèn\nEtableringsår: 1953.\n\nETERNA AB\n\nPnr 114 35\n\nStockholm, Stureg 6. Tel\n08-113200. 1132 16\nVerksamhet: Säljer ur en gros\nAntal anställda: 11\nÅrsomsättning: 1000 000\nAktiekapital: 60 000\nVerkst dir. Horst Bramsen\nEtableringsår: 1945.\n\nETERNITRDR, AB\n\nIngår i Cementakoncernen\nPnr 432 00\n\nVarberg, Box 197. Getteröv. Tel\n0340-16170. Bankgiro 67-3153.\nPostgiro 246346. Tga Aberör.\nTelex 3477\n\nEVA\n\nVerksamhet: Tillverkar o säljer\nasbestcementrör o rördelar under\nvarumärket Eternitrör\nAvdelningskontor: 114 26\nStockholm, Danderydsg 26. Tel\n08-24 51 70\n\nVarunamn: Eternitrör\nAntal anställda: 115\nÅrsomsättning: 16 000 000\nAktiekapital: 6 000 000\nStyrelse: Dir Elam Tunhammar\n(ordf), ambassadör Sten Lindh,\ndr hc Max Schmidheiny, dir Gunnar\nRosenborg, dir Erwin de\nShàren-grad, dir Alphonse Emsens\n(Styrelsen har sitt säte i Malmö)\nVerkst dir: Ingmar Forsström\nEtableringsår: 1947.\n\nESKIL PRODUCTS LTD, AB\n\nPnr 63103\n\nEskilstuna 1, Nyg 17. Box 220.\nTel 016-1415 60. Bankgiro\n601-7305. Postgiro 13438-7.\nTga Eskiltool\n\nVerksamhet: Försäljningsbolag för\nelektroniktänger\nÅrsomsättning: 600 000\nAktiekapital: 150 000\nStyrelse: Sven Wedén (ordf).\nStig Eliasson. Marianne Wedén\nVerkst dir. Stig Eliasson\nEtableringsår: 1957.\n\nESKILSSONS STANS- &amp;\nPRESSVERKTYG AB\n\nPnr 282 00\n\nTyringe, Box 110. Municipalg 3.\nTel 0451-50 9 20. Bankgiro\n288-9145. Postgiro 337163. Tga\nEskilssons\n\nVerksamhet: Tillverkar stans- o\n\nixess verktyg för plåt, formverktyg\nför gummi, plast o keramisk\nindustri, jiggar o fixturer, stansknivar\nför gummi, läder o pappersindustri,\nknivar för tobaksindustrin samt\npelarställ o verktygstillbehör\nAntal anställda: 125\nÅrsomsättning: 7 500 000\nAktiekapital: 48000\nStyrelse: Fru Stina Eskilsson,\ning Bengt Eskilsson, disp Roland\nLundgren, adv Gustav Magnusson,\nverkmäst Ivar Svensson\nVerkst dir: Fru Stina Eskilsson\nDisp: Roland Lundgren\nEtableringsår: 1941.\n\nSEV\n\nSELPRO AB\n\nPnr 401 24\n\nGöteborg 1, Box 245. Aschebergsg\n1. Tel 031-17 6240. Bankgiro\n302-0369. Postgiro 722601-2. Tga\nSelpro. Telex 20949 SELPRO S\nVerksamhet: Intern\nmaterialhantering på den svenska marknaden.\nExport av svenska produkter inom\nintern materialhantering med egna\nagenter i England, Sydafrika, Nya\nZeeland, USA, Tyskland.\nFrankrike samt Finland. Generalagent\nför Flexello Castors (Export) Ltd,\nEngland (länk- o fasthjul), Stilson\nInc, USA (produkter för hantering\nmed vakuum). Henley Forklift Co\nLtd, England (truckar) samt Stewart\nGill &amp; Co Ltd, England\n(hängtran-sportörer)\nAntal anställda: 7\nÅrsomsättning: 4 000 000\nAktiekapital: 25 000\nStyrelse: Dir Olof Wåhlin (ordf),\ning Mats Norrman\nVerkst dir: Olof Wåhlin\nEtableringsàr: 1970.\n\nSEMDA, AB\n\nPnr 412 53\n\nGöteborg, Hedåsg 3. Tel\n031-165242, 1652 33. Bankgiro\n847-8711. Postgiro 42220-4\nVerksamhet: Förnödenheter för\nherr- o damfriseringar\nAntal anställda: 8\nÅrsomsättning: 700000\nAktiekapital: 36 000\nVerkst dir: Fru Elsa Landström\nEtableringsàr: 1931.\n\nSEMPERIT SVENSKA AB\n\nPnr 10310\n\nStockholm 2, Fack. Skeppsbron 20.\nTel 08-24 88 60. Bankgiro 566-0626.\nPostgiro 55302-4. Tga Sempsto.\nTelex 10111 SEMPSTO S\nVetksamhet: Import o grosshandel\nmed ’Semperit’ däck o tekniska\ngummivaror samt polyeter\nAntal anställda: 35\nAktiekapital: 1000000\nEtableringsàr: 1965.\n\nSENNANS TEGELBRUK\n\nse Olsson &amp; Co, AB P.\n\nSEPIA REPRO AB\n\nPnr 411 10\n\nGöteborg, O Hamng 17. Tel\n031-1343 38, 13 45 38. Bankgiro\n852-8234. Postgiro 12122-8\nVerksamhet: Ljus- o fotokopiering\nAntal anställda: 15\nAktiekapital: 5 000\nÄgare o chef: H O Nilsson\nEtableringsàr: 1950\nOmbildat till aktiebolag 1961.\n\nSEPSON S E PETERSONS\nMEKANISKA VERKSTAD AB\n\nPnr 780 50\n\nVansbro, Järnav 4. Box 680. Tel\n0281-110 00. Bankgiro 798-9072.\nPostgiro 163551-5. Tga Sepson\nVerksamhet: Vinschar, kranar,\ntraktorhytter, block o saxar\nAntal anställda: 80\nÅrsomsättning: 5 000 000\n\nAktiekapital: 50000\n\nVerkst dir. Ing Gunnar Peterson\n\nEtableringsån 1949.\n\nSERGEL\nSEKRETERAR-SERVICE AB\n\nPnr 11134\n\nStockholm, Sveav 25-27. Tel\n08-205190, 2015 61. Bankgiro\n618-5177. Postgiro 258825-9\nVerksamhet: Fullständig\nkontorsservice med skrivbyråverksamhet\nAntal anställda: 3\nÅrsomsättning: 100 000\nAktiekapital: 5 000\nVerkst dir: Dagmar Martin\nEtableringsån 1970.\n\nAXELSSON INDUSTRI AB, G E\n\nPnr 653 50\n\nKarlstad, Postl 675. Granlidsv 71.\nTel 054-30485, 300 56. Bankgiro\n100-1411. Postgiro 175767-3. Tga\nHmbergea\n\nVerksamhet: Sågar klent timmer till\nreglar, sparrar o dyl\nAntal anställda: 10\nÅrsomsättning: 2 500 000\nAktiekapital: 100 000\nVerkst dir: Gunnar E Axelsson\nEtableringsår 1935.",
    "structured": {
        "1": {
            "company_name": "LINDS ATELJÉER, AB",
            "pnr": "25104",
            "address": "Helsingborg 1, Box 257. Ingenjörsg 7",
            "phone_number": "042-13 94 45",
            "bank_details": {
                "bankgiro": "653-1545",
                "postgiro": "170058-2"
            },
            "activity": "Tillverkar stämplar o duplikatklichéer, säljer skyltar av alla slag",
            "employees": 13,
            "capital": 20000,
            "key_personnel": [
                {
                    "name": "Disp Curt Lind"
                }
            ],
            "establishment_year": 1914
        },
        "2": {
            "company_name": "ANDERSSON, AB HILMER",
            "pnr": "67040",
            "address": "Amotfors, Adolfsfors",
            "phone_number": "0571-330 01, 330 31",
            "bank_details": {
                "bankgiro": "104-2456",
                "postgiro": "22877-5"
            },
            "activity": "Tillverkar o säljer sågade o hyvlade trävaror",
            "employees": 115,
            "annual_turnover": 18000000,
            "capital": 201000,
            "key_personnel": [
                {
                    "name": "Yngve Andersson"
                }
            ],
            "establishment_year": 1927
        },
        "3": {
            "company_name": "ANDERSON &amp; CO AB, RORBOLAGET HJ",
            "pnr": "502 34",
            "address": "Borås, Skaraborgsv 40",
            "phone_number": "033-1127 99, 1120 99",
            "bank_details": {
                "bankgiro": "53-1149",
                "postgiro": "82253"
            },
            "activity": "Värme-, sanitets- o ventilationsanläggningar",
            "employees": 24,
            "annual_turnover": 2000000,
            "capital": 150000,
            "key_personnel": [
                {
                    "name": "Sixten Anderson"
                }
            ],
            "establishment_year": 1927
        },
        "4": {
            "company_name": "PRAKTISKA NYHETER, AB",
            "pnr": "114 58",
            "address": "Stockholm, Linnég 51-53",
            "phone_number": "08-67 00 70",
            "bank_details": {
                "bankgiro": "447-0019",
                "postgiro": "1329-2"
            },
            "activity": "Brunit skärplatta, Woly skovårdsmedel, maskiner",
            "employees": 15,
            "capital": 350000,
            "key_personnel": [
                {
                    "name": "Harry Brunner"
                }
            ],
            "establishment_year": 1908
        },
        "5": {
            "company_name": "PRAMBERGS METALLVARUFABRIK, S",
            "pnr": "244 00",
            "address": "Kävlinge, Bäckv 15",
            "phone_number": "046-317 48",
            "bank_details": {
                "bankgiro": "260-7083",
                "postgiro": "536420-3"
            },
            "activity": "Tillverkar bly- o trådplomber samt plomberingstråd",
            "key_personnel": [
                {
                    "name": "Sten Pramberg"
                }
            ],
            "establishment_year": 1960
        },
        "6": {
            "company_name": "GOTEBORGS ASFALT AB",
            "pnr": "417 07",
            "address": "Göteborg, Stålverksg 16",
            "phone_number": "031-23 23 50",
            "activity": "Golvläggning samt säljer fogmassa o asfalt. Entreprenadarbeten",
            "employees": 20,
            "annual_turnover": 2500000,
            "capital": 45000,
            "key_personnel": [
                {
                    "name": "Ing Stig Nilsson"
                }
            ],
            "establishment_year": 1922
        },
        "7": {
            "company_name": "PLEXI PRODUKTER AB",
            "pnr": "114 55",
            "address": "Stockholm, Storg 30",
            "phone_number": "08-60 60 81, 60 60 89",
            "bank_details": {
                "bankgiro": "44-7126",
                "postgiro": "3235"
            },
            "activity": "Säljer bearbetad acryl-plast, kupoler, telefonhytter",
            "employees": 3,
            "annual_turnover": 600000,
            "capital": 20000,
            "key_personnel": [
                {
                    "name": "Sven Jonsson"
                },
                {
                    "name": "Bertil Olander"
                }
            ],
            "establishment_year": 1961
        },
        "8": {
            "company_name": "PLIBRICO ELDFAST MATERIAL AB",
            "pnr": "411 01",
            "address": "Göteborg, stampg 38",
            "phone_number": "031-1971 05",
            "bank_details": {
                "bankgiro": "852-4480",
                "postgiro": "422071-1"
            },
            "activity": "Eldfasta infodringar för ångpannor o industriugnar. Konstruktion o tillverkning av sopförbränningsugnar. Försäljning av högeldfasta stamp-, ram- o gjut-massor samt eldfast cement",
            "employees": 30,
            "annual_turnover": 5000000,
            "capital": 345000,
            "key_personnel": [
                {
                    "name": "Magnus Björkman"
                }
            ],
            "establishment_year": 1937
        },
        "9": {
            "company_name": "ANDÉN AB, LENNART",
            "pnr": "500 05",
            "address": "Borås 5, S Kyrkog 31. Box 55028",
            "phone_number": "033-10 31 10, 10 31 11",
            "bank_details": {
                "bankgiro": "560-0176",
                "postgiro": "9560-4"
            },
            "activity": "Textil-, plast- o flockningsmaskiner o tillbehör, instrument o utrustning för berö-rlngsfri mätning o styrning, ståltråd o linor, lim",
            "employees": 4,
            "capital": 60000,
            "key_personnel": [
                {
                    "name": "Civiling Lennart Andèn"
                }
            ],
            "establishment_year": 1953
        },
        "10": {
            "company_name": "ETERNA AB",
            "pnr": "114 35",
            "address": "Stockholm, Stureg 6",
            "phone_number": "08-113200, 1132 16",
            "activity": "Säljer ur en gros",
            "employees": 11,
            "annual_turnover": 1000000,
            "capital": 60000,
            "key_personnel": [
                {
                    "name": "Horst Bramsen"
                }
            ],
            "establishment_year": 1945
        },
        "11": {
            "company_name": "ETERNITRDR, AB",
            "pnr": "432 00",
            "address": "Varberg, Box 197. Getteröv",
            "phone_number": "0340-16170",
            "bank_details": {
                "bankgiro": "67-3153",
                "postgiro": "246346"
            },
            "activity": "Tillverkar o säljer asbestcementrör o rördelar under varumärket Eternitrör",
            "employees": 115,
            "annual_turnover": 16000000,
            "capital": 6000000,
            "key_personnel": [
                {
                    "name": "Ingmar Forsström"
                }
            ],
            "establishment_year": 1947
        },
        "12": {
            "company_name": "ESKIL PRODUCTS LTD, AB",
            "pnr": "63103",
            "address": "Eskilstuna 1, Nyg 17. Box 220",
            "phone_number": "016-1415 60",
            "bank_details": {
                "bankgiro": "601-7305",
                "postgiro": "13438-7"
            },
            "activity": "Försäljningsbolag för elektroniktänger",
            "annual_turnover": 600000,
            "capital": 150000,
            "key_personnel": [
                {
                    "name": "Sven Wedén"
                },
                {
                    "name": "Stig Eliasson"
                },
                {
                    "name": "Marianne Wedén"
                }
            ],
            "establishment_year": 1957
        },
        "13": {
            "company_name": "ESKILSSONS STANS- &amp; PRESSVERKTYG AB",
            "pnr": "282 00",
            "address": "Tyringe, Box 110. Municipalg 3",
            "phone_number": "0451-50 9 20",
            "bank_details": {
                "bankgiro": "288-9145",
                "postgiro": "337163"
            },
            "activity": "Tillverkar stans- o press verktyg för plåt, formverktyg för gummi, plast o keramisk industri, jiggar o fixturer, stansknivar för gummi, läder o pappersindustri, knivar för tobaksindustrin samt pelarställ o verktygstillbehör",
            "employees": 125,
            "annual_turnover": 7500000,
            "capital": 48000,
            "key_personnel": [
                {
                    "name": "Fru Stina Eskilsson"
                },
                {
                    "name": "ing Bengt Eskilsson"
                },
                {
                    "name": "disp Roland Lundgren"
                }
            ],
            "establishment_year": 1941
        },
        "14": {
            "company_name": "SELPRO AB",
            "pnr": "401 24",
            "address": "Göteborg 1, Box 245. Aschebergsg 1",
            "phone_number": "031-17 6240",
            "bank_details": {
                "bankgiro": "302-0369",
                "postgiro": "722601-2"
            },
            "activity": "Intern materialhantering på den svenska marknaden. Export av svenska produkter inom intern materialhantering med egna agenter i England, Sydafrika, Nya Zeeland, USA, Tyskland. Frankrike samt Finland. Generalagent för Flexello Castors (Export) Ltd, England (länk- o fasthjul), Stilson Inc, USA (produkter för hantering med vakuum). Henley Forklift Co Ltd, England (truckar) samt Stewart Gill &amp; Co Ltd, England (hängtran-sportörer)",
            "employees": 7,
            "annual_turnover": 4000000,
            "capital": 25000,
            "key_personnel": [
                {
                    "name": "Dir Olof Wåhlin"
                },
                {
                    "name": "ing Mats Norrman"
                }
            ],
            "establishment_year": 1970
        },
        "15": {
            "company_name": "SEMDA, AB",
            "pnr": "412 53",
            "address": "Göteborg, Hedåsg 3",
            "phone_number": "031-165242, 1652 33",
            "bank_details": {
                "bankgiro": "847-8711",
                "postgiro": "42220-4"
            },
            "activity": "Förnödenheter för herr- o damfriseringar",
            "employees": 8,
            "annual_turnover": 700000,
            "capital": 36000,
            "key_personnel": [
                {
                    "name": "Fru Elsa Landström"
                }
            ],
            "establishment_year": 1931
        },
        "16": {
            "company_name": "SEMPERIT SVENSKA AB",
            "pnr": "10310",
            "address": "Stockholm 2, Fack. Skeppsbron 20",
            "phone_number": "08-24 88 60",
            "bank_details": {
                "bankgiro": "566-0626",
                "postgiro": "55302-4"
            },
            "activity": "Import o grosshandel med ’Semperit’ däck o tekniska gummivaror samt polyeter",
            "employees": 35,
            "capital": 1000000,
            "establishment_year": 1965
        },
        "17": {
            "company_name": "SEPSON S E PETERSONS MEKANISKA VERKSTAD AB",
            "pnr": "780 50",
            "address": "Vansbro, Järnav 4. Box 680",
            "phone_number": "0281-110 00",
            "bank_details": {
                "bankgiro": "798-9072",
                "postgiro": "163551-5"
            },
            "activity": "Vinschar, kranar, traktorhytter, block o saxar",
            "employees": 80,
            "annual_turnover": 5000000,
            "capital": 50000,
            "key_personnel": [
                {
                    "name": "Ing Gunnar Peterson"
                }
            ],
            "establishment_year": 1949
        },
        "18": {
            "company_name": "SERGEL SEKRETERAR-SERVICE AB",
            "pnr": "11134",
            "address": "Stockholm, Sveav 25-27",
            "phone_number": "08-205190, 2015 61",
            "bank_details": {
                "bankgiro": "618-5177",
                "postgiro": "258825-9"
            },
            "activity": "Fullständig kontorsservice med skrivbyråverksamhet",
            "employees": 3,
            "annual_turnover": 100000,
            "capital": 5000,
            "key_personnel": [
                {
                    "name": "Dagmar Martin"
                }
            ],
            "establishment_year": 1970
        },
        "19": {
            "company_name": "AXELSSON INDUSTRI AB, G E",
            "pnr": "653 50",
            "address": "Karlstad, Postl 675. Granlidsv 71",
            "phone_number": "054-30485, 300 56",
            "bank_details": {
                "bankgiro": "100-1411",
                "postgiro": "175767-3"
            },
            "activity": "Sågar klent timmer till reglar, sparrar o dyl",
            "employees": 10,
            "annual_turnover": 2500000,
            "capital": 100000,
            "key_personnel": [
                {
                    "name": "Gunnar E Axelsson"
                }
            ],
            "establishment_year": 1935
        }
    }
}