{
    "original": "NILSSON &amp; INGELSTEN\n\nPnr 33100\n\nVärnamo, Lillegårdsg 3. Tel\n0370-162 22, 16410. Bankgiro 54-2608.\nPostgiro 164583\n\nVerksamhet: Tillverkar\nbutiksinredningar, stålmåttband,\ncementskyfflar, snöskyfflar, sprutboxar,\nlackeringsugnar. Legotillverkning av\npressade artiklar i plåt,\ntrådartiklar, halvfabrikat åt andrå\nindustrier m m\n\nÅrsomsättning: 5 500 000\nChef: Carl Nilsson.\n\nNILLSON &amp; LUTHMAN, AB\n\nPnr 15102\n\nSödertälje 2, Fack. Hertig Carls v\n46. Tel 0755-325 90. Bankgiro\n622-5791. Postgiro 22004-6\nVerksamhet: Säljer by gg smide,\njärn, stål mm i parti\nAntal anställda: 45\nÅrsomsättning: 12 000 000\nAktiekapital: 250 000\nVerkst dir: Per R Forsberg\nEtableringsår: 1882.\n\nNILSSONS MEK VERKSTAD\nEFTR AB\n\nPnr 602 63\n\nBorås, Getängsv 11. Tel\n033-1168 65. Bankgiro 531-1287.\nPostgiro 277844-7\n\nVerksamhet: utför på beställning\n\njärnkonstruktioner, byggnadssmide\nAntal anställda: 25\nÅrsomsättning: 1000 000\nAktiekapital: 53 600\nVerkst dir: Ake Johansson\nEtableringsår: 1940.\n\ndannemora gruvor, ab\n\nPnr 740 62\n\nDannemora. Tel 0295-207 20.\nBankgiro 80-4102. Postgiro 135853.\nTga Gruvkontoret\nVerksamhet: Bryter järnmalm\n(styckemalm o slig)\nAktiekapital: 3 000000\nStyrelse: Bruksdisp Lars Edlund\n(ordf), dir Sven Sjöberg, disp\nGunnar Stenberg, dir Bengt Torssell,\ndisp Lais G Sundblad\nVerkst dir: Disp Gunnar Stenberg\nEtableringsår: 1937.\n\nREKLAMMOSSOR AB\n\nPnr 70102\n\nÖrebro 1, Olaig 7. Box 9. Tel\n019-189250. Bankgiro 81-5883.\nPost-giro 513159. Tga Reklammössor\nVerksamhet: Tillverkar o säljer\nreklammössor o hattar. Störst i\npresentreklam. Besök på begäran\nmed utställningsbuss\nAktiekapital: 5 000\nVerkst dir: Elvin Ohlsson\nEtableringsår: 1959.\n\nDÅNGS VERKSTÄDER, AB\n\nPnr 360 21\n\nKonga. Tel 0477-160 95, 16054\nVerksamhet: Tillverkar sopkärl,\nsopsäcksställningar,\nsopförbränningsugnar o vattenvärmare\nVarunamn: Dåver, Sani-Lett\nAntal anställda: 21\n.Aktiekapital: 60 000\nVerkst dir: Arnold Haglund\nEtableringsår: 1945.\n\nBRATTEFORS BRUK AB\n\nPnr 533 00\n\nGötene. Tel 0511-58109, 58106\nVerksamhet: Tillverkar\nkalkstens-filler, kalkstensmjöl, bränd målen\njordbrukskalk, hydratkalk, makadam,\ngjuterikalk o foderkalk\nAntal anställda: 40\nÅrsomsättning: 2 500 000\nAktiekapital: 50 000\nVerkst dir: Håkan Knutsson\nEtableringsår: 1918.\n\nFEN\n\nFAXE AB, G C\n\nPnr 201 10\n\nMalmö 1, Pack. Larocheg 4. Tel\n040-70860. Bankgiro 640-1657.\nPostgiro 39090-6. Tga Faxius.\nTelex 32504\n\nVerksamhet: Försäljning av gaser.\nKommissionär för Alfax AB, Malmö\nAktiekapital: 1000 000\nVerkst dir: J Faxe\nEtableringsår: 1906.\n\nFCB FOOTE, CONE &amp;\nBELDING AB\n\nPnr 105 62\n\nStockholm, Kungsg 5. Tel\n08-24 02 40. Bankgiro 72-4987.\nPostgiro 154852-8. Tga Effceebee.\nTelex 10736 FCB S\nVerksamhet: Nominerad\nannonsförmedlare\n\nAvdelningskontor: 21134 Malmö,\nSöderg 12. Tel 040-762 10. Telex\n32562 FCB S. Tga Effceebee\nAktiekapital: 1250 000\nVerkst dir: Christian Preisler\nEtableringsår: 1938.\n\nELEKTROINDIKATOR AB\n\nPnr 75106\n\nUppsala 1, Box 400. Marsta. Tel\n018-3672 20. 3672 22. Bankgiro\n24-0019. Postgiro 592220\nVerksamhet: Säljer\nanalysinstrument för vatten o avloppsvatten,\npH-mätinstrument för laboratorier\no industri, syrehaltsmätare, testset\nför vattenundersökningar,\nkontinuerligt analyserande instrument för\nvattenverk etc, analyskemikalier för\nvattenundersökningar, alla typer av\nkonduktivitetsmätinstrument.\nDoseringsutrustningar, instrumentservice\n\nAntal anställda: 4\nÅrsomsättning: 900 000\nAktiekapital: 5 000\nStyrelse: Flygtekniker Verner\nEriksson (ordf), Hans Johansson, ing\nRolf Bodeck\n\nVerkst dir: Ing Rolf J Bodeck\nVerkstadschef: Hans G Johansson\nEtableringsår: 1962.\n\nCOLLIANDER &amp; CO AB, GÖSTA\n\nPnr 733 00\n\nSala, Box 62. Brunnsg 26-28. Tel\n0224-108 89, 108 15. Bankgiro\n661-8144. Postgiro 416347-3\nVerksamhet: Säljer kätting,\nsnökedja-, slirskydd samt jaktvapen\nVarunamn: Sala-kätting, Orginal\nSauer o Sohn\nÅrsomsättning: 500 000\nAktiekapital: 35 000\nVerkst dir: Gösta Colliander\nEtableringsår: 1958.\n\nhemek verkstads ab\n\nPnr 820 93\n\nHede. Tel 0684-105 25. Bankgiro\n77-94 1 3. Postgiro 584553. Tga\nHemek\n\nVerksamhet: Tillverkar\nskogstrak-torutrustningar\nAntal anställda: 47\nÅrsomsättning: 6 000 000\nVerkst dir: Carl V Larsson\nEtableringsår: 1962.\n\nLINDMARK &amp; NILSSON, AB\n\nPnr 70104\n\nÖrebro l.Box 260.Tel 019-125400.\nBankgiro 61-4375. Postgiro 5276.\nTga Abil\n\nVerksamhet: Flätade band o snören\nAktiekapital: 50 000\nVerkst dir: Birger Lindmark\nEtableringsår: 1855.\n\nLINDMARKS TRÄVARU AB,\nAXEL\n\nPnr 96100\n\nBoden, Björkelundsv 5. Tel\n0921-123.50, 134 80, 195 80. Bankgiro\n753-4100. Postgiro 481483-6\nVerksamhet: Tillverkar o säljer\nsågade o hyvlade trävaror samt\nallt slags byggnadsmateriel av trä\nAntal anställda: 25\n\nÅrsomsättning: 2800 000\n\nAktiekapital: 150000\nVerkst din Billy Lindmark\nEtableringsån 1926.",
    "structured": {
        "1": {
            "company_name": "NILSSON & INGELSTEN",
            "pnr": "33100",
            "address": "Värnamo, Lillegårdsg 3",
            "phone_number": "0370-162 22, 16410",
            "bank_details": {
                "bankgiro": "54-2608",
                "postgiro": "164583"
            },
            "activity": "Tillverkar butiksinredningar, stålmåttband, cementskyfflar, snöskyfflar, sprutboxar, lackeringsugnar. Legotillverkning av pressade artiklar i plåt, trådartiklar, halvfabrikat åt andra industrier m m",
            "annual_turnover": 5500000,
            "key_personnel": [
                {
                    "name": "Carl Nilsson",
                    "position": "Chef"
                }
            ],
            "establishment_year": 0
        },
        "2": {
            "company_name": "NILLSON & LUTHMAN, AB",
            "pnr": "15102",
            "address": "Södertälje 2, Fack. Hertig Carls v 46",
            "phone_number": "0755-325 90",
            "bank_details": {
                "bankgiro": "622-5791",
                "postgiro": "22004-6"
            },
            "activity": "Säljer byggsmide, järn, stål mm i parti",
            "employees": 45,
            "annual_turnover": 12000000,
            "capital": 250000,
            "key_personnel": [
                {
                    "name": "Per R Forsberg",
                    "position": "Verkst dir"
                }
            ],
            "establishment_year": 1882
        },
        "3": {
            "company_name": "NILSSONS MEK VERKSTAD EFTR AB",
            "pnr": "60263",
            "address": "Borås, Getängsv 11",
            "phone_number": "033-1168 65",
            "bank_details": {
                "bankgiro": "531-1287",
                "postgiro": "277844-7"
            },
            "activity": "Utför på beställning järnkonstruktioner, byggnadssmide",
            "employees": 25,
            "annual_turnover": 1000000,
            "capital": 53600,
            "key_personnel": [
                {
                    "name": "Ake Johansson",
                    "position": "Verkst dir"
                }
            ],
            "establishment_year": 1940
        },
        "4": {
            "company_name": "DANNEMORA GRUVOR, AB",
            "pnr": "74062",
            "address": "Dannemora",
            "phone_number": "0295-207 20",
            "bank_details": {
                "bankgiro": "80-4102",
                "postgiro": "135853"
            },
            "activity": "Bryter järnmalm (styckemalm och slig)",
            "capital": 3000000,
            "key_personnel": [
                {
                    "name": "Disp Gunnar Stenberg",
                    "position": "Verkst dir"
                }
            ],
            "establishment_year": 1937
        },
        "5": {
            "company_name": "REKLAMMOSSOR AB",
            "pnr": "70102",
            "address": "Örebro 1, Olaig 7, Box 9",
            "phone_number": "019-189250",
            "bank_details": {
                "bankgiro": "81-5883",
                "postgiro": "513159"
            },
            "activity": "Tillverkar och säljer reklammössor och hattar. Störst i presentreklam. Besök på begäran med utställningsbuss",
            "capital": 5000,
            "key_personnel": [
                {
                    "name": "Elvin Ohlsson",
                    "position": "Verkst dir"
                }
            ],
            "establishment_year": 1959
        },
        "6": {
            "company_name": "DÅNGS VERKSTÄDER, AB",
            "pnr": "36021",
            "address": "Konga",
            "phone_number": "0477-160 95, 16054",
            "activity": "Tillverkar sopkärl, sopsäcksställningar, sopförbränningsugnar och vattenvärmare",
            "varunamn": "Dåver, Sani-Lett",
            "employees": 21,
            "capital": 60000,
            "key_personnel": [
                {
                    "name": "Arnold Haglund",
                    "position": "Verkst dir"
                }
            ],
            "establishment_year": 1945
        },
        "7": {
            "company_name": "BRATTEFORS BRUK AB",
            "pnr": "53300",
            "address": "Götene",
            "phone_number": "0511-58109, 58106",
            "activity": "Tillverkar kalkstens-filler, kalkstensmjöl, bränd målen jordbrukskalk, hydratkalk, makadam, gjuterikalk och foderkalk",
            "employees": 40,
            "annual_turnover": 2500000,
            "capital": 50000,
            "key_personnel": [
                {
                    "name": "Håkan Knutsson",
                    "position": "Verkst dir"
                }
            ],
            "establishment_year": 1918
        },
        "8": {
            "company_name": "FEN FAXE AB, G C",
            "pnr": "20110",
            "address": "Malmö 1, Pack. Larocheg 4",
            "phone_number": "040-70860",
            "bank_details": {
                "bankgiro": "640-1657",
                "postgiro": "39090-6"
            },
            "activity": "Försäljning av gaser. Kommissionär för Alfax AB, Malmö",
            "capital": 1000000,
            "key_personnel": [
                {
                    "name": "J Faxe",
                    "position": "Verkst dir"
                }
            ],
            "establishment_year": 1906
        },
        "9": {
            "company_name": "FCB FOOTE, CONE & BELDING AB",
            "pnr": "10562",
            "address": "Stockholm, Kungsg 5",
            "phone_number": "08-24 02 40",
            "bank_details": {
                "bankgiro": "72-4987",
                "postgiro": "154852-8"
            },
            "activity": "Nominerad annonsförmedlare",
            "avdelningskontor": "21134 Malmö, Söderg 12",
            "phone_number_avdelning": "040-762 10",
            "capital": 1250000,
            "key_personnel": [
                {
                    "name": "Christian Preisler",
                    "position": "Verkst dir"
                }
            ],
            "establishment_year": 1938
        },
        "10": {
            "company_name": "ELEKTROINDIKATOR AB",
            "pnr": "75106",
            "address": "Uppsala 1, Box 400, Marsta",
            "phone_number": "018-3672 20, 3672 22",
            "bank_details": {
                "bankgiro": "24-0019",
                "postgiro": "592220"
            },
            "activity": "Säljer analysinstrument för vatten och avloppsvatten, pH-mätinstrument för laboratorier och industri, syrehaltsmätare, testset för vattenundersökningar, kontinuerligt analyserande instrument för vattenverk etc, analyskemikalier för vattenundersökningar, alla typer av konduktivitetsmätinstrument. Doseringsutrustningar, instrumentservice",
            "employees": 4,
            "annual_turnover": 900000,
            "capital": 5000,
            "key_personnel": [
                {
                    "name": "Ing Rolf J Bodeck",
                    "position": "Verkst dir"
                },
                {
                    "name": "Hans G Johansson",
                    "position": "Verkstadschef"
                }
            ],
            "establishment_year": 1962
        },
        "11": {
            "company_name": "COLLIANDER & CO AB, GÖSTA",
            "pnr": "73300",
            "address": "Sala, Box 62, Brunnsg 26-28",
            "phone_number": "0224-108 89, 108 15",
            "bank_details": {
                "bankgiro": "661-8144",
                "postgiro": "416347-3"
            },
            "activity": "Säljer kätting, snökedja-, slirskydd samt jaktvapen",
            "varunamn": "Sala-kätting, Orginal Sauer o Sohn",
            "annual_turnover": 500000,
            "capital": 35000,
            "key_personnel": [
                {
                    "name": "Gösta Colliander",
                    "position": "Verkst dir"
                }
            ],
            "establishment_year": 1958
        },
        "12": {
            "company_name": "HEMEK VERKSTADS AB",
            "pnr": "82093",
            "address": "Hede",
            "phone_number": "0684-105 25",
            "bank_details": {
                "bankgiro": "77-94 1 3",
                "postgiro": "584553"
            },
            "activity": "Tillverkar skogstraktorutrustningar",
            "employees": 47,
            "annual_turnover": 6000000,
            "key_personnel": [
                {
                    "name": "Carl V Larsson",
                    "position": "Verkst dir"
                }
            ],
            "establishment_year": 1962
        },
        "13": {
            "company_name": "LINDMARK & NILSSON, AB",
            "pnr": "70104",
            "address": "Örebro 1, Box 260",
            "phone_number": "019-125400",
            "bank_details": {
                "bankgiro": "61-4375",
                "postgiro": "5276"
            },
            "activity": "Flätade band och snören",
            "capital": 50000,
            "key_personnel": [
                {
                    "name": "Birger Lindmark",
                    "position": "Verkst dir"
                }
            ],
            "establishment_year": 1855
        },
        "14": {
            "company_name": "LINDMARKS TRÄVARU AB, AXEL",
            "pnr": "96100",
            "address": "Boden, Björkelundsv 5",
            "phone_number": "0921-123.50, 134 80, 195 80",
            "bank_details": {
                "bankgiro": "753-4100",
                "postgiro": "481483-6"
            },
            "activity": "Tillverkar och säljer sågade och hyvlade trävaror samt allt slags byggnadsmateriel av trä",
            "employees": 25,
            "annual_turnover": 2800000,
            "capital": 150000,
            "key_personnel": [
                {
                    "name": "Billy Lindmark",
                    "position": "Verkst dir"
                }
            ],
            "establishment_year": 1926
        }
    }
}