{
    "original": "AHLSTRÖM AB, SEWERIN\n\nPnr 570 15\n\nHolsbybrunn. Tel 0383-50100.\nBankgiro 289-6074. Postgiro\n10830-8\n\nVerksamhet: Allt i papper.\nEmballage för industrin o detaljaffärer.\nPåsar, säckar, folie o slang i plast.\nAlla slags tejper\nAntal anställda: 15\nÅrsomsättning: 7000 000\nAktiekapital: 100 000\nVerkst dir: Sven Ahlström\nPlatschef: Disp Kurt Thureson\nKamrer: Lennart Adolphson\nFörsäljn-chef: Stig Thureson\nEtableringsår: 1912.\n\nKRONOBERG, TRYCKERI AB\n\nPnr 351 03\n\nVäxjö 1, Sandgärdsg 22. Box 68.\nTel 0470-127 27. Postgiro 14259\nVerksamhet: Tidnings- o\nciviltryckeri\n\nAntal anställda: 56\nÅrsomsättning: 3 035499\nAktiekapital: 180 000\nVerkst dir: Arne Andersson\nEtableringsår: 1934.\n\nELOS, INDUSTRI AB\n\nPnr 54016\n\nTimmersdala. Tel 0511-81133\nVerksamhet: Finmekanik,\ninstrument, verktyg o experimentarbeten.\nPrecisionskugghjul M 0,2-4,0\nAntal anställda: 25\nAktiekapital: 45 000\nVerkst dir: Fabr Sven Ekström\nEtableringsår: 1951.\n\nGRU\n\nmedel, desinfektions- o sårmedel,\nhandrengöringsmedel samt disk- o\nrengöringsmedel för hushåll o\nindustri\n\nAntal anställda: 110\nÅrsomsättning: 19 000 000\nAktiekapital: 5 000 000\nStyrelse: Dr David Isaksson (ordf),\ndir Sigvard Göranson, dir Arthur\nKalms kog\n\nVerkst dir: Arthur Kalmskog\nFabrikschef: Ragnar Larsson\nAdm-chef: J E Bendel\nInköpschef: Willar Lidholm\nMarknadschef: Sven Sundin\nEtableringsår:\n1908-Dotterbolag till Statsföretag AB\n(1969). Aktierna ägs av AB Kabi\n(1964).\n\nGRUMS PLÅT. &amp; MEK\nVERKSTAD\n\nPnr 664 00\n\nGrums, Sveag 126. Tel0555-10052.\nBankgiro 10-7104. Postgiro 162283\nVerksamhet: Grov- o\ntunnplåtslageri. Ventilationer\nAntal anställda: 4\nÅrsomsättning: 4 000 000\nChef: Nils Forsberg\nEtableringsår: 1944.\n\nGRUNDBERGS MEKANISKA\nVERKSTADS AB\n\nPnr 46101\n\nTrollhättan 1, Stallbackav. Box 5.\nTel 0520-125 60. Bankgiro\n892-5117. Postgiro 33888-9.\nTga Grundbergs\n\nVerksamhet: Utfor\njärnkonstruktioner, maskinbyggnader o\nreparationer\n\nAntal anställda: 75\nÅrsomsättning: 5 000 000\nAktiekapital: 1 000 000\nVerkst dir: Ing Sven Erik\nGrundberg\n\nEtableringsår: 1917.\n\nTOMTA SÄG\n\nPnr 760 45\n\nGrisslehamn, Tomta. Tel\n0175-301 70. Bankgiro 452-6190.\nPostgiro 383200-3\n\nVerksamhet: Tillverkar\nfritidsbostäder. Säljer byggmaterial.\nSågverk. Handelsbrädgård\nVarunamn: Grisslehamnsstugan\n\nAntal anstäUda: 20\nÅrsomsättning: 2 000 000\nÄgare o chefer: Matts Andersson,\nGunnar Andersson\nEtableringsår: 1923.\n\nSVENSSON, EINAR\n\nPnr 413 19\n\nGöteborg, Änggårdsg 40. Tel\n031-82 9213. Bankgiro 509-7134.\nPost-giro 422285-7\n\nVerksamhet: Specialitet: säljer\nsaxar engros för yrkesfolk\nÄgare o chef: Einar Svensson\nEtableringsår: 1947.\n\nSVENSSONS T RAPPFABRIK\nAB, ERIC\n\nPnr 570 13\n\nMyresjö, Hjältaryd. Postl 350. Tel\n0383-91059, 910 69. Bankgiro\n144-9958. Postgiro 464735-0\nVerksamhet: Tillverkar trappor i\nfuru o ek\n\nVerkst dir: Erie Svensson\nEtableringsår: 1946.\n\nSVENSSON SLÖJD &amp; METALL.\nVERKSTAD, F F\n\nPnr 360 70\n\nAseda, Skolg 9. Tel 0474-104 30.\nBankgiro 85-8522. Postgiro 99755-1\nVerksamhet: Tillverkar\nslipstens-o smärgelmaskiner\nAntal anställda: 4\nÅrsomsättning: 300 000\nChef: Fabr F F Svensson\nEtableringsår: 1938.\n\nPALMBLAD AB, BO\n\nPnr 104 62\n\nStockholm 17, Hornsg 58. Box\n17081. Tel 08-24 6160. Bankgiro\n733-2232. Postgiro 193972. Tga\nZedkey. Telex 10696 ZEDKEY S\nVeiksamhet: Säljer\nelektronikkomponenter samt anknytande\nelektromekaniska produkter\nAktiekapital: 100 000\nVeikst dir: Bertil G A Hofberg\nEtableringsår: 1949.\n\nBORENS TRIKÅFABRIK AB\n\nPnr 59101\n\nMotala 1, Abborrgränd 5. Box 67.\nTel 0141-160 40. Postgiro 177317.\nTga Borens Trikåfabrik\nVerksamhet: Tillverkar tiikåvaror\nVerkst dir: Ivar Ericson\nEtableringsår: 1916.\n\nKARLSTRÖM, AB H\n\nPnr 73101\n\nKöping 1, O Långg 13. Box 194.\nTel 0221-139 20. Bankgiro\n811-2419. Postgiro 26921-7. Tga\nKarl-strömstex\n\nVerksamhet: Säljer svenska o\nutländska textilvaror en gros\nAntal anställda: 21\nÅrsomsättning: 12 000 000\nStyrelse: Grossh Bror Hansson\n(ordf), grossh Max Follin\nVerkst dir: Grossh Bror Hansson\nEtableringsår: 1928.\n\nKARMI FÖRETAGSKONSULT.\nBYRA, I\n\nPnr 113 28\n\nStockholm, Upplandsg 38. Tel\n08-30 34 63. Postgiro 658815\nVerksamhet: Administrativ\norganisation, personurval o ledarutbildning\nChef: ls.o Karmi\nEtableringsår: 1967.\n\nOMAN, AB M F\n\nPnr 93100\n\nSkellefteå, Storg 39. Tel\n0910-144 30. Bankgiro 203-9311.\nPostgiro 61632-6. Tga Textilöman\nVerksamhet: Textilvaror o mattor\ni parti o minut\nAntal anställda: 30\n.Aktiekapital: 300 000\nVerkst dir: Erik öman\nEtableringsår: 1937.",
    "structured": {
        "1": {
            "company_name": "AHLSTRÖM AB",
            "activity": "Allt i papper. Emballage för industrin o detaljaffärer. Påsar, säckar, folie o slang i plast. Alla slags tejper",
            "establishment_year": 1912,
            "employees": 15,
            "annual_turnover": 7000000,
            "capital": 100000,
            "key_personnel": [
                {
                    "name": "Sven Ahlström",
                    "position": "Verkst dir"
                },
                {
                    "name": "Disp Kurt Thureson",
                    "position": "Platschef"
                },
                {
                    "name": "Lennart Adolphson",
                    "position": "Kamrer"
                },
                {
                    "name": "Stig Thureson",
                    "position": "Försäljn-chef"
                }
            ]
        },
        "2": {
            "company_name": "KRONOBERG, TRYCKERI AB",
            "activity": "Tidnings- o civiltryckeri",
            "establishment_year": 1934,
            "employees": 56,
            "annual_turnover": 3035499,
            "capital": 180000,
            "key_personnel": [
                {
                    "name": "Arne Andersson",
                    "position": "Verkst dir"
                }
            ]
        },
        "3": {
            "company_name": "ELOS, INDUSTRI AB",
            "activity": "Finmekanik, instrument, verktyg o experimentarbeten. Precisionskugghjul M 0,2-4,0",
            "establishment_year": 1951,
            "employees": 25,
            "capital": 45000,
            "key_personnel": [
                {
                    "name": "Fabr Sven Ekström",
                    "position": "Verkst dir"
                }
            ]
        },
        "4": {
            "company_name": "GRUMS PLÅT. & MEK VERKSTAD",
            "activity": "Grov- o tunnplåtslageri. Ventilationer",
            "establishment_year": 1944,
            "employees": 4,
            "annual_turnover": 4000000,
            "key_personnel": [
                {
                    "name": "Nils Forsberg",
                    "position": "Chef"
                }
            ]
        },
        "5": {
            "company_name": "GRUNDBERGS MEKANISKA VERKSTADS AB",
            "activity": "Utfor järnkonstruktioner, maskinbyggnader o reparationer",
            "establishment_year": 1917,
            "employees": 75,
            "annual_turnover": 5000000,
            "capital": 1000000,
            "key_personnel": [
                {
                    "name": "Ing Sven Erik Grundberg",
                    "position": "Verkst dir"
                }
            ]
        },
        "6": {
            "company_name": "TOMTA SÄG",
            "activity": "Tillverkar fritidsbostäder. Säljer byggmaterial. Sågverk. Handelsbrädgård",
            "establishment_year": 1923,
            "employees": 20,
            "annual_turnover": 2000000,
            "key_personnel": [
                {
                    "name": "Matts Andersson",
                    "position": "Ägare o chefer"
                },
                {
                    "name": "Gunnar Andersson",
                    "position": "Ägare o chefer"
                }
            ]
        },
        "7": {
            "company_name": "SVENSSON, EINAR",
            "activity": "Specialitet: säljer saxar engros för yrkesfolk",
            "establishment_year": 1947,
            "key_personnel": [
                {
                    "name": "Einar Svensson",
                    "position": "Ägare o chef"
                }
            ]
        },
        "8": {
            "company_name": "SVENSSONS T RAPPFABRIK AB, ERIC",
            "activity": "Tillverkar trappor i furu o ek",
            "establishment_year": 1946,
            "key_personnel": [
                {
                    "name": "Erie Svensson",
                    "position": "Verkst dir"
                }
            ]
        },
        "9": {
            "company_name": "SVENSSON SLÖJD & METALL. VERKSTAD, F F",
            "activity": "Tillverkar slipstens-o smärgelmaskiner",
            "establishment_year": 1938,
            "employees": 4,
            "annual_turnover": 300000,
            "key_personnel": [
                {
                    "name": "Fabr F F Svensson",
                    "position": "Chef"
                }
            ]
        },
        "10": {
            "company_name": "PALMBLAD AB, BO",
            "activity": "Säljer elektronikkomponenter samt anknytande elektromekaniska produkter",
            "establishment_year": 1949,
            "capital": 100000,
            "key_personnel": [
                {
                    "name": "Bertil G A Hofberg",
                    "position": "Veikst dir"
                }
            ]
        },
        "11": {
            "company_name": "BORENS TRIKÅFABRIK AB",
            "activity": "Tillverkar tiikåvaror",
            "establishment_year": 1916,
            "key_personnel": [
                {
                    "name": "Ivar Ericson",
                    "position": "Verkst dir"
                }
            ]
        },
        "12": {
            "company_name": "KARLSTRÖM, AB H",
            "activity": "Säljer svenska o utländska textilvaror en gros",
            "establishment_year": 1928,
            "employees": 21,
            "annual_turnover": 12000000,
            "key_personnel": [
                {
                    "name": "Grossh Bror Hansson",
                    "position": "Styrelse"
                },
                {
                    "name": "Grossh Max Follin",
                    "position": "Styrelse"
                },
                {
                    "name": "Grossh Bror Hansson",
                    "position": "Veikst dir"
                }
            ]
        },
        "13": {
            "company_name": "KARMI FÖRETAGSKONSULT. BYRA, I",
            "activity": "Administrativ organisation, personurval o ledarutbildning",
            "establishment_year": 1967,
            "key_personnel": [
                {
                    "name": "ls.o Karmi",
                    "position": "Chef"
                }
            ]
        },
        "14": {
            "company_name": "OMAN, AB M F",
            "activity": "Textilvaror o mattor i parti o minut",
            "establishment_year": 1937,
            "employees": 30,
            "capital": 300000,
            "key_personnel": [
                {
                    "name": "Erik öman",
                    "position": "Verkst dir"
                }
            ]
        }
    }
}