{
    "original": "WINTHRÖP AB\n\nPnr 127 21\n\nSkärholmen 1. Box 31. Bredholmsg\n16. Tel 08-710 09 20. Bankgiro\n722-4348. Postgiro 609006-2. Tga\nWinthlon. Stockholm.\nTelex 10373 WIN AB S\nVerksamhet: Import o försäljning av\nkemiska, kosmetiska o\nfarmaceu-tiska preparat\n\nVarunamn: Fortalgesic, Lobac,\nNegram, Neosynephrine, pHiseHex,\nStromba, Trancopal, Trancoprin mtl\nAntal anställda: 30\nÅrsomsättning: 9 000 000\nAktiekapital: 450 000\nStyrelse: Adv Magnus Koskull\n(ordf), dir Bengt Ahlenius, adv\nSven Harald Bauer, dr Robert\nS Inch\n\nVeikst dir: Bengt Ahlenius\nEkonomichef: Henry Larsson\nMarknadschef: Karl-Egon Eng\nChef för medicinska avdelningen o\ninformationsavdelningen: Dr Anton\nDöberl\n\nEtableringsår: 1959\nDotterbolag till Winthrop Products\nCompany, England.\n\nVINTROSA GUMMI FABRI K AB\n\nPnr 710 15\n\nVintrosa. Nybble. Tel 019-22 4 0 07.\n22 14 16. Bankgiro 358-7516.\nPost-giro 445695-0\nVarunamn: Vigum\nAntal anställda: 40\nÅrsomsättning: 3 000 000\nAktiekapital: 10 000\nStyrelse: Dir Harry Skeppner (ordf),\nfru Ingrid Johansson, Sixten\nJohansson, fru Karin Skeppner\nVerkst dir: Harry Skeppner\nEtableringsår: 1954.\n\nWERCO, AB\n\nPnr 199 00\n\nEnköping, Lillängsg 34. Tel\n0171-315 66. Bankgiro 230-8088.\nPostgiro 320395-7\n\nVerksamhet: Tillverkar\nstapelstolar av trä. Även Karmstolar\nAktiekapital: 50 000\nVerkst dir: C Wallander\nEtableringsår 1945\nf d Erco Industri.\n\nVERDA TRÄINDUSTRIER, AB\n\nPnr 360 60\n\nVissefjärda. Tel 0471-200 00,\n200 39. Tga Verda\nVerksamhet: Sågverk, hyvleri,\nsnickerifabrik, trävaruexport o\nspecialinredningar\nAntal anställda: 40\nÅrsomsättning: 3000 000\nAktiekapital: 300 000\nVerkst dir: Disp Erie Klippvik\nEtableringsår: 1945.\n\nWERDER,\nINGENIÖRSFIRMAN BÖRJE\n\nPnr 211 22\n\nMalmö, Stortorget 17. Tel\n040-10 12 25. Postgiro 148529-1. Tga\nMachinewerder\n\nVerksamhet: Pannor för varmvatten,\nhetvatten o ånga. Hetoljepannor\n300\". Transportabla\nvärmecentraler, stålskorstenar, helautomatiska\noljeeldningsanläggningar o\nträflis-stokeranläggningar med stålsilos.\nRökgasrening o fläktar. Elpumpar\nför varmvatten o olja,\nVVS-materi-al m m\n\nChef: Disp Börje Werder\nEtableringsår 1942.\n\nANDERS MÖBEL AB, HILDING\n\nPnr 280 23\n\nHästveda, Box 61. Tel 0451-304 05.\nBankgiro 282-2088. Postgiro\n164337-8\n\nVerksamhet: Tillverkar\nsovrumsmöbler\n\nAntal anställda: 50\nÅrsomsättning: 8 000 000\nAktiekapital: 60 000\nVerkst dir: Olle Andersson\nEtableringsår: 1939.\n\nADAMSSON AB, H E\n\nPnr 401 24\n\nGöteborg 1. Ringög 36. Box 277.\nTel 031-51 55 55, 51 55 25.\nPost&gt;-giro 48020. Tga Gummicentrum\nVerksamhet Säljer sjukvårds-,\nrehabiliterings- o hälsokostartiklar\nÄgare o chefer: Dir Hjalmar E\nAdamsson, dir Herman Jannerberg\nEtableringsår: 1930.\n\nADAMSON ÅKERI &amp;\nGODS-TRAFIK, AB OSVALD\n\nPnr 56100\n\nHuskvarna, Jönköpingsv 55. Tel\n036-13 25 80. Bankgiro 544-5382.\nPostgiro 280481-3\nVerksamhet: Bilspedition o\nreguljär fjärrtrafik, hus o\nvägbyggnadstransporter\nAktiekapital: 500 000\nVerkst dir: Osvald Adamson\nEtableringsår: 1924.\n\nESCO, AB\n\nPnr 21122\n\nMalmö, Stortorget 17. Tel\n040-712 50. Bankgiro 26-3459. Postgiro\n38334. Tga Esco\nVerksamhet: Engrosrörelse med\ntextilier\n\nAktiekapital: 100 000\nVeikst dir. Gunnar Wingren\nEtableringsår: 1952.\n\nSANNES AB\n\nPnr 45101\n\nUddevalla 1, Strömstads v 19 A.\nBox 102. Tel 0522-141 60.\nBankgiro 428-0335. Postgiro 131933-4.\nTga Sannes. Telex 42048\nVerksamhet: Säljer eldningsolja.\nOljeskadesanering, cisternvård\nAktiekapital: 600 000\nVerkst din P O Berned\nEtableringsår: 1937.\n\nSANTESSONS TENNGJUTERI,\nBO\n\nPnr 18132\n\nLidingö, Lejonv 11. Tel\n08-765 06 35\n\nVerksamhet: Tillverkar o säljer\npiydnadsartiklar i gjutet tenn,\ntenn-o blyknappar, tenn- o blysläggor,\nblytyngder, blyplomber, leksaker.\nReparationer\nChef: B G Santesson\nEtableringsår: 1843.\n\nHEDQVIST AB, IVAN\n\nPnr 124 04\n\nBandhagen 4, Hagsätra torg 7. Box\n435. Tel 08-86 04 90. Bankgiro\n57-8423.Postgiro 607370. Tga Ivanhoe,\nStockholm\n\nVerksamhet: Generalagent för\nNational torrbatterier\nAntal anställda: 17\nÅrsomsättning: 4 200 000\nAktiekapital: 50 000\nVerkst dir: Ivan Hedqvist\nEtableringsår: 1960.\n\nHEDKÄRRA CEMENTVARU.\nFABRIK, AB\n\nPnr 773 00\n\nFagersta, HedkärTa. Tel\n0223-540 17, 530 68. Bankgiro 81-2406.\nPostgiro 86060\n\nVerksamhet: Tillverkar betongvaror.\nSäljer grus, sand, makadam mm\nAntal anställda: 28\nÅrsomsättning: 1700 000\nAktiekapital: 60 000\nVeikst dir Per Smidström\nEtableringsår: 1923 .\n\nNYVALLS VERKSTADS AB\n\nPnr 382 00\n\nNybro. Tel 0481-11400, 10073.\nBankgiro 856-1938. Postgiro\n649626-9\n\nVeiksamhet: Tillverkar\nspecialmaskiner o formverktyg\nAktiekapital: 50000\nVerkst dir: Hans Nyvall\nEtableringsår: 1913.\n\nKUN\n\nKamrer: S Larsson\nTransportledare: B Ivarsson\nEtableringsår: 1940.\n\nVARGARDA KROMVERK, AB\n\nPnr 440 20\n\nVårgårda. Tel 0322-200 92.\nBankgiro 8&amp;-4928. Postgiro 80020\nVerksamhet: Galvanisk\nytbehandling av alla slag\nAktiekapital: 60 000\nVerkst din Gustav Mattsson\nEtableringsår: 1932.",
    "structured": {
        "1": {
            "company_name": "WINTHRÖP AB",
            "pnr": "127 21",
            "address": "Skärholmen 1. Box 31. Bredholmsg 16. Stockholm.",
            "phone_number": "08-710 09 20",
            "bank_details": {
                "bankgiro": "722-4348",
                "postgiro": "609006-2"
            },
            "activity": "Import o försäljning av kemiska, kosmetiska o farmaceutiska preparat. Varunamn: Fortalgesic, Lobac, Negram, Neosynephrine, pHiseHex, Stromba, Trancopal, Trancoprin mtl",
            "employees": 30,
            "annual_turnover": 9000000,
            "capital": 450000,
            "key_personnel": [
                {
                    "name": "Adv Magnus Koskull",
                    "position": "ordf"
                },
                {
                    "name": "dir Bengt Ahlenius",
                    "position": ""
                },
                {
                    "name": "adv Sven Harald Bauer",
                    "position": ""
                },
                {
                    "name": "dr Robert S Inch",
                    "position": ""
                }
            ],
            "establishment_year": 1959
        },
        "2": {
            "company_name": "VINTROSA GUMMI FABRI K AB",
            "pnr": "710 15",
            "address": "Vintrosa. Nybble",
            "phone_number": "019-22 4 0 07, 22 14 16",
            "bank_details": {
                "bankgiro": "358-7516",
                "postgiro": "445695-0"
            },
            "activity": "Varunamn: Vigum",
            "employees": 40,
            "annual_turnover": 3000000,
            "capital": 10000,
            "key_personnel": [
                {
                    "name": "Dir Harry Skeppner",
                    "position": "ordf"
                },
                {
                    "name": "fru Ingrid Johansson",
                    "position": ""
                },
                {
                    "name": "Sixten Johansson",
                    "position": ""
                },
                {
                    "name": "fru Karin Skeppner",
                    "position": ""
                }
            ],
            "establishment_year": 1954
        },
        "3": {
            "company_name": "WERCO, AB",
            "pnr": "199 00",
            "address": "Enköping, Lillängsg 34",
            "phone_number": "0171-315 66",
            "bank_details": {
                "bankgiro": "230-8088",
                "postgiro": "320395-7"
            },
            "activity": "Tillverkar stapelstolar av trä. Även Karmstolar",
            "capital": 50000,
            "key_personnel": [
                {
                    "name": "C Wallander",
                    "position": "Verkst dir"
                }
            ],
            "establishment_year": 1945
        },
        "4": {
            "company_name": "VERDA TRÄINDUSTRIER, AB",
            "pnr": "360 60",
            "address": "Vissefjärda",
            "phone_number": "0471-200 00, 200 39",
            "activity": "Sågverk, hyvleri, snickerifabrik, trävaruexport o specialinredningar",
            "employees": 40,
            "annual_turnover": 3000000,
            "capital": 300000,
            "key_personnel": [
                {
                    "name": "Disp Erie Klippvik",
                    "position": "Verkst dir"
                }
            ],
            "establishment_year": 1945
        },
        "5": {
            "company_name": "WERDER, INGENIÖRSFIRMAN BÖRJE",
            "pnr": "211 22",
            "address": "Malmö, Stortorget 17",
            "phone_number": "040-10 12 25",
            "bank_details": {
                "postgiro": "148529-1"
            },
            "activity": "Pannor för varmvatten, hetvatten o ånga. Hetoljepannor 300\", Transportabla värmecentraler, stålskorstenar, helautomatiska oljeeldningsanläggningar o träflis-stokeranläggningar med stålsilos. Rökgasrening o fläktar. Elpumpar för varmvatten o olja, VVS-material m m",
            "key_personnel": [
                {
                    "name": "Disp Börje Werder",
                    "position": "Chef"
                }
            ],
            "establishment_year": 1942
        },
        "6": {
            "company_name": "ANDERS MÖBEL AB, HILDING",
            "pnr": "280 23",
            "address": "Hästveda, Box 61",
            "phone_number": "0451-304 05",
            "bank_details": {
                "bankgiro": "282-2088",
                "postgiro": "164337-8"
            },
            "activity": "Tillverkar sovrumsmöbler",
            "employees": 50,
            "annual_turnover": 8000000,
            "capital": 60000,
            "key_personnel": [
                {
                    "name": "Olle Andersson",
                    "position": "Verkst dir"
                }
            ],
            "establishment_year": 1939
        },
        "7": {
            "company_name": "ADAMSSON AB, H E",
            "pnr": "401 24",
            "address": "Göteborg 1, Ringög 36. Box 277",
            "phone_number": "031-51 55 55, 51 55 25",
            "bank_details": {
                "postgiro": "48020"
            },
            "activity": "Säljer sjukvårds-, rehabiliterings- o hälsokostartiklar",
            "key_personnel": [
                {
                    "name": "Dir Hjalmar E Adamsson",
                    "position": "Ägare o chefer"
                },
                {
                    "name": "dir Herman Jannerberg",
                    "position": ""
                }
            ],
            "establishment_year": 1930
        },
        "8": {
            "company_name": "ADAMSON ÅKERI & GODS-TRAFIK, AB OSVALD",
            "pnr": "56100",
            "address": "Huskvarna, Jönköpingsv 55",
            "phone_number": "036-13 25 80",
            "bank_details": {
                "bankgiro": "544-5382",
                "postgiro": "280481-3"
            },
            "activity": "Bilspedition o reguljär fjärrtrafik, hus o vägbyggnadstransporter",
            "capital": 500000,
            "key_personnel": [
                {
                    "name": "Osvald Adamson",
                    "position": "Verkst dir"
                }
            ],
            "establishment_year": 1924
        },
        "9": {
            "company_name": "ESCO, AB",
            "pnr": "21122",
            "address": "Malmö, Stortorget 17",
            "phone_number": "040-712 50",
            "bank_details": {
                "bankgiro": "26-3459",
                "postgiro": "38334"
            },
            "activity": "Engrosrörelse med textilier",
            "capital": 100000,
            "key_personnel": [
                {
                    "name": "Gunnar Wingren",
                    "position": "Veikst dir"
                }
            ],
            "establishment_year": 1952
        },
        "10": {
            "company_name": "SANNES AB",
            "pnr": "45101",
            "address": "Uddevalla 1, Strömstads v 19 A. Box 102",
            "phone_number": "0522-141 60",
            "bank_details": {
                "bankgiro": "428-0335",
                "postgiro": "131933-4"
            },
            "activity": "Säljer eldningsolja. Oljeskadesanering, cisternvård",
            "capital": 600000,
            "key_personnel": [
                {
                    "name": "P O Berned",
                    "position": "Verkst din"
                }
            ],
            "establishment_year": 1937
        },
        "11": {
            "company_name": "SANTESSONS TENNGJUTERI, BO",
            "pnr": "18132",
            "address": "Lidingö, Lejonv 11",
            "phone_number": "08-765 06 35",
            "activity": "Tillverkar o säljer prydnadsartiklar i gjutet tenn, tenn-o blyknappar, tenn- o blysläggor, blytyngder, blyplomber, leksaker. Reparationer",
            "key_personnel": [
                {
                    "name": "B G Santesson",
                    "position": "Chef"
                }
            ],
            "establishment_year": 1843
        },
        "12": {
            "company_name": "HEDQVIST AB, IVAN",
            "pnr": "124 04",
            "address": "Bandhagen 4, Hagsätra torg 7. Box 435, Stockholm",
            "phone_number": "08-86 04 90",
            "bank_details": {
                "bankgiro": "57-8423",
                "postgiro": "607370"
            },
            "activity": "Generalagent för National torrbatterier",
            "employees": 17,
            "annual_turnover": 4200000,
            "capital": 50000,
            "key_personnel": [
                {
                    "name": "Ivan Hedqvist",
                    "position": "Verkst dir"
                }
            ],
            "establishment_year": 1960
        },
        "13": {
            "company_name": "HEDKÄRRA CEMENTVARU. FABRIK, AB",
            "pnr": "773 00",
            "address": "Fagersta, HedkärTa",
            "phone_number": "0223-540 17, 530 68",
            "bank_details": {
                "bankgiro": "81-2406",
                "postgiro": "86060"
            },
            "activity": "Tillverkar betongvaror. Säljer grus, sand, makadam mm",
            "employees": 28,
            "annual_turnover": 1700000,
            "capital": 60000,
            "key_personnel": [
                {
                    "name": "Per Smidström",
                    "position": "Veikst dir"
                }
            ],
            "establishment_year": 1923
        },
        "14": {
            "company_name": "NYVALLS VERKSTADS AB",
            "pnr": "382 00",
            "address": "Nybro",
            "phone_number": "0481-11400, 10073",
            "bank_details": {
                "bankgiro": "856-1938",
                "postgiro": "649626-9"
            },
            "activity": "Tillverkar specialmaskiner o formverktyg",
            "capital": 50000,
            "key_personnel": [
                {
                    "name": "Hans Nyvall",
                    "position": "Verkst dir"
                }
            ],
            "establishment_year": 1913
        },
        "15": {
            "company_name": "KUN",
            "key_personnel": [
                {
                    "name": "S Larsson",
                    "position": "Kamrer"
                },
                {
                    "name": "B Ivarsson",
                    "position": "Transportledare"
                },
                {
                    "name": "",
                    "position": ""
                }
            ],
            "establishment_year": 1940
        },
        "16": {
            "company_name": "VARGARDA KROMVERK, AB",
            "pnr": "440 20",
            "address": "Vårgårda",
            "phone_number": "0322-200 92",
            "bank_details": {
                "bankgiro": "8-4928",
                "postgiro": "80020"
            },
            "activity": "Galvanisk ytbehandling av alla slag",
            "capital": 60000,
            "key_personnel": [
                {
                    "name": "Gustav Mattsson",
                    "position": "Verkst dir"
                }
            ],
            "establishment_year": 1932
        }
    }
}