{
    "original": "EN G EJ BILNYTT, AB\n\nPnr 432 00\n\nVarberg, Danska v 16. Box 202.\nTel 0340-180 45. Bankgiro 60-7102.\nPostgiro 593919\n\nVerksamhet: Tillverkning o\nengros-försäljning av bildelar\nAntal anställda: 6\nAktiekapital: 21000\nVerkst dir K I Gunnarsson\nEtableringsår: 1967.\n\nENGELBERG,\nKONSULTERANDE INGENIURSBYRÅ,\nAB HANS\n\nPnr 100 31\n\nStockholm 21, Karlbergsv 56. Box\n21011. Tel 08-34 45 55, 35 52 53.\nBankgiro 566-0675. Postgiro\n383171-6\n\nVerksamhet: Allmän\nrationalisering, teknisk o administrativ\nÄgare o chef: Disp Hans\nEngel-berg\n\nEtableringsår: 1958.\n\nTRIATOR, AB\n\nPnr 55006\n\nJönköping 6, Box 6052. österängsv\n2. Tel 036-118120. Bankgiro\n545-4913. Postgiro 27132-0\nVerksamhet: Kylkompressorer,\nluftkonditioneringskomponenter\nAntal anställda: 20\nAktiekapital: 400 000\nVerkst din Ing Göran Sendel\nEtableringsår: 1951.\n\nWALDENSTRÖM AB, ÅKE\n\nPnr 413 14\n\nGöteborg, Sveag 21. Tel\n031-24 85 02, 24 85 18. Bankgiro\n508-7960. Postgiro 43359-9\nVerksamhet: Säljer konfektyrer i\nparti\n\nAntal anstäUda: 7\nÅrsomsättning: 3 000 000\nAktiekapital: 50 000\nVerkst dir: Bengt Zetterberg\nEtableringsår. 1928.\n\nWALE INGENIORSBYRÅ AB,\nHARALD\n\nPnr 11160\n\nStockholm. Drottningg 102. Tel\n08-23 16 35. Bankgiro 73-0443.\nPostgiro 191543-8\nVerksamhet: Konsulterande\nbyggnadskonstruktioner\nAktiekapital: 10 000\nVerkst din Sven Tyrèn\nEtableringsår: 1954.\n\nASPLUNDS BYGG AB\n\nPnr 702 11\n\nÖrebro, Stortorget 4. Tel\n019-124310. Bankgiro 815-9519.\nPostgiro 24288-3\n\nVerksamhet: Konsult- o\nentreprenadverksamhet\n\nAvdelningskontor: Krylbo, Mejerig 4.\nTel 0226-104 1 6\n\nAvdelningskontor o Betongstation:\n\nHällefors, Köpmanv. Tel 0591-111 15\nAntal anställda: 206\nÅrsomsättning: 22 000 000\nAktiekapital: 150 000\nVerkst dir: Ing Stig Abramsson\nEtableringsår: 1931.\n\nFARDBY IMPORT-EXPORT, I\n\nPnr 415 11\n\nGöteborg, Kalenderv 1 D. Tel\n031-48 9 1 20. Tga Ifard\nVerksamhet: Konstruktion av\nmaskiner för vacuumförpackning\nÄgare o chef: I Fardby\nEtableringsår: 1949.\n\nFER\n\n17 1050. Bankgiro 42-0285.\nPostgiro 45430. Tga Penom. Telex 20888\nVerksamhet: Tillverkar o säljer\ntvätt-, disk- o rengöringsmedel\nVarunamn: Penom, Fen-O-Matic,\nTusen-Ett, Opus\nAntal anställda: 90\nÅrsomsättning: 20 000 000\nAktiekapital: 500 000\nVerkst dir: Walter Hentschel\nEtableringsår: 1929.\n\nFERATOR,\nINGENJÖRSFIRMAN\n\nPnr 12173\n\nJohanneshov, Importörv 5-21. Tel\n08-810120. Bankgiro 16-7112.\nPostgiro 194029. Tga Gnistmagnet,\nStockholm\n\nVerksamhet: Utför maskin- o\nverktygskonstruktioner\nAntal anställda: 52\nChef: Overing Allan Holmqvist\nEtableringsår: 1942\n\nAUTOLIV AB\n\nPnr 440 20\n\nVårgårda, Parkg. Box 11. Tel\n0322-212 00. Bankgiro 894-9497.\nPostgiro 449038-9. Tga Autoliv.\nTelex 2430\n\nVerksamhet: Tillverkar\nbilsäkerhetsbälten m m\nAntal anställda: 40\nAktiekapital: 45 000\nVeikst dir: Lennart Lindblad\nEtableringsår: 1953.\n\nwagner &amp; co, ab g\n\nPnr 560 23\n\nBankeryd, Juneg 4. Box 16. Tel\n036-720 96, 720 94. Bankgiro\n83-6934. Postgiro 162440. Tga Wagner\nVerksamhet: Tillverkar penslar\no bereder tagel\nAntal anställda: 12\nÅrsomsättning: 1000 000\nAktiekapital: 60 000\nVerkst din Erik Wagner\nEtableringsån 1940.\n\nBER\n\nÄgare: Sten Bergh, Gunnar\nLöns-gård\n\nEtableringsår: 1944.\n\nFIXON AB\n\nPnr 434 00\n\nKungsbacka, Verkstadsg 12. Tel\n0300-14150. Bankgiro 26-8144.\nPostgiro 242074\n\nVerksamhet: Tillverkar damkjolar\ntunikor o dambyxor\nVarunamn: Fixon\n.Antal anställda: 40\nÅrsomsättning: 1 400 000\nAktiekapital: 50 000\nVerkst dir: Håkan Bjarne\nEtableringsår: 1963.",
    "structured": {
        "1": {
            "company_name": "EN G EJ BILNYTT, AB",
            "pnr": "432 00",
            "address": "Varberg, Danska v 16. Box 202.",
            "phone_number": "0340-180 45",
            "bank_details": {
                "bankgiro": "60-7102",
                "postgiro": "593919"
            },
            "activity": "Tillverkning o engros-försäljning av bildelar",
            "employees": 6,
            "capital": 21000,
            "key_personnel": [
                {
                    "name": "K I Gunnarsson",
                    "position": "Verkst dir"
                }
            ],
            "establishment_year": 1967
        },
        "2": {
            "company_name": "ENGELBERG, KONSULTERANDE INGENIURSBYRÅ, AB HANS",
            "pnr": "100 31",
            "address": "Stockholm 21, Karlbergsv 56. Box 21011.",
            "phone_number": "08-34 45 55, 35 52 53",
            "bank_details": {
                "bankgiro": "566-0675",
                "postgiro": "383171-6"
            },
            "activity": "Allmän rationalisering, teknisk o administrativ",
            "owner_and_manager": "Disp Hans Engel-berg",
            "establishment_year": 1958
        },
        "3": {
            "company_name": "TRIATOR, AB",
            "pnr": "55006",
            "address": "Jönköping 6, Box 6052. österängsv 2.",
            "phone_number": "036-118120",
            "bank_details": {
                "bankgiro": "545-4913",
                "postgiro": "27132-0"
            },
            "activity": "Kylkompressorer, luftkonditioneringskomponenter",
            "employees": 20,
            "capital": 400000,
            "key_personnel": [
                {
                    "name": "Ing Göran Sendel",
                    "position": "Verkst dir"
                }
            ],
            "establishment_year": 1951
        },
        "4": {
            "company_name": "WALDENSTRÖM AB, ÅKE",
            "pnr": "413 14",
            "address": "Göteborg, Sveag 21",
            "phone_number": "031-24 85 02, 24 85 18",
            "bank_details": {
                "bankgiro": "508-7960",
                "postgiro": "43359-9"
            },
            "activity": "Säljer konfektyrer i parti",
            "employees": 7,
            "annual_turnover": "3 000 000",
            "key_personnel": [
                {
                    "name": "Bengt Zetterberg",
                    "position": "Verkst dir"
                }
            ],
            "establishment_year": 1928
        },
        "5": {
            "company_name": "WALE INGENIORSBYRÅ AB, HARALD",
            "pnr": "11160",
            "address": "Stockholm, Drottningg 102",
            "phone_number": "08-23 16 35",
            "bank_details": {
                "bankgiro": "73-0443",
                "postgiro": "191543-8"
            },
            "activity": "Konsulterande byggnadskonstruktioner",
            "capital": 10000,
            "key_personnel": [
                {
                    "name": "Sven Tyrèn",
                    "position": "Verkst din"
                }
            ],
            "establishment_year": 1954
        },
        "6": {
            "company_name": "ASPLUNDS BYGG AB",
            "pnr": "702 11",
            "address": "Örebro, Stortorget 4",
            "phone_number": "019-124310",
            "bank_details": {
                "bankgiro": "815-9519",
                "postgiro": "24288-3"
            },
            "activity": "Konsult- o entreprenadverksamhet",
            "branch_office_1": "Krylbo, Mejerig 4",
            "phone_number_branch_1": "0226-104 1 6",
            "branch_office_2": "Hällefors, Köpmanv",
            "phone_number_branch_2": "0591-111 15",
            "employees": 206,
            "annual_turnover": "22 000 000",
            "capital": 150000,
            "key_personnel": [
                {
                    "name": "Ing Stig Abramsson",
                    "position": "Verkst dir"
                }
            ],
            "establishment_year": 1931
        },
        "7": {
            "company_name": "FARDBY IMPORT-EXPORT, I",
            "pnr": "415 11",
            "address": "Göteborg, Kalenderv 1 D",
            "phone_number": "031-48 9 1 20",
            "activity": "Konstruktion av maskiner för vacuumförpackning",
            "owner_and_manager": "I Fardby",
            "establishment_year": 1949
        },
        "8": {
            "company_name": "FER",
            "pnr": "171050",
            "bank_details": {
                "bankgiro": "42-0285",
                "postgiro": "45430"
            },
            "activity": "Tillverkar o säljer tvätt-, disk- o rengöringsmedel",
            "product_brands": "Penom, Fen-O-Matic, Tusen-Ett, Opus",
            "employees": 90,
            "annual_turnover": "20 000 000",
            "capital": 500000,
            "key_personnel": [
                {
                    "name": "Walter Hentschel",
                    "position": "Verkst dir"
                }
            ],
            "establishment_year": 1929
        },
        "9": {
            "company_name": "FERATOR, INGENJÖRSFIRMAN",
            "pnr": "12173",
            "address": "Johanneshov, Importörv 5-21",
            "phone_number": "08-810120",
            "bank_details": {
                "bankgiro": "16-7112",
                "postgiro": "194029"
            },
            "activity": "Utför maskin- o verktygskonstruktioner",
            "employees": 52,
            "owner_and_manager": "Overing Allan Holmqvist",
            "establishment_year": 1942
        },
        "10": {
            "company_name": "AUTOLIV AB",
            "pnr": "440 20",
            "address": "Vårgårda, Parkg. Box 11",
            "phone_number": "0322-212 00",
            "bank_details": {
                "bankgiro": "894-9497",
                "postgiro": "449038-9"
            },
            "activity": "Tillverkar bilsäkerhetsbälten m m",
            "employees": 40,
            "capital": 45000,
            "key_personnel": [
                {
                    "name": "Lennart Lindblad",
                    "position": "Veikst dir"
                }
            ],
            "establishment_year": 1953
        },
        "11": {
            "company_name": "wagner & co, ab g",
            "pnr": "560 23",
            "address": "Bankeryd, Juneg 4. Box 16",
            "phone_number": "036-720 96, 720 94",
            "bank_details": {
                "bankgiro": "83-6934",
                "postgiro": "162440"
            },
            "activity": "Tillverkar penslar o bereder tagel",
            "employees": 12,
            "annual_turnover": "1000 000",
            "capital": 60000,
            "key_personnel": [
                {
                    "name": "Erik Wagner",
                    "position": "Verkst din"
                }
            ],
            "establishment_year": 1940
        },
        "12": {
            "company_name": "BER",
            "owners": [
                "Sten Bergh",
                "Gunnar Lönsgård"
            ],
            "establishment_year": 1944
        },
        "13": {
            "company_name": "FIXON AB",
            "pnr": "434 00",
            "address": "Kungsbacka, Verkstadsg 12",
            "phone_number": "0300-14150",
            "bank_details": {
                "bankgiro": "26-8144",
                "postgiro": "242074"
            },
            "activity": "Tillverkar damkjolar tunikor o dambyxor",
            "product_brand": "Fixon",
            "employees": 40,
            "annual_turnover": "1 400 000",
            "capital": 50000,
            "key_personnel": [
                {
                    "name": "Håkan Bjarne",
                    "position": "Verkst dir"
                }
            ],
            "establishment_year": 1963
        }
    }
}