{
    "original": "TRANSOCEAN, REDERUAB\n\nPnr 403 10\n\nGöteborg 2, Packhusplatsen 3.\nFack. Tel 031-17 67 00. Bankgiro\n500-5715. Postgiro 12107. Tga\nNike. Telex 2300\nAktiekapital: 2 700 000\nVerkst dir: Rolf Carlsson\nEtableringsår 1933.\n\nTRANSOHMA FÖRSÄLJNINGS\nAB\n\nPnr 186 00\n\nVallentuna, Fabriksv. Box 54. Tel\n0762-24145. Bankgiro 122-0896.\nPostgiro 231040-7\nVeiksamhet: Tillverkar\ntransformatorer 10 VA-50 KVA\nAntal anställda: 10\nÅrsomsättning: 500 000\nAktiekapital: 25000\nStyrelse: Ing Lars Ekvall (ordf),\nfrk AnnCatrin Erixon\nEtableringsår: 1954.\n\nINT\n\n3151. Postgiro 40585-2. Tga\nInternational. Telex 2256 FABI S\nVerksamhet: Tillverkar färger o\nfernissor, specialitet: fartygsfärger,\nrostskydds- o industrifärger\nAvdelningskontor: 201 20 Malmö 1,\nNordenskiöldsg 1. Box 63. Tel\n040-735 80\n\n100 63 Stockholm 35, Henriksdal.\nFack. Tel 08-44 00 45\n85106 Sundsvall 1, Ostermov 35.\nBox 462. Tel 060-12 34 20\nAntal anställda: 320\nÅrsomsättning: 45 000000\nAktiekapital: 4 300 000\nStyrelse: Dir Karl Rudolf Bökman\n(ordf), dir Eman Högberg, dir Leif\nJanson, dir Cyril Preston,\nbruks-disp Carl Sebardt\nVerkst din Bertil Köhlberg\nEtableringsår: 1913.\n\nINTERNATIONAL GENERAL\nELECTRIC AB\n\nPnr 16125\n\nBromma 1, Fack. Gårdsfogdev 14.\nTel 08-2829 45. Telex 10439\nVerksamhet: Säljer elektronisk o\nelektrisk materiel\nAntal anställda: 20\nAktiekapital: 400 000\nStyrelse: Adv Gotthard\nCalissen-dorff (ordf), bergsing Jan\nBorgen-hard, ing Bertil Johnson, mr E W\nFox\n\nVerkst dir: Ing Bertil Johnsson\nEtableringsån 1963.\n\nINTERNATIONAL HARVES.\nTER COMPANY, AB\n\nPnr 20121\n\nMalmö 1, Box 174. Västkustv. Tel\n040-93 46 20. Bankgiro 609-8024,\n160-1210. Postgiro 15000-3. Tga\nHarvester. Telex 32639\nVerksamhet: Säljer\nlantbruksmaskiner, traktorer o lastbilar\nAntal anställda: 225\nÅrsomsättning: 50 000 000\nAktiekapital: 10 000 000\nVerkst dir. E H Kristiansen\nEtableringsår. 1904.\n\nINTERNATIONAL MAGAZINE\nSERVICE AB\n\nPnr 105 44\n\nStockholm, Tors g 21. Tel\n08-34 90 00. Bankgiro 16-8790.\nPostgiro 1111. Tga Imagserv.\nTelex 10027\n\nVerksamhet: Bildbyrå. Säljer\nutländska bilder o artiklar\nAntal anstäUda: 19\nÅrsomsättning: 3 000 000\nAktiekapital: 5 000\nVeikst dir: Töre Nilsson\nEtableringsår: 1946.\n\nINTERNATIONAL PAPER &amp;\nPULP AB\n\nPnr 411 15\n\nGöteborg C, Kyrkog 4. Tel\n031-13 2106. Postgiro 43246-8. Tga\nProducts. Telex 20680\nVerksamhet: Export av massa,\npapper o träprodukter\nAktiekapital: 300 000\nVerkst din R Karlsen\nEtableringsår: 1957.\n\nINTERNATIONAL TECHNICAL\nCONSULTING BUREAU AB\nSTOCKHOLM\n\nPnr 262 00\n\nÄngelholm, Kullav 16. Tel\n0431-135 25. Postgiro467720. Tga\nA-koncern\n\nVerksamhet: Konsulterande\nverksamhet såsom rationalisering,\nindustri- o maskinvärdering,\nverktygs-o industrimaskiner. Säljer\nträningsapparaten Salud samt avgasreaktor\nNoco för bl a sopförbränning o\noljedestruktion\nVarunamn: Noco, Salud\nAvdelningskontor. 600 03\nNorrköpings, Box 3067. Tel 011-10 51 21\nLinköping. Tel 013-13 00 95\nÅrsomsättning: 5 000 000\nAktiekapital: 50 000\nVerkst dir: Allan Inovius\nEtableringsår: 1959\nOmbUdat till aktiebolag 1962.\n\nINTERNATIONAL TEXTIL AB\n\nPnr 40015\n\nGöteborg 53, Box 53 1 29.\nKungs-portsavenyn 1. Tel 031-17 2650.\nBankgiro 420-0937. Postgiro\n48708-2. Tga Intertex. Telex 2220\nVerksamhet: Agentur för textilvaror\n(bomull, siden, rayon, ull)\nAktiekapital: 125 000\nChef: Disp Werner Hanisch\nEtableringsår: 1943.\n\nsäffle tegelbruk, ab\n\nPnr 661 00\n\nSäffle. Tel 0533-10191, 114 91.\nBankgiro 883-0366. Postgiro\n172454-1\n\nVerksamhet: Tillverkar o säljer\nrött o brun-svart fasadtegel\nAntal anställda: 27\nÅrsomsättning: 2 700 000\nAktiekapital: 150 000\nVerkst dir: Byggmäst Erie Carlsson\nEtableringsår: 1905\nOmbildat till aktiebolag 1952.\n\nsäffle.tidningen, ab\n\nPnr 66100\n\nSäffle, Kaptensg 2. Box 33. Tel\n0533-126 80. Bankgiro 11-4946.\nPostgiro 28482\n\nVerksamhet: Tidnings- o\nciviltryckeri\n\nAntal anställda: 54\nÅrsomsättning: 2 448 000\nAktiekapital: 37 500\nStyrelse: Dir Carl G Andersson\n(ordf), dir Gustav Ander, civiling\nGeorg Bruce, bankdir Tage\nCarlsson, red C Henning Tollesby\nVerkst dir: Red C Henning Tollesby\nPlatschef: Kamrer Sven Ericson\nFaktor: Robert Blomqvist\nEtableringsån 1894.\n\nMIKRON AB\n\nPnr 163 62\n\nSpånga, Glömmingegränd 9. Tel\n08-760 03 35. Bankgiro 560-3196.\nPostgiro 197271-0. Tga Mikronab\nVerksamhet: Import av slipmaterial,\nmaskiner o industrikeramik\nAntal anställda: 3\nAktiekapital: 10000\nVerkst dir: Karl Svensson\nEtableringsår 1944.\n\nCOLDATOR, AB\n\nPnr 17166\n\nSolna, Galoppv 5. Tel 08-85 04 10.\nBankgiro 616-9031/ Postgiro\n112688-7\n\nVerksamhet: Tillverkning av\nkyl-frysenheter för restauranger\nAntal anställda: 25\n\nÅrsomsättning: 3 000 000\nAktiekapital: 50 000\nVerkst dir: Rune Lysén\nEtableringsår:. 195 9.\n\nCOLGAFABRIKEN AB\n\nPnr 104 60 Sthlm 20\nJohanneshov, Huddingev 109. Box\n20061, Sthlm 20. Tel 08-49 25 55\nVerksamhet: Tillverkar tvål,\nhandrengöringsmedel o kosmetika\nÅrsomsättning: 4 000 000\nVerkst dir: Arne Wober\nEtableringsår: 1926.\n\nhemmets journal ab\n\nPnr 200 22\n\nMalmö 3, Fack. S Bulltoftav 46.\nTel 040-93 45 60. Bankgiro\n264-7444. Postgiro 38159-0, 245047-6.\nTga Hemmet.\nTelex 32449 HEMMET S\nVerksamhet: Veckotidningsförlag\no tryckeri\n\nAnnonskontor 11134 Stockholm,\nSveav 52. Tel 08-14 27 30\nStyrelse: Adv Sten Sandell (ordf),\ndir Arne Byskov,\nlandsretssagfgf-rer Esben Dragsted, dir Thorolf\n\nhennig, ab hugo\n\nPnr 50002\n\nBorås 2, Getängsv 4. Box 22023.\nTel 033-117980. Bankgiro\n531-1972. Postgiro 6777-7. Tga Hennig.\nTelex 36032\n\nVerksamhet: Säljer maskiner o\nförnödenheter för textil-, trikå- o\nkonfektionsindustrin samt radialdäck\nAntal anställda: 16\nÅrsomsättning: 7 000 000\nAktiekapital: 150 000\nStyrelse: Adv Gunnar Lagerberg\n(ordf), disp Christer Hennig, dir\nOlof Hennig\nVerkst dir: Olof Hennig\nEtableringsår: 1905\nOmbildat till aktiebolag 1919.\nModerbolag till Svenska\nStålsolffabri-ken, Borås.\n\nhenning ab, walter\n\nPnr 11148\n\nStockholm, Nybrokajen 15. Tel\n08-10 16 46. Bankgiro 565-5238.\nPostgiro 657340-6\n\nVerksamhet: Säljer Fi-Cord\ndik-teringsmaskiner\n\nVarunamn: Fi-Cord\nAktiekapital: 50 000\nVerkst dir: Walter Henning\nEtableringsår: 1962.\n\nMEKANOTEL, INGENIORS.\nFIRMAN\n\nPnr 16131\n\nBromma, Stångjärnsv 12. Tel 08-\n\n26 36 69, 26 36 10. Bankgiro\n567-0435. Postgiro 328956-8. Tga\nMe-kanotelbromma\n\nVerksamhet: Säljer verktyg o\nmaskiner\n\n.Antal anställda: 4\nÅrsomsättning: 1 250 000\nChef: Ing Joe Johnsson\nEtableringsår: 1948.\n\nHEIMDAL AB, GUSTAF\n\nPnr 104 60\n\nStockholm 20, Hammarbyv 76. Fack.\nTel 08-228060. Postgiro 52061.\nTga Engrosheim\nVerksamhet: Generalagenturer:\nskriv-, kontors- o ritmaterial\nVeikst dir: Gunnar Eriksson\nEtableringsår: 1926.\n\nWALLBERGS FABRIKS AB\n\nPnr 30103\n\nHalmstad 1. Slottsmöllan. Box 128.\nTel 035-1180 50. Bankgiro\n423-6261. Postgiro 14894-0. Tga\nWallbergs. Telex 38019 WAFAB S\nVerksamhet: Tillverkar alla slag\nav maskinfilt speciellt för\npappers-o cellulosaindustrin samt för andra\ntekniska ändamål. Tillverkar grova,\nmjukbehandlade ylleunderkläder\nför herrar. Tillverkar tegel vid\nSlottsmöllans Tegelbruk, Halmstad\nRepresentanter:\n\nFör maskinfiltfabriken: Sundsvall.\nAB Åkesson &amp; Blomquist, Förrådsg\n11, Skönsberg\n\nFör tegelbruket: Göteborg N.\nLarsson &amp; Seaton AB, Marieholmsg 36\nAB Tegelcentralen, Malmö\nAntal anställda: 300\nÅrsomsättning: 19500 000\nAktiekapital: 2136 000\nStyrelse: Bankdir Bengt Widén (ordf),\ndisp Sven Baur, adv Sven Colleen,\ndir Bengt Skånsberg, dir Peter\nRau-tenberg\n\nVerkst dir: Peter Rautenberg\nEtableringsår: 1823\nDotterbolag: Slottsmöllans\nTegelbruk, Halmstad.\n\nWALLBERG, HANDELS AB R\n\nPnr 114 58\n\nStockholm, Skepparg 49 A. Tel\n08-6015 08,6015 09. Bankgiro\n16-5536. Postgiro 158197. Tga Reint\nVerksamhet: Säljer\nindustriförnödenheter\n\nVarunamn: Bindex o Ligarex\nVerkst din Lennart Elingfors\nEtableringsår: 1925.\n\nWALLCO, AB\n\nse Astra-Wallco AB.\n\nWALLCO SPORT, AB\n\nse Astra-Wallco AB.\n\nWALLESMETALLFABRIK AB\n\nPnr 330 30\n\nGnosjö. Tel 0370-912 30. Postgiro\n278063\n\nVerksamhet: Tillverkning samt\npressning o dragning av större\nplåtdetaljer. Vi utställer på\nSwed-Expo i Värnamo\n\nÄgare o chef: Evald Johansson\nEtableringsår: 1944.\n\nKARLHOLMS AB\n\nPnr 810 64\n\nKarlholmsbruk. Tel 0294-406 00.\nTelex 81015. Tga Karlholmsbolag\nVerksamhet: Tillverkar\nträfiberskivor, Karlit (hård o porös),\nKar-lit-Panel samt mineralfiberskivor\nKarlit-MineraL Årskapacitet cirka\n130 000 ton\n\nHuvudkontor o exportförsäljning:\n\nStockholm O, Nybrog 3. Tel\n08-241150. Telex 1619. Tga\nKarlit-fiber\n\nVarunamn: Karlit, Karlit-Panel,\nKarlit-Mineral\nAktiekapital: 1500 000\nVerkst dir: Bengt Mossberg\nEtableringsår: 1937.\n\nKARLQVIST &amp; JOHANSSON\nSVETSNINGSVERKSTAD, AB\n\nPnr 53100\n\nLidköping, Brantabäcksg 6. Tel\n0510-240 81. Bankgiro 212-0160.\nPostgiro 327933-8\nVerksamhet: Tillverkar\noljecisterner, lastskopor samt\njärnkonstruktioner. Service o reparation å\nbyggnadshissar o entreprenadmaskiner.\nFörsäljning av Hanomag o Hymas\nentreprenadmaskiner\nAntal anställda: 28\nÅrsomsättning: 2 500 000\nAktiekapital: 50 000\nÄgare o chefer: Lennart Karlqvist,\nStig Johansson\nEtableringsår: 1957.\n\nKARLSBORN, BYGGNADS AB\nBRUDERNA\n\nPnr 113 27\n\nStockholm. Karlbergsv 20. Tel 08-\n\n30 27 16 , 34 4 4 55. Bankgiro 696-\n\n3565. Postgiro 559245-6\n\nVerksamhet: Utför husbyggnad o\n\nreparationer\n\nAntal anställda: 45\n\nÅrsomsättning: 10 000 000\n\nAktiekapital: 30 000\n\nVerkst dir: Byggmäst Carl Karls-\n\nborn\n\nEtableringsår: 1958.",
    "structured": {
        "1": {
            "company_name": "TRANSOCEAN",
            "establishment_year": 1933
        },
        "2": {
            "company_name": "TRANSOHMA FÖRSÄLJNINGS AB",
            "establishment_year": 1954,
            "activity": "Tillverkar transformatorer 10 VA-50 KVA",
            "employees": 10,
            "annual_turnover": 500000,
            "capital": 25000,
            "key_personnel": [
                {
                    "name": "Ing Lars Ekvall",
                    "position": "ordf"
                },
                {
                    "name": "frk AnnCatrin Erixon"
                }
            ]
        },
        "3": {
            "company_name": "INTernational",
            "employees": 320,
            "annual_turnover": 45000000,
            "capital": 4300000,
            "key_personnel": [
                {
                    "name": "Dir Karl Rudolf Bökman",
                    "position": "ordf"
                },
                {
                    "name": "dir Eman Högberg"
                },
                {
                    "name": "dir Leif Janson"
                },
                {
                    "name": "dir Cyril Preston"
                },
                {
                    "name": "bruks-disp Carl Sebardt"
                },
                {
                    "name": "Verkst din Bertil Köhlberg"
                }
            ],
            "establishment_year": 1913
        },
        "4": {
            "company_name": "INTERNATIONAL GENERAL ELECTRIC AB",
            "establishment_year": 1963,
            "activity": "Säljer elektronisk o elektrisk materiel",
            "employees": 20,
            "capital": 400000,
            "key_personnel": [
                {
                    "name": "Adv Gotthard Calissen-dorff",
                    "position": "ordf"
                },
                {
                    "name": "bergsing Jan Borgen-hard",
                    "position": ""
                },
                {
                    "name": "ing Bertil Johnson",
                    "position": ""
                },
                {
                    "name": "mr E W Fox",
                    "position": ""
                }
            ]
        },
        "5": {
            "company_name": "INTERNATIONAL HARVESTER COMPANY, AB",
            "establishment_year": 1904,
            "activity": "Säljer lantbruksmaskiner, traktorer o lastbilar",
            "employees": 225,
            "annual_turnover": 50000000,
            "capital": 10000000,
            "key_personnel": [
                {
                    "name": "Verkst dir. E H Kristiansen"
                }
            ]
        },
        "6": {
            "company_name": "INTERNATIONAL MAGAZINE SERVICE AB",
            "establishment_year": 1946,
            "activity": "Bildbyrå. Säljer utländska bilder o artiklar",
            "employees": 19,
            "annual_turnover": 3000000,
            "capital": 5000,
            "key_personnel": [
                {
                    "name": "Veikst dir: Töre Nilsson"
                }
            ]
        },
        "7": {
            "company_name": "INTERNATIONAL PAPER & PULP AB",
            "establishment_year": 1957,
            "activity": "Export av massa, papper o träprodukter",
            "capital": 300000,
            "key_personnel": [
                {
                    "name": "Verkst din R Karlsen"
                }
            ]
        },
        "8": {
            "company_name": "INTERNATIONAL TECHNICAL CONSULTING BUREAU AB STOCKHOLM",
            "establishment_year": 1959,
            "activity": "Konsulterande verksamhet såsom rationalisering, industri- o maskinvärdering, verktygs-o industrimaskiner. Säljer träningsapparaten Salud samt avgasreaktor Noco för bl a sopförbränning o oljedestruktion",
            "annual_turnover": 5000000,
            "capital": 50000,
            "key_personnel": [
                {
                    "name": "Verkst dir: Allan Inovius"
                }
            ]
        },
        "9": {
            "company_name": "INTERNATIONAL TEXTIL AB",
            "establishment_year": 1943,
            "activity": "Agentur för textilvaror (bomull, siden, rayon, ull)",
            "capital": 125000,
            "key_personnel": [
                {
                    "name": "Chef: Disp Werner Hanisch"
                }
            ]
        },
        "10": {
            "company_name": "SÄFFLE TEGELBRUK, AB",
            "establishment_year": 1905,
            "activity": "Tillverkar o säljer rött o brun-svart fasadtegel",
            "employees": 27,
            "annual_turnover": 2700000,
            "capital": 150000,
            "key_personnel": [
                {
                    "name": "Verkst dir: Byggmäst Erie Carlsson"
                }
            ]
        },
        "11": {
            "company_name": "SÄFFLE.TIDNINGEN, AB",
            "establishment_year": 1894,
            "activity": "Tidnings- o civiltryckeri",
            "employees": 54,
            "annual_turnover": 2448000,
            "capital": 37500,
            "key_personnel": [
                {
                    "name": "Styrelse: Dir Carl G Andersson",
                    "position": "ordf"
                }
            ],
            "additional_info": "Platschef: Kamrer Sven Ericson, Faktor: Robert Blomqvist"
        },
        "12": {
            "company_name": "MIKRON AB",
            "establishment_year": 1944,
            "activity": "Import av slipmaterial, maskiner o industrikeramik",
            "employees": 3,
            "capital": 10000,
            "key_personnel": [
                {
                    "name": "Verkst dir: Karl Svensson"
                }
            ]
        },
        "13": {
            "company_name": "COLDATOR, AB",
            "establishment_year": 1959,
            "activity": "Tillverkning av kyl-frysenheter för restauranger",
            "employees": 25,
            "annual_turnover": 3000000,
            "capital": 50000,
            "key_personnel": [
                {
                    "name": "Verkst dir: Rune Lysén"
                }
            ]
        }
    }
}