{
    "original": "SKOGSALLIANS, AB\n\nPnr 116 26\n\nStockholm, Björngårdsg 13. Tel\n08-44 55 50 , 44 7 5 24. Bankgiro\n728-7378. Postgiro 653080-2. Tga\nSkogsallians.\n\nTelex 10667 SKOGSALL S\nVerksamhet: Agenturrörelse. Alla\nslag av pappersprodukter o\nbyggnadsmateriel. Exporterar all\nslags ved, rundvirke, pålar mm\nAntal anställda: 4\nAktiekapital: 100 000\nVerkst dir: Jan Sjöberg\nEtableringsår: 1961.\n\nBURSERYDS BRUK AB\n\nPnr 330 26\n\nSmålands Burseryd. Tel 0371-\n\n50300. Bankgiro 550-7348.\nPostgiro 22588-8. Tga Bruket. Telex\n70005\n\nVerksamhet: Tillverkar kallvalsat\nbandstål, galvaniserat bandjärn,\ntrådspik, järntråd o staglinor\nFörsäljningskontor: Göteborg V,\nChapmansg 6. Box 12011, Gbg 12.\nTel 031-14 09 38, 14 1139. Telex\n20636\n\nAntal anställda: 170\nÅrsomsättning: 30 000 000\nAktiekapital: 2 500 000\nVerkst dir: C E Josefsson\nEtableringsår. 1910\nOmbildat till aktiebolag 1943.\n\nBURSERYDS FÄRGFABRIK\n\nPnr 330 26\n\nSmålands Burseryd. Tel\n0371-500 74. Bankgiro 55-0758. Postgiro\n88308\n\nVerksamhet: Tillverkar färdiglagad\nrödfärg, oljefärger m m\nÄgare o chef: Folke Andersson\nEtableringsår: 1941.\n\nLB-FÄRJORNA AB\n\nPnr 25102\n\nHelsingborg 1, Box 16. Järnvägsg\n9. Tel 042-12 0180. Bankgiro\n864-1417. Postgiro 321790-8. Tga\nLinjebuss. Telex 72233 LBSPED S\n\nVerksamhet; Färjetrafik mellan\nHelsingborg o He lsingör samt\nspeditionsrörelse\nDotterbolag till Linjebuss\nInternational AB.\nSe detta bolag.\n\nLB-HUS AB\n\nPnr 295 00\n\nBromölla, Storg 2. Box 75. Tel\n0456-280 30. Bankgiro 674-1060.\nPostgiro 323042-2\nVerksamhet: Prefabricering av\nen-familjsvillor, radhus, barnstugor mm\nFörsäljningskontor: Bromölla samt\ndistriktsrepresentation på ett\nflertal platser i södra o mellersta\nSverige\n\nAntal anställda: 225\nÅrsomsättning: 45 000 000\nAktiekapital: 200 000\nStyrelse: Dir Lennart Bengtsson\n(ordf), adv Nils Gustin, disp Erik\nOlsson\n\nVerkst dir: Lennart Bengtsson\nDisp: Erik Olsson\nEtableringsår: 1950.\n\nTYDÉNS PATENTER, AB\n\nPnr 11235\n\nStockholm, N Mälarstrand 64.\nTel 08-50 60 78,51 50 18. Bankgiro\n57-4763. Postgiro 56001\nVerksamhet: Tillverkar o säljer\npatenterade o godkända ljuddämpare,\ngnistsläckare o flamskydd\nVarunamn: Atypa\nAntal anställda: 10\nAktiekapital: 26 000\nVerkst dir: E O E Tydén\nDisp: Törd Östner\nEtableringsår: 1941.\n\nFRIGÖR, INDUSTRI-AB\n\nPnr 112 62\n\nStockholm, Lux g 1-3. Tel 08-13 14 50.\nBankgiro 168-8 5 30. Postgiro\n191958-8. Tga Frigör\nVerksamhet: Distributör för\nFrigi-daire kylskåp,\nluftkonditioneringsaggregat o iskubsautomater. Större\n\nkyl- o frysskåp för storkök o\nbutiker, kyl- o frysrumsanläggningar,\nbardiskar. Chrysler\nluftkonditioneringsaggregat. Foster kyl- o\nfrysskåp. IGLOO-FLEX kyltält\nVarunamn: Frigör, Frigidaire,\nFoster, Chrysler, Igloo-Flex\nAntal anställda: 26\nÅrsomsättning: 3 000 000\nAktiekapital: 100 000\nStyrelse: Adv Erie Köhler (ordf),\ning Sven Lindström, ing Harald\nRoos, kamrer Sven Sjöberg\nVerkst dir: Sven Lindström\nEtableringsår: 1942.\n\nA-H PRODUKTER, FABRIKS\nab\n\nPnr 662 00\n\nAmål, Kottev. Box 48. Tel\n0532-10859, 116 62. Bankgiro 36-9076.\nPostgiro 513351\n\nVerksamhet: Tillverkning o\nförsäljning av fönsterbeslag\nChef: Ake Svanström\nEtableringsår: 1964.\n\nINTERFRAKT, AB\n\nPnr 260 73\n\nÖstra Ljungby, Box 43. Tel\n0435-213 30. Bankgiro 657-3257.\nPostgiro 341609-6\n\nVerksamhet: Internationella\nlastbiltransporter till o från\nkontinenten\n\nAntal anställda: 13\nÅrsomsättning: 1 700 000\nAktiekapital: 30 000\nVerkst dir: Gunnar Augustsson\nEtableringsår: 1955.\n\nGATA, AB\n\nPnr 402 52\n\nGöteborg 13, Gamlestadsv. Box\n13070. Tel 031-25 04 00. Telex\n20944\n\nVerksamhet: Transportörer,\nkompletta transportsystem, automatik,\nprojektering\n\nÅrsomsättning: 7 000 000\nAktiekapital: 1800 000\n\nDotterbolag till Gamlestadens AB.\n\nGATE-HUS AB\n\nPnr 544 00\n\nHjo. Tel 0503-200 53, 20133\nVerksamhet Tillverkar bostadshus,\nfritidshus o garage.\n\nGATU och VÄG AB\n\nPnr 403 17\n\nGöteborg 2, Magasinsg 3. Box 2537.\nTel 031-17 29 50. Tga Geveko\nVerksamhet: Entreprenadfirma för\nvägbyggnads- o\nvägbeläggningsar-beten, vatten- o avloppsledningar,\nbroar m m\n\nAvdelningskontor: 183 50 Täby,\nNäsby Allé 1 C. Tel 08-758 01 95\nAntal anstäUda: 300\nÅrsomsättning: 35 000 000\nAktiekapital: 500 000\nStyrelse: Dir Jarl Ergel (ordf), dir\nGunnar Mattsson, dir Osten\nMattsson, adv Sture Hovden (suppl)\nVerkst dir: Osten Mattsson\nEtableringsår: 1934.\n\nNEIKTER &amp; ROSÉN AB\n\nPnr 36100\n\nEmmaboda. Tel 0471-100 03,100 71.\nBankgiro 854-9461. Postgiro\n73376-6\n\nVerksamhet: Järnvaror o\nbyggnadsmaterial\n\nAntal anställda: 12\nAktiekapital: 240 000\nVerkst dir. Ejnar Tarre\nEtableringsår 1919.\n\nWINEMAR AB. CURT\n\nPnr 872 01\n\nKramfors 1. Box 186. Tel\n0612-124 70. Bankgiro 186-9866.\nPost-53020. Tga Wipress.\nTelex 71021 ELPRESS S\nVerksamhet: Tillverkar o säljer\nkontaktpressningsmateriel som\ntänger, hydrauliska pressar,\nrörkabelskor, skarvhylsor o\nanslagsmaskiner med tillhörande bandmar\nterlel\n\nFörsäljningskontor o\nverktygsfab-rik: Trångsund, Vretv 8. Tel\n08-764 9105\n\nAntal anställda: 190\nÅrsomsättning: 15 000 000\nAktiekapital: 400 000\nVerkst dir. Curt Winemar\nEtableringsån 1959.",
    "structured": {
        "1": {
            "company_name": "SKOGSALLIANS, AB",
            "pnr": "116 26",
            "address": "Stockholm, Björngårdsg 13",
            "phone_number": "08-44 55 50 , 44 7 5 24",
            "bank_details": {
                "bankgiro": "728-7378",
                "postgiro": "653080-2"
            },
            "activity": "Agenturrörelse. Alla slag av pappersprodukter o byggnadsmateriel. Exporterar all slags ved, rundvirke, pålar mm",
            "employees": 4,
            "capital": 100000,
            "key_personnel": [
                {
                    "name": "Jan Sjöberg",
                    "position": "Verkst dir"
                }
            ],
            "establishment_year": 1961
        },
        "2": {
            "company_name": "BURSERYDS BRUK AB",
            "pnr": "330 26",
            "address": "Smålands Burseryd",
            "phone_number": "0371-50300",
            "bank_details": {
                "bankgiro": "550-7348",
                "postgiro": "22588-8"
            },
            "activity": "Tillverkar kallvalsat bandstål, galvaniserat bandjärn, trådspik, järntråd o staglinor",
            "employees": 170,
            "annual_turnover": 30000000,
            "capital": 2500000,
            "key_personnel": [
                {
                    "name": "C E Josefsson",
                    "position": "Verkst dir"
                }
            ],
            "establishment_year": 1910
        },
        "3": {
            "company_name": "BURSERYDS FÄRGFABRIK",
            "pnr": "330 26",
            "address": "Smålands Burseryd",
            "phone_number": "0371-500 74",
            "bank_details": {
                "bankgiro": "55-0758",
                "postgiro": "88308"
            },
            "activity": "Tillverkar färdiglagad rödfärg, oljefärger m m",
            "key_personnel": {
                "name": "Folke Andersson",
                "position": "Ägare o chef"
            },
            "establishment_year": 1941
        },
        "4": {
            "company_name": "LB-FÄRJORNA AB",
            "pnr": "25102",
            "address": "Helsingborg 1, Box 16, Järnvägsg 9",
            "phone_number": "042-12 0180",
            "bank_details": {
                "bankgiro": "864-1417",
                "postgiro": "321790-8"
            },
            "activity": "Färjetrafik mellan Helsingborg o Helsingör samt speditionsrörelse",
            "establishment_year": null
        },
        "5": {
            "company_name": "LB-HUS AB",
            "pnr": "295 00",
            "address": "Bromölla, Storg 2, Box 75",
            "phone_number": "0456-280 30",
            "bank_details": {
                "bankgiro": "674-1060",
                "postgiro": "323042-2"
            },
            "activity": "Prefabricering av en-familjsvillor, radhus, barnstugor mm",
            "employees": 225,
            "annual_turnover": 45000000,
            "capital": 200000,
            "key_personnel": [
                {
                    "name": "Lennart Bengtsson",
                    "position": "Verkst dir"
                },
                {
                    "name": "Erik Olsson",
                    "position": "Disp"
                }
            ],
            "establishment_year": 1950
        },
        "6": {
            "company_name": "TYDÉNS PATENTER, AB",
            "pnr": "11235",
            "address": "Stockholm, N Mälarstrand 64",
            "phone_number": "08-50 60 78,51 50 18",
            "bank_details": {
                "bankgiro": "57-4763",
                "postgiro": "56001"
            },
            "activity": "Tillverkar o säljer patenterade o godkända ljuddämpare, gnistsläckare o flamskydd",
            "employees": 10,
            "capital": 26000,
            "key_personnel": [
                {
                    "name": "E O E Tydén",
                    "position": "Verkst dir"
                },
                {
                    "name": "Törd Östner",
                    "position": "Disp"
                }
            ],
            "establishment_year": 1941
        },
        "7": {
            "company_name": "FRIGÖR, INDUSTRI-AB",
            "pnr": "112 62",
            "address": "Stockholm, Lux g 1-3",
            "phone_number": "08-13 14 50",
            "bank_details": {
                "bankgiro": "168-8 5 30",
                "postgiro": "191958-8"
            },
            "activity": "Distributör för Frigi-daire kylskåp, luftkonditioneringsaggregat o iskubsautomater",
            "employees": 26,
            "annual_turnover": 3000000,
            "capital": 100000,
            "key_personnel": [
                {
                    "name": "Sven Lindström",
                    "position": "Verkst dir"
                }
            ],
            "establishment_year": 1942
        },
        "8": {
            "company_name": "A-H PRODUKTER, FABRIKS ab",
            "pnr": "662 00",
            "address": "Amål, Kottev. Box 48",
            "phone_number": "0532-10859, 116 62",
            "bank_details": {
                "bankgiro": "36-9076",
                "postgiro": "513351"
            },
            "activity": "Tillverkning o försäljning av fönsterbeslag",
            "key_personnel": {
                "name": "Ake Svanström",
                "position": "Chef"
            },
            "establishment_year": 1964
        },
        "9": {
            "company_name": "INTERFRAKT, AB",
            "pnr": "260 73",
            "address": "Östra Ljungby, Box 43",
            "phone_number": "0435-213 30",
            "bank_details": {
                "bankgiro": "657-3257",
                "postgiro": "341609-6"
            },
            "activity": "Internationella lastbiltransporter till o från kontinenten",
            "employees": 13,
            "annual_turnover": 1700000,
            "capital": 30000,
            "key_personnel": {
                "name": "Gunnar Augustsson",
                "position": "Verkst dir"
            },
            "establishment_year": 1955
        },
        "10": {
            "company_name": "GATA, AB",
            "pnr": "402 52",
            "address": "Göteborg 13, Gamlestadsv. Box 13070",
            "phone_number": "031-25 04 00",
            "activity": "Transportörer, kompletta transportsystem, automatik, projektering",
            "annual_turnover": 7000000,
            "capital": 1800000
        },
        "11": {
            "company_name": "GATE-HUS AB",
            "pnr": "544 00",
            "address": "Hjo",
            "phone_number": "0503-200 53, 20133",
            "activity": "Tillverkar bostadshus, fritidshus o garage"
        },
        "12": {
            "company_name": "GATU och VÄG AB",
            "pnr": "403 17",
            "address": "Göteborg 2, Magasinsg 3. Box 2537",
            "phone_number": "031-17 29 50",
            "activity": "Entreprenadfirma för vägbyggnads- o vägbeläggningsar-beten, vatten- o avloppsledningar, broar m m",
            "employees": 300,
            "annual_turnover": 35000000,
            "capital": 500000,
            "key_personnel": [
                {
                    "name": "Jarl Ergel",
                    "position": "Dir"
                },
                {
                    "name": "Gunnar Mattsson",
                    "position": "Dir"
                },
                {
                    "name": "Osten Mattsson",
                    "position": "Verkst dir"
                }
            ],
            "establishment_year": 1934
        },
        "13": {
            "company_name": "NEIKTER & ROSÉN AB",
            "pnr": "36100",
            "address": "Emmaboda",
            "phone_number": "0471-100 03,100 71",
            "bank_details": {
                "bankgiro": "854-9461",
                "postgiro": "73376-6"
            },
            "activity": "Järnvaror o byggnadsmaterial",
            "employees": 12,
            "capital": 240000,
            "key_personnel": {
                "name": "Ejnar Tarre",
                "position": "Verkst dir"
            },
            "establishment_year": 1919
        },
        "14": {
            "company_name": "WINEMAR AB. CURT",
            "pnr": "872 01",
            "address": "Kramfors 1, Box 186",
            "phone_number": "0612-124 70",
            "bank_details": {
                "bankgiro": "186-9866",
                "postgiro": "53020"
            },
            "activity": "Tillverkar o säljer kontaktpressningsmateriel som tänger, hydrauliska pressar, rörkabelskor, skarvhylsor o anslagsmaskiner med tillhörande bandmarterlel",
            "employees": 190,
            "annual_turnover": 15000000,
            "capital": 400000,
            "key_personnel": {
                "name": "Curt Winemar",
                "position": "Verkst dir"
            },
            "establishment_year": 1959
        }
    }
}