{
    "original": "FRÖBERG, AB JOHN\n\nPnr 612 01\n\nFinspång 1, Fack. Tel 0122-290 10.\nBankgiro 132-7147. Postgiro\n15432-8. Tga Jofröberg\nVerksamhet: Pappersförädling,\nstämpelfabrik o tryckeri\nAvdelningskontor: 113 37\nStockholm, Torsg 75. Tel 08-30 9216\nVarunamn: Dixi\nAntal anställda: 74\nÅrsomsättning: 7 000 000\nAktiekapital: 200 000\nDir: Stig Fröberg\nDisp: Rolf Fröberg\nEtableringsår: 1879.\n\nRODENTIN AB\n\nPnr 11134\n\nStockholm, Sveav 45. Tel\n08-21 14 52, 21 5702. Bankgiro 73-0430.\nPostgiro 457554. Tga Rodentin\nVerksamhet: Tillverkar o säljer\nbekämpningsmedel mot skadedjur i\nparti. Saneringsvätska mot\nillaluktande vatten o luft. Cloroben\n(om-givningshygieniskt preparat)\nFabrik: Hägersten, Snöbollsgränd\n16. Tel 08-46 80 32\nVarunamn: Cloroben, Rodentin\nAktiekapital: 10000\nVerkst dir. Uno Wenström\nEtableringsår: 1951.\n\nKINDWALL, AB WILHELM\n\nPnr 104 32\n\nStockholm 19, Tuleg 45-47. Pack.\nTel 08-24 85 80. Bankgiro 174-8128.\nPostgiro 152536-7. Tga Bilkindwall\nVerksamhet: Säljer nya bilar av\nmärket Ford o begagnade bilar\nAntal anställda: 165\nÅrsomsättning: 40 244 000\nAktiekapital: 500 000\nVeikst dir: Bengt Byrenius\nEtableringsår: 1932.\n\nKING, AB INDUSTRI.\nKOMPANIET\n\nPnr 250 05\n\nHälsingborg 5, Hästhagsv 1. Box\n5005. Tel 042-1133 95, 11 37 95.\nBankgiro 65-2947. Postgiro 7994.\nTga Industrikompani\nVerksamhet: Säljer cyklar,\nmopeder o reservdelar till dito i parti\nVarunamn: King\nAktiekapital: 1 500 000\nStyrelse: Adv Bengt Linders (ordf),\ndir Erik Jonsson, dir Stig Jonsson\nVerkst dir: Erik Jonsson\nEtableringsår: 1917\nOmbildat till aktiebolag 1943.\n\nKINNA SKOFABRIK,\nBRÖDERNA ANDERSSON\n\nPnr 51100\n\nKinna, Vallbog 2. Tel 0320-100 67.\nBankgiro 43-4814. Postgiro 9496\nVeiksamhet: Tillverkar\narbetskäng-or, arbetslågskor, barnskor,\nbarn-pjäxor o sandaler\nChef: Gunnar Andersson\nFabr: Nils Andersson\nEtableringsår: 1955.\n\nÄNG\n\nÅKEVALL &amp; HART, AB\n\nPnr 200 60\n\nMalmö 30, Fack. Tel 040-15 80 60.\nBankgiro 641-3470. Postgiro\n431963-8\n\nVerksamhet: Tillverkar plastsvetsa-\n\nde artiklar\n\nAntal anställda: 50\n\nÅrsomsättning: 2000 000\n\nAktiekapital: 45 000\n\nVerkst dir. Norbert Hart\n\nEtableringsån 1952.\n\nINDESKO, AB\n\nPnr 11434\n\nStockholm, Smålandsg 2. Tel\n08-63 12 30. Bankgiro 16-6560.\nPostgiro 57110-9. Tga Indesko.\nTelex 10418\n\nVerksamhet: Säljer råmaterial o\nandra förnödenheter till den\nmetallurgiska industrin, till keramisk\nindustri o till slipskivefabrikanter\nVarunamn: Alurit, Lonsicar,\nSter-chamol\n\nAktiekapital: 200000\nVerkst dir: Tor Carring\nEtableringsår: 1934.\n\nBJERNEKULL AB,\nINGENIÖRSFIRMAN EUG\n\nPnr 11248\n\nStockholm, Kungsholms Strand 175.\nTel 08-52 93 85. Bankgiro 483-4909.\nPostgiro 53339-8. Tga Bjernekull\nVerksamhet: Tillverkar fristående\nhyllor o konsolhyllor av stål\nAktiekapital: 50 000\nVerkst dir: Lennart Lönn\nEtableringsår: 1931.\n\nhenningsons byggnads ab\n\nPnr 550 03\n\nJönköping 3, Box 3132. Fridhemsv\n5. Tel 036-11 92 65. Bankgiro\n544-5481. Postgiro 172384^0\nVerksamhet: Byggnadsrörelse\nAntal anställda: 125\nÅrsomsättning: 10000 000\nAktiekapital: 60 000\nStyrelse: Ing Carl-Ake Wahlstedt\n(ordf), fru Gunvor Wahlstedt\nVerkst dir: Ing Carl-Ake Wahlstedt\nTekn avdelningen: Ing Leif\nGunnarsson\n\nEkonomiavdelningen: Kamrer\nHolger Gustavsson\nEtableringsår: 1960.\n\nhenningsons elektriska\nab\n\nPnr 79101\n\nFalun 1, Asg 43. Box 153. Tel\n023-220 90. Bankgiro 792-6363.\nPostgiro 170549-0\nVerksamhet: Säljer elektr materiel.\nUtför installationer\nAktiekapital: 30 000\nVerkst dir: Torsten Henningson\nEtableringsår: 1954.\n\nKOP\n\nSkogschef: Bror Laage-Hellman\nEkonomichef: Sven Arbring\nEtableringsår: 1885.\n\nKOPPARTRANS\nFÖRSÄLJNINGS AB\n\nPnr 104 32\n\nStockholm 19, Pack. Tel\n08-20 9420. Bankgiro 161-3439.\nPostgiro 626106-9. Tga Koptra\nVerksamhet: Mineraloljor\nAktiekapital: 1500 000\nVerkst dir: Yngve Strömberg\nEtableringsår: 1951.\n\nKOPPARTRANS OLJE.\nAKTIEBOLAG\n\nPnr 402 72\n\nGöteborg 8, Nya Torslandav. Box\n8889. Tel 031-53 02 60. Bankgiro\n160-2804. Tga Koptrashell.\nTelex 20647\n\nVerksamhet: Oljeraffinaderi\nAntal anställda: 205\nAktiekapital: 15 000 000\nVerkst dir: Gustav Renström\nEtableringsår: 1947.\n\nHOGANÄS.AFFÄRSTRYCK AB\n\nPnr 263 01\n\nHöganäs 1, Box 89. Tel 042-412 58.\nBankgiro 270-5002. Postgiro\n374411-7\n\nVerksamhet: Utför boktryck o\noffsettryck\n\nVerkst dir: H G S Petersson\nEtableringsår: 1951.\n\nÅS VERKTYGSINDUSTRI\n\nPnr 330 10\n\nBredaryd, Västboås. Tel\n0371-700 86. Bankgiro 142-7632.\nPostgiro 88919-6\n\nVerksamhet: Tillverkar\nformspru-tade plastartiklar i thermoplast.\nEgen verktygstillverkning\nChef: Fabr Hans Dieck\nEtableringsån 1958.",
    "structured": {
        "1": {
            "company_name": "FRÖBERG, AB JOHN",
            "pnr": "612 01",
            "address": "Finspång 1, Fack.",
            "phone_number": "0122-290 10",
            "bank_details": {
                "bankgiro": "132-7147",
                "postgiro": "15432-8"
            },
            "activity": "Pappersförädling, stämpelfabrik o tryckeri",
            "employees": 74,
            "annual_turnover": 7000000,
            "capital": 200000,
            "key_personnel": [
                {
                    "name": "Stig Fröberg",
                    "position": "Dir"
                },
                {
                    "name": "Rolf Fröberg",
                    "position": "Disp"
                }
            ],
            "establishment_year": 1879
        },
        "2": {
            "company_name": "RODENTIN AB",
            "pnr": "11134",
            "address": "Stockholm, Sveav 45",
            "phone_number": "08-21 14 52, 21 5702",
            "bank_details": {
                "bankgiro": "73-0430",
                "postgiro": "457554"
            },
            "activity": "Tillverkar o säljer bekämpningsmedel mot skadedjur i parti. Saneringsvätska mot illaluktande vatten o luft. Cloroben (om-givningshygieniskt preparat)",
            "establishment_year": 1951
        },
        "3": {
            "company_name": "KINDWALL, AB WILHELM",
            "pnr": "104 32",
            "address": "Stockholm 19, Tuleg 45-47. Pack.",
            "phone_number": "08-24 85 80",
            "bank_details": {
                "bankgiro": "174-8128",
                "postgiro": "152536-7"
            },
            "activity": "Säljer nya bilar av märket Ford o begagnade bilar",
            "employees": 165,
            "annual_turnover": 40244000,
            "capital": 500000,
            "key_personnel": [
                {
                    "name": "Bengt Byrenius",
                    "position": "Veikst dir"
                }
            ],
            "establishment_year": 1932
        },
        "4": {
            "company_name": "KING, AB INDUSTRI. KOMPANIET",
            "pnr": "250 05",
            "address": "Hälsingborg 5, Hästhagsv 1. Box 5005",
            "phone_number": "042-1133 95, 11 37 95",
            "bank_details": {
                "bankgiro": "65-2947",
                "postgiro": "7994"
            },
            "activity": "Säljer cyklar, mopeder o reservdelar till dito i parti",
            "capital": 1500000,
            "key_personnel": [
                {
                    "name": "Adv Bengt Linders",
                    "position": "Styrelse (ordf)"
                },
                {
                    "name": "Erik Jonsson",
                    "position": "dir"
                },
                {
                    "name": "Stig Jonsson",
                    "position": "dir"
                },
                {
                    "name": "Erik Jonsson",
                    "position": "Verkst dir"
                }
            ],
            "establishment_year": 1917
        },
        "5": {
            "company_name": "KINNA SKOFABRIK, BRÖDERNA ANDERSSON",
            "pnr": "51100",
            "address": "Kinna, Vallbog 2",
            "phone_number": "0320-100 67",
            "bank_details": {
                "bankgiro": "43-4814",
                "postgiro": "9496"
            },
            "activity": "Tillverkar arbetskäng-or, arbetslågskor, barnskor, barn-pjäxor o sandaler",
            "chef": "Gunnar Andersson",
            "fabr": "Nils Andersson",
            "establishment_year": 1955
        },
        "6": {
            "company_name": "ÄNG ÅKEVALL & HART, AB",
            "pnr": "200 60",
            "address": "Malmö 30, Fack.",
            "phone_number": "040-15 80 60",
            "bank_details": {
                "bankgiro": "641-3470",
                "postgiro": "431963-8"
            },
            "activity": "Tillverkar plastsvetsade artiklar",
            "employees": 50,
            "annual_turnover": 2000000,
            "capital": 45000,
            "key_personnel": [
                {
                    "name": "Norbert Hart",
                    "position": "Verkst dir"
                }
            ],
            "establishment_year": 1952
        },
        "7": {
            "company_name": "INDESKO, AB",
            "pnr": "11434",
            "address": "Stockholm, Smålandsg 2",
            "phone_number": "08-63 12 30",
            "bank_details": {
                "bankgiro": "16-6560",
                "postgiro": "57110-9"
            },
            "activity": "Säljer råmaterial o andra förnödenheter till den metallurgiska industrin, till keramisk industri o till slipskivefabrikanter",
            "establishment_year": 1934
        },
        "8": {
            "company_name": "BJERNEKULL AB, INGENIÖRSFIRMAN EUG",
            "pnr": "11248",
            "address": "Stockholm, Kungsholms Strand 175",
            "phone_number": "08-52 93 85",
            "bank_details": {
                "bankgiro": "483-4909",
                "postgiro": "53339-8"
            },
            "activity": "Tillverkar fristående hyllor o konsolhyllor av stål",
            "capital": 50000,
            "key_personnel": [
                {
                    "name": "Lennart Lönn",
                    "position": "Verkst dir"
                }
            ],
            "establishment_year": 1931
        },
        "9": {
            "company_name": "henningsons byggnads ab",
            "pnr": "550 03",
            "address": "Jönköping 3, Box 3132. Fridhemsv 5",
            "phone_number": "036-11 92 65",
            "bank_details": {
                "bankgiro": "544-5481",
                "postgiro": "172384^0"
            },
            "activity": "Byggnadsrörelse",
            "employees": 125,
            "annual_turnover": 10000000,
            "capital": 60000,
            "key_personnel": [
                {
                    "name": "Ing Carl-Ake Wahlstedt",
                    "position": "Styrelse (ordf)"
                },
                {
                    "name": "fru Gunvor Wahlstedt",
                    "position": "Styrelse"
                },
                {
                    "name": "Ing Carl-Ake Wahlstedt",
                    "position": "Verkst dir"
                },
                {
                    "name": "Ing Leif Gunnarsson",
                    "position": "Tekn avdelningen"
                },
                {
                    "name": "Holger Gustavsson",
                    "position": "Ekonomiavdelningen"
                }
            ],
            "establishment_year": 1960
        },
        "10": {
            "company_name": "henningsons elektriska ab",
            "pnr": "79101",
            "address": "Falun 1, Asg 43. Box 153",
            "phone_number": "023-220 90",
            "bank_details": {
                "bankgiro": "792-6363",
                "postgiro": "170549-0"
            },
            "activity": "Säljer elektr materiel. Utför installationer",
            "capital": 30000,
            "key_personnel": [
                {
                    "name": "Torsten Henningson",
                    "position": "Verkst dir"
                }
            ],
            "establishment_year": 1954
        },
        "11": {
            "company_name": "KOP",
            "skogschef": "Bror Laage-Hellman",
            "ekonomichef": "Sven Arbring",
            "establishment_year": 1885
        },
        "12": {
            "company_name": "KOPPARTRANS FÖRSÄLJNINGS AB",
            "pnr": "104 32",
            "address": "Stockholm 19, Pack",
            "phone_number": "08-20 9420",
            "bank_details": {
                "bankgiro": "161-3439",
                "postgiro": "626106-9"
            },
            "activity": "Mineraloljor",
            "capital": 1500000,
            "key_personnel": [
                {
                    "name": "Yngve Strömberg",
                    "position": "Verkst dir"
                }
            ],
            "establishment_year": 1951
        },
        "13": {
            "company_name": "KOPPARTRANS OLJE. AKTIEBOLAG",
            "pnr": "402 72",
            "address": "Göteborg 8, Nya Torslandav. Box 8889",
            "phone_number": "031-53 02 60",
            "bank_details": {
                "bankgiro": "160-2804",
                "postgiro": "172384^0"
            },
            "activity": "Oljeraffinaderi",
            "employees": 205,
            "capital": 15000000,
            "key_personnel": [
                {
                    "name": "Gustav Renström",
                    "position": "Verkst dir"
                }
            ],
            "establishment_year": 1947
        },
        "14": {
            "company_name": "HOGANÄS.AFFÄRSTRYCK AB",
            "pnr": "263 01",
            "address": "Höganäs 1, Box 89",
            "phone_number": "042-412 58",
            "bank_details": {
                "bankgiro": "270-5002",
                "postgiro": "374411-7"
            },
            "activity": "Utför boktryck o offsettryck",
            "capital": 1500000,
            "key_personnel": [
                {
                    "name": "H G S Petersson",
                    "position": "Verkst dir"
                }
            ],
            "establishment_year": 1951
        },
        "15": {
            "company_name": "ÅS VERKTYGSINDUSTRI",
            "pnr": "330 10",
            "address": "Bredaryd, Västboås",
            "phone_number": "0371-700 86",
            "bank_details": {
                "bankgiro": "142-7632",
                "postgiro": "88919-6"
            },
            "activity": "Tillverkar formsprutade plastartiklar i thermoplast. Egen verktygstillverkning",
            "chef": "Fabr Hans Dieck",
            "establishment_year": 1958
        }
    }
}