{
    "original": "JOHANSSON, FRITZ\n\nPnr 701 06\n\nÖrebro 1, Nyg 23. Box 485. Tel\n019-1110 41, 11 15 26. Postgiro\n20751. Tga Fritz\nVerksamhet: Grosshandelsrörelse\nmed leksaker, barnvagnar,\ndockvagnar m m\n\nÄgare o chef: Gunnar Bermark\nEtableringsår: 1908.\n\nSTÅLRAMAR, AB\n\nPnr 543 01\n\nTibro 1, Verkstadsg. Box 208. Tel\n\n0504-116 70. Bankgiro 221-4054.\nPostgiro 106910-3\nVerksamhet: Tillverkar\nstålrörs-sängar\n\nVerkst dir: Arthur Persson.\n\nSTÅLSKOG AB, INGENJÖRS.\nFIRMAN RAGNAR\n\nPnr 12142\n\nJohanneshov, Steningev 3. Tel\n08-814310. Bankgiro 569-0102.\nPostgiro 509590-6\n\nVerksamhet: Säljer\njordningsverk-tyg, verktyg för arbete under\nspänning\n\nAktiekapital: 35 000\nVerkst dir: Ragnar Stålskog\nEtableringsår: 1960.\n\nARNO-MASKINER AB\n\nPnr 234 00\n\nLomma. Tel 040-413615. Bankgiro\n673-1020. Postgiro 148734-7. Tga\nArnö. Telex 32268 ARNÖ S\nVerksamhet: Tillverkar\nnitnings-maskiner, knappisättningsmaskiner,\nspikningsmaskiner. Helautomater\nAvdelningskontor: Kävlinge, AB\nARNÖ. Tel 046-319 70. Agentur för\ngarverimaskiner\nVarunamn: Arnö\nAntal anställda: 55\nÅrsomsättning: 4 000 000\nAktiekapital: 200 000\nVerkst dir: Nils J Holst\nEtableringsår: 1942.\n\nÄRO, HANDELS &amp;\nINDUSTRI AB\n\nPnr 102 42\n\nStockholm 5, Grev Tureg 15. Box\n5077. Tel 08-67 9015. Bankgiro\n13-6150. Postgiro 336280. Tga\nAro-handel\n\nVerksamhet: Försäljning genom\nmoderbolaget Rima AB\nAktiekapital: 100 000\nVerkst dir: Ake Dunér\nEtableringsår: 1947\nDotterbolag till Rima AB, Sthlm.\n\nARONSSON &amp; HELL,\nMÄKLAREFIRMAN\n\nPnr 652 25\n\nKarlstad, V Torgg 11. Tel 054-\n\n1107 82, 11 17 82. Postgiro\n320272-8\n\nVerksamhet: Fastighetsförmedling\ninnefattande även\naffärsöverlåtelser, arrenden, bouppteckningar o\nauktioner\nChef: Boris Hell\nEtableringsår: 1909.\n\njunellsab\n\nPnr 501 04\n\nBorås 1, Skaraborgsv 35. Box 176.\nTel 033-10 03 15. Bankgiro 53-1264.\nPostgiro 94218\n\nVerksamhet: Tillverkar dräkter o\nklänningar\nVarunamn: Jönells\nAntal anställda: 50\nÅrsomsättning: 3 000 000\nAktiekapital: 75 000\nVerkst din Ive B Arleving\nEtableringsår: 1935\nOmbildat till aktiebolag 1938.\n\njünküpings borst.\n\nfabrik ab\n\nPnr 555 90\n\nJönköping, Kindgrensg 3. Tel\n036-1151 03, 114123. Bankgiro\n271-8245. Postgiro 171574-7\nVerksamhet: Tillverkar\ncirkulär-borstar av tråd o fiber för\nindustrin, sopmaskinsvalsar samt\nhus-hållsborstar o penslar\nVerkst dir: Fabr O Johansson\nVerkmäst: Ryno Johansson\nEtableringsår: 1941.\n\njunkupings\ndatastansnings ab\n\nPnr 552 40\n\nJönköping, Museig 7. Tel\n036-124202, 129455. Postgiro\n264282-5\n\nVerksamhet: Stansning av\nbokföring, reskontra o löner\nAktiekapital: 10 000\nVerkst dir: Bertil Tolf\nEtableringsår: 1969.\n\njunkupings industri\naffärstjänst\n\nPnr 550 04\n\nJönköping 4, Björnebergsv 29. Box\n4075. Tel 036-12 78 17, 11 56 40.\nBankgiro 83-5698. Postgiro 545006.\nTga Jitab\n\nVerksamhet: Grossiströrelse o\ntillverkning av arbetarskyddsmaterial\nsåsom arbetshandskar i tyg o\nspaltläder, skyddsförkläden i olika\nmaterial samt skåp o automater för\nförbandsmaterial\nVarunamn: Jitab\nAntal anställda: 8\nÄgare o chef: Disp Arne Liw\nEtableringsår: 1963.\n\njunkupings isolerings.\nfirma, ab\n\nPnr 550 07\n\nJönköping 7, Box 7076. Tel\n036-13 55 89. Bankgiro 544-9400\nVerksamhet: Isoleringsarbeten\ninom industri o bostadsbyggnader.\nIsoleringsmaterial\nAktiekapital: 25 000\nVerkst dir: John Svensson\nEtableringsår: 1944.\n\nB 11\n\njunkupings juridiska\nbyrå ab\n\nPnr 104 22\n\nStockholm 22, Box 22116.\nHant-verkareg 8. Tel 08-54 08 60.\nBankgiro 658-8867. Postgiro 401343-9.\nTga Jönköpingsbyrån\nVerksamhet: Inkassorörelse\nAktiekapital: 75 000\nStyrelse: Adv Håkan Rumstedt,\ndir Leif Palmdahl\nVerkst dir: Leif Palmdahl\nKamrer: Bertil Strömberg\nFörsäljn-chef: Rolf Hagström\nEtableringsår: 1874.\n\nÅHLBERG &amp; AHNMÉ AB\n\nPnr 18121\n\nLidingö 1, Box 104. Tel\n08-767 0140. Bankgiro 477-6472.\nPostgiro 354045-7. Tga Ahnmesweden.\nTelex 10834\n\nVerksamhet: Förarstolar, fabrikat\nBostrom\n\nVarunamn: Bostrom\nAntal anställda: 16\nÅrsomsättning: 12 000000\nAktiekapital: 100 000\nVerkst din Lennart Ahnmé\nEtableringsån 1948.\n\nÅLBERGA SÅG- &amp;\nKRAFTVERK AB\n\nPnr 610 50\n\nJönäker. Tel 0155-720 06, 72062.\nBankgiro 61-9119. Postgiro\n130220. Tga Aalbergawood\nVerksamhet: Tillverkar o säljer\nsågade o hyvlade trävaror\nAntal anställda: 70\nÅrsomsättning: 8 000 000\nAktiekapital: 1000 000\nVerkst dir: Jägmäst Fredrik\nSederholm\n\nEtableringsår: 1938.\n\nTK PRODUCTS AB\n\nPnr 423 00\n\nTorslanda, Centrum. Tel\n031-56 0924. Bankgiro 851-8334.\nPostgiro 621475. Tgalnteko\nVerksamhet: Textilmaskiner,\nkonstruktioner o agenturer\nAktiekapital: 5000\nVertist dir. Harry Ryrberg\nEtableringsår: 1961.\n\nMARMOR &amp; GRANIT, AB\n\nPnr 291 01\n\nKristianstad 1, Box 161. Industrig\n4. Tel 044-1123 52, 1134 40.\nBankgiro 867-5001. Postgiro 290991-9\nVerksamhet: Förädlar svenska o\nutländska kalkstens- o\nmarmorsorter. Säljer all slags natursten\ntill byggnader o trädgårdar\nAntal anställda: 18\nÅrsomsättning: 2 000 000\nAktiekapital: 80 000\nStyrelse: Ing Nils B Tenje (ordf),\nfru Anna Brita Tenje\nEtableringsår: 1946.\n\nSALWÉNSONIC, AB\n\nPnr 302 45\n\nHalmstad, Kungsg 1. Tel\n035-11 93 10. Bankgiro 42-3726.\nPostgiro 6520. Tga Salwénsonic\nVerksamhet: Generalagent för\nBranson Instruments, Stamford, USA\nAntal anstäUda: 5\nAktiekapital: 10 000\nVerkst dir: Civiling Gunnar\nSalwén\n\nEtableringsår 1948.\n\nSUNDSTRÖM &amp; LINDQUIST AB\n\nPnr 103 13\n\nStockholm 2, Stortorget 18-20. Box\n2099. Tel 08-11 19 28, 10 04 28.\nBankgiro 446-9417. Postgiro\n255447-5. Tga Cotton. Telex 10438\nVerksamhet: Agentur- o\nhandelsfirma i fetter o fettsyror,\naminosyror, vitaminer, klorkalcium,\nkemikalier m m\n\nÄgare o chef: Gunnar Lindquist\nEtableringsår: 1880\nOmbildat till aktiebolag 1966.\n\nSUNDSTRUMS RESPIRATORER\n\nPnr 18141\n\nLidingö 1, Vasav 84. Tel\n08-76512 52. Bankgiro 743-2404.\nPostgiro 468167-2. Tga Sundarb\nVerksamhet: Tillverkar\narbetar-skyddsmateriel såsom\nskyddsglasögon, respiratorer o gasmasker\nAntal anställda: 8\nÅrsomsättning: 900 000\nÄgare o chef: Per Otto Sundström\nEtableringsår: 1930.\n\nSUNDSTRÖM &amp; OGREN\nMASKIN AB\n\nPnr 163 57\n\nSpånga, Winqvists v 33-39. Tel\n08-760 04 80. Bankgiro 57-7549.\nPostgiro 703057\n\nVerksamhet: Uthyr o säljer\nbyggnadsmaskiner\nAntal anställda: 20\nAktiekapital: 100 000\nVerkst dir: Rudolf Sundström\nEtableringsår: 1963.\n\nSUNDSTRUMS JÄRNHANDEL,\nAB AXEL\n\nPnr 722 15\n\nVästerås, Vasag 20. Tel\n021-13 73 40. Bankgiro 80-8681.\nPost-giro 10901\n\nVerksamhet: Säljer o lagerför\njärnvaror, byggnadsbeslag, verktyg,\nstångjärn, cement mm\nViksängshallen: Västerås, Björnv 8.\nTel 021-13 7340\nAktiekapital: 300 000\nVerkst dir: Erik Sundström\nV verkst dir: Axel Sundström\nEtableringsår: 1891.\n\nHUS\n\nHULTGRENS REVISIONSBYRÅ\nAB, BJÖRN\n\nPnr 41106\n\nGöteborg, N Hamng 32. Tel\n031-17 79 20. Bankgiro 506-5503.\nPost-giro 48301-6\n\nVerksamhet: Revisioner, finansiell\no administrativ konsultverksamhet,\nskattekonsulationer\nAntal anställda: 15\nÅrsomsättning: 850 000\nAktiekapital: 5 000\nChefer: Aukt revisor Björn\nHultgren, aukt revisor Kurt Hellstrand\nEtableringsår: 1952.",
    "structured": {
        "1": {
            "company_name": "JOHANSSON, FRITZ",
            "pnr": "701 06",
            "address": "Örebro 1, Nyg 23. Box 485",
            "phone_number": "019-1110 41, 11 15 26",
            "bank_details": {
                "postgiro": "20751"
            },
            "activity": "Grosshandelsrörelse med leksaker, barnvagnar, dockvagnar m m",
            "establishment_year": 1908,
            "key_personnel": [
                {
                    "name": "Gunnar Bermark",
                    "position": "Ägare o chef"
                }
            ]
        },
        "2": {
            "company_name": "STÅLRAMAR, AB",
            "pnr": "543 01",
            "address": "Tibro 1, Verkstadsg. Box 208",
            "phone_number": "0504-116 70",
            "bank_details": {
                "bankgiro": "221-4054",
                "postgiro": "106910-3"
            },
            "activity": "Tillverkar stålrörs-sängar",
            "key_personnel": [
                {
                    "name": "Arthur Persson",
                    "position": "Verkst dir"
                }
            ]
        },
        "3": {
            "company_name": "STÅLSKOG AB, INGENJÖRS. FIRMAN RAGNAR",
            "pnr": "12142",
            "address": "Johanneshov, Steningev 3",
            "phone_number": "08-814310",
            "bank_details": {
                "bankgiro": "569-0102",
                "postgiro": "509590-6"
            },
            "activity": "Säljer jordningsverktyg, verktyg för arbete under spänning",
            "capital": 35000,
            "key_personnel": [
                {
                    "name": "Ragnar Stålskog",
                    "position": "Verkst dir"
                }
            ],
            "establishment_year": 1960
        },
        "4": {
            "company_name": "ARNO-MASKINER AB",
            "pnr": "234 00",
            "address": "Lomma",
            "phone_number": "040-413615",
            "bank_details": {
                "bankgiro": "673-1020",
                "postgiro": "148734-7"
            },
            "activity": "Tillverkar nitnings-maskiner, knappisättningsmaskiner, spikningsmaskiner. Helautomater",
            "employees": 55,
            "annual_turnover": 4000000,
            "capital": 200000,
            "key_personnel": [
                {
                    "name": "Nils J Holst",
                    "position": "Verkst dir"
                }
            ],
            "establishment_year": 1942
        },
        "5": {
            "company_name": "ÄRO, HANDELS & INDUSTRI AB",
            "pnr": "102 42",
            "address": "Stockholm 5, Grev Tureg 15. Box 5077",
            "phone_number": "08-67 9015",
            "bank_details": {
                "bankgiro": "13-6150",
                "postgiro": "336280"
            },
            "activity": "Försäljning genom moderbolaget Rima AB",
            "capital": 100000,
            "key_personnel": [
                {
                    "name": "Ake Dunér",
                    "position": "Verkst dir"
                }
            ],
            "establishment_year": 1947
        },
        "6": {
            "company_name": "ARONSSON & HELL, MÄKLAREFIRMAN",
            "pnr": "652 25",
            "address": "Karlstad, V Torgg 11",
            "phone_number": "054-1107 82, 11 17 82",
            "bank_details": {
                "postgiro": "320272-8"
            },
            "activity": "Fastighetsförmedling innefattande även affärsöverlåtelser, arrenden, bouppteckningar o auktioner",
            "key_personnel": [
                {
                    "name": "Boris Hell",
                    "position": "Chef"
                }
            ],
            "establishment_year": 1909
        },
        "7": {
            "company_name": "junellsab",
            "pnr": "501 04",
            "address": "Borås 1, Skaraborgsv 35. Box 176",
            "phone_number": "033-10 03 15",
            "bank_details": {
                "bankgiro": "53-1264",
                "postgiro": "94218"
            },
            "activity": "Tillverkar dräkter o klänningar",
            "employees": 50,
            "annual_turnover": 3000000,
            "capital": 75000,
            "key_personnel": [
                {
                    "name": "Ive B Arleving",
                    "position": "Verkst din"
                }
            ],
            "establishment_year": 1935
        }
    }
}