{
    "original": "TIVOLIM AB\n\nPnr 21137\n\nMalmö, Stora Nyg 21. Tel\n040-1297 10,12 97 11. Bankgiro 87-5536.\nPostgiro 148969. Tga Tivotrade\nVerksamhet: Ensamförsäljare för\nAB Tivokemi\nAktiekapital: 100 000\nVerkst din H Homann\nEtableringsån 1947.\n\nNÄSSJÖ VADDFABRIKER, AB\n\nPnr 571 00\n\nNässjö, Brog 12. Box 80. Tel\n0380-18140. Bankgiro 425-9160.\nPostgiro 7831-1. Tga Vaddfabriken\nVerksamhet: Tillverkar vadd av\nalla slag\n\nAktiekapital: 300 000\n\nVerkst dir: Birger Fritz\nEtableringsår: 1886.\n\nNÄSSJÖ\nVATTENGLASFABRIK, AB\n\nPnr 57100\n\nNässjö, Storg 13. Tel 0380-107 55.\nBankgiro 14-3656. Postgiro 96871\nVerksamhet: Tillverkar kali- o\nnatronvattenglas\nÅrsomsättning: 700 000\nAktiekapital: 30 000\nVerkst dir: Melvin Gråberg\nEtableringsår: 1935.\n\nFIGEHOLMS BRUK, AB\n\nPnr 570 92\n\nFigeholm. Tel 0491-312 00.\nBankgiro 450-6069. Postgiro 165362-5.\nTgaFigeholmprespan, Oskarshamn.\nTelex 4990 ELBOARD S\nVerksamhet: Tillverkar\nelektro-presspan, polyespan o polymex\nAntal anställda: 165\nÅrsomsättning: 13 000 000\nAktiekapital: 500 000\nVerkst dir. Nils Biesért\nEtableringsår: 1931.\n\nFOL\n\nom landet med undantag för\nkollektiv tjänstepensionsförsäkring o\nhusdjursförsäkring; utom landet\nmed undantag för kollektiv\ntjänstepensionsförsäkring. Indirekt\nförsäkring (återförsäkring): all slags\nperson- o sakförsäkring inom o\nutom landet med undantag för\nkollektiv tjänstepensionsförsäkring\nAvdelningskontor: 90 stycken över\nhela landet\nAntal anställda: 2 543\nPremieinkomst: 697 000 000\nStyrelse: LO:s förste ordf Arne\nGeijer (ordf), dir Harry Hjalmarson,\ndir Filip Granlund, förbundsordf\nKnut Johansson, dir Ake Linder,\nkommunalråd Karl Erik Lundström,\nförbundsordf Erik Magnusson,\nläns-bostadsdir Gunnar Norrhall,\nsek-tionsordf Evert Svensson, dir Sven\nSwärd, dir Klas Back\nVerkst dir: Klas Back\nI Folksamgruppen ingår följande\nföretag: Folksaro-ömsesidig\nlivförsäkring (grundat 1914), Folksam\nömsesidig sakförsäkring (grundat\n1908), Folksam-ömsesidig\nyrkesskadeförsäkring (grundat 1950) o\nFolksam International Insurance\nCo Ltd (Folksam Internationellt\nFörsäkringsaktiebolag, grundat\n1949).\n\nFOLKTRYCK AB\n\nPnr 631 05\n\nEskilstuna, Box 368.\nRade-macherg 29. Tel 016-13 72 70.\nBankgiro 5304-1003. Postgiro\n10720-1\n\nVerksamhet: Utger tidningen\nFolket\n\nAntal anställda: 190\nÅrsomsättning: 14 000 000\nAktiekapital: 1 290 000\nVerkst dir. Mose Mallsten\nEtableringsår. 1905.\n\nSAA\n\ns\n\nSAAB-ANA AKTIEBOLAG\n\nPnr 61101\n\nNyköping 1, Båthamnsv. Fack. Tel\n0155-807 00. Bankgiro 160-3752.\nPostgiro 135265-7.\nTga Ana. Telex 64018\nVerksamhet: Bolaget är\nrepresentant för bl a SAAB-SCANIA\nAktiebolag, Chrysler International SA,\nSchweiz, Massey-Ferguson Ltd o\nRootes Motors Overseas Ltd,\nEngland. Aterförsäljer bilar, bussar,\njordbrukstraktorer o redskap samt\nlätta o tunga industri- o\nentreprenadsmaskiner dels genom egna\nfilialer o dels genom fristående\nåterförsäljare samt bedriver dessutom\nviss tillverkning av detaljer till\nbilar o traktorer\nVarunamn: Ana\nAntal anställda: 806\nÅrsomsättning: 574 500 000\nAktiekapital: 36 000 000\nStyrelse: Talman Erik Boheman\n(ordf), dir Torsten Arnheim, dir\nTryggve Holm, dir Marc Wallenberg\njr, dir Curt Mileikowsky, dir Rolf\nSandberg\n\nVerkst dir: Torsten Arnheim\nEtableringsår: 1937\nÄges av SAAB-SCANIA\nAktiebolag, Linköping.\n\nSAAB.ANA I STOCKHOLM AB\n\nPnr 17120\n\nSolna 1, Fack. Tel 08-28 90 40.\nBankgiro 200-5049. Postgiro\n52250-8. Tga Bilby\nVerksamhet: Bilförsäljning,\nbilreparationer\n\nAntal anställda: 516\nÅrsomsättning: 136 000 000\nAktiekapital: 400 000\nVerkst dir: Jonas C:son Kjellberg\nEtableringsår: 1934.\n\nSAAB.SCANIA AB\n\nHUVUDKONTOR\nPnr 58188\n\nLinköping. Tel 013-13 00 20\n(12 90 20). Tga SAAB. Telex 64940,\n64960. Bankgiro 12-0156, 16-0380.\nPostgiro 160342\n\nSAAB-SCANIA\n\nEtablerat 1969 genom en fusion\nmellan SAAB o Scania-Vabis, som\ngrundades 1937 resp 1891.\nNordarmatur (NAF), som grundades\n1899, uppgick i SAAB-SCANIA\n1969\n\nAntal anställda: 28 600 (1970)\n\n(i Sverige)\n\nÅrsomsättning: 3 509 000 000 (1970)\nAktiekapital: 425100 000 (1970)\nStyrelse: Tekn dr Marcus\nWallenberg (ordf), ambassadör Erik\nBoheman (l:e v ordf), dir Göte Engfors,\nkonsul Tryggve Holm, dir Alvar\nLindencrona, tekn dr Curt\nMileikowsky, dir Gösta Nilsson, tekn dr\nHåkan Sterky, expeditionschef\nJohan Treschow, frih Nils-Fredrik\nvon Essen, dir Karl-Arvid Norlin,\ndir Marc Wallenberg jr\nVerkst dir: Curt Mileikowsky\nV verkst dinr: Torsten Arnheim,\nTörd Lidmalm, Bertil Johnson,\nHans-Eric Löfkvist, Arne Rydberg,\nTöre Gullstrand, Gunnar Lindström,\nErik Nilsson, Sverker Sjöström\nInformation: Överste Nils-Magnus\nvon Arbin.\n\nBILDIVISIONEN\n\n15187 Södertälje. Tel 0755-34140.\nTga SCANIA. Telex 10200\nDivisionschef o v verkst dir:\n\nE Nilsson\n\nMarknadssektor: Chef dir C J\nLewenhagen\n\nLastbilssektor Chef o v verkst dir\nS Sjöström\n\nPersonbilssektor: Chef dir R\nSandberg (46101 Trollhättan. Tel\n0520-126 00. Tga SAAB. Telex 42110)\nExportchefer: Dir:r: C A Carlson,\nG Beiwert, H Carlsson, L Luthman\nInformation: Dir K Sandell\nVerksamhet: Tillverkare av\npersonbilar, diesellastbilar o bussar,\nindustriella o marina dieselmotorer\nFabriker i: Södertälje, Trollhättan,\nGöteborg, Katrineholm,\nOskarshamn, Luleå, Kristinehamn o\nSibbhult.\n\nFLYGDIVISIONEN\n58188 Linköping. Tel 013-13 00 20\n(12 90 20). Tga SAAB. Telex 64940\nDivisionschef o v verkst dir:\nT Gullstrand\n\nElygplansektor. Chef dir H\nSchröder\n\nRobot- o elektroniksektor: Chef\növering I K Olsson\nMalmö Flygindustri: Chef dir R\nAbelin (20110 Malmö 1. Tel\n040-93 47 10. Tga FLYGIN)\nInformation: Red H G Andersson\nVerksamhet: Tillverkare av\nflygplan, robotvapen, militär elektronik,\nrymdsystem, marin automation m m\nFabriker i: Linköping, Göteborg,\nStockholm, Odeshög, Vidsel,\nDagsberg, Kramfors o Malmö.\n\nDATA- o\nELEKTRONIKDIVISIONEN\n\n581 88 Linköping. Tel 013-11 15 00.\nTga DATASAAB. Telex 64922\n\nDivisionschef o v verkst dir:\n\nG Lindström\n\nDatasektor: Chef dir V Wentzel\nDataservicesektor: Chef övering\nS Yngvell (58188 Linköping. Tel\n013-1300 20, 129020. Tga SAAB.\nTelex 64940)\n\nIndustrisektor: Chef dir B Sylvan\n(550 02 Jönköping 2. Tel\n036-11 97 80. Tga SAAB. Telex 70145)\nMedicinteknisk sektor: Chef\növering H Ericsson (58188 Linköping.\nTel 013-11 13 40. Tga SAAB. Telex\n6494 0)\n\nInformation: Ing B Sigvall\nVerksamhet: Tillverkare av\ndatasystem (datorer), industriella\nstyrsystem o medicinteknisk utrustning\nFabriker i: Linköping, Jönköping,\nStensholm o Kramfors.\n\nNORD ARMATURDIVISIONEN\n581 87 Linköping. Tel 013-12 90 60.\nTga NORDARMATUR. Telex\n64958, 64969\n\nDivisionschef: Dir A Schillström\nVerksamhet: Tillverkare av\nventiler, mät- o reglerutrustning för\nångkraftanläggningar, atomreaktorer,\nskeppsvarv samt kemisk o mekanisk\nindustri, tryckluftbromsar System\nKnorr, vattenmätare\nFabriker i: Linköping, Lund o\nSolna.\n\nSABAVERKEN\nNILSSON &amp; OHRSTROM AB\n\nPnr 21120\n\nMalmö, Carlsg 54. Tel 040-723 00.\nBankgiro 202-2812. Postgiro\n637292-4\n\nVerksamhet:\nOljeeldningsanläggningar, elektroniska mätare o\nnivåvakter, el-, ång- o värmepannor,\nv ar ml uf t spannor, b yggt or kar, v att e\nn-filter, doseringspumpar o -apparater\nAktiekapital: 10 000\nEtableringsår: 1968.\n\nHANGERS TRÄINDUSTRI, AB\n\nPnr 33100\n\nVärnamo. Tel 0370-41180.\nBankgiro 291-5593. Postgiro 133291-5\nVerksamhet: Tillverkar o säljer\nfönster, ytterdörrar o vipportar\nAntal anställda: 30\nÅrsomsättning: 3 500 000\nVerkst dir: Per-Olof Sandwall\nEtableringsår: 1935.\n\nSÖNNERGREN, AB BENGT\n\nPnr 11245\n\nStockholm, Sankt Göransg 124. Tel\n08-512010, 512811. Bankgiro\n733-4527. Postgiro 254075-5\nVerksamhet: Säljer glödlampor,\nlysrör, lysrörsarmaturer samt\nbilringar i parti\nAktiekapital: 5 000\nVeikst dir: Bengt Sönnergren\nEtableringsår: 1955.\n\nSORBERG ARMATURFABRIK\nAB, ERIK\n\nPnr 736 00\n\nKungsör, Box 29. Tel 0227-11000.\nBankgiro 617-9527. Postgiro\n98245-4. Tga Säf\nVerksamhet: Tillverkar armatur\nför gas, vatten o värme samt\nme-tallgjutgods\nAntal anställda: 95\nÅrsomsättning: 11 000 000\nAktiekapital: 150 000\nVeikst dir. Erik Sörberg\nEtableringsår: 1936\nOmbildat till aktiebolag 1956.\n\nSORBY HYVLERI &amp;\nTRÄVARU-AFFÄR\n\nPnr 700 03\n\nÖrebro 3, Sörbyallén 3. Box 3018.\nTel 019-1137 83, 1179 30.\nBankgiro 614-5080. Postgiro 466550-1\nVerksamhet: Säljer trävaror o\nbyggnadsmaterial\nAntal anställda: 3\nÅrsomsättning: 500 000\nChef: Bertil Larsson.\n\nSORBY JÄRN &amp; METALL AB\n\nPnr 722 33\n\nVästerås, Industriv 11. Tel\n021-608 00. Bankgiro 63-0107. Postgiro\n327760\n\nVerksamhet: Mekanisk verkstad\n(legoarbeten). Tillverkning o\nsvetsning i aluminium o rostfritt\nAntal anställda: 13\nÅrsomsättning: 450 000\nAktiekapital: 10 000\nStyrelse: Dir Bengt Fredriksson\n(ordf), herr Claes Herlevsson\nVerkst dir: Bengt Fredriksson\nEtableringsår: 1965\nOmbildat 1967 till nuvarande\nfirmanamn.\n\nSORLING, AB JOHAN\n\nPnr 195 01\n\nMärsta 1, Box 29. Industrig 7. Tel\n0760-40110. Bankgiro 233-9141.\nPostgiro 95062-6. Tga Sörlingtipp\nVerksamhet: Tillverkar hydrauliska\ntippar, betongtransportbehållare,\nkraftuttag, kugghjulspumpar,\nbog-ser- o armédragkrok, boggielyftar,\ntipp- o flakbyggnationer,\nlättdum-pers\n\nVarunamn: Sörling, Sörling\nboggi-lyft\n\nAntal anställda: 140\nÅrsomsättning: 13 000 000\nAktiekapital: 1 500 000\nStyrelse: Kontorschef Viktor Du\nRietz (ordf), fabr Harry Sörling,\nfru Märta Sörling\nVerkst dir: Fabr Harry Sörling\nKontorschef: Viktor Du Rietz\nInköpschef: Sture Heimerdahl\nFörsäljn-chef: Ing Gösta\nPettersson\n\nEtableringsår: 1924\nOmbildat till aktiebolag 1942.\n\nSORMANS\n\nDELIKATESSER AB\n\nPnr 502 45\n\nBorås, Ulricehamnsv. Tel\n033-121601, 122943. Bankgiro\n411-1456. Postgiro 225868-9\nVerksamhet: Tillverkar\nsillinläggningar, fiskrätter\nAntal anställda: 15\nÅrsomsättning: 2 500 000\nAktiekapital: 5 000\nVerkst dir: Vincent Sörman\nEtableringsår: 1957.\n\nBETONGELEMENT, AB\n\nPnr 20110\n\nMalmö 1, Fack. Stormg 14.\nTel 040-97 35 00. Bankgiro\n203-5202. Postgiro 531356-4\nVerksamhet: Försäljning av\nprefabricerade betongelement\nÅrsomsättning: 2 7 00 000\nAktiekapital: 100 000\nVerkst dir: Bengt Randel\nEtableringsår: 1955.\n\nEOL, AB\n\nPnr 412 76\n\nGöteborg, Mejerig 1. Tel 409000,\nriks 031-40 91 00. Tga Eolbolaget.\nTelex 2245\n\nVerksamhet: Livsmedel, textil, järn\no husgeråd m m i parti\nAntal anställda: 1416\nÅrsomsättning: 1225 000 000\nAktiekapital: 13 000 000\nVerkst dir: Erie Ofverström\nEtableringsår: 1938.\n\nEOS TRYCKERIERNA\nENGWALL &amp; STRÅHLE AB\n\nPnr 103 65\n\nStockholm 3, Box 3276. Sveav\n35-37. Tel 08-2313 55\nVerksamhet: Boktryckeri, offset,\nreklam, reklamtryck, tidskrifter\nAntal anställda: 40\nÅrsomsättning: 2 800 000\nVerkst dir: Gösta Andersson\nEtableringsår: 1919.\n\nPEOPAC AB &amp; CO KB\n\nPnr 710 10\n\nFjugesta. Tel 0585-104 60. Telex\n73328. Tga Peopacking, Örebro\nVerksamhet: Tillverkar mynthylsor,\npolyetenfilm o\nportionsförpackningar samt utför kontraktpackning\nAntal anställda: 120\nÅrsomsättning: 12 000 000\nAktiekapital: 2 000 000\nVerkst dir: Hans Lindberg\nEtableringsår: 1961.",
    "structured": {
        "1": {
            "company_name": "TIVOLIM AB",
            "pnr": "21137",
            "address": "Malmö, Stora Nyg 21.",
            "phone_number": "040-1297 10,12 97 11",
            "bank_details": {
                "bankgiro": "87-5536",
                "postgiro": "148969"
            },
            "activity": "Ensamförsäljare för AB Tivokemi",
            "capital": 100000,
            "key_personnel": [
                {
                    "name": "Verkst din H Homann",
                    "position": "Verkställande direktör"
                }
            ],
            "establishment_year": 1947
        },
        "2": {
            "company_name": "NÄSSJÖ VADDFABRIKER, AB",
            "pnr": "571 00",
            "address": "Nässjö, Brog 12. Box 80.",
            "phone_number": "0380-18140",
            "bank_details": {
                "bankgiro": "425-9160",
                "postgiro": "7831-1"
            },
            "activity": "Tillverkar vadd av alla slag",
            "capital": 300000,
            "key_personnel": [
                {
                    "name": "Verkst dir: Birger Fritz",
                    "position": "Verkställande direktör"
                }
            ],
            "establishment_year": 1886
        },
        "3": {
            "company_name": "NÄSSJÖ VATTENGLASFABRIK, AB",
            "pnr": "57100",
            "address": "Nässjö, Storg 13.",
            "phone_number": "0380-107 55",
            "bank_details": {
                "bankgiro": "14-3656",
                "postgiro": "96871"
            },
            "activity": "Tillverkar kali- o natronvattenglas",
            "annual_turnover": "700000",
            "capital": 30000,
            "key_personnel": [
                {
                    "name": "Verkst dir: Melvin Gråberg",
                    "position": "Verkställande direktör"
                }
            ],
            "establishment_year": 1935
        },
        "4": {
            "company_name": "FIGEHOLMS BRUK, AB",
            "pnr": "570 92",
            "address": "Figeholm.",
            "phone_number": "0491-312 00",
            "bank_details": {
                "bankgiro": "450-6069",
                "postgiro": "165362-5"
            },
            "activity": "Tillverkar elektro-presspan, polyespan o polymex",
            "employees": 165,
            "annual_turnover": 13000000,
            "capital": 500000,
            "key_personnel": [
                {
                    "name": "Verkst dir. Nils Biesért",
                    "position": "Verkställande direktör"
                }
            ],
            "establishment_year": 1931
        },
        "5": {
            "company_name": "FOL",
            "activity": "Försäkringsbolag"
        },
        "6": {
            "company_name": "FOLKTRYCK AB",
            "pnr": "631 05",
            "address": "Eskilstuna, Box 368. Rade-macherg 29.",
            "phone_number": "016-13 72 70",
            "bank_details": {
                "bankgiro": "5304-1003",
                "postgiro": "10720-1"
            },
            "activity": "Utger tidningen Folket",
            "employees": 190,
            "annual_turnover": 14000000,
            "capital": 1290000,
            "key_personnel": [
                {
                    "name": "Verkst dir. Mose Mallsten",
                    "position": "Verkställande direktör"
                }
            ],
            "establishment_year": 1905
        },
        "7": {
            "company_name": "SAAB-ANA AKTIEBOLAG",
            "pnr": "61101",
            "address": "Nyköping 1, Båthamnsv.",
            "phone_number": "0155-807 00",
            "bank_details": {
                "bankgiro": "160-3752",
                "postgiro": "135265-7"
            },
            "activity": "Bolaget är representant för bl a SAAB-SCANIA Aktiebolag",
            "employees": 806,
            "annual_turnover": 574500000,
            "capital": 36000000,
            "key_personnel": [
                {
                    "name": "Verkst dir: Torsten Arnheim",
                    "position": "Verkställande direktör"
                }
            ],
            "establishment_year": 1937
        }
    }
}