{
    "original": "FOL\n\nVarunamn: Flymo\nAktiekapital: 4 000 000\nEtableringsår: 1962.\n\nFLÄKT. &amp; REGULATOR.\nSERVICE. AB\n\nPnr 123 57\n\nFarsta, Piprensarv 7. Tel\n08-941504. Bankgiro 53-2579.\nPostgiro 471148\n\nVerksamhet: Tillverkar o säljer\nventilations- o kylanläggningar.\nService av ventilations-, kyl- o\nvärmeanläggningar\nVerkst dir: Conny Porslund\nEtableringsår: 1951\nOmbildat till aktiebolag 1963.\n\nFMR VERKSTAD AB\n\nPnr 311 00\n\nFalkenberg, Box 121. Hamnv. Tel\n0346-14145. Bankgiro 36-1455.\nPostgiro 80239\n\nVerksamhet: Legotillverkning,\ngrövre plåfc- o maskinarbeten\nAntal anställda: 50\nÅrsomsättning: 4 000 000\nAktiekapital: 50 000\nVerkst dir: Stig Gustafsson\nProd-chef: Ing Algot Haglund\nEtableringsår: 1919\nOmbildat till aktiebolag 1961.\n\nFOCUS INSTRUMENT .\nKUGGTEKNIK AB\n\nPnr 12651\n\nHägersten, Styrbjörnsv 11. Tel\n08-19 5200. Bankgiro 825-8600.\nPostgiro 540301-9\n\nVerksamhet: Finmekanisk verkstad\nElektronikavdelning: 175 00\nJakobsberg, Vasav 53. Tel 0758-121 00\nAvdelningskontor, bokföring:\n793 00 Leksand, Box 3010. Tel\n0247-122 85\nAntal anställda: 5\nÅrsomsättning: 350 000\nAktiekapital: 30 000\nVerkst dir: Ing Henning Knutz\nEtableringsår: 1957.\n\nDENTATUS, AB\n\nPnr 126 53\n\nHägersten, Jakobsdalsv 14-16.\nTel 08-45 27 75. Bankgiro\n569-8147. Postgiro 56412-0. Tga\nDen-tatus, Stockholm\nVerksamhet: Tillverkar\ndental-produkter\n\nVarunamn: Dentatus\nAntal anställda: 70\nÅrsomsättning: 3 500 000\n\nAktiekapital: 1200 000\nVerkst dir: Sten Ekberg\nEtableringsår: 1930.\n\nCYKLOP AB\n\nPnr 16111\n\nBromma 11, Ulvsundav 152-156.\n\nBox 11014. Tel 08-25 25 20.\nBankgiro 700-0359. Postgiro 54475-9.\nTga Cyklop. Telex 17367\nVerksamhet: Stålbandsemballering.\nAutomater, bandningsapparater\nAntal anställda: 32\nÅrsomsättning: 14 000 000\nAktiekapital: 300 000\nVerkst dir: Dr Gert Reidemeister\nEtableringsår: 1932.\n\nERC\n\nEtableringsår: 1925\nDotterbolag: Elektromek AB\nGustav Eriksson, Huddinge.\n\nERCO LÄKEMEDEL AB\n\nPnr 114 53\n\nStockholm, Grevg 34. Tel\n08-63 09 1 0. Bankgiro 732-0575. Pos1&gt;\ngiro 54892-5. Tga Ercopharm\nVerksamhet: Tillverkar o säljer\nfarmaceutiska specialiteter\nAntal anställda: 200\nÅrsomsättning: 25 000 000\nAktiekapital: 100 000\nVerkst din Apotekare Erik\nBjä-ringer\n\nEtableringsår: 1949.\n\nRYDBOHOLMS AB\n\nPnr 510 32\n\nViskafors 3, Fack. Rydboholm. Tel\n033-933 00. Bankgiro 839-3621.\nPostgiro 7714-9. Tga\nRydboholms-bolag, Borås.\nTelex 36009 RYDTEX S\nVerksamhet: Tillverkar garn o\nvävnader av bomull o syntetfiber.\nTrikåvaror. Säljer\nheminredningskonfektion, såsom gardiner,\nsängöverkast m m\nAntal anstäUda: 700\nÅrsomsättning: 60 000 000\nAktiekapital: 9 000 000\nVerkst dir: Arne Erikson\nEtableringsån 1834.\n\nHAGELBERG &amp; CO AB,CW\n\nPnr 414 58\n\nGöteborg, Skärgårdsg 4. Tel\n031-24 7 0 70. Bankgiro 51-2915.\nPostgiro 12275\n\nVerksamhet: Tillverkning o grossist\nav bageriråvaror\nAntal anstäUda: 5\nÅrsomsättning: 450 000\nAktiekapital: 65 000\nVerkst dir: Lennart Hagelberg\nEtableringsår: 1908.\n\nHAGELIN &amp; CO, MASKIN AB\nK W\n\nPnr 71401\n\nKopparberg 1, Box 39. Tel\n0580-114 75. Tga Maskinhaco\nVerksamhet: Tillverkar o säljer\nlänkrullar, hjul o transportvagnar\nVarunamn: Haco\nEtableringsår: 1939.\n\nTOMSCEMENTVAROR\n\nPnr 430 33\n\nFjärås, Postl 241. Tel\n0300-40207, 403 62. Bankgiro 42-6483.\nPostgiro 145966\n\nVerksamhet: Tillverkar o säljer\nbetongvaror, jord o grus\nAntal anställda: 16\n\nÅrsomsättning: 1500 000\nChef: Ake Johansson\nEtableringsår: 1957.\n\nBORÅS SYFABRIK, AB\n\nPnr 501 06\n\nBorås 1, Box 332. Katrinedalsg 15.\nTel 033-114275, 121019.\nBankgiro 531-2426. Postgiro 99831-0\nVerksamhet: Tillverkar\narbetskläder för herr o dam\nAktiekapital: 200 000\nEtableringsår: 1944.\n\nWATTHOLMA BRUKS AB\n\nPnr 740 33\n\nVattholma. Tel 018-350100.\nBankgiro 563-4027. Postgiro 109-9.\nTga Bruket\n\nVerksamhet: Mek verkstad, gjuteri\n(spiraltrappor etc) (Bedrives i\nAllmänna Brandredskapsaffärens\nAB regi)\n\nAktiekapital: 100 000\n\nVerkst dir: Civiling Erik Bergström\n\nEtableringsår: 1941.\n\nBEV\n\ncellutrustningar, manuella o\nautomatiska kyl- o frysportar, kyl- o\nfrysrumsdörrar samt olika typer av\nindustriportar\n\nVarunamn: Besam Entré-Matic\nAntal anställda: 60\nÅrsomsättning: 5 000 000\nAktiekapital: 300000\nVerkst dir: Bertil Samuelsson\nFörsäljn-chef: Lars Andersson\nKonstr-chef: Pauli Pedersen\nEtableringsår: 1962.\n\nBESKOW &amp; NILSEN\nARKITEKTKONTOR AB\n\nPnr 803 54\n\nGävle, Byggmästarg 5 A. Tel\n026-1805 35, 18 05 36. Bankgiro\n404-2875. Postgiro 226036-2\nVerksamhet: Stads- o\nbyggnadsplanering, husprojektering,\nbesiktningar o kontroll\nAntal anställda: 5\nÅrsomsättning: 500 000\nAktiekapital: 5 000\nEtableringsår: 1964.",
    "structured": {
        "1": {
            "company_name": "FLÄKT. & REGULATOR. SERVICE. AB",
            "activity": "Tillverkar o säljer ventilations- o kylanläggningar. Service av ventilations-, kyl- o värmeanläggningar",
            "establishment_year": 1951
        },
        "2": {
            "company_name": "FMR VERKSTAD AB",
            "activity": "Legotillverkning, grövre plåfc- o maskinarbeten",
            "employees": 50,
            "annual_turnover": 4000000,
            "capital": 50000,
            "key_personnel": [
                {
                    "name": "Stig Gustafsson",
                    "position": "Verkst dir"
                },
                {
                    "name": "Ing Algot Haglund",
                    "position": "Prod-chef"
                }
            ],
            "establishment_year": 1919
        },
        "3": {
            "company_name": "FOCUS INSTRUMENT . KUGGTEKNIK AB",
            "activity": "Finmekanisk verkstad",
            "address": "Hägersten, Styrbjörnsv 11",
            "phone_number": "08-19 5200",
            "employees": 5,
            "annual_turnover": 350000,
            "capital": 30000,
            "key_personnel": [
                {
                    "name": "Ing Henning Knutz",
                    "position": "Verkst dir"
                }
            ],
            "establishment_year": 1957
        },
        "4": {
            "company_name": "DENTATUS, AB",
            "activity": "Tillverkar dental-produkter",
            "employees": 70,
            "annual_turnover": 3500000,
            "capital": 1200000,
            "key_personnel": [
                {
                    "name": "Sten Ekberg",
                    "position": "Verkst dir"
                }
            ],
            "establishment_year": 1930
        },
        "5": {
            "company_name": "CYKLOP AB",
            "activity": "Stålbandsemballering. Automater, bandningsapparater",
            "address": "Bromma 11, Ulvsundav 152-156. Box 11014",
            "phone_number": "08-25 25 20",
            "employees": 32,
            "annual_turnover": 14000000,
            "capital": 300000,
            "key_personnel": [
                {
                    "name": "Dr Gert Reidemeister",
                    "position": "Verkst dir"
                }
            ],
            "establishment_year": 1932
        },
        "6": {
            "company_name": "ERCO LÄKEMEDEL AB",
            "activity": "Tillverkar o säljer farmaceutiska specialiteter",
            "address": "Stockholm, Grevg 34",
            "phone_number": "08-63 09 1 0",
            "employees": 200,
            "annual_turnover": 25000000,
            "capital": 100000,
            "key_personnel": [
                {
                    "name": "Apotekare Erik Bjä-ringer",
                    "position": "Verkst din"
                }
            ],
            "establishment_year": 1949
        },
        "7": {
            "company_name": "RYDBOHOLMS AB",
            "activity": "Tillverkar garn o vävnader av bomull o syntetfiber. Trikåvaror. Säljer heminredningskonfektion, såsom gardiner, sängöverkast m m",
            "address": "Viskafors 3, Fack. Rydboholm",
            "phone_number": "033-933 00",
            "employees": 700,
            "annual_turnover": 60000000,
            "capital": 9000000,
            "key_personnel": [
                {
                    "name": "Arne Erikson",
                    "position": "Verkst dir"
                }
            ],
            "establishment_year": 1834
        },
        "8": {
            "company_name": "HAGELBERG & CO AB,CW",
            "activity": "Tillverkning o grossist av bageriråvaror",
            "address": "Göteborg, Skärgårdsg 4",
            "phone_number": "031-24 7 0 70",
            "employees": 5,
            "annual_turnover": 450000,
            "capital": 65000,
            "key_personnel": [
                {
                    "name": "Lennart Hagelberg",
                    "position": "Verkst dir"
                }
            ],
            "establishment_year": 1908
        },
        "9": {
            "company_name": "HAGELIN & CO, MASKIN AB K W",
            "activity": "Tillverkar o säljer länkrullar, hjul o transportvagnar",
            "address": "Kopparberg 1, Box 39",
            "phone_number": "0580-114 75",
            "establishment_year": 1939
        },
        "10": {
            "company_name": "TOMSCEMENTVAROR",
            "activity": "Tillverkar o säljer betongvaror, jord o grus",
            "address": "Fjärås, Postl 241",
            "phone_number": "0300-40207, 403 62",
            "employees": 16,
            "annual_turnover": 1500000,
            "key_personnel": [
                {
                    "name": "Ake Johansson",
                    "position": "Chef"
                }
            ],
            "establishment_year": 1957
        },
        "11": {
            "company_name": "BORÅS SYFABRIK, AB",
            "activity": "Tillverkar arbetskläder för herr o dam",
            "address": "Borås 1, Box 332. Katrinedalsg 15",
            "phone_number": "033-114275, 121019",
            "establishment_year": 1944
        },
        "12": {
            "company_name": "WATTHOLMA BRUKS AB",
            "activity": "Mek verkstad, gjuteri (spiraltrappor etc) (Bedrives i Allmänna Brandredskapsaffärens AB regi)",
            "address": "Vattholma",
            "phone_number": "018-350100",
            "capital": 100000,
            "key_personnel": [
                {
                    "name": "Civiling Erik Bergström",
                    "position": "Verkst dir"
                }
            ],
            "establishment_year": 1941
        },
        "13": {
            "company_name": "BEV",
            "activity": "Tillverkar cellutrustningar, manuella o automatiska kyl- o frysportar, kyl- o frysrumsdörrar samt olika typer av industriportar",
            "address": "Unknown",
            "employees": 60,
            "annual_turnover": 5000000,
            "capital": 300000,
            "key_personnel": [
                {
                    "name": "Bertil Samuelsson",
                    "position": "Verkst dir"
                },
                {
                    "name": "Lars Andersson",
                    "position": "Försäljn-chef"
                },
                {
                    "name": "Pauli Pedersen",
                    "position": "Konstr-chef"
                }
            ],
            "establishment_year": 1962
        },
        "14": {
            "company_name": "BESKOW & NILSEN ARKITEKTKONTOR AB",
            "activity": "Stads- o byggnadsplanering, husprojektering, besiktningar o kontroll",
            "address": "Gävle, Byggmästarg 5 A",
            "phone_number": "026-1805 35, 18 05 36",
            "employees": 5,
            "annual_turnover": 500000,
            "capital": 5000,
            "establishment_year": 1964
        }
    }
}