{
    "original": "maskincrona, ab\n\nPnr 104 3 2\n\nStockholm 19, Box 19026. Tulegl6\nTel 08-23 22 00. Bankgiro 73-0417.\nPostgiro 194232. Tga Maskincrona\nVerksamhet: Försäljer Hazet,\nMül-ler ultra kullager, Grasso, Metabo\nVarunamn: DC, Grasso, Hazet,\nHunger, Metabo, Müller, Zanchi\nVerkst dir: Edvard Ernstberger\nEtableringsår: 1943.\n\nIBM SVENSKA AB\n\nPnr 104 35\n\nStockholm 23, Sveav 149. Box\n23006. Tel 08-24 50 60. Tga\nInbus-mach\n\nVerksamhet: Tillverkar\ndatabehandling sutrustning samt hålkort\nAktiekapital: 70 000 000\nAntal anställda: 3 000\nTillverkningsvärde: 200 000 000\nVerkst dir: Arne Lundqvist\nEtableringsår. 1928.\n\nICA FRUKT och GRÖNSAKER\nAB\n\nPnr 251 03\n\nHelsingborg 1, Box 212.\nFäktmäs-tareg 5. Tel 042-622 80. Bankgiro\n652-8848. Postgiro 290209-6. Tga\nICA-HBG. Telex 72350\nVerksamhet: Köper o säljer frukt\no grönsaker i parti\nAntal anställda: 125\nÅrsomsättning: 85 000 000\nAktiekapital: 1100 000\nVerkst dir: Sven Kihlstedt\nEtableringsår 1942.\n\nICA INKOPSCENTRALERNAS\nAB\n\nPnr 102 33\n\nStockholm 6, Odeng 69. Box 6187.\nTel 08-22 65 80. Postgiro 31493.\nTelex 1435. Tga Icacentral\nVerksamhet: Centralorganisation\nför ICA-företagen\nAktiekapital: 3 000 000\nVerkst dir Stig Svensson\nEtableringsår: 1939.\n\nICAB INTERNATIONAL\nCONSTRUCTING AB\n\nPnr 98101\n\nKiruna 1, Box 99. Tel 0980-186 20.\nBankgiro 33-3816. Postgiro 487800.\nTelex 32546. Tga Incob\nVerksamhet: Fordonsteknik.\nKonstruktionsbyrå\n\nAvdelningskontor: 21130 Malmö,\nExercisg 2 A. Tel 040-714 40\nAntal anställda: 20\nÅrsomsättning: 1200000\nAktiekapital: 6 000\nStyrelse: Ing Torsten Henriksson,\ndir Ragnar Muotka, ing Lars\nLandeborg, dlr Bo Sandström\nVeikst dir: Ing Torsten Henriksson\nÖvriga chefer: Dir Ragnar Muotka,\ning Lars Landeborg\nEtableringsår: 1966.\n\nFRIDMAN, K G\n\nPnr 652 24\n\nKarlstad, Herrgårdsg 3. Tel\n054-115115. Bankgiro 828-9985.\nPostgiro 170324-8. Tga Fridmanson.\nTelex 66102 FRIEMAN S\nVerksamhet: Schweiziska\nagenturen aluminiumhalvfabrikat,\npreci-sionssvarvade detaljer, små\nkullager, silverlod\n\nVarunamn: Delta, Menziken, RMB\nÄgare o chef: Bengt Fridman\nEtableringsår: 1926.\n\nSTAR FÖNSTER AB\n\nPnr 70106\n\nÖrebro 1, Adolfsbergsv 4. Box 483.\nTel 019-13 0100. Bankgiro 41-1584.\nPostgiro 544940. Tga Window.\nTelex 73335\n\nVerksamhet: Tillverkning (vid\nfabriker i Örebro o Vimmerby) o\nförsäljning av standard- o\nspecialfönster, fönsterdörrar,\nfönsterelement, fasadelement etc, inkl\nmontage på byggplats\nFörsäljningskontor för\nbostadsfönster o fabrik: 598 00 Vimmerby, Box\n8. Tel 0492-131 50. Tga Starwindow\nVarunamn: Starfönster\nAntal anställda: 425\nÅrsomsättning: 45 000 000\nStyrelse: Dir Rolf Deinoff, dir Ove\nSundberg, dir Sverker Ovesson\nVerkst dir: Sverker Ovesson\nEtableringsår: 1969\nFöretaget ingår i STAB:s\nByggmaterialdivision.\n\nSTARKS BORSTFABRIK, AB M\n\nPnr 355 90\n\nVäxjö, Kalvsvik. Tel 047 0-780 08.\nBankgiro 292-7010. Postgiro\n370227-1\n\nVerksamhet: Tillverkar borstar o\npenslar för industri o hushållsbruk\nAntal anstäUda: 8\nÅrsomsättning: 600 000\nVerkst dir: Erik Stark\nEtableringsår: 1903\nOmbildat till aktiebolag 1963.\n\nSTARPRODUKTER AB\n\nPnr 53101\n\nLidköping 1, Sockerbruksg. Box 89.\nTel 0510-222 45. Bankgiro 84-1440.\nPostgiro 613096. Telex 5049. Tga\nStar\n\nVerksamhet: Säljer köks- o\ngarderobskåp\n\nAntal anstäUda: 400\n\nÅrsomsättning: 30 000 000\nAktiekapital: 400 000\nVerkst dir: Sverker Ovesson.\n\nSTATENS\nLANTBRUKSKEMISKA LABORATORIUM SLL\n\nPnr 750 07\n\nUppsala 7, Box 7054. Vallv 1,\nUltuna. Tel 018-10 20 20. Postgiro\n59813-6\n\nVerksamhet: Analyser,\nhuvudsakligen kemiska på\nlantbruksprodukter, livsmedëlsråvaror, fodermedel,\nnaturprodukter, naturgödsel,\nbiologiskt siam, avfall, handelsgödsel,\njordförbättringsmedel, j ord o vatten.\nAvser huvudsakUgen innehåll av\nnäringsämnen för människor, djur,\nväxter men även skadliga ämnen i\nvissa fall\n\nAntal anstäUda: 60\nÅrsomsättning: 3 000 000\nChef: Agronom dr Sigvard Ekelund\nEtableringsår: 1857.\n\nSTATENS\nPROVNINGSANSTALT\n\nPnr 11486\n\nStockholm 5, Drottning Kristinas v\n31. Box 5608. Tel 08-24 80 60\nVerksamhet: Provningar o\nundersökningar av material o konstruktioner\nAntal anstäUda: 240\nChef: Generaldir Ove Norell\nEtableringsår: 1920.\n\nSTATENS SKOGS.\nINDUSTRIER, AB\n\nPnr 105 22\n\nStockholm, Sveav 59. Tel\n08-221140. Postgiro 179243-1. Tga\nForestry. Telex 19960, 19961\n\nAktiebolaget\nStatens Skogsindustrier\n\nVerksamhet: Skogsindustrien\nproduktion: blekt o oblekt\nsulfatmassa, kraftpapper o kraftliner,\nträkemiska produkter, hårda\nträfiberskivor (wallboard), sågade o\nhyvlade trävaror, snickerier\nVarunamn: Royal\nAntal anställda: 3 700\nÅrsomsättning: 475 000 000\nAktiekapital: 260 000 000\nStyrelseordf: Bankdir Carl-Henrik\nNordlander\n\nVerkst dir: Olov Rynell\nV verkst dir. Ingvar Lindholm\nFörsäljn-dir: Gunnar Englund.\n\nSTATHMOS.LINDELL AB\n\nPnr 550 05\n\nJönköping 5, Fack.Tel 036-11 85 50.\nPostgiro 11492. Telex 70147\nVerksamhet: Tillverkar alla slag\nav vågar för handel, industri o\nsamfärdsel\n\nFilialer: 632 29 Eskilstuna, Hejarg\n9. Tel 016-119200, 119201\n570 22 Forserum. Tel 0380-200 15\n400 51 Göteborg, Hundraårsg 34.\nTel 031-48 00 25\n\n21158 Malmö, Falsterbog 1. Tel\n040-707 10\n\n112 65 Stockholm, Badstrandsv\n20-26. Tel 08-56 13 12, 56 13 13\n\n852 58 Sundsvall, Västra v 122.\nTel 060-639 00\nVarunamn: Stathmos-Lindell\nAntal anstäUda: 400\nÅrsomsättning: 25 000 000\nAktiekepital: 6500 000\nStyrelse: Dir Gunnar Ekman, disp\nFranz Hartmann (ordf), dir Harry\nHjalmarson, dir Sigurd Ljungcrantz\nVerkst dir: Folke Söderström\nEtableringsår: 1868\nOmbildat till aktiebolag 1902.\n\nSTATSFURETAG AB\n\nPnr 102 51\n\nStockholm 27, Box 27075. Linnég\n78-80. Tel 08-63 07 00, 67 04 50.\nBankgiro 653-8243. Postgiro\n3873-3\t»\n\nVerksamhet: Äger o förvaltar\naktierna i 28 statliga företag. De\nsex största företagen i gruppen är\nLKAB, Svenska Tobaks AB,\nStatens Skogsindustrier, Norrbottens\nJärnverk, Uddevallavarvet o\nSveriges Centrala Restaurang AB.\nSom moderbolag i koncernen har\nföretaget till uppgift att ånge målen\nför gruppens företag, tillsätta\nstyrelser i företagen, underlätta för\ndem att skaffa nödvändiga resurser\nför verksamheten, följa de enskilda\nföretagens planering, kontrollera\natt uppställda mål infrias o vidta\nkorrigerande åtgärder vid bristande\nmåluppfyllelse\n\nAntal anstäUda: 30 (30 000 gruppen)\nAktiekapital: 1400 000 000\nÅrsomsättning: 3 500 000 000\n(koncernen)\n\nStyrelse: Statssekreterare\nSven-Göran Olhede (ordf), dir Rune\nJohansson (v ordf), dir Gunnar\nSvärd, ordf Arne Geijer, generaldir\nErik Grafström, dir Harry\nHjalmarson, dir Sigurd Ljungcrantz, dir\nKarl-Erik Nilsson, Lars Sjöborg\n(suppl), Nore Sundberg (suppl)\nVerkst dir: Gunnar Svärd\nEtableringsår: 1970.\n\nNYHOLMS METALL AB\n\nPnr 560 10\n\nSkillingaryd. Tel 0370-750 90.\nBankgiro 981-7933. Postgiro\n146962-6\n\nVerksamhet: Lättare\nmetallmanufakturverk, (finmekanisk verkstad).\nMöbellås o möbelbeslag.\nAutomat-svarvning\n\nAntal anställda: 30\nÅrsomsättning: 3 000 000\nAktiekapital: 60 000\nVerkst dir: Arvid Carlsson\nEtableringsår: 1936.\n\nSTRÄNGBETONG, AB\n\nPnr 102 73\n\nStockholm 9, Mejeriv 4. Box 9205.\nTel 08-18 83 00. Bankgiro 477-3362.\nPostgiro 454742-8. Tga\nSträngbetong\n\nVerksamhet: Fabrikation o montage\nav element i betong\nAntal anställda: 1300\nÅrsomsättning: 120 000 000\nAktiekapital: 10 000 000\nVerkst dir: Henning Collborg\nEtableringsår: 1942.\n\nVRETSTORPS ÅNGSÅG, AB\n\nPnr 690 50\n\nVretstorp, Box 58. Tel 0582-604 65.\nBankgiro 604-5215. Postgiro\n98454-2\n\nVerksamhet: Tillverkar sågade\nträvaror\n\nAntal anställda: 39\nÅrsomsättning: 4 000 000\nAktiekapital: 400 000\nVeikst dir: Gösta Lindholm\n(Älmhult)\n\nEtableringsår: 1918.\n\nBORJESSON &amp; CO, AB A\n\nPnr 235 00\n\nVellinge, Box 31. Börjesg. Tel\n040-42 00 18,42 03 28. Bankgiro 66-6253.\nPostgiro 138820. Tga Börjessons\nVerksamhet: Säljer trävaror,\nbyggmaterial, järnvaror m m\nAntal anställda: 15\nAktiekapital: 60000\nVerkst dir: Börje Börjesson\nEtableringsår: 1888.\n\nWISSINGS INDUSTRI AB\n\nPnr 596 00\n\nSkenninge, Axstadsv 1. Box 20.\nTel 0142-403 90, 407 90. Bankgiro\n130-0326. Postgiro 99353-5\nVerksamhet: Tillverkar möbler,\nTV o radio-lådor, massartiklar i\nträ\n\nAntal anställda: 33\nAktiekapital: 80000\nVerkst din Arne Wissing\nEtableringsån 1951.\n\nEKB-PRODUKTER, AB\n\nPnr 121 04\n\nJohanneshov 4, Box 437. Bergsrådsv\n83. Tel 08-39 02 40. Bankgiro\n74-4791. Postgiro 606350.\nTgaEkobe-produkt. Telex 10722\nVerksamhet: Importagentur.\nElektroteknik\n\nÅrsomsättning: 2 000000\nAktiekapital: 80 000\nVerkst dir: Ing Börje Bengtsson\nEtableringsår: 1959.",
    "structured": {
        "1": {
            "company_name": "MASKINCRONA, AB",
            "address": "Stockholm 19, Box 19026, Tulegl6",
            "phone_number": "08-23 22 00",
            "bank_details": {
                "bankgiro": "73-0417",
                "postgiro": "194232"
            },
            "activity": "Försäljer Hazet, Mül-ler ultra kullager, Grasso, Metabo",
            "establishment_year": 1943
        },
        "2": {
            "company_name": "IBM SVENSKA AB",
            "address": "Stockholm 23, Sveav 149, Box 23006",
            "phone_number": "08-24 50 60",
            "activity": "Tillverkar databehandling sutrustning samt hålkort",
            "capital": 70000000,
            "employees": 3000,
            "annual_turnover": 200000000,
            "establishment_year": 1928
        },
        "3": {
            "company_name": "ICA FRUKT och GRÖNSAKER AB",
            "address": "Helsingborg 1, Box 212, Fäktmäs-tareg 5",
            "phone_number": "042-622 80",
            "bank_details": {
                "bankgiro": "652-8848",
                "postgiro": "290209-6"
            },
            "activity": "Köper o säljer frukt o grönsaker i parti",
            "employees": 125,
            "annual_turnover": 85000000,
            "capital": 1100000,
            "establishment_year": 1942
        },
        "4": {
            "company_name": "ICA INKOPSCENTRALERNAS AB",
            "address": "Stockholm 6, Odeng 69, Box 6187",
            "phone_number": "08-22 65 80",
            "bank_details": {
                "postgiro": "31493"
            },
            "activity": "Centralorganisation för ICA-företagen",
            "capital": 3000000,
            "establishment_year": 1939
        },
        "5": {
            "company_name": "ICAB INTERNATIONAL CONSTRUCTING AB",
            "address": "Kiruna 1, Box 99",
            "phone_number": "0980-186 20",
            "bank_details": {
                "bankgiro": "33-3816",
                "postgiro": "487800"
            },
            "activity": "Fordonsteknik. Konstruktionsbyrå",
            "employees": 20,
            "annual_turnover": 1200000,
            "capital": 6000,
            "key_personnel": [
                {
                    "name": "Ing Torsten Henriksson",
                    "position": "Styrelse"
                },
                {
                    "name": "Ragnar Muotka",
                    "position": "dir"
                },
                {
                    "name": "Lars Landeborg",
                    "position": "ing"
                }
            ],
            "establishment_year": "1966"
        },
        "6": {
            "company_name": "FRIDMAN, K G",
            "address": "Karlstad, Herrgårdsg 3",
            "phone_number": "054-115115",
            "bank_details": {
                "bankgiro": "828-9985",
                "postgiro": "170324-8"
            },
            "activity": "Schweiziska agenturen aluminiumhalvfabrikat, preci-sionssvarvade detaljer, små kullager, silverlod",
            "establishment_year": 1926
        },
        "7": {
            "company_name": "STAR FÖNSTER AB",
            "address": "Örebro 1, Adolfsbergsv 4, Box 483",
            "phone_number": "019-13 0100",
            "bank_details": {
                "bankgiro": "41-1584",
                "postgiro": "544940"
            },
            "activity": "Tillverkning (vid fabriker i Örebro o Vimmerby) o försäljning av standard- o specialfönster, fönsterdörrar, fönsterelement, fasadelement etc, inkl montage på byggplats",
            "employees": 425,
            "annual_turnover": 45000000,
            "key_personnel": [
                {
                    "name": "Rolf Deinoff",
                    "position": "dir"
                },
                {
                    "name": "Ove Sundberg",
                    "position": "dir"
                },
                {
                    "name": "Sverker Ovesson",
                    "position": "verkst dir"
                }
            ],
            "establishment_year": 1969
        },
        "8": {
            "company_name": "STARKS BORSTFABRIK, AB M",
            "address": "Växjö, Kalvsvik",
            "phone_number": "047 0-780 08",
            "bank_details": {
                "bankgiro": "292-7010",
                "postgiro": "370227-1"
            },
            "activity": "Tillverkar borstar o penslar för industri o hushållsbruk",
            "employees": 8,
            "annual_turnover": 600000,
            "establishment_year": 1903
        },
        "9": {
            "company_name": "STARPRODUKTER AB",
            "address": "Lidköping 1, Sockerbruksg. Box 89",
            "phone_number": "0510-222 45",
            "bank_details": {
                "bankgiro": "84-1440",
                "postgiro": "613096"
            },
            "activity": "Säljer köks- o garderobskåp",
            "employees": 400,
            "annual_turnover": 30000000,
            "capital": 400000,
            "key_personnel": [
                {
                    "name": "Sverker Ovesson",
                    "position": "verkst dir"
                }
            ]
        },
        "10": {
            "company_name": "STATENS LANTBRUKSKEMISKA LABORATORIUM SLL",
            "address": "Uppsala 7, Box 7054, Vallv 1, Ultuna",
            "phone_number": "018-10 20 20",
            "postgiro": "59813-6",
            "activity": "Analyser, huvudsakligen kemiska på lantbruksprodukter"
        },
        "11": {
            "company_name": "STATENS PROVNINGSANSTALT",
            "address": "Stockholm 5, Drottning Kristinas v 31, Box 5608",
            "phone_number": "08-24 80 60",
            "activity": "Provningar o undersökningar av material o konstruktioner"
        },
        "12": {
            "company_name": "STATENS SKOGS. INDUSTRIER, AB",
            "address": "Stockholm, Sveav 59",
            "phone_number": "08-221140",
            "postgiro": "179243-1",
            "activity": "Skogsindustrien produktion: blekt o oblekt sulfatmassa, kraftpapper o kraftliner, träkemiska produkter, hårda träfiberskivor (wallboard), sågade o hyvlade trävaror, snickerier"
        },
        "13": {
            "company_name": "STATHMOS.LINDELL AB",
            "address": "Jönköping 5, Fack",
            "phone_number": "036-11 85 50",
            "postgiro": "11492",
            "activity": "Tillverkar alla slag av vågar för handel, industri o samfärdsel",
            "employees": 400,
            "annual_turnover": 25000000,
            "capital": 6500000,
            "key_personnel": [
                {
                    "name": "Gunnar Ekman",
                    "position": "dir"
                },
                {
                    "name": "Franz Hartmann",
                    "position": "disp"
                },
                {
                    "name": "Harry Hjalmarson",
                    "position": "dir"
                },
                {
                    "name": "Sigurd Ljungcrantz",
                    "position": "dir"
                }
            ],
            "establishment_year": 1868
        },
        "14": {
            "company_name": "STATSFURETAG AB",
            "address": "Stockholm 27, Box 27075, Linnég 78-80",
            "phone_number": "08-63 07 00, 67 04 50",
            "bank_details": {
                "bankgiro": "653-8243",
                "postgiro": "3873-3"
            },
            "activity": "Äger o förvaltar aktierna i 28 statliga företag"
        },
        "15": {
            "company_name": "NYHOLMS METALL AB",
            "address": "Skillingaryd",
            "phone_number": "0370-750 90",
            "bank_details": {
                "bankgiro": "981-7933",
                "postgiro": "146962-6"
            },
            "activity": "Lättare metallmanufakturverk, (finmekanisk verkstad). Möbellås o möbelbeslag. Automat-svarvning",
            "employees": 30,
            "annual_turnover": 3000000,
            "capital": 60000
        },
        "16": {
            "company_name": "STRÄNGBETONG, AB",
            "address": "Stockholm 9, Mejeriv 4, Box 9205",
            "phone_number": "08-18 83 00",
            "bank_details": {
                "bankgiro": "477-3362",
                "postgiro": "454742-8"
            },
            "activity": "Fabrikation o montage av element i betong",
            "employees": 1300,
            "annual_turnover": 120000000,
            "capital": 10000000
        },
        "17": {
            "company_name": "VRETSTORPS ÅNGSÅG, AB",
            "address": "Vretstorp, Box 58",
            "phone_number": "0582-604 65",
            "bank_details": {
                "bankgiro": "604-5215",
                "postgiro": "98454-2"
            },
            "activity": "Tillverkar sågade trävaror",
            "employees": 39,
            "annual_turnover": 4000000,
            "capital": 400000
        },
        "18": {
            "company_name": "BORJESSON & CO, AB A",
            "address": "Vellinge, Box 31, Börjesg",
            "phone_number": "040-42 00 18,42 03 28",
            "bank_details": {
                "bankgiro": "66-6253",
                "postgiro": "138820"
            },
            "activity": "Säljer trävaror, byggmaterial, järnvaror m m",
            "employees": 15,
            "capital": 60000
        },
        "19": {
            "company_name": "WISSINGS INDUSTRI AB",
            "address": "Skenninge, Axstadsv 1, Box 20",
            "phone_number": "0142-403 90, 407 90",
            "bank_details": {
                "bankgiro": "130-0326",
                "postgiro": "99353-5"
            },
            "activity": "Tillverkar möbler, TV o radio-lådor, massartiklar i trä",
            "employees": 33,
            "capital": 80000
        },
        "20": {
            "company_name": "EKB-PRODUKTER, AB",
            "address": "Johanneshov 4, Box 437, Bergsrådsv 83",
            "phone_number": "08-39 02 40",
            "bank_details": {
                "bankgiro": "74-4791",
                "postgiro": "606350"
            },
            "activity": "Importagentur. Elektroteknik",
            "annual_turnover": 2000000,
            "capital": 80000
        }
    }
}