{
    "original": "GRAMERS GUMMI AB\n\nPnr 826 01\n\nSöderhamn 1, Box 64. Vågbro. Tel\n0270-121 70. Bankgiro 789-5063.\nPostgiro 13215-9\nVerksamhet: Tillverkar\nfördämningsmattor o gummimattor\nAntal anställda: 4\nÅrsomsättning: 300 000\nAktiekapital: 10000\nVerkst dir: Olle Grämer\nEtableringsår: 1952.\n\nSTE\n\nStyrelse: Dir W Wredenfors (ordf),\ndisp I Bodegård, dir H Ruter\nVerkst dir: Disp I Bodegård\nEtableringsår: 1930.\n\nSTB AB SVENSKA\nTELEGRAM-BYRÅN\n\nPnr 10513\n\nStockholm, Kungsg 18. Tel\n08-14 2100. Postgiro 927-4. Tga\nTelegrambyrån. Telex 10818\nVerksamhet: Konsulterande i\nmarknadsförings- o reklamfrågor\nByråer: Stockholm, Göteborg,\nMalmö, Helsingborg, Karlstad,\nLinköping, Västerås, Köpenhamn,\nHelsingfors, Oslo\nAntal anställda: 500\nÅrsomsättning: 120 000 000\nAktiekapital: 2 000 000\nVerkst dir: Ekon lic Göran Tamm\nEtableringsån 1867.\n\nSTECE-\n\nAB INDUSTRIFJÄDRAR\n\nPnr 383 00\n\nMönsterås. Tel 049 9-111 20.\nBankgiro 855-6391. Postgiro 250581-6.\nTga Stece. Telex 4983\n\nVerksamhet: Tillverkar o säljer\nmekaniska fjädrar, fjäderbrickor,\ntråd- o bandstålsdetaljer,\nslang-klämmor , låsdetaljer för\nsäkerhetsbälten, bock- o pressverktyg samt\ndiverse mekaniska\nverkstadsarbeten. Rörelsen bedrives i separat\nfjäderfabrik, verktygsfabrik samt\npressverkstad med\nmonteringsavdelning\n\nAntal anställda: 400\nÅrsomsättning: 30 000 000\nAktiekapital: 1 000 000\nStyrelse: Dir Thor Boklund (ordf),\ndir Sten Cederberg, fra Inga\nCederberg\n\nVerkst dir: Sten Cederberg\nEkonomichef: Dir Ake Karlsson\nTekn chef: Dir Nils Wahlström\nEtableringsår: 1944.\n\nÅSUNDENS MATTFABRIK, AB\n\nPnr 523 00\n\nUlricehamn, Fiskareg 3. Box 46.\nTel 0321-100 54. Bankgiro 53-2856.\nPostgiro 7750\n\nVerksamhet: Tillverkar\nnöthårs-mattor. Mattgrossist\nAktiekapital: 60 000\nVerkst dir: Ingemar Linard\nEtableringsår: 1910.\n\nHEDLUNDS TRÄVARU AB\n\nPnr 790 70\n\nFurudal, Box 33. Tel 0258-10200.\nBankgiro 79-5007, 46-4230.\nPostgiro 168396-0. Tga Trahedlund\nVerksamhet: Tillverkar sågade o\nhyvlade trävaror, monteringsfärdiga\nträhus\n\nAntal anställda: 125\nÅrsomsättning: 14 000000\nAktiekapital: 300 000\nVerkst dir Disp Erik Hedlund\nEtableringsår: 1934.\n\nELEKTROUTENSILIER, AB\n\nPnr 180 20\n\nÅkers Runo. Tel 0764-20110.\nBankgiro 238-2802. Postgiro 199071-2.\nTga Elutensilier.\nTelex 10912 LKBOLAG S\nVerksamhet: Försäljning av elektro-\n\nnik o teletekniska komponenter,\nkrymppl as tpro dukter\nAktiekapital: 40 000\nVerkst dir: Lennart Kalb\nEtableringsår: 1944.\n\nANDERBERG,AB L J\n\nPnr 102 21\n\nStockholm 12, Fridhemsg 45. Box\n12029. Tel 08-24 39 65. Bankgiro\n56-3407. Postgiro 3123. Tga\nBonus\n\nVerksamhet: Import o export av\nherrbijouterier, present- o\nekipe-ringsartiklar\nAktiekapital: 200 000\nVerkst dir: Lars-Johan Anderberg\nV verkst dir: Carl-Lennart Anderberg\nEtableringsår: 1903\nOmbildat till aktiebolag 1921.\n\nANDERS COMMERCE AB\n\nPnr 753 29\n\nUppsala, Sankt Persg 31. Tel\n018-14 99 00. Postgiro 379086\nVerksamhet: Säljer textil- o\nhus-gerådsvaror\nAntal anställda: 10\nÅrsomsättning: 1100 000\nAktiekapital: 25 000\nVerkst dir: R Granvik\nEtableringsår: 1954.\n\nCONTINENTAL IMPORT, AB\n\nPnr 117 23\n\nStockholm, Brännkyrkag 60. Tel\n08-84 04 35. Bankgiro 564-6856.\nPostgiro 156850-0. Tga Contimo.\nTelex 19368 FRIGAL S\nVerksamhet: Säljer sportartiklar.\nExport o import\nAktiekapital: 30 000\nVerkst dir: Lennart Lundström\nEtableringsår: 1921.\n\nARVO-INDUSTRIN AB\n\nPnr 21231\n\nMalmö, Sallerupsv 227. Tel\n040-49 14 80. Bankgiro 64-2908.\nPostgiro 38055\n\nVerksamhet: Utför formsprutning\nav termoplaster\nAntal anställda: 7\nÅrsomsättning: 250 000\nAktiekapital: 25 000\nVerkst dir: Disp Bror Anderson\nEtableringsår: 1947.\n\nCENTRAVA, AB\n\nPnr 103 40\n\nStockholm 40, Fack. Sveav 9-11.\nTel 23 83 80, riks 08-23 26 50. Tga\nUnilever. Telex 1332 EXPEDO S\nVerksamhet: Tillverkar o säljer\nkemisk-tekniska produkter\nAntal anställda: 1515\nÅrsomsättning: 338 800 000\n■Aktiekapital: 28 000 000\nVerkst dir: Oscar Strugstad.\n\nCENTRIFUGALPLAST, AB\n\nPnr 85102\n\nSundsvall 1, Esplanaden 2. Box 85.\nTel 060-1130 90, 15 64 53\nVerksamhet: Konstruktioner i\nplastsandwich, dörrar av olika slag,\nav-sugningskåpor över filter,\nmanskapsbodar o karosser. Vidare\nfläktar, rör o rördelar i härdplast\nPlastfabrik: Myrnäs, Ankarsvik,\nAlnö. Tel 060-873 34, 870 29\nBergeforsen, Timrå. Tel\n060-798 80, 798 43\nAktiekapital: 100 000\nVerkst dir: Bertil Ericsson\nEtableringsår: 1960.\n\nSAHLINS KONFEKTIONS AB\n\nPnr 24100\n\nEslöv, Kan alg 26. Box 60. Tel\n0413-132 30. Postgiro 84442-3. Tga\nSahlins\n\nVerksamhet: Tillverkar kappor,\ndräkter o jackor för flickor o damer\nAntal anstäUda: 230\nÅrsomsättning: 7 000 000\nAktiekapital: 300000\nVerkst dir: Börje Lernkvist\nEtableringsår: 1858.",
    "structured": {
        "1": {
            "company_name": "GRAMERS GUMMI AB",
            "pnr": "826 01",
            "address": "Söderhamn 1, Box 64. Vågbro",
            "phone_number": "0270-121 70",
            "bank_details": {
                "bankgiro": "789-5063",
                "postgiro": "13215-9"
            },
            "activity": "Tillverkar fördämningsmattor o gummimattor",
            "employees": 4,
            "annual_turnover": 300000,
            "capital": 10000,
            "key_personnel": [
                {
                    "name": "Olle Grämer",
                    "position": "Verkst dir"
                }
            ],
            "establishment_year": 1952
        },
        "2": {
            "company_name": "STB AB SVENSKA TELEGRAM-BYRÅN",
            "pnr": "10513",
            "address": "Stockholm, Kungsg 18",
            "phone_number": "08-14 2100",
            "postgiro": "927-4",
            "activity": "Konsulterande i marknadsförings- o reklamfrågor",
            "employees": 500,
            "annual_turnover": 120000000,
            "capital": 2000000,
            "key_personnel": [
                {
                    "name": "Ekon lic Göran Tamm",
                    "position": "Verkst dir"
                }
            ],
            "establishment_year": 1867
        },
        "3": {
            "company_name": "STECE-AB INDUSTRIFJÄDRAR",
            "pnr": "383 00",
            "address": "Mönsterås",
            "phone_number": "0499-111 20",
            "bank_details": {
                "bankgiro": "855-6391",
                "postgiro": "250581-6"
            },
            "activity": "Tillverkar o säljer mekaniska fjädrar, fjäderbrickor, tråd- o bandstålsdetaljer, slang-klämmor , låsdetaljer för säkerhetsbälten, bock- o pressverktyg samt diverse mekaniska verkstadsarbeten. Rörelsen bedrives i separat fjäderfabrik, verktygsfabrik samt pressverkstad med monteringsavdelning",
            "employees": 400,
            "annual_turnover": 30000000,
            "capital": 1000000,
            "key_personnel": [
                {
                    "name": "Sten Cederberg",
                    "position": "Verkst dir"
                }
            ],
            "establishment_year": 1944
        },
        "4": {
            "company_name": "ÅSUNDENS MATTFABRIK, AB",
            "pnr": "523 00",
            "address": "Ulricehamn, Fiskareg 3. Box 46",
            "phone_number": "0321-100 54",
            "bank_details": {
                "bankgiro": "53-2856"
            },
            "activity": "Tillverkar nöthårs-mattor. Mattgrossist",
            "capital": 60000,
            "key_personnel": [
                {
                    "name": "Ingemar Linard",
                    "position": "Verkst dir"
                }
            ],
            "establishment_year": 1910
        },
        "5": {
            "company_name": "HEDLUNDS TRÄVARU AB",
            "pnr": "790 70",
            "address": "Furudal, Box 33",
            "phone_number": "0258-10200",
            "bank_details": {
                "bankgiro": "79-5007",
                "postgiro": "168396-0"
            },
            "activity": "Tillverkar sågade o hyvlade trävaror, monteringsfärdiga trähus",
            "employees": 125,
            "annual_turnover": 14000000,
            "capital": 300000,
            "key_personnel": [
                {
                    "name": "Disp Erik Hedlund",
                    "position": "Verkst dir"
                }
            ],
            "establishment_year": 1934
        },
        "6": {
            "company_name": "ELEKTROUTENSILIER, AB",
            "pnr": "180 20",
            "address": "Åkers Runo",
            "phone_number": "0764-20110",
            "bank_details": {
                "bankgiro": "238-2802",
                "postgiro": "199071-2"
            },
            "activity": "Försäljning av elektro-nik o teletekniska komponenter, krymppl as tpro dukter",
            "capital": 40000,
            "key_personnel": [
                {
                    "name": "Lennart Kalb",
                    "position": "Verkst dir"
                }
            ],
            "establishment_year": 1944
        },
        "7": {
            "company_name": "ANDERBERG,AB L J",
            "pnr": "102 21",
            "address": "Stockholm 12, Fridhemsg 45. Box 12029",
            "phone_number": "08-24 39 65",
            "bank_details": {
                "bankgiro": "56-3407",
                "postgiro": "3123"
            },
            "activity": "Import o export av herrbijouterier, present- o ekipe-ringsartiklar",
            "capital": 200000,
            "key_personnel": [
                {
                    "name": "Lars-Johan Anderberg",
                    "position": "Verkst dir"
                },
                {
                    "name": "Carl-Lennart Anderberg",
                    "position": "V verkst dir"
                }
            ],
            "establishment_year": 1903
        },
        "8": {
            "company_name": "ANDERS COMMERCE AB",
            "pnr": "753 29",
            "address": "Uppsala, Sankt Persg 31",
            "phone_number": "018-14 99 00",
            "postgiro": "379086",
            "activity": "Säljer textil- o hus-gerådsvaror",
            "employees": 10,
            "annual_turnover": 1100000,
            "capital": 25000,
            "key_personnel": [
                {
                    "name": "R Granvik",
                    "position": "Verkst dir"
                }
            ],
            "establishment_year": 1954
        },
        "9": {
            "company_name": "CONTINENTAL IMPORT, AB",
            "pnr": "117 23",
            "address": "Stockholm, Brännkyrkag 60",
            "phone_number": "08-84 04 35",
            "bank_details": {
                "bankgiro": "564-6856",
                "postgiro": "156850-0"
            },
            "activity": "Säljer sportartiklar. Export o import",
            "capital": 30000,
            "key_personnel": [
                {
                    "name": "Lennart Lundström",
                    "position": "Verkst dir"
                }
            ],
            "establishment_year": 1921
        },
        "10": {
            "company_name": "ARVO-INDUSTRIN AB",
            "pnr": "21231",
            "address": "Malmö, Sallerupsv 227",
            "phone_number": "040-49 14 80",
            "bank_details": {
                "bankgiro": "64-2908",
                "postgiro": "38055"
            },
            "activity": "Utför formsprutning av termoplaster",
            "employees": 7,
            "annual_turnover": 250000,
            "capital": 25000,
            "key_personnel": [
                {
                    "name": "Disp Bror Anderson",
                    "position": "Verkst dir"
                }
            ],
            "establishment_year": 1947
        },
        "11": {
            "company_name": "CENTRAVA, AB",
            "pnr": "103 40",
            "address": "Stockholm 40, Fack. Sveav 9-11",
            "phone_number": "23 83 80, riks 08-23 26 50",
            "activity": "Tillverkar o säljer kemisk-tekniska produkter",
            "employees": 1515,
            "annual_turnover": 338800000,
            "capital": 28000000,
            "key_personnel": [
                {
                    "name": "Oscar Strugstad",
                    "position": "Verkst dir"
                }
            ],
            "establishment_year": null
        },
        "12": {
            "company_name": "CENTRIFUGALPLAST, AB",
            "pnr": "85102",
            "address": "Sundsvall 1, Esplanaden 2. Box 85",
            "phone_number": "060-1130 90, 15 64 53",
            "activity": "Konstruktioner i plastsandwich, dörrar av olika slag, av-sugningskåpor över filter, manskapsbodar o karosser. Vidare fläktar, rör o rördelar i härdplast",
            "capital": 100000,
            "key_personnel": [
                {
                    "name": "Bertil Ericsson",
                    "position": "Verkst dir"
                }
            ],
            "establishment_year": 1960
        },
        "13": {
            "company_name": "SAHLINS KONFEKTIONS AB",
            "pnr": "24100",
            "address": "Eslöv, Kanalg 26. Box 60",
            "phone_number": "0413-132 30",
            "postgiro": "84442-3",
            "activity": "Tillverkar kappor, dräkter o jackor för flickor o damer",
            "employees": 230,
            "annual_turnover": 7000000,
            "capital": 300000,
            "key_personnel": [
                {
                    "name": "Börje Lernkvist",
                    "position": "Verkst dir"
                }
            ],
            "establishment_year": 1858
        }
    }
}