{
    "original": "CORSETEX, AB\n\nPnr 294 00\n\nSölvesborg, Kindstrandsg 9. Tel\n0456-112 98. Bankgiro 664-0163.\nPostgiro 578701-5\nVerksamhet: Tillverkar nattlinnen,\npyjamas o klänningar\nÅrsomsättning: 2 000 000\nAktiekapital: 5 000\nVerkst dir: Stig Blücher\nEtableringsår: 1961.\n\nSIMOTEX AB\n\nPnr 510 94\n\nGrimsås, Box 18. Tel 0325-740 66.\nPostgiro 178216\nVerksamhet: Tillverkar o säljer\nherr- o gossskjortor\nAntal anställda: 60\nAktiekapital: 90000\nVerkst din Bror E Simonson\nEtableringsån 1946.\n\nKAA\n\nK\n\nKAABS INDUSTRI.\nRÄVAROR AB\n\nPnr 262 00\n\nÄngelholm, Metallg 2. Tel\n0431-135 90. Tga Kaabs. Telex 72256\nVerksamhet: Grossist i skrot o\navfallsråvaror. Tillverkar\nmetallhalvfabrikat, metallgjutgods o\noljecisterner\n\nFilialer: Hälsingborg. Tel\n042-11 1136\n\nHässleholm. Tel 0451-125 00\nKlippan. Tel 0435-107 68\nLandskrona. Tel 0418-103 26\nÅstorp. Tel 042-512 45\nAntal anställda: 120\nÅrsomsättning: 16000 000\nAktiekapital: 370 500\nFirmatecknare: Ekonomichef G\nKnutsson\n\nEtableringsår: 1910\nAktiebolag 1950.\n\nKaBe INDUSTRIER AB\n\nPnr 199 00\n\nEnköping, O Järnvägsg 9. Tel\n0171-317 32, 364 38. Bankgiro\n23-0823. Postgiro 360036. Tga KaBe\nVerksamhet: Formgjutning av\ntekn o industriella detaljer i alla\ntermoplastiska material.\nSträngsprutning av rör o profiler. Egen\nverktygstillverkning\nVarunamn: KaBe\nAntal anställda: 50\nÅrsomsättning: 3 500 000\nAktiekapital: 50 000\nStyrelse: Dir Carlaxel Wadström\n(ordf), fabr Carl F Larsson\nVerkst dir: Carlaxel Wadström\nEtableringsår: 1947.\n\nNORDCHOKLAD, AB\n\nPnr 38101\n\nKalmar 1, Fack. Borgmästareg 5.\nTel 0480-223 80. Postgiro 11504.\nTga Choklad. Telex 43030\nVerksamhet: Tillverkar o säljer\nkonfektyrer\nAntal anställda: 360\nÅrsomsättning: 92 000 000\nVerkst dir: Birger Svahn\nEtableringsår: 1903.\n\nNORDELOFS REVISIONS.\nBYRÄ AB, IVAR\n\nPnr 412 54\n\nGöteborg, Södra v 12. Tel\n031-20 6544. Bankgiro 85-2456.\nPost-giro 49049\n\nVerksamhet: Revisionsbyrå\nAktiekapital: 5 000\nÄgare o chefer: Revisor Ivar\nNor-delöf, revisor Stig Nissbrandt\nEtableringsår: 1948.\n\nSKÅNESKOG EK FOR\n\nPnr 29100\n\nKristianstad, Näsbyviadukten. Tel\n044-1153 40. Bankgiro 657-8041.\nPostgiro 89935-1. Tga Scaniawood\nVerksamhet: Moderbolag för\nSkåneskog AB, Broby Industrier, Broby,\nSvanlund &amp; Co AB, Malmö\nAntal anställda: 248 (koncernen\n622)\n\nÅrsomsättning: 52 630000\n(koncernen 108 330 000)\nVerkst dir: Per-Olov Häger\nEtableringsår: 1932.\n\nLUG\n\nAktiekapital: 720 000\nVerkst dir: Sixten Persson\nEtableringsår 1956.\n\nINTONG AB\n\nPnr 690 60\n\nHällabrottet. Tel 019-860 00. Telex\n73315. Tga Intong, Örebro\nVerksamhet: Licensförsäljning,\nlättb et ongf abriker\n.Aktiekapital: 100 000\nStyrelse: Dir Bertil Carlén (ordf),\ndir Bo Rydin, dir Karlerik Savén,\nadv Lars Sjöborg\nVerkst dir: Arne Jacobsson\nEtableringsår. 1945\nNamnändring 1968.\nAdministreras av Yxhults\nSten-huggeri AB.\n\nINVENT AB,\nINGENJÖRS-FIRMAN\n\nPnr 11451\n\nStockholm, Artillerig 18. Tel\n08-617759. Bankgiro 576-8544.\nPostgiro 257539. Tga Inventar\nVerksamhet: Konsulterande\nverksamhet, export o import\nAktiekapital: 5 000\nVerkst dir: Gunnar Thiman\nEtableringsår: 1935.\n\nAREX, AB\n\nPnr 360 70\n\nAseda, Box 48. Tel 0474-112 20.\nBankgiro 700-3833. Postgiro\n351181-3. Tga Arexplastic\nVerksamhet: Tillverkar o monterar\nfläktar o ventilationssystem i\nplast. Levererar o monterar\ntryckrörsystem i PVC o PP.\nGalvanotek-niska konstruktioner i plast.\nDuschbord för sjukhus.\nLegoarbe-ten i PVC, GAP, PP o akryl\nAntal anställda: 20\nÅrsomsättning: 2 000 000\nAkteikapital: 100000\nStyrelse: Adv Sven Munck af\nRo-senschöld (ordf), dir Bertil\nDiedrichs, dir Sven Lindahl\nVerkst dir: Civiling Rolf Arrman\nEtableringsår: 1947\nDotterbolag till AB Stobo,\nStockholm.\n\nARGENTA, HANDELS AB\n\nPnr 433 00\n\nPartilie, Järnringen 17. Box 123.\nTel 031-44 08 50. Bankgiro\n420-0101. Postgiro 24 1 349-0\nVerksamhet: Försäljning av optik\nengros\n\nAntal anställda: 28\nÅrsomsättning: 8 000 000\nAktiekapital: 80 000\nÄgare o chef: O Lindstedt\nEtableringsår: 1946.\n\nTRANSFER, AB\n\nPnr 16211\n\nVällingby 1, Angermannag 158. Box\n55. Tel 08-87 02 50. Bankgiro\n447-3781. Postgiro 251272-1. Tga\nTransfer. Telex 19339\nVerksamhet: Säljer teknisk materiel\nsamt konsumentkapitalvaror\nAntal anställda: 130\nÅrsomsättning: 45 000 000\nAktiekapital: 510 000\nVerkst dir: Håkan Oscarson\nEtableringsår: 1935.\n\nMELLDSAVERKEN AB\n\nPnr 103 44\n\nStockholm 40, Box 40202. Sveav\n9-11. Tel 08-1017 00, 11 3510.\nBankgiro 73-4018. Postgiro\n53265-3. Tga Jim\n\nVerksamhet: Tillverkar tumstockar\nav trä o eloxerad lättmetall samt\nträtumstockar med reklamtryck\nFàbrik: Mellösa. Tel 0157-60046\nPlatschef: Harald Jonson\nFörsäljn-chef: Hilding Planté\n(Sthlm).\n\nMELTOLIT, AB\n\nPnr 400 64\n\nGöteborg 49, Hyvlareg 6. Box\n49002. Tel 031-21 10 20, 21 20 10.\nBankgiro 44-4323. Postgiro 627115.\nTga Meltolit\n\nVerksamhet: Silverlod, hårdlod,\nlödtenn, flussmedel, maskiner, ■\nugnar o tillbehör samt brännare för\nlödning, värmning o härdning\nAktiekapital: 5 000\nVerkst dir: Ragnar V Stenberg\nEtableringsår: 1965.",
    "structured": {
        "1": {
            "company_name": "CORSETEX, AB",
            "pnr": "294 00",
            "address": "Sölvesborg, Kindstrandsg 9",
            "phone_number": "0456-112 98",
            "bank_details": {
                "bankgiro": "664-0163",
                "postgiro": "578701-5"
            },
            "activity": "Tillverkar nattlinnen, pyjamas o klänningar",
            "annual_turnover": 2000000,
            "capital": 5000,
            "key_personnel": [
                {
                    "name": "Stig Blücher",
                    "position": "Verkst dir"
                }
            ],
            "establishment_year": 1961
        },
        "2": {
            "company_name": "SIMOTEX AB",
            "pnr": "510 94",
            "address": "Grimsås, Box 18",
            "phone_number": "0325-740 66",
            "postgiro": "178216",
            "activity": "Tillverkar o säljer herr- o gossskjortor",
            "employees": 60,
            "capital": 90000,
            "key_personnel": [
                {
                    "name": "Bror E Simonson",
                    "position": "Verkst dir"
                }
            ],
            "establishment_year": 1946
        },
        "3": {
            "company_name": "KAABS INDUSTRI. RÄVAROR AB",
            "pnr": "262 00",
            "address": "Ängelholm, Metallg 2",
            "phone_number": "0431-135 90",
            "activity": "Grossist i skrot o avfallsråvaror. Tillverkar metallhalvfabrikat, metallgjutgods o oljecisterner",
            "employees": 120,
            "annual_turnover": 16000000,
            "capital": 370500,
            "key_personnel": [
                {
                    "name": "Ekonomichef G Knutsson",
                    "position": "Firmatecknare"
                }
            ],
            "establishment_year": 1910
        },
        "4": {
            "company_name": "KaBe INDUSTRIER AB",
            "pnr": "199 00",
            "address": "Enköping, O Järnvägsg 9",
            "phone_number": "0171-317 32, 364 38",
            "bank_details": {
                "bankgiro": "23-0823",
                "postgiro": "360036"
            },
            "activity": "Formgjutning av tekn o industriella detaljer i alla termoplastiska material. Strängsprutning av rör o profiler",
            "employees": 50,
            "annual_turnover": 3500000,
            "capital": 50000,
            "key_personnel": [
                {
                    "name": "Carlaxel Wadström",
                    "position": "Verkst dir"
                }
            ],
            "establishment_year": 1947
        },
        "5": {
            "company_name": "NORDCHOKLAD, AB",
            "pnr": "38101",
            "address": "Kalmar 1, Fack. Borgmästareg 5",
            "phone_number": "0480-223 80",
            "postgiro": "11504",
            "activity": "Tillverkar o säljer konfektyrer",
            "employees": 360,
            "annual_turnover": 92000000,
            "key_personnel": [
                {
                    "name": "Birger Svahn",
                    "position": "Verkst dir"
                }
            ],
            "establishment_year": 1903
        },
        "6": {
            "company_name": "NORDELOFS REVISIONS. BYRÄ AB, IVAR",
            "pnr": "412 54",
            "address": "Göteborg, Södra v 12",
            "phone_number": "031-20 6544",
            "bank_details": {
                "bankgiro": "85-2456",
                "postgiro": "49049"
            },
            "activity": "Revisionsbyrå",
            "capital": 5000,
            "key_personnel": [
                {
                    "name": "Revisor Ivar Nor-delöf",
                    "position": "Ägare o chefer"
                },
                {
                    "name": "Revisor Stig Nissbrandt",
                    "position": "Ägare o chefer"
                }
            ],
            "establishment_year": 1948
        },
        "7": {
            "company_name": "SKÅNESKOG EK FOR",
            "pnr": "29100",
            "address": "Kristianstad, Näsbyviadukten",
            "phone_number": "044-1153 40",
            "bank_details": {
                "bankgiro": "657-8041",
                "postgiro": "89935-1"
            },
            "activity": "Moderbolag för Skåneskog AB, Broby Industrier, Broby, Svanlund & Co AB, Malmö",
            "employees": 248,
            "annual_turnover": 52630000,
            "establishment_year": 1932
        },
        "8": {
            "company_name": "INTONG AB",
            "pnr": "690 60",
            "address": "Hällabrottet",
            "phone_number": "019-860 00",
            "bank_details": {
                "telex": "73315"
            },
            "activity": "Licensförsäljning, lättb et ongf abriker",
            "capital": 100000,
            "key_personnel": [
                {
                    "name": "Bertil Carlén",
                    "position": "Styrelse"
                },
                {
                    "name": "Bo Rydin",
                    "position": "Styrelse"
                },
                {
                    "name": "Karlerik Savén",
                    "position": "Styrelse"
                },
                {
                    "name": "Lars Sjöborg",
                    "position": "Styrelse"
                },
                {
                    "name": "Arne Jacobsson",
                    "position": "Verkst dir"
                }
            ],
            "establishment_year": 1945
        },
        "9": {
            "company_name": "INVENT AB, INGENJÖRS-FIRMAN",
            "pnr": "11451",
            "address": "Stockholm, Artillerig 18",
            "phone_number": "08-617759",
            "bank_details": {
                "bankgiro": "576-8544",
                "postgiro": "257539"
            },
            "activity": "Konsulterande verksamhet, export o import",
            "capital": 5000,
            "key_personnel": [
                {
                    "name": "Gunnar Thiman",
                    "position": "Verkst dir"
                }
            ],
            "establishment_year": 1935
        },
        "10": {
            "company_name": "AREX, AB",
            "pnr": "360 70",
            "address": "Aseda, Box 48",
            "phone_number": "0474-112 20",
            "bank_details": {
                "bankgiro": "700-3833",
                "postgiro": "351181-3"
            },
            "activity": "Tillverkar o monterar fläktar o ventilationssystem i plast. Levererar o monterar tryckrörsystem i PVC o PP. Galvanotek-niska konstruktioner i plast. Duschbord för sjukhus. Legoarbe-ten i PVC, GAP, PP o akryl",
            "employees": 20,
            "annual_turnover": 2000000,
            "capital": 100000,
            "key_personnel": [
                {
                    "name": "Sven Munck af Rosenschöld",
                    "position": "Styrelse"
                },
                {
                    "name": "Bertil Diedrichs",
                    "position": "Styrelse"
                },
                {
                    "name": "Sven Lindahl",
                    "position": "Styrelse"
                },
                {
                    "name": "Rolf Arrman",
                    "position": "Verkst dir"
                }
            ],
            "establishment_year": 1947
        },
        "11": {
            "company_name": "ARGENTA, HANDELS AB",
            "pnr": "433 00",
            "address": "Partilie, Järnringen 17",
            "phone_number": "031-44 08 50",
            "bank_details": {
                "bankgiro": "420-0101",
                "postgiro": "24 1 349-0"
            },
            "activity": "Försäljning av optik engros",
            "employees": 28,
            "annual_turnover": 8000000,
            "capital": 80000,
            "key_personnel": [
                {
                    "name": "O Lindstedt",
                    "position": "Ägare o chef"
                }
            ],
            "establishment_year": 1946
        },
        "12": {
            "company_name": "TRANSFER, AB",
            "pnr": "16211",
            "address": "Vällingby 1, Angermannag 158. Box 55",
            "phone_number": "08-87 02 50",
            "bank_details": {
                "bankgiro": "447-3781",
                "postgiro": "251272-1"
            },
            "activity": "Säljer teknisk materiel samt konsumentkapitalvaror",
            "employees": 130,
            "annual_turnover": 45000000,
            "capital": 510000,
            "key_personnel": [
                {
                    "name": "Håkan Oscarson",
                    "position": "Verkst dir"
                }
            ],
            "establishment_year": 1935
        },
        "13": {
            "company_name": "MELLDSAVERKEN AB",
            "pnr": "103 44",
            "address": "Stockholm 40, Box 40202. Sveav 9-11",
            "phone_number": "08-1017 00, 11 3510",
            "bank_details": {
                "bankgiro": "73-4018",
                "postgiro": "53265-3"
            },
            "activity": "Tillverkar tumstockar av trä o eloxerad lättmetall samt trätumstockar med reklamtryck",
            "capital": 5000,
            "key_personnel": [
                {
                    "name": "Harald Jonson",
                    "position": "Platschef"
                },
                {
                    "name": "Hilding Planté",
                    "position": "Försäljn-chef"
                }
            ]
        },
        "14": {
            "company_name": "MELTOLIT, AB",
            "pnr": "400 64",
            "address": "Göteborg 49, Hyvlareg 6. Box 49002",
            "phone_number": "031-21 10 20, 21 20 10",
            "bank_details": {
                "bankgiro": "44-4323",
                "postgiro": "627115"
            },
            "activity": "Silverlod, hårdlod, lödtenn, flussmedel, maskiner, ■ ugnar o tillbehör samt brännare för lödning, värmning o härdning",
            "capital": 5000,
            "key_personnel": [
                {
                    "name": "Ragnar V Stenberg",
                    "position": "Verkst dir"
                }
            ],
            "establishment_year": 1965
        }
    }
}