{
    "original": "ARA NORRKOPING AB\n\nPnr 602 22\n\nNorrköping, ARA-Huset, Bråddg 7.\nTel 011-129160. Postgiro 28334.\nTga Arabolaget\nVerksamhet: Bränslehandel\nAntal anställda: 56\nÅrsomsättning: 37 000 000\nAktiekapital: 1 200 000\nVerkst dir: Lars Appelqvist\nEtableringsår: 1852\nOmbildat till aktiebolag 1926.\n\nARABIN AB\n\nPnr 302 50\n\nHalmstad, Pilefeltsg 58. Tel\n035-113000,113001. Bankgiro 42-3507.\nPostgiro 140064. Tga Arabin\nVerksamhet: Tillverkar\ntapetklister, lim o bindemedel på\nstärkelsebasis\n\nAktiekapital: 150 000\nStyrelseordt: Disp Claes Olsson\nChef: Disp Helge Lindén\nEtableringsår: 1938.\n\nKROSSEKONOMI, AB\n\nPnr 752 20\n\nUppsala, Drottningg 2. Tel\n018-15 51 30. Bankgiro 230-4376.\nPostgiro 678480-5\n\nVeiksamhet: Uthyrning o\nentreprenadverksamhet\nAntal anställda: 15\nÅrsomsättning: 3 000 000\nAktiekapital: 100 000\nVerkst dir: Disp Gunnar Westin\nEtableringsår: 1965.\n\nDELTALUX, AB\n\nPnr 11241\n\nStockholm, Karlsviksg 13. Tel\n08-24 73 85. Bankgiro 575-2399.\nPostgiro 553075-3. Tga Deltalight\nVerksamhet: Tillverkar\nutomhus-strålkastare. Projekterar ljus\nÅrsomsättning: 1500 000\nAktiekapital: 50 000\nVerkst dir Ewe Romberg.\n\nDEMAG AG\n\nStockholmsfilialen\n\nPnr 122 21\n\nEnskede 1, Box 43. Sandborgs v 44.\nTel 08-49 26 80. Bankgiro 296-7545.\nTga Demater, Stockholm.\nTelex 1869 MONTY S\nVerksamhet: Agentur för\nDEMAG-koncernens järnverks-,\nmetallverks-o diverse industriutrustningar,\nkompressorer, blåsmaskiner,\ntrycklufts-motorer, fullortsborrmaskiner mm\nVarunamn: Demag\n\nVerkst dir: Diploming Alfred Reuter\nFörsäljn-chef för avdelningen\nkompressorer o gruvteknik: Diploming\nChristian Heger\nEtableringsår: 1967.\n\nERIBOLAGET\n\nPnr 114 27\n\nStockholm, Tyrg 8. Tel 08-24 52 70.\nTga Eribolagen\n\nVerksamhet: Generalagent för Dymo\nmärksystem, Flo-Code\nrörmärknings-system, Rols dikteringsmaskiner o\nLine Text snabbtextsystem\nVarunamn: Dymo, Flo-code, Rols.\nLine-Text\nAntal anställda: 51\nVerkst dir: Erik Irestedt\nKamrer: Tage Söderqvist\nFörsäljn-chef för Dymo, Rols o\nLine-Text: Hans Sjögren\nFörsäljn-chef för Flo-Code: Erling\nCarlsson\n\nInköpschef: Börje Månsson\nReklamchef: Gunnar Fransson\nEtableringsår: 1961.\n\nRYDBERG, AB OLOF\n\nPnr 103 41\n\nStockholm 40, Kungsg 29. Box\n40039. Tel 08-11 51 74,204806.\nBankgiro 72-2196. Postgiro 151011.\nTelex 10091. Tga Rydol\nVerksamhet: Agentur o import av\nhemtextilier\nAntal anställda: 10\nAktiekapital: 100 000\nVerkst din Generalkonsul Olof\nRydberg\n\nEtableringsår: 1934.\n\nHÄS\n\nHÅLSINGE MAKADAM, AB\n\nPnr 82101\n\nBollnäs 1. Box 20. Tel 0278-\n\n133 50. Bankgiro 19-2818. Postgiro\n\n113346\n\nVerksamhet: Fabriksblandad\nbetong. Olika makadamprodukter\nFilial: Ovanåker, Klon. Tel\n0271-17159\n\nVäxbo. Tel 0278-660 05\nAntal anställda: 28\nÅrsomsättning: 3000000\nAktiekapital: 30 000\nVerkst dir: Wiktor Blomgren.\n\nHÄLSINGEKRAFT, AB\n\nPnr 820 10\n\nArbrå, Box 33. Storg 26. Tel\n0278-403 90\n\nVerksamhet: Elproduktion o\neldistribution\nAntal anställda: 65\nÅrsomsättning: 17000 000\nAktiekapital: 9 000 000\nVerkst dir. Allan Wrebo\nEtableringsår. 1920.\n\nEGELIN &amp; NILSSON AB\n\nPnr 11743\n\nStockholm, Årsta Skolgränd 16 A.\nTel 08-4 5 25 50. Bankgiro 73-3220.\nPostgiro 52302\n\nVerksamhet: Gjutmodeller av järn,\nmetall, plast o trä\nAntal anställda: 30\nÅrsomsättning: 1500 000\nAktiekapital: 25 000\nVerkst dir: Bengt Egelin\nEtableringsår: 1897.\n\nTRYCKLUFTSARBETEN AB\n\nPnr 232 00\n\nArlöv, Lundav 15. Box 26. Tel\n040-43 36 10. Bankgiro 870-6756.\nPost-giro 536399-9\n\nVerksamhet: Utför betongbilning,\nspontslagning, diamantborrning,\nsågning, rörtryckning mm\nAntal anstäUda: 65\nÅrsomsättning: 8 000 000\nAktiekapital: 300 000\nVerkst dir: Ivan Olsson\nEtableringsår: 1959.\n\nFOGELFORS BRUK, AB\n\nPnr 570 75\n\nFågelfors. Tel 0491-512 00.\nBankgiro 150-0115. Postgiro 135113-9.\nTga Fogelfors Bruk, Oskarshamn.\nTelex 4975\n\nVerksamhet: Tillverkar\nmonteringsfärdiga trähus, ytterdörrar, fönster,\nfabrikslackerade köksinredningar,\nsågade o hyvlade trävaror\nAntal anställda: 305\nÅrsomsättning: 33 000 000\nAktiekapital: 1200 000\nStyrelse: Bankdir Yngve Bjerström\n(ordf), dir Erik Nyberg, civilekonom\nBjörn Molin, avd-chef Gunnar\nStenbeck, bruksdisp Melcher Ekströmer,\ninköpschef Hans Lundgren, ing Bo\nHögström, fil lic Magnus Fürst\nVerkst dir: Bruksdisp Melcher\nEkströmer\n\nFörsäljn-chef: Lennart Österberg\nFabrikschef: Per Lundh\nInköpschef: Hans Lundgren\nEtableringsår: 1744\nOmbildat till aktiebolag 1916.\n\nFOGELMARK, ROLF\n\nPnr 411 21\n\nGöteborg, Stora Badhusg 20. Tel\n031-135282, 13 5283. Tga Rolfbox.\nTelex 2536\n\nVerksamhet: Säljer sågade o\nhyvlade trävaror av alla slag\nChef: Rolf V Fogelmark\nEtableringsår: 1951.\n\nTRÄULLIT AB\n\nPnr 731 01\n\nKöping 1, Nya Hamnv. Box 91. Tel\n0221-138 50. Bankgiro 60-6862.\nPostgiro 251690. Tga Träullit\nVerksamhet: Byggnadselement av\nbetong, träullsplattor o träull\nAntal anställda: 100\nAktiekapital: 300 000\nVerkst dir: Henrik Mattsson\nEtableringsår 1943.\n\n[-TRÄULLSPLATTFAB-RIKERNAS-]\n\n{+TRÄULLSPLATTFAB-\nRIKERNAS+} FÖRSÄLJNINGS AB\n\nPnr 126 12\n\nStockholm 42, Box 42013.\nKaru-sellplan 7. Hägersten. Tel\n08-18 82 80. Bankgiro 477-9252.\nPost-giro 2637-7. Tga Teplattor\nVerksamhet: Försäljning av\nträulls plattprodukter\nAntal anställda: 13\nAktiekapital: 80 000\nVerkst dir Civiling Per Herrmann\nEtableringsår 1956.\n\nTRÄVARUINDUSTRIN\nBERTIL JOHANSSON AB\n\nPnr 330 23\n\nSmålandsstenar, Dalsg 17. Tel\n0371-310 60. Bankgiro 427-6366.\nPostgiro 281951-4\nVerksamhet Tillverkar möbler\nAntal anställda: 55\nÅrsomsättning: 4 500 000\nAktiekapital; 400 000\nVerkst dir Nils Erik Johansson\nEtableringsår. 1940.",
    "structured": {
        "1": {
            "company_name": "ARA NORRKOPING AB",
            "pnr": "602 22",
            "address": "Norrköping, ARA-Huset, Bråddg 7",
            "phone_number": "011-129160",
            "bank_details": {
                "postgiro": "28334"
            },
            "activity": "Bränslehandel",
            "employees": 56,
            "annual_turnover": 37000000,
            "capital": 1200000,
            "key_personnel": [
                {
                    "name": "Lars Appelqvist",
                    "position": "Verkst dir"
                }
            ],
            "establishment_year": 1852
        },
        "2": {
            "company_name": "ARABIN AB",
            "pnr": "302 50",
            "address": "Halmstad, Pilefeltsg 58",
            "phone_number": "035-113000,113001",
            "bank_details": {
                "bankgiro": "42-3507",
                "postgiro": "140064"
            },
            "activity": "Tillverkar tapetklister, lim o bindemedel på stärkelsebasis",
            "capital": 150000,
            "key_personnel": [
                {
                    "name": "Disp Claes Olsson",
                    "position": "Styrelseordt"
                },
                {
                    "name": "Disp Helge Lindén",
                    "position": "Chef"
                }
            ],
            "establishment_year": 1938
        },
        "3": {
            "company_name": "KROSSEKONOMI, AB",
            "pnr": "752 20",
            "address": "Uppsala, Drottningg 2",
            "phone_number": "018-15 51 30",
            "bank_details": {
                "bankgiro": "230-4376",
                "postgiro": "678480-5"
            },
            "activity": "Uthyrning o entreprenadverksamhet",
            "employees": 15,
            "annual_turnover": 3000000,
            "capital": 100000,
            "key_personnel": [
                {
                    "name": "Disp Gunnar Westin",
                    "position": "Verkst dir"
                }
            ],
            "establishment_year": 1965
        },
        "4": {
            "company_name": "DELTALUX, AB",
            "pnr": "11241",
            "address": "Stockholm, Karlsviksg 13",
            "phone_number": "08-24 73 85",
            "bank_details": {
                "bankgiro": "575-2399",
                "postgiro": "553075-3"
            },
            "activity": "Tillverkar utomhus-strålkastare. Projekterar ljus",
            "annual_turnover": 1500000,
            "capital": 50000,
            "key_personnel": [
                {
                    "name": "Ewe Romberg",
                    "position": "Verkst dir"
                }
            ]
        },
        "5": {
            "company_name": "DEMAG AG Stockholmsfilialen",
            "pnr": "122 21",
            "address": "Enskede 1, Box 43, Sandborgs v 44",
            "phone_number": "08-49 26 80",
            "bank_details": {
                "bankgiro": "296-7545"
            },
            "activity": "Agentur för DEMAG-koncernens järnverks-, metallverks- o diverse industriutrustningar",
            "establishment_year": 1967
        },
        "6": {
            "company_name": "ERIBOLAGET",
            "pnr": "114 27",
            "address": "Stockholm, Tyrg 8",
            "phone_number": "08-24 52 70",
            "activity": "Generalagent för Dymo märksystem, Flo-Code rörmärknings-system, Rols dikteringsmaskiner o Line Text snabbtextsystem",
            "employees": 51,
            "key_personnel": [
                {
                    "name": "Erik Irestedt",
                    "position": "Verkst dir"
                }
            ],
            "establishment_year": 1961
        },
        "7": {
            "company_name": "RYDBERG, AB OLOF",
            "pnr": "103 41",
            "address": "Stockholm 40, Kungsg 29, Box 40039",
            "phone_number": "08-11 51 74,204806",
            "bank_details": {
                "bankgiro": "72-2196",
                "postgiro": "151011"
            },
            "activity": "Agentur o import av hemtextilier",
            "employees": 10,
            "capital": 100000,
            "key_personnel": [
                {
                    "name": "Generalkonsul Olof Rydberg",
                    "position": "Verkst din"
                }
            ],
            "establishment_year": 1934
        },
        "8": {
            "company_name": "HÄLSINGE MAKADAM, AB",
            "pnr": "82101",
            "address": "Bollnäs 1, Box 20",
            "phone_number": "0278-133 50",
            "bank_details": {
                "bankgiro": "19-2818",
                "postgiro": "113346"
            },
            "activity": "Fabriksblandad betong. Olika makadamprodukter",
            "employees": 28,
            "annual_turnover": 3000000,
            "capital": 30000,
            "key_personnel": [
                {
                    "name": "Wiktor Blomgren",
                    "position": "Verkst dir"
                }
            ]
        },
        "9": {
            "company_name": "HÄLSINGEKRAFT, AB",
            "pnr": "820 10",
            "address": "Arbrå, Box 33, Storg 26",
            "phone_number": "0278-403 90",
            "activity": "Elproduktion o eldistribution",
            "employees": 65,
            "annual_turnover": 17000000,
            "capital": 9000000,
            "key_personnel": [
                {
                    "name": "Allan Wrebo",
                    "position": "Verkst dir"
                }
            ],
            "establishment_year": 1920
        },
        "10": {
            "company_name": "EGELIN & NILSSON AB",
            "pnr": "11743",
            "address": "Stockholm, Årsta Skolgränd 16 A",
            "phone_number": "08-4 5 25 50",
            "bank_details": {
                "bankgiro": "73-3220",
                "postgiro": "52302"
            },
            "activity": "Gjutmodeller av järn, metall, plast o trä",
            "employees": 30,
            "annual_turnover": 1500000,
            "capital": 25000,
            "key_personnel": [
                {
                    "name": "Bengt Egelin",
                    "position": "Verkst dir"
                }
            ],
            "establishment_year": 1897
        },
        "11": {
            "company_name": "TRYCKLUFTSARBETEN AB",
            "pnr": "232 00",
            "address": "Arlöv, Lundav 15, Box 26",
            "phone_number": "040-43 36 10",
            "bank_details": {
                "bankgiro": "870-6756",
                "postgiro": "536399-9"
            },
            "activity": "Utför betongbilning, spontslagning, diamantborrning, sågning, rörtryckning mm",
            "employees": 65,
            "annual_turnover": 8000000,
            "capital": 300000,
            "key_personnel": [
                {
                    "name": "Ivan Olsson",
                    "position": "Verkst dir"
                }
            ],
            "establishment_year": 1959
        },
        "12": {
            "company_name": "FOGELFORS BRUK, AB",
            "pnr": "570 75",
            "phone_number": "0491-512 00",
            "bank_details": {
                "bankgiro": "150-0115",
                "postgiro": "135113-9"
            },
            "activity": "Tillverkar monteringsfärdiga trähus, ytterdörrar, fönster, fabrikslackerade köksinredningar, sågade o hyvlade trävaror",
            "employees": 305,
            "annual_turnover": 33000000,
            "capital": 1200000,
            "key_personnel": [
                {
                    "name": "Bankdir Yngve Bjerström",
                    "position": "Styrelse (ordf)"
                },
                {
                    "name": "dir Erik Nyberg",
                    "position": "civilekonom"
                },
                {
                    "name": "Björn Molin",
                    "position": "avd-chef"
                },
                {
                    "name": "Gunnar Stenbeck",
                    "position": "bruksdisp"
                },
                {
                    "name": "Melcher Ekströmer",
                    "position": "bruksdisp"
                },
                {
                    "name": "Hans Lundgren",
                    "position": "inköpschef"
                },
                {
                    "name": "Bo Högström",
                    "position": "ing"
                },
                {
                    "name": "Magnus Fürst",
                    "position": "fil lic"
                },
                {
                    "name": "Per Lundh",
                    "position": "Fabrikschef"
                }
            ],
            "establishment_year": 1744
        },
        "13": {
            "company_name": "FOGELMARK, ROLF",
            "pnr": "411 21",
            "address": "Göteborg, Stora Badhusg 20",
            "phone_number": "031-135282, 13 5283",
            "activity": "Säljer sågade o hyvlade trävaror av alla slag",
            "key_personnel": [
                {
                    "name": "Rolf V Fogelmark",
                    "position": "Chef"
                }
            ],
            "establishment_year": 1951
        },
        "14": {
            "company_name": "TRÄULLIT AB",
            "pnr": "731 01",
            "address": "Köping 1, Nya Hamnv. Box 91",
            "phone_number": "0221-138 50",
            "bank_details": {
                "bankgiro": "60-6862",
                "postgiro": "251690"
            },
            "activity": "Byggnadselement av betong, träullsplattor o träull",
            "employees": 100,
            "capital": 300000,
            "key_personnel": [
                {
                    "name": "Henrik Mattsson",
                    "position": "Verkst dir"
                }
            ],
            "establishment_year": 1943
        },
        "15": {
            "company_name": "TRÄULLSPLATTFAB-RIKERNAS FÖRSÄLJNINGS AB",
            "pnr": "126 12",
            "address": "Stockholm 42, Box 42013, Karu-sellplan 7, Hägersten",
            "phone_number": "08-18 82 80",
            "bank_details": {
                "bankgiro": "477-9252",
                "postgiro": "2637-7"
            },
            "activity": "Försäljning av träulls plattprodukter",
            "employees": 13,
            "capital": 80000,
            "key_personnel": [
                {
                    "name": "Civiling Per Herrmann",
                    "position": "Verkst dir"
                }
            ],
            "establishment_year": 1956
        },
        "16": {
            "company_name": "TRÄVARUINDUSTRIN BERTIL JOHANSSON AB",
            "pnr": "330 23",
            "address": "Smålandsstenar, Dalsg 17",
            "phone_number": "0371-310 60",
            "bank_details": {
                "bankgiro": "427-6366",
                "postgiro": "281951-4"
            },
            "activity": "Tillverkar möbler",
            "employees": 55,
            "annual_turnover": 4500000,
            "capital": 400000,
            "key_personnel": [
                {
                    "name": "Nils Erik Johansson",
                    "position": "Verkst dir"
                }
            ],
            "establishment_year": 1940
        }
    }
}