{
    "original": "KLEVÅS AROMER AB\n\nPnr 290 37\n\nArkelstorp, Box 56. Tel 044-91048.\nBankgiro 658-1847. Postgiro\n376300-0\n\nVerksamhet: Tillverkar aromer o\nkryddextrakter för speciellt\ncharkuteri-, kött-, grönsaks- o\nfiskkonservfabriker\nAktiekapital: 30 000\nStyrelse: Civilekonom I Winnberg\n(ordf), disp Edvin Karlsson, dir\nSune Klevås\nVerkst dir: Sune Klevås\nEtableringsår: 1966.\n\nBERGERSTAM, AB BRÖDERNA\n\nPnr 570 91\n\nKristdala, Box 640. Tel\n0491-70167, 70164. Bankgiro 451-2059\nVerksamhet: Tillverkar sågade\nträvaror\n\nAntal anstäUda: 25\nÅrsomsättning: 4 000 000\nAktiekapital: 100 000\nVerkst dir: Bengt Bergerstam\nEtableringsår: 1945.\n\nSTADEX, AB\n\nPnr 214 44\n\nMalmö, Kopparbergsg 31. Tel\n040-86640. Bankgiro 640-4206.\nPostgiro 148988-9. Tga Stadex.\nTelex 32239\n\nVerksamhet: Tillverkar\nstärkelsederivat, bageri-,\ncharkuterihjälpme-del, lim, klister, invertsocker o\nkärnbindemedel\nVarunamn: Stadex\nAntal anstäUda: 85\nÅrsomsättning: 20500 000\nAktiekapital: 1000 000\nStyrelse: Bankdir Nils Herslow\n(ordf), dir M H Lubbers, dir Gunnar\nBjörnberg, adv Sten Sandell\nVerkst dir: Gunnar Björnberg\nEtableringsår 1949.\n\nDISSOUSGAS, AB\n\nPnr 462 01\n\nVänersborg 1, Box 187.\nJärnvägsområdet. Tel 0521-105 53, 19230.\nBankgiro 888-7945. Postgiro\n23155-5\n\nVerksamhet: Acetylenfabrik\nAntal anställda: 10\nÅrsomsättning: 2 200000\nAktiekapital: 600000\nVerkst dir: Knut Nilsson\nEtableringsår: 1913.\n\nVÄSTBOARTIKLAR AB\n\nPnr 330 20\n\nAnderstorp. Agatan 8. Tel\n0371-153 60, 156 00. Bankgiro 488-1546.\nPostgiro 321038-2\nVerksamhet: Tillverkar o säljer\nbiltillbehör\nAntal anställda: 5\nÅrsomsättning: 500 000\nAktiekapital: 30 000\nVerkst dir: Bror Johansson\nEtableringsår: 1946.\n\nSYS\n\ngolvunderhåll. Fönsterputsning,\ntvätt o övriga hygienbefrämjande\nåtgärder\n\nAntal anställda: 200\nÅrsomsättning: 1500 000\nAktiekapital: 15 000\nVerkst dir: Stig Olsson\nEtableringsår: 1965.\n\nSYDSVENSKA TAKPAPP.\nFABRIKEN AB\n\nPnr 292 00\n\nKarlshamn, Box 13, Hunnemara.\nTel 0454-16640. Bankgiro\n343-4024. Postgiro 34236-0. Tga\nPappfabriken\n\nVerksamhet: Pappfabrik med\nentreprenadavdelning för tak- o\nisoleringsarbeten\nAntal anställda: 18\nAktiekapital: 500 000\nVerkst dir: Hans Ovgren\nEtableringsår 1908\nOmbildat till aktiebolag 1964.\n\nSYDVAKT AB\n\nPnr 502 44\n\nBorås, Kvarng 30. Tel 033-13 63 20.\nBankgiro 843-5802. Postgiro 6570-6.\nTga Sydvakt. Telex 36031\nVerksamhet: Bevakningsföretag\nAktiekapital: 200 000\nVerkst dir: Harvey Stjernström\nEtableringsår: 1953.\n\nSYDÖSTRA SVERIGES\nDAGBLAD AB\n\nPnr 371 01\n\nKarlskrona 1, Landbrog 17. Box\n110. Tel 0455-190 00. Bankgiro\n343-9858. Postgiro 13776-0. Tga\nSydostran. Telex 43004\nVerksamhet: Tidnings- o\nciviltryckeri\n\nAvdelningskontor: Karlshamn,\nRåd-husg 14. Tel 0454-150 30\nOlofström, Vilhultsv 1. Tel\n0454-400 47\n\nRonneby, Karlskronag 25. Tel\n0457-10148\n\nSölvesborg, Söderg 19. Tel\n0456-10253\n\nAntal anställda: 130\nÅrsomsättning: 6 800 000\nAktiekapital: 374 500\nVerkst dir: Wiking Thomasson\nChefredaktör: Evert Larsson\nFörsäljn-chef: Ake Paulrud\nDistributionschef: Sigurd Jönsson\nKamrer: Inger Bizzozero\nFaktor: Henry Blohm\nEtableringsår: 1903.\n\nSYLVAN &amp; QVIBELIUS,\nBYGGNADSVARU AB\n\nPnr 25102\n\nHelsingborg 1, Box 72. Regementsv\n9. Tel 042-14 4410. Bankgiro\n653-3665. Postgiro 14253-9\nVerksamhet: Säljer byggnadsvaror\nAntal anställda: 60\nÅrsomsättning: 12 000 000\nAktiekapital: 200 000\nStyrelse: Dir Sven Ake Nidelius,\ndisp Arne Brodd\nVeikst dir: Sven Ake Nidelius\nEtableringsår: 1867.\n\nSYLVAN &amp; QVIBELIUS\nSTENKOLSAKTIEBOLAG\n\nPnr 251 03\n\nHelsingborg 1, Box 172. Järnvägsg\n39. Tel 042-12 75 90. Bankgiro\n437-8501. Postgiro 84400-1. Tga\nSylvis\n\nVerksamhet: Säljer fasta bränslen\no eldningsoljor samt oljebrännare\njämte reservdelar o tillbehör.\nUtför tankrengöringar o oljeskadesar\nneringar, slamsugningar,\nhögtrycks-avloppsspolning o ångtvätt\nAntal anställda: 45\nÅrsomsättning: 8 000 000\nAktiekapital: 480 000\nVerkst dir: John Hain\nPlatschef: Malte Neglén\nEtableringsår: 1867\nDotterbolag till G &amp; L Beijer AB,\nMalmö.\n\nSYLVAN SERVICE AB\n\nPnr 41121\n\nGöteborg, Stora Badhusg 20. Tel\n031-11 5632, 11 5642. Bankgiro\n442-4081. Postgiro 241420-9. Tga\nSylva no. Telex 20731\nVerksamhet: Service o reservdelar\nför dieselmotorer o kompressorer\nAntal anställda: 5\nAktiekapital: 250 000\nStyrelse ordf: Civiling Eivind\nK:son Sylvan\n\nChef: Civiling Eivind K:son Sylvan\nAvd-chef: Gösta Fris\nEtableringsår: 1960.\n\nHACKSELIUS AB, A\n\nPnr 412 85\n\nGöteborg. Mölndalsv 85. Tel\n031-8132 20. Bankgiro 50-0602.\nPostgiro 422648. Tga Filmac\nVerksamhet: Agenturrörelse inom\ntextilbranschen\nAktiekapital: 6 000\nEtableringsår: 1947.\n\nHACKSTA SNICKERIFABRIK\nAB\n\nPnr 184 00\n\nAkersberga, Hackstav 9. Tel\n0764-220 98 , 208 38. Bankgiro 238-2521.\nPostgiro 417963-6\nVerksamhet: Tillverkar möbler,\nrestaurant- o butiksinredningar\nAntal anställda: 12\nÅrsomsättning: 1 200000\nAktiekapital: 5 000\nVerkst dir: Sixten Samuelsson\nEtableringsår: 1958.\n\nSVENSKA TOBAKS AB\n\nPnr 104 62\n\nStockholm 17, Maria Bang 6. Box\n17007. Tel 08-69 0900. Bankgiro\n33-0022. Postgiro 47. Tga\nSweto-bacco. Telex 17091\nVerksamhet: Tillverkar,\nimporterar o säljer tobaksvaror\nAntal anställda: 1 500\nÅrsomsättning: 1 960 000 000 (inkl\ntobaksskatt)\n\nAktiekapital: 150 000 000\nVerkst dir Karl Wärnberg\nEtableringsår 1915.\n\nREHNSTROM &amp; CO AB, ALLAN\n\nPnr 80106\n\nGävle 1, österbågen 5. Box 447.\nTel 026-12 31 70, 12 07 70.\nTel 026-12 31 70,120770. Tga\nAlreco. Telex 81155 ALRECO S\nVerksamhet: Alreco pumpar.\nVätske-spridare från Spraying Systems Co\nUSA\n\nVerkst dir: Erik Rehnström.\n\nRENTOKIL SVENSKA AB\n\nPnr 25011\n\nHelsingborg 11, Box 11016.\nIn-dustrig 52. Tel 042-12 09 40.\nBankgiro 107-9649. Postgiro 81898-9.\nTga Rentokil\n\nVerksamhet: Projekterar\nanläggningar för träimpregnering\nAntal anställda: 7\nÅrsomsättning: 8 000 000\nAktiekapital: 100 000\nVeikst dir. Stig Klersën\nEtableringsår: 1968.\n\nÖRINGE METALLGJUTERI\n\nPnr 595 00\n\nMjölby, Hogstad. Tel 0142-72162.\nBankgiro 128-2730. Postgiro\n337335-4\n\nVerksamhet: Tillverkar o säljer\nventilationsmaterial. Utför\nbeställ-ningsgjutningar i kokill\nAntal anställda: 10\nÅrsomsättning: 1200 000\nChef: Fabr J Skånberg\nEtableringsår: 1946.",
    "structured": {
        "1": {
            "company_name": "KLEVÅS AROMER AB",
            "pnr": "290 37",
            "address": "Arkelstorp, Box 56",
            "phone_number": "044-91048",
            "bank_details": {
                "bankgiro": "658-1847"
            },
            "activity": "Tillverkar aromer o kryddextrakter för speciellt charkuteri-, kött-, grönsaks- o fiskkonservfabriker",
            "capital": 30000,
            "key_personnel": [
                {
                    "name": "I Winnberg",
                    "position": "Civilekonom"
                },
                {
                    "name": "Edvin Karlsson",
                    "position": "disp"
                },
                {
                    "name": "Sune Klevås",
                    "position": "dir"
                }
            ],
            "establishment_year": 1966
        },
        "2": {
            "company_name": "BERGERSTAM, AB BRÖDERNA",
            "pnr": "570 91",
            "address": "Kristdala, Box 640",
            "phone_number": "0491-70167, 70164",
            "bank_details": {
                "bankgiro": "451-2059"
            },
            "activity": "Tillverkar sågade trävaror",
            "employees": 25,
            "annual_turnover": 4000000,
            "capital": 100000,
            "key_personnel": [
                {
                    "name": "Bengt Bergerstam",
                    "position": "Verkst dir"
                }
            ],
            "establishment_year": 1945
        },
        "3": {
            "company_name": "STADEX, AB",
            "pnr": "214 44",
            "address": "Malmö, Kopparbergsg 31",
            "phone_number": "040-86640",
            "bank_details": {
                "bankgiro": "640-4206",
                "postgiro": "148988-9"
            },
            "activity": "Tillverkar stärkelsederivat, bageri-, charkuterihjälpmedel, lim, klister, invertsocker o kärnbindemedel",
            "employees": 85,
            "annual_turnover": 20500000,
            "capital": 1000000,
            "key_personnel": [
                {
                    "name": "Nils Herslow",
                    "position": "Bankdir"
                },
                {
                    "name": "M H Lubbers",
                    "position": "dir"
                },
                {
                    "name": "Gunnar Björnberg",
                    "position": "dir"
                },
                {
                    "name": "Sten Sandell",
                    "position": "adv"
                }
            ],
            "establishment_year": 1949
        },
        "4": {
            "company_name": "DISSOUSGAS, AB",
            "pnr": "462 01",
            "address": "Vänersborg 1, Box 187 Järnvägsområdet",
            "phone_number": "0521-105 53, 19230",
            "bank_details": {
                "bankgiro": "888-7945",
                "postgiro": "23155-5"
            },
            "activity": "Acetylenfabrik",
            "employees": 10,
            "annual_turnover": 2200000,
            "capital": 600000,
            "key_personnel": [
                {
                    "name": "Knut Nilsson",
                    "position": "Verkst dir"
                }
            ],
            "establishment_year": 1913
        },
        "5": {
            "company_name": "VÄSTBOARTIKLAR AB",
            "pnr": "330 20",
            "address": "Anderstorp, Agatan 8",
            "phone_number": "0371-153 60, 156 00",
            "bank_details": {
                "bankgiro": "488-1546",
                "postgiro": "321038-2"
            },
            "activity": "Tillverkar o säljer biltillbehör",
            "employees": 5,
            "annual_turnover": 500000,
            "capital": 30000,
            "key_personnel": [
                {
                    "name": "Bror Johansson",
                    "position": "Verkst dir"
                }
            ],
            "establishment_year": 1946
        },
        "6": {
            "company_name": "SYS",
            "activity": "golvunderhåll. Fönsterputsning, tvätt o övriga hygienbefrämjande åtgärder",
            "employees": 200,
            "annual_turnover": 1500000,
            "capital": 15000,
            "key_personnel": [
                {
                    "name": "Stig Olsson",
                    "position": "Verkst dir"
                }
            ],
            "establishment_year": 1965
        },
        "7": {
            "company_name": "SYDSVENSKA TAKPAPP. FABRIKEN AB",
            "pnr": "292 00",
            "address": "Karlshamn, Box 13, Hunnemara",
            "phone_number": "0454-16640",
            "bank_details": {
                "bankgiro": "343-4024",
                "postgiro": "34236-0"
            },
            "activity": "Pappfabrik med entreprenadavdelning för tak- o isoleringsarbeten",
            "employees": 18,
            "capital": 500000,
            "key_personnel": [
                {
                    "name": "Hans Ovgren",
                    "position": "Verkst dir"
                }
            ],
            "establishment_year": 1908
        },
        "8": {
            "company_name": "SYDVAKT AB",
            "pnr": "502 44",
            "address": "Borås, Kvarng 30",
            "phone_number": "033-13 63 20",
            "bank_details": {
                "bankgiro": "843-5802",
                "postgiro": "6570-6"
            },
            "activity": "Bevakningsföretag",
            "capital": 200000,
            "key_personnel": [
                {
                    "name": "Harvey Stjernström",
                    "position": "Verkst dir"
                }
            ],
            "establishment_year": 1953
        },
        "9": {
            "company_name": "SYDÖSTRA SVERIGES DAGBLAD AB",
            "pnr": "371 01",
            "address": "Karlskrona 1, Landbrog 17",
            "phone_number": "0455-190 00",
            "bank_details": {
                "bankgiro": "343-9858",
                "postgiro": "13776-0"
            },
            "activity": "Tidnings- o civiltryckeri",
            "employees": 130,
            "annual_turnover": 6800000,
            "capital": 374500,
            "key_personnel": [
                {
                    "name": "Wiking Thomasson",
                    "position": "Verkst dir"
                },
                {
                    "name": "Evert Larsson",
                    "position": "Chefredaktör"
                },
                {
                    "name": "Ake Paulrud",
                    "position": "Försälj-chef"
                },
                {
                    "name": "Sigurd Jönsson",
                    "position": "Distributionschef"
                },
                {
                    "name": "Inger Bizzozero",
                    "position": "Kamrer"
                },
                {
                    "name": "Henry Blohm",
                    "position": "Faktor"
                }
            ],
            "establishment_year": 1903
        },
        "10": {
            "company_name": "SYLVAN & QVIBELIUS, BYGGNADSVARU AB",
            "pnr": "25102",
            "address": "Helsingborg 1, Box 72, Regementsv 9",
            "phone_number": "042-14 4410",
            "bank_details": {
                "bankgiro": "653-3665",
                "postgiro": "14253-9"
            },
            "activity": "Säljer byggnadsvaror",
            "employees": 60,
            "annual_turnover": 12000000,
            "capital": 200000,
            "key_personnel": [
                {
                    "name": "Sven Ake Nidelius",
                    "position": "Styrelse"
                }
            ],
            "establishment_year": 1867
        },
        "11": {
            "company_name": "SYLVAN & QVIBELIUS STENKOLSAKTIEBOLAG",
            "pnr": "251 03",
            "address": "Helsingborg 1, Box 172, Järnvägsg 39",
            "phone_number": "042-12 75 90",
            "bank_details": {
                "bankgiro": "437-8501",
                "postgiro": "84400-1"
            },
            "activity": "Säljer fasta bränslen o eldningsoljor samt oljebrännare jämte reservdelar o tillbehör. Utför tankrengöringar o oljeskadesarneringar, slamsugningar, högtrycks-avloppsspolning o ångtvätt",
            "employees": 45,
            "annual_turnover": 8000000,
            "capital": 480000,
            "key_personnel": [
                {
                    "name": "John Hain",
                    "position": "Verkst dir"
                },
                {
                    "name": "Malte Neglén",
                    "position": "Platschef"
                }
            ],
            "establishment_year": 1867
        },
        "12": {
            "company_name": "SYLVAN SERVICE AB",
            "pnr": "41121",
            "address": "Göteborg, Stora Badhusg 20",
            "phone_number": "031-11 5632, 11 5642",
            "bank_details": {
                "bankgiro": "442-4081",
                "postgiro": "241420-9"
            },
            "activity": "Service o reservdelar för dieselmotorer o kompressorer",
            "employees": 5,
            "capital": 250000,
            "key_personnel": [
                {
                    "name": "Eivind K:son Sylvan",
                    "position": "Styrelse ordf"
                },
                {
                    "name": "Eivind K:son Sylvan",
                    "position": "Chef"
                },
                {
                    "name": "Gösta Fris",
                    "position": "Avd-chef"
                }
            ],
            "establishment_year": 1960
        },
        "13": {
            "company_name": "HACKSELIUS AB, A",
            "pnr": "412 85",
            "address": "Göteborg, Mölndalsv 85",
            "phone_number": "031-8132 20",
            "bank_details": {
                "bankgiro": "50-0602",
                "postgiro": "422648"
            },
            "activity": "Agenturrörelse inom textilbranschen",
            "capital": 6000,
            "establishment_year": 1947
        },
        "14": {
            "company_name": "HACKSTA SNICKERIFABRIK AB",
            "pnr": "184 00",
            "address": "Akersberga, Hackstav 9",
            "phone_number": "0764-220 98 , 208 38",
            "bank_details": {
                "bankgiro": "238-2521",
                "postgiro": "417963-6"
            },
            "activity": "Tillverkar möbler, restaurant- o butiksinredningar",
            "employees": 12,
            "annual_turnover": 1200000,
            "capital": 5000,
            "key_personnel": [
                {
                    "name": "Sixten Samuelsson",
                    "position": "Verkst dir"
                }
            ],
            "establishment_year": 1958
        },
        "15": {
            "company_name": "SVENSKA TOBAKS AB",
            "pnr": "104 62",
            "address": "Stockholm 17, Maria Bang 6, Box 17007",
            "phone_number": "08-69 0900",
            "bank_details": {
                "bankgiro": "33-0022",
                "postgiro": "47"
            },
            "activity": "Tillverkar, importerar o säljer tobaksvaror",
            "employees": 1500,
            "annual_turnover": 1960000000,
            "capital": 150000000,
            "key_personnel": [
                {
                    "name": "Karl Wärnberg",
                    "position": "Verkst dir"
                }
            ],
            "establishment_year": 1915
        },
        "16": {
            "company_name": "REHNSTROM & CO AB, ALLAN",
            "pnr": "80106",
            "address": "Gävle 1, österbågen 5, Box 447",
            "phone_number": "026-12 31 70,",
            "bank_details": {
                "bankgiro": "107-9649",
                "postgiro": "81898-9"
            },
            "activity": "Alreco pumpar. Vätskespridare från Spraying Systems Co USA",
            "key_personnel": [
                {
                    "name": "Erik Rehnström",
                    "position": "Verkst dir"
                }
            ]
        },
        "17": {
            "company_name": "RENTOKIL SVENSKA AB",
            "pnr": "25011",
            "address": "Helsingborg 11, Box 11016, Industrig 52",
            "phone_number": "042-12 09 40",
            "bank_details": {
                "bankgiro": "107-9649",
                "postgiro": "81898-9"
            },
            "activity": "Projekterar anläggningar för träimpregnering",
            "employees": 7,
            "annual_turnover": 8000000,
            "capital": 100000,
            "key_personnel": [
                {
                    "name": "Stig Klersën",
                    "position": "Verkst dir"
                }
            ],
            "establishment_year": 1968
        },
        "18": {
            "company_name": "ÖRINGE METALLGJUTERI",
            "pnr": "595 00",
            "address": "Mjölby, Hogstad",
            "phone_number": "0142-72162",
            "bank_details": {
                "bankgiro": "128-2730",
                "postgiro": "337335-4"
            },
            "activity": "Tillverkar o säljer ventilationsmaterial. Utför beställ-ningsgjutningar i kokill",
            "employees": 10,
            "annual_turnover": 1200000,
            "key_personnel": [
                {
                    "name": "J Skånberg",
                    "position": "Chef"
                }
            ],
            "establishment_year": 1946
        }
    }
}