{
    "original": "ITAL-VICOM SVENSKA Aü\n\nPnr 14141\n\nHuddinge. Häradsv 144. Tel\n08-97 70 03. Bankgiro 74-7099.\nPostgiro 707100. Tga Rograco\nVerksamhet: Import o\ngrossistförsäljning av saxar\nAntal anställda: 2\nÅrsomsättning: 1000 000\nAktiekapital: 15 000\nVerkst dir: Roland Granlund\nEtableringsår: 1959.\n\nOREBRO GOLVINDUSTRI\n\nPnr 700 03\n\nÖrebro 3, Signalg 9. Box 3024. Tel\n019-117912, 12 00 65. Bankgiro\n35-8898. Postgiro 338493\nVerksamhet: Tillverkar o säljer\ngolvslipmaskiner, golvslippapper\nmm\n\nFörsäljningskontor: Örebro.\nFörsäljnings AB Orebromaskiner,\nSignalg 9. Tel 019-12 00 65. Bankgiro\n81-5920. Postgiro 12662\nÅrsomsättning: 900 000\nChef: Sven Larsson\nEtableringsår: 1947.\n\nANTENN- &amp; TELESERVICE AB\n\nPnr 400 90\n\nGöteborg, Vantg 1. Tel\n031-1248 25. Bankgiro 362-7635.\nPostgiro 521689-0\n\nVerksamhet: Generalagent o\ninstallatör för Robert Bosch\nAntennteknik o Ritto snabb- o porttelefoner\nFilialer: Hägersten, Brådstupsv 11.\nTel 08-88 04 90\n\nMalmö, Nya Agnesfridsv 186. Tel\n040-21 7030, 21 7031\nNorrköping, Tunnbindareg 19. Tel\n011-1808 48\n\nSundsvall, Skönsbergsv 19 A. Tel\n060-12 67 67, 12 68 68\nVästerås, Aspvretsg 15. Tel\n021-1180 00\n\nVarunamn: Elektronik, Ritto\nAntal anställda: 80\nÅrsomsättning: 8 000 000\nAktiekapital: 135 000\nFirmatecknare: Harry W Karlsson\nEtableringsår: 1956.\n\nECKERSTRÖM, AB FOLKE\n\nPnr 51045\n\nSparsör. Tel 033-606 75. Bankgiro\n844-8474. Postgiro 378118-4\nVerksamhet: Trikåtillverkning.\nRå-väv i jacquard, wevenit, plysch,\nfrotté, singeljersey. Trikåpyjamas\nAktiekapital: 5 000\nChef: Folke Eckerström\nEtableringsår: 1952.\n\nSÄGES TÄCKEN, AB\n\nPnr 510 35\n\nBollebygd, Box 977. Tel\n033-85156. Postgiro 398143-8\nVerksamhet: Tillverkar täcken,\näven lönstickning\nÅrsomsättning: 200 000\nAktiekapital: 20 000\nÄgare o chef: Sven Augustsson\nEtableringsån 1951.\n\nVIL\n\nÅrsomsättning: 8 600 000\nAktiekapital: 250 000\nVerkst dir: Ingemar Myregård\nFörsälin-dir: Ake Ericstam\nEtableringsår: 1897.\n\nFORSBERG AB, THURE F\n\nPnr 123 21\n\nFarsta 1, Box79. Forshagag 58.\nTel 08-93 0135. Bankgiro\n747-0321. Postgiro 251177-2. Tga\nIm-porture. Telex 10338 TFFAB S\nVerksamhet: Agentur o\ngrossiströrelse inom elektroniska industrin\nAntal anställda: 8\nÅrsomsättning: 8 000 000\nAktiekapital: 50 000\nVerkst dir: Kobert Olin\nEtableringsår: 1945.\n\nDIEDEN J:or, AB J H\n\nPnr 201 20\n\nMalmö 1, Box 85. Nordenskiöldsg\n14. Tel 040-716 50. Bankgiro\n870-1542. Postgiro 37624-4. Tga Dieden\nVerksamhet: Grosshandel i järn o\nstål, bult, rör, verktyg o stålprofiler,\nQuissle-garage o industriport\nVarunamn: Quissle\nFilial: 271 00 Ystad, Stora Osterg\n38. Tel 0411-137 20\nAntal anställda: 65\nÅrsomsättning: 24 600 000\nAktiekapital: 825 000\nStyrelse: Stig Widell (ordf), William\nFrick, Hulda Holmberg, Gunvor\nWidell\n\nVerkst dir: William Frick\nEtableringsår: 1837.\n\nDALARNES PARAPLYFABRIK\n\nPnr 78200\n\nMalung. Tel 0280-117 80\nVerksamhet: Tillverkar dam-, herr-,\nbarn- o golfparaplyer samt\nparasol-ler\n\nFirmatecknare: Folke Einarsson,\nTorsten Einarsson, Sune Einarsson.\n\nDALARNES TIDNINGS- &amp;\nBOKTRYCKERI AB\n\nPnr 781 00\n\nBorlänge, Borganäsv 37. Tel\n0243-250 00. Bankgiro 794-6734.\nPostgiro 15121-7. Tga Borlänge tidning.\nTelex 7639 BTBLG S\nVerksamhet: Dagstidningar,\ntidskrifter. Affärs- o reklamtryck\nAntal anställda: 170\nÅrsomsättning: 10 000 000\nAktiekapital: 100 000\nVerkst dir: Sten Bengtsson\nEtableringsår: 1900.\n\nALBINS AB\n\nPnr 65109\n\nKarlstad 1, O Torgg 8. Box 590.\nTel 054-117122. Postgiro 160520-3\nVerksamhet: Säljer damväskor,\nreseeffekter, leksaker, babyartiklar\nsamt hobby- o fritidsartiklar\nAntal anställda: 13\nÅrsomsättning: 2 300 000\nAktiekapital: 50 000\nVerkst dir: J Albintz\nEtableringsår: 1935\nOmbildat till aktiebolag 1956.\n\nALBIN MARIN AB\n\nPnr 68101\n\nKristinehamn 1, Fack. Tel\n0550-156 60. Bankgiro 171-2900.\nPost-giro 211960-0. Tga Larstrade\nVerksamhet: Tillverkar motor- o\nsegelbåtar\n\nAvdelningskontor: Stockholm,\nGöteborg\nVarunamn: Albin\nAntal anställda: 200\nÅrsomsättning: 50 000 000\nVerkst dir: Uno Eriksson\nMarknadschef: Gunnar Ahlebro\nExportchef: Ake Ström\nEtableringsår: 1956.",
    "structured": {
        "1": {
            "company_name": "ITAL-VICOM SVENSKA Aü",
            "pnr": "14141",
            "address": "Huddinge. Häradsv 144",
            "phone_number": "08-97 70 03",
            "bank_details": {
                "bankgiro": "74-7099",
                "postgiro": "707100"
            },
            "activity": "Import ogrossistförsäljning av saxar",
            "employees": 2,
            "annual_turnover": 1000000,
            "capital": 15000,
            "key_personnel": [
                {
                    "name": "Roland Granlund",
                    "position": "Verkst dir"
                }
            ],
            "establishment_year": 1959
        },
        "2": {
            "company_name": "OREBRO GOLVINDUSTRI",
            "pnr": "700 03",
            "address": "Örebro 3, Signalg 9. Box 3024",
            "phone_number": "019-117912, 12 00 65",
            "bank_details": {
                "bankgiro": "35-8898",
                "postgiro": "338493"
            },
            "activity": "Tillverkar o säljergolvslipmaskiner, golvslippapper mm",
            "sales_office": "Örebro. Försäljnings AB Orebromaskiner, Signalg 9",
            "annual_turnover": 900000,
            "chief": "Sven Larsson",
            "establishment_year": 1947
        },
        "3": {
            "company_name": "ANTENN- & TELESERVICE AB",
            "pnr": "400 90",
            "address": "Göteborg, Vantg 1",
            "phone_number": "031-1248 25",
            "bank_details": {
                "bankgiro": "362-7635",
                "postgiro": "521689-0"
            },
            "activity": "Generalagent oinstallatör för Robert BoschAntennteknik o Ritto snabb- o porttelefoner",
            "branches": {
                "Hägersten": "Brådstupsv 11",
                "Malmö": "Nya Agnesfridsv 186",
                "Norrköping": "Tunnbindareg 19",
                "Sundsvall": "Skönsbergsv 19 A",
                "Västerås": "Aspvretsg 15"
            },
            "varunamn": "Elektronik, Ritto",
            "employees": 80,
            "annual_turnover": 8000000,
            "capital": 135000,
            "firmatecknare": "Harry W Karlsson",
            "establishment_year": 1956
        },
        "4": {
            "company_name": "ECKERSTRÖM, AB FOLKE",
            "pnr": "51045",
            "address": "Sparsör",
            "phone_number": "033-606 75",
            "bank_details": {
                "bankgiro": "844-8474",
                "postgiro": "378118-4"
            },
            "activity": "Trikåtillverkning. Rå-väv i jacquard, wevenit, plysch, frotté, singeljersey. Trikåpyjamas",
            "capital": 5000,
            "chief": "Folke Eckerström",
            "establishment_year": 1952
        },
        "5": {
            "company_name": "SÄGES TÄCKEN, AB",
            "pnr": "510 35",
            "address": "Bollebygd, Box 977",
            "phone_number": "033-85156",
            "postgiro": "398143-8",
            "activity": "Tillverkar täcken, även lönstickning",
            "annual_turnover": 200000,
            "capital": 20000,
            "owner_och_chef": "Sven Augustsson",
            "establishment_year": 1951
        },
        "6": {
            "company_name": "VIL",
            "annual_turnover": 8600000,
            "capital": 250000,
            "verkst_dir": "Ingemar Myregård",
            "försälin-dir": "Ake Ericstam",
            "establishment_year": 1897
        },
        "7": {
            "company_name": "FORSBERG AB, THURE F",
            "pnr": "123 21",
            "address": "Farsta 1, Box 79. Forshagag 58",
            "phone_number": "08-93 0135",
            "bank_details": {
                "bankgiro": "747-0321",
                "postgiro": "251177-2"
            },
            "activity": "Agentur ogrossiströrelse inom elektroniska industrin",
            "employees": 8,
            "annual_turnover": 8000000,
            "capital": 50000,
            "verkst_dir": "Kobert Olin",
            "establishment_year": 1945
        },
        "8": {
            "company_name": "DIEDEN J:or, AB J H",
            "pnr": "201 20",
            "address": "Malmö 1, Box 85. Nordenskiöldsg 14",
            "phone_number": "040-716 50",
            "bank_details": {
                "bankgiro": "870-1542",
                "postgiro": "37624-4"
            },
            "activity": "Grosshandel i järn ostål, bult, rör, verktyg o stålprofiler, Quisslegarage o industriport",
            "varunamn": "Quissle",
            "filial": "271 00 Ystad, Stora Osterg 38",
            "employees": 65,
            "annual_turnover": 24600000,
            "capital": 825000,
            "styrelse": "Stig Widell (ordf), William Frick, Hulda Holmberg, Gunvor Widell",
            "verkst_dir": "William Frick",
            "establishment_year": 1837
        },
        "9": {
            "company_name": "DALARNES PARAPLYFABRIK",
            "pnr": "78200",
            "address": "Malung",
            "phone_number": "0280-117 80",
            "activity": "Tillverkar dam-, herr-, barn- o golfparaplyer samt parasoller",
            "firmatecknare": "Folke Einarsson, Torsten Einarsson, Sune Einarsson"
        },
        "10": {
            "company_name": "DALARNES TIDNINGS- & BOKTRYCKERI AB",
            "pnr": "781 00",
            "address": "Borlänge, Borganäsv 37",
            "phone_number": "0243-250 00",
            "bank_details": {
                "bankgiro": "794-6734",
                "postgiro": "15121-7"
            },
            "activity": "Dagstidningar, tidskrifter. Affärs- o reklamtryck",
            "employees": 170,
            "annual_turnover": 10000000,
            "capital": 100000,
            "verkst_dir": "Sten Bengtsson",
            "establishment_year": 1900
        },
        "11": {
            "company_name": "ALBINS AB",
            "pnr": "65109",
            "address": "Karlstad 1, O Torgg 8. Box 590",
            "phone_number": "054-117122",
            "postgiro": "160520-3",
            "activity": "Säljer damväskor, reseeffekter, leksaker, babyartiklar samt hobby- o fritidsartiklar",
            "employees": 13,
            "annual_turnover": 2300000,
            "capital": 50000,
            "verkst_dir": "J Albintz",
            "establishment_year": 1935
        },
        "12": {
            "company_name": "ALBIN MARIN AB",
            "pnr": "68101",
            "address": "Kristinehamn 1, Fack",
            "phone_number": "0550-156 60",
            "bank_details": {
                "bankgiro": "171-2900",
                "postgiro": "211960-0"
            },
            "activity": "Tillverkar motor- o segelbåtar",
            "avdelningskontor": "Stockholm, Göteborg",
            "varunamn": "Albin",
            "employees": 200,
            "annual_turnover": 50000000,
            "verkst_dir": "Uno Eriksson",
            "marknadschef": "Gunnar Ahlebro",
            "exportchef": "Ake Ström",
            "establishment_year": 1956
        }
    }
}