{
    "original": "ESS\n\n7202. Postgiro 453458. Tga\nEsma-tek. Telex 10023\nVerksamhet: Representant för\nutländska tillverkare av mekaniska\nkonstruktionselement för\nfinmeka-nisk-, elektroteknisk-,\nfordons-samt tung industri. Försäljning\nfrån lager av fästdetaljer såsom\nskruvar, muttrar, brickor etc samt\nverktygsdetaljer såsom pelarställ,\nhålstansar, borrbussningar,\nbrick-fjädrar, Eladip-plastfjädrar,\nstamformar för plastverktyg,\nBidurit-hårdmetall\nAktiekapital: 25 000\nÄgare: Diploming H Eiger\n(ETH Zurich)\nVerkst dir: Paul Riesterer\nV verkst dir o försälin-chef:\nHeinz Matthiesen\nEtableringsår: 1950\nOmbildat till aktiebolag 1952.\n\nESON PAC AB\n\nPnr 430 20\n\nVeddige, Box 42. Tel 0340-306 20\nVerksamhet: Tillverkar kartonger,\nkapslar o tråg. Offsettryck\nAntal anställda: 30\nÅrsomsättning: 3500 000\nVerkst dir: ing anar Eliasson\nFörsäljningschef: Dag Magnusson\nEtableringsår: 1968.\n\nRYDÉN-MÖBLER AB\n\nPnr 382 00\n\nNybro, Lilla Trädgårdsg 6. Tel\n0481-118 20\n\nVerksamhet: Säljer stilmöbler\nAntal anställda: 57\nAktiekapital: 25 000\nVerkst dir: Gunnar Rydén.\n\nRYDQVIST, K O\n\nPnr 182 11\n\nDanderyd 1, Klubbv 5. Box 70.\nTel 08-755 2675. Postgiro 333254.\nTga Stålrydqvist, Stockholm.\nTelex 10056 RYDCARL S\nVerksamhet: Säljer kol- o\ngrafitelektroder, syrgasverk,\nprocesslinjer, industriugnar, eldfast\ntegel, zirkonoxid o\nkiselkarbid-stavar\n\nEtableringsår: 1914.\n\nda ros\n\nPnr 433 00\n\nPartille. Tel 031-44 08 80. Bankgiro\n55-0545. Postgiro 40480.\nTga Daros, Göteborg. Telex 2414\nVerksamhet: Specialitet: kolvringar,\nkolvstångspackningar o\ncylinderfoder\n\nAktiekapital: 3 000 000\nVerkst dir: Civiling Kurt Madsen\nEtableringsår: 1851.\n\nWESTMAN, NILS\n\nPnr 113 52\n\nStockholm VA, Döbelnsg 40. Tel\n08-319150. Postgiro 55344. Tga\nSkinnar nil s\n\nVerksamhet: Agenturer för\nskinn-o pälsvaror samt pälstillbehör\nÅrsomsättning: 1500 000\nÄgare o chef: Nils Westman\nEtableringsån 1941.\n\nNORDGAS, AB\n\nPnr 11233\n\nStockholm, Kronobergsg. 21. Tel\n08-54 0 9 20. Tga Nordgas.\nTelex 17305 NORDCO S\nVerksamhet: Säljer mängdmätare\nför gasformiga media såsom gas,\npropan/butan, luft etc,\nvarmvattenberedare o centralvärmepannor för\nstadsgas/gasol, tändsäkringar,\ntermostater, regulatorer etc för\nstadsgas o gasol\n\nAktiekapital: 300000\nStyrelse: Adv W Moberg (ordf),\ndu-Il Scherrer, dir B Ahlström\nVerkst dir: Hans Scherrer\nEtableringsår 1930.\n\nDENTALBORRFABRIKEN AB\n\nPnr 21142\n\nMalmö, Storg 30. Tel 040- 1198 50.\nPostgiro 39075. Tga Svedex\nVerksamhet: Tillverkar\ntandläkar-borrar\n\nAktiekapital: 170000\nÄgare o chef: Dir Bror Rohlin\nEtableringsår: 1947.\n\nEHRENSTROM FLYG AB\n\nPnr 16110\n\nBromma 10, Bromma Flygplats.\nFfcck. Tel 08-98 06 50. Bankgiro\n238-2992. Postgiro 611603-2. Telex\n10076 EHR S\n\nVerksamhet: Taxi- o ambulansflyg\nmed 2-motoriga propeller- o\njetflygplan. Säljer flygplan, Aero\nCommander o Jet Commander\nAntal anstäHda: 31\nÅrsomsättning: 5 000 000\n\nAktiekapital: 600 000\nStyrelse: Ingemar Ehrenström\n(ordf), Inez Ehrenström, Sten\nSjödin\n\nVerkst dir: Ingemar Ehrenström\nEkonomichef: Per-Ake Karlsson\nTekn chef: Stig Wikman\nMarknadschef: Tommy Köthnig\nFlygchef: Leif Ståhl\nEtableringsår: 1962.\n\nTURITZ &amp; CO, AB\n\nPnr 415 30\n\nGöteborg 13, Gamlestadsv 3. Box\n13500. Tel 031-25 03 00. Bankgiro\n16-0082, 41-0065. Postgiro 5250.\nTelex 20708 TURITZ S.\nTga Turitz\n\nAntal anställda: 12 000\nÅrsomsättning: 1776400 000\nAktiekapital: 125 000000\nVerkst din Erik Söderberg\nEtableringsår: 1918.\nModerbolag för varuhusen Epa o\nGrand samt EP A Stormarknader.\nDotterbolag till AB Nordiska\nKompaniet, Stockholm.\n\nTURNEX AB\n\nPnr 41122\n\nGöteborg, Husarg 30-32. Tel\n031-13 34 59, 13 37 09. Bankgiro\n501-4709. Postgiro 47898-2.\nTgaTurnex-bolag. Telex 20884 REXTUR S\nVerksamhet Representant för\nFinska Pappers- o\nKartongföräd-lares Förening, CONVERTA,\nHelsingfors, Finland\n\nDotterbolag: 21121 Malmö. Turnex\ni Malmö AB, Gråbrödersg 2. Tel\n040-9745 70\nAntal anställda: 10\nAktiekapital: 15 000\nStyrelse: Dir Olle Jansson (ordf),\nherr K E Hofstedt, försäljn-chef\nSune Lindblom, herr K G Törnmalm\nVerkst din Olle Jansson\nFörsäljn-chef: Sune Lindblom\nEtableringsår. 1962.\n\nHAGAFORS STOLFABRIK, AB\n\nPnr 57100\n\nNässjö, Box 70. Fabriksg. Tel\n0380-180 00. Bankgiro 841-5002.\nPostgiro 11595-6. Tga\nHagafors-stol\n\nVerksamhet: Tillverkning av\nstolar, möbler o ämnen\nAktiekapital: 300 000\nVerkst dir: Disp Björn Stålsmeden\nEtableringsår. 1863.\n\nHAGALUNDS\nMETALLINDUSTRI AB\n\nPnr 330 21\n\nReftele, Bruksg 5. Tel 0371-200 75.\nBankgiro 14-275 2. Postgiro\n132296-5\n\nVerksamhet: Bockade trådartiklar,\ngångjärn för brandskyddsdörrar\nAntal anstäUda: 6\nÅrsomsättning: 400000\nAktiekapital: 20 000\nVerkst dir: Bertil Grundin\nEtableringsår: 1931.\n\nHAGASTRÖMS TEGEL.\nBRUKS AB\n\nPnr 80103\n\nGävle, Centralplan 5. Box 120. Tel\n026-12 00 58, 19 73 38. Postgiro\n22012\n\nVerksamhet: Tillverkar fasadtegel,\nmurtegel o tegelmjöl\nAntal anställda: 18\nÅrsomsättning: 400 000\nAktiekapital: 80 000\nVerkst dir: Erik Nordström\nEtableringsår: 1892.\n\nHAGBERG, HEDENLUND &amp; CO\nAB\n\nPnr 40251\n\nGöteborg 13, Gamlestadsv 6-8.\nBox 13021. Tel 031-25 00 85.\nBankgiro 514-3185. Postgiro 40506-8.\nTga Haghed\n\nVerksamhet: Importhandel med\ndamkonfektion\nVarunamn: Hedenlunds\nAntal anstäUda: 10\nÅrsomsättning: 5 000 000\n\nAktiekapital: 100 000\nDir: John Larsson\nEtableringsår: 1891.\n\nSVENSSON AB, FILIP N\n\nPnr 104 35\n\nStockholm 23, Fack. Dannemorag\n18. Tel 08-24 4845. Bankgiro\n482-7358. Postgiro 13036-9. Tga\nFilipens\n\nVerksamhet: Elektr\ninstallationsmateriel i engros\nAntal anställda: 16\nÅrsomsättning: 5400 000\nAktiekapital: 100 000\nVerkst din Arne Authén\nEtableringsår: 1932.\n\nSVENSSONS EL.BYRÄ AB,\nFRITHIOF\n\nPnr 114 53\n\nStockholm, Grevg 7. Tel\n08-6105 79, 61 84 48. Postgiro 53057-6\nVerksamhet: Elektr\ninstallationsarbeten. Försäljer elektr material,\nbelysningsförslag\nAktiekapital: 50 000\nStyrelse: Ing Lars Berggren (ordf),\ning Bengt Carls, fru Inga Berggren,\ndir Knut Berggren\nVerkst dir: Knut Albert Berggren\nEtableringsår: 1954.",
    "structured": {
        "firms": [
            {
                "company_name": "ESS",
                "bank_details": {
                    "postgiro": "453458"
                },
                "activity": "Representant för utländska tillverkare av mekaniska konstruktionselement för finmekanisk-, elektroteknisk-, fordons- samt tung industri. Försäljning från lager av fästdetaljer såsom skruvar, muttrar, brickor etc samt verktygsdetaljer såsom pelarställ, hålstansar, borrbussningar, brick-fjädrar, Eladip-plastfjädrar, stamformar för plastverktyg, Bidurit-hårdmetall",
                "establishment_year": 1950,
                "key_personnel": [
                    {
                        "name": "Paul Riesterer",
                        "position": "Verkst dir"
                    },
                    {
                        "name": "Heinz Matthiesen",
                        "position": "V verkst dir o försälin-chef"
                    }
                ]
            },
            {
                "company_name": "ESON PAC AB",
                "pnr": "430 20",
                "address": "Veddige, Box 42",
                "phone_number": "0340-306 20",
                "activity": "Tillverkar kartonger, kapslar o tråg. Offsettryck",
                "employees": 30,
                "annual_turnover": 3500000,
                "establishment_year": 1968,
                "key_personnel": [
                    {
                        "name": "ing anar Eliasson",
                        "position": "Verkst dir"
                    },
                    {
                        "name": "Dag Magnusson",
                        "position": "Försäljningschef"
                    }
                ]
            },
            {
                "company_name": "RYDÉN-MÖBLER AB",
                "pnr": "382 00",
                "address": "Nybro, Lilla Trädgårdsg 6",
                "phone_number": "0481-118 20",
                "activity": "Säljer stilmöbler",
                "employees": 57,
                "capital": 25000,
                "key_personnel": [
                    {
                        "name": "Gunnar Rydén",
                        "position": "Verkst dir"
                    }
                ]
            },
            {
                "company_name": "RYDQVIST, K O",
                "pnr": "182 11",
                "address": "Danderyd 1, Klubbv 5. Box 70",
                "phone_number": "08-755 2675",
                "postgiro": "333254",
                "activity": "Säljer kol- o grafitelektroder, syrgasverk, processlinjer, industriugnar, eldfast tegel, zirkonoxid o kiselkarbid-stavar",
                "establishment_year": 1914
            },
            {
                "company_name": "da ros",
                "pnr": "433 00",
                "address": "Partille",
                "phone_number": "031-44 08 80",
                "bank_details": {
                    "bankgiro": "55-0545",
                    "postgiro": "40480"
                },
                "activity": "Specialitet: kolvringar, kolvstångspackningar o cylinderfoder",
                "capital": 3000000,
                "key_personnel": [
                    {
                        "name": "Civiling Kurt Madsen",
                        "position": "Verkst dir"
                    }
                ],
                "establishment_year": 1851
            },
            {
                "company_name": "WESTMAN, NILS",
                "pnr": "113 52",
                "address": "Stockholm VA, Döbelnsg 40",
                "phone_number": "08-319150",
                "postgiro": "55344",
                "activity": "Agenturer för skinn-o pälsvaror samt pälstillbehör",
                "annual_turnover": 1500000,
                "key_personnel": [
                    {
                        "name": "Nils Westman",
                        "position": "Ägare o chef"
                    }
                ],
                "establishment_year": 1941
            },
            {
                "company_name": "NORDGAS, AB",
                "pnr": "11233",
                "address": "Stockholm, Kronobergsg. 21",
                "phone_number": "08-54 0 9 20",
                "activity": "Säljer mängdmätare för gasformiga media såsom gas, propan/butan, luft etc, varmvattenberedare o centralvärmepannor för stadsgas/gasol, tändsäkringar, termostater, regulatorer etc för stadsgas o gasol",
                "capital": 300000,
                "key_personnel": [
                    {
                        "name": "Hans Scherrer",
                        "position": "Verkst dir"
                    }
                ],
                "establishment_year": 1930
            },
            {
                "company_name": "DENTALBORRFABRIKEN AB",
                "pnr": "21142",
                "address": "Malmö, Storg 30",
                "phone_number": "040- 1198 50",
                "postgiro": "39075",
                "activity": "Tillverkar tandläkar-borrar",
                "capital": 170000,
                "key_personnel": [
                    {
                        "name": "Dir Bror Rohlin",
                        "position": "Ägare o chef"
                    }
                ],
                "establishment_year": 1947
            },
            {
                "company_name": "EHRENSTROM FLYG AB",
                "pnr": "16110",
                "address": "Bromma 10, Bromma Flygplats",
                "phone_number": "08-98 06 50",
                "bank_details": {
                    "bankgiro": "238-2992",
                    "postgiro": "611603-2"
                },
                "activity": "Taxi- o ambulansflyg med 2-motoriga propeller- o jetflygplan. Säljer flygplan, Aero Commander o Jet Commander",
                "employees": 31,
                "annual_turnover": 5000000,
                "capital": 600000,
                "key_personnel": [
                    {
                        "name": "Ingemar Ehrenström",
                        "position": "Styrelse"
                    },
                    {
                        "name": "Per-Ake Karlsson",
                        "position": "Ekonomichef"
                    },
                    {
                        "name": "Stig Wikman",
                        "position": "Tekn chef"
                    },
                    {
                        "name": "Tommy Köthnig",
                        "position": "Marknadschef"
                    },
                    {
                        "name": "Leif Ståhl",
                        "position": "Flygchef"
                    }
                ],
                "establishment_year": 1962
            },
            {
                "company_name": "TURITZ & CO, AB",
                "pnr": "415 30",
                "address": "Göteborg 13, Gamlestadsv 3. Box 13500",
                "phone_number": "031-25 03 00",
                "bank_details": {
                    "bankgiro": "16-0082, 41-0065",
                    "postgiro": "5250"
                },
                "employees": 12000,
                "annual_turnover": 1776400000,
                "capital": 125000000,
                "key_personnel": [
                    {
                        "name": "Erik Söderberg",
                        "position": "Verkst dir"
                    }
                ],
                "establishment_year": 1918
            },
            {
                "company_name": "TURNEX AB",
                "pnr": "41122",
                "address": "Göteborg, Husarg 30-32",
                "phone_number": "031-13 34 59, 13 37 09",
                "bank_details": {
                    "bankgiro": "501-4709",
                    "postgiro": "47898-2"
                },
                "activity": "Representant för Finska Pappers- o Kartongförädlare Förening, CONVERTA, Helsingfors, Finland",
                "dotterbolag": {
                    "address": "Turnex i Malmö AB, Gråbrödersg 2",
                    "phone_number": "040-9745 70"
                },
                "employees": 10,
                "capital": 15000,
                "key_personnel": [
                    {
                        "name": "Olle Jansson",
                        "position": "Styrelse"
                    },
                    {
                        "name": "Sune Lindblom",
                        "position": "Försäljn-chef"
                    }
                ],
                "establishment_year": 1962
            },
            {
                "company_name": "HAGAFORS STOLFABRIK, AB",
                "pnr": "57100",
                "address": "Nässjö, Box 70. Fabriksg",
                "phone_number": "0380-180 00",
                "bank_details": {
                    "bankgiro": "841-5002",
                    "postgiro": "11595-6"
                },
                "activity": "Tillverkning av stolar, möbler o ämnen",
                "capital": 300000,
                "key_personnel": [
                    {
                        "name": "Disp Björn Stålsmeden",
                        "position": "Verkst dir"
                    }
                ],
                "establishment_year": 1863
            },
            {
                "company_name": "HAGALUNDS METALLINDUSTRI AB",
                "pnr": "330 21",
                "address": "Reftele, Bruksg",
                "phone_number": "0371-200 75",
                "bank_details": {
                    "bankgiro": "14-275 2",
                    "postgiro": "132296-5"
                },
                "activity": "Bockade trådartiklar, gångjärn för brandskyddsdörrar",
                "employees": 6,
                "annual_turnover": 400000,
                "capital": 20000,
                "key_personnel": [
                    {
                        "name": "Bertil Grundin",
                        "position": "Verkst dir"
                    }
                ],
                "establishment_year": 1931
            },
            {
                "company_name": "HAGASTRÖMS TEGEL. BRUKS AB",
                "pnr": "80103",
                "address": "Gävle, Centralplan 5. Box 120",
                "phone_number": "026-12 00 58, 19 73 38",
                "postgiro": "22012",
                "activity": "Tillverkar fasadtegel, murtegel o tegelmjöl",
                "employees": 18,
                "annual_turnover": 400000,
                "capital": 80000,
                "key_personnel": [
                    {
                        "name": "Erik Nordström",
                        "position": "Verkst dir"
                    }
                ],
                "establishment_year": 1892
            },
            {
                "company_name": "HAGBERG, HEDENLUND & CO AB",
                "pnr": "40251",
                "address": "Göteborg 13, Gamlestadsv 6-8. Box 13021",
                "phone_number": "031-25 00 85",
                "bank_details": {
                    "bankgiro": "514-3185",
                    "postgiro": "40506-8"
                },
                "activity": "Importhandel med damkonfektion",
                "varunamn": "Hedenlunds",
                "employees": 10,
                "annual_turnover": 5000000,
                "capital": 100000,
                "key_personnel": [
                    {
                        "name": "John Larsson",
                        "position": "Dir"
                    }
                ],
                "establishment_year": 1891
            },
            {
                "company_name": "SVENSSON AB, FILIP N",
                "pnr": "104 35",
                "address": "Stockholm 23, Fack. Dannemorag 18",
                "phone_number": "08-24 4845",
                "bankgiro": "482-7358",
                "postgiro": "13036-9",
                "activity": "Elektr installationsmateriel i engros",
                "employees": 16,
                "annual_turnover": 5400000,
                "capital": 100000,
                "key_personnel": [
                    {
                        "name": "Arne Authén",
                        "position": "Verkst din"
                    }
                ],
                "establishment_year": 1932
            },
            {
                "company_name": "SVENSSONS EL.BYRÄ AB, FRITHIOF",
                "pnr": "114 53",
                "address": "Stockholm, Grevg 7",
                "phone_number": "08-6105 79, 61 84 48",
                "postgiro": "53057-6",
                "activity": "Elektr installationsarbeten. Försäljer elektr material, belysningsförslag",
                "capital": 50000,
                "key_personnel": [
                    {
                        "name": "Knut Albert Berggren",
                        "position": "Verkst dir"
                    }
                ],
                "establishment_year": 1954
            }
        ]
    }
}