{
    "original": "KULLGRENS ENKA AB\n\nPnr 451 01\n\nUddevalla 1, Strömstadsv 35. Box\n80. Tel 0522-14440. Tga Kullgrens.\nTelex 42055 K ENKA S\nVerksamhet: Företaget bryter o\nförädlar natursten. Stenbrott i\nBohuslän, Småland o Skåne samt i Norge\no Finland. Förädlingsverk i Skåne.\nVerkstad i Göteborg. Genom\ndotterföretag i Italien o Frankrike direkt\nsamarbete med sydeuropeisk\nstenindustri\n\nProduktion: Blocksten,\nbyggnadssten, gravvårdar, skulpterade\narbeten, halvfabrikat, kantsten.\nTrädgårdssten\n\nFörsäljningskontor: Stockholm,\nGöteborg, Malmö, Broby,\nTrollhättan samt Abo, Finland, Carrara,\nItalien o Paris, Frankrike.\nDotterföretaget Kullgrens Handels\nAB, Broby: Partiförsäljning av\nförnödenheter\nAntal anställda: 600\nÅrsomsättning: 40 000 000\nAktiekapital: 2 880 000\nStyrelse: Dir Bertil Thorburn\n(ordf), dir Stig Danielson, fondkomm\nAlf Kullgren, adv Love Mannheimer,\nhandl Peter K:son Mark\nVerkst dir: Stig Danielson\nEtableringsår: 1842\nOmbildat till aktiebolag 1897.\n\nKULLGRENS HANDELS AB\n\nPnr 280 60\n\nBroby. Tel 044-407 4 5\nVerksamhet: Partihandel med\nindu-strifornödenheter såsom maskiner,\nverktyg o förbrukningsmaterial\nSe vidare Kullgrens Enka AB.\n\nKULLGRENS\nRÖRLEDNINGS-FIRMA AB\n\nPnr 532 00\n\nSkara, Sankt Anneg 23. Tel\n0511-133 70. Bankgiro 21-9822. Postgiro\n76542-7\n\nVerksamhet: WS-entreprenader o\n-service. Säljer WS-material\nAntal anställda: 90\nÅrsomsättning: 10 000 000\nAktiekapital: 35 000\nVerkst dir. Ing Karl-Axel Kullgren\nEtableringsår: 1926.\n\nRICHARDSON, AB JANNE\n\nPnr 302 34\n\nHalmstad, Hvitfeldtsg 14. Tel\n035-1180 40. Bankgiro 42-3606. Postgiro\n30540. Tga Richardi\n\nVerksamhet: Skofabrik.\nAuktoriserad Fordförsäljare i Halmstad o\nLaholm genom dotterbolaget\nRichardsons Bil AB\nAntal anstäUda: 57\nÅrsomsättning: 5 200 000\nAktiekapital: 600000\nVeikst dir: Adv Stig Pehrsson\nEtableringsår: 1898.\n\nSVENSKA Dl PRO AB\n\nPnr 290 34\n\nFjälkinge, Box 45. Tel 044-504 40.\nBankgiro 632-5724. Postgiro\n331084-4\n\nVerksamhet Tillverkar o\nexporterar texturerat vegetabiliskt protein\nVarunamn: Dipro\nAntal anställda: 3\nAktiekapital: 300000\nStyrelse: Dir Sixten Holmquist\n(ordf), disp Lennart Bergman,\nMr Thomas B Humphrey\nVerkst dir: Sixten Holmquist\nAdm-chef: Disp Lennart Bergman\nTeknisk chef: Ing C Arvid Berkelind\nProduktchef: Civilekonom Stig\nMalmberg\n\nEtableringsår: 1969.\n\nCORDINAL, INDUSTRI AB\n\nPnr 40241\n\nGöteborg 12, Box 12077. Karl\nJohansg 152. Tel 031-12 47 00.\nBankgiro 512-7477. Postgiro\n521718. Tga Sytex\nVerksamhet: Tillverkar sysilke o\nsytråd. Försäljning genom\nMöln-lycke Sytråd AB, Göteborg.\n\nCORDINATOR, AB\n\nPnr 50103\n\nBorås 1, Box 101. Armbåga. Tel\n033-1001 30. Bankgiro 531-5908.\nPostgiro 471191-7. Telex 36104\nVerksamhet: Säljer metervaror till\nkonfektions- o textilindustrin.\nSpecialitet: jerseyvävnader i såväl\ntryckt som enfärgat utförande.\nLönarbete i egen regi\nAntal anställda: 4\nÅrsomsättning: 3 500 000\nAktiekapital: 120 000\nStyrelse: Dir Staffan Gran (ordf),\nbankkamrer Gottfrid Månsson, adv\nBo Redgard\n\nVerkst dir: Björn Fridell\nEtableringsår: 1964.\n\nwagner ab, glinther\n\nPnr 104 30\n\nStockholm 45, Kammakarg 21. Box\n45104. Tel 08-23 5930. Bankgiro\n56-5222. Postgiro 54204. Tga\nGUntherwagner\n\nVerksamhet: Säljer kontorsartiklar\no teckningsmateriel\nVarunamn: Pelikan\nAntal anställda: 16\nAktiekapital: 75 000\nVerkst dir: Ernst LUhert\nEtableringsår: 1943.\n\nÅrsomsättning: 2 000 000\nAktiekapital: 75 000\n\nInnehavare: Bo Reichenberg\nEtableringsår: 1960.\n\nHAWA-AGENTURER, AB\n\nPnr 102 73\n\nStockholm 9, Box 9184. Tel\n08-84 3611, 84 3612. Bankgiro\n56-3476. Postgiro 250943. Tga\nHawa-sig. Telex 10519\nVerksamhet: Agenturrörelse med\nförpackningsmaskiner m m\nAktiekapital: 10 000\nEtableringsår: 1945.\n\nHOBERGS TRÄINDUSTRI AB\n\nPnr 440 20\n\nVårgårda, Hoberg. Tel 0322-204 83.\nBankgiro 894-9174. Postgiro\n447136\n\nVerksamhet: Serietillverkade\nfärdiga ämnen till lådor o backar för\nköksinredningar\nAntal anställda: 15\nAktiekapital: 90 000\nÄgare o chefer: Y H Attebring,\nS A J Ellström\nEtableringsår 1954.\n\nHOHULTSLÄTTSSPEGEL.\nINDUSTRI, NYA AB\n\nPnr 360 75\n\nAls termo, Box 22. Tel 0481-610 45.\nBankgiro 14-7035. Postgiro 324416-7\nVerksamhet: Tillverkar speglar,\nhallbord o toalettbord\nAntal anstäUda: 20\nAktiekapital: 40 500\nVerkst dir: Erie Wall\nEtableringsår 1957.\n\nHOHULTSLÄTTS VÄRME &amp;\nSANITET\n\nPnr 360 75\n\nAlstermo, Box 95. Storg 65. Tel\n0481-612 21, 612 22. Bankgiro\n147-0103. Postgiro 399250-0\nVerksamhet Värme-, olje-,\nventilations- o sanitetsteknik\nAntal anstäUda: 12\nÅrsomsättning: 1600 000\nChef: Dir Arne Johansson\nEtableringsår: 1951.\n\nHÖLJE TOFFELFABRIK &amp;\nTRÄ FORÄDLING, AB\n\nPnr 293 00\n\nOlofström, Box 63. Tel 0454-404 10.\n400 10. Bankgiro 151-6897. Postgiro\n284793-7\n\nVerksamhet: Trätoffelbottnar\nAntal anställda: 36\nÅrsomsättning: 2 500 000\nAktiekapital: 140 000\nVerkst dir: Stig Jönsson\nEtableringsår 1912\nOmbildat till aktiebolag 1953.\n\nHOLLANDER &amp; CO AB, F\n\nPnr 103 82\n\nStockholm 7, Birger Jarlsg 6 B.\nBox 7063. Tel 08-22 68 00. Telex\n1590. Tga Hollanderco\nVerksamhet: Hudar o skinn,\nindustriråvaror, maskinutrustningar\nAktiekapital: 1500 000\nVerkst dir: Fritz Hollander\nEtableringsår: 1944.\n\nHOLLINGWORTH &amp; CO I\nOREBRO AB, ANDREW\n\nPnr 70103\n\nÖrebro 1, Hjärstav 16-18. Box 184.\nTel 019-11 92 80. Bankgiro\n614-3531. Postgiro 28483-6. Tga\nHol-lingworths\n\nVerksamhet: Försäljning av\nsani-tet, vatten- o\nvärmeledningsmaterial, maskiner o\nmaskinförnödenheter\n\nAntal anställda: 25\nAktiekapital: 252000\nStyrelse: Dir Per Olov Lindeberg\n\n(ordf), ing Börje Holmström,\ntaxintendent Kjell Holmström, ing\nGunnar Lindeberg\nVerkst dir: Ing Börje Holmström\nEtableringsår: 1928.\n\nVALBO TRÄVARU AB\n\nPnr 81043\n\nSödra Valbo, Box 244. Smäckv 28.\nTel 026-13 20 10 Postgiro\n125044-8\n\nVerksamhet: Brädgård, hyvleri o\nbyggmaterialförsäljning\nAntal anställda: 25\nÅrsomsättning: 4 000 000\nAktiekapital: 100 000\nVerkst din Disp Nils Andersson\nEtableringsår: 1944.\n\nVALDEMARSVIKS\nMEKANO-SVETS AB\n\nPnr 615 00\n\nValdemarsvik, Vammarg 6. Box 66.\nTel 0123-10047, 105 22. Bankgiro\n674-4312. Postgiro 176222-8\nVerksamhet: Beställnings- o\nlego-arbeten av järn- o\nplåtkonstruktioner. Specialitë: plåtdetaljer av\n1-3 m/m plåttjocklek\nAntal anställda: 40\nÅrsomsättning: 2 500 000\nAktiekapital: 30 000\nVerkst dir: Harry Amér\nEtableringsår: 1967.\n\nSHIPS-MECHANO AB\n\nPnr 43139\n\nMölndal, Wennerbergsg 38. Tel\n031-87 22 85, 87 22 86. Bankgiro\n506-1544. Postgiro 429593-7. Tga\nShipsmechano\n\nVerksamhet: Utför\nfartygsreparationer såsom maskinarbeten\n(handarbeten), elektr svetsning mm.\nSpe-ciaUtet: resemontage\nAntal anställda: 12\nÅrsomsättning: 600 000\nAktiekapital: 25 000\nVeikst dir: Erik H Jansen\nEtableringsår 1957.",
    "structured": {
        "1": {
            "company_name": "KULLGRENS ENKA AB",
            "pnr": "451 01",
            "address": "Uddevalla 1, Strömstadsv 35. Box 80",
            "phone_number": "0522-14440",
            "bank_details": {
                "bankgiro": "Not available",
                "postgiro": "Not available"
            },
            "activity": "Företaget bryter o förädlar natursten. Stenbrott i Bohuslän, Småland o Skåne samt i Norge o Finland. Förädlingsverk i Skåne. Verkstad i Göteborg. Genom dotterföretag i Italien o Frankrike direkt samarbete med sydeuropeisk stenindustri. Produktion: Blocksten, byggnadssten, gravvårdar, skulpterade arbeten, halvfabrikat, kantsten. Trädgårdssten. Försäljningskontor: Stockholm, Göteborg, Malmö, Broby, Trollhättan samt Abo, Finland, Carrara, Italien o Paris, Frankrike. Dotterföretaget Kullgrens Handels AB, Broby: Partiförsäljning av förnödenheter",
            "employees": 600,
            "annual_turnover": 40000000,
            "capital": 2880000,
            "key_personnel": [
                {
                    "name": "Bertil Thorburn",
                    "position": "Ordförande"
                },
                {
                    "name": "Stig Danielson",
                    "position": "Direktör"
                },
                {
                    "name": "Alf Kullgren",
                    "position": "Fondkomm"
                },
                {
                    "name": "Love Mannheimer",
                    "position": "Advokat"
                },
                {
                    "name": "Peter K:son Mark",
                    "position": "Handlare"
                }
            ],
            "establishment_year": 1842
        },
        "2": {
            "company_name": "KULLGRENS HANDELS AB",
            "pnr": "280 60",
            "address": "Broby",
            "phone_number": "044-407 4 5",
            "activity": "Partihandel med indu-strifornödenheter såsom maskiner, verktyg o förbrukningsmaterial. Se vidare Kullgrens Enka AB."
        },
        "3": {
            "company_name": "KULLGRENS RÖRLEDNINGS-FIRMA AB",
            "pnr": "532 00",
            "address": "Skara, Sankt Anneg 23",
            "phone_number": "0511-133 70",
            "bank_details": {
                "bankgiro": "21-9822",
                "postgiro": "76542-7"
            },
            "activity": "WS-entreprenader o-service. Säljer WS-material",
            "employees": 90,
            "annual_turnover": 10000000,
            "capital": 35000,
            "key_personnel": [
                {
                    "name": "Ing Karl-Axel Kullgren",
                    "position": "Verkst dir."
                }
            ],
            "establishment_year": 1926
        },
        "4": {
            "company_name": "RICHARDSON, AB JANNE",
            "pnr": "302 34",
            "address": "Halmstad, Hvitfeldtsg 14",
            "phone_number": "035-1180 40",
            "bank_details": {
                "bankgiro": "42-3606",
                "postgiro": "30540"
            },
            "activity": "Skofabrik. Auktoriserad Fordförsäljare i Halmstad o Laholm genom dotterbolaget Richardsons Bil AB",
            "employees": 57,
            "annual_turnover": 5200000,
            "capital": 600000,
            "key_personnel": [
                {
                    "name": "Adv Stig Pehrsson",
                    "position": "Verkst dir"
                }
            ],
            "establishment_year": 1898
        },
        "5": {
            "company_name": "SVENSKA Dl PRO AB",
            "pnr": "290 34",
            "address": "Fjälkinge, Box 45",
            "phone_number": "044-504 40",
            "bank_details": {
                "bankgiro": "632-5724",
                "postgiro": "331084-4"
            },
            "activity": "Tillverkar o exporterar texturerat vegetabiliskt protein. Varunamn: Dipro",
            "employees": 3,
            "capital": 300000,
            "key_personnel": [
                {
                    "name": "Sixten Holmquist",
                    "position": "Ordf"
                },
                {
                    "name": "Lennart Bergman",
                    "position": "Disp"
                },
                {
                    "name": "Thomas B Humphrey",
                    "position": "Mr"
                }
            ],
            "establishment_year": 1969
        },
        "6": {
            "company_name": "CORDINAL, INDUSTRI AB",
            "pnr": "40241",
            "address": "Göteborg 12, Box 12077. Karl Johansg 152",
            "phone_number": "031-12 47 00",
            "bank_details": {
                "bankgiro": "512-7477",
                "postgiro": "521718"
            },
            "activity": "Tillverkar sysilke o sytråd. Försäljning genom Möln-lycke Sytråd AB, Göteborg"
        },
        "7": {
            "company_name": "CORDINATOR, AB",
            "pnr": "50103",
            "address": "Borås 1, Box 101. Armbåga",
            "phone_number": "033-1001 30",
            "bank_details": {
                "bankgiro": "531-5908",
                "postgiro": "471191-7"
            },
            "activity": "Säljer metervaror till konfektions- o textilindustrin. Specialitet: jerseyvävnader i såväl tryckt som enfärgat utförande. Lönarbete i egen regi",
            "employees": 4,
            "annual_turnover": 3500000,
            "capital": 120000,
            "key_personnel": [
                {
                    "name": "Staffan Gran",
                    "position": "Ordf"
                },
                {
                    "name": "Gottfrid Månsson",
                    "position": "Bankkamrer"
                },
                {
                    "name": "Bo Redgard",
                    "position": "Adv"
                },
                {
                    "name": "Björn Fridell",
                    "position": "Verkst dir"
                }
            ],
            "establishment_year": 1964
        },
        "8": {
            "company_name": "wagner ab, glinther",
            "pnr": "104 30",
            "address": "Stockholm 45, Kammakarg 21. Box 45104",
            "phone_number": "08-23 5930",
            "bank_details": {
                "bankgiro": "56-5222",
                "postgiro": "54204"
            },
            "activity": "Säljer kontorsartiklar o teckningsmateriel. Varunamn: Pelikan",
            "employees": 16,
            "capital": 75000,
            "key_personnel": [
                {
                    "name": "Ernst LUhert",
                    "position": "Verkst dir"
                }
            ],
            "establishment_year": 1943
        },
        "9": {
            "company_name": "HAWA-AGENTURER, AB",
            "pnr": "102 73",
            "address": "Stockholm 9, Box 9184",
            "phone_number": "08-84 3611, 84 3612",
            "bank_details": {
                "bankgiro": "56-3476",
                "postgiro": "250943"
            },
            "activity": "Agenturrörelse med förpackningsmaskiner m m",
            "capital": 10000,
            "employees": null,
            "annual_turnover": null,
            "key_personnel": null,
            "establishment_year": 1945
        },
        "10": {
            "company_name": "HOBERGS TRÄINDUSTRI AB",
            "pnr": "440 20",
            "address": "Vårgårda, Hoberg",
            "phone_number": "0322-204 83",
            "bank_details": {
                "bankgiro": "894-9174",
                "postgiro": "447136"
            },
            "activity": "Serietillverkade färdiga ämnen till lådor o backar för köksinredningar",
            "employees": 15,
            "capital": 90000,
            "key_personnel": [
                {
                    "name": "Y H Attebring",
                    "position": "Ägare"
                },
                {
                    "name": "S A J Ellström",
                    "position": "Ägare"
                }
            ],
            "establishment_year": 1954
        },
        "11": {
            "company_name": "HOHULTSLÄTTSSPEGEL. INDUSTRI, NYA AB",
            "pnr": "360 75",
            "address": "Alstermo, Box 22",
            "phone_number": "0481-610 45",
            "bank_details": {
                "bankgiro": "14-7035",
                "postgiro": "324416-7"
            },
            "activity": "Tillverkar speglar, hallbord o toalettbord",
            "employees": 20,
            "capital": 40500,
            "key_personnel": [
                {
                    "name": "Erie Wall",
                    "position": "Verkst dir"
                }
            ],
            "establishment_year": 1957
        },
        "12": {
            "company_name": "HOHULTSLÄTTS VÄRME & SANITET",
            "pnr": "360 75",
            "address": "Alstermo, Box 95. Storg 65",
            "phone_number": "0481-612 21, 612 22",
            "bank_details": {
                "bankgiro": "147-0103",
                "postgiro": "399250-0"
            },
            "activity": "Värme-, olje-, ventilations- o sanitetsteknik",
            "employees": 12,
            "annual_turnover": 1600000,
            "key_personnel": [
                {
                    "name": "Arne Johansson",
                    "position": "Direktör"
                }
            ],
            "establishment_year": 1951
        },
        "13": {
            "company_name": "HÖLJE TOFFELFABRIK & TRÄ FORÄDLING, AB",
            "pnr": "293 00",
            "address": "Olofström, Box 63",
            "phone_number": "0454-404 10, 400 10",
            "bank_details": {
                "bankgiro": "151-6897",
                "postgiro": "284793-7"
            },
            "activity": "Trätoffelbottnar",
            "employees": 36,
            "annual_turnover": 2500000,
            "capital": 140000,
            "key_personnel": [
                {
                    "name": "Stig Jönsson",
                    "position": "Verkst dir"
                }
            ],
            "establishment_year": 1912
        },
        "14": {
            "company_name": "HOLLANDER & CO AB, F",
            "pnr": "103 82",
            "address": "Stockholm 7, Birger Jarlsg 6 B. Box 7063",
            "phone_number": "08-22 68 00",
            "bank_details": {
                "bankgiro": "Not available",
                "postgiro": "Not available"
            },
            "activity": "Hudar o skinn, industriråvaror, maskinutrustningar",
            "capital": 1500000,
            "key_personnel": [
                {
                    "name": "Fritz Hollander",
                    "position": "Verkst dir"
                }
            ],
            "establishment_year": 1944
        },
        "15": {
            "company_name": "HOLLINGWORTH & CO I OREBRO AB, ANDREW",
            "pnr": "70103",
            "address": "Örebro 1, Hjärstav 16-18. Box 184",
            "phone_number": "019-11 92 80",
            "bank_details": {
                "bankgiro": "614-3531",
                "postgiro": "28483-6"
            },
            "activity": "Försäljning av sani-tet, vatten- o värmeledningsmaterial, maskiner o maskinförnödenheter",
            "employees": 25,
            "capital": 252000,
            "key_personnel": [
                {
                    "name": "Per Olov Lindeberg",
                    "position": "Ordf"
                },
                {
                    "name": "Börje Holmström",
                    "position": "Ing"
                },
                {
                    "name": "Kjell Holmström",
                    "position": "Taxintendent"
                },
                {
                    "name": "Gunnar Lindeberg",
                    "position": "Ing"
                }
            ],
            "establishment_year": 1928
        },
        "16": {
            "company_name": "VALBO TRÄVARU AB",
            "pnr": "81043",
            "address": "Södra Valbo, Box 244. Smäckv 28",
            "phone_number": "026-13 20 10",
            "bank_details": {
                "bankgiro": "Not available",
                "postgiro": "125044-8"
            },
            "activity": "Brädgård, hyvleri o byggmaterialförsäljning",
            "employees": 25,
            "annual_turnover": 4000000,
            "capital": 100000,
            "key_personnel": [
                {
                    "name": "Disp Nils Andersson",
                    "position": "Verkst dir"
                }
            ],
            "establishment_year": 1944
        },
        "17": {
            "company_name": "VALDEMARSVIKS MEKANO-SVETS AB",
            "pnr": "615 00",
            "address": "Valdemarsvik, Vammarg 6. Box 66",
            "phone_number": "0123-10047, 105 22",
            "bank_details": {
                "bankgiro": "674-4312",
                "postgiro": "176222-8"
            },
            "activity": "Beställnings- o lego-arbeten av järn- o plåtkonstruktioner. Specialitë: plåtdetaljer av 1-3 m/m plåttjocklek",
            "employees": 40,
            "annual_turnover": 2500000,
            "capital": 30000,
            "key_personnel": [
                {
                    "name": "Harry Amér",
                    "position": "Verkst dir"
                }
            ],
            "establishment_year": 1967
        },
        "18": {
            "company_name": "SHIPS-MECHANO AB",
            "pnr": "43139",
            "address": "Mölndal, Wennerbergsg 38",
            "phone_number": "031-87 22 85, 87 22 86",
            "bank_details": {
                "bankgiro": "506-1544",
                "postgiro": "429593-7"
            },
            "activity": "Utför fartygsreparationer såsom maskinarbeten (handarbeten), elektr svetsning mm. Specialitet: resemontage",
            "employees": 12,
            "annual_turnover": 600000,
            "capital": 25000,
            "key_personnel": [
                {
                    "name": "Erik H Jansen",
                    "position": "Verkst dir"
                }
            ],
            "establishment_year": 1957
        }
    }
}