{
    "original": "FOR\n\nFORSBERGS FURLAG AB,\nBENGT\n\nPnr 21140\n\nMalmö, S Tullg 4. Tel 040-763 20.\n\nBankgiro 156-4129. Postgiro\n\n430667-6. Tga Godbok\n\nVerksamhet: Bokförlagsrörelse o\n\nfilmproduktion\n\nAntal anställda: 5\n\nAktiekapital: 15 000\n\nVerkst dir: Bokförl Bengt Porsberg\n\nEtableringsår: 1944.\n\nFORSBERGS EFTR STÅL.\nSTÄMPELFABRIK, E\n\nPnr 644 00\n\nTorshälla, Box 16. Tel 016-550 52.\nBankgiro 62-3516. Postgiro 103357-0\nVerksamhet: Tillverkar stål- o\nmässingsstämplar, sifferhjul o\nstämpelrullar. Utför maskingravering\nChef: Fabr A Hofmann\nEtableringsår: 1917.\n\nATEKA AB\n\nPnr 401 20\n\nGöteborg 1, Box 49, Importg 16-18.\n\nTel 031-52 04 50. Bankgiro 50-0425.\nPostgiro 3885. Tga Drogvall.\nTelex 2255\n\nVerksamhet: Kemisk tekniska\nartiklar, sjukvårdsartiklar o färger\nFilialer: 201 22 Malmö 1. Celsiusg\n41. Box 227. Tel 040-93 43 20.\nTelex 3156\n\n10271 Stockholm 9, Sjöviksbacken\n19. Box 9079. Tel 08-19 01 80.\nTelex 1655\nAntal anställda: 21\nÅrsomsättning: 25 000 000\nVerkst dir: Owe Sandegren\nEtableringsår: 1960\nSysterbolag till Adaco, Scandistor,\nFransk-Svenska Parfymkompaniet,\nMavello samt Adaco i Danmark o\nNorge.\n\nDotterbolag till Consiva AB.\n\nATELJÉ\n\nse resp namn.\n\nATHENA, AB\n\nPnr 27100\n\nYstad, Ekenäsg. Box 27. Tel\n0411-13785. Bankgiro 670-2120.\nPostgiro 99020-0. Tga Athena\nVerksamhet: Tillverkar möbler o\nskolinredningar\nAntal anställda: 50\nAktiekapital: 20 500\nVerkst dir: Anton Ch Persson\nEtableringsår: 1936.\n\nGELLERÅSEN, AB\n\nPnr 69100\n\nKarlskoga. Tel 0586-150 05.\nBankgiro 109-0240. Postgiro 332062-9\nVerksamhet: Betong, grus, maskiner\no transporter\nAntal anställda: 170\nÅrsomsättning: 19 000 000\nAktiekapital: 500 000\nVerkst dir: Sveneric Frisk\nEtableringsår: 1946.\n\nBUR\n\n451592-0. Tga Bungesven.\nTelex 19174\n\nVerksamhet: I samarbete med\nmoderbolaget Bunge &amp; Born Lda,\nBuenos Aires o systerföretag i\nandra länder bedrives import o\nexport av spannmål, fodervaror,\noljefröer, vegetabiliska oljor m m\nAntal anställda: 5\nAktiekapital: 200 000\nVerkst dir: Folke Brynolf\nEtableringsår: 1950.\n\nDICKMANS VERKSTADER, AB\n\nPnr 170 23\n\nBarkarby, Girov 7, Veddesta\nindustriområde. Tel 08-36 27 55.\nBankgiro 56-7014. Postgiro 52785-3\nVerksamhet: Utför plåtarbeten\nAktiekapital: 147 000\nVerkst dir: John Dickman\nEtableringsår: 1899\nOmbildat till aktiebolag 1928.\n\nDICKSON &amp; AHLMO\n\nPnr 400 16\n\nGöteborg 33, Kungsportsavenyn 1.\nBox 53221. Tel 031-139120,\n13 2081. Tga Dicksal\nVerksamhet: Säljer järn, plåt, stål,\nrör o metaller\nVerkst dir: G A Ahlmo\nEtableringsår: 1946.\n\nMÜNTZING &amp; CO AB, IVAR\n\nPnr 402 22\n\nGöteborg 5, Box 5058. Tegnérsg\n16, Tel 031-16 31 34, 16 31 35.\nBankgiro 847-7630. Postgiro 40522-5\nVerksamhet: Maskiner o\nförnödenheter för pappersbruk o gjuterier\nAntal anställda: 20\nÅrsomsättning: 7 000 000\nAktiekapital: 150 000\nVeikst dir: Evert Larsson\nEtableringsår: 1885.\n\nMYREN &amp; CO AB,\nINGENIÖRSFIRMAN\n\nPnr 436 00\n\nAskim, Box 1055. Industriv. Tel\n031-28 20 60. Bankgiro 506-6758.\nPostgiro 41745-1. Tga\nElektro-myrén. Telex 21313 ELMYREN S\nVerksamhet: Elektromek verkstad,\nsäljer o köper elektr maskiner\nVerkst dir: Harald Myren\nEtableringsår: 1919.\n\nAktiekapital: 5 000 000\nVeikst dir. Einar Järnland\nEtableringsår: 1932.\n\nAHLBERG &amp; BENGTSSON, AB\n\nPnr 26122\n\nLandskrona 1, N Långg 19. Box 5.\nTel 0418-163 40. Bankgiro\n660-0027. Postgiro 13883-4.\nTga Ahlbengt\n\nVerksamhet: Elektr\ninstallationsmateriel o belysningsarmatur i en\ngros. VVS o elektr installationer\nAntal anställda: 82\nAktiekapital: 270000\nVerkst dir: Ulf Bengtsson\nEtableringsår: 1894\nOmbildat till aktiebolag 1908.\n\nAHLBERG &amp; NILSSON\nARKIV-KOPIERING ANA AB\n\nPnr 183 64\n\nTäby, Viggbyholmsv 75. Tel\n08-7561075, 7561076. Bankgiro\n726-9129. Postgiro 354452\nVerksamhet: Arkivfotografering.\nBildkort. Skaländringar på plast\nAktiekapital: 20 000\nChef: Frk Ingrid Ahlberg\nEtableringsår: 1948.\n\nTERMATOR SUDERBLOM&amp;CO\n\nPnr 114 34\n\nStockholm. Styckjunkarg 7. Tel\n08-210900. Bankgiro 73-1629.\nPostgiro 253417\n\nVerksamhet: Säljer varm\nluftsaggregat Termator för öppna spisar\nVarunamn: Termator\nProkurist: Rune Pettersson\nEtableringsår: 1946.\n\nSVEATRADE, AB\n\nPnr 163 21\n\nSpånga 1, Box 32. Winqvists v 6.\nTel 08-760 28 80. Bankgiro\n700-3940. Postgiro 250927-1. Tga\nAtilamaskiner. Telex 17088\nVerksamhet: Säljer\nhydraulgräv-maskiner o kranar samt\nbetong-sprutaggregat\n\nVarunamn: Atila, Meyco Piccola\nAktiekapital: 1000 000\nVerkst dir: Per Åkerman\nEtableringsår: 1946.\n\nNÄVRAGOL SÅGVERKS AB\n\nPnr 360 62\n\nLångasjö. Tel 0477-502 60. Tga\nGeijerträ. Telex 4613 GEIJER S\n\nVerksamhet: Tillverkar sågade o\nhyvlade trävaror\nAntal anstäUda: 50\nAktiekapital: 500 000\nVerkst dir: Disp Herbert Geijer\nEtableringsår: 1956.",
    "structured": {
        "1": {
            "company_name": "FORSBERGS FURLAG AB",
            "address": "S Tullg 4",
            "phone_number": "040-763 20",
            "bank_details": {
                "bankgiro": "156-4129",
                "postgiro": "430667-6"
            },
            "activity": "Bokförlagsrörelse o filmproduktion",
            "employees": 5,
            "capital": 15000,
            "key_personnel": [
                {
                    "name": "Bengt Porsberg",
                    "position": "Bokförl"
                }
            ],
            "establishment_year": 1944
        },
        "2": {
            "company_name": "FORSBERGS EFTR STÅL",
            "address": "Box 16",
            "phone_number": "016-550 52",
            "bank_details": {
                "bankgiro": "62-3516",
                "postgiro": "103357-0"
            },
            "activity": "Tillverkar stål- o mässingsstämplar, sifferhjul o stämpelrullar. Utför maskingravering",
            "employees": null,
            "key_personnel": [
                {
                    "name": "A Hofmann",
                    "position": "Fabr"
                }
            ],
            "establishment_year": 1917
        },
        "3": {
            "company_name": "ATEKA AB",
            "address": "Box 49, Importg 16-18",
            "phone_number": "031-52 04 50",
            "bank_details": {
                "bankgiro": "50-0425",
                "postgiro": "3885"
            },
            "activity": "Kemisk tekniska artiklar, sjukvårdsartiklar o färger",
            "employees": 21,
            "annual_turnover": 25000000,
            "key_personnel": [
                {
                    "name": "Owe Sandegren",
                    "position": "Verkst dir"
                }
            ],
            "establishment_year": 1960
        },
        "4": {
            "company_name": "ATHENA, AB",
            "address": "Ekenäsg. Box 27",
            "phone_number": "0411-13785",
            "bank_details": {
                "bankgiro": "670-2120",
                "postgiro": "99020-0"
            },
            "activity": "Tillverkar möbler o skolinredningar",
            "employees": 50,
            "capital": 20500,
            "key_personnel": [
                {
                    "name": "Anton Ch Persson",
                    "position": "Verkst dir"
                }
            ],
            "establishment_year": 1936
        },
        "5": {
            "company_name": "GELLERÅSEN, AB",
            "address": null,
            "phone_number": "0586-150 05",
            "bank_details": {
                "bankgiro": "109-0240",
                "postgiro": "332062-9"
            },
            "activity": "Betong, grus, maskiner o transporter",
            "employees": 170,
            "annual_turnover": 19000000,
            "capital": 500000,
            "key_personnel": [
                {
                    "name": "Sveneric Frisk",
                    "position": "Verkst dir"
                }
            ],
            "establishment_year": 1946
        },
        "6": {
            "company_name": "BUR",
            "pnr": "451592-0",
            "activity": "I samarbete med moderbolaget Bunge & Born Lda, Buenos Aires o systerföretag i andra länder bedrives import o export av spannmål, fodervaror, oljefröer, vegetabiliska oljor m m",
            "employees": 5,
            "capital": 200000,
            "key_personnel": [
                {
                    "name": "Folke Brynolf",
                    "position": "Verkst dir"
                }
            ],
            "establishment_year": 1950
        },
        "7": {
            "company_name": "DICKMANS VERKSTADER, AB",
            "address": "Girov 7, Veddesta industriområde",
            "phone_number": "08-36 27 55",
            "bank_details": {
                "bankgiro": "56-7014",
                "postgiro": "52785-3"
            },
            "activity": "Utför plåtarbeten",
            "capital": 147000,
            "key_personnel": [
                {
                    "name": "John Dickman",
                    "position": "Verkst dir"
                }
            ],
            "establishment_year": 1899
        },
        "8": {
            "company_name": "DICKSON & AHLMO",
            "pnr": "400 16",
            "address": "Kungsportsavenyn 1, Box 53221",
            "phone_number": "031-139120, 13 2081",
            "activity": "Säljer järn, plåt, stål, rör o metaller",
            "key_personnel": [
                {
                    "name": "G A Ahlmo",
                    "position": "Verkst dir"
                }
            ],
            "establishment_year": 1946
        },
        "9": {
            "company_name": "MÜNTZING & CO AB, IVAR",
            "address": "Box 5058. Tegnérsg 16",
            "phone_number": "031-16 31 34, 16 31 35",
            "bank_details": {
                "bankgiro": "847-7630",
                "postgiro": "40522-5"
            },
            "activity": "Maskiner o förnödenheter för pappersbruk o gjuterier",
            "employees": 20,
            "annual_turnover": 7000000,
            "capital": 150000,
            "key_personnel": [
                {
                    "name": "Evert Larsson",
                    "position": "Veikst dir"
                }
            ],
            "establishment_year": 1885
        },
        "10": {
            "company_name": "MYREN & CO AB, INGENIÖRSFIRMAN",
            "address": "Box 1055. Industriv",
            "phone_number": "031-28 20 60",
            "bank_details": {
                "bankgiro": "506-6758",
                "postgiro": "41745-1"
            },
            "activity": "Elektromek verkstad, säljer o köper elektr maskiner",
            "capital": 5000000,
            "key_personnel": [
                {
                    "name": "Harald Myren",
                    "position": "Verkst dir"
                },
                {
                    "name": "Einar Järnland",
                    "position": "Veikst dir"
                }
            ],
            "establishment_year": 1932
        },
        "11": {
            "company_name": "AHLBERG & BENGTSSON, AB",
            "address": "N Långg 19. Box 5",
            "phone_number": "0418-163 40",
            "bank_details": {
                "bankgiro": "660-0027",
                "postgiro": "13883-4"
            },
            "activity": "Elektr installationsmateriel o belysningsarmatur i en gros. VVS o elektr installationer",
            "employees": 82,
            "capital": 270000,
            "key_personnel": [
                {
                    "name": "Ulf Bengtsson",
                    "position": "Verkst dir"
                }
            ],
            "establishment_year": 1894
        },
        "12": {
            "company_name": "AHLBERG & NILSSON ARKIV-KOPIERING ANA AB",
            "address": "Viggbyholmsv 75",
            "phone_number": "08-7561075, 7561076",
            "bank_details": {
                "bankgiro": "726-9129",
                "postgiro": "354452"
            },
            "activity": "Arkivfotografering. Bildkort. Skaländringar på plast",
            "capital": 20000,
            "key_personnel": [
                {
                    "name": "Frk Ingrid Ahlberg",
                    "position": "Chef"
                }
            ],
            "establishment_year": 1948
        },
        "13": {
            "company_name": "TERMATOR SUDERBLOM&CO",
            "address": "Styckjunkarg 7",
            "phone_number": "08-210900",
            "bank_details": {
                "bankgiro": "73-1629",
                "postgiro": "253417"
            },
            "activity": "Säljer varm luftsaggregat Termator för öppna spisar",
            "key_personnel": [
                {
                    "name": "Rune Pettersson",
                    "position": "Prokurist"
                }
            ],
            "establishment_year": 1946
        },
        "14": {
            "company_name": "SVEATRADE, AB",
            "address": "Box 32. Winqvists v 6",
            "phone_number": "08-760 28 80",
            "bank_details": {
                "bankgiro": "700-3940",
                "postgiro": "250927-1"
            },
            "activity": "Säljer hydraulgräv-maskiner o kranar samt betong-sprutaggregat",
            "capital": 1000000,
            "key_personnel": [
                {
                    "name": "Per Åkerman",
                    "position": "Verkst dir"
                }
            ],
            "establishment_year": 1946
        },
        "15": {
            "company_name": "NÄVRAGOL SÅGVERKS AB",
            "address": null,
            "phone_number": "0477-502 60",
            "bank_details": {
                "bankgiro": "502-6758",
                "postgiro": "41745-1"
            },
            "activity": "Tillverkar sågade o hyvlade trävaror",
            "employees": 50,
            "capital": 500000,
            "key_personnel": [
                {
                    "name": "Disp Herbert Geijer",
                    "position": "Verkst dir"
                }
            ],
            "establishment_year": 1956
        }
    }
}