{
    "original": "MOTORAMI I MALMÖ AB\n\nPnr 20011\n\nMalmö 6, Box 6016. O Tullg 1-3.\nTel 040-73270. Bankgiro874-7529.\nPostgiro 38125-1. Tga Motorami\nVeiksamhet: Säljer person- o\nlastbilar samt reservdel ar.\nReparationsverkstäder\n\nFilialer: Malmö S. Motorami Söder.\nV Hindbyv 18. Tel 040-94 53 10\nMalmö O, Lund av 41. Tel\n040-73270\n\nAktiekapital: 500 000\nDir: Ulf Sparre\nEtableringsår 1949.\n\nPETTERSON, AB RICH\n\nPnr 570 40\n\nAneby, Stigbergsv 8. Tel\n0380-400 72, 407 92. Postgiro 53806\nVerksamhet: Tillverkar rörvinklar\nför luft, vatten mm av koppar,\naluminium o i galvaniserat\nutförande\n\nAktiekapital: 30000\nEtableringsår: 1917\nse Svenska Plåtrör AB.\n\nPETTERSSON SNICKERI- &amp;\nBYGGNADS AB, ROLAND\n\nPnr 602 23\n\nNorrköping, Pilg 9. Tel 011-\n\n12 92 90. Bankgiro 12-5522.\nPostgiro 493868-4\n\nVerksamhet: Beställningssnickeri.\nMindre entreprenader,\nombyggnads-o reparationsarbeten\nAntal anställda: 35\nÅrsomsättning: 2 000 000\nAktiekapital: 60 000\nStyrelse: Byggmäst Roland\nPettersson (ordf), byggn-ing Eddie\nPettersson, kamrer Roger Pettersson\nVerkst dir: Byggmäst Roland\nPettersson\nEtableringsår: 1963.\n\nPETTERSSONS\nMÖBELFABRIK, AB THURE\n\nPnr 57021\n\nMalmbäck, Fabriksg 16. Box 162.\nTel 0380-60037, 60045. Bankgiro\n14-5733. Postgiro 175775\nVerksamhet: Tillverkar\nkompletteringsmöbler såsom bokhyllor, byråar\no skåp\n\nAntal anställda: 15\nÅrsomsättning: 2 050 000\nAktiekapital: 50 000\nStyrelseordf: Thure Pettersson\nVerkst dir: Thure Pettersson\nKamrer: Lennart Svensson\nEtableringsår: 1956.\n\nEMELL, AB\n\nPnr 500 05\n\nBorås 5, Box 55059. Tel 033-770 26.\nPostgiro 471900-1\nVerksamhet: Tillverkar\ndamkappor\n\nAntal anstäUda: 20\nAktiekapital: 5 000\nÄgare o chef: Disp Bertil\nZachrisson\n\nEtableringsår: 1955.\n\nFAGERBERG AB, GUSTAF\n\nPnr 41105\n\nGöteborg, Kronhusg 16. Tel\n031-17 44 00, 17 09 15. Bankgiro\n501-0020. Postgiro 25558-8. Tga Salve.\nTelex 20661 FAGE S\nVerksamhet: Specialfirma i\narmatur (för gas, vatten, olja, ånga,\nsyror), instrument, pumpar\nAvdelningskontor. Stockholm.\nHuddingev 107. Box 13, pa 12121\nJohanneshov 1. Tel 08-59 04 80.\nTelex 17183\n\n852 30 Sundsvall, Storg 16. Tel\n060-1542 20. Telex 71239\nAktiekapital: 30 000\nStyrelse: Fru Gudrun Pihl, dir\nErnst W Larson, dir Rune Olsson\nVerkst dir: Rune Olsson\nEtableringsår. 1897\nOmbildat till aktiebolag 1925.\n\nFAGERHULTS ELEKTRISKA\nAB\n\nPnr 560 40\n\nHabo. Tel 036-43100. Bankgiro\n553-8087. Postgiro 82480-5. Tga Fab\nVerksamhet: Tillverkar elektr\nbelysningsarmatur\nAntal anställda: 180\nÅrsomsättning: 28 000 000\nAktiekapital: 2000 000\nVerkst dir: Bertil Svensson\nEtableringsår: 1949.\n\nFAGERLIDS SÄG &amp; TRÅ.\nINDUSTRI AB\n\nPnr 540 70\n\nHova, Fagerlid. Tel 0506-320 00.\nBankgiro 219-1104. Postgiro\n93165-9. Tga Trälid\nVerksamhet: Tillverkar sågade o\nhyvlade trävaror\nAntal anställda: 45\nÅrsomsättning: 10 000 000\nAktiekapital: 154 000\nVerkst dir: Berndt-Olle Persson\nEtableringsår: 1911.\n\nBÅLFORSENS KRAFT-AB\n\nPnr 85188\n\nSundsvall, S Allén 5. Tel\n060-15 7255. Bankgiro 77-4317.\nPostgiro 474781. Telex 71018\nBAAKAB S\n\nVerksamhet: Producerar o\ndistribuerar elektr energi\nAktiekapital: 50 000 000\nVerkst dir: Bertil Möller\nEtableringsår: 1954.\n\nBÄLSTA CEMENTGJUTERI,\nAB\n\nPnr 64100\n\nKatrineholm, V Fredsg 2. Tel\n0150-16310. Bankgiro 830-0709.\nPostgiro 329380-0\n\nVerksamhet: Tillverkar\nbetongvaror såsom avloppsrör, brunnar o\nkabelblock\n\nFabrik: Bälsta, Kalmarv 5. Tel\n0171-51080. Chef: Ing Hans\nGardehall\n\nVarunamn: KC-kabelblock\nAntal anställda: 14\nÅrsomsättning: 2 000 000\nAktiekapital: 60 000\nStyrelse: Kamrer Olov Olsson\n(ordf), dir Gösta F Eriksson,\ndisp Georg Gustavsson\nVerkst dir: Gösta F Eriksson\nEtableringsår: 1964\nDotterbolag till AB Katrineholm\nCementgjuteri.\n\nBÅREBO AB\n\nPnr 310 70\n\nTorup. Tel 0345-204 10. Bankgiro\n42-7004. Postgiro 30005.\nTga Bårebo\n\nVerksamhet: Tillverkar möbel- o\nbyggnadsbeslag\nAntal anställda: 33\nÅrsomsättning: 4 000 000\nAktiekapital: 300 000\nVerkst dir: Dawid Bauréus\nEtableringsår: 1883\nDotterbolag: AB Svensk Skruv,\nTorup.\n\nBÅSTAD PLAST AB\n\nPnr 260 90\n\nBåstad, Hallandsv. Box 51. Tel\n0431-713 25, 715 60. Postgiro\n351000-5. Tga Båstadsplast\nVerksamhet: Formsprutning upp till\n500 g\n\nAntal anställda: 25\nAktiekapital: 10 000\nVerkst dir: Philip Danowsky\nEtableringsår: 1948.\n\nALVESTA GJUTERI AB\n\nPnr 342 00\n\nAlvesta, Aga tan 18. Box 67. Tel\n0472-130 50. Postgiro 287965-8\nVerksamhet: Tillverkar\ngatube-täckningar, normalrördelar,\nsani-tetsgjutgods, hand- o\nmaskinformat kvalitetsgjutgods\nAntal anställda: 130\nÅrsomsättning: 15 000 000\nAktiekapital: 800 000\nStyrelse: Dir Didrik Hamilton (ordf),\nekonomichef Kjell-Arne Olsson,\nkonsul Ake Raihle\nVerkst dir. Ake Raihle\nPlatschef: Disp Alf Jonsson\nEtableringsår: 1923\nOmbildat till aktiebolag 1943.\nAv Persöner AB, Ystad, helägt\nföretag.\n\nALVESTA GLASBRUK\nLINDAHL &amp; CO\n\nPnr 342 00\n\nAlvesta, Box 120. Tel 0472-102 37,\n102 27. Postgiro 84348-2\nVerksamhet: Tillverkar\nemballageglas för kemisk tekniska fabriker,\nprydnadsglas, lampglas (armatur)\nAntal anställda: 45\nÄgare o chefer: Fabr Georg\nLindahl, kamrer Lorentz Lindahl\nEtableringsår: 1932.\n\nALVESTA JÄRN-&amp;\nMETALL-FURÄDLING AB\n\nPnr 342 00\n\nAlvesta. Tel 0472-107 47, 100 07.\nBankgiro 147-1143. Postgiro\n31667-9. Tga Ajma\nVerksamhet: Pressade massartiklar\ni järn o metaller, plåtarbeten,\njärnkonstruktioner o rostfria\narbeten\n\nVarunamn: Ajma\nAntal anställda: 10\nÅrsomsättning: 400000\nAktiekapital: 15000\nVerkst dir: E Liedberg\nEtableringsår: 1896.\n\nALVESTA METALL. &amp;\nGALVANO AB MEGA\n\nPnr 342 00\n\nAlvesta, Hamrarna. Tel\n0472-105 64. Bankgiro 334-4058.\nPostgiro 86404-1\n\nAllt i\n\nelekfrolytbehandling\n\nVerksamhet: Förnickling,\nförkrom-ning o förzinkning. Specialitet:\nhårdförkromning. Kolvar o rör i\nlängder till 7 meter\nAntal anställda: 20\nÅrsomsättning: 1300000\nAktiekapital: 50 000\nVerkst dir: Gustaf Rosenquist\nEtableringsår: 1947.\n\nLJUNGGREN AB, ERNST W\n\nPnr 21142\n\nMalmö, Regementsg 8. Tel\n040-12 87 49, 97 95 82. Bankgiro\n641-1581. Postgiro 37542-8\nVerksamhet: Parfymer o\nfrisör-utensilier\nAntal anställda: 4\nÅrsomsättning: 900 000\nAktiekapital: 200 000\nVerkst dir. Rune Pettersson\nEtableringsår: 1922.\n\nLJUNGGRENS METALL.\nFABRIK, AB RAGNAR\n\nPnr 330 21\n\nReftele. Tel 0371-200 86\nVerksamhet: Tillverkar\nmjölkkylare\n\nAktiekapital: 20 000\nVerkst dir: Ragnar Ljunggren\nEtableringsår: 1953.\n\nLJUNGHÄLL AB, METALL.\nFABRIKEN\n\nPnr 590 80\n\nSödra Vi. Tel 0492-204 00.\nBankgiro 129-4859. Postgiro 85250-9.\nTelex 3930\n\nrm\n\nVerksamhet: Tillverkar hatthyllor,\nsopnedkastluckor. Specialitet:\nunderreden för stolar (möbelindustrin).\nUtför kokill- o pressgjutningar.\nZinklegeringar i magnesium o\naluminium. Hel- o halvfabrikat. Egen\nverktygstillverkning\nFilial: Horn, Kvarntorp. Tel\n0494-340 23\n\nAntal anställda: 180\nÅrsomsättning: 16 000 000\nAktiekapital: 291 300\nVerkst dir: Olof Ljungkvist\nEtableringsår: 1917\nOmbildat till aktiebolag 1942.\n\nLJUNGKLICHÉER KB\n\nPnr 70105\n\nÖrebro 1, Idrottsv 1. Box 396. Tel\n019-13 02 80. Bankgiro 614-4927.\nPostgiro 390083-4\nVerksamhet: Framställer\nplanklichéer o rundklichéer\nAntal anställda: 10\nChef: Kamrer Birger Holmberg.\n\nLJUNGKVIST, LJUNGQUIST,\nLJUNGQVIST\n\nLJUNGQUIST AB, BRUDERNA\n\nPnr 411 40\n\nGöteborg, Avägen 14. Tel\n031-81 03 50. Bankgiro 50-0129.\nPostgiro 42245. Tga Ljungpaper\nVerksamhet: Papper en gros o\nemballage\n\nAntal anställda: 12\nÅrsomsättning: 2000 000\nAktiekapital: 100000\nVerkst dir: Ing Sten Fallenius\nEtableringsår: 1917.\n\nLJUNGQVISTS TAPET.\nFABRIK, AB\n\nPnr 60102\n\nNorrköping 1, Malmg. Box 26. Tel\n011-1063 40. Bankgiro 50-0051.\nPostgiro 40681. Tga Tapet\nVerksamhet: Tillverkar tapeter\nVarunamn: Sawona\nVerkst dir: H H Rasmussen\nEtableringsår 1904\nTillhör Engblad &amp; Co\nTapetfabriker AB, Norrköping\n\nLJUNGQVISTS PÄLS AB, J F\n\nPnr 573 00\n\nTranås, Agatan 44. Tel\n0140-12134, 15134\n\nVerksamhet: Tillverkar o säljer\nhattar o dampälsar en gros\nAktiekapital: 50 000\nFirmatecknare: Disp Curt\nLjungqvist\n\nEtableringsår: 1956.\n\nLJUNGQVISTS MUBEL.\nFABRIK, AB S\n\nPnr 560 40\n\nHabo. Tel 036-400 93, 40143\nVerksamhet: Tillverkar bord\nAktiekapital: 300 000\nVerkst dir: R Ljungqvist\nEtableringsår: 1926.\n\nLJUNGLUFS\nLITOGRAFISKA AB\n\nPnr 112 49\n\nStockholm, Igeldammsg 22. Tel\n08-52 02 80. Bankgiro 72-9944.\nPostgiro 156813. Tga Ljunglito\nVerksamhet: Offsettryckeri\nAktiekapital: 169 000\nVerkst dir: Göran Z Haeggström\nDisp: Gunnar Andersson\nEtableringsår: 1896.\n\nLJUNGMANS VERK.\nSTÄDER, AB\n\nPnr 200 61\n\nMalmö 30, Limhamnsv 109. Box\n1049. Tel 040-15 50 00. Bankgiro\n87-0342. Postgiro 37610.\nTga Ljungmanis. Telex 3132\nVerksamhet: Tillverkar apparater\nför lagring, uppmätning o\ndistribution av eldfarliga oljor, såsom\nbensinpumpar, armatur,\noljepumpar, biltvättpumpar o\nhögtrycks-smörjpistoler\n\nFilialer: 417 05 Göteborg,\nAng-panneg 4. Tel 031-22 2195. Telex\n2247\n\n18132 Lidingö 1, Sturev 68-70.\n\nTel 08-765 28 00. Telex 1432\n602 15 Norrköping, Hagag 2. Tel\n011-18 03 20. Telex 64140\nÖrnsköldsvik. 890 31 Arnäsvall,\nBox 4. Tel 0660-453 50\nAntal anställda: 800\nÅrsomsättning: 55 000 000\nAktiekapital: 5 000 000\nVerkst dir: Gustav Ekberg\nFörsäljn-chef: Sam Rosén\nEtableringsår: 1925.\n\nSVENSK INDUSTRISERVICE\n\nPnr 82101\n\nBollnäs 1, Stationsg 8. Box 42. Tel\n0278-130 15. Bankgiro 785-5414.\nPostgiro 385285. Tga Rapid\nVerksamhet: Lyftverktyg o\nlyftanordningar av alla slag\nVarunamn: Rapid, MV, Whippet\nVerkst dir: J-E Lorentzoon.\n\nSVENSK KARTTJÄNST SRA\nSWEDISH MAP SERVICE, AB\n\nPnr 16210\n\nVällingby 1, Fack. Sorterarg 23.\nTel 08-89 02 00. Bankgiro\n331-7294. Postgiro 4940-3\nVerksamhet: Kartproduktion o\nkartförsäljning\n\nVerkst dir: Lars Ahstrand.\n\nSVENSK KONFEKTION\n\nPnr 311 00\n\nFalkenberg, Sandslätt 9. Tel\n0346-110 20. Bankgiro 36-1311. Postgiro\n163098-7\n\nVerksamhet: Tillverkar\ndamklänningar\n\nAntal anställda: 15\nChef: Erik Gustafsson\nEtableringsår: 1939.\n\nIRVIN FALLSKÄRMS AB\n\nPnr 170 23\n\nBarkarby, Girov. Tel 08-36 2950.\nBankgiro 728-0761. Postgiro\n255917. Tga Irvinchute. Telex 10299\nVerksamhet: Tillverkar o säljer\nfallskärmar o personlig\nsäkerhetsutrustning (säkerhetsbälten, -selar,\n-linor etc)\n\nAktiekapital: 500 000\nVerkst dir Töre Friberg\nEtableringsår: 1938.\n\nSVE\n\nSVENSKA RIKSBYGGEN\n\nPnr 104 32\n\nStockholm 19, Hagag 2. Box 19015.\nTel 08-34 05 20. Postgiro 159414-2.\nTga Riksbyggen\n\nVerksamhet: Projekterar bostäder,\nförvaltningsbyggnader, skolor,\nbibliotek, varuhus mm. Projekterar\nca 12 000 lägenheter per år\nAntal anställda: 1360\nChef: Gösta Blomqvist\nEtableringsår 1941.\n\nSVENSKA ROTOR\nMASKINER AB\n\nPnr 104 65 Sthlm 15\nNacka, Värmdöv 120. Box 15085,\nSthlm 15. Tel 08-716 25 70.\nPostgiro 151546. Tga Essarem.\nTelex 10883 ESSAREM S\nVerksamhet: Licensgivare för\nluftförvärmare o kompressorer\nAntal anställda: 87\nÅrsomsättning: 10 000 000\nAktiekapital: 5 000 000\nStyrelse: Civiling Gunnar Brundell\n(ordf), bankdir Ernst Anneli,\nbank-dir Niklas Cederberg, adv Per-Olof\nHillström, dir Hans Nilsson\nVerkst din Hans Nilsson\nEtableringsår. 1908.\n\nSVENSKA SALPETER.\nVERKEN, AB\n\nPnr 73100\n\nKöping, Nya Hamnv. Tel\n0221-135 30. Bankgiro 606-8613.\nPostgiro 280970-5. Tga Salpeterberken.\nTelex 4755 SSV S\nVerksamhet: Tillverkar\nhandelsgödsel, ammoniak, salpetersyra,\nurea\n\nFöretaget har sedan 1.6.70\ngemensam ledning med Förenade\nSuper-fosfatfabriker, AB. Se detta\nföretag.\n\nSVENSKA SAXBOLAGET\n\nPnr 672 00\n\nAriäng, Box 49. Tel 0573-108 20.\nBankgiro 11-7331. Postgiro 292316\nVerksamhet: Kirurgiska instrument\no saxar av alla slag\nAntal anställda: 40\nVerkst din K F Jonsson\nEtableringsår 1944.",
    "structured": {
        "1": {
            "company_name": "MOTORAMI I MALMÖ AB",
            "activity": "Säljer person- o lastbilar samt reservdel ar. Reparationsverkstäder",
            "establishment_year": 1949,
            "pnr": "20011",
            "address": "Malmö 6, Box 6016. O Tullg 1-3.",
            "phone_number": "040-73270",
            "bank_details": {
                "bankgiro": "874-7529",
                "postgiro": "38125-1"
            }
        },
        "2": {
            "company_name": "PETTERSON, AB RICH",
            "activity": "Tillverkar rörvinklar för luft, vatten mm av koppar, aluminium o i galvaniserat utförande",
            "establishment_year": 1917,
            "pnr": "570 40",
            "address": "Aneby, Stigbergsv 8.",
            "phone_number": "0380-400 72, 407 92",
            "postgiro": "53806"
        },
        "3": {
            "company_name": "PETTERSSON SNICKERI- & BYGGNADS AB, ROLAND",
            "activity": "Beställningssnickeri. Mindre entreprenader, ombyggnads-o reparationsarbeten",
            "establishment_year": 1963,
            "pnr": "602 23",
            "address": "Norrköping, Pilg 9.",
            "phone_number": "011-12 92 90",
            "bank_details": {
                "bankgiro": "12-5522",
                "postgiro": "493868-4"
            },
            "employees": 35,
            "annual_turnover": 2000000,
            "capital": 60000,
            "key_personnel": [
                {
                    "name": "Byggmäst Roland Pettersson",
                    "position": "ordf"
                },
                {
                    "name": "byggn-ing Eddie Pettersson",
                    "position": null
                },
                {
                    "name": "kamrer Roger Pettersson",
                    "position": null
                }
            ]
        },
        "4": {
            "company_name": "PETTERSSONS MÖBELFABRIK, AB THURE",
            "activity": "Tillverkar kompletteringsmöbler såsom bokhyllor, byråar o skåp",
            "establishment_year": 1956,
            "pnr": "57021",
            "address": "Malmbäck, Fabriksg 16. Box 162.",
            "phone_number": "0380-60037, 60045",
            "bank_details": {
                "bankgiro": "14-5733",
                "postgiro": "175775"
            },
            "employees": 15,
            "annual_turnover": 2050000,
            "capital": 50000,
            "key_personnel": [
                {
                    "name": "Thure Pettersson",
                    "position": "Styrelseordf"
                },
                {
                    "name": "Lennart Svensson",
                    "position": "Kamrer"
                }
            ]
        },
        "5": {
            "company_name": "EMELL, AB",
            "activity": "Tillverkar damkappor",
            "establishment_year": 1955,
            "pnr": "500 05",
            "address": "Borås 5, Box 55059.",
            "phone_number": "033-770 26",
            "postgiro": "471900-1",
            "employees": 20,
            "capital": 5000,
            "key_personnel": [
                {
                    "name": "Disp Bertil Zachrisson",
                    "position": "Ägare o chef"
                }
            ]
        },
        "6": {
            "company_name": "FAGERBERG AB, GUSTAF",
            "activity": "Specialfirma i armatur (för gas, vatten, olja, ånga, syror), instrument, pumpar",
            "establishment_year": 1897,
            "pnr": "41105",
            "address": "Göteborg, Kronhusg 16.",
            "phone_number": "031-17 44 00, 17 09 15",
            "bank_details": {
                "bankgiro": "501-0020",
                "postgiro": "25558-8"
            },
            "key_personnel": [
                {
                    "name": "Fru Gudrun Pihl",
                    "position": "Styrelse"
                },
                {
                    "name": "dir Ernst W Larson",
                    "position": null
                },
                {
                    "name": "dir Rune Olsson",
                    "position": null
                }
            ]
        }
    }
}