{
    "original": "FÄRGELANDA SÅGVERK, AB\n\nPnr 450 60\n\nFärgelanda. Tel\n0528-10033.Postgiro 88895-8\n\nVerksamhet: Tillverkar sågade o\n\nhyvlade trävaror\n\nAntal anställda: 25\n\nÅrsomsättning: 4000 000\n\nAktiekapital: 60 700\n\nVerkst dir: Göran Langenskiöld\n\nInsp: Oscar Wallberg\n\nEtableringsår: 1906\n\nÄges av Munkedals AB, Munkedal.\n\nFÄRGFABRIK\n\nse resp namn.\n\nFÄRGHANDELS.\nAKTIEBOLAGET\n\nPnr 891 00\n\nÖrnsköldsvik, Nyg 18, (Stadshuset).\nTel 0660-12128, 123 63\nVerksamhet: Säljer färger, fernissor\no tapeter i parti o minut.\nMinutförsäljning i modern självvalsbutik\nAntal anställda: 6\nAktiekapital: 9 700\nVerkst dir: Ruben Nilsson\nEtableringsår: 1902.\n\nPLÄMA, AB\n\nPnr 265 01\n\nÅstorp, Box 128. Fabriksg 2. Tel\n042-514 55 , 514 56. Bankgiro\n651-3345. Postgiro 710350-0\nVerksamhet: Reparations- o\nanläggningsarbeten på industrier samt\nnytillverkning av maskiner o\ntransportanordningar, containers\nAntal anstäUda: 20\nÅrsomsättning: 350 000\nAktiekapital: 6000\nVerkst dir: Sven-Ake Svensson\nEtableringsår: 1968.\n\nPLÅT. &amp; JÄRNVERKS.\nPRODUKTER AB\n\nPnr 113 40\n\nStockholm VA, Rörstrandsg 34. Tel\n08-3222 70. Bankgiro 33-1908.\nPostgiro 359670. Tga Platab\nVerksamhet: Sälj er järn o stål samt\nmanufaktur av olika slag\nAktiekapital: 50000\nVerkst dir: Bergverksing Gunnar\nErie Otterblad\nEtableringsår: 1929.\n\nPLÅT &amp; SMIDE I RYDA.\nHOLM AB\n\nPnr 330 17\n\nRydaholm, Sveav 21. Box 164. Tel\n0472-203 90. Bankgiro 14-2540.\nPostgiro 76493\n\nVeiksamhet: Påbyggnadsverkstad\nför lastbilar. Serviceverkstad för\nHIAB-FOCO kranar o tippar.\nLätt-metallkarosser för lastvagnar\nAntal anstäUda: 65\nÅrsomsättning: 6200 000\nAktiekapital: 50000\nVeikst dir: Lars-Olof Nilsson\nEtableringsån 1958.\n\nTWILFIT, AB\n\nPnr 114 44\n\nStockholm, Jungfrug 19. Tel 08-\n\n67 05 50. Tga Twilfit\nVerksamhet: Säljer damkonfektion\n(korsetter, bysthållare, underkläder,\nstrumpor, bad- o strandartiklar,\nstickat)\n\nAktiekapital: 1 323 000\nVerkst din Bo Heigard\nV veikst dir: C M Heigard\nEtableringsån 1922.\n\nFRISELLS MASKINER AB\n\nPnr 13100\n\nNacka, Sickla Industriv 6. Tel\n08-24 62 25. Bankgiro 37-1481.\nPost-giro 170300-8\n\nVerksamhet: Tillverkar svarvar\nÄgare: H Gregfelt\nEtableringsår: 1906.\n\nFRISK AB, MASKINFIRMAN\nC AGNE\n\nPnr 162 03\n\nVällingby 3, Viveka Trolles gränd\n12. Box 364. Tel 08-89 25 13,\n89 25 14. Bankgiro 172-8039.\nPostgiro 199333-6. Tga Grindfrisk\nVerksamhet: Säljer\nmaskinförnödenheter\n\nVarunamn: Air-Loc, Rolette,\nSeal-Peel\n\nAktiekapital: 10 000\nEtableringsår: 1945.\n\nFRISK VENTILATIONS.\nPLÅTSLAGERI, TH\n\nPnr 530 20\n\nKvänum, Karlag, Industriområdet.\nTel 0512-924 28, 925 28. Bankgiro\n220-034 3. Postgiro 369871-9\nVerksamhet: Tillverkar o monterar\nfullt kompletta\nventilationsanläggningar. Tillverkar o säljer\nspiral-falsade rör med detaljer\nAntal anställda: 25\nÅrsomsättning: 25 000 000\nÄgare o chef: Fabr Thure Frisk\nEtableringsår: 1955.\n\nFRISTADS SNICKERI.\nFABRIKS AB\n\nPnr 510 47\n\nFristad. Tel 033-600 17, 606 27.\nBankgiro 844-8276. Postgiro\n266538-8\n\nVerksamhet: sågade o hyvlade\nträvaror samt byggnadsmaterial\nAntal anställda: 38\nÅrsomsättning: 4 500 000\nAktiekapital: 186 000\nVerkst dir: Gösta Persson\nEtableringsår: 1907.\n\nGASMARIN, AB\n\nPnr 114 37\n\nStockholm, Braheg 30. Tel\n08-6 1 03 88 , 61 03 89. Bankgiro\n570-7567. Postgiro 551642-2. Tga\nNautic\n\nVerksamhet: Rederi\nAntal anställda: 20\nAktiekapital: 300 000\nVerkst dir: Ake Wanander\nEtableringsår: 1961.\n\nÖSTRA GREVIE\nTEGEL-BRUK AB\n\nPnr 230 17\n\nÖstra Grevie. Tel 040-48 70 06,\n48 73 72. Bankgiro 870-2342.\nPostgiro 434040-2. Tga Grevietegel,\nMalmö\n\nVerksamhet: Tillverkar fasadtegel\nAntal anställda: 30\nÅrsomsättning: 2 300 000\nAktiekapital: 300 000\nVerkst dir: Disp Ingemar Haby\nEtableringsår: 1951.\n\nNC\n\nNC JÄRN &amp; BYGG\n\nPnr 262 01\n\nÄngelholm, Klippanv. Tel\n0431-17100. Bankgiro 672-2193.\nPostgiro 30476-6\n\nVerksamhet: säljer järnvaror,\nbyggmaterial, husgeråd\nAntal anställda: 23\nÅrsomsättning: 7 000 000\nAktiekapital: 150 000\nVerkst dir: Torsten Christiansson\nEtableringsår: 1902.\n\nMOSESSON &amp; CO AB, B A\n\nPnr 11644\n\nStockholm, Båtklubbsv 7. Tel\n08-44 8142, 44 10 90. Tga Bamosco\nVerksamhet: Elektriska\nmotorreparationer\n\n.Antal anställda: 10\nAktiekapital: 5 000\nVerkst dir: g Wingårdh\nEtableringsår: 1945.\n\nCITOGRAF AB\n\nPnr 370 40\n\nJämjöslätt, Box 101. Tel\n0455-503 50. Postgiro 154735-5. Tga\nCitograf, Karlskrona\nVerksamhet: Tillverkar\nadressmaskiner samt legotillverkning\nAntal anställda: 75\nÅrsomsättning: 5 000 000\nAktiekapital: 200 000\nVerkst dir: Sten Ullstrom\nEtableringsår: 1938.\n\nSCANFORSAB\n\nPnr 12653\n\nHägersten, Jakobsdalsv 18. Tel\n08-18 03 15\n\nVerksamhet: Röntgenartiklar,\nfotografiska kemikalier\nAntal anställda: 40\nÅrsomsättning: 15 000 000\nAktiekapital: 200 000\nVerkst dir: N R Jessen\nEtableringsår: 1952.",
    "structured": {
        "1": {
            "company_name": "FÄRGELANDA SÅGVERK, AB",
            "pnr": "450 60",
            "address": "Färgelanda",
            "phone_number": "0528-10033",
            "bank_details": {
                "postgiro": "88895-8"
            },
            "activity": "Tillverkar sågade o hyvlade trävaror",
            "employees": 25,
            "annual_turnover": 4000000,
            "capital": 60700,
            "key_personnel": [
                {
                    "name": "Göran Langenskiöld",
                    "position": "Verkst dir"
                },
                {
                    "name": "Oscar Wallberg",
                    "position": "Insp"
                }
            ],
            "establishment_year": 1906
        },
        "2": {
            "company_name": "FÄRGHANDELS. AKTIEBOLAGET",
            "pnr": "891 00",
            "address": "Örnsköldsvik, Nyg 18 (Stadshuset)",
            "phone_number": "0660-12128, 123 63",
            "activity": "Säljer färger, fernissor o tapeter i parti o minut. Minutförsäljning i modern självvalsbutik",
            "employees": 6,
            "capital": 9700,
            "key_personnel": [
                {
                    "name": "Ruben Nilsson",
                    "position": "Verkst dir"
                }
            ],
            "establishment_year": 1902
        },
        "3": {
            "company_name": "PLÄMA, AB",
            "pnr": "265 01",
            "address": "Åstorp, Box 128, Fabriksg 2",
            "phone_number": "042-514 55 , 514 56",
            "bank_details": {
                "bankgiro": "651-3345",
                "postgiro": "710350-0"
            },
            "activity": "Reparations- o anläggningsarbeten på industrier samt nytillverkning av maskiner o transportanordningar, containers",
            "employees": 20,
            "annual_turnover": 350000,
            "capital": 6000,
            "key_personnel": [
                {
                    "name": "Sven-Ake Svensson",
                    "position": "Verkst dir"
                }
            ],
            "establishment_year": 1968
        },
        "4": {
            "company_name": "PLÅT. & JÄRNVERKS. PRODUKTER AB",
            "pnr": "113 40",
            "address": "Stockholm VA, Rörstrandsg 34",
            "phone_number": "08-3222 70",
            "bank_details": {
                "bankgiro": "33-1908",
                "postgiro": "359670"
            },
            "activity": "Säljer järn o stål samt manufaktur av olika slag",
            "capital": 50000,
            "key_personnel": [
                {
                    "name": "Bergverksing Gunnar Erie Otterblad",
                    "position": "Verkst dir"
                }
            ],
            "establishment_year": 1929
        },
        "5": {
            "company_name": "PLÅT & SMIDE I RYDA. HOLM AB",
            "pnr": "330 17",
            "address": "Rydaholm, Sveav 21, Box 164",
            "phone_number": "0472-203 90",
            "bank_details": {
                "bankgiro": "14-2540",
                "postgiro": "76493"
            },
            "activity": "Påbyggnadsverkstad för lastbilar. Serviceverkstad för HIAB-FOCO kranar o tippar. Lätt-metallkarosser för lastvagnar",
            "employees": 65,
            "annual_turnover": 6200000,
            "capital": 50000,
            "key_personnel": [
                {
                    "name": "Lars-Olof Nilsson",
                    "position": "Verkst dir"
                }
            ],
            "establishment_year": 1958
        },
        "6": {
            "company_name": "TWILFIT, AB",
            "pnr": "114 44",
            "address": "Stockholm, Jungfrug 19",
            "phone_number": "08-67 05 50",
            "activity": "Säljer damkonfektion (korsetter, bysthållare, underkläder, strumpor, bad- o strandartiklar, stickat)",
            "capital": 1323000,
            "key_personnel": [
                {
                    "name": "Bo Heigard",
                    "position": "Verkst dir"
                },
                {
                    "name": "C M Heigard",
                    "position": "V veikst dir"
                }
            ],
            "establishment_year": 1922
        },
        "7": {
            "company_name": "FRISELLS MASKINER AB",
            "pnr": "13100",
            "address": "Nacka, Sickla Industriv 6",
            "phone_number": "08-24 62 25",
            "bank_details": {
                "bankgiro": "37-1481",
                "postgiro": "170300-8"
            },
            "activity": "Tillverkar svarvar",
            "key_personnel": [
                {
                    "name": "H Gregfelt",
                    "position": "Ägare"
                }
            ],
            "establishment_year": 1906
        },
        "8": {
            "company_name": "FRISK AB, MASKINFIRMAN C AGNE",
            "pnr": "162 03",
            "address": "Vällingby 3, Viveka Trolles gränd 12, Box 364",
            "phone_number": "08-89 25 13, 89 25 14",
            "bank_details": {
                "bankgiro": "172-8039",
                "postgiro": "199333-6"
            },
            "activity": "Säljer maskinförnödenheter",
            "varunamn": "Air-Loc, Rolette, Seal-Peel",
            "capital": 10000,
            "establishment_year": 1945
        },
        "9": {
            "company_name": "FRISK VENTILATIONS. PLÅTSLAGERI, TH",
            "pnr": "530 20",
            "address": "Kvänum, Karlag, Industriområdet",
            "phone_number": "0512-924 28, 925 28",
            "bank_details": {
                "bankgiro": "220-034 3",
                "postgiro": "369871-9"
            },
            "activity": "Tillverkar o monterar fullt kompletta ventilationsanläggningar. Tillverkar o säljer spiral-falsade rör med detaljer",
            "employees": 25,
            "annual_turnover": 25000000,
            "key_personnel": [
                {
                    "name": "Fabr Thure Frisk",
                    "position": "Ägare o chef"
                }
            ],
            "establishment_year": 1955
        },
        "10": {
            "company_name": "FRISTADS SNICKERI. FABRIKS AB",
            "pnr": "510 47",
            "address": "Fristad",
            "phone_number": "033-600 17, 606 27",
            "bank_details": {
                "bankgiro": "844-8276",
                "postgiro": "266538-8"
            },
            "activity": "sågade o hyvlade trävaror samt byggnadsmaterial",
            "employees": 38,
            "annual_turnover": 4500000,
            "capital": 186000,
            "key_personnel": [
                {
                    "name": "Gösta Persson",
                    "position": "Verkst dir"
                }
            ],
            "establishment_year": 1907
        },
        "11": {
            "company_name": "GASMARIN, AB",
            "pnr": "114 37",
            "address": "Stockholm, Braheg 30",
            "phone_number": "08-6 1 03 88 , 61 03 89",
            "bank_details": {
                "bankgiro": "570-7567",
                "postgiro": "551642-2"
            },
            "activity": "Rederi",
            "employees": 20,
            "capital": 300000,
            "key_personnel": [
                {
                    "name": "Ake Wanander",
                    "position": "Verkst dir"
                }
            ],
            "establishment_year": 1961
        },
        "12": {
            "company_name": "ÖSTRA GREVIE TEGEL-BRUK AB",
            "pnr": "230 17",
            "address": "Östra Grevie",
            "phone_number": "040-48 70 06, 48 73 72",
            "bank_details": {
                "bankgiro": "870-2342",
                "postgiro": "434040-2"
            },
            "activity": "Tillverkar fasadtegel",
            "employees": 30,
            "annual_turnover": 2300000,
            "capital": 300000,
            "key_personnel": [
                {
                    "name": "Disp Ingemar Haby",
                    "position": "Verkst dir"
                }
            ],
            "establishment_year": 1951
        },
        "13": {
            "company_name": "NC JÄRN & BYGG",
            "pnr": "262 01",
            "address": "Ängelholm, Klippanv",
            "phone_number": "0431-17100",
            "bank_details": {
                "bankgiro": "672-2193",
                "postgiro": "30476-6"
            },
            "activity": "säljer järnvaror, byggmaterial, husgeråd",
            "employees": 23,
            "annual_turnover": 7000000,
            "capital": 150000,
            "key_personnel": [
                {
                    "name": "Torsten Christiansson",
                    "position": "Verkst dir"
                }
            ],
            "establishment_year": 1902
        },
        "14": {
            "company_name": "MOSESSON & CO AB, B A",
            "pnr": "11644",
            "address": "Stockholm, Båtklubbsv 7",
            "phone_number": "08-44 8142, 44 10 90",
            "activity": "Elektriska motorreparationer",
            "employees": 10,
            "capital": 5000,
            "key_personnel": [
                {
                    "name": "g Wingårdh",
                    "position": "Verkst dir"
                }
            ],
            "establishment_year": 1945
        },
        "15": {
            "company_name": "CITOGRAF AB",
            "pnr": "370 40",
            "address": "Jämjöslätt, Box 101",
            "phone_number": "0455-503 50",
            "postgiro": "154735-5",
            "activity": "Tillverkar adressmaskiner samt legotillverkning",
            "employees": 75,
            "annual_turnover": 5000000,
            "capital": 200000,
            "key_personnel": [
                {
                    "name": "Sten Ullstrom",
                    "position": "Verkst dir"
                }
            ],
            "establishment_year": 1938
        },
        "16": {
            "company_name": "SCANFORSAB",
            "pnr": "12653",
            "address": "Hägersten, Jakobsdalsv 18",
            "phone_number": "08-18 03 15",
            "activity": "Röntgenartiklar, fotografiska kemikalier",
            "employees": 40,
            "annual_turnover": 15000000,
            "capital": 200000,
            "key_personnel": [
                {
                    "name": "N R Jessen",
                    "position": "Verkst dir"
                }
            ],
            "establishment_year": 1952
        }
    }
}