{
    "original": "ESKILSTUNA TUBER AB\n\nPnr 632 33\n\nEskilstuna, Mesta. Tel 016-20182.\nBankgiro 60-1337. Postgiro 291400\nVerksamhet: Tillverkar\nförpackningstuber av aluninium\nVerkst dir. Roland Ericson\nEtableringsår 1964.\n\nBENDIX, JOSEPHSON &amp; CO AB\n\nPnr 124 21\n\nBandhagen 1, Box 80. Harpsundsv\n185. Tel 08-86 01 00. Bankgiro\n168-7862. Postgiro 106-5. Tga\nBendixjosephson\nVerksamhet: Sybehör, modetrikå,\nbadartiklar, barnkläder o sovplagg\niintal anställda: 66\nÅrsomsättning: 13 500 000\nAktiekapital: 2100000\nVerkst dir: Lennart Randerz\nEtableringsår: 1857.\n\nBENGTBO\nPLAST-PRODUKTION AB\n\nPnr 104 35\n\nStockholm 23, Box 23060. Hagag\n29. Tel 08-24 72 00. Bankgiro\n26-0978. Postgiro 195432-0. Tga\nSer-viceoffice. Telex 10625 SERVO S\nVerksamhet: Utför entreprenader\ninom byggnadsindustrin\nAntal anställda: 10\nÅrsomsättning: 500 000\nAktiekapital: 5 000\nVerkst dir: Byggn-ing Bengt Boberg\nEtableringsår: 1968.\n\nPRINS ERIC, AB\n\nPnr 21133\n\nMalmö, Grynbodg 3. Tel 040-321 02,\n97 33 30. Bankgiro 348-2106.\nPostgiro 531835-7\n\nVerksamhet: Tillverkar o säljer\nkonsumentförpackade\ncharkuteriva-ror o färdiglagade rätter\nAntal anstäUda: 20\nÅrsomsättning: 2 000 000\nAktiekapital: 5 000\nVerkst dir: Ing Klaus W\nGuggen-heimer\n\nEtableringsår: 1959.\n\nPRINSFORS METALL.\nFABRIK, AB\n\nPnr 560 23\n\nBankeryd, Box 56. Tel 036-720 38,\n72058, 722 08. Bankgiro 836-9183.\nPostgiro 34691-7\nVerksamhet: Tillverkar\nmöbelbeslag såsom handtag, knappar,\nfothylsor, bössningar o d.\nInrednings-beslag såsom rörhållare,\nkasett-bågar, konfektionshållare o d\nAntal anstäUda: 22\nAktiekapital: 50 000\nÄgare o chefer: Uno Miller,\nSven-Olof Miller\nEtableringsår: 1920\nOmbildat till aktiebolag 1952.\n\nPRINTER^ SERVICE AB\n\nPnr 402 22\n\nGöteborg 5, Prästgårdsängen 6.\nBox 5120. Tel 031-40 93 20. Post&gt;\ngiro 47819. Telex 21089\nVerksamhet: Konsultation o\nproduktion av trycksaker\nAntal anstäUda: 24\nAktiekapital: 100 000\nVerkst dir: Lars Bergström\nEtableringsår: 1962.\n\nSCANDIAMANT AB\n\nPnr 910 40\n\nRobertsfors. Tel 0934-105 15.\nBankgiro 284-0874. Postgiro 6804-9.\nTelex 54049 DIAMANT S\nVerksamhet Tillverkar syntetiska\ndiamanter o verktyg\nAntal anställda: 140\nÅrsomsättning: 16 000 000\nAktiekapital: 5 000 000\nVerkst dir: Erik Lundblad\nEtableringsår: 1967.\n\nNORDIC, FÄRG AB\n\nPnr 11120\n\nStockholm, Vasag 48. Tel\n08-10 7415. Bankgiro 724-5251.\nPostgiro 452750-3. Tga Faergnordic\nVerksamhet: Färger, lim, plaster,\ngrafiska kemikalier\nVarunamn: Aquella, Gängtex,\nSve-dic, Svedicon, Transenol, Vadic\nAktiekapital: 50 000\nVerkst dir: Lennart Nyström\nEtableringsår: 1955.\n\nFORSSA TEGELBRUK, AB\n\nPnr 510 35\n\nBollebygd, Box 121. Tel\n033-850 39, 85140. Bankgiro 531-1212.\nPostgiro 99112-5. Tga Tegelbruket\nVerksamhet: Tillverkar fasadtegel,\nmur- o månghålstegel\nAntal anställda: 34\nÅrsomsättning: 2 500 000\nAktiekapital: 200 000\nStyrelse: Dir Gunnar Hedelin (ordf),\ning Manne Haby, dir Bengt\nEjser-holm\n\nVerkst dir: Bengt Ejserholm\nEtableringsår: 1917.\n\nNIBE-VERKEN AB\n\nPnr 285 00\n\nMarkaryd, Järnvägsg 44. Tel\n0433-112 00. Bankgiro 279-6712.\nPostgiro 399475-3. Telex 72497 NIBE S\nVerksamhet: Tillverkar\nvarmvattenberedare o tryckkärl samt\npreci-sionssåmaskiner\nAntal anställda: 141\nÅrsomsättning: 18 500 000\nAktiekapital: 1000 000\nVerkst dir Civiling Rune Dahlberg\nEtableringsàr: 1952.\n\nNICKELBOLAGET (NICKEL\n-FABRIKS AB GOTTFRID\nCARLSSON)\n\nPnr 63103\n\nEskilstuna 1, Box 152. Smedjeg 34.\nTel 016-14 70 80. Bankgiro\n601-3700. Postgiro 8636-3. Tga Nickel\nVerksamhet: Pressade, tryckta o\nsvarvade detaljer. Sammansättning\ngenom punksvetsning,\nsömsvetsning o lödning. Galvanisk\nytbehandling, eloxering o aluminisering.\nTillbehör för motorfordon såsom\n\nmotorvärmare, kupévärmare, startur,\ngrenkontakter, backljus, dimljus,\nsökar- o traktorlyktor samt reflexer\nVarunamn: Calix, Johnson-Ljus\nAntal anställda: 100\nÅrsomsättning: 10 000 000\nAktiekapital: 900 000\nVerkst dir. Holger Brunell\nInköp o försäljning: Disp Sven\nWiklund\n\nEtableringsàr 1891\n\nÄger AB Erik Svalling, Eskilstuna.\n\nNICKELS &amp; TODSEN, AB\n\nPnr 104 32\n\nStockholm 19, Karlav 5. Box 19080.\nTel 08-23 62 50, 10 48 84. Postgiro\n4884-3. Tga Nickelto. Telex 1439\nVerksamhet: Import, export o\nagenturrörelse med elektr generatorer,\nelektr motorer, järn o stål,\nmetallurgiska utrustningar\nAntal anställda: 20\nÅrsomsättning: 25 000 000\nAktiekapital: 160 000\nStyrelse: Dir Gunnar Berg (ordf),\nciviling Sten Hammer, ing G Svane\nVerkst dir Gunnar Berg\nEtableringsàr 1898.\n\ndata-service-edb, ab\n\nPnr 18211\n\nDanderyd 1, Box 93. Tel\n08-755 27 20. Bankgiro 57-4140.\nPostgiro 556278\n\nVerksamhet: Servicebyrå för\nadministrativ databehandling\nFilialer: Göteborg. Tel\n031-42 03 00\n\nHelsingborg. Tel 042-12 0010\nMalmö. Tel 040-18 00 30\nNorrköping. Tel 011-12 98 90\nÖrebro. Tel 019-14 04 5 0\nAntal anställda: 500\nÅrsomsättning: 50 000 000\nAktiekapital: 5 000000\nStyrelse: Dir Claes-Olof Livijn,\nbankdir Bengt Magnusson, bankdir\nCurt G Olsson, dir Anders Rönn\nVerkst dir: Anders Rönn\nV verkst dir: Magnus Karle’n.\n\ndatema ab\n\nPnr 17121\n\nSolna 1, Box 1056. Huvudstav 1.\nTel 08-83 40 20. Bankgiro 17-1279.\nPostgiro 668850. Telex 10602\nVerksamhet: Tillhandahåller\ndatabehandlingstjänster inom såväl det\nadministrativa som det tekniska\nområdet. Verksamheten omfattar:\ndatabehandling; time-sharing,\nDatema Direkt Data, DDD;\nsystemutveckling; standardsystem för\nredovisning, personaladministration\no materialplanering\nVarunamn: DDD-Datema Direkt\nData\n\nAntal anställda: 200\nÅrsomsättning: 25 000 000\nAktiekapital: 1 000 000\nStyrelse: Bergsing Axel Ax: son\nJohnson (ordf), dir Bo Ax:son\nJohnson, dir Rune Hallåker, dir\nKjell Hellberg, dir Carl Einar\n\nLenngren, dir Nils Mörner, dir\nPer Norlin, dir Rune Smedman,\ndir Gunnar Westerberg\nVerkst dir: Kjell Hellberg\nEtableringsår: 1964.\n\ndavéns express ab. h &amp; e\n\nPnr 151 03\n\nSödertälje 3, Brunnsängsv 32. Box\n3036. Tel 0755-399 65. Bankgiro\n37-4527. Postgiro 13118\nVerksamhet: Transporter,\nflyttningar, magasinering\nAntal anställda: 40\nÅrsomsättning: 3 000000\nAktiekapital: 300 000\nVerkst dir: Hugo Davën\nEtableringsår: 1964.\n\ndavéns äkeri ab, h\n\nPnr 15103\n\nSödertälje 3, Box 3036.\nBrunnsängsv 32. Tel 0755-399 65.\nBankgiro 374-5270. Postgiro 13118-5\nVerksamhet: Utför transporter med\nbl a specialutrustade fordon\nAntal anställda: 70\nÅrsomsättning: 5 000 000\nAktiekapital: 300 000\nVerkst dir: Hugo Davén\nEtableringsår: 1870.\n\nBORENS BRANDREDSKAP AB\n\nPnr 400 61\n\nGöteborg 28, Fack. Carlsteinsv 9,\nPartille. Tel 031-443533, 44 3534.\nBankgiro 51-3139. Postgiro 422184\nVerksamhet: Tillverkar o säljer\neldsläckare, kolsyrebatterier,\nsvetsgaser samt kylvätskor\nVarunamn: Bavaria\nAntal anställda: 6\nAktiekapital: 15 000\nVerkst dir: Stig Borén\nEtableringsår: 1949.\n\nBORENSBERGS SÄG &amp;\nTRAFORÄDLING\n\nPnr 590 30\n\nBorensberg, Norrbyg 3. Tel\n0141-401 24, 404 54. Bankgiro 13-4308.\nPostgiro 131503\nVerksamhet: Säljer trävaror o\nbyggnadsmaterial\nAntal anställda: 12\nÅrsomsättning: 1 100 000\nChefer: Byggmäst Ruben Jansson,\nbyggnadsing Lars Wallqvist\nEtableringsår. 1936.\n\nKAR\n\n18 7100, 307 01. Bankgiro\n439-0167. Postgiro 144189-8\nVerksamhet: Fabrikstillverkning av\nbetong o torrbruk. Tillverkning o\nutläggning av asfalt o oljegrus.\nGrustag\n\nBetongstation: Grums. Tel\n0555-11340\n\nGrustag: Hynboholm. Tel\n054-320 48\n\nFörsäljning: 652 23 Karlstad.\nGruscentralen, Kolg 1. Tel 054-187240\nTorrt)ruksfabrik: Karlstad, Yttre\nHamn. Tel 054-18 97 32\nAntal anställda: 45\nÅrsomsättning: 10000000\nStyrelse: Adv Ormonde Goldie\n(ordf), fru Bengta Gjein, dir Per\nGjein, fru Marianne Lennartsson,\ndir Rolf Lennartsson\nVerkst dir: Rolf Lennartsson\nFörsäljning betong: ing K G\nJohnson\n\nKamrer: östen Grundö\nEtableringsår: 1962.\n\nKARLSTADS KLICHÉ.\nANSTALT AB\n\nPnr 651 04\n\nKarlstad 1, Sjömansg 5. Box 147.\nTel 054-15 58 00. Bankgiro\n438-9326. Postgiro 70098-9\nVerksamhet: Klichéer, matriser,\nstereotyper, teckningar, retuscher,\noffsetrepro\nAntal anställda: 12\nAktiekapital: 50 000\nVerkst dir: Elis Hed\nEtableringsår: 1929.\n\nKARLSTADS\nLASTBIL-CENTRAL EK FüR\n\nPnr 653 41\n\nKarlstad, Rattg 10. Tel\n054-15 65 90. Bankgiro 881-4402.\nPostgiro 170370-1\n\nVerksamhet: Utför alla slag av\ntransporter\nAntal anställda: 95\nÅrsomsättning: 14 000 000\nInsatskapital: 1600 000\nChef: Ivan Ohlson\nEtableringsår: 1941.\n\nKARLSTADS MEKANISKA\nWERK5TAD, AB\n\nPnr 65101\n\nKarlstad 1, Verkstadsg 20. Fack.\nTel 054-11 52 60. Bankgiro\n100-3755. Postgiro 80300-7. Tga\nVerkstaden. Telex 66180 KMWKS S\nVerksamhet: Tillverkar maskiner\nför pappers- o cellulosaindustrin,\nutrustning för vattenkraftverk,\nfartygspropellrar med ställbara blad\nsamt pumpar. Beställningsarbeten\nfrämst inom grövre plåtslageri,\ngjuteri o maskinbearbetning\nVerkstäder: Karlstad, se ovan\nKristinehamn, Kristinehamnsverken.\nTel 0550-152 00. Telex 66050\nKMWKSN S. Tga Verkstaden.\nChef: dir L Pehrsson\nFilipstad, Finshyttans bruk. Tel\n0590-132 70. Tga Finshyttebruk\nVarunamn: KMW, KaMeWa\nAntal anställda: 2 500\nÅrsomsättning: 261000 000\nAktiekapital: 9 000 000\nVerkst dir: Helge Lindberg\nV veikst dir: Lennart Pehrsson\nTekn dir: Sture Eriksson\n\nEkonomidir: Gunnar Gussander\nPersonaldir: Ake Rehnberg\nEtableringsår: 1873.\n\nKARLSTADS\nMOTORRENOVERINGS AB KAMAB\n\nPnr 651 09\n\nKarlstad 1, Lantvärnsg 11. Box\n555. Tel 054-15 65 65. Bankgiro\n102-4066. Postgiro 276159-1.\nTelex 66053\n\nVerksamhet: Renovering av\nmotorer, uthyrning, reparation o service\npå Atlas Copco kompressorer o\nluftverktyg,\nmetalliseringsavdel-ning o försäljning av reservdelar\nAntal anställda: 50\nÅrsomsättning: 4 000 000\nAktiekapital: 60000\nStyrelse: Dir Gösta Edman (ordf),\ndir Sven Folke Blomgren\nVerkst dir: Sven Blomgren\nEtableringsår: 1953.\n\nKARLSTADS SPINNERI &amp;\nVÄFVERI AB\n\nPnr 652 30\n\nKarlstad, Älvg 49. Tel 054-115250.\nBankgiro 881-3172. Postgiro\n30608-4. Tga Spinneri\nVerksamhet: Tillverkning av garner,\ntyger o vävnader\n\nVerkst dir: Göran Sundblad\n(Dalsjö-fors)\n\nEtableringsår: 1898\n\nDotterbolag till Almedahl-Alingsås\nAB, Dalsjöfors.\n\nKARLSTADS STÄMPEL.\nFABRIK, AB\n\nPnr 651 05\n\nKa listad 1, Säteriv 7. Box 343. Tel\n054-115640, 1176 24. Postgiro\n368722-5\n\nVerksamhet: Tillverkar klichéer o\nstämplar\n\nAntal anställda: 10\nÅrsomsättning: 500 000\nAktiekapital: 15 000\nVerkst dir: Sune Lundh\nEtableringsår: 1949.\n\nKARLSTADS\nSYRGAS-FABRIK, AB\n\nPnr 65106\n\nKarlstad 1, Lambergets\nindustriområde. Box 386. Tel 054-150170.\nBankgiro 438-9508. Postgiro\n36146-9\n\nVerksamhet: Tillverkar oxygen\nAntal anställda: 34\nÅrsomsättning: 2 750 000\nAktiekapital: 675000\nStyrelse: Prof Georg Wästlund (ordf),\ndir Christer Danielsson, disp Bengt\nWästlund, godsägare K-F\nHultkrantz, civiling Erik Wästlund\nVerkst dir: Civiling Erik Wästlund\nEtableringsår: 1923.\n\nKARLSTADS TAGELSPINNERI\nADOLF NYHLENAB\n\nPnr 651 03\n\nKarlstad 1, Pumpg 1. Box 62. Tel\n054-18 03 60. Bankgiro 881-3784.\nPostgiro 8952-4. Tga Tagelspinn\nVerksamhet: Tillverkar spunnet o\ngummerat tagel o fiber. Plymåer o\nkuddar i DACRON fiberfill o dun\nAntal anställda: 50\n\nÅrsomsättning: 5 000 000\nAktiekapital: 200 000\nVerkst dir: Gunnar Nyhlén\nEtableringsår: 1904\nOmbildat till aktiebolag 1927.\n\nKARLSTADS VARV AB\n\nPnr 65105\n\nKarlstad 1, Kanikenäsholmen. Box\n306. Tel 054-15 16 00. Bankgiro\n100-3896. Postgiro 82632-1. Tga\nSlipen. Telex 66081 AHLMARK S\nVerksamhet: Fartygsbyggnation\nsamt fartygsreparationer, mek\nverkstad\n\nAntal anställda: 48\nÅrsomsättning: 1944 000\nAktiekapital: 415 250\nVerkst din Bengt Rejmer\nEtableringsån 1918.\n\nKARLSTADS VERKTYGS.\nFABRIK AB\n\nPnr 652 21\n\nKarlstad, Sågverksg 1. Tel\n054-11 85 74, 1100 64. Bankgiro\n881-3800. Postgiro 368260-6\nVerksamhet: Maskin- o\nverktygstillverkning, finmekaniska arbeten\nAntal anställda: 30\nÅrsomsättning: 1800 000\nAktiekapital: 100 000\nChefer: Fabr Sven Karlsson, fabr\nRune Björk\nEtableringsår: 1948.",
    "structured": {
        "1": {
            "company_name": "ESKILSTUNA TUBER AB",
            "address": "Eskilstuna, Mesta",
            "phone_number": "016-20182",
            "bank_details": {
                "bankgiro": "60-1337",
                "postgiro": "291400"
            },
            "activity": "Tillverkar förpackningstuber av aluminium",
            "establishment_year": 1964
        },
        "2": {
            "company_name": "BENDIX, JOSEPHSON & CO AB",
            "address": "Bandhagen 1, Box 80, Harpsundsv 185",
            "phone_number": "08-86 01 00",
            "bank_details": {
                "bankgiro": "168-7862",
                "postgiro": "106-5"
            },
            "activity": "Sybehör, modetrikå, badartiklar, barnkläder o sovplagg",
            "employees": 66,
            "annual_turnover": 13500000,
            "capital": 2100000,
            "establishment_year": 1857
        },
        "3": {
            "company_name": "BENGTBO PLAST-PRODUKTION AB",
            "address": "Stockholm 23, Box 23060, Hagag 29",
            "phone_number": "08-24 72 00",
            "bank_details": {
                "bankgiro": "26-0978",
                "postgiro": "195432-0"
            },
            "activity": "Utför entreprenader inom byggnadsindustrin",
            "employees": 10,
            "annual_turnover": 500000,
            "capital": 5000,
            "establishment_year": 1968
        },
        "4": {
            "company_name": "PRINS ERIC, AB",
            "address": "Malmö, Grynbodg 3",
            "phone_number": "040-321 02, 97 33 30",
            "bank_details": {
                "bankgiro": "348-2106",
                "postgiro": "531835-7"
            },
            "activity": "Tillverkar o säljer konsumentförpackade charkuterivaror o färdiglagade rätter",
            "employees": 20,
            "annual_turnover": 2000000,
            "capital": 5000,
            "establishment_year": 1959
        },
        "5": {
            "company_name": "PRINSFORS METALL. FABRIK, AB",
            "address": "Bankeryd, Box 56",
            "phone_number": "036-720 38, 72058, 722 08",
            "bank_details": {
                "bankgiro": "836-9183",
                "postgiro": "34691-7"
            },
            "activity": "Tillverkar möbelbeslag såsom handtag, knappar, fothylsor, bössningar o d. Inredningsbeslag såsom rörhållare, kasettbågar, konfektionshållare o d",
            "employees": 22,
            "capital": 50000,
            "key_personnel": [
                {
                    "name": "Uno Miller",
                    "position": "Ägare"
                },
                {
                    "name": "Sven-Olof Miller",
                    "position": "Chefer"
                }
            ],
            "establishment_year": 1920,
            "ombildat_till_aktiebolag": 1952
        },
        "6": {
            "company_name": "PRINTER^ SERVICE AB",
            "address": "Göteborg 5, Prästgårdsängen 6, Box 5120",
            "phone_number": "031-40 93 20",
            "bank_details": {
                "postgiro": "47819"
            },
            "activity": "Konsultation o produktion av trycksaker",
            "employees": 24,
            "capital": 100000,
            "establishment_year": 1962
        },
        "7": {
            "company_name": "SCANDIAMANT AB",
            "address": "Robertsfors",
            "phone_number": "0934-105 15",
            "bank_details": {
                "bankgiro": "284-0874",
                "postgiro": "6804-9"
            },
            "activity": "Tillverkar syntetiska diamanter o verktyg",
            "employees": 140,
            "annual_turnover": 16000000,
            "capital": 5000000,
            "establishment_year": 1967
        },
        "8": {
            "company_name": "NORDIC, FÄRG AB",
            "address": "Stockholm, Vasag 48",
            "phone_number": "08-10 7415",
            "bank_details": {
                "bankgiro": "724-5251",
                "postgiro": "452750-3"
            },
            "activity": "Färger, lim, plaster, grafiska kemikalier",
            "capital": 50000,
            "establishment_year": 1955
        },
        "9": {
            "company_name": "FORSSA TEGELBRUK, AB",
            "address": "Bollebygd, Box 121",
            "phone_number": "033-850 39, 85140",
            "bank_details": {
                "bankgiro": "531-1212",
                "postgiro": "99112-5"
            },
            "activity": "Tillverkar fasadtegel, mur- o månghålstegel",
            "employees": 34,
            "annual_turnover": 2500000,
            "capital": 200000,
            "key_personnel": [
                {
                    "name": "Dir Gunnar Hedelin",
                    "position": "Ordförande"
                },
                {
                    "name": "Ing Manne Haby",
                    "position": "Ing"
                },
                {
                    "name": "Dir Bengt Ejserholm",
                    "position": "Direktör"
                }
            ],
            "establishment_year": 1917
        },
        "10": {
            "company_name": "NIBE-VERKEN AB",
            "address": "Markaryd, Järnvägsg 44",
            "phone_number": "0433-112 00",
            "bank_details": {
                "bankgiro": "279-6712",
                "postgiro": "399475-3"
            },
            "activity": "Tillverkar varmvattenberedare o tryckkärl samt precisionsåmaskiner",
            "employees": 141,
            "annual_turnover": 18500000,
            "capital": 1000000,
            "key_personnel": {
                "name": "Civiling Rune Dahlberg",
                "position": "Verkställande direktör"
            },
            "establishment_year": 1952
        }
    }
}