{
    "original": "INTERNORDIA AB\n\nPnr 17104\n\nSolna 4, Ankdammsg 32. Box 431.\nTel 08-27 29 50. Bankgiro 74-6259.\nPostgiro 595040. Telex 10827\nVerksamhet: Försäljning av\n\"Nor-dia\" butiks- o köksinredningar\nAktiekapital: 15 000\nEtableringsår: 1962.\n\nsäf st rom hellgren, ab\n\nPnr 902 46\n\nUmeå, Skolg 51. Tel 090-1184 45.\nBankgiro 201-3415. Postgiro\n63603-5\n\nVerksamhet: Säljer pappersvaror\nen gros\n\nAntal anställda: 10\nAktiekapital: 25 000\nVerkst dir: Bo Nordström\nEtableringsån 1922.\n\nMIKRO OPTIK AB\n\nPnr 124 46\n\nBandhagen, Glanshammarsg 67.\nTel 08-99 17 07. Postgiro 710850-9\nVeiksamhet Säljer Nikon\nmikroskop, industriobjektiv, geodetiska\ninstrument för industrier,\ninstitutioner, skolor o dylikt\nÅrsomsättning: 600 000\nAktiekapital: 5 000\nVeikst dir Inge Laurin\nEtableringsår: 1968.\n\nPAN\n\nEtableringsår. 1949\nNärstående bolag: Pan Nordic\nMusiksystem AB,Pan Nordic Operating AB.\n\nPAN NORDIC\nMUSIKSYSTEM AB\n\nPnr 43040\n\nSärö, Box 8. Tel 031-70 55 00.\nBankgiro 224-8433. Postgiro 238401-4.\nTga Panordic\n\nVerksamhet: Bakgrundsmusik- o\ndiscothèqueanläggningar\nAktiekapital: 5 000\nVerkst dir: Lars E Rydbeck\nEtableringsår: 1966.\n\nPAN NORDIC\nOPERATING AB\n\nPnr 43040\n\nSärö, Box 8. Tel 031-70 55\nOO.Bank-giro 546-6982. Postgiro 624150-9.\nTga Panordic\n\nVerksamhet: Uthyr o\nentreprenad-uppställer serveringsautomater\nAktiekapital: 330 000\nVerkst dir: Lars E Rydbeck\nEtableringsår: 1960.\n\nMEKANO.PRODUKTER\n\nPnr 400 20\n\nGöteborg 14, Box 14036. Tel 031-\n\n180910, 81 1616. Bankgiro 505-\n\n7070. Postgiro 423059-5\n\nVerksamhet: Specialitet: plast- o\n\nrörpackningar\n\nÄgare o chef: Nils Sköld\n\nEtableringsår: 1951.\n\nCM KONTORSMATERIEL, AB\n\nPnr 16145\n\nBromma, Abrahamsberg sv 29. Tel\n08-26 81 43, 26 92 43, butik 2640 80.\nBankgiro 58-1525. Postgiro 157411\nVerksamhet: Köper o säljer\nkon-torsmateriel o reklamartiklar\nÅrsomsättning: 400 000\nAktiekapital: 10 000\nVerkst dir: Curt Magnusson\nEtableringsår: 1967.\n\nCOLD STORES\nAB STOCKHOLMS KYLHUS\n\nPnr 11641\n\nStockholm, Tegelviksg 1&amp;-23. Tel\n08-44 08 70. Bankgiro 560-4442.\nPostgiro 255908-6. Tga Coldstores.\nTelex 19185\n\nVerksamhet: Kommersiellt kyl- o\nfryshus\n\nFilialer: 11743 Stockholm,\nFör-mansv 18. Tel 08-44 08 75\n702 27 Örebro, Vattenverksg 6. Tel\n019-14 8012\nAntal anställda: 70\nAktiekapital: 1000 000\nStyrelse: Adv Johan Ramberg\n(ordf), dir Evert Hännestrand, dir\nKnud Meyer\n\nVerkst dir: Gösta Nyman\nEtableringsår: 1947.\n\nhemlins ab, john w\n\nPnr 100 72\n\nStockholm 43, Årsta Skolgränd 10.\nBox 43033. Tel 08-45 67 30,\n45 67 33. Postgiro 50394-6\nVerksamhet: Specialitet:\nreparationer o tillverkning av\nsättmaski-ner\n\nAktiekapital: 113 000\nVerkst dir: Bertil Carlberg\nEtableringsår: 1919.\n\nHEIME AB, NILS\n\nPnr 21137\n\nMalmö, Stora Nyg 24. Tel\n040-367 70. Postgiro 39393. Telex 3128.\nTga Heimebolaget\nVerksamhet: Trävaruagentur\nAktiekapital: 5 000\nChef: Konsul Törd Heime\nEtableringsår: 1911.\n\nWALLENBERG &amp; CO AB,\nHENRY\n\nPnr 103 81\n\nStockholm 7, Birger Jarlsg 6. Box\n7026. Tel 08-23 86 80. Bankgiro\n160-40 65. Postgiro 190931-6. Tga\nGoing. Telex 19116\nVerksamhet: Export o import\nAktiekapital: 1 000 000\nVerkst dir: Henry Wallenberg\nEtableringsår: 1922.\n\nWALLENBORGS KEMIKALIE\nAB\n\nPnr 161 15\n\nBromma 15, Asplundsv 13. Box\n15026. Tel 08-25 28 80, 25 17 55.\nPostgiro 19043 2. Tga Alliancetrade\n\nVerksamhet: Säljer fotokemikalier\nAktiekapital: 10 000\nVerkst dir: Ivar Waad\nEtableringsår: 1952.\n\nWALLENTIN AB,\nHANDELSFIRMAN NILS\n\nPnr 15010\n\nGnesta, Berghemsg 14. Tel\n0158-11131, 11145\n\nVerksamhet: Säljer husvagnar o\npersonbilssläpvagnar\nÅrsomsättning: 1 000 000\nAktiekapital: 15 000\nEtableringsår. 1962.\n\nKARLSHAMNS BYGG AB\n\nPnr 292 00\n\nKarlshamn, Regeringsg 52. Tel\n0454-136 61, 13125. Bankgiro\n656-7051. Postgiro 135380-4\nVerksamhet: Uppför nybyggnader o\nutför reparationer\nAntal anställda: 25\nÅrsomsättning: 1 200 000\nAktiekapital: 60 000\nVerkst dir: Ing Karl Johnsson\nEtableringsår: 1963.\n\nKARLSHAMNS\nKONFEKTIONS AB\n\nPnr 292 00\n\nKarlshamn, Erik Dahlbergsv 1. Box\n107. Tel 0454-105 85. Bankgiro\n65-107. Tel 0454-105 85. Bankgiro\n656-6855. Postgiro 755 24-9\nVerksamhet: Partihandel med\nfritidskläder o tricotage. Import\nAktiekapital: 85 500\nChef: Disp N E Johansson\nEtableringsår: 1923.\n\nKARLSHAMNS\nOLJEFABRIKER, AB\n\nPnr 292 00\n\nKarlshamn, V Kajen. Tel\n0454-143 00. Bankgiro 72-0013.\nPostgiro 152822. Tga Oljefabrik, Akofab.\nTelex 4510 AKOFAB S\nVerksamhet: Oljefabrik o\nlivsmedelsindustri. Tillverkar\nvegetabiliska o animaliska oljor, fettsyror,\nfettemulsioner, fodermedel,\nspecialprodukter för choklad-,\nlivsmedels-, bageri- o färgindustrierna,\nmargarin, glass, mandelmassa\nVarunamn: Ako, Akofrite, Akolit,\nAkomandin, Akomix, Hushålls-Eve,\nDelikatess-Eve, Bords-Eve, Winner\nAntal anställda: 700\nÅrsomsättning: 321000 000\nAktiekapital: 30 000 000\nVerkst dir: Gordon Nävert\nEtableringsår: 1932\nÄgare: Kooperativa Förbundet,\nStockholm.\n\nKARLSHAMNS STUVERI AB\n\nPnr 292 00\n\nKarlshamn, Drottningg 42. Tel\n0454-166 50. Bankgiro 831-2589.\nPostgiro 663400-0\n\nVerksamhet: Lossning 0 lastning\nav fartyg, bilar o järnvägsvagnar.\nTruckuthyrning. Disponerar\ngaffeltruckar med kapacitet 2-20 ton samt\nlastmaskiner\nAntal anställda: 60\nÅrsomsättning: 4 500 000\nAktiekapital: 11000\nStyrelse: Dir Axel Cederlund (ordf),\ndir Gordon Nävert, dir Tage\nRyt-terling, dir Gunnar Reinholtz, dir\nCurt Högberg, disp Gustaf Thern,\nkapten Kaj Janérus\nVerkst dir: John Forssell\n\nArbetschef: Arne Rehnström\nKamrer: Karl-Erik Eriksson\nEtableringsår: 1908.",
    "structured": {
        "0": {
            "company_name": "INTERNORDIA AB",
            "pnr": "17104",
            "address": "Solna 4, Ankdammsg 32. Box 431.",
            "phone_number": "08-27 29 50",
            "bank_details": {
                "bankgiro": "74-6259"
            },
            "activity": "Försäljning av 'Nor-dia' butiks- o köksinredningar",
            "capital": 15000,
            "establishment_year": 1962
        },
        "1": {
            "company_name": "säf st rom hellgren, ab",
            "pnr": "902 46",
            "address": "Umeå, Skolg 51",
            "phone_number": "090-1184 45",
            "bank_details": {
                "bankgiro": "201-3415"
            },
            "activity": "Säljer pappersvaror en gros",
            "employees": 10,
            "capital": 25000,
            "key_personnel": [
                {
                    "name": "Bo Nordström",
                    "position": "Verkst dir"
                }
            ],
            "establishment_year": 1922
        },
        "2": {
            "company_name": "MIKRO OPTIK AB",
            "pnr": "124 46",
            "address": "Bandhagen, Glanshammarsg 67",
            "phone_number": "08-99 17 07",
            "bank_details": {
                "postgiro": "710850-9"
            },
            "activity": "Säljer Nikon mikroskop, industriobjektiv, geodetiska instrument för industrier, institutioner, skolor o dylikt",
            "annual_turnover": 600000,
            "capital": 5000,
            "key_personnel": [
                {
                    "name": "Inge Laurin",
                    "position": "Veikst dir"
                }
            ],
            "establishment_year": 1968
        },
        "3": {
            "company_name": "PAN",
            "establishment_year": 1949
        },
        "4": {
            "company_name": "PAN NORDIC MUSIKSYSTEM AB",
            "pnr": "43040",
            "address": "Särö, Box 8",
            "phone_number": "031-70 55 00",
            "bank_details": {
                "bankgiro": "224-8433"
            },
            "activity": "Bakgrundsmusik- o discothèqueanläggningar",
            "capital": 5000,
            "key_personnel": [
                {
                    "name": "Lars E Rydbeck",
                    "position": "Verkst dir"
                }
            ],
            "establishment_year": 1966
        },
        "5": {
            "company_name": "PAN NORDIC OPERATING AB",
            "pnr": "43040",
            "address": "Särö, Box 8",
            "phone_number": "031-70 55 00",
            "bank_details": {
                "bankgiro": "546-6982"
            },
            "activity": "Uthyr o entreprenad-uppställer serveringsautomater",
            "capital": 330000,
            "key_personnel": [
                {
                    "name": "Lars E Rydbeck",
                    "position": "Verkst dir"
                }
            ],
            "establishment_year": 1960
        },
        "6": {
            "company_name": "MEKANO.PRODUKTER",
            "pnr": "400 20",
            "address": "Göteborg 14, Box 14036",
            "phone_number": "031-180910, 81 1616",
            "bank_details": {
                "bankgiro": "505-7070",
                "postgiro": "423059-5"
            },
            "activity": "Specialitet: plast- o rörpackningar",
            "key_personnel": [
                {
                    "name": "Nils Sköld",
                    "position": "Ägare o chef"
                }
            ],
            "establishment_year": 1951
        },
        "7": {
            "company_name": "CM KONTORSMATERIEL, AB",
            "pnr": "16145",
            "address": "Bromma, Abrahamsberg sv 29",
            "phone_number": "08-26 81 43, 26 92 43, butik 2640 80",
            "bank_details": {
                "bankgiro": "58-1525",
                "postgiro": "157411"
            },
            "activity": "Köper o säljer kontorsmateriel o reklamartiklar",
            "annual_turnover": 400000,
            "capital": 10000,
            "key_personnel": [
                {
                    "name": "Curt Magnusson",
                    "position": "Verkst dir"
                }
            ],
            "establishment_year": 1967
        },
        "8": {
            "company_name": "COLD STORES AB STOCKHOLMS KYLHUS",
            "pnr": "11641",
            "address": "Stockholm, Tegelviksg 1&amp;-23",
            "phone_number": "08-44 08 70",
            "bank_details": {
                "bankgiro": "560-4442",
                "postgiro": "255908-6"
            },
            "activity": "Kommersiellt kyl- o fryshus",
            "employees": 70,
            "capital": 1000000,
            "key_personnel": [
                {
                    "name": "Gösta Nyman",
                    "position": "Verkst dir"
                }
            ],
            "establishment_year": 1947
        },
        "9": {
            "company_name": "hemlins ab, john w",
            "pnr": "100 72",
            "address": "Stockholm 43, Årsta Skolgränd 10. Box 43033",
            "phone_number": "08-45 67 30, 45 67 33",
            "postgiro": "50394-6",
            "activity": "Specialitet: reparationer o tillverkning av sättmaskiner",
            "capital": 113000,
            "key_personnel": [
                {
                    "name": "Bertil Carlberg",
                    "position": "Verkst dir"
                }
            ],
            "establishment_year": 1919
        },
        "10": {
            "company_name": "HEIME AB, NILS",
            "pnr": "21137",
            "address": "Malmö, Stora Nyg 24",
            "phone_number": "040-367 70",
            "postgiro": "39393",
            "activity": "Trävaruagentur",
            "capital": 5000,
            "key_personnel": [
                {
                    "name": "Konsul Törd Heime",
                    "position": "Chef"
                }
            ],
            "establishment_year": 1911
        },
        "11": {
            "company_name": "WALLENBERG &amp; CO AB, HENRY",
            "pnr": "103 81",
            "address": "Stockholm 7, Birger Jarlsg 6. Box 7026",
            "phone_number": "08-23 86 80",
            "bank_details": {
                "bankgiro": "160-40 65",
                "postgiro": "190931-6"
            },
            "activity": "Export o import",
            "capital": 1000000,
            "key_personnel": [
                {
                    "name": "Henry Wallenberg",
                    "position": "Verkst dir"
                }
            ],
            "establishment_year": 1922
        },
        "12": {
            "company_name": "WALLENBORGS KEMIKALIE AB",
            "pnr": "161 15",
            "address": "Bromma 15, Asplundsv 13. Box 15026",
            "phone_number": "08-25 28 80, 25 17 55",
            "postgiro": "19043 2",
            "activity": "Säljer fotokemikalier",
            "capital": 10000,
            "key_personnel": [
                {
                    "name": "Ivar Waad",
                    "position": "Verkst dir"
                }
            ],
            "establishment_year": 1952
        },
        "13": {
            "company_name": "WALLENTIN AB, HANDELSFIRMAN NILS",
            "pnr": "15010",
            "address": "Gnesta, Berghemsg 14",
            "phone_number": "0158-11131, 11145",
            "activity": "Säljer husvagnar o personbilssläpvagnar",
            "annual_turnover": 1000000,
            "capital": 15000,
            "establishment_year": 1962
        },
        "14": {
            "company_name": "KARLSHAMNS BYGG AB",
            "pnr": "292 00",
            "address": "Karlshamn, Regeringsg 52",
            "phone_number": "0454-136 61, 13125",
            "bank_details": {
                "bankgiro": "656-7051",
                "postgiro": "135380-4"
            },
            "activity": "Uppför nybyggnader o utför reparationer",
            "employees": 25,
            "annual_turnover": 1200000,
            "capital": 60000,
            "key_personnel": [
                {
                    "name": "Ing Karl Johnsson",
                    "position": "Verkst dir"
                }
            ],
            "establishment_year": 1963
        },
        "15": {
            "company_name": "KARLSHAMNS KONFEKTIONS AB",
            "pnr": "292 00",
            "address": "Karlshamn, Erik Dahlbergsv 1. Box 107",
            "phone_number": "0454-105 85",
            "bank_details": {
                "bankgiro": "65-107",
                "postgiro": "755 24-9"
            },
            "activity": "Partihandel med fritidskläder o tricotage. Import",
            "capital": 85500,
            "key_personnel": [
                {
                    "name": "Disp N E Johansson",
                    "position": "Chef"
                }
            ],
            "establishment_year": 1923
        },
        "16": {
            "company_name": "KARLSHAMNS OLJEFABRIKER, AB",
            "pnr": "292 00",
            "address": "Karlshamn, V Kajen",
            "phone_number": "0454-143 00",
            "bank_details": {
                "bankgiro": "72-0013",
                "postgiro": "152822"
            },
            "activity": "Oljefabrik o livsmedelsindustri. Tillverkar vegetabiliska o animaliska oljor, fettsyror, fettemulsioner, fodermedel, specialprodukter för choklad-, livsmedels-, bageri- o färgindustrierna, margarin, glass, mandelmassa",
            "employees": 700,
            "annual_turnover": 321000000,
            "capital": 30000000,
            "key_personnel": [
                {
                    "name": "Gordon Nävert",
                    "position": "Verkst dir"
                }
            ],
            "establishment_year": 1932,
            "owners": "Kooperativa Förbundet, Stockholm"
        },
        "17": {
            "company_name": "KARLSHAMNS STUVERI AB",
            "pnr": "292 00",
            "address": "Karlshamn, Drottningg 42",
            "phone_number": "0454-166 50",
            "bank_details": {
                "bankgiro": "831-2589",
                "postgiro": "663400-0"
            },
            "activity": "Lossning 0 lastning av fartyg, bilar o järnvägsvagnar. Truckuthyrning. Disponerar gaffeltruckar med kapacitet 2-20 ton samt lastmaskiner",
            "employees": 60,
            "annual_turnover": 4500000,
            "capital": 11000,
            "key_personnel": [
                {
                    "name": "John Forssell",
                    "position": "Verkst dir"
                },
                {
                    "name": "Arne Rehnström",
                    "position": "Arbetschef"
                },
                {
                    "name": "Karl-Erik Eriksson",
                    "position": "Kamrer"
                }
            ],
            "establishment_year": 1908
        }
    }
}