{
    "original": "SANDGREEN, AB OTTO\n\nPnr 211 22\n\nMalmö, Kyrkog 1. Tel 040-1167 84,\n12 03 51. Postgiro 635549-9. Tga\nOttosa\n\nVerksamhet: Importerar textilier\n\nAntal anställda: 4\n\nAktiekapital: 18 000\n\nStyrelse: Adv Bengt Linders (ordf),\n\ndir Otto Sandgren\n\nVerkst din Otto Sandgreen\n\nEtableringsår: 1946.\n\nSANDIN och BERG,\nRÖRLEDNINGS AB\n\nPnr 69100\n\nKarlskoga, Fabriksg 18. Tel\n0586-503 00. Bankgiro 823-3280.\nPostgiro 569460-9\n\nVerksamhet: Värme-, ventilations-,\nolje- o sanitetsentreprenader.\nUtför rörinstallationer för industrin\no WS-reparationer\nAntal anställda: 39\nÅrsomsättning: 4 000 000\nAktiekapital: 40000\nStyrelse: Kamrer Karl-Herman\nBerg, adv Lars-Erik Widell\nVerkst dlr: Kanrer Karl-Herman\nBerg\n\nIng: Arthur Persson\nVerkmästare: Ragnar Funke\nEtableringsår: 1965.\n\nmassdekor ab\n\nPnr 21129\n\nMalmö, Gasverksg 7. Tel\n040-12 62 20. Bankgiro 645-8301.\nPostgiro 635210-8\n\nVerksamhet: Screentryckeri,\ndekorationer o utställningar\nAktiekapital: 10 000\nVerkst dir: Yngve Andrén\nEtableringsår 1967\nIngår i Tryckerigruppen i Malmö\nAB.\n\nmasterhand ab\n\nPnr 21450\n\nMalmö, Västanforsg 21. Tel\n040-803 30. Bankgiro 156-4319. Post\ngiro 38249-9. Tga Masterhand\nVerksamhet: Tillverkar herr- o\ndamkonfektion\nAntal anstäUda: 200\nÅrsomsättning: 10 000 000\nAktiekapital: 1200 000\nVerkst dir: Carl Grotte\nEtableringsår: 1924.\n\nVÄRMEKONSTRUKTIONER AB\n\nPnr 38101\n\nKalmar 1, O Sjög 1. Box 134. Tel\n0480-16731, 167 37. Bankgiro\n148-2504. Postgiro 292263-1\nVerksamhet: Konsulterande\ningenjörsbyrå för värme, ventilation o\nsanitet\n\nAntal anställda: 6\nAktiekapital: 5 000\nVerkst dir Nils Franzén\nEtableringsår 1950.\n\nLAGGE, AB H\n\nPnr 852 31\n\nSundsvall, Trädgårdsg 41 A. Tel\n060-U 3947, 113967. Tga\nLagge-bolag\n\nVerksamhet: Specialitet tekn\narmatur av rostfritt-syrafast stål för\ncellulosa- o kemiska industrin\nAktiekapital: 30 000\nVerkst dir: R Frödin\nEtableringsår: 1942\nOmbildat till aktiebolag 1949.\n\nLAGMANSHOLMSVERKEN, AB\n\nPnr 441 00\n\nAlingsås, Nolhaga. Tel 0322-143 30,\n143 31. Bankgiro 889-7522.\nPostgiro 365949-7\n\nVerksamhet: Tillverkar o säljer\nelektr värmeapparater av alla slag\nAktiekapital: 80 000\nÄgare o chefer: Ing Arvid\nSandquist, ing Sigurd Andersson\nEtableringsår: 1947.\n\nHANSON &amp; MOHRING, Ab\n\nPnr 402 74\n\nGöteborg 8, Sannegårdshamnen.\nBox 8992. Tel 031-23 53 40.\nBankgiro 852-6188. Postgiro 41232-0.\nTga Saltimpcrt. Telex 20658\nVerksamhet: Säljer allt i salt,\nkalciumklorid, industrikemikalier,\nlantbrukskemikalier, snäckskal,\nfoderkalk o soda\nAktiekapital: 243 000\nVerkst dir: Per-Olof Hanson\nEtableringsår 1830\nOmbildat till aktiebolag 1905.\n\nHANSSONS PYROTEKNISKA\nAB\n\nPnr 400 30\n\nGöteborg 11, Box 11038. Tel\n031-28 20 00. Bankgiro 50-0141.\nPostgiro 42422. Tga Pyrofabrik\nVerksamhet: Tillverkar\npyrotek-niska artiklar, skeppssignaler,\nstartpatroner, signalmateriel o\nkrigsmateriel\nVarunamn: Ikaros\nAntal anställda: 50\nÅrsomsättning: 3500 000\nAktiekapital: 80000\nStyrelse: Adv Hans Vinge (ordf),\nciviling Edvin Ek, ing Manne\nWilson, civiling Douglas Åberg,\nförsäljn-chef Rustan Åberg\nVerkst dir: Civiling Douglas Åberg\nFabrikschef: Ing Manne Wilson\nFörsäljn-chef: Rustan Åberg\nEtableringsår: 1888.\n\nHANSSON &amp; WESTMAN,\nBYGGNADS AB\n\nPnr 56103\n\nHuskvarna 3, Box 3030. Tormenåsg\n5. Tel 036-13 26 75. Bankgiro\n544-5606. Postgiro 570080-2\nVerksamhet: Husbyggnader,\nreparationer m m\nAntal anställda: 45\nÅrsomsättning: 5 000 000\n\nHANSSON,\nINGENJÖRSFIRMAN C G\n\nPnr 135 02\n\nTyresö 2, Kumla allé 20-22. Box\n2050. Tel 08-71218 90, 71218 94.\nBankgiro 73-4432. Postgiro 225111.\nTga Cegehans, Stockholm\nVerksamhet: Tillverkar o säljer\nnivåkontroller\nAntal anställda: 8\nÅrsomsättning: 650 000\nChef: C G Hansson\nEtableringsår: 1959.\n\nCALE-INDUSTRI AB\n\nPnr 802 20\n\nGävle, S Centralg 22. Tel\n026-18 82 65. Bankgiro 330-1942.\nPostgiro 453587-8\n\nVerksamhet: Tillverkar Cale P-mä-\n\ntare o Cale biljettautomat samt\n\nvägmärken\n\nVarunamn: Cale\n\nAntal anställda: 70\n\nÅrsomsättning: 5 000 000\n\nAktiekapital: 25 000\n\nVerkst dir: Carl Axel Andersson\n\nEtableringsår: 1961.\n\nCALE-PRODUKTER\nGDSTA CANNERHEIM &amp; CO\n\nPnr 413 11\n\nGöteborg, Nordostpassagen 35. Tel\n031-42 35 60, 42 35 62. Postgiro\n425529. Tga Calepro\nVerksamhet: Plaster, plastråvaror\no svetsfolier i PVC-plast\nChef: E J Lennart Leijon\nEtableringsår: 1960.\n\nHALD &amp; TESCH BRAND AB\n\nPnr 11130\n\nStockholm, Skeppsbron 34. Tel\n08-23 29 60. Bankgiro 56-8916.\nPostgiro 3005. Tga Hald. Telex 17308\nVerksamhet: Handbrandsläckare o\nservice av släckare,\nexplosions-säkra kärl o kolsyreanläggningar\nAktiekapital: 90 000\nVeikst dir: Magnus Kistner.\n\nHALD &amp; TESCH STAL AB\n\nPnr 102 51\n\nStockholm 27, Narvav 12. Box\n27018. Tel 08-22 40 60. Bankgiro\n56-9056. Postgiro 609102. Telex\n19996\n\nVerksamhet: Grossist i byggstål\nAntal anställda: 7\nÅrsomsättning: 31200 000\nAktiekapital: 300 000\nVetkst dir: Alf G Lindahl\nEtableringsår: 1959.\n\nLINDAHL &amp; ROTHOFF, AB\n\nPnr 200 62\n\nMalmö 9, Fack. Regementsg 16. Tel\n040-12 23 89, 11 9745. Bankgiro\n641-0161. Postgiro 24521-7. Tga\nLinro\n\nVerksamhet: Försäljning av alla\nslags kontorsmaskiner,\nelektronräknare mm. Serviceverkstad\nAktiekapital: 50 000\nVerkst dir: Henry Persson\nEtableringsår: 1924.\n\nLINJEFLYG AB\n\nPnr 16110\n\nBromma 10, Ulvsundav 189. Fack.\nTel 08-28 9 2 40. Postgiro 60 2 300-6.\nTga Linaero.\nTelex 19165 LIN AIR S\nVerksamhet: Reguljär inrikes\ntrafik. Charter- o beställningsflyg\nVerkst dir: Ame Wickberg\nEtableringsår: 1957.\n\nWENGSTROM &amp; CO AB, STIG\n\nPnr 124 21\n\nBandhagen 1, Skebokvarnsv 275.\nBox 79. Tel 08-86 56 52, 86 56 53.\nBankgiro 47-8703. Postgiro 199032\nVerksamhet: Försäljning o\nmontering av natursten\nAntal anställda: 9\nÅrsomsättning: 1 500 000\nAktiekapital: 5 000\nVerkst dir: Stig Wengström\nEtableringsår: 1944.",
    "structured": {
        "1": {
            "company_name": "SANDGREEN, AB OTTO",
            "pnr": "211 22",
            "address": "Malmö, Kyrkog 1",
            "phone_number": "040-1167 84",
            "bank_details": {
                "postgiro": "635549-9"
            },
            "activity": "Importerar textilier",
            "employees": 4,
            "capital": 18000,
            "key_personnel": [
                {
                    "name": "Adv Bengt Linders",
                    "position": "ordf"
                },
                {
                    "name": "dir Otto Sandgren",
                    "position": null
                },
                {
                    "name": "Verkst din Otto Sandgreen",
                    "position": null
                }
            ],
            "establishment_year": 1946
        },
        "2": {
            "company_name": "SANDIN och BERG, RÖRLEDNINGS AB",
            "pnr": "69100",
            "address": "Karlskoga, Fabriksg 18",
            "phone_number": "0586-503 00",
            "bank_details": {
                "bankgiro": "823-3280",
                "postgiro": "569460-9"
            },
            "activity": "Värme-, ventilations-, olje- o sanitetsentreprenader. Utför rörinstallationer för industrin o WS-reparationer",
            "employees": 39,
            "annual_turnover": 4000000,
            "capital": 40000,
            "key_personnel": [
                {
                    "name": "Kamrer Karl-Herman Berg",
                    "position": null
                },
                {
                    "name": "adv Lars-Erik Widell",
                    "position": null
                },
                {
                    "name": "Verkst dlr: Kanrer Karl-Herman Berg",
                    "position": null
                }
            ],
            "establishment_year": 1965
        },
        "3": {
            "company_name": "massdekor ab",
            "pnr": "21129",
            "address": "Malmö, Gasverksg 7",
            "phone_number": "040-12 62 20",
            "bank_details": {
                "bankgiro": "645-8301",
                "postgiro": "635210-8"
            },
            "activity": "Screentryckeri, dekorationer o utställningar",
            "capital": 10000,
            "key_personnel": [
                {
                    "name": "Verkst dir: Yngve Andrén",
                    "position": null
                }
            ],
            "establishment_year": 1967
        },
        "4": {
            "company_name": "masterhand ab",
            "pnr": "21450",
            "address": "Malmö, Västanforsg 21",
            "phone_number": "040-803 30",
            "bank_details": {
                "bankgiro": "156-4319",
                "postgiro": "38249-9"
            },
            "activity": "Tillverkar herr- o damkonfektion",
            "employees": 200,
            "annual_turnover": 10000000,
            "capital": 1200000,
            "key_personnel": [
                {
                    "name": "Verkst dir: Carl Grotte",
                    "position": null
                }
            ],
            "establishment_year": 1924
        },
        "5": {
            "company_name": "VÄRMEKONSTRUKTIONER AB",
            "pnr": "38101",
            "address": "Kalmar 1, O Sjög 1, Box 134",
            "phone_number": "0480-16731, 167 37",
            "bank_details": {
                "bankgiro": "148-2504",
                "postgiro": "292263-1"
            },
            "activity": "Konsulterande ingenjörsbyrå för värme, ventilation o sanitet",
            "employees": 6,
            "capital": 5000,
            "key_personnel": [
                {
                    "name": "Verkst dir Nils Franzén",
                    "position": null
                }
            ],
            "establishment_year": 1950
        },
        "6": {
            "company_name": "LAGGE, AB H",
            "pnr": "852 31",
            "address": "Sundsvall, Trädgårdsg 41 A",
            "phone_number": "060-U 3947, 113967",
            "activity": "Specialitet tekn armatur av rostfritt-syrafast stål för cellulosa- o kemiska industrin",
            "capital": 30000,
            "key_personnel": [
                {
                    "name": "Verkst dir: R Frödin",
                    "position": null
                }
            ],
            "establishment_year": 1942
        },
        "7": {
            "company_name": "LAGMANSHOLMSVERKEN, AB",
            "pnr": "441 00",
            "address": "Alingsås, Nolhaga",
            "phone_number": "0322-143 30, 143 31",
            "bank_details": {
                "bankgiro": "889-7522",
                "postgiro": "365949-7"
            },
            "activity": "Tillverkar o säljer elektr värmeapparater av alla slag",
            "capital": 80000,
            "key_personnel": [
                {
                    "name": "Ägare o chefer: Ing Arvid Sandquist",
                    "position": null
                },
                {
                    "name": "ing Sigurd Andersson",
                    "position": null
                }
            ],
            "establishment_year": 1947
        },
        "8": {
            "company_name": "HANSON & MOHRING, Ab",
            "pnr": "402 74",
            "address": "Göteborg 8, Sannegårdshamnen, Box 8992",
            "phone_number": "031-23 53 40",
            "bank_details": {
                "bankgiro": "852-6188",
                "postgiro": "41232-0"
            },
            "activity": "Säljer allt i salt, kalciumklorid, industrikemikalier, lantbrukskemikalier, snäckskal, foderkalk o soda",
            "capital": 243000,
            "key_personnel": [
                {
                    "name": "Verkst dir: Per-Olof Hanson",
                    "position": null
                }
            ],
            "establishment_year": 1830
        },
        "9": {
            "company_name": "HANSSONS PYROTEKNISKA AB",
            "pnr": "400 30",
            "address": "Göteborg 11, Box 11038",
            "phone_number": "031-28 20 00",
            "bank_details": {
                "bankgiro": "50-0141"
            },
            "activity": "Tillverkar pyrotekniska artiklar, skeppssignaler, startpatroner, signalmateriel o krigsmateriel",
            "employees": 50,
            "annual_turnover": 3500000,
            "capital": 80000,
            "key_personnel": [
                {
                    "name": "Styrelse: Adv Hans Vinge (ordf)",
                    "position": null
                },
                {
                    "name": "civiling Edvin Ek",
                    "position": null
                },
                {
                    "name": "ing Manne Wilson",
                    "position": null
                },
                {
                    "name": "civiling Douglas Åberg",
                    "position": null
                },
                {
                    "name": "försäljn-chef Rustan Åberg",
                    "position": null
                }
            ],
            "establishment_year": 1888
        },
        "10": {
            "company_name": "HANSSON & WESTMAN, BYGGNADS AB",
            "pnr": "56103",
            "address": "Huskvarna 3, Box 3030, Tormenåsg 5",
            "phone_number": "036-13 26 75",
            "bank_details": {
                "bankgiro": "544-5606",
                "postgiro": "570080-2"
            },
            "activity": "Husbyggnader, reparationer m m",
            "employees": 45,
            "annual_turnover": 5000000
        },
        "11": {
            "company_name": "HANSSON, INGENJÖRSFIRMAN C G",
            "pnr": "135 02",
            "address": "Tyresö 2, Kumla allé 20-22, Box 2050",
            "phone_number": "08-71218 90, 71218 94",
            "bank_details": {
                "bankgiro": "73-4432",
                "postgiro": "225111"
            },
            "activity": "Tillverkar o säljer nivåkontroller",
            "employees": 8,
            "annual_turnover": 650000,
            "capital": null,
            "key_personnel": [
                {
                    "name": "Chef: C G Hansson",
                    "position": null
                }
            ],
            "establishment_year": 1959
        },
        "12": {
            "company_name": "CALE-INDUSTRI AB",
            "pnr": "802 20",
            "address": "Gävle, S Centralg 22",
            "phone_number": "026-18 82 65",
            "bank_details": {
                "bankgiro": "330-1942",
                "postgiro": "453587-8"
            },
            "activity": "Tillverkar Cale P-mätare o Cale biljettautomat samt vägmärken",
            "employees": 70,
            "annual_turnover": 5000000,
            "capital": 25000,
            "key_personnel": [
                {
                    "name": "Verkst dir: Carl Axel Andersson",
                    "position": null
                }
            ],
            "establishment_year": 1961
        },
        "13": {
            "company_name": "CALE-PRODUKTER GDSTA CANNERHEIM & CO",
            "pnr": "413 11",
            "address": "Göteborg, Nordostpassagen 35",
            "phone_number": "031-42 35 60, 42 35 62",
            "bank_details": {
                "postgiro": "425529"
            },
            "activity": "Plaster, plastråvaror o svetsfolier i PVC-plast",
            "employees": null,
            "capital": null,
            "key_personnel": [
                {
                    "name": "Chef: E J Lennart Leijon",
                    "position": null
                }
            ],
            "establishment_year": 1960
        },
        "14": {
            "company_name": "HALD & TESCH BRAND AB",
            "pnr": "11130",
            "address": "Stockholm, Skeppsbron 34",
            "phone_number": "08-23 29 60",
            "bank_details": {
                "bankgiro": "56-8916",
                "postgiro": "3005"
            },
            "activity": "Handbrandsläckare o service av släckare, explosions-säkra kärl o kolsyreanläggningar",
            "capital": 90000,
            "key_personnel": [
                {
                    "name": "Veikst dir: Magnus Kistner",
                    "position": null
                }
            ]
        },
        "15": {
            "company_name": "HALD & TESCH STAL AB",
            "pnr": "102 51",
            "address": "Stockholm 27, Narvav 12, Box 27018",
            "phone_number": "08-22 40 60",
            "bank_details": {
                "bankgiro": "56-9056",
                "postgiro": "609102"
            },
            "activity": "Grossist i byggstål",
            "employees": 7,
            "annual_turnover": 31200000,
            "capital": 300000,
            "key_personnel": [
                {
                    "name": "Vetkst dir: Alf G Lindahl",
                    "position": null
                }
            ],
            "establishment_year": 1959
        },
        "16": {
            "company_name": "LINDAHL & ROTHOFF, AB",
            "pnr": "200 62",
            "address": "Malmö 9, Fack. Regementsg 16",
            "phone_number": "040-12 23 89, 11 9745",
            "bank_details": {
                "bankgiro": "641-0161",
                "postgiro": "24521-7"
            },
            "activity": "Försäljning av alla slags kontorsmaskiner, elektronräknare mm. Serviceverkstad",
            "capital": 50000,
            "key_personnel": [
                {
                    "name": "Verkst dir: Henry Persson",
                    "position": null
                }
            ],
            "establishment_year": 1924
        },
        "17": {
            "company_name": "LINJEFLYG AB",
            "pnr": "16110",
            "address": "Bromma 10, Ulvsundav 189",
            "phone_number": "08-28 9 2 40",
            "bank_details": {
                "postgiro": "60 2 300-6"
            },
            "activity": "Reguljär inrikes trafik. Charter- o beställningsflyg",
            "employees": null,
            "annual_turnover": null,
            "capital": null,
            "key_personnel": [
                {
                    "name": "Verkst dir: Ame Wickberg",
                    "position": null
                }
            ],
            "establishment_year": 1957
        },
        "18": {
            "company_name": "WENGSTROM & CO AB, STIG",
            "pnr": "124 21",
            "address": "Bandhagen 1, Skebokvarnsv 275, Box 79",
            "phone_number": "08-86 56 52, 86 56 53",
            "bank_details": {
                "bankgiro": "47-8703",
                "postgiro": "199032"
            },
            "activity": "Försäljning o montering av natursten",
            "employees": 9,
            "annual_turnover": 1500000,
            "capital": 5000,
            "key_personnel": [
                {
                    "name": "Verkst dir: Stig Wengström",
                    "position": null
                }
            ],
            "establishment_year": 1944
        }
    }
}