{
    "original": "KARLSSON, AB K W\n\nPnr 52010\n\nGäUstad. Tel 0321-702 40\nVerksamhet: Tillverkar yttertrikå\no badartiklar\nAktiekapital: 300 000\nFirmatecknare: Ake Johansson\nEtableringsår: 1923.\n\nCARLSSONS SNICKERI.\nMONTERING, KJELL\n\nPnr 710 23\n\nGlanshammar, Hälglöt. Tel\n019-690 57\n\nVerksamhet: Montage av\naffärsinredning, möbler o andra snickerier\nChef: Kjell Carlsson\nEtableringsår: 1967.\n\nSEDAB DATABEHANDLING AB\n\nPnr 29101\n\nKristianstad 1, Box 317. S Kaserng\n9. Tel 044-12 0981. Bankgiro\n167-8499. Postgiro 173554-6\nVerksamhet: Servicebyrå för\ndatabehandling\nAntal anställda: 17\nÅrsomsättning: 1500 000\nAktiekapital: 25 000\nVerkst dir: Karl Olsson\nEtableringsår 1963.\n\nTHORPLAST AB\n\nPnr 136 00\n\nHanden, Hantverkarv 31. Tel\n08-777 01 40. Bankgiro 478-7040.\nPostgiro 603385-6. Tga Thorplast\nVerksamhet: Formsprutning av\ntermoplaster för industridetaljer mm\nAntal anställda: 30\nÅrsomsättning: 4 500 000\nAktiekapital: 72 000\nVerkst dir: Niels V Thorsen\nEtableringsår: 1959.\n\nSJUBO BRUK, AB\n\nPnr 275 00\n\nSjöbo. Box 4. Tel 0416-108 10.\nBankgiro 662-7699. Postgiro\n291930-6\n\nVerksamhet: Gjuteri o mekanisk\n\nverkstad\n\nVarunamn: Purus\n\nAntal anställda: 100\n\nÅrsomsättning: 10 000 000\n\nAktiekapital: 50 000\n\nStyrelse: Dir Walter Wredenfors\n\n(ordf), bankdir Bengt Senneby, dir\n\nBengt Spånberg\n\nVerkst dir: Bengt Spånberg\n\nEtableringsår: 1945.\n\nGOT\n\nVerksamhet: Termometrar,\nmanometrar, hygrometrar,\nlaboratorieutensilier\nAntal anställda: 13\nÅrsomsättning: 2500 000\nAktiekapital: 20 000\nChef: Dir Helge Schramm\nEtableringsår: 1946.\n\nGOTEBORGS TEXTILENGROS\nAB\n\nPnr 43122\n\nMölndal 1, Box 99. Flöjelbergsg\n6-10. Tel 031-27 52 00. Bankgiro\n33-7261. Postgiro 48640-7. Tga\nKappahl. Telex 20740\nVerksamhet: Säljer tyger en gros\nÅrsomsättning: 1800 000\nAktiekapital: 50 000\nVerkst dir: Per Olof K-son Ahl\nEtableringsår: 1959.\n\nGOTEBORGS TRÄ. &amp;\nFANER AB\n\nPnr 402 71\n\nGöteborg 8, Holmvägen, Holm\nIndustriområde. Box 8844. Tel\n031-66 09 00. Bankgiro 508-7655.\nPostgiro 40891-4. Tga Getefa\nVerksamhet: Utländska träslag,\nfaner, plywood, lamellträ o\nmöbel-smiden\n\nAktiekapital: 225 000\nVerkst dir: Evert Mellkvist\nEtableringsår: 1893\nOmbildat till aktiebolag 1936.\n\nGOTEBORGS VERKSTADS.\nINDUSTRI AB\n\nPnr 417 05\n\nGöteborg. Gustaf Dalënsg 13. Tel\n031-2278 10, 5158 00. Bankgiro\n420-0705. Postgiro 240057-0.\nTga Götabox\n\nVerksamhet: Tillverkar\njärnkonstruktioner, ångpannor, tryckkärl\no värmepannor för villor. Utför\nlicenssvetsning o arbeten i\naluminium o rostfritt samt\nrörlednings-entreprenader. Utför service o\nreparationer åt olika industrier\nVarunamn: Kungspannan\nAntal anställda: 180\nÅrsomsättning: 11300 000\nAktiekapital: 150 000\nVerkst dir: Allan Ericsson\nEtableringsår: 1935\nOmbildat till aktiebolag 1960.\nDotterbolag: Norrhults\nVerkstadsindustri AB.\n\nGOTEBORG-DALS\nPAPPERSBRUK, AB\n\nPnr 402 72\n\nGöteborg 8, Box 8852. Tel\n031-22 21 10. Bankgiro 506-5198.\nPostgiro 426150-9. Tga Dalsbruket.\nTelex 2563\n\nVerksamhet: Tillverkar MG\nsulfit-papper, råpapper för engångskarbon,\nlaminering, vaxning. o fruktomslag\netc. Kräppat sulfitpapper,\nfilterpapper, pappershanddukar, köks- o\ntoalettrullar, specialiteter i\nkräppat\n\nAntal anställda: 155\nÅrsomsättning: 19 000 000\nAktiekapital: 2 000 000\nStyrelse: Dir Sven-Ake Sjöholm\n(ordf), dir Töre Bergbrant, adv Kurt\nMark, disp Gunnar Lundh, dir\nAlbrecht Wagner\n\nVerkst dir: Gunnar Lundh\nFörsäljn-chef: Karl Arne Hjalber\nKamrer: Sven Hansson\nEtableringsår: 1898.\n\nGOT E BORG-FREDERI\nKSHAVN-LINJEN, REDERI AB\n\nPnr 40241\n\nGöteborg 12, Majnabbehamnen. Box\n12065. Tel 031-1249 00. Telex\n20886. Tga Gefel\nVerksamhet: Passagerare-, bil- o\ngodstrafik Göteborg-Frederikshavn\n.Antal anställda: 600\nÅrsomsättning: 35 000 000\nAktiekapital: 3 000 000\nVerkst dir: Kapten Ulf Trapp\nEtableringsår: 1935.\n\nGOTEBORGS-POSTENS\nNYA AB\n\nPnr 405 02\n\nGöteborg, Polhemsplatsen 5. Tel\n031-17 63 00. Telex 2227. Tga\nGot-posten. Postgiro för annonser\n12005-5, för prenumeration Göteborg\n12190-5, för prenumeration utanför\nGöteborg 40120-8, för\npostprenumeration 45701-0, för\nlösnummerförsäljare 524918-0. Bankgiro 501-7637\nVeiksamhet: Tidningstryckeri.\nUtger Göteborgs-Posten: utkommer\ndagligen, medelnettoupplaga l:sta\nhalvåret 1970, vardagar 288 898\nexemplar, söndagar 261842\nexemplar\n\nÅrsomsättning: 77 000 000\nAktiekapital: 200 000\nStyrelse: Anna Hjörne, Lars\nHjör-ne, Hilde Andersson\nVerkst dir: Hilde Andersson\nEtableringsår: 1897.\n\nSOLIDITET AB\n\nPnr 102 25\n\nStockholm 12, Box 12179.\nHuvudkontor Sankt Eriksg 38. Tel\n08-52 07 50. Upplysningsavd\nRege-ringsg 61. Box 7015, 103 81\nStockholm 7. Tel 08-22 34 40. Bankgiro\n332-1684. Postgiro 1252-6. Tga\nSoliditet. Telex 10194\nVerksamhet: Meddelar\nsoliditets-upplysningar, emottager inkasso- o\növriga juridiska o kommersiella\nuppdrag\n\nAvdelningskontor: Göteborg,\nS Hamng 29. Tel 031-17 07 00\nMalmö, Söderg 28. Tel 040-717 50\nUmeå. Storg 50 B. Tel 090-13 24 40\nAntal anstäUda: 350\nAktiekapital: 1000 000\nStyrelse: G Calissendorff, E W\nGreen, C Reichenberg, R F Rivard,\nH Sparring, W Westergren\nEtableringsår: 1908.\n\ngeralf patentbyrä ab, w\n\nPnr 111 56\n\nStockholm C, Kungsg 33. Tel\n08-1152 21, 2185 50. Bankgiro\n23-5157. Postgiro 153058. Tga Wilger\nVerksamhet: Patentombud\nAntal anställda: 9\nAktiekapital: 5 000\nVerkst dir: W Geralf\nEtableringsår: 1937.\n\nLUMACO AB\n\nPnr 40121\n\nGöteborg 1, Packhusg 2-3. Box 77.\nTel 031-1394 40. Bankgiro\n501-6472. Postgiro 628066-3. Tga Lu-\n\nmaco. Telex 2205 EMBE S\nVerksamhet: Försäljning av\nindustrikemikalier o plastråvaror\nAktiekapital: 5 000\nVerkst dir: Bengt Oberg\nEtableringsår: 1965.\n\nLENKO\n\nPnr 83101\n\nÖstersund 1, Inspektörsv 16. Box\n24. Tel 063-191 83. Bankgiro\n19-7961. Postgiro 463906. Tga\nLen-kosaw\n\nVerksamhet: Sågsvärd, sågkedjor\no drivhjul för motorsågar. Sågblad\nför metall, trä o specialändamål.\nHårdmetall- o segmentsågklingor,\nhålsågar, pappersborrar\nÄgare o chef: Lennart Nilsson\nEtableringsår: 1952.\n\nPETTERSSON &amp; STEEN AB\n\nPnr 19150\n\nSollentuna, Sänkhagsv 1 B. Tel\n08-96 01 85. Bankgiro 744-1116.\nPostgiro 679780-7\n\nVerksamhet: Konsulterande\ningenjörsbyrå i värme, sanitet o ventilar\ntion\n\nAntal anställda: 9\n\nÅrsomsättning: 600 000\n\nAktiekapital: 20 000\n\nStyrelse: Bertil Pettersson (ordf),\n\nSven Erik Steen\n\nVerkst dir: B Pettersson\n\nEtableringsår: 1965.\n\nPETTERSSONS SMIDESVERK.\nSTAD EFTR, A G\n\nPnr 633 70\n\nEskilstuna, Industriv 6. Tel\n016-21110. Postgiro 160282-0\nVerksamhet: Tillverkar ventilgaller,\nUhlinstegar o trappor\nVarunamn: Uhlintrappan\nÄgare o chef: Fabr Tage Persson\nEtableringsår 1937.",
    "structured": {
        "1": {
            "company_name": "KARLSSON, AB K W",
            "pnr": "52010",
            "address": "GäUstad",
            "phone_number": "0321-702 40",
            "activity": "Tillverkar yttertrikå o badartiklar",
            "capital": 300000,
            "key_personnel": [
                {
                    "name": "Ake Johansson",
                    "position": "Firmatecknare"
                }
            ],
            "establishment_year": 1923
        },
        "2": {
            "company_name": "CARLSSONS SNICKERI. MONTERING, KJELL",
            "pnr": "710 23",
            "address": "Glanshammar, Hälglöt",
            "phone_number": "019-690 57",
            "activity": "Montage av affärsinredning, möbler o andra snickerier",
            "key_personnel": [
                {
                    "name": "Kjell Carlsson",
                    "position": "Chef"
                }
            ],
            "establishment_year": 1967
        },
        "3": {
            "company_name": "SEDAB DATABEHANDLING AB",
            "pnr": "29101",
            "address": "Kristianstad 1, Box 317, S Kaserng 9",
            "phone_number": "044-12 0981",
            "bank_details": {
                "bankgiro": "167-8499",
                "postgiro": "173554-6"
            },
            "activity": "Servicebyrå för databehandling",
            "employees": 17,
            "annual_turnover": 1500000,
            "capital": 25000,
            "key_personnel": [
                {
                    "name": "Karl Olsson",
                    "position": "Verkst dir"
                }
            ],
            "establishment_year": 1963
        },
        "4": {
            "company_name": "THORPLAST AB",
            "pnr": "136 00",
            "address": "Handen, Hantverkarv 31",
            "phone_number": "08-777 01 40",
            "bank_details": {
                "bankgiro": "478-7040",
                "postgiro": "603385-6"
            },
            "activity": "Formsprutning av termoplaster för industridetaljer mm",
            "employees": 30,
            "annual_turnover": 4500000,
            "capital": 72000,
            "key_personnel": [
                {
                    "name": "Niels V Thorsen",
                    "position": "Verkst dir"
                }
            ],
            "establishment_year": 1959
        },
        "5": {
            "company_name": "SJUBO BRUK, AB",
            "pnr": "275 00",
            "address": "Sjöbo, Box 4",
            "phone_number": "0416-108 10",
            "bank_details": {
                "bankgiro": "662-7699",
                "postgiro": "291930-6"
            },
            "activity": "Gjuteri o mekanisk verkstad",
            "employees": 100,
            "annual_turnover": 10000000,
            "capital": 50000,
            "key_personnel": [
                {
                    "name": "Dir Walter Wredenfors",
                    "position": "Styrelse"
                },
                {
                    "name": "Bengt Spånberg",
                    "position": "Verkst dir"
                }
            ],
            "establishment_year": 1945
        },
        "6": {
            "company_name": "GOT",
            "activity": "Termometrar, manometrar, hygrometrar, laboratorieutensilier",
            "employees": 13,
            "annual_turnover": 2500000,
            "capital": 20000,
            "key_personnel": [
                {
                    "name": "Dir Helge Schramm",
                    "position": "Chef"
                }
            ],
            "establishment_year": 1946
        },
        "7": {
            "company_name": "GOTEBORGS TEXTILENGROS AB",
            "pnr": "43122",
            "address": "Mölndal 1, Box 99, Flöjelbergsg 6-10",
            "phone_number": "031-27 52 00",
            "bank_details": {
                "bankgiro": "33-7261",
                "postgiro": "48640-7"
            },
            "activity": "Säljer tyger en gros",
            "annual_turnover": 1800000,
            "capital": 50000,
            "key_personnel": [
                {
                    "name": "Per Olof K-son Ahl",
                    "position": "Verkst dir"
                }
            ],
            "establishment_year": 1959
        },
        "8": {
            "company_name": "GOTEBORGS TRÄ. & FANER AB",
            "pnr": "402 71",
            "address": "Göteborg 8, Holmvägen, Holm Industriområde, Box 8844",
            "phone_number": "031-66 09 00",
            "bank_details": {
                "bankgiro": "508-7655",
                "postgiro": "40891-4"
            },
            "activity": "Utländska träslag, faner, plywood, lamellträ o möbel-smiden",
            "capital": 225000,
            "key_personnel": [
                {
                    "name": "Evert Mellkvist",
                    "position": "Verkst dir"
                }
            ],
            "establishment_year": 1893
        },
        "9": {
            "company_name": "GOTEBORGS VERKSTADS. INDUSTRI AB",
            "pnr": "417 05",
            "address": "Göteborg, Gustaf Dalënsg 13",
            "phone_number": "031-2278 10, 5158 00",
            "bank_details": {
                "bankgiro": "420-0705",
                "postgiro": "240057-0"
            },
            "activity": "Tillverkar järnkonstruktioner, ångpannor, tryckkärl o värmepannor för villor",
            "employees": 180,
            "annual_turnover": 11300000,
            "capital": 150000,
            "key_personnel": [
                {
                    "name": "Allan Ericsson",
                    "position": "Verkst dir"
                }
            ],
            "establishment_year": 1935
        },
        "10": {
            "company_name": "GOTEBORG-DALS PAPPERSBRUK, AB",
            "pnr": "402 72",
            "address": "Göteborg 8, Box 8852",
            "phone_number": "031-22 21 10",
            "bank_details": {
                "bankgiro": "506-5198",
                "postgiro": "426150-9"
            },
            "activity": "Tillverkar MG sulfit-papper, råpapper för engångskarbon, laminering, vaxning. o fruktomslag etc.",
            "employees": 155,
            "annual_turnover": 19000000,
            "capital": 2000000,
            "key_personnel": [
                {
                    "name": "Gunnar Lundh",
                    "position": "Verkst dir"
                }
            ],
            "establishment_year": 1898
        },
        "11": {
            "company_name": "GOTEBORG-FREDERIKSHAVN-LINJEN, REDERI AB",
            "pnr": "40241",
            "address": "Göteborg 12, Majnabbehamnen, Box 12065",
            "phone_number": "031-1249 00",
            "activity": "Passagerare-, bil- o godstrafik Göteborg-Frederikshavn",
            "employees": 600,
            "annual_turnover": 35000000,
            "capital": 3000000,
            "key_personnel": [
                {
                    "name": "Kapten Ulf Trapp",
                    "position": "Verkst dir"
                }
            ],
            "establishment_year": 1935
        },
        "12": {
            "company_name": "GOTEBORGS-POSTENS NYA AB",
            "pnr": "405 02",
            "address": "Göteborg, Polhemsplatsen 5",
            "phone_number": "031-17 63 00",
            "activity": "Tidningstryckeri. Utger Göteborgs-Posten",
            "annual_turnover": 77000000,
            "capital": 200000,
            "key_personnel": [
                {
                    "name": "Hilde Andersson",
                    "position": "Verkst dir"
                }
            ],
            "establishment_year": 1897
        },
        "13": {
            "company_name": "SOLIDITET AB",
            "pnr": "102 25",
            "address": "Stockholm 12, Box 12179, Huvudkontor Sankt Eriksg 38",
            "phone_number": "08-52 07 50",
            "bank_details": {
                "bankgiro": "332-1684",
                "postgiro": "1252-6"
            },
            "activity": "Meddelar soliditets-upplysningar, emottager inkasso- o övriga juridiska o kommersiella uppdrag",
            "employees": 350,
            "capital": 1000000,
            "key_personnel": [
                {
                    "name": "G Calissendorff",
                    "position": "Styrelse"
                },
                {
                    "name": "W Westergren",
                    "position": "Styrelse"
                }
            ],
            "establishment_year": 1908
        },
        "14": {
            "company_name": "geralf patentbyrä ab, w",
            "pnr": "111 56",
            "address": "Stockholm C, Kungsg 33",
            "phone_number": "08-1152 21, 2185 50",
            "bank_details": {
                "bankgiro": "23-5157",
                "postgiro": "153058"
            },
            "activity": "Patentombud",
            "employees": 9,
            "capital": 5000,
            "key_personnel": [
                {
                    "name": "W Geralf",
                    "position": "Verkst dir"
                }
            ],
            "establishment_year": 1937
        },
        "15": {
            "company_name": "LUMACO AB",
            "pnr": "40121",
            "address": "Göteborg 1, Packhusg 2-3, Box 77",
            "phone_number": "031-1394 40",
            "bank_details": {
                "bankgiro": "501-6472",
                "postgiro": "628066-3"
            },
            "activity": "Försäljning av industri-kemikalier o plastråvaror",
            "capital": 5000,
            "key_personnel": [
                {
                    "name": "Bengt Oberg",
                    "position": "Verkst dir"
                }
            ],
            "establishment_year": 1965
        },
        "16": {
            "company_name": "LENKO",
            "pnr": "83101",
            "address": "Östersund 1, Inspektörsv 16, Box 24",
            "phone_number": "063-191 83",
            "bank_details": {
                "bankgiro": "19-7961",
                "postgiro": "463906"
            },
            "activity": "Sågsvärd, sågkedjor o drivhjul för motorsågar",
            "employees": 0,
            "capital": 0,
            "key_personnel": [
                {
                    "name": "Lennart Nilsson",
                    "position": "Ägare o chef"
                }
            ],
            "establishment_year": 1952
        },
        "17": {
            "company_name": "PETTERSSON & STEEN AB",
            "pnr": "19150",
            "address": "Sollentuna, Sänkhagsv 1 B",
            "phone_number": "08-96 01 85",
            "bank_details": {
                "bankgiro": "744-1116",
                "postgiro": "679780-7"
            },
            "activity": "Konsulterande ingenjörsbyrå i värme, sanitet o ventilation",
            "employees": 9,
            "annual_turnover": 600000,
            "capital": 20000,
            "key_personnel": [
                {
                    "name": "Bertil Pettersson",
                    "position": "Styrelse"
                },
                {
                    "name": "Sven Erik Steen",
                    "position": "Styrelse"
                }
            ],
            "establishment_year": 1965
        },
        "18": {
            "company_name": "PETTERSSONS SMIDESVERK. STAD EFTR, A G",
            "pnr": "633 70",
            "address": "Eskilstuna, Industriv 6",
            "phone_number": "016-21110",
            "bank_details": {
                "postgiro": "160282-0"
            },
            "activity": "Tillverkar ventilgaller, Uhlinstegar o trappor",
            "employees": 0,
            "capital": 0,
            "key_personnel": [
                {
                    "name": "Fabr Tage Persson",
                    "position": "Ägare o chef"
                }
            ],
            "establishment_year": 1937
        }
    }
}