{
    "original": "WERNEDAL&amp; CO AB\n\nPnr 126 37\n\nHägersten, Tellusborgsv 67-71.\nTel 08-19 67 64, 19 79 86. Bankgiro\nTel 08-19 67 64, 19 79 86. Bankgiro\n746-9513. Postgiro 255146-3\nVerksamhet: Plåtarbeten såsom\nchassier, kåpor o pulpeter\nAntal anställda: 25\nAktiekapital: 40 000\nVerkst dir: Erik Wernedal\nEtableringsår: 1947.\n\nWERNERS BYGGNADSVAROR\nAB\n\nPnr 55005\n\nJönköping 5, Vasav 4. Box 5034.\n\nTel 036-119180. Bankgiro\n835-6586. Postgiro 30222-4. Tga\nByggvaror\n\nVerksamhet: Säljer\nbyggnadsmaterial, utför golvbeläggningsarbeten\nm m\n\nAktiekapital: 270 000\nVerkst dir: Lennart Werner\nEtableringsår: 1882\nOmbildat till aktiebolag 1922.\n\nWERNER &amp; CARLSTROM, AB\n\nPnr 401 25\n\nGöteborg 1, Avägen 6. Box 370.\nTel 031-80 0 9 80. Bankgiro 42-0472.\nPostgiro 41940. Tga Carlströms\nVerksamhet:\nHandstickningsgar-ner o strumpor\n\nAvdelningskontor: Stockholm C,\nStora Nyg 21 A. Tel 08-20 80 69\nAntal anställda: 50\nÅrsomsättning: 12 000 000\nVerkst dir: Birger Norinder\nEtableringsår: 1885\nOmbildat till aktiebolag 1898.\nDotterbolag till Gustaf Werner AB.\n\nWERNERS JÄRN AB\n\nPnr 400 20\n\nGöteborg 14, Box 14025.\nMöln-dalsv 63. Tel 031-8109 90.\nBankgiro 505-7708. Postgiro 12039-4\nVerksamhet Järnhandel\nAntal anställda: 18\nÅrsomsättning: 6 000 000\nAktiekapital: 40 100\nStyrelse: Dir Carl Ivar Ahlqvist\n(ordf), ing Thor Johansson, adv\nLars Odert\n\nFörsäljn-chef: Wigert Nilsson\nEtableringsår 1935.\n\nNORSK HYDRO SVERIGE AB\n\nPnr 115 27\n\nStockholm, Oxenstiernsg 31.Tel\n08-67 90 90. Tga Norskhydro.\nTelex 1436\n\nVerksamhet: Gödselmedel, kemikar\nlier, P.V.C. o magnesium\nAktiekapital: 100000\nVerkst dir: S Pronstad\nEtableringsår: 1945.\n\nCEÄSS MÖBLER AB\n\nPnr 51010\n\nHorred. Tel 0320-80148. Bankgiro\n\n43-5802. Postgiro 337103\n\nVerksamhet: Tillverkar skrivbord\n\no säng paneler\n\nAntal anställda: 30\n\nÅrsomsättning: 4 000 000\n\nAktiekapital: 50 000\n\nÄgare o chefer: Arne Claesson,\n\nSven Svensson\n\nEtableringsår: 1948.\n\nFURSCANDIA AB\n\nPnr 57301\n\nTranås 1, Kanalg 1. Box 99. Tel\n0140-170 70. Bankgiro 653-6577.\nPostgiro 463115-6\nVerksamhet: Import o export av\npälsvaror engros\nVerkst dir: Jan Ringquist.\n\nFURUDALS SNICKERIER, AB\n\nPnr 574 00\n\nVetlanda, Björköby. Tel 0383-310 66.\nBankgiro 45-2724. Postgiro 160989\nVerksamhet: Tillverkar\nköksinredningar samt ammunitionslådor\nAntal anställda: 20\nÅrsomsättning: 500 000\nAktiekapital: 30 000\nVerkst dir: Thure Antonsson\nEtableringsår: 1946.\n\nFURUDALS\nTRÄOLJEFABRIKER\n\nPnr 380 24\n\nPåryd. Tel 0480-910 16. Tga\nTrä-oljefabriken\n\nVerksamhet: Tillverkar beck för\nskoindustrin, skomakerier,\nvävskedsfabriker m fi, skeppsbeck,\nträbeck\n\nFirmatecknare: H Nilsson\nEtableringsår: 1885.\n\nSUNLIGHT, AB\n\nPnr 103 40\n\nStockholm 40,Sveav 9-11. Fack.\nTel 08-23 83 80. Postgiro 9113. Tga\nSunlight. Telex 1332 EXPEDO S\nVerksamhet: Tvättmedel, tvål\nAktiekapital: 500 000\nVerkst dir: Rolf Lindman.\nNamnändring 1965 från Nyköpings\nKem Produkter AB.\nKommissio-närsbolag för AB Centrava,\nStockholm.\n\nSUNNAN AB, KONSERV.\nFABRIKEN\n\nPnr 402 74\n\nGöteborg 8, Ringög. Box 8958. Tel\n031-51 37 40. Bankgiro 551-3734.\nPostgiro 393359-5. Tga Sun.\nTelex 20655\n\nVerksamhet: Räkkonserver o\ndjupfrysta skaldjur\nVarunamn: Sunnan\nAntal anstäUda: 50\nÅrsomsättning: 20 000 000\nAktiekapital: 200 000\nVerkst dir: Ralph G Blomström\nEtableringsår: 1951.\n\nmc b sport ab\n\nPnr 74061\n\nTobo. Tel 0295-342 00\nVerksamhet: Grossistförsäljning\nav alla slags sportartiklar för\nsommar- o vintersport\nAntal anställda: 25\nAktiekapital: 100 000\nEtableringsår: 1969.\n\nSPORT &amp; MASKIN AB\n\nPnr 821 01\n\nBoUnäs 1, Box 68. Brog 7. Tel\n0278-133 00. Bankgiro 192-8050.\nPostgiro 73826-0\n\nVerksamhet: Säljer i parti o minut\nsommar- o vintersportartiklar\nAntal anställda: 13\nÅrsomsättning: 2150 000\nAktiekapital: 70 000\nVerkst dir: Knut Helmer Norell\nEtableringsår: 1938.\n\nSVA\n\nSURAHAMMARS BRUKS AB\n\nPnr 735 00\n\nSurahammar. Tel 0220-304 00.\nPostgiro 13271. Telex 4742. Tga Bruket\nVerksamhet: Järnverket. Tillverkar\nkallvalsad dynamoplåt o orienterad\ntransformatorplåt, järnvägshjul o\naxlar, smide, pulvermetallurgiska\nprodukter, permanentmagneter,\njärngjutgods\n\nSpännarhytteförvaltningen:\n\n778 01 Norberg 1, Pack. Tel\n0223-209 70. Tillverkar tackjärn,\nkokiller, järngjutgods\nSkogs- o sågverksförvaltningen:\n73050 Skultuna, Svanå. Tel\n021-730 15. Skogsbruk, såg o lådfabrik\nLantbruksförvaltningen:\n735 00 Surahammar, Lisjö. Tel\n0220-320 22. Lantbruk\nFörsäljningskontor: Surahammars\nBruks AB. 2830 Virum, Danmark\nAntal anställda: 2100\nÅrsomsättning: 225 000 000\nAktiekapital: 50 000 000\nStyrelse: Tekn dr Marcus\nWallenberg (ordf), generalkonsul Ragnar\nSöderberg, dir Curt Nicolin, tekn\ndr Ake Vrethem, disp Göthe\nFern-heden, dir Gösta Lewenhaupt\nVerkst dir: Göthe Fernheden\nV verkst dir: Sven Fornander\nFörsäljn-dir: Sigfrid Sandell\nProd-dir: Björn Törneman\nEkonomichef: Gösta Neuendorff\nInköpschef: Olof Frantzich\nEtableringsån 1872\nBruksdrift sedan 1500-talet.\nDotterbolag: Kohlsva Jernverks\nAB, Kolsva.\n\nSURTER CHARKUTERI FABRIK\nHELGE ARVIDSSON, AB\n\nPnr 440 44\n\nSurte, Box 20. Tel 031-98 20 70.\nBankgiro 892-0332. Postgiro\n523928-0\n\nVerksamhet: Charkuterifabrik.\nStorkök för färdig mat, färsk o\ndjupfryst\n\nAntal anställda: 75\nÅrsomsättning: 18 000 000\nAktiekapital: 200 000\nStyrelse: Dir Helge Arvidsson\n(ordf), fru Astrid Arvidsson, fru\nUlla Andersson, disp Bo Arvidsson\nVerkst din Helge Arvidsson\nDisp: Bo Arvidsson\nEtableringsår: 1958.\n\nLEJONET. APOTEKET\n\nPnr 21134\n\nMalmö, Stortorget 8. Tel\n040-712 35. 707 25\n\nVerksamhet: Utför\nvattenundersökningar o kem analyser.\n\nLEJTIN PÄLSVARU AB, T\n\nPnr 100 56\n\nStockholms Frihamn, Magasin 3.\nTel 08-6128 42, 6188 42. Bankgiro\n16-0292. Postgiro 256648. Tga\nLejtinfur\n\nVerksamhet: Pälsar, beredda o\noberedda pälsskinn\nAktiekapital: 100 000\nVerkst dir: E Lejtin\nEtableringsår: 1946.\n\nINDUSTRILEVERANSER, AB\n\nPnr 60103\n\nNoirköping 1, Box 153. Olai Kyrkog\n50. Tel 011-18 61 60. Bankgiro\n609-8230. Postgiro 385324-9. Tga Råab.\nTelex 64309\n\nVerksamhet: Grossiströrelse med\navfallspapper\n\nFilialer: 80106 Gävle, O\nHamnpiren. Box 513. Tel 026-18 9910\n41707 Göteborg, Stenkolsg 7. Tel\n031-5153 50. Telex 25 70\n58102 Linköping. Box 300. Tel\n013-10 14 30\n\n605 90 Norrköping, Fiskeby. Tel\n011-111450\n\n17104 Solna 4. Box 462. Tel\n08-83 0240. Telex 10153\n753 23 Uppsala, Ostunag 4. Tel\n018-14 7178\n\n703 61 Örebro, Slottsg 10. Tel\n019-18 6510\n\nAntal anställda: 120\nÅrsomsättning: 26 082 000\nAktiekapital: 1000 000\nStyrelse: Dir Esbjörn Ulfsäter\n(ordf), disp Rutger Martin-Löf,\ndir Mats de Verdier, disp Gösta\nHolm\n\nVerkst dir: Anders Beije\nEtableringsår 1952.",
    "structured": {
        "1": {
            "company_name": "WERNEDAL& CO AB",
            "pnr": "126 37",
            "address": "Hägersten, Tellusborgsv 67-71.",
            "phone_number": "08-19 67 64, 19 79 86",
            "bank_details": {
                "bankgiro": "746-9513",
                "postgiro": "255146-3"
            },
            "activity": "Plåtarbeten såsom chassier, kåpor o pulpeter",
            "employees": 25,
            "capital": 40000,
            "key_personnel": [
                {
                    "name": "Erik Wernedal",
                    "position": "Verkst dir"
                }
            ],
            "establishment_year": 1947
        },
        "2": {
            "company_name": "WERNERS BYGGNADSVAROR AB",
            "pnr": "55005",
            "address": "Jönköping 5, Vasav 4. Box 5034.",
            "phone_number": "036-119180",
            "bank_details": {
                "bankgiro": "835-6586",
                "postgiro": "30222-4"
            },
            "activity": "Säljer byggnadsmaterial, utför golvbeläggningsarbeten m m",
            "capital": 270000,
            "key_personnel": [
                {
                    "name": "Lennart Werner",
                    "position": "Verkst dir"
                }
            ],
            "establishment_year": 1882
        },
        "3": {
            "company_name": "WERNER & CARLSTROM, AB",
            "pnr": "401 25",
            "address": "Göteborg 1, Avägen 6. Box 370.",
            "phone_number": "031-80 0 9 80",
            "bank_details": {
                "bankgiro": "42-0472",
                "postgiro": "41940"
            },
            "activity": "Handstickningsgarner o strumpor",
            "employees": 50,
            "annual_turnover": 12000000,
            "key_personnel": [
                {
                    "name": "Birger Norinder",
                    "position": "Verkst dir"
                }
            ],
            "establishment_year": 1885
        },
        "4": {
            "company_name": "WERNERS JÄRN AB",
            "pnr": "400 20",
            "address": "Göteborg 14, Box 14025. Mölndalsv 63.",
            "phone_number": "031-8109 90",
            "bank_details": {
                "bankgiro": "505-7708",
                "postgiro": "12039-4"
            },
            "activity": "Järnhandel",
            "employees": 18,
            "annual_turnover": 6000000,
            "capital": 40100,
            "key_personnel": [
                {
                    "name": "Carl Ivar Ahlqvist",
                    "position": "Styrelse: Dir"
                },
                {
                    "name": "Thor Johansson",
                    "position": "ing"
                },
                {
                    "name": "Lars Odert",
                    "position": "adv"
                },
                {
                    "name": "Wigert Nilsson",
                    "position": "Försäljn-chef"
                }
            ],
            "establishment_year": 1935
        },
        "5": {
            "company_name": "NORSK HYDRO SVERIGE AB",
            "pnr": "115 27",
            "address": "Stockholm, Oxenstiernsg 31.",
            "phone_number": "08-67 90 90",
            "activity": "Gödselmedel, kemikarlier, P.V.C. o magnesium",
            "capital": 100000,
            "key_personnel": [
                {
                    "name": "S Pronstad",
                    "position": "Verkst dir"
                }
            ],
            "establishment_year": 1945
        },
        "6": {
            "company_name": "CEÄSS MÖBLER AB",
            "pnr": "51010",
            "address": "Horred",
            "phone_number": "0320-80148",
            "bank_details": {
                "bankgiro": "43-5802"
            },
            "activity": "Tillverkar skrivbord o säng paneler",
            "employees": 30,
            "annual_turnover": 4000000,
            "capital": 50000,
            "key_personnel": [
                {
                    "name": "Arne Claesson",
                    "position": "Ägare o chefer"
                },
                {
                    "name": "Sven Svensson",
                    "position": "Ägare o chefer"
                }
            ],
            "establishment_year": 1948
        },
        "7": {
            "company_name": "FURSCANDIA AB",
            "pnr": "57301",
            "address": "Tranås 1, Kanalg 1. Box 99.",
            "phone_number": "0140-170 70",
            "bank_details": {
                "bankgiro": "653-6577",
                "postgiro": "463115-6"
            },
            "activity": "Import o export av pälsvaror engros",
            "key_personnel": [
                {
                    "name": "Jan Ringquist",
                    "position": "Verkst dir"
                }
            ]
        },
        "8": {
            "company_name": "FURUDALS SNICKERIER, AB",
            "pnr": "574 00",
            "address": "Vetlanda, Björköby",
            "phone_number": "0383-310 66",
            "bank_details": {
                "bankgiro": "45-2724",
                "postgiro": "160989"
            },
            "activity": "Tillverkar köksinredningar samt ammunitionslådor",
            "employees": 20,
            "annual_turnover": 500000,
            "capital": 30000,
            "key_personnel": [
                {
                    "name": "Thure Antonsson",
                    "position": "Verkst dir"
                }
            ],
            "establishment_year": 1946
        },
        "9": {
            "company_name": "FURUDALS TRÄOLJEFABRIKER",
            "pnr": "380 24",
            "address": "Påryd",
            "phone_number": "0480-910 16",
            "activity": "Tillverkar beck för skoindustrin, skomakerier, vävskedsfabriker m fi, skeppsbeck, träbeck",
            "key_personnel": [
                {
                    "name": "H Nilsson",
                    "position": "Firmatecknare"
                }
            ],
            "establishment_year": 1885
        },
        "10": {
            "company_name": "SUNLIGHT, AB",
            "pnr": "103 40",
            "address": "Stockholm 40,Sveav 9-11",
            "phone_number": "08-23 83 80",
            "bank_details": {
                "postgiro": "9113"
            },
            "activity": "Tvättmedel, tvål",
            "capital": 500000,
            "key_personnel": [
                {
                    "name": "Rolf Lindman",
                    "position": "Verkst dir"
                }
            ],
            "establishment_year": 1965
        },
        "11": {
            "company_name": "SUNNAN AB, KONSERV. FABRIKEN",
            "pnr": "402 74",
            "address": "Göteborg 8, Ringög. Box 8958",
            "phone_number": "031-51 37 40",
            "bank_details": {
                "bankgiro": "551-3734",
                "postgiro": "393359-5"
            },
            "activity": "Räkkonserver o djupfrysta skaldjur",
            "employees": 50,
            "annual_turnover": 20000000,
            "capital": 200000,
            "key_personnel": [
                {
                    "name": "Ralph G Blomström",
                    "position": "Verkst dir"
                }
            ],
            "establishment_year": 1951
        },
        "12": {
            "company_name": "mc b sport ab",
            "pnr": "74061",
            "address": "Tobo",
            "phone_number": "0295-342 00",
            "activity": "Grossistförsäljning av alla slags sportartiklar för sommar- o vintersport",
            "employees": 25,
            "capital": 100000,
            "establishment_year": 1969
        },
        "13": {
            "company_name": "SPORT & MASKIN AB",
            "pnr": "821 01",
            "address": "BoUnäs 1, Box 68. Brog 7",
            "phone_number": "0278-133 00",
            "bank_details": {
                "bankgiro": "192-8050",
                "postgiro": "73826-0"
            },
            "activity": "Säljer i parti o minut sommar- o vintersportartiklar",
            "employees": 13,
            "annual_turnover": 2150000,
            "capital": 70000,
            "key_personnel": [
                {
                    "name": "Knut Helmer Norell",
                    "position": "Verkst dir"
                }
            ],
            "establishment_year": 1938
        },
        "14": {
            "company_name": "SVA SURAHAMMARS BRUKS AB",
            "pnr": "735 00",
            "address": "Surahammar",
            "phone_number": "0220-304 00",
            "postgiro": "13271",
            "activity": "Järnverket. Tillverkar kallvalsad dynamoplåt o orienterad transformatorplåt, järnvägshjul o axlar, smide, pulvermetallurgiska produkter, permanentmagneter, järngjutgods",
            "employees": 2100,
            "annual_turnover": 225000000,
            "capital": 50000000,
            "key_personnel": [
                {
                    "name": "Göthe Fernheden",
                    "position": "V verkst dir"
                },
                {
                    "name": "Sven Fornander",
                    "position": "Försälj-dir"
                },
                {
                    "name": "Sigfrid Sandell",
                    "position": "Prod-dir"
                }
            ],
            "establishment_year": "1500-talet"
        },
        "15": {
            "company_name": "SURTER CHARKUTERI FABRIK HELGE ARVIDSSON, AB",
            "pnr": "440 44",
            "address": "Surte, Box 20",
            "phone_number": "031-98 20 70",
            "bank_details": {
                "bankgiro": "892-0332",
                "postgiro": "523928-0"
            },
            "activity": "Charkuterifabrik. Storkök för färdig mat, färsk o djupfryst",
            "employees": 75,
            "annual_turnover": 18000000,
            "capital": 200000,
            "key_personnel": [
                {
                    "name": "Helge Arvidsson",
                    "position": "Verkst dir"
                }
            ],
            "establishment_year": 1958
        },
        "16": {
            "company_name": "LEJONET. APOTEKET",
            "pnr": "21134",
            "address": "Malmö, Stortorget 8",
            "phone_number": "040-712 35, 707 25",
            "activity": "Utför vattenundersökningar o kem analyser"
        },
        "17": {
            "company_name": "LEJTIN PÄLSVARU AB, T",
            "pnr": "100 56",
            "address": "Stockholms Frihamn, Magasin 3",
            "phone_number": "08-6128 42, 6188 42",
            "bank_details": {
                "bankgiro": "16-0292",
                "postgiro": "256648"
            },
            "activity": "Pälsar, beredda o oberedda pälsskinn",
            "capital": 100000,
            "key_personnel": [
                {
                    "name": "E Lejtin",
                    "position": "Verkst dir"
                }
            ],
            "establishment_year": 1946
        },
        "18": {
            "company_name": "INDUSTRILEVERANSER, AB",
            "pnr": "60103",
            "address": "Noirköping 1, Box 153, Olai Kyrkog 50",
            "phone_number": "011-18 61 60",
            "bank_details": {
                "bankgiro": "609-8230",
                "postgiro": "385324-9"
            },
            "activity": "Grossiströrelse med avfallspapper",
            "employees": 120,
            "annual_turnover": 26082000,
            "capital": 1000000,
            "key_personnel": [
                {
                    "name": "Anders Beije",
                    "position": "Verkst dir"
                }
            ],
            "establishment_year": 1952
        }
    }
}