{
    "original": "SATURNUS, AB FABRIKEN\n\nPnr 214 44\n\nMalmö, Lantmannag 20. Tel\n040-804 80-84. Bankgiro 874-3841.\nPostgiro 38390-1. Tga Saturnus\nVerksamhet: Tillverkar essenser o\nextrakter för läskedrycks-,\nkonfek-tyr- o bageriindustrin,\nlikörextrak-ter, cocktail mix, livsmedelsfärger\nsamt diverse andra produkter för\nlivsmedelsindustrin\nVarunamn: Aroma Saftessens, Cuba\nCola, Lucky Party, Saturnus Glögg,\nSaturnus Likörextrakt, Trocadero\nAktiekapital: 180 900\nStyrelse: Fru Monica\nLiepe-Hå-kansson (ordf), generalkonsul\nNils-Håkan Håkansson, dir Henrik\nLiepe\n\nVeikst dir: Generalkonsul\nNils-Håkan Håkansson\nV veikst dir: Henrik Liepe\nKamrer: Anders Hene\nCiviling: Lennart Schiött\nEtableringsår: 1893\nOmbildat till aktiebolag 1905.\n\nSAWA FABRIKS AB\n\nPnr 360 50\n\nLessebo. Tel 0478-102 50\nVerksamhet: Tillverkar bageri\nutensilier o hushållsapparater,\naluminiumartiklar samt utför eloxering\nAntal anställda: 50\nÅrsomsättning: 4 000 000\nAktiekapital: 400 000\nVerkst din Bror Abrahamsson\nEtableringsår: 1951.\n\nPERSTORP AB\n\nPnr 284 00\n\nPerstoip. Tel 0435-386 00.\nPostgiro 37000. Telex 72470. Tga\nPers-torpab\n\nVerksamhet: KEMISKA\nPRODUKTER: Kreosot (farmaceutisk),\ngrillkol, matättika, formalin,\npolyalko-holer etc.\n\nPLASTER: Läcker o hartser på\nfenol-, karbamid- o melaminbas,\naminopressmassor, vinyl- o\nakryl-hartser, formgods av termo- o\nhärdplast för industri o hushåll samt\nbyggprodukter, tekniskt o\ndekorativt laminat (Perstorp-Plattan),\ntermoplastfilm (polyamid) o\nsträng-sprutade plastnät\n\nFUialer. Göteborg S, Mölndalsv 38.\nTel 031-20 04 20\n\nStockholm VA, Sveav 163. Tel\n08-24 33 95\n\nAntal anstäUda: 1900\nÅrsomsättning: 223 000 000\nAktiekapital: 30000 000\nVerkst dir: Gunnar Wessman\nEtableringsår: 1880\nOmbildat till aktiebolag 1925.\nNamnändring till Perstorp AB 1966.\n\nPERSONER AB\n\nPnr 27100\n\nYstad. Tel 0411-138 00. Bankgiro\n67-0299. Postgiro 75085. Telex\n3146. Tga Persöner\nVerksamhet: Grosshandels- o\nfabriksrörelse. Förädling av\navfallsråvaror såsom textila, järn- o\nmetaller, gummi, plast, papper, etc.\nFartygs upp hugg ning o\nindustride-montering. Vidare försäljning av\nbalpressar, skrotsaxar,\nsopförbränningsugnar, spårväxlar, räls,\nkemtvättmaskiner, lyft- o\ntransportredskap. Ull, bomull, garner, maskiner\no tillbehör för textilindustrin samt\nhalvfabrikat\nVarunamn: Persöner\nAntal anställda: 215\nAktiekapital: 5 500 000\nVerkst din Konsul Ake Raihle\nEtableringsår: 1895\nOmbildat till aktiebolag 1928.\n\nPERSONERS MEKANISKA\nVERKSTAD AB\n\nPnr 27100\n\nYstad, Fridhemsg. Tel0411-138 00.\nTelex 3146 PERSOEN S\nVerksamhet: Tillverkar\njärnvägsmateriel, transportredskap,\nhydrauliska pressar o saxar,\nsopförbränningsugnar, hetluftanläggningar,\nkemtvättmaskiner\nAntal anstäUda: 85\nAktiekapital: 250000\nVerkst din Konsul Ake Raihle\nDisp: Ivan Jacobsson\nEtableringsår: 1955\nFöretaget ingår i\nPersönerkoncer-nen.\n\nPERUZZAROS KONSTSTENS.\nGJUTERI AB\n\nPnr 950 10\n\nGammelstad, Industriv 18. Box 12.\nTel 0920-54214, 54218. Bankgiro\n60-8847. Postgiro 61299\nVeiksamhet: Tillverkar\nkonststens-produkter\n\nAntal anstäUda: 35\nÅrsomsättning: 2 000 000\nAktiekapital: 30 000\nVerkst dir: Ing Giovanni\nPeruz-zaro\n\nEtableringsår: 1947.\n\nOSTGOTA.BYGGEN, AB\n\nPnr 580 04\n\nLinköping 4, LinnSg 7. Box 4039.\nTel 013-11 16 00. Postgiro 380246-9\nVerksamhet: Bygger bostadshus o\nindustribyggnader i egen regi o på\nentreprenad\n\nAvdelningskontor: Stockholm VA,\nOdeng 60. Tel 08-3182 31\nAntal anställda: 400\nÅrsomsättning: 50 000 000\nAktiekapital: 350 000\nVerkst dir: Arnold Larsson\nEtableringsår: 1935.\n\n(ÖSTGÖTA-LANTMÄNNENS\nMASKIN AB)\n\nMASKINBOLAGET TRAVA\n\nPnr 600 08\n\nNorrköping 8, Box 8016. Järng 6.\nTel 011-1117 00. Bankgiro\n349-1982. Postgiro 297450-9. Tga\nLantmaskin\n\nVerksamhet: Försäljning o service\nav traktorer o lantbruksmaskiner\nAntal anställda: 195\nÅrsomsättning: 38 000 000\nAktiekapital: 3 000 000\nVerkst dir: Sven Bolldën\nEtableringsår: 1945.\n\n|RÖ, AB\n\nPnr 523 00\n\nUlricehamn, Vistaholm. Tel\n0321-12120. Bankgiro 844-2527.\nPostgiro 202755-5. Tga Iro.\nTelex 36022 IRO S\nVerksamhet: Tillverkar tillbehör\ntill textilmaskiner\nAntal anstäUda: 150\nÅrsomsättning: 23 000 000\nAktiekapital: 600 000\nVerkst dir: Josef Rosén\nEtableringsår: 1958.\n\nY-MAN INREDNINGAR AB\n\nPnr 294 00\n\nSölvesborg, Tredenborgsv 16. Box\n43. Tel 045 6-125 00. Bankgiro\n67-0128. Postgiro 445650. Telex 3146.\nTga Ymanab\n\nVerksamhet: Tillverkning o\nförsäljning av inredningar o möbler för\nvaruhus, butiker o kontor\n\nXY\n\nFilialer: Stockholm,\nSunnerdahls-plan 3, pa 161 38 Bromma. Tel\n08-26 2910\n\n41137 Göteborg, Kristinelundsg 16.\nTel 031-20 0210\n217 71 Malmö, Köpenhamnsv 46.\nTel 040-769 20\n\n702 22 Örebro, Drottningg 40. Tel\n019-1194 05\n\n582 22 Linköping, Agatan 10. Tel\n013-123505\n\n802 26 Gävle, Rågångsv 11 A. Tel\n026-1814 53\n\n55241 Jönköping, O Storg 101. Tel\n\n036-16 44 28\n\nVarunamn: Y-MAN\n\nAntal anställda: 100\n\nAktiekapital: 500000\n\nVerkst dir: Konsul Ake Raihle\n\n(Ystad)\n\nDisp: Olle Linder\nEtableringsår: 1958\nFöretaget ingår 1\nPersönerkoncer-nen.\n\nYNGEREDSFORS KRAFT AB\n\nPir 43121\n\nMölndal 1, Box 32. Privatv 16. Tel\n031-27 2120. Bankgiro 160-4701.\nPostgiro 31000-3. Tga\nKraftbolaget, Göteborg\nVerksamhet: Distribuerar elkraft\nAntal anställda: 360\nÅrsomsättning: 73 000 000\nAktiekapital: 30 000 000\nVerkst dir: Disp Lars-Erik Swahn\nEtableringsår: 1899.\n\nYOUNG &amp; RUBlCAM/\nTESSAB AB\n\nPnr 104 35\n\nStockholm 23, Sveav 159. Fack.\nTel 08-34 07 00. Bankgiro 483-4776.\nPostgiro 152471-9. Tga Tessab.\nTelex 10342\n\nVerksamhet: Auktoriserad o\nförmedlings nominerad annonsbyrå\n.Antal anställda: 100\nÅrsomsättning: 43 000 000\nAktiekapital: 1000000\nEtableringsår: 1934.\n\nBERGENDAHL OCH\nHÖCKERT, AB\n\nPnr 104 25\n\nStockholm 30, Fack. Nordenflychtsv\n66. Tel 08-13 00 80\nVerksamhet: Byggnads-, väg- o\nanläggningsentreprenörer\nProduktionsavdelningar:\nStockholm, Göteborg, Helsingborg,\nKarlstad, Luleå\nAntal anställda: 1 224\nÅrsomsättning: 126100000\nStyrelse: Civiling B Blomgren,\nciviling Sven Ekberg, dir jur kand\nJ-O Bergenfeldt\nVerkst dir: Sven Ekberg\nEtableringsår: 1932\nOmbildat tül aktiebolag 1943.\n\nBERGENDORFFS EFTR, P\n\nPnr 103 62\n\nStockholm 3, Kungsg 34. Box 3125.\nTel 08-1108 15,1108 16.Bankgiro\n731-6342. Postgiro 151820-8. Tga\nPyrit\n\nVerksamhet: Export o import av\ncellulosamjöl, malmer o mineral\nInnehavare: Dir Erik Sunesson.\n\nBERGENSTROMS\nVERKSTÄDER AB\n\nPnr 85103\n\nSundsvaU 1, Heffners\nIndustriområde. Box 185. Tel 060-15 02 40.\nBankgiro 774-4469. Postgiro\n286993-1\n\nVerksamhet: Tillverkar\nlagringscisterner, tryckkärl,\njärnkonstruktioner, transportanordningar m m.\nUtför mek arbeten i arborrverk,\nlång-fräsmaskiner, kugghjulsautomater\nm m\n\nFilial: Sölvesborg\nAntal anstäUda: 150\nÅrsomsättning: 12 000 000\nVerkst dir: Harry Eriksson\nEtableringsår: 1946.\n\nKIENZLE FÄRDSKRIVARE, AB\n\nPnr 14105\n\nHuddinge 5, Box5057. Jakobslundsv\n25. Tel 08-97 0 2 60. Bankgiro\n572-2343. Postgiro 506926-5.\nTelex 10858\n\nVerksamhet: Försäljning av\nfärd-o varvtalsskrivare,\nlastningsskrivare för gaffeltruckar samt\ntemperaturskrivare o vägmätare\nAktiekapital: 150 000\nDir: Albert Maier.\n\nKIEPE ELEKTRISKA AB\n\nPnr 21145\n\nMalmö, Davidshallsg 18. Tel 040-\n\n125924, 12 59 34: Bankgiro\n87-5438. Postgiro 632558-3. Tga\nKiepeab. Telex 32234\nVerksamhet: Tillverkar o säljer\nkranelektrisk utrustning,\nindustristyrningar, elektrisk utrustning\nför spårvägar, tractionsutrustning,\nutrustning för el-lokomotiv o\ntunnelbanevagnar samt\nelektronikutrustning för industrin\nAktiekapital: 500 000\nVerkst dir: Svend Ilsøe\nEtableringsår: 1964.\n\nGILLE AB, B A\n\nPnr 103 61\n\nStockholm 3, Kungsg 44. Box 3087.\nTel 08-10 5933, 10 59 26.\nBankgiro 447-0712. Postgiro 2470-3.\nTga Gillefirm\n\nVerksamhet: Grossist o agenturer\ni kork- o möbelbranschen\nVarunamn: Helex\nÅrsomsättning: 1500 000\nAktiekapital: 15 000\nVerkst dir: Bertil A Gille\nEtableringsår: 1907.\n\nBERGSTRÖM EFTR, J A\n\nPnr 890 41\n\nSkorped, Box 31. Tel 0661-301 24.\n\nTga Bergström\n\nVerksamhet: Säljer ur, urdelar o\nurmakeriverktyg i parti\nÄgare o chef: Josef Gyll\nEtableringsår: 1919.\n\ndla\n\nO\n\nüba ürestads\nbostadsproduktion ab\n\nPnr 217 64\n\nMalmö, Backåkersv 3 A. Tel\n040-747 70. Bankgiro 455-3129.\nPostgiro 630794-6\n\nVerksamhet: Byggnadsentreprenad\nAntal anställda: 130\nÅrsomsättning: 15 000 000\nAktiekapital: 500 000\nVerkst dir: Ove Åkesson\nEtableringsår: 1963.\n\noberg &amp; co byggnads ab\n\nse Platzer Bygg AB.\n\noberg &amp; horndahl ab\n\nPnr 292 00\n\nKarlshamn, Drottningg 31. Box 79.\nTel 0454-103 11, 108 90. Bankgiro\n34-3436. Telex 4519. Tga Odahl\nVerksamhet: Skeppsmäkleri o\nspedition\n\nAktiekapital: 20 000\n\nVerkst dir: Skeppsmäkl Knut E Pyk\n\nEtableringsår: 1911.\n\noberg &amp; lindén,\nkarosseribolaget\n\nPnr 602 28\n\nNorrköping, Risängsg 15. Tel\n011-1255 45. Bankgiro 82-5813.\nPost-1255 45. Bankgiro 825-8139.\nPostgiro 269070-9\n\nVerksamhet: Tillverkar o reparerar\nalla slags karosserier.\nBilplåtslageri\n\nAntal anställda: 4\n\nÅrsomsättning: 200 000\n\nÄgare o chefen Sture Oberg, Henry\n\nLindén\n\nEtableringsår: 1963.\n\noberg &amp; co ab, c o\n\nPnr 631 02\n\nEskilstuna 1, Västermarksg 38. Box\n1. Tel 016-13 74 60. Bankgiro 99-\n\n1103. Postgiro 10079. Telex 40967.\nTga Obergs\n\nVerksamhet: Tillverkar filar o\nraspar, roterande filar av hårdmetall,\nsnabbstål o verktygsstål samt\nhögfrekvensdrivna\nhandslipmaski-ner, motorer o slipspindlar samt\nomformare\n\nAntal anställda: 500\nÅrsomsättning: 26 000 000\nAktiekapital: 5 000000\n\nStyrelse: Dir Rudolf Domellöf (ordf),\ndir Per Aurell, bruksdisp Sten\nSjöholm, dir Sven Arvid Nilsson\nVerkst dir: Sven Arvid Nilsson.\n\noberg-agent,\nimport-export\n\nPnr 31100\n\nFalkenberg, Box 16. Tel\n0346-126 92. 126 95. Bankgiro 42-5755.\nTga Oebergagent\nVerksamhet: Säljer reseffekter o\nsportartiklar\nÅrsomsättning: 1 000 000\nAktiekapital: 5 000\nVerkst dir: Daniel M Oberg\nEtableringsår: 1954.\n\nodeshogs\nsnickerifabrik, ab\n\nPnr 599 00\n\nOdeshög, Verkstadsg. Box 2. Tel\n0144-100 19. Bankgiro 133-7047.\nPostgiro 70528-5\nVerksamhet: Tillverkar\nbyggnadssnickerier o kyrkinredningar. Säljer\nträvaror, byggnadsmaterial\nAntal anställda: 18\nAktiekapital: 50 000\nVerkst dir: Gösta Arwidson\nEtableringsår: 1902.",
    "structured": {
        "0": {
            "company_name": "SATURNUS, AB FABRIKEN",
            "pnr": "214 44",
            "address": "Malmö, Lantmannag 20",
            "phone_number": "040-804 80-84",
            "bank_details": {
                "bankgiro": "874-3841",
                "postgiro": "38390-1"
            },
            "activity": "Tillverkar essenser o extrakter för läskedrycks-, konfektyr- o bageriindustrin, likörextrakter, cocktail mix, livsmedelsfärger samt diverse andra produkter för livsmedelsindustrin",
            "capital": 180900,
            "key_personnel": [
                {
                    "name": "Fru Monica Liepe-Hå-kansson",
                    "position": "ordf"
                },
                {
                    "name": "Nils-Håkan Håkansson",
                    "position": "generalkonsul"
                },
                {
                    "name": "Henrik Liepe",
                    "position": "dir"
                }
            ],
            "establishment_year": 1893
        },
        "1": {
            "company_name": "Sawa Fabriks AB",
            "pnr": "360 50",
            "address": "Lessebo",
            "phone_number": "0478-102 50",
            "activity": "Tillverkar bageriutensilier o hushållsapparater, aluminiumartiklar samt utför eloxering",
            "employees": 50,
            "annual_turnover": 4000000,
            "capital": 400000,
            "establishment_year": 1951
        },
        "2": {
            "company_name": "Perstorp AB",
            "pnr": "284 00",
            "address": "Perstoip",
            "phone_number": "0435-386 00",
            "postgiro": "37000",
            "bank_details": {
                "telex": "72470"
            },
            "activity": "KEMISKA PRODUKTER: Kreosot (farmaceutisk), grillkol, matättika, formalin, polyalkoholer etc. PLASTER: Läcker o hartser på fenol-, karbamid- o melaminbas, aminopressmassor, vinyl- o akrylhartser, formgods av termo- o härdplast för industri o hushåll samt byggprodukter, tekniskt o dekorativt laminat (Perstorp-Plattan), termoplastfilm (polyamid) o strängsprutade plastnät",
            "employees": 1900,
            "annual_turnover": 223000000,
            "capital": 30000000,
            "key_personnel": [
                {
                    "name": "Gunnar Wessman",
                    "position": "verkst dir"
                }
            ],
            "establishment_year": 1880
        },
        "3": {
            "company_name": "Personer AB",
            "pnr": "27100",
            "address": "Ystad",
            "phone_number": "0411-138 00",
            "bank_details": {
                "bankgiro": "67-0299",
                "postgiro": "75085",
                "telex": "3146"
            },
            "activity": "Grosshandels- o fabriksrörelse. Förädling av avfallsråvaror såsom textila, järn- o metaller, gummi, plast, papper, etc. Fartygs upphuggning o industriedemontering. Vidare försäljning av balpressar, skrotsaxar, sopförbränningsugnar, spårväxlar, räls, kemtvättmaskiner, lyft- o transportredskap. Ull, bomull, garner, maskiner o tillbehör för textilindustrin samt halvfabrikat",
            "employees": 215,
            "capital": 5500000,
            "key_personnel": [
                {
                    "name": "Konsul Ake Raihle",
                    "position": "verkst dir"
                }
            ],
            "establishment_year": 1895
        },
        "4": {
            "company_name": "Personers Mekaniska Verkstad AB",
            "pnr": "27100",
            "address": "Ystad, Fridhemsg",
            "phone_number": "0411-138 00",
            "telex": "3146 PERSOEN S",
            "activity": "Tillverkar järnvägsmateriel, transportredskap, hydrauliska pressar o saxar, sopförbränningsugnar, hetluftanläggningar, kemtvättmaskiner",
            "employees": 85,
            "capital": 250000,
            "key_personnel": [
                {
                    "name": "Konsul Ake Raihle",
                    "position": "verkst dir"
                },
                {
                    "name": "Ivan Jacobsson",
                    "position": "disp"
                }
            ],
            "establishment_year": 1955
        },
        "...": "..."
    }
}