{
    "original": "PALMER, AB GÖSTA\n\nPnr 352 33\n\nVäxjö, Kungsg 8. Tel 0470-126 50,\n110 89\n\nVerksamhet: Säljer trikåvaror,\narbetskläder, skjortor,\nträningsoveraller, gardiner, kortvaror, vitvaror i\nparti\n\nAktiekapital: 22700\nVerkst dir: Nils Erie Palmér\nEtableringsår: 1933.\n\nSVE\n\n10 8125. Bankgiro 331-0141.\nPostgiro 5552&amp;-4\n\nVerksamhet: Bild- o\nfilmvisningsservice\n\nAntal anställda: 7\nÅrsomsättning: 1000 000\nAktiekapital: 75 000\nVerkst dir: Harry Jonasson\nEtableringsår: 1937.\n\nSVENSK LAGERSTANDARD,\nAB\n\nPnr 116 57\n\nStockholm, Hallandsg 38. Tel\n08-44 05 05. Bankgiro 573-3076.\nPostgiro 258390-4\n\nVerksamhet: Lagerinredningar i\nstål. Specialitet: Stemo plastbox\ntör smådelar\nVarunamn: Stemo\nAntal anställda: 5\nÅrsomsättning: 1200 000\nAktiekapital: 5 000\nVerkst dir: Léon Jägre\nEtableringsår: 1954.\nDotterbolag i Västtyskland:\nStemo-box-Vertriebsgesellschaft mbH,\nKoblenz.\n\nSVENSK LAMINATINDUSTRI\n\nPnr 30239\n\nHalmstad, Ankarg 1. Tel\n035-118045. Telex 38021 LAMINAT S\nVerksamhet: Ventilationsmateriel,\ninblåsningsdon, galler o ventiler\nÄgare o chef: O Peterson\nEtableringsår: 1952.\n\nBONTHRON &amp; EWING, AB\n\nPnr 101 28\n\nStockholm 1, Klara N Kyrkog 26.\nBox 632. Tel 08-23 58 25. Postgiro\n2424. Telex 1425. Tga Ewings\nVerksamhet: Maskiner, verktyg o\nmaskinförnödenheter\nVarunamn: ÄRO, C.C., Cholet,\nConomatic, Creusot-Loire, Cri-Dan,\nEclipse (Neill), Ernault-Somua,\nExo, Frömag, Günther, Jacob,\nLehfeldt, Manurhin, Mengele,\nNLM, Pegard, Schneeberger,\nScripta, Titex, Wendt, Volumair,\nVoumard\n\nAntal anställda: 28\nÅrsomsättning: 8 500 000\nVerkst dir: Gunnar Sahlström\nEtableringsår: 1917\nOmbildat till aktiebolag 1932.\n\nBONVING SKOFABRIK,\nAB BRUDERNA\n\nPnr 571 00\n\nNässjö. Tel 0380-132 30. Bankgiro\n45-2712. Postgiro 264770\n\nVerksamhet: Tillverkar mansskor\n\nför finbruk\n\nAntal anställda: 80\n\nÅrsomsättning: 4 000 000\n\nAktiekapital: 90 000\n\nÄgare o chef: Disp Elving Bonving\n\nEtableringsår: 1944.\n\nORBO AB\n\nPnr 703 58\n\nÖrebro, Myrmalmsg 10. Tel\n019-1303 40. Bankgiro 614-4141.\nPostgiro 36360-6\n\nVerksamhet: Tillverkar tätningslist\nAntal anstäUda: 30\nÅrsomsättning: 3 000 000\n\nAktiekapital: 20 000\nVerkst din Erie Petersson\nEtableringsår: 1948.\n\nOREBRO AUTOMOBILAFFÄR\n\nPrr 70106\n\nÖrebro 1. Box 448. Rudbecksg 4.\nTel 019-124055. Bankgiro\n411-9640. Postgiro 382899-3\nVerksamhet: Säljer bilar samt\nreservdelar o tillbehör. Utför\nbilreparationer. Återförsäljare\nför Automobiles Citroen AB,\nHägersten\n\nAntal anstäUda: 3\nÅrsomsättning: 1000 000\nChef: Ingvar Malm\nEtableringsår: 1928.\n\nOREBRO DATA AB\n\nPrr 703 62\n\nÖrebro, Fredsg 18. Tel\n019-140255. Bankgiro 152-7027.\nPostgiro 91620-5. Telex 73229 PIPIP S\nVerksamhet: Databehandling\nAntal anställda: 17\nÅrsomsättning: 1200 000\nAktiekapital: 40 000\nVerkst dir: Sven Dingertz\nEtableringsår: 1966.\n\nOREBRO ELEKTR\nINSTALLA-TION5BYRA, AB\n\nPnr 70212\n\nÖrebro, Manillag 10. Tel\n019-1244 30. Bankgiro 614-4240.\nPost-giro 20784-5\n\nVerksamhet: Elektr Installationer\nAntal anstäUda: 50\nÅrsomsättning: 3 000 000\nAktiekapital: 75 000\nVerkst dir. Mats Otterström\nEtableringsår: 1910.\n\nIVARS BROILER, AB\n\nPnr 382 00\n\nNybro, Kristvallabrunn. Tel\n0480-53100. Bankgiro 65-5973. Postgiro\n256804\n\nVerksamhet: Slaktar o djupfryser\nalla slag av tamfågel\nAntal anställda: 275\nÅrsomsättning: 40 900 000\nAktiekapital: 500 000\nVerkst dir: Ivar Carlsson\nEtableringsår. 1952.\n\nIVARS HUS &amp; FRITIDSTOMTER\nAB\n\nPnr 824 00\n\nHudiksvall, V Tullg 51. Tel\n0650-153 50, 167 10. Postgiro 224220-4\nVerksamhet: Exploatering av\nfritidstomter. Försäljning av\nnyckelfärdiga fritidshus\n.Antal anställda: 3\nÅrsomsättning: 1100 000\nAktiekapital: 50 000\nStyrelse: Dir Ivar Andersson, adv\nStig Lindström\nVerkst dir. Ivar Andersson\nEtableringsår. 1964.\n\nVECTOR MASKIN AB\n\nPnr 11135\n\nStockholm, Kungs g 18. Tel\n08-23 35 30, 10 82 77. Bankgiro\n569-4187. Postgiro 606940-5. Tga\nHakomand\n\nVerksamhet: Tillverkar o säljer\nrivmaskiner o separatorer för\ndatablanketter samt säljer maskiner\nför grafisk industri, emballering\no kontorsbruk\nAntal anställda: 16\nÅrsomsättning: 3 000 000\nAktiekapital: 20 000\nVerkst din Ake Håkanson\nEtableringsår: 1911.\n\nLOVTRÄ, KB\n\nPnr 290 37\n\nArkels torp. Tel 044-911 21, 910 37.\nBankgiro 657-8728. Tga Lövträ\nVerksamhet: Glasspinnar o\nglasskedar. Tungspatlar, tamponpinnar\nAntal anställda: 25\nÅrsomsättning: 2 000 000\nAndelskapital: 11000\nChef: Ingemar Nilsson\nEtableringsår: 1938.\n\neklund ab, helge\n\nPnr 801 05\n\nGävle 1, Nyg 20. Box 414. Tel\n026-12 50 34, 12 57 54. Bankgiro\n60-3635. Postgiro 586929\nVerksamhet: Säljer kol, koks o\nolja. Spedition. Utför sjö- o\nlandtransporter för massgods\n\nAntal anställda: 9\nÅrsomsättning: 4 300000\nAktiekapital: 5 000\nVerkst dir: Helge Eklund\nEtableringsår: 1962.\n\neklund, ingeniorsbyrän\nrolf h\n\nPnr 162 30\n\nVällingby, Viveka Trolles gränd\n15. Tel 08-89 54 60, 3879 06.\nBankgiro 747-2046. Pastgiro 557617-8.\nTga Hartwigo\n\nVerksamhet: Importerar\nblåsmaskiner, pumpar, kompensatorer, filter\nÅrsomsättning: 500 000\nChef: Ing Rolf H Eklund\nEtableringsår: 1958.\n\neklund ab,\ningeniors-firma stig\n\nPnr 162 23\n\nVällingby, Duvedsv 1. Tel 08-\n\n37 29 10. Bankgiro 577-5564.\nPostgiro 196495-6. Tga Hydroskandia.\nTelex 10671 EKLUND S\nVerksamhet: Specialfirma för\nhy-draulik. Generalagent tör\nParker-Hannifin i Skandinavien.\nA/S Cylinderservice i Sverige o\nFinland\n\nSalami hydraulik i Sverige o Finland\nBrüninghaus hydraulik i Sverige\nVarunamn: Parker-Hannifin, Servi,\nBrüninghaus, Manatrol, Crown,\nFPS, Salami\nAntal anställda: 12\nÅrsomsättning: 8 000 000\nAktiekapital: 25 000\nVerkst dir: Ing Stig Eklund\nEtableringsår: 1964.\n\nSVENSKA AB ELOXAL\n\nPnr 13502\n\nTyresö 2, Box 2040. Skog säng sv\n54. Tel 08-7120180, 712 0190.\nBankgiro 13-6172. Postgiro 459665\nVerksamhet: Eloxering.\nYtbehand-ling av aluminium\nAntal anställda: 65\n\nB 20\n\nÅrsomsättning: 7 000 000\nAktiekapital: 500 000\nVerkst dir: Carl Heckscher\nEtableringsår: 1952.\n\nSVENSKA ENTREPRENAD AB\nSENTAB\n\nPnr 102 40\n\nStockholm 5, Braheg 47. Fack. Tel\n08-23 8040. Tga Sentab.\nTelex 19038 SENTAB S\nVerksamhet Entreprenörer,\nrådgivande ingenjörer o\nbyggledningsuppdrag för alla slag av\nbyggnads-o anläggningsarbeten i Sverige o\nutlandet. Specialitet:\nbergrumsarbeten, exempelvis\noljelagrings-anläggningar\nAktiekapital: 2 000 000\nVerkst dir: Harald Alexandersson\nDir: Nils Ellström\nEtableringsår: 1933.\n\nB ELG AS, HANDELS AB\n\nPnr 411 15\n\nGöteborg, Kyrkog 4. Tel\n031-1179 73, 1179 76. Bankgiro\n33-7312. Postgiro 43487. Tga Belgas\nVerksamhet: Agenturrörelse med\nelektr hushållsapparater\nAktiekapital: 100 000\nVerkst dir: Göran Ohlsson\nEtableringsår: 1932.",
    "structured": {
        "1": {
            "company_name": "PALMER, AB GÖSTA",
            "pnr": "352 33",
            "address": "Växjö, Kungsg 8",
            "phone_number": "0470-126 50",
            "activity": "Säljer trikåvaror, arbetskläder, skjortor, träningsoveraller, gardiner, kortvaror, vitvaror i parti",
            "capital": 22700,
            "key_personnel": [
                {
                    "name": "Nils Erie Palmér",
                    "position": "Verkst dir"
                }
            ],
            "establishment_year": 1933
        },
        "2": {
            "company_name": "SVE",
            "pnr": "10 8125",
            "address": "Stockholm, Hallandsg 38",
            "phone_number": "08-44 05 05",
            "bank_details": {
                "bankgiro": "331-0141",
                "postgiro": "5552-4"
            },
            "activity": "Bild- o filmvisningsservice",
            "employees": 7,
            "annual_turnover": 1000000,
            "capital": 75000,
            "key_personnel": [
                {
                    "name": "Harry Jonasson",
                    "position": "Verkst dir"
                }
            ],
            "establishment_year": 1937
        },
        "3": {
            "company_name": "SVENSK LAGERSTANDARD, AB",
            "pnr": "116 57",
            "address": "Stockholm, Hallandsg 38",
            "phone_number": "08-44 05 05",
            "bank_details": {
                "bankgiro": "573-3076",
                "postgiro": "258390-4"
            },
            "activity": "Lagerinredningar i stål. Specialitet: Stemo plastbox för smådelar",
            "employees": 5,
            "annual_turnover": 1200000,
            "capital": 5000,
            "key_personnel": [
                {
                    "name": "Léon Jägre",
                    "position": "Verkst dir"
                }
            ],
            "establishment_year": 1954
        },
        "4": {
            "company_name": "SVENSK LAMINATINDUSTRI",
            "pnr": "30239",
            "address": "Halmstad, Ankarg 1",
            "phone_number": "035-118045",
            "telex": "38021 LAMINAT S",
            "activity": "Ventilationsmateriel, inblåsningsdon, galler o ventiler",
            "key_personnel": [
                {
                    "name": "O Peterson",
                    "position": "Ägare o chef"
                }
            ],
            "establishment_year": 1952
        },
        "5": {
            "company_name": "BONTHRON & EWING, AB",
            "pnr": "101 28",
            "address": "Stockholm 1, Klara N Kyrkog 26, Box 632",
            "phone_number": "08-23 58 25",
            "postgiro": "2424",
            "telex": "1425, Tga Ewings",
            "activity": "Maskiner, verktyg o maskinförnödenheter",
            "varunamn": "ÄRO, C.C., Cholet, Conomatic, Creusot-Loire, Cri-Dan, Eclipse (Neill), Ernault-Somua, Exo, Frömag, Günther, Jacob, Lehfeldt, Manurhin, Mengele, NLM, Pegard, Schneeberger, Scripta, Titex, Wendt, Volumair, Voumard",
            "employees": 28,
            "annual_turnover": 8500000,
            "key_personnel": [
                {
                    "name": "Gunnar Sahlström",
                    "position": "Verkst dir"
                }
            ],
            "establishment_year": 1917
        },
        "6": {
            "company_name": "BONVING SKOFABRIK, AB BRUDERNA",
            "pnr": "571 00",
            "address": "Nässjö",
            "phone_number": "0380-132 30",
            "bank_details": {
                "bankgiro": "45-2712",
                "postgiro": "264770"
            },
            "activity": "Tillverkar mansskor för finbruk",
            "employees": 80,
            "annual_turnover": 4000000,
            "capital": 90000,
            "key_personnel": [
                {
                    "name": "Disp Elving Bonving",
                    "position": "Ägare o chef"
                }
            ],
            "establishment_year": 1944
        },
        "7": {
            "company_name": "ORBO AB",
            "pnr": "703 58",
            "address": "Örebro, Myrmalmsg 10",
            "phone_number": "019-1303 40",
            "bank_details": {
                "bankgiro": "614-4141",
                "postgiro": "36360-6"
            },
            "activity": "Tillverkar tätningslist",
            "employees": 30,
            "annual_turnover": 3000000,
            "capital": 20000,
            "key_personnel": [
                {
                    "name": "Erie Petersson",
                    "position": "Verkst dir"
                }
            ],
            "establishment_year": 1948
        },
        "8": {
            "company_name": "OREBRO AUTOMOBILAFFÄR",
            "pnr": "70106",
            "address": "Örebro 1, Box 448, Rudbecksg 4",
            "phone_number": "019-124055",
            "bank_details": {
                "bankgiro": "411-9640",
                "postgiro": "382899-3"
            },
            "activity": "Säljer bilar samt reservdelar o tillbehör. Utför bilreparationer. Återförsäljare för Automobiles Citroen AB, Hägersten",
            "employees": 3,
            "annual_turnover": 1000000,
            "key_personnel": [
                {
                    "name": "Ingvar Malm",
                    "position": "Chef"
                }
            ],
            "establishment_year": 1928
        },
        "9": {
            "company_name": "OREBRO DATA AB",
            "pnr": "703 62",
            "address": "Örebro, Fredsg 18",
            "phone_number": "019-140255",
            "bank_details": {
                "bankgiro": "152-7027",
                "postgiro": "91620-5"
            },
            "telex": "73229 PIPIP S",
            "activity": "Databehandling",
            "employees": 17,
            "annual_turnover": 1200000,
            "capital": 40000,
            "key_personnel": [
                {
                    "name": "Sven Dingertz",
                    "position": "Verkst dir"
                }
            ],
            "establishment_year": 1966
        },
        "10": {
            "company_name": "OREBRO ELEKTR INSTALLATION5BYRA, AB",
            "pnr": "70212",
            "address": "Örebro, Manillag 10",
            "phone_number": "019-1244 30",
            "bank_details": {
                "bankgiro": "614-4240",
                "postgiro": "20784-5"
            },
            "activity": "Elektr Installationer",
            "employees": 50,
            "annual_turnover": 3000000,
            "capital": 75000,
            "key_personnel": [
                {
                    "name": "Mats Otterström",
                    "position": "Verkst dir"
                }
            ],
            "establishment_year": 1910
        },
        "11": {
            "company_name": "IVARS BROILER, AB",
            "pnr": "382 00",
            "address": "Nybro, Kristvallabrunn",
            "phone_number": "0480-53100",
            "bank_details": {
                "bankgiro": "65-5973",
                "postgiro": "256804"
            },
            "activity": "Slaktar o djupfryser alla slag av tamfågel",
            "employees": 275,
            "annual_turnover": 40900000,
            "capital": 500000,
            "key_personnel": [
                {
                    "name": "Ivar Carlsson",
                    "position": "Verkst dir"
                }
            ],
            "establishment_year": 1952
        },
        "12": {
            "company_name": "IVARS HUS & FRITIDSTOMTER AB",
            "pnr": "824 00",
            "address": "Hudiksvall, V Tullg 51",
            "phone_number": "0650-153 50, 167 10",
            "postgiro": "224220-4",
            "activity": "Exploatering av fritidstomter. Försäljning av nyckelfärdiga fritidshus",
            "employees": 3,
            "annual_turnover": 1100000,
            "capital": 50000,
            "key_personnel": [
                {
                    "name": "Ivar Andersson",
                    "position": "Verkst dir"
                },
                {
                    "name": "Stig Lindström",
                    "position": "adv"
                }
            ],
            "establishment_year": 1964
        },
        "13": {
            "company_name": "VECTOR MASKIN AB",
            "pnr": "11135",
            "address": "Stockholm, Kungs g 18",
            "phone_number": "08-23 35 30, 10 82 77",
            "bank_details": {
                "bankgiro": "569-4187",
                "postgiro": "606940-5"
            },
            "activity": "Tillverkar o säljer rivmaskiner o separatorer för datablanketter samt säljer maskiner för grafisk industri, emballering o kontorsbruk",
            "employees": 16,
            "annual_turnover": 3000000,
            "capital": 20000,
            "key_personnel": [
                {
                    "name": "Ake Håkanson",
                    "position": "Verkst dir"
                }
            ],
            "establishment_year": 1911
        },
        "14": {
            "company_name": "LOVTRÄ, KB",
            "pnr": "290 37",
            "address": "Arkels torp",
            "phone_number": "044-911 21, 910 37",
            "bank_details": {
                "bankgiro": "657-8728"
            },
            "telex": "Lövträ",
            "activity": "Glasspinnar o glasskedar. Tungspatlar, tamponpinnar",
            "employees": 25,
            "annual_turnover": 2000000,
            "andelskapital": 11000,
            "key_personnel": [
                {
                    "name": "Ingemar Nilsson",
                    "position": "Chef"
                }
            ],
            "establishment_year": 1938
        },
        "15": {
            "company_name": "eklund ab, helge",
            "pnr": "801 05",
            "address": "Gävle 1, Nyg 20, Box 414",
            "phone_number": "026-12 50 34, 12 57 54",
            "bank_details": {
                "bankgiro": "60-3635",
                "postgiro": "586929"
            },
            "activity": "Säljer kol, koks o olja. Spedition. Utför sjö- o landtransporter för massgods",
            "employees": 9,
            "annual_turnover": 4300000,
            "capital": 5000,
            "key_personnel": [
                {
                    "name": "Helge Eklund",
                    "position": "Verkst dir"
                }
            ],
            "establishment_year": 1962
        },
        "16": {
            "company_name": "eklund, ingeniorsbyrän rolf h",
            "pnr": "162 30",
            "address": "Vällingby, Viveka Trolles gränd 15",
            "phone_number": "08-89 54 60, 3879 06",
            "bank_details": {
                "bankgiro": "747-2046",
                "postgiro": "557617-8"
            },
            "telex": "Hartwigo",
            "activity": "Importerar blåsmaskiner, pumpar, kompensatorer, filter",
            "annual_turnover": 500000,
            "key_personnel": [
                {
                    "name": "Ing Rolf H Eklund",
                    "position": "Chef"
                }
            ],
            "establishment_year": 1958
        },
        "17": {
            "company_name": "eklund ab, ingeniors-firma stig",
            "pnr": "162 23",
            "address": "Vällingby, Duvedsv 1",
            "phone_number": "08-37 29 10",
            "bank_details": {
                "bankgiro": "577-5564",
                "postgiro": "196495-6"
            },
            "telex": "10671 EKLUND S",
            "activity": "Specialfirma för hy-draulik. Generalagent för Parker-Hannifin i Skandinavien. A/S Cylinderservice i Sverige o Finland, Salami hydraulik i Sverige o Finland, Brüninghaus hydraulik i Sverige",
            "varunamn": "Parker-Hannifin, Servi, Brüninghaus, Manatrol, Crown, FPS, Salami",
            "employees": 12,
            "annual_turnover": 8000000,
            "capital": 25000,
            "key_personnel": [
                {
                    "name": "Ing Stig Eklund",
                    "position": "Verkst dir"
                }
            ],
            "establishment_year": 1964
        },
        "18": {
            "company_name": "SVENSKA AB ELOXAL",
            "pnr": "13502",
            "address": "Tyresö 2, Box 2040, Skog säng sv 54",
            "phone_number": "08-7120180, 712 0190",
            "bank_details": {
                "bankgiro": "13-6172",
                "postgiro": "459665"
            },
            "activity": "Eloxering. Ytbehand-ling av aluminium",
            "employees": 65,
            "annual_turnover": 7000000,
            "capital": 500000,
            "key_personnel": [
                {
                    "name": "Carl Heckscher",
                    "position": "Verkst dir"
                }
            ],
            "establishment_year": 1952
        },
        "19": {
            "company_name": "SVENSKA ENTREPRENAD AB SENTAB",
            "pnr": "102 40",
            "address": "Stockholm 5, Braheg 47",
            "phone_number": "08-23 8040",
            "telex": "19038 SENTAB S",
            "activity": "Entreprenörer, rådgivande ingenjörer o byggledningsuppdrag för alla slag av byggnads-o anläggningsarbeten i Sverige o utlandet. Specialitet: bergrumsarbeten, exempelvis oljelagrings-anläggningar",
            "capital": 2000000,
            "key_personnel": [
                {
                    "name": "Harald Alexandersson",
                    "position": "Verkst dir"
                },
                {
                    "name": "Nils Ellström",
                    "position": "Dir"
                }
            ],
            "establishment_year": 1933
        },
        "20": {
            "company_name": "B ELG AS, HANDELS AB",
            "pnr": "411 15",
            "address": "Göteborg, Kyrkog 4",
            "phone_number": "031-1179 73, 1179 76",
            "bank_details": {
                "bankgiro": "33-7312"
            },
            "activity": "Agenturrörelse med elektr hushållsapparater",
            "capital": 100000,
            "key_personnel": [
                {
                    "name": "Göran Ohlsson",
                    "position": "Verkst dir"
                }
            ],
            "establishment_year": 1932
        }
    }
}