{
    "original": "ANDERSSON, AB HARALD\n\nPnr 87101\n\nHärnösand 1, Varvsg. Box 76. Tel\n0611-13110. Bankgiro 767-8816.\nPostgiro 7897-2. Tga Harald\nVerksamhet: Säljer\nbyggnadsmaterial. Utför golventreprenader\nAntal anställda: 32\nÅrsomsättning: 9 600 000\nAktiekapital: 300 000\nVerkst dir: Gunnar Utterström\nEtableringsår: 1878.\n\nANDERSON ÅKERI AB,\nharry\n\nPnr 415 02\n\nGöteborg, Walckesg 4. Tel\n031-19 9370, 199445. Bankgiro\n444-7025. Postgiro 242667-4\nVerksamhet: Åkeri,\ntransport-rörelse\n\nAntal anställda: 58\nÅrsomsättning: 3 052 000\nAktiekapital: 300 000\nVerkst dir: C Harry Anderson\nFörest: Pieter Rygaard\nEtableringsår: 1920\nOmbildat till aktiebolag 1947.\n\nANDERSSONS TRÄ- &amp;\nBYGG-NADSVARU AB, HENNING\n\nPnr 370 10\n\nBräkne-Hoby, Svenstorp. Box 27.\nTel 0454-300 28. Bankgiro\n151-3571. Postgiro 145495-8\nVerksamhet: Sågverk\nAntal anställda: 35\nÅrsomsättning: 6500 000\nAktiekapital: 100 000\nVerkst din Henning Andersson\nEtableringsår: 1929.\n\nvon BRAUN, DET LÖW B\n\nPnr 411 21\n\nGöteborg, Skeppsbron 4. Tel\n031-11 19 59, 13 79 24. Bankgiro\n500-0369. Tga Detlow\nVerksamhet: Importagenturen\nråvaror för industrin inklusive\nlivsmedelsindustrin\nÅrsomsättning: 5 000 000\nChef: Lennart von Braun\nEtableringsår: 1913.\n\nSERVA JÄRNVARU AB\n\nPnr 104 60\n\nStockholm 20, Mårtendalsv 1. Box\n20019. Tel 08-44 0510. Postgiro\n1139-5. Tga Servajärn.\nTelex 10260, 10261 ALTUMBA S\nVerksamhet: Partiförsäljning av\nrostfria hushållsartiklar o\ndiskbänkar, jakt- o tävlings våp en,\ngräsklippare o trädgårdsredskap,\nelektriska hushållsartiklar, utrustning\nför materialhantering\nFilialer: Göteborg C, Mätare g 2.\nTel 031-1183 06, 1183 26\nMalmö S, Norbergsg 10. Tel\n040-804 90\n\nUmeå, Skolg 62. Tel 090-12 54 80\nAktiekapital: 100 000\nVerkst dir: P O Wernerson\nEtableringsàr 1935.\n\nBENZON &amp; CO, AB ALFRED\n\nPnr 212 14\n\nMalmö, Industrig 11. Tel\n040-93 46 00. Tga Benzona\nVerksamhet: Säljer kemikalier,\nkylgaser, syror, torra färger m m\nAktiekapital: 500 000\nVerkst dir: Börje Novén\nEtableringsår: 1900\nOmbildat till aktiebolag 1913.\n\nBENZON AB MASKIN- &amp;\nMEKANISK VERKSTAD, GÖSTA\n\nPnr 212 25\n\nMalmö, Stillmansg 1. Tel\n040-93 48 65. Bankgiro 641-0575.\nPostgiro 246751-2.\nTelex 3309 PACK AGE S\nVerksamhet: Tillverkar\nförpackningsmaskiner o tillbehör för\nlivsmedelsindustrin\nAntal anställda: 80\nÅrsomsättning: 4 500 000\nAktiekapital: 120 000\nStyrelse: Adv Carl Borgström, dir\nHolger Crafoord, ombudsman\nMagnus Thorfinn\n\nVerkst dir: Sven Wernersson\nKamrer: Stig Iwenstam\nEtableringsår: 1948\nOmbildat till aktiebolag 1960.\n1968 försålt till AB Åkerlund &amp;\nRausing, Lund.\n\nBENSON, AB J\n\nPnr 217 45\n\nMalmö, Mariedalsv 32. Tel\n040-720 25. Postgiro 24528. Tga\nJohnbenson\n\nVerksamhet: Tillverkar cyklar o\n\nmopeder\n\nVarunamn: Maraton\nÅrsomsättning: 5000 000\nAktiekapital: 200 000\nVerkst din Kjell Holmgren\nEtableringsår: 1899.\n\nC LÄSE AB, C A\n\nPnr 41109\n\nGöteborg C. O Hamng 52. Tel\n031-17 60 30. Telex 20696. Tga Albion\nVerksamhet: Säljer asbestvaror,\nbyggvaror o isolermaterial samt\nutför isoleringsarbeten o\ngolvbeläggningar. Vacuumlyftare,\nventiler o mek axeltätningar samt\ngland-packningar, Gyro, radar\nfartygs-stabilisatorer, datorer\nVarunamn: Crane, Everite, Limpet,\nSemtex, Serck, Sindanyo, Sperry\nRand, Turnall, Vac-u-lift\nAktiekapital: 1000 000\nVerkst dir: Viking Clase\nEtableringsår: 1909.\n\nELIASSONS ÅKERI,\nAB BRDDERNA\n\nPnr 302 55\n\nHalmstad, Akeriterminalen. Tel\n035-10 02 40. Bankgiro 338-9822.\nPostgiro 113700-04\nVerksamhet: Godstransporter.\nUthyrning av gaffeltruckar\nAntal anställda: 30\nÅrsomsättning: 1800 000\nAktiekapital: 10 000\nVerkst dir. Harald Eliasson\nEtableringsår. 1949.\n\nELIASSONS LÄDERINDUSTRI\nAB, AND\n\nPnr 782 00\n\nMalung, Box 43. Tel 0280-11740.\nBankgiro 468-4619. Postgiro\n74909-3. Tga Eliassonsläder\nVerksamhet: Tillverkar\nbeklädnads-läder o skoovanläder\nAntal anställda: 100\nÅrsomsättning: 12000 000\nAktiekapital: 600 000\nVerkst dir: Robert Eliasson\nEtableringsår: 1888.\n\nVINGÅKERS ELEKTRISKA AB\n\nPnr 643 00\n\nVingåker. Box 21. Storg 25. Tel\n0151-115 10. Bankgiro 624-7175.\nPostgiro 580915-7\nVerksamhet: Elektr\ninstallations-rörelse\n\nAntal anställda: 28\nÅrsomsättning: 3 000 000\n\nAktiekapital: 62 000\nVerkst dir: Rune Skoglundh\nEtableringsår: 1959.\n\n(VINGÅKERS KONFEKTIONS.\nAB)\n\nMAGNI OF SWEDEN AB\n\nPnr 643 00\n\nVingåker. Tel 0151-11500.\nBankgiro 830-9148. Postgiro 32577-9\nVerksamhet: Försäljer kostymer,\nblazers, byxor, överrockar\nAntal anställda: 40\nÅrsomsättning: 4 000 000\nAktiekapital: 46 700\nVerkst dir. Reidar Ljungström\nEtableringsår: 1923.\n\nHEDEMORA VERKSTÄDER, AB\n\nPnr 776 00\n\nHedemora, Stureg 2. Tel\n0225-12000. Bankgiro 466-8091.\nPostgiro 27757-4. Tga Hedverk. Telex\n7549\n\nVerksamhet: Hedemora\nDieselmotorer. 600-2000 hk. Angljuddämpare,\nljuddämpande personalhytter o\nmaskinhöljen.\n\nUtrustning för cellulosa^,\npappers-o boardindustrin:\nDorr-Oliver\nkausticeringsanlägg-rnngar, Fluosolids mesaombränning,\nfilter, bågsilar, mixers, klarnare,\nförtjockare. Johnson Fractionator\nför steglös fraktionering av fiber.\nHelautomatiska pappmaskiner.\nSul-fitsyraberedningsapparater (kalciumbas)\n\nAntal anställda: 300\nÅrsomsättning: 30000 000\nAktiekapital: 900 000\nStyrelse: Bergsing Axel Ax:son\nJohnson (ordf), dir Bo Ax:son\nJohnson, hovrättsråd Allan\nBjörklund, bruksdisp Carl Einar\nLenngren. dir Gunnar Westerberg, dir\nHelge Lindberg\n\nVerkst dir: Carl Einar Lenngren\nPlatschef: Dir Sven-Eric Håkansson\nFörsäljningschef: Civiling Bertil\nDahllöv\n\nEtableringsår: 1903\nTillhör Johnsonkoncernen.\n\nHEDEN AB, ALRIK\n\nPnr 12109\n\nJohanneshov 9, Box 9067.\nImpor-törv 4-44. Tel 08-8103 90. Postgiro\n451698-5\n\nVerksamhet: Säljer papper,\nengångsartiklar o emballage\nAntal anställda: 14\nÅrsomsättning: 7 000 000\nAktiekapital: 20 000\nVerkst dir: Alrik Hedén\nEtableringsår: 1967.\n\nmaskinbyrån\n\nPnr 600 08\n\nNorrköping 8, Taborsbergsv 10.\nBox 8015. Tel 011-10 13 19,16 12 28.\nBankgiro 835-0142. Postgiro\n4937 84-3\n\nVerksamhet Säljer\nhushållsmaskiner o hobbymaskiner\nÅrsomsättning: 100 000\nChef: Sixten Garhagen\nEtableringsår: 1964.\n\nI CA- RESTAURANGER, AB\n\nPnr 10251\n\nStockholm 27, Osthammarsg 78.\nBox 27074. Tel 08-67 95 80.\nBankgiro 728-4318. Postgiro 49025-0\nVerksamhet: Bar- o\nrestaurangrörelse\n\nAntal anställda: 2 500\nÅrsomsättning: 140 000 000\nAktiekapital: 2500000\nVerkst dir: Gösta Brännström\nEtableringsår: 1944.",
    "structured": {
        "1": {
            "company_name": "ANDERSSON, AB HARALD",
            "pnr": "87101",
            "address": "Härnösand 1, Varvsg. Box 76",
            "phone_number": "0611-13110",
            "bank_details": {
                "bankgiro": "767-8816",
                "postgiro": "7897-2"
            },
            "activity": "Säljer byggnadsmaterial. Utför golventreprenader",
            "employees": 32,
            "annual_turnover": 9600000,
            "capital": 300000,
            "key_personnel": [
                {
                    "name": "Gunnar Utterström",
                    "position": "Verkst dir"
                }
            ],
            "establishment_year": 1878
        },
        "2": {
            "company_name": "ANDERSON ÅKERI AB",
            "pnr": "415 02",
            "address": "Göteborg, Walckesg 4",
            "phone_number": "031-19 9370",
            "bank_details": {
                "bankgiro": "444-7025",
                "postgiro": "242667-4"
            },
            "activity": "Åkeri, transport-rörelse",
            "employees": 58,
            "annual_turnover": 3052000,
            "capital": 300000,
            "key_personnel": [
                {
                    "name": "C Harry Anderson",
                    "position": "Verkst dir"
                },
                {
                    "name": "Pieter Rygaard",
                    "position": "Förest"
                }
            ],
            "establishment_year": 1920
        },
        "3": {
            "company_name": "ANDERSSONS TRÄ- & BYGG-NADSVARU AB",
            "pnr": "370 10",
            "address": "Bräkne-Hoby, Svenstorp. Box 27",
            "phone_number": "0454-300 28",
            "bank_details": {
                "bankgiro": "151-3571",
                "postgiro": "145495-8"
            },
            "activity": "Sågverk",
            "employees": 35,
            "annual_turnover": 6500000,
            "capital": 100000,
            "key_personnel": [
                {
                    "name": "Henning Andersson",
                    "position": "Verkst din"
                }
            ],
            "establishment_year": 1929
        },
        "4": {
            "company_name": "von BRAUN, DET LÖW B",
            "pnr": "411 21",
            "address": "Göteborg, Skeppsbron 4",
            "phone_number": "031-11 19 59, 13 79 24",
            "bank_details": {
                "bankgiro": "500-0369"
            },
            "activity": "Importagenturen råvaror för industrin inklusive livsmedelsindustrin",
            "annual_turnover": 5000000,
            "key_personnel": [
                {
                    "name": "Lennart von Braun",
                    "position": "Chef"
                }
            ],
            "establishment_year": 1913
        },
        "5": {
            "company_name": "SERVA JÄRNVARU AB",
            "pnr": "104 60",
            "address": "Stockholm 20, Mårtendalsv 1. Box 20019",
            "phone_number": "08-44 0510",
            "bank_details": {
                "postgiro": "1139-5"
            },
            "activity": "Partiförsäljning av rostfria hushållsartiklar o diskbänkar, jakt- o tävlingsvapen, gräsklippare o trädgårdsredskap, elektriska hushållsartiklar, utrustning för materialhantering",
            "branches": [
                "Göteborg C, Mätare g 2. Tel 031-1183 06, 1183 26",
                "Malmö S, Norbergsg 10. Tel 040-804 90",
                "Umeå, Skolg 62. Tel 090-12 54 80"
            ],
            "capital": 100000,
            "key_personnel": [
                {
                    "name": "P O Wernerson",
                    "position": "Verkst dir"
                }
            ],
            "establishment_year": 1935
        },
        "6": {
            "company_name": "BENZON & CO, AB ALFRED",
            "pnr": "212 14",
            "address": "Malmö, Industrig 11",
            "phone_number": "040-93 46 00",
            "bank_details": {
                "bankgiro": "N/A",
                "postgiro": "N/A"
            },
            "activity": "Säljer kemikalier, kylgaser, syror, torra färger m m",
            "capital": 500000,
            "key_personnel": [
                {
                    "name": "Börje Novén",
                    "position": "Verkst dir"
                }
            ],
            "establishment_year": 1900
        },
        "7": {
            "company_name": "BENZON AB MASKIN- & MEKANISK VERKSTAD",
            "pnr": "212 25",
            "address": "Malmö, Stillmansg 1",
            "phone_number": "040-93 48 65",
            "bank_details": {
                "bankgiro": "N/A",
                "postgiro": "N/A"
            },
            "activity": "Tillverkar förpackningsmaskiner o tillbehör för livsmedelsindustrin",
            "employees": 80,
            "annual_turnover": 4500000,
            "capital": 120000,
            "key_personnel": [
                {
                    "name": "Sven Wernersson",
                    "position": "Verkst dir"
                },
                {
                    "name": "Stig Iwenstam",
                    "position": "Kamrer"
                }
            ],
            "establishment_year": 1948
        },
        "8": {
            "company_name": "BENSON, AB J",
            "pnr": "217 45",
            "address": "Malmö, Mariedalsv 32",
            "phone_number": "040-720 25",
            "bank_details": {
                "postgiro": "24528"
            },
            "activity": "Tillverkar cyklar o mopeder",
            "varunamn": "Maraton",
            "annual_turnover": 5000000,
            "capital": 200000,
            "key_personnel": [
                {
                    "name": "Kjell Holmgren",
                    "position": "Verkst din"
                }
            ],
            "establishment_year": 1899
        },
        "9": {
            "company_name": "C LÄSE AB, C A",
            "pnr": "41109",
            "address": "Göteborg C, O Hamng 52",
            "phone_number": "031-17 60 30",
            "telex": "20696",
            "activity": "Säljer asbestvaror, byggvaror o isolermaterial samt utför isoleringsarbeten o golvbeläggningar. Vacuumlyftare, ventiler o mek axeltätningar samt gland-packningar, Gyro, radar fartygs-stabilisatorer, datorer",
            "varunamn": "Crane, Everite, Limpet, Semtex, Serck, Sindanyo, Sperry Rand, Turnall, Vac-u-lift",
            "capital": 1000000,
            "key_personnel": [
                {
                    "name": "Viking Clase",
                    "position": "Verkst dir"
                }
            ],
            "establishment_year": 1909
        },
        "10": {
            "company_name": "ELIASSONS ÅKERI, AB BRDDERNA",
            "pnr": "302 55",
            "address": "Halmstad, Akeriterminalen",
            "phone_number": "035-10 02 40",
            "bank_details": {
                "bankgiro": "338-9822",
                "postgiro": "113700-04"
            },
            "activity": "Godstransporter. Uthyrning av gaffeltruckar",
            "employees": 30,
            "annual_turnover": 1800000,
            "capital": 10000,
            "key_personnel": [
                {
                    "name": "Harald Eliasson",
                    "position": "Verkst dir"
                }
            ],
            "establishment_year": 1949
        },
        "11": {
            "company_name": "ELIASSONS LÄDERINDUSTRI AB, AND",
            "pnr": "782 00",
            "address": "Malung, Box 43",
            "phone_number": "0280-11740",
            "bank_details": {
                "bankgiro": "468-4619",
                "postgiro": "74909-3"
            },
            "activity": "Tillverkar beklädnads-läder o skoovanläder",
            "employees": 100,
            "annual_turnover": 12000000,
            "capital": 600000,
            "key_personnel": [
                {
                    "name": "Robert Eliasson",
                    "position": "Verkst dir"
                }
            ],
            "establishment_year": 1888
        },
        "12": {
            "company_name": "VINGÅKERS ELEKTRISKA AB",
            "pnr": "643 00",
            "address": "Vingåker, Box 21, Storg 25",
            "phone_number": "0151-115 10",
            "bank_details": {
                "bankgiro": "624-7175",
                "postgiro": "580915-7"
            },
            "activity": "Elektr installations-rörelse",
            "employees": 28,
            "annual_turnover": 3000000,
            "capital": 62000,
            "key_personnel": [
                {
                    "name": "Rune Skoglundh",
                    "position": "Verkst dir"
                }
            ],
            "establishment_year": 1959
        },
        "13": {
            "company_name": "MAGNI OF SWEDEN AB",
            "pnr": "643 00",
            "address": "Vingåker",
            "phone_number": "0151-11500",
            "bank_details": {
                "bankgiro": "830-9148",
                "postgiro": "32577-9"
            },
            "activity": "Försäljer kostymer, blazers, byxor, överrockar",
            "employees": 40,
            "annual_turnover": 4000000,
            "capital": 46700,
            "key_personnel": [
                {
                    "name": "Reidar Ljungström",
                    "position": "Verkst dir"
                }
            ],
            "establishment_year": 1923
        },
        "14": {
            "company_name": "HEDEMORA VERKSTÄDER, AB",
            "pnr": "776 00",
            "address": "Hedemora, Stureg 2",
            "phone_number": "0225-12000",
            "bank_details": {
                "bankgiro": "466-8091",
                "postgiro": "27757-4"
            },
            "activity": "Hedemora Dieselmotorer. 600-2000 hk. Angljuddämpare, ljuddämpande personalhytter o maskinhöljen. Utrustning för cellulosa, pappers-o boardindustrin: Dorr-Oliver kausticeringsanläggningar, Fluosolids mesaombränning, filter, bågsilar, mixers, klarnare, förtjockare. Johnson Fractionator för steglös fraktionering av fiber. Helautomatiska pappmaskiner. Sulfitsyraberedningsapparater (kalciumbas)",
            "employees": 300,
            "annual_turnover": 30000000,
            "capital": 900000,
            "key_personnel": [
                {
                    "name": "Carl Einar Lenngren",
                    "position": "Verkst dir"
                }
            ],
            "establishment_year": 1903
        },
        "15": {
            "company_name": "HEDEN AB, ALRIK",
            "pnr": "12109",
            "address": "Johanneshov 9, Box 9067",
            "phone_number": "08-8103 90",
            "bank_details": {
                "postgiro": "451698-5"
            },
            "activity": "Säljer papper, engångsartiklar o emballage",
            "employees": 14,
            "annual_turnover": 7000000,
            "capital": 20000,
            "key_personnel": [
                {
                    "name": "Alrik Hedén",
                    "position": "Verkst dir"
                }
            ],
            "establishment_year": 1967
        }
    }
}