{
    "original": "SVEA BAND AB\n\nPnr 58101\n\nLinköping 1, Industrig 6. Fack. Tel\n013-10 22 20. Bankgiro 12-0108.\nPostgiro 15171\n\nVerksamhet: Grafisk industri med\netiketter o\netikettmärkningsmaski-ner som specialitet.\nKvalitetstrycksaker i boktryck o offset. Blister\no blisterpackmaskiner\nFörsäljningskontor i Stockholm,\nGöteborg, Hälsingborg, Örebro\nVarunamn: Collamat, Esmatic,\nGusag, WAM\nAntal anställda: 140\nÅrsomsättning: 11500 000\nAktiekapital: 900 000\nVerkst dir: Bror Axelson\nEtableringsår 1926.\n\nHOFSTEDT, AB AXEL\n\nPnr 41119\n\nGöteborg, Surbrunnsg 6. Tel\n031-1713 90. Bankgiro 420-0846.\nPostgiro 12238-2. Tga Hofgtedt\nVerksamhet: Spedition, befraktning,\nmagasinering o assurans\nAktiekapital: 72 000\nVerkst dir: Carl Axel Hofstedt\nEtableringsår: 1888.\n\nSVERIGES ALLMÄNNA\nHYPOTEKSBANK\n\nPnr 103 82\n\nStockholm 7, Kungsträdgårdsg 16.\nBox 7059. Tel 08-10 03 34.\nBankgiro 700-3999. Postgiro 250600-4.\nTga Hypoteksbanken\nVerksamhet: Obligationsutgivning\nför lån till jord- o skogsbruk\nAntal anställda: 12\nVeikst dir: Gösta Renlund\nEtableringsår: 1861.\n\nSVERIGES HANDELS.\nKALENDER\n\nse Kalenderföretagen, AB Förenade.\n\nSVERIGES KREDITBANK\n\nPnr 103 81\n\nStockholm 7, Norrmalmstorg 2. Box\n7042. Tel 08-24 90 00. Bankgiro\n33-0001. Postgiro 51.\n\nTga Kreditbanken.\n\nTelex 1310 KREBA S\n\nAktiekapital: 158 400 000\n\nVerkst din Carl-Henrik Nordlander\n\nEtableringsån 1923\n\nCa 140 kontor i hela landet.\n\nSVERIGES REDAREFÖRENING\n\nPnr 411 36\n\nGöteborg, Kungsportsavenyn 1. Tel\n031-1718 30. Bankgiro 420-4491.\nPostgiro 41430-0. Tga\nRedareförening. Telex 20746 SWESHIP S\nChef: Jur dr Nils Grenander\nEtableringsår: 1906.\n\nSVERIGES STÄRKELSE.\nPRODUCENTERS FÖRENING\nU P A\n\nPnr 292 00\n\nKarlshamn, Box 50. S Fogdelyckeg\n20 A. Tel 0454-15 0 20. Bankgiro\n343-4016. Postgiro 86660-8. Tga\nStärkelse\n\nVerksamhet: Tillverkar o säljer\npotatismjöl, glykos o druvsocker\nAntal anställda: 40\nÅrsomsättning: 56 000 000\nStyrelse: Valter Persson (ordf),\nH-G Trolle-Wachtmeister (v ordf)\nVeikst din Nils Wixell (Solna)\nEtableringsån 1927.\n\nSVERIGES ÅNGFARTYGS\nASSURANS FÖRENING\n\nPnr 400 40\n\nGöteborg 4, Box 4094. Barlastg 2.\nTel 031-12 46 20. Bankgiro\n511-5910. Postgiro 40467-3. Tga\nSecu-ritas. Telex 2504 SWECLUB S\nVerksamhet: Sjöförsäkring\nAntal anställda: 41\nStyrelse: Sven Brusewitz (ordf),\nPaul G Pålsson, Stig Gorthon,\nDan-Axel Broström, Kjell Andersén,\nFrans Malmros, Curt W Högberg,\nMats Olsson, Per Erik Hedborg\nVeikst dir: Per Erik Hedborg\nEtableringsår: 1872.\n\nSVERIGE, ÅTERFÖR.\nSÄKRINGSAKTIEBOLAGET\n\nPnr 114 51\n\nStockholm, Strandv 5 B. Tel\n08-67 0010. Bankgiro 732-0229.\nPostgiro 3401-7. Tga Sverige\nVerksamhet: Aterförsäkring av\nlivförsäkring o lång sjukförsäkring\nAntal anställda: 27\nAktiekapital: 600 000\nVeikst dir: Ake Svensson\nEtableringsår: 1914.\n\nATRIO ARKITEKTKONTOR AB\n\nPnr 381 00\n\nKalmar, S Vallg 19. Tel 0480-\n\n150 25. Postgiro 108137\nVerksamhet: Projektering av hus\no stadsplaner. Byggnadskontroll\nAntal anställda: 13\nÅrsomsättning: 1100000\nAktiekapital: 6 000\nVerkst dir: Ark SAR Arne Delborn\nEtableringsår: 1952.\n\nKAI DIERKS KONSULT AB\n\nPnr 17143\n\nSolna, Ankdammsg 35. Tel\n08-82 02 95. Bankgiro 712-4159.\nPostgiro 462010-0\n\nVerksamhet: Projektering inom\n\nbyggbranschen\n\nAntal anställda: 45\n\nÅrsomsättning: 5 300 000\n\nAktiekapital: 5 000\n\nVerkst dir: Civiling Kai Dierks\n\nEtableringsår: 1968.\n\n0X1\n\nOmbildat till aktiebolag 1963.\nDotterföretag: Överman GmbH\nEnzberg/Wifrtt. Överman USA, Inc,\nKnoxvill/Tenn.\n\nOVING, AB GERHARD\n\nPnr 416 64\n\nGöteborg, Anders Perssonsg 8. Tel\n031-800245. Bankgiro 506-1445.\nPostgiro 43657-6\nVerksamhet: Utför\nVVS-installa-tioner\n\nAktiekapital: 160 000\nVerkst dir: Torsten Stendahl\nEtableringsår: 1933.\n\nOXELOSUNDS SVETS &amp;\nSMIDE, AB\n\nPnr 61300\n\nOxelösund, Verkstadsg. Tel\n0155-320 46 , 310 45. Bankgiro 293-4842.\nPostgiro 493425-3\nVerksamhet: Tillverkar\nstålkonstruktioner för byggnadsindustrin\nAntal anställda: 70\nÅrsomsättning: 5 200 000\nAktiekapital: 30 000\nVeikst dir: Olof Thor\nEtableringsår: 1952.\n\nB. S. T. -SKO AB\n\nPnr 702 27\n\nÖrebro, Tullängsg 9. Tel\n019-1170 55, 13 70 55. Bankgiro\n35-8785. Postgiro 266152\nVerksamhet: Tillverkar innetofflor\nför barn, dam o herr\nAntal anställda: 50\nÅrsomsättning: 1400 000\nAktiekapital: 50 000\nVerkst dir: Bertil Danielsson\nEtableringsår: 1948.\n\nPR-REKLAM\n\nPnr 83100\n\nÖstersund, Storg 43. Tel\n063-258 08. Bankgiro 81-1341. Post\ngiro 688727-7\n\nVerksamhet: Tillverkar fasad- o\nbiltakskyltar m m i plast. Specialitet:\nserietillverkning av fabriksskyltar\nAntal anställda: 4\nChef: R Cronheden\nEtableringsår: 1966.\n\nDE CHAMPS AB, ARNOLD\n\nPnr 11143\n\nStockholm, Kungsg 7. Tel\n08-111750, 111751. Tga Adechamps.\nTelex 1840\n\nVerksamhet: Rederirörelse i\nreguljär linjefart\nAntal anställda: 77\nAktiekapital: 200 000\nVerkst dir: Skeppsredare Arnold\nde Champs\nEtableringsår: 1927.\n\nKNÄREDS INDUSTRI AB\n\nPnr 310 20\n\nKnäred. Tel 0430-500 00\nVerksamhet: Tillverkar trämöbler\nför lunchrum\nAntal anställda: 20\nÅrsomsättning: 1 000 000\nAktiekapital: 25 000\nVerkst dir: Nils Gustafsson\nEtableringsår: 1963.",
    "structured": {
        "1": {
            "company_name": "SVEA BAND AB",
            "pnr": "58101",
            "address": "Linköping 1, Industrig 6. Fack.",
            "phone_number": "013-10 22 20",
            "bank_details": {
                "bankgiro": "12-0108",
                "postgiro": "15171"
            },
            "activity": "Grafisk industri med etiketter och etikettmärkningsmaskiner som specialitet. Kvalitetstrycksaker i boktryck och offset. Blister och blisterpackmaskiner. Försäljningskontor i Stockholm, Göteborg, Hälsingborg, Örebro.",
            "employees": 140,
            "annual_turnover": 11500000,
            "capital": 900000,
            "key_personnel": [
                {
                    "name": "Bror Axelson",
                    "position": "Verkst dir"
                }
            ],
            "establishment_year": 1926
        },
        "2": {
            "company_name": "HOFSTEDT, AB AXEL",
            "pnr": "41119",
            "address": "Göteborg, Surbrunnsg 6",
            "phone_number": "031-1713 90",
            "bank_details": {
                "bankgiro": "420-0846",
                "postgiro": "12238-2"
            },
            "activity": "Spedition, befraktning, magasinering o assurans",
            "capital": 72000,
            "key_personnel": [
                {
                    "name": "Carl Axel Hofstedt",
                    "position": "Verkst dir"
                }
            ],
            "establishment_year": 1888
        },
        "3": {
            "company_name": "SVERIGES ALLMÄNNA HYPOTEKSBANK",
            "pnr": "103 82",
            "address": "Stockholm 7, Kungsträdgårdsg 16. Box 7059",
            "phone_number": "08-10 03 34",
            "bank_details": {
                "bankgiro": "700-3999",
                "postgiro": "250600-4"
            },
            "activity": "Obligationsutgivning för lån till jord- och skogsbruk",
            "employees": 12,
            "key_personnel": [
                {
                    "name": "Gösta Renlund",
                    "position": "Veikst dir"
                }
            ],
            "establishment_year": 1861
        },
        "4": {
            "company_name": "SVERIGES KREDITBANK",
            "pnr": "103 81",
            "address": "Stockholm 7, Norrmalmstorg 2. Box 7042",
            "phone_number": "08-24 90 00",
            "bank_details": {
                "bankgiro": "33-0001",
                "postgiro": "51"
            },
            "activity": null,
            "capital": 158400000,
            "key_personnel": [
                {
                    "name": "Carl-Henrik Nordlander",
                    "position": "Verkst din"
                }
            ],
            "establishment_year": 1923
        },
        "5": {
            "company_name": "SVERIGES REDAREFÖRENING",
            "pnr": "411 36",
            "address": "Göteborg, Kungsportsavenyn 1",
            "phone_number": "031-1718 30",
            "bank_details": {
                "bankgiro": "420-4491",
                "postgiro": "41430-0"
            },
            "activity": "Redareförening",
            "key_personnel": [
                {
                    "name": "Nils Grenander",
                    "position": "Chef"
                }
            ],
            "establishment_year": 1906
        },
        "6": {
            "company_name": "SVERIGES STÄRKELSEPRODUCENTERS FÖRENING U P A",
            "pnr": "292 00",
            "address": "Karlshamn, Box 50. S Fogdelyckeg 20 A",
            "phone_number": "0454-15 0 20",
            "bank_details": {
                "bankgiro": "343-4016",
                "postgiro": "86660-8"
            },
            "activity": "Tillverkar och säljer potatismjöl, glykos och druvsocker",
            "employees": 40,
            "annual_turnover": 56000000,
            "key_personnel": [
                {
                    "name": "Valter Persson",
                    "position": "Styrelse (ordf)"
                },
                {
                    "name": "H-G Trolle-Wachtmeister",
                    "position": "Styrelse (v ordf)"
                },
                {
                    "name": "Nils Wixell",
                    "position": "Veikst din (Solna)"
                }
            ],
            "establishment_year": 1927
        },
        "7": {
            "company_name": "SVERIGES ÅNGFARTYGS ASSURANS FÖRENING",
            "pnr": "400 40",
            "address": "Göteborg 4, Box 4094. Barlastg 2",
            "phone_number": "031-12 46 20",
            "bank_details": {
                "bankgiro": "511-5910",
                "postgiro": "40467-3"
            },
            "activity": "Sjöförsäkring",
            "employees": 41,
            "key_personnel": [
                {
                    "name": "Per Erik Hedborg",
                    "position": "Veikst dir"
                },
                {
                    "name": "Sven Brusewitz",
                    "position": "Styrelse (ordf)"
                },
                {
                    "name": "Paul G Pålsson",
                    "position": "Styrelse"
                },
                {
                    "name": "Stig Gorthon",
                    "position": "Styrelse"
                },
                {
                    "name": "Dan-Axel Broström",
                    "position": "Styrelse"
                },
                {
                    "name": "Kjell Andersén",
                    "position": "Styrelse"
                },
                {
                    "name": "Frans Malmros",
                    "position": "Styrelse"
                },
                {
                    "name": "Curt W Högberg",
                    "position": "Styrelse"
                },
                {
                    "name": "Mats Olsson",
                    "position": "Styrelse"
                }
            ],
            "establishment_year": 1872
        },
        "8": {
            "company_name": "SVERIGE, ÅTERFÖR. SÄKRINGSAKTIEBOLAGET",
            "pnr": "114 51",
            "address": "Stockholm, Strandv 5 B",
            "phone_number": "08-67 0010",
            "bank_details": {
                "bankgiro": "732-0229",
                "postgiro": "3401-7"
            },
            "activity": "Aterförsäkring av livförsäkring o lång sjukförsäkring",
            "employees": 27,
            "capital": 600000,
            "key_personnel": [
                {
                    "name": "Ake Svensson",
                    "position": "Veikst dir"
                }
            ],
            "establishment_year": 1914
        },
        "9": {
            "company_name": "ATRIO ARKITEKTKONTOR AB",
            "pnr": "381 00",
            "address": "Kalmar, S Vallg 19",
            "phone_number": "0480-150 25",
            "postgiro": "108137",
            "activity": "Projektering av hus och stadsplaner. Byggnadskontroll",
            "employees": 13,
            "annual_turnover": 1100000,
            "capital": 6000,
            "key_personnel": [
                {
                    "name": "Ark SAR Arne Delborn",
                    "position": "Verkst dir"
                }
            ],
            "establishment_year": 1952
        },
        "10": {
            "company_name": "KAI DIERKS KONSULT AB",
            "pnr": "17143",
            "address": "Solna, Ankdammsg 35",
            "phone_number": "08-82 02 95",
            "bank_details": {
                "bankgiro": "712-4159",
                "postgiro": "462010-0"
            },
            "activity": "Projektering inom byggbranschen",
            "employees": 45,
            "annual_turnover": 5300000,
            "capital": 5000,
            "key_personnel": [
                {
                    "name": "Civiling Kai Dierks",
                    "position": "Verkst dir"
                }
            ],
            "establishment_year": 1968
        },
        "11": {
            "company_name": "OVING, AB GERHARD",
            "pnr": "416 64",
            "address": "Göteborg, Anders Perssonsg 8",
            "phone_number": "031-800245",
            "bank_details": {
                "bankgiro": "506-1445",
                "postgiro": "43657-6"
            },
            "activity": "Utför VVS-installationer",
            "capital": 160000,
            "key_personnel": [
                {
                    "name": "Torsten Stendahl",
                    "position": "Verkst dir"
                }
            ],
            "establishment_year": 1933
        },
        "12": {
            "company_name": "OXELOSUNDS SVETS & SMIDE, AB",
            "pnr": "61300",
            "address": "Oxelösund, Verkstadsg",
            "phone_number": "0155-320 46 , 310 45",
            "bank_details": {
                "bankgiro": "293-4842",
                "postgiro": "493425-3"
            },
            "activity": "Tillverkar stålkonstruktioner för byggnadsindustrin",
            "employees": 70,
            "annual_turnover": 5200000,
            "capital": 30000,
            "key_personnel": [
                {
                    "name": "Olof Thor",
                    "position": "Verkst dir"
                }
            ],
            "establishment_year": 1952
        },
        "13": {
            "company_name": "B. S. T. -SKO AB",
            "pnr": "702 27",
            "address": "Örebro, Tullängsg 9",
            "phone_number": "019-1170 55, 13 70 55",
            "bank_details": {
                "bankgiro": "35-8785",
                "postgiro": "266152"
            },
            "activity": "Tillverkar innetofflor för barn, dam och herr",
            "employees": 50,
            "annual_turnover": 1400000,
            "capital": 50000,
            "key_personnel": [
                {
                    "name": "Bertil Danielsson",
                    "position": "Verkst dir"
                }
            ],
            "establishment_year": 1948
        },
        "14": {
            "company_name": "PR-REKLAM",
            "pnr": "83100",
            "address": "Östersund, Storg 43",
            "phone_number": "063-258 08",
            "bank_details": {
                "bankgiro": "81-1341",
                "postgiro": "688727-7"
            },
            "activity": "Tillverkar fasad- och biltakskyltar m.m i plast. Specialitet: serietillverkning av fabriksskyltar",
            "employees": 4,
            "key_personnel": [
                {
                    "name": "R Cronheden",
                    "position": "Chef"
                }
            ],
            "establishment_year": 1966
        },
        "15": {
            "company_name": "DE CHAMPS AB, ARNOLD",
            "pnr": "11143",
            "address": "Stockholm, Kungsg 7",
            "phone_number": "08-111750, 111751",
            "activity": "Rederirörelse i reguljär linjefart",
            "employees": 77,
            "capital": 200000,
            "key_personnel": [
                {
                    "name": "Skeppsredare Arnold de Champs",
                    "position": "Verkst dir"
                }
            ],
            "establishment_year": 1927
        },
        "16": {
            "company_name": "KNÄREDS INDUSTRI AB",
            "pnr": "310 20",
            "address": "Knäred",
            "phone_number": "0430-500 00",
            "activity": "Tillverkar trämöbler för lunchrum",
            "employees": 20,
            "annual_turnover": 1000000,
            "capital": 25000,
            "key_personnel": [
                {
                    "name": "Nils Gustafsson",
                    "position": "Verkst dir"
                }
            ],
            "establishment_year": 1963
        }
    }
}