{
    "original": "HÄRDPLAST, AB\n\nPnr 332 00\n\nGislaved, Hagag 7 E..Tel\n0371-112 29. Bankgiro 143-0685.\nPostgiro 164373-3\n\nFormpressning och\nsprutning i bakelit\n\nAntal anställda: 7\nÅrsomsättning: 340000\nAktiekapital: 20 000\nFirmatecknare: CER Claesson,\nADR Claesson\nEtableringsår: 1958.\n\nHÄRDVERKSTADEN I\nANDERSTORP AB\n\nPnr 330 20\n\nAnderstorp, Agatan 24. Tel\n0371-158 40, 164 40. Bankgiro 488-1645.\nPostgiro 57 86 56-1\nVerksamhet: Värmebehandling av\nstål o lättmetall\nEtableringsår: 1961.\n\nHÄRENFORS METALL.\nVERK AB\n\nPnr 33101\n\nVärnamo 1, Box 14. Tel\n0370-157 80, 167 10.\nTelex 70199 HAMET S\nVeiksamhet: Tillverkar\nautomat-svarvade detaljer, möbelbeslag,\npressad skruv, mutter m m\nAntal anställda: 20\nÅrsomsättning: 300 000\nAktiekapital: 100000\nVerkst dir Henry Holmlind\nEtableringsår: 1962.\n\nHÄRENSTEN &amp; JOSEFSSON,\nAB\n\nPnr 330 30\n\nGnosjö, Målskog. Tel 0370-950 19.\nBankgiro 542-4478. Postgiro\n136583-2\n\nVerksamhet: Tillverkar zick-zack\nfjädrar, spiralfjädrar, spiralkabel,\nreglagewire m m\nAktiekapital: 50 000\nVerkst dir NOG Härensten\nEtableringsår: 1937.\n\nMORGÅRDSHAMMAR AB\n\nPnr 777 01\n\nSmedjebacken 1, Fack. Tel\n0240-71100. Bankgiro 47-0425. Postgiro\n72287. Tga Morgårdshammar,\nLudvika. Telex 73243 MORVERK S\nVerksamhet: Tillverkar o säljer\nmaskiner o utrustningar för\nvarm-o kallvalsverk, gruvor o\nanrikningsverk samt kugghjul o kuggväxlar\nm m. Säljer dotterbolagets, AB\nArboga Mek Verkstad,\ntråddragmaski-ner, kantpressar, gradsaxar, rör- o\nstångdragbänkar samt spånkrossar.\nDriver även kraftverk o jordbruk\nAntal anstäUda: 600\nÅrsomsättning: 60 000 000\nAktiekapital: 11475 000\nVerkst dir: Disp Hans Warrol\nEtableringsår: 1856\nDotterbolag: AB Arboga Mek\nVerkstad, Arboga.\n\nMORINDERS\nVERKSTÄDER, AB\n\nPnr 34100\n\nLjungby, Kånnav. Tel 0372-100 98.\nBankgiro 276-9743. Postgiro\n133295-6\n\nVerksamhet: Tillverkar o säljer\nbalpressar, byggnadssmide o\njärnkonstruktioner. Legoarbeten\nVarunamn: Jonsson Pressen\nAntal anstäUda: 15\nÅrsomsättning: 1400 000\nAktiekapital: 10 000\nVerkst dir: Ing Arne Morlnder\nEtableringsår: 1965.\n\nMORISO HÄNDELS. &amp;\nAGENTURFIRMA\n\nPnr 430 62\n\nPixbo, Ängsv 19. Box 55. Tel\n031-730382. Bankgiro 43-9862.\nPostgiro 424390.\nTga Moriso, Mölnlycke.\nTelex 2331\n\nVerksamhet: Säljer plastfolie,\nväv-plast, presenningsduk, jute o\nstoppningsmaterial\nÄgare o chef: A Morichetto\nEtableringsår: 1950.\n\nPALMGRENS ROR AB\n\nPnr 601 02\n\nNoirköping 1, Box 63. Hamng 2.\nTel 011-18 0175\nVeiksamhet: Rörentreprenörer,\nvärme, vatten, avlopp, olja samt\nånganläggningar\nAktiekapital: 30 000\nFilmatecknare: B J Andersson\nEtableringsår: 1871.\n\nNÄLDENS TRÄINDUSTRI, AB\n\nPnr 830 44\n\nNälden, Box 60. Tel 0640-200 24,\n20242. Bankgiro 19-8942. Postgiro\n22428-7\n\nVeiksamhet: Tillverkar\nspecialsnickerier o inredningar för skolor,\nsjukhus, hotell m fi\nAntal anställda: 20\nÅrsomsättning: 2 500 000\nAktiekapital: 60 000\nVeikst din Fabr Lennart\nHallström\n\nEtableringsår: 1962.\n\nFINSPÅNGS GROVPLÅT AB\n\nPnr 612 02\n\nFinspång 2, Box 2033. Skäggebyv.\nTel0122-150 30. Bankgiro 826-3147.\nPostgiro 347521-7\nVerksamhet: Tillverkning av\ngummibandstransportörer, alla\nutföranden, kedjetransportörer,\nskruvtransportörer,\nstålkonstruktioner, stålformar o grussilos\nAntal anställda: 42\nÅrsomsättning: 3 600 000\nAktiekapital: 5 000\nStyrelse: Dir Anders Sjöberg (ordf),\nfru Gunilla Sjöberg\nVerkst dir: Anders Sjöberg\nEtableringsår: 1956\nOmbildat till aktiebolag 1966.\n\nFINSPÅNGS PAPPERSFORAD.\nLING AB\n\nPnr 612 00\n\nFinspång, Rågången 13. Tel\n0122-502 68. 12102. Bankgiro 132-8384.\nPostgiro 103920-5\nVerksamhet: Tillverkar\npappershylsor o räknemaskinsrullar\nVerkst dir: Ake Wiklund\nEtableringsår: 1962.\n\nKUNGSKVARNS KB\n\nPnr 590 57\n\nMalmslätt. Tel 013-95100.\nBankgiro 120-1391. Postgiro 328126-8\nVerksamhet: Handel med spannmål,\ngödning o fodervaror\nAntal anställda: 10\nÅrsomsättning: 3 500 000\nChef: Disp Ivar Månsson\nEtableringsår: 1950.\n\nAUTOTEKNIK INSTRUMENT AB\n\nPnr 411 08\n\nGöteborg, Trädgårdsg 6. Tel\n031-17 88 55. Bankgiro 41-5320.\nPost-giro 43027\n\nVerksamhet: Försäljning o service\nav industri- o bilinstrument.\nDrift-timräknare, varvräknare,\nhastighetsmätare etc\n\nVarunamn: Halda, Moto-Meter,\nHermann Wetzer Schneider\nAntal anställda: 13\nAktiekapital: 5 000\nVerkst dir: A Samuelson\nEtableringsår: 1962.\n\nMIBIS\n\nPnr 172 22\n\nSundbyberg 1, Box 55. Tel\n08-28 28 50. Bankgiro 33-0259.\nPostgiro 55151. Tga Mibis, Stockholm.\nTelex 10651 MIBIS S\nVerksamhet: Tillverkning o\nförsäljning av vattenreningsutrustning,\navloppsreningsanläggningar,\nsimbad, matarvatten o\navhärdningsan-läggningar\nVarunamn: Mibis\nAntal anställda: 100\nÅrsomsättning: 16 000 000\nAktiekapital: 100 000\nVerkst dir: Göran Hultqvist\nEtableringsår 1908.\n\nPAPYRUS, AB\n\nPnr 43121\n\nMölndal 1, Kvarnbyg 2-4. Box 9.\nTel 031-27 22 40. Bankgiro\n160-8691. Postgiro 11880-2. Tga\nPapyrus, Göteborg.\nTelex 2500 PAPYRUS S\nVerksamhet: Pappers- o\nkartongtillverkning\nAntal anställda: 1 200\nÅrsomsättning: 175 000 000\nAktiekapital: 48 000 000\nVerkst dir: Sigge Rudengren\nEtableringsår: 1895.\n\nPARADIS SÄNGAR och\nSÄNGKLÄDER, AB\n\nPnr 402 71\n\nGöteborg 8, Angpanneg. Box8847.\nTel 031-22 80 80. Bankgiro 50-0009.\nPostgiro 12396. Tga Paradisbed\nVerksamhet: Tillverkar Paradis\nsängar, madrasser, kuddar, täcken,\nsängöverkast. Säljer dessutom\nplädar o textilier\nAvdelningskonton Stockholm C,\nKungsg 53. Tel 08-20 28 97\nVarunamn: Paradis\nAntal anställda: 50\nÅrsomsättning: 7 000 000\nAktiekapital: 100 000\nVerkst dir: Ake Bourghardt\nCivilekonom: A-C Åkerhielm\nFörsäljn-chef: Leif Johansson\nDriftsing: Gunnar Nyström\nEtableringsår 1881.\n\nHALTERMANN AB, JOHANN\n\nPnr 21174\n\nMalmö, Petroleumg 5. Tel\n040-18 12 20. Postgiro 530576-8. Tga\nHansabensin\n\nVerksamhet: Partiförsäljning av\nmineraloljor o\ntjärdestillationspro-dukter\n\nAktiekapital: 500 000\nStyrelse: Adv H Auerbach (ordf),\ndisp U Dunckel, dir H Haltermann\nVerkst dir: G Lemke\nEtableringsår: 1952.\n\nHALVARSSON, SKINNVARU AB\nBRÖDERNA\n\nPnr 782 00\n\nMalung, Box 56. Tel 0280-125 05.\nBankgiro 468-4668. Postgiro\n321794-7\n\nVerksamhet: Tillverkar\nskinnjackor, västar o motorkläder\nAntal anställda: 46\nÅrsomsättning: 2 500 000\nEtableringsår: 1946.",
    "structured": {
        "1": {
            "company_name": "HÄRDPLAST, AB",
            "pnr": "332 00",
            "address": "Gislaved, Hagag 7 E.",
            "phone_number": "0371-112 29",
            "bank_details": {
                "bankgiro": "143-0685",
                "postgiro": "164373-3"
            },
            "activity": "Formpressning och sprutning i bakelit",
            "employees": 7,
            "annual_turnover": 340000,
            "capital": 20000,
            "key_personnel": [
                {
                    "name": "CER Claesson",
                    "position": "Firmatecknare"
                },
                {
                    "name": "ADR Claesson",
                    "position": "Firmatecknare"
                }
            ],
            "establishment_year": 1958
        },
        "2": {
            "company_name": "HÄRDVERKSTADEN I ANDERSTORP AB",
            "pnr": "330 20",
            "address": "Anderstorp, Agatan 24",
            "phone_number": "0371-158 40, 164 40",
            "bank_details": {
                "bankgiro": "488-1645",
                "postgiro": "57 86 56-1"
            },
            "activity": "Värmebehandling av stål o lättmetall",
            "establishment_year": 1961
        },
        "3": {
            "company_name": "HÄRENFORS METALL. VERK AB",
            "pnr": "33101",
            "address": "Värnamo 1, Box 14",
            "phone_number": "0370-157 80, 167 10",
            "telex": "70199 HAMET S",
            "activity": "Tillverkar automat-svarvade detaljer, möbelbeslag, pressad skruv, mutter m m",
            "employees": 20,
            "annual_turnover": 300000,
            "capital": 100000,
            "key_personnel": {
                "name": "Henry Holmlind",
                "position": "Verkst dir"
            },
            "establishment_year": 1962
        },
        "4": {
            "company_name": "HÄRENSTEN & JOSEFSSON, AB",
            "pnr": "330 30",
            "address": "Gnosjö, Målskog",
            "phone_number": "0370-950 19",
            "bank_details": {
                "bankgiro": "542-4478",
                "postgiro": "136583-2"
            },
            "activity": "Tillverkar zick-zack fjädrar, spiralfjädrar, spiralkabel, reglagewire m m",
            "capital": 50000,
            "key_personnel": {
                "name": "NOG Härensten",
                "position": "Verkst dir"
            },
            "establishment_year": 1937
        },
        "5": {
            "company_name": "MORGÅRDSHAMMAR AB",
            "pnr": "777 01",
            "address": "Smedjebacken 1, Fack",
            "phone_number": "0240-71100",
            "bank_details": {
                "bankgiro": "47-0425",
                "postgiro": "72287"
            },
            "activity": "Tillverkar o säljer maskiner o utrustningar för varm-o kallvalsverk, gruvor o anrikningsverk samt kugghjul o kuggväxlar m m. Säljer dotterbolagets, AB Arboga Mek Verkstad, tråddragmaski-ner, kantpressar, gradsaxar, rör- o stångdragbänkar samt spånkrossar. Driver även kraftverk o jordbruk",
            "employees": 600,
            "annual_turnover": 60000000,
            "capital": 11475000,
            "key_personnel": {
                "name": "Disp Hans Warrol",
                "position": "Verkst dir"
            },
            "establishment_year": 1856,
            "dotterbolag": "AB Arboga Mek Verkstad, Arboga"
        },
        "6": {
            "company_name": "MORINDERS VERKSTÄDER, AB",
            "pnr": "34100",
            "address": "Ljungby, Kånnav",
            "phone_number": "0372-100 98",
            "bank_details": {
                "bankgiro": "276-9743",
                "postgiro": "133295-6"
            },
            "activity": "Tillverkar o säljer balpressar, byggnadssmide o järnkonstruktioner. Legoarbeten",
            "employees": 15,
            "annual_turnover": 1400000,
            "capital": 10000,
            "key_personnel": {
                "name": "Ing Arne Morlinder",
                "position": "Verkst dir"
            },
            "establishment_year": 1965
        },
        "7": {
            "company_name": "MORISO HÄNDELS. & AGENTURFIRMA",
            "pnr": "430 62",
            "address": "Pixbo, Ängsv 19, Box 55",
            "phone_number": "031-730382",
            "bank_details": {
                "bankgiro": "43-9862",
                "postgiro": "424390"
            },
            "activity": "Säljer plastfolie, väv-plast, presenningsduk, jute o stoppningsmaterial",
            "owner_chef": "A Morichetto",
            "establishment_year": 1950
        },
        "8": {
            "company_name": "PALMGRENS ROR AB",
            "pnr": "601 02",
            "address": "Noirköping 1, Box 63, Hamng 2",
            "phone_number": "011-18 0175",
            "activity": "Rörentreprenörer, värme, vatten, avlopp, olja samt ånganläggningar",
            "capital": 30000,
            "filmatecknare": "B J Andersson",
            "establishment_year": 1871
        },
        "9": {
            "company_name": "NÄLDENS TRÄINDUSTRI, AB",
            "pnr": "830 44",
            "address": "Nälden, Box 60",
            "phone_number": "0640-200 24",
            "bank_details": {
                "bankgiro": "19-8942",
                "postgiro": "22428-7"
            },
            "activity": "Tillverkar specialsnickerier o inredningar för skolor, sjukhus, hotell m fi",
            "employees": 20,
            "annual_turnover": 2500000,
            "capital": 60000,
            "verkst_dir": "Fabr Lennart Hallström",
            "establishment_year": 1962
        },
        "10": {
            "company_name": "FINSPÅNGS GROVPLÅT AB",
            "pnr": "612 02",
            "address": "Finspång 2, Box 2033, Skäggebyv",
            "phone_number": "0122-150 30",
            "bank_details": {
                "bankgiro": "826-3147",
                "postgiro": "347521-7"
            },
            "activity": "Tillverkning av gummibandstransportörer, alla utföranden, kedjetransportörer, skruvtransportörer, stålkonstruktioner, stålformar o grussilos",
            "employees": 42,
            "annual_turnover": 3600000,
            "capital": 5000,
            "key_personnel": [
                {
                    "name": "Anders Sjöberg",
                    "position": "Styrelse"
                },
                {
                    "name": "fru Gunilla Sjöberg",
                    "position": "Styrelse"
                },
                {
                    "name": "Anders Sjöberg",
                    "position": "Verkst dir"
                }
            ],
            "establishment_year": 1956,
            "ombildat_till_aktiebolag": 1966
        },
        "11": {
            "company_name": "FINSPÅNGS PAPPERSFORAD. LING AB",
            "pnr": "612 00",
            "address": "Finspång, Rågången 13",
            "phone_number": "0122-502 68",
            "activity": "Tillverkar pappershylsor o räknemaskinsrullar",
            "verkst_dir": "Ake Wiklund",
            "establishment_year": 1962
        },
        "12": {
            "company_name": "KUNGSKVARNS KB",
            "pnr": "590 57",
            "address": "Malmslätt",
            "phone_number": "013-95100",
            "bank_details": {
                "bankgiro": "120-1391",
                "postgiro": "328126-8"
            },
            "activity": "Handel med spannmål, gödning o fodervaror",
            "employees": 10,
            "annual_turnover": 3500000,
            "chef": "Disp Ivar Månsson",
            "establishment_year": 1950
        },
        "13": {
            "company_name": "AUTOTEKNIK INSTRUMENT AB",
            "pnr": "411 08",
            "address": "Göteborg, Trädgårdsg 6",
            "phone_number": "031-17 88 55",
            "bank_details": {
                "bankgiro": "41-5320",
                "postgiro": "43027"
            },
            "activity": "Försäljning o service av industri- o bilinstrument. Drift-timräknare, varvräknare, hastighetsmätare etc",
            "employees": 13,
            "capital": 5000,
            "verkst_dir": "A Samuelson",
            "establishment_year": 1962
        },
        "14": {
            "company_name": "MIBIS",
            "pnr": "172 22",
            "address": "Sundbyberg 1, Box 55",
            "phone_number": "08-28 28 50",
            "bank_details": {
                "bankgiro": "33-0259",
                "postgiro": "55151"
            },
            "activity": "Tillverkning o försäljning av vattenreningsutrustning, avloppsreningsanläggningar, simbad, matarvatten o avhärdningsan-läggningar",
            "employees": 100,
            "annual_turnover": 16000000,
            "capital": 100000,
            "verkst_dir": "Göran Hultqvist",
            "establishment_year": 1908
        },
        "15": {
            "company_name": "PAPYRUS, AB",
            "pnr": "43121",
            "address": "Mölndal 1, Kvarnbyg 2-4, Box 9",
            "phone_number": "031-27 22 40",
            "bank_details": {
                "bankgiro": "160-8691",
                "postgiro": "11880-2"
            },
            "activity": "Pappers- o kartongtillverkning",
            "employees": 1200,
            "annual_turnover": 175000000,
            "capital": 48000000,
            "verkst_dir": "Sigge Rudengren",
            "establishment_year": 1895
        },
        "16": {
            "company_name": "PARADIS SÄNGAR och SÄNGKLÄDER, AB",
            "pnr": "402 71",
            "address": "Göteborg 8, Angpanneg",
            "phone_number": "031-22 80 80",
            "bank_details": {
                "bankgiro": "50-0009",
                "postgiro": "12396"
            },
            "activity": "Tillverkar Paradis sängar, madrasser, kuddar, täcken, sängöverkast. Säljer dessutom plädar o textilier",
            "avdelningskonton": "Stockholm C, Kungsg 53. Tel 08-20 28 97",
            "employees": 50,
            "annual_turnover": 7000000,
            "capital": 100000,
            "verkst_dir": "Ake Bourghardt",
            "civilekonom": "A-C Åkerhielm",
            "försäljn-chef": "Leif Johansson",
            "driftsing": "Gunnar Nyström",
            "establishment_year": 1881
        },
        "17": {
            "company_name": "HALTERMANN AB, JOHANN",
            "pnr": "21174",
            "address": "Malmö, Petroleumg 5",
            "phone_number": "040-18 12 20",
            "postgiro": "530576-8",
            "activity": "Partiförsäljning av mineraloljor o tjärdestillationspro-dukter",
            "capital": 500000,
            "styrelse": [
                {
                    "name": "Adv H Auerbach",
                    "position": "Ordf"
                },
                {
                    "name": "disp U Dunckel",
                    "position": "disp"
                },
                {
                    "name": "dir H Haltermann",
                    "position": "Verkst dir"
                }
            ],
            "verkst_dir": "G Lemke",
            "establishment_year": 1952
        },
        "18": {
            "company_name": "HALVARSSON, SKINNVARU AB BRÖDERNA",
            "pnr": "782 00",
            "address": "Malung, Box 56",
            "phone_number": "0280-125 05",
            "bank_details": {
                "bankgiro": "468-4668",
                "postgiro": "321794-7"
            },
            "activity": "Tillverkar skinnjackor, västar o motorkläder",
            "employees": 46,
            "annual_turnover": 2500000,
            "establishment_year": 1946
        }
    }
}