{
    "original": "FORSSBERG, AB S P\n\nPnr 615 00\n\nValdemars vik, Grannes v. Box 77.\n\nTel 0123-11110. Bankgiro 857-\n\n3255. Postgiro 123630-6. Tga\n\nForssbergsbolag\n\nVerksamhet: Tillverkar o säljer\n\nspånskivor\n\nVarunamn: Borgskivan\nAntal anstäUda: 85\nAktiekapital: 600 000\n\nVeikst dir: Disp Wollmar W:son\nHintze\n\nChef för spånskivefabriken: Ing\nKarl Lundberg\nEtableringsår: 1904.\n\nINDUSTRISKROT, AB\n\nPnr 232 00\n\nArlöv, Västkustv. Tel 040-43 03 11.\nPostgiro 535754-6\nEtableringsår: 1958\nSe vidare Trelleborgs Skrot AB.\n\nINDUSTRISMIDE, AB\n\nPnr 213 64\n\nMalmö, Emilstorpsg 27. Tel\n040-94 2130. Bankgiro 264-7493.\nPostgiro 246444-4\n\nVerksamhet: Tillverkar järn- o\nplåtkonstruktioner samt\nbyggnads-smide\n\nINDUSTRI-TEXTIL JOB AB\n\nPnr 51101\n\nKinna 1, Kasthallsv. Box 37. Tel\n0320-124 04, 101 25. Bankgiro\n436-2976. Postgiro 108585-1\nVerksamhet: Filterslangar,\nfilterdukar samt övriga industritextilier\nAntal anställda: 25\nÅrsomsättning: 2 000 000\nAktiekapital: 50 000\nVerkst din J O Bornefalk\nEtableringsår: 1963.\n\nINDUSTRI-TRANSMISSIONER\nAB\n\nPnr 265 01\n\nÅstorp 1, Box 20. Bang 11. Tel\n042-580 1 0, 581 20. Bankgiro\n671-4364. Postgiro 666770-3. Tga\nIndtrans. Telex 72433 MOVING S\nVerksamhet: Tillverkar, importerar\no säljer transmissionselement,\nStarlock låsbrickor samt Brano\nkuggstångsdomkrafter o spärrblock\nVarunamn: Starlock\nÅrsomsättning: 800 000\nAktiekapital: 5 000\nVerkst dir: Bengt Franzén\nEtableringsår: 1964.\n\nARN\n\nARKITEKT-KOPIA\nosten grankvist ab\n\nPnr 113 33\n\nStockholm, Eugeniav 51. Tel\n08-34 01 30, 63 73 90. Bankgiro\n56-4539. Postgiro 357811\nVerksamhet: Ljuskopior o\nritningstryck, reproduktion, foto\nAktiekapital: 25 000\nVerkst dir: Osten Grankvist\nEtableringsår: 1949.\n\nNÄSSJÖHOLM AB\n\nPnr 33101\n\nVärnamo 1, Box 31. Halmstadsv.\nTel 0370-117 20. Bankgiro\n141-8193. Postgiro 178700-1. Tga\nHol-mab. Telex 70068 att: Nässjöholm\nVerksamhet: Tillverkar\ndokumentportföljer, necessärer i läder o\nväv-buren plast samt necessärväskor\nm m i plast, aftonväskor. Svetsade\no sydda detaljer för industrin\nAntal anställda: 100\nAktiekapital: 150 000\nVerkst dir: Henric Andersson\nEtableringsår: 1936.\n\nL|ATORPS SNICKERIFABRIK\n\nPnr 340 20\n\nLiatorp, Postl750. Tel0476-20208.\n\nBankgiro 276-1567. Postgiro\n475791-0\n\nVerksamhet: Tillverkar ytterdörrar,\ngarageportar o vipportar\nAntal anställda: 8\nÅrsomsättning: 600 000\nChef: Edvin Åberg\nEtableringsår: 1954.\n\nLIBA, BIL- &amp;\nMOTORVERKSTADS AB\n\nPnr 25242\n\nHelsingborg, Angelholmsv 36. Tel\n042-1392 85. Bankgiro 864-1136.\nPostgiro 226690-6\nVerksamhet: Verkstadsservice för\ntunga fordon o marinmotorer\nVarunamn: Landi\n.Antal anställda: 26\nÅrsomsättning: 3 500000\nAktiekapital: 50 000\nVerkst dir: earl Hall\nEtableringsår: 1959.\n\nFEJMERT PATENT, AB\n\nPnr 61101\n\nNyköping 1, Box 110. Bergshammar.\nTel 0155-582 00. Postgiro 176555-1.\nTga Fejmert\n\nVerksamhet: Tillverkar o säljer\nOriginal Fejmert Aktivatorer,\nblandningsmaskiner för betong,\nmurbruk, asfalt, glastillverkning,\ngjuterisand m m, stationära o\ntransportabla uppfordringsverk\nDotterbolag: Oskarshamn.\nFejmert-Maskiner AB. Tel 0491-150 25\nAntal anställda: 50\nÅrsomsättning: 6 000 000\nAktiekapital: 600 000\nStyrelse: Civiling E v Fejmert,\ndisp Göran Andersson, revisor\nBirger Bergqvist\nVerkst dir: Göran Andersson\nEtableringsår: 1940.\n\nTÄRNSJO SÅGAKTIEBOLAG\n\nPnr 740 45\n\nTärnsjö. Tel 0292-502 47. Bankgiro\n81-2234. Postgiro 336159\nVerksamhet: Tillverkar o säljer sår\ngade o hyvlade trävaror\nAntal anställda: 30\nÅrsomsättning: 3 000 000\nAktiekapital: 74 000\nVerkst dir: Börje Bengtsson\nEtableringsår 1929.\n\nNYKVARNS BRUK, AB\n\nPnr 150 22\n\nNykvarn. Tel 0755-40280.\nBankgiro 700-1332. Postgiro 15284-3.\nTga Nykvarn, Södertälje.\n\nTelex 1258\n\nVerksamhet: Tillverkar post-,\nskriv-, tryck-, sulfit-, kraft-,\npås-o tapetpapper (wellpapper)\nAntal anställda: 300\nÅrsomsättning: 28 000 000\nAktiekapital: 1 200 000\nStyrelse: Tekn dr Marcus\nWallenberg (ordf), dir Einar Harald, disp\nSigge Rudengren\n\nVeikst dir Disp Sigge Rudengren\nEtableringsår: 1847\nOmbildat Ull aktiebolag 1924.\n\nNYKVARNS\nCEMENT-GJUTERI AB\n\nPnr 15022\n\nNykvarn. Tel 0755-409 05. Bankgiro\n232-3376. Postgiro 97590-4\nVerksamhet: Tillverkar o säljer\nF-iör, Alfa-rör, Beta-rör,\nDeltabrunnar\n\nAntal anställda: 30\nÅrsomsättning: 4 000 000\nAktiekapital: 300 000\nVerkst dir: Sture Waldekrantz\nEtableringsår 1917.\n\nDALSTORPS TRÄ AB\n\nPnr 510 95\n\nDalstorp, Box 27. Tel\n0321-600 78. Bankgiro 84-0639.\nPostgiro 322376\n\nVerksamhet: Säljer sågade o\nhyvlade trävaror\nAntal anställda: 20\nÅrsomsättning: 2 000 000\nAktiekapital: 45 000\nVerkst dir: Sven Johansson\nEtableringsår: 1944.\n\nSANDELIN AB, 0 E\n\nPnr 100 27\n\nStockholm 48, Stenkullav 7. Fack.\nTel 08-56 02 00, 56 02 53. Bankgiro\n17-4820. Postgiro 404900.\nTga Olsandelin.\nTelex 17074 OLSAND S\nVerksamhet: Säljer maskiner o\nförnödenheter för pappers-o\ncellulosaindustrin\n\nAntal anstäUda: 4\nÅrsomsättning: 200 000\nAktiekapital: 5 000\nStyrelse: Civiling Olle Sandelin\n(ordf), fru Sonja Sandelin\nVerkst dir: Olle Sandelin\nEtableringsår: 1966.",
    "structured": {
        "1": {
            "company_name": "FORSSBERG, AB",
            "pnr": "615 00",
            "address": "Valdemars vik, Grannes v. Box 77.",
            "phone_number": "0123-11110",
            "bank_details": {
                "bankgiro": "857-3255",
                "postgiro": "123630-6"
            },
            "activity": "Tillverkar o säljer spånskivor",
            "employees": 85,
            "capital": 600000,
            "key_personnel": [
                {
                    "name": "Disp Wollmar W:son Hintze",
                    "position": "Veikst dir"
                },
                {
                    "name": "Ing Karl Lundberg",
                    "position": "Chef för spånskivefabriken"
                }
            ],
            "establishment_year": 1904
        },
        "2": {
            "company_name": "INDUSTRISKROT, AB",
            "pnr": "232 00",
            "address": "Arlöv, Västkustv.",
            "phone_number": "040-43 03 11",
            "postgiro": "535754-6",
            "establishment_year": 1958
        },
        "3": {
            "company_name": "INDUSTRI-TEXTIL JOB AB",
            "pnr": "51101",
            "address": "Kinna 1, Kasthallsv. Box 37.",
            "phone_number": "0320-124 04, 101 25",
            "bank_details": {
                "bankgiro": "436-2976",
                "postgiro": "108585-1"
            },
            "activity": "Filterslangar, filterdukar samt övriga industritextilier",
            "employees": 25,
            "annual_turnover": 2000000,
            "capital": 50000,
            "key_personnel": [
                {
                    "name": "J O Bornefalk",
                    "position": "Verkst din"
                }
            ],
            "establishment_year": 1963
        },
        "4": {
            "company_name": "INDUSTRI-TRANSMISSIONER AB",
            "pnr": "265 01",
            "address": "Åstorp 1, Box 20. Bang 11.",
            "phone_number": "042-580 1 0, 581 20",
            "bank_details": {
                "bankgiro": "671-4364",
                "postgiro": "666770-3"
            },
            "activity": "Tillverkar, importerar o säljer transmissionselement, Starlock låsbrickor samt Brano kuggstångsdomkrafter o spärrblock",
            "annual_turnover": 800000,
            "capital": 5000,
            "key_personnel": [
                {
                    "name": "Bengt Franzén",
                    "position": "Verkst dir"
                }
            ],
            "establishment_year": 1964
        },
        "5": {
            "company_name": "ARKITEKT-KOPIA osten grankvist ab",
            "pnr": "113 33",
            "address": "Stockholm, Eugeniav 51.",
            "phone_number": "08-34 01 30, 63 73 90",
            "bank_details": {
                "bankgiro": "56-4539",
                "postgiro": "357811"
            },
            "activity": "Ljuskopior o ritningstryck, reproduktion, foto",
            "capital": 25000,
            "key_personnel": [
                {
                    "name": "Osten Grankvist",
                    "position": "Verkst dir"
                }
            ],
            "establishment_year": 1949
        },
        "6": {
            "company_name": "NÄSSJÖHOLM AB",
            "pnr": "33101",
            "address": "Värnamo 1, Box 31. Halmstadsv.",
            "phone_number": "0370-117 20",
            "bank_details": {
                "bankgiro": "141-8193",
                "postgiro": "178700-1"
            },
            "activity": "Tillverkar dokumentportföljer, necessärer i läder o väv-buren plast samt necessärväskor m m i plast, aftonväskor. Svetsade o sydda detaljer för industrin",
            "employees": 100,
            "capital": 150000,
            "key_personnel": [
                {
                    "name": "Henric Andersson",
                    "position": "Verkst dir"
                }
            ],
            "establishment_year": 1936
        },
        "7": {
            "company_name": "L|ATORPS SNICKERIFABRIK",
            "pnr": "340 20",
            "address": "Liatorp, Postl750",
            "phone_number": "0476-20208",
            "bank_details": {
                "bankgiro": "276-1567",
                "postgiro": "475791-0"
            },
            "activity": "Tillverkar ytterdörrar, garageportar o vipportar",
            "employees": 8,
            "annual_turnover": 600000,
            "key_personnel": [
                {
                    "name": "Edvin Åberg",
                    "position": "Chef"
                }
            ],
            "establishment_year": 1954
        },
        "8": {
            "company_name": "LIBA, BIL- & MOTORVERKSTADS AB",
            "pnr": "25242",
            "address": "Helsingborg, Angelholmsv 36",
            "phone_number": "042-1392 85",
            "bank_details": {
                "bankgiro": "864-1136",
                "postgiro": "226690-6"
            },
            "activity": "Verkstadsservice för tunga fordon o marinmotorer",
            "employees": 26,
            "annual_turnover": 3500000,
            "capital": 50000,
            "key_personnel": [
                {
                    "name": "earl Hall",
                    "position": "Verkst dir"
                }
            ],
            "establishment_year": 1959
        },
        "9": {
            "company_name": "FEJMERT PATENT, AB",
            "pnr": "61101",
            "address": "Nyköping 1, Box 110. Bergshammar",
            "phone_number": "0155-582 00",
            "postgiro": "176555-1",
            "activity": "Tillverkar o säljer Original Fejmert Aktivatorer, blandningsmaskiner för betong, murbruk, asfalt, glastillverkning, gjuterisand m m, stationära o transportabla uppfordringsverk",
            "employees": 50,
            "annual_turnover": 6000000,
            "capital": 600000,
            "key_personnel": [
                {
                    "name": "Göran Andersson",
                    "position": "Verkst dir"
                }
            ],
            "establishment_year": 1940
        },
        "10": {
            "company_name": "TÄRNSJO SÅGAKTIEBOLAG",
            "pnr": "740 45",
            "address": "Tärnsjö",
            "phone_number": "0292-502 47",
            "bank_details": {
                "bankgiro": "81-2234"
            },
            "activity": "Tillverkar o säljer sågade o hyvlade trävaror",
            "employees": 30,
            "annual_turnover": 3000000,
            "capital": 74000,
            "key_personnel": [
                {
                    "name": "Börje Bengtsson",
                    "position": "Verkst dir"
                }
            ],
            "establishment_year": 1929
        },
        "11": {
            "company_name": "NYKVARNS BRUK, AB",
            "pnr": "150 22",
            "address": "Nykvarn",
            "phone_number": "0755-40280",
            "bank_details": {
                "bankgiro": "700-1332",
                "postgiro": "15284-3"
            },
            "activity": "Tillverkar post-, skriv-, tryck-, sulfit-, kraft-, pås-o tapetpapper (wellpapper)",
            "employees": 300,
            "annual_turnover": 28000000,
            "capital": 1200000,
            "key_personnel": [
                {
                    "name": "Marcus Wallenberg",
                    "position": "Styrelse (ordf)"
                },
                {
                    "name": "Einar Harald",
                    "position": "Direktör"
                },
                {
                    "name": "Sigge Rudengren",
                    "position": "Disp"
                }
            ],
            "establishment_year": 1847
        },
        "12": {
            "company_name": "NYKVARNS CEMENT-GJUTERI AB",
            "pnr": "15022",
            "address": "Nykvarn",
            "phone_number": "0755-409 05",
            "bank_details": {
                "bankgiro": "232-3376",
                "postgiro": "97590-4"
            },
            "activity": "Tillverkar o säljer F-iör, Alfa-rör, Beta-rör, Deltabrunnar",
            "employees": 30,
            "annual_turnover": 4000000,
            "capital": 300000,
            "key_personnel": [
                {
                    "name": "Sture Waldekrantz",
                    "position": "Verkst dir"
                }
            ],
            "establishment_year": 1917
        },
        "13": {
            "company_name": "DALSTORPS TRÄ AB",
            "pnr": "510 95",
            "address": "Dalstorp, Box 27",
            "phone_number": "0321-600 78",
            "bank_details": {
                "bankgiro": "84-0639",
                "postgiro": "322376"
            },
            "activity": "Säljer sågade o hyvlade trävaror",
            "employees": 20,
            "annual_turnover": 2000000,
            "capital": 45000,
            "key_personnel": [
                {
                    "name": "Sven Johansson",
                    "position": "Verkst dir"
                }
            ],
            "establishment_year": 1944
        },
        "14": {
            "company_name": "SANDELIN AB, 0 E",
            "pnr": "100 27",
            "address": "Stockholm 48, Stenkullav 7",
            "phone_number": "08-56 02 00, 56 02 53",
            "bank_details": {
                "bankgiro": "17-4820",
                "postgiro": "404900"
            },
            "activity": "Säljer maskiner o förnödenheter för pappers-o cellulosaindustrin",
            "employees": 4,
            "annual_turnover": 200000,
            "capital": 5000,
            "key_personnel": [
                {
                    "name": "Olle Sandelin",
                    "position": "Verkst dir"
                }
            ],
            "establishment_year": 1966
        }
    }
}