{
    "original": "AHRNEBERGS AB\n\nPnr 790 30\n\nInsjön. Tel 0247-401 32, 401 35.\nBankgiro 79-5902. Postgiro 136420\nVerksamhet: Tillverkar furumöbler\no presentartiklar\nAntal anställda: 70\nÅrsomsättning: 5 000 000\nAktiekapital: 200 000\nVerkst dir: Disp Olle Ahrneberg\nEtableringsår: 1932.\n\nTRADINCO, AB\n\nPnr 111 56\n\nStockholm C. Kungsg 33. Tel\n08-101400, 101440. Telex 10753.\nTga Tradincobol\nAktiekapital: 30 000\nVerkst dir: Jur dr P Liska\nEtableringsår: 1947.\n\nGOT\n\nGOTEBORGS\nHARTSOLJEFÄRG FABRIK AB\n\nPnr 510 80\n\nTranemo. Tel 0325-707 70.\nBankgiro 55-3208. Postgiro 40696\nVerksamhet: Försäljning av färger\ngenom lagerbutiker\nChef: Disp Ernst Sandström\nEtableringsår: 1878.\n\nGOTEBORGS HATT.\nFABRIK, AB\n\nPnr 416 63\n\nGöteborg, N Gubberog 30. Tel\n031-19 70 85. Bankgiro 847-9875.\nPostgiro 42522-3. Tga Göteborgshatt\nVerksamhet: Tillverkar damhattar\no mössor samt pälshattar\nAvdelningskontor: Stockholm C,\nKungsg 53. Tel 08-11 96 15\nAntal anställda: 29\nAktiekapital: 360 000\nVerkst dir: Rune Johansson\nEtableringsår: 1918.\n\nGOTEBORGS INDUSTRI.\nTILLBEHOR\n\nPnr 400 35\n\nGöteborg 46, Inlandsg 34. Box\n46027. Tel 031-76 08 47, 7618 57.\nBankgiro 337-6498. Postgiro 40392\nVerksamhet: Säljer gummislang\nalla typer, gummiduk,\ngummipackning, gummimattor, brandslang,\ntrassel o putstrasor, arbetskläder,\nregnkläder o arbetshandskar\nÅrsomsättning: 700 000\nÄgare o chef: Olle Blidnert\nEtableringsår: 1959.\n\nGOTEBORGS INTECKNINGS\nGARANTI AB\n\nPnr 403 17\n\nGöteborg 2, V Hamng 10. Box 2503.\nTel 031-17 07 50. Bankgiro 42-0063.\nPostgiro 46788\n\nVerksamhet: Lämnar o förmedlar\nlån mot inteckning i fast egendom\neller tomträtt samt lämnar\nbygg-nadskreditiv, ombesörjer\nfastighetsförvaltning o förmedlar\nfastighet sförsälj ning ar\nAntal anställda: 31\nAktiekapital: 17 000000\nStyrelse: Dir Magnus Pontin (ordf),\ndir Louis Campanello, dir Erik\nJohannesson, bankdir Bert\nLindström, bankdir Arne Nilsson,\nbankdir Sven Raab, dir Axel Ros, ark\nJan Steen\n\nVerkst dir: Arne Nilsson\nEtableringsår: 1869\nDotterbolag till Göteborgs Bank.\n\nGOTEBORGS KARTONG.\nFABRIK, AB\n\nPnr 442 00\n\nKungälv, Fabriksg 6. Box 49. Tel\n0303-11440. Bankgiro 847-8323.\nPostgiro 244854-6. Tga Gekamill\nVerksamhet: Tillverkar emballage\ni papp o kartong (ej wellpapp) samt\nresningsmaskiner för emballage i\npapp. Stansar tjockare papp o\nma-sonit, vacuumformar emballage o\ninreden i PVC o polystyren\nVarunamn: Gepac\nAntal anställda: 30\nÅrsomsättning: 5 500 000\nAktiekapital: 200 000\n\nVerkst dir: Rolf Samuelson\nProduktionschef: Ing Lars-Hugo\n\nOlsson\n\nUtveckling: Curt Anderson\nEtableringsår: 1946\nOmbildat till aktiebolag 1956.\n\nGOTEBORGS KEMISK.TEK.\nNISKA FABRIK VASCO AB\n\nPnr 402 71\n\nGöteborg 8, ö Hamng 4. Box 8838.\nTel 031-17 0185. Tga\nVascofabri-ken\n\nVerksamhet: Tillverkar\nindustriförnödenheter, rengöringsmedel,\nkosmetiska o hygieniska preparat\nAntal anstäUda: 25\nÅrsomsättning: 2 000 000\nAktiekapital: 30 000\nÄgare o chefer: Ing Ragnar\nTörnros, ing Sidney Törnros\nEtableringsår: 1907.\n\nMAR\n\nMARI ESTROMS FABRIK AB\n\nPnr 330 30\n\nGnosjö. Tel 037 0-910 16. Postgiro\n28327-5\n\nVerksamhet: Tillverkar spik, stift,\nkrampor, saxsprintar,\nmutterbrickor, karosseribrickor m m\nAntal anställda: 10\nChef: Fabr Sixten Larsson\nEtableringsår: 1928.\n\nMARKNADSSOCIOLOGEN AB\n\nPnr 17165\n\nSolna, Bagartorpsringen 51. Tel\n08-85 0170. Telex 10896\nVerksamhet: MEM-modellen,\neffektmätning, mediaval Orvesto-rapporten\nÅrsomsättning: 2 000 000\nAktiekapital: 5 000\nVerkst dir: Ingemar Lindberg\nEtableringsår: 1964.\n\nFÖRENADE WELL AB\n\nPnr 24100\n\nEslöv, Verkstadsv 18. Fack. Tel\n0413-139 10. Bankgiro 651-5621.\nPostgiro 436271-1. Tga Wellpack.\nTelex 32397\n\nVerksamhet: Tillverkar o\nkonverterar wellpapp i Eslöv, Billingsfors\no Gävle\n\nFörsäljningskontor: Eslöv,\nStockholm, Göteborg, Gävle o Motala\nAntal anställda: 400\nÅrsomsättning: 53000 000\nAktiekapital: 6 600 000\nVerkst dir: Ewe Wenngren\nEtableringsàr: 1962.\n\nFÖRENADE VVS-KONSULTER\nAB\n\nPnr 11435\n\nStockholm, Riddarg 12. Tel\n08-24 22 20. Bankgiro 48-2119.\nPostgiro 52308\n\nVerksamhet: Rådgivande\ningenjörer för värme, ånga o ventilation\nAntal anställda: 53\nÅrsomsättning: 3 500 000\nAktiekapital: 225 000\nVerkst dir: Gustaf Rubensson\nEtableringsàr 1960.\n\nSTÄDKOMPANIET AB\n\nPnr 11143\n\nStockholm, Norrlands g 18. Tel\n08-1189 00. Bankgiro 170-1499.\nPostgiro 150310-1\n\nVeiksamhet: Entreprenadstädning\nÅrsomsättning: 1 900 000\nAktiekapital: 100 000\nStyrelseordf: Dir Louis R Angleryd\nVeikst dir: Bruno H Linder\nEtableringsår: 1936\nDotterbolag till AB Städcentralen.\n\nSTÄDMAN, AB\n\nPnr 11452\n\nStockholm, Skepparg 27. Tel\n08-63 58 00. Bankgiro 726-6000.\nPostgiro 655551-0\n\nVerksamhet: Kontorsstädning,\nindustristädning o flyttstädning\nVerkst dir: Ake von der Burg.\n\nSTÄDNINGSKÅREN AB\n\nPnr111 23\n\nStockholm, Barnhusg 3. Tel\n08-24 68 10. Bankgiro 484-4130.\nPostgiro 552716-3\n\nVerksamhet: pastighetsstädning\n.Antal anställda: 650\nÅrsomsättning: 11000 000\nAktiekapital: 75 000\nStyrelse: Dir Gustaf Sandström\n(ordf), dir Sven Sandberg, dir Helge\nAsplund\n\nVerkst dir: Helge Asplund\nDir:n Sven Sandberg, Gustaf\nSandström\n\nEtableringsår: 1956.\n\nSUNDMAN &amp; STROMBERG, AB\n\nPnr 12634\n\nHägersten, Tegelbruksv 28. Tel\n08-45 09 19, 45 15 59. Bankgiro\n744-4342. Postgiro 257580-1\nVerksamhet: Tillverkar press\nverktyg o mindre experimentmaskiner\nVerkst dir: G Strömberg\nEtableringsår: 1951.\n\nPRESSACO AB\n\nPnr 415 02\n\nGöteborg, Artillerig 29. Tel\n031-25 35 50, 25 7150. Bankgiro\n654-3748. Postgiro 721650-0\nVerksamhet: Utför\npressningsarbeten. Tillverkar verktyg\nAntal anställda: 15\nÅrsomsättning: 1400 000\nVerkst dir: Disp Torsten Thonfors\nEtableringsår: 1938.\n\nCARRY BROKERS AB\n\nPnr 104 35\n\nStockholm 23, Box 23141.\nDanne-morag 4. Tel 08-34 90 60. Bankgiro\n604-3319. Postgiro 647200-5.\nTga Carrybrokers. Telex 19919\nVerksamhet: Representant för\nlivsmedels- o konfektyrfabrikanter\nAntal anstäUda: 30\nAktiekapital: 50000\nVerkst dir: John Norelid\nEtableringsår: 1964.\n\nCARSTENS SPECIAL.\nMASKINER, AB ERNST\n\nPnr 55102\n\nJönköping 1, Box 441. Tel\n036-725 10. Bankgiro 835-7394.\nPostgiro 262648-9. Tga\nCarstens-maskin. Telex 70038\nVerksamhet: Säljer\nspecialmaskiner för träbearbetning\nAntal anstäUda; 35\nAktiekapital: 100 000\nVerkst dir: Ernst Carstens\nEtableringsår. 1954.",
    "structured": {
        "1": {
            "company_name": "AHRNEBERGS AB",
            "pnr": "790 30",
            "address": "Insjön",
            "phone_number": "0247-401 32, 401 35",
            "bank_details": {
                "bankgiro": "79-5902",
                "postgiro": "136420"
            },
            "activity": "Tillverkar furumöbler o presentartiklar",
            "employees": 70,
            "annual_turnover": 5000000,
            "capital": 200000,
            "key_personnel": {
                "name": "Disp Olle Ahrneberg"
            },
            "establishment_year": 1932
        },
        "2": {
            "company_name": "TRADINCO, AB",
            "pnr": "111 56",
            "address": "Stockholm C. Kungsg 33",
            "phone_number": "08-101400, 101440",
            "bank_details": null,
            "activity": null,
            "annual_turnover": null,
            "capital": 30000,
            "key_personnel": {
                "name": "Jur dr P Liska"
            },
            "establishment_year": 1947
        },
        "3": {
            "company_name": "GOTEBORGS HARTSOLJEFÄRG FABRIK AB",
            "pnr": "510 80",
            "address": "Tranemo",
            "phone_number": "0325-707 70",
            "bank_details": {
                "bankgiro": "55-3208",
                "postgiro": "40696"
            },
            "activity": "Försäljning av färger genom lagerbutiker",
            "employees": null,
            "annual_turnover": null,
            "capital": null,
            "key_personnel": {
                "name": "Disp Ernst Sandström"
            },
            "establishment_year": 1878
        },
        "4": {
            "company_name": "GOTEBORGS HATT. FABRIK, AB",
            "pnr": "416 63",
            "address": "Göteborg, N Gubberog 30",
            "phone_number": "031-19 70 85",
            "bank_details": {
                "bankgiro": "847-9875",
                "postgiro": "42522-3"
            },
            "activity": "Tillverkar damhattar o mössor samt pälshattar",
            "employees": 29,
            "annual_turnover": null,
            "capital": 360000,
            "key_personnel": {
                "name": "Rune Johansson"
            },
            "establishment_year": 1918
        },
        "5": {
            "company_name": "GOTEBORGS INDUSTRI.TILLBEHOR",
            "pnr": "400 35",
            "address": "Göteborg 46, Inlandsg 34. Box 46027",
            "phone_number": "031-76 08 47, 7618 57",
            "bank_details": {
                "bankgiro": "337-6498",
                "postgiro": "40392"
            },
            "activity": "Säljer gummislang alla typer, gummiduk, gummipackning, gummimattor, brandslang, trassel o putstrasor, arbetskläder, regnkläder o arbetshandskar",
            "annual_turnover": 700000,
            "capital": null,
            "key_personnel": {
                "name": "Olle Blidnert"
            },
            "establishment_year": 1959
        },
        "6": {
            "company_name": "GOTEBORGS INTECKNINGS GARANTI AB",
            "pnr": "403 17",
            "address": "Göteborg 2, V Hamng 10. Box 2503",
            "phone_number": "031-17 07 50",
            "bank_details": {
                "bankgiro": "42-0063",
                "postgiro": "46788"
            },
            "activity": "Lämnar o förmedlar lån mot inteckning i fast egendom eller tomträtt samt lämnar bygg-nadskreditiv, ombesörjer fastighetsförvaltning o förmedlar fastighet sförsälj ning ar",
            "employees": 31,
            "capital": 17000000,
            "key_personnel": {
                "name": "Arne Nilsson"
            },
            "establishment_year": 1869
        },
        "7": {
            "company_name": "GOTEBORGS KARTONG. FABRIK, AB",
            "pnr": "442 00",
            "address": "Kungälv, Fabriksg 6. Box 49",
            "phone_number": "0303-11440",
            "bank_details": {
                "bankgiro": "847-8323",
                "postgiro": "244854-6"
            },
            "activity": "Tillverkar emballage i papp o kartong (ej wellpapp) samt resningsmaskiner för emballage i papp. Stansar tjockare papp o masonit, vacuumformar emballage o inreden i PVC o polystyren",
            "employees": 30,
            "annual_turnover": 5500000,
            "capital": 200000,
            "key_personnel": {
                "name": "Rolf Samuelson",
                "position": "Produktionschef: Ing Lars-Hugo"
            },
            "establishment_year": 1946
        },
        "8": {
            "company_name": "GOTEBORGS KEMISK.TEK. NISKA FABRIK VASCO AB",
            "pnr": "402 71",
            "address": "Göteborg 8, ö Hamng 4. Box 8838",
            "phone_number": "031-17 0185",
            "bank_details": null,
            "activity": "Tillverkar industriförnödenheter, rengöringsmedel, kosmetiska o hygieniska preparat",
            "employees": 25,
            "annual_turnover": 2000000,
            "capital": 30000,
            "key_personnel": {
                "name": "Ing Ragnar Törnros"
            },
            "establishment_year": 1907
        },
        "9": {
            "company_name": "MARI ESTROMS FABRIK AB",
            "pnr": "330 30",
            "address": "Gnosjö",
            "phone_number": "037 0-910 16",
            "bank_details": null,
            "activity": "Tillverkar spik, stift, krampor, saxsprintar, mutterbrickor, karosseribrickor m m",
            "employees": 10,
            "key_personnel": {
                "name": "Fabr Sixten Larsson"
            },
            "establishment_year": 1928
        },
        "10": {
            "company_name": "MARKNADSSOCIOLOGEN AB",
            "pnr": "17165",
            "address": "Solna, Bagartorpsringen 51",
            "phone_number": "08-85 0170",
            "bank_details": null,
            "activity": "MEM-modellen, effektmätning, mediaval Orvesto-rapporten",
            "annual_turnover": 2000000,
            "capital": 5000,
            "key_personnel": {
                "name": "Ingemar Lindberg"
            },
            "establishment_year": 1964
        },
        "11": {
            "company_name": "FÖRENADE WELL AB",
            "pnr": "24100",
            "address": "Eslöv, Verkstadsv 18. Fack",
            "phone_number": "0413-139 10",
            "bank_details": {
                "bankgiro": "651-5621",
                "postgiro": "436271-1"
            },
            "activity": "Tillverkar o konverterar wellpapp i Eslöv, Billingsfors o Gävle",
            "employees": 400,
            "annual_turnover": 53000000,
            "capital": 6600000,
            "key_personnel": {
                "name": "Ewe Wenngren"
            },
            "establishment_year": 1962
        },
        "12": {
            "company_name": "FÖRENADE VVS-KONSULTER AB",
            "pnr": "11435",
            "address": "Stockholm, Riddarg 12",
            "phone_number": "08-24 22 20",
            "bank_details": {
                "bankgiro": "48-2119",
                "postgiro": "52308"
            },
            "activity": "Rådgivande ingenjörer för värme, ånga o ventilation",
            "employees": 53,
            "annual_turnover": 3500000,
            "capital": 225000,
            "key_personnel": {
                "name": "Gustaf Rubensson"
            },
            "establishment_year": 1960
        },
        "13": {
            "company_name": "STÄDKOMPANIET AB",
            "pnr": "11143",
            "address": "Stockholm, Norrlands g 18",
            "phone_number": "08-1189 00",
            "bank_details": {
                "bankgiro": "170-1499",
                "postgiro": "150310-1"
            },
            "activity": "Entreprenadstädning",
            "annual_turnover": 1900000,
            "capital": 100000,
            "key_personnel": {
                "name": "Bruno H Linder"
            },
            "establishment_year": 1936
        },
        "14": {
            "company_name": "STÄDMAN, AB",
            "pnr": "11452",
            "address": "Stockholm, Skepparg 27",
            "phone_number": "08-63 58 00",
            "bank_details": {
                "bankgiro": "726-6000",
                "postgiro": "655551-0"
            },
            "activity": "Kontorsstädning, industristädning o flyttstädning",
            "key_personnel": {
                "name": "Ake von der Burg"
            },
            "establishment_year": null
        },
        "15": {
            "company_name": "STÄDNINGSKÅREN AB",
            "pnr": "111 23",
            "address": "Stockholm, Barnhusg 3",
            "phone_number": "08-24 68 10",
            "bank_details": {
                "bankgiro": "484-4130",
                "postgiro": "552716-3"
            },
            "activity": "Pastighetsstädning",
            "employees": 650,
            "annual_turnover": 11000000,
            "capital": 75000,
            "key_personnel": {
                "name": "Sven Sandberg, Gustaf Sandström"
            },
            "establishment_year": 1956
        },
        "16": {
            "company_name": "SUNDMAN & STROMBERG, AB",
            "pnr": "12634",
            "address": "Hägersten, Tegelbruksv 28",
            "phone_number": "08-45 09 19, 45 15 59",
            "bank_details": {
                "bankgiro": "744-4342",
                "postgiro": "257580-1"
            },
            "activity": "Tillverkar press verktyg o mindre experimentmaskiner",
            "key_personnel": {
                "name": "G Strömberg"
            },
            "establishment_year": 1951
        },
        "17": {
            "company_name": "PRESSACO AB",
            "pnr": "415 02",
            "address": "Göteborg, Artillerig 29",
            "phone_number": "031-25 35 50, 25 7150",
            "bank_details": {
                "bankgiro": "654-3748",
                "postgiro": "721650-0"
            },
            "activity": "Utför pressningsarbeten. Tillverkar verktyg",
            "employees": 15,
            "annual_turnover": 1400000,
            "key_personnel": {
                "name": "Disp Torsten Thonfors"
            },
            "establishment_year": 1938
        },
        "18": {
            "company_name": "CARRY BROKERS AB",
            "pnr": "104 35",
            "address": "Stockholm 23, Box 23141. Dannemorag 4",
            "phone_number": "08-34 90 60",
            "bank_details": {
                "bankgiro": "604-3319",
                "postgiro": "647200-5"
            },
            "activity": "Representant för livsmedels- o konfektyrfabrikanter",
            "employees": 30,
            "capital": 50000,
            "key_personnel": {
                "name": "John Norelid"
            },
            "establishment_year": 1964
        },
        "19": {
            "company_name": "CARSTENS SPECIAL. MASKINER, AB ERNST",
            "pnr": "55102",
            "address": "Jönköping 1, Box 441",
            "phone_number": "036-725 10",
            "bank_details": {
                "bankgiro": "835-7394",
                "postgiro": "262648-9"
            },
            "activity": "Säljer specialmaskiner för träbearbetning",
            "employees": 35,
            "capital": 100000,
            "key_personnel": {
                "name": "Ernst Carstens"
            },
            "establishment_year": 1954
        }
    }
}