{
    "original": "VICKERS, SPERRY RAND AB\n\nPnr 172 23\n\nSundbyberg 1, Box 89. Tel\n08-98 02 50. Telex 10050 VICKERS S\nVeiksamhet: Säljer industriell,\nmobil o marin hydraulik\nVarunamn: Vickers\nChef: Dir Bo F Flodman\nSe vidare Speny Rand AB.\n\nWICKMAN &amp; SKOLDHAGEN\nMASKIN AB\n\nPnr 16135\n\nBromma, Drottningsholmsv 284. Tel\n08-25 29 50. Bankgiro 560-5548.\nPostgiro 156890-6. Tga Wickskold\nVerksamhet: Tillverkar o säljer\ntransportanordningar,\ngaffel-staplare o strömtillförselutrustning\nVarunamn: WI-HAG\nChef: Ing Ernst Eng\nEtableringsån 1951.\n\nJANE-LIST AB\n\nPnr 250 07\n\nHelsingborg 7, Rundgången, Berga\nIndustriområde. Box 7043. Tel\n042-14 44 70. Bankgiro 437-8220.\nPostgiro 342522-0\n\nVerksamhet: Tillverkar lister i\nolika utförande o av såväl svenska\nsom utländska träslag, även målade\no laserade\nAntal anställda: 60\nÅrsomsättning: 7 000000\nAktiekapital: 225 000\nVerkst dir: Fabr Ragnar Bengtsson\nEtableringsår: 1949.\n\nJANSSON, JANSON, JANSOHN\n\nJANSSON &amp; CO BYGGNADS AB\n\nPnr 35103\n\nVäxjö 1, Hjalmar Petris v 30. Box\n50. Tel 0470-231 40. Bankgiro\n14-6316. Postgiro 297216\nVerksamhet: Husbyggnad o\nanläggningsarbeten\nAntal anställda: 60\nÅrsomsättning: 6 000 000\nAktiekapital: 250 000\nVerkst dir: Ing Alvar Jonsson\nEtableringsår 1916.\n\nKORVBRUDS-BAGARN AB\n\nPnr 70012\n\n\"Örebro 12, Kyrkv 46. Box 12024.\nTel 019-23 40 10. Bankgiro\n495-5597. Postgiro 471093-5\nVerksamhet: Tillverkar korvbröd o\nhamburgarebröd för korvhandeln o\nbutikskedjor\nAntal anställda: 54\nÅrsomsättning: 7 000 000\nAktiekapital: 200 000\nVerkst din Henry Jansson\nKamrer: Hans Andersson\nProduktionschef: Kjell Jonsson\nEtableringsår: 1957.\n\nBERLINGS GRAFISKA AB\n\nPnr 22104\n\nLund 1, Box 1035. Stora\nGråbrö-dersg 17 B. Tel 046-117240.\nBankgiro 660-7865. Postgiro 30495-6.\nTga Berlings\n\nVerksamhet: Säljer\nboktryckerimaterial, stil, mässingslinjer,\ngrafiska hjälpmaskiner, sättmatriser o\noffsettryckpressar, reproutrustning\nFörsäljningskontor: 113 47\nStockholm, Ynglingag 19. Tel 08-340135.\nTga Berlinggrafiska\nAntal anställda: 6\nAktiekapital: 10 000\nDir: Arne Andersson\nEtableringsår: 1962\nFörsäljningsbolag till Berlingska\nStilgjuteriet.\n\nBERLINGSKA BOKTRYCKERI &amp;\nSTILGJUTERI AB\n\nPnr 22104\n\nLund 1, Box 1035. Stora\nGråbrö-dersg 17 B. Tel 046-12 42 40\n(bok-tiyckeri), 11 72 40(stilgjuteri).\nBankgiro 660-6172. Postgiro\n30490-7. Tga Berlings\nVeiksamhet: Tryckeriet utför\nbok-o offsettryck samt\nbokbinderiarbeten av affärstryck, böcker o\ntidskrifter. Specialitet: vetenskapligt\ntryck, skolböcker, komplicerad\nsättning, flerfärgs offsettryck.\nStilgjuteriet tillverkar\nboktrycksstilar, lågmaterial, mässingslinjer\nAntal anställda: 170\nAktiekapital: 600 000\nVerkst dir: Arne Andersson\nEtableringsår: 1668 (1745)\nOmbildat till aktiebolag 1888.\n\nBERLO FABRIKS AB\n\nPnr 330 20\n\nAnderstorp, AUég 6. Box 71. Tel\n0371-154 72, 158 82. Bankgiro\n48-8013. Postgiro 470700\nVerksamhet: Handväskor,\nportföljer o smålädervaror\nAntal anställda: 10\nÅrsomsättning: 1200 000\nAktiekapital: 100 000\nVerkst dir: Erik Eriksson\nEtableringsår: 1946.\n\nFAGERSTA BIL AB\n\nPnr 773 00\n\nFagersta, Brinellv 107. Tel\n0223-129 90. Bankgiro 60-6990.\nPost-giro 546624\n\nVerksamhet: Auktoriserad\nGM-återförsäljare\n\nÅrsomsättning: Se Köpings Bil AB\nVerkst din Håkan Arnerud\nEtableringsår: 1959.\n\nJUNG A VERKSTÄDER AB\n\nPnr 534 01\n\nVara 1. Jung. Box 25. Tel\n0512-22180. Bankgiro 89-4454. Postgiro\n265793. Tga Reductor\nVerksamhet: Tillverkar Junga o\nCylinda tvättmaskiner\nAntal anställda: 200\nÅrsomsättning: 25 000 000\nAktiekapital: 300 000\nVerkst dir: Fabr K E Andersson\nEtableringsår: 1954.\n\nHJO MEKANISKA VERKSTAD\n\nPnr 544 00\n\nHjo, Tel0503-lll 00. Bankgiro 21-\n\n6437. Postgiro 33229. Tga\nHjome-kaniska. Telex 5064 HJOMEK S\nVeiksamhet: Tillverkar radiatorer,\nstålväggar,\nplåtbearbetningsmaski-ner, kantpressverktyg\nVarunamn: HJO\nAntal anställda: 180\nVerkst dir: Ake Lindholm\nEtableringsår. 1889.\n\nHJORTH TRÄVARUAFFÄR,\nSIGVARD\n\nPnr 710 23\n\nGlanshammar, Box 62. Tel\n019-670 1 4,67 1 48. Bankgiro817-4351.\nPostgiro 169796-0\nVeiksamhet: Sågverk o hyvleri.\nByggnadsmateriel\nÅrsomsättning: 360 000\nChef: Sigvard Hjorth.\n\nHJORT-CONVEYOR AB\n\nPnr 252 27\n\nHelsingborg, Rågångsg 4. Tel\n042-13 74 30. Bankgiro 44-5527.\nPost-giro 34045. Tga Hjortconveyor\nVerksamhet: Försäljning, montage\no service av kedjetransportörer\nAntal anställda: 10\nÅrsomsättning: 2 000 000\nAktiekapital: 100000\nVerkst dir: Gunnar Linde\nEtableringsår: 1962.\n\nWIRON, INGENJÖRSFIRMAN\n\nPnr 414 81\n\nGöteborg. Riksdalersg 32. Tel\n031-4100 35. Bankgiro 602-9375.\nPostgiro 721123-8\nVerksamhet: Konsulterande\ningenjörsfirma inom\nluftbehandlingsteknik o ventilation\nChef: Ing Ronald Öhman\nEtableringsår. 1970.\n\nESWA VÄRME AB\n\nPnr 722 18\n\nVästerås, Sankta Ursulas v 5. Tel\n021-18 5130. Bankgiro 109-8086.\nPostgiro 661230-3\nVerksamhet: Säljer, konstruerar o\nmonterar elektr\ntakvärmeanlägg-ningar\n\nVarunamn: Eswa\nAntal anställda: 12\nÅrsomsättning: 1500 000\nAktiekapital: 100 000\nVerkst dir: Disp Ake Hultström\nEtableringsår 1964.\n\nANA-MASKIN AB\n\nPnr 199 00\n\nEnköping, Westerlundsg 13. Tel\n0171-334 00. Bankgiro 230-8898.\nPostgiro 591580-6\nVerksamhet: Säljer\njordbruksmaskiner o entreprenadmaskiner\nAntal anställda: 90\nÅrsomsättning: 33 200 000\nAktiekepital: 100 000\nVerkst dir: Ake Dahlin\nEtableringsår: 1955.\n\nANA-MASKIN I\nHASSLEHOLM AB\n\nPnr 28101\n\nHässleholm 1, Box 106. Tel\n0451-14140. Bankgiro 410-2612.\nPostgiro 321720-5\n\nVerksamhet: Säljer o uthyr\nentreprenadmaskiner samt service\nAntal anställda: 20\nÅrsomsättning: 5 000 000\nAktiekapital: 5 000\nStyrelse: Dir Torsten Arnheim,\ndir Hans Stenke\nVerkst dir: Kurt Frössling\nEkonomichef: Rune Nilsson\nEtableringsår: 1969.",
    "structured": {
        "1": {
            "company_name": "VICKERS, SPERRY RAND AB",
            "pnr": "172 23",
            "address": "Sundbyberg 1, Box 89",
            "phone_number": "08-98 02 50",
            "activity": "Säljer industriell, mobil o marin hydraulik",
            "key_personnel": [
                {
                    "name": "Dir Bo F Flodman",
                    "position": "Chef"
                }
            ],
            "establishment_year": 1951
        },
        "2": {
            "company_name": "WICKMAN & SKOLDHAGEN MASKIN AB",
            "pnr": "16135",
            "address": "Bromma, Drottningsholmsv 284",
            "phone_number": "08-25 29 50",
            "bank_details": {
                "bankgiro": "560-5548",
                "postgiro": "156890-6"
            },
            "activity": "Tillverkar o säljer transportanordningar, gaffel-staplare o strömtillförselutrustning",
            "key_personnel": [
                {
                    "name": "Ing Ernst Eng",
                    "position": "Chef"
                }
            ],
            "establishment_year": 1951
        },
        "3": {
            "company_name": "JANE-LIST AB",
            "pnr": "250 07",
            "address": "Helsingborg 7, Rundgången, Berga Industriområde, Box 7043",
            "phone_number": "042-14 44 70",
            "bank_details": {
                "bankgiro": "437-8220",
                "postgiro": "342522-0"
            },
            "activity": "Tillverkar lister i olika utförande o av såväl svenska som utländska träslag, även målade o laserade",
            "employees": 60,
            "annual_turnover": 7000000,
            "capital": 225000,
            "key_personnel": [
                {
                    "name": "Fabr Ragnar Bengtsson",
                    "position": "Verkst dir"
                }
            ],
            "establishment_year": 1949
        },
        "4": {
            "company_name": "JANSSON & CO BYGGNADS AB",
            "pnr": "35103",
            "address": "Växjö 1, Hjalmar Petris v 30, Box 50",
            "phone_number": "0470-231 40",
            "bank_details": {
                "bankgiro": "14-6316",
                "postgiro": "297216"
            },
            "activity": "Husbyggnad o anläggningsarbeten",
            "employees": 60,
            "annual_turnover": 6000000,
            "capital": 250000,
            "key_personnel": [
                {
                    "name": "Ing Alvar Jonsson",
                    "position": "Verkst dir"
                }
            ],
            "establishment_year": 1916
        },
        "5": {
            "company_name": "KORVBRUDS-BAGARN AB",
            "pnr": "70012",
            "address": "Örebro 12, Kyrkv 46, Box 12024",
            "phone_number": "019-23 40 10",
            "bank_details": {
                "bankgiro": "495-5597",
                "postgiro": "471093-5"
            },
            "activity": "Tillverkar korvbröd o hamburgarebröd för korvhandeln o butikskedjor",
            "employees": 54,
            "annual_turnover": 7000000,
            "capital": 200000,
            "key_personnel": [
                {
                    "name": "Henry Jansson",
                    "position": "Verkst din"
                },
                {
                    "name": "Hans Andersson",
                    "position": "Kamrer"
                },
                {
                    "name": "Kjell Jonsson",
                    "position": "Produktionschef"
                }
            ],
            "establishment_year": 1957
        },
        "6": {
            "company_name": "BERLINGS GRAFISKA AB",
            "pnr": "22104",
            "address": "Lund 1, Box 1035, Stora Gråbrödersg 17 B",
            "phone_number": "046-117240",
            "bank_details": {
                "bankgiro": "660-7865",
                "postgiro": "30495-6"
            },
            "activity": "Säljer boktryckerimaterial, stil, mässingslinjer, grafiska hjälpmaskiner, sättmatriser o offsettryckpressar, reproutrustning",
            "employees": 6,
            "capital": 10000,
            "key_personnel": [
                {
                    "name": "Arne Andersson",
                    "position": "Dir"
                }
            ],
            "establishment_year": 1962
        },
        "7": {
            "company_name": "BERLINGSKA BOKTRYCKERI & STILGJUTERI AB",
            "pnr": "22104",
            "address": "Lund 1, Box 1035, Stora Gråbrödersg 17 B",
            "phone_number": "046-12 42 40 (bok-tiyckeri), 11 72 40(stilgjuteri)",
            "bank_details": {
                "bankgiro": "660-6172",
                "postgiro": "30490-7"
            },
            "activity": "Tryckeriet utför bok-o offsettryck samt bokbinderiarbeten av affärstryck, böcker o tidskrifter. Specialitet: vetenskapligt tryck, skolböcker, komplicerad sättning, flerfärgs offsettryck. Stilgjuteriet tillverkar boktrycksstilar, lågmaterial, mässingslinjer",
            "employees": 170,
            "capital": 600000,
            "key_personnel": [
                {
                    "name": "Arne Andersson",
                    "position": "Verkst dir"
                }
            ],
            "establishment_year": 1668
        },
        "8": {
            "company_name": "BERLO FABRIKS AB",
            "pnr": "330 20",
            "address": "Anderstorp, AUég 6, Box 71",
            "phone_number": "0371-154 72, 158 82",
            "bank_details": {
                "bankgiro": "48-8013",
                "postgiro": "470700"
            },
            "activity": "Handväskor, portföljer o smålädervaror",
            "employees": 10,
            "annual_turnover": 1200000,
            "capital": 100000,
            "key_personnel": [
                {
                    "name": "Erik Eriksson",
                    "position": "Verkst dir"
                }
            ],
            "establishment_year": 1946
        },
        "9": {
            "company_name": "FAGERSTA BIL AB",
            "pnr": "773 00",
            "address": "Fagersta, Brinellv 107",
            "phone_number": "0223-129 90",
            "bank_details": {
                "bankgiro": "60-6990",
                "postgiro": "546624"
            },
            "activity": "Auktoriserad GM-återförsäljare",
            "key_personnel": [
                {
                    "name": "Håkan Arnerud",
                    "position": "Verkst din"
                }
            ],
            "establishment_year": 1959
        },
        "10": {
            "company_name": "JUNG A VERKSTÄDER AB",
            "pnr": "534 01",
            "address": "Vara 1, Jung, Box 25",
            "phone_number": "0512-22180",
            "bank_details": {
                "bankgiro": "89-4454",
                "postgiro": "265793"
            },
            "activity": "Tillverkar Junga o Cylinda tvättmaskiner",
            "employees": 200,
            "annual_turnover": 25000000,
            "capital": 300000,
            "key_personnel": [
                {
                    "name": "Fabr K E Andersson",
                    "position": "Verkst dir"
                }
            ],
            "establishment_year": 1954
        },
        "11": {
            "company_name": "HJO MEKANISKA VERKSTAD",
            "pnr": "544 00",
            "address": "Hjo",
            "phone_number": "0503-111 00",
            "bank_details": {
                "bankgiro": "21-6437",
                "postgiro": "33229"
            },
            "activity": "Tillverkar radiatorer, stålväggar, plåtbearbetningsmaski-ner, kantpressverktyg",
            "employees": 180,
            "key_personnel": [
                {
                    "name": "Ake Lindholm",
                    "position": "Verkst dir"
                }
            ],
            "establishment_year": 1889
        },
        "12": {
            "company_name": "HJORTH TRÄVARUAFFÄR, SIGVARD",
            "pnr": "710 23",
            "address": "Glanshammar, Box 62",
            "phone_number": "019-670 14, 671 48",
            "bank_details": {
                "bankgiro": "817-4351",
                "postgiro": "169796-0"
            },
            "activity": "Sågverk o hyvleri. Byggnadsmateriel",
            "annual_turnover": 360000,
            "key_personnel": [
                {
                    "name": "Sigvard Hjorth",
                    "position": "Chef"
                }
            ]
        },
        "13": {
            "company_name": "HJORT-CONVEYOR AB",
            "pnr": "252 27",
            "address": "Helsingborg, Rågångsg 4",
            "phone_number": "042-13 74 30",
            "bank_details": {
                "bankgiro": "44-5527",
                "postgiro": "34045"
            },
            "activity": "Försäljning, montage o service av kedjetransportörer",
            "employees": 10,
            "annual_turnover": 2000000,
            "capital": 100000,
            "key_personnel": [
                {
                    "name": "Gunnar Linde",
                    "position": "Verkst dir"
                }
            ],
            "establishment_year": 1962
        },
        "14": {
            "company_name": "WIRON, INGENJÖRSFIRMAN",
            "pnr": "414 81",
            "address": "Göteborg, Riksdalersg 32",
            "phone_number": "031-4100 35",
            "bank_details": {
                "bankgiro": "602-9375",
                "postgiro": "721123-8"
            },
            "activity": "Konsulterande ingenjörsfirma inom luftbehandlingsteknik o ventilation",
            "key_personnel": [
                {
                    "name": "Ing Ronald Öhman",
                    "position": "Chef"
                }
            ],
            "establishment_year": 1970
        },
        "15": {
            "company_name": "ESWA VÄRME AB",
            "pnr": "722 18",
            "address": "Västerås, Sankta Ursulas v 5",
            "phone_number": "021-18 5130",
            "bank_details": {
                "bankgiro": "109-8086",
                "postgiro": "661230-3"
            },
            "activity": "Säljer, konstruerar o monterar elektr takvärmeanläggningar",
            "employees": 12,
            "annual_turnover": 1500000,
            "capital": 100000,
            "key_personnel": [
                {
                    "name": "Disp Ake Hultström",
                    "position": "Verkst dir"
                }
            ],
            "establishment_year": 1964
        },
        "16": {
            "company_name": "ANA-MASKIN AB",
            "pnr": "199 00",
            "address": "Enköping, Westerlundsg 13",
            "phone_number": "0171-334 00",
            "bank_details": {
                "bankgiro": "230-8898",
                "postgiro": "591580-6"
            },
            "activity": "Säljer jordbruksmaskiner o entreprenadmaskiner",
            "employees": 90,
            "annual_turnover": 33200000,
            "capital": 100000,
            "key_personnel": [
                {
                    "name": "Ake Dahlin",
                    "position": "Verkst dir"
                }
            ],
            "establishment_year": 1955
        },
        "17": {
            "company_name": "ANA-MASKIN I HASSLEHOLM AB",
            "pnr": "28101",
            "address": "Hässleholm 1, Box 106",
            "phone_number": "0451-14140",
            "bank_details": {
                "bankgiro": "410-2612",
                "postgiro": "321720-5"
            },
            "activity": "Säljer o uthyr entreprenadmaskiner samt service",
            "employees": 20,
            "annual_turnover": 5000000,
            "capital": 5000,
            "key_personnel": [
                {
                    "name": "Dir Torsten Arnheim",
                    "position": "Styrelse"
                },
                {
                    "name": "dir Hans Stenke",
                    "position": "Styrelse"
                },
                {
                    "name": "Kurt Frössling",
                    "position": "Verkst dir"
                },
                {
                    "name": "Rune Nilsson",
                    "position": "Ekonomichef"
                }
            ],
            "establishment_year": 1969
        }
    }
}