{
    "original": "KÄLLBERGS INDUSTRI AB\n\nPnr 545 00\n\nTöreboda, Skövdev25. Tel\n0506-116 50. Bankgiro 217-1320. Postgiro\n97719-9. Tga Kibol. Telex 5979\nVerksamhet: Tillverkar\näggprodukter, torrmjölk o andra torkade\nlivsmedel, råvaror o halvfabrikat för\nlivsmedelsindustin, den\nfarmacolo-giska industin o d samt utför\nspraytorkning, emulsioner m m\nAktiekapital: 400000\nVerkst dir: Lennart Källberg\nEtableringsår: 1945.\n\nKÄLLDALENS INDUSTRIER,\nAB\n\nPnr 31101\n\nFalkenberg 1, Box 189.\nKveka-torpsv. Tel 0346-143 40\nVerksamhet: Metallindusti,\nprofil-valsning, brännlackering\nÅrsomsättning: 10 000 000\nAktiekapital: 300 000\nVerkst dir: Brita Littorin\nEtableringsår: 1931.\n\nBE RAM, MASKIN AB\n\nPnr 10061\n\nStockholm 11, Bondeg 69. Box\n11110. Tel 08-44 07 65. Bankgiro\n44-6892. Postgiro 256335. Tga\nBeramimport\n\nVerksamhet: Återförsäljare av\nv erktyg smaskiner\nAntal anställda: 9\nÅrsomsättning: 4000000\nAktiekapital: 100 000\nVerkst dir: Bengt Ramström\nEtableringsår: 1948.\n\nHA-STÄLLNINGAR\n\nPnr 302 31\n\nHalmstad, Slottsmöllev 72. Tel\n035-12 8297. Bankgiro 859-5050.\nPost-giro 178464-4\n\nVerksamhet: Försäljning av\ntorn-o lätta serfriceställningar\nChef: Gustaf Beckman\nEtableringsår 1962.\n\nMODELLFABRIKEN, AB\n\nPnr 63102\n\nEskilstuna 1, Kungsg 61. Box 86.\nTel 016-13 26 70, 14 03 70.\nBankgiro 60-1504. Postgiro 462052\nVerksamhet: Tillverkar\ngjuterimo-deller av trä, plast o metall\nAntal anstäUda: 25\nÅrsomsättning: 1000 000\nAktiekapital: 40 000\nChef: Dir Uno Heldert\nEtableringsår: 1929\nTillhör Varnäsföretagen AB,\nKolbäck.\n\nMOD EL L.NILSSONS EFTR\n\nPnr 26190\n\nLandskrona, Hilleshög 15. Tel\n0418-204 44. Bankgiro 868-6446.\nPostgiro 96988-1\nVerksamhet: Gjutmodellsnickeri\nChef: Yngwe Johnsson\nEtableringsår: 1945.\n\nMODERN\nDATA-BEHANDLING, AB\n\nPnr 121 54\n\nJohanneshov, Fyrskeppsv 55. Tel\n08-39 04 50. Bankgiro 580-8654.\nPostgiro 13080-7\n\nVerksamhet: Servicebyrå inom\nadministrativ databehandling\nAntal anstäUda: 17\nÅrsomsättning: 1400 000\nAktiekapital: 25 000\nVeikst dir: Gösta Kärlin\nV verkst dir: Lennart Ring\nEtableringsår: 1962.\n\nMODERN DEKORATION MD\nVERKSTÄDER AB\n\nPnr 113 57\n\nStockholm, Kungstensg 18. Tel\n08-23 07 50. Bankgiro 295-0947.\nPostgiro 57886-4\n\nVerksamhet: Tillverkar o säljer\n\nmekaniska skyltställ\n\nAntal anställda: 17\n\nÅrsomsättning: 1500 000\n\nAktiekapital: 5 000\n\nVerkst dir: ing Gösta Adolfsson\n\nEtableringsår: 1932.\n\nMODERNA\nBUTIKS-INREDNINGAR AB\n\nPnr 433 02\n\nPartille 2, Box 2025. Tel\n031-26 2220. Bankgiro 337-7108.\nPostgiro 62 2 273-1. Tga Stålsystem\nVerksamhet: Butiksinredningar,\ncirkulationsgondol\nAntal anställda: 25\nÅrsomsättning: 6 200 000\nAktiekapital: 100000\nVeikst dir: Lennart Axhamre\nEtableringsår: 1961.\n\nMODERNUM, AB\n\nse Striembolagen AB.\n\nMODIG &amp; CO, BYGGNADS AB\n\nPnr 78101\n\nBorlänge 1, Tunag 9. Box 175.\nTel 0243-198 60. Postgiro 518000\nVerksamhet: Byggnadsverksamhet,\nf asadr e no v eri ng ar\nAntal anstäUda: 25\nÅrsomsättning: 1 500 000\n\nAktiekapital: 30 000\nVerkst dir: Sven Eriksson\nEtableringsår: 1960.\n\nSTENLUND, AB RAGNAR\n\nPnr 791 01\n\nFalun 1, Box 110. Tel 023-15030.\nBankgiro 525-2662. Postgiro\n126742-6\n\nVerksamhet: Säljer förnödenheter\ntill gruvindustrin såsom\npneumatiska o hydrauliska\nmanövercylindrar, borraggregat för malmbrytning,\nventilationstrummor av vävburen\nplast, kulkvarnskulor,\ntryckluft-armatur m m\n\nSTENMANS LÅSFABRIK,\nAB F A\n\nPnr 63102\n\nEskilstuna 1, Västermarksg 16. Box\n60. Tel 016-12 0200. Bankgiro\n60-1387. Postgiro 10795\n\n&lt;FAS) SAK RA LÅS\n\nVerksamhet: Tillverkar lås,\nnycklar o beslag för byggnadsindustrin.\nSpecialitet: tillhållarlås\nVarunamn: FAS\nAktiekapital: 250 000\nVerkst dir: Erie D Matsson\nEtableringsår: 1849.\n\nHAMMARSTRÖMS TRAFIK AB\n\nPnr 660 31\n\nSvanskog, Box 1. Tel 0532-304 00.\nBankgiro 115-0275. Postgiro\n82207-2\n\nVerksamhet: Lokal- o\nfjärrtran-sporter. Väg- o\nbyggnadsschakt-ningar på entreprenad. Säljer\nsten o asfalt\nAntal anstäUda: 50\nÅrsomsättning: 4 500 000\nAktiekapital: 70 000\nVerkst dir: John Hammarström\nEtableringsår: 1936.\n\nmaskin ab svenska gerni\n\nPnr 312 01\n\nLaholm 1, Box 132. Ostertullg 19.\nTel 0430-11100, 11101\nVerksamhet: Högtryckstvätt-,\nkall-o hetvattenaggregat, vattenmängd\n600-1 600 Ut/tim. Tryck 50-80 atö\nVarunamn: Gerni\nAntal anställda: 15\nAktiekapital: 20000\nVerkst dir: Erik Bengtsson\nEtableringsår: 1968.\n\nmaskin teknisk industri,\nab\n\nPnr 101 30\n\nStockholm 1, Box 735. Drottningg\n57. Tel 08-2145 82, 10 3477,\n11 15 35, 1118 91. Bankgiro\n711-5959. Postgiro 353220-7. Tga\nMaskinindust. Telex 10339\nVerksamhet: Säljer kullager,\nrullager, lagerhus, nållager, elektr små\nmotorer, transportrullar, tappväxlar,\nelektromagnetiska borrstativ m m\nEtableringsår: 1953.\n\nmaskin. &amp; transport.\nekonomi, ab\n\nPnr 41666\n\nGöteborg, Borgareg 16. Tel\n031-154650, 15 47 50. Bankgiro\n362-1588. Postgiro 422449-9. Tga\nMake ni\n\nVerksamhet: Vorwerk truck- o\nindustridäck. Transportanordningar\nVarunamn: Vorwerk\nAktiekapital: 25 000\nVerkst dir: Valter Liljevall\nEtableringsår: 1950.\n\nmaskin &amp; verktygsteknik\nallan wilson\n\nPnr 42243\n\nHisings Backa, Lillhagsv 39. Tel\n031-22 67 71. Postgiro 624081-6\nVerksamhet: Maskinelement för\nindustrin enligt ritning\nÄgare o chef: Allan Wilson\nEtableringsår: 1962.\n\nHEDBERGS I VINSLOV AB\n\nPnr 28013\n\nVinslöv, Box 77. Tel 044-808 00.\nBankgiro 674-7844. Postgiro\n23633-1. Tga Hedbergs\nVerksamhet: Försäljning av möbler,\nmattor, gardiner, sängkläder,\nhemtextilier o belysningsarmatur\nAntal anställda: 46\nÅrsomsättning: 9 000 000\nAktiekapital: 272 000\nStyrelse: Dir Sten Ahlberg (ordf),\ndir Jacques Gustavsson, dir Allan\nHedberg, dir Per Arne Nilsson\nVerkst dir: Allan Hedberg\nDisp: Samuel Brandström\nKamrer: Hans Erik Hansson\nEtableringsår: 1905.\n\nHEDBERGS\nKONSTRUKTIONSBYRÅ AB\n\nPrr 96100\n\nBoden, Domusplan 1 D. Tel\n0921-160 10. Postgiro 482510-5\nVerksamhet: Konsulterande\ningenjörer. Ledamot av SKVS\nAntal anställda: 16\nÅrsomsättning: 750 000\nAktiekapital: 5 000\nVerkst dir: Ing Robert Hedberg\nKonstruktionschef: Ing Curt\nTjernström\nEtableringsår: 1957.\n\nSLUUR, AB JULIUS\n\nPnr 116 45\n\nStockholm, Södermalmstorg 4. Tel\n08-2278 00. Tga Järnslöör\nVerksamhet: Byggnadsvaror o\nverktyg\n\nEtableringsår: 1858\nSe i övrigt moderbolag Julius\nSjögren AB.\n\nSMEDBERG &amp; JOHANSSON AB\n\nPnr 16134\n\nBromma, Gesundaplan 55. Tel\n08-26 6513,26 7713. Postgiro 156941\nVerksamhet:\nRörledningsentreprenör\n\nAntal anställda: 18\nAktiekapital: 40 000\nVerkst dir: Edvin Johansson\nEtableringsår: 1956.\n\nICI FIBER AB\n\nPnr 401 23\n\nGöteborg 1, Box 207. Frörensareg\n5, Västra Frölunda. Tel\n031-45 09 65. Tga Icifiber. Telex 20750\nVerksamhet: Säljer syntetfibrer.\nTillverkar kräppnylon\nFabrik: Alingsås. AB Silketvinneri.\nTel 0322-190 30\nAntal anställda: 100\nAktiekapital: 100 000\nVerkst dir. C A Lindecrantz\nEtableringsår: 1964.",
    "structured": {
        "1": {
            "company_name": "KÄLLBERGS INDUSTRI AB",
            "pnr": "545 00",
            "address": "Töreboda, Skövde",
            "phone_number": "0506-116 50",
            "bank_details": {
                "bankgiro": "217-1320",
                "postgiro": "97719-9"
            },
            "activity": "Tillverkar äggprodukter, torrmjölk o andra torkade livsmedel, råvaror o halvfabrikat för livsmedelsindustin, den farmacolo-giska industin o d samt utför spraytorkning, emulsioner m m",
            "capital": 400000,
            "key_personnel": [
                {
                    "name": "Lennart Källberg",
                    "position": "Verkst dir"
                }
            ],
            "establishment_year": 1945
        },
        "2": {
            "company_name": "KÄLLDALENS INDUSTRIER AB",
            "pnr": "31101",
            "address": "Falkenberg 1, Box 189. Kveka-torpsv",
            "phone_number": "0346-143 40",
            "activity": "Metallindusti, profil-valsning, brännlackering",
            "annual_turnover": 10000000,
            "capital": 300000,
            "key_personnel": [
                {
                    "name": "Brita Littorin",
                    "position": "Verkst dir"
                }
            ],
            "establishment_year": 1931
        },
        "3": {
            "company_name": "BE RAM, MASKIN AB",
            "pnr": "10061",
            "address": "Stockholm 11, Bondeg 69. Box 11110",
            "phone_number": "08-44 07 65",
            "bank_details": {
                "bankgiro": "44-6892",
                "postgiro": "256335"
            },
            "activity": "Återförsäljare av verktyg smaskiner",
            "employees": 9,
            "annual_turnover": 4000000,
            "capital": 100000,
            "key_personnel": [
                {
                    "name": "Bengt Ramström",
                    "position": "Verkst dir"
                }
            ],
            "establishment_year": 1948
        },
        "4": {
            "company_name": "HA-STÄLLNINGAR",
            "pnr": "302 31",
            "address": "Halmstad, Slottsmöllev 72",
            "phone_number": "035-12 8297",
            "bank_details": {
                "bankgiro": "859-5050",
                "postgiro": "178464-4"
            },
            "activity": "Försäljning av torn-o lätta serfriceställningar",
            "key_personnel": [
                {
                    "name": "Gustaf Beckman",
                    "position": "Chef"
                }
            ],
            "establishment_year": 1962
        },
        "5": {
            "company_name": "MODELLFABRIKEN, AB",
            "pnr": "63102",
            "address": "Eskilstuna 1, Kungsg 61. Box 86",
            "phone_number": "016-13 26 70, 14 03 70",
            "bank_details": {
                "bankgiro": "60-1504",
                "postgiro": "462052"
            },
            "activity": "Tillverkar gjuterimo-deller av trä, plast o metall",
            "employees": 25,
            "annual_turnover": 1000000,
            "capital": 40000,
            "key_personnel": [
                {
                    "name": "Uno Heldert",
                    "position": "Chef"
                }
            ],
            "establishment_year": 1929
        },
        "6": {
            "company_name": "MOD EL L.NILSSONS EFTR",
            "pnr": "26190",
            "address": "Landskrona, Hilleshög 15",
            "phone_number": "0418-204 44",
            "bank_details": {
                "bankgiro": "868-6446",
                "postgiro": "96988-1"
            },
            "activity": "Gjutmodellsnickeri",
            "key_personnel": [
                {
                    "name": "Yngwe Johnsson",
                    "position": "Chef"
                }
            ],
            "establishment_year": 1945
        },
        "7": {
            "company_name": "MODERN DATA-BEHANDLING, AB",
            "pnr": "121 54",
            "address": "Johanneshov, Fyrskeppsv 55",
            "phone_number": "08-39 04 50",
            "bank_details": {
                "bankgiro": "580-8654",
                "postgiro": "13080-7"
            },
            "activity": "Servicebyrå inom administrativ databehandling",
            "employees": 17,
            "annual_turnover": 1400000,
            "capital": 25000,
            "key_personnel": [
                {
                    "name": "Gösta Kärlin",
                    "position": "Veikst dir"
                },
                {
                    "name": "Lennart Ring",
                    "position": "V verkst dir"
                }
            ],
            "establishment_year": 1962
        },
        "8": {
            "company_name": "MODERN DEKORATION MD VERKSTÄDER AB",
            "pnr": "113 57",
            "address": "Stockholm, Kungstensg 18",
            "phone_number": "08-23 07 50",
            "bank_details": {
                "bankgiro": "295-0947",
                "postgiro": "57886-4"
            },
            "activity": "Tillverkar o säljer mekaniska skyltställ",
            "employees": 17,
            "annual_turnover": 1500000,
            "capital": 5000,
            "key_personnel": [
                {
                    "name": "ing Gösta Adolfsson",
                    "position": "Verkst dir"
                }
            ],
            "establishment_year": 1932
        },
        "9": {
            "company_name": "MODERNA BUTIKS-INREDNINGAR AB",
            "pnr": "433 02",
            "address": "Partille 2, Box 2025",
            "phone_number": "031-26 2220",
            "bank_details": {
                "bankgiro": "337-7108",
                "postgiro": "62 2 273-1"
            },
            "activity": "Butiksinredningar, cirkulationsgondol",
            "employees": 25,
            "annual_turnover": 6200000,
            "capital": 100000,
            "key_personnel": [
                {
                    "name": "Lennart Axhamre",
                    "position": "Veikst dir"
                }
            ],
            "establishment_year": 1961
        },
        "10": {
            "company_name": "MODIG & CO, BYGGNADS AB",
            "pnr": "78101",
            "address": "Borlänge 1, Tunag 9. Box 175",
            "phone_number": "0243-198 60",
            "postgiro": "518000",
            "activity": "Byggnadsverksamhet, f asadr e no v eri ng ar",
            "employees": 25,
            "annual_turnover": 1500000,
            "capital": 30000,
            "key_personnel": [
                {
                    "name": "Sven Eriksson",
                    "position": "Verkst dir"
                }
            ],
            "establishment_year": 1960
        },
        "11": {
            "company_name": "STENLUND, AB RAGNAR",
            "pnr": "791 01",
            "address": "Falun 1, Box 110",
            "phone_number": "023-15030",
            "bank_details": {
                "bankgiro": "525-2662",
                "postgiro": "126742-6"
            },
            "activity": "Säljer förnödenheter till gruvindustrin såsom pneumatiska o hydrauliska manövercylindrar, borraggregat för malmbrytning, ventilationstrummor av vävburen plast, kulkvarnskulor, tryckluft-armatur m m",
            "establishment_year": 1962
        },
        "12": {
            "company_name": "STENMANS LÅSFABRIK, AB F A",
            "pnr": "63102",
            "address": "Eskilstuna 1, Västermarksg 16. Box 60",
            "phone_number": "016-12 0200",
            "bank_details": {
                "bankgiro": "60-1387",
                "postgiro": "10795"
            },
            "activity": "Tillverkar lås, nycklar o beslag för byggnadsindustrin. Specialitet: tillhållarlås",
            "capital": 250000,
            "key_personnel": [
                {
                    "name": "Erie D Matsson",
                    "position": "Verkst dir"
                }
            ],
            "establishment_year": 1849
        },
        "13": {
            "company_name": "HAMMARSTRÖMS TRAFIK AB",
            "pnr": "660 31",
            "address": "Svanskog, Box 1",
            "phone_number": "0532-304 00",
            "bank_details": {
                "bankgiro": "115-0275",
                "postgiro": "82207-2"
            },
            "activity": "Lokal- o fjärrtran-sporter. Väg- o byggnadsschakt-ningar på entreprenad. Säljer sten o asfalt",
            "employees": 50,
            "annual_turnover": 4500000,
            "capital": 70000,
            "key_personnel": [
                {
                    "name": "John Hammarström",
                    "position": "Verkst dir"
                }
            ],
            "establishment_year": 1936
        },
        "14": {
            "company_name": "maskin ab svenska gerni",
            "pnr": "312 01",
            "address": "Laholm 1, Box 132. Ostertullg 19",
            "phone_number": "0430-11100, 11101",
            "activity": "Högtryckstvätt-, kall-o hetvattenaggregat, vattenmängd 600-1 600 Ut/tim. Tryck 50-80 atö",
            "employees": 15,
            "capital": 20000,
            "key_personnel": [
                {
                    "name": "Erik Bengtsson",
                    "position": "Verkst dir"
                }
            ],
            "establishment_year": 1968
        },
        "15": {
            "company_name": "maskin teknisk industri, ab",
            "pnr": "101 30",
            "address": "Stockholm 1, Box 735. Drottningg 57",
            "phone_number": "08-2145 82, 10 3477, 11 15 35, 1118 91",
            "bank_details": {
                "bankgiro": "711-5959",
                "postgiro": "353220-7"
            },
            "activity": "Säljer kullager, rullager, lagerhus, nållager, elektr små motorer, transportrullar, tappväxlar, elektromagnetiska borrstativ m m",
            "establishment_year": 1953
        },
        "16": {
            "company_name": "maskin. & transport. ekonomi, ab",
            "pnr": "41666",
            "address": "Göteborg, Borgareg 16",
            "phone_number": "031-154650, 15 47 50",
            "bank_details": {
                "bankgiro": "362-1588",
                "postgiro": "422449-9"
            },
            "activity": "Vorwerk truck- o industridäck. Transportanordningar",
            "capital": 25000,
            "key_personnel": [
                {
                    "name": "Valter Liljevall",
                    "position": "Verkst dir"
                }
            ],
            "establishment_year": 1950
        },
        "17": {
            "company_name": "maskin & verktygsteknik allan wilson",
            "pnr": "42243",
            "address": "Hisings Backa, Lillhagsv 39",
            "phone_number": "031-22 67 71",
            "postgiro": "624081-6",
            "activity": "Maskinelement för industrin enligt ritning",
            "key_personnel": [
                {
                    "name": "Allan Wilson",
                    "position": "Ägare o chef"
                }
            ],
            "establishment_year": 1962
        },
        "18": {
            "company_name": "HEDBERGS I VINSLOV AB",
            "pnr": "28013",
            "address": "Vinslöv, Box 77",
            "phone_number": "044-808 00",
            "bank_details": {
                "bankgiro": "674-7844",
                "postgiro": "23633-1"
            },
            "activity": "Försäljning av möbler, mattor, gardiner, sängkläder, hemtextilier o belysningsarmatur",
            "employees": 46,
            "annual_turnover": 9000000,
            "capital": 272000,
            "key_personnel": [
                {
                    "name": "Allan Hedberg",
                    "position": "Verkst dir"
                },
                {
                    "name": "Samuel Brandström",
                    "position": "Disp"
                },
                {
                    "name": "Hans Erik Hansson",
                    "position": "Kamrer"
                }
            ],
            "establishment_year": 1905
        },
        "19": {
            "company_name": "HEDBERGS KONSTRUKTIONSBYRÅ AB",
            "pnr": "96100",
            "address": "Boden, Domusplan 1 D",
            "phone_number": "0921-160 10",
            "postgiro": "482510-5",
            "activity": "Konsulterande ingenjörer. Ledamot av SKVS",
            "employees": 16,
            "annual_turnover": 750000,
            "capital": 5000,
            "key_personnel": [
                {
                    "name": "Ing Robert Hedberg",
                    "position": "Verkst dir"
                },
                {
                    "name": "Ing Curt Tjernström",
                    "position": "Konstruktionschef"
                }
            ],
            "establishment_year": 1957
        },
        "20": {
            "company_name": "SLUUR, AB JULIUS",
            "pnr": "116 45",
            "address": "Stockholm, Södermalmstorg 4",
            "phone_number": "08-2278 00",
            "activity": "Byggnadsvaror o verktyg",
            "establishment_year": 1858
        },
        "21": {
            "company_name": "SMEDBERG & JOHANSSON AB",
            "pnr": "16134",
            "address": "Bromma, Gesundaplan 55",
            "phone_number": "08-26 6513,26 7713",
            "postgiro": "156941",
            "activity": "Rörledningsentreprenör",
            "employees": 18,
            "capital": 40000,
            "key_personnel": [
                {
                    "name": "Edvin Johansson",
                    "position": "Verkst dir"
                }
            ],
            "establishment_year": 1956
        },
        "22": {
            "company_name": "ICI FIBER AB",
            "pnr": "401 23",
            "address": "Göteborg 1, Box 207. Frörensareg 5, Västra Frölunda",
            "phone_number": "031-45 09 65",
            "bank_details": {
                "bankgiro": "674-7844",
                "postgiro": "23633-1"
            },
            "activity": "Säljer syntetfibrer. Tillverkar kräppnylon",
            "employees": 100,
            "capital": 100000,
            "key_personnel": [
                {
                    "name": "C A Lindecrantz",
                    "position": "Verkst dir"
                }
            ],
            "establishment_year": 1964
        }
    }
}