{
    "original": "EJJA, AB METALLFABRIKEN\n\nPnr 330 30\n\nGnosjö, Anderstorpsv 26. Postl\n1398. Tel 0370-912 42. Bankgiro\n542-4437. Postgiro 325721-9\nVerksamhet: Tillverkar\nrörledningsarmatur samt metallarbeten\nAntal anställda: 10\nÅrsomsättning: 800 000\nAktiekapital: 20000\nVerkst dir: Anton Johansson\nEtableringsår: 1946.\n\nNILSON RVS AB, CURT\n\nPnr 402 22\n\nGoteborg 5, Box 5111. Berzeliig\n18. Tel 031-811161, 811168.\nBankgiro 642-2141\nVerksamhet: Agenturfirma i rör,\nvärme o sanitet\nÅrsomsättning: 3 500 000\nAktiekapital: 5 000\nVerkst dir: Curt Nilson\nEtableringsår: 1968.\n\nNILSSONS METALL.\nINDUSTRI, E\n\nPnr 664 00\n\nGrums, Sveag 119. Tel 0555-100 09.\nBankgiro 107-1190. Postgiro\n289135-6\n\nVerksamhet: Tillverkar flätade\nbilkorgar o blomställbord\nAntal anställda: 9\nÅrsomsättning: 200 000\nChef: Evert Nilsson\nEtableringsår: 1940.\n\nKRONANS DROGHANDEL AB\n\nPnr 42122\n\nVästra Frölunda 1, Fröfästeg 16 A.\nBox 133. Tel 031-45 02 20.\nBankgiro 420-1091. Postgiro 8425-1.\nTga Kronan\n\nVerksamhet:\nLäkemedelsdistributör\n\nAntal anställda: 110\nAktiekapital: 2500000\nVerkst dir: Lars Erik Bernström\nEtableringsår: 1907.\n\nKRONAN AB, FLAGG. &amp;\nRULLGARDINSFABRIKEN\n\nPnr 252 49\n\nHelsingborg. Nytorgsg 78. Tel\n042-11 41 82, 11 41 84. Bankgiro\n438-0374. Postgiro 91682-5\nVerksamhet: Tillverkar alla slag\nav flaggor o rullgardiner\nAntal anställda: 8\nÅrsomsättning: 500 000\nAktiekapital: 16 000\nVerkst dir: Fabr Lars Wedlin\nEtableringsår: 1932.\n\nTELEPLAN, AB\n\nPnr 17120\n\nSolna 1, Fack. Svetsarv 4. Tel\n08-98 02 00; Bankgiro 404-5126.\nPostgiro 59244-4. Tga Teleplan.\nTelex 17128 TESPACE S\nVerksamhet Konsulterande\ningenjörer inom teleteknik o elektronik\nAntal anställda: 425\nÅrsomsättning: 35 000 000\nAktiekapital: 96 000\nStyrelse: Tekn dr Ch Jacobaeus\n(ordf), dir B Nilsson, dir P A Hult,\n\ndir I Darbäck, tekn dr T Gullstrand,\ndir I Ahlgren\n\nVerkst dir: Civiling Gunnar Stein\nEtableringsår: 1958\nNamnändring från TUAB/TALAB.\nNuv namn 1971.\n\nTELEPRODUKTER\nU JANSSON &amp; CO AB\n\nPnr 104 60\n\nStockholm 20, Box 20094. Virkesv\n9. Tel 08-44 9190. Bankgiro\n118-6071. Postgiro 608339-8\nVerksamhet Tillverkar apparatur\nför manöver, indikering o larm,\nmanöverapparatur för sändare o\nmottagare, apparatur för styrning\nav maskinutrustningar, elektronisk\napparatur för forskning samt\nmilitär elektronik\nAntal anställda: 25\nÅrsomsättning: 1800 000\nAktiekapital: 6 000\nStyrelseordf: Ing Gert Ringquist\nVerkst dir: Ing Ulf Jansson\nEtableringsår: 1961.\n\nTELE-SERVICE,\nS NORDAHL AB\n\nPnr 652 24\n\nKarlstad. Hamng 6. Tel\n054-1548 59,1548 50.Bankgiro88-1630.\nPostgiro 263057\n\nVerksamhet: Försäljning,\ninstallation o service av\nsnabbtelefonanläggningar samt övrig\nsvagströms-utrustning. Bedrivs inom Värmland,\nDalsland o Närke\nAntal anställda: 8\nÅrsomsättning: 600 000\nChef: Sylve Nordahl\nEtableringsår: 1962.\n\nHULIN AB, BRÖDERNA\n\nPnr 52011\n\nVegby, Box 25. Tel 0321-720 03.\nBankgiro 84-0617. Postgiro\n85645-0\n\nVerksamhet: Tillverkar yttertrikå\nför dam o herr\n\nAntal anställda: 15\nÅrsomsättning: 600 000\nAktiekapital: 50 000\nVerkst dir: Disp Arthur W Svedberg\nEtableringsår: 1914.\n\nSYLVAN AB, A S\n\nPnr 402 72\n\nGöteborg8, Box 8866. Askvädersgl.\nTel 031-53 0040. Bankgiro\n441-1625. Postgiro 243724-2. Tga\nAs-sylvanab. Telex 20037 SYLVAN S\nVerksamhet: Tillverkar o säljer\npo-lyeter, formgjutna PVC-detaljer,\nfi-bermattor av kokos- o sisalfiber,\njutefilt, gummikokos samt\nnålfilt-mattor o tuftade mattor\nAntal anställda: 400\nÅrsomsättning: 42 000 000\nAktiekapital: 500 000\nStyrelse: Disp Birger Sylvan (ordf),\ndir Gunnar Sylvan, fru Ulla Sylvan\nVerkst dir: Gunnar Sylvan\nEtableringsår: 1948.\n\nSEELIG &amp; CO, AB\n\nPnr 171 20\n\nSolna 1, Karlsrog 2. Pack. Tel\n08-8503 00. Bankgiro 731-2812.\nPostgiro 636-1. Tga Seeligs\nVerksamhet Spedition o\ndistribution till bok- o pappershandeln\nAntal anställda: 106\n\nÅrsomsättning: 60000 000\nAktiekapital: 1200 000\nStyrelse: Bokhandl Ragnar Clausen\n(crdf), dir John Tengberg (v ordf),\nbokhandl Sven Liljedahl, bokhandl\nBörge Svensson, bokhandl Ake\nRasmusson\n\nVerkst dir. Bengt Lotsander\nAdm-chef: Stig Nilsson\nInformationschef: V ive ka Häggström\nTekn chef: Stig Sunnerholm\nEtableringsår 1848\nOmbildat till aktiebolag 1917.\n\nSEFAB\n\nStrandgrens Entréfasader AB\n\nPnr 910 40\n\nRobertsfors, Box 10. Tel\n0934-105 50. Postgiro 569177-9. Tga\nEntréfasad\n\nVeiksamhet: Tillverkar fasader o\nportar i aluminium o stål\nAntal anställda: 33\nÅrsomsättning: 3 000 000\nAktiekapital: 200 000\nStyrelse: Rektor Erik Johansson\n(ordf), byggn-ing Nils-Eric\nEriksson, dir Gideon Thomas\nVeikst dir: Ing Stig Svensson\nEtableringsår: 1950\nOmbildat till aktiebolag 1965.\n\nSEGA-FABRIKEN I TENHULT\nAB\n\nPnr 56027\n\nTenhult, Tel 036-91213\nVerksamhet: Tillverkare av\nkonstbetong, trappor\nAktiekapital: 25 000\nVerkst dir: C G Pettersson\nEtableringsår. 1919.\n\nKLACKFABRIKEN AB\n\nPnr 570 80\n\nVirserum. Tel 0495-300 21.\nBankgiro 85-7812. Postgiro 26744. Tga\nKlackfabriken\n\nVerksamhet: Tillverkar skoklackar\ni såväl trä som läder samt trätofflor\nAntal anställda: 18\nÅrsomsättning: 700000\nAktiekapital: 120 000\nVerkst dir: Karl-Olof Johansson\nEtableringsår: 1918.\n\nKLAESSONS MDBELFABRIK,\nAB A\n\nPnr 702 10\n\nÖrebro, Våghustorget 3. Tel\n019-1247 45. Bankgiro 815-7257.\nPostgiro 75017-4\n\nVerksamhet: Tillverkar möbler o\ninredningar för offentlig miljö\nAktiekapital: 200 000\nVerkst dir: Gunnar Klaesson\nEtableringsår: 1903.\n\nKLARAVIKS\nTRICOT-FABRIK, AB\n\nPnr 653 42\n\nKarlstad, Romstads v 2. Tel\n054-1104 98, 1174 64. Bankgiro\n100-1718. Postgiro 27960-4\nVerksamhet: Tillverkar\nklänningar, dräkter o stickade varor\nVarunamn: Klaraviks\nAntal anställda: 90\nAktiekapital: 300 000\nVerkst dir: Sven Jonson\nEtableringsår: 1917.\n\nKLARVIKS GJUTERI &amp;\nMODELLFABRIK, AB\n\nPnr 360 72\n\nKlavreström, Box 50. Tel\n0474-400 01, 40271. Bankgiro 500-0179.\nPostgiro 41562\n\nVerksamhet: Tillverkar hand- o\nmaskinformat tackjärnsgjutgods i\nstyckevikter upp till 1000 kg.\nModellfabrikation\nAntal anställda: 50\nÅrsomsättning: 4 000 000\nAktiekapital: 110 000\nStyrelse: Dir Mikael Jahn (ordf),\nkonsul Olof Jahn, ing Bengt Korpe\nVerkst dir: Ing Bengt Korpe\nEtableringsår: 1946.\n\nWIMO MÖBELFABRIK, AB\n\nPnr 560 25\n\nBottnaryd, Snickarev 1. Tel\n036-203 50. Bankgiro 372-9621.\nPost-giro 10191-5\n\nVerksamhet: Tillverkar stoppade\nsittmöbler. Fåtöljer i 2-sits- o\n3-sits utförande\nAntal anställda: 28\nÅrsomsättning: 5 000 000\nStyrelse: Fabr Dan Winberg, fru\nInga Winberg\n\nVeikst dir: Fabr Dan Winberg\nOrder o planeringschef: Bruno\nHektor\n\nVerkmästare: Alf Kureman, Allan\nArwidson\n\nEtableringsàr: 1968.\n\nVIN- &amp; SPRITCENTRALEN, AB\n\nPnr 102 31\n\nStockholm 6, Sankt Eriksg 121.\nBox 6061. Tel 08-22 2200.\nBankgiro 330-1256. Postgiro 86-9. Tga\nSpritcentralen\n\nVerksamhet: Tillverkar vin o\nspritdrycker samt teknisk sprit i parti\nFilialer 40013 Göteborg 36, Fack.\nTel 031-19 26 60. Chef: disp N H\nDahlström\n\nHelsingborg. Box 76, pa 260 35\nOd-åkra. Tel 042-942 00. Chef: disp G\nSvenson\n\n29100 Kristianstad. Tel\n044-114128. Råbränneri. Chef:\nbrännmästare Jan-Erik Spogardh\n117 40 Stockholm, Reimersholmsg 1.\nTel 08-68 01 20. Chef: (lisp Arne\nBresky\n\n117 43 Stockholm, Förmansv 40.\nTel 08-69 04 20. Chef: disp Henry\nCarlsson\n\n85009 Sundsvall 9, Box 9031. Tel\n060-1577 80. Chef: disp Gustav\nJakobsson\n\n15121 Södertälje 1. Box 75. Tel\n0755-325 15. Chef: disp S Stenebro\n290 20 Åhus, Box 83. Tel\n044-24 00 65. Chef: disp Svante Meyer\nAntal anställda: 984\nÅrsomsättning: 371600 000\nAktiekapital: 15 000 000\nStyrelse: President Gustaf Hedborg\n(ordf), landshövd Thure\nAndersson, red Torsten Bengtson, dir John\nEricsson, dir Bengt Lyberg, disp\nTage Magnusson, dir Gösta Nilsson,\ndisp Chr von Sydow\nVerkst dir John Ericsson\nEtableringsån 1917.\n\nDIXIE CUP, AB\n\nPnr 22101\n\nLund 1, Fack. Sölveg 9. Tel\n046-12 29 00. 14 47 10. Bankgiro\n820-2251. Postgiro 636431-9.\nTelex 32207 LEE S\nVerksamhet: Tillverkar o säljer\nengångsartiklar såsom\nplastbelag-da pappersbägare,\npapperstallrikar, koppar, bägardispensers\nVarunamn: Dixie Cup, Dixie Royal\nAntal anställda: 64\nÅrsomsättning: 12 000 000\nAktiekapital: 500 000\nVerkst dir: Gunnar Brime\nV verkst dir: Civiling Alf Linderot\nEtableringsår: 1963.",
    "structured": {
        "1": {
            "company_name": "EJJA, AB METALLFABRIKEN",
            "address": "Gnosjö, Anderstorpsv 26",
            "phone_number": "0370-912 42",
            "bank_details": {
                "bankgiro": "542-4437",
                "postgiro": "325721-9"
            },
            "activity": "Tillverkar rörledningsarmatur samt metallarbeten",
            "employees": 10,
            "annual_turnover": 800000,
            "capital": 20000,
            "key_personnel": [
                {
                    "name": "Anton Johansson",
                    "position": "Verkst dir"
                }
            ],
            "establishment_year": 1946
        },
        "2": {
            "company_name": "NILSON RVS AB, CURT",
            "address": "Goteborg 5, Box 5111, Berzeliig 18",
            "phone_number": "031-811161, 811168",
            "bank_details": {
                "bankgiro": "642-2141"
            },
            "activity": "Agenturfirma i rör, värme o sanitet",
            "annual_turnover": 3500000,
            "capital": 5000,
            "key_personnel": [
                {
                    "name": "Curt Nilson",
                    "position": "Verkst dir"
                }
            ],
            "establishment_year": 1968
        },
        "3": {
            "company_name": "NILSSONS METALL. INDUSTRI, E",
            "address": "Grums, Sveag 119",
            "phone_number": "0555-100 09",
            "bank_details": {
                "bankgiro": "107-1190",
                "postgiro": "289135-6"
            },
            "activity": "Tillverkar flätade bilkorgar o blomställbord",
            "employees": 9,
            "annual_turnover": 200000,
            "key_personnel": [
                {
                    "name": "Evert Nilsson",
                    "position": "Chef"
                }
            ],
            "establishment_year": 1940
        },
        "4": {
            "company_name": "KRONANS DROGHANDEL AB",
            "address": "Västra Frölunda 1, Fröfästeg 16 A, Box 133",
            "phone_number": "031-45 02 20",
            "bank_details": {
                "bankgiro": "420-1091",
                "postgiro": "8425-1"
            },
            "activity": "Läkemedelsdistributör",
            "employees": 110,
            "capital": 2500000,
            "key_personnel": [
                {
                    "name": "Lars Erik Bernström",
                    "position": "Verkst dir"
                }
            ],
            "establishment_year": 1907
        },
        "5": {
            "company_name": "KRONAN AB, FLAGG. & RULLGARDINSFABRIKEN",
            "address": "Helsingborg, Nytorgsg 78",
            "phone_number": "042-11 41 82, 11 41 84",
            "bank_details": {
                "bankgiro": "438-0374",
                "postgiro": "91682-5"
            },
            "activity": "Tillverkar alla slag av flaggor o rullgardiner",
            "employees": 8,
            "annual_turnover": 500000,
            "capital": 16000,
            "key_personnel": [
                {
                    "name": "Fabr Lars Wedlin",
                    "position": "Verkst dir"
                }
            ],
            "establishment_year": 1932
        },
        "6": {
            "company_name": "TELEPLAN, AB",
            "address": "Solna 1, Fack. Svetsarv 4",
            "phone_number": "08-98 02 00",
            "bank_details": {
                "bankgiro": "404-5126",
                "postgiro": "59244-4"
            },
            "activity": "Konsulterande ingenjörer inom teleteknik o elektronik",
            "employees": 425,
            "annual_turnover": 35000000,
            "capital": 96000,
            "key_personnel": [
                {
                    "name": "Civiling Gunnar Stein",
                    "position": "Verkst dir"
                }
            ],
            "establishment_year": 1958
        },
        "7": {
            "company_name": "TELEPRODUKTER U JANSSON & CO AB",
            "address": "Stockholm 20, Box 20094, Virkesv 9",
            "phone_number": "08-44 9190",
            "bank_details": {
                "bankgiro": "118-6071",
                "postgiro": "608339-8"
            },
            "activity": "Tillverkar apparatur för manöver, indikering o larm, manöverapparatur för sändare o mottagare, apparatur för styrning av maskinutrustningar, elektronisk apparatur för forskning samt militär elektronik",
            "employees": 25,
            "annual_turnover": 1800000,
            "capital": 6000,
            "key_personnel": [
                {
                    "name": "Ing Ulf Jansson",
                    "position": "Verkst dir"
                }
            ],
            "establishment_year": 1961
        },
        "8": {
            "company_name": "TELE-SERVICE, S NORDAHL AB",
            "address": "Karlstad, Hamng 6",
            "phone_number": "054-1548 59,1548 50",
            "bank_details": {
                "bankgiro": "88-1630",
                "postgiro": "263057"
            },
            "activity": "Försäljning, installation o service av snabbtelefonanläggningar samt övrig svagströms-utrustning. Bedrivs inom Värmland, Dalsland o Närke",
            "employees": 8,
            "annual_turnover": 600000,
            "key_personnel": [
                {
                    "name": "Sylve Nordahl",
                    "position": "Chef"
                }
            ],
            "establishment_year": 1962
        },
        "9": {
            "company_name": "HULIN AB, BRÖDERNA",
            "address": "Vegby, Box 25",
            "phone_number": "0321-720 03",
            "bank_details": {
                "bankgiro": "84-0617",
                "postgiro": "85645-0"
            },
            "activity": "Tillverkar yttertrikå för dam o herr",
            "employees": 15,
            "annual_turnover": 600000,
            "capital": 50000,
            "key_personnel": [
                {
                    "name": "Disp Arthur W Svedberg",
                    "position": "Verkst dir"
                }
            ],
            "establishment_year": 1914
        },
        "10": {
            "company_name": "SYLVAN AB, A S",
            "address": "Göteborg8, Box 8866, Askvädersgl.",
            "phone_number": "031-53 0040",
            "bank_details": {
                "bankgiro": "441-1625",
                "postgiro": "243724-2"
            },
            "activity": "Tillverkar o säljer po-lyeter, formgjutna PVC-detaljer, fi-bermattor av kokos- o sisalfiber, jutefilt, gummikokos samt nålfiltmattor o tuftade mattor",
            "employees": 400,
            "annual_turnover": 42000000,
            "capital": 500000,
            "key_personnel": [
                {
                    "name": "Gunnar Sylvan",
                    "position": "Verkst dir"
                }
            ],
            "establishment_year": 1948
        },
        "11": {
            "company_name": "SEELIG & CO, AB",
            "address": "Solna 1, Karlsrog 2. Pack",
            "phone_number": "08-8503 00",
            "bank_details": {
                "bankgiro": "731-2812",
                "postgiro": "636-1"
            },
            "activity": "Spedition o distribution till bok- o pappershandeln",
            "employees": 106,
            "annual_turnover": 60000000,
            "capital": 1200000,
            "key_personnel": [
                {
                    "name": "Bengt Lotsander",
                    "position": "Verkst dir"
                }
            ],
            "establishment_year": 1848
        },
        "12": {
            "company_name": "SEFAB Strandgrens Entréfasader AB",
            "address": "Robertsfors, Box 10",
            "phone_number": "0934-105 50",
            "postgiro": "569177-9",
            "activity": "Tillverkar fasader o portar i aluminium o stål",
            "employees": 33,
            "annual_turnover": 3000000,
            "capital": 200000,
            "key_personnel": [
                {
                    "name": "Ing Stig Svensson",
                    "position": "Veikst dir"
                }
            ],
            "establishment_year": 1950
        },
        "13": {
            "company_name": "SEGA-FABRIKEN I TENHULT AB",
            "activity": "Tillverkare av konstbetong, trappor",
            "capital": 25000,
            "key_personnel": [
                {
                    "name": "C G Pettersson",
                    "position": "Verkst dir"
                }
            ],
            "establishment_year": 1919
        },
        "14": {
            "company_name": "KLACKFABRIKEN AB",
            "address": "Virserum",
            "phone_number": "0495-300 21",
            "bank_details": {
                "bankgiro": "85-7812"
            },
            "activity": "Tillverkar skoklackar i såväl trä som läder samt trätofflor",
            "employees": 18,
            "annual_turnover": 700000,
            "capital": 120000,
            "key_personnel": [
                {
                    "name": "Karl-Olof Johansson",
                    "position": "Verkst dir"
                }
            ],
            "establishment_year": 1918
        },
        "15": {
            "company_name": "KLAESSONS MDBELFABRIK, AB A",
            "address": "Örebro, Våghustorget 3",
            "phone_number": "019-1247 45",
            "bank_details": {
                "bankgiro": "815-7257",
                "postgiro": "75017-4"
            },
            "activity": "Tillverkar möbler o inredningar för offentlig miljö",
            "capital": 200000,
            "key_personnel": [
                {
                    "name": "Gunnar Klaesson",
                    "position": "Verkst dir"
                }
            ],
            "establishment_year": 1903
        },
        "16": {
            "company_name": "KLARAVIKS TRICOT-FABRIK, AB",
            "address": "Karlstad, Romstads v 2",
            "phone_number": "054-1104 98, 1174 64",
            "bank_details": {
                "bankgiro": "100-1718",
                "postgiro": "27960-4"
            },
            "activity": "Tillverkar klänningar, dräkter o stickade varor",
            "employees": 90,
            "annual_turnover": 300000,
            "capital": 300000,
            "key_personnel": [
                {
                    "name": "Sven Jonson",
                    "position": "Verkst dir"
                }
            ],
            "establishment_year": 1917
        },
        "17": {
            "company_name": "KLARVIKS GJUTERI & MODELLFABRIK, AB",
            "address": "Klavreström, Box 50",
            "phone_number": "0474-400 01, 40271",
            "bank_details": {
                "bankgiro": "500-0179",
                "postgiro": "41562"
            },
            "activity": "Tillverkar hand- o maskinformat tackjärnsgjutgods i styckevikter upp till 1000 kg. Modellfabrikation",
            "employees": 50,
            "annual_turnover": 4000000,
            "capital": 110000,
            "key_personnel": [
                {
                    "name": "Ing Bengt Korpe",
                    "position": "Verkst dir"
                }
            ],
            "establishment_year": 1946
        },
        "18": {
            "company_name": "WIMO MÖBELFABRIK, AB",
            "address": "Bottnaryd, Snickarev 1",
            "phone_number": "036-203 50",
            "bank_details": {
                "bankgiro": "372-9621",
                "postgiro": "10191-5"
            },
            "activity": "Tillverkar stoppade sittmöbler. Fåtöljer i 2-sits- o 3-sits utförande",
            "employees": 28,
            "annual_turnover": 5000000,
            "key_personnel": [
                {
                    "name": "Fabr Dan Winberg",
                    "position": "Veikst dir"
                }
            ],
            "establishment_year": 1968
        },
        "19": {
            "company_name": "VIN- & SPRITCENTRALEN, AB",
            "address": "Stockholm 6, Sankt Eriksg 121, Box 6061",
            "phone_number": "08-22 2200",
            "bank_details": {
                "bankgiro": "330-1256",
                "postgiro": "86-9"
            },
            "activity": "Tillverkar vin o spritdrycker samt teknisk sprit i parti",
            "employees": 984,
            "annual_turnover": 371600000,
            "capital": 15000000,
            "key_personnel": [
                {
                    "name": "John Ericsson",
                    "position": "Verkst dir"
                }
            ],
            "establishment_year": 1917
        },
        "20": {
            "company_name": "DIXIE CUP, AB",
            "address": "Lund 1, Fack. Sölveg 9",
            "phone_number": "046-12 29 00, 14 47 10",
            "bank_details": {
                "bankgiro": "820-2251",
                "postgiro": "636431-9"
            },
            "activity": "Tillverkar o säljer engångsartiklar såsom plastbelagda pappersbägare, papperstallrikar, koppar, bägardispensers",
            "employees": 64,
            "annual_turnover": 12000000,
            "capital": 500000,
            "key_personnel": [
                {
                    "name": "Gunnar Brime",
                    "position": "Verkst dir"
                }
            ],
            "establishment_year": 1963
        }
    }
}