{
    "original": "MARKS TEXTILFABRIK, AB\n\nPnr 51100\n\nKinna, Kasthallsv. Tel 0320-107 35,\n100 77. Bankgiro 43-4865. Postgiro\n31793\n\nVerksamhet: Tillverkar o säljer\nmöbeltyger till fabrikanter o\ngrossister\n\nAntal anställda: 25\nAktiekapital: 40 000\nVerkst dir: John Hedlund\nEtableringsår: 1908\nOmbildat till aktiebolag 1957.\n\nMARKS YLLEINDUSTRI, AB\n\nPnr 51100\n\nKinna. Tel 0320-480 26. Bankgiro\n434-7449. Postgiro 83314-5.\nTga Marksylle\n\nVerksamhet: Tillverkning av finare\njerseytyger i jacquard som i\nveve-nitmaskiner samt\nklänningstillverkning. Lönstickning utföres\nAntal anstäUda: 6\nÄgare o chef: Carl R Johansson\nEtableringsår: 1932.\n\nAHLMARKSBRÄNSLE AB\n\nPnr 65105\n\nKarlstad 1, Box 316. S Kyrkog 6.\nTel 054-115200. Tga Ahlmarco.\nTelex 66081\n\nVerksamhet: Lagring, försäljning o\ndistribution av\npetroleumprodukter. Kol o koks\n\nFilialer: Arvika. Tel 0570-135 80\nGöteborg. Tel 031-813385\nKarlskoga. Tel 0586-314 00\nKristinehamn. Tel 0550-15150\nAmål. Tel 0532-11780\nÖrebro. Tel 019-1196 55\nAntal anställda: 83\nÅrsomsättning: 41270 000\nAktiekapital: 1000000\nVerkst dir: Bertil Lindström\nEtableringsår: 1953.\n\nALDE-VERKEN AB\n\nPnr 29111\n\nKristianstad 11, Box 11066. Färlöv.\nTel 044-712 70. Bankgiro 27-3902.\nPostgiro 23593. Telex 4441 ALDE S\nVerksamhet: Tillverkar\nsläpvagnstillbehör såsom vakuum-,\ntryckluft-o hydraulbromsar samt\nkulkopplingar, stödhjul, släpvagnsaxlar\netc. Driver grossist- o\ndetaljhandel med all utrustning inom\nhusvagnsbranschen\n\nAntal anställda: 32\nÅrsomsättning: 4 000 000\nAktiekapital: 15 000\nVerkst dir: Fabr Alde Rask\nDisp: Gunnar Eklund\nVerkstadschef: Erie Ohlin\nEtableringsår: 1949\nOmbildat till aktiebolag 1953.\n\nALDO,AB\n\nPnr 631 05\n\nEskilstuna 1, Box 369. Stora Nyby.\nTel 016-1172 30. Tga\nScandia-goods. Telex 40991 EMEESK S\nVerksamhet: Byggmaskiner,\narbets-plattformar, transportanordningar\no stålinredningar\nAvdelningskontor: Stockholm. Tel\n08-43 73 15\n\nLager o service. Tel 08-9747 84\nGöteborg. Tel 031-49 45 40\nAktiekapital: 100 000\nVerkst din John Alderin\nEtableringsår: 1947.\n\nCABBY HUSVAGNAR AB\n\nPnr 68101\n\nKristinehamn 1, Box 107. Tel\n0550-156 20. Postgiro 685730.Tga Cabby\nVerksamhet: Tillverkar husvagnar\nAntal anställda: 150\nÅrsomsättning: 35 000 000\nAktiekapital: 100 000\nVerkst dir: Töre Nilsson\nEtableringsår: 1964.\n\nHOLMQUIST, AB ROB\n\nPnr 50107\n\nBorås 1, Stora Brog 39. Box 483.\nTel 033-10 22 00. Bankgiro\n53-1167. Postgiro 77900. Telex 36028\nVerksamhet: Grosshandel inom\nvärme- o sanitet,\nverktygsmaskiner, verktyg, förnödenheter för\nindustrin, packningsmaterial,\nkullager, kilremmar etc\nAntal anställda: 45\nÅrsomsättning: 12 600 000\nAktiekapital: 224 900\nStyrelse: Adv Erik Grenfors (ordf),\ndir Thure Flink, dir Nils-Göran\nFlink\n\nVerkst dir: Nils-Göran Flink\nKamrer Walter Kollgren\nFörsäljn-chef er: Thure Töllborn,\nInge Ericson\n\nInköpschef: Bengt Leander\nLagerchef: Erik Rådh\nEtableringsår: 1925.\n\nHOLMKVISTS MEK VERK.\nSTADS AB. T\n\nPnr 73100\n\nKöping. Tel 0221-116 48, 140 09.\nBankgiro 81-1313. Postgiro 360557\nVerksamhet: Tillverkar formverktyg.\nUtför revolver- o supportsvarvning\nAntal anställda: 15\nÅrsomsättning: 800 000\nAktiekapital: 10 000\nVerkst dir: Tage Holmkvist\nEtableringsår: 1947.\n\nWIDÉN ARKITEKTKONTOR\nAB, BO\n\nPnr 552 55\n\nJönköping, Trädgàrdsg 37. Tel\n036-1188 20. Bankgiro 544-9715.\nPost-giro 290369-8\n\nVerksamhet: Konsulterande\narkitekter för bl a bostäder, industrier,\nskolor, kontors- o\nförvaltningsbyggnader, sociala byggnader, vårdhem\netc. Stadsplanering\nAntal anställda: 9\nÅrsomsättning: 700 0 00\nChef: Ark SAR Boo D:son Widén\nEtableringsår: 1944.\n\nGARANTIASFALT AB\n\nPnr 102 72\n\nStockholm 9, Tullportsg 186. Box\n9132. Tel 08-69 7915 , 69 7916.\nBankgiro 48-1309. Postgiro 103620\nVerksamhet: Entreprenör inom\nväg-o vattenbyggnad\nAktiekapital: 10 000\nVeikst dir: Runo Lövgren\nEtableringsår: 1959.\n\nBENGTSSONS MEKANISKA AB,\nYNGVE\n\nPnr 591 00\n\nMotala, Nyg 33. Tel 0141-126 04.\nBankgiro 669-4400. Postgiro\n105398-2\n\nVerksamhet: Tillverkar svängbara\nbrevkorgar o telefonhyllor.\nNyckelskåp, verktygsskåp o\nsläpvagnsunderreden samt tunnplåtsarbeten\n.Antal anställda: 4\nÅrsomsättning: 400 000\nAktiekapital: 5 000\nVerkst dir: Fabr Yngve Bengtsson\nEtableringsår: 1964.\n\nJURELLSTRÄVARU AB\n\nPnr 60102\n\nNorrköping 1, Munkg 16. Box 76.\nTel 011-1003 30. Bankgiro\n609-8271. Postgiro 133333-5.\nUtställning Trädgårdsg 42\nVerksamhet: Handel med trävaror,\nbyggnadsvaror o snickerier\nAntal anställda: 15\nVerkst dir: Lennart Jurell\nEtableringsår: 1937.\n\nBOHLIN &amp; SJÖQVIST, AB\n\nPnr 702 27\n\nÖrebro, Skvadronv 5. Tel\n019-1199 75. Bankgiro 463-2261.\nPostgiro 26424-2\n\nVerksamhet: Papper o\nförpackningar en gros\nAntal anställda: 20\nÅrsomsättning: 9000 000\nAktiekapital: 25 000\nVerkst dir: Tage Lernberg\nEtableringsår: 1925.",
    "structured": {
        "1": {
            "company_name": "MARKS TEXTILFABRIK, AB",
            "pnr": "51100",
            "address": "Kinna, Kasthallsv.",
            "phone_number": "0320-107 35, 100 77",
            "bank_details": {
                "bankgiro": "43-4865",
                "postgiro": "31793"
            },
            "activity": "Tillverkar o säljer möbeltyger till fabrikanter o grossister",
            "employees": 25,
            "capital": 40000,
            "key_personnel": [
                {
                    "name": "John Hedlund",
                    "position": "Verkst dir"
                }
            ],
            "establishment_year": 1908
        },
        "2": {
            "company_name": "MARKS YLLEINDUSTRI, AB",
            "pnr": "51100",
            "address": "Kinna",
            "phone_number": "0320-480 26",
            "bank_details": {
                "bankgiro": "434-7449",
                "postgiro": "83314-5"
            },
            "activity": "Tillverkning av finare jerseytyger i jacquard som i veve-nitmaskiner samt klänningstillverkning. Lönstickning utföres",
            "employees": 6,
            "key_personnel": [
                {
                    "name": "Carl R Johansson",
                    "position": "Ägare o chef"
                }
            ],
            "establishment_year": 1932
        },
        "3": {
            "company_name": "AHLMARKSBRÄNSLE AB",
            "pnr": "65105",
            "address": "Karlstad 1, Box 316, S Kyrkog 6",
            "phone_number": "054-115200",
            "bank_details": {
                "bankgiro": "Unknown",
                "postgiro": "Unknown"
            },
            "activity": "Lagring, försäljning o distribution av petroleumprodukter. Kol o koks",
            "employees": 83,
            "annual_turnover": 41270000,
            "capital": 1000000,
            "key_personnel": [
                {
                    "name": "Bertil Lindström",
                    "position": "Verkst dir"
                }
            ],
            "establishment_year": 1953
        },
        "4": {
            "company_name": "ALDE-VERKEN AB",
            "pnr": "29111",
            "address": "Kristianstad 11, Box 11066, Färlöv",
            "phone_number": "044-712 70",
            "bank_details": {
                "bankgiro": "27-3902",
                "postgiro": "23593"
            },
            "activity": "Tillverkar släpvagnstillbehör såsom vakuum-, tryckluft-o hydraulbromsar samt kulkopplingar, stödhjul, släpvagnsaxlar etc. Driver grossist- o detaljhandel med all utrustning inom husvagnsbranschen",
            "employees": 32,
            "annual_turnover": 4000000,
            "capital": 15000,
            "key_personnel": [
                {
                    "name": "Fabr Alde Rask",
                    "position": "Verkst dir"
                },
                {
                    "name": "Gunnar Eklund",
                    "position": "Disp"
                },
                {
                    "name": "Erie Ohlin",
                    "position": "Verkstadschef"
                }
            ],
            "establishment_year": 1949
        },
        "5": {
            "company_name": "ALDO,AB",
            "pnr": "63105",
            "address": "Eskilstuna 1, Box 369, Stora Nyby",
            "phone_number": "016-1172 30",
            "bank_details": {
                "bankgiro": "Unknown",
                "postgiro": "Unknown"
            },
            "activity": "Byggmaskiner, arbets-plattformar, transportanordningar o stålinredningar",
            "employees": 0,
            "capital": 100000,
            "key_personnel": [
                {
                    "name": "John Alderin",
                    "position": "Verkst din"
                }
            ],
            "establishment_year": 1947
        },
        "6": {
            "company_name": "CABBY HUSVAGNAR AB",
            "pnr": "68101",
            "address": "Kristinehamn 1, Box 107",
            "phone_number": "0550-156 20",
            "bank_details": {
                "bankgiro": "Unknown",
                "postgiro": "685730"
            },
            "activity": "Tillverkar husvagnar",
            "employees": 150,
            "annual_turnover": 35000000,
            "capital": 100000,
            "key_personnel": [
                {
                    "name": "Töre Nilsson",
                    "position": "Verkst dir"
                }
            ],
            "establishment_year": 1964
        },
        "7": {
            "company_name": "HOLMQUIST, AB ROB",
            "pnr": "50107",
            "address": "Borås 1, Stora Brog 39, Box 483",
            "phone_number": "033-10 22 00",
            "bank_details": {
                "bankgiro": "53-1167",
                "postgiro": "77900"
            },
            "activity": "Grosshandel inom värme- o sanitet, verktygsmaskiner, verktyg, förnödenheter för industrin, packningsmaterial, kullager, kilremmar etc",
            "employees": 45,
            "annual_turnover": 12600000,
            "capital": 224900,
            "key_personnel": [
                {
                    "name": "Nils-Göran Flink",
                    "position": "Styrelse: Adv Erik Grenfors (ordf)"
                },
                {
                    "name": "Nils-Göran Flink",
                    "position": "Verkst dir"
                }
            ],
            "establishment_year": 1925
        },
        "8": {
            "company_name": "HOLMKVISTS MEK VERKSTADS AB. T",
            "pnr": "73100",
            "address": "Köping",
            "phone_number": "0221-116 48, 140 09",
            "bank_details": {
                "bankgiro": "81-1313",
                "postgiro": "360557"
            },
            "activity": "Tillverkar formverktyg. Utför revolver- o supportsvarvning",
            "employees": 15,
            "annual_turnover": 800000,
            "capital": 10000,
            "key_personnel": [
                {
                    "name": "Tage Holmkvist",
                    "position": "Verkst dir"
                }
            ],
            "establishment_year": 1947
        },
        "9": {
            "company_name": "WIDÉN ARKITEKTKONTOR AB, BO",
            "pnr": "552 55",
            "address": "Jönköping, Trädgàrdsg 37",
            "phone_number": "036-1188 20",
            "bank_details": {
                "bankgiro": "544-9715",
                "postgiro": "290369-8"
            },
            "activity": "Konsulterande arkitekter för bl a bostäder, industrier, skolor, kontors- o förvaltningsbyggnader, sociala byggnader, vårdhem etc. Stadsplanering",
            "employees": 9,
            "annual_turnover": 700000,
            "key_personnel": [
                {
                    "name": "Ark SAR Boo D:son Widén",
                    "position": "Chef"
                }
            ],
            "establishment_year": 1944
        },
        "10": {
            "company_name": "GARANTIASFALT AB",
            "pnr": "102 72",
            "address": "Stockholm 9, Tullportsg 186, Box 9132",
            "phone_number": "08-69 7915, 69 7916",
            "bank_details": {
                "bankgiro": "48-1309",
                "postgiro": "103620"
            },
            "activity": "Entreprenör inom väg-o vattenbyggnad",
            "capital": 10000,
            "key_personnel": [
                {
                    "name": "Runo Lövgren",
                    "position": "Veikst dir"
                }
            ],
            "establishment_year": 1959
        },
        "11": {
            "company_name": "BENGTSSONS MEKANISKA AB, YNGVE",
            "pnr": "591 00",
            "address": "Motala, Nyg 33",
            "phone_number": "0141-126 04",
            "bank_details": {
                "bankgiro": "669-4400",
                "postgiro": "105398-2"
            },
            "activity": "Tillverkar svängbara brevkorgar o telefonhyllor. Nyckelskåp, verktygsskåp o släpvagnsunderreden samt tunnplåtsarbeten",
            "employees": 4,
            "annual_turnover": 400000,
            "capital": 5000,
            "key_personnel": [
                {
                    "name": "Fabr Yngve Bengtsson",
                    "position": "Verkst dir"
                }
            ],
            "establishment_year": 1964
        },
        "12": {
            "company_name": "JURELLSTRÄVARU AB",
            "pnr": "60102",
            "address": "Norrköping 1, Munkg 16, Box 76",
            "phone_number": "011-1003 30",
            "bank_details": {
                "bankgiro": "609-8271",
                "postgiro": "133333-5"
            },
            "activity": "Handel med trävaror, byggnadsvaror o snickerier",
            "employees": 15,
            "key_personnel": [
                {
                    "name": "Lennart Jurell",
                    "position": "Verkst dir"
                }
            ],
            "establishment_year": 1937
        },
        "13": {
            "company_name": "BOHLIN & SJÖQVIST, AB",
            "pnr": "702 27",
            "address": "Örebro, Skvadronv 5",
            "phone_number": "019-1199 75",
            "bank_details": {
                "bankgiro": "463-2261",
                "postgiro": "26424-2"
            },
            "activity": "Papper o förpackningar en gros",
            "employees": 20,
            "annual_turnover": 9000000,
            "capital": 25000,
            "key_personnel": [
                {
                    "name": "Tage Lernberg",
                    "position": "Verkst dir"
                }
            ],
            "establishment_year": 1925
        }
    }
}