{
    "original": "SVENSSON &amp; CO, AB GUNNAR\n\nPnr 114 44\n\nStockholm, Jungfrug 24. Tel\n08-6707 65. Bankgiro 700-2736.\nPostgiro 191536-2. Tga Gesco.\nTelex 10848\n\nVerksamhet: Import av tillbehör o\ndelar till cyklar o motorfordon,\nHELIFLEX plastslang, skruv,\ngasoldetaljer, elektrotejp m m\nAntal anställda: 6\nAktiekapital: 30 000\nVeikst dir: Curt Pettersson\nEtableringsår. 1923.\n\nTHOMÉE, TRAVARU-AB A\n\nPnr 252 29\n\nHälsingborg, Fäktmästareg 8. Tel\n042-12 63 60. Bankgiro 445-6262.\nPostgiro 263505-0. Tga Thomée\nVerksamhet: Säljer trävaror,\nbyggnadsmaterial o\ngolvbeläggningsmaterial\n\nAntal anstäUda: 45\n\nÅrsomsättning: 12 000 000\nAktiekapital: 350 000\nVerkst dir Stig Åberg\nEtableringsår 1907.\n\nHAGBERG &amp; WIN HO LM, AB\n\nPnr 11331\n\nStockholm, Sankt Eriksg 108. Tel\nkontor 08-30 0210. Expedition\nVanadis plan 3. Tel 08-3100 06. Tga\nHagwin\n\nVerksamhet: Säljer\nscreentryckma-skiner- o material. Självhäftande\nplastfolier, papper o etiketter\nAktiekapital: 100000\nVerkst dir: Ludv T Hagberg\nV verkst dir. Ragnar Winholm\nEtableringsår: 1952.\n\nTHURESSON &amp; MORCH\n\nPnr 85102\n\nSundsvall 1, Storg 11. Box 3. Tel\n060-15 07 80. Postgiro 271983. Tga\nBalticon\n\nVerksamhet: Cellulosafabriksmar\nskiner o industriförnödenheter\nÄgare o chef: Gösta Mattsson\nEtableringsår: 1915.\n\nTHURFJELL ARKITEKT.\nKONTOR AB, JAN\n\nPnr 951 00\n\nLuleå, Segelv 15. Tel 0920-107 20.\nBankgiro 758-3610. Postgiro\n386339-6\n\nAvdelningskontor. Gävle, Kar lav 4.\nTel 026-18 0170\n\nGöteborg. Kyrktorget 10, pa\nPartil-le. Tel 031-44 09 05\nNorrköping, Kristinag 10. Tel\n011-10 60 80\n\nSundsvall, Fredsg 11. Tel\n060-12 30 20\n\nUmeå, Skogens Hus. Tel\n090-118575\n\nVäxjö. Kungsg 27. Tel 0470-29030\nAkersberga, Roslagsv 9. Tel\n0764-601 70\n\nÖrnsköldsvik, Nyg 17. Tel\n0660-107 80\n\nAntal anställda: 110\nAktiekapital: 210 000\n\nVerkst dir: Ark SAR Jan Thur-\n\nfjell\n\nEtableringsår: 1957.\n\nVIC\n\nVerksamhet: Tillverkar kapsyler av\naluminium o plast, packningar\nsamt korkgolvet Kork-O-Plast\nFörsäljningskontor: Göteborg 36,\nSandénhuset Partihallarna. Box\n36067. Tel 031-1976 75. Postgiro\n12373. Tga Korkfabriken. Chef:\nDisp Olle Flyning\nFabriken Linköping.\nAlka-fabri-ken, Alkag 2. Tel 013-12 98 30.\nChef: Dir Max Krüll. Tillverkar\nfyllnings- o förslutningsmaskiner\nÄlvängen. Tel 0303-46510.\nTillverkar kork- o presskork artiklar\nAntal anställda: 491\nÅrsomsättning: 33 000 000\nAktiekapital: 8 000 000\nStyrelse: Dir G Ahlzén (ordf), dir\nBo Ax:son Johnson (v ordf), dir\nMax Krtill, dir S-A Magnusson,\ndir Sten Rystedt, dir G Wicander,\nfrih F G Åkerhielm\nVerkst dir: S-A Magnusson\nEtableringsån 1868\nOmbildat till aktiebolag 1889.\n\nVICI AB, INGENJÖRSFIRMAN\n\nPnr 42246\n\nHisings Backa, Backadalsmotet.\nTel 031-5218 62. Postgiro 241804\nVerksamhet: Tillverkar detaljer av\nvävbakelit, asbest, nylon mm\nAktiekapital: 15 000\nVerkst dir: Lennart Johansson\nEtableringsår: 1946.\n\nTRÄDCENTRALEN, AB\n\nPnr 402 24 Gbg 5\nMölndal, Abäcksg 6. Box 5226,\nGbg 5. Tel 031-81 33 00. Bankgiro\n847-899 2. Postgiro 425435-5. Tga\nSpool. Telex 20998 SPOOL S\nVerksamhet: Bomulls- o syntetisk\ntråd samt blixtlås för hushåll o\nindustriella ändamål,\nhandarbets-garner, handarbeten\nAntal anstäUda: 46\nAktiekapital: 500 000\nFirmatecknare: Dir Martin\nWhite-ford, dir Gösta Andersson\nEtableringsån 1888\nOmbildat till aktiebolag 1954.\n\nTRÅD EX, KOMMANDITBOLAG\n\nPnr 510 83\n\nSjötofta. Tel 0325-63013, 630 04.\nBankgiro 55-3165. Postgiro 510506\nVerksamhet: Tillverkar korgar o\ngaller för kyl- o frysindustrin samt\nskyltställ för industrin o handel\nAntal anstäUda: 22\nÅrsomsättning: 1000000\nChef: Dir Lennart Brage\nEtableringsår: 1959.\n\nHUVUDSTADENS ÅKERI AB\n\nPnr 117 46\n\nStockholm, Gröndalsv 118-120. Tel\n08-1901 40. Bankgiro 57-4014.\nPostgiro 155994\n\nVerksamhet: Utför schakt-,\nsprängnings- o transportarbeten\nEtableringsår 1938.\n\nBUR\n\nBURJESSON &amp; NORBERG, AB\n\nPnr 434 00\n\nKungsbacka, \"Kungsmässan\",\nBorg-mästareg 5. Tel 0300-125 70.\nBankgiro 85-2207. Postgiro 520810\nVerksamhet: Tillverkar o säljer\nalla slags plastvaror\nVarunamn: Soberplast\nAntal anställda: 20\nVerkst dir: O Börjesson\nEtableringsår: 1953.\n\nVITAMEX, AB\n\nPnr 112 20\n\nStockholm, Jacob Westinsg 2. Tel\n08-54 52 36. Bankgiro 410-8726.\nPostgiro 650025-0. Tga Vitamex\nVerksamhet: Farmacevtiska\npreparat o kemikalier\nAktiekapital: 5 000\nVerkst dir: Werner Mehks\nEtableringsår: 1960.\n\nERIKSON &amp; WESTMAN, AB\n\nPnr 112 23\n\nStockholm, Bergsg 24- Tel\n08-54 03 00. Bankgiro 568-9112.\nPostgiro 52876-0. Tga Viltlagret\nVerksamhet: Säljer lax, fågel, vilt,\nskaldjur o caviar i parti\nAktiekapital: 100 000\nVerkst dir: Sven Erikson\nEtableringsår: 1900.\n\nERIKSSON &amp; SONERS\nMOBEL-SNICKERI, AB A H\n\nPnr 610 56\n\nVrena, Mårtensdal. Tel\n0155-91001. Bankgiro 61-9080. Postgiro\n71999\n\nVerksamhet: Tillverkar bank- o\nkontorsinredningar samt möbler\nAktiekapital: 25 000\nVerkst dir: Ake Törebrant\nEtableringsår: 1907\nOmbildat till aktiebolag 1954.\n\nERIKSSON, AB A K\n\nPnr 570 30\n\nMariannelund. Tel 0496-107 40.\nBankgiro 451-4105. Postgiro\n91030-7. Tga Akeverken. Telex 3733\nVerksamhet: Tillverkar\nhydrauliska etagepressar med\nbeskickningsanordningar, mobila pressar,\nstockband sågar, bandklyvsågar,\nflerbandlinjer\nVarunamn: AKE\nAntal anställda: 71\nÅrsomsättning: 5 000 000\nAktiekapital: 500 000\nStyrelse: Overing Arvid Stenberg\n(ordf), adv Bengt Skantze,\nciviling Per Olof Stenberg\nVerkst dir: Per Olof Stenberg\nEtableringsår: 1917.\n\nERIKSSON KONSULTERANDE\nINGENJORSBYRÅ, BENGT\n\nPnr 113 55\n\nStockholm, Roslagsg 14. Tel\n08-34 61 10, 3215 60\n\nVerksamhet: Petroleumteknik,\navlopp. Specialitet: petroleum\nÄgare o chef: Ing Bengt Eriksson\nEtableringsår: 1969.\n\nERIKSSON ANNONSBYRÅ AB,\nBO\n\nPnr 114 84\n\nStockholm 5, Skepparg 8. Tel\n08-67 0100. Tga Boerikssonad\nVerksamhet: Auktoriserad\nannonsbyrå\n\nAktiekapital: 175 000\nVerkst dir: Bo Eriksson\nEtableringsår: 1956.\n\nERICSON MÅLERIFIRMA I\nGOTEBORG AB, BROR\n\nPnr 40070\n\nGöteborg 9, Karlavagnsg 22. Fack.\nTel 031-22 2140. Bankgiro 84-7963.\nPostgiro 46385\n\nVerksamhet: Utför målningsarbeten\nAntal anställda: 100\nÅrsomsättning: 4 000 000\nÄgare o chef: Dir Bror Ericson\nEtableringsår: 1935.\n\nERICSON MÅLERIFIRMA I\nUDDEVALLA AB, BROR\n\nPnr 451 00\n\nUddevalla, Föreningsg 3. Tel\n0522-33010\n\nVerksamhet: Utför målningsarbeten\nAntal anställda: 25\nÅrsomsättning: 1500 000\nAktiekapital: 50 000\nVerkst dir: Sten Pettersson\nEtableringsår: 1964.",
    "structured": {
        "1": {
            "company_name": "SVENSSON & CO, AB GUNNAR",
            "pnr": "114 44",
            "address": "Stockholm, Jungfrug 24",
            "phone_number": "08-6707 65",
            "bank_details": {
                "bankgiro": "700-2736",
                "postgiro": "191536-2"
            },
            "activity": "Import av tillbehör o delar till cyklar o motorfordon, HELIFLEX plastslang, skruv, gasoldetaljer, elektrotejp m m",
            "employees": 6,
            "capital": 30000,
            "key_personnel": [
                {
                    "name": "Curt Pettersson",
                    "position": "Veikst dir"
                }
            ],
            "establishment_year": 1923
        },
        "2": {
            "company_name": "THOMÉE, TRAVARU-AB A",
            "pnr": "252 29",
            "address": "Hälsingborg, Fäktmästareg 8",
            "phone_number": "042-12 63 60",
            "bank_details": {
                "bankgiro": "445-6262",
                "postgiro": "263505-0"
            },
            "activity": "Säljer trävaror, byggnadsmaterial o golvbeläggningsmaterial",
            "employees": 45,
            "annual_turnover": 12000000,
            "capital": 350000,
            "key_personnel": [
                {
                    "name": "Stig Åberg",
                    "position": "Verkst dir"
                }
            ],
            "establishment_year": 1907
        },
        "3": {
            "company_name": "HAGBERG & WIN HO LM, AB",
            "pnr": "11331",
            "address": "Stockholm, Sankt Eriksg 108",
            "phone_number": "kontor 08-30 0210, Expedition Vanadis plan 3, Tel 08-3100 06",
            "activity": "Säljer screentryckmaskiner- o material, självhäftande plastfolier, papper o etiketter",
            "capital": 100000,
            "key_personnel": [
                {
                    "name": "Ludv T Hagberg",
                    "position": "Verkst dir"
                },
                {
                    "name": "Ragnar Winholm",
                    "position": "V verkst dir"
                }
            ],
            "establishment_year": 1952
        },
        "4": {
            "company_name": "THURESSON & MORCH",
            "pnr": "85102",
            "address": "Sundsvall 1, Storg 11, Box 3",
            "phone_number": "060-15 07 80",
            "postgiro": "271983",
            "activity": "Cellulosafabriksmaskiner o industriförnödenheter",
            "key_personnel": [
                {
                    "name": "Gösta Mattsson",
                    "position": "Ägare o chef"
                }
            ],
            "establishment_year": 1915
        },
        "5": {
            "company_name": "THURFJELL ARKITEKT. KONTOR AB, JAN",
            "pnr": "951 00",
            "address": "Luleå, Segelv 15",
            "phone_number": "0920-107 20",
            "bankgiro": "758-3610",
            "postgiro": "386339-6",
            "employees": 110,
            "capital": 210000,
            "key_personnel": [
                {
                    "name": "Ark SAR Jan Thur-fjell",
                    "position": "Verkst dir"
                }
            ],
            "establishment_year": 1957
        }
    }
}