{
    "original": "EL EKTROCENTRALEN, AB\n\nPnr 400 11\n\nGöteborg 18, Avägen 17. Box\n18015. Tel 031-8130 10. Bankgiro\n50-0581. Postgiro 425605. Tga\nElcentral\n\nVerksamhet: Elektr\ninstallationsmateriel, apparater, m m\nAntal anställda: 50\nÅrsomsättning: 8 000 000\nAktiekapital: 300 000\nVerkst dir: Ing Roland Strömbäck\nEtableringsår: 1952.\n\nELEKTROCENTRALEN I\nNORRKOPING AB\n\nPnr 60103\n\nNorrköping 1, Box 94. Tel Oll-\n\nIO 66 30. Godsadress: Fredriksdalsg\n16. Bankgiro 609-9147. Postgiro\n329653-0. Tga Abelcentral\nVerksamhet: Säljer elektr installar\ntionsmaterial samt elektr\nledningsmaterial för svag- o starkström\nAntal anställda: 20\nÅrsomsättning: 11000 000\nAktiekapital: 100 000\nVerkst dir: B N G Nilsson\nEtableringsår: 1947\nOmbildat till Aktiebolag 1952.\nEtt SELGA företag.\n\nELEKTRO-DAHLEN AB\n\nPnr 500 04\n\nBorås 4, Björkhemsg 20. Box44049.\nTel 033-12 77 00. Bankgiro 84-3493.\nPostgiro 336829. Tfea Eldahlén\nVerksamhet: Elektr o eljeeldade\nbakugnar, jäsrum o jässkåp för\n\nbagerier o konditorier, jäsbanor,\nkylbanor samt elektr tork- o\nlackeringsugnar för industrin\nAntal anställda: 65\nÅrsomsättning: 6 000 000\nAktiekapital: 200 000\nVerkst dir Disp K E Dahlén\nEtableringsår 1948.\n\nHJÄRNARPS MEK VERKSTAD\n\nPnr 260 84\n\nHjämaip, Box65. Tel 0431-540 41.\nPostgiro 6322-2\n\nVerksamhet: Tillverkar\ngymnastikredskap i stål\n\nÄgare o chef: Harald Ehlorsson\nEtableringsår: 1919.\n\nNAMI, VERKSTADS AB\n\nPnr 29010\n\nTollarp, Box 594. Tel 0450-102 72.\nBankgiro 665-6383. Postgiro\n662050-4\n\nVerksamhet: Tillverkar\nlantbruksvagnar\n\nAntal anställda: 10\nÅrsomsättning: 1000 000\nAktiekapital: 15 000\nVerkst din Ivar Jönsson\nEtableringsån 1944.\n\nFRANKSSON &amp; CO, ROLF\n\nPnr 81600\n\nOckelbo, Box 6. Tel 0297-400 0 2,\n40402. Bankgiro 237-9337.\nPostgiro 448524-9. Tga Franksson\nVerksamhet: Hyvlade o ohyvlade\nträvaror, specialitet: Listverk\nAntal anställda: 15\nÄgare o chef: Civiling Rolf\nFranksson.\n\nFRANSSON, FRANZON\n\nFRANSSON &amp; BRANTEMO AB\n\nPnr 598 00\n\nVimmerby, Rönnbärsg. Tel\n0492-11150\n\nVerksamhet: Tillverkar\ngängmaskiner för utvändig gängning,\ntransportabla o stationära\nAktiekapital: 50 000\nVerkst dir: Karl Erik Fransson\nEtableringsår: 1952.\n\nFRANSSONS VERKSTADS AB,\nBRUDERNA\n\nPnr 591 00\n\nMotala, Fågelsta. Tel 0141-30170.\nBankgiro 13-4223. Postgiro 135132\nVerksamhet: Tillverkar skottkärror,\ntransportvagnar, murbruksbaljor,\nluftgummihjul, båttrailer\nVarunamn: B.F.\nAntal anställda: 45\nÅrsomsättning: 5 000 000\nAktiekapital: 75 000\n\nÄgare o chefer: Harry Fransson,\nOlof Fransson\nEtableringsår: 1934.\n\nFRANSSONS VERKSTÄDER, AB\n\nIngenjörsfirma A Fransson\n\nPnr 850 04\n\nSundsvall 4, Box 4010. Tel\n060-15 06 80. Bankgiro 77-4333.\nPostgiro 297048-1. Tga Fläktfransson\nVerksamhet: Tillverkar o säljer\nrivare, industrifläktar\nÅrsomsättning: 1000 000\nAktiekapital: 20 000\nVerkst dir: Arne Fransson\nEtableringsår: 1945.\n\nFRANSSONS FABRIKER AB,\nERIK\n\nPnr 560 27\n\nTenhult. Tel 036-916 10\nVerksamhet: Tillverkar möbler,\nbyråar, möbelhandtag i trä\n.Antal anställda: 80\nÅrsomsättning: 6 500 000\nAktiekapital: 250 000\nVerkst dir: Erik Fransson\nEtableringsår: 1936.\n\nFRANZONS ELEKTRISKA AB\nROSLAGENS ELEKTRISKA, O\n\nPnr 76100\n\nNorrtälje, Tullportsg 10. Tel\n0176-12610, 105 35. Bankgiro 45-1757.\nPostgiro 34640\n\nVerksamhet: Säljer armatur,\nkylskåp, tvättmaskiner, radio, TV, m m.\nElektr installationsrörelse o\nlinjebyggnader. Reparationsverkstad\nAntal anställda: 52\nVerkst dir: Olle Franzon\nEtableringsår 1921.\n\nBJÖRLING AB, HERBERT\n\nPnr 200 13\n\nMalmö 27, Box 27083. Borrg 3. Tel\n040-18 12 30. Bankgiro 870-2417.\nPostgiro 37599-8. Tga Håbe\nVerksamhet: Säljer järn, metaller,\nmaskiner, verktyg o\nbyggnadsmaterial\n\nAktiekapital: 60 000\nVerkst din Ulla Edgren\nEtableringsår: 1928.\n\nROSTFRIA ARBETEN AB\n\nPnr 16111\n\nBromma 11, Ulvsundav 110. Box\n11006. Tel 08-25 25 75. Bankgiro\n21-1277. Postgiro 151953\nVerksamhet: Tillverkar\nentrépartier, butiksfasader o inredningar,\nlanterniner o fönsterband\nAktiekapital: 50 000\nVerkst dir: John Erikson\nEtableringsår: 1937.\n\nIDE\n\nIDECA, AB\n\nPnr 103 65\n\nStockholm 3, Saltmätarg 14. Box\n3290. Tel 08-24 5225. Bankgiro\n168-8977. Postgiro 131777-5. Tga\nIdecabolag\n\nVerksamhet: Säljer\nkopieringsapparater samt textmaskiner för\nritningar\n\nAntal anställda: 10\nÅrsomsättning: 1200 000\nAktiekapital: 5 000\nVerkst dir: Evert Friberg.\n\nIDÉPRODUKTION\nBENGT FRESK AB\n\nPnr 421 22\n\nVästra Frölunda 1, Box 188.\nFrö-husg 4. Tel 031-4506 20. Bankgiro\n400-4727. Postgiro 721442-2\nVerksamhet: Direktreklam, adresser\nAntal anställda: 18\nÅrsomsättning: 1100 000\nAktiekapital: 5 000\nVerkst dir: Bengt Fresk\nEtableringsår. 1969.\n\nWILSOC AB\n\nPnr 523 00\n\nUlricehamn, Dalg 6. Tel\n0321-10431, 11158. Bankgiro 84-4271.\nPostgiro 331285\nVerksamhet: Tillverkar herr- o\nbarnstrumpor samt strumpbyxor\nAntal anställda: 15\nÅrsomsättning: 1000 000\nVerkst dir: Fabr Sune Claesson\nEtableringsår: 1947.\n\nmb-bolagen ab\n\nPnr 17154\n\nSolna, Vretenv 8. Tel 08-28 28 35.\nBankgiro 560-5902. Postgiro\n598220-2. Tga Embebolagen.\nTelex 19307 BERPROD S\nVerksamhet: Säljer tejp o\nslipmaterial. Exporterar tejpdispenser\nVarunamn: Canada Sand Papers\nLtd, Embe, Tuck\nÅrsomsättning: 2 500 000\nVerkst dir: Ing J Ettlinger\nFörsäljn chef: Hans Berg\nEtableringsår: 1962.\n\nNORSHOLMS SÅGVERKS AB\n\nPnr 610 21\n\nNorsholm, Box 8. Tel 011-540 63.\nBankgiro 61-0000. Postgiro 12974\nVerksamhet: Säljer sågade o hyvlar\nde trävaror\nAntal anställda: 15\nÅrsomsättning: 1800 000\nAktiekapital: 100 000\nVerkst dir: Karl-David Ekström\nEtableringsår 1926.",
    "structured": {
        "1": {
            "company_name": "EL EKTROCENTRALEN, AB",
            "pnr": "400 11",
            "address": "Göteborg 18, Avägen 17. Box 18015",
            "phone_number": "031-8130 10",
            "bank_details": {
                "bankgiro": "50-0581",
                "postgiro": "425605"
            },
            "activity": "Elektr installationsmateriel, apparater, m m",
            "employees": 50,
            "annual_turnover": 8000000,
            "capital": 300000,
            "key_personnel": [
                {
                    "name": "Ing Roland Strömbäck",
                    "position": "Verkst dir"
                }
            ],
            "establishment_year": 1952
        },
        "2": {
            "company_name": "ELEKTROCENTRALEN I NORRKOPING AB",
            "pnr": "60103",
            "address": "Norrköping 1, Box 94",
            "phone_number": "Oll-IO 66 30",
            "bank_details": {
                "bankgiro": "609-9147",
                "postgiro": "329653-0"
            },
            "activity": "Säljer elektr installationsmaterial samt elektr ledningsmaterial för svag- o starkström",
            "employees": 20,
            "annual_turnover": 11000000,
            "capital": 100000,
            "key_personnel": [
                {
                    "name": "B N G Nilsson",
                    "position": "Verkst dir"
                }
            ],
            "establishment_year": 1947
        },
        "3": {
            "company_name": "ELEKTRO-DAHLEN AB",
            "pnr": "500 04",
            "address": "Borås 4, Björkhemsg 20. Box 44049",
            "phone_number": "033-12 77 00",
            "bank_details": {
                "bankgiro": "84-3493",
                "postgiro": "336829"
            },
            "activity": "Elektr o eljeeldade bakugnar, jäsrum o jässkåp för bagerier o konditorier, jäsbanor, kylbanor samt elektr tork- o lackeringsugnar för industrin",
            "employees": 65,
            "annual_turnover": 6000000,
            "capital": 200000,
            "key_personnel": [
                {
                    "name": "Disp K E Dahlén",
                    "position": "Verkst dir"
                }
            ],
            "establishment_year": 1948
        },
        "4": {
            "company_name": "HJÄRNARPS MEK VERKSTAD",
            "pnr": "260 84",
            "address": "Hjämaip, Box65",
            "phone_number": "0431-540 41",
            "postgiro": "6322-2",
            "activity": "Tillverkar gymnastikredskap i stål",
            "key_personnel": [
                {
                    "name": "Harald Ehlorsson",
                    "position": "Ägare o chef"
                }
            ],
            "establishment_year": 1919
        },
        "5": {
            "company_name": "NAMI, VERKSTADS AB",
            "pnr": "29010",
            "address": "Tollarp, Box 594",
            "phone_number": "0450-102 72",
            "bankgiro": "665-6383",
            "postgiro": "662050-4",
            "activity": "Tillverkar lantbruksvagnar",
            "employees": 10,
            "annual_turnover": 1000000,
            "capital": 15000,
            "key_personnel": [
                {
                    "name": "Ivar Jönsson",
                    "position": "Verkst dir"
                }
            ],
            "establishment_year": 1944
        },
        "6": {
            "company_name": "FRANKSSON &amp; CO, ROLF",
            "pnr": "81600",
            "address": "Ockelbo, Box 6",
            "phone_number": "0297-400 0 2, 40402",
            "bankgiro": "237-9337",
            "postgiro": "448524-9",
            "activity": "Hyvlade o ohyvlade trävaror, specialitet: Listverk",
            "employees": 15,
            "key_personnel": [
                {
                    "name": "Civiling Rolf Franksson",
                    "position": "Ägare o chef"
                }
            ]
        },
        "7": {
            "company_name": "FRANSSON, FRANZON FRANSSON &amp; BRANTEMO AB",
            "pnr": "598 00",
            "address": "Vimmerby, Rönnbärsg",
            "phone_number": "0492-11150",
            "activity": "Tillverkar gängmaskiner för utvändig gängning, transportabla o stationära",
            "capital": 50000,
            "key_personnel": [
                {
                    "name": "Karl Erik Fransson",
                    "position": "Verkst dir"
                }
            ],
            "establishment_year": 1952
        },
        "8": {
            "company_name": "FRANSSONS VERKSTADS AB, BRUDERNA",
            "pnr": "591 00",
            "address": "Motala, Fågelsta",
            "phone_number": "0141-30170",
            "bank_details": {
                "bankgiro": "13-4223",
                "postgiro": "135132"
            },
            "activity": "Tillverkar skottkärror, transportvagnar, murbruksbaljor, luftgummihjul, båttrailer",
            "employees": 45,
            "annual_turnover": 5000000,
            "capital": 75000,
            "key_personnel": [
                {
                    "name": "Harry Fransson",
                    "position": "Ägare"
                },
                {
                    "name": "Olof Fransson",
                    "position": "Chefer"
                }
            ],
            "establishment_year": 1934
        },
        "9": {
            "company_name": "FRANSSONS VERKSTÄDER, AB Ingenjörsfirma A Fransson",
            "pnr": "850 04",
            "address": "Sundsvall 4, Box 4010",
            "phone_number": "060-15 06 80",
            "bankgiro": "77-4333",
            "postgiro": "297048-1",
            "activity": "Tillverkar o säljer rivare, industrifläktar",
            "annual_turnover": 1000000,
            "capital": 20000,
            "key_personnel": [
                {
                    "name": "Arne Fransson",
                    "position": "Verkst dir"
                }
            ],
            "establishment_year": 1945
        },
        "10": {
            "company_name": "FRANSSONS FABRIKER AB, ERIK",
            "pnr": "560 27",
            "address": "Tenhult",
            "phone_number": "036-916 10",
            "activity": "Tillverkar möbler, byråar, möbelhandtag i trä",
            "employees": 80,
            "annual_turnover": 6500000,
            "capital": 250000,
            "key_personnel": [
                {
                    "name": "Erik Fransson",
                    "position": "Verkst dir"
                }
            ],
            "establishment_year": 1936
        },
        "11": {
            "company_name": "FRANZONS ELEKTRISKA AB ROSLAGENS ELEKTRISKA, O",
            "pnr": "76100",
            "address": "Norrtälje, Tullportsg 10",
            "phone_number": "0176-12610, 105 35",
            "bankgiro": "45-1757",
            "postgiro": "34640",
            "activity": "Säljer armatur, kylskåp, tvättmaskiner, radio, TV, m m. Elektr installationsrörelse o linjebyggnader. Reparationsverkstad",
            "employees": 52,
            "key_personnel": [
                {
                    "name": "Olle Franzon",
                    "position": "Verkst dir"
                }
            ],
            "establishment_year": 1921
        },
        "12": {
            "company_name": "BJÖRLING AB, HERBERT",
            "pnr": "200 13",
            "address": "Malmö 27, Box 27083. Borrg 3",
            "phone_number": "040-18 12 30",
            "bankgiro": "870-2417",
            "activity": "Säljer järn, metaller, maskiner, verktyg o byggnadsmaterial",
            "capital": 60000,
            "key_personnel": [
                {
                    "name": "Ulla Edgren",
                    "position": "Verkst din"
                }
            ],
            "establishment_year": 1928
        },
        "13": {
            "company_name": "ROSTFRIA ARBETEN AB",
            "pnr": "16111",
            "address": "Bromma 11, Ulvsundav 110. Box 11006",
            "phone_number": "08-25 25 75",
            "bankgiro": "21-1277",
            "postgiro": "151953",
            "activity": "Tillverkar entrépartier, butiksfasader o inredningar, lanterniner o fönsterband",
            "capital": 50000,
            "key_personnel": [
                {
                    "name": "John Erikson",
                    "position": "Verkst dir"
                }
            ],
            "establishment_year": 1937
        },
        "14": {
            "company_name": "IDE IDECA, AB",
            "pnr": "103 65",
            "address": "Stockholm 3, Saltmätarg 14. Box 3290",
            "phone_number": "08-24 5225",
            "bankgiro": "168-8977",
            "postgiro": "131777-5",
            "activity": "Säljer kopieringsapparater samt textmaskiner för ritningar",
            "employees": 10,
            "annual_turnover": 1200000,
            "capital": 5000,
            "key_personnel": [
                {
                    "name": "Evert Friberg",
                    "position": "Verkst dir"
                }
            ]
        },
        "15": {
            "company_name": "IDÉPRODUKTION BENGT FRESK AB",
            "pnr": "421 22",
            "address": "Västra Frölunda 1, Box 188. Frö-husg 4",
            "phone_number": "031-4506 20",
            "bankgiro": "400-4727",
            "postgiro": "721442-2",
            "activity": "Direktreklam, adresser",
            "employees": 18,
            "annual_turnover": 1100000,
            "capital": 5000,
            "key_personnel": [
                {
                    "name": "Bengt Fresk",
                    "position": "Verkst dir"
                }
            ],
            "establishment_year": 1969
        },
        "16": {
            "company_name": "WILSOC AB",
            "pnr": "523 00",
            "address": "Ulricehamn, Dalg 6",
            "phone_number": "0321-10431, 11158",
            "bankgiro": "84-4271",
            "postgiro": "331285",
            "activity": "Tillverkar herr- o barnstrumpor samt strumpbyxor",
            "employees": 15,
            "annual_turnover": 1000000,
            "key_personnel": [
                {
                    "name": "Fabr Sune Claesson",
                    "position": "Verkst dir"
                }
            ],
            "establishment_year": 1947
        },
        "17": {
            "company_name": "mb-bolagen ab",
            "pnr": "17154",
            "address": "Solna, Vretenv 8",
            "phone_number": "08-28 28 35",
            "bankgiro": "560-5902",
            "postgiro": "598220-2",
            "activity": "Säljer tejp o slipmaterial. Exporterar tejpdispenser",
            "employees": "Ing J Ettlinger",
            "key_personnel": {
                "name": "Hans Berg",
                "position": "Försäljn chef"
            },
            "annual_turnover": 2500000,
            "establishment_year": 1962
        },
        "18": {
            "company_name": "NORSHOLMS SÅGVERKS AB",
            "pnr": "610 21",
            "address": "Norsholm, Box 8",
            "phone_number": "011-540 63",
            "bankgiro": "61-0000",
            "postgiro": "12974",
            "activity": "Säljer sågade o hyvlarde trävaror",
            "employees": 15,
            "annual_turnover": 1800000,
            "capital": 100000,
            "key_personnel": [
                {
                    "name": "Karl-David Ekström",
                    "position": "Verkst dir"
                }
            ],
            "establishment_year": 1926
        }
    }
}