{
    "original": "INDUSTRIKOMPONENTER AB\n\nPnr 12612 Sthlm 42\nHägersten, Svandammsv 4 B. Box\n42008, Sthlm 42. Tel 08-18 83 40.\nBankgiro 807-0104. Postgiro\n407272-4. Tga Induskom.\nTelex 1636 INKOM S\nVerksamhet: Import o försäljning\nav elektrotekniska komponenter\nVarunamn: Binder, Inkom, Olten,\nSchaltbau, Tesch\nAntal anställda: 8\nÅrsomsättning: 3 000 000\nAktiekapital: 100000\nVerkst dir: H Federsel\nEtableringsår: 1967.\n\nDAHLBERG, AB SEVERIN\n\nPnr 112 20\n\nStockholm, N Mälarstrand 8-10.\nTel 08-24 08 40, 54 93 00. Bankgiro\n73-4063. Postgiro 1580\nVeiksamhet: Säljer\nträimpregne-ringsmedel o plastpresenningar\nAktiekapital: 65 000\nVerkst dir: Lars-Erik Björkman\nEtableringsår: 1880.\n\nGUSTAFSSON AB, BIRGER\n\nPnr 114 32\n\nStockholm, Engelbrektsg 21. Tel\n08-23 20 20. Bankgiro 476-8529.\nPostgiro 3263-1. Tga Kuvertbolaget\nVerksamhet: Tillverkar kuvert o\nkartonger. Säljer papper\nAktiekapital: 75 000\nChef: Dir Bo Gustafsson\nEtableringsår: 1908.\n\nLE KOMA, AB\n\nPnr 60102\n\nNorrköping 1, Fabriksg 14-16.Box\n41. Tel 011-1002 25. Bankgiro\n349-2360. Postgiro 30318-0\nVerksamhet: Säljer basar o\ntombo-lavaror\n\nAntal anställda: 15\nÅrsomsättning: 3 000 000\nAktiekapital: 35 000\nVerkst dir: Ragnar Lindstam\nEtableringsår: 1926.\n\nLEKSANDS TRYCKERI AB\nLTAB- OFFSET\n\nPnr 793 00\n\nLeksand, Box 89. Rättviksv. Tel\n0247-119 66, 11168\nVerksamhet: Offsettryckeri\nAntal anställda: 22\nÅrsomsättning: 1500 000\nAktiekapital: 75 000\nVerkst dir: Klas Collin\nEtableringsår: 1960.\n\nFRIFE AB\n\nPnr 12149\n\nJohanneshov, Paternosterv 58. Tel\n08-48 52 41, 48 5219. Bankgiro\n73-1094. Postgiro 54746. Telex 10802.\nTga Frifeab\n\nVerksamhet: Handels- o\nagenturrörelse i verktyg o maskiner\nAntal anställda: 5\nAktiekapital: 20 000\nEtableringsår: 1941.\n\nFRIGGERÅKERS RUR AB,\nEFRAB, E\n\nPnr 521 01\n\nFalköping 1, Hollenderg 30. Box\n61. Tel 0515-131 65. Bankgiro\n213-7503. Postgiro 131870-8. Tga Efrab\nVerksamhet: Utför värme-,\nsanitets-o oljeeldningsinstallationer\nAntal anställda: 15\nÅrsomsättning: 1500 000\nAktiekapital: 30 000\nVerkst dir: Fabr Evert Friggeråker\nEtableringsår: 1929.\n\nFRIGGERÅKERS\nVERK-STADER AB\n\nPnr 52100\n\nFalköping, Skövdev. Tel\n0515-11078,140 40. Postgiro262665-3\nVerksamhet: Tillverkar\nsandsprida-re, containers o byggnadssmide\nAntal anställda: 15\nAktiekapital: 24 000\nVerkst dir: B G E Friggeråker\nEtableringsår: 1948.\n\nL-E ENTREPRENAD AB\n\nPnr 600 06\n\nNorrköping 6, Box 6004. Tel\n011-183134, 183131. Postgiro 9924-2\nVerksamhet: Uthyrning av\nväghyv-lar samt kompressorer\nÅrsomsättning: 600000\nAktiekapital: 5 000\nVerkst dir: LE Ringborg\nEtableringsår: 1957.\n\nTYDÉN AB, BIRGER\n\nPnr 12145\n\nJohanneshov, Thunbergsg 27. Tel\n08-59 39 55. Bankgiro 563-1320.\nPostgiro 351112-8. Tga Tydénpen\nVerksamhet: Säljer kontorsartiklar\no presentreklam\nAktiekapital: 10 000\nVerkst dir: Birger Tydén.\n\nTYGELSJO KEMISKA\nFABRIKER, AB\n\nPnr 23042\n\nTygelsjö. Tel 040-46 62 79, 46 6 4 75.\nBankgiro 260-1482. Postgiro\n439449-0. Tga Tykefa\nVerksamhet: Tillverkar o säljer\nbiologiskt nedbrytningsbara\navfett-nings- o avvaxningsmedel,\nrengöringsmedel, golvpreparat, flytande\ntvål mm\n\nAvdelningskontor: 431 37 Mölndal,\nSörgàrdsg 21. Tel 031-16 32 18\nChef: Dir Gunnar Svensson\nEtableringsån 1954.\n\nVEBE-BETONG, AB\n\nPnr 574 00\n\nVetlanda, Björköby. Tel\n0383-312 00. Bankgiro 144-9743.\nPostgiro 10831-6. Tga Vebe\nVerksamhet Betongvaror,\nfabriks-blandad betong\nAntal anställda: 35\nÅrsomsättning: 2500 000\nAktiekapital: 62 000\nFabrikschef: Ing Yngve Romeling\nEtableringsår: 1921.\n\nGAT. och KANTSTEN,\nFÖRSÄLJNINGS AB\n\nPnr 411 36\n\nGöteborg, Kungsportsavenyn 1. Tel\n031-17 88 00. Bankgiro 50-0918.\nPostgiro 428275. Tga Granitab\nVerksamhet: Säljer gat- o kantsten\nav granit\n\nAntal anstäUda: 6\nÅrsomsättning: 18 000 000\n.Aktiekapital: 20 000\nStyrelse: Dir Bo Estberger (ordf),\ndir Nils Andersson, disp Gerhard\nBeer, dir Hjalmar Höij, disp S\nNorrby, förest Dick Svanberg\nVerkst dir: Torsten Springer\nFörsäljn-chef: Harry Erheden\nKamrer: Fru Gun Blanch\nEtableringsår: 1954.\n\nAGRO-SHIPPING AB\n\nPnr 103 23\n\nStockholm 16, Box 16137.\nMalm-torgsg 5. Tel 08-23 33 00. Postgiro\n705830. Tga Agroship. Telex 10868\nVerksamhet: Befraktare för\nJordbrukets Ekonomiska\nFörenings-rörelse\n\nAntal anställda: 14\nAktiekapital: 15 000\nVerkst dir: Nils Nierenburg\nEtableringsår: 1964.",
    "structured": {
        "1": {
            "company_name": "INDUSTRIKOMPONENTER AB",
            "pnr": "12612 Sthlm 42",
            "address": "Hägersten, Svandammsv 4 B, Box 42008, Sthlm 42",
            "phone_number": "08-18 83 40",
            "bank_details": {
                "bankgiro": "807-0104",
                "postgiro": "407272-4"
            },
            "activity": "Import och försäljning av elektrotekniska komponenter",
            "employees": 8,
            "annual_turnover": 3000000,
            "capital": 100000,
            "key_personnel": [
                {
                    "name": "H Federsel",
                    "position": "Verkst dir"
                }
            ],
            "establishment_year": 1967
        },
        "2": {
            "company_name": "DAHLBERG, AB SEVERIN",
            "pnr": "112 20",
            "address": "Stockholm, N Mälarstrand 8-10",
            "phone_number": "08-24 08 40, 54 93 00",
            "bank_details": {
                "bankgiro": "73-4063",
                "postgiro": "1580"
            },
            "activity": "Säljer träimpregneringsmedel och plastpresenningar",
            "capital": 65000,
            "key_personnel": [
                {
                    "name": "Lars-Erik Björkman",
                    "position": "Verkst dir"
                }
            ],
            "establishment_year": 1880
        },
        "3": {
            "company_name": "GUSTAFSSON AB, BIRGER",
            "pnr": "114 32",
            "address": "Stockholm, Engelbrektsg 21",
            "phone_number": "08-23 20 20",
            "bank_details": {
                "bankgiro": "476-8529",
                "postgiro": "3263-1"
            },
            "activity": "Tillverkar kuvert och kartonger, säljer papper",
            "capital": 75000,
            "key_personnel": [
                {
                    "name": "Bo Gustafsson",
                    "position": "Chef"
                }
            ],
            "establishment_year": 1908
        },
        "4": {
            "company_name": "LE KOMA, AB",
            "pnr": "60102",
            "address": "Norrköping 1, Fabriksg 14-16, Box 41",
            "phone_number": "011-1002 25",
            "bank_details": {
                "bankgiro": "349-2360",
                "postgiro": "30318-0"
            },
            "activity": "Säljer basar och tomlobaror",
            "employees": 15,
            "annual_turnover": 3000000,
            "capital": 35000,
            "key_personnel": [
                {
                    "name": "Ragnar Lindstam",
                    "position": "Verkst dir"
                }
            ],
            "establishment_year": 1926
        },
        "5": {
            "company_name": "LEKSANDS TRYCKERI AB LTAB-OFFSET",
            "pnr": "793 00",
            "address": "Leksand, Box 89, Rättviksv",
            "phone_number": "0247-119 66, 11168",
            "activity": "Offsettryckeri",
            "employees": 22,
            "annual_turnover": 1500000,
            "capital": 75000,
            "key_personnel": [
                {
                    "name": "Klas Collin",
                    "position": "Verkst dir"
                }
            ],
            "establishment_year": 1960
        },
        "6": {
            "company_name": "FRIFE AB",
            "pnr": "12149",
            "address": "Johanneshov, Paternosterv 58",
            "phone_number": "08-48 52 41, 48 5219",
            "bank_details": {
                "bankgiro": "73-1094",
                "postgiro": "54746"
            },
            "activity": "Handels- och agenturrörelse i verktyg och maskiner",
            "employees": 5,
            "capital": 20000,
            "establishment_year": 1941
        },
        "7": {
            "company_name": "FRIGGERÅKERS RUR AB, EFRAB, E",
            "pnr": "521 01",
            "address": "Falköping 1, Hollenderg 30, Box 61",
            "phone_number": "0515-131 65",
            "bank_details": {
                "bankgiro": "213-7503",
                "postgiro": "131870-8"
            },
            "activity": "Utför värme-, sanitets- och oljeeldningsinstallationer",
            "employees": 15,
            "annual_turnover": 1500000,
            "capital": 30000,
            "key_personnel": [
                {
                    "name": "Fabr Evert Friggeråker",
                    "position": "Verkst dir"
                }
            ],
            "establishment_year": 1929
        },
        "8": {
            "company_name": "FRIGGERÅKERS VERKSTADER AB",
            "pnr": "52100",
            "address": "Falköping, Skövdev",
            "phone_number": "0515-11078, 140 40",
            "postgiro": "262665-3",
            "activity": "Tillverkar sandspridare, containers och byggnadssmide",
            "employees": 15,
            "capital": 24000,
            "key_personnel": [
                {
                    "name": "B G E Friggeråker",
                    "position": "Verkst dir"
                }
            ],
            "establishment_year": 1948
        },
        "9": {
            "company_name": "L-E ENTREPRENAD AB",
            "pnr": "600 06",
            "address": "Norrköping 6, Box 6004",
            "phone_number": "011-183134, 183131",
            "postgiro": "9924-2",
            "activity": "Uthyrning av väghyvlar samt kompressorer",
            "annual_turnover": 600000,
            "capital": 5000,
            "key_personnel": [
                {
                    "name": "LE Ringborg",
                    "position": "Verkst dir"
                }
            ],
            "establishment_year": 1957
        },
        "10": {
            "company_name": "TYDÉN AB, BIRGER",
            "pnr": "12145",
            "address": "Johanneshov, Thunbergsg 27",
            "phone_number": "08-59 39 55",
            "bank_details": {
                "bankgiro": "563-1320",
                "postgiro": "351112-8"
            },
            "activity": "Säljer kontorsartiklar och presentreklam",
            "capital": 10000,
            "key_personnel": [
                {
                    "name": "Birger Tydén",
                    "position": "Verkst dir"
                }
            ]
        },
        "11": {
            "company_name": "TYGELSJO KEMISKA FABRIKER, AB",
            "pnr": "23042",
            "address": "Tygelsjö",
            "phone_number": "040-46 62 79, 46 6 4 75",
            "bank_details": {
                "bankgiro": "260-1482",
                "postgiro": "439449-0"
            },
            "activity": "Tillverkar och säljer biologiskt nedbrytningsbara avfettnings- och avvaxningsmedel, rengöringsmedel, golvpreparat, flytande tvål mm",
            "employees": null,
            "capital": null,
            "key_personnel": [
                {
                    "name": "Gunnar Svensson",
                    "position": "Chef"
                }
            ],
            "establishment_year": 1954
        },
        "12": {
            "company_name": "VEBE-BETONG, AB",
            "pnr": "574 00",
            "address": "Vetlanda, Björköby",
            "phone_number": "0383-312 00",
            "bank_details": {
                "bankgiro": "144-9743",
                "postgiro": "10831-6"
            },
            "activity": "Betongvaror, fabriksblandad betong",
            "employees": 35,
            "annual_turnover": 2500000,
            "capital": 62000,
            "key_personnel": [
                {
                    "name": "Ing Yngve Romeling",
                    "position": "Fabrikschef"
                }
            ],
            "establishment_year": 1921
        },
        "13": {
            "company_name": "GAT. och KANTSTEN, FÖRSÄLJNINGS AB",
            "pnr": "411 36",
            "address": "Göteborg, Kungsportsavenyn 1",
            "phone_number": "031-17 88 00",
            "bank_details": {
                "bankgiro": "50-0918",
                "postgiro": "428275"
            },
            "activity": "Säljer gat- och kantsten av granit",
            "employees": 6,
            "annual_turnover": 18000000,
            "capital": 20000,
            "key_personnel": [
                {
                    "name": "Bo Estberger",
                    "position": "Styrelse"
                },
                {
                    "name": "Nils Andersson",
                    "position": "Styrelse"
                },
                {
                    "name": "Gerhard Beer",
                    "position": "Disp"
                },
                {
                    "name": "Hjalmar Höij",
                    "position": "Dir"
                },
                {
                    "name": "S Norrby",
                    "position": "Disp"
                },
                {
                    "name": "Dick Svanberg",
                    "position": "Förest"
                }
            ],
            "establishment_year": 1954
        },
        "14": {
            "company_name": "AGRO-SHIPPING AB",
            "pnr": "103 23",
            "address": "Stockholm 16, Box 16137, Malm-torgsg 5",
            "phone_number": "08-23 33 00",
            "postgiro": "705830",
            "activity": "Befraktare för Jordbrukets Ekonomiska Föreningsrörelse",
            "employees": 14,
            "capital": 15000,
            "key_personnel": [
                {
                    "name": "Nils Nierenburg",
                    "position": "Verkst dir"
                }
            ],
            "establishment_year": 1964
        }
    }
}