{
    "original": "TOLLARPS VÄVERI AB\n\nPnr 290 10\n\nTollarp, Box 4. Tel 0450-104 40.\nPostgiro 371875. Tga Tollarpväv\nVerksamhet: Tillverkar o säljer\ntwillser för arbetskläder\nAntal anställda: 30\nÅrsomsättning: 3 500 000\nAktiekapital: 600 000\nStyrelse: Dir John Magnuson (ordf),\ndir Bertil Magnuson, ing Birger\nMagnuson\n\nVerkst dir: Bertil Magnuson\nV verkst dir: Birger Magnuson\nPlatschef: Vävmäst Orvar Sjöbåge\nEtableringsår 1949\nOmbildat till aktiebolag 1952.\n\nTOLLMAR&amp; ENGLUND, AB\n\nPnr 570 21\n\nMalmbäck, Torget 1. Tel\n0380-600 01, 60126. Tga Tolleng\nVerksamhet: Import- o\ngrossist-firma för kakel, mosaik, panel,\ndörrar etc\n\nAktiekapital: 40 000\nVerkst dir: Sture Tollmar\nEtableringsår 1952.\n\nSVENSKA FORMALIN AB\n\nPnr 100 61\n\nStockholm 11, Sickla. Box 11010.\n\nTel 08-44 90 40. Postgiro 191869.\n\nTga Svenskformalin. Telex 10154\n\nVerksamhet: Säljer formalin\n\nAktiekapital: 285 000\n\nStyrelse: Dir Ulf-Christian Bratt\n\n(ordf), dir Lars Landquist, civiling\n\nJan-Peder Trolle\n\nVerkst din Civiling Jan-Peder\n\nTrolle.\n\nSVENSKA FRISÖR.\nDEPOTEN AB\n\nPnr 104 60\n\nStockholm 20, Virke sv 3. Tel\n08-44 94 00. Bankgiro 744-7519. Post-\n\ngiro 251636-7. Tga Fridepo.\nTelex 17242\n\nVerksamhet: Säljer kem-tekn\nprodukter\n\nAntal anställda: 100\nÅrsomsättning: 18000 000\nAktiekapital: 2 000 000\nVerkst dir: Alvar Wikström\nEtableringsår: 1946.\n\nSVENSKA FRUKT.\nFÖRENINGEN U P A\n\nPnr 360 13\n\nUrshult, Box 158. Tel 0477-200 23,\n200 24. Bankgiro 286-5731.\nPost-giro 11436-3. Tga Fruktföreningen\nVerksamhet: Tillverkar o säljer\nsylter, safter, geléer, marmelader,\njuicer o alkoholfria drycker\nAntal anställda: 20\nÅrsomsättning: 1300 000\nAktiekapital: 45 000\nVerkst dir: Ragnar K:son Stanler\nEtableringsår: 1915.\n\nALM\n\nÅrsomsättning: 36 000 000\nPlatschef: Dir Lars Lundgren\nFörsäljning: Dir John Berg.\n\nALMESTROM BYGGMATERIAL,\nCARL\n\nPnr 41657\n\nGöteborg, De Geersg 18. Tel\n031-190830, 190930. Bankgiro\n513-4432. Postgiro 525353\nVerksamhet: Säljer\nbyggnadsmaterial\n\nÄgare o chef: Carl Almeström\nEtableringsår: 1958.\n\nSTO\n\nSTOCKHOLMS\nPAPPERS-INDUSTRI, AB\n\nPnr 68101\n\nKristinehamn 1, Box 199. Telev.\nTel0550-151 90. Bankgiro 110-1625.\nPostgiro 51442-2. Tga Siluett\nVerksamhet: Tillverkar tårtpapper,\nfatpapper o pappersbakformar\nAntal anställda: 50\nAktiekapital: 50 000\nVeikst dir: Rune Olsson\nEtableringsår: 1928.\n\nSTOCKHOLMS PATENTBYRA\nZACCO &amp; BRUHN, AB\n\nPnr 103 62\n\nStockholm 3, Kungsg 36. Box 3129.\nTel 08-22 44 40. Bankgiro 562-9779.\nPostgiro 3429-8. Tga Zacconn.\nTelex 17214\n\nVerksamhet: Patent- o\nvarumärkesbyrå\n\nAvdelningskontor: Skellefteå. Tel\n0910-788 85. Telex 6831\nAntal anställda: 110\nVerkst dir: Ing Nils Larfeldt\nEtableringsår: 1878.\n\nSTOCKHOLMS\nPLATT-SÄTTNINGS AB\n\nPnr 126 30\n\nHägersten, Drivhjulsv 20. Tel\n08-45 28 60. Postgiro 56842-8. Tga\nByggplattor\n\nVerksamhet: Utför\nplattsättnings-o isoleringsarbeten. Säljer\nbyggnadsmaterial\nAntal anstäUda: 200\nÅrsomsättning: 20 000 000\nAktiekapital: 200 000\nStyrelse: Adv Erik Petersson\n(ordf), ing Henrik Mattsson\nVerkst dir: Jan H Mattsson\nV verkst dir: Verner Granberg\nEtableringsår: 1934.\n\nSTOCKHOLMS REDERI AB\nSVEA\n\nPnr 103 12\n\nStockholm 2, Box 2065. Skeppsbron\n28. Tel 08-2290 60. Postgiro\n57228-9. Tga Sveas.\nTelex 19147, 19149 SVEAS S\nVerksamhet: Skeppsrederirörelse o\ndärmed förenlig verksamhet.\nFartyg: Betula, Betula 1, Birger Jarl,\nBirka, Brage, Capella, Carola,\nDana Scarlett, Edda, Emanuel\nHögberg, Farida, Pennia, Folias,\nGarda, Garm, Gondul, Linda\nScarlett, Marga, Margot, Pendula,\nPri-mula, Råne, Ring, Scania, Servus,\nSilva, Stella, Stocksund, Svea\nDrott, Svea Jarl, Sveaborg,\nSvensksund, Vega\nAntal anstäUda: 1910\nÅrsomsättning: 220 100 000\nAktiekapital: 17 640 000\nStyrelse: Emanuel Högberg (ordf),\nE Gester, B Skånsberg, A\nWetter-mark, C W Högberg\nVerkst dir: Curt W Högberg\nEtableringsår: 1871\nDotterbolag: Rederi AB Saturnus,\nLinjebuss International AB, Svea\nLine (Baltic) AB, Svea Line\n(Göteborg) AB, Svea Line (Syd) AB m fi.\n\nSTOCKHOLMS REVETERINGS.\nFABRIK\n\nPnr 19121\n\nSoUentuna 1, Industriv 10. Box 57.\nTel 08-35 2510. Bankgiro 332-2542.\nPostgiro 1279-9\n\nVerksamhet: Tillverkar gipsskivor,\nakustikplattor o reveteringsmattor\nVarunamn: Gipsi, Ideal\nAntal anstäUda: 40\nÅrsomsättning: 7 000 000\nChef: Fabr Karl-Eine Johansson\nEtableringsår: 1921.\n\nMOTORAMI I STOCKHOLM AB\n\nPnr 113 21\n\nStockholm VA, Atlasmuren 1. Tel\n08-34 02 00\n\nVerksamhet: General Motors\nperson- o lastautomobiler\nAktiekapital: 1500 000\nVerkst dir: Bengt Lundahl\nEtableringsår: 1953.\n\nMOTORCENTRALEN I\nUMEÅ AB\n\nPnr 902 32\n\nUmeå, Parkv 9. Tel 090-1180 20.\nBankgiro 759-9434. Postgiro\n64660-4\n\nVerksamhet: Säljer Scania o\nVolkswagen\n\nAntal anställda: 100\nAktiekapital: 50 000\nVerkst dir: Sture Ericsson\nEtableringsår: 1944.\n\nMOTORCENTRALEN\nOMFELDT &amp; CO AB\n\nPnr 57100\n\nNässjö, Sö längs v 62. Box 211. Tel\n0380-13170. Bankgiro 452-8410.\nPostgiro 329882-5\nVerksamhet: Säljer BMC o Fiat\nbilar, reservdelar o service\nAntal anställda: 15\nÅrsomsättning: 2000 000\nAktiekapital: 50 000\n\nVerkst dir: Harald Omfeldt\nEtableringsår: 1947\nOmbildat till aktiebolag 1958.\n\nMOTORDELAR, AB\n\nPnr 161 41\n\nStockholm, Annedalsv 39. Tel\n08-2827 50. Bankgiro 170-9278.\nPost-giro 158322-8. Tga Motordelar.\nTelex 1463\n\nVerksamhet: Säljer\nentreprenadmaskiner\n\nAvdelningskonton Malmö 21,\nVäst-kustv. Tel 040-43 01 30\nVarunamn: Bantam, Blaw Knox,\nBröyt, Hamm, Hydrocon, Lorain,\nNailsea, Parker\nAntal anställda: 75\nÅrsomsättning: 25 000 000\nAktiekapital: 75 000\nVerkst dir Gunnar Lamberg\nEtableringsår: 1947.\n\nPETTERSSON AB, OLOF\n\nPnr 104 40\n\nStockholm 14, Strandv 11. Box 14041.\nTel 08-23 57 90. Bankgiro 172-1067.\nPostgiro 251472-7. Tga Olobolagen\nVerksamhet: Driver detaljhandels-\n\nförsäljning av guldsmedsvaror\nunder firma AB Guld-Fynd\nAntal anställda: 225\nÅrsomsättning: 30 000 000\nAktiekapital: 500 000\nVerkst dir: Olof Pettersson\nEtableringsår: 1945.\n\nPETERSSON\nKONSTRUK-TIONSBYRÄ AB, PAUL\n\nPnr 113 43\n\nStockholm, Dalag 61. Tel\n08-24 37 30. Bankgiro 72-8479.\nPostgiro 56759\n\nVerksamhet Konsulterande\ningenjörsbyrå inom VVS-branschen\nAntal anställda: 36\nÅrsomsättning: 2 400 000\nAktiekapital: 5100\nVerkst din Gösta Wennberg\nEtableringsår: 1915.\n\nRUTEBO KERAMIK\n\nPnr 793 00\n\nLeksand,Box 3004. Tel\n0247-11177. Bankgiro 467-2366.\nPostgiro 339046-5\n\nVerksamhet: Ateljéproduktion av\nsintrat stengods\nVarunamn: Rutebo\nAntal anställda: 5\nChef: Rut Landström\nEtableringsår: 1948.\n\nEÉNS MASKINAFFÄR, AXEL\n\nPnr 12121\n\nJohanneshov 1, Box 19. Skagersv\n27. Tel 08-81 65 50 - 60. Bankgiro\n74-4716. Postgiro 2486\nVerksamhet: Montering av alla slags\nstängsel över hela landet.\nTillverkning av stängselmaterial,\ngrindanläggningar o byggnadssmide\n.Antal anställda: 15\nÅrsomsättning: 1 500 000\nChef: Fabr Carl Gustaf Danielsson\nEtableringsår: 1928.\n\nEEN-HOLMGREN\nORTOPEDISKA AB\n\nPnr 753 23\n\nUppsala, Bergsbrunnag 1. Tel\n018-10 2055. Postgiro 144855\nVerksamhet: Tillverkar\nortorpe-diska hjälpmedel\nAntal anställda: 50\nÅrsomsättning: 3 000 000\nAktiekapital: 150 000\nVerkst dir: Ing Helge Een\nEtableringsår: 1957.\n\nAXELSON, AB GUSTAF\n\nPnr 21618\n\nMalmö, Glimmingeg 24. Tel\n040-15 95 50. Tga Guax\nVerksamhet: Import o export av\nverktygsmaskiner\nAktiekapital: 50 000\nVerkst dir: Gustaf Axelson\nEtableringsår: 1940.\n\nAXELSSONS BYGGNADSFIRMA\nab, nils\n\nPnr 252 25\n\nHelsingborg, Söderg 56. Tel\n042-12 63 75. Bankgiro 268-9024.\nPostgiro 369253-0\n\nVerksamhet: Husbyggnad,\nentreprenader\n\nAntal anställda: 22\nÅrsomsättning: 2 000 000\nAktiekapital: 60 000\nVerkst dir: Byggmäst Nils Axelsson\nEtableringsår: 1929.\n\nTEKNORIT, AB\n\nPnr 171 37\n\nSolna, Råsundav 72. Tel 08-83 09 20.\nBankgiro 482-0908. Postgiro\n196486-5. Tga Teknorit, Stockholm\nVerksamhet: Agentur o grosshandel\nmed rit- o kontorsmateriel\nAntal anställda: 12\nÅrsomsättning: 2 200 000\nAktiekapital: 5000\nVerkst dir Sten Moström\nEtableringsår 1950.",
    "structured": {
        "1": {
            "company_name": "TOLLARPS VÄVERI AB",
            "address": "Tollarp, Box 4",
            "phone_number": "0450-104 40",
            "bank_details": {
                "postgiro": "371875"
            },
            "activity": "Tillverkar o säljer twillser för arbetskläder",
            "employees": 30,
            "annual_turnover": 3500000,
            "capital": 600000,
            "key_personnel": [
                {
                    "name": "John Magnuson",
                    "position": "ordf"
                },
                {
                    "name": "Bertil Magnuson",
                    "position": "dir"
                },
                {
                    "name": "Birger Magnuson",
                    "position": "ing"
                },
                {
                    "name": "Bertil Magnuson",
                    "position": "Verkst dir"
                },
                {
                    "name": "Birger Magnuson",
                    "position": "V verkst dir"
                },
                {
                    "name": "Orvar Sjöbåge",
                    "position": "Platschef"
                }
            ],
            "establishment_year": 1949
        },
        "2": {
            "company_name": "TOLLMAR& ENGLUND, AB",
            "address": "Malmbäck, Torget 1",
            "phone_number": "0380-600 01, 60126",
            "activity": "Import- o grossist-firma för kakel, mosaik, panel, dörrar etc",
            "capital": 40000,
            "key_personnel": [
                {
                    "name": "Sture Tollmar",
                    "position": "Verkst dir"
                }
            ],
            "establishment_year": 1952
        },
        "3": {
            "company_name": "SVENSKA FORMALIN AB",
            "address": "Stockholm 11, Sickla, Box 11010",
            "phone_number": "08-44 90 40",
            "bank_details": {
                "postgiro": "191869"
            },
            "activity": "Säljer formalin",
            "capital": 285000,
            "key_personnel": [
                {
                    "name": "Ulf-Christian Bratt",
                    "position": "ordf"
                },
                {
                    "name": "Lars Landquist",
                    "position": "dir"
                },
                {
                    "name": "Jan-Peder Trolle",
                    "position": "civiling"
                },
                {
                    "name": "Jan-Peder Trolle",
                    "position": "Verkst dir"
                }
            ]
        },
        "4": {
            "company_name": "SVENSKA FRISÖR. DEPOTEN AB",
            "address": "Stockholm 20, Virke sv 3",
            "phone_number": "08-44 94 00",
            "bank_details": {
                "bankgiro": "744-7519",
                "postgiro": "251636-7"
            },
            "activity": "Säljer kem-tekn produkter",
            "employees": 100,
            "annual_turnover": 18000000,
            "capital": 2000000,
            "key_personnel": [
                {
                    "name": "Alvar Wikström",
                    "position": "Verkst dir"
                }
            ],
            "establishment_year": 1946
        },
        "5": {
            "company_name": "SVENSKA FRUKT. FÖRENINGEN U P A",
            "address": "Urshult, Box 158",
            "phone_number": "0477-200 23, 200 24",
            "bank_details": {
                "bankgiro": "286-5731",
                "postgiro": "11436-3"
            },
            "activity": "Tillverkar o säljer sylter, safter, geléer, marmelader, juicer o alkoholfria drycker",
            "employees": 20,
            "annual_turnover": 1300000,
            "capital": 45000,
            "key_personnel": [
                {
                    "name": "Ragnar K:son Stanler",
                    "position": "Verkst dir"
                }
            ],
            "establishment_year": 1915
        },
        "6": {
            "company_name": "ALM",
            "annual_turnover": 36000000,
            "key_personnel": [
                {
                    "name": "Lars Lundgren",
                    "position": "Platschef"
                },
                {
                    "name": "John Berg",
                    "position": "Försäljning: Dir"
                }
            ]
        },
        "7": {
            "company_name": "ALMESTROM BYGGMATERIAL, CARL",
            "address": "Göteborg, De Geersg 18",
            "phone_number": "031-190830, 190930",
            "bank_details": {
                "bankgiro": "513-4432",
                "postgiro": "525353"
            },
            "activity": "Säljer byggnadsmaterial",
            "key_personnel": [
                {
                    "name": "Carl Almeström",
                    "position": "Ägare o chef"
                }
            ],
            "establishment_year": 1958
        }
    }
}