{
    "original": "KUNGS-BETONG AB\n\nPnr 434 00\n\nKungsbacka, Varbergsv. Tel\n0300-107 27, 134 00. Bankgiro 546-5406.\nPostgiro 427456-9\nVerksamhet: Tillverkar o säljer\ncementvaror o LECA murblock\nAntal anställda: 18\nAktiekapital: 100 000\nVerkst dir: Gunnar Johansson\nEtableringsår: 1945\nOmbildat till aktiebolag 1960.\n\nKUNGSFOTO AB\n\nPnr 124 02\n\nBandhagen 2, Huvudkontor\nBand-hagsplan 16-18. Box 207. Tel\n08-47 26 40. Bankgiro 28-4522.\nPostgiro 356771\n\nVerksamhet Fotolaboratorier\nFotolaboratorier:\n\nStockholm 12, Fack. Strandbergsg\n57. Tel 08-52 06 20\nMalmö, Ystadsv 22. Tel 040-800 10\nMölndal, Bergfotsg 5. Tel\n031-27 51 25\n\nÅnge. Tel 0690-110 60\nAntal anställda: 300\nÅrsomsättning: 25 000 000\nAktiekapital: 60 000\nStyrelse: Adv Gösta Bergqvist\n(ordf), dir Rune Ricknert, dir Curt\nUlle\n\nVerkst dir. Curt Ulle\nEtableringsår: 1955.\n\nKUNGSHOLMS EXPRESS- &amp;\nSPEDITIONS AB\n\nPnr 112 31\n\nStockholm, Bergsg 57. Tel\n08-5408 50. Bankgiro 729-9373.\nPostgiro 50 735-0. Tga Kungsped.\nTelex 10014 KUNGSH S\nVerksamhet: Lastbilstransporter,\nlastbilsuthyrning, flyttningar,\nexportpackningar, magasinering o\npresenningsuthyrning\nAntal anställda: 125\nÅrsomsättning: 5 000 000\nAktiekapital: 300000\nÄgare o chef: Dir Lars östman\nEtableringsår: 1896.\n\nNÄRKANDERSMATTOR\n\nPnr 582 52\n\nLinköping, Nya Tanneforsv 72. Tel\n013-10 2115. Bankgiro 301-3794\nVerksamhet: Försäljning, leverans\no läggning av heltäckande mattor,\nplastgolv, väggbeklädnad i badrum\no parkettgolv\nAntal anställda: 3\nÅrsomsättning: 700 000\nVerkst dir: Ingemar Närkander\nEtableringsår: 1970.\n\nÄST\n\nÅSTORPS TEGEL AB\n\nPnr 265 00\n\nÅstorp, Lantmannag 8. Tel 042-\n\n513 12. Bankgiro 671-4430.\nPost-giro 579292-4\n\nVerksamhet: Tillverkar murtegel o\ndräneringsrör\nAntal anställda: 20\nÅrsomsättning: 800 000\nAktiekapital: 25 000\nChefer: Byggnadsing Bertil\nAndersson, byggmäst Stig Steen\nEtableringsår: 1965.\n\nÅSTRANDS SÅG &amp; SNICKERI\nAB, BRUDERNA\n\nPnr 740 30\n\nBjörklinge, Industriv 1. Tel\n018-37 0031. Postgiro 30660\nVerksamhet: Säljer trävaror o\nbyggnadsmaterial\nAntal anställda: 12\nÅrsomsättning: 900 000\nAktiekapital: 40 000\nVerkst dir: Georg Åstrand\nEtableringsår: 1937.\n\nÅSTRÖM &amp; SÖNERS MODELL.\nVERKSTAD\n\nPnr 654 65\n\nKarlstad. Rudsplan 3. Tel\n054-1134 39. Bankgiro 881-4105.\nPost-giro 171048-2\n\nVerksamhet: Tillverkar\nträmodeller till gjuterier\nChef: Yngve Åström\nEtableringsår: 1929.\n\nGÖINGE BIL I OSBY AB\n\nPnr 283 00\n\nOsby, Box 75. Sågg. Tel\n0479-11950. Bankgiro 862-9479.\nPostgiro 287738-9\n\nVerksamhet: Auktoriserad\nVolvoåterförsäljare. Service o\nbiluthyrning\n\nFilial: 343 00 Älmhult. Danska v.\nTel 0476-124 10\nAntal anställda: 60\nÅrsomsättning: 15 000 000\nAktiekapital: 300 000\nStyrelse: Dir Carl Persson, fru\nEva Persson\nVerkst dir: Carl Persson\nEkonomichef: Arvid Sivermo\nFörsäljn-chef: Viggo Månsson\nVerkstadschef: Erik Sandell\nEtableringsår: 1928\nDotterbolag till Göinge Bil AB,\nHässleholm.\n\nGÖINGE DATASERVICE AB\nGEDAB\n\nPnr 283 00\n\nOsby. V Järnvägsg. Tel 047\n9-11900. Postgiro 6075\nVerksamhet: Dataservice\nChef: Disp Gert Andersson.\n\nGÖINGE MEKANISKA\nVERKSTAD AB\n\nPnr 28101\n\nHässleholm 1. S Industrig. Box 170.\nTel 0451-144 40. Bankgiro 270-1191.\nPostgiro 110461-1\nVerksamhet: Tillverkar järn- o\nstålkonstruktioner\nAntal anstäUda: 130\nAktiekapital: 500 000\nVerkst dir: Arthur Carlsson\nEtableringsår: 1946.\n\nAUTOTEKNIK BIL AB\n\nPnr 41101\n\nGöteborg, Friggag 20. Tel\n031-8014 10. Bankgiro 22-5770.\nPostgiro 241222\n\nVerksamhet: Auktoriserad\nBMW-försäljning\nAntal anställda: 35\nEtableringsår: 1968.\n\nMIB\n\nAktiekapital: 150 000\nVerkst dir: E Jörnvall\nEtableringsår: 1955.\n\nPARAGON AB\n\nPnr 593 01\n\nVästervik 1, Box 324. Baumansg 1.\nTel 0490-167 20. Bankgiro\n301-7837. Postgiro 2831-6. Tga Paragon\nVerksamhet: Specialtryckeri för\ndata- o systemblanketter i stamsats\no ändlös bana för data o kontor.\nParagonblock, OCR-blanketter.\nregisterblanketter, fraktsedlar o\nadress lappar\n\nVarunamn: Speediset,\nParagonblock, Speedibok, Paraflex\nAvdelningskontor: 111 20\nStockholm. V as ag 16. Tel 22 95 00, riks\n08-22 9540\n\n414 56 Göteborg, Blåsutg 5. Tel\n031-14 7017. 14 70 28\n21219 Malmö. Lundav 52. Tel\n040-93 07 32, 93 07 33\nKonsulenter i: Västerås, Växjö,\nÖrebro,Örnsköldsvik\nVerkst dir: Per Halse\nEtableringsår: 1901.\n\nTORNBERG, AB MARTIN\n\nPnr 654 60\n\nKarlstad. Wibelig 11. Tel\n054-15 05 31, 15 05 32. Bankgiro\n881-6654. Postgiro 200505-6. Tga\nTörnbergs\n\nVerksamhet: Säljer kyl- o\nfrysanläggningar\nAntal anställda: 7\nÅrsomsättning: 1000 000\nVerkst dir: Martin Törnberg\nEtableringsår: 1957.\n\nTORNBLOMS ANNONSBYRÅ,\nAB\n\nPnr 103 40\n\nStockholm 40, Sveav 17. Fack. Tel\n08-23 59 85. Bankgiro 722-4108.\nPostgiro 4105-3. Tga Tornad.\nTelex 10879\n\nVerksamhet: Konsulterande företag\ni reklam- o marknadsfrågor\nAktiekapital: 150000\nVerkst dir: Owe Söderström\nEtableringsår: 1921.\n\nHAMBERGS MEK VERKSTAD,\nAB\n\nPnr 19149\n\nSollentuna, Klasrov 19. Tel\n08-35 56 30. Postgiro 477444\nVerksamhet; Legoarbeten\nAntal anställda: 3\nÅrsomsättning: 115 000\nAktiekapital: 5 000\nVerkst dir: Arthur Hamberg\nEtableringsår: 1956.\n\nSTELLANA PLAST AB\n\nPnr 695 01\n\nLaxå 1, Box 54. Tel 0584-108 40.\nBankgiro 46-1630. Postgiro 394086.\nTga Stellana. Telex 73371\nVerksamhet: Tillverkar\nindustriformgods i härd- o termoplast;\nhartser o pressmassor. Se under\nrubrikerna Plastvaror, Lager,\nLänkrullar i Inköpsregistret\nAntal anställda: 100\nÅrsomsättning: 11000 000\nAktiekapital: 300 000\nVerkst dir: Pol mag Sture Emilson\nDriftchef: Sven Olov Kumlin\nInköpschef: Kamrer Osten Hörnell\nFörsäljn-chef: Sture Eldewall.\n\nSTELLEGENT AB\n\nPnr 41251\n\nGöteborg, skåneg 33. Tel\n031-1815 86,18 31 88. Bankgiro\n42-0600. Postgiro 422336-8. Tga\nStel-legent. Telex 21043 STELLE S\nVerksamhet: Säljer ur engros\nAntal anställda: 4\nÅrsomsättning: 1500 000\nAktiekapital: 50 000\nVerkst dir: David Stelle\nEtableringsår: 1949.\n\nSTEMA TRÄ- &amp;\nBYGG-SERVICE, AB\n\nse MASAB.\n\nSTENS CYKEL &amp; SPORT,\nSTEN SVENSSONS METALL.\nINDUSTRI\n\nPnr 330 30\n\nGnosjö.Box 100. Läroverksg 4. Tel\n0370-91184. Bankgiro 984-9498.\nPostgiro 98680-2\n\nVerksamhet: Exenterpressning,\nautomatpressning o djupdragningar,\nelektr bandklammer o\nkontaktmate-riel, beslag för skaft, justerbrickor,\nmetalldetaljer för plastindustrin,\nklippning o bockning för olika\nändamål\n\nÄgare o chef: Sten Svensson\nEtableringsår: 1937.",
    "structured": {
        "1": {
            "company_name": "KUNGS-BETONG AB",
            "pnr": "434 00",
            "address": "Kungsbacka, Varbergsv",
            "phone_number": "0300-107 27",
            "bank_details": {
                "bankgiro": "546-5406",
                "postgiro": "427456-9"
            },
            "activity": "Tillverkar o säljer cementvaror o LECA murblock",
            "employees": 18,
            "capital": 100000,
            "key_personnel": [
                {
                    "name": "Gunnar Johansson",
                    "position": "Verkst dir"
                }
            ],
            "establishment_year": 1945
        },
        "2": {
            "company_name": "KUNGSFOTO AB",
            "pnr": "124 02",
            "address": "Bandhagen 2, Huvudkontor",
            "phone_number": "08-47 26 40",
            "bank_details": {
                "bankgiro": "28-4522",
                "postgiro": "356771"
            },
            "activity": "Fotolaboratorier",
            "locations": [
                {
                    "city": "Stockholm",
                    "address": "Fack. Strandbergsg 57",
                    "phone_number": "08-52 06 20"
                },
                {
                    "city": "Malmö",
                    "address": "Ystadsv 22",
                    "phone_number": "040-800 10"
                },
                {
                    "city": "Mölndal",
                    "address": "Bergfotsg 5",
                    "phone_number": "031-27 51 25"
                },
                {
                    "city": "Ånge",
                    "phone_number": "0690-110 60"
                }
            ],
            "employees": 300,
            "annual_turnover": 25000000,
            "capital": 60000,
            "key_personnel": [
                {
                    "name": "Adv Gösta Bergqvist",
                    "position": "Styrelse ordf"
                },
                {
                    "name": "Rune Ricknert",
                    "position": "dir"
                },
                {
                    "name": "Curt Ulle",
                    "position": "dir, Verkst dir"
                }
            ],
            "establishment_year": 1955
        },
        "3": {
            "company_name": "KUNGSHOLMS EXPRESS- & SPEDITIONS AB",
            "pnr": "112 31",
            "address": "Stockholm, Bergsg 57",
            "phone_number": "08-5408 50",
            "bank_details": {
                "bankgiro": "729-9373",
                "postgiro": "50 735-0"
            },
            "activity": "Lastbilstransporter, lastbilsuthyrning, flyttningar, exportpackningar, magasinering o presenningsuthyrning",
            "employees": 125,
            "annual_turnover": 5000000,
            "capital": 300000,
            "key_personnel": [
                {
                    "name": "Lars östman",
                    "position": "Ägare o chef"
                }
            ],
            "establishment_year": 1896
        },
        "4": {
            "company_name": "NÄRKANDERSMATTOR",
            "pnr": "582 52",
            "address": "Linköping, Nya Tanneforsv 72",
            "phone_number": "013-10 2115",
            "bank_details": {
                "bankgiro": "301-3794"
            },
            "activity": "Försäljning, leverans o läggning av heltäckande mattor, plastgolv, väggbeklädnad i badrum o parkettgolv",
            "employees": 3,
            "annual_turnover": 700000,
            "key_personnel": [
                {
                    "name": "Ingemar Närkander",
                    "position": "Verkst dir"
                }
            ],
            "establishment_year": 1970
        },
        "5": {
            "company_name": "ÅSTORPS TEGEL AB",
            "pnr": "265 00",
            "address": "Åstorp, Lantmannag 8",
            "phone_number": "042-513 12",
            "bank_details": {
                "bankgiro": "671-4430",
                "postgiro": "579292-4"
            },
            "activity": "Tillverkar murtegel o dräneringsrör",
            "employees": 20,
            "annual_turnover": 800000,
            "capital": 25000,
            "key_personnel": [
                {
                    "name": "Bertil Andersson",
                    "position": "Byggnadsing"
                },
                {
                    "name": "Stig Steen",
                    "position": "byggmäst"
                }
            ],
            "establishment_year": 1965
        },
        "6": {
            "company_name": "ÅSTRANDS SÅG & SNICKERI AB, BRUDERNA",
            "pnr": "740 30",
            "address": "Björklinge, Industriv 1",
            "phone_number": "018-37 0031",
            "bank_details": {
                "postgiro": "30660"
            },
            "activity": "Säljer trävaror o byggnadsmaterial",
            "employees": 12,
            "annual_turnover": 900000,
            "capital": 40000,
            "key_personnel": [
                {
                    "name": "Georg Åstrand",
                    "position": "Verkst dir"
                }
            ],
            "establishment_year": 1937
        },
        "7": {
            "company_name": "ÅSTRÖM & SÖNERS MODELL. VERKSTAD",
            "pnr": "654 65",
            "address": "Karlstad, Rudsplan 3",
            "phone_number": "054-1134 39",
            "bank_details": {
                "bankgiro": "881-4105",
                "postgiro": "171048-2"
            },
            "activity": "Tillverkar trämodeller till gjuterier",
            "employees": null,
            "key_personnel": [
                {
                    "name": "Yngve Åström",
                    "position": "Chef"
                }
            ],
            "establishment_year": 1929
        },
        "8": {
            "company_name": "GÖINGE BIL I OSBY AB",
            "pnr": "283 00",
            "address": "Osby, Box 75. Sågg",
            "phone_number": "0479-11950",
            "bank_details": {
                "bankgiro": "862-9479",
                "postgiro": "287738-9"
            },
            "activity": "Auktoriserad Volvoåterförsäljare. Service o biluthyrning",
            "locations": [
                {
                    "city": "Älmhult",
                    "address": "Danska v",
                    "phone_number": "0476-124 10"
                }
            ],
            "employees": 60,
            "annual_turnover": 15000000,
            "capital": 300000,
            "key_personnel": [
                {
                    "name": "Carl Persson",
                    "position": "Styrelse dir"
                },
                {
                    "name": "Eva Persson",
                    "position": "Styrelse fru"
                },
                {
                    "name": "Arvid Sivermo",
                    "position": "Ekonomichef"
                }
            ],
            "establishment_year": 1928
        },
        "9": {
            "company_name": "GÖINGE DATASERVICE AB GEDAB",
            "pnr": "283 00",
            "address": "Osby. V Järnvägsg",
            "phone_number": "0479-11900",
            "bank_details": {
                "postgiro": "6075"
            },
            "activity": "Dataservice",
            "key_personnel": [
                {
                    "name": "Gert Andersson",
                    "position": "Chef"
                }
            ]
        },
        "10": {
            "company_name": "GÖINGE MEKANISKA VERKSTAD AB",
            "pnr": "28101",
            "address": "Hässleholm 1. S Industrig. Box 170",
            "phone_number": "0451-144 40",
            "bank_details": {
                "bankgiro": "270-1191",
                "postgiro": "110461-1"
            },
            "activity": "Tillverkar järn- o stålkonstruktioner",
            "employees": 130,
            "capital": 500000,
            "key_personnel": [
                {
                    "name": "Arthur Carlsson",
                    "position": "Verkst dir"
                }
            ],
            "establishment_year": 1946
        },
        "11": {
            "company_name": "AUTOTEKNIK BIL AB",
            "pnr": "41101",
            "address": "Göteborg, Friggag 20",
            "phone_number": "031-8014 10",
            "bank_details": {
                "bankgiro": "22-5770",
                "postgiro": "241222"
            },
            "activity": "Auktoriserad BMW-försäljning",
            "employees": 35,
            "capital": 150000,
            "key_personnel": [
                {
                    "name": "E Jörnvall",
                    "position": "Verkst dir"
                }
            ],
            "establishment_year": 1968
        },
        "12": {
            "company_name": "PARAGON AB",
            "pnr": "593 01",
            "address": "Västervik 1, Box 324. Baumansg 1",
            "phone_number": "0490-167 20",
            "bank_details": {
                "bankgiro": "301-7837",
                "postgiro": "2831-6"
            },
            "activity": "Specialtryckeri för data- o systemblanketter i stamsats o ändlös bana för data o kontor. Paragonblock, OCR-blanketter. registerblanketter, fraktsedlar o adress lappar",
            "locations": [
                {
                    "city": "Stockholm",
                    "address": "Vasag"
                },
                {
                    "city": "Göteborg",
                    "address": "Blåsutg 5",
                    "phone_number": "031-14 7017"
                },
                {
                    "city": "Malmö",
                    "address": "Lundav 52",
                    "phone_number": "040-93 07 32"
                }
            ],
            "key_personnel": [
                {
                    "name": "Per Halse",
                    "position": "Verkst dir"
                }
            ],
            "establishment_year": 1901
        },
        "13": {
            "company_name": "TORNBERG, AB MARTIN",
            "pnr": "654 60",
            "address": "Karlstad, Wibelig 11",
            "phone_number": "054-15 05 31, 15 05 32",
            "bank_details": {
                "bankgiro": "881-6654",
                "postgiro": "200505-6"
            },
            "activity": "Säljer kyl- o frysanläggningar",
            "employees": 7,
            "annual_turnover": 1000000,
            "key_personnel": [
                {
                    "name": "Martin Törnberg",
                    "position": "Verkst dir"
                }
            ],
            "establishment_year": 1957
        },
        "14": {
            "company_name": "TORNBLOMS ANNONSBYRÅ, AB",
            "pnr": "103 40",
            "address": "Stockholm 40, Sveav 17. Fack",
            "phone_number": "08-23 59 85",
            "bank_details": {
                "bankgiro": "722-4108",
                "postgiro": "4105-3"
            },
            "activity": "Konsulterande företag i reklam- o marknadsfrågor",
            "capital": 150000,
            "key_personnel": [
                {
                    "name": "Owe Söderström",
                    "position": "Verkst dir"
                }
            ],
            "establishment_year": 1921
        },
        "15": {
            "company_name": "HAMBERGS MEK VERKSTAD, AB",
            "pnr": "19149",
            "address": "Sollentuna, Klasrov 19",
            "phone_number": "08-35 56 30",
            "bank_details": {
                "postgiro": "477444"
            },
            "activity": "Legoarbeten",
            "employees": 3,
            "annual_turnover": 115000,
            "capital": 5000,
            "key_personnel": [
                {
                    "name": "Arthur Hamberg",
                    "position": "Verkst dir"
                }
            ],
            "establishment_year": 1956
        },
        "16": {
            "company_name": "STELLANA PLAST AB",
            "pnr": "695 01",
            "address": "Laxå 1, Box 54",
            "phone_number": "0584-108 40",
            "bank_details": {
                "bankgiro": "46-1630",
                "postgiro": "394086"
            },
            "activity": "Tillverkar industriformgods i härd- o termoplast; hartser o pressmassor",
            "employees": 100,
            "annual_turnover": 11000000,
            "capital": 300000,
            "key_personnel": [
                {
                    "name": "Pol mag Sture Emilson",
                    "position": "Verkst dir"
                },
                {
                    "name": "Sven Olov Kumlin",
                    "position": "Driftchef"
                },
                {
                    "name": "Osten Hörnell",
                    "position": "Inköpschef"
                }
            ]
        },
        "17": {
            "company_name": "STELLEGENT AB",
            "pnr": "41251",
            "address": "Göteborg, skåneg 33",
            "phone_number": "031-1815 86,18 31 88",
            "bank_details": {
                "bankgiro": "42-0600",
                "postgiro": "422336-8"
            },
            "activity": "Säljer ur engros",
            "employees": 4,
            "annual_turnover": 1500000,
            "capital": 50000,
            "key_personnel": [
                {
                    "name": "David Stelle",
                    "position": "Verkst dir"
                }
            ],
            "establishment_year": 1949
        }
    }
}