{
    "original": "HÄLLERS KONSERVER AB\n\nPnr 450 43\n\nSmögen, Ben 26. Tel 0523-31018,\n31118. Bankgiro 551-0516.\nPostgiro 36808-4. Tga Hällerskonserv\nVerksamhet: Konserverade o frysta\nräkor\n\nAntal anställda: 40\nÅrsomsättning: 4 000 000\nAktiekapital: 20 000\nVerkst dir: Fabr Leif Häller\nEtableringsår: 1952.\n\nEHN &amp; LAND, MASKIN AB\n\nPnr 11534\n\nStockholm, Armfeltsg 18. Tel\n08-67 74 85, 67 74 86. Tga Ehnland\nVerksamhet: Säljer\nverktygsmaskiner o verktyg\nVamnamn: Ifanger\nAktiekapital: 100 000\nÄgare o chef: Ing Lennart Karåker\nEtableringsår: 1950.\n\nTUNO MEKANISKA\n\nPnr 33020\n\nAnderstorp, Tokarp. Tel\n0371-162 06. Bankgiro 98-5745. Postgiro\n666280\n\nVerksamhet: Automatsvarvning\nAntal anställda: 4\nChef: Uno Andersson\nEtableringsår: 1964.\n\nTHUNSTRÖM, BYGGNADS AB\nSVEN A\n\nPnr 11120\n\nStockholm, Vasag 40. Tel\n08-112154,11 31 54. Bankgiro 57-5925.\nPostgiro 56173-8\n\nVerksamhet: Byggnadsentreprenör.\nÄven asfalt- o isoleringsarbeten\nAntal anställda: 100\nÅrsomsättning: 6000000\nAktiekapital: 50 000\nVerkst din Byggn-ing Nils Schelin\nEtableringsån 1927.\n\nSIK\n\nPaul Dax, dir Erik Esping,\nbruks-disp Wilhelm Haglund, dir Hans\nMott, docent Börje Rudewald, Johan\nBottheim\n\nVerkst dir: Johan Bottheim\nEtableringsår: 1893.\n\nPULVE FABRIKS AB\n\nPnr 11138\n\nStockholm, Johannesg 2. Tel\n08-20 97 73 , 20 97 74\n\nVerksamhet: Specialitet:\nelektrostatisk pulverlackering\nFabrik: 775 00 Krylbo, Västmannag\n9. Tel 0226-107 60, 107 61\nAktiekapital: 100 000\nStyrelse: Dir Tage Ohlin, dir\nL Persson, målarmäst Bertil\nDahlquist, ing Erik Ström.\n\nPUMP-SEPARATORS\nGJUTERIER, AB\n\nPnr 64100\n\nKatrineholm, Gjuterig 4-5. Box 18.\nTel 0150-133 45. Bankgiro 28-2573.\nPostgiro 13089. Tga Gjuterierna\nVerksamhet: Tillverkar gjutgods i\ngråjärn, rostfritt o metall.\nBearbetning, modeller för gjuterier\nAntal anställda: 400\nÅrsomsättning: 20 000 000\nAktiekapital: 1000 000\nStyrelse: Dir Hans Ståhle (ordf),\ndir Alrik Östberg, dir Gunnar\nPerén, dir Allan Sund\nVerkst dir: Alrik Östberg\nEtableringsår: 1916\nÄgare: Alfa-La val AB, Tumba.\n\nPUMPTEKNIK AB\n\nPnr 421 20\n\nVästra Frölunda 1, Frötallsg 11-13.\nFack. Tel 031-45 02 30. Bankgiro\n50-0045. Postgiro 12454.\nTga Pumpteknik, Göteborg.\nTelex 20652 PUMPTEK S\nVerksamhet: Tillverkar\ncentrifugalpumpar. Representerar utländska\npump tillverkare\n\nVarunamn: Boge, Deming, Gentil,\nIP, Jung, Marelli, Speck, Vogel\nAntal anställda: 30\nÅrsomsättning: 4 000 000\nAktiekapital: 300 000\nEtableringsår: 1936.\n\nBJORKSÄTRA LÄDERVARU AB\n\nPnr 330 20\n\nAnders torp. Tel 0371-15178, 15495.\nBankgiro 488-0142. Postgiro\n172083-0\n\nVerksamhet: Tillverkar reseffekter,\nplånböcker, reklamartiklar m m\nAntal anställda: 35\nÅrsomsättning: 2000 000\nVerkst dir: A S Jansson\nEtableringsår: 1942.\n\nH.K INDUSTRIAKTIEBOLAG\n\nPnr 22104\n\nLund i, Bredg 13. Box 1136. Tel\n046-1179 70. Bankgiro 869-2907.\nPostgiro 37611-1\nVerksamhet: Tillverkar\nLunnavil-lan o huselement\nAntal anstäUda: 100\nÅrsomsättning: 20 000 000\nAktiekapital: 500 000\nVerkst dir Kurt Månsson\nEtableringsår 1955.\n\nTELEHYTT AB\n\nPnr 19501\n\nMärsta 1, Box 58. Bristag. Tel\n0760-142 00. Bankgiro 627-4468.\nPostgiro 22405-5\nVerksamhet: Tillverkar\ntelefonhytter\n\nVarunamn: ASA\nAktiekapital: 25 000\nEtableringsår: 1962.\n\nELEKTRO-ARMATUR, AB\n\nPnr 80104\n\nGävle 1, Lötängsg 13. Box 306.\nTel 026-12 97 10. Bankgiro\n78-3706. Postgiro 22067\nVerksamhet: Elektr kraft- o\nbelysningsanläggningar, hissar o\nfartygsinstallationer\n\nFilialer: S Valbo. Tel 026-13 06 77\nSkutskär. Tel 026-79810\nAktiekapital: 50 000\nVerkst dir: Helge Rask\nEtableringsår: 1921.\n\nSVEA RESEBUREAU AB\n\nPnr 103 14\n\nStockholm 2, Skeppsbron 10. Box\n2136. Tel 08-14 13 10. Bankgiro\n729-5793. Postgiro 600145-7.\nTga Sveatravel. Telex 10097\nVerksamhet: Resebyrå\nAktiekapital: 100 000\nVerkst dir: Hans Elwe\nEtableringsår: 1952.",
    "structured": {
        "firms": [
            {
                "company_name": "HÄLLERS KONSERVER AB",
                "pnr": "450 43",
                "address": "Smögen, Ben 26",
                "phone_number": "0523-31018, 31118",
                "bank_details": {
                    "bankgiro": "551-0516",
                    "postgiro": "36808-4"
                },
                "activity": "Konserverade o frysta räkor",
                "employees": 40,
                "annual_turnover": 4000000,
                "capital": 20000,
                "key_personnel": [
                    {
                        "name": "Fabr Leif Häller",
                        "position": "Verkst dir"
                    }
                ],
                "establishment_year": 1952
            },
            {
                "company_name": "EHN & LAND, MASKIN AB",
                "pnr": "11534",
                "address": "Stockholm, Armfeltsg 18",
                "phone_number": "08-67 74 85, 67 74 86",
                "activity": "Säljer verktygsmaskiner o verktyg",
                "capital": 100000,
                "key_personnel": [
                    {
                        "name": "Ing Lennart Karåker",
                        "position": "Ägare o chef"
                    }
                ],
                "establishment_year": 1950
            },
            {
                "company_name": "TUNO MEKANISKA",
                "pnr": "33020",
                "address": "Anderstorp, Tokarp",
                "phone_number": "0371-162 06",
                "bank_details": {
                    "bankgiro": "98-5745",
                    "postgiro": "666280"
                },
                "activity": "Automatsvarvning",
                "employees": 4,
                "key_personnel": [
                    {
                        "name": "Uno Andersson",
                        "position": "Chef"
                    }
                ],
                "establishment_year": 1964
            },
            {
                "company_name": "THUNSTRÖM, BYGGNADS AB SVEN A",
                "pnr": "11120",
                "address": "Stockholm, Vasag 40",
                "phone_number": "08-112154,11 31 54",
                "bank_details": {
                    "bankgiro": "57-5925",
                    "postgiro": "56173-8"
                },
                "activity": "Byggnadsentreprenör. Även asfalt- o isoleringsarbeten",
                "employees": 100,
                "annual_turnover": 6000000,
                "capital": 50000,
                "key_personnel": [
                    {
                        "name": "Byggn-ing Nils Schelin",
                        "position": "Verkst din"
                    }
                ],
                "establishment_year": 1927
            },
            {
                "company_name": "SIK",
                "key_personnel": [
                    {
                        "name": "Johan Bottheim",
                        "position": "Verkst dir"
                    }
                ],
                "establishment_year": 1893
            },
            {
                "company_name": "PULVE FABRIKS AB",
                "pnr": "11138",
                "address": "Stockholm, Johannesg 2",
                "phone_number": "08-20 97 73 , 20 97 74",
                "activity": "Specialitet: elektrostatisk pulverlackering",
                "capital": 100000,
                "key_personnel": [
                    {
                        "name": "Dir Tage Ohlin"
                    },
                    {
                        "name": "Dir L Persson"
                    },
                    {
                        "name": "Målarmäst Bertil Dahlquist"
                    },
                    {
                        "name": "Ing Erik Ström"
                    }
                ]
            },
            {
                "company_name": "PUMP-SEPARATORS GJUTERIER, AB",
                "pnr": "64100",
                "address": "Katrineholm, Gjuterig 4-5. Box 18",
                "phone_number": "0150-133 45",
                "bank_details": {
                    "bankgiro": "28-2573",
                    "postgiro": "13089"
                },
                "activity": "Tillverkar gjutgods i gråjärn, rostfritt o metall. Bearbetning, modeller för gjuterier",
                "employees": 400,
                "annual_turnover": 20000000,
                "capital": 1000000,
                "key_personnel": [
                    {
                        "name": "Dir Hans Ståhle (ordf)"
                    },
                    {
                        "name": "Dir Alrik Östberg"
                    },
                    {
                        "name": "Dir Gunnar Perén"
                    },
                    {
                        "name": "Dir Allan Sund"
                    },
                    {
                        "name": "Alrik Östberg",
                        "position": "Verkst dir"
                    }
                ],
                "establishment_year": 1916,
                "owner": "Alfa-La val AB, Tumba"
            },
            {
                "company_name": "PUMPTEKNIK AB",
                "pnr": "421 20",
                "address": "Västra Frölunda 1, Frötallsg 11-13",
                "phone_number": "031-45 02 30",
                "bank_details": {
                    "bankgiro": "50-0045",
                    "postgiro": "12454"
                },
                "activity": "Tillverkar centrifugalpumpar. Representerar utländska pump tillverkare",
                "capital": 300000,
                "employees": 30,
                "annual_turnover": 4000000,
                "establishment_year": 1936
            },
            {
                "company_name": "BJORKSÄTRA LÄDERVARU AB",
                "pnr": "330 20",
                "address": "Anders torp",
                "phone_number": "0371-15178, 15495",
                "bank_details": {
                    "bankgiro": "488-0142",
                    "postgiro": "172083-0"
                },
                "activity": "Tillverkar reseffekter, plånböcker, reklamartiklar m m",
                "employees": 35,
                "annual_turnover": 2000000,
                "key_personnel": [
                    {
                        "name": "A S Jansson",
                        "position": "Verkst dir"
                    }
                ],
                "establishment_year": 1942
            },
            {
                "company_name": "H.K INDUSTRIAKTIEBOLAG",
                "pnr": "22104",
                "address": "Lund i, Bredg 13. Box 1136",
                "phone_number": "046-1179 70",
                "bank_details": {
                    "bankgiro": "869-2907",
                    "postgiro": "37611-1"
                },
                "activity": "Tillverkar Lunnavil-lan o huselement",
                "employees": 100,
                "annual_turnover": 20000000,
                "capital": 500000,
                "key_personnel": [
                    {
                        "name": "Kurt Månsson",
                        "position": "Verkst dir"
                    }
                ],
                "establishment_year": 1955
            },
            {
                "company_name": "TELEHYTT AB",
                "pnr": "19501",
                "address": "Märsta 1, Box 58. Bristag",
                "phone_number": "0760-142 00",
                "bank_details": {
                    "bankgiro": "627-4468",
                    "postgiro": "22405-5"
                },
                "activity": "Tillverkar telefonhytter",
                "capital": 25000,
                "establishment_year": 1962
            },
            {
                "company_name": "ELEKTRO-ARMATUR, AB",
                "pnr": "80104",
                "address": "Gävle 1, Lötängsg 13. Box 306",
                "phone_number": "026-12 97 10",
                "bank_details": {
                    "bankgiro": "78-3706",
                    "postgiro": "22067"
                },
                "activity": "Elektr kraft- o belysningsanläggningar, hissar o fartygsinstallationer",
                "capital": 50000,
                "key_personnel": [
                    {
                        "name": "Helge Rask",
                        "position": "Verkst dir"
                    }
                ],
                "establishment_year": 1921
            },
            {
                "company_name": "SVEA RESEBUREAU AB",
                "pnr": "103 14",
                "address": "Stockholm 2, Skeppsbron 10. Box 2136",
                "phone_number": "08-14 13 10",
                "bank_details": {
                    "bankgiro": "729-5793",
                    "postgiro": "600145-7"
                },
                "activity": "Resebyrå",
                "capital": 100000,
                "key_personnel": [
                    {
                        "name": "Hans Elwe",
                        "position": "Verkst dir"
                    }
                ],
                "establishment_year": 1952
            }
        ]
    }
}