{
    "original": "INDUSTRIKONSULT, AB\n\nPnr 33100\n\nVärnamo, Brog 2. Tel 0370-130 61,\n13062. Bankgiro 981-8600.\nPostgiro 286742-2\n\nVerksamhet: Konsulter i\nproduktionsteknik, teknisk organisation,\narbetsstudier o industriplanering\nAntal anställda: 10\nAktiekapital: 15 000\nVeikst dir. Ing Bo Jonsson\nEtableringsår: 1958.\n\nINDUSTRIKRAFT AB,\nINGENJÖRSFIRMAN\n\nPnr 191 21\n\nSollentuna 1, Box 52. Tel\n08-961452. Bankgiro 746-6600.\nPostgiro 503281-8\n\nVerksamhet: Hydraulik,\nkonstruktion o tillverkning\nVarunamn: IK-Hydraulik\nVerkst dir: Ing Ake Sjölund\nEtableringsår: 1963.\n\nINDUSTRIKRAFTS\nFÖRSÄLJ-NINGS AB, INGENJÖRSFIRMAN\n\nPnr 162 36\n\nVällingby, Aprikosg 27. Tel\n08-38 65 65. Bankgiro 29-5950.\nPostgiro 600009\n\nVerksamhet: Försäljning o service\nav hydrauliska maskiner\nVerkst dir: Ing Bengt Jansson\nEtableringsår: 1966.\n\nGUSTAFSON, AB A\n\nPnr 70101\n\nÖrebro 1, Ormesta. Fack. Tel\n019-13 6140. Postgiro 28375-4\nVerksamhet: Tillverkar\ncharkuteri-varor o färdiglagad mat\nAntal anställda: 148\nÅrsomsättning: 43 000 000\nAktiekapital: 250 000\nVeikst dir: Gustaf Westerberg\nEtableringsår: 1894.\n\nGUSTAFSSONS FROHANDELS\nAB, BERTIL\n\nPnr 15010\n\nGnesta. Tel 0158-11215. Postgiro\n7613-3. Tga Bertil\nVerksamhet: Säljer fröer\nAntal anställda: 33\nAktiekapital: 363400\nVerkst dir: Hans Gustafsson\nEtableringsår: 1907.\n\nDAHLBERG AB, J O\n\nPnr 872 01\n\nKramfors 1, Box 205. Tel\n0612-114 40. Bankgiro 76-9506. Postgiro\n274967. Telex 71022\nVerksamhet: Tillverkar köksskåp o\ngarderobsinredningar\nAntal anställda: 150\nÅrsomsättning: 10 000 000\nAktiekapital: 500000\nVerkst dir: Georg Dahlberg\nEtableringsår: 1925.\n\nDAHLBERGS VERKSTÄDER,\nAB M\n\nPnr 890 50\n\nBjörna, Pack 14. Tel 0662-100 08.\nBankgiro 77-2304. Postgiro 62417.\nTga Dahlbergs\n\nVerksamhet: Grövre smiden,\nlastbilssläpvagnar o brobaneräcken\nAntal anställda: 9\nÅrsomsättning: 100 000\nAktiekapital: 31000\nVerkst dir: S Dahlberg\nEtableringsår: 1921.\n\nLEKOBOLAGEN I ESKILSTUNA\n\nPnr 631 06\n\nEskilstuna 1, Box 403. Tel\n016-11 91 82, 11 26 75. Bankgiro\n413-9507. Postgiro 167702-0. Tga Leko\nVerksamhet: Maskinkonstruktioner\no exportförsäljning\nVarunamn: Leketta\nAntal anställda: 7\nAktiekapital: 5 000\n\nVerkst dir: Leif Kellerth\nKonstruktionschef: Ing G Kellerth\nEtableringsår: 1969.\n\nDAL\n\nVerksamhet: Säljer svenska o\nimporterade grönsaker, potatis o frukt\nAntal anställda: 90\nÅrsomsättning: 30 000 000\nAktiekapital: 40 000\nVerkst dir: Einar Dahlin\nEtableringsår: 1950.\n\nDAHLQVIST AB,\nINGENJÖRSFIRMAN G\n\nPnr 234 00\n\nLomma, Industrig 25. Tel\n040-41 14 00. Bankgiro 876-3526.\nPostgiro 430940-7\n\nVerksamhet: Verkstad för\nventilationsplåtslageri\nAntal anställda: 30\nÅrsomsättning: 3 000 000\nAktiekapital: 75 000\nVerkst dir: Ing Gunnar Dahlqvist\nEtableringsår: 1950.\n\nDALLE REKLAM AB\n\nPnr 103 82\n\nStockholm 7, Box 7056. Biblioteksg\n27. Tel 08-24 9810. Bankgiro\n568-1648. Postgiro 453578-7\nVerksamhet: Reklam\nAntal anställda: 16\nÅrsomsättning: 4 000 000\nAktiekapital: 50 000\nVerkst dir. Ake Dalle\nEtableringsår: 1950.\n\nDAHLLÖF &amp; CO, AB LINNE\n\nPnr 41118\n\nGöteborg, N Liden 4. Tel\n031-17 29 90. Bankgiro 84-7977.\nPostgiro 12234. Tga Dahlco.\nTelex 2358\n\nVerksamhet: Import o försäljning\nav eldningsoljor, kol o koks\nAntal anställda: 13\nÅrsomsättning: 26 000 000\nAktiekapital: 180 000\nDir:r: Ingvar Grundell, Lars-Eric\nDahllöf\n\nEtableringsår: 1925\nDotterbolag: Lidköping Kol &amp; Koks\nAB, Lidköping, AB Bröderna\nWijk-lunds Kolimport, Falkenberg, Curt\nNycander AB, Strömstad.\n\nDALMA, AB\n\nPnr 103 62\n\nStockholm 3, Box 3119. Sveav 21.\nTel 08-24 84 30. Bankgiro 56-3025,\n84-5510. Postgiro 603775. Tga\nAbe-dalma. Telex 10609 DALMA S\nVerksamhet: Agenturfirma för\nkemiska, plast- o gummiindustrin\nAktiekapital: 50 000\nVerkst dir: Dr Karl Walter Petersen\nEtableringsår: 1959.\n\nAGMAKO AB\n\nPnr 13101\n\nNacka 1, Becksjudarv 29. Box 73.\nTel 08-7167276, 71672 77.\nBankgiro 74-6056. Postgiro 340027.\nTga Agmaskin, Stockholm.\nTelex 10467 AGMAKO S\nVerksamhet: Importerar o säljer\nmek o pneumatiska\ntransportan-läggningar, kranar, linbanor,\ngruvanläggningar, krossar,\nmalanlägg-ningar, kylare,\nsopförbränningsao-läggningar.stoftavskiljningsanlägg-ningar o slangfilter, tegel för ugnar,\nugnar för kem o petrokemisk\nindustri, förädlingsmaskiner för\npappers-o aluminiumfolie- samt\nemballageindustrin, transportband o\nkeramiska friktionsbeläggningar\nAntal anställda: 6\nÅrsomsättning: 10 000 000\nAktiekapital: 100000\nStyrelse: Dir Karel V Bisicky\n(ordf), fru Aino Bisicky\nVerkst dir: Karel V Bisicky\nEtableringsår: 1962.\n\nFORSHAGA AB\n\nPnr 401 22\n\nGöteborg 1, Box 172. Tel\n031-4003 00. Bankgiro 848-0524,\n505-7260. Postgiro 12096-4. Tga\nForshaga. Telex 2309 FORSHAG S\nVerksamhet: Linoleum, golvplast,\nheltäckande textila mattor, parkett,\nväggplast, plastprofiler,\nkorrugerade plastplattor (Forbo)\nFörsäljningskontor: Stockholm C,\nKungsg 38. Tel 08-23 6160\nAntal anställda: 412\nÅrsomsättning: 72400 000\nAktiekapital: 4 000 000\nVerkst dir: Lennart Johansson\nEtableringsår: 1896.\n\nFORSHAMMARS BERGVERK,\nAB\n\nPnr 73101\n\nKöping 1, Box 23. Stora g 12. Tel\n0221-139 05. Bankgiro 81-1211.\nPostgiro 370320. Tga Fältspat\nVerksamhet: Brytning o förmälning\nav fältspats- o kvartsprodukter vid\nbergverket i Forshammar.\nTillverkar kupolugnsmassa, eldfast\ncement (stamp-, avlagrings- o\ngjut-massor, eldfast service) vid\nkvartsverket i Rådanefors\nAvdelningskonton 431 37 Mölndal,\nFlöjelbergsg 11. Tel 031-87 00 35\nStenbrott o malverk: Riddarhyttan.\nTel 0222-31014\nVarunamn: Rådanit\nAntal anställda: 87\nAktiekapital: 500 000\nVerkst dir: Erie Olson\nEtableringsår: 1944.\n\nFORSHEDA GUMMIFABRIK AB\n\nPnr 330 12\n\nForsheda, Storg 26. Tel\n0370-81250. Bankgiro 141-8029.\nPostgiro 323268-3. Tga Forshedagummi.\nTelex 70004 FORSHED S\n\nI FORSHEDA\n\nVerksamhet: Tillverkar\ntätnings-ringar för rörfogar, G-ring;\naxel-lagertätningar, V-ring;\nindustrigummi. formgjorda detaljer av\nnaturgummi o olika typer av\nsyntetiskt gummi,\ngummi-metallbindningar, kompletta\nvibrationsdämpare\n\nExportförsäljning: Forsheda.\nForsheda International AB. Tel\n0370-81250. Telex 70004 FORSHED S.\nTga Forshedainter. Verkst dir:\nErik Sporre\n\nVarunamn: G-ring, G-ringkoppling,\nV-ring\n\nAntal anställda: 600\nÅrsomsättning: 40 000 000\nAktiekapital: 1215 000\nStyrelse: Dir Erik Sporre (ordf),\ndir Sten Sporre, dir Sigurd\nTeden-stad. adv Sten Carlston, dir Knut\nStehagen\n\nVerkst dir: Sigurd Tedenstad\nMarknadsdir: Göran Widenfelt\nEtableringsår: 1946.\n\nFORSHEDAVERKEN, AB\n\nPnr 330 12\n\nForsheda. Tel 0370-812 60.\nBankgiro 141-7211. Postgiro 13371-0.\nTga Forshedaverken\nVerksamhet: Tillverkar präglade\narbeten, söljor o ringar,\nskidbind-ningar, spännen o knäppen för\növerdragskläder. trådkedjor mm.\nMassartiklar av tråd o plåt efter\nmodeller eller ritningar\nAntal anställda: 25\nÅrsomsättning: 2 000 000\nAktiekapital: 200 000\nVerkst dir: Ing Nat Peterson\nDisp: David Peterson\nCiviling: Ragnar Peterson\nEtableringsår: 1920\nOmbildat till aktiebolag 1953.\n\nFORSHELL, FIRMA B\n\nPnr 383 00\n\nMönsterås, Box 36. Tel\n0499-10102. Bankgiro 142-7996.\nPostgiro 41570-3. Tga Beforshell\nVerksamhet: Säljer etsade,\neloxe-rade, lacktryckta o graverade\nskyltar, skalor, instrumentpaneler o\nfronter, dekaler o etiketter. Tryckta\nledningskretsar\nÄgare o chef: Sten Olsson\nEtableringsår: 1931.\n\nNYR\n\noljor, tryckfärgsoljor o andra\nspecialoljor för industrin, asfalt o\nasfaltlösningar, organiska\nkiselför-eningar o naftenatlösningar,\ntillverkas vid egna raffinaderier i\nNynäshamn, Göteborg o Malmö\nRaffinaderier: Göteborg. Tel\n031-630280\n\nMalmö. Tel 040-32300\nNynäshamn. Tel 0752-142 60\nVerkst din Bo Ax: son Johnson\nEtableringsàr. 1930.\n\nNYRAM AB\n\nPnr 61101\n\nNyköping 1, Box 150. Tel\n0155-57155. Bankgiro 44-6746.\nPostgiro 170755. Tga Nyram\nVerksamhet: Tillverkar ramlist o\nramar. Säljer reproduktioner.\n\nNYSILVERSMEDJAN\n\nPnr 53100\n\nLidköping, Vink elg 4. Tel\n0510-21006. Postgiro 281528\nVerksamhet: Försilvrar, förnicklar,\nförkromar o elförzinkar\nAntal anställda: 40\nChef: Fabr Per Johansson\nEtableringsàr: 1936.\n\nNYSTRAND KONSULTERANDE\nINGENJORSBYRÅ AB, AXEL S\n\nPnr 824 00\n\nHudiksvall, N Kyrkog\n10.Tel0650-11445, 11462. Postgiro 691570\nVerksamhet: Hus-, bro- o\nhamnbyggnader\nAntal anställda: 10\nÅrsomsättning: 500 000\nVerkst dir: Byggnadsing Axel S\nNystrand\n\nEtableringsàr: 1947.\n\nNYSTROMS BIL AB\n\nPnr 550 02\n\nJönköping 2, Box 2126. Odeng 38.\nTel 036-1197 70. Bankgiro\n545-3519. Postgiro 12745-6\nVerksamhet: Aukt återförsäljare\nför Volvo person- o lastbilar\nAntal anställda: 95\nÅrsomsättning: 17 860 000\nVerkst dir: Bertil Lindström\nEtableringsàr: 1951.\n\nNYSTROM AB, BRÖDERNA\n\nPnr 761 00\n\nNorrtälje, Box 66. Baldersg 20. Tel\n0176-127 80. Bankgiro 231-8111.\nPostgiro 281370-7\nVerksamhet: Tillverkar\nstålkonstruktioner, byggnadssmiden, grövre\nplåtarbeten\nAntal anställda: 32\nÅrsomsättning: 2 400 000\nAktiekapital: 20 000\nVerkst dir: Konrad Nyström\nVerkstadschef: Gunnar Nyström\nKamrer: Rolf Nyström\nEtableringsàr: 1944\nOmbildat till aktiebolag 1959.\n\nNYSTROMS CEMENTVARU.\nFABRIK AB\n\nPnr 762 00\n\nRimbo, Rö. Tel 0175-620 80, 620 82.\nBankgiro 805-8455. Postgiro\n264399-7\n\nVerksamhet: Tillverkar all slags\ncementvaror, såsom betongbjälklag\nav typ EW, betonghålsten,\nlerklin-kerblock, rör, brunnsringar,\nplattor m m. Säljer byggnadsvaror\nBetongstation för Salu-betong: Tel\n0175-62192\nAntal anställda: 25\nÅrsomsättning: 6 000 000\nChef: Dir Gunnar Nyström\nEtableringsàr: 1952.\n\nNYST ROM &amp; LINDELL AB\n\nPnr 541 00\n\nSkövde, Varnhemsg 20-22. Tel\n0500-106 90. Bankgiro 210-0527.\nPostgiro 141925-8\nVerksamhet: Trä- o\nbyggmaterialhandel i parti o minut\nAntal anställda: 32\nÅrsomsättning: 13 000 000\nAktiekapital: 500 000\nStyrelse: Disp Erik Hermansson\n(ordf), dir Gunnar Lindell, disp\nNils Carlsson, aukt revisor Arne\nLindell, trävaruh Nils Sahlström\nVerkst din Gunnar Lindell\nEtableringsàr 1916\nOmbildat till aktiebolag 1957.\nDotterbolag: Karl Larssons Trävaru\nAB, TibroByggvaror AB, Skaraborgs\nGolv AB, Edli Industri AB,\nSkaraborgs Plattsättning AB.\n\nNYST ROM &amp; MATTHEY, AB\n\nPnr 104 62\n\nStockholm 17, Rosenlundsg 52. Box\n17103. Tel 08-84 22 20, 84 22 36.\nBankgiro 235-1104. Postgiro\n53909-8. Tga Stany. Telex 10699\nVerksamhet: Adla metaller för\nsil-ver- o guldvarutillverkare samt för\ndentala o industriella ändamål.\nFärgpigment. Keramiska\nugnstillbehör. Porslinsformningsmaskiner.\n\"Sintox\" industrikeramik\nVarunamn: Easyflo, Silfos\nAktiekapital: 900 000\nVerkst dir: Arvid Nyström\nEtableringsàr: 1932\nDotterbolag till Johnson, Matthey\n&amp; Co Ltd, London.\nRepresenterar dessutom: Blythe\nColours Ltd., Cresswell. The\nDiamond Clay Co Ltd., Stoke-on-Trent.\nService (Engineers) Ltd.,\nStoke-on-Trent. Smiths Industries Ltd.,\nCeramic Division, Rugby.\n\nNYSTROMS MEKANISKA AB\n\nPnr 690 50\n\nVretstorp, Fagerlid. Tel\n0582-604 00, 604 01. Bankgiro 819-5653.\nPostgiro 649440\n\nVerksamhet: Tillverkar släpvagnar\nför traktorer o bilar. Utför mek\narbeten, svarvning, fräsning o\npressning\nAntal anställda: 6\nAktiekapital: 30 000\nEtableringsàr: 1969.\n\nNYST ROMS MEKANISKA, AB\nBRÖDERNA\n\nPnr 93100\n\nSkellefteå, Mjödvattnet. Tel\n0914-42018. 42058. Bankgiro 203-9196.\nPostgiro 480676-6. Tga Nymek\nVerksamhet: Tillverkar\ntransportvagnar, elcentraler, järn- o\nkaros-seridetaljer i serieproduktion\n\nAntal anställda: 70\nÅrsomsättning: 4 000 000\nAktiekapital: 65 000\nVerkst dir: Ivan Nyström\nEtableringsàr: 1947.\n\nNYSTROMS MONTAGE\nSERVICE AB\n\nPnr 640 33\n\nBettna, Aspudden. Tel 0155-940 42\nVerksamhet: Tillverkar\nventilations-materiel o järnkonstruktioner. Utför\nmontage av\nventilationsanläggningar, ställningsmontering,\nsvetsningsarbeten i galvplåt o svartplåt\nAntal anställda: 8\nÅrsomsättning: 500 000\nAktiekapital: 5 000\nVerkst dir: Bernt Nyström\nEtableringsàr: 1964.\n\nNYSTROMS OLJOR AB\n\nPnr 40273\n\nGöteborg 8, Box 8902. Polstjärneg\n8 B. Tel 031-17 20 20. Bankgiro\n501-6043. Postgiro 627577-0\nVerksamhet: Säljer o distribuerar\neldningsoljor\n\nFörsäljningskontor: Nässjö,\nOtter-bäcken, Trollhättan, Uddevalla\nAntal anställda: 30\nÅrsomsättning: 18000 000\nAktiekapital: 200 000\nVerkst dir: Hans-Börje Wallenholm\nFörsäljn-chef: Harry Niklasson\nEtableringsàr: 1958\nDotterbolag: Thiel &amp; Tegnhammar\nAB, Floby, AB Göteborgs\nOljetjänst, Göteborg.\n\nNYSTROM AB,\nINGENJÖRSFIRMA B J\n\nPnr 60102\n\nNorrköping 1, N Promenaden 127.\nBox 36. Tel 011-13 00 89, 13 00 88.\nBankgiro 61-0002. Postgiro 272294\nVerksamhet: Säljer pumpar o\ntemperaturregulatorer\nAntal anställda: 7\nChef: Ing B J Nyström\nEtableringsån 1932 .\n\nBRONÄS INDUSTRI AB\n\nPnr 661 00\n\nSäffle, Brov 27. Tel 0533-40150.\nBankgiro881-3982. Postgiro 8132-3\nVerksamhet: Tillverkar\nskolpaviljonger, affärsbyggnader,\nbostadshus samt manskapsvagnar o -bodar\nFörsäljningskontor: Stockholm C,\nDrottningg 81 A. Tel 08-10 56 25\nGöteborg SV, Dr Forselius g 17.\nTel 031-18 8148\n\nHöör, Villa Evershill. Tel\n0413-202 54\n\nVarunamn: Bronäsvagnen, Cubhus,\nKarlskronavillan\nAntal anställda: 225\nÅrsomsättning: 24 000 000\nAktiekapital: 100 000\nStyrelse: Dir Olle Haglund (ordf),\ndir Gustaf Nordén, dir-ass Christer\nNordén\n\nVerkst dir: Gustaf Nordén\nEtableringsår: 1943\nOmbildat till aktiebolag 1960.\n\nBRONÄS KVARNFABRIK, AB\n\nPnr 530 42\n\nVinninga, Box 39. Tel\n0510-50150, 50416. Bankgiro 212-4097.\nPostgiro 365783-0\nVerksamhet: Tillverkar kvarnar,\nspannmålkrossar, blandare,\nportionerare, automatiska fodercentraler.\nKvarnmaskiner för lantbruket\nVarunamn: Nirvana\n.Antal anställda: 20\nÅrsomsättning: 1200000\nAktiekapital: 50 000\nVerkst dir: Arne Ivarsson\nEtableringsår: 1920.\n\nHÄGGLUNDS SNICKERI.\nFABRIK, AB\n\nPnr 78100\n\nBorlänge, Tunag 21. Tel\n0243-110 06. Bankgiro 79-4681. Postgiro\n92785\n\nVerksamhet: Skåpinredningar för\nskolor\n\nAntal anställda: 14\nAktiekapital: 10000\nVeikst dir Kurt Hägglund\nEtableringsår 1932.",
    "structured": {
        "1": {
            "company_name": "INDUSTRIKONSULT, AB",
            "pnr": "33100",
            "address": "Brog 2, Värnamo",
            "phone_number": "0370-130 61, 13062",
            "bank_details": {
                "bankgiro": "981-8600",
                "postgiro": "286742-2"
            },
            "activity": "Konsulter i produktionsteknik, teknisk organisation, arbetsstudier o industriplanering",
            "employees": 10,
            "capital": 15000,
            "key_personnel": [
                {
                    "name": "Ing Bo Jonsson",
                    "position": "Veikst dir"
                }
            ],
            "establishment_year": 1958
        },
        "2": {
            "company_name": "INDUSTRIKRAFT AB, INGENJÖRSFIRMAN",
            "pnr": "191 21",
            "address": "Box 52, Sollentuna",
            "phone_number": "08-961452",
            "bank_details": {
                "bankgiro": "746-6600",
                "postgiro": "503281-8"
            },
            "activity": "Hydraulik, konstruktion o tillverkning",
            "establishment_year": 1963
        },
        "3": {
            "company_name": "INDUSTRIKRAFTS FÖRSÄLJ-NINGS AB, INGENJÖRSFIRMAN",
            "pnr": "162 36",
            "address": "Aprikosg 27, Vällingby",
            "phone_number": "08-38 65 65",
            "bank_details": {
                "bankgiro": "29-5950",
                "postgiro": "600009"
            },
            "activity": "Försäljning o service av hydrauliska maskiner",
            "establishment_year": 1966
        },
        "4": {
            "company_name": "GUSTAFSON, AB A",
            "pnr": "70101",
            "address": "Ormesta, Örebro",
            "phone_number": "019-13 6140",
            "postgiro": "28375-4",
            "activity": "Tillverkar charkuteri-varor o färdiglagad mat",
            "employees": 148,
            "annual_turnover": 43000000,
            "capital": 250000,
            "key_personnel": [
                {
                    "name": "Gustaf Westerberg",
                    "position": "Veikst dir"
                }
            ],
            "establishment_year": 1894
        },
        "5": {
            "company_name": "GUSTAFSSONS FROHANDELS AB, BERTIL",
            "pnr": "15010",
            "address": "Gnesta",
            "phone_number": "0158-11215",
            "postgiro": "7613-3",
            "activity": "Säljer fröer",
            "employees": 33,
            "capital": 363400,
            "key_personnel": [
                {
                    "name": "Hans Gustafsson",
                    "position": "Verkst dir"
                }
            ],
            "establishment_year": 1907
        },
        "6": {
            "company_name": "DAHLBERG AB, J O",
            "pnr": "872 01",
            "address": "Box 205, Kramfors",
            "phone_number": "0612-114 40",
            "bank_details": {
                "bankgiro": "76-9506",
                "postgiro": "274967"
            },
            "activity": "Tillverkar köksskåp o garderobsinredningar",
            "employees": 150,
            "annual_turnover": 10000000,
            "capital": 500000,
            "key_personnel": [
                {
                    "name": "Georg Dahlberg",
                    "position": "Verkst dir"
                }
            ],
            "establishment_year": 1925
        },
        "7": {
            "company_name": "DAHLBERGS VERKSTÄDER, AB M",
            "pnr": "890 50",
            "address": "Pack 14, Björna",
            "phone_number": "0662-100 08",
            "bank_details": {
                "bankgiro": "77-2304",
                "postgiro": "62417"
            },
            "activity": "Grövre smiden, lastbilssläpvagnar o brobaneräcken",
            "employees": 9,
            "annual_turnover": 100000,
            "capital": 31000,
            "key_personnel": [
                {
                    "name": "S Dahlberg",
                    "position": "Verkst dir"
                }
            ],
            "establishment_year": 1921
        },
        "8": {
            "company_name": "LEKOBOLAGEN I ESKILSTUNA",
            "pnr": "631 06",
            "address": "Box 403, Eskilstuna",
            "phone_number": "016-11 91 82, 11 26 75",
            "bank_details": {
                "bankgiro": "413-9507",
                "postgiro": "167702-0"
            },
            "activity": "Maskinkonstruktioner o exportförsäljning",
            "varunamn": "Leketta",
            "employees": 7,
            "capital": 5000,
            "key_personnel": [
                {
                    "name": "Leif Kellerth",
                    "position": "Verkst dir"
                },
                {
                    "name": "Ing G Kellerth",
                    "position": "Konstruktionschef"
                }
            ],
            "establishment_year": 1969
        },
        "9": {
            "company_name": "DAL",
            "activity": "Säljer svenska o importerade grönsaker, potatis o frukt",
            "employees": 90,
            "annual_turnover": 30000000,
            "capital": 40000,
            "key_personnel": [
                {
                    "name": "Einar Dahlin",
                    "position": "Verkst dir"
                }
            ],
            "establishment_year": 1950
        },
        "10": {
            "company_name": "DAHLQVIST AB, INGENJÖRSFIRMAN G",
            "pnr": "234 00",
            "address": "Industrig 25, Lomma",
            "phone_number": "040-41 14 00",
            "bank_details": {
                "bankgiro": "876-3526",
                "postgiro": "430940-7"
            },
            "activity": "Verkstad för ventilationsplåtslageri",
            "employees": 30,
            "annual_turnover": 3000000,
            "capital": 75000,
            "key_personnel": [
                {
                    "name": "Ing Gunnar Dahlqvist",
                    "position": "Verkst dir"
                }
            ],
            "establishment_year": 1950
        },
        "11": {
            "company_name": "DALLE REKLAM AB",
            "pnr": "103 82",
            "address": "Box 7056, Stockholm",
            "phone_number": "08-24 9810",
            "bank_details": {
                "bankgiro": "568-1648",
                "postgiro": "453578-7"
            },
            "activity": "Reklam",
            "employees": 16,
            "annual_turnover": 4000000,
            "capital": 50000,
            "key_personnel": [
                {
                    "name": "Ake Dalle",
                    "position": "Verkst dir"
                }
            ],
            "establishment_year": 1950
        },
        "12": {
            "company_name": "DAHLLÖF & CO, AB LINNE",
            "pnr": "41118",
            "address": "N Liden 4, Göteborg",
            "phone_number": "031-17 29 90",
            "bank_details": {
                "bankgiro": "84-7977",
                "postgiro": "12234"
            },
            "activity": "Import o försäljning av eldningsoljor, kol o koks",
            "employees": 13,
            "annual_turnover": 26000000,
            "capital": 180000,
            "key_personnel": [
                {
                    "name": "Ingvar Grundell",
                    "position": "Dir"
                },
                {
                    "name": "Lars-Eric Dahllöf",
                    "position": "Dir"
                }
            ],
            "establishment_year": 1925,
            "dotterbolag": [
                "Lidköping Kol & Koks AB, Lidköping",
                "AB Bröderna Wijklunds Kolimport, Falkenberg",
                "Curt Nycander AB, Strömstad"
            ]
        },
        "13": {
            "company_name": "DALMA, AB",
            "pnr": "103 62",
            "address": "Box 3119, Stockholm",
            "phone_number": "08-24 84 30",
            "bank_details": {
                "bankgiro": "56-3025, 84-5510",
                "postgiro": "603775"
            },
            "activity": "Agenturfirma för kemiska, plast- o gummiindustrin",
            "capital": 50000,
            "key_personnel": [
                {
                    "name": "Dr Karl Walter Petersen",
                    "position": "Verkst dir"
                }
            ],
            "establishment_year": 1959
        },
        "14": {
            "company_name": "AGMAKO AB",
            "pnr": "13101",
            "address": "Becksjudarv 29, Nacka",
            "phone_number": "08-7167276, 71672 77",
            "bank_details": {
                "bankgiro": "74-6056",
                "postgiro": "340027"
            },
            "activity": "Importerar o säljer mek o pneumatiska transportan-läggningar, kranar, linbanor, gruvanläggningar, krossar, malanlägg-ningar, kylare, sopförbränningsao-läggningar.stoftavskiljningsanlägg-ningar o slangfilter",
            "employees": 6,
            "annual_turnover": 1000000,
            "capital": 100000,
            "key_personnel": [
                {
                    "name": "Karel V Bisicky",
                    "position": "Verkst dir"
                }
            ],
            "establishment_year": 1962
        },
        "15": {
            "company_name": "FORSHAGA AB",
            "pnr": "401 22",
            "address": "Box 172, Göteborg",
            "phone_number": "031-4003 00",
            "bank_details": {
                "bankgiro": "848-0524, 505-7260",
                "postgiro": "12096-4"
            },
            "activity": "Tillverkar linoleum, golvplast, heltäckande textila mattor, parkett, väggplast, plastprofiler, korrugerade plastplattor (Forbo)",
            "försäljningskontor": "Stockholm C, Kungsg 38, Tel: 08-23 6160",
            "employees": 412,
            "annual_turnover": 72400000,
            "capital": 4000000,
            "key_personnel": [
                {
                    "name": "Lennart Johansson",
                    "position": "Verkst dir"
                }
            ],
            "establishment_year": 1896
        },
        "16": {
            "company_name": "FORSHAMMARS BERGVERK, AB",
            "pnr": "73101",
            "address": "Box 23, Köping",
            "phone_number": "0221-139 05",
            "bank_details": {
                "bankgiro": "81-1211",
                "postgiro": "370320"
            },
            "activity": "Brytning o förmälning av fältspats o kvartsprodukter vid bergverket i Forshammar. Tillverkar kupolugnsmassa, eldfast cement (stamp-, avlagrings- o gjut-massor, eldfast service) vid kvartsverket i Rådanefors",
            "avdelningskonton": "431 37 Mölndal, Flöjelbergsg 11, Tel: 031-87 00 35",
            "varunamn": "Rådanit",
            "employees": 87,
            "capital": 500000,
            "key_personnel": [
                {
                    "name": "Erie Olson",
                    "position": "Verkst dir"
                }
            ],
            "establishment_year": 1944
        },
        "17": {
            "company_name": "FORSHEDA GUMMIFABRIK AB",
            "pnr": "330 12",
            "address": "Storg 26, Forsheda",
            "phone_number": "0370-81250",
            "bank_details": {
                "bankgiro": "141-8029",
                "postgiro": "323268-3"
            },
            "activity": "Tillverkar tätningsringar för rörfogar, axellagertätningar, industrigummi. formgjorda detaljer av naturgummi o olika typer av syntetiskt gummi, gummi-metallbindningar, kompletta vibrationsdämpare",
            "exportförsäljning": "Forsheda International AB, Tel: 0370-81250",
            "employees": 600,
            "annual_turnover": 40000000,
            "capital": 1215000,
            "key_personnel": [
                {
                    "name": "Erik Sporre",
                    "position": "Verkst dir"
                }
            ],
            "establishment_year": 1946
        },
        "18": {
            "company_name": "FORSHEDAVERKEN, AB",
            "pnr": "330 12",
            "address": "Forsheda",
            "phone_number": "0370-812 60",
            "bank_details": {
                "bankgiro": "141-7211",
                "postgiro": "13371-0"
            },
            "activity": "Tillverkar präglade arbeten, söljor o ringar, skidbindningar, spännen o knäppen för överdragskläder, trådkedjor mm. Massartiklar av tråd o plåt efter modeller eller ritningar",
            "employees": 25,
            "annual_turnover": 2000000,
            "capital": 200000,
            "key_personnel": [
                {
                    "name": "Ing Nat Peterson",
                    "position": "Verkst dir"
                },
                {
                    "name": "David Peterson",
                    "position": "Disp"
                },
                {
                    "name": "Ragnar Peterson",
                    "position": "Civiling"
                }
            ],
            "establishment_year": 1920,
            "ombildat till aktiebolag": 1953
        },
        "19": {
            "company_name": "FORSHELL, FIRMA B",
            "pnr": "383 00",
            "address": "Box 36, Mönsterås",
            "phone_number": "0499-10102",
            "bank_details": {
                "bankgiro": "142-7996",
                "postgiro": "41570-3"
            },
            "activity": "Säljer etsade, eloxerade, lacktryckta o graverade skyltar, skalor, instrumentpaneler o fronter, dekaler o etiketter. Tryckta ledningskretsar",
            "owner_n_chef": "Sten Olsson",
            "establishment_year": 1931
        },
        "20": {
            "company_name": "NYRAM AB",
            "pnr": "61101",
            "address": "Box 150, Nyköping",
            "phone_number": "0155-57155",
            "bank_details": {
                "bankgiro": "44-6746",
                "postgiro": "170755"
            }
        }
    }
}