{
    "original": "WESTMANS PLÅTSLAGERI, I\n\nPnr 87100\n\nHärnösand, Thuleg 24. Tel\n0611-139 63\n\nVerksamhet: Specialitet\nbyggnadsplåtslageri\n\nÄgare o chef: I Westman\nEtableringsår: 1953.\n\nNORDGREN AB, BRÖDERNA\n\nPnr 820 13\n\nRunemo. Tel 0271-15100. Bankgiro\n78-4764. Postgiro 367808. Tga\nNefab, Bollnäs\n\nVerksamhet: Tillverkar o säljer\ntransportemballage för\nlivsmedels-distribution, transport- o\nförvaringslådor för industrin, försvaret\nmm\n\nFörsäljningskontor: Stockholm,\nEngelbrektsg 25. Tel 08-20 05 20\nVarunamn: NEFAB\nAntal anställda: 140\nÅrsomsättning: 12 000 000\nAktiekapital: 50000\nVerkst dir: Hans Elov Nordgren\nEtableringsår: 1949.\n\nNORDGRENS PUMPAR AB,\nGUSTAV\n\nPnr 141 24\t«\n\nHuddinge 1, Box 1159. Dalhemsv\n44. Tel 08-774 03 70. Bankgiro\n478-6448. Postgiro 98040-9. Tga\nNor-pump. Telex 10595\nVerksamhet: Försäljning av pumpar\no armatur. Bil-, gummi- o\nbensinstationsutrustningar\nAktiekapital: 250 000\nVerkst dir: Gustav Nordgren\nEtableringsår: 1955.\n\nAUTODELAR AB\n\nPnr 702 20\n\nÖrebro, Väpnareg 29. Tel\n019-1156 80, 1289 81. Bankgiro\n614-5767. Postgiro 171473-2\nVerksamhet: Utför bilskrotning.\nSäljer bilreservdelar\nAntal anställda: 5\nAktiekapital: 90 000\nVerkst dir: Ove Whall\nEtableringsår: 1947.\n\nNILSSON, AB GOTTFRID\n\nPnr 852 30\n\nSundsvaU, Storg 11. Tel 060-15 65 12,\n11 23 64. Postgiro 28188\nVerksamhet: Försäljning av dam-,\nherr- o barnskor\nAktiekapital: 50 000\nChef: Förest Ingvar Stridsberg\nEtableringsår: 1916.\n\nNILSSON SNICKE-RI.\nFABRIK AB, GOTTFRID\n\nPnr 232 00\n\nAriöv. Hammarv. Tel 040-43 36 80.\nBankgiro 260-5590. Postgiro\n430310-3\n\nVerksamhet: Tillverkar\ninrednings-snickerier\nAntal anstäUda: 11\nÅrsomsättning: 1 000 000\nAktiekapital: 100 000\n\n\" Verkst dir: Torsten Bergström\nVerkstadschef: Algot Svensson\nEtableringsår: 1927.\n\nTELGE MASKINKONSULT, AB\n\nPnr 151 33\n\nSödertälje, Täppg 25. Tel\n0755-345 05 , 643 05. Bankgiro 622-8332.\nPostgiro 676363-5\nVerksamhet: Maskin o\nverktygskonstruktioner\nAntal anställda: 16\nÅrsomsättning: 1000 000\nAktiekapital: 5000\nStyrelse: Ing Björn Larsson (ordf),\ning Lennart Bergström, ing Rune\nLarsson, herr Elis Lundén\nVerkst dir: Ing Bjöm Larsson\nEtableringsår: 1965.\n\nSH I 0:s EKONOMITJÄNST\n\nPnr 702 12\n\nÖrebro, Engelbrektsg 6. Tel\n019-1246 70. Bankgiro 263-9060.\nPostgiro 417453-8\n\nVerksamhet: Revisioner,\nkonsultationer i företagekonomiska frågor\nAntal anstäUda: 14\nÅrsomsättning: 600 000\nChef: Revisor SRS C G Hjelmqvist\nEtableringsår 1957.\n\nVÄSTERVIKS KRAFT AB\n\nPnr 593 01\n\nVästervik 1, Box 25. Kvarng 12.\nTel 0490-169 20. Postgiro 705 81\nVerksamhet: Kraftverk,\neldistribution, busstrafik\n\nKraftstationer: Gunnebobruk.\nBo-torps Kraftstation. Tel 0490-220 23\nGunnebobruk. Tovehults Krafts\nstation. Tel 0490-260 77\nAntal anställda: 66\nÅrsomsättning: 8 213 000\nAktiekapital: 1 200 000\nVerkst din Sven Gustafsson\nChefsing: Einar Lavesson\nEtableringsår: 1897.\nOmbildat till aktiebolag 1930.\n\nWESTERVIKS\nPAPPERSBRUKS AB\n\nPnr 593 03\n\nVästervik. Tel 0490-130 90. Telex\n3906. Tga Pappbruket\nVerksamhet; Tillverkar testliner\nAntal anställda: 200\nÅrsomsättning: 30 000 000\nAktiekapital: 1400 000\nStyrelse: Tor Albertsson, Hans\nCavalli-Björkman. Gösta Holm.\nNils Linnander. Esbjörn Ulfsäter.\nLennart Ulvæus\nVerkst dir: Gösta Holm\nKamrer. A Andersson\nFörsäljn-chef: H Leife\nInköpschef: R Lundin.\n\nVÄSTERÅS BYGGMATERIAL\nAB\n\nPnr 72103\n\nVästerås 1, Verksg 4. Box 13. Tel\n021-13 7900. Bankgiro 80-8657.\nPostgiro 360785. Tga Västeråsbygg\nVerksamhet: Säljer\nbyggnadsmaterial o byggnadsindustrimaskiner\nAntal anställda: 70\nÅrsomsättning: 18 000 000\nAktiekapital: 200000\nVerkst din Disp Ake Hultström\nEtableringsår: 1947.\n\nPERSSON, JOHAN\n\nPnr 330 10\n\nBredaryd, Lanna. Tel 0370-83069.\nBankgiro 54-2511. Postgiro 76817-6\nVerksamhet: Tillverkar garnvindor,\nsybågar, rullband, artiklar i teak\nsamt stoppsvampar\nVerkst dir: Johan Persson.\n\nPERSSONS BYGGNADSVAROR,\nAB JOHAN\n\nPnr 294 00\n\nSölvesborg, Skånev 23. Tel 045\n6-10900. Bankgiro 285-9429.\nPostgiro 171750-3\n\nVerksamhet: Försäljning av\nbyggnadsmateriel. Sågverk\nAntal anstäUda: 38\nÅrsomsättning: 9 000 000\nAktiekapital: 262 000\nVerkst dir: Kjell Jonefors\nEtableringsår: 1939.\n\nPERSSONS TRÄVARU AB,\nJOSEPH\n\nPnr 401 24\n\nGöteborg 1, Nils Ericsonsg 4. Box\n255. Tel 031-80 13 10. Bankgiro\n50-6776. Postgiro 12401\nVerksamhet Säljer trävaror o\nbyggnadsmateriel\n\nAktiekapital: 500 000\nVerkst din Joseph Karlsson\nEtableringsår: 1917.\n\nTRE\n\nplast, textilavfall, gummiskrot o\növerskottsmateriel. Nedskrotning\nav industrianläggningar o rivning\nav fastigheter\n\nAvdelningskontor: 232 00 Arlöv. AB\nIndustriskrot, Västkustv. Tel\n040-43 03 11. Chef: Ingemar Fredricsson\n223 53 Lund. AB Metallexport,\nPrenneg 6. Tel 046-11 07 3 0. Chef:\nBengt Areskoug\n232 00 Arlöv. AB Metallexport,\nSege. Tel 040-43 0 9 00\nAntal anställda: 30\nÅrsomsättning: 7 000 000\nChef: Dir Bertil Areskoug\nEtableringsår: 1902.\n\nKOBBS SÖNER, AB M S\n\nPnr 41105\n\nGöteborg, Kronhusg 16. Tel\n031-131989, 1380 20. Bankgiro\n500-7299. Postgiro 42200-6. Tga Kobbs\nVerksamhet: Té import\nAktiekapital: 100 000\nVerkst dir: Gösta Wingstrand\nEtableringsår: 1809\nOmbildat till aktiebolag 1958.\n\nKOCK AB, BIRGER\n\nPnr 113 53\n\nStockholm, Tuleg 15. Tel\n08-32 99 52, 32 99 72. Bankgiro\n560-2404. Postgiro 57208-1. Tga Ate-\n\nprogress\n\nVerksamhet: Agenturförsäljning av\nsiffer- o teckenindikatorer,\nräkneverk, metallbälgar, axelkopplingar\no kuggväxelmotorer\nAntal anställda: 3\nAktiekapital: 36 000\nVerkst dir: Lennart Bergsten\nEtableringsår: 1934.",
    "structured": {
        "1": {
            "company_name": "WESTMANS PLÅTSLAGERI",
            "activity": "Specialitet byggnadsplåtslageri",
            "establishment_year": 1953
        },
        "2": {
            "company_name": "NORDGREN AB, BRÖDERNA",
            "address": "Runemo",
            "phone_number": "0271-15100",
            "bank_details": {
                "bankgiro": "78-4764",
                "postgiro": "367808"
            },
            "activity": "Tillverkar o säljer transportemballage för livsmedels-distribution, transport- o förvaringslådor för industrin, försvaret mm",
            "employees": 140,
            "annual_turnover": 12000000,
            "capital": 50000,
            "key_personnel": [
                {
                    "name": "Hans Elov Nordgren",
                    "position": "Verkst dir"
                }
            ],
            "establishment_year": 1949
        },
        "3": {
            "company_name": "NORDGRENS PUMPAR AB, GUSTAV",
            "address": "Huddinge 1, Box 1159, Dalhemsv 44",
            "phone_number": "08-774 03 70",
            "bank_details": {
                "bankgiro": "478-6448",
                "postgiro": "98040-9"
            },
            "activity": "Försäljning av pumpar o armatur. Bil-, gummi- o bensinstationsutrustningar",
            "capital": 250000,
            "key_personnel": [
                {
                    "name": "Gustav Nordgren",
                    "position": "Verkst dir"
                }
            ],
            "establishment_year": 1955
        },
        "4": {
            "company_name": "AUTODELAR AB",
            "address": "Örebro, Väpnareg 29",
            "phone_number": "019-1156 80, 1289 81",
            "bank_details": {
                "bankgiro": "614-5767",
                "postgiro": "171473-2"
            },
            "activity": "Utför bilskrotning. Säljer bilreservdelar",
            "employees": 5,
            "capital": 90000,
            "key_personnel": [
                {
                    "name": "Ove Whall",
                    "position": "Verkst dir"
                }
            ],
            "establishment_year": 1947
        },
        "9": {
            "company_name": "NILSSON, AB GOTTFRID",
            "address": "SundsvaU, Storg 11",
            "phone_number": "060-15 65 12, 11 23 64",
            "postgiro": "28188",
            "activity": "Försäljning av dam-, herr- o barnskor",
            "capital": 50000,
            "key_personnel": [
                {
                    "name": "Ingvar Stridsberg",
                    "position": "Chef"
                }
            ],
            "establishment_year": 1916
        },
        "10": {
            "company_name": "NILSSON SNICKE-RI. FABRIK AB, GOTTFRID",
            "address": "Ariöv. Hammarv",
            "phone_number": "040-43 36 80",
            "bank_details": {
                "bankgiro": "260-5590",
                "postgiro": "430310-3"
            },
            "activity": "Tillverkar inrednings-snickerier",
            "employees": 11,
            "annual_turnover": "1 000 000",
            "capital": 100000,
            "key_personnel": [
                {
                    "name": "Torsten Bergström",
                    "position": "Verkst dir"
                },
                {
                    "name": "Algot Svensson",
                    "position": "Verkstadschef"
                }
            ],
            "establishment_year": 1927
        },
        "12": {
            "company_name": "TELGE MASKINKONSULT, AB",
            "address": "Södertälje, Täppg 25",
            "phone_number": "0755-345 05 , 643 05",
            "bank_details": {
                "bankgiro": "622-8332",
                "postgiro": "676363-5"
            },
            "activity": "Maskin o verktygskonstruktioner",
            "employees": 16,
            "annual_turnover": "1000 000",
            "capital": 5000,
            "key_personnel": [
                {
                    "name": "Ing Björn Larsson",
                    "position": "Styrelse"
                },
                {
                    "name": "Ing Lennart Bergström",
                    "position": "Styrelse"
                },
                {
                    "name": "Ing Rune Larsson",
                    "position": "Styrelse"
                },
                {
                    "name": "Elis Lundén",
                    "position": "Styrelse"
                },
                {
                    "name": "Ing Bjöm Larsson",
                    "position": "Verkst dir"
                }
            ],
            "establishment_year": 1965
        },
        "15": {
            "company_name": "VÄSTERVIKS KRAFT AB",
            "address": "Västervik 1, Box 25, Kvarng 12",
            "phone_number": "0490-169 20",
            "postgiro": "705 81",
            "activity": "Kraftverk, eldistribution, busstrafik",
            "kraftstationer": [
                "Gunnebobruk",
                "Bo-torps Kraftstation",
                "Tovehults Krafts station"
            ],
            "employees": 66,
            "annual_turnover": 8213000,
            "capital": 1200000,
            "key_personnel": [
                {
                    "name": "Sven Gustafsson",
                    "position": "Verkst din"
                },
                {
                    "name": "Einar Lavesson",
                    "position": "Chefsing"
                }
            ],
            "establishment_year": 1897
        },
        "16": {
            "company_name": "WESTERVIKS PAPPERSBRUKS AB",
            "address": "Västervik",
            "phone_number": "0490-130 90",
            "telex": "3906",
            "activity": "Tillverkar testliner",
            "employees": 200,
            "annual_turnover": 30000000,
            "capital": 1400000,
            "key_personnel": [
                {
                    "name": "Gösta Holm",
                    "position": "Styrelse"
                }
            ],
            "establishment_year": null
        },
        "17": {
            "company_name": "VÄSTERÅS BYGGMATERIAL AB",
            "address": "Västerås 1, Verksg 4, Box 13",
            "phone_number": "021-13 7900",
            "bank_details": {
                "bankgiro": "80-8657",
                "postgiro": "360785"
            },
            "activity": "Säljer byggnadsmaterial o byggnadsindustrimaskiner",
            "employees": 70,
            "annual_turnover": 18000000,
            "capital": 200000,
            "key_personnel": [
                {
                    "name": "Disp Ake Hultström",
                    "position": "Verkst din"
                }
            ],
            "establishment_year": 1947
        },
        "20": {
            "company_name": "PERSSON, JOHAN",
            "address": "Bredaryd, Lanna",
            "phone_number": "0370-83069",
            "bankgiro": "54-2511",
            "postgiro": "76817-6",
            "activity": "Tillverkar garnvindor, sybågar, rullband, artiklar i teak samt stoppsvampar",
            "key_personnel": [
                {
                    "name": "Johan Persson",
                    "position": "Verkst dir"
                }
            ]
        },
        "21": {
            "company_name": "PERSSONS BYGGNADSVAROR, AB JOHAN",
            "address": "Sölvesborg, Skånev 23",
            "phone_number": "0456-10900",
            "bank_details": {
                "bankgiro": "285-9429",
                "postgiro": "171750-3"
            },
            "activity": "Försäljning av byggnadsmateriel. Sågverk",
            "employees": 38,
            "annual_turnover": 9000000,
            "capital": 262000,
            "key_personnel": [
                {
                    "name": "Kjell Jonefors",
                    "position": "Verkst dir"
                }
            ],
            "establishment_year": 1939
        },
        "22": {
            "company_name": "PERSSONS TRÄVARU AB, JOSEPH",
            "address": "Göteborg 1, Nils Ericsonsg 4, Box 255",
            "phone_number": "031-80 13 10",
            "bankgiro": "50-6776",
            "activity": "Säljer trävaror o byggnadsmateriel",
            "capital": 500000,
            "key_personnel": [
                {
                    "name": "Joseph Karlsson",
                    "position": "Verkst din"
                }
            ],
            "establishment_year": 1917
        },
        "23": {
            "company_name": "TRE",
            "activity": "Nedskrotning av plast, textilavfall, gummiskrot o överskottsmateriel. Nedskrotning av industrianläggningar o rivning av fastigheter",
            "avdelningskontor": [
                {
                    "address": "232 00 Arlöv",
                    "company_name": "AB Industriskrot",
                    "phone_number": "040-43 03 11",
                    "key_personnel": [
                        {
                            "name": "Ingemar Fredricsson",
                            "position": "Chef"
                        }
                    ]
                },
                {
                    "address": "223 53 Lund",
                    "company_name": "AB Metallexport",
                    "phone_number": "046-11 07 3 0",
                    "key_personnel": [
                        {
                            "name": "Bengt Areskoug",
                            "position": "Chef"
                        }
                    ]
                },
                {
                    "address": "232 00 Arlöv",
                    "company_name": "AB Metallexport",
                    "phone_number": "040-43 0 9 00",
                    "key_personnel": [
                        {
                            "name": "Bertil Areskoug",
                            "position": "Chef"
                        }
                    ]
                }
            ],
            "employees": 30,
            "annual_turnover": 7000000,
            "capital": null,
            "key_personnel": [
                {
                    "name": "Dir Bertil Areskoug",
                    "position": "Chef"
                }
            ],
            "establishment_year": 1902
        },
        "24": {
            "company_name": "KOBBS SÖNER, AB M S",
            "address": "Göteborg, Kronhusg 16",
            "phone_number": "031-131989, 1380 20",
            "bank_details": {
                "bankgiro": "500-7299",
                "postgiro": "42200-6"
            },
            "activity": "Té import",
            "capital": 100000,
            "key_personnel": [
                {
                    "name": "Gösta Wingstrand",
                    "position": "Verkst dir"
                }
            ],
            "establishment_year": 1809
        },
        "25": {
            "company_name": "KOCK AB, BIRGER",
            "address": "Stockholm, Tuleg 15",
            "phone_number": "08-32 99 52, 32 99 72",
            "bank_details": {
                "bankgiro": "560-2404",
                "postgiro": "57208-1"
            },
            "activity": "Agenturförsäljning av siffer- o teckenindikatorer, räkneverk, metallbälgar, axelkopplingar o kuggväxelmotorer",
            "employees": 3,
            "capital": 36000,
            "key_personnel": [
                {
                    "name": "Lennart Bergsten",
                    "position": "Verkst dir"
                }
            ],
            "establishment_year": 1934
        }
    }
}