{
    "original": "ELEKTROKOPPAR, AB\n\nPnr 25101\n\nHelsingborg 1, Fack. Elektrog. Tel\n042-13 90 40. Bankgiro 160-0709.\nPostgiro 441289-6. Tga Cuprum.\nTelex 72337 CUPRUM S\nVerksamhet: Tillverkar valstråd,\ndragen tråd, band, lina o lacktråd\nav koppar samt valstråd, dragen\ntråd o lina av aluminium samt\nstål-aluminiumlina (Electral-lina)\nVarunamn: Electral-Lina\nAntal anställda: 280\nÅrsomsättning: 265 000 000\nAktiekapital: 15 000 000\nStyrelse: Bankdir Göte Engfors\n(ordf), dlr Nils Mölstad, dirDouglas\nvan Reis, tekn dr Ake T Vrethem,\ndir Sven T Åberg, dir Yngve\nÅkesson\n\nVerkst dir: Nils Mölstad\nSekretariat: Ulla Cederqvist\nFörsäljn o inköp: Erie Rangbo\nRäkenskapsavd: Reinhold Roslund\nProduktion: Börje Nilsson\nMaterialkontroll o\nproduktutveckling: Wolfgang Bronnvall\nEtableringsår: 1918\nÄges av ASEA (75%) och L M\nEricsson (25%).\n\nELEKTRO-LOOF AB\n\nPnr 540 72\n\nGullspång, Box 80. Tel\n0551-205 60. Bankgiro 220-5102.\nPostgiro 14227-8. Tga Elektrolööf\nVerksamhet: Tillverkar märksystem\nför elektr kontrollutrustningar\nVarunamn: Partex\nAntal anställda: 60\nÅrsomsättning: 4 000 000\nChef: N O Töre Lööf\nEtableringsår: 1948.\n\nELEKTROMATERIEL\nJOH PERSSON AB\n\nPnr 652 25\n\nKarlstad, Järnvägsg 2. Tel\n054-1870 55. Bankgiro 438-8088.\nPostgiro 21086-4\n\nVerksamhet: Försäljning av\nel-artiklar. Installations- o\nentreprenadrörelse\nAntal anstäUda: 35\nÅrsomsättning: 3 000 000\nAktiekapital: 100 000\nVerkst dir. Johan Persson\nInstallatör Enar Persson\nEtableringsår. 1923.\n\nELEKTROMEKANISKA AB\nGUSTAV ERIKSSON\n\nPnr 14171\n\nHuddinge, Ekhagsv 2. Tel\n08-88 83 95. Bankgiro 47-7907.\nPostgiro 56728\n\nVerksamhet: Elektr maskiner\nsåsom omformare, generatorer,\nelkraftaggregat, el-automatiska\nutrustningar\nAntal anstäUda: 23\nÅrsomsättning: 1 200 000\nAktiekapital: 15 000\nStyrelse: Ing Harald Erbing (ordf),\ning Nils G Eriksson, civiling Sven\nMeiton\n\nVerkst dir: Civiling Sven Meiton\nEtableringsår: 1915\nDotterbolag till AB Erbings\nMaskin affär, Stockholm.\n\nELEKTROMEKANOI\nBREDARYD AB\n\nPnr 33010\n\nBredaryd, Smedg 3. Box 84. Tel\n0370-80310. Bankgiro 142-7053.\nPostgiro 387331-2\nVerksamhet: Tillverkar o säljer\nCan Can tandläkarstolar o\ndental-utrustningar\nAntal anstäUda: 30\nÅrsomsättning: 3 000 000\nAktiekapital: 100 000\nVerkst dir: Ing Per Larson\nEtableringsår: 1949.\n\nVÄSTANHEDE TRÄ, AB\n\nPnr 770 60\n\nHomdal, Box 2150. Tel\n0226-710 39. Bankgiro 956-1028.\nPostgiro 71066-5\n\nVaksamhet: Tillverkar o säljer\nträull o trävaror\nAntal anställda: 10\nAktiekapital: 10 000\nVerkst dir: Sven Berg\nEtableringsår: 1966.\n\nFERNMO INDUSTRI AB\n\nPnr 542 01\n\nMariestad 1, Karlsrog 13. Box 25.\nTel 0501-165 10. Bankgiro\n213-2298. Postgiro 321411-1\nVerksamhet: Tillverkar förarhytter\nför traktorer, skogsmaskiner,\nväg-maskiner, skördetröskor, truckar m m\nVarunamn: Fernmo-Hytten\nAntal anställda: 55\nÅrsomsättning: 7 000 000\nAktiekapital: 50 000\nStyrelse: Disp Erie Fernmo (ordf),\nfru Stina Fernmo\nVerkst dir: Erik Fernmo\nEtableringsår: 1954\nOmbildat till aktiebolag 1961.\n\nFERMIA, AB\n\nPnr 25102\n\nHälsingborg 1, Industrig 37. Box\n47. Tel 042-1104 41,1106 00.\nBankgiro 863-6573. Postgiro 13908-9.\nTga Fermia\n\nVerksamhet: Tillverkar\nsockerkulör, invertsocker, säljer glykos,\ndruvsocker o sackarin\nVarunamn: Fermilin\nAktiekapital: 250 000\nVerkst dir: Konsul Herbert Iacobi\nEtableringsår: 1907.\n\nSVENSKA VÄGAKTIEBOLAG ET\n\nPnr 171 97\n\nSolna, Vretenv 13. Tel 08-98 18 40.\nBankgiro 165-5406. Postgiro\n52333-2. Tga Viaco\nVerksamhet: Entreprenad\nomfattande vägar, beläggningar,\nanläggningsarbeten o husbyggnader\nRegionskontor:\n\n402 41 Göteborg 12, Box 12075.\nKarl Johansg 66-70. Tel\n031-4203 60\n\n851 05 Sundsvall 1, Box 359.\nN Kajen 1. Tel 060-15 75 80\n352 31 Växjö, Klosterg 6. Tel\n0470-280 50\nAntal anställda: 5 000\nÅrsomsättning: 500 000 000\nAktiekapital: 3 000 000\nVeikst dir: Curt Nilsson\nDirektion: Produktionsdirr Folke\nEkwall, Sven Jansson, Evert Seth,\nadm dir Henry Lange\nEtableringsår. 1930\nDotterbolag: Granit och Beton AB,\nJohnson Construction Company AB,\nNorrländska Betong- och\nStenindustri AB, Förenad\nByggnadsprojektering AB.\n\nSVENSKA VÄGG.\nBEKLÄDNADER\n\nPnr 414 68\n\nGöteborg, Godhemsg 60. Tel\n031-24 55 52. Postgiro 522822\nVerksamhet: Utför fasadbeklädnad\nmed Malmex o Sidi-plattor mm,\ntaktäckningar med Eternit, taktegel\nmm samt byggnadsreparationer o\nändringar\n\nEtableringsår: 1962.\n\nHULTÉNS PAPPERS AB\n\nPnr 200 32\n\nMalmö 18, Volframg 14. Box 18050.\nTel 040-94 2140. Bankgiro 87-0256.\nPostgiro 38635\n\nVerksamhet: Engros- o\nagenturförsäljning av emballage för industrin\nsåsom papper, säckar, bindgarn,\ntejper, wellpappemballage,\npoly-etenföipackningar m m.\nSopkompri-matorer, sopsäcksställningar o\nsäckar. Pallhuvar\nAktiekapital: 150 000\nVerkst dir: Lennart Hultén\nEtableringsår 1937.\n\nUNÉR AB, H\n\nPnr 60101\n\nNorrköping 1,Fack. Trädgårdsg 42.\nTel 011-100040. Bankgiro\n125-0844. Postgiro 76460-5. Tga Unér.\nTelex 64053\n\nVerksamhet: Auktoriserade\nskeppsklarerare o skeppsmäklare\nAntal anställda: 35\nAktiekapital: 125 000\nVerkst dir: Göran Crafoord\nEtableringsår: 1848\nOmbildat till aktiebolag 1914.\n\nUNI SLIPSKIVOR.\nSVENMANS AB\n\nPnr 17107\n\nSolna 7, Box 707. Järvstigen 1.\nPostgiro 473647-6. Tga Abrasives.\nTelex 17694 UNISLIP S\n\nVerksamhet: Säljer UNI,\nUNI-NEVEN o EAC slipprodukter\nAntal anställda: 5\nAktiekapital: 50 000\nVerkst din Per Börjesson\nEtableringsår: 1957.\n\nTOPP INDUSTRI, AB\n\nPnr 701 06\n\nÖrebro 1, Fabriksg 10-12. Box 484.\nTel 019-13 6180. Bankgiro\n61-4409. Postgiro 272167. Tga\nToppindustri\n\nVerksamhet: Importerar o säljer\nSTAR MIX köksmaskiner, el vispar\nsamt STAR MASTER dammsugare\nVarunamn: Automix, Starboy,\nStar-king, Starlett, Starmaster, Star Mix,\nTopp\n\nAntal anställda: 70\nÅrsomsättning: 6 000 000\nAktiekapital: 25 000\nStyrelse: Dir Magnus Lundekvam\n(crdf), fru Ruth Lundekvam\nVerkst dir: Magnus Lundekvam\nEtableringsår: 1944.\n\nRENIL, AB\n\nPnr 18109\n\nLidingö 9, Vesslev 4. Box 956.\nTel 08-767 02 60. Bankgiro 56-9335.\nPostgiro 156474-9. Tga Renil.\nTelex 19110\n\nVerksamhet: Agenturrörelse med\nelektrisk installationsmateriel samt\nelektriska o elektroniska\nkomponenter för industrin\nAntal anstäUda: 8\nAktiekapital: 5 000\nVerkst dir Olof Revvik\nEtableringsår 1926.\n\nFROSTENSON &amp; LARSSON AB\n\nPnr 201 21\n\nMalmö 1, Skeppsbron 13 B. Box\n147. Tel 040-727 40. Tga Frolab.\nTelex 32338\n\nVeiksamhet: Skeppsmäkleri,\nfar-tygsklarering o lagerrörelse\nÅrsomsättning: 600 000\nEtableringsår: 1935.\n\nLKG PRESSDISTRIBUTION AB\n\nPnr 690 45\n\nÅsbro. Tel 0582-504 85. Bankgiro\n33-1161. Postgiro 597714\nVerksamhet: Utbärning av\nmorgontidningar\n\nAntal anställda: 40\n\nÅrsomsättning: 250 000\nAktiekapital: 5 000\nVeikst dir: Lars-Eric Gustafsson\nEtableringsår: 1959.",
    "structured": {
        "1": {
            "company_name": "ELEKTROKOPPAR, AB",
            "pnr": "25101",
            "address": "Helsingborg 1, Fack. Elektrog. Tel 042-13 90 40",
            "phone_number": "042-13 90 40",
            "bank_details": {
                "bankgiro": "160-0709",
                "postgiro": "441289-6"
            },
            "activity": "Tillverkar valstråd, dragen tråd, band, lina o lacktråd av koppar samt valstråd, dragen tråd o lina av aluminium samt stål-aluminiumlina (Electral-lina)",
            "employees": 280,
            "annual_turnover": 265000000,
            "capital": 15000000,
            "key_personnel": [
                {
                    "name": "Bankdir Göte Engfors",
                    "position": "ordf"
                },
                {
                    "name": "Nils Mölstad",
                    "position": "dlr"
                },
                {
                    "name": "Douglas van Reis",
                    "position": "dir"
                },
                {
                    "name": "Ake T Vrethem",
                    "position": "tekn dr"
                },
                {
                    "name": "Sven T Åberg",
                    "position": "dir"
                },
                {
                    "name": "Yngve Åkesson",
                    "position": "dir"
                }
            ],
            "establishment_year": 1918,
            "ownership": "Äges av ASEA (75%) och L M Ericsson (25%)"
        },
        "2": {
            "company_name": "ELEKTRO-LOOF AB",
            "pnr": "540 72",
            "address": "Gullspång, Box 80",
            "phone_number": "0551-205 60",
            "bank_details": {
                "bankgiro": "220-5102",
                "postgiro": "14227-8"
            },
            "activity": "Tillverkar märksystem för elektr kontrollutrustningar",
            "employees": 60,
            "annual_turnover": 4000000,
            "chief": "N O Töre Lööf",
            "establishment_year": 1948
        },
        "3": {
            "company_name": "ELEKTROMATERIELJ PERSSON AB",
            "pnr": "652 25",
            "address": "Karlstad, Järnvägsg 2",
            "phone_number": "054-1870 55",
            "bank_details": {
                "bankgiro": "438-8088",
                "postgiro": "21086-4"
            },
            "activity": "Försäljning av el-artiklar. Installations- o entreprenadrörelse",
            "employees": 35,
            "annual_turnover": 3000000,
            "capital": 100000,
            "chief_executive": "Johan Persson",
            "establishment_year": 1923
        },
        "4": {
            "company_name": "ELEKTROMEKANISKA AB GUSTAV ERIKSSON",
            "pnr": "14171",
            "address": "Huddinge, Ekhagsv 2",
            "phone_number": "08-88 83 95",
            "bank_details": {
                "bankgiro": "47-7907",
                "postgiro": "56728"
            },
            "activity": "Elektr maskiner såsom omformare, generatorer, elkraftaggregat, el-automatiska utrustningar",
            "employees": 23,
            "annual_turnover": 1200000,
            "capital": 15000,
            "key_personnel": [
                {
                    "name": "Ing Harald Erbing",
                    "position": "ordf"
                },
                {
                    "name": "Nils G Eriksson",
                    "position": "ing"
                },
                {
                    "name": "Sven Meiton",
                    "position": "civiling"
                }
            ],
            "establishment_year": 1915,
            "subsidiary_of": "AB Erbings Maskin affär, Stockholm"
        },
        "5": {
            "company_name": "ELEKTROMEKANOI BREDARYD AB",
            "pnr": "33010",
            "address": "Bredaryd, Smedg 3. Box 84",
            "phone_number": "0370-80310",
            "bank_details": {
                "bankgiro": "142-7053",
                "postgiro": "387331-2"
            },
            "activity": "Tillverkar o säljer Can Can tandläkarstolar o dental-utrustningar",
            "employees": 30,
            "annual_turnover": 3000000,
            "capital": 100000,
            "chief_executive": "Ing Per Larson",
            "establishment_year": 1949
        },
        "6": {
            "company_name": "VÄSTANHEDE TRÄ, AB",
            "pnr": "770 60",
            "address": "Homdal, Box 2150",
            "phone_number": "0226-710 39",
            "bank_details": {
                "bankgiro": "956-1028",
                "postgiro": "71066-5"
            },
            "activity": "Tillverkar o säljer träull o trävaror",
            "employees": 10,
            "capital": 10000,
            "chief_executive": "Sven Berg",
            "establishment_year": 1966
        },
        "7": {
            "company_name": "FERNMO INDUSTRI AB",
            "pnr": "542 01",
            "address": "Mariestad 1, Karlsrog 13. Box 25",
            "phone_number": "0501-165 10",
            "bank_details": {
                "bankgiro": "213-2298",
                "postgiro": "321411-1"
            },
            "activity": "Tillverkar förarhytter för traktorer, skogsmaskiner, väg-maskiner, skördetröskor, truckar m m",
            "employees": 55,
            "annual_turnover": 7000000,
            "capital": 50000,
            "key_personnel": [
                {
                    "name": "Disp Erie Fernmo",
                    "position": "ordf"
                },
                {
                    "name": "Stina Fernmo",
                    "position": "fru"
                }
            ],
            "chief_executive": "Erik Fernmo",
            "establishment_year": 1954,
            "converted_to_joint_stock_company": 1961
        },
        "8": {
            "company_name": "FERMIA, AB",
            "pnr": "25102",
            "address": "Hälsingborg 1, Industrig 37. Box 47",
            "phone_number": "042-1104 41,1106 00",
            "bank_details": {
                "bankgiro": "863-6573",
                "postgiro": "13908-9"
            },
            "activity": "Tillverkar sockerkulör, invertsocker, säljer glykos, druvsocker o sackarin",
            "employees": 0,
            "capital": 250000,
            "chief_executive": "Konsul Herbert Iacobi",
            "establishment_year": 1907
        },
        "9": {
            "company_name": "SVENSKA VÄGAKTIEBOLAG ET",
            "pnr": "171 97",
            "address": "Solna, Vretenv 13",
            "phone_number": "08-98 18 40",
            "bank_details": {
                "bankgiro": "165-5406",
                "postgiro": "52333-2"
            },
            "activity": "Entreprenad omfattande vägar, beläggningar, anläggningsarbeten o husbyggnader",
            "employees": 5000,
            "annual_turnover": 500000000,
            "capital": 3000000,
            "chief_executive": "Curt Nilsson",
            "board_of_directors": [
                {
                    "name": "Produktionsdirr Folke Ekwall"
                },
                {
                    "name": "Sven Jansson"
                },
                {
                    "name": "Evert Seth"
                },
                {
                    "name": "Henry Lange",
                    "position": "adm dir"
                }
            ],
            "establishment_year": 1930,
            "subsidiaries": [
                "Granit och Beton AB",
                "Johnson Construction Company AB",
                "Norrländska Betong- och Stenindustri AB",
                "Förenad Byggnadsprojektering AB"
            ]
        },
        "10": {
            "company_name": "SVENSKA VÄGG BEKLÄDNADER",
            "pnr": "414 68",
            "address": "Göteborg, Godhemsg 60",
            "phone_number": "031-24 55 52",
            "postgiro": "522822",
            "activity": "Utför fasadbeklädnad med Malmex o Sidi-plattor mm, taktäckningar med Eternit, taktegel mm samt byggnadsreparationer o ändringar",
            "establishment_year": 1962
        },
        "11": {
            "company_name": "HULTÉNS PAPPERS AB",
            "pnr": "200 32",
            "address": "Malmö 18, Volframg 14. Box 18050",
            "phone_number": "040-94 2140",
            "bank_details": {
                "bankgiro": "87-0256",
                "postgiro": "38635"
            },
            "activity": "Engros- o agenturförsäljning av emballage för industrin såsom papper, säckar, bindgarn, tejper, wellpappemballage, poly-etenföipackningar m m. Sopkompri-matorer, sopsäcksställningar o säckar. Pallhuvar",
            "capital": 150000,
            "chief_executive": "Lennart Hultén",
            "establishment_year": 1937
        },
        "12": {
            "company_name": "UNÉR AB, H",
            "pnr": "60101",
            "address": "Norrköping 1,Fack. Trädgårdsg 42",
            "phone_number": "011-100040",
            "bank_details": {
                "bankgiro": "125-0844",
                "postgiro": "76460-5"
            },
            "activity": "Auktoriserade skeppsklarerare o skeppsmäklare",
            "employees": 35,
            "capital": 125000,
            "chief_executive": "Göran Crafoord",
            "establishment_year": 1848,
            "converted_to_joint_stock_company": 1914
        },
        "13": {
            "company_name": "UNI SLIPSKIVOR. SVENMANS AB",
            "pnr": "17107",
            "address": "Solna 7, Box 707. Järvstigen 1",
            "postgiro": "473647-6",
            "activity": "Säljer UNI, UNI-NEVEN o EAC slipprodukter",
            "employees": 5,
            "capital": 50000,
            "chief_executive": "Per Börjesson",
            "establishment_year": 1957
        },
        "14": {
            "company_name": "TOPP INDUSTRI, AB",
            "pnr": "701 06",
            "address": "Örebro 1, Fabriksg 10-12. Box 484",
            "phone_number": "019-13 6180",
            "bank_details": {
                "bankgiro": "61-4409",
                "postgiro": "272167"
            },
            "activity": "Importerar o säljer STAR MIX köksmaskiner, el vispar samt STAR MASTER dammsugare",
            "employees": 70,
            "annual_turnover": 6000000,
            "capital": 25000,
            "board_of_directors": [
                {
                    "name": "Magnus Lundekvam",
                    "position": "crdf"
                },
                {
                    "name": "Ruth Lundekvam",
                    "position": "fru"
                }
            ],
            "chief_executive": "Magnus Lundekvam",
            "establishment_year": 1944
        },
        "15": {
            "company_name": "RENIL, AB",
            "pnr": "18109",
            "address": "Lidingö 9, Vesslev 4. Box 956",
            "phone_number": "08-767 02 60",
            "bank_details": {
                "bankgiro": "56-9335",
                "postgiro": "156474-9"
            },
            "activity": "Agenturrörelse med elektrisk installationsmateriel samt elektriska o elektroniska komponenter för industrin",
            "employees": 8,
            "capital": 5000,
            "chief_executive": "Olof Revvik",
            "establishment_year": 1926
        },
        "16": {
            "company_name": "FROSTENSON & LARSSON AB",
            "pnr": "201 21",
            "address": "Malmö 1, Skeppsbron 13 B. Box 147",
            "phone_number": "040-727 40",
            "activity": "Skeppsmäkleri, fartygsklarering o lagerrörelse",
            "annual_turnover": 600000,
            "establishment_year": 1935
        },
        "17": {
            "company_name": "LKG PRESSDISTRIBUTION AB",
            "pnr": "690 45",
            "address": "Åsbro",
            "phone_number": "0582-504 85",
            "bank_details": {
                "bankgiro": "33-1161",
                "postgiro": "597714"
            },
            "activity": "Utbärning av morgontidningar",
            "employees": 40,
            "annual_turnover": 250000,
            "capital": 5000,
            "chief_executive": "Lars-Eric Gustafsson",
            "establishment_year": 1959
        }
    }
}