{
    "original": "ORE\n\nAktiekapital: 15 000\nFinnatecknare: Disp Ragnar T:son\nAqvist, civilekonom Torsten\nLandin\n\nEtableringsår: 1936.\n\nÖREBRO TAKPANNEFABRIK\nAB BRÖDERNA SCHÖN\n\nPnr 705 90\n\nÖrebro, Närkes Kil. Tel\n019-23 12 84. Bankgiro 78-3950.\nPostgiro 340466\n\nVerksamhet: Tillverkar o säljer\nen- o tvåkupiga betongtakpannor\nAntal anställda: 7\nÅrsomsättning: 500 000\nChef: Lars Schön\nEtableringsår: 1964.\n\nOREBRO TEKN\nGUMMI-FABRIK AB\n\nPnr 703 58\n\nOtebro, Stålg 2. Tel 019-1190 85.\nBankgiro 463-1545. Postgiro\n327246-5\n\nVerksamhet: Gummifabrik\nAntal anställda: 150\nÅrsomsättning: 9 000 000\nAktiekapital: 360 000\nÄgare o chefer: Valter Cedstål,\nJohn Elverskog, Göte Neiby\nEtableringsår: 1946.\n\nWIKMANS BIL AB\n\nPnr 800 06\n\nGävle 6, Box 6055. S Kungsg 44.\nTel 026-1153 60. Bankgiro\n237-1730. Postgiro 124793-1\nVerksamhet: Auktoriserad\nFordrepresentant\nAntal anställda: 105\nÅrsomsättning: 15 000 000\nAktiekapital: 100 000\nVerkst dir: Torsten Wikman\nEtableringsår: 1951.\n\nELECTRONIC.SERVICE\n\nPnr 693 00\n\nDegerfors, Lervik 1. Tel\n0586-270 21. Postgiro 669422-8\nVerksamhet: Service av\nkommunikationsradioanläggningar\nChef: Erling Olsen\nEtableringsår: 1964.\n\ngiro 157262. Tga Eleckomp. Telex\n17418\n\nVerksamhet: Tillverkar reläer o\nelektroniska styr- o\nreglerutrust-ningar. Agenturförsäljning av\nreläer, fotocellutrustningar, induktiva\ngivare samt transformatorer\nAntal anställda: 20\nÅrsomsättning: 4 000 000\nAktiekapital: 20 000\nStyrelse: Ing Karl-Erik Eriksson\n(ordf), ing F van der Leer\nVerkst dir: Ing F van der Leer\nFörsäljn-chef: Ing Gunnar\nLindström\n\nEtableringsår: 1967.\n\nELEIKO, ELEKTRO MEK\nFABRIKEN\n\nPnr 300 04\n\nHalmstad 4, Kristian IV:s v. Box\n4001. Tel 035-1190 60. Bankgiro\n54-0220. Postgiro 140393. Tga\nEleiko\n\nVerksamhet: Tillverkar elektr\nhushållsapparater, automatik för\nsoprum, träningsredskap o\ntoalettstolar för småbarn\n\nFirmatecknare: Fru Tyra\nJohansson, ing Stig Edebalk\nEtableringsår: 1926.\n\nFROSTA SPARBANK\n\nPnr 242 00\n\nHörby, Box 53. Nyg 22. Tel\n0415-114 10. Bankgiro 981-0797.\nPostgiro 86880-2\nAntal anställda: 32\nBalansomslutning: 216 087 000\nVerkst dir: Bror Hansson\nEtableringsår: 1848.\n\nFROSTELL BOKBINDERI AB,\nHANSFR\n\nPnr 117 25\n\nStockholm, Timmermansg 10. Tel\n08-40 90 63, 40 90 93. Bankgiro\n57-1524. Postgiro 57037\nVeiksamhet: Parti- o\nprivatbokbin-deri\n\nAntal anstäUda: 17\nÅrsomsättning: 745 000\nAktiekapital: 5 000\nVeikst dir: Hansfr Frostell\nEtableringsår: 1930.\n\nVAL\n\nTel 08-22 44 60. Telex 17247 wahls s.\nTga Textilwahl. Inköps- o\nförsäljningskontor\n\nVerksamhet: Tillverkning o\nförsäljning av damkonfektion, klänningar,\nblusar, kjolar o fritidsplagg\nKonfektionsfabrik: 523 00\nUlricehamn, Dalg 8. Box 162. Tel\n0321-122 30\n\nFörsäljningskontor: 412 52Göteborg,\nSten Stureg 36. Tel 031-16 98 29\nVarunamn: Wahls\nAntal anställda: 200\nÅrsomsättning: 25 000000\nAktiekapital: 600 000\nVerkst dir: David Wahl\nEtableringsår: 1934\nOmbildat till aktiebolag 1940.\n\nVALAND, ÖMSESIDIGT, LIV.\nFÖRSÄKRINGSBOLAGET\n\nPnr 103 80\n\nStockholm 7, Birger Jarlsg 43.\nFack. Tel 08-22 34 20. Bankgiro\n72-2112. Postgiro 1158\nVerksamhet: Pensions- o\nlivförsäkringar\n\nAntal anställda: 297\nÅrsomsättning: 185 300 000\nVerkst dir: Mats Ernulf\nEtableringsår: 1894.\n\nKRISTOFFERSON, BROR\n\nPnr 212 15\n\nMalmö, Värnhemsg 4. Tel\n040-325 16, 93 34 96. Bankgiro\n691-4964. Postgiro 148905-3\n\nVeiksamhet: Konsthantverksalster i\nhuvudsak tennsmycken, emalj,\nCorpus tennartiklar, fat, kannor\netc. Bättre souvenirer\nChef: Bror Kristofferson\nEtableringsår: 1961.\n\nFASADPUTS ALLAN OLSSON\nAB\n\nPnr 117 30\n\nStockholm, Högalidsg 46 A. Tel\n08-69 0120. Bankgiro 56-7044.\nPostgiro 55890\n\nVerksamhet: Byggnadsverksamhet,\nfasadrenoveringar mm\nAntal anställda: 58\nÅrsomsättning: 4 000 000\nAktiekapital: 50 000\nVerkst dir: Ing Allan Olsson\nEtableringsår: 1959.\n\nINDUSTRINEON\n\nPnr 14141\n\nHuddinge, Poppelv 1. Tel\n08-757 57 66. 7578775.Bankgiro\n62-6079. Postgiro 9776\nVerksamhet: Tillverkar o säljer\nneon-plast- o metallskyltar\nAntal anställda: 10\nÅrsomsättning: 1000 000\nChef: Ing Curt Bertil Hertzberg\nEtableringsår: 1958.\n\nINDUSTRINS VATTEN, och\nLUFTVÅRD AB\n\nPnr 114 28\n\nStockholm, Drottning Kristinas v\n47 D. Tel 08-22 25 40. Bankgiro\n481-8167. Postgiro 51444-8\nVerksamhet: Undersökningar,\nutredningar, rådgivning o\nanalysverksamhet\n\nAvdelningskontor o laboratorium:\n\n11743 Stockholm, Liljeholmsv 32.\n\nChef: Ing Gustaf Blidberg\n\n400 4 0 Göteborg 4, Box 4052.\n\nChefer: Civiling Anders Hallhagen,\n\nprof Cyril Brosset\n\nAntal anställda: 74\n\nÅrsomsättning: 6 000 000\n\nAktiekapital: 10 000\n\nVerkst dir: Fil lic Stig Freyschuss\n\nV verkst dir: Leif Bruneau\n\nEtableringsår: 1965.\n\nHULTÉN &amp; EKSTRÖM, AB\n\nPnr 11347\n\nStockholm, Ynglingag 14. Tel\n08-23 53 25. Bankgiro 568-0525. Tga\nHultenmetall\n\nVerksamhet: Säljer metaller, bult,\ntråd, kablar, plåt, band, profiler,\nrör, spik, nitar, brickor, skruv,\nmuttrar, mattskenor, lödtenn, tenn,\nbly, koppar, antimon m m\nAntal anställda: 16\nAktiekapital: 100 000\nVerkst dir: Törd Svensson\nEtableringsår 1923.\n\nFIS\n\nFINSÉNS MEK VERKSTAD, E\n\nPnr 792 00\n\nMora, Box 972. Tel 0250-109 57.\nPostgiro 373022\n\nVerksamhet: Tillverkar\nstansverktyg, presentartiklar i järn, koppar\no mässing, socker-, is- o\nolivtänger. Försilvringsanläggning\nChef: Erik Finsén.\n\nFINSKA GUMMI AB\n\nPnr 126 30\n\nHägersten, Drivhjulsv 22-26.\nTel 08-45 25 40. Bankgiro 73-1740.\nPostgiro 226600. Tga Finskgummi.\nTelex 1802\n\nVerksamhet: Säljer bildäck o\nslangar\n\nVarunamn: Hakkapeliitta, Nokia\nVerkst dir: Mats Franzén\nEtableringsår: 1959\nDotterbolag till OY Nokia AB.\nFinska Gummifabriken,\nHelsingfors.\n\nFINSKA PAPPERS, och\nKARTONG AB\n\nPnr 103 83\n\nStockholm 7, Jakobsbergsg 9. Box\n7139. Tel 08-20 0174, 20 0175.\nBankgiro 56-9352. Postgiro 652369.\nTga Finservice. Telex 19127\nVerksamhet: Representerar Finska\nPappersbruksföreningen o Finska\nKartongföreningen\nAktiekapitel: 10 000\nVerkst dir: Ben Gummerus\nEtableringsår: 1949.",
    "structured": {
        "1": {
            "company_name": "ÖREBRO TAKPANNEFABRIK AB BRÖDERNA SCHÖN",
            "address": "Örebro, Närkes Kil",
            "phone_number": "019-23 12 84",
            "bank_details": {
                "bankgiro": "78-3950",
                "postgiro": "340466"
            },
            "activity": "Tillverkar o säljer en- o tvåkupiga betongtakpannor",
            "employees": 7,
            "annual_turnover": 500000,
            "key_personnel": [
                {
                    "name": "Lars Schön",
                    "position": "Chef"
                }
            ],
            "establishment_year": 1964
        },
        "2": {
            "company_name": "ÖREBRO TEKN GUMMI-FABRIK AB",
            "address": "Otebro, Stålg 2",
            "phone_number": "019-1190 85",
            "bank_details": {
                "bankgiro": "463-1545",
                "postgiro": "327246-5"
            },
            "activity": "Gummifabrik",
            "employees": 150,
            "annual_turnover": 9000000,
            "capital": 360000,
            "key_personnel": [
                {
                    "name": "Valter Cedstål",
                    "position": "Ägare o chefer"
                },
                {
                    "name": "John Elverskog",
                    "position": "Ägare o chefer"
                },
                {
                    "name": "Göte Neiby",
                    "position": "Ägare o chefer"
                }
            ],
            "establishment_year": 1946
        },
        "3": {
            "company_name": "WIKMANS BIL AB",
            "address": "Gävle 6, Box 6055, S Kungsg 44",
            "phone_number": "026-1153 60",
            "bank_details": {
                "bankgiro": "237-1730",
                "postgiro": "124793-1"
            },
            "activity": "Auktoriserad Fordrepresentant",
            "employees": 105,
            "annual_turnover": 15000000,
            "capital": 100000,
            "key_personnel": [
                {
                    "name": "Torsten Wikman",
                    "position": "Verkst dir"
                }
            ],
            "establishment_year": 1951
        },
        "4": {
            "company_name": "ELECTRONIC.SERVICE",
            "address": "Degerfors, Lervik 1",
            "phone_number": "0586-270 21",
            "bank_details": {
                "postgiro": "669422-8"
            },
            "activity": "Service av kommunikationsradioanläggningar",
            "employees": 20,
            "annual_turnover": 4000000,
            "capital": 20000,
            "key_personnel": [
                {
                    "name": "Ing Karl-Erik Eriksson",
                    "position": "Styrelse (ordf)"
                },
                {
                    "name": "Ing F van der Leer",
                    "position": "Styrelse"
                },
                {
                    "name": "Ing F van der Leer",
                    "position": "Verkst dir"
                },
                {
                    "name": "Ing Gunnar Lindström",
                    "position": "Försäljn-chef"
                }
            ],
            "establishment_year": 1967
        },
        "5": {
            "company_name": "ELEIKO, ELEKTRO MEK FABRIKEN",
            "address": "Halmstad 4, Kristian IV:s v. Box 4001",
            "phone_number": "035-1190 60",
            "bank_details": {
                "bankgiro": "54-0220",
                "postgiro": "140393"
            },
            "activity": "Tillverkar elektr hushållsapparater, automatik för soprum, träningsredskap o toalettstolar för småbarn",
            "key_personnel": [
                {
                    "name": "Fru Tyra Johansson",
                    "position": "Firmatecknare"
                },
                {
                    "name": "Ing Stig Edebalk",
                    "position": "Firmatecknare"
                }
            ],
            "establishment_year": 1926
        },
        "6": {
            "company_name": "FROSTA SPARBANK",
            "address": "Hörby, Box 53, Nyg 22",
            "phone_number": "0415-114 10",
            "bank_details": {
                "bankgiro": "981-0797",
                "postgiro": "86880-2"
            },
            "employees": 32,
            "annual_turnover": 216087000,
            "key_personnel": [
                {
                    "name": "Bror Hansson",
                    "position": "Verkst dir"
                }
            ],
            "establishment_year": 1848
        }
    }
}