{
    "original": "JUNEKAROSSERIER AB\n\nPnr 550 06\n\nJönköping 6, Fack. Tel 036-13 27 80\nVerksamhet: Karosseritillverkning\nAktiekapital: 100 000\nVerkst dir: C-A Ekström\nEtableringsår: 1939.\n\nEMBALLAGEFABRIKEN\n\nPnr 585 90\n\nLinköping, Karebyg. Tel\n013-1200 66\n\nVerksamhet: Tillverkar lådembal-\n\nlage av trä i alla storlekar samt\n\nlastpallar o pallkragar\n\nAntal anställda: 6\n\nÄgare o chef: Einar Andersson\n\nEtableringsår: 1951.\n\nERIKSSON AB, KARL-ERIK\n\nPnr 35103\n\nVäxjö 1, Box 8. Smedieg 33. Tel\n0470-103 40. Bankgiro 357-1775.\nPostgiro 515101-4\nVerksamhet: Säljer\nbyggnadsmaterial i parti o minut\nAntal anställda: 8\nÅrsomsättning: 4 000 000\nAktiekapital: 10 000\nVerkst dir Nils-Eric Nilsson\nEtableringsår. 1960.\n\nLAGERSTRÖM AB, BRÖDERNA\n\nPnr 104 25\n\nStockholm 30, Kellgrensg 10-12.\nBox 30041. Tel 08-54 09 80.\nBankgiro 48-2754. Postgiro 2323\n\nVerksamhet: Boktryck, offset o\nbokbinderi\nAntal anställda: 100\nAktiekapital: 600 000\nVerkst dir: Ingvar Guldstrand\nEtableringsår: 1903.\n\nASPLUNDVERKEN AB\n\nPnr 15102\n\nSödertälje 2, Hertig Karls v 57.\nFack. Tel 0755-395 40. Telex\n10238 DEVERK S. Tga\nAsplundverk\n\nVerksamhet: Maskiner o verktyg\nVerkst dir: C G Asplund\nEtableringsår: 1958\nHelägt dotterbolag till Defibrator\nAB, Stockholm.\n\nASPRO AB\n\nPnr 11322\n\nStockholm, Odeng 74. Tel\n08-309290, 318104. Bankgiro\n331-7039. Postgiro 150770-6.\nTga Asprolab\n\nVerksamhet: Säljer asfaltkokare,\ndisk-, rengörings- o torkmedel\nVarunamn: Asprol\nAntal anställda: 4\nÅrsomsättning: 250 000\nAktiekapital: 20000\nVerkst dir: Walter Smith\nEtableringsår: 1955.\n\nmaterialkontroll ab\n\nPnr 21134\n\nMalmö, Stortorget 29. Tel\n040-749 20. Bankgiro 870-5741.\nPostgiro 431221-1\n\nVerksamhet: Röntgenkontroll o icke\nförstörande materialprovning.\nTillverkningskontroll o besiktning av\ntryckkärl, stålkonstruktioner\nVerkst dir: Heinz Lüdicke\nEtableringsår: 1954.\n\nMEL\n\nMELANDERS VERKSTADS AB\n\nPnr 302 40\n\nHalmstad, Jutarumsv 6. Tel\n035-12 40 74. Bankgiro 53-0192.\nPostgiro 160639\n\nVerksamhet: Tillverkar längdmät-\n\nningsapparater, uppspänningsdornar\n\nAntal anstäUda: 5\n\nÄgare o chefer: Sture Grahn, Folke\n\nÄngel\n\nEtableringsår: 1939.\n\nSVETSPRODUKTER\n\nPnr 544 00\n\nHjo, Sveav 33. Tel 0503-106 49.\nBankgiro 21-6352. Postgiro 473306\nVerksamhet: Tillverkar\noljecisterner, järnkonstruktioner mm\nAntal anställda: 18\nÅrsomsättning: 750 000\nChef: Folke Kjellqvist\nEtableringsår 1954.\n\nHALLS BOKTRYCKERI AB, H\n\nPnr 55102\n\nJönköping 1. V Storg 27. Box 616.\nTel 036-11 98 00. Bankgiro 54-5402.\nPostgiro 6496. Telex 70041, 70140\nVerksamhet: Utger dagstidningarna\nJönköpings-Posten, Smålands\nAllehanda, Värnamo-Tidningen\n(Hallpressen). veckotidningen Svenska\nPosten, accidenstryckeri o förlag\nAntal anställda: 270\nÅrsomsättning: 20 200 000\n(koncernen 37 900 000)\nAktiekapital: 700 000\nVerkst dir: Stig Fredriksson\nV verkst dir: Bertil Petré\nFörsäljningsdir: Nils Seton\nEtableringsår: 1874\nDotterbolag: Smålands-Tidningens\nTryckeri AB, Eksjö, AB\nVetlanda-Posten, Vetlanda, Tidaholms\nTryckeri AB, Tidaholm, AB\nSmålänningen, Ljungby.\n\nHALLA AUTOMATSVARV.\nNINGSFABRIK, AB\n\nPnr 330 30\n\nGnosjö. Tel 0370-910 41\n\nVerksamhet: Specialitet:\nautomat-svarvning, armatur för vatten o\nvärme, övrigt efter prov eller\nritningar\n\nAktiekapital: 90 000\nVerkst dir: A Johansson\nEtableringsår: 1945.\n\nKPSSVENSKA AB\n\nPnr 417 05\n\nGöteborg, Gustaf Dalénsg 13. Tel\n031-513510. Bankgiro 165-1520.\nPostgiro 44701-1\nVerksamhet: Tillverkar kylskåp,\nfrysskåp, frysboxar, elspisar\nAntal anställda: 14\nAktiekapital: 25 000\nEtableringsår: 1962.",
    "structured": {
        "1": {
            "company_name": "JUNEKAROSSERIER AB",
            "pnr": "550 06",
            "address": "Jönköping 6, Fack.",
            "phone_number": "036-13 27 80",
            "activity": "Karosseritillverkning",
            "capital": 100000,
            "key_personnel": [
                {
                    "name": "C-A Ekström",
                    "position": "Verkst dir"
                }
            ],
            "establishment_year": 1939
        },
        "2": {
            "company_name": "EMBALLAGEFABRIKEN",
            "pnr": "585 90",
            "address": "Linköping, Karebyg.",
            "phone_number": "013-1200 66",
            "activity": "Tillverkar lådembal-lage av trä i alla storlekar samt lastpallar o pallkragar",
            "employees": 6,
            "key_personnel": [
                {
                    "name": "Einar Andersson",
                    "position": "Ägare o chef"
                }
            ],
            "establishment_year": 1951
        },
        "3": {
            "company_name": "ERIKSSON AB, KARL-ERIK",
            "pnr": "35103",
            "address": "Växjö 1, Box 8. Smedieg 33.",
            "phone_number": "0470-103 40",
            "bank_details": {
                "bankgiro": "357-1775",
                "postgiro": "515101-4"
            },
            "activity": "Säljer byggnadsmaterial i parti o minut",
            "employees": 8,
            "annual_turnover": 4000000,
            "capital": 10000,
            "key_personnel": [
                {
                    "name": "Nils-Eric Nilsson",
                    "position": "Verkst dir"
                }
            ],
            "establishment_year": 1960
        },
        "4": {
            "company_name": "LAGERSTRÖM AB, BRÖDERNA",
            "pnr": "104 25",
            "address": "Stockholm 30, Kellgrensg 10-12. Box 30041.",
            "phone_number": "08-54 09 80",
            "bank_details": {
                "bankgiro": "48-2754",
                "postgiro": "2323"
            },
            "activity": "Boktryck, offset o bokbinderi",
            "employees": 100,
            "capital": 600000,
            "key_personnel": [
                {
                    "name": "Ingvar Guldstrand",
                    "position": "Verkst dir"
                }
            ],
            "establishment_year": 1903
        },
        "5": {
            "company_name": "ASPLUNDVERKEN AB",
            "pnr": "15102",
            "address": "Södertälje 2, Hertig Karls v 57.",
            "phone_number": "0755-395 40",
            "activity": "Maskiner o verktyg",
            "key_personnel": [
                {
                    "name": "C G Asplund",
                    "position": "Verkst dir"
                }
            ],
            "establishment_year": 1958
        },
        "6": {
            "company_name": "ASPRO AB",
            "pnr": "11322",
            "address": "Stockholm, Odeng 74.",
            "phone_number": "08-309290, 318104",
            "bank_details": {
                "bankgiro": "331-7039",
                "postgiro": "150770-6"
            },
            "activity": "Säljer asfaltkokare, disk-, rengörings- o torkmedel",
            "employees": 4,
            "annual_turnover": 250000,
            "capital": 20000,
            "key_personnel": [
                {
                    "name": "Walter Smith",
                    "position": "Verkst dir"
                }
            ],
            "establishment_year": 1955
        },
        "7": {
            "company_name": "MATERIALKONTROLL AB",
            "pnr": "21134",
            "address": "Malmö, Stortorget 29.",
            "phone_number": "040-749 20",
            "bank_details": {
                "bankgiro": "870-5741",
                "postgiro": "431221-1"
            },
            "activity": "Röntgenkontroll o icke förstörande materialprovning. Tillverkningskontroll o besiktning av tryckkärl, stålkonstruktioner",
            "key_personnel": [
                {
                    "name": "Heinz Lüdicke",
                    "position": "Verkst dir"
                }
            ],
            "establishment_year": 1954
        },
        "8": {
            "company_name": "MELANDERS VERKSTADS AB",
            "pnr": "302 40",
            "address": "Halmstad, Jutarumsv 6.",
            "phone_number": "035-12 40 74",
            "bank_details": {
                "bankgiro": "53-0192",
                "postgiro": "160639"
            },
            "activity": "Tillverkar längdmät-ningsapparater, uppspänningsdornar",
            "employees": 5,
            "key_personnel": [
                {
                    "name": "Sture Grahn",
                    "position": "Ägare o chefer"
                },
                {
                    "name": "Folke Ängel",
                    "position": "Ägare o chefer"
                }
            ],
            "establishment_year": 1939
        },
        "9": {
            "company_name": "SVETSPRODUKTER",
            "pnr": "544 00",
            "address": "Hjo, Sveav 33.",
            "phone_number": "0503-106 49",
            "bank_details": {
                "bankgiro": "21-6352",
                "postgiro": "473306"
            },
            "activity": "Tillverkar oljecisterner, järnkonstruktioner mm",
            "employees": 18,
            "annual_turnover": 750000,
            "key_personnel": [
                {
                    "name": "Folke Kjellqvist",
                    "position": "Chef"
                }
            ],
            "establishment_year": 1954
        },
        "10": {
            "company_name": "HALLS BOKTRYCKERI AB, H",
            "pnr": "55102",
            "address": "Jönköping 1. V Storg 27. Box 616.",
            "phone_number": "036-11 98 00",
            "bank_details": {
                "bankgiro": "54-5402",
                "postgiro": "6496"
            },
            "activity": "Utger dagstidningarna Jönköpings-Posten, Smålands Allehanda, Värnamo-Tidningen (Hallpressen). veckotidningen Svenska Posten, accidenstryckeri o förlag",
            "employees": 270,
            "annual_turnover": 20200000,
            "capital": 700000,
            "key_personnel": [
                {
                    "name": "Stig Fredriksson",
                    "position": "Verkst dir"
                },
                {
                    "name": "Bertil Petré",
                    "position": "V verkst dir"
                },
                {
                    "name": "Nils Seton",
                    "position": "Försäljningsdir"
                }
            ],
            "establishment_year": 1874,
            "dotterbolag": "Smålands-Tidningens Tryckeri AB, Eksjö, AB Vetlanda-Posten, Vetlanda, Tidaholms Tryckeri AB, Tidaholm, AB Smålänningen, Ljungby"
        },
        "11": {
            "company_name": "HALLA AUTOMATSVARV. NINGSFABRIK, AB",
            "pnr": "330 30",
            "address": "Gnosjö.",
            "phone_number": "0370-910 41",
            "activity": "Specialitet: automat-svarvning, armatur för vatten o värme, övrigt efter prov eller ritningar",
            "capital": 90000,
            "key_personnel": [
                {
                    "name": "A Johansson",
                    "position": "Verkst dir"
                }
            ],
            "establishment_year": 1945
        },
        "12": {
            "company_name": "KPSSVENSKA AB",
            "pnr": "417 05",
            "address": "Göteborg, Gustaf Dalénsg 13.",
            "phone_number": "031-513510",
            "bank_details": {
                "bankgiro": "165-1520",
                "postgiro": "44701-1"
            },
            "activity": "Tillverkar kylskåp, frysskåp, frysboxar, elspisar",
            "employees": 14,
            "capital": 25000,
            "establishment_year": 1962
        }
    }
}