{
    "original": "SCH\n\nAktiekapital: 400 000\n\nVerkst dir Ing Joachim Lorenz\nEtableringsàr: 1958\nDotterbolag till Schunk &amp; Ebe\nGmbH, Giessen, Väst Tyskland.\n\nSCHWALBE,\nMASKINBYGGNADSFIRMAN INGEMAR\n\nPnr 11138\n\nStockholm, David Bagares g 8. Tel\n08-2150 49. Postgiro 57727\nVeiksamhet: Allmän mekanisk\nutvecklings- o uppfinnarverksamhet.\nPrototyptillverkning\nÄgare o chef: Civiling Ingemar\nSchwalbe.\n\nSCHWARTZMAN&amp; NORD.\nSTRÖM, AB\n\nPnr 45101\n\nUddevaUa 1, Osterg. Pack. Tel\n0522-140 60. Bankgiro 42-8034.\nPostgiro 32196. Tga Tiger\nVerksamhet: Tillverkar o säljer\nherr- o gosskonfektion\nAntal anställda: 575\nÅrsomsättning: 25 000 000\nAktiekapital: 500 000\nVerkst dir: Heinz König\nEtableringsàr: 1903.\n\nSCHüTT, VERKTYGSFIRMA\nROLAND\n\nPnr 135 00\n\nTyresö, Lidv 29. Tel 08-712 3276.\nBankgiro 983-1850. Postgiro\n152109-5. Tga Unigrinder\nVeiksamhet: Tillverkar o säljer\nverktygs s lipmaskiner\nChef: Konstr Roland Schütt\nEtableringsàr. 1946.\n\nSCHUTZ jr, AB CARL\n\nPnr 402 51\n\nGöteborg 13. Box 13036.\nMarie-holmsg 50. Tel 031-19 5101,\n19 5130. Bankgiro 569-3452.\nPostgiro 627420-3\n\nVerksamhet: Grossisthandel o\ntillverkning av charkuteriprodukter\nAntal anställda: 30\nÅrsomsättning: 6 000 000\nAktiekapital: 45 000\nVeikst dir Ivan Person\nEtableringsàr 1938.\n\nSCHOLLIN &amp; AHLSTRÖM\nBYGGVARU AB\n\nPnr 186 00\n\nVallentuna, Ekskogen. Tel\n0762-353 30 , 3 53 31. Bankgiro\n711-2576. Postgiro 136840-6\nVerksamhet: Tillverkar o säljer\nhus- o husdelar. Säljer trä- o\nbyggnadsmateriel\nAntal anställda: 25\nÅrsomsättning: 3 000 000\nAktiekapital: 50 000\nVeikst dir Lars Schöllin\nEtableringsàr: 1968.\n\nSCHOLLIN &amp; CO AB, E\n\nPnr 183 51\n\nTäby, Djursholmsv 79. Tel\n08-756 20 22. Tga Schollinco\nVerksamhet: Representant för\namerikanska sågverk. Hickory, Douglas\nFir, Sitka Spruce, Red Wood, Wes-\n\ntern Red Cedar, Yellow Pine o\nCa-nadian Maple\n\nStyrelse: Dir Eskil Schöllin (ordf),\ning Olof Ward.\n\nSCHONTHAL AB, HERBERT\n\nPnr 162 04\n\nVällingby 4, Aprikosg 14. Box 473.\nTel 08-38 58 82. Tga Herbthal,\nStockholm\n\nVerksamhet: Säljer ylle-,\nbomulls-o sidenvaror, spetsar, brodyrvaror\no garneringsband\nAktiekapital: 10000\nVerkst dir Kurt Schönthal\nEtableringsàr 1914\nOmbildat till aktiebolag 1947.\n\nSCHONWELL MOSSFABRIK\nAB, R\n\nPnr 212 28\n\nMalmö, Johanneslustg 1. Tel\n040-184775,18 4776. Bankgiro 64-1206.\nPostgiro 37908\n\nVeiksamhet: Mössfabrik. Engros-\n\nförsäljning av herr- o damhattar\n\nAntal anställda: 30\n\nAktiekapital: 20 000\n\nVeikst dir Fabr Reinhold Schön-\n\nwell\n\nEtableringsàr 1932.\n\nARLÖVS PLASTGJUTERI AB\n\nPnr 232 00\n\nArlöv, Industribyn. Tel\n040-43 37 20, 344 30. Bankgiro\n264-8061. Postgiro 148951-7\nVerksamhet: Formsprutning av\nirriustridetaljer i alla\ntermoplastmaterial\n\nStyrelseordf: Dir E Söderlund\nVerkst dir: Edgar Söderlund\nKamrer: Ove Nilsson\nEtableringsår: 1954.\n\nRADIOMEKANO\n\nPnr 260 36\n\nHittarp, Laröd. Tel 042-924 29.\nPostgiro 10347-3\n\nVerksamhet: Tillverkar elektriska\napparater o mätinstrument\nÄgare o chef: Eilert Persson\nEtableringsår: 1949.\n\nMOBREY AB\n\nPnr 117 34\n\nStockholm, Hornsbruksg 11. Tel\n08-68 04 35. Bankgiro 23-3898.\nPostgiro 403435. Telex 17397. Tga\nMobrey\n\nVerksamhet: Säljer Mobrey\nnivågivare. Proscon termostater,\nTri-Flex ångfällor o\nkondensvattenav-ledare. Sensall ultraljud för\nnivåkontroll\n\nVarunamn: Mobrey, Proscon,\nTri-Flex, Sensall\nAntal anstäUda: 7\nÅrsomsättning: 1 800 000\nAktiekapital: 150 000\nVerkst dir: Olle Ruder\nEtableringsår: 1966.\n\nSTEENIE, JOS\n\nPnr 112 20\n\nStockholm, N Mälarstrand 32. Tel\n08-50 94 50. Postgiro 50697-5. Tga\nSteenietrade\n\nVerksamhet: Säljer serveringstänger,\ndruvsaxar o presentartiklar mm\nEtableringsår: 1923.\n\nÅrsomsättning: 1 500 000\nAktiekapital: 25 000\nVerkst dir: Ragnar Stenlund\nEtableringsår: 1957.\n\nSTENLUNDS TRIKÄ.\nFABRIK, AB UNO\n\nPnr 501 02\n\nBorås 1, Box 30. Lilla Brog 9.\nTel 033-11 00 04. Tga Polo\nVerksamhet: Tillverkar yttertrikå,\nbadartiklar o klänningar\nAktiekapital: 125 000\nVerkst dir: Ulf C-H Nilsson\nEtableringsår: 1925.\n\nSTENINGE LERVARUFABRIK\nAB\n\nPnr 195 00\n\nMärsta. Tel 0760-52160. Postgiro\n82730\n\nVerksamhet: Tillverkar oglaserat\no glaserat lergods\nAntal anställda: 100\nDir: Ingvar Merinder\nEtableringsår: 1917.\n\nFOR\n\nFÄLLMANS INGENJÖRS.\nB YRA AB\n\nPnr 41121\n\nGöteborg, Stora Badhusg 14. Tel\n031-10 56 90\n\nVerksamhet: Byggnadsteknik\nAktiekapital: 10000\nVerkst dir: Ing E A Fällman.\n\nFÄLT AB, TRIKÅINDUSTRI\nW A\n\nPnr 51200\n\nSvenljunga. Tel 0325-114 48.\nBankgiro 54-2310. Postgiro 325319\nVerksamhet: Barnpyjamas o\ngymnastikdräkter i interlock väv\nAntal anställda: 30\nÅrsomsättning: 1500 000\nAktiekapital: 100 000\nVerkst din Torsten Ahlberg\nEtableringsår: 1944.\n\nFÄLTENBORG &amp; FRANZÉN\nAB\n\nPnr 574 01\n\nVetlanda 1, Industrig 10. Box 124.\nTel 0383-14070. Bankgiro 28-9636.\nPostgiro 142164\n\nVerksamhet: Säljer\nbyggnadsmaterial\n\nAntal anställda: 10\nÅrsomsättning: 3 500 000\nAktiekapital: 150 000\nVerkst dir: Rolf Franzén\nEtableringsår: 1937.\n\nERIKSSON &amp; CO, J A\n\nPnr 901 02\n\nUmeå 1, Box 123. Nyg 11. Tel\n090-11 13 78. 11 13 71. Bankgiro\n613-3078. Postgiro 62715-8\nVerksamhet: Säljer bilar,\nreservdelar, tillbehör o verktyg\nAntal anställda: 11\nÅrsomsättning: 1000 000\nAktiekapital: 42 000\nVerkst dir. Erik Eriksson\nEtableringsår 1920.\n\nBORÅS SNICKERIFABRIK, AB\n\nPnr 501 02\n\nBorås 1, Norrby Tvärg 6. Box 82.\nTel 033-11 23 64, 1105 64.\nBankgiro 36-0870. Postgiro 85400\nVerksamhet:\nHusbyggnadssnicke-rier, trävaror mm\nAktiekapital: 100 000\nVerkst dir: O Lund\nEtableringsår: 1913.\n\nBETA TEXTILAKTIEBOLAG\n\nPnr 652 30\n\nKarlstad, Älvg 39. Tel 054-113870.\nBankgiro 100-0512. Postgiro\n81111-7\n\nVerksamhet: Säljer vävnader,\ntrikå, strumpor, corsetter,\nskyddskläder o kortvaror en gros\nAntal anställda: 6\nÅrsomsättning: 2 600 000\nAktiekapital: 100400\nÄgare o chefer: Kontorschef Paul\nPettersson, inköpschef Matz\nFrend-berg\n\nEtableringsår: 1936.\n\nBERDÉN, AB HANS\n\nPnr 212 14\n\nMalmö, Industrig 14-18. Tel\n040-93 49 90. Bankgiro 87-5503.\nPostgiro 431855\n\nVerksamhet: Försäljning av\ntät-ningslist för fönster o d.\nTillverkning av specialutrustning för\nundervisningsändamål. Import o\nförsäljning av detaljer för mörkläggning,\npersienner o d\nAktiekapital: 20 000\nVerkst dir: Hans Berdén\nEtableringsår: 1953.",
    "structured": {
        "1": {
            "company_name": "SCH",
            "establishment_year": 1958,
            "key_personnel": [
                {
                    "name": "Ing Joachim Lorenz",
                    "position": "Verkst dir"
                }
            ]
        },
        "2": {
            "company_name": "SCHWALBE, MASKINBYGGNADSFIRMAN INGEMAR",
            "pnr": "11138",
            "address": "Stockholm, David Bagares g 8",
            "phone_number": "08-2150 49",
            "bank_details": {
                "postgiro": "57727"
            },
            "activity": "Allmän mekanisk utvecklings- o uppfinnarverksamhet. Prototyptillverkning",
            "key_personnel": [
                {
                    "name": "Civiling Ingemar Schwalbe",
                    "position": "Ägare o chef"
                }
            ],
            "establishment_year": 1958
        },
        "3": {
            "company_name": "SCHWARTZMAN& NORD. STRÖM, AB",
            "pnr": "45101",
            "address": "UddevaUa 1, Osterg. Pack",
            "phone_number": "0522-140 60",
            "bank_details": {
                "bankgiro": "42-8034",
                "postgiro": "32196"
            },
            "activity": "Tillverkar o säljer herr- o gosskonfektion",
            "employees": 575,
            "annual_turnover": 25000000,
            "capital": 500000,
            "key_personnel": [
                {
                    "name": "Heinz König",
                    "position": "Verkst dir"
                }
            ],
            "establishment_year": 1903
        },
        "4": {
            "company_name": "SCHüTT, VERKTYGSFIRMA ROLAND",
            "pnr": "135 00",
            "address": "Tyresö, Lidv 29",
            "phone_number": "08-712 3276",
            "bank_details": {
                "bankgiro": "983-1850",
                "postgiro": "152109-5"
            },
            "activity": "Tillverkar o säljer verktygsslipmaskiner",
            "key_personnel": [
                {
                    "name": "Konstr Roland Schütt",
                    "position": "Chef"
                }
            ],
            "establishment_year": 1946
        },
        "5": {
            "company_name": "SCHUTZ jr, AB CARL",
            "pnr": "402 51",
            "address": "Göteborg 13, Box 13036, Marie-holmsg 50",
            "phone_number": "031-19 5101, 19 5130",
            "bank_details": {
                "bankgiro": "569-3452",
                "postgiro": "627420-3"
            },
            "activity": "Grossisthandel o tillverkning av charkuteriprodukter",
            "employees": 30,
            "annual_turnover": 6000000,
            "capital": 45000,
            "key_personnel": [
                {
                    "name": "Ivan Person",
                    "position": "Veikst dir"
                }
            ],
            "establishment_year": 1938
        },
        "6": {
            "company_name": "SCHOLLIN& CO AB, E",
            "pnr": "183 51",
            "address": "Täby, Djursholmsv 79",
            "phone_number": "08-756 20 22",
            "activity": "Representant för amerikanska sågverk. Hickory, Douglas Fir, Sitka Spruce, Red Wood, Western Red Cedar, Yellow Pine o Ca-nadian Maple",
            "key_personnel": [
                {
                    "name": "Eskil Schöllin",
                    "position": "Styrelseordf"
                },
                {
                    "name": "Olof Ward",
                    "position": "Ing"
                }
            ],
            "establishment_year": 1968
        },
        "7": {
            "company_name": "SCHONTHAL AB, HERBERT",
            "pnr": "162 04",
            "address": "Vällingby 4, Aprikosg 14, Box 473",
            "phone_number": "08-38 58 82",
            "activity": "Säljer ylle-, bomulls-o sidenvaror, spetsar, brodyrvaror o garneringsband",
            "capital": 10000,
            "key_personnel": [
                {
                    "name": "Kurt Schönthal",
                    "position": "Verkst dir"
                }
            ],
            "establishment_year": 1947
        },
        "8": {
            "company_name": "SCHONWELL MOSSFABRIK AB, R",
            "pnr": "212 28",
            "address": "Malmö, Johanneslustg 1",
            "phone_number": "040-184775,18 4776",
            "bank_details": {
                "bankgiro": "64-1206",
                "postgiro": "37908"
            },
            "activity": "Mössfabrik. Engrosförsäljning av herr- o damhattar",
            "employees": 30,
            "capital": 20000,
            "key_personnel": [
                {
                    "name": "Fabr Reinhold Schönwell",
                    "position": "Veikst dir"
                }
            ],
            "establishment_year": 1932
        },
        "9": {
            "company_name": "ARLÖVS PLASTGJUTERI AB",
            "pnr": "232 00",
            "address": "Arlöv, Industribyn",
            "phone_number": "040-43 37 20, 344 30",
            "bank_details": {
                "bankgiro": "264-8061",
                "postgiro": "148951-7"
            },
            "activity": "Formsprutning av irriustridetaljer i alla termoplastmaterial",
            "key_personnel": [
                {
                    "name": "E Söderlund",
                    "position": "Styrelseordf"
                },
                {
                    "name": "Edgar Söderlund",
                    "position": "Verkst dir"
                },
                {
                    "name": "Ove Nilsson",
                    "position": "Kamrer"
                }
            ],
            "establishment_year": 1954
        },
        "10": {
            "company_name": "RADIOMEKANO",
            "pnr": "260 36",
            "address": "Hittarp, Laröd",
            "phone_number": "042-924 29",
            "bank_details": {
                "postgiro": "10347-3"
            },
            "activity": "Tillverkar elektriska apparater o mätinstrument",
            "key_personnel": [
                {
                    "name": "Eilert Persson",
                    "position": "Ägare o chef"
                }
            ],
            "establishment_year": 1949
        },
        "11": {
            "company_name": "MOBREY AB",
            "pnr": "117 34",
            "address": "Stockholm, Hornsbruksg 11",
            "phone_number": "08-68 04 35",
            "bank_details": {
                "bankgiro": "23-3898",
                "postgiro": "403435"
            },
            "activity": "Säljer Mobrey nivågivare. Proscon termostater, Tri-Flex ångfällor o kondensvattenav-ledare. Sensall ultraljud för nivåkontroll",
            "employees": 7,
            "annual_turnover": 1800000,
            "capital": 150000,
            "key_personnel": [
                {
                    "name": "Olle Ruder",
                    "position": "Verkst dir"
                }
            ],
            "establishment_year": 1966
        },
        "12": {
            "company_name": "STEENIE, JOS",
            "pnr": "112 20",
            "address": "Stockholm, N Mälarstrand 32",
            "phone_number": "08-50 94 50",
            "bank_details": {
                "postgiro": "50697-5"
            },
            "activity": "Säljer serveringstänger, druvsaxar o presentartiklar mm",
            "establishment_year": 1923,
            "annual_turnover": 1500000,
            "capital": 25000,
            "key_personnel": [
                {
                    "name": "Ragnar Stenlund",
                    "position": "Verkst dir"
                }
            ]
        },
        "13": {
            "company_name": "STENLUNDS TRIKÄ. FABRIK, AB UNO",
            "pnr": "501 02",
            "address": "Borås 1, Box 30, Lilla Brog 9",
            "phone_number": "033-11 00 04",
            "activity": "Tillverkar yttertrikå, badartiklar o klänningar",
            "capital": 125000,
            "key_personnel": [
                {
                    "name": "Ulf C-H Nilsson",
                    "position": "Verkst dir"
                }
            ],
            "establishment_year": 1925
        },
        "14": {
            "company_name": "STENINGE LERVARUFABRIK AB",
            "pnr": "195 00",
            "address": "Märsta",
            "phone_number": "0760-52160",
            "activity": "Tillverkar oglaserat o glaserat lergods",
            "employees": 100,
            "key_personnel": [
                {
                    "name": "Ingvar Merinder",
                    "position": "Dir"
                }
            ],
            "establishment_year": 1917
        },
        "15": {
            "company_name": "FÄLLMANS INGENJÖRS. BYRA AB",
            "pnr": "41121",
            "address": "Göteborg, Stora Badhusg 14",
            "phone_number": "031-10 56 90",
            "activity": "Byggnadsteknik",
            "capital": 10000,
            "key_personnel": [
                {
                    "name": "Ing E A Fällman",
                    "position": "Verkst dir"
                }
            ]
        },
        "16": {
            "company_name": "FÄLT AB, TRIKÅINDUSTRI W A",
            "pnr": "51200",
            "address": "Svenljunga",
            "phone_number": "0325-114 48",
            "bank_details": {
                "bankgiro": "54-2310",
                "postgiro": "325319"
            },
            "activity": "Barnpyjamas o gymnastikdräkter i interlock väv",
            "employees": 30,
            "annual_turnover": 1500000,
            "capital": 100000,
            "key_personnel": [
                {
                    "name": "Torsten Ahlberg",
                    "position": "Verkst din"
                }
            ],
            "establishment_year": 1944
        },
        "17": {
            "company_name": "FÄLTENBORG& FRANZÉN AB",
            "pnr": "574 01",
            "address": "Vetlanda 1, Industrig 10, Box 124",
            "phone_number": "0383-14070",
            "bank_details": {
                "bankgiro": "28-9636",
                "postgiro": "142164"
            },
            "activity": "Säljer byggnadsmaterial",
            "employees": 10,
            "annual_turnover": 3500000,
            "capital": 150000,
            "key_personnel": [
                {
                    "name": "Rolf Franzén",
                    "position": "Verkst dir"
                }
            ],
            "establishment_year": 1937
        },
        "18": {
            "company_name": "ERIKSSON& CO, J A",
            "pnr": "901 02",
            "address": "Umeå 1, Box 123, Nyg 11",
            "phone_number": "090-11 13 78, 11 13 71",
            "bank_details": {
                "bankgiro": "613-3078",
                "postgiro": "62715-8"
            },
            "activity": "Säljer bilar, reservdelar, tillbehör o verktyg",
            "employees": 11,
            "annual_turnover": 1000000,
            "capital": 42000,
            "key_personnel": [
                {
                    "name": "Erik Eriksson",
                    "position": "Verkst dir"
                }
            ],
            "establishment_year": 1920
        },
        "19": {
            "company_name": "BORÅS SNICKERIFABRIK, AB",
            "pnr": "501 02",
            "address": "Borås 1, Norrby Tvärg 6, Box 82",
            "phone_number": "033-11 23 64, 1105 64",
            "bank_details": {
                "bankgiro": "36-0870",
                "postgiro": "85400"
            },
            "activity": "Husbyggnadssnicke-rier, trävaror mm",
            "capital": 100000,
            "key_personnel": [
                {
                    "name": "O Lund",
                    "position": "Verkst dir"
                }
            ],
            "establishment_year": 1913
        },
        "20": {
            "company_name": "BETA TEXTILAKTIEBOLAG",
            "pnr": "652 30",
            "address": "Karlstad, Älvg 39",
            "phone_number": "054-113870",
            "bank_details": {
                "bankgiro": "100-0512",
                "postgiro": "81111-7"
            },
            "activity": "Säljer vävnader, trikå, strumpor, corsetter, skyddskläder o kortvaror en gros",
            "employees": 6,
            "annual_turnover": 2600000,
            "capital": 100400,
            "key_personnel": [
                {
                    "name": "Paul Pettersson",
                    "position": "Kontorschef"
                },
                {
                    "name": "Matz Frend-berg",
                    "position": "Inköpschef"
                }
            ],
            "establishment_year": 1936
        },
        "21": {
            "company_name": "BERDÉN, AB HANS",
            "pnr": "212 14",
            "address": "Malmö, Industrig 14-18",
            "phone_number": "040-93 49 90",
            "bank_details": {
                "bankgiro": "87-5503",
                "postgiro": "431855"
            },
            "activity": "Försäljning av tät-ningslist för fönster o d. Tillverkning av specialutrustning för undervisningsändamål. Import o försäljning av detaljer för mörkläggning, persienner o d",
            "capital": 20000,
            "key_personnel": [
                {
                    "name": "Hans Berdén",
                    "position": "Verkst dir"
                }
            ],
            "establishment_year": 1953
        }
    }
}