{
    "original": "GERNANDT, J C E\n\nPnr 12612\n\nStockholm 42, Box 42124.\nVretens-borgsv 19. Tel 08-19 02 30.\nBankgiro 73-0222. Postgiro 2755. Tga\nGernandter. Telex 19077\nVerksamhet: Tillverkar färger o\nfernissor, lim o\npolyvinylacetat-dispersioner samt trèdlacker för\nel industrin\nAntal anställda: 105\nÄgare o chef: Disp Stig Gernandt\nEtableringsår: 1876.\n\nTORINA KONFEKTION\n\nPnr 46100\n\nTrollhättan, Föreningsg 1. Tel\n0520-337 00. Bankgiro 89-2814\nVerksamhet: Klänningskonfektion.\nBättre mellanklänningar, blusar\nAntal anställda: 45\nÅrsomsättning: 1 000 000\nChef: Inge Persson-Staaf\nEtableringsår: 1965.\n\nOREBRO SKOFABRIK. AB\n\nPnr 70102\n\nÖrebro 1, Klosterg 35. Box 10. Tel\n019-1105 55, 1145 55. Bankgiro\n463-1529. Postgiro 71378-4\nAktiekapital: 400 000\nVerkst dir: Lars Olson\nEtableringsår 1894.\n\nAXONIT AB\n\nPnr 15031\n\nÅkers Styckebruk. Tel 0159-302 60.\nTelex 10257 ÅKERS S\nVeiksamhet: Bryter o förädlar\nki-selgur av egna fyndigheter för\nförädling av gur för värmeisolering,\nfiltrering, absorption samt för\nkatalysatorer\n\nVarunamn: Axonit\nAntal anställda: 8\nÅrsomsättning: 380 000\nAktiekapital: 90 000\nStyrelse: Bruksdisp Torsten\nCol-lén (ordf), bergsing Claes Gejrot,\nadv Per Axel Wesllen\nVerkst dir: Bergsing Claes Gejrot\nEtableringsår: 1941.\n\nA PH-PRODUKTER, AB\n\nPnr 200 29\n\nMalmö 29, Box 460. Kvarnby. Tel\n040-44 88 50,49 00 14.\nBankgiro870-4686. Postgiro 535442-8. Tga Muhrs,\nKvarnby. Telex 32285\nVerksamhet: Blomsterproduktion,\nspecialisering nejlikor samt\ngrossist- o importverksamhet av\naktuella snittblommor\nAntal anställda: 35\nÅrsomsättning: 7 500000\nAktiekapital: 50 000\nStyrelse: Dir Bertil Muhr (ordf),\nfru Olga Muhr, dir Carl-Anders Muhr\nVerkst dir: Carl-Anders Muhr\nFörsäljn-chef: Jörgen Paulsson\nEtableringsår: 1899.\n\nGUMAELIUS, AB\n\nPnr 10110\n\nStockholm 1, Pack. Rålambsv 7.\nTel 08-22 39 00. Bankgiro 70-0065.\nPostgiro 805. Tga Annonsbyrån.\nTelex 17079 GUMADST S\nVerksamhet: Auktoriserad\nreklamkonsult. Av TU nominerad\nannons-förmedlare\n\nSjälvständigt arbetande byråer:\n\n402 31 Götebcrg 7, Pörsta Långg\n16. Box 7047. Tel 031-12 44 80.\nTelex 20832 GUMADG S\n550 06 Jönköping 6, Birkag. Pack.\nTel 036-13 25 50. Telex 70154\nGUMADJS\n\n203 13 Malmö 4, S Tullg 4 A. Box\n\n4245. Tel 040-714 00. Telex 32545\n\nGUMADMS\n\nAntal anställda: 375\n\nÅrsomsättning: 95 000 000\n\nAktiekapital: 2 650 000\n\nKoncernledning:\n\nVerkst dir: Sven Hellsten\n\nl:e V verkst dir: Olle Grafström\n\n2:e V verkst dir Evert Ståhl\n\nEtableringsår: 1877.\n\nNYN\n\nNYLANDER &amp; BERGLUND,\nBYGGNADS AB\n\nPnr 852 33\n\nSundsvall, Packhusg 2. Tel\n060-15 07 85. Bankgiro 180-2172.\nPostgiro 477581-3\n\nVerksamhet: Uppför bostads- o\naffärshus samt industribyggnader.\nUtför ombyggnads- o\nreparationsarbeten\n\nAntal anställda: 80\nÅrsomsättning: 7 000 000\nAktiekapital: 50 000\nStyrelse: Byggmäst J A Nylander\n(ordf), fru Ebba Nylander, ing Per\nOve Nylander\n\nVeikst din Byggmäst J A Nylander\nEtableringsår 1955\nOmbildat till aktiebolag 1958.\n\nNYLANDERS SNICKERI AB\n\nPnr 31016\n\nVallberga, Lantmannag 1. Tel\n0430-232 14. Bankgiro 372-2451.\nPostgiro 493739-7\nVerksamhet: Dörrar o glaspartier i\nspecialutförande\nAntal anställda: 6\nÅrsomsättning: 325 000\nAktiekapital: 5 000\nVerkst din G Nylander\nEtableringsår 1960.\n\nSÖD\n\n121 70. Bankgiro 106-6396.\nPostgiro 390651-8\n\nVerksamhet: Förnickling av järn,\nstål o metall. El-förzinkning,\nsåväl häng- som trumgods.\nSvartoxi-dering av stål o järn. Slipning o\npoleringar\n\nÅrsomsättning: 120000\nChef: Ingvar Karlsson\nEtableringsår: 1966.\n\nSDDERLINDS\nMETALL-GJUTERI EFTR\n\nPnr 126 30\n\nHägersten, Vretensborgsv 6. Tel\n08-45 75 50, 45 85 54. Bankgiro\n22-0578. Postgiro 404562\nVerksamhet: Beställningsgjutgods i\ntung- o lättmetaller\nAntal anställda: 7\nÅrsomsättning: 500 000\nEtableringsår: 1926.\n\nSDDERLINGS FABRIKER,\nAB C F\n\nPnr 234 00\n\nLomma, Industrig 11. Box 18. Tel\n040-41 20 03 , 41 20 1 9. Bankgiro\n673-1384. Postgiro 436030-1. Tga\nSöderling\n\nVerksamhet: Tillverkar o säljer\npo-lerskivor av tyg, sisal filt, puts- o\nglänsvaxer för metall o plast, tekn\nborstar, slipband m m\nAntal anstäüda: 15\nAktiekapital: 50 000\nVerkst dir: Hans F Söderling\nEtableringsår: 1908.\n\nVÄSTGÖTA VÄFNADS AB\n\nPnr 310 63\n\nAlvsered. Box 55. Tel 0325-312 00.\nBankgiro 55-2834. Postgiro 34404\nVerksamhet: Postorderförsäljning\nAntal anställda: 60\nÅrsomsättning: 12 500 000\nAktiekapital: 600 000\nStyrelse: Disp Bertil Gustafsson\n(ordf), köpman Erik Gustafsson,\nlandskamrer Seth.Manhem, disp\nSven Manhem\n\nVerkst dir: Disp Sven Manhem\nEtableringsån 1897.\n\nVÄSTKUSTEN, FÖRSÄLJNINGS\nAB T.S. 30\n\nPnr 417 04\n\nGöteborg, Kvilleg 9. Tel\n031-23 93 20. 23 43 66. Postgiro 621052\nVerksamhet: Försäljningsuppdrag\nAktiekapital: 5 000\nVerkst dir. Ove Håkansson\nEtableringsån 1960.\n\nFORSSELLS KONSTSTENS AB\n\nPnr 778 00\n\nNorberg. Tel 0223-209 10. Tga\nKonststen\n\nVerksamhet: Tillverkar o monterar\nbetongvaror för byggnadsindustrin:\nspeciellt trappor o\ngolvbeläggningar av konststen\nAvdelningskontor: 126 04\nHägersten 4, Box 463. Tel 08-97 0250\nAntal anstäUda: 210\nÅrsomsättning: 15 000 000\nAktiekapital: 200 000\nVerkst dir: Jan Auby\nEtableringsår: 1924.\n\nFORSSELLS SMIDESVERK.\nSTAD, AB H\n\nPnr 14146\n\nHuddinge. Dalhemsv 28. Tel\n08-757 3610. 774 36 09. Bankgiro\n746-5008. Postgiro 103925-4\nVerksamhet: Byggnadssmide.\nsvetsning, legotillverkning\nAntal anstäUda: 10\nÅrsomsättning: 900 000\nAktiekapital: 15 000\nVerkst dir: Harry Forssell\nEtableringsår: 1958.",
    "structured": {
        "1": {
            "company_name": "GERNANDT, J C E",
            "activity": "Tillverkar färger o fernissor, lim o polyvinylacetat-dispersioner samt trèdlacker för el industrin",
            "establishment_year": 1876,
            "employees": 105,
            "key_personnel": [
                {
                    "name": "Disp Stig Gernandt",
                    "position": "Ägare o chef"
                }
            ]
        },
        "2": {
            "company_name": "TORINA KONFEKTION",
            "activity": "Klänningskonfektion. Bättre mellanklänningar, blusar",
            "establishment_year": 1965,
            "employees": 45,
            "annual_turnover": 1000000,
            "key_personnel": [
                {
                    "name": "Inge Persson-Staaf",
                    "position": "Chef"
                }
            ]
        },
        "3": {
            "company_name": "OREBRO SKOFABRIK. AB",
            "capital": 400000,
            "activity": "",
            "establishment_year": 1894,
            "key_personnel": [
                {
                    "name": "Lars Olson",
                    "position": "Verkst dir"
                }
            ]
        },
        "4": {
            "company_name": "AXONIT AB",
            "activity": "Bryter o förädlar ki-selgur av egna fyndigheter för förädling av gur för värmeisolering, filtrering, absorption samt för katalysatorer",
            "establishment_year": 1941,
            "employees": 8,
            "annual_turnover": 380000,
            "capital": 90000,
            "key_personnel": [
                {
                    "name": "Bergsing Claes Gejrot",
                    "position": "Styrelse: Bruksdisp"
                },
                {
                    "name": "adv Per Axel Wesllen",
                    "position": "Styrelse"
                },
                {
                    "name": "Bergsing Claes Gejrot",
                    "position": "Verkst dir"
                }
            ]
        },
        "5": {
            "company_name": "A PH-PRODUKTER, AB",
            "activity": "Blomsterproduktion, specialisering nejlikor samt grossist- o importverksamhet av aktuella snittblommor",
            "establishment_year": 1899,
            "employees": 35,
            "annual_turnover": 7500000,
            "capital": 50000,
            "key_personnel": [
                {
                    "name": "Dir Bertil Muhr",
                    "position": "Styrelse: Dir"
                },
                {
                    "name": "fru Olga Muhr",
                    "position": "Styrelse"
                },
                {
                    "name": "Carl-Anders Muhr",
                    "position": "Verkst dir"
                },
                {
                    "name": "Jörgen Paulsson",
                    "position": "Försäljn-chef"
                }
            ]
        },
        "6": {
            "company_name": "GUMAELIUS, AB",
            "activity": "Auktoriserad reklamkonsult. Av TU nominerad annons-förmedlare",
            "establishment_year": 1877,
            "employees": 375,
            "annual_turnover": 95000000,
            "capital": 2650000,
            "key_personnel": [
                {
                    "name": "Sven Hellsten",
                    "position": "Verkst dir"
                },
                {
                    "name": "Olle Grafström",
                    "position": "l:e V verkst dir"
                },
                {
                    "name": "Evert Ståhl",
                    "position": "2:e V verkst dir"
                }
            ]
        },
        "7": {
            "company_name": "NYN NYLANDER & BERGLUND, BYGGNADS AB",
            "activity": "Uppför bostads- o affärshus samt industribyggnader. Utför ombyggnads- o reparationsarbeten",
            "establishment_year": 1955,
            "employees": 80,
            "annual_turnover": 7000000,
            "capital": 50000,
            "key_personnel": [
                {
                    "name": "Byggmäst J A Nylander",
                    "position": "Styrelse: Byggmäst"
                },
                {
                    "name": "Fru Ebba Nylander",
                    "position": "Styrelse"
                },
                {
                    "name": "ing Per Ove Nylander",
                    "position": "Verkst din Byggmäst"
                }
            ]
        },
        "8": {
            "company_name": "NYLANDERS SNICKERI AB",
            "activity": "Dörrar o glaspartier i specialutförande",
            "establishment_year": 1960,
            "employees": 6,
            "annual_turnover": 325000,
            "capital": 5000,
            "key_personnel": [
                {
                    "name": "G Nylander",
                    "position": "Verkst din"
                }
            ]
        },
        "9": {
            "company_name": "SÖD",
            "activity": "Förnickling av järn, stål o metall. El-förzinkning, såväl häng- som trumgods. Svartoxi-dering av stål o järn. Slipning o poleringar",
            "establishment_year": 1966,
            "annual_turnover": 120000,
            "key_personnel": [
                {
                    "name": "Ingvar Karlsson",
                    "position": "Chef"
                }
            ]
        },
        "10": {
            "company_name": "SDDERLINDS METALL-GJUTERI EFTR",
            "activity": "Beställningsgjutgods i tung- o lättmetaller",
            "establishment_year": 1926,
            "employees": 7,
            "annual_turnover": 500000
        },
        "11": {
            "company_name": "SDDERLINGS FABRIKER, AB C F",
            "activity": "Tillverkar o säljer polerskivor av tyg, sisal filt, puts- o glänsvaxer för metall o plast, tekn borstar, slipband m m",
            "establishment_year": 1908,
            "employees": 15,
            "capital": 50000,
            "key_personnel": [
                {
                    "name": "Hans F Söderling",
                    "position": "Verkst dir"
                }
            ]
        },
        "12": {
            "company_name": "VÄSTGÖTA VÄFNADS AB",
            "activity": "Postorderförsäljning",
            "establishment_year": 1897,
            "employees": 60,
            "annual_turnover": 12500000,
            "capital": 600000,
            "key_personnel": [
                {
                    "name": "Disp Bertil Gustafsson",
                    "position": "Styrelse: Disp"
                },
                {
                    "name": "köpman Erik Gustafsson",
                    "position": "Styrelse"
                },
                {
                    "name": "landskamrer Seth.Manhem",
                    "position": "Styrelse"
                },
                {
                    "name": "Disp Sven Manhem",
                    "position": "Verkst dir"
                }
            ]
        },
        "13": {
            "company_name": "VÄSTKUSTEN, FÖRSÄLJNINGS AB T.S. 30",
            "activity": "Försäljningsuppdrag",
            "establishment_year": 1960,
            "capital": 5000,
            "key_personnel": [
                {
                    "name": "Ove Håkansson",
                    "position": "Verkst dir"
                }
            ]
        },
        "14": {
            "company_name": "FORSSELLS KONSTSTENS AB",
            "activity": "Tillverkar o monterar betongvaror för byggnadsindustrin: speciellt trappor o golvbeläggningar av konststen",
            "establishment_year": 1924,
            "employees": 210,
            "annual_turnover": 15000000,
            "capital": 200000,
            "key_personnel": [
                {
                    "name": "Jan Auby",
                    "position": "Verkst dir"
                }
            ]
        },
        "15": {
            "company_name": "FORSSELLS SMIDESVERK. STAD, AB H",
            "activity": "Byggnadssmide. svetsning, legotillverkning",
            "establishment_year": 1958,
            "employees": 10,
            "annual_turnover": 900000,
            "capital": 15000,
            "key_personnel": [
                {
                    "name": "Harry Forssell",
                    "position": "Verkst dir"
                }
            ]
        }
    }
}