{
    "original": "SDDERLUNDSMETALL AB\n\nPnr 330 30\n\nGnosjö. Tel 0370-912 37, 918 00.\nBankgiro 542-4577. Postgiro\n362883-1\n\nAUTOMATSVARVMG\n\nejter prov eller ritning\n\nVerksamhet: Tillverkar ljusstakar\ni mässing, automatsvarvning.\nSpecialitet: allt inom\nautomatsvarvning efter prov eller ritningar. Vi\nutställer på Swed-Expo, Värnamo\nAntal anställda: 18\nÅrsomsättning: 2 500 000\nAktiekapital: 70 000\nVerkst dir: Sven-Olof Söderlund\nEtableringsår: 1960.\n\nWÄSTGOTA TÄCKFABRIK AB\n\nPnr 52400\n\nHerr ljunga. Box 109. Tel\n0513-10154. Bankgiro 84-1065.\nPostgiro 514551\n\nVerksamhet: Tillverkar sängkläder,\ntäcken o sovsäckstäcken\nVarunamn: Suss\nAktiekapital: 30 000\nVerkst din Fredrik Larsson\nEtableringsår: 1939.\n\nBROMMA PERSIENNSERVICE\n\nPnr 172 21\n\nSundbyberg 1, Vegag 16. Box 10.\nTel 08-29 4252. Bankgiro 588-9639.\nPostgiro 320334-6\nVerksamhet: Tillverkar o säljer\npersienner, jalusier o kornischer\nChef: Georg Gabrielsson\nEtableringsår: 1956.\n\nBROMMA SMIDES&amp;\nMEK VERKSTAD, AB\n\nPnr 162 26\n\nVällingby, Krossg 31-33. Tel\n08-38 00 30. Bankgiro 172-8138.\nPostgiro 609534-3. Tga Backtemanmek.\nTelex 10224 CONQUIP S\nVerksamhet: Tillverkar\njärnkonstruktioner, containerutrustningar,\ncontainerok m m\nVerkst dir. Hans Backteman\nEtableringsår: 1960.\n\nL\n\nL\n\nL.A PLAST AB\n\nPnr 44101\n\nAlingsås 1, Verkstadsg 3. Box 9.\nTel 0322-180 15. Bankgiro 436-6134.\nPostgiro 370450-9\nVerksamhet: Tillverkar sko- o\nträ-toffelsulor samt mattor av plast.\nLäderimitationer.\nPolyurethanartik-lar\n\nVarunamn: L-A, Poronylia\nAntal anställda: 40\nÅrsomsättning: 3 000 000\n.Aktiekapital: 30 000\nVerkst dir: Hilding Apoi\nEtableringsår: 1957.\n\nFUR\n\nÅkers Krutbruk. Pack, 150 31 Åkers\nStyckebruk. Tel 0159-30270\nTorpedverkstaden. Pack, 59101\nMotala 1. Tel 0141-16160\nZakrisdalsverken. Pack, 65101\nKarlstad 1. Tel 054-11 53 60\nVingåkersverken. 643 00 Vingåker.\nTel 0151-12080\nGällöverken. 840 50 Gällö. Tel\n0693-20415\n\nBeklädnadsverkstaden. Pack,\n371 01 Karlskrona 1. Tel 0455-190 95\nCVA. Fack, 732 00 Arboga. Tel\n0589-128 00\n\nCVM. Fack, 590 57 Malmslätt. Tel\n013-996 00\n\növerskottsförsäljningen. Fack,\n17108 Solna 8. Tel 08-27 25 70\nTvätteriernas Centralkontor, Box\n5036, 630 05 Eskilstuna 5. Tel\n016-1172 00\n\nTvätterier i: Alingsås, Boden,\nEskilstuna, Karlskrona, Karlstad,\nLandskrona, Lund, Långsele,\nMalmö, Ockelbo, Umeå, Visby,\nOdeshög, Östersund\nVarunamn för kylkompressorer:\nPolfrost\n\nAntal anställda: 6 800\nÅrsomsättning: 454 500000\nStyrelse: Dir Gunnar Svärd (ordf),\nbruksdisp Carl Sebardt (v ordf),\ngeneraldir Erie Malmberg,\nriksdagsman Harald Almgren, tekn dir\nSigfrid Akselson, docent Lennart\nSchotte, generaldir Sten Wåhlin\nDirektion: Generaldir Erie\nMalmberg, tekn dir Sigfrid Akselson,\nekonomidir Jacob Lindahl, övering\nSven Osterlind, avd-dir Raoul\nBoström\n\nEtableringsår: 1943.\nDotterbolag: Telub AB, Viking\nSport Arms Co AB. FFV är även\ndelägare i KB United Stirling\n(Sweden) AB &amp; Co samt\nutvecklingsbolaget Innovations AB\nPro-jection KB.\n\nFÖRENADE FABRIKSVERKEN\nÅKERS KRUTBRUK\n\nPnr 15031\n\nÅkers Styckebnik. Tel 0159-30270.\nPostgiro 1068. Tga Krutbruket,\nMariefred. Telex 1267\nVerksamhet: Tillverkar\nexplosivämnen, kemisk-tekniska produkter\no läkemedel.\nBeställningstillverkning av kemiska produkter samt\nuppfödning av laboratoriedjur\nChef: Övering Rolf Juhlin\nFörsäljn-chef: Lars Andersson\nInköpschef: Lars-Göran Knutsson\nEtableringsår: 1600-talet\nÄges av Svenska Staten.\n\nFÖRENADE FÄRG, AB\n\nPnr 42120\n\nVästra Frölunda 1, Fack. Fröfästeg\n21. Tel 031-45 00 20. Tga\nFörenade-färg. Telex 2394\n\nVerksamhet: Färg- o fernissfabrik\nAvdelningskontor: Linköping,\nAgatan 55. Tel 013-13 47 70\nLuleå, Gammelstadsv 3. Tel\n0920-115 87, 227 53\n\nMalmö, Brageg 15. Tel 040-802 3 0\n\nStockholm, Sjöviksbacken 12. Tel\n08-18 04 40. Telex 10635\nSundsvall, Storg 52. Tel\n060-156285, 15 6330\nÖrebro, Idrottshuset. Tel\n019-125532, 18 2121\n\nDotterbolag: Oslo. Tömteveienl,\npa Kolboth. Tel Ski 801967\nAntal anställda: 425\nÅrsomsättning: 65 000 000\nAktiekapital: 1200 000\nStyrelse: Bankdir Gösta Olson, dir\nMatts Carlgren, bruksdisp Lars\nDegefors\n\nVerkst dir: Allan Hultén\nEtableringsår: 1889\nOmbildat 1954.\n\nDotterbolag till AB Wilh Becker.\n\nFÖRENADE GOLV AB\n\nPnr 20073\n\nMalmö 19, Lorensborgsg 4 A. Box\n19062. Tel 040-86925. Postgiro\n245550-9. Tga Förenadegolv\nVerksamhet: Marknadsför\ngolvbeläggningar speciellt för industri o\nhandel, statliga o kommunala verk,\nkontor, hotell, restauranger,\nsjukhus, värdhem, läroanstalter etc,\nsamt tätskikt för isolering mot\nvatten. Tillverkar golvmassor,\nfogmassor, plastmassor o asfaltvaror\nAvdelningskontor: 104 35 Stockholm\n23, Hagag 29. Box 23060. Tel\n08-24 72 00. Platschef: Ing Bertil\nOlehag\n\nAntal anställda: 15\nÅrsomsättning: 4 000 000\nAktiekapital: 100000\nStyrelse: Ekonomichef Bengt-Ake\nAndersson, dir Robert von Bahr,\nbyggnadsing Nils-E Fajerson,\nekonomichef Bertil Hersler (suppl)\nVerkst dir: Nils-E Fajerson\nEtableringsår: 1952.\n\nFÖRENADE GRANIT.\nINDUSTRIER, AB\n\nPnr 292 00\n\nKarlshamn, Hamng 12. Box 69. Tel\n0454-142 50. Postgiro 46530. Tga\n\nGranitindustri\n\nVerksamhet: Tillverkar\nbyggnadssten m fi arbeten av granit\nFörsäljningskontor: Stockholm C,\nUpplandsg 3. Tel 08-208240\nAktiekapital: 500 000\nVerkst dir: Stig Danielson\nEtableringsår: 1917\nDotterbolag till Investment AB\nSkansen Lejonet.\n\nFÖRENADE INREDNINGAR AB\nFIAB\n\nPnr 161 13\n\nBromma 13, Box 1346. Osmundsv\n23. Tel 08-2529 80. Bankgiro\n330-0514. Postgiro 190568-6\nVerksamhet: Inrednings- o konsult\nverksamhet, kompletta inredningar\nAntal anställda: 16\nÅrsomsättning: 7100 000\nAktiekapital: 500000\nVerkst dir: Lennart Kjellin\nEtableringsår: 1941.\n\nFÖRENADE\nKONTORS-MASKINER\n\nPnr 11121\n\nStockholm, Klarabergsg 33. Tel\n08-24 5 9 60. Postgiro 55351-1. Tga\nUnitedtype\n\nVerksamhet: Säljer\nkontorsmaskiner. Utför reparationer\nVarunamn: Casio, Triumph\n\nÄgare: Fritz Hasselblad, Thure\n\nMolvidsson\n\nEtableringsår: 1932.\n\nFÖRENADE\nLANDSORTSTIDNINGAR AB\n\nPnr 102 32\n\nStockholm 6, Box 6079. Odeng 69.\nTel 08-23 0040. Bankgiro 196-0400.\nPostgiro 55780-1. Tga Landspress.\nTelex 19191, 19192\nVerksamhet: Produktion o\nförmedling av redaktionellt material,\ntext o bild, i första hand åt\nledande borgerlig lands ortspress.\nInformations- o\nutbildningsaktiviteter på annonsmarknaden\nAntal anställda: 30\nAktiekapital: 180 000\nVerkst dir: Töre Wahlström\nRedaktionschef: Töre Sandvall\nMarknadschef: Bo Forssell\nEtableringsår: 1933.\n\nFÖRENADE\nLÄDER-VAROR, AB\n\nPnr 70103\n\nÖrebro 1, Rudbecksg 33. Box 103.\nTel 019-1198 75. Bankgiro\n358-8035. Postgiro 10425-7\nVerksamhet: Tillverkar dam- o\nshoppingväskor o smyckeskrin, skärp\nAntal anställda: 60\nÅrsomsättning: 3 000 000\nAktiekapital: 200 000\nVerkst dir: Gunnar Nilsson\nEtableringsår: 1939\nOmbildat till aktiebolag 1947.\n\nFÖRENADE RÖR I\nGÖTE-BORG AB\n\nPnr 413 03\n\nGöteborg, Värmlandsg 9. Tel\n031-14 56 64, 14 56 63.Bankgiro 50-8868.\nPostgiro 521124\n\nVerksamhet: Rörinstallationer,\nreparationer o oljeanläggningar\n.Aktiekapital: 40 000\nVerkst dir: A Willén\nEtableringsår: 1923.\n\nflenmo egendom ab\n\nPnr 640 30\n\nHälleforsnäs, Flenmo. Tel\n0157-603 30. Bankgiro 60-1654.\nPostgiro 275837.\n\nVerksamhet: Säljer byggnadsmate-\n\nrial, trävaror o massaved\nÅrsomsättning: 875 000\nAktiekapital: 25 000\nVerkst dir: Kaj Eriksson\nEtableringsår: 1957.\n\nWESTERN LABORATORIES AB\n\nPnr 30104\n\nHalmstad 4, Box 215.\nSimlångsda-len. Tel 035-702 70, 11 91 75.\nBankgiro 530-2450. Postgiro 450789-3.\nTga Labwest\n\nVerksamhet: Tillverkar o säljer\nkem tekn preparat såsom\nkosmetiska artiklar, hårpreparat o\nhårfärg\n\nVarunamn: Dermetics, Lasting,\nRoux\n\nAntal anställda: 20\nÅrsomsättning: 3 000000\nAktiekapital: 5 000\nStyrelse: Dir Curt Persson, fru\nElsa Hernritz\nVerkst dir: Curt Persson\nEtableringsår: 1953.\n\nWESTERSTRAND\nELECTRONIC AB\n\nPnr 545 00\n\nTöreboda, Box 71. Verkstadsg. Tel\n0506-116 75. Bankgiro 671-6260.\nPostgiro 444744-7\nVerksamhet: Tillverkar o säljer\nTV-mottagare, ljudprodukter\nAntal anställda: 40\nÅrsomsättning: 9 000 000\nAktiekapital: 100000\nVerkst dir: Gustav Westerstrand\nEtableringsår: 1966.\n\nWESTERSTRAND &amp; SÖNER\nURFABRIK, AB\n\nPnr 54 5 00\n\nTöreboda. Tel 0506-116 00. Tga\nWesterstrands.\nTelex 5971 WSTRAND S\nVerksamhet: Tillverkar\nprogramverk o automatik till\nhushållsmaskiner, väggur, korttidsmätare,\ntidkontrollur, timer, tornur,\nfasadur, huvudur, sekundärur, synkronur,\nhotellväckningsanläggningar,\nsport- o resultatur, kugghjul samt\nautomatsvarvade o pressade\ndetaljer för räkneverk, urverk o\ninstrument\n\nFörsäljningskontor: 113 35\nStockholm, Karlbergsv 66. Tel\n08-315835, 3158 45\nAntal anställda: 280\nÅrsomsättning: 14 000000\nAktiekapital: 150000\nStyrelse: Disp Ruben Westerstrand\n(ordf), ing Helge Lingwall, ing\nJames Westerstrand, disp Jean\nWesterstrand\n\nVerkst dir: James Westerstrand\nEtableringsår: 1906.\n\nVESTERÅS\n\nse Västerås.\n\nWESTIMPORT AB\n\nPnr 31101\n\nFalkenberg 1, Box 66. Badhusv.\nTel 0346-160 20. Bankgiro\n277-0659. Postgiro 271180-2. Tga\nWest import\n\nVerksamhet: Säljer skor engros\nAntal anställda: 5\nÅrsomsättning: 5 000 000\nAktiekapital: 50 000\nChef: Dir Thure Rosander\nEtableringsår: 1966.\n\nWESTIN &amp; BACKLUND, AB\n\nPnr 102 72\n\nStockholm 9, Liljeholmsv 8. Box\n9126. Tel 08-18 84 00. Postgiro\n53933. Tga Webac.\nTelex 10175 WEBAC S\nVerksamhet: Maskiner, ugnar,\nverktyg o förnödenheter för gjuterier o\nmodellverkstäder, smörjapparater,\nfilter o regulatorer\nFilialer: 41135 Göteborg, Teaterg\n17. Tel 031-20 38 33, 20 44 55.\nTga Web. Disp: Arne Wiksten\n21129 Malmö, S Promenaden 5.\nGjuteriavdelningen: Tel\n040-355 25, 355 30. Tga Webac. Chef:\nDisp Arne Holst\n21129 Malmö, S Promenaden 5.\nNorgrenavdelningen: Tel\n040-973002, 973004. Chef: Ing Harry\nJönsson\n\n85230 Sundsvall, Storg 34. Tel\n060-12 5 3 80. Ing: Ove Nilsson\nVerkstad: 733 00 Sala, Bergslagsg\n1. Tel 0224-150 05. Tga Webac.\nVerkstadschef: Ing A Schön\nVarunamn: Poseco, Metalit,\nNorgren. Speedmullor, Webac,\nVirvelvind. Whirl-Air-Flow\nAntal anställda: 110\nÅrsomsättning: 20000000\nAktiekapital: 875000\nStyrelse: Doc B Westin (ordf), dir\nK G Westin, civilekonom R Löhr,\ning J Westin, ing U Westin\nVeikst dir: Civiling K G Westin\nEtableringsår: 1932.\n\nWESTINGHOUSE BROMS- &amp;\nREGLERTEKNIK AB\n\nPnr 21446\n\nMalmö, Idunsg 26. Tel 040-92 22 90.\nBankgiro 615-1575. Postgiro\n637830. Tga West Broms.\nTelex 32615\n\nVerksamhet: Pneumatiska\nbromssystem. Kedjetransmissioner\nAntal anställda: 59\nAktiekapital: 1000 000\nVerkst dir: Harry Merseburg\nEtableringsår: 1969.\n\nWESTINGHOUSE BROMS- och\nREGLERTEKNIK AB\nHOVAVERKEN\n\nPnr 54070\n\nHova, Box 96. Industrig. Tel\n0506-306 10. Bankgiro 570-3749,\n664-1153. Postgiro 197420-3.\nTelex 5935\n\nVerksamhet: Tillverkar o säljer\ntryckluftkomponenter av\nWabco-Westinghouse fabrikat. Samtliga\nkomponenter avsedda för tyngre\nlastfordon o släpvagnar\nAntal anställda: 55\nÅrsomsättning: 8 000 000\nVerkst din Harry Merseburg\nPlatschef Hova: Disp Alf Wikander\nEtableringsån 1945.\n\nMETRONIK AB\n\nPnr 217 44\n\nMalmö, Fågelbacksg 13. Tel\n040-776 40. Bankgiro 645-5190.\nPostgiro 630279-8\n\nVerksamhet: Utför alla slags elektr\ninstallationer. Tillverkar elektr\nautomatik o pneumatiska\nutrustningar\n\nAntal anställda: 35\nÅrsomsättning: 3 500 000\nAktiekapital: 5 000\nStyrelseordf: René Lundström\nVerkst dir: René Lundström\nEtableringsår: 1963.\n\nSVENSKA STORNO AB\n\nPnr 123 55\n\nFarsta 4, Bengt Bagares Gränd 13.\nBox 493. Tel 08-94 0 4 45. Bankgiro\n643-6182. Postgiro 533752-2. Tga\nStornoradio. Telex 10383\nVerksamhet: Säljer Storno\nkommunikationsradio i Sverige\nAntal anställda: 130\nÅrsomsättning: 11000000\nAktiekapital: 2 000 000\nVerkst dir. Bengt Oregård\nEtableringsår: 1961.\n\nKONTORSELEKTRONIK, AB\n\nPnr 400 51\n\nGöteborg 47, Kortedala torg 7. Box\n47002. Tel 031-46 27 05. Bankgiro\n85-2262. Postgiro 621610-5\nVerksamhet: Specialitet:\nsnabbtelefoner, centraldikteringar o\ncentral-musikanläggningar\nAntal anställda: 5\nAktiekapital: 5 000\nVerkst dir: Sture Andréasson\nEtableringsår: 1961.\n\nKONTORSFOURNERINGEN I\nSTOCKHOLM AB\n\nPnr 11137\n\nStockholm, Luntmakarg 36. Tel\n08-23 38 85. Bankgiro 48-2440.\nPostgiro 51627\n\nVerksamhet: Säljer all slags kon-\n\ntorsmateriel\n\nAntal anställda: 8\n\n.Aktiekapital: 5 000\n\nVerkst dir: Carl-Olof Bergh\n\nEtableringsår: 1930\n\nOmbildat till aktiebolag 1938.\n\nKONTORSINDUSTRI AB\n\nPnr 851 04\n\nSundsvall 1, Agatan 3. Box 278.\nTel 060-11 2930. Postgiro 375966.\nTga Kiab\n\nVerksamhet: Tryckeri\nVerkst dir: KG Hägglund\nEtableringsår: 1951.\n\nKONTORSSERVICE AB,\nCHEFSSEKRETERAREN\n\nPnr 18107\n\nLidingö 7, Box 734. Klosterv 3.\nTel 08-767 0105. Bankgiro\n746-5040. Postgiro 145863-7\nVerksamhet Skrivbyrå,\nkontorsservice, offsettryckeri,\nljuskopiering\n\nAntal anställda: 65\nÅrsomsättning: 1500 000\nAktiekapital: 30 000\nVerkst dir. Disp Erie Bergstrand\nEtableringsår: 1957\nOmbildat till aktiebolag 1970.\n\nKONTORSSPECIAL\n\nPnr 574 01\n\nVetlanda 1, Box 34. Tel\n0383-140 20\n\nVerksamhet: Säljer kontorsmöbler\no -maskiner, kontorsmaieriel i\nparti\n\nVerkst dir: Nisse Palm.\n\nKONTORSSTÄDNING AB\n\nPnr 11134\n\nStockholm, Sveav 25-27. Tel\n08-2442 55. Bankgiro 29-5167.\nPost-giro 353450-0\n\nVerksamhet: Städning av kontor,\nfabriker o fastigheter\nAntal anställda: 1200\nÅrsomsättning: 12 000 000\n.Aktiekapital: 25 000\nVerkst dir: Yngve Jödahl\nEtableringsår: 1948.\n\nKONTORSTJÄNST,\nSTEN REHMNERT\n\nPnr 83100\n\nÖstersund, Rådhusg 48. Tel\n063-154 04, 187 70. Bankgiro 25-0119.\nPostgiro 276842-2\nVerksamhet: Kontorsmaskiner,\nkontorsmöbler, snabbtelefoner,\ninventarier o materiel, skrivbyrå,\nverkstad m m\n\nAntal anställda: 7\nÅrsomsättning: 900 000\nÄgare o chef: S Rehmnert\nEtableringsår: 1946.",
    "structured": {
        "SwedishFirms": [
            {
                "company_name": "SDDERLUNDSMETALL AB",
                "pnr": "330 30",
                "address": "Gnosjö. Tel 0370-912 37, 918 00.",
                "phone_number": "0370-912 37, 918 00",
                "bank_details": {
                    "bankgiro": "542-4577",
                    "postgiro": "362883-1"
                },
                "activity": "Tillverkar ljusstakar i mässing, automatsvarvning.",
                "employees": 18,
                "annual_turnover": 2500000,
                "capital": 70000,
                "key_personnel": [
                    {
                        "name": "Sven-Olof Söderlund",
                        "position": "Verkst dir"
                    }
                ],
                "establishment_year": 1960
            },
            {
                "company_name": "WÄSTGOTA TÄCKFABRIK AB",
                "pnr": "52400",
                "address": "Herr ljunga. Box 109. Tel 0513-10154.",
                "phone_number": "0513-10154",
                "bank_details": {
                    "bankgiro": "84-1065",
                    "postgiro": "514551"
                },
                "activity": "Tillverkar sängkläder, täcken o sovsäckstäcken.",
                "capital": 30000,
                "key_personnel": [
                    {
                        "name": "Fredrik Larsson",
                        "position": "Verkst din"
                    }
                ],
                "establishment_year": 1939
            },
            {
                "company_name": "BROMMA PERSIENNSERVICE",
                "pnr": "172 21",
                "address": "Sundbyberg 1, Vegag 16. Box 10. Tel 08-29 4252.",
                "phone_number": "08-29 4252",
                "bank_details": {
                    "bankgiro": "588-9639",
                    "postgiro": "320334-6"
                },
                "activity": "Tillverkar o säljer persienner, jalusier o kornischer",
                "employees": null,
                "annual_turnover": null,
                "capital": null,
                "key_personnel": [
                    {
                        "name": "Georg Gabrielsson",
                        "position": "Chef"
                    }
                ],
                "establishment_year": 1956
            },
            {
                "company_name": "BROMMA SMIDES&MEK VERKSTAD, AB",
                "pnr": "162 26",
                "address": "Vällingby, Krossg 31-33. Tel 08-38 00 30.",
                "phone_number": "08-38 00 30",
                "bank_details": {
                    "bankgiro": "172-8138",
                    "postgiro": "609534-3"
                },
                "activity": "Tillverkar järnkonstruktioner, containerutrustningar, containerok m m",
                "employees": null,
                "annual_turnover": null,
                "capital": null,
                "key_personnel": [
                    {
                        "name": "Hans Backteman",
                        "position": "Verkst dir"
                    }
                ],
                "establishment_year": 1960
            },
            {
                "company_name": "L.A PLAST AB",
                "pnr": "44101",
                "address": "Alingsås 1, Verkstadsg 3. Box 9. Tel 0322-180 15.",
                "phone_number": "0322-180 15",
                "bank_details": {
                    "bankgiro": "436-6134",
                    "postgiro": "370450-9"
                },
                "activity": "Tillverkar sko- o trä-toffelsulor samt mattor av plast. Läderimitationer.",
                "employees": 40,
                "annual_turnover": 3000000,
                "capital": 30000,
                "key_personnel": [
                    {
                        "name": "Hilding Apoi",
                        "position": "Verkst dir"
                    }
                ],
                "establishment_year": 1957
            }
        ]
    }
}