{
    "original": "BEKATEK AB\n\nPnr 162 21\n\nVällingby, Vällingbyv 170. Tel\n08-87 76 00. Bankgiro 472-5636.\nPostgiro 55632-4. Tga Bekatek\nVerksamhet Säljer kontorsmaskiner\nsamt specialmaskiner för kontor\nAktiekapital: 20 000\nVerkst dir: I Bjernefalk\nEtableringsår: 1967.\n\nBEKKEDAHL&amp; ORTENBLAD,\nAB\n\nPnr 40125\n\nGöteborg 1, Tegnërsg 15. Box 345.\nTel 031-810920\n\nVerksamhet: Bil-, traktor- o\nindustridäck. Regummeringsfabrik.\nSlangar\n\nRegummeringsfabrik: Vara,\nBad-husg 22. Tel 0512-112 25\nAntal anställda: 60\nÅrsomsättning: 12 000 000\nAktiekapital: 225 000\nVerkst din Lennart \"Säll\nEtableringsår: 1932.\n\nTRUCKIMPORT, AB\n\nPnr 194 01\n\nUpplands Väsby 1, Tetorpsv 6.\nBox 17. Tel 0760-34160. Bankgiro\n700-4260. Postgiro 445030-0. Tga\nDumptruck, Stockholm.\nTelex 10228\n\nVerksamhet: Säljer entreprenad-,\nindustri- o arbetsmaskiner\nVarunamn: Wabco, Wabco Loader\nAktiekapital: 200 000\nStyrelseordf: Dir Paul Dylting\nVerkst dir: Paul Dylting\nEtableringsår 1954.\n\nTRUCK-SERVICE AB,\nSTOCK-HOLMS TULLPACKHUSLAGS\n\nPnr 11641\n\nStockholm, Barnängsg 43. Tel\n08-23 11 10. Postgiro 51746-6\nVerksamhet: Uthyrning av truckar\nAktiekapital: 5 000\nVerkst dir. Leif Larson\nEtableringsår: 1957.\n\nSVE\n\nSVENSKA ELEKTRISKA\nREGULATOR AB (SERA)\n\nPnr 421 09\n\nVästra Frölunda 9, Box 9010. Tel\n031-29 55 61. Bankgiro 512-7725.\nPostgiro 420815-3\nVerksamhet: Tillverkar\nspannmålstorkar, varmluftspannor, elevatorer,\naspiratörer, förvaringssilor,\nplantransportörer, grillar, salamandrar,\nvärmerier o potatisskalare\nVarunamn: SERA\nÅrsomsättning: 1300 000\nAktiekapital: 12000\nVerkst dir Patrik Hedendahl\nEtableringsår 1949.\n\nSVENSKA\nELEKTROINSTRU-MENT\n\nPnr 16126\n\nBromma 1, Box 39. Tyska\nBottens v 42. Tel 08-37 47 40.\nBankgiro 744-0183. Postgiro 251972-6\nVerksamhet: Tillverkar\nstyrkristaller\n\nAntal anställda: 8\nChef: Ing Einar Lagerström\nEtableringsår: 1951.\n\nSVENSKA\nELEKTROMAGNETER, AB\n\nPnr 662 00\n\nÅmål, Box 30. Nygård. Tel\n0532-120 10. Tga Magneter. Telex 5324\n\nVerksamhet: Tillverkar\ntändmag-neter, svänghjulsmagneter,\ndrag-magneter för lik- o växelström,\ntransformatorer, signal- o\nsummer-aggregat, elektr specialapparater\nVarunamn: SEM\nAntal anställda: 300\nÅrsomsättning: 12 000 000\nAktiekapital: 1500 000\nVerkst dir: Erik Grunander\nEtableringsår 1916.\n\nLUNDVALLS BRÄNSLE AB\n\nPnr 252 21\n\nHelsingborg, Drottningg 1. Tel\n042-13 91 60. Bankgiro 652-9135.\nPostgiro 14231-5. Tga Lundvall\nVerksamhet: Handel med\neldningsoljor, kol o koks\nAntal anställda: 31\n\nÅrsomsättning: 10000 000\nAktiekapital: 580 000\nVerkst dir: Karl Engfors\nEtableringsår: 1884.\n\nLUNDWALL &amp; CO AB,\nINGENIÖRSFIRMAN\n\nPnr 42131\n\nVästra Frölunda, Fröklöversg 5.\nTel 031-45 43 50. Bankgiro\n500-3959. Postgiro 48713-2. Tga\nMill-wall. Telex 20635 MILLWAL S\nVerksamhet: Säljer maskiner o\nverktyg, instrument o\nmarinutrust-ning\n\nAntal anställda: 35\nAktiekapital: 100000\nVerkst dir: B Lundwall\nEtableringsår: 1941.\n\ngenberg, henrik\n\nPnr 41110\n\nGöteborg, O Hamng 19 B. Tel\n031-17 6130. Bankgiro 84-8348.\nPostgiro 243688. Tga Oxides\nVerksamhet: Importagentur av kem\nråvaror för gummi-, färg-, plast-,\npapper-, keramik m fi industrier\nÄgare o chef: Ulf Genberg\nEtableringsår: 1930.\n\nCONTEMPORA AB\n\nPnr 21122\n\nMalmö, N Vallg 90-92. Tel\n040-11 90 25, 11 90 30. Bankgiro\n644-3303. Postgiro 435448-6. Tga\nContempora\n\nVerksamhet: Säljer\ndekorationstextilier, möbeltyger, mattor o\nheltäckningsmattor\nVarunamn: Contempora\nAntal anställda: 3\nÅrsomsättning: 2 500 000\nAktiekapital: 50 000\nVerkst dir: Arkitekt Kurt Pålsson\nEtableringsår: 1953.\n\nCONTINENTALS\nHERRKLÄDER, AB\n\nPnr 502 32\n\nBorås 1, Hötorget 1. Box 405. Tel\n033-1113 07, 12 39 77. Bankgiro\n839-1625. Postgiro 99580-3\nVerksamhet: Säljer färdig\nkonfektion o ekiperingsartiklar för herr\no yngling\nAntal anställda: 7\nAktiekapital: 30 000\nDisp: Gillis Claeson\nEtableringsår: 1934.\n\nSJOSA AB\n\nPnr 61100\n\nNyköping. Tel 0155-200 51, 20010.\nTga Sjösaträ\n\nVerksamhet: Byggnadsmaterialför-\n\nsäljning i parti o minut\n\nAntal anstäUda: 100\n\nÅrsomsättning: 7 500000\n\nAktiekapital: 240 000\n\nVeikst dir Frih August Trolle-\n\nLöwen\n\nEtableringsår 1946.\n\nSJOSTEDT &amp; CO, MASKIN AB\nSVEN\n\nPnr 11123\n\nStockholm, Torsg 8. Tel 08-11 19 59,\n1184 96. Postgiro 150911.\nTga Triplex\n\nVerksamhet: Importerar o tillverkar\nmaskiner för kem tvätt\nAktiekapital: 60 000\nStyrelse: B Bäck, S Hallberg\nEtableringsår 1915.\n\nSIOSTEENS BOKTRYCKERI\nAB, BRÖDERNA\n\nPnr 112 26\n\nStockholm, Fleming g 25. Tel\n08-54 64 54 , 53 08 92. Bankgiro\n136-1963. Postgiro 4882-7\nVerksamhet: Trycksaker,\nuppläggning av layouter\nAntal anställda-, 11\nAktiekapital: 45 000\nStyrelse: Adv Fredrik Adlercreutz\n(ordf), dlr fru Marie-Louise\nBiörcke, byråsekr Teofron\nDahlman\n\nVeikst dir Fru Marie-Louise\nBiörcke\n\nEtableringsår. 1882.\n\nSJO\n\nVerksamhet Agenturfirma för\npappersindustrin\nAntal anställda: 10\nÅrsomsättning: 20 900 0 00\nAktiekapital: 50 000\nVerkst dir. Olle Sjö\nEtableringsår: 1911.\n\nSJUBERGS KONFEKTYR.\nINDUSTRI AB\n\nPnr 41105\n\nGöteborg, Kronhusg 5. Tel\n031-1198 94. 11 19 44. Bankgiro\n50-6650. Postgiro 426345\nVeiksamhet: Tillverkar gelé- o\nlakritsartiklar\nAntal anställda: 11\nÅrsomsättning: 2 000 000\nAktiekapital: 5 000\nVerkst dir: Rune Sjöberg\nEtableringsår: 1936.\n\nRICKARDSSONS FABRIKS AB\n\nPnr 28101\n\nHässleholm 1, Box 9. N Industrig.\nTel 0451-800 60. Bankgiro\n866-3619. Postgiro 202095-6\nVerksamhet: Tillverkar släpvagnar\nför lastbilar\nAntal anstäUda: 50\nÅrsomsättning: 7 000 000\nAktiekapital: 100 000\nStyrelse: Ing Nils Rickardsson\n(crdf), fru Elsa Rickardsson\nVerkst din Nils Rickardsson\nEtableringsår. 1958.\n\nRICHARDSSON &amp; JOHANSSON\nROR AB\n\nPnr 792 00\n\nMora, Godsv 10. Tel 0250-119 50.\nBankgiro 469-1291. Postgiro\n294590-5\n\nVeiksamhet: Utför\nVVS-installa-tioner. Tillverkar cisterner\nAntal anstäUda: 31\nAktiekapital: 25 000\nChef: Stig Gustav Richardsson\nEtableringsår: 1946.\n\nNOR\n\nVerksamhet: Bokföring, revisioner\no skatteärenden\nAktiekapital: 5 000\nChef: Revisor SRS Arne Hultgren\nEtableringsàr: 1945.\n\nNORDING AB, ANTOINETTE W\n\nPnr 115 43\n\nStockholm, Midskogsgränd 11. Tel\n08-23 02 30. Bankgiro 564-5940.\nPostgiro 3515-4. Tga\nParfumnor-ding\n\nVerksamhet: Parfymeri. 5 butiker i\nStockholm o Cascades parfymeri\nVerkst dir: Civiling Klas Nording\nEtableringsàr: 1847.\n\nNORDISK BEVAKNING &amp;\nBUTIKSKONTROLL AB\n\nPnr 11121\n\nStockholm, Drottningg 70. Tel\n08-24 93 30. Bankgiro 575-9295. Postr\ngiro 604200-6\n\nVerksamhet Bevakningsföretag\nAntal anställda: 500\nÅrsomsättning: 8 000 000\nAktiekapital: 100 000\nStyrelse: Dir Lars Frimodig (ordf),\ndir Lennart Byréus, dir Martin\nSchönning, dir Bengt Sundevall\nVerkst dir: Martin Schönning.\n\nNORDISK ELEKTRA AB\n\nPnr 21124\n\nMalmö, Hanö g 2. Tel 040-18 06 50.\nBankgiro 870-3514. Postgiro\n38976-7. Tga Nordelektra.\nTelex 32415\n\nVerksamhet: Säljer elektr motorer,\ngeneratorer, telfrar, truckar,\nkuggväxelmotorer, växlar, variatorer o\nreserv elverk\n\nFörsäljningskontor: Stockholm. Tel\n08-27 34 35\n\nGöteborg. Tel 031-42 38 64\nEksjö. Tel 0381-116 93\nFalun. Tel 023-120 52\nVarunamn: Asug, Balkancar, DAE,\nDale, Elhy, Knödler, Norcf,\nStephan, VEM\nAktiekapital: 75 000\nVerkst dir: Karl Jarving\nEtableringsàr: 1934.\n\nNORDISK ELEKTRONIK AB,\nINGENJÖRSFIRMAN\n\nPnr 103 80\n\nStockholm 7, Stureplan 3. Fack.\nTel 08-24 83 40. Bankgiro 72-5032.\nPostgiro 53996. Tga Nordtron.\nTelex 10547\n\nVerksamhet: Försäljning av\nelektronikkomponenter, utrustningar o\nsystem samt datorer. Tillverkning av\nelektronik för industriell\nautomation, datalogging, alarmsystem m m\nAntal anställda: 55\nAktiekapital: 300 000\nStyrelse: Bergsing Axel Ax:son\nJohnson (ordf), dir A Haverdahl,\ndir N Mörner, dir B Nilsson, dir G\nWesterberg\n\nVerkst dir: Nils Mörner\nEtableringsàr: 1963.\n\nNORDISK ELISOLATION AB\nNORDISOLA\n\nPnr 940 20\n\nÖjebyn. Tel 0911-652 65. Bankgiro\n37-2651. Postgiro 488850. Tga\n\nNordisola, Piteå.\nTelex 80420 ELPLAST S\nVerksamhet: Tillverkar hartser,\nläcker, lim, isoler- o\nspackelmassor, impregnerad textil o papper,\npressmassor o pressmattor,\nlaminerade skivor, rör o profiler,\nglimmer-produkter, glasfiberarmerade\nplastprodukter, formgods av härd- o\ntermoplast. Skärande bearbetning\nav plastmaterial\nVarunamn: Asepreg\nAntal anställda: 250\nÅrsomsättning: 25 000 000\nAktiekapital: 5 000 000\nVerkst dir: Stig Lundmark\nEtableringsàr: 1969\nHelägt dotterbolag till ASEA.\n\nNORDISK EXPRESS, AB\n\nPnr 41113\n\nGöteborg, Kronhusg 2 B. Tel\n031-13 0427, 1304 02. Bankgiro\n509-6110. Postgiro 46038-6.\nTga Nordexpress. Telex 2381\nVerksamhet: Genomgång\nsbefrakt-ning till transoceana marknader\nAvdelningskontor: 104 30 Stockholm\n45, Box 45132. Kungstensg 38. Tel\n08-34 09 70\nAntal anställda: 10\nAktiekapital: 50 000\nVerkst dir: Oluf Lindeqvist\nEtableringsàr: 1911.\n\nNORDISK FILMKOPIA, AB\n\nPnr 100 31\n\nStockholm 21, Box 21058. N\nSta-tionsg 79-81. Tel 08-23 47 85.\nBankgiro 728-1181. Postgiro 658658-0\nVerksamhet: Utför framkallning o\nkopiering. Textar film\nAntal anställda: 55\nÅrsomsättning: 5 000 000\nAktiekapital: 250 000\nVerkst dir: Oscar Ertnaes\nEtableringsàr: 1933.\n\nNORDISK FLÄKT.\nINDUSTRI, AB\n\nPnr 214 50\n\nMalmö, Västanforsg 16. Tel\n040-92 24 60. Bankgiro 265-2204.\nPostgiro 249905-1\n\nVerksamhet: Tillverkar fläktar,\n\nspåntransportanläggningar, varm-\n\nluftsapparater\n\nAktiekapital: 25 000\n\nVerkst dir: Ing Birger Persson\n\nChef: Ing Gert Persson\n\nEtableringsàr: 1927.\n\nNORDISK HELIOTEXTIL, AB\n\nPnr 440 53\n\nOdsmål, Box 29. Tel 0303-730 01.\nBankgiro 430705. Postgiro 414035.\nTga Heliotextil\n\nVerksamhet Tillverkning av\nfärg-äkta tryckta textiletiketter\nVerkst dir: R Grimpe\nEtableringsàr: 1960.\n\nNORDISK KARTRO AB\n\nPnr 123 21\n\nFarsta 1, Tunnelbanehuset. Box 99\nTel 08-94 03 80. Bankgiro 47-9007.\nPostgiro 54144. Telex 10794. Tga\nKartro\n\nVerksamhet: Spik-, häft- o\nkartong-förslutningsmaskiner\n\nAntal anställda: 95\nAktiekapital: 1000000\nVerkst dir: Georg Rahmqvist\nEtableringsàr: 1932.\n\nNORDISK KONSULTATION AB\n\nPnr 217 74\n\nMalmö, Vikingag 62. Tel\n040-15 7070. Bankgiro 870-3589.\nPostgiro 431625-3. Tga Nordkonsult\nVerksamhet: Konsultverksamhet på\nföretagsledande nivå\nAntal anställda: 7\nAktiekapital: 30 000\nVerkst dir: Civiling Artur Warbert\nEtableringsàr 1951.",
    "structured": {
        "0": {
            "company_name": "BEKATEK AB",
            "activity": "Säljer kontorsmaskiner samt specialmaskiner för kontor",
            "establishment_year": 1967,
            "capital": 20000,
            "key_personnel": [
                {
                    "name": "I Bjernefalk",
                    "position": "Verkst dir"
                }
            ]
        },
        "1": {
            "company_name": "BEKKEDAHL& ORTENBLAD, AB",
            "activity": "Bil-, traktor- o industridäck. Regummeringsfabrik. Slangar",
            "establishment_year": 1932,
            "employees": 60,
            "annual_turnover": 12000000,
            "capital": 225000,
            "key_personnel": [
                {
                    "name": "Lennart \"Säll",
                    "position": "Verkst dir"
                }
            ]
        },
        "2": {
            "company_name": "TRUCKIMPORT, AB",
            "activity": "Säljer entreprenad-, industri- o arbetsmaskiner",
            "establishment_year": 1954,
            "capital": 200000,
            "key_personnel": [
                {
                    "name": "Paul Dylting",
                    "position": "Styrelseordf, Verkst dir"
                }
            ]
        },
        "3": {
            "company_name": "TRUCK-SERVICE AB, STOCK-HOLMS TULLPACKHUSLAGS",
            "activity": "Uthyrning av truckar",
            "establishment_year": 1957,
            "capital": 5000,
            "key_personnel": [
                {
                    "name": "Leif Larson",
                    "position": "Verkst dir"
                }
            ]
        },
        "4": {
            "company_name": "SVENSKA ELEKTRISKA REGULATOR AB (SERA)",
            "activity": "Tillverkar spannmålstorkar, varmluftspannor, elevatorer, aspiratörer, förvaringssilor, plantransportörer, grillar, salamandrar, värmerier o potatisskalare",
            "establishment_year": 1949,
            "employees": null,
            "annual_turnover": 1300000,
            "capital": 12000,
            "key_personnel": [
                {
                    "name": "Patrik Hedendahl",
                    "position": "Verkst dir"
                }
            ]
        },
        "5": {
            "company_name": "SVENSKA ELEKTROINSTRUMENT",
            "activity": "Tillverkar styrkristaller",
            "establishment_year": 1951,
            "employees": 8,
            "key_personnel": [
                {
                    "name": "Ing Einar Lagerström",
                    "position": "Chef"
                }
            ]
        },
        "6": {
            "company_name": "SVENSKA ELEKTROMAGNETER, AB",
            "activity": "Tillverkar tändmagneter, svänghjulsmagneter, dragmagneter för lik- o växelström, transformatorer, signal- o summer-aggregat, elektr specialapparater",
            "establishment_year": 1916,
            "employees": 300,
            "annual_turnover": 12000000,
            "capital": 1500000,
            "key_personnel": [
                {
                    "name": "Erik Grunander",
                    "position": "Verkst dir"
                }
            ]
        },
        "7": {
            "company_name": "LUNDVALLS BRÄNSLE AB",
            "activity": "Handel med eldningsoljor, kol o koks",
            "establishment_year": 1884,
            "employees": 31,
            "annual_turnover": 10000000,
            "capital": 580000,
            "key_personnel": [
                {
                    "name": "Karl Engfors",
                    "position": "Verkst dir"
                }
            ]
        },
        "8": {
            "company_name": "LUNDWALL& CO AB, INGENJÖRSFIRMAN",
            "activity": "Säljer maskiner o verktyg, instrument o marinutrustning",
            "establishment_year": 1941,
            "employees": 35,
            "capital": 100000,
            "key_personnel": [
                {
                    "name": "B Lundwall",
                    "position": "Verkst dir"
                }
            ]
        },
        "9": {
            "company_name": "genberg, henrik",
            "activity": "Importagentur av kem råvaror för gummi-, färg-, plast-, papper-, keramik m fi industrier",
            "establishment_year": 1930,
            "key_personnel": [
                {
                    "name": "Ulf Genberg",
                    "position": "Ägare o chef"
                }
            ]
        }
    }
}