{
    "original": "partille mek fabriks ab\n\nPnr 43300\n\nPartilie. Tel031-4419 16, 44 38 95.\nBankgiro 446-1430. Postgiro\n623130-2\n\nVerksamhet: Tillverkar o säljer\nbyggnadsmaskiner, voit system för\nträdgården, byggsystem Tapp o Kil\nÅrsomsättning: 1000 000\nAktiekapital: 5 000\nVerkst dir: Fabr Gunnar\nBjörkman\n\nEtableringsår: 1962.\n\npassad automation ab\n\nPnr 126 60\n\nHägersten, Vasaloppsv 42-46. Tel\n08-880155, 97 37 00. Bankgiro\n578-2792. Postgiro 671667-4.\nTga Passadair\n\nVerksamhet: Tillverkar\nspecialmaskiner, matningsanordningar,\ncylindrar, ventiler o vibratorer.\nSpecialitet: pneumatik o hydraulik\nVarunamn: Schrader\nAntal anställda: 25\nAktiekapital: 10000\nVerkst dir: Ing Börje Sjögren\nEtableringsår 1965.\n\npatentbyrån gunnar\nbacker\n\nPnr 41114\n\nGöteborg, Drottningg 15. Tel\n031-11 2066. Bankgiro 848-1152.\nPostgiro 40773-4. Tga Backerpat\nVerksamhet: Patent- o\nvarumärkes-samt mönsterärenden\nÄgare o chef: Civiling Gunnar.\nBacker\n\nEtableringsår: 1926.\n\nBERGDAHL &amp; OLSSON, AB\n\nPnr 41140\n\nGöteborg, Ullevi. Tel 031-80 04 50.\nBankgiro 500-8909. Postgiro\n242081-8\n\nVerksamhet: Säljer bilreservdelar,\nbiltillbehör, maskiner o verktyg\nAntal anställda: 14\nÅrsomsättning: 3000000\nAktiekapital: 120 000\nVerkst dir: Töre Olsson\nLagerchef: Ragnar Gustavsson\nEtableringsår: 1947.\n\nBERGDALA GLASBRUK\nBERGDALAGLAS AB\n\nPnr 360 51\n\nHovmantorp. Tel 0478-180 65.\nBankgiro 122-2934. Postgiro 668762-8.\nTga Bergdalaglas, Växjö\nVerksamhet: Tillverkar konst-,\nprydnads- o hushållsglas samt\nlampor o lyktor\nAntal anställda: 35\nÅrsomsättning: 1500000\nAktiekapital: 120 000\nKontaktman: Elving Conradson\nEtableringsår: Bruket grundat 1869.\n\nBERGENS MEKANISKE\nVERKSTEDERSSVENSKA AB\n\nPnr 417 05\n\nGöteborg, Gustaf Dalénsg 11. Tel\n031-5138 90. Bankgiro 50-0880.\nPostgiro 241310. Tga Bergenmarin.\nTelex 20742\n\nVerksamhet: Försäljning av det\nnorska moderföretagets produkter\nVarunamn: Bergen Diesel, BMV,\nNormo, Norwinch\nAktiekapital: 70000\nVerkst dir: Tor Torgersen\nEtableringsår: 1962.\n\nKLICHÉHUSET AB\n\nPnr 17141\n\nSolna, Englundav 8. Box 307,\n10124 Sthlm 1. Tel 08-98 12 00.\nBankgiro 483-5351. Postgiro\n600449-3. Tga Kliché\nVerksamhet: Annonssättning,\nannonsmaterial, annonsklichéer,\nboktrycksklichéer (svartvitt o färg),\noffset- o djuptrycksrepro (svartvitt\no färg), tryckning, reprosättning,\nfotosättning, tone-line,\nkornraster-kopior\n\nVarunamn: No-Pac,\nPluralis-klichéer, Termoset\nAntal anställda: 180\nÅrsomsättning: 12 000 000\nAktiekapital: 20600\nFirmatecknare: Dir Karl O S\nFjaestad, dir Per S Fjaestad\nEtableringsår: 1906.\n\nVAC\n\nwaco ab, maskinfabriken\n\nPnr 30102\n\nHalmstad 1, Nässjög. Box 41. Tel\n035-1187 20. Bankgiro 530-0538.\nPostgiro 93626-0. Tga Waco.\nTelex 38010 WACO S\n\n3EJ\n\nVerksamhet: Tillverkar maskiner\no verktyg för träbearbetning\nVarunamn: Waco\nAntal anställda: 110\nÅrsomsättning: 9 000 000\nAktiekapital: 300 000\nStyrelse: Dir Gunnar Wahlbeck\n(ordf), ing Bengt Andersson,\ndriftschef Allan Bergqvist, frk Ann-Helen\nBlomberg, fru Margit Hörnfeldt, dir\nCarl-Eric Wahlbeck\nVerkst dir: Carl-Eric Wahlbeck\nEtableringsår: 1918\nOmbildat till aktiebolag 1950.\n\nvacuum-extractor, ab\n\nPnr 403 14\n\nGöteborg 2, Box 2213. Drottningg\n13. Tel 031-17 0740. Bankgiro\n50-0737. Postgiro 428441. Tga Vacex.\nTelex 21083 SEVATO S\nVerksamhet: Tillverkare o\nensamförsäljare av specialinstrument\nför gynekologi o obstetrik\nAntal anställda: 5\nÅrsomsättning: 1000 000\nAktiekapital: 5 000\nVerkst din Göran O Uddenberg\nEtableringsån 1954.\n\nvadstena\nbyggnads-snickerier, ab\n\nPnr 592 00\n\nVadstena, Industriv. Tel\n0143-10178, 102 68. Bankgiro 127-0511.\nPostgiro 74416-9\n\nVerksamhet: Tillverkar\nbyggnadssnickerier. Säljer trävaror\nAntal anställda: 25\nÅrsomsättning: 2 500 000\nAktiekapital: 20 000\nVerkst dir: Ryno Edvardsson\nEtableringsår: 1925.\n\nvadstena\nmetall-gjuteri, ab\n\nPnr 592 00\n\nVadstena, Strandpromenaden. Box\n5. Tel 0143-10210. Postgiro\n326110-4. Tga Valetamaskin\nVerksamhet: Tillverkar\nmetallgjut-gods\n\nV\n\nAktiekapital: 5 000\nVerkst dir: Ing Nils Engström\nEtableringsår: 1946.\n\nWENNERLUNDS MASKIN AB\n\nPnr 41134\n\nGöteborg, Götabergs g 28. Tel\n031-1664 14, 20 3032. Bankgiro\n510-7214. Postgiro 43874-7. Tga\nGe Hå We-maskiner\nVerksamhet: Alla typer av flata\ndrivremmar, rundremmar o\ntransportband i moderna material\nVarunamn: VIS\nAktiekapital: 10 000\nVerkst din Owe Björklund\nEtableringsår: 1932.\n\nLJUNGBERG &amp; CO AB, KARL\n\nPnr 281 01\n\nHässleholm 1, Första Avenyen 1.\nBox 8. Tel 0451-143 00. Bankgiro\n27-0 1 38. Postgiro 293770.\nTga Ljungco. Telex 4458\nVerksamhet: Grossiströrelse med\nwallboard, plywood o spånplattor.\nProjekterar o säljer kompletta\nbandsågverk o såglinjer. Säljer\ntunga bandsågar för sågverk o\nhyvlerier\n\n.Aktiekapital: 250 000\n\nÄgare o chefer: Karl Ljungberg,\n\nKaj Ljungberg.\n\nLJUNGBERG &amp; CO, AB LARS\n\nPnr 115 26\n\nStockholm NO, Gyllenstiernsg 18.\nTel 08-63 58 70. Bankgiro 73-0743.\nPostgiro 507999. Telex 17372. Tga\nLars trade\n\nVerksamhet: Säljer\nelektromedi-cinska instrument\nVerkst dir: Civilekonom Lars\nLjungberg\n\nEtableringsår: 1955.\n\nLJUNGBERGS LÄDERFABRIK,\nAB N H\n\nPnr 500 06\n\nBoiås 6, Gässlösav 28. Box 66091.\nTel 033-1277 60. Bankgiro 53-1211.\nPostgiro 33786\n\nVerksamhet: Tillverkar lädervaror,\nskodon o tofflor\nAntal anställda: 110\nÅrsomsättning: 9 000 000\nAktiekapital: 2 331000\nVerkst dir: g Rangert\nEtableringsår: 1916.\n\nLJUNGBERG, BYGGNADS AB\nTAGE\n\nPnr 113 59\n\nStockholm, Kungstensg 57. Tel\n08-34 07 30. Bankgiro 447-0381. Postr\ngiro 258711-1\n\nVerksamhet Bygger flerfamiljshus,\n\nvillor, fabriksbyggnader samt utför\nombyggnadsarbeten\nAntal anställda: 80\nÅrsomsättning: 7 000 000\nAktiekapital: 100000\nVerkst dir. Byggn-ing Tage\nLjungberg\n\nEtableringsår: 1946.\n\nLJUNGBERGS MEK\nVERKSTAD AB, W\n\nPnr 55102\n\nJönköping 1, Kämpev 6. Box 436.\nTel 036-11 14 81, 1217 20.\nBankgiro 341-9496. Postgiro 160550-0\nVerksamhet: Tillverkar\nlekplatsut-rustningar, parksoffor, cykelställ,\nmattpiskställ, rörverktyg,\nrensverktyg, lyftverktyg m m\nAntal anställda: 35\nÅrsomsättning: 2 000 000\nAktiekapital: 61000\nVerkst dir: Bertil Ljungberg\nEtableringsår: 1945.\n\nANDRÉN AB, BO\n\nPnr 19147\n\nSollentuna, Industriv 16, Tureberg.\nTel 08-35 27 50. Tga Zoka.\nTelex 1857 ANDREN S\nVerksamhet: Import o grosshandel\ni lövträ, fanér, plywood, lamell- o\nspånskivor\nAntal anställda: 25\nAktiekapital: 500 000\nVerkst dir: Bo Andrén\nEtableringsår: 1942.\n\ngällstads ylle, ab\n\nPnr 520 10\n\nGäUstad. Box 48. Tel 0321-712 80.\nBankgiro 840-6480. Postgiro\n323199-0\n\nVerksamhet: Modevaror i acryl\nAntal anstäUda: 25\nÅrsomsättning: 2000 000\nAktiekapital: 45 000\nStyrelse: Fabr Martin Göthager\n(ordf), fabr Tage Henningsson,\nfabr Ragnar Thylander\nVerkst dir: Fabr Martin Göthager\nEtableringsår: 1946.\n\nINFORMATIONS TV AB\n\nPnr 21748\n\nMalmö, Regementsg 52 C. Tel\n040-756 25. Bankgiro 640-4800\nVerksamhet: Intern television för\nbostadsområden o travbanor\nAntal anställda: 28\nÅrsomsättning: 600000\nAktiekapital: 125 000\nVerkst dlr Carl-Erik Tornheden\nEtableringsår: 1961.\n\nIGGESUNDS BRUK, AB\n\nPnr 825 00\n\nIggesund. Tel 0650-208 00.\nBankgiro 99-1249. Postgiro 76700.\nTga Iggesund, Hudiksvall.\nTelex 8220\n\nVerksamhet: Skogsbruk samt\ntillverkning av cellulosa, homogen\nkartong, trävaror, sågblad,\nhugg-maskinknivar, barkverktyg, Stamick\npostningssystem\nVarunamn: Inverboard\nAntal anställda: 3 500\nAktiekapital: 140000 000\nVerkst dir: Lars G Sundblad\nEtableringsår 1685.",
    "structured": {
        "1": {
            "company_name": "partille mek fabriks ab",
            "pnr": "43300",
            "address": "Partilie",
            "phone_number": "031-4419 16, 44 38 95",
            "bank_details": {
                "bankgiro": "446-1430",
                "postgiro": "623130-2"
            },
            "activity": "Tillverkar o säljer byggnadsmaskiner, voit system för trädgården, byggsystem Tapp o Kil",
            "annual_turnover": 1000000,
            "capital": 5000,
            "key_personnel": {
                "name": "Fabr Gunnar Björkman"
            },
            "establishment_year": 1962
        },
        "2": {
            "company_name": "passad automation ab",
            "pnr": "126 60",
            "address": "Hägersten, Vasaloppsv 42-46",
            "phone_number": "08-880155, 97 37 00",
            "bank_details": {
                "bankgiro": "578-2792",
                "postgiro": "671667-4"
            },
            "activity": "Tillverkar specialmaskiner, matningsanordningar, cylindrar, ventiler o vibratorer",
            "employees": 25,
            "annual_turnover": 10000000,
            "capital": 10000,
            "key_personnel": {
                "name": "Ing Börje Sjögren"
            },
            "establishment_year": 1965
        },
        "3": {
            "company_name": "patentbyrån gunnar backer",
            "pnr": "41114",
            "address": "Göteborg, Drottningg 15",
            "phone_number": "031-11 2066",
            "bank_details": {
                "bankgiro": "848-1152",
                "postgiro": "40773-4"
            },
            "activity": "Patent- o varumärkes-samt mönsterärenden",
            "key_personnel": {
                "name": "Civiling Gunnar. Backer"
            },
            "establishment_year": 1926
        },
        "4": {
            "company_name": "BERGDAHL & OLSSON, AB",
            "pnr": "41140",
            "address": "Göteborg, Ullevi",
            "phone_number": "031-80 04 50",
            "bank_details": {
                "bankgiro": "500-8909",
                "postgiro": "242081-8"
            },
            "activity": "Säljer bilreservdelar, biltillbehör, maskiner o verktyg",
            "employees": 14,
            "annual_turnover": 3000000,
            "capital": 120000,
            "key_personnel": {
                "name": "Töre Olsson"
            },
            "establishment_year": 1947
        },
        "5": {
            "company_name": "BERGDALA GLASBRUK BERGDALAGLAS AB",
            "pnr": "360 51",
            "address": "Hovmantorp",
            "phone_number": "0478-180 65",
            "bank_details": {
                "bankgiro": "122-2934",
                "postgiro": "668762-8"
            },
            "activity": "Tillverkar konst-, prydnads- o hushållsglas samt lampor o lyktor",
            "employees": 35,
            "annual_turnover": 1500000,
            "capital": 120000,
            "key_personnel": {
                "name": "Elving Conradson"
            },
            "establishment_year": 1869
        },
        "6": {
            "company_name": "BERGENS MEKANISKE VERKSTEDERSSVENSKA AB",
            "pnr": "417 05",
            "address": "Göteborg, Gustaf Dalénsg 11",
            "phone_number": "031-5138 90",
            "bank_details": {
                "bankgiro": "50-0880",
                "postgiro": "241310"
            },
            "activity": "Försäljning av det norska moderföretagets produkter",
            "employees": 0,
            "capital": 70000,
            "key_personnel": {
                "name": "Tor Torgersen"
            },
            "establishment_year": 1962
        },
        "7": {
            "company_name": "KLICHÉHUSET AB",
            "pnr": "17141",
            "address": "Solna, Englundav 8, Box 307",
            "phone_number": "08-98 12 00",
            "bank_details": {
                "bankgiro": "483-5351",
                "postgiro": "600449-3"
            },
            "activity": "Annonssättning, annonsmaterial, annonsklichéer, boktrycksklichéer (svartvitt o färg), offset- o djuptrycksrepro (svartvitt o färg), tryckning, reprosättning, fotosättning, tone-line, kornraster-kopior",
            "employees": 180,
            "annual_turnover": 12000000,
            "capital": 20600,
            "key_personnel": [
                {
                    "name": "Dir Karl O S Fjaestad",
                    "position": "dir"
                },
                {
                    "name": "dir Per S Fjaestad",
                    "position": "dir"
                }
            ],
            "establishment_year": 1906
        },
        "8": {
            "company_name": "VAC waco ab, maskinfabriken",
            "pnr": "30102",
            "address": "Halmstad 1, Nässjög, Box 41",
            "phone_number": "035-1187 20",
            "bank_details": {
                "bankgiro": "530-0538",
                "postgiro": "93626-0"
            },
            "activity": "Tillverkar maskiner o verktyg för träbearbetning",
            "employees": 110,
            "annual_turnover": 9000000,
            "capital": 300000,
            "key_personnel": [
                {
                    "name": "Dir Gunnar Wahlbeck",
                    "position": "ordf"
                },
                {
                    "name": "ing Bengt Andersson",
                    "position": null
                },
                {
                    "name": "driftschef Allan Bergqvist",
                    "position": null
                },
                {
                    "name": "frk Ann-Helen Blomberg",
                    "position": null
                },
                {
                    "name": "fru Margit Hörnfeldt",
                    "position": null
                },
                {
                    "name": "dir Carl-Eric Wahlbeck",
                    "position": null
                }
            ],
            "establishment_year": 1918
        },
        "9": {
            "company_name": "vacuum-extractor, ab",
            "pnr": "403 14",
            "address": "Göteborg 2, Box 2213, Drottningg 13",
            "phone_number": "031-17 0740",
            "bank_details": {
                "bankgiro": "50-0737",
                "postgiro": "428441"
            },
            "activity": "Tillverkare o ensamförsäljare av specialinstrument för gynekologi o obstetrik",
            "employees": 5,
            "annual_turnover": 1000000,
            "capital": 5000,
            "key_personnel": {
                "name": "Verkst din Göran O Uddenberg"
            },
            "establishment_year": 1954
        },
        "10": {
            "company_name": "vadstena byggnads-snickerier, ab",
            "pnr": "592 00",
            "address": "Vadstena, Industriv",
            "phone_number": "0143-10178, 102 68",
            "bank_details": {
                "bankgiro": "127-0511",
                "postgiro": "74416-9"
            },
            "activity": "Tillverkar byggnadssnickerier. Säljer trävaror",
            "employees": 25,
            "annual_turnover": 2500000,
            "capital": 20000,
            "key_personnel": {
                "name": "Ryno Edvardsson"
            },
            "establishment_year": 1925
        },
        "11": {
            "company_name": "vadstena metall-gjuteri, ab",
            "pnr": "592 00",
            "address": "Vadstena, Strandpromenaden, Box 5",
            "phone_number": "0143-10210",
            "bank_details": {
                "postgiro": "326110-4"
            },
            "activity": "Tillverkar metallgjut-gods",
            "capital": 5000,
            "key_personnel": {
                "name": "Ing Nils Engström"
            },
            "establishment_year": 1946
        },
        "12": {
            "company_name": "WENNERLUNDS MASKIN AB",
            "pnr": "41134",
            "address": "Göteborg, Götabergs g 28",
            "phone_number": "031-1664 14, 20 3032",
            "bank_details": {
                "bankgiro": "510-7214",
                "postgiro": "43874-7"
            },
            "activity": "Alla typer av flata drivremmar, rundremmar o transportband i moderna material",
            "employees": 0,
            "capital": 10000,
            "key_personnel": {
                "name": "Verkst din Owe Björklund"
            },
            "establishment_year": 1932
        },
        "13": {
            "company_name": "LJUNGBERG & CO AB, KARL",
            "pnr": "281 01",
            "address": "Hässleholm 1, Första Avenyen 1, Box 8",
            "phone_number": "0451-143 00",
            "bank_details": {
                "bankgiro": "27-0 1 38",
                "postgiro": "293770"
            },
            "activity": "Grossiströrelse med wallboard, plywood o spånplattor. Projekterar o säljer kompletta bandsågverk o såglinjer. Säljer tunga bandsågar för sågverk o hyvlerier",
            "capital": 250000,
            "key_personnel": [
                {
                    "name": "Karl Ljungberg",
                    "position": null
                },
                {
                    "name": "Kaj Ljungberg",
                    "position": null
                }
            ]
        },
        "14": {
            "company_name": "LJUNGBERG & CO, AB LARS",
            "pnr": "115 26",
            "address": "Stockholm NO, Gyllenstiernsg 18",
            "phone_number": "08-63 58 70",
            "bank_details": {
                "bankgiro": "73-0743",
                "postgiro": "507999"
            },
            "activity": "Säljer elektromedi-cinska instrument",
            "key_personnel": {
                "name": "Civilekonom Lars Ljungberg"
            },
            "establishment_year": 1955
        },
        "15": {
            "company_name": "LJUNGBERGS LÄDERFABRIK, AB N H",
            "pnr": "500 06",
            "address": "Boiås 6, Gässlösav 28, Box 66091",
            "phone_number": "033-1277 60",
            "bank_details": {
                "bankgiro": "53-1211",
                "postgiro": "33786"
            },
            "activity": "Tillverkar lädervaror, skodon o tofflor",
            "employees": 110,
            "annual_turnover": 9000000,
            "capital": 2331000,
            "key_personnel": {
                "name": "g Rangert"
            },
            "establishment_year": 1916
        },
        "16": {
            "company_name": "LJUNGBERG, BYGGNADS AB TAGE",
            "pnr": "113 59",
            "address": "Stockholm, Kungstensg 57",
            "phone_number": "08-34 07 30",
            "bank_details": {
                "bankgiro": "447-0381",
                "postgiro": "258711-1"
            },
            "activity": "Bygger flerfamiljshus, villor, fabriksbyggnader samt utför ombyggnadsarbeten",
            "employees": 80,
            "annual_turnover": 7000000,
            "capital": 100000,
            "key_personnel": {
                "name": "Byggn-ing Tage Ljungberg"
            },
            "establishment_year": 1946
        },
        "17": {
            "company_name": "LJUNGBERGS MEK VERKSTAD AB, W",
            "pnr": "55102",
            "address": "Jönköping 1, Kämpev 6, Box 436",
            "phone_number": "036-11 14 81, 1217 20",
            "bank_details": {
                "bankgiro": "341-9496",
                "postgiro": "160550-0"
            },
            "activity": "Tillverkar lekplatsut-rustningar, parksoffor, cykelställ, mattpiskställ, rörverktyg, rensverktyg, lyftverktyg m m",
            "employees": 35,
            "annual_turnover": 2000000,
            "capital": 61000,
            "key_personnel": {
                "name": "Bertil Ljungberg"
            },
            "establishment_year": 1945
        },
        "18": {
            "company_name": "ANDRÉN AB, BO",
            "pnr": "19147",
            "address": "Sollentuna, Industriv 16, Tureberg",
            "phone_number": "08-35 27 50",
            "activity": "Import o grosshandel i lövträ, fanér, plywood, lamell- o spånskivor",
            "employees": 25,
            "capital": 500000,
            "key_personnel": {
                "name": "Bo Andrén"
            },
            "establishment_year": 1942
        },
        "19": {
            "company_name": "gällstads ylle, ab",
            "pnr": "520 10",
            "address": "GäUstad, Box 48",
            "phone_number": "0321-712 80",
            "bank_details": {
                "bankgiro": "840-6480",
                "postgiro": "323199-0"
            },
            "activity": "Modevaror i acryl",
            "employees": 25,
            "annual_turnover": 2000000,
            "capital": 45000,
            "key_personnel": {
                "name": "Fabr Martin Göthager"
            },
            "establishment_year": 1946
        },
        "20": {
            "company_name": "INFORMATIONS TV AB",
            "pnr": "21748",
            "address": "Malmö, Regementsg 52 C",
            "phone_number": "040-756 25",
            "bank_details": {
                "bankgiro": "640-4800"
            },
            "activity": "Intern television för bostadsområden o travbanor",
            "employees": 28,
            "annual_turnover": 600000,
            "capital": 125000,
            "key_personnel": {
                "name": "Verkst dlr Carl-Erik Tornheden"
            },
            "establishment_year": 1961
        },
        "21": {
            "company_name": "IGGESUNDS BRUK, AB",
            "pnr": "825 00",
            "address": "Iggesund",
            "phone_number": "0650-208 00",
            "bank_details": {
                "bankgiro": "99-1249",
                "postgiro": "76700"
            },
            "activity": "Skogsbruk samt tillverkning av cellulosa, homogen kartong, trävaror, sågblad, hugg-maskinknivar, barkverktyg, Stamick postningssystem",
            "employees": 3500,
            "capital": 140000000,
            "key_personnel": {
                "name": "Lars G Sundblad"
            },
            "establishment_year": 1685
        }
    }
}