{
    "original": "ROSTFRIA SKYLTAR, AB\n\nPnr 802 22\n\nGävle, S Känslig 8. Tel 026-127301\nVerksamhet: Tillverkar graverade\nskyltar\n\nEtableringsår 1947.\n\nBULO-BOLAGET AB\n\nPnr 102 61\n\nStockholm 4, Box 4004. Asög\n113-119. Tel 08-44 0235. Bankgiro\n570-4408. Postgiro 197370-4\nVerksamhet: Tillverkar o säljer\nVerksamhet: Plastdetaljer för\nbyggnadsindustrien\nAntal anställda: 8\nÅrsomsättning: 1200 000\nAktiekapital: 5 000\nVerkst din Rune Lodén\nEtableringsår: 1964.\n\nKODAK AB\n\nPnr 431 20\n\nMölndal 1, Flöjelbergsg 8 B. Fack.\nTel 031-87 00 60. Bankgiro\n500-0195. Postgiro 12388-5. Tga Kodak.\nTelex 20687\n\nVerksamhet: Fotografiska artiklar\nAktiekapital: 1800 000\nVeikst dir: T F Cannon.\n\nKOGES DEKORATIONS.\nATELJE\n\nPnr 552 40\n\nJönköping, Museig 5. Tel\n036-113256. Bankgiro 14-0235.\nPostgiro 145677-1\n\nVerksamhet: Ombesörjer all reklam\nsåsom dekorationer, skyltar i\nolika utföranden, utställningar på\nmässor o dyl såväl i Sverige som\ni utlandet. Teckningar, logotypes,\nsilksreentryck m m\nAntal anställda: 6\nÅrsomsättning: 500 000\nChef: Karl-Olof Gustavson\nAteljéchef: Ingvar Alfredsson\nEtableringsår: 1939.\n\nTIBRO BYGGVAROR AB\n\nPnr 543 01\n\n11 bro 1. Box 29. Polhemsg 16. Tel\n0504-116 75. Bankgiro 585-3122.\nPostgiro 298760-0\nVerksamhet: Säljer trävaror o\nbyggnadsmaterial\nAntal anställda: 8\nÅrsomsättning: 2500 000\nAktiekapital: 50 000\nVerkst dir: Sigge Andersson\nEtableringsår: 1967.\n\nFREJS BAKELITINDUSTRI, AB\n\nPnr 332 00\n\nGislaved, Filarg 14. Box 118. Tel\n0371-105 96. Bankgiro 426-7183.\nPostgiro 14455-0\n\nVerksamhet: Formsprutning o\npressning av hårdplast\n\nÄgare: Enoc Svensson, John\nSvensson\n\nEtableringsår: 1946.\n\nWALLIN AB, C A\n\nPnr 116 46\n\nStockholm, Katarinav 20. Tel\n08-40 9182, 40 9183. Bankgiro\n330-2189. Postgiro 506445-6\nVerksamhet: Säljbolag för\nutländska fabriker\nAntal anställda: 9\nAktiekapital: 10 000\nVerkst din Carl-Arne Wallin\nEtableringsår: 1946.\n\nWALLIN AB,\nBYGGNADSFIRMAN ERIK\n\nPnr 112 39\n\nStockholm K, Sankt Eriksg 29. Tel\n08-50 50 69, 50 50 79. Postgiro\n195933\n\nVerksamhet: Hus- o\nindustribyggnader\n\nAntal anställda: 25\nÅrsomsättning: 2 000 000\nAktiekapital: 120 000\nVerkst dir: Ing Erik Wallin\nEtableringsår: 1946.\n\nWALLIN, BIL AB KARL\n\nPnr 641 00\n\nKatrineholm, Djulög 37. Box 5. Tel\n0150-100 54, 100 55. Bankgiro\n617-1235. Postgiro 295288-5\nVerksamhet: Säljer bilar\nAntal anställda: 15\nÅrsomsättning: 4 000 000\nAktiekapital: 50 000\nVeikst dir: Karl Wallin\nEtableringsår: 1946.\n\nWALLIT, AB\n\nPnr 113 59\n\nStockholm, Tegnérg 34. Tel\n08-34 98 80. Tga Wallit\nVerksamhet Trähusfabrik,\npaviljonger o liknande\nAntal anställda: 165\nÅrsomsättning: 18 000 000\nAktiekapital: 1250 000\nVeikst dir: Ivan Oresjö\nEtableringsår: 1946.\n\nWALLQVIST &amp; JANSSON AB,\nBYGGNADSFIRMA\n\nPnr 590 30\n\nBorensberg, Norrbyg 3. Pack. Tel\n0141-401 24. 404 54. Bankgiro\n13-4402. Postgiro 29855\nVerksamhet: Entreprenader av\nbostadshus, skolor o industrier\nAntal anställda: 45\nÅrsomsättning: 3 000 000\nAktiekapital: 40000\nVerkst dir: Byggnadsing SBR Lars\nWallqvist\n\nEtableringsår: 1936.\n\nWALLQVISTS EL\nLINDAREVERKSTAD AB. C A\n\nPnr 11136\n\nStockholm, Holländarg 18. Tel\n08-2118 06, 2117 06. Bankgiro\n73-0507. Postgiro 53323. Tga\nCegeweab\n\nVerksamhet: Säljer motorer o\nmaskiner, reparationer, reservdelar\nAntal anställda: 15\nÅrsomsättning: 1000 000\nAktiekapital: 80 000\nVerkst dir: C G Wallqvist\nEtableringsår: 1919\nOmbildat till aktiebolag 1960.\n\nWALLMAN &amp; CO, AB N G\n\nPnr 11230\n\nStockholm, Celsiusg 4. Tel\n08-50 39 07, 52 97 98. Bankgiro\n44-6831. Postgiro 503650. Tga\nWall-manco\n\nVerksamhet: Säljer\nindustrikemikalier o skyltar\n\nVarunam: Gap, Kåbex, Kåbexol,\nNiwapan, Niwasan\nÅrsomsättning: 1000 000\nAktiekapital: 25 000\nVerkst dir: Nils G Wallman\nEtableringsår: 1953.\n\nPORTIA AB\n\nPnr 21152\n\nMalmö, Skolg 8. Tel 040-738 90.\nBankgiro 26-4282. Postgiro 24409.\nTga Portia\n\nVerksamhet: Tillverkar slipsar,\nhängslen, bälten o scarves\nVarunamn: Portia\nAntal anställda: 50\nAktiekapital: 300 000\nVerkst dir Bertil Åkesson\nEtableringsår: 1924\nOmbildat till aktiebolag 1945.\n\nPORTSTROMS\nSMIDES-VERKSTAD\n\nPnr 80104\n\nGävle 1, Box 315. Upplandsg 9. Tel\n026-12 94 45. Bankgiro 237-2613.\nPostgiro 568637-3\nVerksamhet: Smidesarbeten o\nreparationer\n\nAntal anställda: 15\nÅrsomsättning: 800000\nEtableringsår: 1918.\n\nPOSTMAN MODERN METALL\nAB\n\nPnr 17171\n\nSolna, Ulriksdalsv. Jakobsdal. Tel\n08-85 03 25. Bankgiro 56-7509.\nPostgiro 195550\n\nVerksamhet: VVS-grossist. Säljer\nrostfria artiklar, pumpar o teknisk\narmatur m m\n\nÅrsomsättning: 1500 000\nAktiekapital: 50000\nVerkst dir: Curt Byrman\nEtableringsår: 1948.\n\nPERGOLA FARMACEVTISKA\nPRODUKTER AB\n\nPnr 11456\n\nStockholm, Strandv 17. Tel\n08-67 57 28. Bankgiro 16-0676.\nPostgiro 257750-0. Tga Al ogrep\nVerksamhet: Säljer läkemedel\nAktiekapital: 10 000\nVerkst dlr: Jacques Pergola\nEtableringsår: 1954.\n\nOLSEN AB, TRYGVE\n\nPnr 50005\n\nBorås 5, Box 55026. Femte Villag\n22. Tel 03 3-12 0 0 80, 12 97 67,\n91935. Bankgiro 531-4992. Postgiro\n21104-5. Tga Lidim\n\nGeneralagent för\nOY GLENOIT &amp; LILLJA AB\nTRAVIS FABRICS INC. N.Y.\nTIKKURILA OY FINLAND\n\nVerksamhet: Textilagentur,\nförsäljning av metervaror till\nkonfektio-närer o grossister\nÅrsomsättning: 4 000 000\nAktiekapital: 5 000\nVerkst dir: Tryggve Olsen\nEtableringsår: 1962.\n\nOLSSON, OLSON, OHLSSON,\nOHLSON\n\nOLSSON &amp; BERGGREN\nSHIPPING AB\n\nPnr 15102\n\nSödertälje 2, Box 2021. Sydhamnen.\nTel 0755-602 90. Bankgiro\n170-6415. Postgiro 390950-4. Tga\nShip-son. Telex 1266\nVerksamhet: Skeppsklarering o\nspedition\n\nAktiekapital: 120000\nVerkst dir: Axel B Backman\nEtableringsår: 1956.\n\nESKILSTUNA\nELEKTRO-FABRIKS AB\n\nPnr 631 03\n\nEskilstuna 1, Gillbergav 4. Box\n200. Tel 016-134600. Bankgiro\n82-8019. Postgiro 277865\nVerksamhet: Tillverkar elektr\nbelysningsarmatur\nVerkst dlr: K G Lorentzon\nEtableringsår: 1944.\n\nESKILSTUNA\nFABRIKSAKTIEBOLAG\n\nPnr 631 04\n\nEskilstuna 1, Box 204. Kungsg 41.\nFusionerades hösten 1970 med\nBulten-Kanthal AB.\nSe i övrigt Bulten-Kanthal AB,\n\nKedjedivisionen.\n\nESKILSTUNA\nFASTIGHETS-SERVICE, AB\n\nPnr 632 20\n\nEskilstuna. Smedjeg 25. Tel\n016-1200 90. Bankgiro 600-9807.\nPostgiro 298825-1\n\nVerksamhet:\nFastighetsreparaktioner, fastighetsförvaltning,\nombyggnader o villabyggnationer\nAntal anstäUda: 15\nÅrsomsättning: 1000 000\nAktiekapital: 5 000\nStyrelse: Byggmäst Göte Eriksson\n(ordf), ing Percy Hagman, kamrer\nBo Ericson, fru Tora Eriksson\nVerkst dir: Byggmäst Göte Eriksson\nArbetschef: P Hagman\nEkonomi o kamerala avd:\nKamrer Bo Ericson\nEtableringsår: 1963.",
    "structured": {
        "1": {
            "company_name": "ROSTFRIA SKYLTAR, AB",
            "pnr": "802 22",
            "address": "Gävle, S Känslig 8",
            "phone_number": "026-127301",
            "activity": "Tillverkar graverade skyltar",
            "establishment_year": 1947
        },
        "2": {
            "company_name": "BULO-BOLAGET AB",
            "pnr": "102 61",
            "address": "Stockholm 4, Box 4004. Asög 113-119",
            "phone_number": "08-44 0235",
            "bank_details": {
                "bankgiro": "570-4408",
                "postgiro": "197370-4"
            },
            "activity": "Tillverkar o säljer plastdetaljer för byggnadsindustrien",
            "employees": 8,
            "annual_turnover": 1200000,
            "capital": 5000,
            "key_personnel": [
                {
                    "name": "Rune Lodén",
                    "position": "Verkst din"
                }
            ],
            "establishment_year": 1964
        },
        "3": {
            "company_name": "KODAK AB",
            "pnr": "431 20",
            "address": "Mölndal 1, Flöjelbergsg 8 B. Fack",
            "phone_number": "031-87 00 60",
            "bank_details": {
                "bankgiro": "500-0195",
                "postgiro": "12388-5"
            },
            "activity": "Fotografiska artiklar",
            "capital": 1800000,
            "key_personnel": [
                {
                    "name": "T F Cannon",
                    "position": "Veikst dir"
                }
            ],
            "establishment_year": 0
        },
        "4": {
            "company_name": "KOGES DEKORATIONS. ATELJE",
            "pnr": "552 40",
            "address": "Jönköping, Museig 5",
            "phone_number": "036-113256",
            "bank_details": {
                "bankgiro": "14-0235",
                "postgiro": "145677-1"
            },
            "activity": "Ombesörjer all reklam såsom dekorationer, skyltar i olika utföranden, utställningar på mässor o dyl såväl i Sverige som i utlandet. Teckningar, logotypes, silksreentryck m m",
            "employees": 6,
            "annual_turnover": 500000,
            "key_personnel": [
                {
                    "name": "Karl-Olof Gustavson",
                    "position": "Chef"
                },
                {
                    "name": "Ingvar Alfredsson",
                    "position": "Ateljéchef"
                }
            ],
            "establishment_year": 1939
        },
        "5": {
            "company_name": "TIBRO BYGGVAROR AB",
            "pnr": "543 01",
            "address": "11 bro 1, Box 29. Polhemsg 16",
            "phone_number": "0504-116 75",
            "bank_details": {
                "bankgiro": "585-3122",
                "postgiro": "298760-0"
            },
            "activity": "Säljer trävaror o byggnadsmaterial",
            "employees": 8,
            "annual_turnover": 2500000,
            "capital": 50000,
            "key_personnel": [
                {
                    "name": "Sigge Andersson",
                    "position": "Verkst dir"
                }
            ],
            "establishment_year": 1967
        },
        "6": {
            "company_name": "FREJS BAKELITINDUSTRI, AB",
            "pnr": "332 00",
            "address": "Gislaved, Filarg 14. Box 118",
            "phone_number": "0371-105 96",
            "bank_details": {
                "bankgiro": "426-7183",
                "postgiro": "14455-0"
            },
            "activity": "Formsprutning o pressning av hårdplast",
            "establishment_year": 1946
        },
        "7": {
            "company_name": "WALLIN AB, C A",
            "pnr": "116 46",
            "address": "Stockholm, Katarinav 20",
            "phone_number": "08-40 9182, 40 9183",
            "bank_details": {
                "bankgiro": "330-2189",
                "postgiro": "506445-6"
            },
            "activity": "Säljbolag för utländska fabriker",
            "employees": 9,
            "capital": 10000,
            "key_personnel": [
                {
                    "name": "Carl-Arne Wallin",
                    "position": "Verkst dir"
                }
            ],
            "establishment_year": 1946
        },
        "8": {
            "company_name": "WALLIN AB, BYGGNADSFIRMAN ERIK",
            "pnr": "112 39",
            "address": "Stockholm K, Sankt Eriksg 29",
            "phone_number": "08-50 50 69, 50 50 79",
            "postgiro": "195933",
            "activity": "Hus- o industribyggnader",
            "employees": 25,
            "annual_turnover": 2000000,
            "capital": 120000,
            "key_personnel": [
                {
                    "name": "Ing Erik Wallin",
                    "position": "Verkst dir"
                }
            ],
            "establishment_year": 1946
        },
        "9": {
            "company_name": "WALLIN, BIL AB KARL",
            "pnr": "641 00",
            "address": "Katrineholm, Djulög 37. Box 5",
            "phone_number": "0150-100 54, 100 55",
            "bank_details": {
                "bankgiro": "617-1235",
                "postgiro": "295288-5"
            },
            "activity": "Säljer bilar",
            "employees": 15,
            "annual_turnover": 4000000,
            "capital": 50000,
            "key_personnel": [
                {
                    "name": "Karl Wallin",
                    "position": "Veikst dir"
                }
            ],
            "establishment_year": 1946
        },
        "10": {
            "company_name": "WALLIT, AB",
            "pnr": "113 59",
            "address": "Stockholm, Tegnérg 34",
            "phone_number": "08-34 98 80",
            "activity": "Trähusfabrik, paviljonger o liknande",
            "employees": 165,
            "annual_turnover": 18000000,
            "capital": 1250000,
            "key_personnel": [
                {
                    "name": "Ivan Oresjö",
                    "position": "Veikst dir"
                }
            ],
            "establishment_year": 1946
        },
        "11": {
            "company_name": "WALLQVIST & JANSSON AB, BYGGNADSFIRMA",
            "pnr": "590 30",
            "address": "Borensberg, Norrbyg 3",
            "phone_number": "0141-401 24. 404 54",
            "bank_details": {
                "bankgiro": "13-4402",
                "postgiro": "29855"
            },
            "activity": "Entreprenader av bostadshus, skolor o industrier",
            "employees": 45,
            "annual_turnover": 3000000,
            "capital": 40000,
            "key_personnel": [
                {
                    "name": "Lars Wallqvist",
                    "position": "Verkst dir"
                }
            ],
            "establishment_year": 1936
        },
        "12": {
            "company_name": "WALLQVISTS EL LINDAREVERKSTAD AB. C A",
            "pnr": "11136",
            "address": "Stockholm, Holländarg 18",
            "phone_number": "08-2118 06, 2117 06",
            "bank_details": {
                "bankgiro": "73-0507",
                "postgiro": "53323"
            },
            "activity": "Säljer motorer o maskiner, reparationer, reservdelar",
            "employees": 15,
            "annual_turnover": 1000000,
            "capital": 80000,
            "key_personnel": [
                {
                    "name": "C G Wallqvist",
                    "position": "Verkst dir"
                }
            ],
            "establishment_year": 1919
        },
        "13": {
            "company_name": "WALLMAN & CO, AB N G",
            "pnr": "11230",
            "address": "Stockholm, Celsiusg 4",
            "phone_number": "08-50 39 07, 52 97 98",
            "bank_details": {
                "bankgiro": "44-6831",
                "postgiro": "503650"
            },
            "activity": "Säljer industri-kemikalier o skyltar",
            "varunam": "Gap, Kåbex, Kåbexol, Niwapan, Niwasan",
            "annual_turnover": 1000000,
            "capital": 25000,
            "key_personnel": [
                {
                    "name": "Nils G Wallman",
                    "position": "Verkst dir"
                }
            ],
            "establishment_year": 1953
        },
        "14": {
            "company_name": "PORTIA AB",
            "pnr": "21152",
            "address": "Malmö, Skolg 8",
            "phone_number": "040-738 90",
            "bank_details": {
                "bankgiro": "26-4282",
                "postgiro": "24409"
            },
            "activity": "Tillverkar slipsar, hängslen, bälten o scarves",
            "varunamn": "Portia",
            "employees": 50,
            "capital": 300000,
            "key_personnel": [
                {
                    "name": "Bertil Åkesson",
                    "position": "Verkst dir"
                }
            ],
            "establishment_year": 1924
        },
        "15": {
            "company_name": "PORTSTROMS SMIDES-VERKSTAD",
            "pnr": "80104",
            "address": "Gävle 1, Box 315. Upplandsg 9",
            "phone_number": "026-12 94 45",
            "bank_details": {
                "bankgiro": "237-2613",
                "postgiro": "568637-3"
            },
            "activity": "Smidesarbeten o reparationer",
            "employees": 15,
            "annual_turnover": 800000,
            "establishment_year": 1918
        },
        "16": {
            "company_name": "POSTMAN MODERN METALL AB",
            "pnr": "17171",
            "address": "Solna, Ulriksdalsv. Jakobsdal",
            "phone_number": "08-85 03 25",
            "bank_details": {
                "bankgiro": "56-7509",
                "postgiro": "195550"
            },
            "activity": "VVS-grossist. Säljer rostfria artiklar, pumpar o teknisk armatur m m",
            "annual_turnover": 1500000,
            "capital": 50000,
            "key_personnel": [
                {
                    "name": "Curt Byrman",
                    "position": "Verkst dir"
                }
            ],
            "establishment_year": 1948
        },
        "17": {
            "company_name": "PERGOLA FARMACEVTISKA PRODUKTER AB",
            "pnr": "11456",
            "address": "Stockholm, Strandv 17",
            "phone_number": "08-67 57 28",
            "bank_details": {
                "bankgiro": "16-0676",
                "postgiro": "257750-0"
            },
            "activity": "Säljer läkemedel",
            "capital": 10000,
            "key_personnel": [
                {
                    "name": "Jacques Pergola",
                    "position": "Verkst dlr"
                }
            ],
            "establishment_year": 1954
        },
        "18": {
            "company_name": "OLSEN AB, TRYGVE",
            "pnr": "50005",
            "address": "Borås 5, Box 55026. Femte Villag 22",
            "phone_number": "033-120080, 129767, 91935",
            "bank_details": {
                "bankgiro": "531-4992",
                "postgiro": "21104-5"
            },
            "activity": "Textilagentur, försäljning av metervaror till konfektio-närer o grossister",
            "annual_turnover": 4000000,
            "capital": "5000",
            "key_personnel": [
                {
                    "name": "Tryggve Olsen",
                    "position": "Verkst dir"
                }
            ],
            "establishment_year": 1962
        },
        "19": {
            "company_name": "OLSSON, OLSON, OHLSSON, OHLSON OLSSON & BERGGREN SHIPPING AB",
            "pnr": "15102",
            "address": "Södertälje 2, Box 2021. Sydhamnen",
            "phone_number": "0755-602 90",
            "bank_details": {
                "bankgiro": "170-6415",
                "postgiro": "390950-4"
            },
            "activity": "Skeppsklarering o spedition",
            "capital": 120000,
            "key_personnel": [
                {
                    "name": "Axel B Backman",
                    "position": "Verkst dir"
                }
            ],
            "establishment_year": 1956
        },
        "20": {
            "company_name": "ESKILSTUNA ELEKTRO-FABRIKS AB",
            "pnr": "631 03",
            "address": "Eskilstuna 1, Gillbergav 4. Box 200",
            "phone_number": "016-134600",
            "bank_details": {
                "bankgiro": "82-8019",
                "postgiro": "277865"
            },
            "activity": "Tillverkar elektr belysningsarmatur",
            "key_personnel": [
                {
                    "name": "K G Lorentzon",
                    "position": "Verkst dlr"
                }
            ],
            "establishment_year": 1944
        },
        "21": {
            "company_name": "ESKILSTUNA FABRIKSAKTIEBOLAG",
            "pnr": "631 04",
            "address": "Eskilstuna 1, Box 204. Kungsg 41",
            "activity": "Fusionerades hösten 1970 med Bulten-Kanthal AB. Se i övrigt Bulten-Kanthal AB, Kedjedivisionen"
        },
        "22": {
            "company_name": "ESKILSTUNA FASTIGHETS-SERVICE, AB",
            "pnr": "632 20",
            "address": "Eskilstuna, Smedjeg 25",
            "phone_number": "016-1200 90",
            "bank_details": {
                "bankgiro": "600-9807",
                "postgiro": "298825-1"
            },
            "activity": "Fastighetsreparaktioner, fastighetsförvaltning, ombyggnader o villabyggnationer",
            "employees": 15,
            "annual_turnover": 1000000,
            "capital": 5000,
            "key_personnel": [
                {
                    "name": "Byggmäst Göte Eriksson",
                    "position": "Styrelse: Byggmäst Göte Eriksson (ordf), ing Percy Hagman, kamrer Bo Ericson, fru Tora Eriksson"
                }
            ],
            "establishment_year": 1963
        }
    }
}