{
    "original": "COMO MASKIN AB\n\nPnr 342 00\n\nAlvesta, Industrig 13. Tel\n0472-112 10. Bankgiro 848-1053.\nPostgiro 101699-7. Tga Comographic\nVerksamhet: Tillverkar\nskärmaskiner för den grafiska industrien\nAntal anställda: 50\nAktiekapital: 100 000\nVerkst dir: Ake Gadler.\n\nCOMPOMAC, AB\n\nPnr 100 54\n\nStockholm 39, Box 39011.\nMid-skogsgränd 11. Tel 08-23 42 90.\nPostgiro 356941\n\nVerksamhet: Tillverkar\nasfaltemulsion för vägbeläggningsändamål\nAntal anställda: 4\nÅrsomsättning: 600 000\nAktiekapital: 300 000\nVerkst dir: Gunnar Hazén\nEtableringsår: 1949.\n\nCOMP -\nTEXSTRUMPFABRIK, AB\n\nPnr 502 34\n\nBorås, Skarabcrgsv 9. Tel\n033-1153 30. Bankgiro 531-7748.\nPostgiro 441612-9\n\nVerksamhet: Tillverkar o säljer\nherr, barn- o damstrumpor\nAntal anställda: 10\nÅrsomsättning: 480000\nAktiekapital: 5 000\nVerkst dir: Carl Erie Carlsson\nEtableringsår: 1963.\n\nCOMPUTER SYSTEMS\nINTERNATIONAL (CSI) AB\n\nPnr 182 11\n\nDanderyd 1, Mysingsv 5. Box 82.\nTel 08-753 03 00. Bankgiro 17-1281.\nPostgiro 674 6 28. Tga\nComputer-system, Stockholm\nVerksamhet: Systemutveckling o\nprogrammering\nAntal anställda: 45\nÅrsomsättning: 2 600 000\nAktiekapital: 10 000\nVerkst dir: Sven Davidson\nEtableringsår: 1965.\n\nKULLBERG-MR, FRED\n\nPnr 114 24\n\nStockholm, Karlav 7. Tel\n08-11 34 01. Postgiro 294363\nVerksamhet: Utför takbeläggningar\no isoleringar\nChef: Fred Kullberg\nEtableringsår: 1935.\n\nMAG\n\nM\n\nMAB och MYA AB\n\nPnr 200 70\n\nMalmö 5, Pack. Rönneholmsv 38.\nTel 040-714 30. Bankgiro 640-1632.\nPostgiro 39345-4. Tga Mabim\nVerksamhet: Mab o Mya AB\ndriver tillverkning av vävburen plast\no laminerade produkter i Furulund\nVarunamn: Maborex\nAntal anställda: 100\nAktiekapital: 11200 000\nStyrelse: Adv Sten Sandell (ordf),\ndir Claes Lindskog, dir Sigge\nUlfsparre, hovrättsassessor Carl H\nBergh, dir C A Frick, bergsing\nGunnar Edstrand, civilekonom Olof\nForsgrén\n\nVerkst dir: C A Frick\nEtableringsår: 1855\nDotterbolag: MMT Tricot AB o\nMaborex AB.\n\nMABU MASKINFIRMAN\nHANS BAUER AB\n\nPnr 302 37\n\nHalmstad, Sunnanv 4. Tel 035-\n\n121024,121002. Bankgiro\n423-5099. Postgiro 360137-4\nVerksamhet: Tillverkar o säljer\nmaskiner o verktyg för\nglasindustrin\n\nÅrsomsättning: 1000 000\nÄgare o chef: Hans Bauer\nEtableringsår: 1953.\n\nMABÄCKERS SPIKSMIDE,\nHENRY\n\nPnr 660 06\n\nBäckefors, Postl 317. Tel\n0530-60144. Postgiro 268267\nVerksamhet: Tillverkar\nhandsmidda ek- o dekorationsspik\nChef: Henry Mabäcker\nEtableringsår: 1919.\n\nMACHINERY AND GEARS\nHANSEN NORD AB\nMGH-NORD\n\nPnr 10125\n\nStockholm 1, Box 404. Barnhusg 22.\nTel 08-24 31 20. Bankgiro 92-5082.\nPostgiro 654132. Tga Emgehonord.\nTelex 17132 HANSUN S\nVerksamhet: Säljer\ntransmissionselement, kopplingar m m\nVarunamn: Debex, Hansen Patent,\nHydro-Flow, Penco, Texrope,\nVari-Phi\n\nAktiekapital: 100000\nVerkst dir: Lars Ericsson\nEtableringsår: 1969.\n\nMACTAC INTERNATIONAL\nLTD INC USA FILIAL\n\nPnr 20013\n\nMalmö 27, Box 27092. Hemsög. Tel\n040-18 08 30. Bankgiro 154-2000.\nPostgiro 637701-4. Tga Mactac\nVerksamhet: Säljer självhäftande\nmaterial för grafisk o övrig industri,\nsjukhus o\n\"gör-det-själv\"-marknaden\nVarunamn: Mactac\nVerkst dir: Arne Nyqvist\nEtableringsår: 1968.\n\nLIN\n\n13 00 40. Bankgiro 61-4350.\nPostgiro 449232. Tga Linco\nVerksamhet: Armerade plastslangar\nav alla slag, nylonslang även\nsjälvrullande, slangarmatur\nVerkst dir: Hans Lindgren\nEtableringsår: 1954\nOmbildat till aktiebolag 1961.\n\nLINDGREN AB, LAMBERT\n\nPnr 11146\n\nStockholm, Norrmalmstorg 1-5 A.\nTel 08-1188 81, 1188 86. Bankgiro\n73-1719. Postgiro 653380\nVerksamhet: Agentur i trävaror o\nträfiberplattor\nAntal anställda: 4\nÅrsomsättning: 18 000 000\nAktiekapital: 30 000\nVerkst din Lambert Lindgren\nEtableringsår: 1961.\n\nGREBBESTAD BIL &amp; MOTOR\n\nPnr 450 82\n\nHavstenssund. Tel 0525-211 26.\nBankgiro 42-9810. Postgiro 510966\nVerksamhet: Generalagent i Sverige\nför FM o Newage/BMC\nmarinmotorer av såväl förgasare- som\ndiesel-typ, WL länspumpar, tankar o\nbåtventiler. Försäljning o förmedling\nav motorbåtar\n\nVarunamn: BMC (Newage),\nFM-motorn, WL\n\nÅrsomsättning: 900 000\nÄgare o chef: Gösta Hansson\nEtableringsår: 1956.\n\nHEYMAN &amp; HOLMBERG AB\n\nPnr 41138\n\nGöteborg C, Storg 41. Tel\n031-13 08 91, 11 19 85. Tga Heyberg.\nTelex 20695 HEYBERG S\nVerksamhet: Agenturrörelse inom\ntextilbranschen\nAntal anställda: 12\nAktiekapital: 96 000\nChefer: Allan G Johansson.\nPer-Olof Lindblom\nEtableringsår: 1909.\n\nFRÖVI BRANDDORRAR AB\n\nPnr 710 40\n\nFrövi. Tel 0581-30155, 309 55.\nBankgiro 822-6169. Postgiro\n377540-0\n\nVerksamhet: Tillverkar vikportar\no sopskåp\nAntal anställda: 25\nÅrsomsättning: 3 000 000\nAktiekapital: 50 000\nVerkst dir: G Andersson\nEtableringsår: 1949.\n\nFOTOGRAMMETRI BYRÅN AB\n\nPnr 162 03\n\nVällingby 3, Hässelbytorg 10. Box\n307. Tel 08-38 02 70. Bankgiro\n74-5795. Postgiro 118094. Tga\nFotogram\n\nVerksamhet: Kartframställning o\nfältmätning\nAntal anställda: 45\nÅrsomsättning: 3 500 000\nAktiekapital: 300 000\nDir:r: Ing H Persson, ing O\nCarlsson\n\nEtableringsår: 1957.\n\nÅNGTEKNISKA BYRÅN AB\n\nPnr 413 17\n\nGöteborg, Hjorthagsg 10. Tel\n031-42 17 45, 42 17 47. Bankgiro\n364-8979. Postgiro 241289-8\nVerksamhet: Konsulterande\ningenjörsverksamhet inom värme-,\nventilation-, sanitet-, ång- o kylteknik\nAntal anställda: 12\nÅrsomsättning: 650 000\nAktiekapital: 25 000\nStyrelse: Kamrer Elly Wassberg\n(ordf), ing Ingemar Larsson\nVerkst din Ingemar Larsson\nÖvriga chefer: Kamrer Elly\nWassberg\n\nEtableringsår: 1946.\n\nNILSSONS TRÄVARU AB, N P\n\nPnr 260 92\n\nBåstad 2, Box 7. Tel 0431-613 00.\nBankgiro 650-8493. Postgiro 6708-2\nVerksamhet:\nByggnadsmaterialhandel\n\nAntal anställda: 45\nAktiekapital: 200 000\nVerkst dir: Sven-Ake Nidelius\nEtableringsår: 1907.",
    "structured": {
        "1": {
            "company_name": "COMO MASKIN AB",
            "pnr": "342 00",
            "address": "Alvesta, Industrig 13",
            "phone_number": "0472-112 10",
            "bank_details": {
                "bankgiro": "848-1053",
                "postgiro": "101699-7"
            },
            "activity": "Tillverkar skärmaskiner för den grafiska industrien",
            "employees": 50,
            "capital": 100000,
            "key_personnel": [
                {
                    "name": "Ake Gadler",
                    "position": "Verkst dir"
                }
            ],
            "establishment_year": 0
        },
        "2": {
            "company_name": "COMPOMAC, AB",
            "pnr": "100 54",
            "address": "Stockholm 39, Box 39011, Mid-skogsgränd 11",
            "phone_number": "08-23 42 90",
            "postgiro": "356941",
            "activity": "Tillverkar asfaltemulsion för vägbeläggningsändamål",
            "employees": 4,
            "annual_turnover": 600000,
            "capital": 300000,
            "key_personnel": [
                {
                    "name": "Gunnar Hazén",
                    "position": "Verkst dir"
                }
            ],
            "establishment_year": 1949
        },
        "3": {
            "company_name": "COMP - TEXSTRUMPFABRIK, AB",
            "pnr": "502 34",
            "address": "Borås, Skarabcrgsv 9",
            "phone_number": "033-1153 30",
            "bank_details": {
                "bankgiro": "531-7748",
                "postgiro": "441612-9"
            },
            "activity": "Tillverkar o säljer herr, barn- o damstrumpor",
            "employees": 10,
            "annual_turnover": 480000,
            "capital": 5000,
            "key_personnel": [
                {
                    "name": "Carl Erie Carlsson",
                    "position": "Verkst dir"
                }
            ],
            "establishment_year": 1963
        },
        "4": {
            "company_name": "COMPUTER SYSTEMS INTERNATIONAL (CSI) AB",
            "pnr": "182 11",
            "address": "Danderyd 1, Mysingsv 5, Box 82",
            "phone_number": "08-753 03 00",
            "bank_details": {
                "bankgiro": "17-1281",
                "postgiro": "674 6 28"
            },
            "activity": "Systemutveckling o programmering",
            "employees": 45,
            "annual_turnover": 2600000,
            "capital": 10000,
            "key_personnel": [
                {
                    "name": "Sven Davidson",
                    "position": "Verkst dir"
                }
            ],
            "establishment_year": 1965
        },
        "5": {
            "company_name": "KULLBERG-MR, FRED",
            "pnr": "114 24",
            "address": "Stockholm, Karlav 7",
            "phone_number": "08-11 34 01",
            "postgiro": "294363",
            "activity": "Utför takbeläggningar o isoleringar",
            "key_personnel": [
                {
                    "name": "Fred Kullberg",
                    "position": "Chef"
                }
            ],
            "establishment_year": 1935
        },
        "6": {
            "company_name": "MAG M MAB och MYA AB",
            "pnr": "200 70",
            "address": "Malmö 5, Pack. Rönneholmsv 38",
            "phone_number": "040-714 30",
            "bank_details": {
                "bankgiro": "640-1632",
                "postgiro": "39345-4"
            },
            "activity": "Mab o Mya AB driver tillverkning av vävburen plast o laminerade produkter i Furulund",
            "employees": 100,
            "capital": 11200000,
            "key_personnel": [
                {
                    "name": "C A Frick",
                    "position": "Verkst dir"
                }
            ],
            "establishment_year": 1855
        },
        "7": {
            "company_name": "MABU MASKINFIRMAN HANS BAUER AB",
            "pnr": "302 37",
            "address": "Halmstad, Sunnanv 4",
            "phone_number": "035-121024,121002",
            "bank_details": {
                "bankgiro": "423-5099",
                "postgiro": "360137-4"
            },
            "activity": "Tillverkar o säljer maskiner o verktyg för glasindustrin",
            "annual_turnover": 1000000,
            "key_personnel": [
                {
                    "name": "Hans Bauer",
                    "position": "Ägare o chef"
                }
            ],
            "establishment_year": 1953
        },
        "8": {
            "company_name": "MABÄCKERS SPIKSMIDE, HENRY",
            "pnr": "660 06",
            "address": "Bäckefors, Postl 317",
            "phone_number": "0530-60144",
            "postgiro": "268267",
            "activity": "Tillverkar handsmidda ek- o dekorationsspik",
            "key_personnel": [
                {
                    "name": "Henry Mabäcker",
                    "position": "Chef"
                }
            ],
            "establishment_year": 1919
        },
        "9": {
            "company_name": "MACHINERY AND GEARS HANSEN NORD AB MGH-NORD",
            "pnr": "10125",
            "address": "Stockholm 1, Box 404, Barnhusg 22",
            "phone_number": "08-24 31 20",
            "bank_details": {
                "bankgiro": "92-5082",
                "postgiro": "654132"
            },
            "activity": "Säljer transmissionselement, kopplingar m m",
            "capital": 100000,
            "key_personnel": [
                {
                    "name": "Lars Ericsson",
                    "position": "Verkst dir"
                }
            ],
            "establishment_year": 1969
        },
        "10": {
            "company_name": "MACTAC INTERNATIONAL LTD INC USA FILIAL",
            "pnr": "20013",
            "address": "Malmö 27, Box 27092, Hemsög",
            "phone_number": "040-18 08 30",
            "bank_details": {
                "bankgiro": "154-2000",
                "postgiro": "637701-4"
            },
            "activity": "Säljer självhäftande material för grafisk o övrig industri, sjukhus o 'gör-det-själv'-marknaden",
            "key_personnel": [
                {
                    "name": "Arne Nyqvist",
                    "position": "Verkst dir"
                }
            ],
            "establishment_year": 1968
        },
        "11": {
            "company_name": "LIN",
            "address": "13 00 40",
            "bank_details": {
                "bankgiro": "61-4350",
                "postgiro": "449232"
            },
            "activity": "Armerade plastslangar av alla slag, nylonslang även självrullande, slangarmatur",
            "key_personnel": [
                {
                    "name": "Hans Lindgren",
                    "position": "Verkst dir"
                }
            ],
            "establishment_year": 1954
        },
        "12": {
            "company_name": "LINDGREN AB, LAMBERT",
            "pnr": "11146",
            "address": "Stockholm, Norrmalmstorg 1-5 A",
            "phone_number": "08-1188 81, 1188 86",
            "bank_details": {
                "bankgiro": "73-1719",
                "postgiro": "653380"
            },
            "activity": "Agentur i trävaror o träfiberplattor",
            "employees": 4,
            "annual_turnover": 18000000,
            "capital": 30000,
            "key_personnel": [
                {
                    "name": "Lambert Lindgren",
                    "position": "Verkst dir"
                }
            ],
            "establishment_year": 1961
        },
        "13": {
            "company_name": "GREBBESTAD BIL & MOTOR",
            "pnr": "450 82",
            "address": "Havstenssund",
            "phone_number": "0525-211 26",
            "bank_details": {
                "bankgiro": "42-9810",
                "postgiro": "510966"
            },
            "activity": "Generalagent i Sverige för FM o Newage/BMC marinmotorer av såväl förgasare- som diesel-typ, WL länspumpar, tankar o båtventiler. Försäljning o förmedling av motorbåtar",
            "annual_turnover": 900000,
            "key_personnel": [
                {
                    "name": "Gösta Hansson",
                    "position": "Ägare o chef"
                }
            ],
            "establishment_year": 1956
        },
        "14": {
            "company_name": "HEYMAN & HOLMBERG AB",
            "pnr": "41138",
            "address": "Göteborg C, Storg 41",
            "phone_number": "031-13 08 91, 11 19 85",
            "activity": "Agenturrörelse inom textilbranschen",
            "employees": 12,
            "capital": 96000,
            "key_personnel": [
                {
                    "name": "Allan G Johansson.",
                    "position": "Chefer"
                },
                {
                    "name": "Per-Olof Lindblom",
                    "position": "Chefer"
                }
            ],
            "establishment_year": 1909
        },
        "15": {
            "company_name": "FRÖVI BRANDDÖRRAR AB",
            "pnr": "710 40",
            "address": "Frövi",
            "phone_number": "0581-30155, 309 55",
            "bank_details": {
                "bankgiro": "822-6169",
                "postgiro": "377540-0"
            },
            "activity": "Tillverkar vikportar o sopskåp",
            "employees": 25,
            "annual_turnover": 3000000,
            "capital": 50000,
            "key_personnel": [
                {
                    "name": "G Andersson",
                    "position": "Verkst dir"
                }
            ],
            "establishment_year": 1949
        },
        "16": {
            "company_name": "FOTOGRAMMETRI BYRÅN AB",
            "pnr": "162 03",
            "address": "Vällingby 3, Hässelbytorg 10, Box 307",
            "phone_number": "08-38 02 70",
            "bank_details": {
                "bankgiro": "74-5795",
                "postgiro": "118094"
            },
            "activity": "Kartframställning o fältmätning",
            "employees": 45,
            "annual_turnover": 3500000,
            "capital": 300000,
            "key_personnel": [
                {
                    "name": "Ing H Persson",
                    "position": "Dir:r"
                },
                {
                    "name": "ing O Carlsson",
                    "position": "Dir:r"
                }
            ],
            "establishment_year": 1957
        },
        "17": {
            "company_name": "ÅNGTEKNISKA BYRÅN AB",
            "pnr": "413 17",
            "address": "Göteborg, Hjorthagsg 10",
            "phone_number": "031-42 17 45, 42 17 47",
            "bank_details": {
                "bankgiro": "364-8979",
                "postgiro": "241289-8"
            },
            "activity": "Konsulterande ingenjörsverksamhet inom värme-, ventilation-, sanitet-, ång- o kylteknik",
            "employees": 12,
            "annual_turnover": 650000,
            "capital": 25000,
            "key_personnel": [
                {
                    "name": "Kamrer Elly Wassberg",
                    "position": "Styrelse: ordf"
                },
                {
                    "name": "Ingemar Larsson",
                    "position": "Verkst dir"
                }
            ],
            "establishment_year": 1946
        },
        "18": {
            "company_name": "NILSSONS TRÄVARU AB, N P",
            "pnr": "260 92",
            "address": "Båstad 2, Box 7",
            "phone_number": "0431-613 00",
            "bank_details": {
                "bankgiro": "650-8493",
                "postgiro": "6708-2"
            },
            "activity": "Byggnadsmaterialhandel",
            "employees": 45,
            "capital": 200000,
            "key_personnel": [
                {
                    "name": "Sven-Ake Nidelius",
                    "position": "Verkst dir"
                }
            ],
            "establishment_year": 1907
        }
    }
}