{
    "original": "BATTERI-BRANZA AB\n\nPnr 651 07\n\nKarlstad 1, Box 468. Lantvärnsg 8.\nTel 054-1157 60. Bankgiro\n344-4304. Postgiro 264698-2. Tga\nBran-za. Telex 66038 BRANZA S\nVerksamhet: Tillverkar o säljer\nbatterier o startkablar\nFilialer: Solna, Göteborg, Malmö,\nÖrnsköldsvik\nVarunamn: Branza\nAktiekapital: 100000\nVerkst dir: Ing K A Branzell\nEtableringsår: 1961.\n\nPRESKA, AB\n\nPnr 252 31\n\nHelsingborg, Brunnbäcksg 26. Tel\n042-12 91 19. Bankgiro 438-0747.\nPostgiro 80159-7\nVerksamhet: Tillverkar bilkapell\no presenningar samt utför service\nVaiunamn: Preska\nAntal anställda: 9\nÅrsomsättning: 950 000\nAktiekapital: 20 000\nVeikst dir: Elsa Nilsson\nEtableringsår: 1958.\n\nEKSJÖ MÖBELFABRIK, AB\n\nPnr 575 00\n\nEksjö, Box 5. Västerlångg 34. Tel\n0381-107 37, 107 47. Bankgiro\n266-457. Postgiro 91025-7\nVerksamhet: Tillverkar möbler.\nSpecialitet: radio- o TV-möbler\nAntal anställda: 35\nÅrsomsättning: 2000 000\nAktiekapital: 175000\nStyrelseordförande: Dir Folke Rudén\nVerkst dir: Folke Rudén\nEtableringsår: 1931.\n\nDUNDER BYGGNADS AB, AND\n\nPnr 123 53\n\nFarsta, Sköndalsv 89. Tel\n08-93 04 50. Postgiro 55583\nVerksamhet:\nByggnadsentreprenörer\n\nAntal anställda: 60\nÅrsomsättning: 5 000 000\nAktiekapital: 400 000\nVerkst dir: Jan Anders Dunder\nEtableringsår: 1927.\n\nHAGERROT, AB GUNNAR\n\nPnr 20122\n\nMalmö 1, Hans Michelsensg 2. Box\n217. Tel 040-10 0375. Bankgiro\n870-1757, 354-2370. Postgiro\n245970-9. Tga Hagerimport\nVerksamhet: Import o export av\nkonfekt yrer\nAntal anställda: 20\nÅrsomsättning: 15 000 000\nAktiekapital: 1000 000\nVerkst dir: Gunnar Hagerrot\nFörsäljn-chef: Knut Ahlström\nKontorschef: Carl-Erik Lindevi\nEtableringsår: 1943\nDotterbolag: AB Svenska\nChokladförmedlingen, AB Presentchoklad.\n\nHAGLUND &amp; ERICSON BOK.\nTRYCKERI AB\n\nPnr 116 31\n\nStockholm, Rensüernas g 12. Tel\n08-44 06 40. Bankgiro 169-8018.\nPostgiro 54557-4\nVerksamhet: Allt i boktryck,\nbokbinderi o offset\nAntal anställda: 28\nÅrsomsättning: 2 800 000\nAktiekapital: 40000\nVerkst dir: Boktr Sune Haglund\nEtableringsår: 1920.\n\nBYGGNADSTEKNISKA BYRÅN\n\nPnr 41136\n\nGöteborg, Kungsportsavenyn 31-35.\nTel 031-200940. Bankgiro 41-0146.\nPostgiro 428910\n\nVerksamhet: Industriprojektering,\n\nbyggnadskonstruktioner\n\nÄgare o chefer Sten Albrektsson,\n\nGösta Waller, Harald Laursen\n\nEtableringsår: 1910.\n\nBYGG-NATOR, AB\n\nPnt 124 40\n\nBandhagen, Stallarholmsv 37. Tel\n08-8601 80. Bankgiro 577-9525.\nPostgiro 555324-3\nVerksamhet: Utför schakt- o\nsprängningsarbeten för byggnader\nAntal anställda: 30\nÅrsomsättning: 4 000 000\nAktiekapital: 100 000\nVerkst dir: Ing Sigfrid Fransson\nEtableringsår: 1957.\n\nCARMAN TRÄ AB, C A\n\nPnr 591 00\n\nMotala, Prästg 4. Tel 0141-113 40,\n187 40. Bankgiro 82-2062. Postgiro\n92105\n\nVerksamhet: Grossistförsäljning\nav sågade o hyvlade trävaror\nAntal anställda: 3\nAktiekapital: 50 000\nVerkst dir: Bengt Malmberg\nEtableringsår: 1952.\n\nCARNEGIE &amp; CO,\nPORTERBRYGGERI AB D\n\nPnr 402 41\n\nGöteborg 12, Klippg. Box 12006.\nTel 031-1240 00. Tga Porterbola-\n\nget\n\nVerksamhet: Bryggeri o maltfabrik\nAntal anställda: 70\nÅrsomsättning: 17 000 000\nPlatschef: Overing Erik Lindeman\nEtableringsår: 1813.\n\ndalumverken ab\n\nPnr 520 25\n\nDalum, Box 46. Tel 0321-322 40.\nBankgiro 843-3104. Postgiro\n117546-2\n\nVerksamhet: Tillverkar\nljuddämpare o avgasrör för bilar\nAntal anställda: 50\nÅrsomsättning: 4 000 000\nAktiekapital: 75 000\nVerkst dir: Lars Steén\nEtableringsår: 1952.\n\nTERROL, AB\n\nPnr 11135\n\nStockholm, Kungsg 32. Tel\n08-1152 15.Bankgiro 482-4249.\nPostgiro 159301-1. Tga Terrol\nVerksamhet: Säljer smörjmedel o\npresenningar\nAntal anställda: 10\nÅrsomsättning: 2 000 000\nAktiekapital: 60 000\nVerkst dir. Stig Carsing\nEtableringsår: 1945.\n\nGRANROTHS EFTR, H\n\nPnr 21121\n\nMalmö. Gråbrödersg 2. Tel\n040-120110. Tga Xylonite\nVerksamhet: Importagent.\nPlastvaror\n\nChef: E Ehnbom\nEtableringsår: 1948.\n\nGRANRUDS KONSTRUKTIONS.\nBYRÅ AB\n\nPnr 653 40\n\nKarlstad, Malmtorgsg 4. Tel\n054-15 68 50. Bankgiro 100-2468.\nPostgiro 394021-0\n\nVerksamhet: Konstruktioner för\nhus-o industribyggnader. Byggledning,\nbyggkontroll o besiktningar\nAvdelningskontor: 702 32 Örebro,\nIdrottsv 2. Tel 019-18 22 50\nAntal anstäUda: 11\nÅrsomsättning: 700 000\nAktiekapital: 50 000\nVerkst dir: Ing Gösta Granrud\nEtableringsår: 1954.",
    "structured": {
        "1": {
            "company_name": "BATTERI-BRANZA AB",
            "pnr": "651 07",
            "address": "Karlstad 1, Box 468. Lantvärnsg 8.",
            "phone_number": "054-1157 60",
            "bank_details": {
                "bankgiro": "344-4304",
                "postgiro": "264698-2"
            },
            "activity": "Tillverkar o säljer batterier o startkablar",
            "establishment_year": 1961
        },
        "2": {
            "company_name": "PRESKA, AB",
            "pnr": "252 31",
            "address": "Helsingborg, Brunnbäcksg 26",
            "phone_number": "042-12 91 19",
            "bank_details": {
                "bankgiro": "438-0747",
                "postgiro": "80159-7"
            },
            "activity": "Tillverkar bilkapell o presenningar samt utför service",
            "employees": 9,
            "annual_turnover": 950000,
            "capital": 20000,
            "establishment_year": 1958
        },
        "3": {
            "company_name": "EKSJÖ MÖBELFABRIK, AB",
            "pnr": "575 00",
            "address": "Eksjö, Box 5. Västerlångg 34",
            "phone_number": "0381-107 37, 107 47",
            "bank_details": {
                "bankgiro": "266-457",
                "postgiro": "91025-7"
            },
            "activity": "Tillverkar möbler. Specialitet: radio- o TV-möbler",
            "employees": 35,
            "annual_turnover": 2000000,
            "capital": 175000,
            "key_personnel": [
                {
                    "name": "Dir Folke Rudén",
                    "position": "Styrelseordförande"
                },
                {
                    "name": "Folke Rudén",
                    "position": "Verkst dir"
                }
            ],
            "establishment_year": 1931
        },
        "4": {
            "company_name": "DUNDER BYGGNADS AB, AND",
            "pnr": "123 53",
            "address": "Farsta, Sköndalsv 89",
            "phone_number": "08-93 04 50",
            "postgiro": "55583",
            "activity": "Byggnadsentreprenörer",
            "employees": 60,
            "annual_turnover": 5000000,
            "capital": 400000,
            "key_personnel": [
                {
                    "name": "Jan Anders Dunder",
                    "position": "Verkst dir"
                }
            ],
            "establishment_year": 1927
        },
        "5": {
            "company_name": "HAGERROT, AB GUNNAR",
            "pnr": "20122",
            "address": "Malmö 1, Hans Michelsensg 2. Box 217",
            "phone_number": "040-10 0375",
            "bank_details": {
                "bankgiro": "870-1757",
                "postgiro": "245970-9"
            },
            "activity": "Import o export av konfekt yrer",
            "employees": 20,
            "annual_turnover": 15000000,
            "capital": 1000000,
            "key_personnel": [
                {
                    "name": "Gunnar Hagerrot",
                    "position": "Verkst dir"
                },
                {
                    "name": "Knut Ahlström",
                    "position": "Försäljn-chef"
                },
                {
                    "name": "Carl-Erik Lindevi",
                    "position": "Kontorschef"
                }
            ],
            "establishment_year": 1943,
            "subsidiaries": [
                "AB Svenska Chokladförmedlingen",
                "AB Presentchoklad"
            ]
        },
        "6": {
            "company_name": "HAGLUND & ERICSON BOK. TRYCKERI AB",
            "pnr": "116 31",
            "address": "Stockholm, Rensüernas g 12",
            "phone_number": "08-44 06 40",
            "bank_details": {
                "bankgiro": "169-8018",
                "postgiro": "54557-4"
            },
            "activity": "Allt i boktryck, bokbinderi o offset",
            "employees": 28,
            "annual_turnover": 2800000,
            "capital": 40000,
            "key_personnel": [
                {
                    "name": "Boktr Sune Haglund",
                    "position": "Verkst dir"
                }
            ],
            "establishment_year": 1920
        },
        "7": {
            "company_name": "BYGGNADSTEKNISKA BYRÅN",
            "pnr": "41136",
            "address": "Göteborg, Kungsportsavenyn 31-35",
            "phone_number": "031-200940",
            "bankgiro": "41-0146",
            "postgiro": "428910",
            "activity": "Industriprojektering, byggnadskonstruktioner"
        },
        "8": {
            "company_name": "BYGG-NATOR, AB",
            "pnr": "124 40",
            "address": "Bandhagen, Stallarholmsv 37",
            "phone_number": "08-8601 80",
            "bank_details": {
                "bankgiro": "577-9525",
                "postgiro": "555324-3"
            },
            "activity": "Utför schakt- o sprängningsarbeten för byggnader",
            "employees": 30,
            "annual_turnover": 4000000,
            "capital": 100000,
            "key_personnel": [
                {
                    "name": "Ing Sigfrid Fransson",
                    "position": "Verkst dir"
                }
            ],
            "establishment_year": 1957
        },
        "9": {
            "company_name": "CARMAN TRÄ AB, C A",
            "pnr": "591 00",
            "address": "Motala, Prästg 4",
            "phone_number": "0141-113 40, 187 40",
            "bankgiro": "82-2062",
            "activity": "Grossistförsäljning av sågade o hyvlade trävaror",
            "employees": 3,
            "capital": 50000,
            "key_personnel": [
                {
                    "name": "Bengt Malmberg",
                    "position": "Verkst dir"
                }
            ],
            "establishment_year": 1952
        },
        "10": {
            "company_name": "CARNEGIE & CO, PORTERBRYGGERI AB D",
            "pnr": "402 41",
            "address": "Göteborg 12, Klippg. Box 12006",
            "phone_number": "031-1240 00",
            "activity": "Bryggeri o maltfabrik",
            "employees": 70,
            "annual_turnover": 17000000,
            "key_personnel": [
                {
                    "name": "Overing Erik Lindeman",
                    "position": "Platschef"
                }
            ],
            "establishment_year": 1813
        },
        "11": {
            "company_name": "DAlumverken AB",
            "pnr": "520 25",
            "address": "Dalum, Box 46",
            "phone_number": "0321-322 40",
            "bankgiro": "843-3104",
            "postgiro": "117546-2",
            "activity": "Tillverkar ljuddämpare o avgasrör för bilar",
            "employees": 50,
            "annual_turnover": 4000000,
            "capital": 75000,
            "key_personnel": [
                {
                    "name": "Lars Steén",
                    "position": "Verkst dir"
                }
            ],
            "establishment_year": 1952
        },
        "12": {
            "company_name": "TERROL, AB",
            "pnr": "11135",
            "address": "Stockholm, Kungsg 32",
            "phone_number": "08-1152 15",
            "bankgiro": "482-4249",
            "postgiro": "159301-1",
            "activity": "Säljer smörjmedel o presenningar",
            "employees": 10,
            "annual_turnover": 2000000,
            "capital": 60000,
            "key_personnel": [
                {
                    "name": "Stig Carsing",
                    "position": "Verkst dir"
                }
            ],
            "establishment_year": 1945
        },
        "13": {
            "company_name": "GRANROTHS EFTR, H",
            "pnr": "21121",
            "address": "Malmö, Gråbrödersg 2",
            "phone_number": "040-120110",
            "activity": "Importagent. Plastvaror",
            "chief": "E Ehnbom",
            "establishment_year": 1948
        },
        "14": {
            "company_name": "GRANRUDS KONSTRUKTIONS. BYRÅ AB",
            "pnr": "653 40",
            "address": "Karlstad, Malmtorgsg 4",
            "phone_number": "054-15 68 50",
            "bankgiro": "100-2468",
            "postgiro": "394021-0",
            "activity": "Konstruktioner för hus-o industribyggnader. Byggledning, byggkontroll o besiktningar",
            "sub_office_address": "702 32 Örebro, Idrottsv 2",
            "sub_office_phone_number": "019-18 22 50",
            "employees": 11,
            "annual_turnover": 700000,
            "capital": 50000,
            "key_personnel": [
                {
                    "name": "Ing Gösta Granrud",
                    "position": "Verkst dir"
                }
            ],
            "establishment_year": 1954
        }
    }
}