{
    "original": "WIGÉN, AB OSCAR\n\nPnr 573 00\n\nTranås, Säbyv 25. Tel 0140-17000.\nBankgiro 365-5966. Postgiro\n11698-8. TgaWigënos\nVerksamhet: Tillverkar\nhuvudbonader av tyg o päls för damer o\nherrar. Tillverkar pälskappor för\ndamer. Pälsskinn o hattar engros\nFilial: Stockholm C, Upplandsg 3.\nTel 08-23 0190\nAntal anställda: 300\nÅrsomsättning: 40 000 000\nAktiekapital: 3 450 000\nStyrelse: Dir Arthur Herentz (ordf),\nbankdir Osten Nilson, disp\nWilliam Arvidson, försäljn-chef\nGunnar Borg, disp Manfred Lebenberg,\nherr Evert Stjernvall\nVerkst dir: Gösta Ståhl\nEtableringsår: 1906\nOmbildat till aktiebolag 1911.\n\nVIGGBYHOLMSBRÄDGÅRDAB\n\nPnr 183 04\n\nTäby 4, Drakskeppsv 3-11. Box\n4017. Tel 08-756 00 90. Bankgiro\n62-6417, 44-7037. Postgiro 36545\nVerksamhet: Säljer trävaror,\nsnickerier o övrigt byggnadsmaterial\nAntal anställda: 25\nÅrsomsättning: 6 500 000\nAktiekapital: 100 000\nDin Lars Schöllin\nEtableringsår: 1928.\n\nWIGGMANS MÖBELFABRIK\nEFTR, BRÖDERNA\n\nPnr 775 00\n\nKrylbo, Västerbov 5. Tel\n0226-113 58. Bankgiro 151-5261.\nPostgiro 132200-7\n\nVerksamhet: Tillverkar\nbäddmöbler\n\nAntal anställda: 4\nÅrsomsättning: 200 000\nChef: Fabr Rune Wiggman\nEtableringsån 1908.\n\nSÖDERTÄLJE LÄDERINDUSTRI\n\nPnr 15014\n\nVagnhärad. Tel 0156-105 80.\nBankgiro 371-3724. Postgiro 518680-4\nVerksamhet: Tillverkar o säljer\nreseffekter, mode- o sportartiklar\nVarunamn: Tälje\nAntal anställda: 15\nÅrsomsättning: 600000\nChef: Holger Wilhelmsson\nEtableringsår: 1960.\n\nVEN\n\nAktiekapital: 100 000\nStyrelse: Adv Mauritz Grönberger\n(ordf), civilekonom Arne Orreborn,\ndir Gösta Wennberg\nVerkst dir: Civilekonom Arne\nOrreborn\n\nEtableringsår: 1932.\n\nRISBERGS INGENJÖRS.\nBYRÄ AB\n\nPnr 41118\n\nGöteborg, N Liden 6. Te 1\n031-11 37 10, 11 37 60. Postgiro 529410\nVerksamhet: Utför\nbyggnadskonstruktioner, grundundersökningar,\nbesiktningar o kontroll\nAntal anställda: 8\nAktiekapital: 5 000\nVerkst dir: Ing Axel Risberg\nEtableringsår: 1960.\n\nRISBERGS\nJÄRNKONSTRUKTIONER AB\n\nPnr 265 01\n\nÅstorp 1, Box 52. Tel 042-506 64,\n51104. Bankgiro 671-3580.\nPostgiro 339044-0\n\nVerksamhet: Svetsning,\ngrovplåtslageri o järnkonstruktioner\nAntal anställda: 40\nÅrsomsättning: 3 200 000\nAktiekapital: 30 000\nVerkst dir: Hans Risberg\nEtableringsår: 1946.\n\nRISBERGS TRYCKERI AB\n\nPnr 451 01\n\nUddevalla 1, Kuröds Industriområde.\nBox 321. Tel 0522-36090. Bankgiro\n42-8309. Postgiro 663660\nVerksamhet: Bok- o offsettryck\nAntal anställda: 20\nAktiekapital: 50 000\nStyrelse: Boktr Lennart Risberg.\n\nRISENTA, AB\n\nPnr 114 34\n\nStockholm, Birger Jarlsg 8. Tel\n08-23 06 95. Bankgiro 700-1415.\nPostgiro 158736-9. Tga Risenta.\nTelex 10411\n\nVeiksamhet: Import av\nkolonialvaror, speciellt kryddor, mandel,\nnötkärnor, konserver, torkad frukt,\nkakao, bönor, risgryn, ärter,\nfågel-fröer m m. Förmalningsanläggning\nför kryddor o frörenseri i\nStockholms Frihamn\nAntal anställda: 20\nAktiekapital: 125 000\nStyrelse: Dir Sven G Lind (ordf),\ndir Uno Grindby, fru Brita Grindby\nVeikst dir: Uno Grindby\nV veikst dir: Torsten Olsson\nKamrer: Hans Malmström\nEtableringsår: 1940.\n\nBYGGES SPECIAL.\nARBETEN AB, FIRMA\n\nPnr 582 31\n\nLinköping, Alkag 4: Tel\n013-13 03 20. Bankgiro 60-8054.\nPostgiro 101065\n\nVerksamhet: Taktäckningar,\ngolvläggningar, plattsättningar mm\nAktiekapital: 15 000\nChef: Dir Gerhard Gustafsson\nEtableringsår: 1962.\n\nBYGGELEMENT, AB\n\nSäv sjö-H us\n\nPnr 576 00\n\nSävsjö, Box 142. O Järnvägsg. Tel\n0382-11250. Bankgiro 285-4685.\nPostgiro 82221-3\n\nVerksamhet: Byggnadssnickerier o\n\nmonteringsfärdiga hus.\nByggnadsmaterial\n\nAntal anställda: 28\nÅrsomsättning: 1700000\nAktiekapital: 30 000\nVerkst dir: Ing Kurt Andersson\nEtableringsår 1924.\n\nDIREKTTRANSPORT, AB\n\nPnr 401 20\n\nGöteborg 1. Box 44. Packhusg 2-3.\nTel 031-171410. Postgiro 25414-4.\nTga Zell. Telex 20875\nVerksamhet: Containeroperatörer\no transportörer\nAntal anställda: 22\nÅrsomsättning: 15 900 000\nAktiekapital: 100 000\nVerkst dir. Karl Olof Stoltz\nEtableringsår 1868\nOmbildat till aktiebolag 1964.\n\nDIREKT US ab\n\nPnr 171 80\n\nSolna, Englundav 7. Tel 08-98 01 30.\nBankgiro 74-6813. Postgiro 352541.\nTga Directmail. Telex 17149\nVerksamhet: Distribution av\ndirektreklam, registeruppläggningar,\nDörr-till-Dörr, tryckeri\n\nFilial: 212 28 Malmö, Scheeleg 9.\nTel 040-18 5100. Telex 32 503\nAntal anställda: 125\nÅrsomsättning: 15 000000\nAktiekapital: 100 000\nVerkst dir: Stefan Lindberg\nEtableringsår: 1953.\n\nSTABIL MEK VERKSTAD, AB\n\nPnr 44100\n\nAlingsås, Drottningg 34. Tel\n0322-126 55, 16285. Bankgiro 436-6183.\nPostgiro 397041-5\nVerksamhet: Tillverkar textilma-\n\nskiner o hjälpapparater för\ntextilindustrin\n\nChef: Gunnar Ytterström\nEtableringsår: 1951\nOmbildat till aktiebolag 1960.\n\nSTABILATOR AB\n\nPnr 16126\n\nBromma 1. Box 46. Tel 08-26 28 00.\nBankgiro 56-6756. Postgiro 152950.\nTelex 10084. Tga Stabilator\nVerksamhet: Borrnings-,\ninjekterings- o speciella betongarbeten.\nPålning, spontning o övriga\ngrundarbeten. Tillverkning av\nbetongpålar\n\nAvdelningskontor: Göteborg SV,\nFörsta Långg 26. Tel 031-42 25 50\nMalmö C, Nordenskiölds g 13. Tel\n040-1440 00\n\nNorrköping, Skogslotten 1. Tel\n011-490 90\n\nSkellefteå, Kanalg71. Tel\n0910-18995\n\nÅrsomsättning: 40 000 000\nAktiekapital: 5 000\nStvrelse: Dir Ulf Widerström (ordf),\növering Claes Alberts, dir Bengt\nHaak, övering Torsten Hjertonsson,\ndir Johan Magnius\nChef: övering Claes Alberts\nEtableringsår: 1965.\n\nSTACKE AB, METALL.\nFABRIKEN\n\nPnr 330 30\n\nGnosjö, Postl 733. Tel 0370-914 65.\nBankgiro 542-5244. Postgiro\n164479-8\n\nVerksamhet: Utför\nsvarvningsarbe-ten o varmpressning\nAntal anstäUda: 16\nÅrsomsättning: 2 500 000\nAktiekapital: 50 000\nVerkst dir: Edwin Stacke\nEtableringsår: 1938.\n\nTORNVALLS\nKONFEKTIONS AB\n\nPnr 200 45\n\nMalmö 23, V Hindby v 14. Fack. Tel\n040-94 20 30. Bankgiro 83-0286.\nPostgiro 11089\n\nVerksamhet: Tillverkar dam- o\ntonårskappor samt dräkter\nAntal anställda: 200\nÅrsomsättning: 9 500000\nAktiekapital: 820 000\nVerkst dir: Erie Tornvall\nEtableringsår: 1919.\n\nSEDACO, AB\n\nPnr 433 02\n\nPartilie 2, Box 2024. Tel\n031-26 2180. Bankgiro 508-0700.\nPostgiro 528094. Tga Sedacobolaget\nVerksamhet: Tillverkar plastpåsar\no plastbärkassar\nAktiekapital: 50 000\nVerkst dir: Stig Alm\nEtableringsår. 1960.\n\nHEBRO METALL AB\n\nPnr 33012\n\nForshed a. Tel 0370-81132.\nBankgiro 14-1944. Postgiro 138244\nVerksamhet: Pressade\nmassartiklar av järn o metall. Specialitet:\nbiltillbehör\nAktiekapital: 10 000\nVerkst dir: G H Johansson\nEtableringsår: 1956.",
    "structured": {
        "1": {
            "company_name": "WIGÉN, AB OSCAR",
            "pnr": "573 00",
            "address": "Tranås, Säbyv 25",
            "phone_number": "0140-17000",
            "bank_details": {
                "bankgiro": "365-5966",
                "postgiro": "11698-8"
            },
            "activity": "Tillverkar huvudbonader av tyg o päls för damer o herrar. Tillverkar pälskappor för damer. Pälsskinn o hattar engros.",
            "employees": 300,
            "annual_turnover": 40000000,
            "capital": 3450000,
            "key_personnel": [
                {
                    "name": "Arthur Herentz",
                    "position": "Dir"
                },
                {
                    "name": "Osten Nilson",
                    "position": "Bankdir"
                },
                {
                    "name": "William Arvidson",
                    "position": "Disp"
                },
                {
                    "name": "Gunnar Borg",
                    "position": "Försäljn-chef"
                },
                {
                    "name": "Manfred Lebenberg",
                    "position": "Disp"
                },
                {
                    "name": "Evert Stjernvall",
                    "position": "Herr"
                }
            ],
            "establishment_year": 1906
        },
        "2": {
            "company_name": "VIGGBYHOLMSBRÄDGÅRDAB",
            "pnr": "183 04",
            "address": "Täby 4, Drakskeppsv 3-11. Box 4017",
            "phone_number": "08-756 00 90",
            "bank_details": {
                "bankgiro": "62-6417, 44-7037",
                "postgiro": "36545"
            },
            "activity": "Säljer trävaror, snickerier o övrigt byggnadsmaterial",
            "employees": 25,
            "annual_turnover": 6500000,
            "capital": 100000,
            "establishment_year": 1928
        },
        "3": {
            "company_name": "WIGGMANS MÖBELFABRIK EFTR, BRÖDERNA",
            "pnr": "775 00",
            "address": "Krylbo, Västerbov 5",
            "phone_number": "0226-113 58",
            "bank_details": {
                "bankgiro": "151-5261",
                "postgiro": "132200-7"
            },
            "activity": "Tillverkar bäddmöbler",
            "employees": 4,
            "annual_turnover": 200000,
            "key_personnel": [
                {
                    "name": "Rune Wiggman",
                    "position": "Chef"
                }
            ],
            "establishment_year": 1908
        },
        "4": {
            "company_name": "SÖDERTÄLJE LÄDERINDUSTRI",
            "pnr": "15014",
            "address": "Vagnhärad",
            "phone_number": "0156-105 80",
            "bank_details": {
                "bankgiro": "371-3724",
                "postgiro": "518680-4"
            },
            "activity": "Tillverkar o säljer reseffekter, mode- o sportartiklar",
            "employees": 15,
            "annual_turnover": 600000,
            "key_personnel": [
                {
                    "name": "Holger Wilhelmsson",
                    "position": "Chef"
                }
            ],
            "establishment_year": 1960
        },
        "5": {
            "company_name": "VEN",
            "capital": 100000,
            "key_personnel": [
                {
                    "name": "Mauritz Grönberger",
                    "position": "Adv"
                },
                {
                    "name": "Arne Orreborn",
                    "position": "CivilEkonom"
                },
                {
                    "name": "Gösta Wennberg",
                    "position": "Dir"
                },
                {
                    "name": "Arne Orreborn",
                    "position": "Civilekonom"
                }
            ],
            "establishment_year": 1932
        },
        "6": {
            "company_name": "RISBERGS INGENJÖRS. BYRÄ AB",
            "pnr": "41118",
            "address": "Göteborg, N Liden 6",
            "phone_number": "031-11 37 10, 11 37 60",
            "postgiro": "529410",
            "activity": "Utför byggnadskonstruktioner, grundundersökningar, besiktningar o kontroll",
            "employees": 8,
            "capital": 5000,
            "key_personnel": [
                {
                    "name": "Ing Axel Risberg",
                    "position": "Verkst dir"
                }
            ],
            "establishment_year": 1960
        },
        "7": {
            "company_name": "RISBERGS JÄRNKONSTRUKTIONER AB",
            "pnr": "265 01",
            "address": "Åstorp 1, Box 52",
            "phone_number": "042-506 64, 51104",
            "bank_details": {
                "bankgiro": "671-3580",
                "postgiro": "339044-0"
            },
            "activity": "Svetsning, grovplåtslageri o järnkonstruktioner",
            "employees": 40,
            "annual_turnover": 3200000,
            "capital": 30000,
            "key_personnel": [
                {
                    "name": "Hans Risberg",
                    "position": "Verkst dir"
                }
            ],
            "establishment_year": 1946
        },
        "8": {
            "company_name": "RISBERGS TRYCKERI AB",
            "pnr": "451 01",
            "address": "Uddevalla 1, Kuröds Industriområde. Box 321",
            "phone_number": "0522-36090",
            "bankgiro": "42-8309",
            "activity": "Bok- o offsettryck",
            "employees": 20,
            "capital": 50000,
            "key_personnel": [
                {
                    "name": "Lennart Risberg",
                    "position": "Boktr"
                }
            ]
        },
        "9": {
            "company_name": "RISENTA, AB",
            "pnr": "114 34",
            "address": "Stockholm, Birger Jarlsg 8",
            "phone_number": "08-23 06 95",
            "bank_details": {
                "bankgiro": "700-1415",
                "postgiro": "158736-9"
            },
            "activity": "Import av kolonialvaror, speciellt kryddor, mandel, nötkärnor, konserver, torkad frukt, kakao, bönor, risgryn, ärter, fågel-fröer m m. Förmalningsanläggning för kryddor o frörenseri i Stockholms Frihamn",
            "employees": 20,
            "capital": 125000,
            "key_personnel": [
                {
                    "name": "Sven G Lind",
                    "position": "Dir"
                },
                {
                    "name": "Uno Grindby",
                    "position": "Dir"
                },
                {
                    "name": "Brita Grindby",
                    "position": "Fru"
                }
            ],
            "establishment_year": 1940
        },
        "10": {
            "company_name": "BYGGES SPECIAL. ARBETEN AB, FIRMA",
            "pnr": "582 31",
            "address": "Linköping, Alkag 4",
            "phone_number": "013-13 03 20",
            "bank_details": {
                "bankgiro": "60-8054",
                "postgiro": "101065"
            },
            "activity": "Taktäckningar, golvläggningar, plattsättningar mm",
            "capital": 15000,
            "key_personnel": [
                {
                    "name": "Gerhard Gustafsson",
                    "position": "Dir"
                }
            ],
            "establishment_year": 1962
        },
        "11": {
            "company_name": "BYGGELEMENT, AB",
            "pnr": "576 00",
            "address": "Sävsjö, Box 142. O Järnvägsg",
            "phone_number": "0382-11250",
            "bank_details": {
                "bankgiro": "285-4685",
                "postgiro": "82221-3"
            },
            "activity": "Byggnadssnickerier o monteringsfärdiga hus. Byggnadsmaterial",
            "employees": 28,
            "annual_turnover": 1700000,
            "capital": 30000,
            "key_personnel": [
                {
                    "name": "Kurt Andersson",
                    "position": "Ing"
                }
            ],
            "establishment_year": 1924
        },
        "12": {
            "company_name": "DIREKTTRANSPORT, AB",
            "pnr": "401 20",
            "address": "Göteborg 1, Box 44, Packhusg",
            "phone_number": "031-171410",
            "postgiro": "25414-4",
            "activity": "Containeroperatörer o transportörer",
            "employees": 22,
            "annual_turnover": 15900000,
            "capital": 100000,
            "key_personnel": [
                {
                    "name": "Karl Olof Stoltz",
                    "position": "Verkst dir"
                }
            ],
            "establishment_year": 1868
        },
        "13": {
            "company_name": "DIREKT US ab",
            "pnr": "171 80",
            "address": "Solna, Englundav 7",
            "phone_number": "08-98 01 30",
            "bank_details": {
                "bankgiro": "74-6813",
                "postgiro": "352541"
            },
            "activity": "Distribution av direktreklam, registeruppläggningar, Dörr-till-Dörr, tryckeri",
            "employees": 125,
            "annual_turnover": 15000000,
            "capital": 100000,
            "key_personnel": [
                {
                    "name": "Stefan Lindberg",
                    "position": "Verkst dir"
                }
            ],
            "establishment_year": 1953
        },
        "14": {
            "company_name": "STABIL MEK VERKSTAD, AB",
            "pnr": "44100",
            "address": "Alingsås, Drottningg 34",
            "phone_number": "0322-126 55, 16285",
            "bank_details": {
                "bankgiro": "436-6183",
                "postgiro": "397041-5"
            },
            "activity": "Tillverkar textilmaskiner o hjälpapparater för textilindustrin",
            "key_personnel": [
                {
                    "name": "Gunnar Ytterström",
                    "position": "Chef"
                }
            ],
            "establishment_year": 1951
        },
        "15": {
            "company_name": "STABILATOR AB",
            "pnr": "16126",
            "address": "Bromma 1, Box 46",
            "phone_number": "08-26 28 00",
            "bank_details": {
                "bankgiro": "56-6756",
                "postgiro": "152950"
            },
            "activity": "Borrnings-, injekterings- o speciella betongarbeten. Pålning, spontning o övriga grundarbeten. Tillverkning av betongpålar",
            "employees": 40,
            "annual_turnover": 40000000,
            "capital": 5000,
            "key_personnel": [
                {
                    "name": "Ulf Widerström",
                    "position": "Dir"
                },
                {
                    "name": "Claes Alberts",
                    "position": "Övering"
                },
                {
                    "name": "Bengt Haak",
                    "position": "Dir"
                },
                {
                    "name": "Torsten Hjertonsson",
                    "position": "Övering"
                },
                {
                    "name": "Johan Magnius",
                    "position": "Dir"
                }
            ],
            "establishment_year": 1965
        },
        "16": {
            "company_name": "STACKE AB, METALL. FABRIKEN",
            "pnr": "330 30",
            "address": "Gnosjö, Postl 733",
            "phone_number": "0370-914 65",
            "bank_details": {
                "bankgiro": "542-5244",
                "postgiro": "164479-8"
            },
            "activity": "Utför svarvningsarbeten o varmpressning",
            "employees": 16,
            "annual_turnover": 2500000,
            "capital": 50000,
            "key_personnel": [
                {
                    "name": "Edwin Stacke",
                    "position": "Verkst dir"
                }
            ],
            "establishment_year": 1938
        },
        "17": {
            "company_name": "TORNVALLS KONFEKTIONS AB",
            "pnr": "200 45",
            "address": "Malmö 23, V Hindby v 14",
            "phone_number": "040-94 20 30",
            "bank_details": {
                "bankgiro": "83-0286",
                "postgiro": "11089"
            },
            "activity": "Tillverkar dam- o tonårskappor samt dräkter",
            "employees": 200,
            "annual_turnover": 9500000,
            "capital": 820000,
            "key_personnel": [
                {
                    "name": "Erie Tornvall",
                    "position": "Verkst dir"
                }
            ],
            "establishment_year": 1919
        },
        "18": {
            "company_name": "SEDACO, AB",
            "pnr": "433 02",
            "address": "Partilie 2, Box 2024",
            "phone_number": "031-26 2180",
            "bank_details": {
                "bankgiro": "508-0700",
                "postgiro": "528094"
            },
            "activity": "Tillverkar plastpåsar o plastbärkassar",
            "capital": 50000,
            "key_personnel": [
                {
                    "name": "Stig Alm",
                    "position": "Verkst dir"
                }
            ],
            "establishment_year": 1960
        },
        "19": {
            "company_name": "HEBRO METALL AB",
            "pnr": "33012",
            "address": "Forshed a",
            "phone_number": "0370-81132",
            "bank_details": {
                "bankgiro": "14-1944",
                "postgiro": "138244"
            },
            "activity": "Pressade massartiklar av järn o metall. Specialitet: biltillbehör",
            "capital": 10000,
            "key_personnel": [
                {
                    "name": "G H Johansson",
                    "position": "Verkst dir"
                }
            ],
            "establishment_year": 1956
        }
    }
}