{
    "original": "BROBY INDUSTRIER AB\n\nPnr 280 60\n\nBroby. Tel 044-412 00. Bankgiro\n657-9569. Postgiro 476507-9.\nTelex 4424 BROBY S\nVerksamhet: Halvkemisk massa o\npappersbruk. Sågverk\nAntal anställda: 250\nAktiekapital: 12900 000\nVerkst dir: P O Häger\nEtableringsår: 1970\nIngår i Skåneskogkoncernen.\n\nBROBY MEK VERKSTADS AB\n\nPnr 280 60\n\nBroby. Tel 044-400 37, 41177\nVerksamhet: Tillverkar garage- o\nindustriporten Quissle.\nArmerings-järnringar. Mek arbeten\nFörsäljningskontor: 20120 Malmö 1.\nAB J H Dieden J:r, Box 85. Tel\n040-716 50\nAntal anställda: 35\nÅrsomsättning: 4 000 000\nAktiekapital: 20500\nStyrelse: Hulda Holmberg (ordf),\nWilliam Frick, Gunvor Widell\nVerkst dir: Gunvor Widell\nEtableringsår: 1907.\n\nSVENSKA STRAMAX AB\n\nPnr 104 32\n\nStockholm 19, Bragev 12. Box\n19054. Tel 08-24 0215. Postgiro\n503765-0\n\nVerksamhet: Strålningstakinstallar\ntioner\n\nAntal anställda: 6\nÅrsomsättning: 500 000\nAktiekapital: 5 000\nVerkst dir: Torsten Björklund.\n\nSVENSKA\nSTAL-PRODUKTER, AB\n\nPnr 63103\n\nEskilstuna 1, Box 247. Stålbergsv\n7. Tel 016-117160. Bankgiro\n601-5457. Postgiro 451631-6. Tga\nSwedsteel\n\nVerksamhet: Tillverkning av\nrostfria hushåll-, restaurang- o\nsjukhusartiklar samt svetsade\nspecialrör\n\nVerkst dir: Disp Carl Lewerentz\nMarknadschef: Göran Thorén\nEtableringsår: 1935.\n\nSVENSKA STALSOLF.\nFABRIKEN\n\nPnr 50002\n\nBorås 2, Getängsv 4. Box 22023.\nTel 033-1179 80. Postgiro\n140050-6. Tga Hennig\nVerksamhet: Tillverkar o säljer\nkompletta skaftramar, ramtillbehör,\njacquardvikter, stålsolv mm\nAntal anställda: 16\nÄgare o chef: Olof Hennig\nEtableringsår 1907\nDotterbolag till AB Hugo Hennig,\nBorås.\n\nSVENSKA STÄNGSEL.\nBYGGEN, AB\n\nPnr 11634\n\nStockholm, Duvnäsg 8. Tel\n08-403044, 31 38 64. Bankgiro\n578-9177. Postgiro 190776-5\nVerksamhet: Tillverkar o monterar\nkompletta stängselanläggningar\nsamt trästaket\nAntal anställda: 12\nÅrsomsättning: 800 000\nAktiekapital: 30 000\nVerkst dir: Bror Allan Widén\nEtableringsår 1935.\n\nSVENSKA SUPERFOSFAT\nFÖRSÄLJNINGS AB\n\nPnr 261 20\n\nLandskrona 1, Fack. Storg 24. Tel\n0418-16040. Bankgiro 86-3999.\nPostgiro 14373. Tga Fosforsyra.\nTelex 72417 SUPER S\nVerksamhet: Grosshandel med\ngödselmedel\n\nFörsäljningskontor: 402 51\nGöteborg 13, Marieholmsg. Box 13043\n11135 Stockholm, Kungsg 28\nAntal anställda: 36\nÅrsomsättning: 90 000 000\nAktiekapital: 3 600 000\nStyrelse: Dir Folke Mårtensson\n(ordf), dir Olof Rydbert, intendent\nSven Mårtensson\nVerkst dir: Olof Rydbert\nEtableringsår: 1909\nDotterbolag till AB Förenade\nSu-perfosfatfabriker, Landskrona.\n\nSVENSKA SÄCK AB\n\nPnr 21120\n\nMalmö C, Citadellsv 17. Tel\n040-723 95. Bankgiro 260-9055.\nPostgiro 24433-5. Tga Säckkompaniet.\nTelex 3172\n\nVerksamhet: Tillverkar o säljer nya\nsäckar, plastsäckar, papperssäckar,\npolyetenfolie, PVC-folie,\nPVC-växthus, plasthallar, presenningar.\nUthyrning av presenningar\nAktiekapital: 50 000\nVerkst dir: O Jörgensen\nEtableringsår. 1916.\n\nSVENSKA TACKS.\nFABRIKEN, AB\n\nPnr 46101\n\nTrollhättan 1, Järnvägsg 18-20.\nBox 55. Tel 0520-100 62, 106 02.\nBankgiro 89-2433. Postgiro 20661.\nTga Tacksfabriken\nVerksamhet: Tillverkar tacks,\nskostift, klackstift, tapetsörnubb,\nskofjädrar, pappgelänk, fotstöd,\ntrådspik, stålspik o byggnadsspik\nAntal anställda: 75\nAktiekapital: 720 000\nStyrelse: Fru Lisa Lawson (ordf),\ndir Bertil Lawson, fru Barbro\nLawson\n\nVerkst dir: Bertil Lawson\nEtableringsår: 1911.\n\nSVENSKA TAPET &amp;\nLINOLEUM AB\n\nPnr 125 34\n\nÄlvsjö, Johan Skyttes v 200. Tel\n08-47 20 30, 47 86 74. Postgiro\n153362-9\n\nVerksamhet: Säljer tapeter o\ngolvbeläggningsmaterial\nAktiekapital: 10 000\nStyrelse: Dir C G Söderberg (ordf),\nherr Nils Löfberg\nVerkst dir: C G Söderberg\nEtableringsår. 1961.\n\nJÄRNKONST AB\n\nPnr 261 22\n\nLandskrona 1, Lyktg. Box 94. Tel\n0418-162 90. Bankgiro 86-8513.\nPostgiro 290512. Telex 7 2280. Tga\nJaernkonst\n\nVerksamhet: Tillverkar ljusarmatur,\nundertak o elvärmeradiatorer\n\nAvdelningskontor: 413 09 Göteborg,\nVegag 22. Tel 031-42 02 95\nHägersten, Vretensborgsv 9. Box\n42023, 12612 Stockholm 42. Tel\n08-18 03 10\n\n85244 Sundsvall, Enhörningsv 24.\nTel 060-12 34 70\nAntal anställda: 430\nÅrsomsättning: 45 000 000\nAktiekapital: 8 000 000\nVerkst dir: Gösta Carlsson\nTekn dir: Harry Häggberg\nMarknadsdir: Rune Forster\nEkonomidir: Stig Nordström\nInköpschef: Arthur Carlsson\nVerkstadschef: Lennart Hansson\nEtableringsår: 1945\nOmbildat till aktiebolag 1954.\n\nJÄRNKONSTRUKTIONER, AB\n\nPnr 252 27\n\nHelsingborg, Gåsebäcksv 10. Tel\n042-12 06 55. Bankgiro 340-5404.\nPostgiro 160802-5\nVerksamhet: Utför mekaniska\narbeten o svetsningsarbeten\nAntal anställda: 30\nÅrsomsättning: 2 000 000\nAktiekapital: 60 000\nVerkst dir: Ing Ake Järnum\nEtableringsår: 1939.\n\nBYGGTJÄNST I KUNGÄLV AB\n\nPnr 442 00\n\nKungälv, Torgg 2. Box 94. Tel\n0303-150 60. Bankgiro 547-3939.\nPostgiro 667660-5\nVerksamhet: Husbyggnads- o\nreparationsarbeten\nAntal anställda: 32\nÅrsomsättning: 3 000 000\nAktiekapital: 15 000\nVerkst dir: Leif Mårtensson\nEtableringsår: 1965.\n\nHAGMANS KEMI AB\n\nPnr 510 20\n\nFritsla, Box 112. Tel 0320-72100.\nBankgiro 531-2566. Postgiro\n264909. Tga Hagmanit.\nTelex 36040\n\nVerksamhet: Tillverkar färger,\nbiltekniska preparat, asfaltprodukter,\nljuddämpande- o träns\nportskyddande plaster, golvbeläggningar på\nplastbasis, tätningsmedel, lim\nVarunamn: Hagmanit\nVerkst dir: Gunnar Hagman\nDisp: Sten Wallin\nEtableringsår: 1942.\n\nHAGMAN,\nKONSTRUKTIONS-FIRMAN LARS\n\nPnr 44044\n\nSurte. Box 24. Tel 031-98 15 41,\n98 11 65. Bankgiro 655-3648.\nPostgiro 627025-0\n\nVerksamhet: Allmänna\nmaskinkonstruktioner\nChef: Lars Hagman\nEtableringsår. 1969.\n\nAJC\n\nDriftsing i Vargön S Hellman\nDriftsförest 1 Trollhättan E Sjögren\nAnläggningstjänst: övering E\nHällgren\n\nAntal anställda: 500\nÅrsomsättning: 150 000 000\nAktiekapital: 12 000 000\nVerkst dir: S Tjernström\nInköpschef: B Hansson\nKörsäljn-chefer: S Elliot, S Ahlm\nEkonomichef: E Mandorf\nEtableringsår: 1874.\n\nTENECO, AB\n\nPnr 11342\n\nStockholm, Vikingag 29. Tel\n08-344010, 34 4011. Bankgiro\n56-0519. Postgiro 190911 Tga\nTene-corp\n\nVerksamhet: Säljer elektriska\nmotorer\n\nAntal anställda: 3\nÅrsomsättning: 510 000\nAktiekapital: 5 000\nVerkst din Olof Neander\nEtableringsår 1941.\n\nLIN\n\nVerksamhet: Specialfabrik för\ntillverkning av tänger\nVarunamn: Kongsberg, Lindström,\nSupreme\n\nAntal anställda: 140\nÅrsomsättning: 9000 000\nAktiekapital: 900 000\nStyrelse: Dir Sven Wedén (ordf),\ning Lennart Eklöf, disp Stig\nEliasson, dir Gunnar Ericsson, herr Sven\nKarlsson, dir C O Lindqvist, disp\nSture Nilsson, herr Ingvar\nPettersson, civilekonom Lars Wedén\nVerkst dir: Carl O Lindqvist\nEtableringsår: 1856.\n\nTAR\n\nAntal anställda: 25\nÅrsomsättning: 2 000 000\nAktiekapital: 70 000\nVerkst dir: Süg Olof Tamén\nEtableringsàr: 1948.\n\nTANDSBYNS MEK VERKSTAD\nBR ERICSON &amp; CO\n\nPnr 830 21\n\nTandsb.vn, Box 78. Tel 063-542 20.\nBankgiro 777-8962. Postgiro\n274056-1\n\nVerksamhet: Tillverkar motorsågar\nAntal anställda: 40\nChefen Olof Einar Andersson, Sven\nHugo Ericson, Carl Stefan Ericson\nEtableringsàr 1943\nDotterbolag till Husqvarna\nVapenfabriks AB, Huskvarna.\n\nTANK &amp; SVETS AB\n\nPnr 610 53\n\nEnstaberga, Box 40. Tel\n0155-57117, 570 12. Postgiro 264432\nVerksamhet: Tillverkar\noljecisterner o farmaggregat\nAktiekapital: 25 000\nFirmatecknare: H Anderson,\nS.Anderson\nEtableringsàr: 1953.\n\nTANKCLEANING, AB\n\nPnr 402 71\n\nGöteborg 8, Box 8842.\nSkarviks-hamnen. Tel 031-53 89 25.\nBankgiro 44-1301. Postgiro 620136\nVerksamhet: Rengöring av\ntankfartyg, emottagning av ballast m m\nAntal anställda: 30\nAktiekapital: 105000\nVerkst dir: Sven Danielsson\nEtableringsàr: 1956.\n\nTANKMOBIL AB\n\nPnr 200 13\n\nMalmö 27. Aspög 5. Box 27036.\nTel 040-93 69 80. Bankgiro 34-8300.\nPostgiro 350985. Telex 32434. Tga\nOlswaggon\n\nVerksamhet: Bulktransportfordon o\ncisterner. Tankbilsreparationer\nAntal anställda: 40\nÅrsomsättning: 4 000 000\nVerkst dir: Kjell Svensson.\n\nTANKVAGNAR, AB\n\nPnr 31100\n\nFalkenberg, Varbergsv 12. Box\n176. Tel 0346-116 98, 134 57.\nTelex 38038 ABTANKV S\nVerksamhet: Uthyr o säljer\njärn-vägcisternvagnar\n\nStockholmskontor: Tel 08-23 3915\nÅrsomsättning: 27 0 000\nAktiekapital: 25 000\nStyrelse: Fru Erna Olsson, adv\nStig Pehrsson, dir A Franzon\nVerkst dir: A Franzon.\n\nTANY, AB PÄRMFABRIKEN\n\nPnr 360 24\n\nLinneryd. Tel 0470-343 50.\nBankgiro 292-6954. Postgiro 86455-3\nVerksamhet: Tillverkar\nfakturapärmar, register i plast, kartong o\npapper samt lagerregister. Plast,\nartiklar såsom aktmappar,\nanbudsmappar o plastfickor. Specialitet:\nalla slags reklampärmar i plast.\n\npluviusin, conrit samt konstläder,\näven med firmatryck i folie eller\nscreentryck\nAntal anställda: 90\nÅrsomsättning: 8 000 000\nAktiekapital: 75 000\nStyrelse: Fabr Tage Nyblom, fru\nEmy Nyblom, disp Lil Nyblom\nVerkst din Fabr Tage Nyblom\nEtableringsàr: 1956.\n\nTAPE, PAPPERS AB\n\nPnr 150 20\n\nJärna, Box 80. Tel 0755-716 78,\n716 79. Bankgiro 28-3891. Postgiro\n55112. Tga Pabtape, Södertälje\nVerksamhet: Vaxpapper med o\nutan tryck\n\nAktiekapital: 15 000\nVerkst dir Sture Nilsson\nEtableringsàr 1932.\n\nISENTA, ISOLERINGS AB\n\nPnr 702 27\n\nÖrebro, Radiatorv 5. Tel\n019-13 07 20. Bankgiro 822-7050.\nPostgiro 141273\n\nVerksamhet: Entreprenader\navseende: Komfort-isolering,\nindustriisolering, fartygsisolering,\nventilationsisolering, brandisolering,\nplåtbeklädnader, kyl- o\nfrysrumsanläggningar\nRegionkontor\n\n112 59 Stockholm, Rålambsv 7.\nTel 08-24 58 85\n\n42131 Västra Frölunda, Frökotteg\n10. Tel 031-49 03 75\n213 64 Malmö, Emilstorpsg 26.\nTel 040-94 65 45\n\n901 02 Umeå 1, Box 52. Förrådsv\n4. Tel 090-13 50 10\n852 30 Sundsvall, Storg 54. Tel\n060-1146 62\n\n652 21 Karlstad, Sågverksg 24. Tel\n054-18 52 00\n\n723 35 Västerås, Baldersg 8. Tel\n021-13 57 52\n\n602 23 Norrköping, Fabriksg 8.\nTel 011-18 89 00\n951 00 Luleå, Varvsg 69. Tel\n0920-166 26\n\n826 00 Söderhamn, Jämtlandsv 1.\nTel 0270-146 23\n702 27 Örebro, Radiatorv 5. Tel\n019-13 07 20\nAntal anställda: 700\nÅrsomsättning: 50 000 000\nStyrelse: Dir Bo Anderberg (ordf),\ndir Rolf Strand, dir Carl Larsson,\ndisp Gösta Larsson\nVeikst dir: Rolf Strand\nDotterbolag: Isenta i Örebro AB,\nIsenta i Stockholm AB, Isenta i\nKarlstad AB.\n\nISHAMMARS AUTOMATFABRIK,\nAB\n\nPnr 21218\n\nMalmö, Lundav 11 B. Tel\n040-93 68 80. Bankgiro 614-2368.\nPostgiro 530192-4. Tga Glsaf\n\nVerksamhet: Tillverkning,\nuthyrning, försäljning o service av\nautomater för kikare-, musik- o\nsällskapsspel\nAktiekapital: 50 000\nFörsäljning: Fru Valborg Ishammar\nEtableringsår: 1950.\n\nISIDOR-SKÅP\nGRONKVIST &amp; ORNLINDE\n\nPnr 113 31\n\nStockholm, Sankt Eriksg 101. Tel\n08-30 96 99. Bankgiro 56-5423.\nPostgiro 655785\n\nVerksamhet: Säljer Isidor\nritningsskåp o säkerhetsskåp\nVaiunamn: Isidor\n\nChef: Civilekonom Lars Grönkvist\nEtableringsår 1961.",
    "structured": {
        "1": {
            "company_name": "BROBY INDUSTRIER AB",
            "address": "Broby",
            "phone_number": "044-412 00",
            "bank_details": {
                "bankgiro": "657-9569",
                "postgiro": "476507-9"
            },
            "activity": "Halvkemisk massa o pappersbruk. Sågverk",
            "employees": 250,
            "capital": 12900000,
            "key_personnel": [
                {
                    "name": "P O Häger",
                    "position": "Verkst dir"
                }
            ],
            "establishment_year": 1970
        },
        "2": {
            "company_name": "BROBY MEK VERKSTADS AB",
            "address": "Broby",
            "phone_number": "044-400 37, 41177",
            "activity": "Tillverkar garage- o industriporten Quissle. Armerings-järnringar. Mek arbeten",
            "employees": 35,
            "annual_turnover": 4000000,
            "capital": 20500,
            "key_personnel": [
                {
                    "name": "Gunvor Widell",
                    "position": "Verkst dir"
                }
            ],
            "establishment_year": 1907
        },
        "3": {
            "company_name": "SVENSKA STRAMAX AB",
            "address": "Stockholm 19, Bragev 12. Box 19054",
            "phone_number": "08-24 0215",
            "bank_details": {
                "postgiro": "503765-0"
            },
            "activity": "Strålningstakinstallar tioner",
            "employees": 6,
            "capital": 5000,
            "key_personnel": [
                {
                    "name": "Torsten Björklund",
                    "position": "Verkst dir"
                }
            ],
            "establishment_year": null
        },
        "4": {
            "company_name": "SVENSKA STAL-PRODUKTER, AB",
            "address": "Eskilstuna 1, Box 247. Stålbergsv 7",
            "phone_number": "016-117160",
            "bank_details": {
                "bankgiro": "601-5457",
                "postgiro": "451631-6"
            },
            "activity": "Tillverkning av rostfria hushåll-, restaurang- o sjukhusartiklar samt svetsade specialrör",
            "key_personnel": [
                {
                    "name": "Disp Carl Lewerentz",
                    "position": "Verkst dir"
                },
                {
                    "name": "Göran Thorén",
                    "position": "Marknadschef"
                }
            ],
            "establishment_year": 1935
        },
        "5": {
            "company_name": "SVENSKA STALSOLF. FABRIKEN",
            "address": "Borås 2, Getängsv 4. Box 22023",
            "phone_number": "033-1179 80",
            "bank_details": {
                "postgiro": "140050-6"
            },
            "activity": "Tillverkar o säljer kompletta skaftramar, ramtillbehör, jacquardvikter, stålsolv mm",
            "employees": 16,
            "key_personnel": [
                {
                    "name": "Olof Hennig",
                    "position": "Ägare o chef"
                }
            ],
            "establishment_year": 1907
        },
        "6": {
            "company_name": "SVENSKA STÄNGSEL. BYGGEN, AB",
            "address": "Stockholm, Duvnäsg 8",
            "phone_number": "08-403044, 31 38 64",
            "bank_details": {
                "bankgiro": "578-9177",
                "postgiro": "190776-5"
            },
            "activity": "Tillverkar o monterar kompletta stängselanläggningar samt trästaket",
            "employees": 12,
            "annual_turnover": 800000,
            "capital": 30000,
            "key_personnel": [
                {
                    "name": "Bror Allan Widén",
                    "position": "Verkst dir"
                }
            ],
            "establishment_year": 1935
        },
        "7": {
            "company_name": "SVENSKA SUPERFOSFAT FÖRSÄLJNINGS AB",
            "address": "Landskrona 1, Fack. Storg 24",
            "phone_number": "0418-16040",
            "bank_details": {
                "bankgiro": "86-3999",
                "postgiro": "14373"
            },
            "activity": "Grosshandel med gödselmedel",
            "employees": 36,
            "annual_turnover": 90000000,
            "capital": 3600000,
            "key_personnel": [
                {
                    "name": "Olof Rydbert",
                    "position": "Verkst dir"
                }
            ],
            "establishment_year": 1909
        },
        "8": {
            "company_name": "SVENSKA SÄCK AB",
            "address": "Malmö C, Citadellsv 17",
            "phone_number": "040-723 95",
            "bank_details": {
                "bankgiro": "260-9055",
                "postgiro": "24433-5"
            },
            "activity": "Tillverkar o säljer nya säckar, plastsäckar, papperssäckar, polyetenfolie, PVC-folie, PVC-växthus, plasthallar, presenningar. Uthyrning av presenningar",
            "capital": 50000,
            "key_personnel": [
                {
                    "name": "O Jörgensen",
                    "position": "Verkst dir"
                }
            ],
            "establishment_year": 1916
        },
        "9": {
            "company_name": "SVENSKA TACKS. FABRIKEN, AB",
            "address": "Trollhättan 1, Järnvägsg 18-20. Box 55",
            "phone_number": "0520-100 62, 106 02",
            "bank_details": {
                "bankgiro": "89-2433",
                "postgiro": "20661"
            },
            "activity": "Tillverkar tacks, skostift, klackstift, tapetsörnubb, skofjädrar, pappgelänk, fotstöd, trådspik, stålspik o byggnadsspik",
            "employees": 75,
            "capital": 720000,
            "key_personnel": [
                {
                    "name": "Bertil Lawson",
                    "position": "Verkst dir"
                }
            ],
            "establishment_year": 1911
        },
        "10": {
            "company_name": "SVENSKA TAPET & LINOLEUM AB",
            "address": "Älvsjö, Johan Skyttes v 200",
            "phone_number": "08-47 20 30, 47 86 74",
            "bank_details": {
                "postgiro": "153362-9"
            },
            "activity": "Säljer tapeter o golvbeläggningsmaterial",
            "capital": 10000,
            "key_personnel": [
                {
                    "name": "C G Söderberg",
                    "position": "Verkst dir"
                }
            ],
            "establishment_year": 1961
        },
        "11": {
            "company_name": "JÄRNKONST AB",
            "address": "Landskrona 1, Lyktg. Box 94",
            "phone_number": "0418-162 90",
            "bank_details": {
                "bankgiro": "86-8513",
                "postgiro": "290512"
            },
            "activity": "Tillverkar ljusarmatur, undertak o elvärmeradiatorer",
            "employees": 430,
            "annual_turnover": 45000000,
            "capital": 8000000,
            "key_personnel": [
                {
                    "name": "Gösta Carlsson",
                    "position": "Verkst dir"
                }
            ],
            "establishment_year": 1945
        },
        "12": {
            "company_name": "JÄRNKONSTRUKTIONER, AB",
            "address": "Helsingborg, Gåsebäcksv 10",
            "phone_number": "042-12 06 55",
            "bank_details": {
                "bankgiro": "340-5404",
                "postgiro": "160802-5"
            },
            "activity": "Utför mekaniska arbeten o svetsningsarbeten",
            "employees": 30,
            "annual_turnover": 2000000,
            "capital": 60000,
            "key_personnel": [
                {
                    "name": "Ing Ake Järnum",
                    "position": "Verkst dir"
                }
            ],
            "establishment_year": 1939
        },
        "13": {
            "company_name": "BYGGTJÄNST I KUNGÄLV AB",
            "address": "Kungälv, Torgg 2",
            "phone_number": "0303-150 60",
            "bank_details": {
                "bankgiro": "547-3939",
                "postgiro": "667660-5"
            },
            "activity": "Husbyggnads- o reparationsarbeten",
            "employees": 32,
            "annual_turnover": 3000000,
            "capital": 15000,
            "key_personnel": [
                {
                    "name": "Leif Mårtensson",
                    "position": "Verkst dir"
                }
            ],
            "establishment_year": 1965
        },
        "14": {
            "company_name": "HAGMANS KEMI AB",
            "address": "Fritsla, Box 112",
            "phone_number": "0320-72100",
            "bank_details": {
                "bankgiro": "531-2566",
                "postgiro": "264909"
            },
            "activity": "Tillverkar färger, biltekniska preparat, asfaltprodukter, ljuddämpande- o tränsportskyddande plaster, golvbeläggningar på plastbasis, tätningsmedel, lim",
            "key_personnel": [
                {
                    "name": "Gunnar Hagman",
                    "position": "Verkst dir"
                }
            ],
            "establishment_year": 1942
        },
        "15": {
            "company_name": "HAGMAN, KONSTRUKTIONS-FIRMAN LARS",
            "address": "Surte. Box 24",
            "phone_number": "031-98 15 41, 98 11 65",
            "bank_details": {
                "bankgiro": "655-3648",
                "postgiro": "627025-0"
            },
            "activity": "Allmänna maskinkonstruktioner",
            "key_personnel": [
                {
                    "name": "Lars Hagman",
                    "position": "Chef"
                }
            ],
            "establishment_year": 1969
        },
        "16": {
            "company_name": "AJC",
            "activity": "Driftsing i Vargön S Hellman Driftsförest 1 Trollhättan E Sjögren Anläggningstjänst: övering E Hällgren",
            "employees": 500,
            "annual_turnover": 150000000,
            "capital": 12000000,
            "key_personnel": [
                {
                    "name": "S Tjernström",
                    "position": "Verkst dir"
                },
                {
                    "name": "B Hansson",
                    "position": "Inköpschef"
                },
                {
                    "name": "S Elliot",
                    "position": "Körsäljn-chefer"
                },
                {
                    "name": "S Ahlm",
                    "position": "Körsäljn-chefer"
                },
                {
                    "name": "E Mandorf",
                    "position": "Ekonomichef"
                }
            ],
            "establishment_year": 1874
        },
        "17": {
            "company_name": "TENECO, AB",
            "address": "Stockholm, Vikingag 29",
            "phone_number": "08-344010, 34 4011",
            "bank_details": {
                "bankgiro": "56-0519",
                "postgiro": "190911"
            },
            "activity": "Säljer elektriska motorer",
            "employees": 3,
            "annual_turnover": 510000,
            "capital": 5000,
            "key_personnel": [
                {
                    "name": "Olof Neander",
                    "position": "Verkst din"
                }
            ],
            "establishment_year": 1941
        },
        "18": {
            "company_name": "LIN",
            "activity": "Specialfabrik för tillverkning av tänger",
            "employees": 140,
            "annual_turnover": 9000000,
            "capital": 900000,
            "key_personnel": [
                {
                    "name": "Sven Wedén",
                    "position": "Styrelse"
                },
                {
                    "name": "Lennart Eklöf",
                    "position": "Styrelse"
                }
            ],
            "establishment_year": 1856
        },
        "19": {
            "company_name": "TAR",
            "employees": 25,
            "annual_turnover": 2000000,
            "capital": 70000,
            "key_personnel": [
                {
                    "name": "Sög Olof Tamén",
                    "position": "Verkst dir"
                }
            ],
            "establishment_year": 1948
        },
        "20": {
            "company_name": "TANDSBYNS MEK VERKSTAD BR ERICSON & CO",
            "address": "Tandsb.vn, Box 78",
            "phone_number": "063-542 20",
            "bank_details": {
                "bankgiro": "777-8962",
                "postgiro": "274056-1"
            },
            "activity": "Tillverkar motorsågar",
            "employees": 40,
            "key_personnel": [
                {
                    "name": "Olof Einar Andersson",
                    "position": "Chef"
                },
                {
                    "name": "Sven Hugo Ericson",
                    "position": "Chef"
                },
                {
                    "name": "Carl Stefan Ericson",
                    "position": "Chef"
                }
            ],
            "establishment_year": 1943
        },
        "21": {
            "company_name": "TANK & SVETS AB",
            "address": "Enstaberga, Box 40",
            "phone_number": "0155-57117, 570 12",
            "postgiro": "264432",
            "activity": "Tillverkar oljecisterner o farmaggregat",
            "capital": 25000,
            "key_personnel": [
                {
                    "name": "H Anderson",
                    "position": "Firmatecknare"
                },
                {
                    "name": "S.Anderson",
                    "position": "Firmatecknare"
                }
            ],
            "establishment_year": 1953
        }
    }
}