{
    "original": "TB-PERSIENNER\n\nPnr 72219\n\nVästerås, Hülphersg 9. Tel\n021-1164 00. Bankgiro 220-1895.\nPostgiro 105340-4\n\nVerksamhet: Tillverkar persienner.\nSäljer persienner,\nmörkläggningsridåer, jalusier\nÅrsomsättning: 100 000\nChef: George Hoffsten\nEtableringsår: 1955.\n\nCIRRUS AB\n\nPnr 573 00\n\nTranås, V Järnvägsg 3. Tel\n0140-130 30. Bankgiro 365-6121.\nPostgiro 509920-5. Tga Cirrus\nVerksamhet: Tillverkar\nskumgummi o skumplastartiklar\nAntal anställda: 160\nÅrsomsättning: 20 000 000\nAktiekapital: 100000\nVerkst dir: Bo Fjaestad\nEtableringsår: 1956.\n\nNORDLUND AB, AXEL\n\nPnr 41119\n\nGöteborg, Kungsg 10. Tel\n031-13 16 53, 13 16 82. Postgiro 44273.\nTga Anotex. Telex 2526\nVerksamhet: Textilagentur\nAntal anställda: 5\nAktiekapital: 20 000\nVerkst dir: Axel Nordlund\nEtableringsår: 1953.\n\nNORDLUND AB,\nAUTOMOBIL-FIRMAN J G\n\nPnr 871 00\n\nHärnösand, Box 109. Bergsg 12.\n\nTel 0611-131 40. Postgiro 9242.\nTga Bilnordlund\nVerksamhet: Återförsäljare för\nSaab-Scania lastbilar o AB Svenska\nVolkswagen personbilar\nAntal anställda: 100\nÅrsomsättning: 14 000 000\nAktiekapital: 450000\nVerkst dir: j Gunnar Nordlund\nEtableringsår: 1924.\n\nNORDMARKS SMIDES. &amp;\nMEK VERKSTAD\n\nPnr 824 00\n\nHudiksvall, Nybruksv 4. Tel\n0650-109 94. Postgiro 396131\nVerksamhet: Tillverkar\nbyggnads-smide, cisterner mm\nChef: E E Nordmark, N B\nNordmark\n\nEtableringsår: 1909.\n\nNORDMARK - KLARÄLVENS\nJÄRNVÄGAR AB\n\nPnr 683 01\n\nHagfors 1, Fack. Tel 0563-11000.\nPostgiro 8201-6. Tga\nKlarälvsbanorna\n\nVerksamhet: järnvägs- o\nlastbilstransporter. Resebyrå\nAntal anställda: 130\nÅrsomsättning: 8 000 000\nAktiekapital: 4 500 000\nVerkst dir: Valter Hjelm\nEtableringsår: 1880\nDotterbolag till Uddeholms AB.\n\nNORDPOOLEN SCANDINAVIAN\nMARKETING SERVICES AB\n\nPnr 12185\n\nJohanneshov. Tel 08-913030.\nBankgiro 44-6927. Postgiro 56430.\nTga Lejltin\n\nVerksamhet: Auktoriserad\nannonsbyrå, av TU nomineringsförmedlad\nDotterföretag: 113 83 Stockholm 6.\nLeijon &amp; Ltining i Stockholm AB,\nBox 6504. Tel 08-1517 80\n114 55 Stockholm. Norman, Craig\n&amp; Kummel AB, Grev Magnig 6.\nTel 08-63 0 1 70\n\n200 31 Malmö 15. Leijon &amp; Ltining\ni Malmö AB, Box 15027. Tel\n040-94 5160\n\nAntal anställda: 70\nÅrsomsättning: 25 000 000\nAktiekapital: 780 000\nVerkst dir: Krister Lüning\nEtableringsår: 1961.\n\nall-gravyr\nk-g davidsson ab\n\nPnr 555 90\n\nJönköping, Furubacksv 10. Tel\n036-660 77. Bankgiro 835-6693.\nPostgiro 515390-3\nVerksamhet: Industri- o skyltgra-\n\nvering\n\nÄgare o chef: K G Davidsson\nEtableringsår: 1959.\n\nHASSELBLAD &amp; CO, AB F W\n\nPnr 41110\n\nGöteborg C, O Hamng 3. Tel\n031-17 19 60. Bankgiro 50-6507.\nPostgiro 40724. Telex 2279. Tga\nHasselblads\n\nAktiekapital: 5 650 000\nVerkst dir: Victor Hasselblad\nEtableringsår: 1841.\n\nBERG, AB GÖSTA\n\nPnr 114 49\n\nStockholm, Karlav 62. Tel\n08-67 97 60. Bankgiro 211-1607.\nPost-giro 152790-2. Tga Motorberg.\nTelex 19399 GBERG S\nVerksamhet: Säljer båtar o\nmotorer\n\nAntal anställda: 60\nÅrsomsättning: 13 500 000\nAktiekapital: 100 000\nVerkst dir: Gunnar Sundman\nEtableringsår: 1937.\n\nBERG EXPORT-IMPORT AB,\nGÖSTA\n\nPnr 41135\n\nGöteborg, Chalmersg 11. Tel\n031-11 50 20. Postgiro 427659-8. Tga\nCoalberg\n\nVerksamhet: Import o export av\nbränslevaror samt import av tunga\nkemikalier\n\nÅrsomsättning: 3 000 000\nAktiekapital: 5 000\nStyrelse: Fru Greta Berg (ordf),\nfru Solveig Lindahl\nEtableringsår: 1958.\n\nAEROSOL PRODUKTER, AB\n\nPnr 114 29\n\nStockholm, Birger Jarlsg 32. Tel\n08-218179. Bankgiro 73-4027.\nPostgiro 502662. Tga\nAerosolprodukt\n\nVerksamhet: Provförsäljning av\nkem tekn preparat i aerosoler\nAktiekapital: 30 000\nVerkst dir: B Löwenberg\nEtableringsår: 1953.\n\nBJU\n\n0411-136 00. Bankgiro 67-0123.\nPostgiro 97000. Telex 32341\nVerksamhet: Tidningsutgivning.\n(Ystads Allehanda) samt\naccidens-o tidskriftstryckeri\nAntal anställda: 120\nÅrsomsättning: 8 200 000\nVerkst dir: Adv Fredrik Björnberg\nV verkst dir: civilekonom Stellan\nMörner\n\nRedaktionschef: Orvar Nilsson\nAnnonschef: Lennart Brandt\nEtableringsår: 1873.\n\nBJURSTROMS GEOTEKNISKA\nBYRÅ AB\n\nPnr 18121\n\nLidingö 1, Box 136. Grenstigen 2 A.\nTel 08-765 25 95. Bankgiro564-7268.\nPostgiro 254791-7\nVerksamhet: Geotekniska,\ngeologiska o geofysiska undersökningar.\nGrundvatten. Erosion\nAntal anställda: 25\nÅrsomsättning: 2 000000\nAktiekapital: 5000\nStyrelse: Dr Gösta Bjurström(ordf),\nark Kjell Wretling\nVerkst dir: Fil lic, civiling Gösta\nBJurström\n\nÖveringenjör: Geotekniker Laimonis\nLakka\n\nIngenjör: Geotekniker Mats\nHellström\n\nCivilingenjör: Geofysiker östen\nHansson\n\nEtableringsår: 1945.\n\nOSTROM &amp; FISCHER AB\n\nPnr 660 50\n\nVålberg. Tel 054-420 50. Bankgiro\n10-0022. Postgiro 11911. Tga\nOstrom, Karlstad\n\nVerksamhet: Tillverkar bobiner o\nandra svarvade artiklar\nAntal anställda: 15\nÅrsomsättning: 1000 000\nAktiekapital: 200 000\nVerkst dir: Disp Erling Kylenfelt.\n\nOSTSVENSKA\nTRÄDGÄRDS-PRODUKTER AB\n\nPnr 12173\n\nJohanneshov, Brunnbyv 20. Tel\n08-8104 30. Bankgiro 74-8516.\nPostgiro 602326-1\nVerksamhet: Försäljning av frukt\no grönsaker i parti\nAntal anställda: 5\nÅrsomsättning: 7 500 000\n\nAktiekapital: 10 000\nVerkst dir Töre Norman\nEtableringsår: 1960.\n\nUVA, AB\n\nPnr 16131\n\nBromma, Johannesfredsv 15-17.\nTel 08-25 25 10. Bankgiro\n605-3029. Postgiro 6500-3. Tga UVA\nVerkab, Stockholm. Telex 19904\n\nUVA\n\nVerksamhet: Tillverkar\nhålslip-maskiner o slipspindlar,\nhydrauliska apparater, hydrauliska växlar\nför järnvägsdrift m m\nVarunamn: Uva\nAntal anställda: 330\nÅrsomsättning: 17 400 000\nAktiekapital: 4000 000\nVerkst dir: Lennart Odqvist\nTekn din Gerszon Gluchowicz\nFörsäljn-chef: Kurt Gustavsson\nProduktionschef: Bertil Aronsson\nEkonomichef: Dan Persson\nEtableringsår: 1928.",
    "structured": {
        "1": {
            "company_name": "TB-PERSIENNER",
            "pnr": "72219",
            "address": "Västerås, Hülphersg 9",
            "phone_number": "021-1164 00",
            "bank_details": {
                "bankgiro": "220-1895",
                "postgiro": "105340-4"
            },
            "activity": "Tillverkar persienner. Säljer persienner, mörkläggningsridåer, jalusier",
            "annual_turnover": 100000,
            "key_personnel": [
                {
                    "name": "George Hoffsten",
                    "position": "Chef"
                }
            ],
            "establishment_year": 1955
        },
        "2": {
            "company_name": "CIRRUS AB",
            "pnr": "573 00",
            "address": "Tranås, V Järnvägsg 3",
            "phone_number": "0140-130 30",
            "bank_details": {
                "bankgiro": "365-6121",
                "postgiro": "509920-5"
            },
            "activity": "Tillverkar skumgummi o skumplastartiklar",
            "employees": 160,
            "annual_turnover": 20000000,
            "capital": 100000,
            "key_personnel": [
                {
                    "name": "Bo Fjaestad",
                    "position": "Verkst dir"
                }
            ],
            "establishment_year": 1956
        },
        "3": {
            "company_name": "NORDLUND AB, AXEL",
            "pnr": "41119",
            "address": "Göteborg, Kungsg 10",
            "phone_number": "031-13 16 53, 13 16 82",
            "postgiro": "44273",
            "activity": "Textilagentur",
            "employees": 5,
            "capital": 20000,
            "key_personnel": [
                {
                    "name": "Axel Nordlund",
                    "position": "Verkst dir"
                }
            ],
            "establishment_year": 1953
        },
        "4": {
            "company_name": "NORDLUND AB, AUTOMOBIL-FIRMAN J G",
            "pnr": "871 00",
            "address": "Härnösand, Box 109, Bergsg 12",
            "phone_number": "0611-131 40",
            "postgiro": "9242",
            "activity": "Återförsäljare för Saab-Scania lastbilar o AB Svenska Volkswagen personbilar",
            "employees": 100,
            "annual_turnover": 14000000,
            "capital": 450000,
            "key_personnel": [
                {
                    "name": "j Gunnar Nordlund",
                    "position": "Verkst dir"
                }
            ],
            "establishment_year": 1924
        },
        "5": {
            "company_name": "NORDMARKS SMIDES. & MEK VERKSTAD",
            "pnr": "824 00",
            "address": "Hudiksvall, Nybruksv 4",
            "phone_number": "0650-109 94",
            "postgiro": "396131",
            "activity": "Tillverkar byggnads-smide, cisterner mm",
            "key_personnel": [
                {
                    "name": "E E Nordmark, N B Nordmark",
                    "position": "Chef"
                }
            ],
            "establishment_year": 1909
        },
        "6": {
            "company_name": "NORDMARK - KLARÄLVENS JÄRNVÄGAR AB",
            "pnr": "683 01",
            "address": "Hagfors 1, Fack",
            "phone_number": "0563-11000",
            "postgiro": "8201-6",
            "activity": "Järnvägs- o lastbilstransporter. Resebyrå",
            "employees": 130,
            "annual_turnover": 8000000,
            "capital": 4500000,
            "key_personnel": [
                {
                    "name": "Valter Hjelm",
                    "position": "Verkst dir"
                }
            ],
            "establishment_year": 1880
        },
        "7": {
            "company_name": "NORDPOOLEN SCANDINAVIAN MARKETING SERVICES AB",
            "pnr": "12185",
            "address": "Johanneshov",
            "phone_number": "08-913030",
            "bank_details": {
                "bankgiro": "44-6927",
                "postgiro": "56430"
            },
            "activity": "Auktoriserad annonsbyrå, av TU nomineringsförmedlad",
            "employees": 70,
            "annual_turnover": 25000000,
            "capital": 780000,
            "key_personnel": [
                {
                    "name": "Krister Lüning",
                    "position": "Verkst dir"
                }
            ],
            "establishment_year": 1961
        },
        "8": {
            "company_name": "all-gravyr k-g davidsson ab",
            "pnr": "555 90",
            "address": "Jönköping, Furubacksv 10",
            "phone_number": "036-660 77",
            "bank_details": {
                "bankgiro": "835-6693",
                "postgiro": "515390-3"
            },
            "activity": "Industri- o skyltgravering",
            "key_personnel": [
                {
                    "name": "K G Davidsson",
                    "position": "Ägare o chef"
                }
            ],
            "establishment_year": 1959
        },
        "9": {
            "company_name": "HASSELBLAD & CO, AB F W",
            "pnr": "41110",
            "address": "Göteborg C, O Hamng 3",
            "phone_number": "031-17 19 60",
            "bank_details": {
                "bankgiro": "50-6507",
                "postgiro": "40724"
            },
            "activity": "Försäljning av båtar o motorer",
            "employees": 60,
            "annual_turnover": 13500000,
            "capital": 5650000,
            "key_personnel": [
                {
                    "name": "Victor Hasselblad",
                    "position": "Verkst dir"
                }
            ],
            "establishment_year": 1841
        },
        "10": {
            "company_name": "BERG, AB GÖSTA",
            "pnr": "114 49",
            "address": "Stockholm, Karlav 62",
            "phone_number": "08-67 97 60",
            "bank_details": {
                "bankgiro": "211-1607",
                "postgiro": "152790-2"
            },
            "activity": "Säljer båtar o motorer",
            "employees": 60,
            "annual_turnover": 13500000,
            "capital": 100000,
            "key_personnel": [
                {
                    "name": "Gunnar Sundman",
                    "position": "Verkst dir"
                }
            ],
            "establishment_year": 1937
        },
        "11": {
            "company_name": "BERG EXPORT-IMPORT AB, GÖSTA",
            "pnr": "41135",
            "address": "Göteborg, Chalmersg 11",
            "phone_number": "031-11 50 20",
            "postgiro": "427659-8",
            "activity": "Import o export av bränslevaror samt import av tunga kemikalier",
            "annual_turnover": 3000000,
            "capital": 5000,
            "key_personnel": [
                {
                    "name": "Fru Greta Berg",
                    "position": "Styrelse (ordf)"
                },
                {
                    "name": "fru Solveig Lindahl",
                    "position": "Styrelse"
                }
            ],
            "establishment_year": 1958
        },
        "12": {
            "company_name": "AEROSOL PRODUKTER, AB",
            "pnr": "114 29",
            "address": "Stockholm, Birger Jarlsg 32",
            "phone_number": "08-218179",
            "bank_details": {
                "bankgiro": "73-4027",
                "postgiro": "502662"
            },
            "activity": "Provförsäljning av kem tekn preparat i aerosoler",
            "capital": 30000,
            "key_personnel": [
                {
                    "name": "B Löwenberg",
                    "position": "Verkst dir"
                }
            ],
            "establishment_year": 1953
        },
        "13": {
            "company_name": "BJU",
            "phone_number": "0411-136 00",
            "bank_details": {
                "bankgiro": "67-0123",
                "postgiro": "97000"
            },
            "activity": "Tidningsutgivning. (Ystads Allehanda) samt accidens-o tidskriftstryckeri",
            "employees": 120,
            "annual_turnover": 8200000,
            "key_personnel": [
                {
                    "name": "Adv Fredrik Björnberg",
                    "position": "Verkst dir"
                },
                {
                    "name": "civilekonom Stellan Mörner",
                    "position": "V verkst dir"
                },
                {
                    "name": "Orvar Nilsson",
                    "position": "Redaktionschef"
                },
                {
                    "name": "Lennart Brandt",
                    "position": "Annonschef"
                }
            ],
            "establishment_year": 1873
        },
        "14": {
            "company_name": "BJURSTROMS GEOTEKNISKA BYRÅ AB",
            "pnr": "18121",
            "address": "Lidingö 1, Box 136, Grenstigen 2 A",
            "phone_number": "08-765 25 95",
            "bank_details": {
                "bankgiro": "564-7268",
                "postgiro": "254791-7"
            },
            "activity": "Geotekniska, geologiska o geofysiska undersökningar. Grundvatten. Erosion",
            "employees": 25,
            "annual_turnover": 2000000,
            "capital": 5000,
            "key_personnel": [
                {
                    "name": "Dr Gösta Bjurström",
                    "position": "Styrelse (ordf)"
                },
                {
                    "name": "ark Kjell Wretling",
                    "position": "Styrelse"
                },
                {
                    "name": "Fil lic, civiling Gösta Bjurström",
                    "position": "Verkst dir"
                }
            ],
            "establishment_year": 1945
        },
        "15": {
            "company_name": "OSTROM & FISCHER AB",
            "pnr": "660 50",
            "address": "Vålberg",
            "phone_number": "054-420 50",
            "bank_details": {
                "bankgiro": "10-0022",
                "postgiro": "11911"
            },
            "activity": "Tillverkar bobiner o andra svarvade artiklar",
            "employees": 15,
            "annual_turnover": 1000000,
            "capital": 200000,
            "key_personnel": [
                {
                    "name": "Disp Erling Kylenfelt",
                    "position": "Verkst dir"
                }
            ],
            "establishment_year": 1953
        },
        "16": {
            "company_name": "OSTSVENSKA TRÄDGÄRDS-PRODUKTER AB",
            "pnr": "12173",
            "address": "Johanneshov, Brunnbyv 20",
            "phone_number": "08-8104 30",
            "bank_details": {
                "bankgiro": "74-8516",
                "postgiro": "602326-1"
            },
            "activity": "Försäljning av frukt o grönsaker i parti",
            "employees": 5,
            "annual_turnover": 7500000,
            "capital": 10000,
            "key_personnel": [
                {
                    "name": "Töre Norman",
                    "position": "Verkst dir"
                }
            ],
            "establishment_year": 1960
        },
        "17": {
            "company_name": "UVA, AB",
            "pnr": "16131",
            "address": "Bromma, Johannesfredsv 15-17",
            "phone_number": "08-25 25 10",
            "bank_details": {
                "bankgiro": "605-3029",
                "postgiro": "6500-3"
            },
            "activity": "Tillverkar hålslip-maskiner o slipspindlar, hydrauliska apparater, hydrauliska växlar för järnvägsdrift m m",
            "employees": 330,
            "annual_turnover": 17400000,
            "capital": 4000000,
            "key_personnel": [
                {
                    "name": "Lennart Odqvist",
                    "position": "Verkst dir"
                },
                {
                    "name": "Gerszon Gluchowicz",
                    "position": "Tekn din"
                },
                {
                    "name": "Kurt Gustavsson",
                    "position": "Försäljn-chef"
                },
                {
                    "name": "Bertil Aronsson",
                    "position": "Produktionschef"
                },
                {
                    "name": "Dan Persson",
                    "position": "Ekonomichef"
                }
            ],
            "establishment_year": 1928
        }
    }
}