{
    "original": "DELTAFOR AKTIEBOLAG\n\nPnr 590 57\n\nMalmslätt. Tel 013-95105.\nBankgiro 276-6004. Postgiro 251761-3\nVerksamhet: Tillverkning o\nförsäljning av vitamin- o mineralfoder,\nensileringsmedel m m\nVarunamn: Calcifcr, Deltamin,\nDeltaplex\n\nAntal anställda: 10\nÅrsomsättning: 1 800 000\nAktiekapital: 60 000\nStyrelse: Adv Britt Åström (ordf),\ndisp Ivar Månsson, fru Olga Månsson\nVerkst dir: Disp Ivar Månsson\nKontorschef: Ake Weinerfelt\nEtableringsår: 1944.\n\nNORBA AB\n\nPnr 38401\n\nBlomstermåla 1, Box 1. Tel\n0499-20650. Bankgiro 148-2215.\nPostgiro 8615-7. Tga Norba\nVerksamhet: Tillverkar\nsophämtningsaggregat, stationära\nkomprima-torer, förbränningsugnar, sopkärl,\nsäckhållare, gjutgods o\ngalvanise-ringsarbeten\nVarunamn: Norba\nAntal anstäUda: 300\nAktiekapital: 420000\nVerkst dir: Börge Westergren\nEtableringsår: 1913.\n\nHOL\n\nStyrelse: Ingolf Holmström, Barbro\nHolmström\nEtableringsår. 1959\nOmbildat till aktiebolag 1961.\n\nHOLMSTROM AB, PELLE\n\nPnr 89101\n\nÖrnsköldsvik 1, Fabriksg 7. Box\n17. Tel 0660-11164, 11274.\nBankgiro 62-6915. Postgiro 62446\nVerksamhet: Försäljning i parti av\nmode- o metervaror\nAntal anställda: 10\nÅrsomsättning: 2000 000\nAktiekapital: 100 000\nVerkst dir: Kjell Kallin\nEtableringsår: 1914.\n\nHOLMSTROM, RÖRLEDNINGS\nAB T\n\nPnr 250 04\n\nHelsingborg 4, Box 4008.\nGustavs-lundsv, Nya Gustavslund. Tel\n042-965 85. Bankgiro 268-9222.\nPostgiro 133534\n\nVerksamhet: Utför\nVVS-installa-tioner\n\nAntal anställda: 45\n\nAktiekapital: 100 000\n\nStyrelse: Fabr Tage Holmström,\n\n(ordf), ing Per-Erik Holmström,\n\ning Stig Holmström\n\nVerkst dir: Ing Per-Erik Holmström\n\nEtableringsår: 1945.\n\nHAGGSTRUM AB, T A\n\nPnr 417 24\n\nGöteborg, Rösebergsg 7. Tel\n031-530643, 53 06 34. Postgiro 49644-8.\nTelex 20912. Tga Tahtex\nVerksamhet: Agenturfirma i garner\no maskiner\nAntal anställda: 5\nÅrsomsättning: 30 000 000\nAktiekapital: 5 000\nVerkst dir: Tor-Arne Häggström\nEtableringsår: 1962.\n\nDACKES GOLV AB\n\nPnr 360 31\n\nHelgevärma. Tel 0470-606 35\nVerksamhet: Säljer parkett,\nlino-leum, heltäckande mattor o\nplastfiltmattor, ryamattor m m\nChef: Stig Dacke.\n\nDAFFE &amp; CO AB\n\nPnr 103 82\n\nStockholm 7, Box 7099.\nNorrmalmstorg 1. Tel 08-10 07 34, 1007 43.\nPostgiro 401890-9. Tga Daffeco\nVerksamhet: Motorer, släpfordon,\nlyfttruckar, karosserier, kapell,\nbil- o båttillbehör, elektroniska\ninstrument, epoxifärger av 1- o\n2-komponentstyp, markerfärg,\nrostskyddsfärg, impregneringsmedel\nÅrsomsättning: 400 000\nAktiekapital: 5 000\nVerkst dir: David Larsson\nDisp: Anders Wester\nEtableringsår: 1966.\n\nGUSUMS BRUK AB\n\nPnr 61040\n\nGusum. Tel 0123-204 00. Telex\n64027. Tga Gusumbruk, Norrköping\nVerksamhet: Metallduksväveri för\nalla slag av dukar, däribland s k\nviror upp till 9,35 m bredd för\npappersmaskiner. Tillverkar band,\nstänger, profiler, rör, tråd av\nmässing, koppar, brons, knappnålar,\nblixtlås, kulkedjor m m\nAvdelningskontor: Gnosjö. Tel\n0370-915 39\n\nHelsingborg. Tel 042-12 5012\nGöteborg. Tel 031-131045,1122 02\nNorrköping. Tel 011-18 0195\nStockholm. Tel 08-44 98 1 5\nAntal anställda: 628\nÅrsomsättning: 124 000 000\nTaxeringsvärde: 23 471000\nAktiekapital: 9 660 000\nStyrelseordf: Konsul Tryggve Holm\nVerkst dir: Lennart Torstenson\nTekn dir: N-O Engström\nFörsäljn-dir: Walter G Grenstadius\nEkonomichef: Harry Friberg\nInköpschef: Stig Ringström\nInspektor: Lennart Horgby\nSkogsmäst: John Åkesson\nEtableringsår: 1653.\n\nE-MODUL AB\n\nPnr 66001\n\nEd, Industrig. Tel 0534-104 75,\n10480. Bankgiro 40-0749. Postgiro\n260685. Tga Emodul\nVerksamhet: Tillverkning av\nhelfärdiga badrum, toalettenheter o\ns k våtväggar för byggnadsbranschen\nAntal anställda: 10\nAktiekapital: 75 000\nStyrelse: Lennart Ericsson (ordf),\nTerje Braaten, Roland Eriksson,\nTage Eriksson, Osten Eriksson,\nGöran Kron\n\nVerkst dir: Tage Eriksson\nEtableringsår 1969.\n\nCANDERT 8. CO AB, KNUT\n\nPnr 104 25\n\nStockholm 30, Lindhagensg 128.\nBox 30048. Tel 08-23 77 45.\nBankgiro 33-1726. Postgiro 351428\nVerksamhet: Allt i kontorsmateriel:\nKuvert, trycksaker o plastpärmar för\nolika ändamål\nVerkst dir: Knut K Candert\nEtableringsår: 1947.\n\nMONTUR, RURLEDNINGS-AB\n\nPnr 113 57\n\nStockholm, Rehnsg 5. Tel\n08-34 99 10. Bankgiro 73-4506.\nPost-giro 3680\n\nVerksamhet: Utför gas-, vatten-,\navlopps-, värmelednings-,\nventilations- o oljeeldningsanläggningar.\nLedningar för högtrycksånga o\ntryckluft, oljelagringsanläggningar\n\nÅrsomsättning: 16 000 000\nAktiekapital: 200 000\nVerkst dir: Yngve Permert\nEtableringsår: 1910.\n\nDORMITFABRIKEN\n\nPnr 770 71\n\nStjärnsund, Dormsjö. Tel\n0225-230 39. Postgiro 387650\nVerksamhet: Tillverkar träull\nAntal anställda: 9\nÅrsomsättning: 600000\nChef: G Friström\nEtableringsår: 1936.",
    "structured": {
        "1": {
            "Företagsnamn": "DELTAFOR AKTIEBOLAG",
            "Pnr": "590 57",
            "Adress": "Malmslätt",
            "Telefonnummer": "013-95105",
            "Bankuppgifter": {
                "Bankgiro": "276-6004",
                "Postgiro": "251761-3"
            },
            "Verksamhet": "Tillverkning o försäljning av vitamin- o mineralfoder, ensileringsmedel m m",
            "Antal anställda": 10,
            "Årsomsättning": 1800000,
            "Aktiekapital": 60000,
            "Styrelse": "Adv Britt Åström (ordf), disp Ivar Månsson, fru Olga Månsson",
            "Verkställande direktör": "Disp Ivar Månsson",
            "Kontorschef": "Ake Weinerfelt",
            "Etableringsår": 1944
        },
        "2": {
            "Företagsnamn": "NORBA AB",
            "Pnr": "38401",
            "Adress": "Blomstermåla 1, Box 1",
            "Telefonnummer": "0499-20650",
            "Bankuppgifter": {
                "Bankgiro": "148-2215",
                "Postgiro": "8615-7"
            },
            "Verksamhet": "Tillverkar sophämtningsaggregat, stationära komprimatorer, förbränningsugnar, sopkärl, säckhållare, gjutgods o galvaniseringsarbeten",
            "Antal anställda": 300,
            "Aktiekapital": 420000,
            "Verkställande direktör": "Börge Westergren",
            "Etableringsår": 1913
        },
        "3": {
            "Företagsnamn": "HOLMSTROM AB, PELLE",
            "Pnr": "89101",
            "Adress": "Örnsköldsvik 1, Fabriksg 7, Box 17",
            "Telefonnummer": "0660-11164, 11274",
            "Bankuppgifter": {
                "Bankgiro": "62-6915",
                "Postgiro": "62446"
            },
            "Verksamhet": "Försäljning i parti av mode- o metervaror",
            "Antal anställda": 10,
            "Årsomsättning": "2000 000",
            "Aktiekapital": 100000,
            "Verkställande direktör": "Kjell Kallin",
            "Etableringsår": 1914
        },
        "4": {
            "Företagsnamn": "HOLMSTROM, RÖRLEDNINGSAB T",
            "Pnr": "250 04",
            "Adress": "Helsingborg 4, Box 4008, Gustavslundsv, Nya Gustavslund",
            "Telefonnummer": "042-965 85",
            "Bankuppgifter": {
                "Bankgiro": "268-9222",
                "Postgiro": "133534"
            },
            "Verksamhet": "Utför VVS-installationer",
            "Antal anställda": 45,
            "Aktiekapital": 100000,
            "Styrelse": "Fabr Tage Holmström (ordf), ing Per-Erik Holmström, ing Stig Holmström",
            "Verkställande direktör": "Ing Per-Erik Holmström",
            "Etableringsår": 1945
        },
        "5": {
            "Företagsnamn": "HAGGSTRUM AB, TA",
            "Pnr": "417 24",
            "Adress": "Göteborg, Rösebergsg 7",
            "Telefonnummer": "031-530643, 53 06 34",
            "Postgiro": "49644-8",
            "Telex": "20912",
            "Verksamhet": "Agenturfirma i garner o maskiner",
            "Antal anställda": 5,
            "Årsomsättning": "30000000",
            "Aktiekapital": 5000,
            "Verkställande direktör": "Tor-Arne Häggström",
            "Etableringsår": 1962
        },
        "6": {
            "Företagsnamn": "DACKES GOLV AB",
            "Pnr": "360 31",
            "Adress": "Helgevärma",
            "Telefonnummer": "0470-606 35",
            "Verksamhet": "Säljer parkett, linoleum, heltäckande mattor o plastfiltmattor, ryamattor m m",
            "Chef": "Stig Dacke",
            "Etableringsår": null
        },
        "7": {
            "Företagsnamn": "DAFFE & CO AB",
            "Pnr": "103 82",
            "Adress": "Stockholm 7, Box 7099, Norrmalmstorg 1",
            "Telefonnummer": "08-10 07 34, 1007 43",
            "Postgiro": "401890-9",
            "Tga": "Daffeco",
            "Verksamhet": "Motorer, släpfordon, lyfttruckar, karosserier, kapell, bil- o båttillbehör, elektroniska instrument, epoxifärger av 1- o 2-komponentstyp, markerfärg, rostskyddsfärg, impregneringsmedel",
            "Årsomsättning": 400000,
            "Aktiekapital": 5000,
            "Verkställande direktör": "David Larsson",
            "Disp": "Anders Wester",
            "Etableringsår": 1966
        },
        "8": {
            "Företagsnamn": "GUSUMS BRUK AB",
            "Pnr": "61040",
            "Adress": "Gusum",
            "Telefonnummer": "0123-204 00",
            "Telex": "64027",
            "Tga": "Gusumbruk, Norrköping",
            "Verksamhet": "Metallduksväveri för alla slag av dukar, däribland s k viror upp till 9,35 m bredd för pappersmaskiner. Tillverkar band, stänger, profiler, rör, tråd av mässing, koppar, brons, knappnålar, blixtlås, kulkedjor m m",
            "Avdelningskontor": {
                "Gnosjö": "Tel 0370-915 39",
                "Helsingborg": "Tel 042-12 5012",
                "Göteborg": "Tel 031-131045,1122 02",
                "Norrköping": "Tel 011-18 0195",
                "Stockholm": "Tel 08-44 98 1 5"
            },
            "Antal anställda": 628,
            "Årsomsättning": 124000000,
            "Taxeringsvärde": "23471000",
            "Aktiekapital": 9660000,
            "Styrelseordf": "Konsul Tryggve Holm",
            "Verkställande direktör": "Lennart Torstenson",
            "Teknisk direktör": "N-O Engström",
            "Försäljningsdirektör": "Walter G Grenstadius",
            "Ekonomichef": "Harry Friberg",
            "Inköpschef": "Stig Ringström",
            "Inspektor": "Lennart Horgby",
            "Skogsmästare": "John Åkesson",
            "Etableringsår": 1653
        },
        "9": {
            "Företagsnamn": "E-MODUL AB",
            "Pnr": "66001",
            "Adress": "Ed, Industrig",
            "Telefonnummer": "0534-104 75, 10480",
            "Bankuppgifter": {
                "Bankgiro": "40-0749",
                "Postgiro": "260685"
            },
            "Tga": "Emodul",
            "Verksamhet": "Tillverkning av helfärdiga badrum, toalettenheter o s k våtväggar för byggnadsbranschen",
            "Antal anställda": 10,
            "Aktiekapital": 75000,
            "Styrelse": "Lennart Ericsson (ordf), Terje Braaten, Roland Eriksson, Tage Eriksson, Osten Eriksson, Göran Kron",
            "Verkställande direktör": "Tage Eriksson",
            "Etableringsår": 1969
        },
        "10": {
            "Företagsnamn": "CANDERT 8. CO AB, KNUT",
            "Pnr": "104 25",
            "Adress": "Stockholm 30, Lindhagensg 128, Box 30048",
            "Telefonnummer": "08-23 77 45",
            "Bankuppgifter": {
                "Bankgiro": "33-1726",
                "Postgiro": "351428"
            },
            "Verksamhet": "Allt i kontorsmateriel: Kuvert, trycksaker o plastpärmar för olika ändamål",
            "Verkställande direktör": "Knut K Candert",
            "Etableringsår": 1947
        },
        "11": {
            "Företagsnamn": "MONTUR, RURLEDNINGS-AB",
            "Pnr": "113 57",
            "Adress": "Stockholm, Rehnsg 5",
            "Telefonnummer": "08-34 99 10",
            "Bankuppgifter": {
                "Bankgiro": "73-4506",
                "Postgiro": "3680"
            },
            "Verksamhet": "Utför gas-, vatten-, avlopps-, värmelednings-, ventilations- o oljeeldningsanläggningar. Ledningar för högtrycksånga o tryckluft, oljelagringsanläggningar",
            "Årsomsättning": 16000000,
            "Aktiekapital": 200000,
            "Verkställande direktör": "Yngve Permert",
            "Etableringsår": 1910
        },
        "12": {
            "Företagsnamn": "DORMITFABRIKEN",
            "Pnr": "770 71",
            "Adress": "Stjärnsund, Dormsjö",
            "Telefonnummer": "0225-230 39",
            "Postgiro": "387650",
            "Verksamhet": "Tillverkar träull",
            "Antal anställda": 9,
            "Årsomsättning": 600000,
            "Chef": "G Friström",
            "Etableringsår": 1936
        }
    }
}