{
    "original": "STILMUNSTER, AB\n\nPnr 103 62\n\nStockholm 3, Sveav 53. Box 3148.\nTel 08-24 22 60, 26 26 50. Bankgiro\n575-1813. Postgiro 195456-9. Tga\nStilmoenster\n\nVerksamhet: Tillverkar o säljer\npappers mönster\nAntal anstäUda: 110\nÅrsomsättning: 8 000 000\nAktiekapital: 900 000\nVerkst dir: Johan Bonnier\nEtableringsår: 1945.\n\nVUL\n\nVerksamhet: Tillverkar o säljer\nsnöplogar, sidovingar mm\nAntal anställda: 30\nÅrsomsättning: 2 000 000\nAktiekapital: 75 000\nEtableringsår: 1963.\n\nHOLMYS, ATELJÉ\n\nPnr 12122\n\nJohanneshov 1, Box 98. Ymsenv 14.\nTel 08-9199 97, 9133 22. Bankgiro\n74-4790. Postgiro 251359-6\nVeiksamhet: Tillverkar o säljer\nbrudkronor, diadem o bijouterier\nAntal anställda: 3\nChef: Sven Holm\nEtableringsår: 1944.\n\nVEL\n\nstämplar för kontor o industri\nAntal anställda: 20\nÅrsomsättning: 850 000\nStyrelse: Dir Nils Hellkvist\n(ordf), revisor Thore Edenholm,\nfabr Gottfrid Hellkvist\nVerkst dir. Nils Hellkvist\nFabr: Gottfrid Hellkvist\nEtableringsår 1958.\n\nWELLNER,\nINGENJÖRS-FIRMAN PER A\n\nPnr 41274\n\nGöteborg, Lillkulleg 11. Tel\n031-40 8865. Bankgiro 515-2475.\nPostgiro 42033-1\n\nVerksamhet: Försäljning av\nsvets-aggregat, svetshjälmar\nChef: Ing Per A Wellner\nEtableringsår: 1953.\n\nGOTLANDS NYA\nTEGELBRUKS AB\n\nPnr 62101\n\nVisby 1, Söderv 10. Fack. Tel\n0498-154 5 0\n\nVerksamhet: Tegel o rör\nFilial: Havdhem. Tel 0498-810 13\nAntal anställda: 19\nÅrsomsättning: 709 000\nAktiekapital: 43 000\nVerkst dir: Arne Rabne\nEtableringsår: 1914\nÄger Havdhems Tegelbruk.\n\nGOTLANDS SLIPSTENSBOLAG\nHUGO HANSEN &amp; CO\n\nPnr 62010\n\nBurgsvik, Box 7. Tel 0498-970 01,\n970 52. Bankgiro 83-5209.\nPost-giro 70853. Tga Slipstenbolaget,\nVisby\n\nVerksamhet: Tillverkar o säljer\nslipstenar o brynstenar samt\nutför alla sorters arbeten i sandsten\no gotlandskalksten för\nbyggnadsändamål\n\nAntal anställda: 22\nÅrsomsättning: 800 000\nChef: Dlr Victor Hansén\nEtableringsår: 1873.\n\nJÄMTFRAKT EK FÖRENING\n\nPnr 831 00\n\nÖstersund, Odensalag 39. Tel\n063-176 20. Bankgiro 427-4122. Postr\ngiro 126387-0\n\nVerksamhet Transport- o\nmaskinförmedling, grusförsäljning o\nschaktentreprenader\nAntal anställda: 16\nÅrsomsättning: 22000 000\nChef: Ing Erik Persson\nEtableringsår: 1967.\n\nEKBLAD &amp; CO,AB C O\n\nPnr 593 00\n\nVästervik, Stora Torget. Tel\n0490-13160. Bankgiro 66-7006.\nPostgiro 6411. Telex 3911\nVerksamhet: Boktryckeri,\nbokbinderi, förlag med tidningsutgivning\nAntal anställda: 117\nÅrsomsättning: 6 200 000\nAktiekapital: 300 000\nChef: Dir Olle Hultgren\nEtableringsår: 1834.\n\nEKBLADS INGENJORSBYRÅ\nAB, TEKN LIC K-G\n\nPnr 703 40\n\nÖrebro, Hertig Karls allé 18. Tel\n019-1300 70. Bankgiro 614-7086.\nPostgiro 116163-7\nVerksamhet: Konsulterande\ningen-jörsbyrå för hus- o\nindustribyggnader. Konstruktioner, projektering,\nutredningar o kontroll\nAntal anställda: 22\nChef: Tekn lic Karl-Göran Ekblad\nEtableringsår: 1956.\n\nABAT T ERICSSON AB\n\nPnr 701 03\n\nÖrebro 1, Box 213. Nyg 9. Tel\n019-14 0170. Bankgiro 614-7920.\nPostgiro 117171-0\n\nVerksamhet: Tillverkar o säljer\nspecialdetaljer för\nbyggnadsindustrin såsom luckor, lock, stegjärn\nm m av aluminium o järn. Uthyrning,\nförsäljning, reparation av allt inom\ntryckluft, pumpar, byggtorkar,\ntjältinare, generatorer m m\nVerkstad: Lillån, Västanbergsv.\nTel 019-322 27\nAntal anställda: 5\nÅrsomsättning: 1700 000\nAktiekapital: 25 000\nVerkst dir: Tage Ericsson\nEtableringsår: 1968.\n\nBALDER AB, TRYCKERI\n\nPnr 161 11\n\nBromma 11, Box 11056. Ulvsundav\n168. Tel 08-25 26 90. Bankgiro\n13-6133. Postgiro 2663\nVerksamhet: Boktryckeri o\nbokbinderi. Specialitet: tidskrifter o\nkataloger\n\nAntal anställda: 42\nÅrsomsättning: 2 800 000\nAktiekapital: 100 000\nVerkst dir: Folke Hallin\nDisp: Lennart Hallin\nEtableringsår: 1922.\n\nBALLINGSLOVS\nTRÄ-FÖRÄDLING, AB\n\nPnr 28014\n\nBallingslöv, Box 75. Tel\n0451-31200. Tga Btinredet\nVerksamhet: Tillverkar\nköksinredningar o förvaringsskåp\nAktiekapital: 765 000\nVerkst dir: Bertil Albinsson\nEtableringsår: 1929.\n\nDONSO NÄTFABRIK\n\nPnr 43082\n\nDonsö, Box 20. Tel 031-77 05 25,\n77 05 00. Bankgiro 55-5107.\nPostgiro 424510. Tga Donsö\nVerksamhet: Tillverkar\nplastbe-handlade grova fisknät\nAntal anställda: 17\nÅrsomsättning: 1000 000\nChefer: Polke Nyfeldt, Harry\nNy-feldt\n\nEtableringsår: 1950.",
    "structured": {
        "1": {
            "company_name": "STILMUNSTER, AB",
            "pnr": "103 62",
            "address": "Stockholm 3, Sveav 53. Box 3148",
            "phone_number": "08-24 22 60, 26 26 50",
            "bank_details": {
                "bankgiro": "575-1813",
                "postgiro": "195456-9"
            },
            "activity": "Tillverkar o säljer pappers mönster",
            "employees": 110,
            "annual_turnover": 8000000,
            "capital": 900000,
            "key_personnel": [
                {
                    "name": "Johan Bonnier",
                    "position": "Verkst dir"
                }
            ],
            "establishment_year": 1945
        },
        "2": {
            "company_name": "VUL",
            "activity": "Tillverkar o säljer snöplogar, sidovingar mm",
            "employees": 30,
            "annual_turnover": 2000000,
            "capital": 75000,
            "establishment_year": 1963
        },
        "3": {
            "company_name": "HOLMYS, ATELJÉ",
            "pnr": "12122",
            "address": "Johanneshov 1, Box 98. Ymsenv 14",
            "phone_number": "08-9199 97, 9133 22",
            "bank_details": {
                "bankgiro": "74-4790",
                "postgiro": "251359-6"
            },
            "activity": "Tillverkar o säljer brudkronor, diadem o bijouterier",
            "employees": 3,
            "key_personnel": [
                {
                    "name": "Sven Holm",
                    "position": "Chef"
                }
            ],
            "establishment_year": 1944
        },
        "4": {
            "company_name": "VEL",
            "activity": "stämplar för kontor o industri",
            "employees": 20,
            "annual_turnover": 850000,
            "key_personnel": [
                {
                    "name": "Nils Hellkvist",
                    "position": "Verkst dir"
                },
                {
                    "name": "Thore Edenholm",
                    "position": "revisor"
                },
                {
                    "name": "Gottfrid Hellkvist",
                    "position": "fabr"
                }
            ],
            "establishment_year": 1958
        },
        "5": {
            "company_name": "WELLNER, INGENJÖRS-FIRMAN PER A",
            "pnr": "41274",
            "address": "Göteborg, Lillkulleg 11",
            "phone_number": "031-40 8865",
            "bank_details": {
                "bankgiro": "515-2475",
                "postgiro": "42033-1"
            },
            "activity": "Försäljning av svets-aggregat, svetshjälmar",
            "employees": 0,
            "key_personnel": [
                {
                    "name": "Ing Per A Wellner",
                    "position": "Chef"
                }
            ],
            "establishment_year": 1953
        },
        "6": {
            "company_name": "GOTLANDS NYA TEGELBRUKS AB",
            "pnr": "62101",
            "address": "Visby 1, Söderv 10",
            "phone_number": "0498-154 5 0",
            "activity": "Tegel o rör",
            "employees": 19,
            "annual_turnover": 709000,
            "capital": 43000,
            "key_personnel": [
                {
                    "name": "Arne Rabne",
                    "position": "Verkst dir"
                }
            ],
            "establishment_year": 1914
        },
        "7": {
            "company_name": "GOTLANDS SLIPSTENSBOLAG HUGO HANSEN & CO",
            "pnr": "62010",
            "address": "Burgsvik, Box 7",
            "phone_number": "0498-970 01, 970 52",
            "bank_details": {
                "bankgiro": "83-5209",
                "postgiro": "70853"
            },
            "activity": "Tillverkar o säljer slipstenar o brynstenar samt utför alla sorters arbeten i sandsten o gotlandskalksten för byggnadsändamål",
            "employees": 22,
            "annual_turnover": 800000,
            "key_personnel": [
                {
                    "name": "Dlr Victor Hansén",
                    "position": "Chef"
                }
            ],
            "establishment_year": 1873
        },
        "8": {
            "company_name": "JÄMTFRAKT EK FÖRENING",
            "pnr": "831 00",
            "address": "Östersund, Odensalag 39",
            "phone_number": "063-176 20",
            "bank_details": {
                "bankgiro": "427-4122",
                "postgiro": "126387-0"
            },
            "activity": "Transport- o maskinförmedling, grusförsäljning o schaktentreprenader",
            "employees": 16,
            "annual_turnover": 22000000,
            "key_personnel": [
                {
                    "name": "Ing Erik Persson",
                    "position": "Chef"
                }
            ],
            "establishment_year": 1967
        },
        "9": {
            "company_name": "EKBLAD & CO,AB C O",
            "pnr": "593 00",
            "address": "Västervik, Stora Torget",
            "phone_number": "0490-13160",
            "bank_details": {
                "bankgiro": "66-7006",
                "postgiro": "6411"
            },
            "activity": "Boktryckeri, bokbinderi, förlag med tidningsutgivning",
            "employees": 117,
            "annual_turnover": 6200000,
            "capital": 300000,
            "key_personnel": [
                {
                    "name": "Dir Olle Hultgren",
                    "position": "Chef"
                }
            ],
            "establishment_year": 1834
        },
        "10": {
            "company_name": "EKBLADS INGENJORSBYRÅ AB, TEKN LIC K-G",
            "pnr": "703 40",
            "address": "Örebro, Hertig Karls allé 18",
            "phone_number": "019-1300 70",
            "bank_details": {
                "bankgiro": "614-7086",
                "postgiro": "116163-7"
            },
            "activity": "Konsulterande ingen-jörsbyrå för hus- o industribyggnader. Konstruktioner, projektering, utredningar o kontroll",
            "employees": 22,
            "key_personnel": [
                {
                    "name": "Tekn lic Karl-Göran Ekblad",
                    "position": "Chef"
                }
            ],
            "establishment_year": 1956
        },
        "11": {
            "company_name": "ABAT T ERICSSON AB",
            "pnr": "701 03",
            "address": "Örebro 1, Box 213. Nyg 9",
            "phone_number": "019-14 0170",
            "bank_details": {
                "bankgiro": "614-7920",
                "postgiro": "117171-0"
            },
            "activity": "Tillverkar o säljer specialdetaljer för byggnadsindustrin såsom luckor, lock, stegjärn m m av aluminium o järn",
            "employees": 5,
            "annual_turnover": 1700000,
            "capital": 25000,
            "key_personnel": [
                {
                    "name": "Tage Ericsson",
                    "position": "Verkst dir"
                }
            ],
            "establishment_year": 1968
        },
        "12": {
            "company_name": "BALDER AB, TRYCKERI",
            "pnr": "161 11",
            "address": "Bromma 11, Box 11056. Ulvsundav 168",
            "phone_number": "08-25 26 90",
            "bank_details": {
                "bankgiro": "13-6133",
                "postgiro": "2663"
            },
            "activity": "Boktryckeri o bokbinderi. Specialitet: tidskrifter o kataloger",
            "employees": 42,
            "annual_turnover": 2800000,
            "capital": 100000,
            "key_personnel": [
                {
                    "name": "Folke Hallin",
                    "position": "Verkst dir"
                },
                {
                    "name": "Lennart Hallin",
                    "position": "Disp"
                }
            ],
            "establishment_year": 1922
        },
        "13": {
            "company_name": "BALLINGSLOVS TRÄ-FÖRÄDLING, AB",
            "pnr": "28014",
            "address": "Ballingslöv, Box 75",
            "phone_number": "0451-31200",
            "activity": "Tillverkar köksinredningar o förvaringsskåp",
            "capital": 765000,
            "key_personnel": [
                {
                    "name": "Bertil Albinsson",
                    "position": "Verkst dir"
                }
            ],
            "establishment_year": 1929
        },
        "14": {
            "company_name": "DONSO NÄTFABRIK",
            "pnr": "43082",
            "address": "Donsö, Box 20",
            "phone_number": "031-77 05 25, 77 05 00",
            "bank_details": {
                "bankgiro": "55-5107",
                "postgiro": "424510"
            },
            "activity": "Tillverkar plastbe-handlade grova fisknät",
            "employees": 17,
            "annual_turnover": 1000000,
            "key_personnel": [
                {
                    "name": "Polke Nyfeldt",
                    "position": "chef"
                },
                {
                    "name": "Harry Ny-feldt",
                    "position": "chef"
                }
            ],
            "establishment_year": 1950
        }
    }
}