{
    "original": "EDSBYVERKEN, AB\n\nPnr 828 00\n\nEdsbyn. Tel 0271-212 10.\nBankgiro 78-6027. Postgiro 9559.\nTga Edsbyverk.\nTelex 81168 EDSBYVK S\nVerksamhet: Tillverkar hemmöbler,\nkontorsmöbler o skidor\nAntal anställda: 335\nÅrsomsättning: 30 600 000\nAktiekapital: 2 000 000\nVerkst dir: Bengt Ivarsson\nEtableringsår: 1899.\n\nMOTORDRIFT AB\n\nPnr 171 22\n\nSolna 1, Box 1098. Nybodag 16.\nTel 08-83 02 79. Bankgiro 284-8588.\nPostgiro 403774-3. Tga Motordrift.\nTelex 17044\n\nVerksamhet: Försäljning o service\nav konventionella o hydrauliska\nkranar, transportmaskiner för\nskogsindustrin samt gaffeltruckar.\nGeneralagent för American Hoist &amp;\nDerrick Co, Illinois, USA,\nPetti-bone Corp, New York, USA o Still\nEss lingen Fahrzeugwerke GmbH,\nHamburg, Tyskland\nModerbolag: Norge. Motordrift A/S,\nBryns en g v 1, Oslo. Tel\n00947-268 34 40\n\nVarunamn: American, Pettibone, SE\nAktiekapital: 300 000\nStyrelse: Adv Gustaf A Rising\n(ordf), greve Carl Johan Bernadotte,\ncivilekonom Carl Bolinder, dir\nRagnar Saether, agronom Anders\nSaether (suppl)\nVerkst dir: Ragnar Saether\nV verkst dir: Anders Saether\nEtableringsår: 1965\nDotterbolag: Motorflyg i Stockholm\nAB. Generalagent for Cessna\nAir-craft Co, USA. Ägs till 50%\ngemensamt med Wihuri-Yhtymä OY,\nFinland.\n\nMOTORENOVA I\nHÄLSINGBORG, AB\n\nPnr 252 27\n\nHälsingborg, Verkstadsg 13. Tel\n042-12 07 85. Bankgiro 44-5372.\nPostgiro 164950\nVerksamhet: Renoverar\nförbränningsmotorer o säljer\nmotorreservdelar\n\nAktiekapital: 100000\nVerkst dir: A Palenius\nEtableringsår: 1949.\n\nMOTOR-FLERON GOTEBORG\nAB\n\nPnr 411 01\n\nGöteborg, Stampg 50. Tel\n031-15 09 04. Postgiro 421150. Tga\nFlerona\n\nAktiekapital: 15000\n\nVerkst dir: Sten Mellgren\nPlatschef: Carl Hansson\nEtableringsår 1949\nIngår i Flerongruppen, Malmö.\n\nMOTOR-FLERON\nSTOCK-HOLM AB\n\nPnr 114 48\n\nStockholm, Kommendörsg 12-14.\n\nTel 08-63 0175. Postgiro 258414.\n\nTga Flerona\n\nAktiekapital: 25 000\n\nVerkst dir: Björn Lindhe\n\nEtableringsår: 1947\n\nIngår i Flerongruppen, Malmö.\n\nMOTOR-FLERON\nSUNDS-VALL AB\n\nPnr 852 31\n\nSundsvall, Trädgårdsg 3. Tel\n060-1119 91. Postgiro 103030.\nTelex 71002 FLERONA S\nAktiekapital: 10 000\nVerkst dir: Björn Lindhe\nDisp: Håkan Uhlman\nEtableringsår: 1956\nIngår i Flerongruppen, Malmö.\n\nMOTORKOMPANIET I\nBLEKINGE AB\n\nPnr 292 00\n\nKarlshamn, Drottningg 107. Tel\n0454-144 50. Bankgiro 656-6095.\nPostgiro 245775-2\nVerksamhet: Aukt\nVolvoåterförsäljare samt service\nAntal anställda: 106\nÅrsomsättning: 19 000 000\nVerkst din Sigurd Hermansson\nEtableringsår 1950.\n\nJONASSONS BYGGNADS AB\n\nPnr 302 42\n\nHalmstad, Kyrkog 10. Tel\n035-1190 20. Bankgiro 33 8-9483.\nPostgiro 383806-7\nVerksamhet: Husbyggnad\nAntal anställda: 125\nÅrsomsättning: 10000 000\nAktiekapital: 40 000\nVerkst dir: Byggn-ing Gösta\nLarsson\n\nEtableringsår: 1947\nOmbildat till aktiebolag 1949.\n\nJONASSON TRÄVARU.\nAKTIEBOLAG, J N\n\nPnr 73100\n\nKöping, Vävareg 3. Tel\n0221-12858.’Bankgiro 606-7607.\nPost-giro 390291-3. Tga Jonaswood\nVerksamhet: Kundvirkesexport\nAktiekapital: 50 000\nVerkst dir: Jägmäst Bo Jonasson\nEtableringsår: 1956.\n\nJOHNSSONS SÖNER AB\n\nPnr 510 90\n\nLimmared. Box 26. Tel\n0325-710 61, 716 96. Bankgiro 53-2504.\nPostgiro 292303\nVerksamhet: Strängsprutning av\nprofiler o slang i PVC\nAntal anställda: 40\nÅrsomsättning: 5 000 000\nAktiekapital: 300000\nVerkst dir: Karl-Erik Johnsson\nEtableringsår: 1945.\n\nKRYLBO STÄLT RÅDSVÄVERI\n\nPnr 775 01\n\nKrylbo 1, Box 420. Parkg 3. Tel\n0226-11147. Bankgiro 23-3525.\nPostgiro 176701-1\nVerksamhet: Tillverkar\nZig-Zag-resårer för stoppmöbelindustrin\nAntal anställda: 12\nChef: Hilding Nilsson\nEtableringsår: 1930.\n\nHEL\n\nÅrsomsättning: 5 000 000\nAktiekapital: 140 000\nVeikst dir: Gunnar Held\nEtableringsår: 1935.\n\nHELÉNS FÖRSÄLJNINGS AB,\nPAUL\n\nPnr 30102\n\nHalmstad 1, Box 101.\nVästergårds-v 16. Tel 035-36000. Bankgiro\n423-8457. Postgiro 345540-9. Tga\nSteel. Telex 38078 HELEN S\nVerksamhet: Säljer sömlösa o\nsvetsade stålrör, tuber o stålprofiler\nAntal anställda: 75\nÅrsomsättning: 60 000 000\nAktiekapital: 1000 000\nVerkst dir. Carl Helén\nEtableringsår. 1927.\n\nHELGESSONS\nINGENJÖRS-BYRÄ AB, ROLF\n\nPnr 30104\n\nHalmstad 1, Box 247. Snöstorpsv\n94. Tel 035-1003 70. Bankgiro\n530-1999. Postgiro 352474-1\nVerksamhet: Konsulterande inom\nWS-teknik\nAntal anställda: 7\nÅrsomsättning: 300 000\nAktiekapital: 5 000\nVerkst dir: Ing Rolf Helgesson\nEtableringsår: 1953.\n\nFUN\n\nFRYS- &amp; KYLMASKINER AB\n\nPnr 722 20\n\nVästerås, Mästarg 5. Tel\n021-14 60 10. 13 2134. Bankgiro\n23-2525. Postgiro 298169. Tga Kylner\nVerksamhet: Försäljning,\nreparationer, tillverkning o installation av\nkylanläggningar\nAktiekapital: 25 000\nVerkst dir: Gösta Lindmark\nEtableringsår: 1946.\n\nRODOR, AB\n\nPnr 651 07\n\nKarlstad 1, Lägatan 4. Box 436.\nTel 054-18 0150. Bankgiro\n174-8433. Postgiro 584650-6\nVerksamhet: Tillverkar\nbetongblandare, mottagningsfickor för betong,\nbetongbasker, sop-containers.\nLegotillverkning av plåt- o\nmaskinarbeten. Uthyrning av byggnadsmaskiner\nVarunamn: Rodor\nAntal anställda: 30\nÅrsomsättning: 3 000 000\nAktiekapital: 120 000\nStyrelseordf: Dir C G Eurenius\nEtableringsån 1966.\n\nRODOVERKENSVENUNGSSON\n&amp;CO\n\nPnr 400 13\n\nGöteborg 36, Box 36087.\nPartihallarna. Tel 031-8012 00.\nTga Rodosven. Telex 2347\nVerksamhet: Tillverkar\njärnkonstruktioner, tryckkärl o\nlagringstankar för olja o kemikalier\nAntal anställda: 100\nÅrsomsättning: 14 000 000\nChef: Dir Rodolfo Arbella\nEtableringsår: 1944.\n\nT.IMATRIKÄ, AB\n\nPnr 540 16\n\nTimmersdala. Tel 0511.81260.\n\nBankgiro 224-3285. Postgiro\n287278-6\n\nVerksamhet; Tillverkar\ndamunderkläder o nylonvelour.\n\nTIMBER TRADING CO AB\n\nPnr 401 27\n\nGöteborg 1, Box 498. Exportg,\nHisings Backa. Tel 031-52 03 60.\nPostgiro 41811. Tga Woodgoods.\nTelex 2251 WOOD S\nVerksamhet: Export av sågade o\nhyvlade trävaror, stammvaror,\nstammblocke, sulfits sulfat-\nlövmassaved, stolpar, props,\nträfiberplattor, langholz, dörrar. Inhemsk\nmarknad av sulfit-, sulfat- o\nlövmassaved, stolpar, pålar, trävaror,\nbyggnadsmaterial o snickerier\nAntal anställda: 65\nÅrsomsättning: 35 000000\nAktiekapital: 490 000\nStyrelse: Adv Dag Magnusson\n(ordf), dir Arne Andersson, dir J\nAlfred Olsson\nVerkst dir Arne Andersson\nEtableringsår 1926.\n\nUDD\n\nVerkst dir Johan Schreil\nV verkst dir: Ingvar Trogen\nFörsäljning: Dir Sven Obo\nEtableringsår 1946\nDotterbolag: Uddevallavarvet\nAB-Skandiaverken, Lysekil.\n\nUDDEVALLAVARVET\nAB-SKANDIAVERKEN\n\nPnr 453 00\n\nLysekil, Verkstadsg 2. Tel\n0523-117 30. Bankgiro 54-8327. Postgiro\n102852. Telex 4 2077. Tga\nSkandia-motor\n\nVerksamhet: Tillverkar\ndieselmotorer för marint o stationärt bruk,\nprecisionskuggväxlar, marinväxlar\nhydraulkomponenter o gjutgods\nMeehanite. Utför maskinarbeten\nAntal anställda: 340\nAktiekapital: 500 000\nVerkst dir Johan Schreil\nPlatschef: Overing Birger\nSöderberg\n\nEtableringsår. 1899\nOmbildat till aktiebolag 1905.\nDotterbolag till Uddevallavarvet AB,\nUddevalla.\n\nUGNAR &amp; MASKINER, AB\n\nPnr 431 04\n\nMölndal 4, Bågskytteg 1. Box 4032.\nTel 031-27 80 00. Bankgiro 85-3214.\nPostgiro 623610. Tga Maskinugnar\nVerksamhet: Säljer bageriugnar\nalla slag\n\nAntal anställda: 4\nÅrsomsättning: 900 000\nAktiekapital: 9 000\nVerkst dir: Erik Malmgård\nEtableringsår 1962.",
    "structured": {
        "1": {
            "company_name": "EDSBYVERKEN, AB",
            "address": "Edsbyn",
            "phone_number": "0271-212 10",
            "bank_details": {
                "bankgiro": "78-6027",
                "postgiro": "9559"
            },
            "activity": "Tillverkar hemmöbler, kontorsmöbler o skidor",
            "employees": 335,
            "annual_turnover": 30600000,
            "capital": 2000000,
            "key_personnel": [
                {
                    "name": "Bengt Ivarsson",
                    "position": "Verkst dir"
                }
            ],
            "establishment_year": 1899
        },
        "2": {
            "company_name": "MOTORDRIFT AB",
            "address": "Solna 1, Box 1098. Nybodag 16",
            "phone_number": "08-83 02 79",
            "bank_details": {
                "bankgiro": "284-8588",
                "postgiro": "403774-3"
            },
            "activity": "Försäljning o service av konventionella o hydrauliska kranar, transportmaskiner för skogsindustrin samt gaffeltruckar",
            "employees": null,
            "annual_turnover": null,
            "capital": 300000,
            "key_personnel": [
                {
                    "name": "Ragnar Saether",
                    "position": "Verkst dir"
                },
                {
                    "name": "Anders Saether",
                    "position": "V verkst dir"
                }
            ],
            "establishment_year": 1965,
            "parent_company": "Motordrift A/S, Bryns en g v 1, Oslo"
        },
        "3": {
            "company_name": "MOTORENOVA I HÄLSINGBORG, AB",
            "address": "Hälsingborg, Verkstadsg 13",
            "phone_number": "042-12 07 85",
            "bank_details": {
                "bankgiro": "44-5372",
                "postgiro": "164950"
            },
            "activity": "Renoverar förbränningsmotorer o säljer motorreservdelar",
            "capital": 100000,
            "key_personnel": [
                {
                    "name": "A Palenius",
                    "position": "Verkst dir"
                }
            ],
            "establishment_year": 1949
        },
        "4": {
            "company_name": "MOTOR-FLERON GOTEBORG AB",
            "address": "Göteborg, Stampg 50",
            "phone_number": "031-15 09 04",
            "postgiro": "421150",
            "activity": null,
            "capital": 15000,
            "key_personnel": [
                {
                    "name": "Sten Mellgren",
                    "position": "Verkst dir"
                },
                {
                    "name": "Carl Hansson",
                    "position": "Platschef"
                }
            ],
            "establishment_year": 1949,
            "affiliation": "Flerongruppen, Malmö"
        },
        "5": {
            "company_name": "MOTOR-FLERON STOCK-HOLM AB",
            "address": "Stockholm, Kommendörsg 12-14",
            "phone_number": "08-63 0175",
            "postgiro": "258414",
            "activity": null,
            "capital": 25000,
            "key_personnel": [
                {
                    "name": "Björn Lindhe",
                    "position": "Verkst dir"
                }
            ],
            "establishment_year": 1947,
            "affiliation": "Flerongruppen, Malmö"
        },
        "6": {
            "company_name": "MOTOR-FLERON SUNDS-VALL AB",
            "address": "Sundsvall, Trädgårdsg 3",
            "phone_number": "060-1119 91",
            "postgiro": "103030",
            "activity": null,
            "capital": 10000,
            "key_personnel": [
                {
                    "name": "Björn Lindhe",
                    "position": "Verkst dir"
                },
                {
                    "name": "Håkan Uhlman",
                    "position": "Disp"
                }
            ],
            "establishment_year": 1956,
            "affiliation": "Flerongruppen, Malmö"
        },
        "7": {
            "company_name": "MOTORKOMPANIET I BLEKINGE AB",
            "address": "Karlshamn, Drottningg 107",
            "phone_number": "0454-144 50",
            "bank_details": {
                "bankgiro": "656-6095",
                "postgiro": "245775-2"
            },
            "activity": "Aukt Volvoåterförsäljare samt service",
            "employees": 106,
            "annual_turnover": 19000000,
            "key_personnel": [
                {
                    "name": "Sigurd Hermansson",
                    "position": "Verkst dir"
                }
            ],
            "establishment_year": 1950
        },
        "8": {
            "company_name": "JONASSONS BYGGNADS AB",
            "address": "Halmstad, Kyrkog 10",
            "phone_number": "035-1190 20",
            "bank_details": {
                "bankgiro": "33 8-9483",
                "postgiro": "383806-7"
            },
            "activity": "Husbyggnad",
            "employees": 125,
            "annual_turnover": 10000000,
            "capital": 40000,
            "key_personnel": [
                {
                    "name": "Byggn-ing Gösta Larsson",
                    "position": "Verkst dir"
                }
            ],
            "establishment_year": 1947
        },
        "9": {
            "company_name": "JONASSON TRÄVARU. AKTIEBOLAG, J N",
            "address": "Köping, Vävareg 3",
            "phone_number": "0221-12858",
            "bank_details": {
                "bankgiro": "606-7607",
                "postgiro": "390291-3"
            },
            "activity": "Kundvirkesexport",
            "capital": 50000,
            "key_personnel": [
                {
                    "name": "Jägmäst Bo Jonasson",
                    "position": "Verkst dir"
                }
            ],
            "establishment_year": 1956
        },
        "10": {
            "company_name": "JOHNSSONS SÖNER AB",
            "address": "Limmared, Box 26",
            "phone_number": "0325-710 61, 716 96",
            "bank_details": {
                "bankgiro": "53-2504",
                "postgiro": "292303"
            },
            "activity": "Strängsprutning av profiler o slang i PVC",
            "employees": 40,
            "annual_turnover": 5000000,
            "capital": 300000,
            "key_personnel": [
                {
                    "name": "Karl-Erik Johnsson",
                    "position": "Verkst dir"
                }
            ],
            "establishment_year": 1945
        }
    }
}