{
    "original": "SVENSK MARIN RADIO AB\n\nPnr 412 63\n\nGöteborg, Mölndals v 40-42. Tel\n031-16 3280, 16 3281. Bankgiro\n50-6721. Postgiro 421115. Tga\nMarinradio\n\nVerksamhet: Försäljning o service\nav radio, radar, ekolod o\nautomatstyrningar\n\nVarunamn: Ferrograph, Furuno,\nMarconi, Sharp\nAktiekapital: 75 000\nEtableringsår: 1949.\n\nHOGANÄSARBETEN, AB\n\nPnr 263 01\n\nHöganäs 1, Fack. Tel 042-424 00.\nBankgiro 20-2169. Postgiro 159170.\nTga Höganäsarbeten. Telex 72258\nVerksamhet: Entreprenadföretag\nför eldfasta o syrafasta\ninmurningar, plattsättning samt\nindustriella plastarbeten\nAntal anställda: 140\nÅrsomsättning: 10 000 000\nAktiekapital: 90 000\nVerkst dir: Gösta Lindqvist\nEtableringsår 1910\nDotterföretag till Höganäs AB.\n\nHOGANÄS-KERAMIK AB\n\nPnr 263 00\n\nHöganäs. Tel 042-423 40. Bankgiro\n654-5297. Postgiro 30487-3. Tga\nPottery\n\nVerksamhet: Nytto- o\nprydnadskeramik\n\nVarunamn: Old Höganäs, Höganäs\nStengods\n\nAntal anställda: 100\n\nÅrsomsättning: 5 000 000\n\nAktiekapital: 100 000\nVerkst dir. Gösta Sigfridsson\nEtableringsår 1910.\n\nGRO\n\nGRÄNGESHEDLUND AB\n\nPnr 104 60\n\nStockholm 20, Hammarbyv 40. Tel\n08-247100. Telex 10484. Tga\nHed-lundsteel\n\nVerksamhet: Tillverkar o monterar\nstålkonstruktioner\nVerkstad: Hammarby, Västerås\nRörverk: Jordbro. Tel 0750-21120\nAktiekapital: 4 200 000\nVerkst dir: John Dahlfors\nEtableringsår: 1911.\n\nTAPETMASKINER, AB\n\nPnr 125 21\n\nÄlvsjö 1, Sjättenovemberv 210-214.\nBox 46. Tel 08-47 25 40. Telex\n17599\n\nVerksamhet: Tillverkar o säljer tar\npetmaskiner\n\nÅrsomsättning: 2 000 000\nAktiekapital: 5 000\nVerkst dir: I Ramnhagen\nEtableringsàr: 1959.\n\nTAPISSERIBOLAGET\nT HARALDSON AB\n\nPnr 401 21\n\nGöteborg 1, Tredje Långg 13. Box\n62. Tel 031-1245 60. Bankgiro\n410-0665. Postgiro 44203-8\nVerksamhet Tillverkning av\nhemtextilier\n\nAntal anställda: 100\nAktiekapital: 100 000\nVerkst dir: Torleif Haraldson\nEtableringsàr 1935.\n\nSVENSKA BUKO AB\n\nPnr 163 03\n\nSpånga 3, Box 379. Enev 30. Tel\n08-36 30 30, 36 3700. Bankgiro\n734-9530. Postgiro 502990-5\nVerksamhet: Försäljning av dansk\nmjukost även ädelost\nAntal anställda: 15\nÅrsomsättning: 5 000000\nVerkst dir: Hans Bromert\nEtableringsår: 1967.\n\nBILFÖRSÄLJNINGS AB,\nBILFORSÄLJNINGSFIRMAN\n\nse resp namn.\n\nBILHALLEN I MALMÖ AB\n\nPnr 217 58\n\nMalmö, Tessins v 2. Tel\n040-9155 52. Bankgiro 884-0530.\nPostgiro 435980-8\n\nVerksamhet: Auktoriserad\nåterförsäljare för Toyota person- o\nlastfordon samt service\nAntal anstäUda: 5\nÅrsomsättning: 3 000 000\nAktiekapital: 100 000\nStyrelse: Dir Waldemar Persson,\nförsäljn-chef Bertil Silfverberg,\nekonomichef Kjell Grahn\nVerkst dir: Waldemar Persson\nFörsäljn-chef: Bertil Silfverberg\nEkonomichef: Kjell Grahn.\n\nBILIA, AB\n\nPnr 113 84\n\nStockholm 6, Box 6603. Hälsingeg\n43. Tel 08-34 06 00. Bankgiro\n581-0007. Postgiro 1310-2\nVerksamhet: Auktoriserad\nVolvoservice, reservdelar, tillbehör.\nSäljer nya Volvo o begagnade bilar\nAntal anstäUda: 740\nÅrsomsättning: 180 000 000\nAktiekapital: 5 000 000\nVerkst dir: Bengt Hagman\nEtableringsår: 1968\nRepresentant för AB Volvo, Göteborg.\n\nBILINDUSTRI I BLIDSBERG AB\n\nPnr 520 24\n\nBlidsberg, Box 58. Tel 0321-312 20,\n312 21, 312 22. Bankgiro 580-4604.\nPostgiro 712920-8. Tga\nBlidsbergs-tipp\n\nVerksamhet: Tillverkar utrustningar\nför lastbilar o släpvagnar,\nhuvudsakligen tippar o flak. Monterar\nolika utrustningsdetaljer på\nlastfordon\n\nFörsälj ningskontor:\n\nDanmark: Auge Jensen Ingeniör- og\nHändelsvirkomhed. Jernbaneallé\n24. Espergaerde. Tel 03-216844\nNorge: Planesystemer A/S. Boks\n45, N 2001 Lilleström. Tel\n02-714120\n\nVarunamn: Blidsbergstippen, Bili\nAntal anställda: 70\nÅrsomsättning: 4 500000\nAktiekapital: 50 000\nVerkst dir: Göte Håkanson\nFörsäljn-chef: Harald Dahlälv\nInköpschef: Olof Andersson\nEtableringsår: 1938.\n\nSMÅLÄNDSKA LÄDER, AB\n\nPnr 330 32\n\nNissafors, Kämpabo. Tel\n0371-19017, 19047. Bankgiro 488-0597.\nPostgiro 146896-6\nVerksamhet: Tillverkar plånböcker,\nklackportmonnäer, smålandsbörsar,\nkonduktörsväskor samt etuier i\nskinn o läder\n\nFörsäljningskontor o fabrik:\nNissafors, Kämpabo. Tel 0371-190 17\nAntal anställda: 55\nÅrsomsättning: 3 000 000\nAktiekapital: 108 000\nChefer: Fabr Axel Ljungberg, fabr\nTure Hiljemark, fabr Arnold\nHilje-mark, fabr Wåge Hiljemark\nEtableringsår: 1945\nOmbildat till aktiebolag 1965.\n\nSMÅLÄNNINGEN, AB\n\nPnr 34100\n\nLjungby, Storg 32. Tel 0372-124 30\nVerksamhet: Bok-, offset- o\ntidningstryckeri. Utger\nLjungbytid-ningen-Älmhults Tidning\nSmålänningen\n\nAktiekapital: 150 000\nVerkst dir: stig Fredriksson\nEtableringsår: 1921.\n\nSMUGENS PLÅT. &amp; SVETSIN.\nDUSTRI WAHLE &amp; JOHANSSON\n\nPnr 450 43\n\nSmögen, Postl 921. Tel 0523-312 36.\nBankgiro 551-0102. Postgiro\n293953-6\n\nVeiksamhet: Tillverkar bilfärjor,\ncontainers, oljecisterner\nAntal anstäUda: il\nÅrsomsättning: 600 000\nChefer: Fabr Alf Johansson, fabr\nYngve Wahle\nEtableringsår: 1944.\n\nJYDEN AB, RAMFABRIKEN\n\nPnr 452 00\n\nStrömstad, Box 8. Tel 0526-12450.\nBankgiro 551-3650. Postgiro\n321061-4\n\nVerksamhet: Tillverkar fotoramar\ni metall. Grossistförsäljning av\nalla slags fotoramar o fotoalbum\njämte listklippmaskiner\nVarunamn: Jyden\nAntal anställda: 115\nÅrsomsättning: 7 000 000\nAktiekapital: 400 000\nVerkst dir: Leif Ranghöj\nEtableringsår: 1945.\n\nADJA, AB\n\nPnr 332 00\n\nGislaved, Box 103. Mårtensg 16.\nTel 0371-120 50. Bankgiro\n426-7027. Postgiro 365630-3\nVerksamhet: Tillverkar\nmassartiklar för industri. Specialitet:\ntekniska detaljer av bl a cellulosa-\n\nacetat, polystyrene, polyethene,\nnylon, akrylat, polykarbonat etc,\nkompletteringsdetaljer för industrin,\nkonstruktion o egen\nverktygstillverkning, svetsning av plastfickor\no pärmar\n\nAH\n\nAntal anställda: 50\nAktiekapital: 80 000\nStyrelse: Ragnar Andersson (ordf),\nGustav Andersson, Arne Dehlin,\nBirger Johansen\nVerkst dir: Arne Dehlin\nEtableringsår: 1946.\n\nAMAB-HYDRAUL AB\n\nPnr 212 25\n\nMalmö, Kruseg 50. Tel\n040-93 69 60. Bankgiro 614-1014.\nPostgiro 439500-0\n\nVerksamhet: Säljer hydrauliska\nslangar, kopplingar o packningar\nVarunamn: Amab\nAntal anställda: 10\nÅrsomsättning: 35 000 000\nAktiekapital: 100 000\nVerkst dir: Kjell Larsson\nEtableringsår: 1945.",
    "structured": {
        "1": {
            "company_name": "SVENSK MARIN RADIO AB",
            "pnr": "412 63",
            "address": "Göteborg, Mölndals v 40-42",
            "phone_number": "031-16 3280, 16 3281",
            "bank_details": {
                "bankgiro": "50-6721",
                "postgiro": "421115"
            },
            "activity": "Försäljning o service av radio, radar, ekolod o automatstyrningar",
            "varunamn": "Ferrograph, Furuno, Marconi, Sharp",
            "capital": 75000,
            "establishment_year": 1949
        },
        "2": {
            "company_name": "HOGANÄSARBETEN, AB",
            "pnr": "263 01",
            "address": "Höganäs 1",
            "phone_number": "042-424 00",
            "bank_details": {
                "bankgiro": "20-2169",
                "postgiro": "159170"
            },
            "activity": "Entreprenadföretag för eldfasta o syrafasta inmurningar, plattsättning samt industriella plastarbeten",
            "employees": 140,
            "annual_turnover": 10000000,
            "capital": 90000,
            "key_personnel": [
                {
                    "name": "Gösta Lindqvist",
                    "position": "Verkst dir"
                }
            ],
            "establishment_year": 1910
        },
        "3": {
            "company_name": "HOGANÄS-KERAMIK AB",
            "pnr": "263 00",
            "address": "Höganäs",
            "phone_number": "042-423 40",
            "bank_details": {
                "bankgiro": "654-5297",
                "postgiro": "30487-3"
            },
            "activity": "Nytto- o prydnadskeramik",
            "varunamn": "Old Höganäs, Höganäs Stengods",
            "employees": 100,
            "annual_turnover": 5000000,
            "capital": 100000,
            "key_personnel": [
                {
                    "name": "Gösta Sigfridsson",
                    "position": "Verkst dir"
                }
            ],
            "establishment_year": 1910
        },
        "4": {
            "company_name": "GRÄNGESHEDLUND AB",
            "pnr": "104 60",
            "address": "Stockholm 20, Hammarbyv 40",
            "phone_number": "08-247100",
            "activity": "Tillverkar o monterar stålkonstruktioner",
            "employees": null,
            "capital": 4200000,
            "key_personnel": [
                {
                    "name": "John Dahlfors",
                    "position": "Verkst dir"
                }
            ],
            "establishment_year": 1911
        },
        "5": {
            "company_name": "TAPETMASKINER, AB",
            "pnr": "125 21",
            "address": "Älvsjö 1, Sjättenovemberv 210-214, Box 46",
            "phone_number": "08-47 25 40",
            "activity": "Tillverkar o säljer tapetmaskiner",
            "annual_turnover": 2000000,
            "capital": 5000,
            "key_personnel": [
                {
                    "name": "I Ramnhagen",
                    "position": "Verkst dir"
                }
            ],
            "establishment_year": 1959
        },
        "6": {
            "company_name": "TAPISSERIBOLAGET T HARALDSON AB",
            "pnr": "401 21",
            "address": "Göteborg 1, Tredje Långg 13, Box 62",
            "phone_number": "031-1245 60",
            "bank_details": {
                "bankgiro": "410-0665",
                "postgiro": "44203-8"
            },
            "activity": "Tillverkning av hemtextilier",
            "employees": 100,
            "capital": 100000,
            "key_personnel": [
                {
                    "name": "Torleif Haraldson",
                    "position": "Verkst dir"
                }
            ],
            "establishment_year": 1935
        },
        "7": {
            "company_name": "SVENSKA BUKO AB",
            "pnr": "163 03",
            "address": "Spånga 3, Box 379, Enev 30",
            "phone_number": "08-36 30 30, 36 3700",
            "bank_details": {
                "bankgiro": "734-9530",
                "postgiro": "502990-5"
            },
            "activity": "Försäljning av dansk mjukost även ädelost",
            "employees": 15,
            "annual_turnover": 5000000,
            "key_personnel": [
                {
                    "name": "Hans Bromert",
                    "position": "Verkst dir"
                }
            ],
            "establishment_year": 1967
        },
        "8": {
            "company_name": "BILHALLEN I MALMÖ AB",
            "pnr": "217 58",
            "address": "Malmö, Tessins v 2",
            "phone_number": "040-9155 52",
            "bank_details": {
                "bankgiro": "884-0530",
                "postgiro": "435980-8"
            },
            "activity": "Auktoriserad återförsäljare för Toyota person- o lastfordon samt service",
            "employees": 5,
            "annual_turnover": 3000000,
            "capital": 100000,
            "key_personnel": [
                {
                    "name": "Waldemar Persson",
                    "position": "Verkst dir"
                },
                {
                    "name": "Bertil Silfverberg",
                    "position": "försäljn-chef"
                },
                {
                    "name": "Kjell Grahn",
                    "position": "ekonomichef"
                }
            ]
        },
        "9": {
            "company_name": "BILIA, AB",
            "pnr": "113 84",
            "address": "Stockholm 6, Box 6603, Hälsingeg 43",
            "phone_number": "08-34 06 00",
            "bank_details": {
                "bankgiro": "581-0007",
                "postgiro": "1310-2"
            },
            "activity": "Auktoriserad Volvoservice, reservdelar, tillbehör. Säljer nya Volvo o begagnade bilar",
            "employees": 740,
            "annual_turnover": 180000000,
            "capital": 5000000,
            "key_personnel": [
                {
                    "name": "Bengt Hagman",
                    "position": "Verkst dir"
                }
            ],
            "establishment_year": 1968
        },
        "10": {
            "company_name": "BILINDUSTRI I BLIDSBERG AB",
            "pnr": "520 24",
            "address": "Blidsberg, Box 58",
            "phone_number": "0321-312 20, 312 21, 312 22",
            "bank_details": {
                "bankgiro": "580-4604",
                "postgiro": "712920-8"
            },
            "activity": "Tillverkar utrustningar för lastbilar o släpvagnar, huvudsakligen tippar o flak. Monterar olika utrustningsdetaljer på lastfordon",
            "försälj ningskontor": [
                {
                    "country": "Danmark",
                    "name": "Auge Jensen Ingeniör- og Händelsvirkomhed",
                    "address": "Jernbaneallé 24, Espergaerde",
                    "phone_number": "03-216844"
                },
                {
                    "country": "Norge",
                    "name": "Planesystemer A/S",
                    "address": "Boks 45, N 2001 Lilleström",
                    "phone_number": "02-714120"
                }
            ],
            "varunamn": "Blidsbergstippen, Bili",
            "employees": 70,
            "annual_turnover": 4500000,
            "capital": 50000,
            "key_personnel": [
                {
                    "name": "Göte Håkanson",
                    "position": "Verkst dir"
                },
                {
                    "name": "Harald Dahlälv",
                    "position": "Försäljn-chef"
                },
                {
                    "name": "Olof Andersson",
                    "position": "Inköpschef"
                }
            ],
            "establishment_year": 1938
        },
        "11": {
            "company_name": "SMÅLÄNDSKA LÄDER, AB",
            "pnr": "330 32",
            "address": "Nissafors, Kämpabo",
            "phone_number": "0371-19017, 19047",
            "bank_details": {
                "bankgiro": "488-0597",
                "postgiro": "146896-6"
            },
            "activity": "Tillverkar plånböcker, klackportmonnäer, smålandsbörsar, konduktörsväskor samt etuier i skinn o läder",
            "employees": 55,
            "annual_turnover": 3000000,
            "capital": 108000,
            "key_personnel": [
                {
                    "name": "Fabr Axel Ljungberg",
                    "position": "Fabr"
                },
                {
                    "name": "Fabr Ture Hiljemark",
                    "position": "Fabr"
                },
                {
                    "name": "Fabr Arnold Hilje-mark",
                    "position": "Fabr"
                },
                {
                    "name": "Fabr Wåge Hiljemark",
                    "position": "Fabr"
                }
            ],
            "establishment_year": 1945
        },
        "12": {
            "company_name": "SMÅLÄNNINGEN, AB",
            "pnr": "34100",
            "address": "Ljungby, Storg 32",
            "phone_number": "0372-124 30",
            "activity": "Bok-, offset- o tidningstryckeri. Utger Ljungbytid-ningen-Älmhults Tidning Smålänningen",
            "capital": 150000,
            "key_personnel": [
                {
                    "name": "Stig Fredriksson",
                    "position": "Verkst dir"
                }
            ],
            "establishment_year": 1921
        },
        "13": {
            "company_name": "SMUGENS PLÅT. & SVETSIN. DUSTRI WAHLE & JOHANSSON",
            "pnr": "450 43",
            "address": "Smögen, Postl 921",
            "phone_number": "0523-312 36",
            "bank_details": {
                "bankgiro": "551-0102",
                "postgiro": "293953-6"
            },
            "activity": "Tillverkar bilfärjor, containers, oljecisterner",
            "employees": 11,
            "annual_turnover": 600000,
            "key_personnel": [
                {
                    "name": "Fabr Alf Johansson",
                    "position": "Fabr"
                },
                {
                    "name": "Fabr Yngve Wahle",
                    "position": "Fabr"
                }
            ],
            "establishment_year": 1944
        },
        "14": {
            "company_name": "JYDEN AB, RAMFABRIKEN",
            "pnr": "452 00",
            "address": "Strömstad, Box 8",
            "phone_number": "0526-12450",
            "bank_details": {
                "bankgiro": "551-3650",
                "postgiro": "321061-4"
            },
            "activity": "Tillverkar fotoramar i metall. Grossistförsäljning av alla slags fotoramar o fotoalbum jämte listklippmaskiner",
            "varunamn": "Jyden",
            "employees": 115,
            "annual_turnover": 7000000,
            "capital": 400000,
            "key_personnel": [
                {
                    "name": "Leif Ranghöj",
                    "position": "Verkst dir"
                }
            ],
            "establishment_year": 1945
        },
        "15": {
            "company_name": "ADJA, AB",
            "pnr": "332 00",
            "address": "Gislaved, Box 103, Mårtensg 16",
            "phone_number": "0371-120 50",
            "bank_details": {
                "bankgiro": "426-7027",
                "postgiro": "365630-3"
            },
            "activity": "Tillverkar massartiklar för industri. Specialitet: tekniska detaljer av bl a cellulosa-acetat, polystyrene, polyethene, nylon, akrylat, polykarbonat etc, kompletteringsdetaljer för industrin, konstruktion o egen verktygstillverkning, svetsning av plastfickor o pärmar",
            "employees": 50,
            "capital": 80000,
            "key_personnel": [
                {
                    "name": "Arne Dehlin",
                    "position": "Verkst dir"
                }
            ],
            "establishment_year": 1946
        },
        "16": {
            "company_name": "AMAB-HYDRAUL AB",
            "pnr": "212 25",
            "address": "Malmö, Kruseg 50",
            "phone_number": "040-93 69 60",
            "bank_details": {
                "bankgiro": "614-1014",
                "postgiro": "439500-0"
            },
            "activity": "Säljer hydrauliska slangar, kopplingar o packningar",
            "varunamn": "Amab",
            "employees": 10,
            "annual_turnover": 35000000,
            "capital": 100000,
            "key_personnel": [
                {
                    "name": "Kjell Larsson",
                    "position": "Verkst dir"
                }
            ],
            "establishment_year": 1945
        }
    }
}