{
    "original": "ELI\n\nELFSBORG\n\nse Älvsborg.\n\nELFSTROMS TEKNISKA\nFABRIK, AB\n\nPnr 80102\n\nGävle 1, Atlasg 1. Box 93. Tel\n026-1139 29, 12 6980. Bankgiro\n193-9156. Postgiro 21414-8.\nTga Elfströmsfabrik\nVerksamhet: Tillverkar o säljer\nReporia Svavel-Tjärtvål, Reporia\nJod-tvål, stearinljus, tvålflingor,\ntvättvål, lutpulver o handpasta\nVarunamn: Reporia, Mimosa\nAktiekapital: 154 200\nFirmatecknare: Disp G Eriksson,\nfru Sonja Eriksson\nEtableringsår: 1912\nOmbildat till aktiebolag 1927.\n\nELFSTROMS BOKTRYCKERI\nAB, AXEL R\n\nPnr 112 28\n\nStockholm, Scheeleg 17. Tel\n08-50 85 54. 53 25 54. Bankgiro\n723-7621. Postgiro 50282-3\nVerksamhet: Reklam-, tidskrift- o\naffärstryck i boktryck\nAntal anställda: 12\nÅrsomsättning: 900 000\nAktiekapital: 30 000\nVerkst dir: Ingmar Elfström\nEtableringsår: 1910.\n\nFINNEBÄCKS AB\n\nPnr 670 30\n\nEdane. Tel 0570-20015. Bankgiro\n10-5534. Postgiro 88595\nVerksamhet: Tillverkar monterbara\nkyl- o frysrum, kyl- o frysskåp\nAntal anställda: 30\nÅrsomsättning: 2 500 000\nAktiekapital: 120 000\nVerkst din Gunnar Wästlund\nEtableringsår 1917.\n\nENGSTRAND AB, GUNNAR\n\nPnr 114 32\n\nStockholm, Engelbrektsg 6. Tel\n08-1099 90, 10 9122. Bankgiro\n13-6175. Postgiro 3034. Tga Guneng\nVerksamhet: Grosshandel med oljor\no industriförnödenheter, agenturer\nför industri o sjöfart\nVarunamn: Huck\nAntal anställda: 3\nÅrsomsättning: 600 000\nAktiekapital: 15 000\nVerkst dir: Disp G W Engstrand\nKontorschef: Erik Brundin\nEtableringsår: 1928\nOmbildat till aktiebolag 1962.\n\nENGSTRÖM &amp; DEHLIN,\nBAKELIT AB\n\nPnr 332 00\n\nGislaved, Svarvareg. Box 77. Tel\n0371-106 70. Bankgiro 14-3057.\nPostgiro 118158\nVerksamhet: Formpressning o\ntransfersprutning av samtliga inom\nbranschen förekommande material.\nPressar från 30-250 ton. Egen\nverktygstillverkning\nÅrsomsättning: 1000 000\nAktiekapital: 10 000\nVerkst dir: F Dehlin\nEtableringsår: 1946.\n\nolands cement ab\n\nPnr 380 65\n\nDegerhamn. Tel 0485-604 70.\nBank-giro66-1811.Postgiro 11302.Telex\n4846. Tga Insula\nVerksamhet: Tillverkar\nstandardcement o snabbcement\nAntal anställda: 170\nÅrsomsättning: 18 000 000\nAktiekapital: 2 700 000\nPlatschef: Låge Themner\nEtableringsår: 1886\nDotterbolag till AB Cementa, Malmö.\n\nolands maltfabrik ab\n\nPnr 380 70\n\nBorgholm, Box 31. Tel 0485-10031.\nPostgiro 73895\n\nVerksamhet: Säljer malt,\nspannmål, fodervaror o gödningsämnen\nAktiekapital: 65 900\nVerkst dir: Harald Ohlson\nEtableringsån 1927.\n\nERICSSON &amp; HORNDAHL AB\n\nPnr 602 22\n\nNorrköping, Saltängsg 70-72. Tel\n011-12 92 50. Tga Horndahl.\nTelex 64136\n\nVerksamhet: Kol, koks o olja.\nSkeppsklarering, spedition\nFilial: Linköping. Tel 013-141288\nAntal anställda: 18\nÅrsomsättning: 7 000 000\nAktiekapital: 150 000\nVerkst dir: Bo Horndahl\nEtableringsår 1899.\n\nHYGIEN &amp; SKYDD AB\n\nPnr 183 05\n\nTäby 5, Viggbyholmsv 75. Fack.\nTel 08-756 29 80. Bankgiro\n481-8241. Postgiro 31855-0\nVerksamhet: säljer o tillverkar\nar-betsskydds- o kem tekn artiklar\nVarunamn: G 5 Extra, Elexin\nAntal anställda: 3\nAktiekapital: 5 000\nVerkst dir: Robert Barrehag\nEtableringsår: 1957.\n\nwaern &amp; co, ab c fr\n\nPnr 41114\n\nGöteborg, S Hamng 23. Tel\n031-1756 00. Bankgiro 420-4665.\nPostgiro 40345-1. Tga Waern.\nTelex 2548\n\nVerksamhet Exporterar papper o\npapp, maskiner, verktyg,\nträartiklar, wallboard. Importerar klockor\nporslin, reklamartiklar o\ntextilvaror\n\nAktiekapital: 300 000\nVerkst dir: Carl Waern\nEtableringsår: 1813.\n\nvaggeryds mek\nverk-stad, ab\n\nPnr 56012\n\nVaggeryd, Box 20. Tel 0393-107 55,\n100 94. Tga Mekaniska\nVerksamhet: Tillverkar hydrauliska\nventiler, kolvar o grävaggregat för\ntraktorer\n\nAntal anställda: 40\nÅrsomsättning: 5 500 000\nAktiekapital: 105 000\nVerkst dir: Pabr Polke Mattsson\nEtableringsår: 1912.\n\nwaggerydsmöbel.\nfabrik ab\n\nPnr 56012\n\nVaggeryd, Frideborgsv 15. Box 153.\nTel 0393-100 30, 100 40. Bankgiro\n289-2552. Postgiro 23499-7\nVerksamhet Tillverkning av\nmöbler i olika utförande\nAntal anställda: 22\nÅrsomsättning: 1 500 000\nAktiekapital: 150 000\nÄgare o chef: Pabr Polke Carlson\nEtableringsår: 1911.\n\nWENNERGREN.WILLIAMS AB\n\nPnr 104 25\n\nStockholm 30, Nordenflychtsv 70.\nFack. Tel 08-5412 00. Bankgiro\n73-3836. Postgiro 97. Telex 19937.\nTga Wennerbolag\n\nVerksamhet: Tidningsimport\no-export samt prenumerationsservice,\nmönsterförsäljning, utomhus- o\npresentreklam\nAntal anställda: 125\nÅrsomsättning: 50 000000\nAktiekapital: 500 000\nVerkst dir: Claës Westman\nEtableringsår: 1921.\n\nSÖDRA METALLEXPORTEN,\nAB\n\nPnr 116 44\n\nStockholm, Vävar Johans v, Lugnet.\nTel 08-42 45 51, 4132 31. Bankgiro\n731-0600. Postgiro 158777.\nTga Commerce\n\nVerksamhet: Metallgrosshandel\nmed metallskrot, halvfabrikat o\nmetalltackor\n\nAntal anställda: 3\nÅrsomsättning: 5 000 000\nAktiekapital: 100 000\nÄgare o chefer: Einar Sjöbeck,\nWalter Rubinstein\nEtableringsår: 1938.\n\nSÖDRA SNICKERI.\nFABRIKENS AB\n\nPnr 500 06\n\nBorås 6, Box 66058. Tel\n033-1175 00. Bankgiro 839-3761.\nPostgiro 85885-2\n\nVerksamhet: Försäljning av trävaror,\nsnickerier o byggmaterial.\nTillverkning av specialinredningar\nAntal anställda: 65\nAktiekapital: 154000\nVerkst dir: Ingvar Kempe\nEtableringsår: 1894.\n\nSPE\n\nSPADFABRIKEN\nKARLSTAD AB\n\nPnr 65106\n\nKarlstad 1, Box 388. Tel\n054-187175. Bankgiro 438-9516.\nPostgiro 36151-9\n\nVerksamhet: Tillverkar\nhandredskap såsom spadar, grepar m m\nAntal anställda: 21\nAktiekapital: 60000\nVerkst dir: Disp Gösta P Ohlsson\nEtableringsån 1923.",
    "structured": {
        "1": {
            "company_name": "ELFSTROMS TEKNISKA FABRIK, AB",
            "pnr": "80102",
            "address": "Gävle 1, Atlasg 1. Box 93.",
            "phone_number": "026-1139 29, 12 6980",
            "bank_details": {
                "bankgiro": "193-9156",
                "postgiro": "21414-8"
            },
            "activity": "Tillverkar o säljer Reporia Svavel-Tjärtvål, Reporia Jod-tvål, stearinljus, tvålflingor, tvättvål, lutpulver o handpasta",
            "employees": 0,
            "annual_turnover": 0,
            "annual_production_value": null,
            "capital": 154200,
            "key_personnel": [
                {
                    "name": "Disp G Eriksson",
                    "position": null
                },
                {
                    "name": "fru Sonja Eriksson",
                    "position": null
                }
            ],
            "establishment_year": 1912
        },
        "2": {
            "company_name": "ELFSTROMS BOKTRYCKERI AB, AXEL R",
            "pnr": "112 28",
            "address": "Stockholm, Scheeleg 17",
            "phone_number": "08-50 85 54, 53 25 54",
            "bank_details": {
                "bankgiro": "723-7621",
                "postgiro": "50282-3"
            },
            "activity": "Reklam-, tidskrift- o affärstryck i boktryck",
            "employees": 12,
            "annual_turnover": 900000,
            "annual_production_value": null,
            "capital": 30000,
            "key_personnel": [
                {
                    "name": "Ingmar Elfström",
                    "position": "Verkst dir"
                }
            ],
            "establishment_year": 1910
        },
        "3": {
            "company_name": "FINNEBÄCKS AB",
            "pnr": "670 30",
            "address": "Edane",
            "phone_number": "0570-20015",
            "bank_details": {
                "bankgiro": "10-5534",
                "postgiro": "88595"
            },
            "activity": "Tillverkar monterbara kyl- o frysrum, kyl- o frysskåp",
            "employees": 30,
            "annual_turnover": 2500000,
            "annual_production_value": null,
            "capital": 120000,
            "key_personnel": [
                {
                    "name": "Gunnar Wästlund",
                    "position": "Verkst din"
                }
            ],
            "establishment_year": 1917
        },
        "4": {
            "company_name": "ENGSTRAND AB, GUNNAR",
            "pnr": "114 32",
            "address": "Stockholm, Engelbrektsg 6",
            "phone_number": "08-1099 90, 10 9122",
            "bank_details": {
                "bankgiro": "13-6175",
                "postgiro": "3034"
            },
            "activity": "Grosshandel med oljor o industriförnödenheter, agenturer för industri o sjöfart",
            "employees": 3,
            "annual_turnover": 600000,
            "annual_production_value": null,
            "capital": 15000,
            "key_personnel": [
                {
                    "name": "Disp G W Engstrand",
                    "position": "Verkst dir"
                },
                {
                    "name": "Erik Brundin",
                    "position": "Kontorschef"
                }
            ],
            "establishment_year": 1928
        },
        "5": {
            "company_name": "ENGSTRÖM & DEHLIN, BAKELIT AB",
            "pnr": "332 00",
            "address": "Gislaved, Svarvareg. Box 77",
            "phone_number": "0371-106 70",
            "bank_details": {
                "bankgiro": "14-3057",
                "postgiro": "118158"
            },
            "activity": "Formpressning o transfersprutning av samtliga inom branschen förekommande material. Pressar från 30-250 ton. Egen verktygstillverkning",
            "employees": 0,
            "annual_turnover": 1000000,
            "annual_production_value": null,
            "capital": 10000,
            "key_personnel": [
                {
                    "name": "F Dehlin",
                    "position": "Verkst dir"
                }
            ],
            "establishment_year": 1946
        }
    }
}