{
    "original": "LOBA, BYGG AB\n\nPnr 240 20\n\nFlnulund, Fack. Bantorget 1. Tel\n\n046-32215. Bankgiro 673-1640.\nPostgiro 38874-4\nVerksamhet: Byggnadsrörelse\nAktiekapital: 150 000\nVerkst dir: Bertil Anderberg\nEtableringsår: 1958.\n\nENGQVIST &amp; UDESEN\n\nPnr 414 63\n\nGöteborg, Barlastg 2. Tel\n031-12 44 90. Bankgiro 441-1757.\nPostgiro 25491-2. Tga Eochu.\nTelex 20778\n\nVerksamhet: Rostskydds- o\nimpreg-neringsoljor, tjära\nAntal anställda: 28\nÅrsomsättning: 6 000 000\nÄgare o chef: Dlr Arthur Udesen\nEtableringsår: 1928.\n\nENGLUND &amp; JONSSON\nSNICKERIFABRIK\n\nPnr 823 00\n\nKilafors. Tel 0278-500 70. Postgiro\n31792\n\nVerksamhet: Tillverkar\nbyggnadssnickerier\nChef: Alfr Englund\nEtableringsår: 1927.\n\nENGLUNDS KONTORSSERVICE\nAB\n\nPnr 70105\n\nÖrebro 1, Engelbrektsg 32. Box\n350. Tel 019-13 39 30, 13 39 31.\nBankgiro 358-8381. Postgiro\n115911-0\n\nVerksamhet: Säljer kontorsmöbler,\n-maskiner o -förnödenheter\nAntal anställda: 10\nÅrsomsättning: 2 000000\nAktiekapital: 15000\nVerkst din Jan Englund\nEtableringsår: 1962.\n\nENGLUNDS\nPROJEKTERINGS-BYRA AB\n\nPnr 12173\n\nJohanneshov, Importörv 23. Tel\n08-81 02 60. Bankgiro 744-3732.\nPostgiro 257330-1\n\nVerksamhet: Totalprojektering av\nbyggnader genom avdelningar för\narkitektur, byggnads-, vvs- o\nel-konstruktioner\nAntal anställda: 30\nAktiekapital: 100 000\nÄgare o chef: Ing Jonas Englund\nEtableringsår: 1958.\n\nBERGSTEN, UGNSFIRMAN\n\nPnr 510 47\n\nFristad, Box 103. Tel 033-602 70\nVerksamhet: Elektriska-, gas- o\noljeeldade ugnar\nChef: Ing Hilding Bergsten\nEtableringsår. 1955.\n\nBERGSTENS BOKTRYCKERI,\nAB ERNST\n\nPnr 252 27\n\nHelsingborg, Rågångsg 8. Tel\n042-1205 75. Bankgiro 437-8626.\nPostgiro 89888-2\nVerksamhet: Trycksaker\nAktiekapital: 100 000\nVerkst dir: Fru Kerstin Mattsson\nEtableringsår: 1923.\n\nKIL\n\nAktiekapital: 5 000\nVerkst dir: Ake G Karlsson\nEtableringsår: 1970.\n\nERIKSSON &amp; CARLSSON AB\n\nPnr 545 00\n\nTöreboda. Tel 0506-100 13.\nPostgiro 75930\n\nVerksamhet: Säljer konfektyrer\nAktiekapital: 200 000\nVerkst dir: Ragnar Westin\nEtableringsår: 1915.\n\nERIKSSON &amp; CO MEK\nVERKSTADS AB\n\nPrr 162 26\n\nVällingby. Krossg 43-45. Tel\n08-89 76 76, 89 76 30. Bankgiro\n730-4280. Postgiro 4586-4\nVerksamhet: Utför\njärnkonstruktioner, maskin-, mek-, montage-,\nsvetsnings-, tunn- o\ngrovplåts-arbeten. Tillverkar hydrauliska\nutrustningar\nAntal anställda: 24\nÅrsomsättning: 1500 000\nAktiekapital: 35 000\nEtableringsår: 1913.\n\nSNI\n\n67 55 26, 67 55 85. Bankgiro\n730-7390. Postgiro 57499-6\nVerksamhet: Försäljningskontor för\nbyggnadssnickerier o spånskivor\nAktiekapital: 15 000\nVerkst dir: Ing Martin Lindell\nEtableringsår: 1934.\n\nSNICKERIFABRIKER\n\nse resp namn.\n\nSNICKERIPRODUKTER\nOLMATS&amp; PERSSON AB\n\nPnr 828 00\n\nEdsbyn, Box 92. Tel 0271-212 75.\nBankgiro 78-6048. Postgiro\n345490-7\n\nVerksamhet: Tillverkar o säljer\nfönster samt ytterdörrar i standard\nAntal anställda: 225\nÅrsomsättning: 27 000 000\nAktiekapital: 1400 000\nVerkst dir: Disp Nils Holgersson\nEtableringsår: 1957.\n\nARE\n\nÅrsomsättning: 4 400 000\n\nAktiekapital: 150 000\n\nÄgare o chefer: Fabr Tage O Lorén,\n\nfabr Hans Ofverström\n\nEtableringsår: 1951\n\nOmbildat till aktiebolag 1957.\n\nAHREMARKS\nKONFEKTIONS AB\n\nPnr 50102\n\nBorås 1, Göteborgsv 10. Box 10.\nTel 033-117135, 117160.\nBankgiro 839-3050. Postgiro 72925-1.\nTga Swedus\n\nVerksamhet: Barn-, goss-, herr-,\nflick- o dambyxor\nAntal anställda: 85\nÅrsomsättning: 7 000 000\nAktiekapital: 500 000\nVerkst dir: Olof Ahremark\nEtableringsår: 1901.\n\nARVIKA NYHETER, AB\n\nPnr 67101\n\nArvika 1, Box 125. Repslagareg 16.\nTel 0570-140 80. Bankgiro 103-0204.\nPostgiro 28468-7\nVerksamhet: Tidningstryckeri.\nUtgivning 3 ggr i veckan\nAntal anställda: 37\nAktiekapital: 53 000\nVerkst dir: Owe Eklöf\nEtableringsår: 1895\nOmbildat till aktiebolag 1918.\n\nARVIKA PLASTINDUSTRI\n\nPnr 671 00\n\nArvika, Jössefors. Tel 0570-213 80,\n21194. Bankgiro 670-9844. Postgiro\n716780-2\n\nVerksamhet: Tillverkar båttypen\nS-30 ’Joker’, segelbåtar av\nhavs-kry s särtyp i glasfiberarmerad plast.\nBeställningsarbeten i\nglasfiberarmerad plast\nAntal anställda: 21\nÅrsomsättning: 2 500 000\nChefer: Jerry Albinsson, Kennet\nAlbinsson\n\nEtableringsår: 1969.\n\nSKÅNSKA BRAND.HERMES,\nÖMSESIDIGT, FORSÄKRINGS.\nBOLAGET\n\nPnr 22105\n\nLund 1, Tegnérsplatsen 4. Box\n1255. Tel 046-1170 50. Bankgiro\n660-6743. Postgiro 11010-6. Tga\nSkånskabrand. Telex 3349\nVerksamhet: Alla slag av\nförsäkringar (exklusive liv)\nVerkst dir: Sven-Thorsten Frostell\nEtableringsår: 1828.\n\nKAR\n\n601-4831. Postgiro 96588-9. Tga\nKnifeman\n\nVerksamhet: Tillverkar köksknivar,\nstekspadar o osthyvlar\nVarunamn: KN\nAntal anställda: 65\nÅrsomsättning: 5 500 000\nAktiekapital: 1 500 000\nVerkst dir: Gerhard Rydén\nEtableringsår: 1932.\n\nCARLSSON, VERKTYGS AB\nBRUDERNA\n\nPnr 59100\n\nMotala, Saturnusg 5. Tel\n0141-155 21. Bankgiro 821-9479.\nPostgiro 515275-6\n\nVerksamhet: Tillverkar press-,\nbock- o formverktyg, jiggar o\nfixturer\n\nAntal anställda: 20\nÅrsomsättning: 900 000\nAktiekapital: 60 000\nVerkst dir: Carl-Erik Carlsson\nEtableringsår: 1959.\n\nCARLSSON &amp; WESTERBERG\nVERKTYGSFABRIK, AB\n\nPnr 63103\n\nEskilstuna 1, Kungsg 59. Box 150.\nTel 016-1318 70, 13 07 72.\nBankgiro 601-3536. Postgiro 10783-9\nVerksamhet: Tillverkar\nexcenter-pressar o reservdelar till\nBolinder-Munktells pressar, svarvar o\nhejare samt gäng- o pressverktyg,\ngiggar, fixturer, gängringar,\ngängtolkar m m samt utför\nprecisions-gängslipning\nAntal anställda: 30\nÅrsomsättning: 1500 000\nAktiekapital: 250 000\nVerkst dir: Sven Lindberg\nEtableringsår: 1917\nOmbildat till aktiebolag 1943.\nÄgare AB Lundin &amp; Lindberg,\nEskilstuna.\n\nKARLSSON &amp; WINGESJD,\nBYGGNADS AB\n\nPnr 643 00\n\nVingåker, Hantverksg 29. Box 125.\nTel 0151-115 70. Bankgiro\n624-8140. Postgiro 139894-0\nVerksamhet: Nybyggnad av\nbostadshus o industribyggnader\nAntal anställda: 155\nÅrsomsättning: 20 000 000\nAktiekapital: 50 000\nVerkst dir: Ing Ingemar Wingesjö\nEtableringsår: 1934.",
    "structured": {
        "0": {
            "company_name": "LOBA, BYGG AB",
            "address": "Fack. Bantorget 1, 240 20 Flnulund",
            "phone_number": "046-32215",
            "bank_details": {
                "bankgiro": "673-1640",
                "postgiro": "38874-4"
            },
            "activity": "Byggnadsrörelse",
            "capital": 150000,
            "key_personnel": [
                {
                    "name": "Bertil Anderberg",
                    "position": "Verkst dir"
                }
            ],
            "establishment_year": 1958
        },
        "1": {
            "company_name": "ENGQVIST & UDESEN",
            "address": "Barlastg 2, 414 63 Göteborg",
            "phone_number": "031-12 44 90",
            "bank_details": {
                "bankgiro": "441-1757",
                "postgiro": "25491-2"
            },
            "activity": "Rostskydds- o impregneringsoljor, tjära",
            "employees": 28,
            "annual_turnover": 6000000,
            "key_personnel": [
                {
                    "name": "Dlr Arthur Udesen",
                    "position": "Ägare o chef"
                }
            ],
            "establishment_year": 1928
        },
        "2": {
            "company_name": "ENGLUND & JONSSON SNICKERIFABRIK",
            "address": "Kilafors, 823 00",
            "phone_number": "0278-500 70",
            "activity": "Tillverkar byggnadssnickerier",
            "key_personnel": [
                {
                    "name": "Alfr Englund",
                    "position": "Chef"
                }
            ],
            "establishment_year": 1927
        },
        "3": {
            "company_name": "ENGLUNDS KONTORSSERVICE AB",
            "address": "Engelbrektsg 32, 70105 Örebro 1, Box 350",
            "phone_number": "019-13 39 30, 013 39 31",
            "bank_details": {
                "bankgiro": "358-8381",
                "postgiro": "115911-0"
            },
            "activity": "Säljer kontorsmöbler, -maskiner o -förnödenheter",
            "employees": 10,
            "annual_turnover": 2000000,
            "capital": 15000,
            "key_personnel": [
                {
                    "name": "Jan Englund",
                    "position": "Verkst din"
                }
            ],
            "establishment_year": 1962
        },
        "4": {
            "company_name": "ENGLUNDS PROJEKTERINGS-BYRA AB",
            "address": "Importörv 23, 12173 Johanneshov",
            "phone_number": "08-81 02 60",
            "bank_details": {
                "bankgiro": "744-3732",
                "postgiro": "257330-1"
            },
            "activity": "Totalprojektering av byggnader genom avdelningar för arkitektur, byggnads-, vvs- o el-konstruktioner",
            "employees": 30,
            "capital": 100000,
            "key_personnel": [
                {
                    "name": "Ing Jonas Englund",
                    "position": "Ägare o chef"
                }
            ],
            "establishment_year": 1958
        },
        "5": {
            "company_name": "BERGSTEN, UGNSFIRMAN",
            "address": "Box 103, 510 47 Fristad",
            "activity": "Elektriska-, gas- o oljeeldade ugnar",
            "key_personnel": [
                {
                    "name": "Ing Hilding Bergsten",
                    "position": "Chef"
                }
            ],
            "establishment_year": 1955
        },
        "6": {
            "company_name": "BERGSTENS BOKTRYCKERI, AB ERNST",
            "address": "Rågångsg 8, 252 27 Helsingborg",
            "phone_number": "042-1205 75",
            "bank_details": {
                "bankgiro": "437-8626",
                "postgiro": "89888-2"
            },
            "activity": "Trycksaker",
            "capital": 100000,
            "key_personnel": [
                {
                    "name": "Fru Kerstin Mattsson",
                    "position": "Verkst dir"
                }
            ],
            "establishment_year": 1923
        },
        "7": {
            "company_name": "KIL",
            "capital": 5000,
            "key_personnel": [
                {
                    "name": "Ake G Karlsson",
                    "position": "Verkst dir"
                }
            ],
            "establishment_year": 1970
        },
        "8": {
            "company_name": "ERIKSSON & CARLSSON AB",
            "address": "545 00 Töreboda",
            "phone_number": "0506-100 13",
            "postgiro": "75930",
            "activity": "Säljer konfektyrer",
            "capital": 200000,
            "key_personnel": [
                {
                    "name": "Ragnar Westin",
                    "position": "Verkst dir"
                }
            ],
            "establishment_year": 1915
        },
        "9": {
            "company_name": "ERIKSSON & CO MEK VERKSTADS AB",
            "address": "Krossg 43-45, 162 26 Vällingby",
            "phone_number": "08-89 76 76, 89 76 30",
            "bank_details": {
                "bankgiro": "730-4280",
                "postgiro": "4586-4"
            },
            "activity": "Utför järnkonstruktioner, maskin-, mek-, montage-, svetsnings-, tunn- o grovplåts-arbeten. Tillverkar hydrauliska utrustningar",
            "employees": 24,
            "annual_turnover": 1500000,
            "capital": 35000,
            "establishment_year": 1913
        }
    }
}