{
    "original": "SAND EX, AB\n\nPnr 81100\n\nSandviken, Västanbyn. Tel\n026-25 21 00. Bankgiro 78-8784.\nPostgiro 372545\n\nVerksamhet: Montage av\nmaskinenheter inom industrin\nAntal anställda: 7\nÅrsomsättning: 200 000\nAktiekapital: 15 000\nVeikst dir: Folke Lindholm\nEtableringsår: 1962.\n\nSANDGRENS\nTRÄTOFFEL-FABRIK AB, BRUDERNA\n\nPnr 38024\n\nPåryd. Tel 0480-912 50. Tga\nSand-grenshoe, Kalmar\n\nVerksamhet: Tillverkar trätofflor o\nortopediska specialsandaler i\npatenterat utförande\nAntal anställda: 120\nÅrsomsättning: 10 000 000\nAktiekapital: 300 000\nVerkst dir: Börje Swanstein\nEtableringsår: 1906.\n\nVÄGG &amp; VALV AB\n\nPnr 417 34\n\nGöteborg, Ovädersg 14. Tel\n031-53 04 65. Bankgiro 441-1682.\nPostgiro 420984-7\n\nVerksamhet: Uthyr o säljer\nbyggnadsformar\nAntal anställda: 70\nÅrsomsättning: 7 000 000\nAktiekapital: 500 000\nVerkst dir: Georg Lindeberg\nEtableringsår: 1948.\n\nB LA\n\nBLACK &amp; DECKER LTD\nENGLAND-SVENSK FILIAL\n\nPnr 421 20\n\nVästra Frölunda 1, Fack. Frötallsg.\nTel 031-4904 40. Bankgiro 50-6731.\nPostgiro 622300. Tga Blacdeck.\nTelex 2541\n\nVerksamhet: Elektriska\nhandverktyg\n\nAntal anställda: 40\nÅrsomsättning: 20 000 000\nChef: Dir Lennart Ericsson\nEtableringsår: 1962.\n\nLAGERWALL AB,C A\n\nPnr 402 31\n\nGöteborg 7, Första Långg 21. Box\n7007. Tel 031-12 44 00. Bankgiro\n50-0218. Postgiro 25496-1. Tga\nLagship. Telex 20627\nVerksamhet: Skeppsmäkleri,\nlinje-agenturer o fartygsklarering\nAktiekapital: 40 000\nVerkst dir: Claes-Axel Lagerwall\nEtableringsår: 1960.\n\nLINDAHL &amp; NERMARK AB\n\nPnr 44101\n\nAlingsås 1, Pack. Göteborgsv 16.\nTel 0322-73000. Bankgiro436-5318.\nPostgiro 13913-9. Tga Luna.\nTelex 2409 LUNA S\nVerksamhet: Grosshandel med\nverktyg o maskiner. Tillverkar\nplåtbearbetning smaskiner\nVarunamn: Abrafile, Ahrens,\nBes-sey, Beyeler, Bombled, Boxer,\nBWP, Collins, Eckold, Emco-Mat,\nEmco-Star, Erdi, Evans, Fasti,\nForstner, Gedore, Inca, Just\nHansen, Knatten, Lockformer, Luna,\nMarco, Maximat, Mistral, Myford,\nOlwa, H K Porter, Promecam,\nStewe, Supreme, Trennjaeger,\nTrumpf, Turnus, Welty-Way, Wezel,\nWhitney, X-Acto\nAntal anställda: 250\nÅrsomsättning: 100 000 000\nAktiekapital: 2000000\nVerkst dir: Gunnar Lindahl\nInköpschef: Stig Lindahl\nFörsäljn-chef: Bertil Bernhult\nEkonomichef: Göte Granström\nReklamchef: Folke Nermark\nEtableringsår: 1917.\n\nHOLM|A, FORSÄKRINGS AB\n\nPnr 103 63\n\nStockholm 3, Sveav 31. Box 3185.\nTel 08-24 0190, 8103 10. Tga\nHolmiaförsäkra\n\nVerksamhet: Försäkringsrörelse\nAntal anställda: 47\nPremieinkomst: 11000 000\nAktiekapital: 1000 000\nStyrelse: Generalkonsul Carl Asker\n(ordf), generaldir Ernst Bexelius,\nadv Carl v Plomgren, dir Lennart\nde la Cour\n\nVerkst dir. Per Wahlström\nEtableringsår: 1923.\n\nHOLMKVIST, HOLMQUIST,\nHOLMQVIST\n\nHOLMKVIST &amp; HILL EST ROM,\nAB\n\nPnr 122 32\n\nEnskede, Enskedev 44-46. Tel\n08-481001. Bankgiro 571-2690.\nPostgiro 150994\n\nVerksamhet: Konstruerar o\ntillverkar specialmaskiner, instrument o\noljehydraulisk utrustning,\nhuvudsakligen inom finmekaniska\nområdet\n\nVeikst dir: Birger Flodström\nEtableringsår: 1921.\n\nDALSJOFORS TRYCKERI\n\nPnr 510 50\n\nDalsjöfors. Tel 033-70011.\nBankgiro 532-1393. Postgiro 75873-0\nVerksamhet: Trycksaker för\nhandel o industri\nAntal anställda: 3\nÄgare o chefer: G Hjort vall, B\nHjortvall\n\nEtableringsår: 1919.\n\nDALSKOGS ÅNGSÅG &amp;\nT RA FORÄDLINGS AB\n\nPnr 460 70\n\nDals Rostock, Dalskog. Tel\n0530-210 55. Bankgiro 533-7084.\nPostgiro 8 0268-6\n\nVerksamhet: Tillverkar dörr- o\nfönstersnickerier, inredningar.\nSäljer allt i byggmaterial\nAntal anställda: 45\nÅrsomsättning: 5 300000\nAktiekapital: 318000\nVerkst dir: Allan Jonasson\nEtableringsår: 1927.\n\nFEINSTEIN REVISIONSBYRÅ\nAB, STEN ERIK\n\nPnr 114 35\n\nStockholm, Riddarg 10. Tel\n08-23 19 55. Postgiro 56829\nVerksamhet: Revisionsbyrå\nAntal anställda: 12\nÅrsomsättning: 1000 000\nAktiekapital: 25000\nVerkst dir: Aukt revisor Sten\nErik Feinstein\nEtableringsår 1945.\n\nLEVY AB, HANS W\n\nPnr 402 21\n\nGöteborg 5, Box 5029. Tel\n031-18 41 01. Bankgiro 509-6730.\nPostgiro 424221-0. Tga Hanslev\nVerksamhet: Byggvaror,\nsanitetsin-redningar. Maskiner för keramisk- o\nglasindustri, pressverktyg.\nFörnödenheter för måleribranschen\nAktiekapital: 5 000\nVerkst dir: Ing Hans W Levy\nEtableringsår: 1952.\n\nERI\n\nVerkst dir: Ulf Ericson\nEtableringsår: 1932\nOmbildat till aktiebolag 1960.\n\nERICSSON, GECKO\nBYGG-MASKINER, AB G H\n\nPnr 230 30\n\nOxie. Tel 040-44 84 00, 44 84 01.\nBankgiro 64-1357. Postgiro 430961\nVerksamhet: Tillverkar garage- o\nindustriportar\nEtableringsår: 1950.",
    "structured": {
        "1": {
            "company_name": "SAND EX, AB",
            "pnr": "81100",
            "address": "Sandviken, Västanbyn",
            "phone_number": "026-25 21 00",
            "bank_details": {
                "bankgiro": "78-8784",
                "postgiro": "372545"
            },
            "activity": "Montage av maskinenheter inom industrin",
            "employees": 7,
            "annual_turnover": 200000,
            "capital": 15000,
            "key_personnel": [
                {
                    "name": "Folke Lindholm",
                    "position": "Veikst dir"
                }
            ],
            "establishment_year": 1962
        },
        "2": {
            "company_name": "SANDGRENS TRÄTOFFEL-FABRIK AB, BRUDERNA",
            "pnr": "38024",
            "address": "Påryd",
            "phone_number": "0480-912 50",
            "activity": "Tillverkar trätofflor o ortopediska specialsandaler i patenterat utförande",
            "employees": 120,
            "annual_turnover": 10000000,
            "capital": 300000,
            "key_personnel": [
                {
                    "name": "Börje Swanstein",
                    "position": "Verkst dir"
                }
            ],
            "establishment_year": 1906
        },
        "3": {
            "company_name": "VÄGG & VALV AB",
            "pnr": "417 34",
            "address": "Göteborg, Ovädersg 14",
            "phone_number": "031-53 04 65",
            "bank_details": {
                "bankgiro": "441-1682",
                "postgiro": "420984-7"
            },
            "activity": "Uthyr o säljer byggnadsformar",
            "employees": 70,
            "annual_turnover": 7000000,
            "capital": 500000,
            "key_personnel": [
                {
                    "name": "Georg Lindeberg",
                    "position": "Verkst dir"
                }
            ],
            "establishment_year": 1948
        },
        "4": {
            "company_name": "BLACK & DECKER LTD ENGLAND-SVENSK FILIAL",
            "pnr": "421 20",
            "address": "Västra Frölunda 1, Fack. Frötallsg.",
            "phone_number": "031-4904 40",
            "bank_details": {
                "bankgiro": "50-6731",
                "postgiro": "622300"
            },
            "activity": "Elektriska handverktyg",
            "employees": 40,
            "annual_turnover": 20000000,
            "key_personnel": [
                {
                    "name": "Lennart Ericsson",
                    "position": "Chef"
                }
            ],
            "establishment_year": 1962
        },
        "5": {
            "company_name": "LAGERWALL AB,C A",
            "pnr": "402 31",
            "address": "Göteborg 7, Första Långg 21, Box 7007",
            "phone_number": "031-12 44 00",
            "bank_details": {
                "bankgiro": "50-0218",
                "postgiro": "25496-1"
            },
            "activity": "Skeppsmäkleri, linje-agenturer o fartygsklarering",
            "capital": 40000,
            "key_personnel": [
                {
                    "name": "Claes-Axel Lagerwall",
                    "position": "Verkst dir"
                }
            ],
            "establishment_year": 1960
        },
        "6": {
            "company_name": "LINDAHL & NERMARK AB",
            "pnr": "44101",
            "address": "Alingsås 1, Pack. Göteborgsv 16",
            "phone_number": "0322-73000",
            "bank_details": {
                "bankgiro": "436-5318",
                "postgiro": "13913-9"
            },
            "activity": "Grosshandel med verktyg o maskiner. Tillverkar plåtbearbetning smaskiner",
            "varunamn": "Abrafile, Ahrens, Bes-sey, Beyeler, Bombled, Boxer, BWP, Collins, Eckold, Emco-Mat, Emco-Star, Erdi, Evans, Fasti, Forstner, Gedore, Inca, Just Hansen, Knatten, Lockformer, Luna, Marco, Maximat, Mistral, Myford, Olwa, H K Porter, Promecam, Stewe, Supreme, Trennjaeger, Trumpf, Turnus, Welty-Way, Wezel, Whitney, X-Acto",
            "employees": 250,
            "annual_turnover": 100000000,
            "capital": 2000000,
            "key_personnel": [
                {
                    "name": "Gunnar Lindahl",
                    "position": "Verkst dir"
                },
                {
                    "name": "Stig Lindahl",
                    "position": "Inköpschef"
                },
                {
                    "name": "Bertil Bernhult",
                    "position": "Försäljn-chef"
                },
                {
                    "name": "Göte Granström",
                    "position": "Ekonomichef"
                },
                {
                    "name": "Folke Nermark",
                    "position": "Reklamchef"
                }
            ],
            "establishment_year": 1917
        },
        "7": {
            "company_name": "HOLM|A, FORSÄKRINGS AB",
            "pnr": "103 63",
            "address": "Stockholm 3, Sveav 31, Box 3185",
            "phone_number": "08-24 0190, 8103 10",
            "activity": "Försäkringsrörelse",
            "employees": 47,
            "premieinkomst": 11000000,
            "capital": 1000000,
            "board_of_directors": [
                "Generalkonsul Carl Asker (ordf)",
                "generaldirektör Ernst Bexelius",
                "advokat Carl v Plomgren",
                "dir Lennart de la Cour"
            ],
            "verkst_dir": "Per Wahlström",
            "establishment_year": 1923
        },
        "8": {
            "company_name": "HOLMKVIST & HILL EST ROM, AB",
            "pnr": "122 32",
            "address": "Enskede, Enskedev 44-46",
            "phone_number": "08-481001",
            "bank_details": {
                "bankgiro": "571-2690",
                "postgiro": "150994"
            },
            "activity": "Konstruerar o tillverkar specialmaskiner, instrument o oljehydraulisk utrustning, huvudsakligen inom finmekaniska området",
            "key_personnel": [
                {
                    "name": "Birger Flodström",
                    "position": "Veikst dir"
                }
            ],
            "establishment_year": 1921
        },
        "9": {
            "company_name": "DALSJOFORS TRYCKERI",
            "pnr": "510 50",
            "address": "Dalsjöfors",
            "phone_number": "033-70011",
            "bank_details": {
                "bankgiro": "532-1393",
                "postgiro": "75873-0"
            },
            "activity": "Trycksaker för handel o industri",
            "employees": 3,
            "owners_and_managers": [
                "G Hjortvall",
                "B Hjortvall"
            ],
            "establishment_year": 1919
        },
        "10": {
            "company_name": "DALSKOGS ÅNGSÅG & TRÄFORÄDLINGS AB",
            "pnr": "460 70",
            "address": "Dals Rostock, Dalskog",
            "phone_number": "0530-210 55",
            "bank_details": {
                "bankgiro": "533-7084",
                "postgiro": "8 0268-6"
            },
            "activity": "Tillverkar dörr- o fönstersnickerier, inredningar. Säljer allt i byggmaterial",
            "employees": 45,
            "annual_turnover": 5300000,
            "capital": 318000,
            "key_personnel": [
                {
                    "name": "Allan Jonasson",
                    "position": "Verkst dir"
                }
            ],
            "establishment_year": 1927
        },
        "11": {
            "company_name": "FEINSTEIN REVISIONSBYRÅ AB, STEN ERIK",
            "pnr": "114 35",
            "address": "Stockholm, Riddarg 10",
            "phone_number": "08-23 19 55",
            "postgiro": "56829",
            "activity": "Revisionsbyrå",
            "employees": 12,
            "annual_turnover": 1000000,
            "capital": 25000,
            "key_personnel": [
                {
                    "name": "Aukt revisor Sten Erik Feinstein",
                    "position": "Verkst dir"
                }
            ],
            "establishment_year": 1945
        },
        "12": {
            "company_name": "LEVY AB, HANS W",
            "pnr": "402 21",
            "address": "Göteborg 5, Box 5029",
            "phone_number": "031-18 41 01",
            "bank_details": {
                "bankgiro": "509-6730",
                "postgiro": "424221-0"
            },
            "activity": "Byggvaror, sanitetsin-redningar. Maskiner för keramisk- o glasindustri, pressverktyg. Förnödenheter för måleribranschen",
            "capital": 5000,
            "key_personnel": [
                {
                    "name": "Ing Hans W Levy",
                    "position": "Verkst dir"
                }
            ],
            "establishment_year": 1952
        },
        "13": {
            "company_name": "ERICSSON, GECKO BYGG-MASKINER, AB G H",
            "pnr": "230 30",
            "address": "Oxie",
            "phone_number": "040-44 84 00, 44 84 01",
            "bank_details": {
                "bankgiro": "64-1357",
                "postgiro": "430961"
            },
            "activity": "Tillverkar garage- o industriportar",
            "establishment_year": 1950
        }
    }
}