{
    "original": "SYD\n\nSYDFERNISS, AB\n\nPnr 251 03\n\nHelsingborg 1, Box 203. Cindersg\n16. Tel 042-18 01 60. Tga\nSydfer-niss. Telex 72221\nVerksamhet: Tillverkar o säljer\nfärger o läcker\nAktiekapital: 200 000\nVerkst dir: Bertil Lidal\nEtableringsår: 1924.\n\nLÄCKÖ, PLAST AB\n\nPnr 330 20\n\nAnderstorp, Tokarp. Tel\n0371-154 60. Bankgiro 48-8038. Postgiro\n371333\n\nVerksamhet: Utför\nindustrilackering o tillverkar trådartiklar\nAntal anställda: 12\nAktiekapital: 30 000\nVerkst dir: Kjell Hedlund\nEtableringsår: 1949\nOmbildat till aktiebolag 1956.\n\nLACTAMIN, AB\n\nPnr 104 35\n\nStockholm 23, Pack. Sveav 166. Tel\n08-23 11 50. Bankgiro 722-4397.\nPostgiro 450683-8\nVerksamhet: Tillverkar o säljer\nfoder till kalvar, svin o lamm\nAntal anställda: 50\nÅrsomsättning: 55 000 000\nAktiekapital: 10 000\nVerkst dir: Anders Bergström\nEtableringsår: 1955.\n\nAKTINO PLAST AB\n\nPnr 126 21\n\nHägersten 1, Box 40. Glidgränd 13.\nTel 08-46 08 90, 46 9293\nVerksamhet: Tillverkar o säljer\nplastartiklar, hyllbård\nAktiekapital: 20 000\nVerkst dir: J G Nordström\nEtableringsår: 1954.\n\nAKTIV FORETAGS.\nLEDNING AB\n\nPnr 211 37\n\nMalmö, Stora Nyg 65. Tel\n040-351 23. Bankgiro 260-5145.\nPost-giro 538811-1\n\nVerksamhet: Konsulter till mindre\no medelstora företag inom\nföretagsledning, långsiktsplanering,\nmarknadsfrågor, organisatoriska\nfrågor, personurval. Ekonomisk\nplanering o kontroll. Uppdrag\nsåsom styrelseledamöter\nFilial: 411 32 Göteborg, Pontus\nWiknersg 3\nAntal anställda: 3\nÅrsomsättning: 350 000\nAktiekapital: 15000\nVerkst dir: Sven Olof Ariebäck\nDirektörsass: Fil kand Hans\nBrunlid\n\nEtableringsår: 1962.\n\nLÖVENKJÄR AB, S\n\nPnr 280 40\n\nSkånes Fagerhult, Box 65. Tel\n0433-302 70. Bankgiro 532-3555.\nPostgiro 117676-7\nVerksamhet: Tillverkar packningar\ntill bilindustrin. Kompressorer,\nmotorsågar, mopeder, pumpar,\nkranar, ventiler, värmeväxlare mm\nAntal anställda: 18\nÅrsomsättning: 2 000 000\nAktiekapital: 25 000\nStyrelse: Bankdir Nils Gustafsson,\nfabr Svend Lövenkjär, fru Rita\nGustafsson\n\nVerkst dir: Svend Lövenkjär\nEtableringsår: 1968.\n\nLOVENS LÄKEMEDEL AB\n\nPnr 20110\n\nMalmö 1, Citadellsv 19. Fack. Tel\n040-756 30. Bankgiro 644-9656.\nPostgiro 539696-5. Tga Lionpharm\nVerksamhet: Säljer läkemedel\nAntal anställda: 30\nÅrsomsättning: 10 000 000\nAktiekapital: 500 000\nVeikst dir: Arne L Sjöberg\nEtableringsår: 1960.\n\nEKELUND &amp; ESSPE, AB\n\nPnr 51010\n\nHorred. Tel 0320-800 01, 801 61.\nBankgiro 43-5814. Postgiro 22661.\nTga Linnevaror\n\nVerksamhet: Tillverkar\nlinnevävnader, tapisseri o allmogevävnader\nAntal anställda: 8\nÅrsomsättning: 500 000\nAktiekapital: 200 000\nVerkst dir: Per Ekelund\nEtableringsår: 1909.\n\nVISKAVERKEN AB\n\nPnr 400 14\n\nGöteborg 53. Erie Dahlbergsg 11 B.\nBox 53044. Tel 031-11 8500,\n114611. Bankgiro 420-5878.\nPostgiro 528407-0. Tga Viskaverken\nVerksamhet: Tillverkar\nnavrondel-ler o kapskivor, fiberrondeller,\nmetallsågblad, svarvdubbar o\nskaftkilar\n\nVarunamn: Raffo\nÅrsomsättning: 1000 000\nAktiekapital: 5000\nVeikst dir: Sture Brocker\nEtableringsår. 1960.\n\nBORJESON AB, GILLIS\n\nPnr 292 00\n\nKarlshamn, Box 141. Prinsg 2. Tel\n0454-142 90. Bankgiro 65-6590.\nPostgiro 468293-6. Tga Gillis.\nTelex 4561\n\nVerksamhet: Skeppsmäkleri o\nbefraktning, skeppskl ar ering\nAntal anställda: 12\nAktiekapital: 10 000\nVerkst dir: Gillis Börjeson\nEtableringsår: 1945.\n\nBORJESSON &amp; CO,\nBYGGNADS AB H\n\nPnr 41119\n\nGöteborg, Kungsg 26. Tel 031-\n\n13 32 05,13 22 90. Bankgiro84-8035.\nPostgiro 25590\n\nVerksamhet: Nybyggnader,\nändringar o reparationer\nAktiekapital: 35 000\nVerkst dir: Owe Holm\nEtableringsår: 1886.\n\nKILSTRDMERS AB\n\nPnr 41115\n\nGöteborg, Kyrkog 4. Tel\n031-17 73 70. Postgiro 529172.\nBankgiro 50-6629. Tga Westport\nVerksamhet: Leverans o montering\nav flyttbara mellanväggar\nAntal anställda: 14\nÅrsomsättning: 2 900 000\nAktiekapital: 15 000\nVerkst dir: Ing Lennart Kilströmer\nEtableringsår: 1960.\n\nKILSTRÖMER, INGENIORS.\nFIRMA LENNART\n\nPnr 41115\n\nGöteborg, Kyrkog 4. Tel\n031-17 73 70. Bankgiro 50-6548.\nPostgiro 425598. Tga Westport\nVerksamhet: Leverans av\ngarage-o industriportar\nAntal anställda: 4\nÅrsomsättning: 900 000\nÄgare o chef: Ing Lennart\nKilströmer\n\nEtableringsår: 1952.\n\nKILSVERKEN, AB\n\nPnr 665 00\n\nKU, Box 57. Tel 0554-11040.\nBankgiro 881-3354. Postgiro 289059-8\nVerksamhet: Tillverkar maskiner o\napparater för pappers- o\ncellulosaindustrin\n\nAntal anställda: 125\nÅrsomsättning: 9 000 000\nAktiekapital: 85 000\nVerkst dir: Lennart Bylock\nEtableringsår: 1957.\n\nSTRÅLFORS AB, TH\n\nPnr 34100\n\nLjungby, Hälsingborgsv. Box 138.\nTel 0372-124 90. Bankgiro\n276-9404. Postgiro 37459-0. Tga\nTehå-ess. Telex 4657\n\nVerksamhet: Tillverkar hålkort,\n\nändlösa blanketter o snabbset,\nhålremsor, färgband för computers\nAntal anställda: 300\nÅrsomsättning: 50 000 000\nAktiekapital: 150 000\nVerkst dir: Göthe Parkander\nEtableringsår: 1919.\n\nBANDSKÄRNING AB\n\nPnr 330 23\n\nSnålandsstenar, Box 13. Ox elg 13.\nTel 0371-30241, 30413. Bankgiro\n427-6051. Postgiro 339559-7\nVerksamhet: Skär o säljer bandjärn\ni rullar samt plåt i format\nAntal anställda: 12\nÅrsomsättning: 3000 000\nAktiekapital: 60 000\nVerkst dir: Fabr Gunnar Stegerling\nEtableringsår: 1948.",
    "structured": {
        "1": {
            "company_name": "SYDFERNISS, AB",
            "pnr": "251 03",
            "address": "Helsingborg 1, Box 203. Cindersg 16",
            "phone_number": "042-18 01 60",
            "activity": "Tillverkar o säljer färger o läcker",
            "capital": 200000,
            "key_personnel": [
                {
                    "name": "Bertil Lidal",
                    "position": "Verkst dir"
                }
            ],
            "establishment_year": 1924
        },
        "2": {
            "company_name": "LÄCKÖ, PLAST AB",
            "pnr": "330 20",
            "address": "Anderstorp, Tokarp",
            "phone_number": "0371-154 60",
            "bank_details": {
                "bankgiro": "48-8038"
            },
            "activity": "Utför industrilackering o tillverkar trådartiklar",
            "employees": 12,
            "capital": 30000,
            "key_personnel": [
                {
                    "name": "Kjell Hedlund",
                    "position": "Verkst dir"
                }
            ],
            "establishment_year": 1949
        },
        "3": {
            "company_name": "LACTAMIN, AB",
            "pnr": "104 35",
            "address": "Stockholm 23, Pack. Sveav 166",
            "phone_number": "08-23 11 50",
            "bank_details": {
                "bankgiro": "722-4397",
                "postgiro": "450683-8"
            },
            "activity": "Tillverkar o säljer foder till kalvar, svin o lamm",
            "employees": 50,
            "annual_turnover": 55000000,
            "capital": 10000,
            "key_personnel": [
                {
                    "name": "Anders Bergström",
                    "position": "Verkst dir"
                }
            ],
            "establishment_year": 1955
        },
        "4": {
            "company_name": "AKTINO PLAST AB",
            "pnr": "126 21",
            "address": "Hägersten 1, Box 40. Glidgränd 13",
            "phone_number": "08-46 08 90, 46 9293",
            "activity": "Tillverkar o säljer plastartiklar, hyllbård",
            "capital": 20000,
            "key_personnel": [
                {
                    "name": "J G Nordström",
                    "position": "Verkst dir"
                }
            ],
            "establishment_year": 1954
        },
        "5": {
            "company_name": "AKTIV FORETAGS. LEDNING AB",
            "pnr": "211 37",
            "address": "Malmö, Stora Nyg 65",
            "phone_number": "040-351 23",
            "bank_details": {
                "bankgiro": "260-5145",
                "postgiro": "538811-1"
            },
            "activity": "Konsulter till mindre o medelstora företag inom företagsledning",
            "employees": 3,
            "annual_turnover": 350000,
            "capital": 15000,
            "key_personnel": [
                {
                    "name": "Sven Olof Ariebäck",
                    "position": "Verkst dir"
                },
                {
                    "name": "Fil kand Hans Brunlid",
                    "position": "Direktörsass"
                }
            ],
            "establishment_year": 1962
        },
        "6": {
            "company_name": "LÖVENKJÄR AB, S",
            "pnr": "280 40",
            "address": "Skånes Fagerhult, Box 65",
            "phone_number": "0433-302 70",
            "bank_details": {
                "bankgiro": "532-3555",
                "postgiro": "117676-7"
            },
            "activity": "Tillverkar packningar till bilindustrin",
            "employees": 18,
            "annual_turnover": 2000000,
            "capital": 25000,
            "key_personnel": [
                {
                    "name": "Svend Lövenkjär",
                    "position": "Verkst dir"
                }
            ],
            "establishment_year": 1968
        },
        "7": {
            "company_name": "LOVENS LÄKEMEDEL AB",
            "pnr": "20110",
            "address": "Malmö 1, Citadellsv 19",
            "phone_number": "040-756 30",
            "bank_details": {
                "bankgiro": "644-9656",
                "postgiro": "539696-5"
            },
            "activity": "Säljer läkemedel",
            "employees": 30,
            "annual_turnover": 10000000,
            "capital": 500000,
            "key_personnel": [
                {
                    "name": "Arne L Sjöberg",
                    "position": "Veikst dir"
                }
            ],
            "establishment_year": 1960
        },
        "8": {
            "company_name": "EKELUND &amp; ESSPE, AB",
            "pnr": "51010",
            "address": "Horred",
            "phone_number": "0320-800 01, 801 61",
            "bank_details": {
                "bankgiro": "43-5814",
                "postgiro": "22661"
            },
            "activity": "Tillverkar linnevävnader, tapisseri o allmogevävnader",
            "employees": 8,
            "annual_turnover": 500000,
            "capital": 200000,
            "key_personnel": [
                {
                    "name": "Per Ekelund",
                    "position": "Verkst dir"
                }
            ],
            "establishment_year": 1909
        },
        "9": {
            "company_name": "VISKAVERKEN AB",
            "pnr": "400 14",
            "address": "Göteborg 53, Erie Dahlbergsg 11 B. Box 53044",
            "phone_number": "031-11 8500, 114611",
            "bank_details": {
                "bankgiro": "420-5878",
                "postgiro": "528407-0"
            },
            "activity": "Tillverkar navrondel-ler o kapskivor, fiberrondeller, metallsågblad, svarvdubbar o skaftkilar",
            "tradename": "Raffo",
            "annual_turnover": 1000000,
            "capital": 5000,
            "key_personnel": [
                {
                    "name": "Sture Brocker",
                    "position": "Verkst dir"
                }
            ],
            "establishment_year": 1960
        },
        "10": {
            "company_name": "BORJESON AB, GILLIS",
            "pnr": "292 00",
            "address": "Karlshamn, Box 141. Prinsg 2",
            "phone_number": "0454-142 90",
            "bank_details": {
                "bankgiro": "65-6590",
                "postgiro": "468293-6"
            },
            "activity": "Skeppsmäkleri o befraktning, skeppskl ar ering",
            "employees": 12,
            "capital": 10000,
            "key_personnel": [
                {
                    "name": "Gillis Börjeson",
                    "position": "Verkst dir"
                }
            ],
            "establishment_year": 1945
        },
        "11": {
            "company_name": "BORJESSON &amp; CO, BYGGNADS AB H",
            "pnr": "41119",
            "address": "Göteborg, Kungsg 26",
            "phone_number": "031-13 32 05,13 22 90",
            "bank_details": {
                "bankgiro": "84-8035",
                "postgiro": "25590"
            },
            "activity": "Nybyggnader, ändringar o reparationer",
            "capital": 35000,
            "key_personnel": [
                {
                    "name": "Owe Holm",
                    "position": "Verkst dir"
                }
            ],
            "establishment_year": 1886
        },
        "12": {
            "company_name": "KILSTRDMERS AB",
            "pnr": "41115",
            "address": "Göteborg, Kyrkog 4",
            "phone_number": "031-17 73 70",
            "bank_details": {
                "postgiro": "529172",
                "bankgiro": "50-6629"
            },
            "activity": "Leverans o montering av flyttbara mellanväggar",
            "employees": 14,
            "annual_turnover": 2900000,
            "capital": 15000,
            "key_personnel": [
                {
                    "name": "Ing Lennart Kilströmer",
                    "position": "Verkst dir"
                }
            ],
            "establishment_year": 1960
        },
        "13": {
            "company_name": "KILSTRÖMER, INGENIORS. FIRMA LENNART",
            "pnr": "41115",
            "address": "Göteborg, Kyrkog 4",
            "phone_number": "031-17 73 70",
            "bank_details": {
                "bankgiro": "50-6548",
                "postgiro": "425598"
            },
            "activity": "Leverans av garage-o industriportar",
            "employees": 4,
            "annual_turnover": 900000,
            "key_personnel": [
                {
                    "name": "Ing Lennart Kilströmer",
                    "position": "Ägare o chef"
                }
            ],
            "establishment_year": 1952
        },
        "14": {
            "company_name": "KILSVERKEN, AB",
            "pnr": "665 00",
            "address": "KU, Box 57",
            "phone_number": "0554-11040",
            "bank_details": {
                "bankgiro": "881-3354",
                "postgiro": "289059-8"
            },
            "activity": "Tillverkar maskiner o apparater för pappers- o cellulosaindustrin",
            "employees": 125,
            "annual_turnover": 9000000,
            "capital": 85000,
            "key_personnel": [
                {
                    "name": "Lennart Bylock",
                    "position": "Verkst dir"
                }
            ],
            "establishment_year": 1957
        },
        "15": {
            "company_name": "STRÅLFORS AB, TH",
            "pnr": "34100",
            "address": "Ljungby, Hälsingborgsv. Box 138",
            "phone_number": "0372-124 90",
            "bank_details": {
                "bankgiro": "276-9404",
                "postgiro": "37459-0"
            },
            "activity": "Tillverkar hålkort, ändlösa blanketter o snabbset, hålremsor, färgband för computers",
            "employees": 300,
            "annual_turnover": 50000000,
            "capital": 150000,
            "key_personnel": [
                {
                    "name": "Göthe Parkander",
                    "position": "Verkst dir"
                }
            ],
            "establishment_year": 1919
        },
        "16": {
            "company_name": "BANDSKÄRNING AB",
            "pnr": "330 23",
            "address": "Snålandsstenar, Box 13. Ox elg 13",
            "phone_number": "0371-30241, 30413",
            "bank_details": {
                "bankgiro": "427-6051",
                "postgiro": "339559-7"
            },
            "activity": "Skär o säljer bandjärn i rullar samt plåt i format",
            "employees": 12,
            "annual_turnover": 3000000,
            "capital": 60000,
            "key_personnel": [
                {
                    "name": "Fabr Gunnar Stegerling",
                    "position": "Verkst dir"
                }
            ],
            "establishment_year": 1948
        }
    }
}