{
    "original": "BEJRA MÖBLER I TIBRO AB\n\nPnr 543 01\n\nT ib ro 1, Fabrik sg 5. Box 133. Tel\n0504-125 00. Bankgiro 221-3809.\nPostgiro 268859-6. Tga Bejra\nVerksamhet: Tillverkar\nsoffgrup-per, kompletteringsfåtöljer o\nbäddsoffor\n\nAntal anställda: 80\nÅrsomsättning: 12 000 000\n\nAktiekapital: 120 000\nVerkst dir: Beyron Andersson\nEtableringsår: 1948.\n\nTRUBENBACH AB, A G HEINR\n\nPnr 416 64\n\nGöteborg. Fabrik N Agatan 10.\nTel 031-19 07 09. Butik Magasinsg\n8. Tel 031-13 14 36. Bankgiro\n500-1508. Postgiro 41310-4\nVerksamhet: Stämpelfabrik o\ngravyrateljé\n\nÄgare o chef: A Bengtsson\nEtableringsår 1886.\n\nDLW SVENSKA AB\n\nPnr 102 51\n\nStockholm 27, Box 27063.\nVal-hallav 191 A. Tel 08-63 58 90.\nBankgiro 700-4815. Postgiro\n53855-3. Tga Deelwe.\nTelex 10458 DEELWE S\nVerksamhet: Tillverkar alla slag\nav golvbeläggning\nVarunamn: DLW Linoleum, DLW\nHeltäckningsmattor, DLW Plast,\nDeltex\n\nAntal anställda: 8\nÅrsomsättning: 10000 000\nAktiekapital: 25 000\nVerkst dir: Bcris Kostenko\nEtableringsår: 1963.\n\nLUNDVALL AB, HILDING\n\nPnr 70104\n\nÖrebro 1, Storg 16. Box 300. Tel\n019-13 09 30. Bankgiro 463186.\nPostgiro 21275\n\nVeiksamhet: Säljer möbler i parti\nAntal anställda: 8\nÅrsomsättning: 6 95 0 000\nAktiekapital: 200 000\nVerkst dir: Ing Ake Lundvall\nEtableringsår: 1911\nOmbildat till aktiebolag 1937.\n\nLUNDÅS VERKSTÄDER AB\n\nPnr 763 02\n\nHallstavik 2, Box 207. Tel\n0175-208 51, 208 52\n\nVerksamhet: Tillverkar\nkallpressa-de skruvar o andra automatstukade\nmassartiklar av legerat främst\nrostfritt stål, utför legohärdning\nAntal anstäUda: 34\nÅrsomsättning: 2 450 000\nAktiekapital: 200 000\nStyrelse: Grossh Ludvig Engström\n(ordf), disp Stig Engström, civ-ing\nEsbjörn Sunström\nVeikst dir: Civiling Esbjörn\nSunström\n\nEtableringsår: 1946.\n\nLUOSSAVAARA- Kl IR\nUNA-VAARA AB\n\nPnr 100 41\n\nStockholm 26, Stureg 11. Pack. Tel\n08-24 90 60. Tga Luossavara.\nTelex 1812 LKABS S\nVerksamhet: Bryter o förädlar\njärnmalm i Kiruna, Svappavaara\no Malmberget. Produkterna\nskeppas över de egna hamnarna i Luleå\no Narvik\n\nFörvaltningar: Kiruna. Tel\n0980-120 00. Telex 8755\nLuleå 1, Box 1. Tel 0920-10190.\nTelex 8337. Tga Malmexport\nMalmberget, Bolagsv. Tel\n0970-210 00. Telex 8665. Tga\nGällivaremalm\n\nÅrsomsättning: 1148 000 000\nAktiekapital: 500 000 000\nStyrelse: Riksbankschef Per\nAs-brink (ordf), riksdagsman Thure\nDahlberg, ing Gunnar Fjällborg,\nriksdagsman Torsten Fredriksson,\nlandshövd Mats Lemne, envoyé\nArne S Lundberg, tekn dr Hjalmar\nOlson, gruvarbetare Bruno Poromaa,\ndir Erland Waldenström\nVerkst dir: Arne S Lundberg\nEtableringsår: 1890.\n\nLURS SNICKERIFABRIK &amp;\nTRÄVARUAFFÄR, AB\n\nPnr 450 83\n\nLur. Tel 0525-240 14. Bankgiro\n429-4583. Postgiro 3689 69-2\nVeiksamhet: Tillverkar ytterdörrar\nAntal anställda: 8\nÅrsomsättning: 600 000\nAktiekapital: 5 000\nVerkst dir: Sven Hultman\nEtableringsår: 1949.\n\nVITAVA AB\n\nPnr 102 24\n\nStockholm 12. Box 12170.\nFran-zéng 9. Tel 08-54 10 40. Postgiro\n653860. Tga Vitavapharm\nVerksamhet: Agenturer med\nfarmacevtiska preparat o kemikalier\nAktiekapital: 5 000\nEtableringsår: 1954.\n\nSIGMA AB\n\nPnr 10122\n\nStockholm 1, Drottningg 61. Box\n183. Tel 08-1127 52, 20 48 58. Tga\nSigmacomp\n\nVerksamhet: Export o import\nAktiekapital: 5 250\nVeikst dir: Oskar Strömbäck\nEtableringsår 1927.\n\nSIGMA AB,\nINGENJÖRS-FIRMAN\n\nPnr 25102\n\nHelsingborg 1, Box 71. Bryggareg\n35 A. Tel 042-18 00 60. Bankgiro\n653-0315. Postgiro 129210-1. Tga\nSigma. Telex 72408\nVeiksamhet: Maskiner o\nmaskinverktyg, pumpar o pumpaggregat\nAktiekapital: 100 000\nEtableringsår: 1950.\n\nALSTRÖM AB, RAGNAR\n\nPnr 50102\n\nBorås 1, Box 50. Drufveforsv 32.\nTel 033-1124 05, 1194 55.\nBankgiro 839-3068. Postgiro 33009-2\nVerksamhet:\nHerrkonfektionsfabrik\n\nAktiekapital: 100 000\nVerkst dir: Rune Thureson\nEtableringsår: 1943.\n\nKRONOBERG, TRÄVARU AB\n\nPnr 360 33\n\nRäppe, Räppev. Box 34. Tel\n0470-606 40. Bankgiro 35-7123. Postgiro\n34876. Tga Krono\nVerksamhet: Tillverkar lådbräder,\nträemballage, backar, lastpallar\nAntal anställda: 33\nÅrsomsättning: 4 000 000\nAktiekapital: 200 000\nDisp: Stig Skärström\nEtableringsår: 1923.\n\nELNIVA AB, INGENJÖRSFIRMA\n\nPnr 212 32\n\nMalmö 14, Box 14003. Virentoftag 1.\nTel 040-4918 58, 4919 58.\nBankgiro 876-5422. Postgiro 632074-1.\nTelex 32629\n\nVerksamhet: Tillverkar o säljer\nelektr nivå vakter för korniga,\ngra-nulerade o pulverformiga produkter\nsamt för vätskor. Generalagentur\nför Protimeter vattenhaltsmätare o\nHunting vattenhaltsregulatorer\nsamt Bin-o-Matic nivåvakter\nVarunamn: Bin-O-Matic, Elniva,\nHunting, Protimeter\nÅrsomsättning: 600 000\nAktiekapital: 10000\nVerkst dir. Ing Bertil Nilsson\nEtableringsår: 1965.\n\nTHOMÉE AB, EDW H\n\nPnr 201 10\n\nMalmö 1, Engelbrektsg 11. Fack.\nTel 040-707 60. Bankgiro 260-2688.\nPostgiro 14063-2. Tga Edwin.\nTelex 3104 EDWIN S\nVerksamhet: Grossistföretag inom\njärnmanufakturbranschen med\nförsäljning av bl a skruv,\nbyggnadsbeslag, lås, bult, handredskap,\nstängselnät, spik, ståltråd,\ntackjärn, rör. Tillverkar inredningar\nAntal anställda: 70\nÅrsomsättning: 25 000 000\nAktiekapital: 1400 000\n\nStyrelse: Dir Per-Hjalmar\nFagerholm (ordf), dir Sven Broman, Jens\nGelbjerg-Hansen\nVerkst dir: Sven Broman\nEtableringsår 1892\nOmbildat till aktiebolag 1916.\nDotterbolag: AB Hörle Tråd,\nThomées Lantbruksmaskiner AB.\n\nTHOMÉE AB, GUSTAF\n\nPnr 20011\n\nMalmö 6, Drottningtorget 4. Box\n6050. Tel 040-711 25. Bankgiro\n874-8303. Postgiro 531140-2. Tga\nGustaf. Telex 32572\nVerksamhet: Säljer\nindustrikemikalier, plastråvaror\nAntal anstäUda: 4\nÅrsomsättning: 8 000 000\nAktiekapital: 5 000\nChef: Ing Nils Bengtsson\nEtableringsår: 1882.\n\nTOMELILLA EXPRESSBYRÅ,\nAB\n\nPnr 273 00\n\nTomelilla, Klintg 4. Tel\n0417-116 35. Bankgiro 351-7034.\nPostgiro 294513-7\nVerksamhet: Åkeri\nOmbudskontor: Ystad. AB\nGodstrafik &amp; Bilspedition, V Hamnområdet.\nTel 0411-142 50\nAntal anställda: 60\nÅrsomsättning: 5 500 000\nAktiekapital: 150 000\nStyrelse: Anna Andersson, Elvin\nAndersson, Georg Andersson\nVerkst dir: Georg Andersson\nEtableringsår: 1912\nOmbildat till aktiebolag 1955.\n\nTOMELILLA SPARBANK\n\nPnr 273 00\n\nTomeMla, Box 117. Torget 4. Tel\n0417-125 10. Bankgiro 981-3585.\nPostgiro 329143-2\nVerksamhet: Bankrörelse\nAntal anställda: 18\nÅrsomsättning: 105 400 000\nStyrelseordf: Rektor Ivan Olsson\nVerkst dir: Kurt Jansson\nUtlåning: Kamrer Roland Lönnmyr\nInlåning o expedition: Kamrer Lars\nKarlsson\n\nEtableringsår: 1882.\n\nTOMELILLA TRÄVARU AB\n\nPnr 273 00\n\nTomeliUa, Industrig. Box 72. Tel\n0417-113 50, 115 50. Bankgiro\n671-1097, 617-0922. Postgiro\n494660-4\n\nVerksamhet: Tillverkar o sälj er\nträvaror. Byggnadsmaterial\n.Antal anstäUda: 50\nÅrsomsättning: 6 000 000\nÄgare o chef: Trävaruhandl\nPehr-Arne Pehrsson\nEtableringsår 1956.",
    "structured": {
        "1": {
            "company_name": "BEJRA MÖBLER I TIBRO AB",
            "pnr": "543 01",
            "address": "Tibro 1, Fabriksgatan 5, Box 133",
            "phone_number": "0504-125 00",
            "bank_details": {
                "bankgiro": "221-3809",
                "postgiro": "268859-6"
            },
            "activity": "Tillverkar soffgrupper, kompletteringsfåtöljer och bäddsoffor",
            "employees": 80,
            "annual_turnover": 12000000,
            "capital": 120000,
            "key_personnel": [
                {
                    "name": "Beyron Andersson",
                    "position": "Verkställande direktör"
                }
            ],
            "establishment_year": 1948
        },
        "2": {
            "company_name": "TRUBENBACH AB, A G HEINR",
            "pnr": "416 64",
            "address": "Göteborg, Fabrik N Agatan 10",
            "phone_number": "031-19 07 09",
            "bank_details": {
                "bankgiro": "500-1508",
                "postgiro": "41310-4"
            },
            "activity": "Stämpelfabrik och gravyrateljé",
            "owners": "A Bengtsson",
            "establishment_year": 1886
        },
        "3": {
            "company_name": "DLW SVENSKA AB",
            "pnr": "102 51",
            "address": "Stockholm 27, Box 27063, Valhallavägen 191 A",
            "phone_number": "08-63 58 90",
            "bank_details": {
                "bankgiro": "700-4815",
                "postgiro": "53855-3"
            },
            "activity": "Tillverkar alla slag av golvbeläggning",
            "varunamn": "DLW Linoleum, DLW Heltäckningsmattor, DLW Plast, Deltex",
            "employees": 8,
            "annual_turnover": 10000000,
            "capital": 25000,
            "key_personnel": [
                {
                    "name": "Bcris Kostenko",
                    "position": "Verkställande direktör"
                }
            ],
            "establishment_year": 1963
        },
        "4": {
            "company_name": "LUNDVALL AB, HILDING",
            "pnr": "70104",
            "address": "Örebro 1, Storgatan 16, Box 300",
            "phone_number": "019-13 09 30",
            "bank_details": {
                "bankgiro": "463186",
                "postgiro": "21275"
            },
            "activity": "Säljer möbler i parti",
            "employees": 8,
            "annual_turnover": 6950000,
            "capital": 200000,
            "key_personnel": [
                {
                    "name": "Ing Ake Lundvall",
                    "position": "Verkställande direktör"
                }
            ],
            "establishment_year": 1911
        },
        "5": {
            "company_name": "LUNDÅS VERKSTÄDER AB",
            "pnr": "763 02",
            "address": "Hallstavik 2, Box 207",
            "phone_number": "0175-208 51, 208 52",
            "activity": "Tillverkar kallpressade skruvar och andra automatstukade massartiklar av legerat främst rostfritt stål, utför legohärdning",
            "employees": 34,
            "annual_turnover": 2450000,
            "capital": 200000,
            "key_personnel": [
                {
                    "name": "Grossh Ludvig Engström",
                    "position": "Styrelseordförande"
                },
                {
                    "name": "Stig Engström",
                    "position": "Disponent"
                },
                {
                    "name": "Esbjörn Sunström",
                    "position": "Civilingenjör"
                },
                {
                    "name": "Esbjörn Sunström",
                    "position": "Verkställande direktör"
                }
            ],
            "establishment_year": 1946
        },
        "6": {
            "company_name": "LUOSSAVAARA-KIIRUNAVAARA AB",
            "pnr": "100 41",
            "address": "Stockholm 26, Sturegatan 11, Pack",
            "phone_number": "08-24 90 60",
            "activity": "Bryter och förädlar järnmalm i Kiruna, Svappavaara och Malmberget. Produkterna skeppas över de egna hamnarna i Luleå och Narvik",
            "forvaltningar": {
                "kiruna": "0980-120 00",
                "luleå": "0920-10190",
                "malmberget": "0970-210 00"
            },
            "annual_turnover": 1148000000,
            "capital": 500000000,
            "key_personnel": [
                {
                    "name": "Riksbankschef Per Asbrink",
                    "position": "Styrelseordförande"
                },
                {
                    "name": "Thure Dahlberg",
                    "position": "Riksdagsman"
                },
                {
                    "name": "Gunnar Fjällborg",
                    "position": "Ingenjör"
                },
                {
                    "name": "Torsten Fredriksson",
                    "position": "Riksdagsman"
                },
                {
                    "name": "Mats Lemne",
                    "position": "Landshövding"
                },
                {
                    "name": "Arne S Lundberg",
                    "position": "Envoyé"
                },
                {
                    "name": "Hjalmar Olson",
                    "position": "Teknologie doktor"
                },
                {
                    "name": "Bruno Poromaa",
                    "position": "Gruvarbetare"
                },
                {
                    "name": "Erland Waldenström",
                    "position": "Direktör"
                },
                {
                    "name": "Arne S Lundberg",
                    "position": "Verkställande direktör"
                }
            ],
            "establishment_year": 1890
        },
        "7": {
            "company_name": "LURS SNICKERIFABRIK & TRÄVARUAB",
            "pnr": "450 83",
            "address": "Lur",
            "phone_number": "0525-240 14",
            "bank_details": {
                "bankgiro": "429-4583",
                "postgiro": "368969-2"
            },
            "activity": "Tillverkar ytterdörrar",
            "employees": 8,
            "annual_turnover": 600000,
            "capital": 5000,
            "key_personnel": [
                {
                    "name": "Sven Hultman",
                    "position": "Verkställande direktör"
                }
            ],
            "establishment_year": 1949
        },
        "8": {
            "company_name": "VITAVA AB",
            "pnr": "102 24",
            "address": "Stockholm 12, Box 12170, Franzéngatan 9",
            "phone_number": "08-54 10 40",
            "bank_details": {
                "postgiro": "653860"
            },
            "activity": "Agenturer med farmaceutiska preparat och kemikalier",
            "capital": 5000,
            "establishment_year": 1954
        },
        "9": {
            "company_name": "SIGMA AB",
            "pnr": "10122",
            "address": "Stockholm 1, Drottninggatan 61, Box 183",
            "phone_number": "08-1127 52, 20 48 58",
            "activity": "Export och import",
            "capital": 5250,
            "key_personnel": [
                {
                    "name": "Oskar Strömbäck",
                    "position": "Verkställande direktör"
                }
            ],
            "establishment_year": 1927
        },
        "10": {
            "company_name": "SIGMA AB, INGENJÖRS-FIRMAN",
            "pnr": "25102",
            "address": "Helsingborg 1, Box 71, Bryggaregatan 35 A",
            "phone_number": "042-18 00 60",
            "bank_details": {
                "bankgiro": "653-0315",
                "postgiro": "129210-1"
            },
            "activity": "Maskiner och maskinverktyg, pumpar och pumpaggregat",
            "capital": 100000,
            "establishment_year": 1950
        },
        "11": {
            "company_name": "ALSTRÖM AB, RAGNAR",
            "pnr": "50102",
            "address": "Borås 1, Box 50, Drufveforsvägen 32",
            "phone_number": "033-1124 05, 1194 55",
            "bank_details": {
                "bankgiro": "839-3068",
                "postgiro": "33009-2"
            },
            "activity": "Herrkonfektionsfabrik",
            "key_personnel": [
                {
                    "name": "Rune Thureson",
                    "position": "Verkställande direktör"
                }
            ],
            "establishment_year": 1943
        },
        "12": {
            "company_name": "KRONOBERG, TRÄVARU AB",
            "pnr": "360 33",
            "address": "Räppe, Räppevägen, Box 34",
            "phone_number": "0470-606 40",
            "bank_details": {
                "bankgiro": "35-7123",
                "postgiro": "34876"
            },
            "activity": "Tillverkar lådbräder, träemballage, backar, lastpallar",
            "employees": 33,
            "annual_turnover": 4000000,
            "capital": 200000,
            "key_personnel": [
                {
                    "name": "Stig Skärström",
                    "position": "Disponent"
                }
            ],
            "establishment_year": 1923
        },
        "13": {
            "company_name": "ELNIVA AB, INGENJÖRSFIRMA",
            "pnr": "212 32",
            "address": "Malmö 14, Box 14003, Virentoftagatan 1",
            "phone_number": "040-4918 58, 4919 58",
            "bank_details": {
                "bankgiro": "876-5422",
                "postgiro": "632074-1"
            },
            "activity": "Tillverkar och säljer elektrnivåvakter för korniga, granulerade och pulverformiga produkter samt för vätskor. Generalagentur för Protimeter vattenhaltsmätare och Hunting vattenhaltsregulatorer samt Bin-o-Matic nivåvakter",
            "varunamn": "Bin-O-Matic, Elniva, Hunting, Protimeter",
            "annual_turnover": 600000,
            "capital": 10000,
            "key_personnel": [
                {
                    "name": "Ing Bertil Nilsson",
                    "position": "Verkställande direktör"
                }
            ],
            "establishment_year": 1965
        },
        "14": {
            "company_name": "THOMÉE AB, EDW H",
            "pnr": "201 10",
            "address": "Malmö 1, Engelbrektsgatan 11, Fack",
            "phone_number": "040-707 60",
            "bank_details": {
                "bankgiro": "260-2688",
                "postgiro": "14063-2"
            },
            "activity": "Grossistföretag inom järnmanufakturbranschen med försäljning av bl a skruv, byggnadsbeslag, lås, bult, handredskap, stängselnät, spik, ståltråd, tackjärn, rör. Tillverkar inredningar",
            "employees": 70,
            "annual_turnover": 25000000,
            "capital": 1400000,
            "key_personnel": [
                {
                    "name": "Per-Hjalmar Fagerholm",
                    "position": "Styrelseordförande"
                },
                {
                    "name": "Sven Broman",
                    "position": "Verkställande direktör"
                }
            ],
            "establishment_year": 1892
        },
        "15": {
            "company_name": "THOMÉE AB, GUSTAF",
            "pnr": "20011",
            "address": "Malmö 6, Drottningtorget 4, Box 6050",
            "phone_number": "040-711 25",
            "bank_details": {
                "bankgiro": "874-8303",
                "postgiro": "531140-2"
            },
            "activity": "Säljer industri-kemikalier, plastråvaror",
            "employees": 4,
            "annual_turnover": 8000000,
            "capital": 5000,
            "key_personnel": [
                {
                    "name": "Ing Nils Bengtsson",
                    "position": "Chef"
                }
            ],
            "establishment_year": 1882
        },
        "16": {
            "company_name": "TOMELILLA EXPRESSBYRÅ, AB",
            "pnr": "273 00",
            "address": "Tomelilla, Klintgatan 4",
            "phone_number": "0417-116 35",
            "bank_details": {
                "bankgiro": "351-7034",
                "postgiro": "294513-7"
            },
            "activity": "Åkeri",
            "ombudskontor": "Ystad, AB Godstrafik & Bilspedition, V Hamnområdet, Tel 0411-142 50",
            "employees": 60,
            "annual_turnover": 5500000,
            "capital": 150000,
            "key_personnel": [
                "Anna Andersson",
                "Elvin Andersson",
                "Georg Andersson"
            ],
            "establishment_year": 1912
        },
        "17": {
            "company_name": "TOMELILLA SPARBANK",
            "pnr": "273 00",
            "address": "Tomelilla, Box 117, Torget 4",
            "phone_number": "0417-125 10",
            "bank_details": {
                "bankgiro": "981-3585",
                "postgiro": "329143-2"
            },
            "activity": "Bankrörelse",
            "employees": 18,
            "annual_turnover": 105400000,
            "key_personnel": [
                "Rektor Ivan Olsson",
                "Kurt Jansson",
                "Roland Lönnmyr"
            ],
            "establishment_year": 1882
        },
        "18": {
            "company_name": "TOMELILLA TRÄVARU AB",
            "pnr": "273 00",
            "address": "Tomelilla, Industrigatan, Box 72",
            "phone_number": "0417-113 50, 115 50",
            "bank_details": {
                "bankgiro": "671-1097, 617-0922",
                "postgiro": "494660-4"
            },
            "activity": "Tillverkar och säljer trävaror, byggnadsmaterial",
            "employees": 50,
            "annual_turnover": 6000000,
            "owners": "Trävaruhandl Pehr-Arne Pehrsson",
            "establishment_year": 1956
        }
    }
}