{
    "original": "HAGA OPTIK AB\n\nPnr 79100\n\nFalun, Ingarvet. Tel 023-230 50.\nBankgiro 792-4970. Postgiro\n499 280-6\n\nVerksamhet: Glasögonbågar o\nsolglasögon i parti\nAntal anstäUda: 12\nChef: Dir Ake Henrikson\nEtableringsår: 1957.\n\nHAGA SNICKERIFABRIK,\nERNST OLSSON KB\n\nPnr 740 47\n\nHarbonäs. Tel 0292-310 34, 310 85.\nBankgiro 812-6021. Postgiro\n145224-2\n\nVerksamhet: Tillverkar köks- o\ng arderob snick erier\nAntal anstäUda: 40\nÅrsomsättning: 2700 000\nKommanditbolag: 100 000\nChef: Ernst Olsson\nEtableringsår: 1922.\n\nBLOEMER AB, ALEXANDER\n\nPnr 302 40\n\nHalmstad, Drevstigen 6. Tel\n035-361 55, 361 56. Postgiro 577400-5.\nTga Bloemerexport\nVerksamhet: Tillverkare av\nflis-huggar samt exportör av\ngaffeltruckar, sågverksmaskiner samt\ntransportinredningar\n\nVaranamn: Schwedenmaschinen\nAntal anställda: 3\nÅrsomsättning: 5 000 000\nChef: Dipl-ing Alexander Bloemer\nEtableringsår: 1961.\n\nSVETSNINGSVERKSTADEN\n\nPnr 280 20\n\nBjärnum, Mala. Tel 0451-170 13,\n17130. Bankgiro 265-3491.\nPostgiro 139103-6\n\nVerksamhet: Tillverkar cisterner.\nUtför plåt- o järnkonstruktioner\nChef: Walter H Romberg\nEtableringsår: 1937.\n\nJAGENBERG SVENSKA AB\n\nPnr 18211\n\nDanderyd 1, Mörbydalen 17. Box 31.\nTel 08-755 25 55. Bankgiro62-8710.\nPostgiro 81907. Telex 10217. Tga\nJagenbergwerk, Stockholm\nVerksamhet: Säljer\nbearbetningsmaskiner till pappers- o cellulosa^\nindustrin såsom rull- o\nskärmaskiner, bestryknings- o\nbefuktnings-anläggningar, filtar, viror etc, samt\netiketteringsmaskiner\nVarunamn: Jagenberg\nAntal anställda: 10\nAktiekapital: 100 000\nStyrelse: Dr jur F Fischier (ordf),\ndir P U Bodin, dir R Meyer\nVerkst dir: P U Bodin\nEtableringsår: 1961\nDotterbolag till Jagenberg-Werke\nAG, Düsseldorf, Västtyskland.\n\nJAKEFA, AB\n\nPnr 21122\n\nMalmö. Stortorget 17. Tel\n040-335 67. Bankgiro 26-3436.\nPostgiro 245657. Tga Jakefa\nVerksamhet: Säljer fett, oljor,\nfettsyror, fettalkoholer, sulfonater o\nhjälpmedel för textil- o\nläderindustrin\n\nAktiekapital: 50000\nVerkst dir: Egon Jansson\nEtableringsår: 1945.\n\nJAKOBSDALS KAMGARNS.\nSPINNERI, AB\n\nPnr 402 21\n\nGöteborg 5, Sofierov 5. Box 5046.\nTel 031-400050. Tga Jakobsdals\nVerksamhet: Tillverkar\nhandstick-ningsgarn, trikå- o strumpgarner\nAvdelningskontor: Malmö C, Da^\nvidhallsg 23. Box 17028, Malmö 17.\nTel 040-1247 58, 11 20 55\nStockholm C, Kammakareg 38. Box\n45031, Sthlm 45. Tel 08-1114 98,\n205140\n\nSundsvall 1, Köpmang 38 A. Box\n424. Tel 060-115900, 115910\nAntal anställda: 160\nÅrsomsättning: 18 000 000\nAktiekapital: 2 000 000\nVerkst dir: Agne Langfält\nEtableringsår: 1910.\n\nWICKMAN, AB AUG\n\nPnr 402 31\n\nGöteborg 7, Fjärde Långg 8 B.\nBox 7001. Tel 031-14 42 09,\n24 73 73. Bankgiro 50-8715.\nPostgiro 42226. Tga Awick\nVerksamhet: Fabrikation av\ngördlar o behå\nAntal anställda: 90\nÅrsomsättning: 5 000 000\nAktiekapital: 150 000\nVerkst dir: Olle Svensson\nEtableringsår: 1907.\n\nSKRUV &amp; MUTTER, AB\n\nPnr 102 45\n\nStockholm 5, Björnnäs v 10,\nAlbano. Box 5256. Tel 08-63 5100.\nBankgiro 12-5318. Postgiro 2064\nVerksamhet: Säljer rostfria o\nsyrafasta bultartiklar.\n\nSKRUVFABRIKS-AKTIE.\nBOLAGET\n\nPnr 152 00\n\nSträngnäs, Larslundav 1. Tel\n0152-103 64, 10012. Bankgiro 62-1680.\nPostgiro 9475\n\nVerksamhet: Tillverkar svarvade\ndetaljer av järn o mässing\nAntal anställda: 18\nÅrsomsättning: 1200 000\nAktiekapital: 168 000\nStyrelse: Verkmäst Per-Henry\nPersson (ordf), Olof Olsson, fru Annar\nLisa Ander\n\nVerkst dir: Ing Olof Olsson\nEtableringsån 1920.\n\nKORROSIONSSKYDD, AB\n\nPnr 102 45\n\nStockholm 5, Brantingsg 42. Box\n5207. Tel 08-6234 25, 627952.\nBankgiro 168-5106. Postgiro\n403001-1\n\nVerksamhet: Korrosionsskyddar,\noljetankar, hydroforer mm\nAktiekapital: 15 000\nVerkst dir: Björn Möller.\n\nKORSNÄS.MARMA AB\n\nPnr 80111\n\nGävle 1, Box 592. Tel 026-19 20 00.\nPostgiro 13001. Tga Korsnäs.\nTelex 81030, 81031\nVerksamhet: Tillverkar sågade\nträvaror, hel-, halv- o oblekt\nsulfatmassa, slipmassa, hel-, halv- o\noblekt kraftpapper\nSågverk (Korsnäsverken o\nMarma-verken), cellulosafabriker\n(Korsnäsverken, Marmaverken),\nträsliperi (Lottefors), pappersbruk o\nklor-alkalifabrik (Korsnäsverken)\nAntal anställda: 3900\nÅrsomsättning: 480 000 000\nAktiekapital: 190 625 000\nStyrelse: Adv Hugo Stenbeck (ordf),\ndir Ulf Barkman, dir Gerard\nLundeberg, överint Knut von Horn,\ngreve Carl-Gustaf Klingspor, dir\nJacob Engwall, adv Hugo Stenbeck\njr, doc Nils Landqvist\nVerkst dir: Nils Landqvist\nV verkst dir:r: Ivan Martinson, Sven\nSpangenberg, Hans Lundberg\nEtableringsår: 1855.\n\nBERLIN &amp; CO AB, G\n\nPnr 75104\n\nUppsala 1, Box 202. Bolandsg 9.\nTel 018-12 6900, 126901.\nBankgiro 230-3816. Postgiro 668995-4.\nTga Berco. Telex 7463 BERCO S\nVerksamhet: Agentur- o\ngrossiströrelse inom industrimotorbranschen\nAntal anställda: 8\n\nÅrsomsättning: 900 000\nAktiekapital: 100 000\nVerkst dir: Göran Berlin\nEtableringsår: 1965.\n\nJUNGAFüRSÄLJNINGEN AB\n\nPnr 433 00\n\nPartilie, Smedbodalsv 15. Box 154.\nTel 031-44 54 11, 44 54 12.\nBankgiro 84-8096. Postgiro 522374-8.\nTga Pon\n\nVerksamhet: Grossist- o\ndetaljistförsäljning av Junga tvättmaskiner,\nSkandilux frysboxar o frysskåp,\nHelo bastuaggregat\nAktiekapital: 10 000\nStyrelse: Dir P-O Nordfeldt (ordf),\nrevisor Olle Lundén, fru Maja\nNordfeldt\n\nVerkst dir: P-O Nordfeldt\nEtableringsår 1954.\n\nFAGERSTA BRUKS AB\n\nPnr 773 01\n\nFagersta 1, Fack. Tel 0223-180 00.\n\nPostgiro 10035. Telex 7525. Tga\nF ag sta\n\nVerksamhet: Tillverkar stål,\nstålmanufaktur, hårdmetallprodukter\no bedriver dessutom gruv-,\nskogs-o lantbruk\n\nStålverk: Fagersta.\nFagerstaverk-en. Tel 0223-18000\nForsbacka. Forsbackaverken. Tel\n026-35180\n\nHorndal. Horndalsverken. Tel\n0226-404 00\n\nLångshyttan. Klosterverken. Tel\n0225-603 80\n\nOsterbybruk. Osterbyverken.\nTel 0295-207 00\n\nHårdmetall fabrik: Fagersta. SECO.\nTel 0223-18000\nVerktygsfabrik: Arboga.\nSECO-verken. Tel 0589-129 00\nJärnmalmsgruva: Garpenberg.\nSmäl-tarmossgruvan. Tel 0223-180 00\nRiddarhyttan, Bäckegruvan. Tel\n\n0222-133\t52\n\nFörsäljningskontor: Eskilstuna,\nBruksg 8. Tel 016-13 7055. Telex\n40963\n\nFagersta, Bergslagskontoret. Tel\n\n0223-160\t20. Telex 7525\nGöteborg. Importg 2-4, pa Hisings\nBacka 4. Tel 031-520210. Telex\n2282. Kontor även i Anderstorp.\nFagersta Bruks AB, Storg 19. Tel\n0371-167 10. 16711\nLinköping, Oskarsg 15. Tel\n013-13 04 00. Telex 64948\n\nMalmö C, Lodg 4. Tel 040-93 42 20.\nTelex 3135\n\nStockholm. Konsumentv 12, pa\nÄlvsjö. Fack, Bandhagen 4. Tel\n08-47 28 00. Telex 19357\nRepresentanter: Härnösand. AB Fr\nRamström, Skeppsbron 17-19. Tel\n0611-156 30. Telex 71020\nKarlstad. Herman Geijer &amp; Co AB,\nKöpmannag 2. Box 76. Tel\n054-1153 00. Telex 66029\nLuleå. AB Fr Ramström,\nSko-makarg 36. Box 28. Tel 0920-149 35,\n167 10\n\nÖrebro. Herman Geijer &amp; Co AB,\nTackjärnsg 8. Box 496. Tel\n019-18 39 40, 18 39 50\nAntal anställda: 6 700\nÅrsomsättning: 550 000 000\nAktiekapital: 100 000 000\nStyrelse: Herr Lars Wlrström (ordf),\ndlr Nils Berggren, bruksdisp Lars\nEdlund, bruksdisp Nils Elfström,\ndir Sven Häggqvist, dir Christer\nHöglund, frih Carl Langenskiöld\nVerkst dir: Lars Edlund\nV verkst din Erik Nygren\nEkonomidir: Nils Svensson\nFörsälln-dir: Carl-Erik Foogde\n(Stål). Bengt Almen (Seco)\nInköpschef: Intendent Erik\nSundelin\n\nEtableringsår: 1873\nDotterbolag: Rostfria Tak AB,\nFagersta. E G Larssons\nHårdmetall AB, Norrköping.\nStjärnverk-tyg AB, Norberg, AB Dannemora\nGruvor, Dannemora.\n\nFAGERSTA PLÅTSLAGERI AB\n\nPnr 773 00\n\nFagersta. Lövparksv 14. Tel\n0223-105 37. Bankgiro 810-4010.\nPostgiro 416109-7\n\nVerksamhet: Tillverkar o monterar\nhängrännor o stuprör. Utför\nventilationer, taktäckning o -målning\nsamt byte av taktegel\n\nAntal anställda: 12\nÅrsomsättning: 600 000\nAktiekapital: 40 000\nVerkst dir. Fabr John Markström\nDriftschef: Fabr Per-Gunnar\nFäll-gren\n\nEtableringsår 1945.\n\nFAGERSTROM &amp; CO, AB\nGUNNAR\n\nPnr 523 00\n\nUlricehamn, Box 44. Ekhultsg 4. Tel\n0321-107 07, 10710. Bankgiro\n53-2800. Postgiro 174710. Tga\nFager-strömylle\n\nVerksamhet: Stickade varor för\nherr, dam, flick o goss\nAntal anställda: 7\nÅrsomsättning: 2 000 000\nAktiekapital: 20 000\nVerkst dir: Sune Mattsson\nEtableringsår: 1941.",
    "structured": {
        "1": {
            "company_name": "HAGA OPTIK AB",
            "address": "Falun, Ingarvet",
            "phone_number": "023-230 50",
            "bank_details": {
                "bankgiro": "792-4970",
                "postgiro": "499 280-6"
            },
            "activity": "Glasögonbågar o solglasögon i parti",
            "employees": 12,
            "key_personnel": [
                {
                    "name": "Dir Ake Henrikson",
                    "position": "Chef"
                }
            ],
            "establishment_year": 1957
        },
        "2": {
            "company_name": "HAGA SNICKERIFABRIK, ERNST OLSSON KB",
            "address": "Harbonäs",
            "phone_number": "0292-310 34, 310 85",
            "bank_details": {
                "bankgiro": "812-6021",
                "postgiro": "145224-2"
            },
            "activity": "Tillverkar köks- o g arderob snick erier",
            "employees": 40,
            "annual_turnover": 2700000,
            "capital": 100000,
            "key_personnel": [
                {
                    "name": "Ernst Olsson",
                    "position": "Chef"
                }
            ],
            "establishment_year": 1922
        },
        "3": {
            "company_name": "BLOEMER AB, ALEXANDER",
            "address": "Halmstad, Drevstigen 6",
            "phone_number": "035-361 55, 361 56",
            "postgiro": "577400-5",
            "activity": "Tillverkare av flis-huggar samt exportör av gaffeltruckar, sågverksmaskiner samt transportinredningar",
            "employees": 3,
            "annual_turnover": 5000000,
            "key_personnel": [
                {
                    "name": "Dipl-ing Alexander Bloemer",
                    "position": "Chef"
                }
            ],
            "establishment_year": 1961
        },
        "4": {
            "company_name": "SVETSNINGSVERKSTADEN",
            "address": "Bjärnum, Mala",
            "phone_number": "0451-170 13, 17130",
            "bank_details": {
                "bankgiro": "265-3491",
                "postgiro": "139103-6"
            },
            "activity": "Tillverkar cisterner. Utför plåt- o järnkonstruktioner",
            "key_personnel": [
                {
                    "name": "Walter H Romberg",
                    "position": "Chef"
                }
            ],
            "establishment_year": 1937
        },
        "5": {
            "company_name": "JAGENBERG SVENSKA AB",
            "address": "Danderyd 1, Mörbydalen 17, Box 31",
            "phone_number": "08-755 25 55",
            "bank_details": {
                "bankgiro": "62-8710",
                "postgiro": "81907"
            },
            "telex": "10217",
            "activity": "Säljer bearbetningsmaskiner till pappers- o cellulosa^ industrin",
            "employees": 10,
            "capital": 100000,
            "key_personnel": [
                {
                    "name": "Dr jur F Fischier",
                    "position": "Styrelseordförande"
                },
                {
                    "name": "P U Bodin",
                    "position": "Styrelseledamot"
                },
                {
                    "name": "R Meyer",
                    "position": "Styrelseledamot"
                },
                {
                    "name": "P U Bodin",
                    "position": "Verkställande direktör"
                }
            ],
            "establishment_year": 1961
        },
        "6": {
            "company_name": "JAKEFA, AB",
            "address": "Malmö, Stortorget 17",
            "phone_number": "040-335 67",
            "bank_details": {
                "bankgiro": "26-3436",
                "postgiro": "245657"
            },
            "activity": "Säljer fett, oljor, fettsyror, fettalkoholer, sulfonater o hjälpmedel för textil- o läderindustrin",
            "capital": 50000,
            "key_personnel": [
                {
                    "name": "Egon Jansson",
                    "position": "Verkställande direktör"
                }
            ],
            "establishment_year": 1945
        },
        "7": {
            "company_name": "JAKOBSDALS KAMGARNS. SPINNERI, AB",
            "address": "Göteborg 5, Sofierov 5, Box 5046",
            "phone_number": "031-400050",
            "activity": "Tillverkar handstick-ningsgarn, trikå- o strumpgarner",
            "employees": 160,
            "annual_turnover": "18 000 000",
            "capital": 2000000,
            "key_personnel": [
                {
                    "name": "Agne Langfält",
                    "position": "Verkställande direktör"
                }
            ],
            "establishment_year": 1910
        },
        "8": {
            "company_name": "WICKMAN, AB AUG",
            "address": "Göteborg 7, Fjärde Långg 8 B, Box 7001",
            "phone_number": "031-14 42 09, 24 73 73",
            "bank_details": {
                "bankgiro": "50-8715",
                "postgiro": "42226"
            },
            "activity": "Fabrikation av gördlar o behå",
            "employees": 90,
            "annual_turnover": "5 000 000",
            "capital": 150000,
            "key_personnel": [
                {
                    "name": "Olle Svensson",
                    "position": "Verkställande direktör"
                }
            ],
            "establishment_year": 1907
        },
        "9": {
            "company_name": "SKRUV & MUTTER, AB",
            "address": "Stockholm 5, Björnnäs v 10, Albano, Box 5256",
            "phone_number": "08-63 5100",
            "bank_details": {
                "bankgiro": "12-5318",
                "postgiro": "2064"
            },
            "activity": "Säljer rostfria o syrafasta bultartiklar"
        },
        "10": {
            "company_name": "SKRUVFABRIKS-AKTIE. BOLAGET",
            "address": "Strängnäs, Larslundav 1",
            "phone_number": "0152-103 64, 10012",
            "bank_details": {
                "bankgiro": "62-1680",
                "postgiro": "9475"
            },
            "activity": "Tillverkar svarvade detaljer av järn o mässing",
            "employees": 18,
            "annual_turnover": 1200000,
            "capital": 168000,
            "key_personnel": [
                {
                    "name": "Verkmäst Per-Henry Persson",
                    "position": "Styrelseordförande"
                },
                {
                    "name": "Olof Olsson",
                    "position": "Styrelseledamot"
                }
            ],
            "establishment_year": 1920
        },
        "11": {
            "company_name": "KORROSIONSSKYDD, AB",
            "address": "Stockholm 5, Brantingsg 42, Box 5207",
            "phone_number": "08-6234 25, 627952",
            "bank_details": {
                "bankgiro": "168-5106",
                "postgiro": "403001-1"
            },
            "activity": "Korrosionsskyddar, oljetankar, hydroforer mm",
            "capital": 15000,
            "key_personnel": [
                {
                    "name": "Björn Möller",
                    "position": "Verkställande direktör"
                }
            ]
        },
        "12": {
            "company_name": "KORSNÄS.MARMA AB",
            "address": "Gävle 1, Box 592",
            "phone_number": "026-19 20 00",
            "postgiro": "13001",
            "activity": "Tillverkar sågade trävaror, hel-, halv- o oblekt sulfatmassa, slipmassa, hel-, halv- o oblekt kraftpapper",
            "employees": 3900,
            "annual_turnover": 480000000,
            "capital": 190625000,
            "key_personnel": [
                {
                    "name": "Adv Hugo Stenbeck",
                    "position": "Styrelseordförande"
                },
                {
                    "name": "Nils Landqvist",
                    "position": "Verkställande direktör"
                }
            ],
            "establishment_year": 1855
        },
        "13": {
            "company_name": "BERLIN & CO AB, G",
            "address": "Uppsala 1, Box 202, Bolandsg 9",
            "phone_number": "018-12 6900, 126901",
            "bank_details": {
                "bankgiro": "230-3816",
                "postgiro": "668995-4"
            },
            "activity": "Agentur- o grossiströrelse inom industrimotorbranschen",
            "employees": 8,
            "annual_turnover": 900000,
            "capital": 100000
        },
        "14": {
            "company_name": "JUNGAFüRSÄLJNINGEN AB",
            "address": "Partille, Smedbodalsv 15, Box 154",
            "phone_number": "031-44 54 11, 44 54 12",
            "bank_details": {
                "bankgiro": "84-8096",
                "postgiro": "522374-8"
            },
            "activity": "Grossist- o detaljistförsäljning av Junga tvättmaskiner, Skandilux frysboxar o frysskåp, Helo bastuaggregat",
            "capital": 10000,
            "key_personnel": [
                {
                    "name": "Dir P-O Nordfeldt",
                    "position": "Styrelseordförande"
                }
            ],
            "establishment_year": 1954
        },
        "15": {
            "company_name": "FAGERSTA BRUKS AB",
            "address": "Fagersta 1, Fack",
            "phone_number": "0223-180 00",
            "postgiro": "10035",
            "telex": "7525",
            "activity": "Tillverkar stål, stålmanufaktur, hårdmetallprodukter o bedriver dessutom gruv-, skogs-o lantbruk",
            "employees": 6700,
            "annual_turnover": 550000000,
            "capital": 100000000,
            "key_personnel": [
                {
                    "name": "Lars Wlrström",
                    "position": "Styrelseordförande"
                },
                {
                    "name": "Lars Edlund",
                    "position": "Verkställande direktör"
                }
            ],
            "establishment_year": 1873
        },
        "16": {
            "company_name": "FAGERSTA PLÅTSLAGERI AB",
            "address": "Fagersta, Lövparksv 14",
            "phone_number": "0223-105 37",
            "bank_details": {
                "bankgiro": "810-4010",
                "postgiro": "416109-7"
            },
            "activity": "Tillverkar o monterar hängrännor o stuprör. Utför ventilationer, taktäckning o -målning samt byte av taktegel",
            "employees": 12,
            "annual_turnover": 600000,
            "capital": 40000,
            "key_personnel": [
                {
                    "name": "Fabr John Markström",
                    "position": "Verkställande direktör"
                }
            ],
            "establishment_year": 1945
        },
        "17": {
            "company_name": "FAGERSTROM & CO, AB GUNNAR",
            "address": "Ulricehamn, Box 44, Ekhultsg 4",
            "phone_number": "0321-107 07, 10710",
            "bank_details": {
                "bankgiro": "53-2800",
                "postgiro": "174710"
            },
            "activity": "Stickade varor för herr, dam, flick o goss",
            "employees": 7,
            "annual_turnover": 2000000,
            "capital": 20000,
            "key_personnel": [
                {
                    "name": "Sune Mattsson",
                    "position": "Verkställande direktör"
                }
            ],
            "establishment_year": 1941
        }
    }
}