{
    "original": "KNUTSSON AB, K G\n\nPnr 16130\n\nBromma, Ulvsundav 146. Tel\n08-25 26 60. Telex 1504. Tga Knuting\nVerksamhet: Säljer elektr o\ninstrumentutrustning, kopplingar o\nkopplingsskivor, växellådor,\nstyrinrättningar, axlar o gjutgods för\nmotorfordon. Teknisk konsultation.\nGeneralagent för tyska o amerikanska\nfirmor\n\nAvdelningskontor: Göteborg H,\nRusk väders g 10. Tel 031-530460.\nTelex 20955\n\nMalmö O, Murmansg 122. Tel\n040-93 74 30\n\nSundsvall, N Järnvägsg 8-10. Tel\n060-121945\n\nVarunamn: Alfing, Altenburger,\nBartel, Bing, Coroplast, Elring,\nBeru, Boge, MWH, Fri wi, Güldner,\nHella, KS. Magura, PLEUCO, VDO,\nZF, ZP\n\nAntal anställda: 140\nÅrsomsättning: 30 000 000\nAktiekapital: 2 000 000\nVerkst dir: K G Knuts son\nEtableringsår: 1946\nOmbildat till aktiebolag 1954.\n\nKNUTZ VERKSTADS AB\n\nPnr 793 00\n\nLeksand, Box 3010. Tel\n0247-122 85. Bankgiro 642-3776. Post&gt;\ngiro 711700-5\n\nVeiksamhet: Finmekanisk verkstad\nmed speciell inriktning på\ntillverkning av små precisionskugghjul\nAntal anställda: 12\nÅrsomsättning: 600 000\nAktiekapital: 25 000\nStyrelse: Ing Henning Knutz (ordf),\nfru Maj-Britt Knutz\nVerkst dir: Ing Henning Knutz\nEtableringsår: 1968.\n\nSCHOLANDERS IMPORT AB\n\nPnr 20110\n\nMalmö 1. Fack. Själbodg 10. Tel\n040-702 40. Bankgiro 870-1898.\n\nPostgiro 75110-7. Tga Scholanders.\nTelex 32705\n\nVerksamhet: Importerar o säljer\n\nfossilt bränsle samt produkter för\n\nbyggnadsindustrin\n\nVerkst dir: Ove Löfstedt (Ystad)\n\nPlatschef i Malmö: Ruben Ibstedt.\n\nSCHOLANDER JÄRN AB\n\nPnr 20110\n\nMalmö 1, Pack. Själbodg 10. Tel\n040-70240. Bankgiro 870-1898.\nPostgiro 14088-9. Tga Scholanders.\nTelex 32705\n\nVeiksamhet: Säljer järn, stål,\nbalkar, plåt, järnmanufaktur, WS- o\nsvetsmaterial, verkstadsmaskiner\nAvdelningskontor: Ystad,\nBorn-holmsg. Tel 0411-13650\nAktiekapital: 1750 000\nReservfond: 350 000\nVeikst din Ove Löfstedt (Ystad)\nPlatschef i Malmö: Ruben Ibstedt\nEtableringsår: 1903\nÄger. A Scholander &amp; Co AB,\nMalmö, Scholanders Import AB, Malmö.\n\nSCHOLANDER &amp; CO AB, A\n\nPnr 20110\n\nMalmö 1, Fack. Själbodg 10. Tel\n040-702 40. Bankgiro 870-1898.\nPostgiro 75110-7. Tga Scholanders.\nTelex 32705\n\nVerksamhet: Kol, koks, ved o\neldningsoljor\n\nAvdelningskontor: Lund. Tel\n046-112000\n\nTrelleborg. Tel 0410-100 07\nYstad. Tel 0411-136 50\nVerkst dir: Ove Löfstedt (Ystad)\nPlatschef i Malmö: Ruben Ibstedt.\n\nSCHREUDER &amp; OLSSON, AB\n\nPnr 115 31\n\nStockholm. Strandbergsg 51. Tel\n08-53 1249, 50 77 82.\nBankgiro733-8312. Postgiro 1393-8\nVerksamhet: Tillverkar o säljer\ngjutna konstindustriella tennsaker\nsamt industriella tillverkningar av\nbly o brickor\nÅrsomsättning: 500 000\nAktiekapital: 20 000\nVeikst dir: Bengt Schreuder\nEtableringsår: 1896.\n\nÅKERMAN &amp; DAHL, AB\n\nPnr 602 24\n\nNorrköping, Gamla Rådstugug 31.\nTel 011-13 74 00. Postgiro 71833.\nTga Wilhelm\n\nVerksamhet: Agentur,\ngrossiströrelse samt fastighetsförvaltning\nAntal anställda: 8\nAktiekapital: 125 000\nVerkst din Kapten Harald Bergman\nEtableringsån 1897\nOmbildat till aktiebolag 1918.\n\nÅKERMAN &amp; DAHLS\nTEXTIL, AB\n\nPnr 602 24\n\nNorrköping, Gamla Rådstugug 31.\nTel 011-13 74 00. Postgiro\n167285-6. Tga Wilhelm\nVerksamhet: Säljer ull, syntetiska\nfibrer o garner\nAktiekapital: 40 000\nEtableringsån 1953.\n\nÅKERMANS INGENJORSBYRÅ\nAB\n\nPnr 252 24\n\nHelsingborg, Trädgårdsg 9. Tel\n042-12 10 60, 134242. Bankgiro\n653-1891. Postgiro 646792-2\n\nVerksamhet: Konsulterande i\nbyggbranschen\nAntal anställda: 7\nÅrsomsättning: 400 000\nAktiekapital: 5 000\nVerkst dir: Ing Allan Åkerman\nEtableringsår: 1962.\n\nÅKERMAN &amp; LUNDS NYA\nORGELFABRIKS AB\n\nPnr 741 00\n\nKnivsta, Sjöv 5. Box 31. Tel\n018-38 0319, 38 0818. Bankgiro\n233-4423. Postgiro 28102-2\nVerksamhet: Tillverkar piporglar\nför kyrkor, skolor o andra lokaler\nAntal anställda: 17\nÅrsomsättning: 650 000\n.Aktiekapital: 60 500\nStyrelse: Köpman Maurits Lanners\n(ordf), dir Signe Johansson\nVerkst dir: Fru Signe Johansson\nEtableringsår: 1860.\n\nLECORA AB\n\nPnr 703 40\n\nÖrebro, Hertig Karls Allé 5. Tel\n019-1197 70. Bankgiro 63-0526.\nPostgiro 647707. Telex 73425.\nTga Lecora\n\nVeiksamhet: Tillverkar o säljer\nlivsmedel för storkök. Djupfrysta\nlivsmedel, konserver o skalfri\npotatis\n\nAvdelningskontor. 430 70\nSäveda-len, Göteborgsv 1. Tel 031-26 37 45\n592 00 Vadstena, Kvarnbacksv 6.\nTel 0143-113 48\n\nFabrik: 592 00 Vadstena,\nKvarnbacksv 6. Tel 0143-122 50\nVarunamn: Daloon, Lecora\nAntal anställda: 40\nÅrsomsättning: 13 500 000\nAktiekapital: 100 000\nVerkst dir: Lars Pettersson\nFörsäljn-chef: Hans Stenmark\nEtableringsår: 1959\nOmbildat till aktiebolag o\nnuvarande namn 1964.\n\nLEDERHAUSEN AB, PAUL\n\nPnr 11242\n\nStockholm, Drottningholmsv 80.\nTel 08-13 13 60. Bankgiro 731-3109.\nPostgiro 659020-2\nVerksamhet: Sälj» grillar o\nmikrovågsugnar\nAntal anställda: 20\nÅrsomsättning: 7 500 000\nAktiekapital: 50 000\nVerkst din Paul Lederhausen\nEtableringsår: 1962.\n\nASKERSUNDSVERKEN AB\n\nPnr 696 00\n\nAskersund, Trädgårdsg 1-3. Tel\n0583-111 60. Postgiro 33715-4. Tga\nAvaverken\n\nVerksamhet: Mek verkstad i\nAskersund. Tillverkar belysningsstolpar,\nspännstolpar o rörmaster.\nTransport-o lagerlådor av stålplåt. Koniska\ncontainer. Utför mekaniska\nlego-arbeten. Framställer\nstålverksko-killer o grovt handformat gods med\nstyckevikter upp till 15 ton vid\nHögforsbruks Nya Gjuteri AB,\nHögforsbruk\nVarunamn: AVA\nAntal anställda: 40\nAktiekapital: 300 000\nStyrelse: Adv Hans-Erik Mattsson,\ndir Gustav Åström, disp John Axel\nFranzén\n\nVerkst dir: John Axel Franzén\nKamrer Bertil Gustafsson\nEtableringsår: 1932.\n\nASKIM GUMMI VAREFABRIK\nSVENSKA AB\n\nPnr 43122\n\nMölndal 1, Kråketorpsg 18. Box\n179. Tel 031-27 53 40. Bankgiro\n847-8604. Postgiro 529510-0.\nTga Askimgummi. Telex 20607\nVerksamhet: Tillverkar Viking\nbildäck, cykel-, moped-, skoter- o\nmc-däck, industri- o lantbruksdäck\nsamt slangar, luftgummihjul,\nIndustrigummi o plast,\ngummibeläggningar, gummiskodon, konfektion\nAvdelningskontor: 116 24 Stockholm,\nAsög 142. Tel 08-410011, 4100 77\n212 20 Malmö, Kirsebergs Torg 5.\nTel 040-18 57 00, 18 57 01\n652 23 Karlstad, Herrhagsg 4. Tel\n054-15 98 50\n\n852 40 Sundsvall, SLdsjöv 45. Tel\n060-117580\n\nDistriktrepresentant: 62100 Visby,\nFagningsg 16. Tel 0498-129 67\nVarunamn: Viking\nAntal anställda: 40\nÅrsomsättning: 26 000 000\nAktiekapital: 200 000\nStyrelse: Adv Kurt Bark (ordf),\ndir Lennart Jonsson, dir Christian\nLangaard\n\nVerkst dir: Lennart Jonsson\nEtableringsår: 1961\nDotterbolag till Askimkoncernen i\nNorge bestående av A/S Askim\nGummivarefabrik, A/S Mjöndalen\nGummivarefabrik, A/S Vestlandske\nGummivarefabrik, A/S Sanitized,\nGummifabriken National A/S.\n\nASKLUNDS\nTRÄ-VARU AB, OLOF\n\nPnr 31200\n\nLaholm, Lantmannag. Box 99. Tel\n043 0-122 30. Bankgiro 65-9101.\nPostgiro 293338\n\nVerksamhet: Försäljning av alla\nslags trävaror o byggnadsmaterial\nAntal anställda: 12\nÅrsomsättning: 3500 000\nAktiekapital: 55 000\nVerkst dir: Kurt Asklund\nEtableringsår: 1908.\n\nASMUNDTORPS\nBORST-FABRIKS AB\n\nPnr 260 10\n\nAsmundtorp, Box 28. Trastv 5. Tel\n0418-32016. Postgiro 23231-4\nVerksamhet: Tillverkar borstar o\npenslar. Specialitet: maskinborstar\nAktiekapital: 10 500\nStyrelse: Disp Ake Brorsson (ordf),\nfru Olga Bengtsson, disp Börje\nBrorson\n\nVerkst dir: Olga Bengtsson\nEtableringsår: 1902.\n\nALB\n\nA KVA TERRA, AB\n\nPnr 701 03\n\nÖrebro 1. Nyg 9. Box 148. Tel\n019-14 0170. Bankgiro 614-3150.\nPostgiro 117170-1\n\nVerksamhet; Projektering av\ngrundvattentäkter o för\ngrundvattensänkningar samt utbyggnad av\nbrunnsanläggningar för städer, kommuner o\nprivata förbrukare\nAntal anställda: 4\nÅrsomsättning: 400 000\nAktiekapital: 25000\nVerkst dir: Tage Ericsson\nEtableringsår: 1960.\n\nSVALLING, AB ERIK\n\nPnr 63103\n\nEskilstuna 1, Bruksg 17. Box 196.\nTel 016-14 70 80. Bankgiro\n601-5424. Postgiro 74550-5. Tga\nSaxling\n\nVerksamhet: Tillverkar\nhandplåt-saxar, trädgårdsredskap samt utför\nhejarsmide\nAntal anställda: 4\nÅrsomsättning: 145 000\nAktiekapital: 50 000\nVerkst dir: Holger Brunell\nEtableringsår: 1905\nÄgare: Nickelfabriks AB Gottfrid\nCarlsson, Eskilstuna.\n\nSWAHN GJUTERI &amp; MEK\nVERKSTAD AB, C H\n\nPnr 78100\n\nBorlänge, Hagav 4. Tel 0243-159 20.\nBankgiro 79-4616. Postgiro 11186\nVerksamhet: Utför brunnsborrning,\nvatten- o avloppsanläggningar\nAktiekapital: 150000\nVerkst dir: Ing Olof Swahn\nEtableringsår: 1903.\n\nSPRINTER SYSTEM AB\n\nPnr 30103\n\nHalmstad 1, Laholmsv. Box 152.\nTel 035-11 82 80. Tga Sprinter.\nTelex 38047\n\nVerksamhet: Tillverkar o säljer\n\nförpackningsmaskiner\n\nVerkst dir: Yngve Hammenberg\n\nEtableringsår 1962\n\nSe vidare under Sprinter Pack AB.\n\nSPRÅKFORLAGET/\nSVENSKA BOKFURLAGET, AB\n\nse Läromedelsförlagen P ,A\nNorstedt &amp; Söner - Albert Bonnier, AB.\n\nSPÅNGA LANTBRUKS- &amp;\nINDUSTRIMASKINER, AB\n\nPnr 163 21\n\nSpånga 1, Skydraget 42. Box 97. Tel\n08-36 62 00, 36 6203. Bankgiro\n745-1198. Postgiro 652608-1\nVerksamhet: Säljer\nlantbrukstraktorer, grävmaskiner\nAntal anstäUda: 20\nÅrsomsättning: 4000 000\nAktiekapital: 25 000\nVerkst dir: Lennart Magnusson\nEtableringsår 1967.\n\nBERTE QVARN AKTIEBOLAG\n\nPnr 310 50\n\nSlöinge, Berte. Box 69. Tel\n0346-404 50. Bankgiro 433-9024.\nPostgiro 5555-8. Tga Berte\nVerksamhet: Kvarnrörelse o\nlantbruk. Tillverkar mjöl o fodervaror\nRepresentanter: Göteborg C.\nGunnar Rydell &amp; Co, Frilagerhuset.\nTel 031-13 12 95\n\nUddevalla. Bertil Haglind, S\nDrottningg 25. Tel 0522-113 15\nBorås. Hjalmar Lindeberg,\nGässlösav 28. Tel 033-1217 80\nVarunamn: Berte\nAntal anställda: 26\nÅrsomsättning: 12000 000\nAktiekapital: 660 000\nVerkst dir: Olof Stenström\nEtableringsår: 1569\nOmbildat till aktiebolag 1895.\n\nBERTERS NORDISKA AB\n\nPnr 200 61\n\nMalmö 30, Box 30003. Riddareg 2 B.\nTel 040-15 46 75, 1610 00. Bankgiro\n870-6269. Postgiro 431215-3. Tga\nBerters\n\nVerksamhet: Import o försäljning\nav manuella o automatiska\nmaskiner för bandning o buntning med\nkallvalsat emballagestålband,\nribboband o bindgarn. Inbrotts- o\nbrandi arm\nVarunamn: Berters\nAntal anställda: 5\nAktiekapital: 25 000\nVerkst dir: Bertil H Evers\nEtableringsår: 1943\nOmbildat till aktiebolag 1951.\n\nBERYLL AB\n\nPnr 51046\n\nFrufällan, Box 46. Tel 033-474 00.\nBankgiro 839-4389. Postgiro\n442455-2\n\nVerksamhet: Tillverkar modevaror\ni trikå, klänningar i tetoron\nAntal anställda: 30\nÅrsomsättning: 2 000 000\nAktiekapital: 150 000\nVerkst dir: Olof Carlsson\nEtableringsår: 1966.\n\nBESAB,\n\nBETONGSPRUTNINGS AB\n\nPnr 415 10\n\nGöteborg, Kortedala Torg 7 B. Tel\n031-46 02 50. Postgiro 520108.\nTga Bergbetong\nVerksamhet: Entreprenad o\nförsäljningsverksamhet inom\nbyggnadsbranschen. Specialitet:\nbetongsprutning, injektering,\nmarkstabilisering, injekteringsbetong,\ndragförankringar, kärnborming.\nTillverkar o säljer betongsprutor o\nkolloid-blandare\n\nAntal anställda: 74\nÅrsomsättning: 5 000 000\nAktiekapital: 110 000\nVerkst dir: Ing Bertil Sandell\nEtableringsår: 1956.\n\nSKOGSBORGS MEKANISKA\nVERKSTAD AB\n\nPnr 292 00\n\nKarlshamn, Box 104. Tel\n0454-107 17. 119 71. Bankgiro 343-3158.\nPostgiro 9808-7\n\nVerksamhet: Tillverkar\nspecialmaskiner efter ritningar\nAntal anställda: 15\nÅrsomsättning: 1000 000\nAktiekapital: 75 000\nVerkst dir: Ing Anders Bjerede\nEtableringsår: 1938.",
    "structured": {
        "1": {
            "company_name": "KNUTSSON AB",
            "pnr": "16130",
            "address": "Bromma, Ulvsundav 146",
            "phone_number": "08-25 26 60",
            "activity": "Säljer elektr o instrumentutrustning, kopplingar o kopplingsskivor, växellådor, styrinrättningar, axlar o gjutgods för motorfordon. Teknisk konsultation. Generalagent för tyska o amerikanska firmor",
            "employees": 140,
            "annual_turnover": 30000000,
            "capital": 2000000,
            "key_personnel": [
                {
                    "name": "K G Knuts son",
                    "position": "Verkst dir"
                }
            ],
            "establishment_year": 1946
        },
        "2": {
            "company_name": "KNUTZ VERKSTADS AB",
            "pnr": "793 00",
            "address": "Leksand, Box 3010",
            "phone_number": "0247-122 85",
            "bank_details": {
                "bankgiro": "642-3776",
                "postgiro": "711700-5"
            },
            "activity": "Finmekanisk verkstad med speciell inriktning på tillverkning av små precisionskugghjul",
            "employees": 12,
            "annual_turnover": 600000,
            "capital": 25000,
            "key_personnel": [
                {
                    "name": "Ing Henning Knutz",
                    "position": "Verkst dir"
                }
            ],
            "establishment_year": 1968
        },
        "3": {
            "company_name": "SCHOLANDERS IMPORT AB",
            "pnr": "20110",
            "address": "Malmö 1, Fack. Själbodg 10",
            "phone_number": "040-702 40",
            "bank_details": {
                "bankgiro": "870-1898",
                "postgiro": "75110-7"
            },
            "activity": "Importerar o säljer fossilt bränsle samt produkter för byggnadsindustrin",
            "key_personnel": [
                {
                    "name": "Ove Löfstedt",
                    "position": "Verkst dir"
                }
            ]
        },
        "4": {
            "company_name": "SCHREUDER & OLSSON, AB",
            "pnr": "115 31",
            "address": "Stockholm, Strandbergsg 51",
            "phone_number": "08-53 1249, 50 77 82",
            "bank_details": {
                "bankgiro": "733-8312",
                "postgiro": "1393-8"
            },
            "activity": "Tillverkar o säljer gjutna konstindustriella tennsaker samt industriella tillverkningar av bly o brickor",
            "annual_turnover": 500000,
            "capital": 20000,
            "key_personnel": [
                {
                    "name": "Bengt Schreuder",
                    "position": "Verkst dir"
                }
            ],
            "establishment_year": 1896
        },
        "5": {
            "company_name": "ÅKERMAN & DAHL, AB",
            "pnr": "602 24",
            "address": "Norrköping, Gamla Rådstugug 31",
            "phone_number": "011-13 74 00",
            "postgiro": "71833",
            "activity": "Agentur, grossiströrelse samt fastighetsförvaltning",
            "employees": 8,
            "capital": 125000,
            "key_personnel": [
                {
                    "name": "Kapten Harald Bergman",
                    "position": "Verkst din"
                }
            ],
            "establishment_year": 1897
        },
        "6": {
            "company_name": "ÅKERMAN & DAHLS TEXTIL, AB",
            "pnr": "602 24",
            "address": "Norrköping, Gamla Rådstugug 31",
            "phone_number": "011-13 74 00",
            "postgiro": "167285-6",
            "activity": "Säljer ull, syntetiska fibrer o garner",
            "capital": 40000,
            "establishment_year": 1953
        },
        "7": {
            "company_name": "ÅKERMANS INGENJORSBYRÅ AB",
            "pnr": "252 24",
            "address": "Helsingborg, Trädgårdsg 9",
            "phone_number": "042-12 10 60, 134242",
            "bank_details": {
                "bankgiro": "653-1891",
                "postgiro": "646792-2"
            },
            "activity": "Konsulterande i byggbranschen",
            "employees": 7,
            "annual_turnover": 400000,
            "capital": 5000,
            "key_personnel": [
                {
                    "name": "Ing Allan Åkerman",
                    "position": "Verkst dir"
                }
            ],
            "establishment_year": 1962
        },
        "8": {
            "company_name": "ÅKERMAN & LUNDS NYA ORGELFABRIKS AB",
            "pnr": "741 00",
            "address": "Knivsta, Sjöv 5",
            "phone_number": "018-38 0319, 38 0818",
            "bank_details": {
                "bankgiro": "233-4423",
                "postgiro": "28102-2"
            },
            "activity": "Tillverkar piporglar för kyrkor, skolor o andra lokaler",
            "employees": 17,
            "annual_turnover": 650000,
            "capital": 60500,
            "key_personnel": [
                {
                    "name": "Köpman Maurits Lanners",
                    "position": "Styrelse"
                },
                {
                    "name": "Signe Johansson",
                    "position": "dir"
                }
            ],
            "establishment_year": 1860
        },
        "9": {
            "company_name": "LECORA AB",
            "pnr": "703 40",
            "address": "Örebro, Hertig Karls Allé 5",
            "phone_number": "019-1197 70",
            "bank_details": {
                "bankgiro": "63-0526",
                "postgiro": "647707"
            },
            "activity": "Tillverkar o säljer livsmedel för storkök. Djupfrysta livsmedel, konserver o skalfri potatis",
            "employees": 40,
            "annual_turnover": 13500000,
            "capital": 100000,
            "key_personnel": [
                {
                    "name": "Lars Pettersson",
                    "position": "Verkst dir"
                },
                {
                    "name": "Hans Stenmark",
                    "position": "Försäljn-chef"
                }
            ],
            "establishment_year": 1959
        },
        "10": {
            "company_name": "LEDERHAUSEN AB, PAUL",
            "pnr": "11242",
            "address": "Stockholm, Drottningholmsv 80",
            "phone_number": "08-13 13 60",
            "bank_details": {
                "bankgiro": "731-3109",
                "postgiro": "659020-2"
            },
            "activity": "Sälj» grillar o mikrovågsugnar",
            "employees": 20,
            "annual_turnover": 7500000,
            "capital": 50000,
            "key_personnel": [
                {
                    "name": "Paul Lederhausen",
                    "position": "Verkst dir"
                }
            ],
            "establishment_year": 1962
        },
        "11": {
            "company_name": "ASKERSUNDSVERKEN AB",
            "pnr": "696 00",
            "address": "Askersund, Trädgårdsg 1-3",
            "phone_number": "0583-111 60",
            "postgiro": "33715-4",
            "activity": "Mek verkstad i Askersund. Tillverkar belysningsstolpar, spännstolpar o rörmaster. Transport-o lagerlådor av stålplåt. Koniska container. Utför mekaniska lego-arbeten. Framställer stålverksko-killer o grovt handformat gods med styckevikter upp till 15 ton vid Högforsbruks Nya Gjuteri AB, Högforsbruk",
            "key_personnel": [
                {
                    "name": "John Axel Franzén",
                    "position": "Verkst dir"
                }
            ],
            "establishment_year": 1932
        },
        "12": {
            "company_name": "ASKIM GUMMI VAREFABRIK SVENSKA AB",
            "pnr": "43122",
            "address": "Mölndal 1, Kråketorpsg 18",
            "phone_number": "031-27 53 40",
            "bank_details": {
                "bankgiro": "847-8604",
                "postgiro": "529510-0"
            },
            "activity": "Tillverkar Viking bildäck, cykel-, moped-, skoter- o mc-däck, industri- o lantbruksdäck samt slangar, luftgummihjul, Industrigummi o plast, gummibeläggningar, gummiskodon, konfektion",
            "employees": 40,
            "annual_turnover": 26000000,
            "capital": 200000,
            "key_personnel": [
                {
                    "name": "Lennart Jonsson",
                    "position": "Verkst dir"
                }
            ],
            "establishment_year": 1961
        },
        "13": {
            "company_name": "ASKLUNDS TRÄ-VARU AB, OLOF",
            "pnr": "31200",
            "address": "Laholm, Lantmannag. Box 99",
            "phone_number": "043 0-122 30",
            "bank_details": {
                "bankgiro": "65-9101",
                "postgiro": "293338"
            },
            "activity": "Försäljning av alla slags trävaror o byggnadsmaterial",
            "employees": 12,
            "annual_turnover": 3500000,
            "capital": 55000,
            "key_personnel": [
                {
                    "name": "Kurt Asklund",
                    "position": "Verkst dir"
                }
            ],
            "establishment_year": 1908
        },
        "14": {
            "company_name": "ASMUNDTORPS BORST-FABRIKS AB",
            "pnr": "260 10",
            "address": "Asmundtorp, Box 28",
            "phone_number": "0418-32016",
            "postgiro": "23231-4",
            "activity": "Tillverkar borstar o penslar. Specialitet: maskinborstar",
            "capital": 10500,
            "key_personnel": [
                {
                    "name": "Olga Bengtsson",
                    "position": "Verkst dir"
                }
            ],
            "establishment_year": 1902
        },
        "15": {
            "company_name": "ALB A KVA TERRA, AB",
            "pnr": "701 03",
            "address": "Örebro 1, Nyg 9",
            "phone_number": "019-14 0170",
            "bank_details": {
                "bankgiro": "614-3150",
                "postgiro": "117170-1"
            },
            "activity": "Projektering av grundvattentäkter o för grundvattensänkningar samt utbyggnad av brunnsanläggningar för städer, kommuner o privata förbrukare",
            "employees": 4,
            "annual_turnover": 400000,
            "capital": 25000,
            "key_personnel": [
                {
                    "name": "Tage Ericsson",
                    "position": "Verkst dir"
                }
            ],
            "establishment_year": 1960
        },
        "16": {
            "company_name": "SVALLING, AB ERIK",
            "pnr": "63103",
            "address": "Eskilstuna 1, Bruksg 17",
            "phone_number": "016-14 70 80",
            "bank_details": {
                "bankgiro": "601-5424",
                "postgiro": "74550-5"
            },
            "activity": "Tillverkar handplåt-saxar, trädgårdsredskap samt utför hejarsmide",
            "employees": 4,
            "annual_turnover": 145000,
            "capital": 50000,
            "key_personnel": [
                {
                    "name": "Holger Brunell",
                    "position": "Verkst dir"
                }
            ],
            "establishment_year": 1905
        },
        "17": {
            "company_name": "SWAHN GJUTERI & MEK VERKSTAD AB",
            "pnr": "78100",
            "address": "Borlänge, Hagav 4",
            "phone_number": "0243-159 20",
            "bank_details": {
                "bankgiro": "79-4616",
                "postgiro": "11186"
            },
            "activity": "Utför brunnsborrning, vatten- o avloppsanläggningar",
            "capital": 150000,
            "key_personnel": [
                {
                    "name": "Ing Olof Swahn",
                    "position": "Verkst dir"
                }
            ],
            "establishment_year": 1903
        },
        "18": {
            "company_name": "SPRINTER SYSTEM AB",
            "pnr": "30103",
            "address": "Halmstad 1, Laholmsv. Box 152",
            "phone_number": "035-11 82 80",
            "activity": "Tillverkar o säljer förpackningsmaskiner",
            "key_personnel": [
                {
                    "name": "Yngve Hammenberg",
                    "position": "Verkst dir"
                }
            ],
            "establishment_year": 1962
        }
    }
}