{
    "original": "LUNDGRENS GJUTERI, AB M\n\nPnr 30102\n\nHalmstad 1, Nässjög 12. Box 82.\n\nTel 035-1184 10. Bankgiro\n530-4746. Postgiro 33299-9\nVaksamhet: Tillverkar\nsanitets-gjutgods o pumpar. Emalj erat o\nplastbelagt sanitetsgjutgods. Utför\nbeställningsarb eten\nAntal anställda: 140\nÅrsomsättning: 9 000 000\nAktiekapital: 1 200 000\nVerkst dir: Lars Magnus Lundgren\nEtableringsår: 1917.\n\nLUNDGRENS INGENIURSBYRÅ\nAB, AKE\n\nPnr 611 02\n\nNyköping 2, Fack. Tel 0155-154 28,\n153 91. Bankgiro 827-3005.\nPostgiro 3 835 69-1\n\nVerksamhet: Konsulterande\ningenjörsbyrå, materialprovning\nAntal anställda: 10\nÅrsomsättning: 500 000\nAktiekapital: 5 000\nVerkst dir. Tekn dr S Ake Lundgren\nEtableringsår: 1954.\n\nDALBYVERKEN H LINSE &amp; CO\n\nPnr 212 28\n\nMalmö, Singelg6. Tel 040-93 50 20.\nBankgiro 651-2156. Postgiro\n431186-6\n\nVerksamhet: Säljer fabriksblandad\nbetong o makadam\nEtableringsår: 1946.\n\nBON\n\nAktiekapital: 6 000\nVerkst dir: Ark Narve Bonna\nEtableringsår: 1964.\n\nBONNEDAHLS SMIDES- &amp;\nMEKANISKA VERKSTAD,\nKB E A\n\nPnr 902 44\n\nUmeå, öbackav 14-16. Tel\n090-111170, 1148 70. Bankgiro\n613-3037. Postgiro 63041-8\nVerksamhet: Järn- o\nplåtkonstruktioner, pressade detaljer i exenter\no hydraulpressar bockade\nrördetaljer samt mek beställningsarbeten,\nreparationer m m\nAntal anställda: 23\nÅrsomsättning: 1600 000\nEtableringsår: 1922.\n\nBONNIERS FORLAG AB,\nALBERT\n\nPnr 103 63\n\nStockholm 3, Box 3159. Sveav 56.\nTel 08-22 91 20. Bankgiro 16-8894.\nPostgiro 844. Tga Bonniers\nVerksamhet: Bokförlag med bok- o\noffsettryckeri, bokbinderi o\nklichéanstalt\n\nAntal anställda: 1050\nAktiekapital: 2 500 000\nStyrelse: Bokförl Albert Bonnier jr,\nbokförl Gerard Bonnier, dir\nJohan Bonnier, bokförl Lukas\nBonnier, bokförl Tor Bonnier,\nbokförl Ake Bonnier, dr Georg\nSvensson\n\nVerkst dir: Gerard Bonnier\nV verkst dir:r. Georg Svensson,\nOlle Måberg\nEtableringsår: 1837\nOmbildat till aktiebolag 1940.\n\nBONNING, AB NILS\n\nPnr 23015\n\nHåslöv. Tel 040-42 32 50. Tga\nBonning\n\nVerksamhet: Spannmål, foder- o\ngödningsämnen\nAntal anställda: 20\nÅrsomsättning: 30500 000\nAktiekapital: 600 000\nVerkst dir: Ebbe Bonning\nEtableringsår: 1952.\n\nSVE\n\nAktiekapital: 51000 000\nStyrelse: Generaldir Erik\nGrafström (ordf), försäkringsdir C-O\nWesterberg, bankdir Olov Ernsell,\nbruksdisp Gunnar Hindemark,\nbankdir Sven Hägerstedt, bankdir Olof\nKyhlberg, bankdir Lars Nyrén, adv\nHugo Stenbeck jr, dir Robert Tolf,\nbankdir Hans-Erik Wihlborg\nVerkst dir. Hans-Erik Wihlborg\nV verkst dir: Bengt Runstad\nEtableringsår: 1869.\n\nSVENSKA INTERNATIONELLA\nBÅTUTSTÄLLNINGEN\n\nPnr 41126\n\nGöteborg, Erik Dahlbergsg 3. Tel\n031-13 92 72, 13 92 74. Bankgiro\n510-2553. Postgiro 603523-2. Tga\n\nBoatshow\n\nVerksamhet Arrangerar Svenska\nInternationella Båtutställningen\nsom årligen äger rum i februari i\nSvenska Mässans hallar i Göteborg\nKanslichef: Rolf Lindqvist\nEtableringsår: 1960.\n\nWOLRATHS JARN AB\n\nPnr 75104\n\nUppsala 1, Svartbäcksg 14. Box\n196, Tel 018-14 9200. Bankgiro\n80-2118. Postgiro 7633\nVerksamhet: Säljer järnvaror o\nbyggnadsmaterial\n\nAntal anställda: 115\nÅrsomsättning: 30 000 000\nAktiekapital: 2 000 000\nVerkst dir: Rune Sjöberg\nEtableringsår: 1901.\n\nFLOOR MASKINER AB\n\nPnr 802 28\n\nGävle, Linnév 6. Tel 026-1112 70,\n1115 70. Bankgiro 60-3654.\nPostgiro 106362. Tga Floor\nVerksamhet: Fabriksplanering\ninom cellulosabranschen\nVarunamn: Moulator\nÄgare o chef: Johan Larsson\nEtableringsår: 1950.\n\nEGNELL, PUMP AB EINAR\n\nPnr 46101\n\nTrollhättan 1, Faktorsg 2. Box\n218. Tel 0520-30240. Bankgiro\n892-6461. Postgiro 199724-6.\nTga Pumpegnell\n\nVerksamhet: Tillverkar\noperationspumpar o andra medicinska\nsug-pumpar. Uthyr brostpumpar\nVarunamn: Pump-Egnell\nAntal anställda: 11\nAktiekapital: 25 000\nVerkst dir: Holger Infeldt\nEtableringsår: 1946.\n\nEGNELLS SNORFABRIK, AB\nEINAR\n\nPnr 602 23\n\nNorrköping, Kronängsg 3. Tel\n011-18 0045. Bankgiro 12-5063.\nPostgiro 79686. Tga Egnellfabrik\nVerksamhet: Kabeltillverkning\nAntal anställda: 100\nVerkst idr: Erik Lönnqvist\nEtableringsår: 1949.\n\nEGNELL, AB INGENIORS.\nFIRMA FRITZ\n\nPnr 10127\n\nStockholm 1, Box 531. Tunnelg\n20 B. Tel 08-24 34 30. Bankgiro\n560-0929. Postgiro 3453-8. Tga\nMotor\n\nVerksamhet: Säljer\ngasanalysappa-rater, pyrometrar, indikatorer,\nrör-kopplingar, högtrycksslang o andra\nledningskomponenter för\nhydraulik o tryckluft\nAntal anställda: 55\nÅrsomsättning: 15 000 000\nAktiekapital: 800 000\nStyrelse: Civiling Arvid\nHammarskiöld (ordf), ing Fritz Gunnar\nEgnell, adv G A Rising\nVerkst dir: Fritz Gunnar Egnell\nEtableringsår: 1911.\n\nEGNELLSKA\nBOK-TRYCKERIET, AB\n\nPnr 116 53\n\nStockholm, Rosenlundsg 52. Tel\n08-69 08 00. Bankgiro 56-4541.\nPostgiro 151400. Tga Ebetryck\nVerksamhet: Tidskrifter, böcker o\nkataloger\n\nAntal anställda: 200\n\nAktiekapital: 85000\n\nVerkst dir: Hans Boije af Gennäs\n\nEtableringsår: 1919.\n\nDEL\n\nAktiekapital: 100 000\nVerkst dir: J-A Delmar\nEtableringsår: 1906.\n\nAEROSOL PACKING CO, AB\n\nPnr 186 00\n\nVallentuna, Box 61. Pabriksv. Tel\n0762-221 00. Bankgiro 734-0953.\nPostgiro 553696-6. Tga\nApcopro-dukt\n\nVerksamhet: Lönfyllning av\naerosoler\n\nAntal anställda: 45\n\nAktiekapital: 50 000\n\nStyrelse: Ing Börje Karlson (ordf),\n\ndr Bruno Löwenberg\n\nVerkst dir: Dr Bruno Löwenberg\n\nEtableringsår: 1956.\n\nHARTMANS KORTFORLAG AB\n\nPnr 750 03\n\nUppsala 3, Sankt Olofsg 50. Box\n3024. Tel 018-14 90 50. Bankgiro\n233-8168. Postgiro 88888-3\nVerksamhet: Försäljning en gros\nav gratulationskort o andra kort\nAntal anstäUda: 18\nÅrsomsättning: 1500 000\nAktiekapital: 150 000\nVerkst dir: Nils Olin\nEtableringsår: 1934.",
    "structured": {
        "1": {
            "company_name": "LUNDGRENS GJUTERI, AB M",
            "pnr": "30102",
            "address": "Halmstad 1, Nässjög 12. Box 82.",
            "phone_number": "035-1184 10",
            "bank_details": {
                "bankgiro": "530-4746",
                "postgiro": "33299-9"
            },
            "activity": "Tillverkar sanitetsgjutgods o pumpar. Emaljerat o plastbelagt sanitetsgjutgods. Utför beställningsarbeten",
            "employees": 140,
            "annual_turnover": 9000000,
            "capital": 1200000,
            "key_personnel": [
                {
                    "name": "Lars Magnus Lundgren",
                    "position": "Verkst dir"
                }
            ],
            "establishment_year": 1917
        },
        "2": {
            "company_name": "LUNDGRENS INGENIURSBYRÅ AB, AKE",
            "pnr": "611 02",
            "address": "Nyköping 2, Fack. Tel 0155-154 28, 153 91",
            "bank_details": {
                "bankgiro": "827-3005",
                "postgiro": "3 835 69-1"
            },
            "activity": "Konsulterande ingenjörsbyrå, materialprovning",
            "employees": 10,
            "annual_turnover": 500000,
            "capital": 5000,
            "key_personnel": [
                {
                    "name": "Tekn dr S Ake Lundgren",
                    "position": "Verkst dir"
                }
            ],
            "establishment_year": 1954
        },
        "3": {
            "company_name": "DALBYVERKEN H LINSE & CO",
            "pnr": "212 28",
            "address": "Malmö, Singelg6. Tel 040-93 50 20",
            "bank_details": {
                "bankgiro": "651-2156",
                "postgiro": "431186-6"
            },
            "activity": "Säljer fabriksblandad betong o makadam",
            "establishment_year": 1946
        },
        "4": {
            "company_name": "BON",
            "capital": 6000,
            "key_personnel": [
                {
                    "name": "Ark Narve Bonna",
                    "position": "Verkst dir"
                }
            ],
            "establishment_year": 1964
        },
        "5": {
            "company_name": "BONNEDAHLS SMIDES- & MEKANISKA VERKSTAD, KB E A",
            "pnr": "902 44",
            "address": "Umeå, öbackav 14-16. Tel 090-111170, 1148 70",
            "bank_details": {
                "bankgiro": "613-3037",
                "postgiro": "63041-8"
            },
            "activity": "Järn- o plåtkonstruktioner, pressade detaljer i exenter o hydraulpressar bockade rördetaljer samt mek beställningsarbeten, reparationer m m",
            "employees": 23,
            "annual_turnover": 1600000,
            "establishment_year": 1922
        },
        "6": {
            "company_name": "BONNIERS FORLAG AB, ALBERT",
            "pnr": "103 63",
            "address": "Stockholm 3, Box 3159. Sveav 56. Tel 08-22 91 20",
            "bank_details": {
                "bankgiro": "16-8894",
                "postgiro": "844"
            },
            "activity": "Bokförlag med bok- o offsettryckeri, bokbinderi o klichéanstalt",
            "employees": 1050,
            "capital": 2500000,
            "key_personnel": [
                {
                    "name": "Gerard Bonnier",
                    "position": "Verkst dir"
                },
                {
                    "name": "Georg Svensson",
                    "position": "V verkst dir"
                },
                {
                    "name": "Olle Måberg",
                    "position": "V verkst dir"
                }
            ],
            "establishment_year": 1837
        },
        "7": {
            "company_name": "BONNING, AB NILS",
            "pnr": "23015",
            "address": "Håslöv. Tel 040-42 32 50",
            "activity": "Spannmål, foder- o gödningsämnen",
            "employees": 20,
            "annual_turnover": 30500000,
            "capital": 600000,
            "key_personnel": [
                {
                    "name": "Ebbe Bonning",
                    "position": "Verkst dir"
                }
            ],
            "establishment_year": 1952
        },
        "8": {
            "company_name": "SVE",
            "capital": 51000000,
            "key_personnel": [
                {
                    "name": "Hans-Erik Wihlborg",
                    "position": "Verkst dir"
                },
                {
                    "name": "Bengt Runstad",
                    "position": "V verkst dir"
                }
            ],
            "establishment_year": 1869
        },
        "9": {
            "company_name": "SVENSKA INTERNATIONELLA BÅTUTSTÄLLNINGEN",
            "pnr": "41126",
            "address": "Göteborg, Erik Dahlbergsg 3. Tel 031-13 92 72, 13 92 74",
            "bank_details": {
                "bankgiro": "510-2553",
                "postgiro": "603523-2"
            },
            "activity": "Arrangerar Svenska Internationella Båtutställningen som årligen äger rum i februari i Svenska Mässans hallar i Göteborg",
            "employees": null,
            "establishment_year": 1960
        },
        "10": {
            "company_name": "WOLRATHS JARN AB",
            "pnr": "75104",
            "address": "Uppsala 1, Svartbäcksg 14. Box 196, Tel 018-14 9200",
            "bank_details": {
                "bankgiro": "80-2118",
                "postgiro": "7633"
            },
            "activity": "Säljer järnvaror o byggnadsmaterial",
            "employees": 115,
            "annual_turnover": 30000000,
            "capital": 2000000,
            "key_personnel": [
                {
                    "name": "Rune Sjöberg",
                    "position": "Verkst dir"
                }
            ],
            "establishment_year": 1901
        },
        "11": {
            "company_name": "FLOOR MASKINER AB",
            "pnr": "802 28",
            "address": "Gävle, Linnév 6. Tel 026-1112 70, 1115 70",
            "bank_details": {
                "bankgiro": "60-3654",
                "postgiro": "106362"
            },
            "activity": "Fabriksplanering inom cellulosabranschen",
            "varunamn": "Moulator",
            "employees": null,
            "establishment_year": 1950
        },
        "12": {
            "company_name": "EGNELL, PUMP AB EINAR",
            "pnr": "46101",
            "address": "Trollhättan 1, Faktorsg 2. Box 218. Tel 0520-30240",
            "bank_details": {
                "bankgiro": "892-6461",
                "postgiro": "199724-6"
            },
            "activity": "Tillverkar operationspumpar o andra medicinska sug-pumpar. Uthyr brostpumpar",
            "varunamn": "Pump-Egnell",
            "employees": 11,
            "capital": 25000,
            "key_personnel": [
                {
                    "name": "Holger Infeldt",
                    "position": "Verkst dir"
                }
            ],
            "establishment_year": 1946
        },
        "13": {
            "company_name": "EGNELLS SNORFABRIK, AB EINAR",
            "pnr": "602 23",
            "address": "Norrköping, Kronängsg 3. Tel 011-18 0045",
            "bank_details": {
                "bankgiro": "12-5063",
                "postgiro": "79686"
            },
            "activity": "Kabeltillverkning",
            "employees": 100,
            "key_personnel": [
                {
                    "name": "Erik Lönnqvist",
                    "position": "Verkst idr"
                }
            ],
            "establishment_year": 1949
        },
        "14": {
            "company_name": "EGNELL, AB INGENIORS. FIRMA FRITZ",
            "pnr": "10127",
            "address": "Stockholm 1, Box 531. Tunnelg 20 B. Tel 08-24 34 30",
            "bank_details": {
                "bankgiro": "560-0929",
                "postgiro": "3453-8"
            },
            "activity": "Säljer gasanalysapparater, pyrometrar, indikatorer, rörkopplingar, högtrycksslang o andra ledningskomponenter för hydraulik o tryckluft",
            "employees": 55,
            "annual_turnover": 15000000,
            "capital": 800000,
            "key_personnel": [
                {
                    "name": "Fritz Gunnar Egnell",
                    "position": "Verkst dir"
                }
            ],
            "establishment_year": 1911
        },
        "15": {
            "company_name": "EGNELLSKA BOK-TRYCKERIET, AB",
            "pnr": "116 53",
            "address": "Stockholm, Rosenlundsg 52. Tel 08-69 08 00",
            "bank_details": {
                "bankgiro": "56-4541",
                "postgiro": "151400"
            },
            "activity": "Tidskrifter, böcker o kataloger",
            "employees": 200,
            "capital": 85000,
            "key_personnel": [
                {
                    "name": "Hans Boije af Gennäs",
                    "position": "Verkst dir"
                }
            ],
            "establishment_year": 1919
        },
        "16": {
            "company_name": "DEL",
            "capital": 100000,
            "key_personnel": [
                {
                    "name": "J-A Delmar",
                    "position": "Verkst dir"
                }
            ],
            "establishment_year": 1906
        },
        "17": {
            "company_name": "AEROSOL PACKING CO, AB",
            "pnr": "186 00",
            "address": "Vallentuna, Box 61. Pabriksv. Tel 0762-221 00",
            "bank_details": {
                "bankgiro": "734-0953",
                "postgiro": "553696-6"
            },
            "activity": "Lönfyllning av aerosoler",
            "employees": 45,
            "capital": 50000,
            "key_personnel": [
                {
                    "name": "Dr Bruno Löwenberg",
                    "position": "Verkst dir"
                }
            ],
            "establishment_year": 1956
        },
        "18": {
            "company_name": "HARTMANS KORTFORLAG AB",
            "pnr": "750 03",
            "address": "Uppsala 3, Sankt Olofsg 50. Box 3024. Tel 018-14 90 50",
            "bank_details": {
                "bankgiro": "233-8168",
                "postgiro": "88888-3"
            },
            "activity": "Försäljning en gros av gratulationskort o andra kort",
            "employees": 18,
            "annual_turnover": 1500000,
            "capital": 150000,
            "key_personnel": [
                {
                    "name": "Nils Olin",
                    "position": "Verkst dir"
                }
            ],
            "establishment_year": 1934
        }
    }
}