{
    "original": "HAG\n\nH\n\nHABBERSTAD AB, ASBJÖRN\n\nPnr 40251\n\nGöteborg 13, Box 13058. von\nUt-falls g 9 A. Tel 031-26 2240.\nTga Habkonsult.\nTelex 20683 HABCONS S\nVerksamhet: Konsulterande inom\nalla tekniska o merkantila\nmanagementområden\n\nFilial: 11122 Stockholm, Kungsg\n60; Tel 08-24 1 2 85.\nAntal anställda: 194 (koncernen)\nAktiekapital: 350 000 (koncernen)\nSvensk chef: Dir Olaf Röe\nEtableringsår: 1940\nOmbildat till aktiebolag 1960.\n\nHABER, INDUSTRI AB\n\nPnr 125 42\n\nÄlvsjö, Huddingev 447. Tel\n08-47 26 50\n\nVerksamhet: Tillverkar\nhalvfabrikat för persienner m m\nAktiekapital: 11000\nVerkst dir: Thure Densën\nDisp: Bertil Sjögren\nEtableringsår: 1947\nOmbildat till aktiebolag 1959.\n\nHABIA KOMMANDITBOLAG\n\nPnr 74100\n\nKnivsta, Brantshammar. Tel\n018-34 10 00. Bankgiro 233-4415.\nPostgiro 375522-0. Tga Habia.\nTelex 7430\n\nVerksamhet: Tillverkar produkter\ni Teflon\n\nVarunamn: Habia, Teflon\nAntal anställda: 80\nÅrsomsättning: 12 000 000\nAktiekapital: 450000\nStyrelse: Civiling Carl-Herbert\nJacobson\n\nVerkst dir: Civiling Carl-Herbert\nJacobson\n\nTekn dir: Ing B Waage\nFörsäljn-chef: Ing B Kjällström\nFörsäljning: Ing A Kullberg, ing\nD Thulin\n\nInköp: Ing B Sundqvist\nKassa o bokföring: Kamrer E\nSjögren\n\nEtableringsår: 1963\nFöretaget har direkt övertagit den\nsedan år 1957 av Hammarby\nBakelit Industri AB i Knivsta\nbedrivna verksamheten.\n\nHABING AB, HAGBERT\n\nPnr 52100\n\nFalköping, Mossv 21. Tel\n0515-17160\n\nVerksamhet: Säljer sågade o\nhyvlade trävaror samt alla slags\nbyggnadsmateriel\n\nAktiekapital: 25 000\nVerkst dir: Algot Gedelius\nEtableringsår: 1953.\n\nHABO EMBALLAGE.\nFABRIK AB\n\nPnr 560 40\n\nHabo, Box 72. Tel 036-403 53,\n405 14. Tga Haboemballage\nVerksamhet: Specialtillverkning\nav runda o fyrkantiga pappburkar\ni alla utföranden, spiralspolade\npapphylsor o pappbobiner samt\nblåsta plastflaskor o formsprutade\nplastdetaljer\nAntal anställda: 40\nÅrsomsättning: 3 000 000\nAktiekapital: 50 000\nVerkst dir: Thure Svensson\nEtableringsår: 1956.\n\nLINDQVIST AB, BO\n\nPnr 11139\n\nStockholm, Jutas backe 1. Tel\n08-23 3 5 05. Bankgiro 282-8739.\nPostgiro 405722-0. Tga Bolinox.\nTelex 19909\n\nVerksamhet; Generalagentur.\nSäljer plåt, band, stång, valstråd,\ndragen tråd, smiden, gjutgods,\nsömlösa o svetsade rör inkl ämnesrör\ni rostfria, syrafasta o eldhärdiga\nstål samt titan o specialmetaller\nVarunamn: Bolinox, Uginox, UK,\nTrefinox, Vallourec, MS\nÅrsomsättning: 33 000 000\nAktiekapital: 50 000\nVerkst dir: Bo Lindqvist.\n\nLINDQVIST AB, E A\n\nPnr 93100\n\nSkellefteå, Stationsg 12. Tel\n0910-165 22, 176 22. Bankgiro 75-3102.\nPostgiro 62195. Tga Produkter\nVerksamhet: Sågar o hyvlar\nträvaror. Skogsavverkningar\nAntal anställda: 52\nÅrsomsättning: 5 000 000\nAktiekapital: 100 000\nVerkst dir: E A Lindqvist\nEtableringsår: 1929.\n\nLINDQUIST PATENTBYRÅ AB,\nERIK\n\nPnr 114 43\n\nStockholm, Sibylleg 81. Tel\n08-63 16 80. Bankgiro 726-8543.\nPostgiro 194958-5. Tga Pali\nVerksamhet: Patentbyrå\nÄgare o chef: Erik Lindquist\nEtableringsår: 1944.\n\nLINDQVIST, BYGGNADS AB\nGUNNAR\n\nPnr 932 00\n\nSkelleftehamn, S Hamng 4. Tel\n0910-312 51. Bankgiro 615-6160.\nPostgiro 67503-3\n\nVerksamhet: Byggnadsentreprenör\nAntal anstäUda: 25\nÅrsomsättning: 2000 000\nAktiekapital: 100 000\nVerkst dir: Ing Sören Lindqvist\nEtableringsår: 1953.\n\nLINDQVIST MOTORFABRIK\nAB, BRÖDERNA H\n\nPnr 662 00\n\nÅmål, Pabriksg 2. Tel 0532-10445.\nBankgiro 895-1675. Postgiro\n72895-6\n\nVerksamhet: Mekanisk verkstad.\nSpecialitet: serietillverkning av\nbildetaljer\nAntal anställda: 75\nÅrsomsättning: 5 000 000\nAktiekapital: 300 000\nVerkst dir: Herbert Lindqvist\nEtableringsår: 1935.\n\nKUGGKRANSAR, AB\n\nPnr 430 70\n\nSävedalen, Industriv. Box 23. Tel\n031-262040. Bankgiro 446-1422.\nPostgiro 244743-1\nVerksamhet: Tillverkar\nstartkransar till bil- o båtmotorer\nÅrsomsättning: 300 000\nAktiekapital: 30 000\nVerkst dir: Lennart Ryberg\nEtableringsår: 1948.\n\nMAFAL\n\nPnr 260 80\n\nMunkaljungby. Tel 0431-300 69,\n302 21. Bankgiro 576-6571.\nPostgiro 322271-8. Tga Mafal\nVerksamhet: Tillverkar\nlantbruks-maskiner o kapsågar\nChef: Övering Ingvar Falk\nEtableringsår: 1938.\n\nMAGNÉRS MOTOR &amp;\nMEK VERKSTAD, IVAR\n\nPnr 572 00\n\nOskarshamn, Rådmansg 6. Tel\n0491-10 1 77\n\nVerksamhet: Tillverkar båtmotorn\n•Magne\"\n\nChef: Ivar Magnér.\n\nMAGNETIC AB\n\nPnr 16111\n\nBromma 11, Box 11060.\nGårdsfog-dev 18. Tel 08-29 04 60. Bankgiro\n332-0306. Postgiro 56654-7. Tga\nMagnetic. Telex 19037\nVerksamhet: Utvecklar o säljer\nelektroniska specialinstrument\nAntal anställda: 110\nÅrsomsättning: 14 000 000\nAktiekapital: 100000\nVerkst dir. Bengt Dahlman\nEtableringsår 1951.\n\nBYGG-KEMI, AB\n\nPnr 230 23\n\nAnderslöv, Järnvägsg. Tel\n0410-205 80, fabrik 280 50. Bankgiro\n65-0056. Postgiro 536920\nVerksamhet: Tillverkar o säljer\nBe-mix-produkter, -betongtillsatsmedel mm. Agentur i byggvaror\nVarunamn: Bemix\nAktiekapital: 10 000\nVerkst dir: Conrad Nilsson\nEtableringsår: 1960.\n\nULLMAN AB. ING TORSTEN\n\nPnr 34Q36\n\nMoheda. Tel 0472-708 20.\nBankgiro 668-1605. Postgiro 276145-0.\nTga Ullmanab, Växjö\nVerksamhet: Utför\nautomatsvarv-ning av finmekaniska detaljer o\nkugghjul, induktionshärdning samt\nrund-, planparallell- o\ncenter-lesslipning\nAntal anställda: 150\nÅrsomsättning: 12 000 000\nAktiekapital: 192 000\nStyrelse: Ing Torsten Ullman (ordf),\nfru Marianne Ullman\nVerkst dir: Ing Erland Ullman\nKamrer: Nils Quant\nEtableringsår 1945.\n\nSVENSK VÄRMEMÄTNING, AB\n\nPnr 161 31\n\nBromma, Ståltrådsv 33. Tel\n08-26 26 70. Bankgiro 16-4618.\nPostgiro 190367-3. Tga Värmemätning\nVerksamhet: Tillverkar mätare för\nmätning av värme o varmvatten\nVarunamn: SVM\nAntal anställda: 42\nÅrsomsättning: 2 200 000\nAktiekapital: 288 000\nVerkst dir: Lennart Hallberg\nEtableringsår: 1942.\n\nFRODÉNS VERKSTÄDER, AB\n\nPnr 552 68\n\nJönköping, Kindgrensg 16. Tel\n036-16 50 40. Bankgiro 835-7329.\nPostgiro 264702-2\n\nVerksamhet: Tillverkar\nspiralfal-sade rör med detaljer o tillbehör\n\nFilialer: 415 05 Göteborg, von\nUt-fallsg 7. Tel 031-26 58 00\n126 59 Hägersten, Stöttingsgränd\n22. Tel 08-8894 82\nAntal anställda: 200\nÅrsomsättning: 20 000 000\nAktiekapital: 250 000\nVerkst dir: Stig V Frödén\nEtableringsår: 1878.\n\nFRÖDINS REDOVISNINGSBYRÅ\nAB\n\nPnr 11138\n\nStockholm, Malmskillnadsg 45. Tel\n08-20 05 10. Bankgiro 57-6942.\nPostgiro 452269-4\nVerksamhet: Utför bokförings-,\nredovisnings- o revisionsarbeten\nAntal anställda: 6\nÅrsomsättning: 700 000\nAktiekapital: 5 000\nVerkst dir: Revisor Tor Frödin\nEtableringsår: 1956.\n\nVARBERGS SÄNGFABRIK, AB\n\nPnr 432 00\n\nVarberg, Susvindsv. Tel\n0340-10732. Bankgiro 354-7684.\nPostgiro 295054-1\n\nVerksamhet: Tillverkar\nschäslonger o dagbäddar samt våningssängar\nAntal anställda: 13\nÅrsomsättning: 1400 000\nChefer: Fabr Gösta Ivarsson, fabr\nStig Ivarsson\nEtableringsår: 1928.\n\nJOHANSSON, AB GUSTAF W\n\nPnr 200 41\n\nMalmö 8, Box 8096. Tel\n040-44 82 85,44 83 51. Bankgiro\n641-3769. Postgiro 38331-5. Tga Furu\nVerksamhet: Säljer trävaror,\nsnickerier o byggvaror. Sågverk o\nhyvleri. Tryckimpregneringsverk\nAntal anställda: 25\nÅrsomsättning: 5 000 000\nAktiekapital: 300 000\nEtableringsår: 1897.",
    "structured": {
        "1": {
            "company_name": "HABBERSTAD AB, ASBJÖRN",
            "pnr": "40251",
            "address": "Göteborg 13, Box 13058. von Ut-falls g 9 A",
            "phone_number": "031-26 2240",
            "bank_details": {
                "bankgiro": "N/A",
                "postgiro": "N/A"
            },
            "activity": "Konsulterande inom alla tekniska o merkantila managementområden",
            "employees": 194,
            "capital": 350000,
            "key_personnel": [
                {
                    "name": "Dir Olaf Röe",
                    "position": "Svensk chef"
                }
            ],
            "establishment_year": 1940
        },
        "2": {
            "company_name": "HABER, INDUSTRI AB",
            "pnr": "125 42",
            "address": "Älvsjö, Huddingev 447",
            "phone_number": "08-47 26 50",
            "activity": "Tillverkar halvfabrikat för persienner m m",
            "capital": 11000,
            "key_personnel": [
                {
                    "name": "Thure Densën",
                    "position": "Verkst dir"
                },
                {
                    "name": "Bertil Sjögren",
                    "position": "Disp"
                }
            ],
            "establishment_year": 1947
        },
        "3": {
            "company_name": "HABIA KOMMANDITBOLAG",
            "pnr": "74100",
            "address": "Knivsta, Brantshammar",
            "phone_number": "018-34 10 00",
            "bank_details": {
                "bankgiro": "233-4415",
                "postgiro": "375522-0"
            },
            "activity": "Tillverkar produkter i Teflon",
            "employees": 80,
            "annual_turnover": 12000000,
            "capital": 450000,
            "key_personnel": [
                {
                    "name": "Civiling Carl-Herbert Jacobson",
                    "position": "Styrelse"
                },
                {
                    "name": "Civiling Carl-Herbert Jacobson",
                    "position": "Verkst dir"
                },
                {
                    "name": "Ing B Waage",
                    "position": "Tekn dir"
                }
            ],
            "establishment_year": 1963
        },
        "4": {
            "company_name": "HABING AB, HAGBERT",
            "pnr": "52100",
            "address": "Falköping, Mossv 21",
            "phone_number": "0515-17160",
            "activity": "Säljer sågade o hyvlade trävaror samt alla slags byggnadsmateriel",
            "capital": 25000,
            "key_personnel": [
                {
                    "name": "Algot Gedelius",
                    "position": "Verkst dir"
                }
            ],
            "establishment_year": 1953
        },
        "5": {
            "company_name": "HABO EMBALLAGE. FABRIK AB",
            "pnr": "560 40",
            "address": "Habo, Box 72",
            "phone_number": "036-403 53, 405 14",
            "activity": "Specialtillverkning av runda o fyrkantiga pappburkar i alla utföranden, spiralspolade papphylsor o pappbobiner samt blåsta plastflaskor o formsprutade plastdetaljer",
            "employees": 40,
            "annual_turnover": 3000000,
            "capital": 50000,
            "key_personnel": [
                {
                    "name": "Thure Svensson",
                    "position": "Verkst dir"
                }
            ],
            "establishment_year": 1956
        },
        "6": {
            "company_name": "LINDQVIST AB, BO",
            "pnr": "11139",
            "address": "Stockholm, Jutas backe 1",
            "phone_number": "08-23 3 5 05",
            "bank_details": {
                "bankgiro": "282-8739",
                "postgiro": "405722-0"
            },
            "activity": "Generalagentur. Säljer plåt, band, stång, valstråd, dragan tråd, smiden, gjutgods, sömlösa o svetsade rör inkl ämnesrör i rostfria, syrafasta o eldhärdiga stål samt titan o specialmetaller",
            "annual_turnover": 33000000,
            "capital": 50000,
            "key_personnel": [
                {
                    "name": "Bo Lindqvist",
                    "position": "Verkst dir"
                }
            ]
        }
    }
}