{
    "original": "PEHRSON &amp; CO, AB J\n\nPnr 70104\n\nÖrebro 1, Tackjärnsg 8. Box 235.\nTel 019-11 94 60. Bankgiro\n815-7430. Postgiro 5148-2. Tga Pehrson\nVerksamhet: Detaljhandelskedja\ninom skobranschen\nVarunamn: Engelbrekt, Ingeborg\nAntal anstäUda: 145\nAktiekapital: 1500 000\nStyrelse: Harry Jonsson (ordf),\nTorsten Berglund sr, Anders\nBerglund, Torsten Berglund jr, Ragnar\nBerglund\n\nVerkst dir: Torsten Berglund sr\nEtableringsår: 1901.\n\nPERSSON KB, BYGGNADS.\nFIRMA JOEL\n\nPnr 83100\n\nÖstersund, Regementsg 17. Tel\n063-204 50. Bankgiro 777-8707.\nPostgiro 467347-1\nVerksamhet: Uppför bostads-,\naffärs- o industribyggnader etc\nAntal anstäUda: 80\nÅrsomsättning: 8000 000\nChef: Byggmäst Joel Persson\nEtableringsår: 1953.\n\nVÄS\n\nspännen, klädhängare,\nindustridetaljer, lönpressning\nAntal anställda: 11\nÅrsomsättning: 1000 000\nAktiekapital: 50 000\nVerkst dir. Erik Pettersson\nEtableringsår: 1948\nOmbildat till aktiebolag 1964.\n\nVÄSTERBOTTENS\nFOLK-BLAD, TRYCKERI AB\n\nPnr 902 47\n\nUmeå, Rådhusesplanaden 4. Tel\n090-1185 50. Bankgiro 983-3104.\nPostgiro 23053-2\nTelex 54045 YFUMEA S\nVerksamhet: Tidnings- o\nciviltryckeri\n\nAvdelningskontor: Skellefteå, Nyg\n58. Tel 0910-14270\nAktiekapital: 343 300\nVeikst dir: Clas Hanell\nEtableringsår: 1917.\n\nVÄSTERBOTTENS SKOGS.\nÄGAREFORENING\nEK FÖRENING\n\nPnr 93101\n\nSkellefteå 1, Box 133. Tel\n0910-144 25.Bankgiro 203-9212. Postgiro\n61811-6. Tga Skellefteskog.\nTelex 6882 SKOGSKE S\nPnr 901 02 Umeå 1. Box 23. Tel\n090-11 81 60. Bankgiro 201-3068.\nPostgiro 63283-6. Tga Tall o Gran\nVeiksamhet: Köper o säljer\nrundvirke, stolpar o specialsortiment.\nEgna sågverk med hyvleri i Umeå,\nKåge o Stensele jämte sågverk 1\nLövsele, Lövånger. Exporterar\nsågade trävaror, stolpar m fi\nsortiment\n\nAntal anställda: 375\nÅrsomsättning: 51000 000\nInsatskapital: 10875 707\nVerkst dir: Abel Olsson\nDisp: Bernth Holmlund\nEtableringsår: 1933.\n\nVÄSTERBOTTENS.\nKURIREN5 AB\n\nPnr 90102\n\nUmeå 1, Box 47. Rådhusesplanaden\n10. Tel 090-11 86 00. Bankgiro\n201-44 3 9. Postgiro 62017-9. Tga\nKu-riren.\n\nTelex 54052, 54070 VKREDUM S\nVerksamhet: Utger\nVästerbottens-Kuriren sex dagar i veckan.\nTS-kontrollerad upplaga 39 576 ex\nAntal anställda: 145\nÅrsomsättning: 12 800 000\nAktiekapital: 200 000\nVerkst dir: Sven Tollin\nChefred: Matts Balgård\nKamrer: Yngve Ybrandt\nAnnonschef: Hilding Rothelius\nEtableringsår: 1900.\n\nVÄSTERVIKS FISK\nFÖRSÄLJ-NINGSFORENING UPA\n\nPnr 593 00\n\nVästervik, Barlastudden. Tel\n0490-130 70. Bankgiro 66-7120. Postgiro\n279219-0\n\nVerksamhet: Säljer fisk engros.\nFiskredskaps affär\nAntal anställda: 30\nÅrsomsättning: 6 000 000\nStyrelse: Erie Källgren (ordf),\nJosef Larsson, Nils Mattsson,\n\nBirger Wiström, Karl-Erik Thorén\nChef: Disp Gustaf Lannér\nEtableringsår: 1936.\n\nTRELLEBORGPLAST, AB\n\nPnr 34100\n\nLjungby, Box 149. Tel\n0372-125 20. Bankgiro 640-6409.\nPostgiro 438376-6. Tga\nTrelleborgplast. Telex 4690\nVerksamhet: Tillverkar produkter\nav termoplast o armerad plast\nsåsom folier, sprutade o\nvakuumfor-made artiklar, karosseridetaljer,\ntankar, emballage, pressade\nprodukter, rotationsgjutna\ntrafiksäkerhetsdetaljer\nAntal anställda: 550\nÅrsomsättning: 40 000 000\nAktiekapital: 10 000 000\nVerkst dir: Göran Hellner\nFörsäljn-chef: Dir Yngve .Askblad\nEtableringsår: 1956\nDotterbolag till Trelleborgs\nGummifabriks AB.\n\nTREMIX AB\n\nPnr 13101\n\nNacka 1, Becksjudarv 37. Box 84.\nTel 08-7162745. Bankgiro\n746-0124. Postgiro 570710-4. Tga\nSteelman, Stockholm.\nTelex 1634 STEEL S\nVerksamhet: Vibratorer,\nvibrerings-o jordkomprimeringsmaskiner,\nbe-tonggolvläggningsmaskiner\nVarunamn: Tremix\nAntal anställda: 90\nÅrsomsättning: 11000 000\nAktiekapital: 100 000\nAvdelningskontor: 433 00 Partille,\nBox 103. Järnstångsv 15. Tel\n031-44 5512\n\nMalmö. Arlövs Industriby, pa 23200\nArlöv. Tel 040^13 30 50\n852 35 Sundsvall, Nybrog 29. Tel\n060-12 81 80\n\nVerkst dir: E Wrethagen\nEtableringsår: 1960.\n\nTRENSUMS MASKININDUSTRI,\nAB\n\nPnr 290 73\n\nTrensum. Tel 0454-613 00.\nBankgiro 656-5089. Postgiro 109790-6\nVerksamhet: Tillverkar kyl- o\nfryselement\nAntal anställda: 15\nÅrsomsättning: 2 000 000\nAktiekapital: 30 000\nStyrelse: Pabr Ake Knutsson (ordf),\nfabr Osten Haraldsson, fabr Kjell\nBengtsson\n\nVerkst dir: Kjell Bengtsson\nEtableringsån 1954.\n\nTRETORN,\n\nHELSINGBORGS\nGUMMI-FABRIKS AB\n\nPnr 25101\n\nHelsingborg 1, Fack. Tel\n042-12 61 00. Bankgiro 653-0216.\nPost-giro 14333-9. Tga Tretorn.\nTelex 72372\n\nVerksamhet: Tillverkar\ngummistövlar, ytterskor, galoscher, textilskor,\nbadskor, lek- o sportbollar,\ntennisbollar, tennisrackets,\nreflexmaterial samt industriplast\nNederlag: Göteborg, Luleå,\nStockholm, Sundsvall, Örebro\nAntal anställda: 2 700 (inkl\ndotterbolag i Sverige o utlandet)\nÅrsomsättning: 149 500 000 (inkl\ndotterbolag i Sverige o utlandet)\nAktiekapital: 33 276 800\nVerkst dir o koncernchef: Ake\nStåhlbrandt\n\nPlats- o produktionschef: Börje\nSwanstein\n\nEkonomichef: Bertil Andersson\nMarknadschef: Folke Lundgren\nEtableringsår: 1891\nBolaget samarbetar under\ngemensam koncernledning med\nTrelleborgs Gummifabriks AB.\n\nTRETORN DATA CENTER AB\n\nPnr 251 01\n\nHelsingborg 1, Fack. Rönnowsg 10.\nTel 042-14 44 40. Bankgiro\n410-2653. Postgiro 396820-3. Tga\nTretorn. Telex 72372\nVerksamhet: Servicebyrå inom\nföreträdesvis det administrativa\nområdet med en stor mängd\nstandardsystem för olika branscher o\nrutiner. On-line system för lager- o\nreskontrarutiner m m.\nDetaljhandelssystem som körs för hela\nnorden i samarbete med NCR. Ett\nhel-ägt dotterbolag Tretorn Drev AB\ninom direkreklam med hjälp av ADB\nAntal anställda: 43\nÅrsomsättning: 4 000 000\nAktiekapital: 100 000\nVerkst dir Bo C: son Lindberg\nMarknadschef: Leif Fogelberg\nEtableringsån 1969.\n\nKOCK, AB JOH\n\nPnr 23101\n\nTrelleborg, Box 67. Osterg 54. Tel\n0410-153 40. Bankgiro 66-5907.\nPostgiro 142750. Tga Kockab\nVerksamhet: Trävaror, byggvaror,\nfärdig betong\nAktiekapital: 566 000\nVerkst dir: Hermod Nordenhök\nEtableringsår: 1925.\n\nALINGSÅS KARAMELL AB\n\nPnr 44101\n\nAlingsås 1, Box 85. Nolhagag.\nTel 0322-15925. Bankgiro\n889-7373. Postgiro 280917-6\nVerksamhet: Tillverkar\nkarameller o klubbor\nAntal anställda: 20\nÅrsomsättning: 3 500 00\nAktiekapital: 90 000\nVerkst dir: Sven Peterson\nFörsäljn-chef: Bertil Bernersjö\nExpeditionschef: Hermann Imhof\nEtableringsår: 1952\nOmbildat till aktiebolag 1958.\n\nALINGSÅS KONFEKTIONS AB\n\nPnr 44101\n\nAlingsås 1, Box 79. N Strömg 48.\nTel 0322-10102, 112 63. Bankgiro\n889-6839. Postgiro 83430-9. Tga\nAkab\n\nVerksamhet: Tillverkar\nherrkostymer, damdräkter o uniformer\nAntal anställda: 25\nÅrsomsättning: 800000\nAktiekapital: 112000\nVerkst dir: Hans Belfrage\nEtableringsår: 1923.\n\nNP-TRYCK AB\n\nPnr 25005\n\nHelsingborg 5, Box 5016.\nHäst-hagsv 18. Tel 042-14 44 50.\nBankgiro 438-0614. Postgiro 268037-9\nVeiksamhet: Offsettryck av alla\nslag samt boktryck i mindre skala\nAntal anstäUda: 25\nÅrsomsättning: 3 300000\nAktiekapital: 60 000\nVeikst dir: Gunnar Paulsson\nEtableringsår. 1958.\n\nVÄXJÖ BYGGKONSULT AB\n\nPnr 35231\n\nVäxjö, Klosterg 13. Tel\n0470-215 00. 21501. Bankgiro 153-5681.\nPostgiro 665696-1\n\nVerksamhet: Råd o information inom\nhusbyggnadsfacket. Projektering\nAntal anställda: 6\nÅrsomsättning: 450 000\nAktiekapital: 20 000\nVerkst dir Ing Thure Olovsson\nEtableringsår: 1964.\n\nHYLTE BYGGBO, AB\n\nPnr 310 80\n\nHyltebmk, N Industrig 29. Box 77.\nTel 0345-100 83, 108 30. Bankgiro\n434-4073. Postgiro 94880-2\nVerksamhet: Säljer byggnads- o\ngolvmaterial, utför golvläggning\nAntal anställda: 30\nÅrsomsättning: 2000 000\nAktiekapital: 100000\nVerkst dir: Byggmäst Viktor\nJosefsson\n\nEtableringsår: 1928.\n\nSVENSKA DETRA AB\n\nPnr 20313\n\nMalmö 4, Box 4179. S Tullg 4 A.\nTel 040-363 70. Bankgiro 140-3146.\nPostgiro 531883-7\nVerksamhet: Säljer Aweso\ninredningssystem o Kralex byggsystem\nVarunamn: Aweso, Kralex\nAktiekapital: 25 000\nVerkst dir: Agne Walhagen\nEtableringsår: 1966.\n\nORE\n\nAntal anställda: 26\nÅrsomsättning: 2 000 000\nAktiekapital: 30 000\nVerkst dir: Sten Olsson\nEtableringsår: 1940.",
    "structured": {
        "1": {
            "company_name": "PEHRSON & CO, AB",
            "pnr": "70104",
            "address": "Tackjärnsg 8. Box 235",
            "phone_number": "019-11 94 60",
            "bank_details": {
                "bankgiro": "815-7430",
                "postgiro": "5148-2"
            },
            "activity": "Detaljhandelskedja inom skobranschen",
            "employees": 145,
            "capital": 1500000,
            "key_personnel": [
                {
                    "name": "Harry Jonsson",
                    "position": "ordf"
                },
                {
                    "name": "Torsten Berglund sr",
                    "position": "Verkst dir"
                }
            ],
            "establishment_year": 1901
        },
        "2": {
            "company_name": "PERSSON KB, BYGGNADS",
            "pnr": "83100",
            "address": "Regementsg 17",
            "phone_number": "063-204 50",
            "bank_details": {
                "bankgiro": "777-8707",
                "postgiro": "467347-1"
            },
            "activity": "Uppför bostads-, affärs- o industribyggnader etc",
            "employees": 80,
            "annual_turnover": 8000000,
            "key_personnel": [
                {
                    "name": "Byggmäst Joel Persson",
                    "position": "Chef"
                }
            ],
            "establishment_year": 1953
        },
        "3": {
            "company_name": "VÄS",
            "activity": "spännen, klädhängare, industridetaljer, lönpressning",
            "employees": 11,
            "annual_turnover": "1000000",
            "capital": 50000,
            "key_personnel": [
                {
                    "name": "Erik Pettersson",
                    "position": "Verkst dir"
                }
            ],
            "establishment_year": 1948
        },
        "4": {
            "company_name": "VÄSTERBOTTENS FOLK-BLAD, TRYCKERI AB",
            "pnr": "902 47",
            "address": "Rådhusesplanaden 4",
            "phone_number": "090-1185 50",
            "bank_details": {
                "bankgiro": "983-3104",
                "postgiro": "23053-2"
            },
            "activity": "Tidnings- o civiltryckeri",
            "employees": null,
            "capital": 343300,
            "key_personnel": [
                {
                    "name": "Clas Hanell",
                    "position": "Verkst dir"
                }
            ],
            "establishment_year": 1917
        },
        "5": {
            "company_name": "VÄSTERBOTTENS SKOGSÄGAREFORENING EK FÖRENING",
            "pnr": "93101",
            "address": "Box 133",
            "phone_number": "0910-144 25",
            "bank_details": {
                "bankgiro": "203-9212",
                "postgiro": "61811-6"
            },
            "activity": "Köper o säljer rundvirke, stolpar o specialsortiment.",
            "employees": 375,
            "annual_turnover": 51000000,
            "capital": 10875707,
            "key_personnel": [
                {
                    "name": "Abel Olsson",
                    "position": "Verkst dir"
                },
                {
                    "name": "Bernth Holmlund",
                    "position": "Disp"
                }
            ],
            "establishment_year": 1933
        },
        "6": {
            "company_name": "VÄSTERBOTTENS KURIREN5 AB",
            "pnr": "90102",
            "address": "Rådhusesplanaden 10",
            "phone_number": "090-11 86 00",
            "bank_details": {
                "bankgiro": "201-4439",
                "postgiro": "62017-9"
            },
            "activity": "Utger Västerbottens-Kuriren sex dagar i veckan.",
            "employees": 145,
            "annual_turnover": 12800000,
            "capital": 200000,
            "key_personnel": [
                {
                    "name": "Sven Tollin",
                    "position": "Verkst dir"
                },
                {
                    "name": "Matts Balgård",
                    "position": "Chefred"
                },
                {
                    "name": "Yngve Ybrandt",
                    "position": "Kamrer"
                },
                {
                    "name": "Hilding Rothelius",
                    "position": "Annonschef"
                }
            ],
            "establishment_year": 1900
        },
        "7": {
            "company_name": "VÄSTERVIKS FISK FÖRSÄLJ-NINGSFORENING UPA",
            "pnr": "593 00",
            "address": "Barlastudden",
            "phone_number": "0490-130 70",
            "bank_details": {
                "bankgiro": "66-7120",
                "postgiro": "279219-0"
            },
            "activity": "Säljer fisk engros. Fiskredskaps affär",
            "employees": 30,
            "annual_turnover": 6000000,
            "key_personnel": [
                {
                    "name": "Erie Källgren",
                    "position": "ordf"
                },
                {
                    "name": "Disp Gustaf Lannér",
                    "position": "Chef"
                }
            ],
            "establishment_year": 1936
        },
        "8": {
            "company_name": "TRELLEBORGPLAST, AB",
            "pnr": "34100",
            "address": "Box 149",
            "phone_number": "0372-125 20",
            "bank_details": {
                "bankgiro": "640-6409",
                "postgiro": "438376-6"
            },
            "activity": "Tillverkar produkter av termoplast o armerad plast.",
            "employees": 550,
            "annual_turnover": 40000000,
            "capital": 10000000,
            "key_personnel": [
                {
                    "name": "Göran Hellner",
                    "position": "Verkst dir"
                },
                {
                    "name": "Dir Yngve .Askblad",
                    "position": "Försäljn-chef"
                }
            ],
            "establishment_year": 1956
        },
        "9": {
            "company_name": "TREMIX AB",
            "pnr": "13101",
            "address": "Becksjudarv 37. Box 84",
            "phone_number": "08-7162745",
            "bank_details": {
                "bankgiro": "746-0124",
                "postgiro": "570710-4"
            },
            "activity": "Vibratorer, vibrerings-o jordkomprimeringsmaskiner, betonggolvläggningsmaskiner.",
            "employees": 90,
            "annual_turnover": 11000000,
            "capital": 100000,
            "key_personnel": [
                {
                    "name": "E Wrethagen",
                    "position": "Verkst dir"
                }
            ],
            "establishment_year": 1960
        },
        "10": {
            "company_name": "TRENSUMS MASKININDUSTRI, AB",
            "pnr": "290 73",
            "address": null,
            "phone_number": "0454-613 00",
            "bank_details": {
                "bankgiro": "656-5089",
                "postgiro": "109790-6"
            },
            "activity": "Tillverkar kyl- o fryselement",
            "employees": 15,
            "annual_turnover": 2000000,
            "capital": 30000,
            "key_personnel": [
                {
                    "name": "Pabr Ake Knutsson",
                    "position": "ordf"
                },
                {
                    "name": "Osten Haraldsson",
                    "position": "fabr"
                },
                {
                    "name": "Kjell Bengtsson",
                    "position": "Verkst dir"
                }
            ],
            "establishment_year": 1954
        },
        "11": {
            "company_name": "TRETORN, HELSINGBORGS GUMMI-FABRIKS AB",
            "pnr": "25101",
            "address": "Fack",
            "phone_number": "042-12 61 00",
            "bank_details": {
                "bankgiro": "653-0216",
                "postgiro": "14333-9"
            },
            "activity": "Tillverkar gummistövlar, ytterskor, galoscher, textilskor, badskor, lek- o sportbollar, tennisbollar, tennisrackets, reflexmaterial samt industriplast.",
            "employees": 2700,
            "annual_turnover": 149500000,
            "capital": 33276800,
            "key_personnel": [
                {
                    "name": "Ake Ståhlbrandt",
                    "position": "Verkst dir o koncernchef"
                },
                {
                    "name": "Börje Swanstein",
                    "position": "Plats- o produktionschef"
                },
                {
                    "name": "Bertil Andersson",
                    "position": "Ekonomichef"
                },
                {
                    "name": "Folke Lundgren",
                    "position": "Marknadschef"
                }
            ],
            "establishment_year": 1891
        },
        "12": {
            "company_name": "TRETORN DATA CENTER AB",
            "pnr": "251 01",
            "address": "Fack. Rönnowsg 10",
            "phone_number": "042-14 44 40",
            "bank_details": {
                "bankgiro": "410-2653",
                "postgiro": "396820-3"
            },
            "activity": "Servicebyrå inom företrädesvis det administrativa området med en stor mängd standardsystem för olika branscher o rutiner.",
            "employees": 43,
            "annual_turnover": 4000000,
            "capital": 100000,
            "key_personnel": [
                {
                    "name": "Bo C: son Lindberg",
                    "position": "Verkst dir"
                },
                {
                    "name": "Leif Fogelberg",
                    "position": "Marknadschef"
                }
            ],
            "establishment_year": 1969
        },
        "13": {
            "company_name": "KOCK, AB JOH",
            "pnr": "23101",
            "address": "Osterg 54",
            "phone_number": "0410-153 40",
            "bank_details": {
                "bankgiro": "66-5907",
                "postgiro": "142750"
            },
            "activity": "Trävaror, byggvaror, färdig betong",
            "capital": 566000,
            "key_personnel": [
                {
                    "name": "Hermod Nordenhök",
                    "position": "Verkst dir"
                }
            ],
            "establishment_year": 1925
        },
        "14": {
            "company_name": "ALINGSÅS KARAMELL AB",
            "pnr": "44101",
            "address": "Nolhagag",
            "phone_number": "0322-15925",
            "bank_details": {
                "bankgiro": "889-7373",
                "postgiro": "280917-6"
            },
            "activity": "Tillverkar karameller o klubbor",
            "employees": 20,
            "annual_turnover": 3500000,
            "capital": 90000,
            "key_personnel": [
                {
                    "name": "Sven Peterson",
                    "position": "Verkst dir"
                },
                {
                    "name": "Bertil Bernersjö",
                    "position": "Försäljn-chef"
                },
                {
                    "name": "Hermann Imhof",
                    "position": "Expeditionschef"
                }
            ],
            "establishment_year": 1952
        },
        "15": {
            "company_name": "ALINGSÅS KONFEKTIONS AB",
            "pnr": "44101",
            "address": "N Strömg 48",
            "phone_number": "0322-10102, 112 63",
            "bank_details": {
                "bankgiro": "889-6839",
                "postgiro": "83430-9"
            },
            "activity": "Tillverkar herrkostymer, damdräkter o uniformer",
            "employees": 25,
            "annual_turnover": 800000,
            "capital": 112000,
            "key_personnel": [
                {
                    "name": "Hans Belfrage",
                    "position": "Verkst dir"
                }
            ],
            "establishment_year": 1923
        },
        "16": {
            "company_name": "NP-TRYCK AB",
            "pnr": "25005",
            "address": "Hästhagsv 18",
            "phone_number": "042-14 44 50",
            "bank_details": {
                "bankgiro": "438-0614",
                "postgiro": "268037-9"
            },
            "activity": "Offsettryck av alla slag samt boktryck i mindre skala",
            "employees": 25,
            "annual_turnover": 3300000,
            "capital": 60000,
            "key_personnel": [
                {
                    "name": "Gunnar Paulsson",
                    "position": "Verkst dir"
                }
            ],
            "establishment_year": 1958
        },
        "17": {
            "company_name": "VÄXJÖ BYGGKONSULT AB",
            "pnr": "35231",
            "address": "Klosterg 13",
            "phone_number": "0470-215 00, 21501",
            "bank_details": {
                "bankgiro": "153-5681",
                "postgiro": "665696-1"
            },
            "activity": "Råd o information inom husbyggnadsfacket. Projektering",
            "employees": 6,
            "annual_turnover": 450000,
            "capital": 20000,
            "key_personnel": [
                {
                    "name": "Ing Thure Olovsson",
                    "position": "Verkst dir"
                }
            ],
            "establishment_year": 1964
        },
        "18": {
            "company_name": "HYLTE BYGGBO, AB",
            "pnr": "310 80",
            "address": "N Industrig 29. Box 77",
            "phone_number": "0345-100 83, 108 30",
            "bank_details": {
                "bankgiro": "434-4073",
                "postgiro": "94880-2"
            },
            "activity": "Säljer byggnads- o golvmaterial, utför golvläggning",
            "employees": 30,
            "annual_turnover": 2000000,
            "capital": 100000,
            "key_personnel": [
                {
                    "name": "Byggmäst Viktor Josefsson",
                    "position": "Verkst dir"
                }
            ],
            "establishment_year": 1928
        },
        "19": {
            "company_name": "SVENSKA DETRA AB",
            "pnr": "20313",
            "address": "S Tullg 4 A",
            "phone_number": "040-363 70",
            "bank_details": {
                "bankgiro": "140-3146",
                "postgiro": "531883-7"
            },
            "activity": "Säljer Aweso inredningssystem o Kralex byggsystem",
            "employees": 26,
            "annual_turnover": 2000000,
            "capital": 30000,
            "key_personnel": [
                {
                    "name": "Agne Walhagen",
                    "position": "Verkst dir"
                }
            ],
            "establishment_year": 1966
        }
    }
}