{
    "original": "MARINTILLBEHUR\n\nPnr 400 62\n\nGöteborg 29, Persg 11. Box 29011.\nTel 031-15 49 24, 15 49 23.\nBankgiro 508-8943. Postgiro 526920-4.\nTga Fundahna\n\nVerksamhet: Oljefilter,\nviskosimet-rar, genomströmningsmätare,\ndieselmotorer\n\nÅrsomsättning: 200000\nÄgare o chef: Arne Fundahn\nEtableringsår: 1958.\n\nMARK &amp; CO AB,\nAUG JOHANSSON\n\nPnr 40121\n\nGöteborg 1, Avägen 6. Box 114.\nTel 031-19 25 60. Bankgiro 50-9635.\nPostgiro 42429. Tga Mark\nVerksamhet: Garn o tapisseri\nAvdelningskontor: Malmö C, Per\nWeijersg 6 A. Box 4070, Malmö 4.\nTel 040-120113\n\nStockholm C,Stora Nyg 2IB. Box\n2014, Sthlm 2. Tel 08-10 06 78\nKöpenhamn N. Marks Garner AS,\nMimersgade 56. Tel TAGA 8695,\n8696\n\nAntal anställda: 170\nÅrsomsättning: 30 000 000\nVerkst dir: Birger Norinder\nEtableringsår: 1879\nDotterbolag till Gustaf Werner AB.\n\nMARKS JACQUARDVÄVERI, AB\n\nPnr 510 13\n\nBjörketorp, Box 70. Tel\n0320-60160. Bankgiro 435-6234.\nPostgiro 22655-5\n\nVerksamhet: Tillverkar\ninredningstyger\n\nAntal anställda: 95\nÅrsomsättning: 8 000 000\nAktiekapital: 440 000\nVerkst dir: Nils Gröndahl\nEtableringsår: 1926.\n\nHOLMKVIST &amp; LARSSON\n\nPnr 414 52\n\nGöteborg, Ostindieg 20. Tel\n031-1403 33, 12 50 30. Bankgiro\n420-3386. Postgiro 45524-6. Tga Olrob\nVerksamhet: Säljer gradsaxar,\nrundsaxar, sick- o bärtelmaskiner,\nkilspårmaskiner, verktygsmaskiner,\nverktyg, slipmaterial o\nverkstadsförnödenheter. Tillverkar\ngradsaxar. rundsaxar, sick- o bärtelmar\nskiner\n\nVarunamn: HL\nAntal anställda: 8\nÅrsomsättning: 1500 000\nChef: Ing B Norrhede\nEtableringsår 1933.\n\nHOLMQVISTS BOKTRYCKERI\nAB, C R\n\nPnr 403 14\n\nGöteborg 2, Magasinsg 3. Box 2228.\nTel031-17 13 10. Bankgiro 200-8472.\nPostgiro 239390-8\n\nVerksamhet: Kataloger, reklamtryck\n\no blanketter\n\nAntal anställda: 31\n\nAktiekapital: 5 000\n\nVetkst dir: Boktr E Zetterquist\n\nEtableringsår: 1886.\n\nHOLMQVISTS REVISIONS.\nBYRA, FILIP\n\nPnr 41124\n\nGöteborg, Vasag 5 C. Tel\n031-1137 89, 1137 90\nVerksamhet: Revisionsbyrå\nÄgare o chef: Aukt revisor\nThor-wald Sundgren.\n\nHOLMQVIST PATENTBYRÄ\nAB, LARS\n\nPnr 203 14\n\nMalmö 4, Box 4289. S Tullg 3. Tel\n040-705 40. Bankgiro 874-8592.\nPostgiro 4384 68-1\nVerksamhet: Patentbyrå\nAntal anställda: 21\nÅrsomsättning: 1900 000\nAktiekapital: 30 000\nVerkst dir Jur lic, fil mag Lars\nHolmqvist\n\nEtableringssår: 1963.\n\nCABANCO TRADING AB\n\nPnr 114 25\n\nStockholm, Rådmansg 22. Tel\n08-107749. Bankgiro 605-8895.\nPostgiro 159950-5. Tga Cabancotrade.\nTelex 1518 CABANCO S\nVerksamhet: Agenturaffärer i\nträvaror, pumpar, tekn produkter\nAktiekapital: 100 000\nVerkst dir: Ake Fredrikson\nEtableringsår: 1969.\n\nG AMI MEKANISKA VERKSTAD\n\nPnr 417 18\n\nGöteborg, Knapeg 6. Tel 031-\n\n23 36 51\n\nVerksamhet: Säljer\nsågskärpnings-maskin Gami 102, transportörer\nÄgare o chef: Hugo Gustafsson\nEtableringsår: 1943.\n\nGAMLA DRAGARELAGET\nUPA, FÖRENINGEN\n\nPnr 252 28\n\nHelsingborg, Sydhamnsg. Tel\n042-13 90 60. Bankgiro 65-2868.\nPostgiro 85261\n\nVerksamhet: Transporter,\nflyttningar o magasinering\nAntal anställda: 129\nÅrsomsättning: 8 250 000\nEtableringsår: 1735\nÄgare: AB Godstrafik &amp;\nBilspedi-tion, Göteborg.\n\nGAMLEBY GJUTERI, AB\n\nPnr 594 00\n\nGamleby. Tel 0493-100 46\nVerksamhet: Tillverkar\ntackjärns-gjutgods till 1 500 kg styck vikt\nAntal anställda: 18\nÅrsomsättning: 1 300 000\nAktiekapital: 10 500\nVerkst dir: Gjutmäst Thore\nCarlsson\n\nEtableringsår: 1950\n\nOmbildat till aktiebolag 1952.\n\nGAMLESTADENS AB\n\nPnr 402 52\n\nGöteborg 13, Box 13070. Tel\n031-25 04 00. Bankgiro 514-3474.\nPostgiro 8820-3. Tga Gamlestaden.\nTelex 20944 ASKEN S\nVerksamhet: Bomullsindustri,\nnon-woven-, nätfabrik samt mek\nverkstad. Tillverkar modetyger,\nhemtextilier, fisknät, non-wovens o mek\ntransportanordningar\nAntal anställda: 1000\nÅrsomsättning: 70 000 000\nAktiekapital: 24 000 000\nVerkst dir: Bengt Karlson\nEtableringsår: 1865.\n\nGAMMA,\nMASKINAKTIEBOLAGET\n\nPnr 104 35\n\nStockholm 23, Ynglingag 18. Box\n23034. Tel 08-3 3 9 6 39 , 33 3 2 41.\nPostgiro 694150. Telex 19991.\nTga Machinetool\n\nVerksamhet: Säljer nya o begagnade\nverktygsmaskiner o tillbehör\nÅrsomsättning: 1000 000\nAktiekapital: 50 000\nEtableringsår: 1969.\n\nGAMMELSTADS HANDVÄVERI\nAB\n\nPnr 95010\n\nGammelstad, Box 25. Tel\n0920-548 20. Bankgiro 75-2810.\nPostgiro 487494\n\nVerksamhet: Konsthantverk.\nHandvävda mattor o bildvävnader i rö\nlakanteknik. Monumentala vävnader\nAntal anställda: 12\nÅrsomsättning: 700 000\nAktiekapital: 75 000\nVerkst din Anders Wärnegàrd\nEtableringsår: 1966.\n\nJPN\n\nJPN:s FABRIKS AB\n\nPnr 570 80\n\nVirserum, Box 3. Tel 0495-31010.\nBankgiro 10-6392. Postgiro 269522\nVerksamhet: Tillverkar skyltdockor.\nMek verkstad för metallinredningar\nAntal anställda: 16\nÅrsomsättning: 800 000\nAktiekapital: 5 000\nVerkst din Jörgen P Nielsén\nEtableringsår: 1957.\n\nBOHLIN &amp; LÖFGREN AB\n\nPnr 40120\n\nGöteborg 1, Box 31. Pontus\nWik-nersg 6. Tel 031-20 00 45.\nBankgiro 50-0759. Postgiro 47970. Tga\nBoselo. Telex 20747\nVerksamhet: Tillverkning o\nförsäljning av eldfast o\nisoleringsmaterial samt gjuteriförnödenheter.\nEntreprenader\n\nFabrik o lager: Lidköping,\nSocker-bruksg. Tel 0510-253 41\nAntal anställda: 35\nAktiekapital: 500 000\nVerkst dir: Folke Bohlin\nEtableringsår: 1943\nOmbildat till aktiebolag 1955.\n\nBOHLINS MEKANISKA\nVERKSTAD AB\n\nPnr 149 00\n\nNynäshamn, Sandtorpsv 14. Tel\n0752-12077. Bankgiro 620-0059.\nPostgiro 363497-9\nVerksamhet: Tillverkar\nautomatdetaljer o kapar tunnväggiga rör\ni specialmaskiner\nAntal anställda: 10\nAktiekapital: 75 000\nVerkst dir: Arne Bohlin\nEtableringsår: 1947\nOmbildat till aktiebolag 1964.\n\nBOHLIN &amp; NILSSON AB\n\nPnr 100 73\n\nStockholm 44, Box 44064.\nOrm-bergsv 5. Tel 08-45 27 60. Tga\nNibolproducts\n\nVerksamhet: Tillverkar o säljer\nelektr installationsmateriel\nAntal anställda: 20\nChef: Uno Nilsson\nEtableringsår: 1948.\n\nJUST AB, E W\n\nPnr 500 02\n\nBorås 2. Box 22064. Getängsv\n22-26. Tel 033-11 71 00. Bankgiro\n531-3002. Postgiro 6507-8.\nTga Just. Telex 36010 JUST S\nVerksamhet: Färgning, blekning o\nappretering av trikå o charmeuse,\nberedning av plysch o nylonvelour,\nprägling o kalandrering, laminering\nav textilmaterial med skumplast,\nbondning samt plissering.\nSpecialitet: Beredning av\nsyntetfibervaror, laminering o bondning\nAntal anställda: 288\nÅrsomsättning: 15 000 000\nAktiekapital: 900 000\nVerkst dir: Ernst Just\nEtableringsår: 1898.\n\nJUSTITIA, AB SVENSK\nHANDELSTIDNING\n\nPnr 103 23\n\nStockholm 16, Drottningg 6. Box\n16141. Tel 08-23 05 60. Bankgiro\n56-8144. Postgiro 4686-2. Tga\nJustitia\n\nVerksamhet: Veckovisa\nsammandrag av offentliga\nbetalningsanmärkningar såsom protesterade\nväxlar, betalningsförelägganden,\nlagsökningsutslag,\nskatteresolutioner, konkurser, utmätningar o\ntredsk odomar. Företagsinteckningar,\nlagfarter o tomträtter, nyregistrerade\naktiebolag, kapitaländringar m m\nAntal anställda: 20\nÅrsomsättning: 2 260 000\nAktiekapital: 160 000\nStyrelse: Adv Bure Malmström (ordf),\nnotarie Claes Essén, dir Sven\nCarlberg, civiling Gunnar Mannerstråle\nVerkst dir: Bertil Rietz\nEtableringsår: 1890.\n\nJUSTITIAS INKASSO- &amp;\nJURIDISKA BYRA AB\n\nPnr 104 60\n\nStockholm 20, Virkesv7. Box 20079.\nTel 08-44 09 20. Bankgiro 73-0412.\nPostgiro 1241-9. Tga Jus\nVerksamhet: Inkasso- o juridisk\nbyrå\n\nAntal anställda: 60\nAktiekapital: 150 000\nVerkst dir: Lars Lindén\nEtableringsår: 1924.\n\nWELLA AB\n\nPnr 121 20\n\nJohanneshov 1, Huddingev 103 B.\nFack. Tel 08-59 01 10. Bankgiro\n74-6005. Postgiro 150232. Tga\nSveawella, Stockholm\nVerksamhet: Grossist i\nfrisörbranschen\nAntal anställda: 95\nÅrsomsättning: 20 000 000\nAktiekapital: 150 000\nVerkst dir: Per Nilson\nEtableringsår: 1932.\n\nSÄTTRABY VERKSTADS AB\n\nPnr 760 31\n\nEdsbro. Box 420. Tel 0175-630 27,\n630 66. Bankgiro 805-8604.\nPostgiro 356444-0\n\nVerksamhet: Mekaniska\nlego-arbeten. Specialitet: svetsning o\nplåtarbeten i tunnplåt\n\nAntal anställda: 8\nÅrsomsättning: 400 000\nChef: Stig Björklund\nEtableringsår: 1950.\n\nSÄVEDALENS\nPAPPERSBRUK AB\n\nPnr 415 05\n\nGöteborg, von Utfallsg. Tel\n031-2677 01, 26 77 02. Bankgiro\n617-1977\n\nVerksamhet: Tillverkar hylspapp\nfrån 150-400 gr\nAntal anställda: 15\nÅrsomsättning: 2 000 000\nAktiekapital: 25 000\nChefer: Disp Albert Hall,\nfabr-chef Gösta Järnfors\nPlatschef: Pappersmäst Filip\nSvensson\n\nEtableringsår: 1970\n\nÄges av Svensk Pappersindustri\n\nJärnfors &amp; Hall AB, Sandared.\n\nSÄVSJO BLECKVARUFABRIK\n\nPnr 576 00\n\nSävsjö, Odeng 23. Box 120. Tel\n0382-100 26, 101 16\nVerksamhet: Engros-försäljning av\nhushållsartiklar, redskap, verktyg,\nsportartiklar mm\nAntal anställda: 15\nÅrsomsättning: 3 500 000\nChef: Ake Green\nEtableringsår: 1919.\n\nELECTRO-ENOC, AB\n\nPnr 330 20\n\nAnders torp, Postl 1107. Tel\n0371-150 42. Bankgiro 48-8095. Postgiro\n293502\n\nVerksamhet: Tillverkar kapslad\ninstallationsmaterial\nAntal anställda: 6\nÅrsomsättning: 800 000\nAktiekapital: 10 000\nChef: Pabr Alvar Enocson\nEtableringsår: 1957.",
    "structured": {
        "1": {
            "company_name": "MARINTILLBEHUR",
            "activity": "Oljefilter, viskosimet-rar, genomströmningsmätare, dieselmotorer",
            "establishment_year": 1958,
            "employees": null,
            "annual_turnover": 200000,
            "annual_production_value": null,
            "capital": null,
            "key_personnel": [
                {
                    "name": "Arne Fundahn",
                    "position": "Ägare o chef"
                }
            ]
        },
        "2": {
            "company_name": "MARK & CO AB",
            "activity": "Garn o tapisseri",
            "establishment_year": 1879,
            "employees": 170,
            "annual_turnover": 30000000,
            "annual_production_value": null,
            "capital": null,
            "key_personnel": [
                {
                    "name": "Birger Norinder",
                    "position": "Verkst dir"
                }
            ]
        },
        "3": {
            "company_name": "MARKS JACQUARDVÄVERI, AB",
            "activity": "Tillverkar inredningstyger",
            "establishment_year": 1926,
            "employees": 95,
            "annual_turnover": 8000000,
            "annual_production_value": null,
            "capital": 440000,
            "key_personnel": [
                {
                    "name": "Nils Gröndahl",
                    "position": "Verkst dir"
                }
            ]
        },
        "4": {
            "company_name": "HOLMKVIST & LARSSON",
            "activity": "Säljer gradsaxar, rundsaxar, sick- o bärtelmaskiner, kilspårmaskiner, verktygsmaskiner, verktyg, slipmaterial o verkstadsförnödenheter. Tillverkar gradsaxar. rundsaxar, sick- o bärtelmaskiner",
            "establishment_year": 1933,
            "employees": 8,
            "annual_turnover": 1500000,
            "annual_production_value": null,
            "capital": null,
            "key_personnel": [
                {
                    "name": "Ing B Norrhede",
                    "position": "Chef"
                }
            ]
        },
        "5": {
            "company_name": "HOLMQVISTS BOKTRYCKERI AB, C R",
            "activity": "Kataloger, reklamtryck o blanketter",
            "establishment_year": 1886,
            "employees": 31,
            "annual_turnover": null,
            "annual_production_value": null,
            "capital": 5000,
            "key_personnel": [
                {
                    "name": "Boktr E Zetterquist",
                    "position": "Vetkst dir"
                }
            ]
        },
        "6": {
            "company_name": "HOLMQVISTS REVISIONS. BYRA, FILIP",
            "activity": "Revisionsbyrå",
            "establishment_year": null,
            "employees": null,
            "annual_turnover": null,
            "annual_production_value": null,
            "capital": null,
            "key_personnel": [
                {
                    "name": "Aukt revisor Thor-wald Sundgren",
                    "position": "Ägare o chef"
                }
            ]
        },
        "7": {
            "company_name": "HOLMQVIST PATENTBYRÄ AB, LARS",
            "activity": "Patentbyrå",
            "establishment_year": 1963,
            "employees": 21,
            "annual_turnover": 1900000,
            "annual_production_value": null,
            "capital": 30000,
            "key_personnel": [
                {
                    "name": "Jur lic, fil mag Lars Holmqvist",
                    "position": "Verkst dir"
                }
            ]
        },
        "8": {
            "company_name": "CABANCO TRADING AB",
            "activity": "Agenturaffärer i trävaror, pumpar, tekn produkter",
            "establishment_year": 1969,
            "employees": null,
            "annual_turnover": null,
            "annual_production_value": null,
            "capital": 100000,
            "key_personnel": [
                {
                    "name": "Ake Fredrikson",
                    "position": "Verkst dir"
                }
            ]
        },
        "9": {
            "company_name": "G AMI MEKANISKA VERKSTAD",
            "activity": "Säljer sågskärpnings-maskin Gami 102, transportörer",
            "establishment_year": 1943,
            "employees": null,
            "annual_turnover": null,
            "annual_production_value": null,
            "capital": null,
            "key_personnel": [
                {
                    "name": "Hugo Gustafsson",
                    "position": "Ägare o chef"
                }
            ]
        },
        "10": {
            "company_name": "GAMLA DRAGARELAGET UPA, FÖRENINGEN",
            "activity": "Transporter, flyttningar o magasinering",
            "establishment_year": 1735,
            "employees": 129,
            "annual_turnover": 8250000,
            "annual_production_value": null,
            "capital": null,
            "key_personnel": [
                {
                    "name": "AB Godstrafik & Bilspeditions, Göteborg",
                    "position": "Ägare"
                }
            ]
        },
        "11": {
            "company_name": "GAMLEBY GJUTERI, AB",
            "activity": "Tillverkar tackjärnsgjutgods till 1 500 kg styck vikt",
            "establishment_year": 1950,
            "employees": 18,
            "annual_turnover": 1300000,
            "annual_production_value": null,
            "capital": 10500,
            "key_personnel": [
                {
                    "name": "Gjutmäst Thore Carlsson",
                    "position": "Verkst dir"
                }
            ]
        },
        "12": {
            "company_name": "GAMLESTADENS AB",
            "activity": "Bomullsindustri, non-woven-, nätfabrik samt mek verkstad\ntillverkar modetyger, hemtextilier, fisknät, non-wovens o mek transportanordningar",
            "establishment_year": 1865,
            "employees": 1000,
            "annual_turnover": 70000000,
            "annual_production_value": null,
            "capital": 24000000,
            "key_personnel": [
                {
                    "name": "Bengt Karlson",
                    "position": "Verkst dir"
                }
            ]
        },
        "13": {
            "company_name": "GAMMA, MASKINAKTIEBOLAGET",
            "activity": "Säljer nya o begagnade verktygsmaskiner o tillbehör",
            "establishment_year": 1969,
            "employees": null,
            "annual_turnover": 1000000,
            "annual_production_value": null,
            "capital": 50000,
            "key_personnel": [
                {
                    "name": null,
                    "position": null
                }
            ]
        },
        "14": {
            "company_name": "GAMMELSTADS HANDVÄVERI AB",
            "activity": "Konsthantverk. Handvävda mattor o bildvävnader i rö lakanteknik. Monumentala vävnader",
            "establishment_year": 1966,
            "employees": 12,
            "annual_turnover": 700000,
            "annual_production_value": null,
            "capital": 75000,
            "key_personnel": [
                {
                    "name": "Anders Wärnegàrd",
                    "position": "Verkst dir"
                }
            ]
        },
        "15": {
            "company_name": "JPN:s FABRIKS AB",
            "activity": "Tillverkar skyltdockor. Mek verkstad för metallinredningar",
            "establishment_year": 1957,
            "employees": 16,
            "annual_turnover": 800000,
            "annual_production_value": null,
            "capital": 5000,
            "key_personnel": [
                {
                    "name": "Jörgen P Nielsén",
                    "position": "Verkst dir"
                }
            ]
        },
        "16": {
            "company_name": "BOHLIN & LÖFGREN AB",
            "activity": "Tillverkning o försäljning av eldfast o\nisoleringsmaterial samt gjuteriförnödenheter.\nEntreprenader",
            "establishment_year": 1943,
            "employees": 35,
            "annual_turnover": null,
            "annual_production_value": null,
            "capital": 500000,
            "key_personnel": [
                {
                    "name": "Folke Bohlin",
                    "position": "Verkst dir"
                }
            ]
        },
        "17": {
            "company_name": "BOHLINS MEKANISKA VERKSTAD AB",
            "activity": "Tillverkar automatdetaljer o kapar tunnväggiga rör i specialmaskiner",
            "establishment_year": 1947,
            "employees": 10,
            "annual_turnover": null,
            "annual_production_value": null,
            "capital": 75000,
            "key_personnel": [
                {
                    "name": "Arne Bohlin",
                    "position": "Verkst dir"
                }
            ]
        },
        "18": {
            "company_name": "BOHLIN & NILSSON AB",
            "activity": "Tillverkar o säljer elektr installationsmateriel",
            "establishment_year": 1948,
            "employees": 20,
            "annual_turnover": null,
            "annual_production_value": null,
            "capital": null,
            "key_personnel": [
                {
                    "name": "Uno Nilsson",
                    "position": "Chef"
                }
            ]
        },
        "19": {
            "company_name": "JUST AB, E W",
            "activity": "Färgning, blekning o appretering av trikå o charmeuse, beredning av plysch o nylonvelour, prägling o kalandrering, laminering av textilmaterial med skumplast, bondning samt plissering. Specialitet: Beredning av syntetfibervaror, laminering o bondning",
            "establishment_year": 1898,
            "employees": 288,
            "annual_turnover": 15000000,
            "annual_production_value": null,
            "capital": 900000,
            "key_personnel": [
                {
                    "name": "Ernst Just",
                    "position": "Verkst dir"
                }
            ]
        },
        "20": {
            "company_name": "JUSTITIA, AB SVENSK HANDELSTIDNING",
            "activity": "Veckovisa sammandrag av offentliga betalningsanmärkningar såsom protesterade växlar, betalningsförelägganden, lagsökningsutslag, skatteresolutioner, konkurser, utmätningar o tredsk odomar. Företagsinteckningar, lagfarter o tomträtter, nyregistrerade aktiebolag, kapitaländringar m m",
            "establishment_year": 1890,
            "employees": 20,
            "annual_turnover": 2260000,
            "annual_production_value": null,
            "capital": 160000,
            "key_personnel": [
                {
                    "name": "Bertil Rietz",
                    "position": "Verkst dir"
                }
            ]
        },
        "21": {
            "company_name": "JUSTITIAS INKASSO- & JURIDISKA BYRA AB",
            "activity": "Inkasso- o juridisk byrå",
            "establishment_year": 1924,
            "employees": 60,
            "annual_turnover": null,
            "annual_production_value": null,
            "capital": 150000,
            "key_personnel": [
                {
                    "name": "Lars Lindén",
                    "position": "Verkst dir"
                }
            ]
        },
        "22": {
            "company_name": "WELLA AB",
            "activity": "Grossist i frisörbranschen",
            "establishment_year": 1932,
            "employees": 95,
            "annual_turnover": 20000000,
            "annual_production_value": null,
            "capital": 150000,
            "key_personnel": [
                {
                    "name": "Per Nilson",
                    "position": "Verkst dir"
                }
            ]
        },
        "23": {
            "company_name": "SÄTTRABY VERKSTADS AB",
            "activity": "Mekaniska lego-arbeten. Specialitet: svetsning o plåtarbeten i tunnplåt",
            "establishment_year": 1950,
            "employees": 8,
            "annual_turnover": 400000,
            "annual_production_value": null,
            "capital": null,
            "key_personnel": [
                {
                    "name": "Stig Björklund",
                    "position": "Chef"
                }
            ]
        },
        "24": {
            "company_name": "SÄVEDALENS PAPPERSBRUK AB",
            "activity": "Tillverkar hylspapp från 150-400 gr",
            "establishment_year": 1970,
            "employees": 15,
            "annual_turnover": 2000000,
            "annual_production_value": null,
            "capital": 25000,
            "key_personnel": [
                {
                    "name": "Disp Albert Hall, fabr-chef Gösta Järnfors",
                    "position": "Chefer"
                }
            ]
        },
        "25": {
            "company_name": "SÄVSJO BLECKVARUFABRIK",
            "activity": "Engros-försäljning av hushållsartiklar, redskap, verktyg, sportartiklar mm",
            "establishment_year": 1919,
            "employees": 15,
            "annual_turnover": 3500000,
            "annual_production_value": null,
            "capital": null,
            "key_personnel": [
                {
                    "name": "Ake Green",
                    "position": "Chef"
                }
            ]
        },
        "26": {
            "company_name": "ELECTRO-ENOC, AB",
            "activity": "Tillverkar kapslad installationsmaterial",
            "establishment_year": 1957,
            "employees": 6,
            "annual_turnover": 800000,
            "annual_production_value": null,
            "capital": 10000,
            "key_personnel": [
                {
                    "name": "Pabr Alvar Enocson",
                    "position": "Chef"
                }
            ]
        }
    }
}