{
    "original": "LJUNGBY EXPRESS AB\n\nPnr 34100\n\nLjungby, Långg. Tel 0372-135 85.\nBankgiro 147-3222. Postgiro\n512044-9\n\nVerksamhet: Godsterminal. Utför\ngodstransporter i fjärr- o\nlokaltrafik\n\nAntal anställda: 41\n\nÅrsomsättning: 4 000 000\n\nAktiekapital: 50 000\n\nDir:r: Olle Andersson, Sven-Erik\n\nAndersson\n\nEtableringsår: 1966.\n\nLJUNGBY METALLYT.\nFDRÄDLING\n\nPnr 341 00\n\nLjungby, Högarörsg. Tel\n0372-10101\n\nVeiksamhet: Utför ytbehandling,\nförnickling o förkromning\nChef: Stig Johansson\nEtableringsår: 1946.\n\nLJUNGBY MUBEL.\nINDUSTRI, AB\n\nPnr 34100\n\nLjungby, Box 113. Långg. Tel\n0372-807 20. Postgiro 22408-9\nVeiksamhet: Tillverkar\nbutiksinredningar\nAntal anställda: 38\nÅrsomsättning: 4 000 000\nAktiekapital: 198 000\nVerkst dir: Ove Andersson\n(Västerås)\nEtableringsår: 1931.\n\nANDRÉN AB, BROR\n\nPnr 661 00\n\nSäffle, Box 20. Billerudsg 26.\nTel 0533-12615. Bankgiro 11-4902.\nPostgiro 224 1 20. Tga Andrén.\n\nTelex 5335\n\nVerksamhet: Skeppsmäklare o\n\nspedition\n\nAntal anställda: 11\nAktiekapital: 35 000\nVerkst dir: Bror Ake Andrén\nEtableringsår: 1928.\n\nVER\n\nTga Jacobstege. Telex 19176\nVaksamhet: Agenturaffär i\nträvaror o trämassa\nAntal anställda: 9\nÅrsomsättning: 40 000 000\nAktiekapital: 50 000\nChef: Hugo The lin\nEtableringsàr: 1889.\n\nVERYWELL AB\n\nPnr 16117\n\nBromma 17, Box 17001. Alstensg\n16. Tel 08-268003 . 26 80 05.\nBankgiro 744-0415. Postgiro 255617-3.\nTga Verywell\n\nVerksamhet: Svetstillbehör,\nmotordelar mm\n\nAktiekapital: 40 000\n\nVerkst dir Civilekonom Jan Ak-\n\nselsson\n\nEtableringsån 1944\nNuvarande namn 1967.\n\nWESLIEN AB, LENNART\n\nPnr 601 02\n\nNorrköping 1, Box 70. Lindåkersg\n29. Tel 011-12 7854, 12 2617.\nBankgiro 349-1950. Postgiro\n86925-5\n\nVerksamhet: Partiförsäljning av\nkonfektyrer, tekn artiklar, tobak\nAntal anställda: 10\nÅrsomsättning: 7 500 000\nAktiekapital: 10 000\nVerkst dir: Lennart Weslien\nEtableringsàr: 1933.\n\nWESSAG, AB\n\nPnr 10053\n\nStockholm 37, Pack. Oregrundsg 15.\nTel 08-24 88 50. Bankgiro 160-9049.\nPostgiro 505010-9. Tga Weslind.\nTelex 10353\n\nVerksamhet: Eldfast material samt\nutrustningar för järn- o stålverk\nAktiekapital: 10 000\nVerkst dir: H B Drakenberg\nEtableringsàr: 1958.\n\nWESSELS, AB\n\nPnr 200 31\n\nMalmö 15, Jägersrov. Pack. Tel\n040-94 20 20. Bankgiro 260-4536.\nPostgiro 37733-3. Tga Wessels.\nTelex 32581\nVerksamhet: Varuhus\nAntal anställda: 710\nÅrsomsättning: 212 600 000\nAktiekapital: 8 000 000\nVerkst dir: Thorolf Hjort\nEtableringsàr: 1880.\n\nWESSEL &amp; CO AB\n\nPnr 104 25\n\nStockholm 30, Lindhage nsg 124.\nFack. Tel 08-52 02 00. Bankgiro\n167-8093. Postgiro 156660-3. Tga\nAbwesco\n\nVerksamhet: Strömställare m m\nVarunamn: Wesco\nAntal anställda: 65\nÅrsomsättning: 5 000 000\nAktiekapital: 100 000\nStyrelse: Adv Ivar Blanck (ordf),\ning Gunnar Wessel, dir Lennart\nWirström\n\nVerkst dir: Lennart Wirström\n\nEtableringsàr: 1939\nOmbildat till aktiebolag 1944.\nDotterbolag till Wessel &amp; Co A/S,\nSkårer, Norge.\n\nWESSI AB\n\nPnr 416 64\n\nGöteborg, Ranängsg 5-7. Tel\n031-190741, 19 18 92. Bankgiro\n848-4917. Postgiro 162417\nVerksamhet: Engrosfirma i glas,\nporslin, linne, papper, silver,\nrostfritt, möbler, maskiner o\nköksutensilier\n\nÄgare o chef: Ralph Glimnell\nEtableringsàr: 1934.\n\nVESSIGEBRO TRÄINDUSTRI,\nAB\n\nPnr 310 58\n\nVessigebro. Tel 0346-202 63.\nBankgiro 425-7523. Postgiro 372398-8\nVerksamhet: Sågade o hyvlade\nträvaror. Lådor o lådämnen\nAntal anställda: 17\nÅrsomsättning: 2 500 000\nAktiekapital: 60 000\nVerkst dir: Alvar Persson\nEtableringsàr: 1953.\n\nWESSTRUMS VERKTYGS.\nFABRIK, AB ALFR\n\nPnr 19107\n\nSollentuna 7, Fack. Tel\n08-714 00 50. Postgiro 10432-3. Tga\nWesstromverktyg\n\nVerksamhet: Spånavskiljande\nmaskinverktyg såsom brotschar,\nfrasar o hobbar\nAntal anställda: 65\nÅrsomsättning: 3 700 000\nAktiekapital: 436 800\nVerkst dir: Olle Wesström\nEtableringsàr: 1898.\n\nWESTAL EL-BELYSNING, AB\n\nPnr 560 23\n\nBankeryd, Fabriksv 5. Box 112.\nTel 036-771 90. Bankgiro 55-3811.\nPostgiro 322547. Tga Westal\nVerksamhet: Tillverkar o säljer\nelektrisk belysningsarmatur\nAntal anställda: 30\nÅrsomsättning: 3 000 000\nAktiekapital: 50 000\nVeikst dir: Fabr Holger Johansson\nEtableringsàr. 1961.\n\nWESTBORG AB, A L\n\nPnr 121 56\n\nJohanneshov, Vikstensv 61. Tel\n08-59 9196, 59 8801. Bankgiro\n89-6021. Postgiro 453410. Tga\nAlwe-pro, Stockholm\n\nVerksamhet: Säljer\nförpackningsmaterial för bagerier m m\nAntal anställda: 25\nÅrsomsättning: 2 500 000\nAktiekapital: 40 000\nVerkst dir: Arne L Westborg\nEtableringsàr: 1950.\n\nWESTCOAST.\nALAFORS-VERKEN AB\n\nPnr 440 42\n\nAlafors. Tel 0303-404 34\nVerksamhet: Tillverkar Westooast\nträimpregneringsolja o lasyrfärger\n\nSvensk distributör. Ragnar\nBergstedt AB, Göteborg\nKontrollant samt distributör\nutanför Sverige: Mobil Oil\nAntal anställda: 7\nÅrsomsättning: 2 500000\nVerkst dir Gunnar Jarland\nEtableringsån 1969.\n\nIGGESUNDS MASKIN AB\n\nPnr 825 00\n\nIggesund, Box 26. Tel 0650-208 70.\nBankgiro 192-1055. Postgiro\n215430-0\n\nVerksamhet: Flis- o\nspånblåsnings-system m m\nAntal anställda: 62\nÅrsomsättning: 4 200 000\nAktiekapital: 10 000\nVeikst dir: Gunnar Nilsson\nEtableringsår 1948.\n\nINGARPSTRÄVAROR AB\n\nPnr 575 00\n\nEksjö, Ingarp. Tel 0381-400 01,\n400 95. Bankgiro 266-4860.\nPostgiro 510220-7\n\nVerksamhet: Tillverkar sågade o\nhyvlade trävaror\nAntal anställda: 70\nÅrsomsättning: 8 000000\nAktiekapital: 100000\nVerkst dir: Arne Gerhardsson\nEtableringsår: 1946.\n\nSCANSTOCK AB\n\nPnr 302 45\n\nHalmstad, Kungsg 2. Tel\n035-100175. Tga Scanstock.\nTelex 38059 JACWOOD S\nVerksamhet: Inköp o försäljning av\nträvaror för engros o export\nChef: Dir Jacob Kjellerup\nFörsäljn-chef: Bruno Bergström\nAktiekapital: 75 000\nEtableringsår: 1964.\n\nRYTTAREN. AB\n\nPnr 560 42\n\nSandhem, Box 20. Tel 0515-60012,\n60108. Bankgiro 140-1520.\nPostgiro 80683-6. Tga Ryttaren\nVerksamhet: Tillverkar o säljer trär\null\n\nAntal anställda: 20\nÅrsomsättning: 2 000 000\nAktiekapital: 160 000\nVerkst dir: Hans Hartelius\nEtableringsår 1964.\n\nSKÅ\n\nVeiksamhet: Tillverkar\nkontorsmöbler, beslag, stativ o inredning\nför möbelindustrin, beslag för\nemballageindustrin, pallramsbeslag,\nlastpallar, pallramar\nAntal anställda: 12\nÅrsomsättning: 1 600 000\nAktiekapital: 50000\nVerkst dir: Berthold Blomqvist\nProd-chef: Ingvar Gärdebrand\nEtableringsår: 1965.\n\nSKULTUNA NYA\nMETALLFABRIKS AB\n\nPnr 730 50\n\nSkultuna, Sofieberg. Box 28. Tel\n021-704 00. Bankgiro 80-8767.\nPosb-giro 582550\n\nVerksamhet: Cisterner, tankar o\napparatur till kemisk tekniska\nindustrin, konstruktioner,\nargonsvets-ning, rörbockning, allt inom\nbranschen i metallerna koppar, mässing\no aluminium\nAntal anställda: 9\nÅrsomsättning: 600 000\nAktiekapital: 5 000\nVerkst dir: Nils Björklund\nEtableringsår: 1961.\n\nHALLGRENS INDUSTRI AB\n\nPnr 310 80\n\nHyltebruk. Tel 0345-110 50.\nBankgiro 43-4447. Postgiro 135983.\nTga Hallo\n\nVerksamhet: Tillverkar\nväggkon-servöppnare, antennmaterial mm\nAntal anställda: 40\nÅrsomsättning: 2 000 000\nAktiekapital: 90000\nVerkst dir: Kaleb Hallgren\nEtableringsår 1937.\n\nNILENS ELEKTRISKA AB\n\nPnr 22121\n\nLund, Bredg 18. Tel 046-14 03 10.\nBankgiro 869-3 1 03. Postgiro\n764J7-5\n\nVerksamhet: Utför elektriska\ninstallationer. Säljer belysningsarmatur\no elmaterial\nAntal anställda: 50\nÅrsomsättning: 2500 000\nAktiekapital: 120 000\nVerkst dir: Civiling Ake Nilén\nEtableringsår: 1939.",
    "structured": {
        "1": {
            "company_name": "LJUNGBY EXPRESS AB",
            "pnr": "34100",
            "address": "Ljungby, Långg",
            "phone_number": "0372-135 85",
            "bank_details": {
                "bankgiro": "147-3222",
                "postgiro": "512044-9"
            },
            "activity": "Godsterminal. Utför godstransporter i fjärr- o lokaltrafik",
            "employees": 41,
            "annual_turnover": 4000000,
            "capital": 50000,
            "key_personnel": [
                {
                    "name": "Olle Andersson",
                    "position": "Dir:r"
                },
                {
                    "name": "Sven-Erik Andersson"
                }
            ],
            "establishment_year": 1966
        },
        "2": {
            "company_name": "LJUNGBY METALLYT. FDRÄDLING",
            "pnr": "341 00",
            "address": "Ljungby, Högarörsg",
            "phone_number": "0372-10101",
            "activity": "Utför ytbehandling, förnickling o förkromning",
            "employees": null,
            "annual_turnover": null,
            "capital": null,
            "key_personnel": [
                {
                    "name": "Stig Johansson",
                    "position": "Chef"
                }
            ],
            "establishment_year": 1946
        },
        "3": {
            "company_name": "LJUNGBY MUBEL. INDUSTRI, AB",
            "pnr": "34100",
            "address": "Ljungby, Box 113, Långg",
            "phone_number": "0372-807 20",
            "postgiro": "22408-9",
            "activity": "Tillverkar butiksinredningar",
            "employees": 38,
            "annual_turnover": 4000000,
            "capital": 198000,
            "key_personnel": [
                {
                    "name": "Ove Andersson (Västerås)",
                    "position": "Verkst dir"
                }
            ],
            "establishment_year": 1931
        },
        "4": {
            "company_name": "ANDRÉN AB, BROR",
            "pnr": "66100",
            "address": "Säffle, Box 20, Billerudsg 26",
            "phone_number": "0533-12615",
            "bank_details": {
                "bankgiro": "11-4902",
                "postgiro": "224 1 20"
            },
            "activity": "Skeppsmäklare o spedition",
            "employees": 11,
            "capital": 35000,
            "key_personnel": [
                {
                    "name": "Bror Ake Andrén",
                    "position": "Verkst dir"
                }
            ],
            "establishment_year": 1928
        }
    }
}