{
    "original": "NORDHYDRAULIC AB\n\nPnr 872 01\n\nKramfors 1, Box 189.Gränsg 11. Tel\n0612-115 50. Bankgiro 232-3269.\nPostgiro 100096-7. Tga\nNordhy-draulic\n\nVerksamhet: Tillverkar\nhydraulkom-ponenter för mobilhydraulik\nAntal anställda: 105\nÅrsomsättning: 11000 000\nAktiekapital: 200 000\nVerkst dir: Rune Nord\nEtableringsår: 1965.\n\nFOR\n\nPostningsklossar för ramsågar av\nvattenfast plywood\nChefer: Jan-Anders Bergquist,\nPer-Eric Bergquist\nEtableringsår: 1896.\n\nNIC\n\nVerksamhet: Specialaffär för mattor\no heminredningstextilier\nAntal anställda: 45\nÅrsomsättning: 14 000000\nAktiekapital: 500 000\nVerkst dir: Sven Pinnander\nEtableringsàr: 1914.\n\nNEST|US PAPPERS AB\n\nPnr 100 21\n\nStockholm 18, Box 18008.\nKrono-bergsg 45. Tel 08-52 09 20.\nBankgiro 331-0984. Postgiro 51364-8\nVerksamhet: Säljer papper, kuvert\n\n0\tkontorsmateriel, trycksaker\nAntal anställda: 31\nÅrsomsättning: 10 011000\nAktiekapital: 500 000\nStyrelse: Karl D Björkman (ordf),\nGunvor Björkman, Anita Björkman\nVerkst dir: Gunvor Björkman\nEtableringsàr: 1934.\n\nNETTERSTAD, CARL J\n\nPnr 703 61\n\nÖrebro, Klosterg 7-9. Tel\n019-14 17 18 , 24 06 86. Postgiro\n283054-5. Tga Nett.erstadagent\nVerksamhet: Skoagenturer\nÅrsomsättning: 1000 000\nChef: Carl J Netterstad\nEtableringsàr: 1966.\n\nNETTO-FABRIKERNA\n\nPnr 57100\n\nNässjö, Koltorpsg 6. Tel\n0380-117 27. Postgiro 390663-3.\nTga Toliv\n\nVerksamhet: Import o\npartiförsäljning\n\nVarunamn: Duette\nÅrsomsättning: 150 000\nChef: Köpman Oliver Törnqvist\nEtableringsàr: 1949.\n\nNEUMAN MARKETING,\nBERTIL\n\nPnr 11157\n\nStockholm, Sveav 17. Tel\n08-2166 38, 2166 94. Postgiro 453258\nVerksamhet: Rådgivning till\nföretags- o försäljningsledning\nVerkst dir. Civilekonom Bertil\nNeuman\n\nEtableringsàr. 1954.\n\nNEWMAN, AB BRÖDERNA\n\nPnr 283 00\n\nOsby, Kristianstadsg 1. Box 76.\nTel 0479-119 70. Bankgiro\n281-6496. Postgiro 30565-6\nVerksamhet: VVS-installationer o\n\n01\tj ebrännares er vic e\nAntal anställda: 77\nÅrsomsättning: 9100000\nAktiekapital: 90 000\nVerkst dir: Ewe Newman\nEtableringsàr: 1913.\n\nNEVOTEX, AB\n\nPnr 57100\n\nNässjö, Brog 12. Box 80. Tel\n0380-18140. Bankgiro 834-8377. Post\ngiro 37069-2\n\nVerksamhet: Säljer\ntapetserar-material en gros\n\nAktiekapital: 200 000\nVerkst dir: Birger Fritz\nDotterbolag till AB Nässjö\nVaddfabriker.\n\nNEVSTEN AB, ANDERS\n\nPnr 21145\n\nMalmö, Davidshallsg 19. Tel\n040-395 25. Bankgiro 264-2759.\nPostgiro 38936-1\n\nVerksamhet: Byggnadsrörelse\nAntal anställda: 120\nÅrsomsättning: 15 000 000\nAktiekapital: 240 000\nVerkst dir: Ing Gunnar Karyd\nEtableringsàr: 1939.\n\nNIBBLER FABRIKS AB\n\nPnr 330 30\n\nGnosjö, Box 3. Industrig 13. Tel\n0370-91147, 915 82. Bankgiro\n542-4601. Postgiro 266559-4. Tga\nGevemaskiner\n\nVerksamhet: Tillverkar Nibbler\nuniversella\nplåtbearbetningsmaski-ner, bandvindor, gängapparater.\nMek legoarbeten\nVarunamn: Nibbler\nAntal anställda: 15\nÅrsomsättning: 1500000\nÄgare o chef: Fabr Olof\nPettersson.\n\nNIBELLO INDUSTRIVAROR\nAB\n\nPnr 41117\n\nGöteborg, V Hamng 13. Tel\n031-1124 62, 1194 45. Bankgiro\n27-5598. Postgiro 629290\nVerksamhet: Försäljning av\nspecialartiklar för byggnadsbranschen,\nspeciellt för cementfabriker o\nrörledningsfirmor. Tillverkning av\ntätningsringar för cementrör\nVarunamn: Byggnadsmaterial\nAntal anställda: 3\nÅrsomsättning: 350 000\nAktiekapital: 25000\nStyrelse: Dir Nils Ardahl (ordf),\ndir LE Ajell.herr Bertil Lennermar\nVerkst dir: Nils Ardahl\nEtableringsàr 1966.\n\nVÄSTKUSTTIDNINGAR AB\n\nPnr 401 27\n\nGöteborg 1, Box 516. Frölundag 23.\nTel 031-27 51 20. Postgiro 526839-6\nVerksamhet: Utgivare av\nGöteborgs stadsdels- o förortstidningar\nAntal anställda: 28\nÅrsomsättning: 3 000 000\nAktiekapital: 5 000\nVerkst dir: Börje Weinitz\nEtableringsår. 1964.\n\nGUL\n\nAktiekapital: 60 000 000\nVerkst dir: Disp Tage \"Arnell\nEtableringsår. 1906.\n\nKILAFORS TRÄVARU AB\n\nPnr 823 00\n\nKilafors, Box 44. Tel 0278-507 00.\nBankgiro 787-9133. Postgiro\n71075-6. Tga Kilaforsbolag\nVerksamhet: Tillverkar sågade\nträvaror\n\nAntal anställda: 57\nÅrsomsättning: 8 000 000\nAktiekapital: 200 000\nVerkst dir: J Lennart Larsson\nEtableringsår: 1955.\n\nKILANDA CEMENTGJUTERI\nAB\n\nPnr 440 40\n\nAlvängen, Postl 1233. Tel\n0303-470 50, 470 37. Bankgiro 89-5627.\nPostgiro 273676\nVerksamhet: Tillverkar o säljer\ncementvaror samt betong\nAntal anställda: 10\nÅrsomsättning: 1 000 000\nAktiekapital: 40 000\nStyrelse: Verkmäst Rune Johansson\n(ordf), dir Arvid Johansson,\nverkmäst Leif Johansson\nVerkst dir: Arvid Johansson\nEtableringsår. 1931\nOmbildat till aktiebolag 1966.\n\nKILANDA GRUS AB\n\nPnr 44040\n\nÄlvängen, Box 53. Tel\n0303-465 30. Bankgiro 895-6773.\nPostgiro 667720-7\n\nVerksamhet: Krossning o sortering\nav grusprodukter\nAntal anställda: 6\nÅrsomsättning: 1900 000\nAktiekapital: 50 000\nVerkst dir: Helge Frick\nEtableringsår: 1964.\n\nNYMANS SERIGRAFISKA, AB\n\nPnr 104 60\n\nStockholm 20, Virkesv 26 C. Tel\n08-44 03 45, 4004 00. Bankgiro\n744-8244. Postgiro 337910-4\nVerksamhet: Screentryckeri.\nTrycker på div pappers-, plast- o\ntextilmaterial\n\nFörsäljningskontor 11355\nStockholm. Seritex International AB,\nRoslagsg 23. Tel 08-3135 41\nAntal anställda: 30\nÅrsomsättning: 2500 000\nAktiekapital: 10 000\nStyrelse: Dir Lars Nyman, fru\nStina Nyman\n\nVerkst dir: Lars G Nyman\nEtableringsår: 1949.\n\nGERHARDS MASKIN AB\n\nPnr 700 06\n\nÖrebro 6, Hjälmarv 53. Box 6032.\nTel 019-13 44 53. Bankgiro\n358-7839. Postgiro 387211-6\nVerksamhet: Säljer o reparerar\nlantbruks-, skogsbruks- o\nindustrimaskiner\n\nVerkstad: 702 20 Örebro, Hjälmarv\n41. Tel 019-12 37 87\nAntal anställda: 15\nÅrsomsättning: 3 500 000\nAktiekapital: 25000\nVerkst dir: Gerhard Larsson\nKamrer: Arne Gerhardsson\nReservdelschef: Göran Wallbom\nServicechef: Hans Gerhardsson\nEtableringsår: 1962.\n\nGERHARDSSON SNICKERI AB,\nBRÖDERNA\n\nPnr 642 00\n\nFlen, Kungsbrog 3. Tel\n0157-109 28. Bankgiro 615-8547.\nPostgiro 284404-1\n\nVerksamhet: Inredningssnickerier\ntill skolor, hotell, butiker m m\nAntal anställda: 10\nÅrsomsättning: 900 000\nVerkst dir. Björn Gerhardsson\nEtableringsår: 1948.\n\nELE\n\nAktiekapital: 5 000\nVerkst dir: Carsten Jacobsen\nEtableringsår: 1955.\n\nELEKTRO DATA BOLAGET.\nEDB AB\n\nPnr 102 25\n\nStockholm 12, Box 12195. Sankt\nEriksg 48. Tel 08-24 72 40.\nBankgiro 44-7328. Postgiro 700380\n\nlelektrol data I bolaget I\n\nVerksamhet: Dataserviceföretag.\nSpecialitet: Standardsystem för\nhandel o industri\n\nFilialer: Örebro. Tel 019-140450,\n14 04 51, 14 04 5 2, 14 04 5 3\nMalmö. Tel 040-117710\nNorrköping. Tel 011-1298 90\nNorberg (stanscentral). Tel\n0223-219 00\n\nAntal anställda: 200\nÅrsomsättning: 17 000 000\nAktiekapital: 100 000\nVetkst dir: Claes Olof Livijn\nEtableringsår: 1963.\n\nBEIJER KEMIKALIE AB\n\nPnr 21124\n\nMalmö, Bjurög 43. Tel 040-18 0 0 5 0.\nBankgiro 21-7602. Postgiro 634500.\nTga Beijerkem. Telex 32248\nVerksamhet: Återförsäljare av\nkemikalier o lösningsmedel.\nDistributör för Dow Chemical, USA\nFörsäljningskontor:\nStockholm. Tel 08-22 82 60\nGöteborg. Tel 031-17 6 6 4 0\nDotterbolag: Gust Kjellberg AB,\nNorrköping. Tel 011-12 0126\nAntal anställda: 50\nÅrsomsättning: 50 000 000\nAktiekapital: 1000 000\nVerkst dir: Bertil Palmqvist\nEtableringsår: 1936.",
    "structured": {
        "1": {
            "company_name": "NORDHYDRAULIC AB",
            "pnr": "872 01",
            "address": "Kramfors 1, Box 189.Gränsg 11.",
            "phone_number": "0612-115 50",
            "bank_details": {
                "bankgiro": "232-3269",
                "postgiro": "100096-7"
            },
            "activity": "Tillverkar hydraulkomponenter för mobilhydraulik",
            "employees": 105,
            "annual_turnover": 11000000,
            "capital": 200000,
            "key_personnel": [
                {
                    "name": "Rune Nord",
                    "position": "Verkst dir"
                }
            ],
            "establishment_year": 1965
        },
        "2": {
            "company_name": "NIC",
            "pnr": "Not available",
            "address": "Not available",
            "phone_number": "Not available",
            "bank_details": {
                "bankgiro": "Not available",
                "postgiro": "Not available"
            },
            "activity": "Specialaffär för mattor o heminredningstextilier",
            "employees": 45,
            "annual_turnover": 14000000,
            "capital": 500000,
            "key_personnel": [
                {
                    "name": "Sven Pinnander",
                    "position": "Verkst dir"
                }
            ],
            "establishment_year": 1914
        },
        "3": {
            "company_name": "NEST|US PAPPERS AB",
            "pnr": "100 21",
            "address": "Stockholm 18, Box 18008.Krono-bergsg 45.",
            "phone_number": "08-52 09 20",
            "bank_details": {
                "bankgiro": "331-0984",
                "postgiro": "51364-8"
            },
            "activity": "Säljer papper, kuvert, kontorsmateriel, trycksaker",
            "employees": 31,
            "annual_turnover": 10011000,
            "capital": 500000,
            "key_personnel": [
                {
                    "name": "Karl D Björkman",
                    "position": "Styrelse"
                },
                {
                    "name": "Gunvor Björkman",
                    "position": "Styrelse"
                },
                {
                    "name": "Anita Björkman",
                    "position": "Styrelse"
                },
                {
                    "name": "Gunvor Björkman",
                    "position": "Verkst dir"
                }
            ],
            "establishment_year": 1934
        },
        "4": {
            "company_name": "NETTERSTAD, CARL J",
            "pnr": "703 61",
            "address": "Örebro, Klosterg 7-9.",
            "phone_number": "019-14 17 18 , 24 06 86",
            "bank_details": {
                "postgiro": "283054-5"
            },
            "activity": "Skoagenturer",
            "employees": "Not available",
            "annual_turnover": 1000000,
            "key_personnel": [
                {
                    "name": "Carl J Netterstad",
                    "position": "Chef"
                }
            ],
            "establishment_year": 1966
        },
        "5": {
            "company_name": "NETTO-FABRIKERNA",
            "pnr": "57100",
            "address": "Nässjö, Koltorpsg 6.",
            "phone_number": "0380-117 27",
            "bank_details": {
                "postgiro": "390663-3"
            },
            "activity": "Import o partiförsäljning",
            "employees": "Not available",
            "annual_turnover": 150000,
            "key_personnel": [
                {
                    "name": "Köpman Oliver Törnqvist",
                    "position": "Chef"
                }
            ],
            "establishment_year": 1949
        },
        "6": {
            "company_name": "NEUMAN MARKETING, BERTIL",
            "pnr": "11157",
            "address": "Stockholm, Sveav 17.",
            "phone_number": "08-2166 38, 2166 94",
            "bank_details": {
                "postgiro": "453258"
            },
            "activity": "Rådgivning till företags- o försäljningsledning",
            "employees": "Not available",
            "annual_turnover": "Not available",
            "capital": "Not available",
            "key_personnel": [
                {
                    "name": "Civilekonom Bertil Neuman",
                    "position": "Verkst dir"
                }
            ],
            "establishment_year": 1954
        },
        "7": {
            "company_name": "NEWMAN, AB BRÖDERNA",
            "pnr": "283 00",
            "address": "Osby, Kristianstadsg 1. Box 76.",
            "phone_number": "0479-119 70",
            "bank_details": {
                "bankgiro": "281-6496",
                "postgiro": "30565-6"
            },
            "activity": "VVS-installationer o j ebrännares er vic e",
            "employees": 77,
            "annual_turnover": 9100000,
            "key_personnel": [
                {
                    "name": "Ewe Newman",
                    "position": "Verkst dir"
                }
            ],
            "establishment_year": 1913
        },
        "8": {
            "company_name": "NEVOTEX, AB",
            "pnr": "57100",
            "address": "Nässjö, Brog 12. Box 80.",
            "phone_number": "0380-18140",
            "bank_details": {
                "bankgiro": "834-8377",
                "postgiro": "37069-2"
            },
            "activity": "Säljer tapetserar-material en gros",
            "capital": 200000,
            "key_personnel": [
                {
                    "name": "Birger Fritz",
                    "position": "Verkst dir"
                }
            ],
            "establishment_year": "Not available"
        },
        "9": {
            "company_name": "NEVSTEN AB, ANDERS",
            "pnr": "21145",
            "address": "Malmö, Davidshallsg 19.",
            "phone_number": "040-395 25",
            "bank_details": {
                "bankgiro": "264-2759",
                "postgiro": "38936-1"
            },
            "activity": "Byggnadsrörelse",
            "employees": 120,
            "annual_turnover": 15000000,
            "capital": 240000,
            "key_personnel": [
                {
                    "name": "Ing Gunnar Karyd",
                    "position": "Verkst dir"
                }
            ],
            "establishment_year": 1939
        },
        "10": {
            "company_name": "NIBBLER FABRIKS AB",
            "pnr": "330 30",
            "address": "Gnosjö, Box 3. Industrig 13.",
            "phone_number": "0370-91147, 915 82",
            "bank_details": {
                "bankgiro": "542-4601",
                "postgiro": "266559-4"
            },
            "activity": "Tillverkar Nibbler universella plåtbearbetningsmaski-ner, bandvindor, gängapparater. Mek legoarbeten",
            "employees": 15,
            "annual_turnover": 1500000,
            "key_personnel": [
                {
                    "name": "Fabr Olof Pettersson",
                    "position": "Ägare o chef"
                }
            ],
            "establishment_year": "Not available"
        },
        "11": {
            "company_name": "NIBELLO INDUSTRIVAROR AB",
            "pnr": "41117",
            "address": "Göteborg, V Hamng 13.",
            "phone_number": "031-1124 62, 1194 45",
            "bank_details": {
                "bankgiro": "27-5598",
                "postgiro": "629290"
            },
            "activity": "Försäljning av specialartiklar för byggnadsbranschen, speciellt för cementfabriker o rörledningsfirmor. Tillverkning av tätningsringar för cementrör",
            "employees": 3,
            "annual_turnover": 350000,
            "capital": 25000,
            "key_personnel": [
                {
                    "name": "Nils Ardahl",
                    "position": "Styrelse"
                },
                {
                    "name": "LE Ajell.herr Bertil Lennermar",
                    "position": "Styrelse"
                },
                {
                    "name": "Nils Ardahl",
                    "position": "Verkst dir"
                }
            ],
            "establishment_year": "Not available"
        },
        "12": {
            "company_name": "VÄSTKUSTTIDNINGAR AB",
            "pnr": "401 27",
            "address": "Göteborg 1, Box 516. Frölundag 23.",
            "phone_number": "031-27 51 20",
            "bank_details": {
                "postgiro": "526839-6"
            },
            "activity": "Utgivare av Göteborgs stadsdels- o förortstidningar",
            "employees": 28,
            "annual_turnover": 3000000,
            "capital": 5000,
            "key_personnel": [
                {
                    "name": "Börje Weinitz",
                    "position": "Verkst dir"
                }
            ],
            "establishment_year": 1964
        },
        "13": {
            "company_name": "KILAFORS TRÄVARU AB",
            "pnr": "823 00",
            "address": "Kilafors, Box 44.",
            "phone_number": "0278-507 00",
            "bank_details": {
                "bankgiro": "787-9133",
                "postgiro": "71075-6"
            },
            "activity": "Tillverkar sågade trävaror",
            "employees": 57,
            "annual_turnover": 8000000,
            "capital": 200000,
            "key_personnel": [
                {
                    "name": "J Lennart Larsson",
                    "position": "Verkst dir"
                }
            ],
            "establishment_year": 1955
        },
        "14": {
            "company_name": "KILANDA CEMENTGJUTERI AB",
            "pnr": "440 40",
            "address": "Alvängen, Postl 1233.",
            "phone_number": "0303-470 50, 470 37",
            "bank_details": {
                "bankgiro": "89-5627",
                "postgiro": "273676"
            },
            "activity": "Tillverkar o säljer cementvaror samt betong",
            "employees": 10,
            "annual_turnover": 1000000,
            "capital": 40000,
            "key_personnel": [
                {
                    "name": "Verkmäst Rune Johansson",
                    "position": "Styrelse"
                },
                {
                    "name": "Arvid Johansson",
                    "position": "Styrelse"
                },
                {
                    "name": "Leif Johansson",
                    "position": "Styrelse"
                },
                {
                    "name": "Arvid Johansson",
                    "position": "Verkst dir"
                }
            ],
            "establishment_year": 1931
        },
        "15": {
            "company_name": "KILANDA GRUS AB",
            "pnr": "44040",
            "address": "Älvängen, Box 53.",
            "phone_number": "0303-465 30",
            "bank_details": {
                "bankgiro": "895-6773",
                "postgiro": "667720-7"
            },
            "activity": "Krossning o sortering av grusprodukter",
            "employees": 6,
            "annual_turnover": 1900000,
            "capital": 50000,
            "key_personnel": [
                {
                    "name": "Helge Frick",
                    "position": "Verkst dir"
                }
            ],
            "establishment_year": 1964
        },
        "16": {
            "company_name": "NYMANS SERIGRAFISKA, AB",
            "pnr": "104 60",
            "address": "Stockholm 20, Virkesv 26 C.",
            "phone_number": "08-44 03 45, 4004 00",
            "bank_details": {
                "bankgiro": "744-8244",
                "postgiro": "337910-4"
            },
            "activity": "Screentryckeri. Trycker på div pappers-, plast- o textilmaterial",
            "employees": 30,
            "annual_turnover": 2500000,
            "capital": 10000,
            "key_personnel": [
                {
                    "name": "Lars Nyman",
                    "position": "Styrelse"
                },
                {
                    "name": "Stina Nyman",
                    "position": "Styrelse"
                },
                {
                    "name": "Lars G Nyman",
                    "position": "Verkst dir"
                }
            ],
            "establishment_year": 1949
        },
        "17": {
            "company_name": "GERHARDS MASKIN AB",
            "pnr": "700 06",
            "address": "Örebro 6, Hjälmarv 53. Box 6032.",
            "phone_number": "019-13 44 53",
            "bank_details": {
                "bankgiro": "358-7839",
                "postgiro": "387211-6"
            },
            "activity": "Säljer o reparerar lantbruks-, skogsbruks- o industrimaskiner",
            "employees": 15,
            "annual_turnover": 3500000,
            "capital": 25000,
            "key_personnel": [
                {
                    "name": "Gerhard Larsson",
                    "position": "Verkst dir"
                }
            ],
            "establishment_year": 1962
        },
        "18": {
            "company_name": "GERHARDSSON SNICKERI AB, BRÖDERNA",
            "pnr": "642 00",
            "address": "Flen, Kungsbrog 3.",
            "phone_number": "0157-109 28",
            "bank_details": {
                "bankgiro": "615-8547",
                "postgiro": "284404-1"
            },
            "activity": "Inredningssnickerier till skolor, hotell, butiker m m",
            "employees": 10,
            "annual_turnover": 900000,
            "key_personnel": [
                {
                    "name": "Björn Gerhardsson",
                    "position": "Verkst dir"
                }
            ],
            "establishment_year": 1948
        },
        "19": {
            "company_name": "ELE",
            "pnr": "Not available",
            "address": "Not available",
            "phone_number": "Not available",
            "bank_details": {
                "bankgiro": "Not available",
                "postgiro": "Not available"
            },
            "activity": "Not available",
            "capital": 5000,
            "key_personnel": [
                {
                    "name": "Carsten Jacobsen",
                    "position": "Verkst dir"
                }
            ],
            "establishment_year": 1955
        },
        "20": {
            "company_name": "ELEKTRO DATA BOLAGET. EDB AB",
            "pnr": "102 25",
            "address": "Stockholm 12, Box 12195. Sankt Eriksg 48.",
            "phone_number": "08-24 72 40",
            "bank_details": {
                "bankgiro": "44-7328",
                "postgiro": "700380"
            },
            "activity": "Dataserviceföretag. Specialitet: Standardsystem för handel o industri",
            "employees": 200,
            "annual_turnover": 17000000,
            "capital": 100000,
            "key_personnel": [
                {
                    "name": "Claes Olof Livijn",
                    "position": "Vetkst dir"
                }
            ],
            "establishment_year": 1963
        },
        "21": {
            "company_name": "BEIJER KEMIKALIE AB",
            "pnr": "21124",
            "address": "Malmö, Bjurög 43.",
            "phone_number": "040-18 0 0 5 0",
            "bank_details": {
                "bankgiro": "21-7602",
                "postgiro": "634500"
            },
            "activity": "Återförsäljare av kemikalier o lösningsmedel. Distributör för Dow Chemical, USA",
            "employees": 50,
            "annual_turnover": 50000000,
            "capital": 1000000,
            "key_personnel": [
                {
                    "name": "Bertil Palmqvist",
                    "position": "Verkst dir"
                }
            ],
            "establishment_year": 1936
        }
    }
}