{
    "original": "CAPSTAN AB\n\nPnr 126 12\n\nStockholm 42, Box 42016. Elektrav\n49. Tel 08-19 04 10\nVerksamhet: Import o försäljning\nav segelbåtar\nÅrsomsättning: 1 000 000\nAktiekapital: 5 000\nVerkst dir: Curt H Andréasson\nEtableringsår: 1965.\n\nBERNER &amp; CO, AB\n\nPnr 831 00\n\nÖstersund, Storg 39. Tel\n063-172 40. Bankgiro 197-9558.\nPostgiro 9208-0. Tga Berners\nVerksamhet: Försäljning o\nverkstadsrörelse för Scania-Vabis\nAntal anställda: 170\nÅrsomsättning: 30 000 000\nAktiekapital: 90 200\nVeikst dir: Walther Rasteby\nEtableringsår: 1925.\n\nBERNER HANDELS AB,\nBRÖDERNA\n\nPnr 123 21\n\nFarsta 1, Nykroppag 27. Box 71.\nTel 08-94 01 00. Bankgiro 578-2057.\nPostgiro 455423-4. Tga\nBerner-brothers\n\nVerksamhet: Partihandel\nAntal anställda: 16\nÅrsomsättning: 5 000 000\nAktiekapital: 50000\nVerkst dir: Harry B Berner\nEtableringsår: 1960.\n\nMYRSTEDT, AB SVEN\n\nPnr 11143\n\nStockholm, Kungsg 5. Tel\n08-231685. Bankgiro 160-1392.\nPost-giro 4590-6. Tga Matthörnan\nVerksamhet: Detalj- o\nleveransförsäljning av orientaliska o\nmaskin-vävda mattor\n\nFilialaffär: Stockholm SV, Hornsg\n54. Tel 08-40 58 61\nAntal anställda: 52\nAktiekapital: 500 000\nStyrelse: Dir Gunnar Svensson\n(ordf), herr Christer Svensson,\ndir Ove Fahlander\nVerkst din Ove Fahlander\nKamrer M O Friberg\nEtableringsår: 1919\nOmbildat till aktiebolag 1931.\n\nMYRSTEN, AB ROB\n\nPnr 620 30\n\nSUte, Box 25. Tel 0498-200 01,\n20002. Bankgiro 834-8088.\nPostgiro 189850-1\n\nVerksamhet: Skeppsklarerings- o\nskeppsmäklerirörelse samt rederi\nAntal anställda: 50\nAktiekapital: 30 000\nVerkst dir: Robert Myrsten\nEtableringsår: 1935.\n\nLEHMANNS HANDELS AB\n\nPnr 11651\n\nStockholm, Krukmakarg 22. Tel\n08-84 8312, 84 8313. Bankgiro\n70-0114. Postgiro 1371. Tga Lehmhab\nVeiksamhet: Grosshandel. Säljer\ntoilette- o presentartiklar\nAntal anställda: 17\n.Aktiekapital: 100 000\nVerkst dir: B Skolin\nEtableringsår: 1949.\n\nDAHLANDERSTAPETER AB\n\nPnr 402 21\n\nGöteborg 5, Anders Perssonsg 10.\nBox 5065. Tel 031-80 05 30.\nBankgiro 505-7575. Postgiro 40792-4.\nTga Dahlander.\nTelex 20882 SALUBRA S\nVerksamhet: Säljer tapeter i\nparti o minut. Generalagent för\nSalubra A. G., Basel m fi\nVarunamn: Pareta Seide, Plastelie,\nSalubra, Tekko\n.Aktiekapital: 100000\nVerkst dir: Lars Henrik Jonson\n\nEtableringsår: 1850\nOmbildat till nuvarande\naktiebolag 1964.\n\nDALA-PERFO AB\n\nPnr 770 66\n\nFors. Tel 0226-30180. Bankgiro\n576-6548. Tga Perforator\nVerksamhet: Tillverkar perforerad\nplåt för alla ändamål\nAntal anställda: 9\nVerkst din Sture Dellen.\n\nDALARNAS\nFORSÄKRINGS-BOLAG\n\nPnr 79101\n\nFalun 1, Box 31. Parkg 5-7. Tel\n023-220 50. Bankgiro 464-1205.\nPostgiro 140632-1\nVerksamhet: Säljer sakförsäkring.\nÖmsesidigt bolag\nAntal anställda: 31\nÅrsomsättning: 12 000 000\nVerkst dir: Karl-Erik Liljegren\nEtableringsår: 1846.\n\nFORSELIUS AB, G C\n\nPnr 302 41\n\nHalmstad, Asgårdsv 5. Tel\n035-1240 25. Bankgiro 53-0386.\nPosfc-giro 55 3279. Telex 38033\nVerksamhet: Säljer\nspecialmaskiner för textil- o plastindustrin\nChef: Ing G C Forselius\nEtableringsår: 1956.\n\nFORSELLS MEKANISKA\nVERKSTAD, BRUDERNA\n\nPnr 460 50\n\nGrästorp. Tel 0514-10083.\nBankgiro 218-8225. Postgiro 33411-0\nVerksamhet: Tillverkar planskivor\no mindre båtmotorer samt\nhydrauliska styranordningar för båtar.\nLegoarbeten o maskinreparationer\nChef: Fru Gunborg Andersson\nEtableringsår: 1918.\n\nELLOS POSTORDER AB\n\nPnr 501 86\n\nBorås, Skaraborgs v 62-64. Tel\n033-13 71 00. Bankgiro 531-3093.\nPostgiro 381309-4\n\nVerksamhet: Postorderförsäljning\ndirekt till konsumenten\nAntal anställda: 325\nÅrsomsättning: 91500 000\nVerkst dir: Olle Blomqvist\nEtableringsår: 1947.\n\nGEV\n\n2345. Tel 031-17 2945. Bankgiro\n847-8620. Postgiro 45143-5. Tga\nGeveko\n\nBITUMULS Asfaltemulsioner\nESSMAK Asfaltmassa\nMERCALIN Trafiklinjefär!\nMERCATON Inomhusfärg\nMURFAS T Fasadfärg\nDURAHART Skeppsbotlenfärt\nMERCASEAL Underredsmassa\nMERCASOL Rostskyddsolja\n\nVerksamhet: Asfaltprodukter o\nfärger\n\nAntal anställda: 50\nÅrsomsättning: 8 000 000\nAktiekapital: 200 000\nStyrelse: Dir Gunnar Mattsson\n(ordf), civiling Jarl Ergel, dir\nösten Mattsson\nVerkst dir: Civiling Jarl Ergel\nFabrikschef: Ing Bengt Jungqvist\nEtableringsår: 1932\nNuvarande namn 1960.\n\nGEVERAM, AB\n\nPnr 113 47\n\nStockholm, Hagag 39. Tel\n08-33 34 56, 33 34 68. Bankgiro\n724-5582. Postgiro 551034-2\nVerksamhet: Bokbinderi.\nSpecialitet: montering av kartor\nAntal anställda: 12\nAktiekapital: 5 000\nVerkst dir: Gösta W Rahm\nEtableringsår: 1955,\n\nGUNNARSSON, AB BRÖDERNA\n\nPnr 510 81\n\nAmbjömarp. Tel 0325-601 24.\nBankgiro 55-3189. Postgiro 377017\nVerksamhet: Hårgarn- o\nnöthårs-mattor\n\nAntal anställda: 6\nÅrsomsättning: 300 000\nAktiekapital: 20000\nVerkst dir: Arne Gunnarsson\nEtableringsår: 1949.\n\nLJU\n\nAktiekapital: 75 000\nVerkst dir: Bendix Lecander\nEtableringsår: 1962.",
    "structured": {
        "1": {
            "company_name": "CAPSTAN AB",
            "pnr": "126 12",
            "address": "Stockholm 42, Box 42016. Elektrav 49",
            "phone_number": "08-19 04 10",
            "activity": "Import o försäljning av segelbåtar",
            "annual_turnover": 1000000,
            "capital": 5000,
            "key_personnel": [
                {
                    "name": "Curt H Andréasson",
                    "position": "Verkst dir"
                }
            ],
            "establishment_year": 1965
        },
        "2": {
            "company_name": "BERNER & CO, AB",
            "pnr": "831 00",
            "address": "Östersund, Storg 39",
            "phone_number": "063-172 40",
            "bank_details": {
                "bankgiro": "197-9558",
                "postgiro": "9208-0"
            },
            "activity": "Försäljning o verkstadsrörelse för Scania-Vabis",
            "employees": 170,
            "annual_turnover": 30000000,
            "capital": 90200,
            "key_personnel": [
                {
                    "name": "Walther Rasteby",
                    "position": "Verkst dir"
                }
            ],
            "establishment_year": 1925
        },
        "3": {
            "company_name": "BERNER HANDELS AB, BRÖDERNA",
            "pnr": "123 21",
            "address": "Farsta 1, Nykroppag 27. Box 71",
            "phone_number": "08-94 01 00",
            "bank_details": {
                "bankgiro": "578-2057",
                "postgiro": "455423-4"
            },
            "activity": "Partihandel",
            "employees": 16,
            "annual_turnover": 5000000,
            "capital": 50000,
            "key_personnel": [
                {
                    "name": "Harry B Berner",
                    "position": "Verkst dir"
                }
            ],
            "establishment_year": 1960
        },
        "4": {
            "company_name": "MYRSTEDT, AB SVEN",
            "pnr": "11143",
            "address": "Stockholm, Kungsg 5",
            "phone_number": "08-231685",
            "bank_details": {
                "bankgiro": "160-1392",
                "postgiro": "4590-6"
            },
            "activity": "Detalj- o leveransförsäljning av orientaliska o maskin-vävda mattor",
            "employees": 52,
            "capital": 500000,
            "key_personnel": [
                {
                    "name": "Ove Fahlander",
                    "position": "Verkst dir"
                },
                {
                    "name": "M O Friberg",
                    "position": "Kamrer"
                }
            ],
            "establishment_year": 1919
        },
        "5": {
            "company_name": "MYRSTEN, AB ROB",
            "pnr": "620 30",
            "address": "SUte, Box 25",
            "phone_number": "0498-200 01, 20002",
            "bank_details": {
                "bankgiro": "834-8088",
                "postgiro": "189850-1"
            },
            "activity": "Skeppsklarerings- o skeppsmäklerirörelse samt rederi",
            "employees": 50,
            "capital": 30000,
            "key_personnel": [
                {
                    "name": "Robert Myrsten",
                    "position": "Verkst dir"
                }
            ],
            "establishment_year": 1935
        },
        "6": {
            "company_name": "LEHMANNS HANDELS AB",
            "pnr": "11651",
            "address": "Stockholm, Krukmakarg 22",
            "phone_number": "08-84 8312, 84 8313",
            "bank_details": {
                "bankgiro": "70-0114",
                "postgiro": "1371"
            },
            "activity": "Grosshandel. Säljer toilette- o presentartiklar",
            "employees": 17,
            "capital": 100000,
            "key_personnel": [
                {
                    "name": "B Skolin",
                    "position": "Verkst dir"
                }
            ],
            "establishment_year": 1949
        },
        "7": {
            "company_name": "DAHLANDERSTAPETER AB",
            "pnr": "402 21",
            "address": "Göteborg 5, Anders Perssonsg 10. Box 5065",
            "phone_number": "031-80 05 30",
            "bank_details": {
                "bankgiro": "505-7575",
                "postgiro": "40792-4"
            },
            "activity": "Säljer tapeter i parti o minut. Generalagent för Salubra A. G., Basel m fi",
            "capital": 100000,
            "key_personnel": [
                {
                    "name": "Lars Henrik Jonson",
                    "position": "Verkst dir"
                }
            ],
            "establishment_year": 1850
        },
        "8": {
            "company_name": "DALA-PERFO AB",
            "pnr": "770 66",
            "address": "Fors",
            "phone_number": "0226-30180",
            "bank_details": {
                "bankgiro": "576-6548"
            },
            "activity": "Tillverkar perforerad plåt för alla ändamål",
            "employees": 9,
            "key_personnel": [
                {
                    "name": "Sture Dellen",
                    "position": "Verkst din"
                }
            ]
        },
        "9": {
            "company_name": "DALARNAS FORSÄKRINGS-BOLAG",
            "pnr": "79101",
            "address": "Falun 1, Box 31. Parkg 5-7",
            "phone_number": "023-220 50",
            "bank_details": {
                "bankgiro": "464-1205",
                "postgiro": "140632-1"
            },
            "activity": "Säljer sakförsäkring. Ömsesidigt bolag",
            "employees": 31,
            "annual_turnover": 12000000,
            "key_personnel": [
                {
                    "name": "Karl-Erik Liljegren",
                    "position": "Verkst dir"
                }
            ],
            "establishment_year": 1846
        },
        "10": {
            "company_name": "FORSELIUS AB, G C",
            "pnr": "302 41",
            "address": "Halmstad, Asgårdsv 5",
            "phone_number": "035-1240 25",
            "bank_details": {
                "bankgiro": "53-0386",
                "postgiro": "55 3279"
            },
            "activity": "Säljer specialmaskiner för textil- o plastindustrin",
            "key_personnel": [
                {
                    "name": "Ing G C Forselius",
                    "position": "Chef"
                }
            ],
            "establishment_year": 1956
        },
        "11": {
            "company_name": "FORSELLS MEKANISKA VERKSTAD, BRUDERNA",
            "pnr": "460 50",
            "address": "Grästorp",
            "phone_number": "0514-10083",
            "bank_details": {
                "bankgiro": "218-8225",
                "postgiro": "33411-0"
            },
            "activity": "Tillverkar planskivor o mindre båtmotorer samt hydrauliska styranordningar för båtar. Legoarbeten o maskinreparationer",
            "key_personnel": [
                {
                    "name": "Fru Gunborg Andersson",
                    "position": "Chef"
                }
            ],
            "establishment_year": 1918
        },
        "12": {
            "company_name": "ELLOS POSTORDER AB",
            "pnr": "501 86",
            "address": "Borås, Skaraborgs v 62-64",
            "phone_number": "033-13 71 00",
            "bank_details": {
                "bankgiro": "531-3093",
                "postgiro": "381309-4"
            },
            "activity": "Postorderförsäljning direkt till konsumenten",
            "employees": 325,
            "annual_turnover": 91500000,
            "key_personnel": [
                {
                    "name": "Olle Blomqvist",
                    "position": "Verkst dir"
                }
            ],
            "establishment_year": 1947
        },
        "13": {
            "company_name": "GEV",
            "phone_number": "031-17 2945",
            "bank_details": {
                "bankgiro": "847-8620",
                "postgiro": "45143-5"
            }
        },
        "14": {
            "company_name": "GEVERAM, AB",
            "pnr": "113 47",
            "address": "Stockholm, Hagag 39",
            "phone_number": "08-33 34 56, 33 34 68",
            "bank_details": {
                "bankgiro": "724-5582",
                "postgiro": "551034-2"
            },
            "activity": "Bokbinderi. Specialitet: montering av kartor",
            "employees": 12,
            "capital": 5000,
            "key_personnel": [
                {
                    "name": "Gösta W Rahm",
                    "position": "Verkst dir"
                }
            ],
            "establishment_year": 1955
        },
        "15": {
            "company_name": "GUNNARSSON, AB BRÖDERNA",
            "pnr": "510 81",
            "address": "Ambjömarp",
            "phone_number": "0325-601 24",
            "bank_details": {
                "bankgiro": "55-3189",
                "postgiro": "377017"
            },
            "activity": "Hårgarn- o nöthårs-mattor",
            "employees": 6,
            "annual_turnover": 300000,
            "capital": 20000,
            "key_personnel": [
                {
                    "name": "Arne Gunnarsson",
                    "position": "Verkst dir"
                }
            ],
            "establishment_year": 1949
        },
        "16": {
            "company_name": "LJU",
            "capital": 75000,
            "key_personnel": [
                {
                    "name": "Bendix Lecander",
                    "position": "Verkst dir"
                }
            ],
            "establishment_year": 1962
        }
    }
}