{
    "original": "NECKS VERKSTÄDER AB\n\nPnr 460 40\n\nNossebro. Tel 0512-506 00\nVerksamhet: Smiden för elektr\nledningar, klena o medelgrova smiden,\nsänksmide, fotskrapor m m\nAntal anställda: 240\nÅrsomsättning: 20000 000\nAktiekapital: 1000 000\nStyrelse: Ing Sixten Neck (ordf),\nlagerchef William Mattsson, ing\nRoland Neck, fru Selma Neck, kamrer\nI Emander\n\nVerkst dir. Ing Roland Neck\nEtableringsår: 1919.\n\nNEDERLULEÅ\nLASTBIL-CENTRAL\n\nPnr 95100\n\nLuleå 8, Box 80042. Tel\n0920-10045. Bankgiro 752-5223.\nPostgiro 386658\n\nVerksamhet: Transportförmedling\nAntal anställda: 50\nÅrsomsättning: 16 000 000\nInsatskapital: 500 000\nVerkst dir: Folke Hedberg\nEtableringsår: 1948.\n\nNEDRE NORRLANDS\nPRODUCENTFURENING\nEK FUR\n\nPnr 83101\n\nÖstersund 1, Fack. Kyrkg 64. Tel\n063-17100. Bankgiro 41-4871.\nPostgiro 179974-1. Tga\nNordprodukt. Telex 6509\nVerksamhet: Tillverkar flytande\nmjölkprodukter o hårdost m m\nAntal anställda: 1 400\nÅrsomsättning: 350 000 000\nVerkst dir: Bengt Sjölund\nEtableringsår: 1970.\n\nMOTALA GRÄVMASKINER AB\n\nPnr 591 01\n\nMotala 1, Ostermalmsg-Myntg.Box\n150. Tel 0141-198 00, 124 29.\nBankgiro 13-4111. Postgiro 140198\nVerksamhet: Schaktentreprenader\nför byggnader o vägar\nAntal anställda: 25\nÅrsomsättning: 2 255 000\nAktiekapital: 80 000\nVerkst dir: Ivar Andersson\nEtableringsår. 1950.\n\nWIXELL, AB AND O\n\nPnr 211 20\n\nMalmö, Västkustv 1. Tel\n040-93 64 20. Bankgiro 26-0056.\nPostgiro 14053\n\nVerksamhet: Tillverkar färger.\nSäljer färger o tapeter i parti o minut\nAntal anställda: 85\nAktiekapital: 375 000\nStyrelse: Frk Signe Wixell (ordf),\nfrk Berna Wixell, herr Lars Wixell\nVerkst dir: Lars Wixell\nEtableringsår: 1899\nOmbildat till aktiebolag 1938.\n\nWIXNER AB, SVEN\n\nPnr 113 54\n\nStockholm. Roslagsg 60. Tel\n08-34 0170. Bankgiro 576-3081.\nPostgiro 250844-8\n\nVerksamhet: Auktoriserad\nåterförsäljare för Peugeot\n•Antal anställda: 20\nÅrsomsättning: 11000 000\nAktiekapital: 75 000\nVerkst dir. Sven Wixner\nEtableringsår: 1954.\n\nSMEDBY KONFEKTYR AB\n\nPnr 380 26\n\nSmedby, Nybrov 16. Box 91. Tel\n0480-716 60. Bankgiro 342-5063.\nPostgiro 138103-7\nVerksamhet: Karamell- o\nklubbtillverkning\nAntal anställda: 25\nÅrsomsättning: 3 000 000\nAktiekapital: 60 000\nVerkst dir: Disp Lars-Göran\nIsraelson\n\nEtableringsår: 1929.\n\nGRAFISET SYSTEM AB\n\nPnr 124 40\n\nBandhagen, Stallarholmsv 55. Tel\n08-86 00 50. Bankgiro 603-1579.\nPostgiro 57180-2. Tga Grafiset\nVerksamhet: Tillverkar o säljer\nByggin system för skiljeväggar\nAntal anställda: 12\nÅrsomsättning: 1000000\nAktiekapital: 75 000\nVerkst din Karl-Gunnar Kroopp\nEtableringsår: 1962.\n\nCLI\n\nBankgiro 420-7163. Postgiro\n626530-0\n\nVerksamhet: Lagring o distribution\nav petroleumprodukter\nAntal anställda: 12\nÅrsomsättning: 5 000 000\nAktiekapital: 140 000\nVerkst dir: Bo Ingelson\nEtableringsår: 1964.\n\nSCANGOLV, AB\n\nPnr 400 43\n\nGöteborg 30, Kapplandsg 130. Box\n30069. Tel 031-4163 80. Bankgiro\n154-2604. Postgiro 627241-3. Tga\nScanfloor\n\nVerksamhet: Samordnande,\ntekniskt o försäljningsorgan för\nledande in- o utländska fabrikanter o\nertreprenörer av industrigolv mm.\nFörsäljning o uthyrning av\ngolv-o byggnadsmaskiner.\nTeknisk-, försäljnings- samt\nentreprenadverksamhet över hela\nSkandinavien\nAktiekapital: 25 000\nVerkst dir: Byggning Tommy\nBergstrand\nEtableringsår: 1964.\n\nMON\n\nStyrelse: Dir Lennart Mohlin(ordf),\nfru Viola Mohlin\nVerkst dir: Lennart Mohlin\nKamrer: Rolf Johansson\nEtableringsàr: 1961.\n\nMOLIN &amp; WESTBERG\nINGENJURSFIRMA, AB\n\nPnr 214 53\n\nMalmö, Professorsg 5. Tel\n040-218000. Bankgiro 870-3548.\nPostgiro 246876-7\n\nVerksamhet: Tillverkar o säljer\nbrand- o arbetarskyddsmateriel\nVarunamn: Mowe\nAntal anställda: 4\nAktiekapital: 50 000\nVerkst dir: Göran M Molin\nEtableringsàr: 1948\nOmbildat till aktiebolag 1953.\n\nMOLIN, OTTO\n\nPnr 291 01\n\nKristianstad 1, Box 66.\nNorre-tullsv 15. Tel 044-11 52 20.\nBankgiro 867-5225. Postgiro 27480-3\nVerksamhet: Försäljning av\njärnvaror i parti\nAntal anställda: 15\nChef: Köpman Otto Molin\nAvd-chef: Sven Schalling\nEtableringsàr 1926.\n\nENWEX AB\n\nPnr 44101\n\nAlingsås 1. Afzelii v 37. Box 181.\nTel 0322-119 80, 118 94. Bankgiro\n88-9756. Postgiro 360165\nVerksamhet: Tillverkar hatthyllor o\nklädställ för tak- o golvmontage\nmed patenterat\nklädupphängnings-system (Enwex Kulgalge-Galgen\nsom inte faller): Varunamn Enwex.\nArbetsbockar. Rörspett: Varunamn\nPraktic\n\nFabrik: Alingsås, Borgmästarev.\nTel 0322-119 80, 118 94\nVarunamn: Enwex, Praktic\nAktiekapital: 153 100\nStyrelseordf: Civiling H Norberg\nVerkst dir: Civiling H Norberg\nEtableringsår: 1947.\n\nGARPHYTTE BRUK, AB\n\nPnr 71016\n\nGarphyttan. Tel 019-980 00.\nBankgiro 160-1053. Postgiro 8266-9.\nTga Garphyttan, Örebro.\nTelex 73213\n\nVerksamhet: Manufakturverk med\ntråddrageri, stålline- o fjäderfabrik\nAntal anställda: 700\nÅrsomsättning: 75 000 000\nAktiekapital: 15 000 000\nVerkst dir: Disp Henrik Werme\nEtableringsår: 1906.",
    "structured": {
        "1": {
            "company_name": "NECKS VERKSTÄDER AB",
            "pnr": "460 40",
            "address": "Nossebro",
            "phone_number": "0512-506 00",
            "activity": "Smiden för elektr ledningar, klena o medelgrova smiden, sänksmide, fotskrapor m m",
            "employees": 240,
            "annual_turnover": 20000000,
            "capital": 1000000,
            "key_personnel": [
                {
                    "name": "Ing Sixten Neck",
                    "position": "ordf"
                },
                {
                    "name": "William Mattsson",
                    "position": "lagerchef"
                },
                {
                    "name": "Roland Neck",
                    "position": "ing"
                },
                {
                    "name": "Selma Neck",
                    "position": "fru"
                },
                {
                    "name": "I Emander",
                    "position": "kamrer"
                }
            ],
            "establishment_year": 1919
        },
        "2": {
            "company_name": "NEDERLULEÅ LASTBIL-CENTRAL",
            "pnr": "95100",
            "address": "Luleå 8, Box 80042",
            "phone_number": "0920-10045",
            "bank_details": {
                "bankgiro": "752-5223",
                "postgiro": "386658"
            },
            "activity": "Transportförmedling",
            "employees": 50,
            "annual_turnover": 16000000,
            "capital": 500000,
            "key_personnel": [
                {
                    "name": "Folke Hedberg",
                    "position": "Verkst dir"
                }
            ],
            "establishment_year": 1948
        },
        "3": {
            "company_name": "NEDRE NORRLANDS PRODUCENTFURENING EK FUR",
            "pnr": "83101",
            "address": "Östersund 1, Fack. Kyrkg 64",
            "phone_number": "063-17100",
            "bank_details": {
                "bankgiro": "41-4871",
                "postgiro": "179974-1"
            },
            "activity": "Tillverkar flytande mjölkprodukter o hårdost m m",
            "employees": 1400,
            "annual_turnover": 350000000,
            "key_personnel": [
                {
                    "name": "Bengt Sjölund",
                    "position": "Verkst dir"
                }
            ],
            "establishment_year": 1970
        },
        "4": {
            "company_name": "MOTALA GRÄVMASKINER AB",
            "pnr": "591 01",
            "address": "Motala 1, Ostermalmsg-Myntg.Box 150",
            "phone_number": "0141-198 00, 124 29",
            "bank_details": {
                "bankgiro": "13-4111",
                "postgiro": "140198"
            },
            "activity": "Schaktentreprenader för byggnader o vägar",
            "employees": 25,
            "annual_turnover": 2255000,
            "capital": 80000,
            "key_personnel": [
                {
                    "name": "Ivar Andersson",
                    "position": "Verkst dir"
                }
            ],
            "establishment_year": 1950
        },
        "5": {
            "company_name": "WIXELL, AB AND O",
            "pnr": "211 20",
            "address": "Malmö, Västkustv 1",
            "phone_number": "040-93 64 20",
            "bank_details": {
                "bankgiro": "26-0056",
                "postgiro": "14053"
            },
            "activity": "Tillverkar färger. Säljer färger o tapeter i parti o minut",
            "employees": 85,
            "capital": 375000,
            "key_personnel": [
                {
                    "name": "Signe Wixell",
                    "position": "ordf"
                },
                {
                    "name": "Berna Wixell",
                    "position": "frk"
                },
                {
                    "name": "Lars Wixell",
                    "position": "herr"
                },
                {
                    "name": "Lars Wixell",
                    "position": "Verkst dir"
                }
            ],
            "establishment_year": 1899
        },
        "6": {
            "company_name": "WIXNER AB, SVEN",
            "pnr": "113 54",
            "address": "Stockholm, Roslagsg 60",
            "phone_number": "08-34 0170",
            "bank_details": {
                "bankgiro": "576-3081",
                "postgiro": "250844-8"
            },
            "activity": "Auktoriserad återförsäljare för Peugeot",
            "employees": 20,
            "annual_turnover": 11000000,
            "capital": 75000,
            "key_personnel": [
                {
                    "name": "Sven Wixner",
                    "position": "Verkst dir"
                }
            ],
            "establishment_year": 1954
        },
        "7": {
            "company_name": "SMEDBY KONFEKTYR AB",
            "pnr": "380 26",
            "address": "Smedby, Nybrov 16, Box 91",
            "phone_number": "0480-716 60",
            "bank_details": {
                "bankgiro": "342-5063",
                "postgiro": "138103-7"
            },
            "activity": "Karamell- o klubbtillverkning",
            "employees": 25,
            "annual_turnover": 3000000,
            "capital": 60000,
            "key_personnel": [
                {
                    "name": "Lars-Göran Israelson",
                    "position": "Verkst dir"
                }
            ],
            "establishment_year": 1929
        },
        "8": {
            "company_name": "GRAFISET SYSTEM AB",
            "pnr": "124 40",
            "address": "Bandhagen, Stallarholmsv 55",
            "phone_number": "08-86 00 50",
            "bank_details": {
                "bankgiro": "603-1579",
                "postgiro": "57180-2"
            },
            "activity": "Tillverkar o säljer Byggin system för skiljeväggar",
            "employees": 12,
            "annual_turnover": 1000000,
            "capital": 75000,
            "key_personnel": [
                {
                    "name": "Karl-Gunnar Kroopp",
                    "position": "Verkst din"
                }
            ],
            "establishment_year": 1962
        },
        "9": {
            "company_name": "CLI",
            "bank_details": {
                "bankgiro": "420-7163",
                "postgiro": "626530-0"
            },
            "activity": "Lagring o distribution av petroleumprodukter",
            "employees": 12,
            "annual_turnover": 5000000,
            "capital": 140000,
            "key_personnel": [
                {
                    "name": "Bo Ingelson",
                    "position": "Verkst dir"
                }
            ],
            "establishment_year": 1964
        },
        "10": {
            "company_name": "SCANGOLV, AB",
            "pnr": "400 43",
            "address": "Göteborg 30, Kapplandsg 130, Box 30069",
            "phone_number": "031-4163 80",
            "bank_details": {
                "bankgiro": "154-2604",
                "postgiro": "627241-3"
            },
            "activity": "Samordnande, tekniskt o försäljningsorgan för ledande in- o utländska fabrikanter o ertreprenörer av industrigolv mm. Försäljning o uthyrning av golv-o byggnadsmaskiner. Teknisk-, försäljnings- samt entrepenadverksamhet över hela Skandinavien",
            "capital": 25000,
            "key_personnel": [
                {
                    "name": "Tommy Bergstrand",
                    "position": "Verkst dir"
                }
            ],
            "establishment_year": 1964
        },
        "11": {
            "company_name": "MON",
            "key_personnel": [
                {
                    "name": "Lennart Mohlin",
                    "position": "Styrelse: Dir"
                },
                {
                    "name": "Viola Mohlin",
                    "position": "Styrelse: fru"
                },
                {
                    "name": "Lennart Mohlin",
                    "position": "Verkst dir"
                },
                {
                    "name": "Rolf Johansson",
                    "position": "Kamrer"
                }
            ],
            "establishment_year": 1961
        },
        "12": {
            "company_name": "MOLIN & WESTBERG INGENJURSFIRMA, AB",
            "pnr": "214 53",
            "address": "Malmö, Professorsg 5",
            "phone_number": "040-218000",
            "bank_details": {
                "bankgiro": "870-3548",
                "postgiro": "246876-7"
            },
            "activity": "Tillverkar o säljer brand- o arbetarskyddsmateriel",
            "employees": 4,
            "capital": 50000,
            "key_personnel": [
                {
                    "name": "Göran M Molin",
                    "position": "Verkst dir"
                }
            ],
            "establishment_year": 1953
        },
        "13": {
            "company_name": "MOLIN, OTTO",
            "pnr": "291 01",
            "address": "Kristianstad 1, Box 66, Norre-tullsv 15",
            "phone_number": "044-11 52 20",
            "bank_details": {
                "bankgiro": "867-5225",
                "postgiro": "27480-3"
            },
            "activity": "Försäljning av järnvaror i parti",
            "employees": 15,
            "key_personnel": [
                {
                    "name": "Otto Molin",
                    "position": "Chef"
                },
                {
                    "name": "Sven Schalling",
                    "position": "Avd-chef"
                }
            ],
            "establishment_year": 1926
        },
        "14": {
            "company_name": "ENWEX AB",
            "pnr": "44101",
            "address": "Alingsås 1, Afzelii v 37, Box 181",
            "phone_number": "0322-119 80, 118 94",
            "bank_details": {
                "bankgiro": "88-9756",
                "postgiro": "360165"
            },
            "activity": "Tillverkar hatthyllor o klädställ för tak- o golvmontage med patenterat klädupphängnings-system (Enwex Kulgalge-Galgen som inte faller). Arbetsbockar. Rörspett: Varunamn Praktic",
            "employees": null,
            "capital": 153100,
            "key_personnel": [
                {
                    "name": "Civiling H Norberg",
                    "position": "Styrelseordf"
                },
                {
                    "name": "Civiling H Norberg",
                    "position": "Verkst dir"
                }
            ],
            "establishment_year": 1947
        },
        "15": {
            "company_name": "GARPHYTTE BRUK, AB",
            "pnr": "71016",
            "address": "Garphyttan",
            "phone_number": "019-980 00",
            "bank_details": {
                "bankgiro": "160-1053",
                "postgiro": "8266-9"
            },
            "activity": "Manufakturverk med tråddrageri, stålline- o fjäderfabrik",
            "employees": 700,
            "annual_turnover": 75000000,
            "capital": 15000000,
            "key_personnel": [
                {
                    "name": "Henrik Werme",
                    "position": "Verkst dir"
                }
            ],
            "establishment_year": 1906
        }
    }
}