{
    "original": "VÄNNÄS DORR AB\n\nPnr 91100\n\nVännäs, Box 1030. Industrig. Tel\n0935-109 70. Bankgiro 76-5750.\nPostgiro 296588-7\nVerksamhet: Tillverkar o säljer\nin- o utvändiga dörrsnickerier i\nädelträ o för målning, glaspartier\ni ädelträ o för målning\nAntal anställda: 35\nÅrsomsättning: 3 000 000\nAktiekapital: 50 000\nStyrelse: Disp Ola Ingvarsson.\ndisp Osten Ingvarsson\nVerkst dir: Disp Ola Ingvarsson\nEtableringsår: 1924\nOmbildat till aktiebolag 1964.\n\nVÄRDESKYDD, AB\n\nPnr 800 08\n\nGävle 8, Box 8023. Tel\n026-18 03 60. Bankgiro 336-7257.\nPostgiro 13295-1\n\nAB |\n\nVÄRDESKYDD\n\nBROMMA HAGELINS\n\nVerksamhet: Tillverkar\ndokument-skåp, värdeskåp samt\nkassavalvsdörrar\n\nFörsäljningskontor: Stockholm,\nGrevg 12. Tel 08-67 90 70\nAntal anställda: 75\nVerkst dir: Rune Andersson\nEtableringsår: 1857\nNamnändring 1969.\n\nVÄRM-DAL, MASKIN AB\n\nPnr 65108\n\nKarlstad 1, Gjuterig 1. Box 510.\nTel 054-15 67 40. Bankgiro\n100-0827. Postgiro 290938-0. Tga\nVärmdal\n\nVerksamhet: Direktförsäljning av\nmaskiner för lantbruk-, skog-,\nindu-stri- o trädgårdsskötsel\nAntal anställda: 25\nÅrsomsättning: 6 000 000\nAktiekapital: 227 500\nStyrelse: Dir Karl Helmer (ordf),\ndir John Olsson, Olof Plantin, Per\nOlsson\n\nVerkst dir John Olsson\nEtableringsår: 1946.\n\nVÄRME- och\nSANITETS-TEKNISKA BYRÄN AB\n\nPnr 801 04\n\nGävle 1, Box 281. Kyrkog 28. Tel\n026-12 95 35. Bankgiro 783-8071.\nPostgiro 192285-5\n\nVerksamhet: utför projektering,\nkontroll o besiktning\nAntal anställda: 10\nÅrsomsättning: 500 000\nAktiekapital: 5 000\nVerkst dir: Gustav Rubensson\nEtableringsår: 1946.\n\nVÄRME- &amp; VENTILATIONS.\nSERVICE G ANDRE AB\n\nPnr 603 50\n\nNonköping, Albrektsv 89. Tel\n011-18 55 51. Bankgiro 82-6086.\nPostgiro 590610\n\nVerksamhet: Installation av\nventilationsanläggningar\nÅrsomsättning: 350 000\nAktiekapital: 10 000\nVerkst dir: Ing Gösta André\nEtableringsår: 1962.\n\nMELLBERGS BIL AB\n\nPnr 89100\n\nÖrnsköldsvik, staüonsplan 5. Tel\n066 0-10 1 90. Bankgiro 77-1571.\nPostgiro 366427-3\nVerksamhet: Säljer GM-bilar, båtar\no motorer\n\nAntal anstäUda: 50\nÅrsomsättning: 10000 000\nAktiekapital: 102 000\nVerkst dir: Ing Hans-Olof Mellberg\nEtableringsår: 1948.\n\nSANDIN, AB GEORG\n\nPnr 10460\n\nStockholm, Virkesv 26 C. Tel\n08-2340 80. Bankgiro 573-4587.\nPostgiro 251060-0\n\nVeiksamhet: Tillverkar fasader,\nfönster, dörrar samt övriga\nbyggnadsdetaljer i olika metaller.\nUtfor plåtarbeten\nAktiekapital: 75 000\nVeikst dir: Folke Hägg\nEtableringsår: 1947.\n\nSANDLUNDS KOMMUNAL.\nTEKNISKA BYRÄ AB\n\nPnr 602 22\n\nNorrköping, Slottsg 116. Tel\n011-13 9945. Postgiro 389142\nVeiksamhet: Konsulterande\ningenjörsbyrå\n\nAntal anställda: 12\n\nÅrsomsättning: 400000\nAktiekapital: 25 000\nVeikst dir: Ing John A Sandlund\nEtableringsår: 1948.\n\nmasonite ab\n\nPnr 910 02\n\nRundviksverken. Tel 0930-305 00.\nBankgiro 763-2268. Postgiro\n\n62486-6. Tga Masonite.\nTelex 54042\n\nVeiksamhet: Tillverkar sågade\nträvaror o träfiberplattor (Masonite)\nvid Rundviksverken samt\nflottnings-smide, traktorband o\nsläpvagnskopplingar vid Olofsfors.\nDistribuerar elektr kraft från Vännäs\nDotterbolag: Vännäs. Vännäs Kraft\nAB. Tel 0935-109 20\nVarunamn: Masonite\nAntal anstäUda: 748\nÅrsomsättning: 61500 000\nAktiekapital: 10 800 000\nVerkst dir: Hans Sköldkvist\nEtableringsår: 1861.\n\nLAGSTROM, AB E\n\nPnr 11221\n\nStockholm, Hantverkarg 18-20. Tel\n08-50 82 33, 50 84 60. Bankgiro\n166-0554. Postgiro 58347-6\nVerksamhet: Handel med in- o\nutländska konfektyrer o choklad\nAntal anställda: 8\n-Aktiekapital: 50 000\nVerkst dir: E Lag ström\nEtableringsår: 1917.\n\nHAK\n\nVamnamn: Haki\nAntal anställda: 80\nÅrsomsättning: 10000 000\nAktiekapital: 600 000\nStyrelse: Fabr Olle Olsson (ordf),\nfru Essie Olsson, fabr Agne Olsson,\nfru Ingrid Olsson\nVerkst dir: Agne Olsson\nExportchef: Henning Listerud\nKamrer: Sten Andersson\nVerkstadsing: Bengt&gt;Erik Persson\nInköpschef: Ingemar Olsson\nKonstruktion: Mats Turesson\nVeikmästare: Sven-Erik Johansson\nEtableringsår: 1909\nOmbildat till aktiebolag 1960.\n\nHAKONBOLAGET\n(AB HAKON SWENSON)\n\nPnr 72184\nAnslutet till ICA\nVästerås, Sjöhagsv 3. Tel\n021-144100. Postgiro 389080-3. Tga\nHakonbolaget. Telex 4702\nVerksamhet: Kolonialvaror, frukt,\ntextil, järn o husgeråd m m i parti\nAntal anställda: 1799\nÅrsomsättning: 1327 000 000\nAktiekapital: 18 780 000\nVerkst dir: Carl-Hakon Swenson\nEtableringsår: 1917.\n\nLINDAHL, AB AUG\n\nPnr 360 70\n\nAseda. Tel 0474-108 00. Bankgiro\n85-8558. Postgiro 33797\nVerksamhet: Tillverkar transport-\n\nanordningar for sågverk, bark- o\nhugganläggningar. Kylrör för\nglasindustrin. Utför elektr\ninstallationer i bostads- o industrilokaler.\nSäljer sågverksmaskiner, bark- o\nhuggmaskiner, cirkelsågverk, elektr\nmotorer samt maskinförnödenheter\nAntal anställda: 85\nÅrsomsättning: 10 000000\nAktiekapital: 500 000\nStyrelseordf: G B Lindahl\nVerkst din Henning Lindahl\nEtableringsår: 1941.\n\nCALIC, AB\n\nPnr 510 35\n\nBollebygd, Box 115. Kungsbackav\n5. Tel 033-852 45. Bankgiro\n844-6346. Postgiro 429480-7\nVerksamhet: Agentur o\nengrosför-säljning av vapen o ammunition\nAntal anställda: 8\nÅrsomsättning: 2 300 000\nAktiekapital: 50 000\nVerkst dir: Bengt Ake Carlsson\nEtableringsår: 1947.\n\nCALLIDUS AB,\nINGENIÖRSFIRMAN\n\nPnr 430 50\n\nKållered, Box 21. Tel 031-75 04 05.\nBankgiro 85-2807. Postgiro 422714.\nTga Callidussales\nVerksamhet: Säljer\noljeeldnings-aggregat o varmluftspannor\nAntal anställda: 17\nÅrsomsättning: 4 500 000\nAktiekapital: 60 000\nChefer: Ing O-G Bengtström, ing\nC-A Gilljam\nEtableringsår: 1950.\n\nLINJE.PAC AB\n\nPnr 131 03\n\nNacka 3, Turbinv 9 A. Fack. Tel\n08-716 94 30. Bankgiro 56-6624.\nPostgiro 603995\n\nVerksamhet: Säljer lås, dörrtrycken,\ngångjärn o skruv. Samt emballage\nav cellplast, plywood o trä\nAvdelningskontor: Göteborg C,\nViktoriag 2 A. Tel 031-1188 43\nVärnamo, Jönköpingsv 11. Tel\n0370-15510\n\nVarunamn: Por-Pac, Böda\nAntal anställda: 24\nÅrsomsättning: 14000 000\nAktiekapital: 120000\nVerkst dir: Bertil Voss-Schrader\nEtableringsår: 1959.\n\nLINJERING och PÄRM.\nINDUSTRI AB\n\nPnr 41108\n\nGöteborg C, Stcra Nyg 29. Tel\n031-1174 59, 1344 25\nVerksamhet: Tillverkar\nkontorsböcker, pärmar o register\nAktiekapital: 60000\nÄgare o chefer: Allan Persson,\nInga Persson\nEtableringsår: 1950.\n\nWENGELIN &amp; KALLMAN AB\n\nPnr 114 57\n\nStockholm, Riddarg 30. Tel\n08-62 89 01. Bankgiro 476-8974.\nPostgiro 54457-7. Tga Brokers\nVerksamhet: Säljer tvätteritillbehör\nengros\n\nÅrsomsättning: 300 000\nAktiekapital: 5 000\nVerkst dir L Lindström\nEtableringsår: 1921.",
    "structured": {
        "0": {
            "company_name": "VÄNNÄS DORR AB",
            "pnr": "91100",
            "address": "Vännäs, Box 1030. Industrig.",
            "phone_number": "0935-109 70",
            "bank_details": {
                "bankgiro": "76-5750",
                "postgiro": "296588-7"
            },
            "activity": "Tillverkar o säljer in- o utvändiga dörrsnickerier i ädelträ o för målning, glaspartier i ädelträ o för målning",
            "employees": 35,
            "annual_turnover": 3000000,
            "capital": 50000,
            "key_personnel": [
                {
                    "name": "Disp Ola Ingvarsson",
                    "position": "Styrelse"
                },
                {
                    "name": "disp Osten Ingvarsson",
                    "position": "Styrelse"
                },
                {
                    "name": "Disp Ola Ingvarsson",
                    "position": "Verkst dir"
                }
            ],
            "establishment_year": 1924
        },
        "1": {
            "company_name": "VÄRDESKYDD, AB",
            "pnr": "80008",
            "address": "Gävle 8, Box 8023",
            "phone_number": "026-18 03 60",
            "bank_details": {
                "bankgiro": "336-7257",
                "postgiro": "13295-1"
            },
            "activity": "Tillverkar dokument-skåp, värdeskåp samt kassavalvsdörrar",
            "employees": 75,
            "establishment_year": 1857
        },
        "2": {
            "company_name": "VÄRM-DAL, MASKIN AB",
            "pnr": "65108",
            "address": "Karlstad 1, Gjuterig 1. Box 510",
            "phone_number": "054-15 67 40",
            "bank_details": {
                "bankgiro": "100-0827",
                "postgiro": "290938-0"
            },
            "activity": "Direktförsäljning av maskiner för lantbruk-, skog-, indu-stri- o trädgårdsskötsel",
            "employees": 25,
            "annual_turnover": 6000000,
            "capital": 227500,
            "key_personnel": [
                {
                    "name": "Dir Karl Helmer",
                    "position": "Styrelse"
                },
                {
                    "name": "Dir John Olsson",
                    "position": "Styrelse"
                },
                {
                    "name": "Olof Plantin",
                    "position": "Styrelse"
                },
                {
                    "name": "Per Olsson",
                    "position": "Styrelse"
                },
                {
                    "name": "Verkst dir John Olsson",
                    "position": "Verkst dir"
                }
            ],
            "establishment_year": 1946
        },
        "3": {
            "company_name": "VÄRME- och SANITETS-TEKNISKA BYRÄN AB",
            "pnr": "80104",
            "address": "Gävle 1, Box 281. Kyrkog 28",
            "phone_number": "026-12 95 35",
            "bank_details": {
                "bankgiro": "783-8071",
                "postgiro": "192285-5"
            },
            "activity": "utför projektering, kontroll o besiktning",
            "employees": 10,
            "annual_turnover": 500000,
            "capital": 5000,
            "key_personnel": [
                {
                    "name": "Gustav Rubensson",
                    "position": "Verkst dir"
                }
            ],
            "establishment_year": 1946
        },
        "4": {
            "company_name": "VÄRME- & VENTILATIONS. SERVICE G ANDRE AB",
            "pnr": "60350",
            "address": "Nonköping, Albrektsv 89",
            "phone_number": "011-18 55 51",
            "bank_details": {
                "bankgiro": "82-6086",
                "postgiro": "590610"
            },
            "activity": "Installation av ventilationsanläggningar",
            "annual_turnover": 350000,
            "capital": 10000,
            "key_personnel": [
                {
                    "name": "Ing Gösta André",
                    "position": "Verkst dir"
                }
            ],
            "establishment_year": 1962
        },
        "5": {
            "company_name": "MELLBERGS BIL AB",
            "pnr": "89100",
            "address": "Örnsköldsvik, staüonsplan 5",
            "phone_number": "066 0-10 1 90",
            "bank_details": {
                "bankgiro": "77-1571",
                "postgiro": "366427-3"
            },
            "activity": "Säljer GM-bilar, båtar o motorer",
            "employees": 50,
            "annual_turnover": 10000000,
            "capital": 102000,
            "key_personnel": [
                {
                    "name": "Ing Hans-Olof Mellberg",
                    "position": "Verkst dir"
                }
            ],
            "establishment_year": 1948
        },
        "6": {
            "company_name": "SANDIN, AB GEORG",
            "pnr": "10460",
            "address": "Stockholm, Virkesv 26 C",
            "phone_number": "08-2340 80",
            "bank_details": {
                "bankgiro": "573-4587",
                "postgiro": "251060-0"
            },
            "activity": "Tillverkar fasader, fönster, dörrar samt övriga byggnadsdetaljer i olika metaller. Utfor plåtarbeten",
            "capital": 75000,
            "key_personnel": [
                {
                    "name": "Folke Hägg",
                    "position": "Veikst dir"
                }
            ],
            "establishment_year": 1947
        },
        "7": {
            "company_name": "SANDLUNDS KOMMUNAL. TEKNISKA BYRÄ AB",
            "pnr": "60222",
            "address": "Norrköping, Slottsg 116",
            "phone_number": "011-13 9945",
            "postgiro": "389142",
            "activity": "Konsulterande ingenjörsbyrå",
            "employees": 12,
            "annual_turnover": 400000,
            "capital": 25000,
            "key_personnel": [
                {
                    "name": "Ing John A Sandlund",
                    "position": "Veikst dir"
                }
            ],
            "establishment_year": 1948
        },
        "8": {
            "company_name": "masonite ab",
            "pnr": "910 02",
            "activity": "Tillverkar sågade trävaror o träfiberplattor (Masonite) vid Rundviksverken samt flottnings-smide, traktorband o släpvagnskopplingar vid Olofsfors. Distribuerar elektr kraft från Vännäs Dotterbolag: Vännäs. Vännäs Kraft AB.",
            "employees": 748,
            "annual_turnover": 61500000,
            "capital": 10800000,
            "key_personnel": [
                {
                    "name": "Hans Sköldkvist",
                    "position": "Verkst dir"
                }
            ],
            "establishment_year": 1861
        },
        "9": {
            "company_name": "LAGSTROM, AB E",
            "pnr": "11221",
            "address": "Stockholm, Hantverkarg 18-20",
            "phone_number": "08-50 82 33, 50 84 60",
            "bank_details": {
                "bankgiro": "166-0554",
                "postgiro": "58347-6"
            },
            "activity": "Handel med in- o utländska konfektyrer o choklad",
            "employees": 8,
            "capital": 50000,
            "key_personnel": [
                {
                    "name": "E Lag ström",
                    "position": "Verkst dir"
                }
            ],
            "establishment_year": 1917
        },
        "10": {
            "company_name": "HAK",
            "activity": "Tillverkar och säljer..."
        },
        "11": {
            "company_name": "HAKONBOLAGET",
            "pnr": "72184",
            "address": "Västerås, Sjöhagsv 3",
            "phone_number": "021-144100",
            "postgiro": "389080-3",
            "activity": "Kolonialvaror, frukt, textil, järn o husgeråd m m i parti",
            "employees": 1799,
            "annual_turnover": 1327000000,
            "capital": 18780000,
            "key_personnel": [
                {
                    "name": "Carl-Hakon Swenson",
                    "position": "Verkst dir"
                }
            ],
            "establishment_year": 1917
        },
        "12": {
            "company_name": "LINDAHL, AB AUG",
            "pnr": "36070",
            "address": "Aseda",
            "phone_number": "0474-108 00",
            "bank_details": {
                "bankgiro": "85-8558",
                "postgiro": "33797"
            },
            "activity": "Tillverkar transport-anordningar for sågverk, bark- o hugganläggningar. Kylrör för glasindustrin. Utför elektr installationer i bostads- o industrilokaler. Säljer sågverksmaskiner, bark- o huggmaskiner, cirkelsågverk, elektr motorer samt maskinförnödenheter",
            "employees": 85,
            "annual_turnover": 10000000,
            "capital": 500000,
            "key_personnel": [
                {
                    "name": "G B Lindahl",
                    "position": "Styrelseordf"
                },
                {
                    "name": "Henning Lindahl",
                    "position": "Verkst din"
                }
            ],
            "establishment_year": 1941
        },
        "13": {
            "company_name": "CALIC, AB",
            "pnr": "51035",
            "address": "Bollebygd, Box 115. Kungsbackav 5",
            "phone_number": "033-852 45",
            "bank_details": {
                "bankgiro": "844-6346",
                "postgiro": "429480-7"
            },
            "activity": "Agentur o engrosför-säljning av vapen o ammunition",
            "employees": 8,
            "annual_turnover": 2300000,
            "capital": 50000,
            "key_personnel": [
                {
                    "name": "Bengt Ake Carlsson",
                    "position": "Verkst dir"
                }
            ],
            "establishment_year": 1947
        },
        "14": {
            "company_name": "CALLIDUS AB, INGENIÖRSFIRMAN",
            "pnr": "43050",
            "address": "Kållered, Box 21",
            "phone_number": "031-750 405",
            "bank_details": {
                "bankgiro": "85-2807",
                "postgiro": "422714"
            },
            "activity": "Säljer oljeeldnings-aggregat o varmluftspannor",
            "employees": 17,
            "annual_turnover": 4500000,
            "capital": 60000,
            "key_personnel": [
                {
                    "name": "Ing O-G Bengtström",
                    "position": "Chefer"
                },
                {
                    "name": "Ing C-A Gilljam",
                    "position": "Chefer"
                }
            ],
            "establishment_year": 1950
        },
        "15": {
            "company_name": "LINJE.PAC AB",
            "pnr": "13103",
            "address": "Nacka 3, Turbinv 9 A",
            "phone_number": "08-716 94 30",
            "bank_details": {
                "bankgiro": "56-6624",
                "postgiro": "603995"
            },
            "activity": "Säljer lås, dörrtrycken, gångjärn o skruv. Samt emballage av cellplast, plywood o trä",
            "employees": 24,
            "annual_turnover": 14000000,
            "capital": 120000,
            "key_personnel": [
                {
                    "name": "Bertil Voss-Schrader",
                    "position": "Verkst dir"
                }
            ],
            "establishment_year": 1959
        },
        "16": {
            "company_name": "LINJERING och PÄRM. INDUSTRI AB",
            "pnr": "41108",
            "address": "Göteborg C, Stcra Nyg 29",
            "phone_number": "031-1174 59, 1344 25",
            "activity": "Tillverkar kontorsböcker, pärmar o register",
            "capital": 60000,
            "key_personnel": [
                {
                    "name": "Allan Persson",
                    "position": "Ägare o chefer"
                },
                {
                    "name": "Inga Persson",
                    "position": "Ägare o chefer"
                }
            ],
            "establishment_year": 1950
        },
        "17": {
            "company_name": "WENGELIN & KALLMAN AB",
            "pnr": "11457",
            "address": "Stockholm, Riddarg 30",
            "phone_number": "08-628901",
            "bank_details": {
                "bankgiro": "476-8974",
                "postgiro": "54457-7"
            },
            "activity": "Säljer tvätteritillbehör engros",
            "annual_turnover": 300000,
            "capital": 5000,
            "key_personnel": [
                {
                    "name": "L Lindström",
                    "position": "Verkst dir"
                }
            ],
            "establishment_year": 1921
        }
    }
}