{
    "original": "G RONMARK AB, SVEN\n\nPnr 175 00\n\nJakobsberg, Box 51. Lidv 4. Tel\n0758-347 00. Bankgiro 392-3158.\nPostgiro 73737-9\n\nVerksamhet: Importerar väggpaneler\nVarunamn: Solpanel\nAntal anställda: 5\nÅrsomsättning: 1000 000\nAktiekapital: 5 000\nVerkst dir: Sven Grönmark\nEtableringsår: 1965.\n\nGRONVALL AB, INGENIORS\n-FIRMA STURE\n\nPnr 182 36\n\nDanderyd, Danaröv 16. Tel\n08-755 96 70, 755 96 80. Bankgiro\n870-3720. Postgiro 656530-3\nVerksamhet: Säljer färger, fernissor\no avfettningsmedel\nAktiekapital: 10 000\nVerkst dir: Ing Sture Grönvall\nEtableringsår: 1957.\n\nGRONVALL ORGELBYGGERI,\nJOHN\n\nPnr 463 00\n\nLilla Edet. Göteborgsv 22. Tel\n0520-505 34, 51186. Bankgiro\n891-0366. Postgiro 164953-2\nVerksamhet: Tillverkar kyrkorglar\ni alla storlekar. Utför reparation\no renoveringar av äldre orglar.\nSäljer musikinstrument\nAntal anställda: 6\nÅrsomsättning: 350 000\nChefer: Bo Grönvall, Bertil\nGrönvall\n\nEtableringsår: 1927.\n\nGRONVALLS LÄDERFABRIK,\nAB WILH\n\nPnr 262 01\n\nÄngelholm 1, Storg 71. Fack. Tel\n0431-137 00. Bankgiro 672-2300.\nPostgiro 73550-6. Tga Grönvall.\nTelex 72384\n\nVerksamhet: Tillverkar\nskoovanläder, stövelläder, toffelläder,\nreseffektläder o packningar\nAntal anställda: 190\nÅrsomsättning: 25 250 000\nAktiekapital: 2 500 000\nStyrelse: Konsul Ingemar Ekblom\n(ordf), kapten Ake Engström, med\ndr Herman Grönvall, dir Wilhelm\nGrönvall, disp Jan Ekblom\nVerkst dir: Wilhelm Grönvall\nFörsäljningschefer: Edvard\nLehmann, Staffan Rydinger\nEtableringsår: 1858.\n\nETON AB\n\nPnr 510 51\n\nGånghester, Stora v 8. Tel\n033-56 1 00. Bankgiro 360-8 1 97.\nPostgiro 169930-5\n\nVerksamhet: Tillverkar\nherrskjortor\n\nAktiekapital: 180000\nVerkst dir: Rune Davidsson\nEtableringsår: 1955.\n\nETRI ERIKSSONS\nTRÄINDUSTRIER AB\n\nPnr 930 64\n\nBjurträsket. Tel 0918-230 70.\nBankgiro 763-4231. Postgiro 61415-6\nVerksamhet: Tillverkar fönster o\nutfackningspartier, trävit laserad\no målad list samt sågade o hyvlar\nde trävaror\nAntal anställda: 165\nÅrsomsättning: 11000 000\nAktiekapital; 250 000\nVerkst din Sten Sernevi\nPlatschef: Ing Per-Olov Eriksson\nProduktionschef: Ing Geje Persson\nPlaneringschef: Ing Stig Wiksten\nEkonomichef: Kamrer Helge Renberg\nEtableringsår: 1908.\n\nEURENIUS AB, MASKIN.\nFIRMAN C G\n\nPnr 65107\n\nKarlstad 1, box 436. Gjuterig 5.\nTel 054-18 01 50. Bankgiro 344-4379.\nPostgiro 291160-0. Tga Eurenius\nVerksamhet: Säljer\nKockum-Landsverk gräv-, last- o\ntransportmaskiner, John Deere hjullastmaskiner,\nAB Bofors slitdetaljer för entrepre-\n\nnadmaskiner samt Svenska\nStålline-fabrikens stållinor o tillbehör.\nRenoveringsverkstad för\nentreprenadmaskiner\n\nAvdelningskontor: Falun,\nSvärd-sjög 11. Tel 023-174 50\nÖrebro, Slussg 5. Tel 019-12 08 22\nAntal anställda: 40\nÅrsomsättning: 13 000 000\nAktiekapital: 500 000\nStyrelse: Bankdir Emil Gill (ordf),\nadv Bertil Cederlöv, dir C G\nEurenius, rektor Malte Eurenius, Lars\nGöran Eurenius\nVerkst dir: C G Eurenius\nEtableringsår: 1945\nOmbildat till aktiebolag 1952.\n\nEURODRIVE AB\n\nPnr 550 07\n\nJönköping 7, Box 7062. Gnejsv 6-8.\nTel 036-1650 70. Bankgiro\n201-6657. Postgiro 230433-5. Telex\n70162\n\nVerksamhet: Tillverkar o monterar\nkugg- o snäckväxlar, kugg- o\nsnäckväxelmotorer, variatorer,\nel-motorer, kopplingar m m\nAvdelningskontor: Göteborg. Arne\nLeijon &amp; Co AB, Kyrkv 37, Askim.\nTel 031-281188, 28 08 58\nMalmö. Ingenjörsfirma Erie\nFransson, Viking ag 28. Tel 040-15 15 34\nVarunamn: Rollastic, Varibloc,\nVaridisc, Varimot\nAntal anställda: 30\nAktiekapital; 375 000\nVerkst din Ing Hans Appelgren\nFörsäljn-chef: Ing Birger Bring\nVerkstadschef: Ing Karl Wischer\nEtableringsår 1968\nDotterbolag till Süddeutsche\nElek-tro-Motoren Werke, Bruchsal,\nVästtyskland.\n\nEUROMEKAN AB\n\nPnr 44101\n\nAlingsås 1, Box 69. Kungsg 4. Tel\n0322-170 70. Bankgiro\n84-6324-Postgiro 628069. Tga Euromekan.\nTelex 2432 EUROMEK S\nVerksamhet:\nHögtryckstvättaggre-gat, kemisk-tekniska produkter för\nrengöring\n\nAvdelningskontor: 126 55 Hägersten,\nSelmedalsv 46. Tel 08-9714 50\n214 64 Malmö, Kulladalsg 24 A.\nTel 040-96 35 60\nVarunamn: Euroclean\nAntal anställda: 105\nVerkst dir: Fredrik Schumacher\nMarknadschef: G Rendefors\nEtableringsår: 1965.\n\nOLS\n\nVarunamn: Anhydrol, Antivermin,\nCarbosol, Carlinum, Hydropal,\nKop-ralin, Mammut\nAktiekapital: 530 200\nVerkst dir: Ake Rydberg\nEtableringsår: 1859\nOmbildat till aktiebolag 1899.\n\nOLSSON, AB KARL W\n\nPnr 113 51\n\nStockholm, Odeng 45. Tel\n08-349240. Bankgiro 576-2893.\nPostgiro 351366-0. Tga Karlwols.\nTelex 10114 KARLWOL S\nVerksamhet: Grossist-o\nagenturhandel med elektr installationsmaterial\nAntal anställda: 20\nAktiekapital: 25 000\nVerkst dir: Karl W Olsson\nEtableringsår: 1953.\n\nAIR\n\nÅrsomsättning: 360 000\nAktiekapital: 5 000\nVerkst dir: Fabr Gerhard Thellman\nEtableringsår: 1960.\n\nfalk &amp; co ltd ab\n\nPnr 114 45\n\nStockholm, Artillerig 40. Tel 08-\n\n63 67 26, 63 67 27. Bankgiro\n565-2268. Postgiro 253016-0. Tga\nFalcom\n\nVerksamhet: Import o export av\nhushålls- o projektionsartiklar\nAktiekapital: 25 000\nVerkst dir: Civilekonom Hugo Falk\nEtableringsår: 1946.\n\nDOM\n\nFörsäljningskontor: 302 45\nHalmstad, Kungsg 10. Tel 035-104030\n113 30 Stockholm, Gävleg 12 A.\nTel 08-34 91 60\n\n400 62 Göteborg 29, Box 29006.\nTorkelsg 4 A. Tel 031-15 3840\n21120 Malmö, Nordenskiöldsg 17.\nTel 040-399 95\n\nVamnamn: Duni, Bilå, Dunicel\nAntal anställda: 800\nÅrsomsättning: 100 000 000\nStyrelse: Disp Göran Forsell (ordf),\ndir Arne Lundin, ekonomidir Claes\nReuterskiöld\nVeikst din Arne Lundin\nMarknadsdir.n Gösta Fransson,\nAke Ryding (export), Olof Stigmar\nEkonomidir: Martti Heino\nEtableringsår: 1970.\n\nNÄRKES ELEKTRISKA AB\n\nPnr 70102\n\nÖrebro 1, Box 45. Klerkg 18. Tel\n019-1249 59. Bankgiro 815-49 65.\nPostgiro 36003-2. Telex 73233\nVerksamhet: Elektr installationer\no hissanläggningar\nAntal anställda: 200\nÅrsomsättning: 26 000 000\nAktiekapital: 1000 000\nVerkst dir: Ingmar Broberg\nEtableringsår: 1931.\n\nVVS-TEKNIK AB\n\nPnr 217 63\n\nMalmö. Hallingsg 6 B. Tel\n040-865 30. Bankgiro 26-3488. Postgiro\n247473\n\nVerksamhet: Konsulterande\ningenjörsbyrå avseende värme,\nventilation, kyl o sanitet\nAvdelningskontor: 222 22 Lund.\nKlosterg 9. Tel 046-12 4 8 60\nAntal anställda: 49\nÅrsomsättning: 2 500 000\nAktiekapital: 100 000\nVerkst dir: Ing Sig Holst\nEtableringsår: 1953.\n\nALPUS AB\n\nPnr 442 00\n\nKungälv, Box 46. Byggmästareg 8.\nTel 0303-15315. Bankgiro\n514-3102. Postgiro 43496-9\nVerksamhet: Släpvagnar\nAntal anställda: 30\nÅrsomsättning: 4 000000\nAktiekapital: 100 000\nVerkst dir: Lennart Sandberg\nEtableringsår: 1935.\n\nSVENSKA KONRDR AB\n\nPnr 170 24\n\nSkälby, Ve g av 43. Tel 08-89 43 97.\nBankgiro 239-3395. Postgiro\n674041-9\n\nVeiksamhet: Mek verkstad. Utför\ngas- o elsvetsning. Tillverkar\nman-tågsstöttor. Specialitet: koniska\nrör max 50 mm\nAktiekapital: 5 000\nVerkst dir: Georg Swedel\nEtableringsår: 1965.\n\nSVENSKA KONSULTERANDE\nINGENJÖRERS FÖRENING\n(SKIF)\n\nPnr 11438\n\nStockholm, Grev Tureg 29. Tel\n08-67 02 05. Bankgiro 569-4138.\nPostgiro 2902-5\n\nVerkst dir: Civiling Ragnar\nWide-gren\n\nEtableringsår: 1910.\n\nSVENSKA\nKONTORSMUBEL-INDUSTRIER, AB\n\nPnr 100 61\n\nStockholm 11, Erstag 9. Box 11031.\nTel 08-43 85 77, 43 96 32. Postgiro\n152953. Tga Askmi\nVerksamhet: Tillverkar o säljer\nkontorsmöbler o inredningar\nFabrik: Eksjö. Tel 0381-107 47\nAntal anställda: 35\nAktiekapital: 15 000\nVerkst dir: Folke Rudén\nEtableringsår: 1937.",
    "structured": {
        "0": {
            "company_name": "G RONMARK AB",
            "pnr": "175 00",
            "address": "Jakobsberg, Box 51. Lidv 4",
            "phone_number": "0758-347 00",
            "bank_details": {
                "bankgiro": "392-3158",
                "postgiro": "73737-9"
            },
            "activity": "Importerar väggpaneler",
            "employees": 5,
            "annual_turnover": 1000000,
            "capital": 5000,
            "key_personnel": [
                {
                    "name": "Sven Grönmark",
                    "position": "Verkst dir"
                }
            ],
            "establishment_year": 1965
        },
        "1": {
            "company_name": "GRONVALL AB",
            "pnr": "182 36",
            "address": "Danderyd, Danaröv 16",
            "phone_number": "08-755 96 70, 755 96 80",
            "bank_details": {
                "bankgiro": "870-3720",
                "postgiro": "656530-3"
            },
            "activity": "Säljer färger, fernissor o avfettningsmedel",
            "capital": 10000,
            "key_personnel": [
                {
                    "name": "Ing Sture Grönvall",
                    "position": "Verkst dir"
                }
            ],
            "establishment_year": 1957
        },
        "2": {
            "company_name": "GRONVALL ORGELBYGGERI, JOHN",
            "pnr": "463 00",
            "address": "Lilla Edet. Göteborgsv 22",
            "phone_number": "0520-505 34, 51186",
            "bank_details": {
                "bankgiro": "891-0366",
                "postgiro": "164953-2"
            },
            "activity": "Tillverkar kyrkorglar i alla storlekar. Utför reparation o renoveringar av äldre orglar. Säljer musikinstrument",
            "employees": 6,
            "annual_turnover": 350000,
            "key_personnel": [
                {
                    "name": "Bo Grönvall",
                    "position": "Chefer"
                },
                {
                    "name": "Bertil Grönvall",
                    "position": "Chefer"
                }
            ],
            "establishment_year": 1927
        },
        "3": {
            "company_name": "GRONVALLS LÄDERFABRIK, AB WILH",
            "pnr": "262 01",
            "address": "Ängelholm 1, Storg 71",
            "phone_number": "0431-137 00",
            "bank_details": {
                "bankgiro": "672-2300",
                "postgiro": "73550-6"
            },
            "activity": "Tillverkar skoovanläder, stövelläder, toffelläder, reseffektläder o packningar",
            "employees": 190,
            "annual_turnover": 25250000,
            "capital": 2500000,
            "key_personnel": [
                {
                    "name": "Wilhelm Grönvall",
                    "position": "Verkst dir"
                }
            ],
            "establishment_year": 1858
        },
        "4": {
            "company_name": "ETON AB",
            "pnr": "510 51",
            "address": "Gånghester, Stora v 8",
            "phone_number": "033-56 1 00",
            "bank_details": {
                "bankgiro": "360-8 1 97",
                "postgiro": "169930-5"
            },
            "activity": "Tillverkar herrskjortor",
            "capital": 180000,
            "key_personnel": [
                {
                    "name": "Rune Davidsson",
                    "position": "Verkst dir"
                }
            ],
            "establishment_year": 1955
        },
        "5": {
            "company_name": "ETRI ERIKSSONS TRÄINDUSTRIER AB",
            "pnr": "930 64",
            "address": "Bjurträsket",
            "phone_number": "0918-230 70",
            "bank_details": {
                "bankgiro": "763-4231",
                "postgiro": "61415-6"
            },
            "activity": "Tillverkar fönster o utfackningspartier, trävit laserad o målad list samt sågade o hyvlarde trävaror",
            "employees": 165,
            "annual_turnover": 11000000,
            "capital": 250000,
            "key_personnel": [
                {
                    "name": "Sten Sernevi",
                    "position": "Verkst dir"
                },
                {
                    "name": "Ing Per-Olov Eriksson",
                    "position": "Platschef"
                },
                {
                    "name": "Ing Geje Persson",
                    "position": "Produktionschef"
                },
                {
                    "name": "Ing Stig Wiksten",
                    "position": "Planeringschef"
                },
                {
                    "name": "Kamrer Helge Renberg",
                    "position": "Ekonomichef"
                }
            ],
            "establishment_year": 1908
        }
    }
}