{
    "original": "FRI\n\nFRITZELL, AB G\n\nPnr 570 41\n\nFrinnaryd, Box 113. Tel 0140-20011,\n20047. Bankgiro 13-0522.Postgiro\n273385\n\nVerksamhet: Tillverkar\nstålrörste-gar, expansionskärl o VVS-armatur\nAntal anställda: 25\nAktiekapital: 100 000\nVerkst dir: Gillis Fritzell\nEtableringsår: 1904.\n\nOLS\n\nFilialer: Malmö C, Söderg 1. Tel\n040-70170\nAntal anstäUda: 164\nÅrsomsättning: 14 400 000\nAktiekapital: 1500 000\nStyrelse: Dir Thorsten Westerström\n(ordf), dir Ake Arenhill, dir Thor\nOhlsson, kamrer Börje Warnbeck,\ndlr Botvid Wedeen\nVerkst dir: Thor Ohlsson\nEtableringsår: 1887.\n\nOLSSONS INDUSTRIER AB,\nEINAR\n\nPnr 283 00\n\nOsby. Tel 0479-105 80, 124 53.\nBankgiro 281-6023. Postgiro\n512217-1\n\nVerksamhet: Tillverkar\nträdgårdsmöbler i trä o stål samt olika slag\nav rörstommar. Plastbeläggning av\nrörstommar med EPOXY-pulver\neller PVC. Tryckimpregnering\nAntal anstäUda: 60\nÅrsomsättning: 4 500 000\nAktiekapital: 40 000\nVerkst dir: Einar Olsson\nEtableringsår: 1934.\n\nVÄTTERTEGEL AB\n\nPnr 560 40\n\nHabo, Baskarp. Tel 036-43150.\nBankgiro 21-8379. Postgiro 443277\nVerksamhet: Tillverkar\nkalksand-sten för fasader o mellanväggar,\nfogbruk m m\nAktiekapital: 500 000\nVeikst dir: Folke Mårtensson\nEtableringsår 1963.\n\nAUTOLACKING, AB\n\nPnr 360 30\n\nLammhult. Tel 0472-603 10\nVerksamhet: Utför billackering,\nugnslackering, bilriktning o\nkaros-serireparationer\n\nFirmatecknare: Lennart Andersson,\nHenry Johansson\nEtableringsår: 1953.\n\nNILSSON, AB ERIK V\n\nPnr 217 58\n\nMalmö, Tessins v 8. Tel\n040-9149 77. Bankgiro 876-1108.\nPostgiro 432644-3\n\nVerksamhet: Trävaror, specialitet:\nsågad o helböjd bok, hyvlade lister\nsamt formpressade detaljer\nFilial: Östra Ljungby. Tel\n0435-215 35\n\nAktiekapital: 20 000\nVerkst dir: Erik V Nilsson\nEtableringsår: 1953.\n\nTHELIN &amp; CO, SKOFABRIKS\nAB\n\nPnr 330 23\n\nSmålandsstenar, Box 18. Oxelg.\nTel 0371-30620. Bankgiro\n427-6713. Postgiro 510609-1\nVerksamhet: Tillverkar arbetsskor\no arbetsstövlar\nAntal anställda: 12\nÅrsomsättning: 800 000\nChefer Evert Thelin, Thure\nCarlsson, Lennart Eriksson\nEtableringsår. 1959.\n\nSEWIN, INGENJURSFIRMAN\n\nPnr 56100\n\nHuskvarna, Hagstensg 22. Tel\n036-1316 89\n\nVerksamhet: Tillverkar dubbelkon-\n\nblandare, siktar\n\nÄgare o chefer Stig Efverlund,\n\nGustaf Winqvist\n\nEtableringsår. 1948.\n\nSEXDREGA SYFABRIK,\nAHL &amp; CO\n\nPnr 512 02\n\nSvenljunga 2, Box 38. Tel\n0325-25200. Bankgiro 43-7529. Postgiro\n283617\n\nVerksamhet: Tillverkar herr- o\npojkpyjamas, fritidsskjortor,\nundershorts, dressinggown, rökrockar,\nbadrockar o badbyxor\nAntal anställda: 50\nÅrsomsättning: 2 200000\nChefen Herman Ahl, Einar\nHög-feldt, Valter Svensson\nEtableringsår. 1939.\n\nWALFRIDSON &amp; CO, E\n\nPnr 57100\n\nNässjö, Stensjön. Tel 0380-91130.\nBankgiro 452-7891\nVerksamhet: Tillverkar\nrörledningsarmatur i mässing o rödgods. Utför\nautomatsvarvning\nAntal anstäUda: 14\nÅrsomsättning: 1000 000\nChef: Fabr Viktor Walfridson\nEtableringsår: 1946.\n\nNILSSONS FABRIKER, AB A W\n\nPnr 291 02\n\nKristianstad 2, Industrig. Box 2095.\nTel 044J12 30 40. Bankgiro 26-4243.\nPostgiro 38576-5. Tga Awnilsson\nVerksamhet: TUlverkar barnvagnar\no tillbehör till dessa, stålmöbler,\nsjukhusmöbler o vårdmateriel. Utför\ninredningsarbeten i stålrör o\nrör-konstruktioner efter ritning\nAntal anstäUda: 110\nÅrsomsättning: 7 000 000\nAktiekapital: 625 000\nVerkst dir: Yngve Rollof\nKontors- o inköpschef:\nK-I Magnusson\n\nFörsäljn-chef: Tage Andersson\nEtableringsår: 1855.\n\nfalkenbergs\nkartong-fabrik ab\n\nPnr 31100\n\nFalkenberg, Schubergsv 24. Tel\n0346-11216, 106 46. Bankgiro\n425-7119. Postgiro 289717-1\nVerksamhet: Tillverkar\nskokartonger, kapslar, industrikartonger (ej\nwellpapp) o konfektionsväskor\nAntal anstäUda: 19\nÅrsomsättning: 1 200 000\nAktiekapital: 30 000\nVerkst dir: Kurt Anderson\nEtableringsår: 1947\nOmbildat till aktiebolag 1963.\n\nfalkenbergs kolimport,\nLINDVALL &amp; co\n\nPnr 31100\n\nFalkenberg, Tegelbruksv 15. Tel\n0346-144 05. Bankgiro 42-5712.\nPostgiro 289660. Tga Kolimporten\nVerksamhet: Säljer eldningsoljor,\ntankrengöring. Medlem av STOR\nChef: Disp Nils Schtitt.\n\nfalkenbergs tegelbruks\nAB\n\nPnr 31100\n\nFalkenberg, Tegelbruksv 16. Tel\n0346-144 30. Bankgiro 361-3445.\nPostgiro 370121-6. Tga Tegelbruket\nVerksamhet: Tillverkar\ndräneringsrör svensk standard\nAntal anstäUda: 47\nÅrsomsättning: 3 000 000\nAktiekapital: 390 000\nStyrelse: Dlr N E Lindvall,\nmarin-dir H Hallberg, disp S E\nChristianson, kamrer H Engström, disp N\nSchütt\n\nVerkst dir: Nils Schütt\nEtableringsår. 1904.",
    "structured": {
        "1": {
            "company_name": "Fritzell, AB Gillis",
            "pnr": "570 41",
            "address": "Frinnaryd, Box 113",
            "phone_number": "0140-20011, 20047",
            "bank_details": {
                "bankgiro": "13-0522",
                "postgiro": "273385"
            },
            "activity": "Tillverkar stålrörstegar, expansionskärl o VVS-armatur",
            "employees": 25,
            "capital": 100000,
            "key_personnel": [
                {
                    "name": "Gillis Fritzell",
                    "position": "Verkst dir"
                }
            ],
            "establishment_year": 1904
        },
        "2": {
            "company_name": "Ols",
            "address": "Malmö C, Söderg 1",
            "phone_number": "040-70170",
            "employees": 164,
            "annual_turnover": 14400000,
            "capital": 1500000,
            "key_personnel": [
                {
                    "name": "Thorsten Westerström",
                    "position": "Styrelse"
                },
                {
                    "name": "Ake Arenhill",
                    "position": "Styrelse"
                },
                {
                    "name": "Thor Ohlsson",
                    "position": "Verkst dir"
                }
            ],
            "establishment_year": 1887
        },
        "3": {
            "company_name": "Olssons Industrier AB, Einar",
            "pnr": "283 00",
            "address": "Osby",
            "phone_number": "0479-105 80, 124 53",
            "bank_details": {
                "bankgiro": "281-6023",
                "postgiro": "512217-1"
            },
            "activity": "Tillverkar trädgårdsmöbler i trä o stål samt olika slag av rörstommar. Plastbeläggning av rörstommar med EPOXY-pulver eller PVC. Tryckimpregnering",
            "employees": 60,
            "annual_turnover": 4500000,
            "capital": 40000,
            "key_personnel": [
                {
                    "name": "Einar Olsson",
                    "position": "Verkst dir"
                }
            ],
            "establishment_year": 1934
        },
        "4": {
            "company_name": "Vättertegel AB",
            "pnr": "560 40",
            "address": "Habo, Baskarp",
            "phone_number": "036-43150",
            "bank_details": {
                "bankgiro": "21-8379",
                "postgiro": "443277"
            },
            "activity": "Tillverkar kalksandsten för fasader o mellanväggar, fogbruk m m",
            "capital": 500000,
            "key_personnel": [
                {
                    "name": "Folke Mårtensson",
                    "position": "Veikst dir"
                }
            ],
            "establishment_year": 1963
        },
        "5": {
            "company_name": "Autolacking AB",
            "pnr": "360 30",
            "address": "Lammhult",
            "phone_number": "0472-603 10",
            "activity": "Utför billackering, ugnslackering, bilriktning o karosserireparationer",
            "key_personnel": [
                {
                    "name": "Lennart Andersson",
                    "position": "Firmatecknare"
                },
                {
                    "name": "Henry Johansson",
                    "position": "Firmatecknare"
                }
            ],
            "establishment_year": 1953
        },
        "6": {
            "company_name": "Nilsson, AB Erik V",
            "pnr": "217 58",
            "address": "Malmö, Tessins v 8",
            "phone_number": "040-9149 77",
            "bank_details": {
                "bankgiro": "876-1108",
                "postgiro": "432644-3"
            },
            "activity": "Trävaror, specialitet: sågad o helböjd bok, hyvlade lister samt formpressade detaljer",
            "employees": 0,
            "capital": 20000,
            "key_personnel": [
                {
                    "name": "Erik V Nilsson",
                    "position": "Verkst dir"
                }
            ],
            "establishment_year": 1953
        },
        "7": {
            "company_name": "Thelin & Co, Skofabriks AB",
            "pnr": "330 23",
            "address": "Smålandsstenar, Box 18, Oxelg",
            "phone_number": "0371-30620",
            "bank_details": {
                "bankgiro": "427-6713",
                "postgiro": "510609-1"
            },
            "activity": "Tillverkar arbetsskor o arbetsstövlar",
            "employees": 12,
            "annual_turnover": 800000,
            "key_personnel": [
                {
                    "name": "Evert Thelin",
                    "position": "Chefer"
                },
                {
                    "name": "Thure Carlsson",
                    "position": "Chefer"
                },
                {
                    "name": "Lennart Eriksson",
                    "position": "Chefer"
                }
            ],
            "establishment_year": 1959
        },
        "8": {
            "company_name": "Sewin, Ingenjursfirman",
            "pnr": "56100",
            "address": "Huskvarna, Hagstensg 22",
            "phone_number": "036-1316 89",
            "activity": "Tillverkar dubbelkonblandare, siktar",
            "key_personnel": [
                {
                    "name": "Stig Efverlund",
                    "position": "Ägare o chefer"
                },
                {
                    "name": "Gustaf Winqvist",
                    "position": "Ägare o chefer"
                }
            ],
            "establishment_year": 1948
        },
        "9": {
            "company_name": "Sexdrega Syfabrik, Ahl & Co",
            "pnr": "512 02",
            "address": "Svenljunga 2, Box 38",
            "phone_number": "0325-25200",
            "bank_details": {
                "bankgiro": "43-7529",
                "postgiro": "283617"
            },
            "activity": "Tillverkar herr- o pojkpyjamas, fritidsskjortor, undershorts, dressinggown, rökrockar, badrockar o badbyxor",
            "employees": 50,
            "annual_turnover": 2200000,
            "key_personnel": [
                {
                    "name": "Herman Ahl",
                    "position": "Chef"
                },
                {
                    "name": "Einar Hög-feldt",
                    "position": "Chef"
                },
                {
                    "name": "Valter Svensson",
                    "position": "Chef"
                }
            ],
            "establishment_year": 1939
        },
        "10": {
            "company_name": "Walfridson & Co, E",
            "pnr": "57100",
            "address": "Nässjö, Stensjön",
            "phone_number": "0380-91130",
            "bank_details": {
                "bankgiro": "452-7891"
            },
            "activity": "Tillverkar rörledningsarmatur i mässing o rödgods. Utför automatsvarvning",
            "employees": 14,
            "annual_turnover": 1000000,
            "key_personnel": [
                {
                    "name": "Fabr Viktor Walfridson",
                    "position": "Chef"
                }
            ],
            "establishment_year": 1946
        },
        "11": {
            "company_name": "Nilssons Fabriker, AB A W",
            "pnr": "291 02",
            "address": "Kristianstad 2, Industrig, Box 2095",
            "phone_number": "044J12 30 40",
            "bank_details": {
                "bankgiro": "26-4243",
                "postgiro": "38576-5"
            },
            "activity": "Tillverkar barnvagnar o tillbehör till dessa, stålmöbler, sjukhusmöbler o vårdmateriel. Utför inredningsarbeten i stålrör o rörkonstruktioner efter ritning",
            "employees": 110,
            "annual_turnover": 7000000,
            "capital": 625000,
            "key_personnel": [
                {
                    "name": "Yngve Rollof",
                    "position": "Verkst dir"
                },
                {
                    "name": "K-I Magnusson",
                    "position": "Kontors- o inköpschef"
                },
                {
                    "name": "Tage Andersson",
                    "position": "Försäljn-chef"
                }
            ],
            "establishment_year": 1855
        },
        "12": {
            "company_name": "Falkenbergs Kartongfabrik AB",
            "pnr": "31100",
            "address": "Falkenberg, Schubergsv 24",
            "phone_number": "0346-11216, 106 46",
            "bank_details": {
                "bankgiro": "425-7119",
                "postgiro": "289717-1"
            },
            "activity": "Tillverkar skokartonger, kapslar, industrikartonger (ej wellpapp) o konfektionsväskor",
            "employees": 19,
            "annual_turnover": 1200000,
            "capital": 30000,
            "key_personnel": [
                {
                    "name": "Kurt Anderson",
                    "position": "Verkst dir"
                }
            ],
            "establishment_year": 1947
        },
        "13": {
            "company_name": "Falkenbergs Kolimport, Lindvall & Co",
            "pnr": "31100",
            "address": "Falkenberg, Tegelbruksv 15",
            "phone_number": "0346-144 05",
            "bank_details": {
                "bankgiro": "42-5712",
                "postgiro": "289660"
            },
            "activity": "Säljer eldningsoljor, tankrengöring",
            "key_personnel": [
                {
                    "name": "Disp Nils Schtitt",
                    "position": "Chef"
                }
            ]
        },
        "14": {
            "company_name": "Falkenbergs Tegelbruks AB",
            "pnr": "31100",
            "address": "Falkenberg, Tegelbruksv 16",
            "phone_number": "0346-144 30",
            "bank_details": {
                "bankgiro": "361-3445",
                "postgiro": "370121-6"
            },
            "activity": "Tillverkar dräneringsrör svensk standard",
            "employees": 47,
            "annual_turnover": 3000000,
            "capital": 390000,
            "key_personnel": [
                {
                    "name": "Nils Schütt",
                    "position": "Verkst dir"
                }
            ],
            "establishment_year": 1904
        }
    }
}