{
    "original": "SCHMID AB, ERNST\n\nPnr 162 21\n\nVäUingby, Vällingbyv 208. Tel\n08-87 02 30. Bankgiro 483-4677.\nPostgiro 55449-3. Tga Presto\nVerksamhet: Säljer bagerimaskiner\nAntal anstäUda: 3\nAktiekapital: 90 000\nVerkst din Gösta Karlshammar\nEtableringsån 1928.\n\nFRAMNÄS VÄVERI AB\n\nPnr 51101\n\nKinna, Box 24. Tel 0320-106 85.\nBankgiro 43-4719. Postgiro82260.\nTga Framnäs\n\nVerksamhet: Tillverkar\nheminredningstextilier\nAktiekapital: 200 000\nVerkst dir: Johan Renck\nEtableringsår: 1900.\n\nFRAMTIDEN I MALMÖ,\nTRYCKERI AB\n\nPnr 201 21\n\nMalmö 1, Box 125. Bergsg 20. Tel\n040-20 50 00. Bankgiro 644-0374.\nPostgiro 14065-7.\nTelex 3182 ARBETET S\nVerksamhet: Tidningstryckeri\nAntal anställda: 609\nÅrsomsättning: 55 000 000\nAktiekapital: 4 837 000\nStyrelseordf: Erik Magnusson\nVerkst dir: Frans Nilsson\nAnnonsdir: H Holmström\nDir: L Ewers\n\nDistributionsdir: N Olausson\nEkonomidir: F Anderberg\nRedaktionschef: H Ekblom\nTekn-dir: P J Erixon\nEtableringsår: 1887.\n\nHALLRUP AB, ERNST\n\nPnr 340 36\n\nMoheda, Box 7. Torpsbruksv. Tel\n0472-700 15 , 70115. Bankgiro\n669-8104. Postgiro 94547-7\nVerksamhet: Säljer sågade o\nhyvlade trävaror samt sparrar i parti\nAntal anställda: 40\nÅrsomsättning: 4 500 000\nAktiekapital: 400 000\nVerkst dir: Torsten Hallrup\nEtableringsår: 1917.\n\nHALLSBERGS\nCEMENTVARU-FABRIK AB\n\nPnr 694 00\n\nHallsberg, Box 117. Långg. Tel\n0582-120 25. Bankgiro 819-3211.\nPostgiro 142499-3\nVerksamhet: Tillverkar betongvaror\no betongelement\nAntal anställda: 70\nÅrsomsättning: 7 000 000\nAktiekapital: 900 000\nVerkst dir. Sigurd Westin\nEtableringsår: 1938.\n\nARDEN AB, ELIZABETH\n\nPnr 21135\n\nMalmö, Kalendeg 9. Tel 040-35 6 05,\n35606. Bankgiro 263-8054.\nPostgiro 247350-2. Tga Elizarden\nVerksamhet: Parfym o kosmetiska\nartiklar i parti\n\nLager: Malmö S, Norberg-sg 11. Tel\n040-92 89 80\n\nFörsäljningskontor: Stockholm O,\nBirger Jarlsg 8. Tel 08-2141 17\nAktiekapital: 250 000\n\nStyrelse: Dir Carl-S Roos (ordf),\nadv Ake Wettermark, dir Th G\n\nYates\n\nVerkst dir: Ake Wettermark\nEtableringsår: 1948.\n\nTHUN AB, ERIK\n\nPnr 531 01\n\nLidköping 1, O Hamnen 7. Box 10.\nTel 0510-220 20. Bankgiro 84-1394.\nPostgiro 85463. Tga Thunship.\nTelex 67070\n\nVerksamhet: Rederi-,\nbefraktnings-o speditionsrörelse\nAntal anställda: 70\nÅrsomsättning: 35 000 000\nAktiekapital: 300 000\nVerkst dir: Helge Källsson\nEtableringsår: 1926.\n\nTUNAB TUNHEMS INDUSTRI\nAB\n\nPnr 461 00\n\nTrollhättan, V Tunhem. Tel\n0520-212 05, 21050. Bankgiro 892-4433.\nPostgiro 478150-6\nVerksamhet: Klippning o\nstansning av bilisolering. Trä- o\nmasonitearbeten. Emballage repareras o\nnytillverkas\nAntal anställda: 17\nAktiekapital: 20 000\nVerkst dir Rolf Andersson\nEtableringsår: 1961.\n\nTHUNBERGSBYGGNADS AB,\nGUNNAR\n\nPnr 171 52\n\nSolna, Råsundav 11. Tel 08-27 22 26.\nBankgiro 620-9308. Postgiro\n576320-6\n\nVerksamhet: Fastighetsförvaltning,\nrivningsarbeten etc\nAktiekapital: 100 000\nVerkst dir Byggmäst Gunnar\nThunberg\n\nEtableringsår 1960.\n\nTUNELIUS FABRIKER\nTHORMAN &amp; CO AB\n\nPnr 815 00\n\nTierp. Tel 0293-100 20. Bankgiro\n23-6290. Postgiro 37275-5\nVerksamhet: Tillverkar o säljer\nborstar o penslar\nAntal anställda: 40\nÅrsomsättning: 2000 000\nAktiekapital: 205000\nVerkst dir Tuve Johansson\nEtableringsår 1963.\n\nGUT &amp; CO AB, H\n\nPnr 200 22\n\nMalmö 3, Box 3064. Tel\n040-93 07 27, 93 07 28. Bankgiro 26-0070\nPostgiro 532541. Tga Sidengut\nVerksamhet: Sälj er damtyger av ylle\nrayon, natursilke, syntetfiber etc\nAntal anställda: 12\nÅrsomsättning: 4 000 000\nAktiekapital: 75 000\nVerkst dir: Gösta Wahlfrid\nEtableringsår: 1960.\n\nELP\n\nELPAR, AB\n\nPnr 631 02\n\nEskilstuna 1, Box 63. Skruven 1.\nTel 016-560 80. Bankgiro 82-8011.\nPostgiro 102939\n\nVerksamhet: Tillverkar elektr\nvåffeljärn o elektr hårfläktar\nAktiekapital: 40 000\nVerkst dir: Bengt Parnéus\nEtableringsår: 1955.\n\nÅMINNE BRUK AB\n\nPnr 33100\n\nVärnamo. Tel 0370-270 60, 270 26.\nBankgiro 554-4150. Postgiro\n388888-0. Tga Ferrum\nVerksamhet: Gjuteri o mek\nverkstad i Åminne. Tillverkar\nhandformat kvalitetsgjutgods i\nstyckestorlekar på max 3 ton, i\nkvalité-ter S I S 0115, 0120, 0125, 0130\nsamt gjuterimodeller\nAntal anställda: 40\nÅrsomsättning: 3 000 000\nAktiekapital: 150 000\nVerkst din A Gramler\nKontor: B Zoks\nProduktion: S Ahlgren\nEtableringsån 1826.\n\nÅMOT FORS\nPAPPERS-BRUKS AB\n\nPnr 670 40\n\nAmotfors. Tel 0571-308 00\nFörsäljningskontor: Karlstad 1,\nFack. Tel 054-18 02 80.\nTelex 66043 RGROUPK S\nVerksamhet: Tillverkar oglättat o\nglättat kraftpapper, kreppat papper,\nimpregnerat papper o gummerade\nförs lutnings rem sor\nAntal anställda: 350\nPlatschef: Dir Max Bäck\nDotterbolag till Rottneros AB.\n\nÅMÅLS GJUTERI &amp;\nME-KANISKA VERKSTAD, AB\n\nPnr 662 00\n\nÅmål, V Bang 6. Tel 0532-12045.\nBankgiro 369-05 18. Postgiro\n12810-8. Tga Gjuteriet.\nTelex 5345 AMV S\nVerksamhet: Tillverkar maskiner o\nutrustningar för konvertering av\npapper, plast, al-folie m m.\nPneumatlskt expanderande rullspindlar.\nValsverk för plast o gummiindustrin.\nTackjärnsgjutgods\nVarunamn: Aero-Shaft\nAntal anställda: 70\nÅrsomsättning: 4 000000\nAktiekapital: 60 000\nVerkst dir: Ing Sigward Boström\nEtableringsån 1929.\n\nARNDT, AB J E\n\nPnr 824 01\n\nHudiksvall 1, Godsg 5. Box 7. Tel\n0650-153 30. Bankgiro 787-0025.\nPostgiro 29895-0. Tga\nArndt-bolaget. Telex 8225\nVerksamhet: Säljer\nbyggnadsmaterial, färger, oljor, kol, koks o\neldningsoljor. Skeppsmäkleri o\nspedition\n\nAntal anställda: 35\nÅrsomsättning: 6 500 000\nAktiekapital: 200 000\nStyrelse: Dir Karl Jakobsson(ordf),\ndir Tage Grimner, kapten Jerker\nArndt\n\nVerkst dir: Tage Grimner\nEtableringsår: 1909.\n\nGOTEBORGS KEXFABRIKS AB\n\nPnr 442 00\n\nKungälv. Tel 0303-109 10.\nBankgiro 430-9084. Postgiro 8995-3. Tga\nKexfabriken\n\nVerksamhet: Tillverkar kex,\nwafers o chokladvaror\nFörsäljningskontor: Stockholm,\nSvarvareg 9-11. Tel 08-50 2 0 55,\n5 1 04 55\n\nAntal anställda: 500\nÅrsomsättning: 36 000 000\nAktiekapital: 2 500 000\nVerkst dir: Gösta Cederryd\nEtableringsår: 1888.\n\nGOTEBORGS\nKLICHÉ-ANSTALT, AB\n\nPnr 401 25\n\nGöteborg 1, Odinsplatsen 2 B. Box\n334. Tel 031-80 05 40. Bankgiro\n50-6614. Postgiro 42912\nVerksamhet: Annons- o\nreproduktionssättningar o offset/repro\n(maskin-, ludlow-, hand- o\nfotosättning). Tillverkar klichéer o\nplast-o semperitduplikat o matriser.\nTryckeri\n\nAntal anstäUda: 120\nAktiekapital: 60 000\nVerkst dir: Thore Kitzing\nEtableringsår: 1909\nOmbildat till aktiebolag 1960.\n\nGOTEBORGS KOLVRING.\nFABRIK\n\nPnr 400 11\n\nGöteborg 18, Gårdav 18. Box\n18001. Tel 031-15 28 74, 15 28 75.\nBankgiro 50-7965. Postgiro 40801\nVerksamhet: Tillverkar kolvringar\nav alla slag, skär- o rullmaskiner\nför papper o toalettpappersmaskiner\nÄgare o chefer: G Boge, R Boge\nEtableringsår: 1922.\n\nGOTEBORGS KONSERV.\nFABRIK, AB\n\nPnr 414 51\n\nGöteborg, Banehagsliden 2. Tel\n031-1244 20. Bankgiro 440-6708.\nPostgiro 428200-0. Tga Sardinco\nVerksamhet: Inläggning av\nfiskkonserver\n\nAntal anstäUda: 117\nÅrsomsättning: 8 505 000\n\nAktiekapital: 88 000\nVerkst dir: Harald Asland\nEtableringsår: 1939.\n\nGOTEBORGS LIST. &amp; TRÄ.\nINDUSTRI AB\n\nPnr 424 56\n\nAngered. Tel 031-30 03 00.\nBankgiro 892-0399. Postgiro 240295-6\nVerksamhet: Lövträlist i parti.\nUtför skärpning av hårdmetallverktyg\nVerkst dir: D E Brunedal\nEtableringsår: 1945.",
    "structured": {
        "companies": [
            {
                "company_name": "SCHMID AB, ERNST",
                "pnr": "162 21",
                "address": "VäUingby, Vällingbyv 208",
                "phone_number": "08-87 02 30",
                "bank_details": {
                    "bankgiro": "483-4677",
                    "postgiro": "55449-3"
                },
                "activity": "Säljer bagerimaskiner",
                "employees": 3,
                "capital": 90000,
                "key_personnel": [
                    {
                        "name": "Verkst din Gösta Karlshammar"
                    }
                ],
                "establishment_year": 1928
            },
            {
                "company_name": "FRAMNÄS VÄVERI AB",
                "pnr": "51101",
                "address": "Kinna, Box 24",
                "phone_number": "0320-106 85",
                "bank_details": {
                    "bankgiro": "43-4719",
                    "postgiro": "82260"
                },
                "activity": "Tillverkar heminredningstextilier",
                "capital": 200000,
                "key_personnel": [
                    {
                        "name": "Verkst dir: Johan Renck"
                    }
                ],
                "establishment_year": 1900
            },
            {
                "company_name": "FRAMTIDEN I MALMÖ, TRYCKERI AB",
                "pnr": "201 21",
                "address": "Malmö 1, Box 125, Bergsg 20",
                "phone_number": "040-20 50 00",
                "bank_details": {
                    "bankgiro": "644-0374",
                    "postgiro": "14065-7"
                },
                "activity": "Tidningstryckeri",
                "employees": 609,
                "annual_turnover": 55000000,
                "capital": 4837000,
                "key_personnel": [
                    {
                        "name": "Styrelseordf: Erik Magnusson"
                    },
                    {
                        "name": "Verkst dir: Frans Nilsson"
                    },
                    {
                        "name": "Annonsdir: H Holmström"
                    },
                    {
                        "name": "Dir: L Ewers"
                    },
                    {
                        "name": "Distributionsdir: N Olausson"
                    },
                    {
                        "name": "Ekonomidir: F Anderberg"
                    },
                    {
                        "name": "Redaktionschef: H Ekblom"
                    },
                    {
                        "name": "Tekn-dir: P J Erixon"
                    }
                ],
                "establishment_year": 1887
            },
            {
                "company_name": "HALLRUP AB, ERNST",
                "pnr": "340 36",
                "address": "Moheda, Box 7, Torpsbruksv",
                "phone_number": "0472-700 15 , 70115",
                "bank_details": {
                    "bankgiro": "669-8104",
                    "postgiro": "94547-7"
                },
                "activity": "Säljer sågade o hyvlade trävaror samt sparrar i parti",
                "employees": 40,
                "annual_turnover": 4500000,
                "capital": 400000,
                "key_personnel": [
                    {
                        "name": "Verkst dir: Torsten Hallrup"
                    }
                ],
                "establishment_year": 1917
            },
            {
                "company_name": "HALLSBERGS CEMENTVARU-FABRIK AB",
                "pnr": "694 00",
                "address": "Hallsberg, Box 117, Långg",
                "phone_number": "0582-120 25",
                "bank_details": {
                    "bankgiro": "819-3211",
                    "postgiro": "142499-3"
                },
                "activity": "Tillverkar betongvaror o betongelement",
                "employees": 70,
                "annual_turnover": 7000000,
                "capital": 900000,
                "key_personnel": [
                    {
                        "name": "Verkst dir. Sigurd Westin"
                    }
                ],
                "establishment_year": 1938
            },
            {
                "company_name": "ARDEN AB, ELIZABETH",
                "pnr": "21135",
                "address": "Malmö, Kalendeg 9",
                "phone_number": "040-35 6 05, 35606",
                "bank_details": {
                    "bankgiro": "263-8054",
                    "postgiro": "247350-2"
                },
                "activity": "Parfym o kosmetiska artiklar i parti",
                "address_lager": "Malmö S, Norberg-sg 11",
                "phone_lager": "040-92 89 80",
                "address_försäljningskontor": "Stockholm O, Birger Jarlsg 8",
                "phone_försäljningskontor": "08-2141 17",
                "capital": 250000,
                "key_personnel": [
                    {
                        "name": "Styrelse: Dir Carl-S Roos (ordf), adv Ake Wettermark, dir Th G Yates"
                    },
                    {
                        "name": "Verkst dir: Ake Wettermark"
                    }
                ],
                "establishment_year": 1948
            }
        ]
    }
}