{
    "original": "SVENSKA ELOPAK AB\n\nPnr 252 32\n\nHelsingborg, Högastens g 19. Tel\n042-62240. Bankgiro 852-4456.\nPostgiro 621224-5. Tga Elopak.\nTelex 72454 ELOPAK S\nVerksamhet: Säljer o uthyr\nmjölk-föipackningsmaskiner i Sverige för\nEx-Cell-O Corporation, Detroit.\nTillverkar o säljer\nförpackningsmaterial till dessa maskiner\nVarunamn: Pure-Pak\nAntal anställda: 80\nÅrsomsättning: 37000 000\nAktiekapital: 500 000\nVerkst dir: Arne Ställberg\nFabrikschef: Raoul Otter\nKamrer: Henry Sehrman\nEtableringsår: 1961.\n\nflink maskinfabrik, g\n\nPnr 662 00\n\nÅmål, Vänersborgsv 53. Tel\n0532-112 09. Bankgiro 89-5116.\nPostgiro 373822\n\nVerksamhet: Handslipmaskiner,\nsportmotorcyklar o -motorer\nAntal anställda: 9\nÄgare o chef: Fabr Gustav Flink\nEtableringsår: 1946.\n\nBROMAN &amp; HELLDÉN, AB\n\nPnr 102 45\n\nStockholm 5, Box 5249. Nybrog\n25-27. Tel 08-638006, 638007.\nBankgiro 734-9186. Postgiro\n2722-7. Tga Brohell\nVerksamhet: Säljer\nmaskinförnödenheter, skyddskläder,\npresenningar o biltillbehör\nAktiekapital: 75 000\nVerkst dir: Bengt Broman\nEtableringsår: 1926.\n\nESSELTE AB\n\nPnr 10110\n\nStockholm 1, Vasag 16. Fack. Tel\n08-22 95 00, direktion 08-23 66 50\nVerksamhet: Moderbolag till ett\nstort antal företag (se förteckning\nnedan), som bedriver olika slag av\nindustri, handel o service,\növervägande inom grafiska branschen:\nmassa o papper, emballage o\nförpackningar, tryckerirörelse,\nbokbinderi, förlagsverksamhet,\nkartografi, papperskonsumentvaror,\nkon-torsmateriel, system o\ndatabehandling samt läromedel\nAntal anställda: 7 500\nArsomsaumng: azu uuu uuu\n\nAktiekapital: 72 325 000\n\nStyrelse: Generalkonsul Ragnar\nSöderberg (ordf), dir Ingemar\nBlennow, överintendent Knut von\nHorn, hovrättsrådet Bengt Lassen,\nfil dr Carl M:son Mannerfelt, dir\nRagnar Sundén, dir Erik Söderberg,\nciviling Sven Dahlbäck (suppl),\nhovrättsassessor Henry\nMontgomery (suppl)\n\nVerkst dir Carl M:son Mannerfelt\nV verkst dir: Sven Dahlbäck\nOmbudsman: Nils Olof Aurelius\nEkonomi: Ake Steineck\nFinans: Hampus Grunditz\nStruktur/utveckling: Lars Lidén\nBolaget grundat 1913 (namnändring\n1970)\n\nTill koncernen är bl a knutna\nföljande företag i Sverige:\nÖrebro Pappersbruks AB, Örebro\nFrö vifors Bruks AB\nEsseltewell AB, Norrahammar\nEsseltepac AB, Norrköping\nAB P A Norstedt &amp; Söner,\nStockholm\n\nBoktryckeri AB Thule\nAB Draken Iltryck\nEsselte Tryck AB\nVår Bok AB\nFjrlags AB Pan\nGumperts Skolmateriel AB\nAkuma AB, Tyringe\nEsselte Kart AB, Stockholm\nGeneralstabens Litografiska\nAnstalt\n\nAB Kartografiska Institutet\nAB Kartlitografen\nKartförlaget GLA AB\nEsselte Herzog s AB, Nacka\nRotogravyr AB, Solna\nWezäta-Melins AB, Göteborg\nWemco AB\n\nAB Grako, Stockholm\nEskil Holms Konstförlag AB\nGustaf Melins AB\nEsselte Öbergs AB, Stockholm\n\nGustaf Heimdal AB\nEsselte System AB\nAB Hasse W Tullberg\nCentraltryckeriets Stämpelfabrik\nSvanströms Pappershandel\nAB Skrivrit, Sollentuna\nEsselte ARrkonsult AB, Stockholm.\n\nESSELTE HERZOGS AB\n\nPnr 13101\n\nNacka 1, Fack. Ryssviksv 2. Tel\n08-716 26 80. Bankgiro 74-6015.\nPostgiro 465. Tga Herzog\nVerksamhet: Parti- o\nprivatbok-binderi, bibelförlag, kalendrar\nAntal anställda: 275\nÅrsomsättning: 19 000 000\nAktiekapital: 10 000\nVerkst dir: Disp R Sirvell\nEtableringsår: 1862\nAnslutet till Esselte AB, Stockholm.\n\nESSELTE KIENZLE\nDATASYSTEM AB\n\nPnr 10110\n\nStockholm 1. Fack. Tel 08-22 9 5 00.\nBankgiro 614-8860. Postgiro\n453755-1. Tga Kienzle.\nTelex 1598 ESSELTE S\nVerksamhet: Marknadsföring av\nfaktureringsmaskiner,\nkontorsdatamaskiner o datafångstutrustning\nProgrammeringsavdelning o service:\n17140 Solna. Virebergsv 15. Tel\n08-83 07 50. Telex 10530\nFilialer: Göteborg, Malmö,\nJönköping, Örebro, Gävle\nVarunamn: Kienzle\nAntal anställda: 50\nÅrsomsättning: 6000 000\nAktiekapital: 1200 000\nStyrelse: Adv Hakon Auerbach, dr\nMartin Fahnauer, dir Bengt\nStrandberg\n\nVerkst dir: Bo G Talldal\nMarknadschef: Bernt Forsmoo\nEtableringsår: 1970.\n\nMEYER, AB ARNÖ\n\nPnr 111 57\n\nStockholm, Sveav 17. Tel\n08-212711. Bankgiro 160-0196.\nPostgiro 57586-0\n\nVerksamhet: Textilagenturrörelse\ni herr- o damekiperingsbranschen\nAntal anställda: 3\nÅrsomsättningar: 2 000 000\nAktiekapital: 15 000\nVerkst dir: Arne Wallberg\nEtableringsår: 1923.\n\nESKILSTUNA KARTONG AB\n\nPnr 633 55\n\nEskilstuna, Kvarngärdesg 4. Tel\n016-13 05 05. Bankgiro 601-4443.\nPostgiro 328982-4\nVerksamhet: Kartongemballage\nAntal anställda: 10\nÅrsomsättning: 260 000\nAktiekapital: 39 000\nÄgare o chef: Erik Lundqvist\nEtableringsår: 1946.\n\nESKILSTUNA KOLIMPORT &amp;\nHANDELS AB\n\nPnr 63102\n\nEskilstuna 1, Box 10. Kungsg 14.\nTel 016-137700. Tga Kolimporten\nVerksamhet: Stenkol, koks o\neldningsoljor. Järn o byggnadsmaterial\nAntal anställda: 60\nÅrsomsättning: 18000000\nAktiekapital: 600 000\nVerkst dir: Folke Wallén\nEtableringsår: 1922.\n\nESKILSTUNA MEKANISKA\nVERKSTAD\n\nPnr 635 90\n\nEskilstuna 1, Posü 3112. Tel\n016-91115. Bankgiro 82-8022.\nPostgiro 94923-0\n\nVerksamhet: Tillverkar\nväxelborr-skaft, handdrivna slipmaskiner,\ngängapparater, borrchuckar samt\nutför automatsvarvning\nVarunamn: EMVE\nÄgare o chef: Ake Lindblom\nEtableringsår: 1936.\n\nESKILSTUNA\nMETALL-INDUSTRI AB\n\nPnr 632 32\n\nEskilstuna, Langsg 3. Tel\n016-13 16 18, 13 16 19. Bankgiro\n601-3346. Postgiro 26838-3\nVerksamhet: Elektr\nhushållsapparater. Presentartiklar i metall\nVarunamn: EMI\nAktiekapital: 50 000\nDirektion: Birger Malmlöf, Bengt\nSkoglund\n\nEtableringsår: 1920.\n\nESKILSTUNA\nMODELL-INDUSTRI AB\n\nPnr 633 55\n\nEskilstuna, Loheg 4. Tel 016-\n\n131202. Bankgiro 369-3363.\nPostgiro 140126-4\n\nVerksamhet: Tillverkar\ngjuterimo-deller av trä, plast o metall,\nkokiller samt pressgjutningsverktyg.\nUtför svarv- o fräsarbeten, järn o\nmetall\n\nAntal anställda: 35\nÅrsomsättning: 1500000\nAktiekapital: 20000\nVerkst dir: Fabr August Pölmas\nEtableringsår: 1914\nOmbildat till aktiebolag 1960.\n\nESKILSTUNA\nPLAST-BELÄGGNING AB\n\nPnr 63103\n\nEskilstuna 1, Kungsg 16. Box 236.\nTel 016-14 75 75,14 96 65. Bankgiro\n828-1099. Postgiro 99001-0\nVerksamhet: Värmeisolerade betkar\no huvar för starka syror\n(patent-sökt). Reduceringsanläggningar.\nUtluftningstrummor o skorstenar.\nUtför armerade o oarmerade\nplastbeläggningar för byggen o industri\nFilial: Stockholm. Tel 08-18 55 61\nFabrik: Eskilstuna, Kyrkog 11 H.\nTel 016-14 96 67\nÅrsomsättning: 1300 000\nAktiekapital: 42000\nVerkst dir: Disp Elof Lönnmar\nVerkmäst: Folke Carlsson\nKontorschef: Lars Blomkvist\nEtableringsår: 1960.\n\nESKILSTUNA\nSTÄMPEL-FABRIK, AB\n\nPnr 632 20\n\nEskilstuna, Kyrkog 11 N. Tel\n016-130651. Postgiro 33276\nVerksamhet: Tillverkar stål-,\nmetall- o gummistämplar,\npräglingsstansar samt maskingravyr\nÄgare o chef: Fabr Arne\nPettersson\n\nEtableringsår: 1900.\n\nESKILSTUNA\nTERMOMETERFABRIK AB\n\nPnr 632 27\n\nEskilstuna, Svengrensg 14. Tel\n016-13 51 25. Bankgiro 36-9304.\nPostgiro 278246\n\nVerksamhet: Tillverkar o säljer alla\nslags termometrar.\n\nESKILSTUNA\nTRÄD-PLAST AB\n\nPnr 630 02\n\nEskilstuna 2, Box 2022. Nyforsg 37.\nTel 016-1153 33. Bankgiro 36-9327.\nPostgiro 445515\n\nVerksamhet: Tillverkar plastade\ntrådartiklar, bilkorgar oskyltställ\nAntal anställda: 5\nAktiekapital: 5 000\nÄgare o chef: Jörgen Jonsson\nEtableringsår: 1954.\n\nSCANDIASTEEL AB\n\nPnr 114 58\n\nStockholm, Linnég 51-53. Tel\n08-63 22 25, 62 5121’. Postgiro 2081-8\nTga Delimp\n\nVeiksamhet: Säljer rostfria\ncafeteria- o storköksutrustningar\nVeikst dir: G Ålund\nEtableringsår: 1943.\n\nPRINTEX AFFÄRSTRYCK AB\n\nPnr 59101\n\nMotala 1, Fack. Stjärnorpsg 5. Tel\n0141-503 00, 107 65. Bankgiro\n134-296 3. Postgiro 297743-7\nVerksamhet: Bok- o offsettryckeri\nAntal anställda: 30\nEtableringsår: 1971.\n\nPRINTING DEVELOPMENTS\nINTERNATIONAL\n(SCANDI-NAVIA) AB\n\nPnr 172 34\n\nSundbyberg, Starrbäcksg 3. Tel\n08-291011, 2910 20. Bankgiro\n161-0195. Postgiro 656265-6. Tga\nPrintdevel. Telex 17946 PDISTO S\nVerksamhet: Scanning\n(färgseparering). Fotokompositioner,\ndupli-kattillverkning. Försäljning av\nlicenstillverkade\nframkallningsma-skiner\n\nFilialer: 113 32 Stockholm, Falug\n\n8. Tel 08-30 98 09\n\n172 32 Sundbyberg, Kyrkog 7. Tel\n\n08-29 49 21\n\nVarunamn: PDI\n\nAntal anstäUda: 18\n\nÅrsomsättning: 3 000 000\n\nAktiekapital: 200 000\n\nStyrelse: Dir Hans Josephson\n\n(ordf), adv Per H Gedda, John Leo\n\nLyons\n\nVerkst dir: Per H Gedda\nStudio manager: Kurt H Pilat\nEtableringsår: 1961\n\nDotterbolag till Time Inc., New\nYork.\n\nPRINTING EQUIPMENT, AB\n\nPnr 191 87\n\nSollentuna, Knistav 21. Tel\n08-35 27 80. Bankgiro 167-0546.\nTga Printing, Stockholm.\nTelex 10283\n\nVerksamhet: Tillverkar o säljer\nark- o rulloffsetpressar\nFabrik: Valdemarsvik. Tel\n0123-11150\n\nVarunamn: Solna offset\nAntal anstäUda: 620\nÅrsomsättning: 85 000 000\nAktiekapital: 750 000\nStyrelse: Bokförl Albert Bonnier jr\n(ordf), dir Erik Annergren, bokförl\nGerard Bonnier, dir Johan Bonnier,\nbokförl Lukas Bonnier,\nbankdirGö-te Engfors\n\nVerkst dir: Bengt Frid\nEkonomidir: Ake Lindblad\nFörsäljn-chef Sverige: Henry\nKarlson\n\nTeknisk chef: Yngve Claesson\nKonstr-chef: Rune Lundbladh\nEtableringsår: 1947.\n\nBE LOS AB, INDUSTRI\n\nPnr 762 00\n\nRimbo, Box 84. Stockholmsv 15.\nTel 0175-709 20. Bankgiro 11-1737.\nTga Belosab, Stockholm\nVerksamhet: Tillverkar Belos\nuniversaltraktorer med redskap\nAntal anställda: 67\nAktiekapital: 500 000\nVerkst dir: Civiling Olof Bennich\nEtableringsår: 1964.\n\nBEMEL ab\n\nTRANSPORT, och ELTEKNIK\n\nPnr 11243\n\nStockholm, Gyllenhorgsg 4. Tel\n08-53 08 00, 51 84 50. Tga Bemel\nVerksamhet: Levererar interna\ntransportanläggningar o rulltrappor,\nförsäljer starkströmsapparater o\nbrickdukningssystem o\ndiskmaskiner\n\nDistriktskontor: 21139 Malmö,\nGustaf Adolfs torg 45. Tel 040-12 19 81\n41118 Göteborg, N Liden 4. Tel\n031-1167 50\nAntal anställda: 25\nÅrsomsättning: 6 000 000\nAktiekapital: 50 000\nVerkst dir: Civiling Edgar Pålson\nTekn dir: Civiling Yngve Lerud\nEtableringsår: 1950.\n\nSVENSKA REKLAMBREV\n\nPnr 100 31\n\nStockholm 21. Vikingag 21. Fack.\nTel 08-34 70 70, 34 70 71.\nBankgiro 391-2128. Postgiro 51084-2\nVerksamhet: Offsettryckeri med\nreproavdelning\nAntal anställda: 14\nÅrsomsättning: 500 000\nEtableringsår: 1924.",
    "structured": {
        "1": {
            "company_name": "SVENSKA ELOPAK AB",
            "address": "Högastens g 19, 252 32 Helsingborg",
            "phone_number": "042-62240",
            "bank_details": {
                "bankgiro": "852-4456",
                "postgiro": "621224-5"
            },
            "activity": "Säljer o uthyr mjölk-förpackningsmaskiner i Sverige för Ex-Cell-O Corporation, Detroit. Tillverkar o säljer förpackningsmaterial till dessa maskiner",
            "employees": 80,
            "annual_turnover": 37000000,
            "capital": 500000,
            "key_personnel": [
                {
                    "name": "Arne Ställberg",
                    "position": "Verkst dir"
                },
                {
                    "name": "Raoul Otter",
                    "position": "Fabrikschef"
                },
                {
                    "name": "Henry Sehrman",
                    "position": "Kamrer"
                }
            ],
            "establishment_year": 1961
        },
        "2": {
            "company_name": "FLINK MASKINFABRIK, AB",
            "address": "Vänersborgsv 53, 662 00 Åmål",
            "phone_number": "0532-112 09",
            "bank_details": {
                "bankgiro": "89-5116"
            },
            "activity": "Handslipmaskiner, sportmotorcyklar o -motorer",
            "employees": 9,
            "establishment_year": 1946
        },
        "3": {
            "company_name": "BROMAN & HELLDÉN, AB",
            "address": "Box 5249, Nybrog 25-27, 102 45 Stockholm 5",
            "phone_number": "08-638006, 638007",
            "bank_details": {
                "bankgiro": "734-9186",
                "postgiro": "2722-7"
            },
            "activity": "Säljer maskinförnödenheter, skyddskläder, presenningar o biltillbehör",
            "capital": 75000,
            "key_personnel": [
                {
                    "name": "Bengt Broman",
                    "position": "Verkst dir"
                }
            ],
            "establishment_year": 1926
        },
        "4": {
            "company_name": "ESSELTE AB",
            "address": "Vasag 16, 10110 Stockholm 1",
            "phone_number": "08-22 95 00",
            "activity": "Moderbolag till ett stort antal företag (se förteckning nedan), som bedriver olika slag av industri, handel o service, övervägande inom grafiska branschen: massa o papper, emballage o förpackningar, tryckerirörelse, bokbinderi, förlagsverksamhet, kartografi, papperskonsumentvaror, kon-torsmateriel, system o databehandling samt läromedel",
            "employees": 7500,
            "annual_turnover": "azu uuu uuu",
            "capital": 72325000,
            "key_personnel": [
                {
                    "name": "Carl M:son Mannerfelt",
                    "position": "Verkst dir"
                },
                {
                    "name": "Sven Dahlbäck",
                    "position": "V verkst dir"
                }
            ],
            "establishment_year": 1913
        },
        "...": "..."
    }
}